{
  "type": "Feature",
  "properties": {
    "name": "Goléré",
    "country": "SN",
    "subdivision": "14",
    "timezone": "Africa/Dakar"
  },
  "geometry": {
    "type": "Point",
    "coordinates": [
      -14.10165,
      16.25575
    ]
  }
}