{
  "type": "Feature",
  "properties": {
    "name": "Batifa",
    "country": "IQ",
    "subdivision": "08",
    "timezone": "Asia/Baghdad"
  },
  "geometry": {
    "type": "Point",
    "coordinates": [
      43.01233,
      37.17454
    ]
  }
}