{
  "type": "Feature",
  "properties": {
    "name": "Sīnah",
    "country": "IQ",
    "subdivision": "08",
    "timezone": "Asia/Baghdad"
  },
  "geometry": {
    "type": "Point",
    "coordinates": [
      43.03935,
      36.80851
    ]
  }
}