{
  "type": "Feature",
  "properties": {
    "name": "Nonoichi",
    "country": "JP",
    "subdivision": "15",
    "timezone": "Asia/Tokyo"
  },
  "geometry": {
    "type": "Point",
    "coordinates": [
      136.61667,
      36.53333
    ]
  }
}