{
  "type": "Feature",
  "properties": {
    "name": "Nong Khai",
    "country": "TH",
    "subdivision": "17",
    "timezone": "Asia/Bangkok"
  },
  "geometry": {
    "type": "Point",
    "coordinates": [
      102.742,
      17.87847
    ]
  }
}