{
  "type": "Feature",
  "properties": {
    "name": "Sangkhom",
    "country": "TH",
    "subdivision": "17",
    "timezone": "Asia/Bangkok"
  },
  "geometry": {
    "type": "Point",
    "coordinates": [
      102.27364,
      18.06389
    ]
  }
}