{
  "type": "Feature",
  "properties": {
    "name": "Tha Bo",
    "country": "TH",
    "subdivision": "17",
    "timezone": "Asia/Bangkok"
  },
  "geometry": {
    "type": "Point",
    "coordinates": [
      102.58139,
      17.85003
    ]
  }
}