{
  "type": "Feature",
  "properties": {
    "name": "Saint Helier",
    "country": "JE",
    "subdivision": "3237864",
    "timezone": "Europe/Jersey"
  },
  "geometry": {
    "type": "Point",
    "coordinates": [
      -2.10491,
      49.18804
    ]
  }
}