{
  "type": "Feature",
  "properties": {
    "name": "Magway",
    "country": "MM",
    "subdivision": "15",
    "timezone": "Asia/Yangon"
  },
  "geometry": {
    "type": "Point",
    "coordinates": [
      94.93246,
      20.14956
    ]
  }
}