{
  "type": "Feature",
  "properties": {
    "name": "Jyllinge",
    "country": "DK",
    "subdivision": "20",
    "timezone": "Europe/Copenhagen"
  },
  "geometry": {
    "type": "Point",
    "coordinates": [
      12.10315,
      55.75295
    ]
  }
}