{
  "type": "Feature",
  "properties": {
    "name": "Svebølle",
    "country": "DK",
    "subdivision": "20",
    "timezone": "Europe/Copenhagen"
  },
  "geometry": {
    "type": "Point",
    "coordinates": [
      11.28658,
      55.65183
    ]
  }
}