{
  "type": "Feature",
  "properties": {
    "name": "Drăgăneşti",
    "country": "RO",
    "subdivision": "05",
    "timezone": "Europe/Bucharest"
  },
  "geometry": {
    "type": "Point",
    "coordinates": [
      22.38333,
      46.61667
    ]
  }
}