{
  "type": "Feature",
  "properties": {
    "name": "Galoșpetreu",
    "country": "RO",
    "subdivision": "05",
    "timezone": "Europe/Bucharest"
  },
  "geometry": {
    "type": "Point",
    "coordinates": [
      22.2173,
      47.48345
    ]
  }
}