{
  "type": "Feature",
  "properties": {
    "name": "Groși",
    "country": "RO",
    "subdivision": "05",
    "timezone": "Europe/Bucharest"
  },
  "geometry": {
    "type": "Point",
    "coordinates": [
      22.47965,
      47.04525
    ]
  }
}