{
  "type": "Feature",
  "properties": {
    "name": "Popeşti",
    "country": "RO",
    "subdivision": "05",
    "timezone": "Europe/Bucharest"
  },
  "geometry": {
    "type": "Point",
    "coordinates": [
      22.41667,
      47.23333
    ]
  }
}