{
  "type": "Feature",
  "properties": {
    "name": "Sălacea",
    "country": "RO",
    "subdivision": "05",
    "timezone": "Europe/Bucharest"
  },
  "geometry": {
    "type": "Point",
    "coordinates": [
      22.31667,
      47.46667
    ]
  }
}