{
  "type": "Feature",
  "properties": {
    "name": "Șilindru",
    "country": "RO",
    "subdivision": "05",
    "timezone": "Europe/Bucharest"
  },
  "geometry": {
    "type": "Point",
    "coordinates": [
      22.04683,
      47.43725
    ]
  }
}