{
  "type": "Feature",
  "properties": {
    "name": "Şuncuiuş",
    "country": "RO",
    "subdivision": "05",
    "timezone": "Europe/Bucharest"
  },
  "geometry": {
    "type": "Point",
    "coordinates": [
      22.53333,
      46.93333
    ]
  }
}