{
  "type": "Feature",
  "properties": {
    "name": "Suplacu de Barcău",
    "country": "RO",
    "subdivision": "05",
    "timezone": "Europe/Bucharest"
  },
  "geometry": {
    "type": "Point",
    "coordinates": [
      22.53195,
      47.25729
    ]
  }
}