{
  "type": "Feature",
  "properties": {
    "name": "Tășad",
    "country": "RO",
    "subdivision": "05",
    "timezone": "Europe/Bucharest"
  },
  "geometry": {
    "type": "Point",
    "coordinates": [
      22.12516,
      46.93773
    ]
  }
}