{
  "type": "Feature",
  "properties": {
    "name": "Voivozi",
    "country": "RO",
    "subdivision": "05",
    "timezone": "Europe/Bucharest"
  },
  "geometry": {
    "type": "Point",
    "coordinates": [
      22.39024,
      47.21562
    ]
  }
}