{
  "type": "Feature",
  "properties": {
    "name": "Pervomayskoye",
    "country": "RU",
    "subdivision": "75",
    "timezone": "Asia/Tomsk"
  },
  "geometry": {
    "type": "Point",
    "coordinates": [
      86.2313,
      57.0761
    ]
  }
}