{
  "type": "Feature",
  "properties": {
    "name": "Chodzież",
    "country": "PL",
    "subdivision": "86",
    "timezone": "Europe/Warsaw"
  },
  "geometry": {
    "type": "Point",
    "coordinates": [
      16.9198,
      52.99505
    ]
  }
}