{
  "type": "Feature",
  "properties": {
    "name": "Czarnków",
    "country": "PL",
    "subdivision": "86",
    "timezone": "Europe/Warsaw"
  },
  "geometry": {
    "type": "Point",
    "coordinates": [
      16.56413,
      52.90214
    ]
  }
}