{
  "type": "Feature",
  "properties": {
    "name": "Dobrzyca",
    "country": "PL",
    "subdivision": "86",
    "timezone": "Europe/Warsaw"
  },
  "geometry": {
    "type": "Point",
    "coordinates": [
      17.60336,
      51.86663
    ]
  }
}