{
  "type": "Feature",
  "properties": {
    "name": "Janków Przygodzki",
    "country": "PL",
    "subdivision": "86",
    "timezone": "Europe/Warsaw"
  },
  "geometry": {
    "type": "Point",
    "coordinates": [
      17.78824,
      51.59808
    ]
  }
}