{
  "type": "Feature",
  "properties": {
    "name": "Komorniki",
    "country": "PL",
    "subdivision": "86",
    "timezone": "Europe/Warsaw"
  },
  "geometry": {
    "type": "Point",
    "coordinates": [
      16.81063,
      52.3387
    ]
  }
}