{
  "type": "Feature",
  "properties": {
    "name": "Koźmin Wielkopolski",
    "country": "PL",
    "subdivision": "86",
    "timezone": "Europe/Warsaw"
  },
  "geometry": {
    "type": "Point",
    "coordinates": [
      17.45391,
      51.82712
    ]
  }
}