{
  "type": "Feature",
  "properties": {
    "name": "Koźminek",
    "country": "PL",
    "subdivision": "86",
    "timezone": "Europe/Warsaw"
  },
  "geometry": {
    "type": "Point",
    "coordinates": [
      18.33893,
      51.79874
    ]
  }
}