{
  "type": "Feature",
  "properties": {
    "name": "Krotoszyn",
    "country": "PL",
    "subdivision": "86",
    "timezone": "Europe/Warsaw"
  },
  "geometry": {
    "type": "Point",
    "coordinates": [
      17.43738,
      51.69868
    ]
  }
}