{
  "type": "Feature",
  "properties": {
    "name": "Książ Wielkopolski",
    "country": "PL",
    "subdivision": "86",
    "timezone": "Europe/Warsaw"
  },
  "geometry": {
    "type": "Point",
    "coordinates": [
      17.23952,
      52.06167
    ]
  }
}