{
  "type": "Feature",
  "properties": {
    "name": "Mikstat",
    "country": "PL",
    "subdivision": "86",
    "timezone": "Europe/Warsaw"
  },
  "geometry": {
    "type": "Point",
    "coordinates": [
      17.97378,
      51.53236
    ]
  }
}