{
  "type": "Feature",
  "properties": {
    "name": "Miłosław",
    "country": "PL",
    "subdivision": "86",
    "timezone": "Europe/Warsaw"
  },
  "geometry": {
    "type": "Point",
    "coordinates": [
      17.48955,
      52.20318
    ]
  }
}