{
  "type": "Feature",
  "properties": {
    "name": "Nekla",
    "country": "PL",
    "subdivision": "86",
    "timezone": "Europe/Warsaw"
  },
  "geometry": {
    "type": "Point",
    "coordinates": [
      17.41329,
      52.36496
    ]
  }
}