{
  "type": "Feature",
  "properties": {
    "name": "Pakosław",
    "country": "PL",
    "subdivision": "86",
    "timezone": "Europe/Warsaw"
  },
  "geometry": {
    "type": "Point",
    "coordinates": [
      17.05793,
      51.61438
    ]
  }
}