{
  "type": "Feature",
  "properties": {
    "name": "Pleszew",
    "country": "PL",
    "subdivision": "86",
    "timezone": "Europe/Warsaw"
  },
  "geometry": {
    "type": "Point",
    "coordinates": [
      17.78549,
      51.89636
    ]
  }
}