{
  "type": "Feature",
  "properties": {
    "name": "Rakoniewice",
    "country": "PL",
    "subdivision": "86",
    "timezone": "Europe/Warsaw"
  },
  "geometry": {
    "type": "Point",
    "coordinates": [
      16.27346,
      52.13906
    ]
  }
}