{
  "type": "Feature",
  "properties": {
    "name": "Rawicz",
    "country": "PL",
    "subdivision": "86",
    "timezone": "Europe/Warsaw"
  },
  "geometry": {
    "type": "Point",
    "coordinates": [
      16.85852,
      51.60946
    ]
  }
}