{
  "type": "Feature",
  "properties": {
    "name": "Rogalinek",
    "country": "PL",
    "subdivision": "86",
    "timezone": "Europe/Warsaw"
  },
  "geometry": {
    "type": "Point",
    "coordinates": [
      16.89989,
      52.24945
    ]
  }
}