{
  "type": "Feature",
  "properties": {
    "name": "Rokietnica",
    "country": "PL",
    "subdivision": "86",
    "timezone": "Europe/Warsaw"
  },
  "geometry": {
    "type": "Point",
    "coordinates": [
      16.7457,
      52.51245
    ]
  }
}