{
  "type": "Feature",
  "properties": {
    "name": "Święciechowa",
    "country": "PL",
    "subdivision": "86",
    "timezone": "Europe/Warsaw"
  },
  "geometry": {
    "type": "Point",
    "coordinates": [
      16.49805,
      51.85503
    ]
  }
}