{
  "type": "Feature",
  "properties": {
    "name": "Słupca",
    "country": "PL",
    "subdivision": "86",
    "timezone": "Europe/Warsaw"
  },
  "geometry": {
    "type": "Point",
    "coordinates": [
      17.87192,
      52.28733
    ]
  }
}