{
  "type": "Feature",
  "properties": {
    "name": "Żerków",
    "country": "PL",
    "subdivision": "86",
    "timezone": "Europe/Warsaw"
  },
  "geometry": {
    "type": "Point",
    "coordinates": [
      17.56349,
      52.06877
    ]
  }
}