{
  "type": "Feature",
  "properties": {
    "name": "Złotów",
    "country": "PL",
    "subdivision": "86",
    "timezone": "Europe/Warsaw"
  },
  "geometry": {
    "type": "Point",
    "coordinates": [
      17.04082,
      53.36346
    ]
  }
}