{
  "type": "Feature",
  "properties": {
    "name": "Arroyo Zapotillo",
    "country": "MX",
    "subdivision": "20",
    "timezone": "America/Mexico_City"
  },
  "geometry": {
    "type": "Point",
    "coordinates": [
      -96.54417,
      18.07639
    ]
  }
}