{
  "type": "Feature",
  "properties": {
    "name": "Benito Juárez II (San Martín)",
    "country": "MX",
    "subdivision": "20",
    "timezone": "America/Mexico_City"
  },
  "geometry": {
    "type": "Point",
    "coordinates": [
      -96.46139,
      18.14056
    ]
  }
}