{
  "type": "Feature",
  "properties": {
    "name": "Cerro Armadillo Grande",
    "country": "MX",
    "subdivision": "20",
    "timezone": "America/Mexico_City"
  },
  "geometry": {
    "type": "Point",
    "coordinates": [
      -96.30861,
      17.86611
    ]
  }
}