{
  "type": "Feature",
  "properties": {
    "name": "Cieneguilla",
    "country": "MX",
    "subdivision": "20",
    "timezone": "America/Mexico_City"
  },
  "geometry": {
    "type": "Point",
    "coordinates": [
      -97.31762,
      16.32353
    ]
  }
}