{
  "type": "Feature",
  "properties": {
    "name": "Coixtlahuaca",
    "country": "MX",
    "subdivision": "20",
    "timezone": "America/Mexico_City"
  },
  "geometry": {
    "type": "Point",
    "coordinates": [
      -97.3188,
      17.72021
    ]
  }
}