{
  "type": "Feature",
  "properties": {
    "name": "Constancia del Rosario",
    "country": "MX",
    "subdivision": "20",
    "timezone": "America/Mexico_City"
  },
  "geometry": {
    "type": "Point",
    "coordinates": [
      -97.94125,
      17.0382
    ]
  }
}