{
  "type": "Feature",
  "properties": {
    "name": "Cuicatlan",
    "country": "MX",
    "subdivision": "20",
    "timezone": "America/Mexico_City"
  },
  "geometry": {
    "type": "Point",
    "coordinates": [
      -96.95939,
      17.80272
    ]
  }
}