{
  "type": "Feature",
  "properties": {
    "name": "Ejutla de Crespo",
    "country": "MX",
    "subdivision": "20",
    "timezone": "America/Mexico_City"
  },
  "geometry": {
    "type": "Point",
    "coordinates": [
      -96.73123,
      16.56623
    ]
  }
}