{
  "type": "Feature",
  "properties": {
    "name": "El Arador",
    "country": "MX",
    "subdivision": "20",
    "timezone": "America/Mexico_City"
  },
  "geometry": {
    "type": "Point",
    "coordinates": [
      -97.18194,
      16.54111
    ]
  }
}