{
  "type": "Feature",
  "properties": {
    "name": "Huajintepec",
    "country": "MX",
    "subdivision": "20",
    "timezone": "America/Mexico_City"
  },
  "geometry": {
    "type": "Point",
    "coordinates": [
      -98.23028,
      16.61003
    ]
  }
}