{
  "type": "Feature",
  "properties": {
    "name": "Ixtlán de Juárez",
    "country": "MX",
    "subdivision": "20",
    "timezone": "America/Mexico_City"
  },
  "geometry": {
    "type": "Point",
    "coordinates": [
      -96.48812,
      17.33211
    ]
  }
}