{
  "type": "Feature",
  "properties": {
    "name": "La Tabaquera",
    "country": "MX",
    "subdivision": "20",
    "timezone": "America/Mexico_City"
  },
  "geometry": {
    "type": "Point",
    "coordinates": [
      -96.45129,
      18.33582
    ]
  }
}