{
  "type": "Feature",
  "properties": {
    "name": "Loma Chapultepec",
    "country": "MX",
    "subdivision": "20",
    "timezone": "America/Mexico_City"
  },
  "geometry": {
    "type": "Point",
    "coordinates": [
      -96.83917,
      18.11972
    ]
  }
}