{
  "type": "Feature",
  "properties": {
    "name": "Los Naranjos Esquipulas",
    "country": "MX",
    "subdivision": "20",
    "timezone": "America/Mexico_City"
  },
  "geometry": {
    "type": "Point",
    "coordinates": [
      -96.45889,
      15.98167
    ]
  }
}