{
  "type": "Feature",
  "properties": {
    "name": "Macín Chico",
    "country": "MX",
    "subdivision": "20",
    "timezone": "America/Mexico_City"
  },
  "geometry": {
    "type": "Point",
    "coordinates": [
      -96.27184,
      18.0682
    ]
  }
}