{
  "type": "Feature",
  "properties": {
    "name": "Magdalena Ocotlán",
    "country": "MX",
    "subdivision": "20",
    "timezone": "America/Mexico_City"
  },
  "geometry": {
    "type": "Point",
    "coordinates": [
      -96.7101,
      16.70865
    ]
  }
}