{
  "type": "Feature",
  "properties": {
    "name": "Mancuernas",
    "country": "MX",
    "subdivision": "20",
    "timezone": "America/Mexico_City"
  },
  "geometry": {
    "type": "Point",
    "coordinates": [
      -98.11018,
      16.3894
    ]
  }
}