{
  "type": "Feature",
  "properties": {
    "name": "Nuevo San Martín",
    "country": "MX",
    "subdivision": "20",
    "timezone": "America/Mexico_City"
  },
  "geometry": {
    "type": "Point",
    "coordinates": [
      -95.52346,
      17.57987
    ]
  }
}