{
  "type": "Feature",
  "properties": {
    "name": "Peña Colorada",
    "country": "MX",
    "subdivision": "20",
    "timezone": "America/Mexico_City"
  },
  "geometry": {
    "type": "Point",
    "coordinates": [
      -97.79417,
      17.47778
    ]
  }
}