{
  "type": "Feature",
  "properties": {
    "name": "Río Chiquito",
    "country": "MX",
    "subdivision": "20",
    "timezone": "America/Mexico_City"
  },
  "geometry": {
    "type": "Point",
    "coordinates": [
      -95.93688,
      17.61989
    ]
  }
}