{
  "type": "Feature",
  "properties": {
    "name": "Salina Cruz",
    "country": "MX",
    "subdivision": "20",
    "timezone": "America/Mexico_City"
  },
  "geometry": {
    "type": "Point",
    "coordinates": [
      -95.19424,
      16.17535
    ]
  }
}