{
  "type": "Feature",
  "properties": {
    "name": "San Pablo Villa de Mitla",
    "country": "MX",
    "subdivision": "20",
    "timezone": "America/Mexico_City"
  },
  "geometry": {
    "type": "Point",
    "coordinates": [
      -96.3599,
      16.92283
    ]
  }
}