{
  "type": "Feature",
  "properties": {
    "name": "San Sebastián Río Hondo",
    "country": "MX",
    "subdivision": "20",
    "timezone": "America/Mexico_City"
  },
  "geometry": {
    "type": "Point",
    "coordinates": [
      -96.46535,
      16.1838
    ]
  }
}