{
  "type": "Feature",
  "properties": {
    "name": "San Lucas Camotlán",
    "country": "MX",
    "subdivision": "20",
    "timezone": "America/Mexico_City"
  },
  "geometry": {
    "type": "Point",
    "coordinates": [
      -95.71382,
      16.94473
    ]
  }
}