{
  "type": "Feature",
  "properties": {
    "name": "San Miguel Tlacotepec",
    "country": "MX",
    "subdivision": "20",
    "timezone": "America/Mexico_City"
  },
  "geometry": {
    "type": "Point",
    "coordinates": [
      -98.00547,
      17.45621
    ]
  }
}