{
  "type": "Feature",
  "properties": {
    "name": "San Sebastián Tutla",
    "country": "MX",
    "subdivision": "20",
    "timezone": "America/Mexico_City"
  },
  "geometry": {
    "type": "Point",
    "coordinates": [
      -96.67604,
      17.05834
    ]
  }
}