{
  "type": "Feature",
  "properties": {
    "name": "San Juan Atepec",
    "country": "MX",
    "subdivision": "20",
    "timezone": "America/Mexico_City"
  },
  "geometry": {
    "type": "Point",
    "coordinates": [
      -96.53968,
      17.42819
    ]
  }
}