{
  "type": "Feature",
  "properties": {
    "name": "San Juan Quiahue",
    "country": "MX",
    "subdivision": "20",
    "timezone": "America/Mexico_City"
  },
  "geometry": {
    "type": "Point",
    "coordinates": [
      -97.31729,
      16.3022
    ]
  }
}