{
  "type": "Feature",
  "properties": {
    "name": "San Andrés Chicahuaxtla",
    "country": "MX",
    "subdivision": "20",
    "timezone": "America/Mexico_City"
  },
  "geometry": {
    "type": "Point",
    "coordinates": [
      -97.83703,
      17.15698
    ]
  }
}