{
  "type": "Feature",
  "properties": {
    "name": "San Cristóbal Lachirioag",
    "country": "MX",
    "subdivision": "20",
    "timezone": "America/Mexico_City"
  },
  "geometry": {
    "type": "Point",
    "coordinates": [
      -96.16503,
      17.33582
    ]
  }
}