{
  "type": "Feature",
  "properties": {
    "name": "San Felipe Jalapa de Díaz",
    "country": "MX",
    "subdivision": "20",
    "timezone": "America/Mexico_City"
  },
  "geometry": {
    "type": "Point",
    "coordinates": [
      -96.53562,
      18.0712
    ]
  }
}