{
  "type": "Feature",
  "properties": {
    "name": "San Pedro Martir",
    "country": "MX",
    "subdivision": "20",
    "timezone": "America/Mexico_City"
  },
  "geometry": {
    "type": "Point",
    "coordinates": [
      -96.71118,
      16.74317
    ]
  }
}