{
  "type": "Feature",
  "properties": {
    "name": "San Agustín Etla",
    "country": "MX",
    "subdivision": "20",
    "timezone": "America/Mexico_City"
  },
  "geometry": {
    "type": "Point",
    "coordinates": [
      -96.76661,
      17.18654
    ]
  }
}