{
  "type": "Feature",
  "properties": {
    "name": "San Antonio las Palmas",
    "country": "MX",
    "subdivision": "20",
    "timezone": "America/Mexico_City"
  },
  "geometry": {
    "type": "Point",
    "coordinates": [
      -96.09083,
      17.67167
    ]
  }
}