{
  "type": "Feature",
  "properties": {
    "name": "San Mateo Nejápam",
    "country": "MX",
    "subdivision": "20",
    "timezone": "America/Mexico_City"
  },
  "geometry": {
    "type": "Point",
    "coordinates": [
      -98.41662,
      17.65604
    ]
  }
}