{
  "type": "Feature",
  "properties": {
    "name": "San Juan Teitipac",
    "country": "MX",
    "subdivision": "20",
    "timezone": "America/Mexico_City"
  },
  "geometry": {
    "type": "Point",
    "coordinates": [
      -96.60619,
      16.92799
    ]
  }
}