{
  "type": "Feature",
  "properties": {
    "name": "San Mateo Yoloxochitlán",
    "country": "MX",
    "subdivision": "20",
    "timezone": "America/Mexico_City"
  },
  "geometry": {
    "type": "Point",
    "coordinates": [
      -96.86865,
      18.14341
    ]
  }
}