{
  "type": "Feature",
  "properties": {
    "name": "San Jerónimo Tlacochahuaya",
    "country": "MX",
    "subdivision": "20",
    "timezone": "America/Mexico_City"
  },
  "geometry": {
    "type": "Point",
    "coordinates": [
      -96.58275,
      17.00874
    ]
  }
}