{
  "type": "Feature",
  "properties": {
    "name": "San Andrés Zautla",
    "country": "MX",
    "subdivision": "20",
    "timezone": "America/Mexico_City"
  },
  "geometry": {
    "type": "Point",
    "coordinates": [
      -96.86419,
      17.18697
    ]
  }
}