{
  "type": "Feature",
  "properties": {
    "name": "San Francisco Javier",
    "country": "MX",
    "subdivision": "20",
    "timezone": "America/Mexico_City"
  },
  "geometry": {
    "type": "Point",
    "coordinates": [
      -96.7775,
      17.02861
    ]
  }
}