{
  "type": "Feature",
  "properties": {
    "name": "San Sebastián Etla",
    "country": "MX",
    "subdivision": "20",
    "timezone": "America/Mexico_City"
  },
  "geometry": {
    "type": "Point",
    "coordinates": [
      -96.78343,
      17.16437
    ]
  }
}