{
  "type": "Feature",
  "properties": {
    "name": "San Bartolomé Loxícha",
    "country": "MX",
    "subdivision": "20",
    "timezone": "America/Mexico_City"
  },
  "geometry": {
    "type": "Point",
    "coordinates": [
      -96.70957,
      15.96981
    ]
  }
}