{
  "type": "Feature",
  "properties": {
    "name": "San Lorenzo Cacaotepec",
    "country": "MX",
    "subdivision": "20",
    "timezone": "America/Mexico_City"
  },
  "geometry": {
    "type": "Point",
    "coordinates": [
      -96.80244,
      17.12774
    ]
  }
}