{
  "type": "Feature",
  "properties": {
    "name": "San Marcial Ozolotepec",
    "country": "MX",
    "subdivision": "20",
    "timezone": "America/Mexico_City"
  },
  "geometry": {
    "type": "Point",
    "coordinates": [
      -96.40561,
      16.08903
    ]
  }
}