{
  "type": "Feature",
  "properties": {
    "name": "San Pedro Ixtlahuaca",
    "country": "MX",
    "subdivision": "20",
    "timezone": "America/Mexico_City"
  },
  "geometry": {
    "type": "Point",
    "coordinates": [
      -96.81841,
      17.0636
    ]
  }
}