{
  "type": "Feature",
  "properties": {
    "name": "San Miguel Tlacamama",
    "country": "MX",
    "subdivision": "20",
    "timezone": "America/Mexico_City"
  },
  "geometry": {
    "type": "Point",
    "coordinates": [
      -98.06301,
      16.41547
    ]
  }
}