{
  "type": "Feature",
  "properties": {
    "name": "San Pedro Juchaltengo",
    "country": "MX",
    "subdivision": "20",
    "timezone": "America/Mexico_City"
  },
  "geometry": {
    "type": "Point",
    "coordinates": [
      -97.08954,
      16.3453
    ]
  }
}