{
  "type": "Feature",
  "properties": {
    "name": "Santo Tomás Jalieza",
    "country": "MX",
    "subdivision": "20",
    "timezone": "America/Mexico_City"
  },
  "geometry": {
    "type": "Point",
    "coordinates": [
      -96.67063,
      16.84469
    ]
  }
}