{
  "type": "Feature",
  "properties": {
    "name": "Santiago Cuixtla",
    "country": "MX",
    "subdivision": "20",
    "timezone": "America/Mexico_City"
  },
  "geometry": {
    "type": "Point",
    "coordinates": [
      -97.18586,
      16.06196
    ]
  }
}