{
  "type": "Feature",
  "properties": {
    "name": "Santiago Ixtaltepec",
    "country": "MX",
    "subdivision": "20",
    "timezone": "America/Mexico_City"
  },
  "geometry": {
    "type": "Point",
    "coordinates": [
      -94.90583,
      16.68833
    ]
  }
}