{
  "type": "Feature",
  "properties": {
    "name": "Santiago Malacatepec",
    "country": "MX",
    "subdivision": "20",
    "timezone": "America/Mexico_City"
  },
  "geometry": {
    "type": "Point",
    "coordinates": [
      -95.6075,
      17.01639
    ]
  }
}