{
  "type": "Feature",
  "properties": {
    "name": "Santa María Cortijo",
    "country": "MX",
    "subdivision": "20",
    "timezone": "America/Mexico_City"
  },
  "geometry": {
    "type": "Point",
    "coordinates": [
      -98.28549,
      16.45151
    ]
  }
}