{
  "type": "Feature",
  "properties": {
    "name": "Santa Lucía",
    "country": "MX",
    "subdivision": "20",
    "timezone": "America/Mexico_City"
  },
  "geometry": {
    "type": "Point",
    "coordinates": [
      -96.61404,
      16.1886
    ]
  }
}