{
  "type": "Feature",
  "properties": {
    "name": "Santiago Ixtayutla",
    "country": "MX",
    "subdivision": "20",
    "timezone": "America/Mexico_City"
  },
  "geometry": {
    "type": "Point",
    "coordinates": [
      -97.65285,
      16.56649
    ]
  }
}