{
  "type": "Feature",
  "properties": {
    "name": "Santa María Tonameca",
    "country": "MX",
    "subdivision": "20",
    "timezone": "America/Mexico_City"
  },
  "geometry": {
    "type": "Point",
    "coordinates": [
      -96.54704,
      15.74805
    ]
  }
}