{
  "type": "Feature",
  "properties": {
    "name": "Santa Cruz Acatepec",
    "country": "MX",
    "subdivision": "20",
    "timezone": "America/Mexico_City"
  },
  "geometry": {
    "type": "Point",
    "coordinates": [
      -96.87503,
      18.16369
    ]
  }
}