{
  "type": "Feature",
  "properties": {
    "name": "Santa María Jalapa del Marqués",
    "country": "MX",
    "subdivision": "20",
    "timezone": "America/Mexico_City"
  },
  "geometry": {
    "type": "Point",
    "coordinates": [
      -95.44454,
      16.44027
    ]
  }
}