{
  "type": "Feature",
  "properties": {
    "name": "Santa María Temaxcaltepec",
    "country": "MX",
    "subdivision": "20",
    "timezone": "America/Mexico_City"
  },
  "geometry": {
    "type": "Point",
    "coordinates": [
      -97.1971,
      16.16552
    ]
  }
}