{
  "type": "Feature",
  "properties": {
    "name": "Santiago Yogana",
    "country": "MX",
    "subdivision": "20",
    "timezone": "America/Mexico_City"
  },
  "geometry": {
    "type": "Point",
    "coordinates": [
      -96.78786,
      16.4613
    ]
  }
}