{
  "type": "Feature",
  "properties": {
    "name": "Santa María Zapotitlán",
    "country": "MX",
    "subdivision": "20",
    "timezone": "America/Mexico_City"
  },
  "geometry": {
    "type": "Point",
    "coordinates": [
      -95.85239,
      16.12781
    ]
  }
}