{
  "type": "Feature",
  "properties": {
    "name": "Tanetze de Zaragoza",
    "country": "MX",
    "subdivision": "20",
    "timezone": "America/Mexico_City"
  },
  "geometry": {
    "type": "Point",
    "coordinates": [
      -96.30111,
      17.37616
    ]
  }
}