{
  "type": "Feature",
  "properties": {
    "name": "Tapanalá",
    "country": "MX",
    "subdivision": "20",
    "timezone": "America/Mexico_City"
  },
  "geometry": {
    "type": "Point",
    "coordinates": [
      -95.72476,
      15.96659
    ]
  }
}