{
  "type": "Feature",
  "properties": {
    "name": "Texcatitlán",
    "country": "MX",
    "subdivision": "20",
    "timezone": "America/Mexico_City"
  },
  "geometry": {
    "type": "Point",
    "coordinates": [
      -97.06625,
      17.71259
    ]
  }
}