{
  "type": "Feature",
  "properties": {
    "name": "Valdeflores",
    "country": "MX",
    "subdivision": "20",
    "timezone": "America/Mexico_City"
  },
  "geometry": {
    "type": "Point",
    "coordinates": [
      -96.82435,
      16.76588
    ]
  }
}