{
  "type": "Feature",
  "properties": {
    "name": "Villa Chalcatongo de Hidalgo",
    "country": "MX",
    "subdivision": "20",
    "timezone": "America/Mexico_City"
  },
  "geometry": {
    "type": "Point",
    "coordinates": [
      -97.57057,
      17.03247
    ]
  }
}