{
  "type": "Feature",
  "properties": {
    "name": "Villa Sola de Vega",
    "country": "MX",
    "subdivision": "20",
    "timezone": "America/Mexico_City"
  },
  "geometry": {
    "type": "Point",
    "coordinates": [
      -96.9781,
      16.51844
    ]
  }
}