{
  "type": "Feature",
  "properties": {
    "name": "Yetla de Juárez",
    "country": "MX",
    "subdivision": "20",
    "timezone": "America/Mexico_City"
  },
  "geometry": {
    "type": "Point",
    "coordinates": [
      -97.99124,
      17.66559
    ]
  }
}