{
  "type": "Feature",
  "properties": {
    "name": "Grnčari",
    "country": "MK",
    "subdivision": "86",
    "timezone": "Europe/Skopje"
  },
  "geometry": {
    "type": "Point",
    "coordinates": [
      21.05333,
      41.01722
    ]
  }
}