{
  "type": "Feature",
  "properties": {
    "name": "El Tular",
    "country": "HN",
    "subdivision": "17",
    "timezone": "America/Tegucigalpa"
  },
  "geometry": {
    "type": "Point",
    "coordinates": [
      -87.51528,
      13.46639
    ]
  }
}