{
  "type": "Feature",
  "properties": {
    "name": "Chemal",
    "country": "RU",
    "subdivision": "03",
    "timezone": "Asia/Barnaul"
  },
  "geometry": {
    "type": "Point",
    "coordinates": [
      86.005,
      51.41111
    ]
  }
}