{
  "type": "Feature",
  "properties": {
    "name": "Elekmonar",
    "country": "RU",
    "subdivision": "03",
    "timezone": "Asia/Barnaul"
  },
  "geometry": {
    "type": "Point",
    "coordinates": [
      85.98778,
      51.45889
    ]
  }
}