{
  "type": "Feature",
  "properties": {
    "name": "Onguday",
    "country": "RU",
    "subdivision": "03",
    "timezone": "Asia/Barnaul"
  },
  "geometry": {
    "type": "Point",
    "coordinates": [
      86.15,
      50.75
    ]
  }
}