{
  "type": "Feature",
  "properties": {
    "name": "Turochak",
    "country": "RU",
    "subdivision": "03",
    "timezone": "Asia/Barnaul"
  },
  "geometry": {
    "type": "Point",
    "coordinates": [
      87.1224,
      52.2576
    ]
  }
}