{
  "type": "Feature",
  "properties": {
    "name": "Ust’-Kan",
    "country": "RU",
    "subdivision": "03",
    "timezone": "Asia/Barnaul"
  },
  "geometry": {
    "type": "Point",
    "coordinates": [
      84.761,
      50.9276
    ]
  }
}