{
  "type": "Feature",
  "properties": {
    "name": "Cotacachi",
    "country": "EC",
    "subdivision": "11",
    "timezone": "America/Guayaquil"
  },
  "geometry": {
    "type": "Point",
    "coordinates": [
      -78.26428,
      0.30107
    ]
  }
}