{
  "type": "Feature",
  "properties": {
    "name": "Anderlecht",
    "country": "BE",
    "subdivision": "BRU",
    "timezone": "Europe/Brussels"
  },
  "geometry": {
    "type": "Point",
    "coordinates": [
      4.31454,
      50.83619
    ]
  }
}