{
  "type": "Feature",
  "properties": {
    "name": "Daru",
    "country": "PG",
    "subdivision": "06",
    "timezone": "Pacific/Port_Moresby"
  },
  "geometry": {
    "type": "Point",
    "coordinates": [
      143.20893,
      -9.07786
    ]
  }
}