{
  "type": "Feature",
  "properties": {
    "name": "Morehead",
    "country": "PG",
    "subdivision": "06",
    "timezone": "Pacific/Port_Moresby"
  },
  "geometry": {
    "type": "Point",
    "coordinates": [
      141.63668,
      -8.71065
    ]
  }
}