{
  "type": "Feature",
  "properties": {
    "name": "Philipsburg",
    "country": "SX",
    "subdivision": "",
    "timezone": "America/Lower_Princes"
  },
  "geometry": {
    "type": "Point",
    "coordinates": [
      -63.04582,
      18.026
    ]
  }
}