{
  "type": "Feature",
  "properties": {
    "name": "Nyeri",
    "country": "KE",
    "subdivision": "44",
    "timezone": "Africa/Nairobi"
  },
  "geometry": {
    "type": "Point",
    "coordinates": [
      36.94759,
      -0.42013
    ]
  }
}