{
  "type": "Feature",
  "properties": {
    "name": "Mosfilotí",
    "country": "CY",
    "subdivision": "03",
    "timezone": "Asia/Nicosia"
  },
  "geometry": {
    "type": "Point",
    "coordinates": [
      33.42518,
      34.95322
    ]
  }
}