{
  "type": "Feature",
  "properties": {
    "name": "Pérgamos",
    "country": "CY",
    "subdivision": "03",
    "timezone": "Asia/Nicosia"
  },
  "geometry": {
    "type": "Point",
    "coordinates": [
      33.70833,
      35.04167
    ]
  }
}