{
  "type": "Feature",
  "properties": {
    "name": "Troúlloi",
    "country": "CY",
    "subdivision": "03",
    "timezone": "Asia/Nicosia"
  },
  "geometry": {
    "type": "Point",
    "coordinates": [
      33.61551,
      35.03263
    ]
  }
}