{
  "type": "Feature",
  "properties": {
    "name": "Digby",
    "country": "CA",
    "subdivision": "07",
    "timezone": "America/Halifax"
  },
  "geometry": {
    "type": "Point",
    "coordinates": [
      -65.7586,
      44.62188
    ]
  }
}