{
  "type": "Feature",
  "properties": {
    "name": "Fall River",
    "country": "CA",
    "subdivision": "07",
    "timezone": "America/Halifax"
  },
  "geometry": {
    "type": "Point",
    "coordinates": [
      -63.6154,
      44.81685
    ]
  }
}