{
  "type": "Feature",
  "properties": {
    "name": "Halifax",
    "country": "CA",
    "subdivision": "07",
    "timezone": "America/Halifax"
  },
  "geometry": {
    "type": "Point",
    "coordinates": [
      -63.57291,
      44.6464
    ]
  }
}