{
  "type": "Feature",
  "properties": {
    "name": "Kentville",
    "country": "CA",
    "subdivision": "07",
    "timezone": "America/Halifax"
  },
  "geometry": {
    "type": "Point",
    "coordinates": [
      -64.49605,
      45.0771
    ]
  }
}