{
  "type": "Feature",
  "properties": {
    "name": "Wolfville",
    "country": "CA",
    "subdivision": "07",
    "timezone": "America/Halifax"
  },
  "geometry": {
    "type": "Point",
    "coordinates": [
      -64.36546,
      45.08345
    ]
  }
}