{
  "type": "Feature",
  "properties": {
    "name": "Tursunzoda",
    "country": "TJ",
    "subdivision": "RR",
    "timezone": "Asia/Dushanbe"
  },
  "geometry": {
    "type": "Point",
    "coordinates": [
      68.23163,
      38.51271
    ]
  }
}