{
  "type": "Feature",
  "properties": {
    "name": "Nal’chik",
    "country": "RU",
    "subdivision": "22",
    "timezone": "Europe/Moscow"
  },
  "geometry": {
    "type": "Point",
    "coordinates": [
      43.61889,
      43.49806
    ]
  }
}