{
  "type": "Feature",
  "properties": {
    "name": "Psygansu",
    "country": "RU",
    "subdivision": "22",
    "timezone": "Europe/Moscow"
  },
  "geometry": {
    "type": "Point",
    "coordinates": [
      43.79066,
      43.41338
    ]
  }
}