{
  "type": "Feature",
  "properties": {
    "name": "Urvan’",
    "country": "RU",
    "subdivision": "22",
    "timezone": "Europe/Moscow"
  },
  "geometry": {
    "type": "Point",
    "coordinates": [
      43.76379,
      43.48936
    ]
  }
}