{
  "type": "Feature",
  "properties": {
    "name": "Gubkinskiy",
    "country": "RU",
    "subdivision": "87",
    "timezone": "Asia/Yekaterinburg"
  },
  "geometry": {
    "type": "Point",
    "coordinates": [
      76.50261,
      64.434
    ]
  }
}