{
  "type": "Feature",
  "properties": {
    "name": "Azovo",
    "country": "RU",
    "subdivision": "54",
    "timezone": "Asia/Omsk"
  },
  "geometry": {
    "type": "Point",
    "coordinates": [
      73.02367,
      54.69972
    ]
  }
}