{
  "type": "Feature",
  "properties": {
    "name": "Kalachinsk",
    "country": "RU",
    "subdivision": "54",
    "timezone": "Asia/Omsk"
  },
  "geometry": {
    "type": "Point",
    "coordinates": [
      74.57511,
      55.05286
    ]
  }
}