{
  "type": "Feature",
  "properties": {
    "name": "Odesskoye",
    "country": "RU",
    "subdivision": "54",
    "timezone": "Asia/Omsk"
  },
  "geometry": {
    "type": "Point",
    "coordinates": [
      72.9651,
      54.215
    ]
  }
}