{
  "type": "Feature",
  "properties": {
    "name": "Poltavka",
    "country": "RU",
    "subdivision": "54",
    "timezone": "Asia/Omsk"
  },
  "geometry": {
    "type": "Point",
    "coordinates": [
      71.76319,
      54.36629
    ]
  }
}