{
  "type": "Feature",
  "properties": {
    "name": "Ust’-Ishim",
    "country": "RU",
    "subdivision": "54",
    "timezone": "Asia/Omsk"
  },
  "geometry": {
    "type": "Point",
    "coordinates": [
      71.1665,
      57.6935
    ]
  }
}