{
  "type": "Feature",
  "properties": {
    "name": "Znamenskoye",
    "country": "RU",
    "subdivision": "54",
    "timezone": "Asia/Omsk"
  },
  "geometry": {
    "type": "Point",
    "coordinates": [
      73.82821,
      57.12806
    ]
  }
}