{
  "type": "Feature",
  "properties": {
    "name": "Benito García (El Zorrillo)",
    "country": "MX",
    "subdivision": "02",
    "timezone": "America/Tijuana"
  },
  "geometry": {
    "type": "Point",
    "coordinates": [
      -116.51139,
      31.67111
    ]
  }
}