{
  "type": "Feature",
  "properties": {
    "name": "Benito Juárez",
    "country": "MX",
    "subdivision": "02",
    "timezone": "America/Tijuana"
  },
  "geometry": {
    "type": "Point",
    "coordinates": [
      -114.99422,
      32.56852
    ]
  }
}