{
  "type": "Feature",
  "properties": {
    "name": "Ciudad Coahuila (Kilómetro Cincuenta y Siete)",
    "country": "MX",
    "subdivision": "02",
    "timezone": "America/Tijuana"
  },
  "geometry": {
    "type": "Point",
    "coordinates": [
      -115.0025,
      32.19556
    ]
  }
}