{
  "type": "Feature",
  "properties": {
    "name": "Colinas del Sol",
    "country": "MX",
    "subdivision": "02",
    "timezone": "America/Tijuana"
  },
  "geometry": {
    "type": "Point",
    "coordinates": [
      -117.03056,
      32.40306
    ]
  }
}