{
  "type": "Feature",
  "properties": {
    "name": "Ejido Javier Rojo Gómez",
    "country": "MX",
    "subdivision": "02",
    "timezone": "America/Tijuana"
  },
  "geometry": {
    "type": "Point",
    "coordinates": [
      -116.82222,
      32.49389
    ]
  }
}