{
  "type": "Feature",
  "properties": {
    "name": "Ejido Netzahualcóyotl",
    "country": "MX",
    "subdivision": "02",
    "timezone": "America/Tijuana"
  },
  "geometry": {
    "type": "Point",
    "coordinates": [
      -115.06222,
      32.62444
    ]
  }
}