{
  "type": "Feature",
  "properties": {
    "name": "Lomas de Santa Anita",
    "country": "MX",
    "subdivision": "02",
    "timezone": "America/Tijuana"
  },
  "geometry": {
    "type": "Point",
    "coordinates": [
      -116.65139,
      32.54278
    ]
  }
}