{
  "type": "Feature",
  "properties": {
    "name": "Poblado Lázaro Cárdenas (La Veintiocho)",
    "country": "MX",
    "subdivision": "02",
    "timezone": "America/Tijuana"
  },
  "geometry": {
    "type": "Point",
    "coordinates": [
      -115.06528,
      32.37333
    ]
  }
}