{
  "type": "Feature",
  "properties": {
    "name": "Pórticos de San Antonio",
    "country": "MX",
    "subdivision": "02",
    "timezone": "America/Tijuana"
  },
  "geometry": {
    "type": "Point",
    "coordinates": [
      -117.03417,
      32.4425
    ]
  }
}