{
  "type": "Feature",
  "properties": {
    "name": "San Luis",
    "country": "MX",
    "subdivision": "02",
    "timezone": "America/Tijuana"
  },
  "geometry": {
    "type": "Point",
    "coordinates": [
      -113.75,
      28.43333
    ]
  }
}