{
  "type": "Feature",
  "properties": {
    "name": "San Vicente",
    "country": "MX",
    "subdivision": "02",
    "timezone": "America/Tijuana"
  },
  "geometry": {
    "type": "Point",
    "coordinates": [
      -116.24662,
      31.32518
    ]
  }
}