{
  "type": "Feature",
  "properties": {
    "name": "Tecate",
    "country": "MX",
    "subdivision": "02",
    "timezone": "America/Tijuana"
  },
  "geometry": {
    "type": "Point",
    "coordinates": [
      -116.62509,
      32.56717
    ]
  }
}