{
  "type": "Feature",
  "properties": {
    "name": "Tecolots",
    "country": "MX",
    "subdivision": "02",
    "timezone": "America/Tijuana"
  },
  "geometry": {
    "type": "Point",
    "coordinates": [
      -114.98333,
      32.56667
    ]
  }
}