{
  "type": "Feature",
  "properties": {
    "name": "Airlie Beach",
    "country": "AU",
    "subdivision": "04",
    "timezone": "Australia/Brisbane"
  },
  "geometry": {
    "type": "Point",
    "coordinates": [
      148.71471,
      -20.26751
    ]
  }
}