{
  "type": "Feature",
  "properties": {
    "name": "Alexandra Headland",
    "country": "AU",
    "subdivision": "04",
    "timezone": "Australia/Brisbane"
  },
  "geometry": {
    "type": "Point",
    "coordinates": [
      153.10058,
      -26.67154
    ]
  }
}