{
  "type": "Feature",
  "properties": {
    "name": "Avoca",
    "country": "AU",
    "subdivision": "04",
    "timezone": "Australia/Brisbane"
  },
  "geometry": {
    "type": "Point",
    "coordinates": [
      152.30794,
      -24.87822
    ]
  }
}