{
  "type": "Feature",
  "properties": {
    "name": "Ayr",
    "country": "AU",
    "subdivision": "04",
    "timezone": "Australia/Brisbane"
  },
  "geometry": {
    "type": "Point",
    "coordinates": [
      147.40666,
      -19.57393
    ]
  }
}