{
  "type": "Feature",
  "properties": {
    "name": "Babinda",
    "country": "AU",
    "subdivision": "04",
    "timezone": "Australia/Brisbane"
  },
  "geometry": {
    "type": "Point",
    "coordinates": [
      145.92265,
      -17.3439
    ]
  }
}