{
  "type": "Feature",
  "properties": {
    "name": "Bahrs Scrub",
    "country": "AU",
    "subdivision": "04",
    "timezone": "Australia/Brisbane"
  },
  "geometry": {
    "type": "Point",
    "coordinates": [
      153.16667,
      -27.73333
    ]
  }
}