{
  "type": "Feature",
  "properties": {
    "name": "Bald Hills",
    "country": "AU",
    "subdivision": "04",
    "timezone": "Australia/Brisbane"
  },
  "geometry": {
    "type": "Point",
    "coordinates": [
      153.00857,
      -27.32112
    ]
  }
}