{
  "type": "Feature",
  "properties": {
    "name": "Banyo",
    "country": "AU",
    "subdivision": "04",
    "timezone": "Australia/Brisbane"
  },
  "geometry": {
    "type": "Point",
    "coordinates": [
      153.07903,
      -27.38236
    ]
  }
}