{
  "type": "Feature",
  "properties": {
    "name": "Barney Point",
    "country": "AU",
    "subdivision": "04",
    "timezone": "Australia/Brisbane"
  },
  "geometry": {
    "type": "Point",
    "coordinates": [
      151.26577,
      -23.84793
    ]
  }
}