{
  "type": "Feature",
  "properties": {
    "name": "Beaconsfield",
    "country": "AU",
    "subdivision": "04",
    "timezone": "Australia/Brisbane"
  },
  "geometry": {
    "type": "Point",
    "coordinates": [
      149.16544,
      -21.09121
    ]
  }
}