{
  "type": "Feature",
  "properties": {
    "name": "Belgian Gardens",
    "country": "AU",
    "subdivision": "04",
    "timezone": "Australia/Brisbane"
  },
  "geometry": {
    "type": "Point",
    "coordinates": [
      146.79455,
      -19.24507
    ]
  }
}