{
  "type": "Feature",
  "properties": {
    "name": "Bellmere",
    "country": "AU",
    "subdivision": "04",
    "timezone": "Australia/Brisbane"
  },
  "geometry": {
    "type": "Point",
    "coordinates": [
      152.89003,
      -27.08441
    ]
  }
}