{
  "type": "Feature",
  "properties": {
    "name": "Benaraby",
    "country": "AU",
    "subdivision": "04",
    "timezone": "Australia/Brisbane"
  },
  "geometry": {
    "type": "Point",
    "coordinates": [
      151.3341,
      -24.00417
    ]
  }
}