{
  "type": "Feature",
  "properties": {
    "name": "Benowa",
    "country": "AU",
    "subdivision": "04",
    "timezone": "Australia/Brisbane"
  },
  "geometry": {
    "type": "Point",
    "coordinates": [
      153.38583,
      -28.0077
    ]
  }
}