{
  "type": "Feature",
  "properties": {
    "name": "Bilinga",
    "country": "AU",
    "subdivision": "04",
    "timezone": "Australia/Brisbane"
  },
  "geometry": {
    "type": "Point",
    "coordinates": [
      153.51667,
      -28.16667
    ]
  }
}