{
  "type": "Feature",
  "properties": {
    "name": "Biloela",
    "country": "AU",
    "subdivision": "04",
    "timezone": "Australia/Brisbane"
  },
  "geometry": {
    "type": "Point",
    "coordinates": [
      150.51504,
      -24.39589
    ]
  }
}