{
  "type": "Feature",
  "properties": {
    "name": "Bokarina",
    "country": "AU",
    "subdivision": "04",
    "timezone": "Australia/Brisbane"
  },
  "geometry": {
    "type": "Point",
    "coordinates": [
      153.13049,
      -26.73843
    ]
  }
}