{
  "type": "Feature",
  "properties": {
    "name": "Boonah",
    "country": "AU",
    "subdivision": "04",
    "timezone": "Australia/Brisbane"
  },
  "geometry": {
    "type": "Point",
    "coordinates": [
      152.68108,
      -27.99724
    ]
  }
}