{
  "type": "Feature",
  "properties": {
    "name": "Bowen Hills",
    "country": "AU",
    "subdivision": "04",
    "timezone": "Australia/Brisbane"
  },
  "geometry": {
    "type": "Point",
    "coordinates": [
      153.03728,
      -27.44369
    ]
  }
}