{
  "type": "Feature",
  "properties": {
    "name": "Broadbeach",
    "country": "AU",
    "subdivision": "04",
    "timezone": "Australia/Brisbane"
  },
  "geometry": {
    "type": "Point",
    "coordinates": [
      153.43343,
      -28.02782
    ]
  }
}