{
  "type": "Feature",
  "properties": {
    "name": "Bucasia",
    "country": "AU",
    "subdivision": "04",
    "timezone": "Australia/Brisbane"
  },
  "geometry": {
    "type": "Point",
    "coordinates": [
      149.15726,
      -21.03494
    ]
  }
}