{
  "type": "Feature",
  "properties": {
    "name": "Bundamba",
    "country": "AU",
    "subdivision": "04",
    "timezone": "Australia/Brisbane"
  },
  "geometry": {
    "type": "Point",
    "coordinates": [
      152.81133,
      -27.60947
    ]
  }
}