{
  "type": "Feature",
  "properties": {
    "name": "Cashmere",
    "country": "AU",
    "subdivision": "04",
    "timezone": "Australia/Brisbane"
  },
  "geometry": {
    "type": "Point",
    "coordinates": [
      152.90662,
      -27.29767
    ]
  }
}