{
  "type": "Feature",
  "properties": {
    "name": "Charters Towers City",
    "country": "AU",
    "subdivision": "04",
    "timezone": "Australia/Brisbane"
  },
  "geometry": {
    "type": "Point",
    "coordinates": [
      146.26275,
      -20.07774
    ]
  }
}