{
  "type": "Feature",
  "properties": {
    "name": "Chatsworth",
    "country": "AU",
    "subdivision": "04",
    "timezone": "Australia/Brisbane"
  },
  "geometry": {
    "type": "Point",
    "coordinates": [
      152.61503,
      -26.14398
    ]
  }
}