{
  "type": "Feature",
  "properties": {
    "name": "Cloncurry",
    "country": "AU",
    "subdivision": "04",
    "timezone": "Australia/Brisbane"
  },
  "geometry": {
    "type": "Point",
    "coordinates": [
      140.51303,
      -20.70718
    ]
  }
}