{
  "type": "Feature",
  "properties": {
    "name": "Collinsville",
    "country": "AU",
    "subdivision": "04",
    "timezone": "Australia/Brisbane"
  },
  "geometry": {
    "type": "Point",
    "coordinates": [
      147.84399,
      -20.55223
    ]
  }
}