{
  "type": "Feature",
  "properties": {
    "name": "Cooktown",
    "country": "AU",
    "subdivision": "04",
    "timezone": "Australia/Brisbane"
  },
  "geometry": {
    "type": "Point",
    "coordinates": [
      145.24984,
      -15.4657
    ]
  }
}