{
  "type": "Feature",
  "properties": {
    "name": "Cooloola Cove",
    "country": "AU",
    "subdivision": "04",
    "timezone": "Australia/Brisbane"
  },
  "geometry": {
    "type": "Point",
    "coordinates": [
      152.99355,
      -25.9864
    ]
  }
}