{
  "type": "Feature",
  "properties": {
    "name": "Coominya",
    "country": "AU",
    "subdivision": "04",
    "timezone": "Australia/Brisbane"
  },
  "geometry": {
    "type": "Point",
    "coordinates": [
      152.5006,
      -27.39009
    ]
  }
}