{
  "type": "Feature",
  "properties": {
    "name": "Craignish",
    "country": "AU",
    "subdivision": "04",
    "timezone": "Australia/Brisbane"
  },
  "geometry": {
    "type": "Point",
    "coordinates": [
      152.72429,
      -25.28258
    ]
  }
}