{
  "type": "Feature",
  "properties": {
    "name": "Craiglie",
    "country": "AU",
    "subdivision": "04",
    "timezone": "Australia/Brisbane"
  },
  "geometry": {
    "type": "Point",
    "coordinates": [
      145.46963,
      -16.53789
    ]
  }
}