{
  "type": "Feature",
  "properties": {
    "name": "Cranbrook",
    "country": "AU",
    "subdivision": "04",
    "timezone": "Australia/Brisbane"
  },
  "geometry": {
    "type": "Point",
    "coordinates": [
      146.75286,
      -19.30553
    ]
  }
}