{
  "type": "Feature",
  "properties": {
    "name": "Cunnamulla",
    "country": "AU",
    "subdivision": "04",
    "timezone": "Australia/Brisbane"
  },
  "geometry": {
    "type": "Point",
    "coordinates": [
      145.68439,
      -28.06766
    ]
  }
}