{
  "type": "Feature",
  "properties": {
    "name": "Dakabin",
    "country": "AU",
    "subdivision": "04",
    "timezone": "Australia/Brisbane"
  },
  "geometry": {
    "type": "Point",
    "coordinates": [
      152.99097,
      -27.22594
    ]
  }
}