{
  "type": "Feature",
  "properties": {
    "name": "Eagleby",
    "country": "AU",
    "subdivision": "04",
    "timezone": "Australia/Brisbane"
  },
  "geometry": {
    "type": "Point",
    "coordinates": [
      153.21667,
      -27.68333
    ]
  }
}