{
  "type": "Feature",
  "properties": {
    "name": "Earlville",
    "country": "AU",
    "subdivision": "04",
    "timezone": "Australia/Brisbane"
  },
  "geometry": {
    "type": "Point",
    "coordinates": [
      145.73308,
      -16.95078
    ]
  }
}