{
  "type": "Feature",
  "properties": {
    "name": "East Ipswich",
    "country": "AU",
    "subdivision": "04",
    "timezone": "Australia/Brisbane"
  },
  "geometry": {
    "type": "Point",
    "coordinates": [
      152.77232,
      -27.60637
    ]
  }
}