{
  "type": "Feature",
  "properties": {
    "name": "East Innisfail",
    "country": "AU",
    "subdivision": "04",
    "timezone": "Australia/Brisbane"
  },
  "geometry": {
    "type": "Point",
    "coordinates": [
      146.03487,
      -17.53324
    ]
  }
}