{
  "type": "Feature",
  "properties": {
    "name": "Emu Park",
    "country": "AU",
    "subdivision": "04",
    "timezone": "Australia/Brisbane"
  },
  "geometry": {
    "type": "Point",
    "coordinates": [
      150.82679,
      -23.2568
    ]
  }
}