{
  "type": "Feature",
  "properties": {
    "name": "Eudlo",
    "country": "AU",
    "subdivision": "04",
    "timezone": "Australia/Brisbane"
  },
  "geometry": {
    "type": "Point",
    "coordinates": [
      152.95395,
      -26.72963
    ]
  }
}