{
  "type": "Feature",
  "properties": {
    "name": "Ferny Grove",
    "country": "AU",
    "subdivision": "04",
    "timezone": "Australia/Brisbane"
  },
  "geometry": {
    "type": "Point",
    "coordinates": [
      152.93475,
      -27.4008
    ]
  }
}