{
  "type": "Feature",
  "properties": {
    "name": "Flinders View",
    "country": "AU",
    "subdivision": "04",
    "timezone": "Australia/Brisbane"
  },
  "geometry": {
    "type": "Point",
    "coordinates": [
      152.77451,
      -27.65046
    ]
  }
}