{
  "type": "Feature",
  "properties": {
    "name": "Gatton",
    "country": "AU",
    "subdivision": "04",
    "timezone": "Australia/Brisbane"
  },
  "geometry": {
    "type": "Point",
    "coordinates": [
      152.27618,
      -27.55873
    ]
  }
}