{
  "type": "Feature",
  "properties": {
    "name": "Gaythorne",
    "country": "AU",
    "subdivision": "04",
    "timezone": "Australia/Brisbane"
  },
  "geometry": {
    "type": "Point",
    "coordinates": [
      152.98333,
      -27.41667
    ]
  }
}