{
  "type": "Feature",
  "properties": {
    "name": "Gin Gin",
    "country": "AU",
    "subdivision": "04",
    "timezone": "Australia/Brisbane"
  },
  "geometry": {
    "type": "Point",
    "coordinates": [
      151.95808,
      -24.99363
    ]
  }
}