{
  "type": "Feature",
  "properties": {
    "name": "Glenview",
    "country": "AU",
    "subdivision": "04",
    "timezone": "Australia/Brisbane"
  },
  "geometry": {
    "type": "Point",
    "coordinates": [
      153.01667,
      -26.76667
    ]
  }
}