{
  "type": "Feature",
  "properties": {
    "name": "Graceville",
    "country": "AU",
    "subdivision": "04",
    "timezone": "Australia/Brisbane"
  },
  "geometry": {
    "type": "Point",
    "coordinates": [
      152.98222,
      -27.52201
    ]
  }
}