{
  "type": "Feature",
  "properties": {
    "name": "Helensvale",
    "country": "AU",
    "subdivision": "04",
    "timezone": "Australia/Brisbane"
  },
  "geometry": {
    "type": "Point",
    "coordinates": [
      153.33275,
      -27.91828
    ]
  }
}