{
  "type": "Feature",
  "properties": {
    "name": "Highfields",
    "country": "AU",
    "subdivision": "04",
    "timezone": "Australia/Brisbane"
  },
  "geometry": {
    "type": "Point",
    "coordinates": [
      151.95386,
      -27.46343
    ]
  }
}