{
  "type": "Feature",
  "properties": {
    "name": "Holland Park West",
    "country": "AU",
    "subdivision": "04",
    "timezone": "Australia/Brisbane"
  },
  "geometry": {
    "type": "Point",
    "coordinates": [
      153.06046,
      -27.52625
    ]
  }
}