{
  "type": "Feature",
  "properties": {
    "name": "Jamboree Heights",
    "country": "AU",
    "subdivision": "04",
    "timezone": "Australia/Brisbane"
  },
  "geometry": {
    "type": "Point",
    "coordinates": [
      152.93402,
      -27.55634
    ]
  }
}