{
  "type": "Feature",
  "properties": {
    "name": "Jensen",
    "country": "AU",
    "subdivision": "04",
    "timezone": "Australia/Brisbane"
  },
  "geometry": {
    "type": "Point",
    "coordinates": [
      146.65289,
      -19.2457
    ]
  }
}