{
  "type": "Feature",
  "properties": {
    "name": "Kensington Grove",
    "country": "AU",
    "subdivision": "04",
    "timezone": "Australia/Brisbane"
  },
  "geometry": {
    "type": "Point",
    "coordinates": [
      152.47205,
      -27.53278
    ]
  }
}