{
  "type": "Feature",
  "properties": {
    "name": "Kepnock",
    "country": "AU",
    "subdivision": "04",
    "timezone": "Australia/Brisbane"
  },
  "geometry": {
    "type": "Point",
    "coordinates": [
      152.37518,
      -24.87606
    ]
  }
}