{
  "type": "Feature",
  "properties": {
    "name": "Kuraby",
    "country": "AU",
    "subdivision": "04",
    "timezone": "Australia/Brisbane"
  },
  "geometry": {
    "type": "Point",
    "coordinates": [
      153.09367,
      -27.60683
    ]
  }
}