{
  "type": "Feature",
  "properties": {
    "name": "Laidley",
    "country": "AU",
    "subdivision": "04",
    "timezone": "Australia/Brisbane"
  },
  "geometry": {
    "type": "Point",
    "coordinates": [
      152.39285,
      -27.63278
    ]
  }
}