{
  "type": "Feature",
  "properties": {
    "name": "Little Mountain",
    "country": "AU",
    "subdivision": "04",
    "timezone": "Australia/Brisbane"
  },
  "geometry": {
    "type": "Point",
    "coordinates": [
      153.09218,
      -26.78436
    ]
  }
}