{
  "type": "Feature",
  "properties": {
    "name": "Logan Central",
    "country": "AU",
    "subdivision": "04",
    "timezone": "Australia/Brisbane"
  },
  "geometry": {
    "type": "Point",
    "coordinates": [
      153.10725,
      -27.64385
    ]
  }
}