{
  "type": "Feature",
  "properties": {
    "name": "Longreach",
    "country": "AU",
    "subdivision": "04",
    "timezone": "Australia/Brisbane"
  },
  "geometry": {
    "type": "Point",
    "coordinates": [
      144.24921,
      -23.44212
    ]
  }
}