{
  "type": "Feature",
  "properties": {
    "name": "Lower Beechmont",
    "country": "AU",
    "subdivision": "04",
    "timezone": "Australia/Brisbane"
  },
  "geometry": {
    "type": "Point",
    "coordinates": [
      153.24572,
      -28.04751
    ]
  }
}