{
  "type": "Feature",
  "properties": {
    "name": "Mackay",
    "country": "AU",
    "subdivision": "04",
    "timezone": "Australia/Brisbane"
  },
  "geometry": {
    "type": "Point",
    "coordinates": [
      149.16554,
      -21.15345
    ]
  }
}