{
  "type": "Feature",
  "properties": {
    "name": "Margate",
    "country": "AU",
    "subdivision": "04",
    "timezone": "Australia/Brisbane"
  },
  "geometry": {
    "type": "Point",
    "coordinates": [
      153.09809,
      -27.24761
    ]
  }
}