{
  "type": "Feature",
  "properties": {
    "name": "Maroochydore",
    "country": "AU",
    "subdivision": "04",
    "timezone": "Australia/Brisbane"
  },
  "geometry": {
    "type": "Point",
    "coordinates": [
      153.09953,
      -26.66008
    ]
  }
}