{
  "type": "Feature",
  "properties": {
    "name": "Maryborough",
    "country": "AU",
    "subdivision": "04",
    "timezone": "Australia/Brisbane"
  },
  "geometry": {
    "type": "Point",
    "coordinates": [
      152.70493,
      -25.54073
    ]
  }
}