{
  "type": "Feature",
  "properties": {
    "name": "Menzies",
    "country": "AU",
    "subdivision": "04",
    "timezone": "Australia/Brisbane"
  },
  "geometry": {
    "type": "Point",
    "coordinates": [
      139.49717,
      -20.71809
    ]
  }
}