{
  "type": "Feature",
  "properties": {
    "name": "Mermaid Waters",
    "country": "AU",
    "subdivision": "04",
    "timezone": "Australia/Brisbane"
  },
  "geometry": {
    "type": "Point",
    "coordinates": [
      153.43081,
      -28.04912
    ]
  }
}