{
  "type": "Feature",
  "properties": {
    "name": "Miami",
    "country": "AU",
    "subdivision": "04",
    "timezone": "Australia/Brisbane"
  },
  "geometry": {
    "type": "Point",
    "coordinates": [
      153.44158,
      -28.07173
    ]
  }
}