{
  "type": "Feature",
  "properties": {
    "name": "Minyama",
    "country": "AU",
    "subdivision": "04",
    "timezone": "Australia/Brisbane"
  },
  "geometry": {
    "type": "Point",
    "coordinates": [
      153.12353,
      -26.69573
    ]
  }
}