{
  "type": "Feature",
  "properties": {
    "name": "Mission River",
    "country": "AU",
    "subdivision": "04",
    "timezone": "Australia/Brisbane"
  },
  "geometry": {
    "type": "Point",
    "coordinates": [
      141.9576,
      -12.59509
    ]
  }
}