{
  "type": "Feature",
  "properties": {
    "name": "Mornington",
    "country": "AU",
    "subdivision": "04",
    "timezone": "Australia/Brisbane"
  },
  "geometry": {
    "type": "Point",
    "coordinates": [
      139.49586,
      -20.73415
    ]
  }
}