{
  "type": "Feature",
  "properties": {
    "name": "Mount Crosby",
    "country": "AU",
    "subdivision": "04",
    "timezone": "Australia/Brisbane"
  },
  "geometry": {
    "type": "Point",
    "coordinates": [
      152.80583,
      -27.53948
    ]
  }
}