{
  "type": "Feature",
  "properties": {
    "name": "Mount Sheridan",
    "country": "AU",
    "subdivision": "04",
    "timezone": "Australia/Brisbane"
  },
  "geometry": {
    "type": "Point",
    "coordinates": [
      145.73244,
      -16.98608
    ]
  }
}