{
  "type": "Feature",
  "properties": {
    "name": "Murray",
    "country": "AU",
    "subdivision": "04",
    "timezone": "Australia/Brisbane"
  },
  "geometry": {
    "type": "Point",
    "coordinates": [
      146.79494,
      -19.31803
    ]
  }
}