{
  "type": "Feature",
  "properties": {
    "name": "Newtown",
    "country": "AU",
    "subdivision": "04",
    "timezone": "Australia/Brisbane"
  },
  "geometry": {
    "type": "Point",
    "coordinates": [
      152.77675,
      -27.6163
    ]
  }
}