{
  "type": "Feature",
  "properties": {
    "name": "North Toowoomba",
    "country": "AU",
    "subdivision": "04",
    "timezone": "Australia/Brisbane"
  },
  "geometry": {
    "type": "Point",
    "coordinates": [
      151.96117,
      -27.54415
    ]
  }
}