{
  "type": "Feature",
  "properties": {
    "name": "Ormeau Hills",
    "country": "AU",
    "subdivision": "04",
    "timezone": "Australia/Brisbane"
  },
  "geometry": {
    "type": "Point",
    "coordinates": [
      153.2567,
      -27.79653
    ]
  }
}