{
  "type": "Feature",
  "properties": {
    "name": "Pacific Paradise",
    "country": "AU",
    "subdivision": "04",
    "timezone": "Australia/Brisbane"
  },
  "geometry": {
    "type": "Point",
    "coordinates": [
      153.07781,
      -26.61807
    ]
  }
}