{
  "type": "Feature",
  "properties": {
    "name": "Palm Beach",
    "country": "AU",
    "subdivision": "04",
    "timezone": "Australia/Brisbane"
  },
  "geometry": {
    "type": "Point",
    "coordinates": [
      153.46584,
      -28.11694
    ]
  }
}