{
  "type": "Feature",
  "properties": {
    "name": "Parkside",
    "country": "AU",
    "subdivision": "04",
    "timezone": "Australia/Brisbane"
  },
  "geometry": {
    "type": "Point",
    "coordinates": [
      139.48865,
      -20.7377
    ]
  }
}