{
  "type": "Feature",
  "properties": {
    "name": "Parkwood",
    "country": "AU",
    "subdivision": "04",
    "timezone": "Australia/Brisbane"
  },
  "geometry": {
    "type": "Point",
    "coordinates": [
      153.36304,
      -27.95461
    ]
  }
}