{
  "type": "Feature",
  "properties": {
    "name": "Pimlico",
    "country": "AU",
    "subdivision": "04",
    "timezone": "Australia/Brisbane"
  },
  "geometry": {
    "type": "Point",
    "coordinates": [
      146.78803,
      -19.28172
    ]
  }
}