{
  "type": "Feature",
  "properties": {
    "name": "Raceview",
    "country": "AU",
    "subdivision": "04",
    "timezone": "Australia/Brisbane"
  },
  "geometry": {
    "type": "Point",
    "coordinates": [
      152.77519,
      -27.63472
    ]
  }
}