{
  "type": "Feature",
  "properties": {
    "name": "Rangeville",
    "country": "AU",
    "subdivision": "04",
    "timezone": "Australia/Brisbane"
  },
  "geometry": {
    "type": "Point",
    "coordinates": [
      151.97997,
      -27.58318
    ]
  }
}