{
  "type": "Feature",
  "properties": {
    "name": "Regency Downs",
    "country": "AU",
    "subdivision": "04",
    "timezone": "Australia/Brisbane"
  },
  "geometry": {
    "type": "Point",
    "coordinates": [
      152.44049,
      -27.53359
    ]
  }
}