{
  "type": "Feature",
  "properties": {
    "name": "Russell Island",
    "country": "AU",
    "subdivision": "04",
    "timezone": "Australia/Brisbane"
  },
  "geometry": {
    "type": "Point",
    "coordinates": [
      153.38124,
      -27.64867
    ]
  }
}