{
  "type": "Feature",
  "properties": {
    "name": "Samford Valley",
    "country": "AU",
    "subdivision": "04",
    "timezone": "Australia/Brisbane"
  },
  "geometry": {
    "type": "Point",
    "coordinates": [
      152.86699,
      -27.3727
    ]
  }
}