{
  "type": "Feature",
  "properties": {
    "name": "Scarborough",
    "country": "AU",
    "subdivision": "04",
    "timezone": "Australia/Brisbane"
  },
  "geometry": {
    "type": "Point",
    "coordinates": [
      153.10939,
      -27.20118
    ]
  }
}