{
  "type": "Feature",
  "properties": {
    "name": "Slacks Creek",
    "country": "AU",
    "subdivision": "04",
    "timezone": "Australia/Brisbane"
  },
  "geometry": {
    "type": "Point",
    "coordinates": [
      153.15,
      -27.65
    ]
  }
}