{
  "type": "Feature",
  "properties": {
    "name": "Strathpine",
    "country": "AU",
    "subdivision": "04",
    "timezone": "Australia/Brisbane"
  },
  "geometry": {
    "type": "Point",
    "coordinates": [
      152.98977,
      -27.30414
    ]
  }
}