{
  "type": "Feature",
  "properties": {
    "name": "Stuart",
    "country": "AU",
    "subdivision": "04",
    "timezone": "Australia/Brisbane"
  },
  "geometry": {
    "type": "Point",
    "coordinates": [
      146.84378,
      -19.34702
    ]
  }
}