{
  "type": "Feature",
  "properties": {
    "name": "Sunrise Beach",
    "country": "AU",
    "subdivision": "04",
    "timezone": "Australia/Brisbane"
  },
  "geometry": {
    "type": "Point",
    "coordinates": [
      153.10305,
      -26.41646
    ]
  }
}