{
  "type": "Feature",
  "properties": {
    "name": "Sunset",
    "country": "AU",
    "subdivision": "04",
    "timezone": "Australia/Brisbane"
  },
  "geometry": {
    "type": "Point",
    "coordinates": [
      139.50824,
      -20.71026
    ]
  }
}