{
  "type": "Feature",
  "properties": {
    "name": "Tanawha",
    "country": "AU",
    "subdivision": "04",
    "timezone": "Australia/Brisbane"
  },
  "geometry": {
    "type": "Point",
    "coordinates": [
      153.03018,
      -26.71981
    ]
  }
}