{
  "type": "Feature",
  "properties": {
    "name": "Tara",
    "country": "AU",
    "subdivision": "04",
    "timezone": "Australia/Brisbane"
  },
  "geometry": {
    "type": "Point",
    "coordinates": [
      150.45676,
      -27.27613
    ]
  }
}