{
  "type": "Feature",
  "properties": {
    "name": "Taringa",
    "country": "AU",
    "subdivision": "04",
    "timezone": "Australia/Brisbane"
  },
  "geometry": {
    "type": "Point",
    "coordinates": [
      152.97861,
      -27.49061
    ]
  }
}