{
  "type": "Feature",
  "properties": {
    "name": "The Gap",
    "country": "AU",
    "subdivision": "04",
    "timezone": "Australia/Brisbane"
  },
  "geometry": {
    "type": "Point",
    "coordinates": [
      152.93861,
      -27.44187
    ]
  }
}