{
  "type": "Feature",
  "properties": {
    "name": "Thornlands",
    "country": "AU",
    "subdivision": "04",
    "timezone": "Australia/Brisbane"
  },
  "geometry": {
    "type": "Point",
    "coordinates": [
      153.26481,
      -27.55751
    ]
  }
}