{
  "type": "Feature",
  "properties": {
    "name": "Tin Can Bay",
    "country": "AU",
    "subdivision": "04",
    "timezone": "Australia/Brisbane"
  },
  "geometry": {
    "type": "Point",
    "coordinates": [
      153.0032,
      -25.91914
    ]
  }
}