{
  "type": "Feature",
  "properties": {
    "name": "Victoria Point",
    "country": "AU",
    "subdivision": "04",
    "timezone": "Australia/Brisbane"
  },
  "geometry": {
    "type": "Point",
    "coordinates": [
      153.31172,
      -27.58329
    ]
  }
}