{
  "type": "Feature",
  "properties": {
    "name": "Vincent",
    "country": "AU",
    "subdivision": "04",
    "timezone": "Australia/Brisbane"
  },
  "geometry": {
    "type": "Point",
    "coordinates": [
      146.76463,
      -19.28341
    ]
  }
}