{
  "type": "Feature",
  "properties": {
    "name": "Wandal",
    "country": "AU",
    "subdivision": "04",
    "timezone": "Australia/Brisbane"
  },
  "geometry": {
    "type": "Point",
    "coordinates": [
      150.49381,
      -23.36878
    ]
  }
}