{
  "type": "Feature",
  "properties": {
    "name": "Warner",
    "country": "AU",
    "subdivision": "04",
    "timezone": "Australia/Brisbane"
  },
  "geometry": {
    "type": "Point",
    "coordinates": [
      152.94981,
      -27.31222
    ]
  }
}