{
  "type": "Feature",
  "properties": {
    "name": "West Rockhampton",
    "country": "AU",
    "subdivision": "04",
    "timezone": "Australia/Brisbane"
  },
  "geometry": {
    "type": "Point",
    "coordinates": [
      150.48175,
      -23.37941
    ]
  }
}