{
  "type": "Feature",
  "properties": {
    "name": "Whitfield",
    "country": "AU",
    "subdivision": "04",
    "timezone": "Australia/Brisbane"
  },
  "geometry": {
    "type": "Point",
    "coordinates": [
      145.73335,
      -16.89508
    ]
  }
}