{
  "type": "Feature",
  "properties": {
    "name": "Wulkuraka",
    "country": "AU",
    "subdivision": "04",
    "timezone": "Australia/Brisbane"
  },
  "geometry": {
    "type": "Point",
    "coordinates": [
      152.72191,
      -27.61429
    ]
  }
}