{
  "type": "Feature",
  "properties": {
    "name": "Yungaburra",
    "country": "AU",
    "subdivision": "04",
    "timezone": "Australia/Brisbane"
  },
  "geometry": {
    "type": "Point",
    "coordinates": [
      145.58335,
      -17.27058
    ]
  }
}