{
  "type": "Feature",
  "properties": {
    "name": "Zillmere",
    "country": "AU",
    "subdivision": "04",
    "timezone": "Australia/Brisbane"
  },
  "geometry": {
    "type": "Point",
    "coordinates": [
      153.04453,
      -27.35591
    ]
  }
}