{
  "type": "Feature",
  "properties": {
    "name": "Balykshi",
    "country": "KZ",
    "subdivision": "06",
    "timezone": "Asia/Atyrau"
  },
  "geometry": {
    "type": "Point",
    "coordinates": [
      51.86667,
      47.06667
    ]
  }
}