{
  "type": "Feature",
  "properties": {
    "name": "Niihama",
    "country": "JP",
    "subdivision": "05",
    "timezone": "Asia/Tokyo"
  },
  "geometry": {
    "type": "Point",
    "coordinates": [
      133.30522,
      33.96047
    ]
  }
}