{
  "type": "Feature",
  "properties": {
    "name": "Sigulda",
    "country": "LV",
    "subdivision": "C7",
    "timezone": "Europe/Riga"
  },
  "geometry": {
    "type": "Point",
    "coordinates": [
      24.85953,
      57.15375
    ]
  }
}