{
  "type": "Feature",
  "properties": {
    "name": "Gwarzo",
    "country": "NG",
    "subdivision": "29",
    "timezone": "Africa/Lagos"
  },
  "geometry": {
    "type": "Point",
    "coordinates": [
      7.9337,
      11.91597
    ]
  }
}