{
  "type": "Feature",
  "properties": {
    "name": "Balvanera",
    "country": "AR",
    "subdivision": "07",
    "timezone": "America/Argentina/Buenos_Aires"
  },
  "geometry": {
    "type": "Point",
    "coordinates": [
      -58.39766,
      -34.61032
    ]
  }
}