{
  "type": "Feature",
  "properties": {
    "name": "Burträsk",
    "country": "SE",
    "subdivision": "23",
    "timezone": "Europe/Stockholm"
  },
  "geometry": {
    "type": "Point",
    "coordinates": [
      20.65,
      64.51667
    ]
  }
}