{
  "type": "Feature",
  "properties": {
    "name": "Täfteå",
    "country": "SE",
    "subdivision": "23",
    "timezone": "Europe/Stockholm"
  },
  "geometry": {
    "type": "Point",
    "coordinates": [
      20.47857,
      63.8397
    ]
  }
}