{
  "type": "Feature",
  "properties": {
    "name": "Consolación del Sur",
    "country": "CU",
    "subdivision": "01",
    "timezone": "America/Havana"
  },
  "geometry": {
    "type": "Point",
    "coordinates": [
      -83.51442,
      22.50419
    ]
  }
}