{
  "type": "Feature",
  "properties": {
    "name": "San Luis",
    "country": "CU",
    "subdivision": "01",
    "timezone": "America/Havana"
  },
  "geometry": {
    "type": "Point",
    "coordinates": [
      -83.75956,
      22.27898
    ]
  }
}