{
  "type": "Feature",
  "properties": {
    "name": "Viñales",
    "country": "CU",
    "subdivision": "01",
    "timezone": "America/Havana"
  },
  "geometry": {
    "type": "Point",
    "coordinates": [
      -83.70694,
      22.61892
    ]
  }
}