{
  "type": "Feature",
  "properties": {
    "name": "RaÄe",
    "country": "SI",
    "subdivision": "98",
    "timezone": "Europe/Ljubljana"
  },
  "geometry": {
    "type": "Point",
    "coordinates": [
      15.68139,
      46.45194
    ]
  }
}