{
  "type": "Feature",
  "properties": {
    "name": "Puerto Pilón",
    "country": "PA",
    "subdivision": "04",
    "timezone": "America/Panama"
  },
  "geometry": {
    "type": "Point",
    "coordinates": [
      -79.79333,
      9.36316
    ]
  }
}