{
  "type": "Feature",
  "properties": {
    "name": "Aillant-sur-Tholon",
    "country": "FR",
    "subdivision": "27",
    "timezone": "Europe/Paris"
  },
  "geometry": {
    "type": "Point",
    "coordinates": [
      3.35049,
      47.87426
    ]
  }
}