{
  "type": "Feature",
  "properties": {
    "name": "Ancy-le-Franc",
    "country": "FR",
    "subdivision": "27",
    "timezone": "Europe/Paris"
  },
  "geometry": {
    "type": "Point",
    "coordinates": [
      4.16361,
      47.77586
    ]
  }
}