{
  "type": "Feature",
  "properties": {
    "name": "Arc-sur-Tille",
    "country": "FR",
    "subdivision": "27",
    "timezone": "Europe/Paris"
  },
  "geometry": {
    "type": "Point",
    "coordinates": [
      5.18666,
      47.34349
    ]
  }
}