{
  "type": "Feature",
  "properties": {
    "name": "Bart",
    "country": "FR",
    "subdivision": "27",
    "timezone": "Europe/Paris"
  },
  "geometry": {
    "type": "Point",
    "coordinates": [
      6.7709,
      47.48861
    ]
  }
}