{
  "type": "Feature",
  "properties": {
    "name": "Besançon",
    "country": "FR",
    "subdivision": "27",
    "timezone": "Europe/Paris"
  },
  "geometry": {
    "type": "Point",
    "coordinates": [
      6.01815,
      47.24878
    ]
  }
}