{
  "type": "Feature",
  "properties": {
    "name": "Bourogne",
    "country": "FR",
    "subdivision": "27",
    "timezone": "Europe/Paris"
  },
  "geometry": {
    "type": "Point",
    "coordinates": [
      6.91654,
      47.56307
    ]
  }
}