{
  "type": "Feature",
  "properties": {
    "name": "Branges",
    "country": "FR",
    "subdivision": "27",
    "timezone": "Europe/Paris"
  },
  "geometry": {
    "type": "Point",
    "coordinates": [
      5.18465,
      46.64441
    ]
  }
}