{
  "type": "Feature",
  "properties": {
    "name": "Châtenoy-le-Royal",
    "country": "FR",
    "subdivision": "27",
    "timezone": "Europe/Paris"
  },
  "geometry": {
    "type": "Point",
    "coordinates": [
      4.8119,
      46.79797
    ]
  }
}