{
  "type": "Feature",
  "properties": {
    "name": "Chaussin",
    "country": "FR",
    "subdivision": "27",
    "timezone": "Europe/Paris"
  },
  "geometry": {
    "type": "Point",
    "coordinates": [
      5.40791,
      46.96612
    ]
  }
}