{
  "type": "Feature",
  "properties": {
    "name": "Crissey",
    "country": "FR",
    "subdivision": "27",
    "timezone": "Europe/Paris"
  },
  "geometry": {
    "type": "Point",
    "coordinates": [
      4.88185,
      46.81652
    ]
  }
}