{
  "type": "Feature",
  "properties": {
    "name": "Dampierre",
    "country": "FR",
    "subdivision": "27",
    "timezone": "Europe/Paris"
  },
  "geometry": {
    "type": "Point",
    "coordinates": [
      5.74167,
      47.15498
    ]
  }
}