{
  "type": "Feature",
  "properties": {
    "name": "Dijon",
    "country": "FR",
    "subdivision": "27",
    "timezone": "Europe/Paris"
  },
  "geometry": {
    "type": "Point",
    "coordinates": [
      5.01667,
      47.31667
    ]
  }
}