{
  "type": "Feature",
  "properties": {
    "name": "Frahier-et-Chatebier",
    "country": "FR",
    "subdivision": "27",
    "timezone": "Europe/Paris"
  },
  "geometry": {
    "type": "Point",
    "coordinates": [
      6.75,
      47.66667
    ]
  }
}