{
  "type": "Feature",
  "properties": {
    "name": "Frotey-lès-Vesoul",
    "country": "FR",
    "subdivision": "27",
    "timezone": "Europe/Paris"
  },
  "geometry": {
    "type": "Point",
    "coordinates": [
      6.18831,
      47.62078
    ]
  }
}