{
  "type": "Feature",
  "properties": {
    "name": "Joncherey",
    "country": "FR",
    "subdivision": "27",
    "timezone": "Europe/Paris"
  },
  "geometry": {
    "type": "Point",
    "coordinates": [
      7.00323,
      47.52895
    ]
  }
}