{
  "type": "Feature",
  "properties": {
    "name": "Ladoix-Serrigny",
    "country": "FR",
    "subdivision": "27",
    "timezone": "Europe/Paris"
  },
  "geometry": {
    "type": "Point",
    "coordinates": [
      4.88333,
      47.06667
    ]
  }
}