{
  "type": "Feature",
  "properties": {
    "name": "Le Russey",
    "country": "FR",
    "subdivision": "27",
    "timezone": "Europe/Paris"
  },
  "geometry": {
    "type": "Point",
    "coordinates": [
      6.72912,
      47.16055
    ]
  }
}