{
  "type": "Feature",
  "properties": {
    "name": "Lepuix",
    "country": "FR",
    "subdivision": "27",
    "timezone": "Europe/Paris"
  },
  "geometry": {
    "type": "Point",
    "coordinates": [
      6.81434,
      47.7605
    ]
  }
}