{
  "type": "Feature",
  "properties": {
    "name": "Magny-Cours",
    "country": "FR",
    "subdivision": "27",
    "timezone": "Europe/Paris"
  },
  "geometry": {
    "type": "Point",
    "coordinates": [
      3.15,
      46.88333
    ]
  }
}