{
  "type": "Feature",
  "properties": {
    "name": "Magny-Vernois",
    "country": "FR",
    "subdivision": "27",
    "timezone": "Europe/Paris"
  },
  "geometry": {
    "type": "Point",
    "coordinates": [
      6.47545,
      47.66997
    ]
  }
}