{
  "type": "Feature",
  "properties": {
    "name": "Maillot",
    "country": "FR",
    "subdivision": "27",
    "timezone": "Europe/Paris"
  },
  "geometry": {
    "type": "Point",
    "coordinates": [
      3.30784,
      48.17557
    ]
  }
}