{
  "type": "Feature",
  "properties": {
    "name": "Matour",
    "country": "FR",
    "subdivision": "27",
    "timezone": "Europe/Paris"
  },
  "geometry": {
    "type": "Point",
    "coordinates": [
      4.48178,
      46.30654
    ]
  }
}