{
  "type": "Feature",
  "properties": {
    "name": "Mélisey",
    "country": "FR",
    "subdivision": "27",
    "timezone": "Europe/Paris"
  },
  "geometry": {
    "type": "Point",
    "coordinates": [
      6.58014,
      47.75229
    ]
  }
}