{
  "type": "Feature",
  "properties": {
    "name": "Méziré",
    "country": "FR",
    "subdivision": "27",
    "timezone": "Europe/Paris"
  },
  "geometry": {
    "type": "Point",
    "coordinates": [
      6.92072,
      47.53336
    ]
  }
}