{
  "type": "Feature",
  "properties": {
    "name": "Migennes",
    "country": "FR",
    "subdivision": "27",
    "timezone": "Europe/Paris"
  },
  "geometry": {
    "type": "Point",
    "coordinates": [
      3.51787,
      47.96548
    ]
  }
}