{
  "type": "Feature",
  "properties": {
    "name": "Miserey-Salines",
    "country": "FR",
    "subdivision": "27",
    "timezone": "Europe/Paris"
  },
  "geometry": {
    "type": "Point",
    "coordinates": [
      5.97387,
      47.28638
    ]
  }
}