{
  "type": "Feature",
  "properties": {
    "name": "Montferrand-le-Château",
    "country": "FR",
    "subdivision": "27",
    "timezone": "Europe/Paris"
  },
  "geometry": {
    "type": "Point",
    "coordinates": [
      5.91534,
      47.17536
    ]
  }
}