{
  "type": "Feature",
  "properties": {
    "name": "Morbier",
    "country": "FR",
    "subdivision": "27",
    "timezone": "Europe/Paris"
  },
  "geometry": {
    "type": "Point",
    "coordinates": [
      6.01532,
      46.53693
    ]
  }
}