{
  "type": "Feature",
  "properties": {
    "name": "Moulins-Engilbert",
    "country": "FR",
    "subdivision": "27",
    "timezone": "Europe/Paris"
  },
  "geometry": {
    "type": "Point",
    "coordinates": [
      3.81084,
      46.98821
    ]
  }
}