{
  "type": "Feature",
  "properties": {
    "name": "Neuvy-sur-Loire",
    "country": "FR",
    "subdivision": "27",
    "timezone": "Europe/Paris"
  },
  "geometry": {
    "type": "Point",
    "coordinates": [
      2.88333,
      47.52323
    ]
  }
}