{
  "type": "Feature",
  "properties": {
    "name": "Nevers",
    "country": "FR",
    "subdivision": "27",
    "timezone": "Europe/Paris"
  },
  "geometry": {
    "type": "Point",
    "coordinates": [
      3.159,
      46.98956
    ]
  }
}