{
  "type": "Feature",
  "properties": {
    "name": "Palinges",
    "country": "FR",
    "subdivision": "27",
    "timezone": "Europe/Paris"
  },
  "geometry": {
    "type": "Point",
    "coordinates": [
      4.21964,
      46.55357
    ]
  }
}