{
  "type": "Feature",
  "properties": {
    "name": "Perrigny-lès-Dijon",
    "country": "FR",
    "subdivision": "27",
    "timezone": "Europe/Paris"
  },
  "geometry": {
    "type": "Point",
    "coordinates": [
      5.00628,
      47.26648
    ]
  }
}