{
  "type": "Feature",
  "properties": {
    "name": "Plombières-lès-Dijon",
    "country": "FR",
    "subdivision": "27",
    "timezone": "Europe/Paris"
  },
  "geometry": {
    "type": "Point",
    "coordinates": [
      4.96667,
      47.33333
    ]
  }
}