{
  "type": "Feature",
  "properties": {
    "name": "Prémery",
    "country": "FR",
    "subdivision": "27",
    "timezone": "Europe/Paris"
  },
  "geometry": {
    "type": "Point",
    "coordinates": [
      3.32743,
      47.16952
    ]
  }
}