{
  "type": "Feature",
  "properties": {
    "name": "Romenay",
    "country": "FR",
    "subdivision": "27",
    "timezone": "Europe/Paris"
  },
  "geometry": {
    "type": "Point",
    "coordinates": [
      5.06904,
      46.50208
    ]
  }
}