{
  "type": "Feature",
  "properties": {
    "name": "Roye",
    "country": "FR",
    "subdivision": "27",
    "timezone": "Europe/Paris"
  },
  "geometry": {
    "type": "Point",
    "coordinates": [
      6.54139,
      47.66995
    ]
  }
}