{
  "type": "Feature",
  "properties": {
    "name": "Saint-Sernin-du-Bois",
    "country": "FR",
    "subdivision": "27",
    "timezone": "Europe/Paris"
  },
  "geometry": {
    "type": "Point",
    "coordinates": [
      4.43271,
      46.84074
    ]
  }
}