{
  "type": "Feature",
  "properties": {
    "name": "Saint-Éloi",
    "country": "FR",
    "subdivision": "27",
    "timezone": "Europe/Paris"
  },
  "geometry": {
    "type": "Point",
    "coordinates": [
      3.22228,
      46.97342
    ]
  }
}