{
  "type": "Feature",
  "properties": {
    "name": "Saint-Jean-de-Losne",
    "country": "FR",
    "subdivision": "27",
    "timezone": "Europe/Paris"
  },
  "geometry": {
    "type": "Point",
    "coordinates": [
      5.26556,
      47.10247
    ]
  }
}