{
  "type": "Feature",
  "properties": {
    "name": "Saint-Julien-du-Sault",
    "country": "FR",
    "subdivision": "27",
    "timezone": "Europe/Paris"
  },
  "geometry": {
    "type": "Point",
    "coordinates": [
      3.29556,
      48.03188
    ]
  }
}