{
  "type": "Feature",
  "properties": {
    "name": "Sancé",
    "country": "FR",
    "subdivision": "27",
    "timezone": "Europe/Paris"
  },
  "geometry": {
    "type": "Point",
    "coordinates": [
      4.83049,
      46.33926
    ]
  }
}