{
  "type": "Feature",
  "properties": {
    "name": "Sanvignes-les-Mines",
    "country": "FR",
    "subdivision": "27",
    "timezone": "Europe/Paris"
  },
  "geometry": {
    "type": "Point",
    "coordinates": [
      4.29188,
      46.66444
    ]
  }
}