{
  "type": "Feature",
  "properties": {
    "name": "Savigny-lès-Beaune",
    "country": "FR",
    "subdivision": "27",
    "timezone": "Europe/Paris"
  },
  "geometry": {
    "type": "Point",
    "coordinates": [
      4.81821,
      47.06357
    ]
  }
}