{
  "type": "Feature",
  "properties": {
    "name": "Seignelay",
    "country": "FR",
    "subdivision": "27",
    "timezone": "Europe/Paris"
  },
  "geometry": {
    "type": "Point",
    "coordinates": [
      3.60136,
      47.90542
    ]
  }
}