{
  "type": "Feature",
  "properties": {
    "name": "Selongey",
    "country": "FR",
    "subdivision": "27",
    "timezone": "Europe/Paris"
  },
  "geometry": {
    "type": "Point",
    "coordinates": [
      5.18483,
      47.58846
    ]
  }
}