{
  "type": "Feature",
  "properties": {
    "name": "Semur-en-Auxois",
    "country": "FR",
    "subdivision": "27",
    "timezone": "Europe/Paris"
  },
  "geometry": {
    "type": "Point",
    "coordinates": [
      4.33333,
      47.48333
    ]
  }
}