{
  "type": "Feature",
  "properties": {
    "name": "Sergines",
    "country": "FR",
    "subdivision": "27",
    "timezone": "Europe/Paris"
  },
  "geometry": {
    "type": "Point",
    "coordinates": [
      3.26213,
      48.34203
    ]
  }
}