{
  "type": "Feature",
  "properties": {
    "name": "Simandre",
    "country": "FR",
    "subdivision": "27",
    "timezone": "Europe/Paris"
  },
  "geometry": {
    "type": "Point",
    "coordinates": [
      4.98777,
      46.62364
    ]
  }
}