{
  "type": "Feature",
  "properties": {
    "name": "Varennes-Vauzelles",
    "country": "FR",
    "subdivision": "27",
    "timezone": "Europe/Paris"
  },
  "geometry": {
    "type": "Point",
    "coordinates": [
      3.14037,
      47.01678
    ]
  }
}