{
  "type": "Feature",
  "properties": {
    "name": "Vercel-Villedieu-le-Camp",
    "country": "FR",
    "subdivision": "27",
    "timezone": "Europe/Paris"
  },
  "geometry": {
    "type": "Point",
    "coordinates": [
      6.40082,
      47.18318
    ]
  }
}