{
  "type": "Feature",
  "properties": {
    "name": "Albertstadt",
    "country": "DE",
    "subdivision": "13",
    "timezone": "Europe/Berlin"
  },
  "geometry": {
    "type": "Point",
    "coordinates": [
      13.76667,
      51.08333
    ]
  }
}