{
  "type": "Feature",
  "properties": {
    "name": "Bernsbach",
    "country": "DE",
    "subdivision": "13",
    "timezone": "Europe/Berlin"
  },
  "geometry": {
    "type": "Point",
    "coordinates": [
      12.76751,
      50.57624
    ]
  }
}