{
  "type": "Feature",
  "properties": {
    "name": "Bernstadt",
    "country": "DE",
    "subdivision": "13",
    "timezone": "Europe/Berlin"
  },
  "geometry": {
    "type": "Point",
    "coordinates": [
      14.82784,
      51.04736
    ]
  }
}