{
  "type": "Feature",
  "properties": {
    "name": "Berthelsdorf",
    "country": "DE",
    "subdivision": "13",
    "timezone": "Europe/Berlin"
  },
  "geometry": {
    "type": "Point",
    "coordinates": [
      14.22197,
      51.04679
    ]
  }
}