{
  "type": "Feature",
  "properties": {
    "name": "Boxberg",
    "country": "DE",
    "subdivision": "13",
    "timezone": "Europe/Berlin"
  },
  "geometry": {
    "type": "Point",
    "coordinates": [
      14.57598,
      51.40373
    ]
  }
}