{
  "type": "Feature",
  "properties": {
    "name": "Burgstädt",
    "country": "DE",
    "subdivision": "13",
    "timezone": "Europe/Berlin"
  },
  "geometry": {
    "type": "Point",
    "coordinates": [
      12.806,
      50.91333
    ]
  }
}