{
  "type": "Feature",
  "properties": {
    "name": "Crimmitschau",
    "country": "DE",
    "subdivision": "13",
    "timezone": "Europe/Berlin"
  },
  "geometry": {
    "type": "Point",
    "coordinates": [
      12.39045,
      50.81644
    ]
  }
}