{
  "type": "Feature",
  "properties": {
    "name": "Dippoldiswalde",
    "country": "DE",
    "subdivision": "13",
    "timezone": "Europe/Berlin"
  },
  "geometry": {
    "type": "Point",
    "coordinates": [
      13.66905,
      50.89621
    ]
  }
}