{
  "type": "Feature",
  "properties": {
    "name": "Doberschütz",
    "country": "DE",
    "subdivision": "13",
    "timezone": "Europe/Berlin"
  },
  "geometry": {
    "type": "Point",
    "coordinates": [
      12.74792,
      51.4987
    ]
  }
}