{
  "type": "Feature",
  "properties": {
    "name": "Frankenthal",
    "country": "DE",
    "subdivision": "13",
    "timezone": "Europe/Berlin"
  },
  "geometry": {
    "type": "Point",
    "coordinates": [
      14.10893,
      51.13129
    ]
  }
}