{
  "type": "Feature",
  "properties": {
    "name": "Frankenberg",
    "country": "DE",
    "subdivision": "13",
    "timezone": "Europe/Berlin"
  },
  "geometry": {
    "type": "Point",
    "coordinates": [
      13.04011,
      50.91297
    ]
  }
}