{
  "type": "Feature",
  "properties": {
    "name": "Freital",
    "country": "DE",
    "subdivision": "13",
    "timezone": "Europe/Berlin"
  },
  "geometry": {
    "type": "Point",
    "coordinates": [
      13.6488,
      51.00166
    ]
  }
}