{
  "type": "Feature",
  "properties": {
    "name": "Geising",
    "country": "DE",
    "subdivision": "13",
    "timezone": "Europe/Berlin"
  },
  "geometry": {
    "type": "Point",
    "coordinates": [
      13.79278,
      50.75742
    ]
  }
}