{
  "type": "Feature",
  "properties": {
    "name": "Hauswalde",
    "country": "DE",
    "subdivision": "13",
    "timezone": "Europe/Berlin"
  },
  "geometry": {
    "type": "Point",
    "coordinates": [
      14.0863,
      51.15212
    ]
  }
}