{
  "type": "Feature",
  "properties": {
    "name": "Herrnhut",
    "country": "DE",
    "subdivision": "13",
    "timezone": "Europe/Berlin"
  },
  "geometry": {
    "type": "Point",
    "coordinates": [
      14.74381,
      51.01624
    ]
  }
}