{
  "type": "Feature",
  "properties": {
    "name": "Hirschfeld",
    "country": "DE",
    "subdivision": "13",
    "timezone": "Europe/Berlin"
  },
  "geometry": {
    "type": "Point",
    "coordinates": [
      12.45722,
      50.62453
    ]
  }
}