{
  "type": "Feature",
  "properties": {
    "name": "Höckendorf",
    "country": "DE",
    "subdivision": "13",
    "timezone": "Europe/Berlin"
  },
  "geometry": {
    "type": "Point",
    "coordinates": [
      13.90935,
      51.22423
    ]
  }
}