{
  "type": "Feature",
  "properties": {
    "name": "Horka",
    "country": "DE",
    "subdivision": "13",
    "timezone": "Europe/Berlin"
  },
  "geometry": {
    "type": "Point",
    "coordinates": [
      14.25523,
      51.26342
    ]
  }
}