{
  "type": "Feature",
  "properties": {
    "name": "Jahnsdorf",
    "country": "DE",
    "subdivision": "13",
    "timezone": "Europe/Berlin"
  },
  "geometry": {
    "type": "Point",
    "coordinates": [
      12.85414,
      50.74509
    ]
  }
}