{
  "type": "Feature",
  "properties": {
    "name": "Kirschau",
    "country": "DE",
    "subdivision": "13",
    "timezone": "Europe/Berlin"
  },
  "geometry": {
    "type": "Point",
    "coordinates": [
      14.4284,
      51.09317
    ]
  }
}