{
  "type": "Feature",
  "properties": {
    "name": "Königshain",
    "country": "DE",
    "subdivision": "13",
    "timezone": "Europe/Berlin"
  },
  "geometry": {
    "type": "Point",
    "coordinates": [
      14.86667,
      51.18333
    ]
  }
}