{
  "type": "Feature",
  "properties": {
    "name": "Krauschwitz",
    "country": "DE",
    "subdivision": "13",
    "timezone": "Europe/Berlin"
  },
  "geometry": {
    "type": "Point",
    "coordinates": [
      14.71211,
      51.52153
    ]
  }
}