{
  "type": "Feature",
  "properties": {
    "name": "Kurort Jonsdorf",
    "country": "DE",
    "subdivision": "13",
    "timezone": "Europe/Berlin"
  },
  "geometry": {
    "type": "Point",
    "coordinates": [
      14.70922,
      50.85751
    ]
  }
}