{
  "type": "Feature",
  "properties": {
    "name": "Laußig",
    "country": "DE",
    "subdivision": "13",
    "timezone": "Europe/Berlin"
  },
  "geometry": {
    "type": "Point",
    "coordinates": [
      12.6293,
      51.54676
    ]
  }
}