{
  "type": "Feature",
  "properties": {
    "name": "Leisnig",
    "country": "DE",
    "subdivision": "13",
    "timezone": "Europe/Berlin"
  },
  "geometry": {
    "type": "Point",
    "coordinates": [
      12.9279,
      51.15743
    ]
  }
}