{
  "type": "Feature",
  "properties": {
    "name": "Leubnitz",
    "country": "DE",
    "subdivision": "13",
    "timezone": "Europe/Berlin"
  },
  "geometry": {
    "type": "Point",
    "coordinates": [
      12.3566,
      50.72313
    ]
  }
}