{
  "type": "Feature",
  "properties": {
    "name": "Lugau",
    "country": "DE",
    "subdivision": "13",
    "timezone": "Europe/Berlin"
  },
  "geometry": {
    "type": "Point",
    "coordinates": [
      12.74861,
      50.73843
    ]
  }
}