{
  "type": "Feature",
  "properties": {
    "name": "Malschwitz",
    "country": "DE",
    "subdivision": "13",
    "timezone": "Europe/Berlin"
  },
  "geometry": {
    "type": "Point",
    "coordinates": [
      14.52163,
      51.23759
    ]
  }
}