{
  "type": "Feature",
  "properties": {
    "name": "Markersbach",
    "country": "DE",
    "subdivision": "13",
    "timezone": "Europe/Berlin"
  },
  "geometry": {
    "type": "Point",
    "coordinates": [
      12.86149,
      50.53545
    ]
  }
}