{
  "type": "Feature",
  "properties": {
    "name": "Mittelherwigsdorf",
    "country": "DE",
    "subdivision": "13",
    "timezone": "Europe/Berlin"
  },
  "geometry": {
    "type": "Point",
    "coordinates": [
      14.76667,
      50.91667
    ]
  }
}