{
  "type": "Feature",
  "properties": {
    "name": "Mochau",
    "country": "DE",
    "subdivision": "13",
    "timezone": "Europe/Berlin"
  },
  "geometry": {
    "type": "Point",
    "coordinates": [
      13.18333,
      51.13333
    ]
  }
}