{
  "type": "Feature",
  "properties": {
    "name": "Naunhof",
    "country": "DE",
    "subdivision": "13",
    "timezone": "Europe/Berlin"
  },
  "geometry": {
    "type": "Point",
    "coordinates": [
      12.58827,
      51.2777
    ]
  }
}