{
  "type": "Feature",
  "properties": {
    "name": "Nebelschütz",
    "country": "DE",
    "subdivision": "13",
    "timezone": "Europe/Berlin"
  },
  "geometry": {
    "type": "Point",
    "coordinates": [
      14.15849,
      51.26227
    ]
  }
}