{
  "type": "Feature",
  "properties": {
    "name": "Neschwitz",
    "country": "DE",
    "subdivision": "13",
    "timezone": "Europe/Berlin"
  },
  "geometry": {
    "type": "Point",
    "coordinates": [
      14.329,
      51.27056
    ]
  }
}