{
  "type": "Feature",
  "properties": {
    "name": "Neusalza-Spremberg",
    "country": "DE",
    "subdivision": "13",
    "timezone": "Europe/Berlin"
  },
  "geometry": {
    "type": "Point",
    "coordinates": [
      14.5356,
      51.03945
    ]
  }
}