{
  "type": "Feature",
  "properties": {
    "name": "Niederwiesa",
    "country": "DE",
    "subdivision": "13",
    "timezone": "Europe/Berlin"
  },
  "geometry": {
    "type": "Point",
    "coordinates": [
      13.01667,
      50.86667
    ]
  }
}