{
  "type": "Feature",
  "properties": {
    "name": "Niederau",
    "country": "DE",
    "subdivision": "13",
    "timezone": "Europe/Berlin"
  },
  "geometry": {
    "type": "Point",
    "coordinates": [
      13.54563,
      51.1773
    ]
  }
}