{
  "type": "Feature",
  "properties": {
    "name": "Oschatz",
    "country": "DE",
    "subdivision": "13",
    "timezone": "Europe/Berlin"
  },
  "geometry": {
    "type": "Point",
    "coordinates": [
      13.10984,
      51.30001
    ]
  }
}