{
  "type": "Feature",
  "properties": {
    "name": "Pfaffroda",
    "country": "DE",
    "subdivision": "13",
    "timezone": "Europe/Berlin"
  },
  "geometry": {
    "type": "Point",
    "coordinates": [
      12.51497,
      50.86134
    ]
  }
}