{
  "type": "Feature",
  "properties": {
    "name": "Radebeul",
    "country": "DE",
    "subdivision": "13",
    "timezone": "Europe/Berlin"
  },
  "geometry": {
    "type": "Point",
    "coordinates": [
      13.66047,
      51.10654
    ]
  }
}