{
  "type": "Feature",
  "properties": {
    "name": "Radibor",
    "country": "DE",
    "subdivision": "13",
    "timezone": "Europe/Berlin"
  },
  "geometry": {
    "type": "Point",
    "coordinates": [
      14.39842,
      51.24481
    ]
  }
}