{
  "type": "Feature",
  "properties": {
    "name": "Rammenau",
    "country": "DE",
    "subdivision": "13",
    "timezone": "Europe/Berlin"
  },
  "geometry": {
    "type": "Point",
    "coordinates": [
      14.13333,
      51.15
    ]
  }
}