{
  "type": "Feature",
  "properties": {
    "name": "Regis-Breitingen",
    "country": "DE",
    "subdivision": "13",
    "timezone": "Europe/Berlin"
  },
  "geometry": {
    "type": "Point",
    "coordinates": [
      12.43841,
      51.08883
    ]
  }
}