{
  "type": "Feature",
  "properties": {
    "name": "Schleife",
    "country": "DE",
    "subdivision": "13",
    "timezone": "Europe/Berlin"
  },
  "geometry": {
    "type": "Point",
    "coordinates": [
      14.53333,
      51.53333
    ]
  }
}