{
  "type": "Feature",
  "properties": {
    "name": "Taucha",
    "country": "DE",
    "subdivision": "13",
    "timezone": "Europe/Berlin"
  },
  "geometry": {
    "type": "Point",
    "coordinates": [
      12.48333,
      51.38333
    ]
  }
}