{
  "type": "Feature",
  "properties": {
    "name": "Thallwitz",
    "country": "DE",
    "subdivision": "13",
    "timezone": "Europe/Berlin"
  },
  "geometry": {
    "type": "Point",
    "coordinates": [
      12.68333,
      51.43333
    ]
  }
}