{
  "type": "Feature",
  "properties": {
    "name": "Torgau",
    "country": "DE",
    "subdivision": "13",
    "timezone": "Europe/Berlin"
  },
  "geometry": {
    "type": "Point",
    "coordinates": [
      12.99617,
      51.56016
    ]
  }
}