{
  "type": "Feature",
  "properties": {
    "name": "Uhyst",
    "country": "DE",
    "subdivision": "13",
    "timezone": "Europe/Berlin"
  },
  "geometry": {
    "type": "Point",
    "coordinates": [
      14.506,
      51.36469
    ]
  }
}