{
  "type": "Feature",
  "properties": {
    "name": "Venusberg",
    "country": "DE",
    "subdivision": "13",
    "timezone": "Europe/Berlin"
  },
  "geometry": {
    "type": "Point",
    "coordinates": [
      13.01854,
      50.69918
    ]
  }
}