{
  "type": "Feature",
  "properties": {
    "name": "Wachau",
    "country": "DE",
    "subdivision": "13",
    "timezone": "Europe/Berlin"
  },
  "geometry": {
    "type": "Point",
    "coordinates": [
      13.90651,
      51.16172
    ]
  }
}