{
  "type": "Feature",
  "properties": {
    "name": "Waldheim",
    "country": "DE",
    "subdivision": "13",
    "timezone": "Europe/Berlin"
  },
  "geometry": {
    "type": "Point",
    "coordinates": [
      13.02004,
      51.07282
    ]
  }
}