{
  "type": "Feature",
  "properties": {
    "name": "Weißkeißel",
    "country": "DE",
    "subdivision": "13",
    "timezone": "Europe/Berlin"
  },
  "geometry": {
    "type": "Point",
    "coordinates": [
      14.71515,
      51.49405
    ]
  }
}