{
  "type": "Feature",
  "properties": {
    "name": "Werda",
    "country": "DE",
    "subdivision": "13",
    "timezone": "Europe/Berlin"
  },
  "geometry": {
    "type": "Point",
    "coordinates": [
      12.30473,
      50.43811
    ]
  }
}