{
  "type": "Feature",
  "properties": {
    "name": "Wiednitz",
    "country": "DE",
    "subdivision": "13",
    "timezone": "Europe/Berlin"
  },
  "geometry": {
    "type": "Point",
    "coordinates": [
      14.02683,
      51.38608
    ]
  }
}