{
  "type": "Feature",
  "properties": {
    "name": "Wiesa",
    "country": "DE",
    "subdivision": "13",
    "timezone": "Europe/Berlin"
  },
  "geometry": {
    "type": "Point",
    "coordinates": [
      13.01377,
      50.61114
    ]
  }
}