{
  "type": "Feature",
  "properties": {
    "name": "Wilkau-Haßlau",
    "country": "DE",
    "subdivision": "13",
    "timezone": "Europe/Berlin"
  },
  "geometry": {
    "type": "Point",
    "coordinates": [
      12.51482,
      50.67504
    ]
  }
}