{
  "type": "Feature",
  "properties": {
    "name": "Wilsdruff",
    "country": "DE",
    "subdivision": "13",
    "timezone": "Europe/Berlin"
  },
  "geometry": {
    "type": "Point",
    "coordinates": [
      13.53657,
      51.05199
    ]
  }
}