{
  "type": "Feature",
  "properties": {
    "name": "Wittichenau",
    "country": "DE",
    "subdivision": "13",
    "timezone": "Europe/Berlin"
  },
  "geometry": {
    "type": "Point",
    "coordinates": [
      14.24403,
      51.38496
    ]
  }
}