{
  "type": "Feature",
  "properties": {
    "name": "Zwickau",
    "country": "DE",
    "subdivision": "13",
    "timezone": "Europe/Berlin"
  },
  "geometry": {
    "type": "Point",
    "coordinates": [
      12.48839,
      50.72724
    ]
  }
}