{
  "type": "Feature",
  "properties": {
    "name": "Zwota",
    "country": "DE",
    "subdivision": "13",
    "timezone": "Europe/Berlin"
  },
  "geometry": {
    "type": "Point",
    "coordinates": [
      12.42241,
      50.35103
    ]
  }
}