{
  "type": "Feature",
  "properties": {
    "name": "Shimsk",
    "country": "RU",
    "subdivision": "52",
    "timezone": "Europe/Moscow"
  },
  "geometry": {
    "type": "Point",
    "coordinates": [
      30.71269,
      58.21201
    ]
  }
}