{
  "type": "Feature",
  "properties": {
    "name": "Kanel",
    "country": "SN",
    "subdivision": "15",
    "timezone": "Africa/Dakar"
  },
  "geometry": {
    "type": "Point",
    "coordinates": [
      -13.17627,
      15.4916
    ]
  }
}