{
  "type": "Feature",
  "properties": {
    "name": "Ouro Sogui",
    "country": "SN",
    "subdivision": "15",
    "timezone": "Africa/Dakar"
  },
  "geometry": {
    "type": "Point",
    "coordinates": [
      -13.3223,
      15.60588
    ]
  }
}