{
  "type": "Feature",
  "properties": {
    "name": "Sémé",
    "country": "SN",
    "subdivision": "15",
    "timezone": "Africa/Dakar"
  },
  "geometry": {
    "type": "Point",
    "coordinates": [
      -12.94482,
      15.19422
    ]
  }
}