{
  "type": "Feature",
  "properties": {
    "name": "Khāliş",
    "country": "IQ",
    "subdivision": "10",
    "timezone": "Asia/Baghdad"
  },
  "geometry": {
    "type": "Point",
    "coordinates": [
      44.53343,
      33.80809
    ]
  }
}