{
  "type": "Feature",
  "properties": {
    "name": "Mandalī",
    "country": "IQ",
    "subdivision": "10",
    "timezone": "Asia/Baghdad"
  },
  "geometry": {
    "type": "Point",
    "coordinates": [
      45.55503,
      33.7481
    ]
  }
}