{
  "type": "Feature",
  "properties": {
    "name": "Jinhua",
    "country": "CN",
    "subdivision": "02",
    "timezone": "Asia/Shanghai"
  },
  "geometry": {
    "type": "Point",
    "coordinates": [
      119.64421,
      29.10678
    ]
  }
}