{
  "type": "Feature",
  "properties": {
    "name": "Jinxiang",
    "country": "CN",
    "subdivision": "02",
    "timezone": "Asia/Shanghai"
  },
  "geometry": {
    "type": "Point",
    "coordinates": [
      120.60625,
      27.43265
    ]
  }
}