{
  "type": "Feature",
  "properties": {
    "name": "Lanxi",
    "country": "CN",
    "subdivision": "02",
    "timezone": "Asia/Shanghai"
  },
  "geometry": {
    "type": "Point",
    "coordinates": [
      119.47156,
      29.21588
    ]
  }
}