{
  "type": "Feature",
  "properties": {
    "name": "Shaoxing",
    "country": "CN",
    "subdivision": "02",
    "timezone": "Asia/Shanghai"
  },
  "geometry": {
    "type": "Point",
    "coordinates": [
      120.57864,
      30.00237
    ]
  }
}