{
  "type": "Feature",
  "properties": {
    "name": "Yiwu",
    "country": "CN",
    "subdivision": "02",
    "timezone": "Asia/Shanghai"
  },
  "geometry": {
    "type": "Point",
    "coordinates": [
      120.07676,
      29.31506
    ]
  }
}