{
  "type": "Feature",
  "properties": {
    "name": "Kristinestad",
    "country": "FI",
    "subdivision": "15",
    "timezone": "Europe/Helsinki"
  },
  "geometry": {
    "type": "Point",
    "coordinates": [
      21.37596,
      62.27429
    ]
  }
}