{
  "type": "Feature",
  "properties": {
    "name": "Oravais",
    "country": "FI",
    "subdivision": "15",
    "timezone": "Europe/Helsinki"
  },
  "geometry": {
    "type": "Point",
    "coordinates": [
      22.37821,
      63.30135
    ]
  }
}