{
  "type": "Feature",
  "properties": {
    "name": "Ytteresse",
    "country": "FI",
    "subdivision": "15",
    "timezone": "Europe/Helsinki"
  },
  "geometry": {
    "type": "Point",
    "coordinates": [
      22.99456,
      63.62209
    ]
  }
}