{
  "type": "Feature",
  "properties": {
    "name": "Promyshlennyy",
    "country": "RU",
    "subdivision": "34",
    "timezone": "Europe/Moscow"
  },
  "geometry": {
    "type": "Point",
    "coordinates": [
      63.91667,
      67.58333
    ]
  }
}