{
  "type": "Feature",
  "properties": {
    "name": "Shudayag",
    "country": "RU",
    "subdivision": "34",
    "timezone": "Europe/Moscow"
  },
  "geometry": {
    "type": "Point",
    "coordinates": [
      53.60582,
      63.52665
    ]
  }
}