{
  "type": "Feature",
  "properties": {
    "name": "Sindor",
    "country": "RU",
    "subdivision": "34",
    "timezone": "Europe/Moscow"
  },
  "geometry": {
    "type": "Point",
    "coordinates": [
      51.89051,
      62.86286
    ]
  }
}