{
  "type": "Feature",
  "properties": {
    "name": "Tsementnozavodskiy",
    "country": "RU",
    "subdivision": "34",
    "timezone": "Europe/Moscow"
  },
  "geometry": {
    "type": "Point",
    "coordinates": [
      64.08965,
      67.62834
    ]
  }
}