{
  "type": "Feature",
  "properties": {
    "name": "Ukhta",
    "country": "RU",
    "subdivision": "34",
    "timezone": "Europe/Moscow"
  },
  "geometry": {
    "type": "Point",
    "coordinates": [
      53.68348,
      63.56705
    ]
  }
}