{
  "type": "Feature",
  "properties": {
    "name": "Vizinga",
    "country": "RU",
    "subdivision": "34",
    "timezone": "Europe/Moscow"
  },
  "geometry": {
    "type": "Point",
    "coordinates": [
      50.10311,
      61.07493
    ]
  }
}