{
  "type": "Feature",
  "properties": {
    "name": "Candia",
    "country": "US",
    "subdivision": "NH",
    "timezone": "America/New_York"
  },
  "geometry": {
    "type": "Point",
    "coordinates": [
      -71.27673,
      43.07786
    ]
  }
}