{
  "type": "Feature",
  "properties": {
    "name": "Durham",
    "country": "US",
    "subdivision": "NH",
    "timezone": "America/New_York"
  },
  "geometry": {
    "type": "Point",
    "coordinates": [
      -70.92645,
      43.13397
    ]
  }
}