{
  "type": "Feature",
  "properties": {
    "name": "Effingham",
    "country": "US",
    "subdivision": "NH",
    "timezone": "America/New_York"
  },
  "geometry": {
    "type": "Point",
    "coordinates": [
      -70.99645,
      43.76119
    ]
  }
}