{
  "type": "Feature",
  "properties": {
    "name": "Franklin",
    "country": "US",
    "subdivision": "NH",
    "timezone": "America/New_York"
  },
  "geometry": {
    "type": "Point",
    "coordinates": [
      -71.6473,
      43.44424
    ]
  }
}