{
  "type": "Feature",
  "properties": {
    "name": "Meredith",
    "country": "US",
    "subdivision": "NH",
    "timezone": "America/New_York"
  },
  "geometry": {
    "type": "Point",
    "coordinates": [
      -71.50035,
      43.65757
    ]
  }
}