{
  "type": "Feature",
  "properties": {
    "name": "Milan",
    "country": "US",
    "subdivision": "NH",
    "timezone": "America/New_York"
  },
  "geometry": {
    "type": "Point",
    "coordinates": [
      -71.18508,
      44.57339
    ]
  }
}