{
  "type": "Feature",
  "properties": {
    "name": "Orford",
    "country": "US",
    "subdivision": "NH",
    "timezone": "America/New_York"
  },
  "geometry": {
    "type": "Point",
    "coordinates": [
      -72.14009,
      43.90535
    ]
  }
}