{
  "type": "Feature",
  "properties": {
    "name": "Pelham",
    "country": "US",
    "subdivision": "NH",
    "timezone": "America/New_York"
  },
  "geometry": {
    "type": "Point",
    "coordinates": [
      -71.32451,
      42.73453
    ]
  }
}