{
  "type": "Feature",
  "properties": {
    "name": "Pembroke",
    "country": "US",
    "subdivision": "NH",
    "timezone": "America/New_York"
  },
  "geometry": {
    "type": "Point",
    "coordinates": [
      -71.45757,
      43.14675
    ]
  }
}