{
  "type": "Feature",
  "properties": {
    "name": "Plaistow",
    "country": "US",
    "subdivision": "NH",
    "timezone": "America/New_York"
  },
  "geometry": {
    "type": "Point",
    "coordinates": [
      -71.09478,
      42.83648
    ]
  }
}