{
  "type": "Feature",
  "properties": {
    "name": "South Hooksett",
    "country": "US",
    "subdivision": "NH",
    "timezone": "America/New_York"
  },
  "geometry": {
    "type": "Point",
    "coordinates": [
      -71.43534,
      43.02647
    ]
  }
}