{
  "type": "Feature",
  "properties": {
    "name": "Tilton",
    "country": "US",
    "subdivision": "NH",
    "timezone": "America/New_York"
  },
  "geometry": {
    "type": "Point",
    "coordinates": [
      -71.58896,
      43.4423
    ]
  }
}