{
  "type": "Feature",
  "properties": {
    "name": "Tuftonboro",
    "country": "US",
    "subdivision": "NH",
    "timezone": "America/New_York"
  },
  "geometry": {
    "type": "Point",
    "coordinates": [
      -71.22201,
      43.69647
    ]
  }
}