{
  "type": "Feature",
  "properties": {
    "name": "Weare",
    "country": "US",
    "subdivision": "NH",
    "timezone": "America/New_York"
  },
  "geometry": {
    "type": "Point",
    "coordinates": [
      -71.73063,
      43.0948
    ]
  }
}