{
  "type": "Feature",
  "properties": {
    "name": "Whitefield",
    "country": "US",
    "subdivision": "NH",
    "timezone": "America/New_York"
  },
  "geometry": {
    "type": "Point",
    "coordinates": [
      -71.61008,
      44.37312
    ]
  }
}