{
  "type": "Feature",
  "properties": {
    "name": "Woodstock",
    "country": "US",
    "subdivision": "NH",
    "timezone": "America/New_York"
  },
  "geometry": {
    "type": "Point",
    "coordinates": [
      -71.68508,
      43.97757
    ]
  }
}