{
  "type": "Feature",
  "properties": {
    "name": "Ambarawa",
    "country": "ID",
    "subdivision": "07",
    "timezone": "Asia/Jakarta"
  },
  "geometry": {
    "type": "Point",
    "coordinates": [
      110.3975,
      -7.26333
    ]
  }
}