{
  "type": "Feature",
  "properties": {
    "name": "Baekrajan",
    "country": "ID",
    "subdivision": "07",
    "timezone": "Asia/Jakarta"
  },
  "geometry": {
    "type": "Point",
    "coordinates": [
      110.8541,
      -6.7674
    ]
  }
}