{
  "type": "Feature",
  "properties": {
    "name": "Banyumas",
    "country": "ID",
    "subdivision": "07",
    "timezone": "Asia/Jakarta"
  },
  "geometry": {
    "type": "Point",
    "coordinates": [
      109.29417,
      -7.51417
    ]
  }
}