{
  "type": "Feature",
  "properties": {
    "name": "Bulakamba",
    "country": "ID",
    "subdivision": "07",
    "timezone": "Asia/Jakarta"
  },
  "geometry": {
    "type": "Point",
    "coordinates": [
      108.9559,
      -6.8748
    ]
  }
}