{
  "type": "Feature",
  "properties": {
    "name": "Jaten",
    "country": "ID",
    "subdivision": "07",
    "timezone": "Asia/Jakarta"
  },
  "geometry": {
    "type": "Point",
    "coordinates": [
      110.8975,
      -7.57722
    ]
  }
}