{
  "type": "Feature",
  "properties": {
    "name": "Karanganom",
    "country": "ID",
    "subdivision": "07",
    "timezone": "Asia/Jakarta"
  },
  "geometry": {
    "type": "Point",
    "coordinates": [
      110.625,
      -7.64889
    ]
  }
}