{
  "type": "Feature",
  "properties": {
    "name": "Kudus",
    "country": "ID",
    "subdivision": "07",
    "timezone": "Asia/Jakarta"
  },
  "geometry": {
    "type": "Point",
    "coordinates": [
      110.8405,
      -6.8048
    ]
  }
}