{
  "type": "Feature",
  "properties": {
    "name": "Lasem",
    "country": "ID",
    "subdivision": "07",
    "timezone": "Asia/Jakarta"
  },
  "geometry": {
    "type": "Point",
    "coordinates": [
      111.4527,
      -6.6922
    ]
  }
}