{
  "type": "Feature",
  "properties": {
    "name": "Margasari",
    "country": "ID",
    "subdivision": "07",
    "timezone": "Asia/Jakarta"
  },
  "geometry": {
    "type": "Point",
    "coordinates": [
      109.025,
      -7.09484
    ]
  }
}