{
  "type": "Feature",
  "properties": {
    "name": "Mertoyudan",
    "country": "ID",
    "subdivision": "07",
    "timezone": "Asia/Jakarta"
  },
  "geometry": {
    "type": "Point",
    "coordinates": [
      110.22639,
      -7.52
    ]
  }
}