{
  "type": "Feature",
  "properties": {
    "name": "Muntilan",
    "country": "ID",
    "subdivision": "07",
    "timezone": "Asia/Jakarta"
  },
  "geometry": {
    "type": "Point",
    "coordinates": [
      110.29278,
      -7.58111
    ]
  }
}