{
  "type": "Feature",
  "properties": {
    "name": "Rembangan",
    "country": "ID",
    "subdivision": "07",
    "timezone": "Asia/Jakarta"
  },
  "geometry": {
    "type": "Point",
    "coordinates": [
      111.3416,
      -6.7036
    ]
  }
}