{
  "type": "Feature",
  "properties": {
    "name": "Aymavilles",
    "country": "IT",
    "subdivision": "19",
    "timezone": "Europe/Rome"
  },
  "geometry": {
    "type": "Point",
    "coordinates": [
      7.24683,
      45.7013
    ]
  }
}