{
  "type": "Feature",
  "properties": {
    "name": "Fénis",
    "country": "IT",
    "subdivision": "19",
    "timezone": "Europe/Rome"
  },
  "geometry": {
    "type": "Point",
    "coordinates": [
      7.49544,
      45.73469
    ]
  }
}