{
  "type": "Feature",
  "properties": {
    "name": "Morgex",
    "country": "IT",
    "subdivision": "19",
    "timezone": "Europe/Rome"
  },
  "geometry": {
    "type": "Point",
    "coordinates": [
      7.04123,
      45.75664
    ]
  }
}