{
  "type": "Feature",
  "properties": {
    "name": "Nus",
    "country": "IT",
    "subdivision": "19",
    "timezone": "Europe/Rome"
  },
  "geometry": {
    "type": "Point",
    "coordinates": [
      7.4666,
      45.74026
    ]
  }
}