{
  "type": "Feature",
  "properties": {
    "name": "Pollein",
    "country": "IT",
    "subdivision": "19",
    "timezone": "Europe/Rome"
  },
  "geometry": {
    "type": "Point",
    "coordinates": [
      7.35146,
      45.7278
    ]
  }
}