{
  "type": "Feature",
  "properties": {
    "name": "Saint-Christophe",
    "country": "IT",
    "subdivision": "19",
    "timezone": "Europe/Rome"
  },
  "geometry": {
    "type": "Point",
    "coordinates": [
      7.3472,
      45.75406
    ]
  }
}