{
  "type": "Feature",
  "properties": {
    "name": "Valtournenche",
    "country": "IT",
    "subdivision": "19",
    "timezone": "Europe/Rome"
  },
  "geometry": {
    "type": "Point",
    "coordinates": [
      7.6243,
      45.87607
    ]
  }
}