{
  "type": "Feature",
  "properties": {
    "name": "Baker",
    "country": "US",
    "subdivision": "MT",
    "timezone": "America/Denver"
  },
  "geometry": {
    "type": "Point",
    "coordinates": [
      -104.28466,
      46.36695
    ]
  }
}