{
  "type": "Feature",
  "properties": {
    "name": "Bonner-West Riverside",
    "country": "US",
    "subdivision": "MT",
    "timezone": "America/Denver"
  },
  "geometry": {
    "type": "Point",
    "coordinates": [
      -113.88678,
      46.87669
    ]
  }
}