{
  "type": "Feature",
  "properties": {
    "name": "Forsyth",
    "country": "US",
    "subdivision": "MT",
    "timezone": "America/Denver"
  },
  "geometry": {
    "type": "Point",
    "coordinates": [
      -106.67781,
      46.26638
    ]
  }
}