{
  "type": "Feature",
  "properties": {
    "name": "Orchard Homes",
    "country": "US",
    "subdivision": "MT",
    "timezone": "America/Denver"
  },
  "geometry": {
    "type": "Point",
    "coordinates": [
      -114.04844,
      46.86326
    ]
  }
}