{
  "type": "Feature",
  "properties": {
    "name": "Plentywood",
    "country": "US",
    "subdivision": "MT",
    "timezone": "America/Denver"
  },
  "geometry": {
    "type": "Point",
    "coordinates": [
      -104.56246,
      48.77475
    ]
  }
}