{
  "type": "Feature",
  "properties": {
    "name": "Sidney",
    "country": "US",
    "subdivision": "MT",
    "timezone": "America/Denver"
  },
  "geometry": {
    "type": "Point",
    "coordinates": [
      -104.15633,
      47.71668
    ]
  }
}