{
  "type": "Feature",
  "properties": {
    "name": "Stevensville",
    "country": "US",
    "subdivision": "MT",
    "timezone": "America/Denver"
  },
  "geometry": {
    "type": "Point",
    "coordinates": [
      -114.09316,
      46.50992
    ]
  }
}