{
  "type": "Feature",
  "properties": {
    "name": "Three Forks",
    "country": "US",
    "subdivision": "MT",
    "timezone": "America/Denver"
  },
  "geometry": {
    "type": "Point",
    "coordinates": [
      -111.55219,
      45.89243
    ]
  }
}