{
  "type": "Feature",
  "properties": {
    "name": "Townsend",
    "country": "US",
    "subdivision": "MT",
    "timezone": "America/Denver"
  },
  "geometry": {
    "type": "Point",
    "coordinates": [
      -111.5208,
      46.3191
    ]
  }
}