{
  "type": "Feature",
  "properties": {
    "name": "Accokeek",
    "country": "US",
    "subdivision": "MD",
    "timezone": "America/New_York"
  },
  "geometry": {
    "type": "Point",
    "coordinates": [
      -77.02831,
      38.66762
    ]
  }
}