{
  "type": "Feature",
  "properties": {
    "name": "Arden on the Severn",
    "country": "US",
    "subdivision": "MD",
    "timezone": "America/New_York"
  },
  "geometry": {
    "type": "Point",
    "coordinates": [
      -76.57885,
      39.06594
    ]
  }
}