{
  "type": "Feature",
  "properties": {
    "name": "Ashton-Sandy Spring",
    "country": "US",
    "subdivision": "MD",
    "timezone": "America/New_York"
  },
  "geometry": {
    "type": "Point",
    "coordinates": [
      -77.00504,
      39.14976
    ]
  }
}