{
  "type": "Feature",
  "properties": {
    "name": "Baden",
    "country": "US",
    "subdivision": "MD",
    "timezone": "America/New_York"
  },
  "geometry": {
    "type": "Point",
    "coordinates": [
      -76.77775,
      38.65928
    ]
  }
}