{
  "type": "Feature",
  "properties": {
    "name": "Brooklyn Park",
    "country": "US",
    "subdivision": "MD",
    "timezone": "America/New_York"
  },
  "geometry": {
    "type": "Point",
    "coordinates": [
      -76.61636,
      39.22844
    ]
  }
}