{
  "type": "Feature",
  "properties": {
    "name": "Cambridge",
    "country": "US",
    "subdivision": "MD",
    "timezone": "America/New_York"
  },
  "geometry": {
    "type": "Point",
    "coordinates": [
      -76.07883,
      38.56317
    ]
  }
}