{
  "type": "Feature",
  "properties": {
    "name": "Capitol Heights",
    "country": "US",
    "subdivision": "MD",
    "timezone": "America/New_York"
  },
  "geometry": {
    "type": "Point",
    "coordinates": [
      -76.91581,
      38.88511
    ]
  }
}