{
  "type": "Feature",
  "properties": {
    "name": "Catonsville",
    "country": "US",
    "subdivision": "MD",
    "timezone": "America/New_York"
  },
  "geometry": {
    "type": "Point",
    "coordinates": [
      -76.73192,
      39.27205
    ]
  }
}