{
  "type": "Feature",
  "properties": {
    "name": "Chester",
    "country": "US",
    "subdivision": "MD",
    "timezone": "America/New_York"
  },
  "geometry": {
    "type": "Point",
    "coordinates": [
      -76.2894,
      38.97539
    ]
  }
}