{
  "type": "Feature",
  "properties": {
    "name": "Crownsville",
    "country": "US",
    "subdivision": "MD",
    "timezone": "America/New_York"
  },
  "geometry": {
    "type": "Point",
    "coordinates": [
      -76.60135,
      39.02844
    ]
  }
}