{
  "type": "Feature",
  "properties": {
    "name": "Derwood",
    "country": "US",
    "subdivision": "MD",
    "timezone": "America/New_York"
  },
  "geometry": {
    "type": "Point",
    "coordinates": [
      -77.16109,
      39.11733
    ]
  }
}