{
  "type": "Feature",
  "properties": {
    "name": "Ellicott City",
    "country": "US",
    "subdivision": "MD",
    "timezone": "America/New_York"
  },
  "geometry": {
    "type": "Point",
    "coordinates": [
      -76.79831,
      39.26733
    ]
  }
}