{
  "type": "Feature",
  "properties": {
    "name": "Emmitsburg",
    "country": "US",
    "subdivision": "MD",
    "timezone": "America/New_York"
  },
  "geometry": {
    "type": "Point",
    "coordinates": [
      -77.32693,
      39.70454
    ]
  }
}