{
  "type": "Feature",
  "properties": {
    "name": "Fallston",
    "country": "US",
    "subdivision": "MD",
    "timezone": "America/New_York"
  },
  "geometry": {
    "type": "Point",
    "coordinates": [
      -76.41107,
      39.51455
    ]
  }
}