{
  "type": "Feature",
  "properties": {
    "name": "Garrison",
    "country": "US",
    "subdivision": "MD",
    "timezone": "America/New_York"
  },
  "geometry": {
    "type": "Point",
    "coordinates": [
      -76.76053,
      39.40594
    ]
  }
}