{
  "type": "Feature",
  "properties": {
    "name": "Huntingtown",
    "country": "US",
    "subdivision": "MD",
    "timezone": "America/New_York"
  },
  "geometry": {
    "type": "Point",
    "coordinates": [
      -76.61302,
      38.61595
    ]
  }
}