{
  "type": "Feature",
  "properties": {
    "name": "Jarrettsville",
    "country": "US",
    "subdivision": "MD",
    "timezone": "America/New_York"
  },
  "geometry": {
    "type": "Point",
    "coordinates": [
      -76.47774,
      39.60455
    ]
  }
}