{
  "type": "Feature",
  "properties": {
    "name": "La Vale",
    "country": "US",
    "subdivision": "MD",
    "timezone": "America/New_York"
  },
  "geometry": {
    "type": "Point",
    "coordinates": [
      -78.81058,
      39.65564
    ]
  }
}