{
  "type": "Feature",
  "properties": {
    "name": "Lake Shore",
    "country": "US",
    "subdivision": "MD",
    "timezone": "America/New_York"
  },
  "geometry": {
    "type": "Point",
    "coordinates": [
      -76.48496,
      39.10705
    ]
  }
}