{
  "type": "Feature",
  "properties": {
    "name": "Largo",
    "country": "US",
    "subdivision": "MD",
    "timezone": "America/New_York"
  },
  "geometry": {
    "type": "Point",
    "coordinates": [
      -76.83025,
      38.89761
    ]
  }
}