{
  "type": "Feature",
  "properties": {
    "name": "Linthicum",
    "country": "US",
    "subdivision": "MD",
    "timezone": "America/New_York"
  },
  "geometry": {
    "type": "Point",
    "coordinates": [
      -76.65275,
      39.20511
    ]
  }
}