{
  "type": "Feature",
  "properties": {
    "name": "Lutherville",
    "country": "US",
    "subdivision": "MD",
    "timezone": "America/New_York"
  },
  "geometry": {
    "type": "Point",
    "coordinates": [
      -76.62608,
      39.42122
    ]
  }
}