{
  "type": "Feature",
  "properties": {
    "name": "Maugansville",
    "country": "US",
    "subdivision": "MD",
    "timezone": "America/New_York"
  },
  "geometry": {
    "type": "Point",
    "coordinates": [
      -77.74472,
      39.69287
    ]
  }
}