{
  "type": "Feature",
  "properties": {
    "name": "Mayo",
    "country": "US",
    "subdivision": "MD",
    "timezone": "America/New_York"
  },
  "geometry": {
    "type": "Point",
    "coordinates": [
      -76.5119,
      38.88761
    ]
  }
}