{
  "type": "Feature",
  "properties": {
    "name": "Mount Rainier",
    "country": "US",
    "subdivision": "MD",
    "timezone": "America/New_York"
  },
  "geometry": {
    "type": "Point",
    "coordinates": [
      -76.96498,
      38.9415
    ]
  }
}