{
  "type": "Feature",
  "properties": {
    "name": "National Harbor",
    "country": "US",
    "subdivision": "MD",
    "timezone": "America/New_York"
  },
  "geometry": {
    "type": "Point",
    "coordinates": [
      -77.01506,
      38.78264
    ]
  }
}