{
  "type": "Feature",
  "properties": {
    "name": "New Carrollton",
    "country": "US",
    "subdivision": "MD",
    "timezone": "America/New_York"
  },
  "geometry": {
    "type": "Point",
    "coordinates": [
      -76.87997,
      38.96983
    ]
  }
}