{
  "type": "Feature",
  "properties": {
    "name": "North Laurel",
    "country": "US",
    "subdivision": "MD",
    "timezone": "America/New_York"
  },
  "geometry": {
    "type": "Point",
    "coordinates": [
      -76.87053,
      39.139
    ]
  }
}