{
  "type": "Feature",
  "properties": {
    "name": "Oakland",
    "country": "US",
    "subdivision": "MD",
    "timezone": "America/New_York"
  },
  "geometry": {
    "type": "Point",
    "coordinates": [
      -79.40671,
      39.40787
    ]
  }
}