{
  "type": "Feature",
  "properties": {
    "name": "Odenton",
    "country": "US",
    "subdivision": "MD",
    "timezone": "America/New_York"
  },
  "geometry": {
    "type": "Point",
    "coordinates": [
      -76.70025,
      39.084
    ]
  }
}