{
  "type": "Feature",
  "properties": {
    "name": "Peppermill Village",
    "country": "US",
    "subdivision": "MD",
    "timezone": "America/New_York"
  },
  "geometry": {
    "type": "Point",
    "coordinates": [
      -76.88654,
      38.89472
    ]
  }
}