{
  "type": "Feature",
  "properties": {
    "name": "Potomac Park",
    "country": "US",
    "subdivision": "MD",
    "timezone": "America/New_York"
  },
  "geometry": {
    "type": "Point",
    "coordinates": [
      -78.80585,
      39.61176
    ]
  }
}