{
  "type": "Feature",
  "properties": {
    "name": "Rising Sun",
    "country": "US",
    "subdivision": "MD",
    "timezone": "America/New_York"
  },
  "geometry": {
    "type": "Point",
    "coordinates": [
      -76.06273,
      39.69789
    ]
  }
}