{
  "type": "Feature",
  "properties": {
    "name": "Solomons",
    "country": "US",
    "subdivision": "MD",
    "timezone": "America/New_York"
  },
  "geometry": {
    "type": "Point",
    "coordinates": [
      -76.45412,
      38.31846
    ]
  }
}