{
  "type": "Feature",
  "properties": {
    "name": "Suitland",
    "country": "US",
    "subdivision": "MD",
    "timezone": "America/New_York"
  },
  "geometry": {
    "type": "Point",
    "coordinates": [
      -76.92386,
      38.84872
    ]
  }
}