{
  "type": "Feature",
  "properties": {
    "name": "West Laurel",
    "country": "US",
    "subdivision": "MD",
    "timezone": "America/New_York"
  },
  "geometry": {
    "type": "Point",
    "coordinates": [
      -76.8997,
      39.10122
    ]
  }
}