{
  "type": "Feature",
  "properties": {
    "name": "Wilson-Conococheague",
    "country": "US",
    "subdivision": "MD",
    "timezone": "America/New_York"
  },
  "geometry": {
    "type": "Point",
    "coordinates": [
      -77.83157,
      39.65351
    ]
  }
}