{
  "type": "Feature",
  "properties": {
    "name": "Kragerø",
    "country": "NO",
    "subdivision": "38",
    "timezone": "Europe/Oslo"
  },
  "geometry": {
    "type": "Point",
    "coordinates": [
      9.41494,
      58.8693
    ]
  }
}