{
  "type": "Feature",
  "properties": {
    "name": "Melsomvik",
    "country": "NO",
    "subdivision": "38",
    "timezone": "Europe/Oslo"
  },
  "geometry": {
    "type": "Point",
    "coordinates": [
      10.33616,
      59.22394
    ]
  }
}