{
  "type": "Feature",
  "properties": {
    "name": "Sem",
    "country": "NO",
    "subdivision": "38",
    "timezone": "Europe/Oslo"
  },
  "geometry": {
    "type": "Point",
    "coordinates": [
      10.33004,
      59.2823
    ]
  }
}