{
  "type": "Feature",
  "properties": {
    "name": "Ano Arhanes",
    "country": "GR",
    "subdivision": "ESYE43",
    "timezone": "Europe/Athens"
  },
  "geometry": {
    "type": "Point",
    "coordinates": [
      25.16667,
      35.23333
    ]
  }
}