{
  "type": "Feature",
  "properties": {
    "name": "Eloúnda",
    "country": "GR",
    "subdivision": "ESYE43",
    "timezone": "Europe/Athens"
  },
  "geometry": {
    "type": "Point",
    "coordinates": [
      25.72127,
      35.265
    ]
  }
}