{
  "type": "Feature",
  "properties": {
    "name": "Palaióchora",
    "country": "GR",
    "subdivision": "ESYE43",
    "timezone": "Europe/Athens"
  },
  "geometry": {
    "type": "Point",
    "coordinates": [
      23.68185,
      35.23128
    ]
  }
}