{
  "type": "Feature",
  "properties": {
    "name": "Thrapsanón",
    "country": "GR",
    "subdivision": "ESYE43",
    "timezone": "Europe/Athens"
  },
  "geometry": {
    "type": "Point",
    "coordinates": [
      25.28091,
      35.18798
    ]
  }
}