{
  "type": "Feature",
  "properties": {
    "name": "Violí Charáki",
    "country": "GR",
    "subdivision": "ESYE43",
    "timezone": "Europe/Athens"
  },
  "geometry": {
    "type": "Point",
    "coordinates": [
      24.43857,
      35.35864
    ]
  }
}