{
  "type": "Feature",
  "properties": {
    "name": "Tekman",
    "country": "TR",
    "subdivision": "25",
    "timezone": "Europe/Istanbul"
  },
  "geometry": {
    "type": "Point",
    "coordinates": [
      41.50542,
      39.64111
    ]
  }
}