{
  "type": "Feature",
  "properties": {
    "name": "Bayt al Faqīh",
    "country": "YE",
    "subdivision": "08",
    "timezone": "Asia/Aden"
  },
  "geometry": {
    "type": "Point",
    "coordinates": [
      43.32446,
      14.51635
    ]
  }
}