{
  "type": "Feature",
  "properties": {
    "name": "Bachíniva",
    "country": "MX",
    "subdivision": "06",
    "timezone": "America/Chihuahua"
  },
  "geometry": {
    "type": "Point",
    "coordinates": [
      -107.25559,
      28.76801
    ]
  }
}