{
  "type": "Feature",
  "properties": {
    "name": "Cerocahui",
    "country": "MX",
    "subdivision": "06",
    "timezone": "America/Chihuahua"
  },
  "geometry": {
    "type": "Point",
    "coordinates": [
      -108.055,
      27.29906
    ]
  }
}