{
  "type": "Feature",
  "properties": {
    "name": "Colonia Revolución",
    "country": "MX",
    "subdivision": "06",
    "timezone": "America/Chihuahua"
  },
  "geometry": {
    "type": "Point",
    "coordinates": [
      -105.44361,
      28.24167
    ]
  }
}