{
  "type": "Feature",
  "properties": {
    "name": "Ejido La Quemada",
    "country": "MX",
    "subdivision": "06",
    "timezone": "America/Chihuahua"
  },
  "geometry": {
    "type": "Point",
    "coordinates": [
      -107.02152,
      28.84761
    ]
  }
}