{
  "type": "Feature",
  "properties": {
    "name": "Ejido El Largo",
    "country": "MX",
    "subdivision": "06",
    "timezone": "America/Chihuahua"
  },
  "geometry": {
    "type": "Point",
    "coordinates": [
      -108.26667,
      29.68333
    ]
  }
}