{
  "type": "Feature",
  "properties": {
    "name": "El Sauz",
    "country": "MX",
    "subdivision": "06",
    "timezone": "America/Chihuahua"
  },
  "geometry": {
    "type": "Point",
    "coordinates": [
      -106.2528,
      29.05056
    ]
  }
}