{
  "type": "Feature",
  "properties": {
    "name": "Estación Conchos",
    "country": "MX",
    "subdivision": "06",
    "timezone": "America/Chihuahua"
  },
  "geometry": {
    "type": "Point",
    "coordinates": [
      -105.28843,
      27.97326
    ]
  }
}