{
  "type": "Feature",
  "properties": {
    "name": "José Mariano Jiménez",
    "country": "MX",
    "subdivision": "06",
    "timezone": "America/Chihuahua"
  },
  "geometry": {
    "type": "Point",
    "coordinates": [
      -104.92391,
      27.13076
    ]
  }
}