{
  "type": "Feature",
  "properties": {
    "name": "Las Varas (Estación Babícora)",
    "country": "MX",
    "subdivision": "06",
    "timezone": "America/Chihuahua"
  },
  "geometry": {
    "type": "Point",
    "coordinates": [
      -108.02556,
      29.48083
    ]
  }
}