{
  "type": "Feature",
  "properties": {
    "name": "Madera",
    "country": "MX",
    "subdivision": "06",
    "timezone": "America/Chihuahua"
  },
  "geometry": {
    "type": "Point",
    "coordinates": [
      -108.14684,
      29.19366
    ]
  }
}