{
  "type": "Feature",
  "properties": {
    "name": "Nuevo Casas Grandes",
    "country": "MX",
    "subdivision": "06",
    "timezone": "America/Chihuahua"
  },
  "geometry": {
    "type": "Point",
    "coordinates": [
      -107.91166,
      30.41552
    ]
  }
}