{
  "type": "Feature",
  "properties": {
    "name": "Octaviano López",
    "country": "MX",
    "subdivision": "06",
    "timezone": "America/Chihuahua"
  },
  "geometry": {
    "type": "Point",
    "coordinates": [
      -105.03306,
      27.0025
    ]
  }
}