{
  "type": "Feature",
  "properties": {
    "name": "Rodrígo M. Quevedo",
    "country": "MX",
    "subdivision": "06",
    "timezone": "America/Chihuahua"
  },
  "geometry": {
    "type": "Point",
    "coordinates": [
      -107.52079,
      29.91982
    ]
  }
}