{
  "type": "Feature",
  "properties": {
    "name": "Samalayuca",
    "country": "MX",
    "subdivision": "06",
    "timezone": "America/Ojinaga"
  },
  "geometry": {
    "type": "Point",
    "coordinates": [
      -106.47981,
      31.34242
    ]
  }
}