{
  "type": "Feature",
  "properties": {
    "name": "San Buenaventura",
    "country": "MX",
    "subdivision": "06",
    "timezone": "America/Chihuahua"
  },
  "geometry": {
    "type": "Point",
    "coordinates": [
      -107.46067,
      29.8432
    ]
  }
}