{
  "type": "Feature",
  "properties": {
    "name": "Bovril",
    "country": "AR",
    "subdivision": "08",
    "timezone": "America/Argentina/Cordoba"
  },
  "geometry": {
    "type": "Point",
    "coordinates": [
      -59.44512,
      -31.34311
    ]
  }
}