{
  "type": "Feature",
  "properties": {
    "name": "Chajarí",
    "country": "AR",
    "subdivision": "08",
    "timezone": "America/Argentina/Cordoba"
  },
  "geometry": {
    "type": "Point",
    "coordinates": [
      -57.97962,
      -30.75048
    ]
  }
}