{
  "type": "Feature",
  "properties": {
    "name": "Colonia Elía",
    "country": "AR",
    "subdivision": "08",
    "timezone": "America/Argentina/Cordoba"
  },
  "geometry": {
    "type": "Point",
    "coordinates": [
      -58.32538,
      -32.67144
    ]
  }
}