{
  "type": "Feature",
  "properties": {
    "name": "Concordia",
    "country": "AR",
    "subdivision": "08",
    "timezone": "America/Argentina/Cordoba"
  },
  "geometry": {
    "type": "Point",
    "coordinates": [
      -58.02089,
      -31.39296
    ]
  }
}