{
  "type": "Feature",
  "properties": {
    "name": "Conscripto Bernardi",
    "country": "AR",
    "subdivision": "08",
    "timezone": "America/Argentina/Cordoba"
  },
  "geometry": {
    "type": "Point",
    "coordinates": [
      -59.08435,
      -31.04837
    ]
  }
}