{
  "type": "Feature",
  "properties": {
    "name": "Diamante",
    "country": "AR",
    "subdivision": "08",
    "timezone": "America/Argentina/Cordoba"
  },
  "geometry": {
    "type": "Point",
    "coordinates": [
      -60.63837,
      -32.06641
    ]
  }
}