{
  "type": "Feature",
  "properties": {
    "name": "Domínguez",
    "country": "AR",
    "subdivision": "08",
    "timezone": "America/Argentina/Cordoba"
  },
  "geometry": {
    "type": "Point",
    "coordinates": [
      -58.96197,
      -31.9871
    ]
  }
}