{
  "type": "Feature",
  "properties": {
    "name": "Federación",
    "country": "AR",
    "subdivision": "08",
    "timezone": "America/Argentina/Cordoba"
  },
  "geometry": {
    "type": "Point",
    "coordinates": [
      -57.89962,
      -31.00621
    ]
  }
}