{
  "type": "Feature",
  "properties": {
    "name": "General Campos",
    "country": "AR",
    "subdivision": "08",
    "timezone": "America/Argentina/Cordoba"
  },
  "geometry": {
    "type": "Point",
    "coordinates": [
      -58.4049,
      -31.52311
    ]
  }
}