{
  "type": "Feature",
  "properties": {
    "name": "Herrera",
    "country": "AR",
    "subdivision": "08",
    "timezone": "America/Argentina/Cordoba"
  },
  "geometry": {
    "type": "Point",
    "coordinates": [
      -58.63177,
      -32.43401
    ]
  }
}