{
  "type": "Feature",
  "properties": {
    "name": "Victoria",
    "country": "AR",
    "subdivision": "08",
    "timezone": "America/Argentina/Cordoba"
  },
  "geometry": {
    "type": "Point",
    "coordinates": [
      -60.15478,
      -32.61841
    ]
  }
}