{
  "type": "Feature",
  "properties": {
    "name": "L’Arbaa Naït Irathen",
    "country": "DZ",
    "subdivision": "14",
    "timezone": "Africa/Algiers"
  },
  "geometry": {
    "type": "Point",
    "coordinates": [
      4.19864,
      36.63112
    ]
  }
}