{
  "type": "Feature",
  "properties": {
    "name": "Panajachel",
    "country": "GT",
    "subdivision": "19",
    "timezone": "America/Guatemala"
  },
  "geometry": {
    "type": "Point",
    "coordinates": [
      -91.15676,
      14.74185
    ]
  }
}