{
  "type": "Feature",
  "properties": {
    "name": "San Antonio Palopó",
    "country": "GT",
    "subdivision": "19",
    "timezone": "America/Guatemala"
  },
  "geometry": {
    "type": "Point",
    "coordinates": [
      -91.11638,
      14.69232
    ]
  }
}