{
  "type": "Feature",
  "properties": {
    "name": "San Marcos La Laguna",
    "country": "GT",
    "subdivision": "19",
    "timezone": "America/Guatemala"
  },
  "geometry": {
    "type": "Point",
    "coordinates": [
      -91.25844,
      14.72504
    ]
  }
}