{
  "type": "Feature",
  "properties": {
    "name": "Santa Catarina Palopó",
    "country": "GT",
    "subdivision": "19",
    "timezone": "America/Guatemala"
  },
  "geometry": {
    "type": "Point",
    "coordinates": [
      -91.13428,
      14.72335
    ]
  }
}