{
  "type": "Feature",
  "properties": {
    "name": "Bassano",
    "country": "CA",
    "subdivision": "01",
    "timezone": "America/Edmonton"
  },
  "geometry": {
    "type": "Point",
    "coordinates": [
      -112.46805,
      50.78998
    ]
  }
}