{
  "type": "Feature",
  "properties": {
    "name": "Blackfalds",
    "country": "CA",
    "subdivision": "01",
    "timezone": "America/Edmonton"
  },
  "geometry": {
    "type": "Point",
    "coordinates": [
      -113.7853,
      52.38342
    ]
  }
}