{
  "type": "Feature",
  "properties": {
    "name": "Camrose",
    "country": "CA",
    "subdivision": "01",
    "timezone": "America/Edmonton"
  },
  "geometry": {
    "type": "Point",
    "coordinates": [
      -112.83525,
      53.01684
    ]
  }
}