{
  "type": "Feature",
  "properties": {
    "name": "Cochrane",
    "country": "CA",
    "subdivision": "01",
    "timezone": "America/Edmonton"
  },
  "geometry": {
    "type": "Point",
    "coordinates": [
      -114.46871,
      51.18341
    ]
  }
}