{
  "type": "Feature",
  "properties": {
    "name": "Fox Creek",
    "country": "CA",
    "subdivision": "01",
    "timezone": "America/Edmonton"
  },
  "geometry": {
    "type": "Point",
    "coordinates": [
      -116.80238,
      54.40007
    ]
  }
}