{
  "type": "Feature",
  "properties": {
    "name": "High Prairie",
    "country": "CA",
    "subdivision": "01",
    "timezone": "America/Edmonton"
  },
  "geometry": {
    "type": "Point",
    "coordinates": [
      -116.4858,
      55.4334
    ]
  }
}