{
  "type": "Feature",
  "properties": {
    "name": "Jasper Park Lodge",
    "country": "CA",
    "subdivision": "01",
    "timezone": "America/Edmonton"
  },
  "geometry": {
    "type": "Point",
    "coordinates": [
      -118.05625,
      52.88633
    ]
  }
}