{
  "type": "Feature",
  "properties": {
    "name": "Lethbridge",
    "country": "CA",
    "subdivision": "01",
    "timezone": "America/Edmonton"
  },
  "geometry": {
    "type": "Point",
    "coordinates": [
      -112.81856,
      49.69999
    ]
  }
}