{
  "type": "Feature",
  "properties": {
    "name": "Lloydminster",
    "country": "CA",
    "subdivision": "01",
    "timezone": "America/Edmonton"
  },
  "geometry": {
    "type": "Point",
    "coordinates": [
      -110.02256,
      53.27237
    ]
  }
}