{
  "type": "Feature",
  "properties": {
    "name": "Okotoks",
    "country": "CA",
    "subdivision": "01",
    "timezone": "America/Edmonton"
  },
  "geometry": {
    "type": "Point",
    "coordinates": [
      -113.98281,
      50.72885
    ]
  }
}