{
  "type": "Feature",
  "properties": {
    "name": "Sexsmith",
    "country": "CA",
    "subdivision": "01",
    "timezone": "America/Edmonton"
  },
  "geometry": {
    "type": "Point",
    "coordinates": [
      -118.78602,
      55.34998
    ]
  }
}