{
  "type": "Feature",
  "properties": {
    "name": "Slave Lake",
    "country": "CA",
    "subdivision": "01",
    "timezone": "America/Edmonton"
  },
  "geometry": {
    "type": "Point",
    "coordinates": [
      -114.76896,
      55.28344
    ]
  }
}