{
  "type": "Feature",
  "properties": {
    "name": "Springbrook",
    "country": "CA",
    "subdivision": "01",
    "timezone": "America/Edmonton"
  },
  "geometry": {
    "type": "Point",
    "coordinates": [
      -113.87981,
      52.1792
    ]
  }
}