{
  "type": "Feature",
  "properties": {
    "name": "Spruce Grove",
    "country": "CA",
    "subdivision": "01",
    "timezone": "America/Edmonton"
  },
  "geometry": {
    "type": "Point",
    "coordinates": [
      -113.91874,
      53.53344
    ]
  }
}