{
  "type": "Feature",
  "properties": {
    "name": "St. Paul",
    "country": "CA",
    "subdivision": "01",
    "timezone": "America/Edmonton"
  },
  "geometry": {
    "type": "Point",
    "coordinates": [
      -111.28507,
      53.98347
    ]
  }
}