{
  "type": "Feature",
  "properties": {
    "name": "Tofield",
    "country": "CA",
    "subdivision": "01",
    "timezone": "America/Edmonton"
  },
  "geometry": {
    "type": "Point",
    "coordinates": [
      -112.66862,
      53.36684
    ]
  }
}