{
  "type": "Feature",
  "properties": {
    "name": "Viking",
    "country": "CA",
    "subdivision": "01",
    "timezone": "America/Edmonton"
  },
  "geometry": {
    "type": "Point",
    "coordinates": [
      -111.77527,
      53.09606
    ]
  }
}