{
  "type": "Feature",
  "properties": {
    "name": "Wild Rose",
    "country": "CA",
    "subdivision": "01",
    "timezone": "America/Edmonton"
  },
  "geometry": {
    "type": "Point",
    "coordinates": [
      -113.38119,
      53.4708
    ]
  }
}