{
  "type": "Feature",
  "properties": {
    "name": "Codrington",
    "country": "AG",
    "subdivision": "01",
    "timezone": "America/Antigua"
  },
  "geometry": {
    "type": "Point",
    "coordinates": [
      -61.83333,
      17.63333
    ]
  }
}