{
  "type": "Feature",
  "properties": {
    "name": "Chala",
    "country": "TZ",
    "subdivision": "24",
    "timezone": "Africa/Dar_es_Salaam"
  },
  "geometry": {
    "type": "Point",
    "coordinates": [
      31.26667,
      -7.58333
    ]
  }
}