{
  "type": "Feature",
  "properties": {
    "name": "Nkove",
    "country": "TZ",
    "subdivision": "24",
    "timezone": "Africa/Dar_es_Salaam"
  },
  "geometry": {
    "type": "Point",
    "coordinates": [
      30.85,
      -7.95
    ]
  }
}