{
  "type": "Feature",
  "properties": {
    "name": "Temuco",
    "country": "CL",
    "subdivision": "04",
    "timezone": "America/Santiago"
  },
  "geometry": {
    "type": "Point",
    "coordinates": [
      -72.59842,
      -38.73965
    ]
  }
}