{
  "type": "Feature",
  "properties": {
    "name": "Victoria",
    "country": "CL",
    "subdivision": "04",
    "timezone": "America/Santiago"
  },
  "geometry": {
    "type": "Point",
    "coordinates": [
      -72.33292,
      -38.23291
    ]
  }
}