{
  "type": "Feature",
  "properties": {
    "name": "Villarrica",
    "country": "CL",
    "subdivision": "04",
    "timezone": "America/Santiago"
  },
  "geometry": {
    "type": "Point",
    "coordinates": [
      -72.2279,
      -39.28569
    ]
  }
}