{
  "type": "Feature",
  "properties": {
    "name": "Yuza",
    "country": "JP",
    "subdivision": "44",
    "timezone": "Asia/Tokyo"
  },
  "geometry": {
    "type": "Point",
    "coordinates": [
      139.92909,
      39.01573
    ]
  }
}