{
  "type": "Feature",
  "properties": {
    "name": "Beşpınar",
    "country": "TR",
    "subdivision": "76",
    "timezone": "Europe/Istanbul"
  },
  "geometry": {
    "type": "Point",
    "coordinates": [
      41.60219,
      37.83709
    ]
  }
}