{
  "type": "Feature",
  "properties": {
    "name": "Hasankeyf",
    "country": "TR",
    "subdivision": "76",
    "timezone": "Europe/Istanbul"
  },
  "geometry": {
    "type": "Point",
    "coordinates": [
      41.4048,
      37.70612
    ]
  }
}