{
  "type": "Feature",
  "properties": {
    "name": "Hisar",
    "country": "TR",
    "subdivision": "76",
    "timezone": "Europe/Istanbul"
  },
  "geometry": {
    "type": "Point",
    "coordinates": [
      41.22799,
      37.60094
    ]
  }
}