{
  "type": "Feature",
  "properties": {
    "name": "Jertih",
    "country": "MY",
    "subdivision": "13",
    "timezone": "Asia/Kuala_Lumpur"
  },
  "geometry": {
    "type": "Point",
    "coordinates": [
      102.4897,
      5.7336
    ]
  }
}