{
  "type": "Feature",
  "properties": {
    "name": "Chengzhong",
    "country": "CN",
    "subdivision": "12",
    "timezone": "Asia/Shanghai"
  },
  "geometry": {
    "type": "Point",
    "coordinates": [
      113.55284,
      30.94454
    ]
  }
}