{
  "type": "Feature",
  "properties": {
    "name": "Fengkou",
    "country": "CN",
    "subdivision": "12",
    "timezone": "Asia/Shanghai"
  },
  "geometry": {
    "type": "Point",
    "coordinates": [
      113.33346,
      30.08268
    ]
  }
}