{
  "type": "Feature",
  "properties": {
    "name": "Jingmen",
    "country": "CN",
    "subdivision": "12",
    "timezone": "Asia/Shanghai"
  },
  "geometry": {
    "type": "Point",
    "coordinates": [
      112.20472,
      31.03361
    ]
  }
}