{
  "type": "Feature",
  "properties": {
    "name": "Laohekou",
    "country": "CN",
    "subdivision": "12",
    "timezone": "Asia/Shanghai"
  },
  "geometry": {
    "type": "Point",
    "coordinates": [
      111.66778,
      32.38583
    ]
  }
}