{
  "type": "Feature",
  "properties": {
    "name": "Shiyan",
    "country": "CN",
    "subdivision": "12",
    "timezone": "Asia/Shanghai"
  },
  "geometry": {
    "type": "Point",
    "coordinates": [
      110.77806,
      32.6475
    ]
  }
}