{
  "type": "Feature",
  "properties": {
    "name": "Xiangyang",
    "country": "CN",
    "subdivision": "12",
    "timezone": "Asia/Shanghai"
  },
  "geometry": {
    "type": "Point",
    "coordinates": [
      112.14479,
      32.0422
    ]
  }
}