{
  "type": "Feature",
  "properties": {
    "name": "Zhijiang",
    "country": "CN",
    "subdivision": "12",
    "timezone": "Asia/Shanghai"
  },
  "geometry": {
    "type": "Point",
    "coordinates": [
      111.75333,
      30.42139
    ]
  }
}