{
  "type": "Feature",
  "properties": {
    "name": "Lánycsók",
    "country": "HU",
    "subdivision": "02",
    "timezone": "Europe/Budapest"
  },
  "geometry": {
    "type": "Point",
    "coordinates": [
      18.62526,
      46.00543
    ]
  }
}