{
  "type": "Feature",
  "properties": {
    "name": "Sellye",
    "country": "HU",
    "subdivision": "02",
    "timezone": "Europe/Budapest"
  },
  "geometry": {
    "type": "Point",
    "coordinates": [
      17.84711,
      45.87247
    ]
  }
}