{
  "type": "Feature",
  "properties": {
    "name": "Szigetvár",
    "country": "HU",
    "subdivision": "02",
    "timezone": "Europe/Budapest"
  },
  "geometry": {
    "type": "Point",
    "coordinates": [
      17.80554,
      46.04865
    ]
  }
}