{
  "type": "Feature",
  "properties": {
    "name": "Boćki",
    "country": "PL",
    "subdivision": "81",
    "timezone": "Europe/Warsaw"
  },
  "geometry": {
    "type": "Point",
    "coordinates": [
      23.04485,
      52.65155
    ]
  }
}