{
  "type": "Feature",
  "properties": {
    "name": "Grajewo",
    "country": "PL",
    "subdivision": "81",
    "timezone": "Europe/Warsaw"
  },
  "geometry": {
    "type": "Point",
    "coordinates": [
      22.45537,
      53.64728
    ]
  }
}