{
  "type": "Feature",
  "properties": {
    "name": "Knyszyn",
    "country": "PL",
    "subdivision": "81",
    "timezone": "Europe/Warsaw"
  },
  "geometry": {
    "type": "Point",
    "coordinates": [
      22.91963,
      53.31406
    ]
  }
}