{
  "type": "Feature",
  "properties": {
    "name": "Mały Płock",
    "country": "PL",
    "subdivision": "81",
    "timezone": "Europe/Warsaw"
  },
  "geometry": {
    "type": "Point",
    "coordinates": [
      22.02836,
      53.30385
    ]
  }
}