{
  "type": "Feature",
  "properties": {
    "name": "Nurzec-Stacja",
    "country": "PL",
    "subdivision": "81",
    "timezone": "Europe/Warsaw"
  },
  "geometry": {
    "type": "Point",
    "coordinates": [
      23.08571,
      52.46249
    ]
  }
}