{
  "type": "Feature",
  "properties": {
    "name": "Alsike",
    "country": "SE",
    "subdivision": "21",
    "timezone": "Europe/Stockholm"
  },
  "geometry": {
    "type": "Point",
    "coordinates": [
      17.77331,
      59.75324
    ]
  }
}