{
  "type": "Feature",
  "properties": {
    "name": "Älvkarleby",
    "country": "SE",
    "subdivision": "21",
    "timezone": "Europe/Stockholm"
  },
  "geometry": {
    "type": "Point",
    "coordinates": [
      17.44895,
      60.57081
    ]
  }
}