{
  "type": "Feature",
  "properties": {
    "name": "Gamla Uppsala",
    "country": "SE",
    "subdivision": "21",
    "timezone": "Europe/Stockholm"
  },
  "geometry": {
    "type": "Point",
    "coordinates": [
      17.63386,
      59.89817
    ]
  }
}