{
  "type": "Feature",
  "properties": {
    "name": "Storvreta",
    "country": "SE",
    "subdivision": "21",
    "timezone": "Europe/Stockholm"
  },
  "geometry": {
    "type": "Point",
    "coordinates": [
      17.70588,
      59.95933
    ]
  }
}