{
  "type": "Feature",
  "properties": {
    "name": "Bekalta",
    "country": "TN",
    "subdivision": "16",
    "timezone": "Africa/Tunis"
  },
  "geometry": {
    "type": "Point",
    "coordinates": [
      10.99466,
      35.61739
    ]
  }
}