{
  "type": "Feature",
  "properties": {
    "name": "Beni Hassane",
    "country": "TN",
    "subdivision": "16",
    "timezone": "Africa/Tunis"
  },
  "geometry": {
    "type": "Point",
    "coordinates": [
      10.80869,
      35.5672
    ]
  }
}