{
  "type": "Feature",
  "properties": {
    "name": "Sidi Ben Nour",
    "country": "TN",
    "subdivision": "16",
    "timezone": "Africa/Tunis"
  },
  "geometry": {
    "type": "Point",
    "coordinates": [
      10.91667,
      35.53333
    ]
  }
}