{
  "type": "Feature",
  "properties": {
    "name": "Albești-Muru",
    "country": "RO",
    "subdivision": "30",
    "timezone": "Europe/Bucharest"
  },
  "geometry": {
    "type": "Point",
    "coordinates": [
      26.20899,
      44.9444
    ]
  }
}