{
  "type": "Feature",
  "properties": {
    "name": "Brazii de Sus",
    "country": "RO",
    "subdivision": "30",
    "timezone": "Europe/Bucharest"
  },
  "geometry": {
    "type": "Point",
    "coordinates": [
      26.01667,
      44.86667
    ]
  }
}