{
  "type": "Feature",
  "properties": {
    "name": "Colceag",
    "country": "RO",
    "subdivision": "30",
    "timezone": "Europe/Bucharest"
  },
  "geometry": {
    "type": "Point",
    "coordinates": [
      26.35,
      44.95
    ]
  }
}