{
  "type": "Feature",
  "properties": {
    "name": "Dumbrava",
    "country": "RO",
    "subdivision": "30",
    "timezone": "Europe/Bucharest"
  },
  "geometry": {
    "type": "Point",
    "coordinates": [
      26.18333,
      44.88333
    ]
  }
}