{
  "type": "Feature",
  "properties": {
    "name": "Ghioșești",
    "country": "RO",
    "subdivision": "30",
    "timezone": "Europe/Bucharest"
  },
  "geometry": {
    "type": "Point",
    "coordinates": [
      25.62671,
      45.24235
    ]
  }
}