{
  "type": "Feature",
  "properties": {
    "name": "Gornet-Cricov",
    "country": "RO",
    "subdivision": "30",
    "timezone": "Europe/Bucharest"
  },
  "geometry": {
    "type": "Point",
    "coordinates": [
      26.26667,
      45.08333
    ]
  }
}