{
  "type": "Feature",
  "properties": {
    "name": "Gradiștea",
    "country": "RO",
    "subdivision": "30",
    "timezone": "Europe/Bucharest"
  },
  "geometry": {
    "type": "Point",
    "coordinates": [
      26.5152,
      44.88803
    ]
  }
}