{
  "type": "Feature",
  "properties": {
    "name": "Pleașa",
    "country": "RO",
    "subdivision": "30",
    "timezone": "Europe/Bucharest"
  },
  "geometry": {
    "type": "Point",
    "coordinates": [
      26.07211,
      45.00583
    ]
  }
}