{
  "type": "Feature",
  "properties": {
    "name": "Plopeni",
    "country": "RO",
    "subdivision": "30",
    "timezone": "Europe/Bucharest"
  },
  "geometry": {
    "type": "Point",
    "coordinates": [
      25.95202,
      45.04955
    ]
  }
}