{
  "type": "Feature",
  "properties": {
    "name": "Podenii Vechi",
    "country": "RO",
    "subdivision": "30",
    "timezone": "Europe/Bucharest"
  },
  "geometry": {
    "type": "Point",
    "coordinates": [
      26.11584,
      45.08939
    ]
  }
}