{
  "type": "Feature",
  "properties": {
    "name": "Potigrafu",
    "country": "RO",
    "subdivision": "30",
    "timezone": "Europe/Bucharest"
  },
  "geometry": {
    "type": "Point",
    "coordinates": [
      26.10014,
      44.78504
    ]
  }
}