{
  "type": "Feature",
  "properties": {
    "name": "Puchenii Moșneni",
    "country": "RO",
    "subdivision": "30",
    "timezone": "Europe/Bucharest"
  },
  "geometry": {
    "type": "Point",
    "coordinates": [
      26.08701,
      44.81213
    ]
  }
}