{
  "type": "Feature",
  "properties": {
    "name": "Râfov",
    "country": "RO",
    "subdivision": "30",
    "timezone": "Europe/Bucharest"
  },
  "geometry": {
    "type": "Point",
    "coordinates": [
      26.13333,
      44.86667
    ]
  }
}