{
  "type": "Feature",
  "properties": {
    "name": "Schiulești",
    "country": "RO",
    "subdivision": "30",
    "timezone": "Europe/Bucharest"
  },
  "geometry": {
    "type": "Point",
    "coordinates": [
      25.95403,
      45.28471
    ]
  }
}