{
  "type": "Feature",
  "properties": {
    "name": "Strejnicu",
    "country": "RO",
    "subdivision": "30",
    "timezone": "Europe/Bucharest"
  },
  "geometry": {
    "type": "Point",
    "coordinates": [
      25.95109,
      44.91676
    ]
  }
}