{
  "type": "Feature",
  "properties": {
    "name": "Tătărani",
    "country": "RO",
    "subdivision": "30",
    "timezone": "Europe/Bucharest"
  },
  "geometry": {
    "type": "Point",
    "coordinates": [
      26.03509,
      44.89763
    ]
  }
}