{
  "type": "Feature",
  "properties": {
    "name": "Tinosu",
    "country": "RO",
    "subdivision": "30",
    "timezone": "Europe/Bucharest"
  },
  "geometry": {
    "type": "Point",
    "coordinates": [
      26.01667,
      44.81667
    ]
  }
}