{
  "type": "Feature",
  "properties": {
    "name": "Trăisteni",
    "country": "RO",
    "subdivision": "30",
    "timezone": "Europe/Bucharest"
  },
  "geometry": {
    "type": "Point",
    "coordinates": [
      25.72767,
      45.33857
    ]
  }
}