{
  "type": "Feature",
  "properties": {
    "name": "Tufeni",
    "country": "RO",
    "subdivision": "30",
    "timezone": "Europe/Bucharest"
  },
  "geometry": {
    "type": "Point",
    "coordinates": [
      25.83976,
      45.0579
    ]
  }
}