{
  "type": "Feature",
  "properties": {
    "name": "Valea Cucului",
    "country": "RO",
    "subdivision": "30",
    "timezone": "Europe/Bucharest"
  },
  "geometry": {
    "type": "Point",
    "coordinates": [
      26.22793,
      45.06525
    ]
  }
}