{
  "type": "Feature",
  "properties": {
    "name": "Ardon",
    "country": "CH",
    "subdivision": "VS",
    "timezone": "Europe/Zurich"
  },
  "geometry": {
    "type": "Point",
    "coordinates": [
      7.26012,
      46.20951
    ]
  }
}