{
  "type": "Feature",
  "properties": {
    "name": "Evionnaz",
    "country": "CH",
    "subdivision": "VS",
    "timezone": "Europe/Zurich"
  },
  "geometry": {
    "type": "Point",
    "coordinates": [
      7.02232,
      46.18096
    ]
  }
}