{
  "type": "Feature",
  "properties": {
    "name": "Evolène",
    "country": "CH",
    "subdivision": "VS",
    "timezone": "Europe/Zurich"
  },
  "geometry": {
    "type": "Point",
    "coordinates": [
      7.49407,
      46.11422
    ]
  }
}