{
  "type": "Feature",
  "properties": {
    "name": "Leuk",
    "country": "CH",
    "subdivision": "VS",
    "timezone": "Europe/Zurich"
  },
  "geometry": {
    "type": "Point",
    "coordinates": [
      7.63412,
      46.31736
    ]
  }
}