{
  "type": "Feature",
  "properties": {
    "name": "Leytron",
    "country": "CH",
    "subdivision": "VS",
    "timezone": "Europe/Zurich"
  },
  "geometry": {
    "type": "Point",
    "coordinates": [
      7.2078,
      46.1866
    ]
  }
}