{
  "type": "Feature",
  "properties": {
    "name": "Naters",
    "country": "CH",
    "subdivision": "VS",
    "timezone": "Europe/Zurich"
  },
  "geometry": {
    "type": "Point",
    "coordinates": [
      7.98912,
      46.32536
    ]
  }
}