{
  "type": "Feature",
  "properties": {
    "name": "Vouvry",
    "country": "CH",
    "subdivision": "VS",
    "timezone": "Europe/Zurich"
  },
  "geometry": {
    "type": "Point",
    "coordinates": [
      6.8895,
      46.33746
    ]
  }
}