{
  "type": "Feature",
  "properties": {
    "name": "Lunglei",
    "country": "IN",
    "subdivision": "31",
    "timezone": "Asia/Kolkata"
  },
  "geometry": {
    "type": "Point",
    "coordinates": [
      92.74218,
      22.89247
    ]
  }
}