{
  "type": "Feature",
  "properties": {
    "name": "Gakem",
    "country": "NG",
    "subdivision": "22",
    "timezone": "Africa/Lagos"
  },
  "geometry": {
    "type": "Point",
    "coordinates": [
      8.9912,
      6.76963
    ]
  }
}