{
  "type": "Feature",
  "properties": {
    "name": "Tingo María",
    "country": "PE",
    "subdivision": "10",
    "timezone": "America/Lima"
  },
  "geometry": {
    "type": "Point",
    "coordinates": [
      -75.99574,
      -9.29532
    ]
  }
}