{
  "type": "Feature",
  "properties": {
    "name": "Ivano-Frankove",
    "country": "UA",
    "subdivision": "15",
    "timezone": "Europe/Kiev"
  },
  "geometry": {
    "type": "Point",
    "coordinates": [
      23.72913,
      49.91978
    ]
  }
}