{
  "type": "Feature",
  "properties": {
    "name": "Khodoriv",
    "country": "UA",
    "subdivision": "15",
    "timezone": "Europe/Kiev"
  },
  "geometry": {
    "type": "Point",
    "coordinates": [
      24.3113,
      49.40681
    ]
  }
}