{
  "type": "Feature",
  "properties": {
    "name": "Pidbuzh",
    "country": "UA",
    "subdivision": "15",
    "timezone": "Europe/Kiev"
  },
  "geometry": {
    "type": "Point",
    "coordinates": [
      23.25117,
      49.33194
    ]
  }
}