{
  "type": "Feature",
  "properties": {
    "name": "Potelych",
    "country": "UA",
    "subdivision": "15",
    "timezone": "Europe/Kiev"
  },
  "geometry": {
    "type": "Point",
    "coordinates": [
      23.54674,
      50.20804
    ]
  }
}