{
  "type": "Feature",
  "properties": {
    "name": "Ralivka",
    "country": "UA",
    "subdivision": "15",
    "timezone": "Europe/Kiev"
  },
  "geometry": {
    "type": "Point",
    "coordinates": [
      23.23739,
      49.49982
    ]
  }
}