{
  "type": "Feature",
  "properties": {
    "name": "Rodatychi",
    "country": "UA",
    "subdivision": "15",
    "timezone": "Europe/Kiev"
  },
  "geometry": {
    "type": "Point",
    "coordinates": [
      23.53336,
      49.79862
    ]
  }
}