{
  "type": "Feature",
  "properties": {
    "name": "Silets",
    "country": "UA",
    "subdivision": "15",
    "timezone": "Europe/Kiev"
  },
  "geometry": {
    "type": "Point",
    "coordinates": [
      24.20462,
      50.29712
    ]
  }
}