{
  "type": "Feature",
  "properties": {
    "name": "Suai",
    "country": "TL",
    "subdivision": "CO",
    "timezone": "Asia/Dili"
  },
  "geometry": {
    "type": "Point",
    "coordinates": [
      125.25648,
      -9.31286
    ]
  }
}