{
  "type": "Feature",
  "properties": {
    "name": "Gavrilovka Vtoraya",
    "country": "RU",
    "subdivision": "72",
    "timezone": "Europe/Moscow"
  },
  "geometry": {
    "type": "Point",
    "coordinates": [
      42.76633,
      52.87697
    ]
  }
}