{
  "type": "Feature",
  "properties": {
    "name": "Marvdasht",
    "country": "IR",
    "subdivision": "07",
    "timezone": "Asia/Tehran"
  },
  "geometry": {
    "type": "Point",
    "coordinates": [
      52.8025,
      29.8742
    ]
  }
}