{
  "type": "Feature",
  "properties": {
    "name": "Ţahţā",
    "country": "EG",
    "subdivision": "24",
    "timezone": "Africa/Cairo"
  },
  "geometry": {
    "type": "Point",
    "coordinates": [
      31.50198,
      26.76866
    ]
  }
}