{
  "type": "Feature",
  "properties": {
    "name": "Pombas",
    "country": "CV",
    "subdivision": "05",
    "timezone": "Atlantic/Cape_Verde"
  },
  "geometry": {
    "type": "Point",
    "coordinates": [
      -25.02007,
      17.15026
    ]
  }
}