{
  "type": "Feature",
  "properties": {
    "name": "Salinas",
    "country": "PR",
    "subdivision": "123",
    "timezone": "America/Puerto_Rico"
  },
  "geometry": {
    "type": "Point",
    "coordinates": [
      -66.29795,
      17.97747
    ]
  }
}