{
  "type": "Feature",
  "properties": {
    "name": "Bayat",
    "country": "TR",
    "subdivision": "03",
    "timezone": "Europe/Istanbul"
  },
  "geometry": {
    "type": "Point",
    "coordinates": [
      30.92472,
      38.98306
    ]
  }
}