{
  "type": "Feature",
  "properties": {
    "name": "Evciler",
    "country": "TR",
    "subdivision": "03",
    "timezone": "Europe/Istanbul"
  },
  "geometry": {
    "type": "Point",
    "coordinates": [
      29.88667,
      38.04139
    ]
  }
}