{
  "type": "Feature",
  "properties": {
    "name": "Kızılören",
    "country": "TR",
    "subdivision": "03",
    "timezone": "Europe/Istanbul"
  },
  "geometry": {
    "type": "Point",
    "coordinates": [
      30.15167,
      38.25806
    ]
  }
}