{
  "type": "Feature",
  "properties": {
    "name": "Klaeng",
    "country": "TH",
    "subdivision": "47",
    "timezone": "Asia/Bangkok"
  },
  "geometry": {
    "type": "Point",
    "coordinates": [
      101.64831,
      12.77972
    ]
  }
}