{
  "type": "Feature",
  "properties": {
    "name": "Sam Phran",
    "country": "TH",
    "subdivision": "53",
    "timezone": "Asia/Bangkok"
  },
  "geometry": {
    "type": "Point",
    "coordinates": [
      100.21526,
      13.72698
    ]
  }
}