{
  "type": "Feature",
  "properties": {
    "name": "Vĩnh Long",
    "country": "VN",
    "subdivision": "69",
    "timezone": "Asia/Ho_Chi_Minh"
  },
  "geometry": {
    "type": "Point",
    "coordinates": [
      105.9722,
      10.25369
    ]
  }
}