{
  "type": "Feature",
  "properties": {
    "name": "Barice",
    "country": "BA",
    "subdivision": "01",
    "timezone": "Europe/Sarajevo"
  },
  "geometry": {
    "type": "Point",
    "coordinates": [
      18.48069,
      44.54065
    ]
  }
}