{
  "type": "Feature",
  "properties": {
    "name": "Cazin",
    "country": "BA",
    "subdivision": "01",
    "timezone": "Europe/Sarajevo"
  },
  "geometry": {
    "type": "Point",
    "coordinates": [
      15.94306,
      44.96694
    ]
  }
}