{
  "type": "Feature",
  "properties": {
    "name": "Čitluk",
    "country": "BA",
    "subdivision": "01",
    "timezone": "Europe/Sarajevo"
  },
  "geometry": {
    "type": "Point",
    "coordinates": [
      17.70083,
      43.22861
    ]
  }
}