{
  "type": "Feature",
  "properties": {
    "name": "Drežnica",
    "country": "BA",
    "subdivision": "01",
    "timezone": "Europe/Sarajevo"
  },
  "geometry": {
    "type": "Point",
    "coordinates": [
      17.2812,
      43.52891
    ]
  }
}