{
  "type": "Feature",
  "properties": {
    "name": "Dubravica",
    "country": "BA",
    "subdivision": "01",
    "timezone": "Europe/Sarajevo"
  },
  "geometry": {
    "type": "Point",
    "coordinates": [
      18.11883,
      44.44131
    ]
  }
}