{
  "type": "Feature",
  "properties": {
    "name": "Dubrave Gornje",
    "country": "BA",
    "subdivision": "01",
    "timezone": "Europe/Sarajevo"
  },
  "geometry": {
    "type": "Point",
    "coordinates": [
      18.72685,
      44.47229
    ]
  }
}