{
  "type": "Feature",
  "properties": {
    "name": "Fojnica",
    "country": "BA",
    "subdivision": "01",
    "timezone": "Europe/Sarajevo"
  },
  "geometry": {
    "type": "Point",
    "coordinates": [
      17.90288,
      43.95952
    ]
  }
}