{
  "type": "Feature",
  "properties": {
    "name": "Kobilja Glava",
    "country": "BA",
    "subdivision": "01",
    "timezone": "Europe/Sarajevo"
  },
  "geometry": {
    "type": "Point",
    "coordinates": [
      18.38864,
      43.88188
    ]
  }
}