{
  "type": "Feature",
  "properties": {
    "name": "KoÄerin",
    "country": "BA",
    "subdivision": "01",
    "timezone": "Europe/Sarajevo"
  },
  "geometry": {
    "type": "Point",
    "coordinates": [
      17.48552,
      43.39005
    ]
  }
}