{
  "type": "Feature",
  "properties": {
    "name": "Konjic",
    "country": "BA",
    "subdivision": "01",
    "timezone": "Europe/Sarajevo"
  },
  "geometry": {
    "type": "Point",
    "coordinates": [
      17.96082,
      43.65126
    ]
  }
}