{
  "type": "Feature",
  "properties": {
    "name": "Orašac",
    "country": "BA",
    "subdivision": "01",
    "timezone": "Europe/Sarajevo"
  },
  "geometry": {
    "type": "Point",
    "coordinates": [
      16.07443,
      44.63039
    ]
  }
}