{
  "type": "Feature",
  "properties": {
    "name": "Polje-Bijela",
    "country": "BA",
    "subdivision": "01",
    "timezone": "Europe/Sarajevo"
  },
  "geometry": {
    "type": "Point",
    "coordinates": [
      17.97216,
      43.63299
    ]
  }
}