{
  "type": "Feature",
  "properties": {
    "name": "Sladna",
    "country": "BA",
    "subdivision": "01",
    "timezone": "Europe/Sarajevo"
  },
  "geometry": {
    "type": "Point",
    "coordinates": [
      18.42575,
      44.72897
    ]
  }
}