{
  "type": "Feature",
  "properties": {
    "name": "Srebrenik",
    "country": "BA",
    "subdivision": "01",
    "timezone": "Europe/Sarajevo"
  },
  "geometry": {
    "type": "Point",
    "coordinates": [
      18.48834,
      44.70819
    ]
  }
}