{
  "type": "Feature",
  "properties": {
    "name": "Stolac",
    "country": "BA",
    "subdivision": "01",
    "timezone": "Europe/Sarajevo"
  },
  "geometry": {
    "type": "Point",
    "coordinates": [
      17.95995,
      43.084
    ]
  }
}