{
  "type": "Feature",
  "properties": {
    "name": "Tešanj",
    "country": "BA",
    "subdivision": "01",
    "timezone": "Europe/Sarajevo"
  },
  "geometry": {
    "type": "Point",
    "coordinates": [
      17.98552,
      44.61191
    ]
  }
}