{
  "type": "Feature",
  "properties": {
    "name": "Velagići",
    "country": "BA",
    "subdivision": "01",
    "timezone": "Europe/Sarajevo"
  },
  "geometry": {
    "type": "Point",
    "coordinates": [
      16.73349,
      44.55618
    ]
  }
}