{
  "type": "Feature",
  "properties": {
    "name": "Zenica",
    "country": "BA",
    "subdivision": "01",
    "timezone": "Europe/Sarajevo"
  },
  "geometry": {
    "type": "Point",
    "coordinates": [
      17.90397,
      44.20169
    ]
  }
}