{
  "type": "Feature",
  "properties": {
    "name": "Aleksandrów Łódzki",
    "country": "PL",
    "subdivision": "74",
    "timezone": "Europe/Warsaw"
  },
  "geometry": {
    "type": "Point",
    "coordinates": [
      19.30384,
      51.81965
    ]
  }
}