{
  "type": "Feature",
  "properties": {
    "name": "Galewice",
    "country": "PL",
    "subdivision": "74",
    "timezone": "Europe/Warsaw"
  },
  "geometry": {
    "type": "Point",
    "coordinates": [
      18.25756,
      51.34471
    ]
  }
}