{
  "type": "Feature",
  "properties": {
    "name": "Gałków Mały",
    "country": "PL",
    "subdivision": "74",
    "timezone": "Europe/Warsaw"
  },
  "geometry": {
    "type": "Point",
    "coordinates": [
      19.71359,
      51.72554
    ]
  }
}