{
  "type": "Feature",
  "properties": {
    "name": "Kleszczów",
    "country": "PL",
    "subdivision": "74",
    "timezone": "Europe/Warsaw"
  },
  "geometry": {
    "type": "Point",
    "coordinates": [
      19.30418,
      51.22355
    ]
  }
}