{
  "type": "Feature",
  "properties": {
    "name": "Konstantynów Łódzki",
    "country": "PL",
    "subdivision": "74",
    "timezone": "Europe/Warsaw"
  },
  "geometry": {
    "type": "Point",
    "coordinates": [
      19.32564,
      51.74776
    ]
  }
}