{
  "type": "Feature",
  "properties": {
    "name": "Mokrsko",
    "country": "PL",
    "subdivision": "74",
    "timezone": "Europe/Warsaw"
  },
  "geometry": {
    "type": "Point",
    "coordinates": [
      18.48879,
      51.17897
    ]
  }
}