{
  "type": "Feature",
  "properties": {
    "name": "Przedbórz",
    "country": "PL",
    "subdivision": "74",
    "timezone": "Europe/Warsaw"
  },
  "geometry": {
    "type": "Point",
    "coordinates": [
      19.87384,
      51.08789
    ]
  }
}