{
  "type": "Feature",
  "properties": {
    "name": "Rokiciny-Kolonia",
    "country": "PL",
    "subdivision": "74",
    "timezone": "Europe/Warsaw"
  },
  "geometry": {
    "type": "Point",
    "coordinates": [
      19.78312,
      51.66468
    ]
  }
}