{
  "type": "Feature",
  "properties": {
    "name": "Stryków",
    "country": "PL",
    "subdivision": "74",
    "timezone": "Europe/Warsaw"
  },
  "geometry": {
    "type": "Point",
    "coordinates": [
      19.60536,
      51.90224
    ]
  }
}