{
  "type": "Feature",
  "properties": {
    "name": "Sulmierzyce",
    "country": "PL",
    "subdivision": "74",
    "timezone": "Europe/Warsaw"
  },
  "geometry": {
    "type": "Point",
    "coordinates": [
      19.19595,
      51.18456
    ]
  }
}