{
  "type": "Feature",
  "properties": {
    "name": "Ujazd",
    "country": "PL",
    "subdivision": "74",
    "timezone": "Europe/Warsaw"
  },
  "geometry": {
    "type": "Point",
    "coordinates": [
      19.92225,
      51.59781
    ]
  }
}