{
  "type": "Feature",
  "properties": {
    "name": "Zapolice",
    "country": "PL",
    "subdivision": "74",
    "timezone": "Europe/Warsaw"
  },
  "geometry": {
    "type": "Point",
    "coordinates": [
      18.88335,
      51.54319
    ]
  }
}