{
  "type": "Feature",
  "properties": {
    "name": "Zduńska Wola",
    "country": "PL",
    "subdivision": "74",
    "timezone": "Europe/Warsaw"
  },
  "geometry": {
    "type": "Point",
    "coordinates": [
      18.93974,
      51.59915
    ]
  }
}