{
  "type": "Feature",
  "properties": {
    "name": "Łęczyca",
    "country": "PL",
    "subdivision": "74",
    "timezone": "Europe/Warsaw"
  },
  "geometry": {
    "type": "Point",
    "coordinates": [
      19.19972,
      52.05959
    ]
  }
}