{
  "type": "Feature",
  "properties": {
    "name": "Łowicz",
    "country": "PL",
    "subdivision": "74",
    "timezone": "Europe/Warsaw"
  },
  "geometry": {
    "type": "Point",
    "coordinates": [
      19.94525,
      52.10714
    ]
  }
}