{
  "type": "Feature",
  "properties": {
    "name": "Ak-Suu",
    "country": "KG",
    "subdivision": "07",
    "timezone": "Asia/Bishkek"
  },
  "geometry": {
    "type": "Point",
    "coordinates": [
      78.52702,
      42.49948
    ]
  }
}