{
  "type": "Feature",
  "properties": {
    "name": "Kadzhi-Say",
    "country": "KG",
    "subdivision": "07",
    "timezone": "Asia/Bishkek"
  },
  "geometry": {
    "type": "Point",
    "coordinates": [
      77.17848,
      42.14107
    ]
  }
}