{
  "type": "Feature",
  "properties": {
    "name": "Lopandino",
    "country": "RU",
    "subdivision": "10",
    "timezone": "Europe/Moscow"
  },
  "geometry": {
    "type": "Point",
    "coordinates": [
      34.8163,
      52.4666
    ]
  }
}