{
  "type": "Feature",
  "properties": {
    "name": "Lyubokhna",
    "country": "RU",
    "subdivision": "10",
    "timezone": "Europe/Moscow"
  },
  "geometry": {
    "type": "Point",
    "coordinates": [
      34.38847,
      53.50332
    ]
  }
}