{
  "type": "Feature",
  "properties": {
    "name": "Novyy Ropsk",
    "country": "RU",
    "subdivision": "10",
    "timezone": "Europe/Moscow"
  },
  "geometry": {
    "type": "Point",
    "coordinates": [
      32.31206,
      52.29781
    ]
  }
}