{
  "type": "Feature",
  "properties": {
    "name": "Balatonkenese",
    "country": "HU",
    "subdivision": "23",
    "timezone": "Europe/Budapest"
  },
  "geometry": {
    "type": "Point",
    "coordinates": [
      18.10671,
      47.04019
    ]
  }
}