{
  "type": "Feature",
  "properties": {
    "name": "Sümeg",
    "country": "HU",
    "subdivision": "23",
    "timezone": "Europe/Budapest"
  },
  "geometry": {
    "type": "Point",
    "coordinates": [
      17.28209,
      46.97703
    ]
  }
}