{
  "type": "Feature",
  "properties": {
    "name": "Corminboeuf",
    "country": "CH",
    "subdivision": "FR",
    "timezone": "Europe/Zurich"
  },
  "geometry": {
    "type": "Point",
    "coordinates": [
      7.10535,
      46.81029
    ]
  }
}