{
  "type": "Feature",
  "properties": {
    "name": "Ecublens",
    "country": "CH",
    "subdivision": "FR",
    "timezone": "Europe/Zurich"
  },
  "geometry": {
    "type": "Point",
    "coordinates": [
      6.80895,
      46.60735
    ]
  }
}