{
  "type": "Feature",
  "properties": {
    "name": "La Roche",
    "country": "CH",
    "subdivision": "FR",
    "timezone": "Europe/Zurich"
  },
  "geometry": {
    "type": "Point",
    "coordinates": [
      7.13721,
      46.6962
    ]
  }
}