{
  "type": "Feature",
  "properties": {
    "name": "Murten/Morat",
    "country": "CH",
    "subdivision": "FR",
    "timezone": "Europe/Zurich"
  },
  "geometry": {
    "type": "Point",
    "coordinates": [
      7.11715,
      46.92827
    ]
  }
}