{
  "type": "Feature",
  "properties": {
    "name": "Cuscatancingo",
    "country": "SV",
    "subdivision": "10",
    "timezone": "America/El_Salvador"
  },
  "geometry": {
    "type": "Point",
    "coordinates": [
      -89.18161,
      13.72702
    ]
  }
}