{
  "type": "Feature",
  "properties": {
    "name": "Justo Daract",
    "country": "AR",
    "subdivision": "19",
    "timezone": "America/Argentina/San_Luis"
  },
  "geometry": {
    "type": "Point",
    "coordinates": [
      -65.18277,
      -33.8594
    ]
  }
}