{
  "type": "Feature",
  "properties": {
    "name": "La Toma",
    "country": "AR",
    "subdivision": "19",
    "timezone": "America/Argentina/San_Luis"
  },
  "geometry": {
    "type": "Point",
    "coordinates": [
      -65.62385,
      -33.05258
    ]
  }
}