{
  "type": "Feature",
  "properties": {
    "name": "Unión",
    "country": "AR",
    "subdivision": "19",
    "timezone": "America/Argentina/San_Luis"
  },
  "geometry": {
    "type": "Point",
    "coordinates": [
      -65.94602,
      -35.15282
    ]
  }
}