{
  "type": "Feature",
  "properties": {
    "name": "Vize",
    "country": "TR",
    "subdivision": "39",
    "timezone": "Europe/Istanbul"
  },
  "geometry": {
    "type": "Point",
    "coordinates": [
      27.76583,
      41.5725
    ]
  }
}