{
  "type": "Feature",
  "properties": {
    "name": "Yeşilhisar",
    "country": "TR",
    "subdivision": "38",
    "timezone": "Europe/Istanbul"
  },
  "geometry": {
    "type": "Point",
    "coordinates": [
      35.08873,
      38.35232
    ]
  }
}