{
  "type": "Feature",
  "properties": {
    "name": "Ban Sam Chuk",
    "country": "TH",
    "subdivision": "51",
    "timezone": "Asia/Bangkok"
  },
  "geometry": {
    "type": "Point",
    "coordinates": [
      100.09531,
      14.74219
    ]
  }
}