{
  "type": "Feature",
  "properties": {
    "name": "Langui",
    "country": "PE",
    "subdivision": "08",
    "timezone": "America/Lima"
  },
  "geometry": {
    "type": "Point",
    "coordinates": [
      -71.27306,
      -14.43194
    ]
  }
}