{
  "type": "Feature",
  "properties": {
    "name": "Lima Pampa",
    "country": "PE",
    "subdivision": "08",
    "timezone": "America/Lima"
  },
  "geometry": {
    "type": "Point",
    "coordinates": [
      -71.33664,
      -14.08976
    ]
  }
}