{
  "type": "Feature",
  "properties": {
    "name": "Tinta",
    "country": "PE",
    "subdivision": "08",
    "timezone": "America/Lima"
  },
  "geometry": {
    "type": "Point",
    "coordinates": [
      -71.40694,
      -14.145
    ]
  }
}