{
  "type": "Feature",
  "properties": {
    "name": "Tungasuca",
    "country": "PE",
    "subdivision": "08",
    "timezone": "America/Lima"
  },
  "geometry": {
    "type": "Point",
    "coordinates": [
      -71.47667,
      -14.16389
    ]
  }
}