{
  "type": "Feature",
  "properties": {
    "name": "Mecitözü",
    "country": "TR",
    "subdivision": "19",
    "timezone": "Europe/Istanbul"
  },
  "geometry": {
    "type": "Point",
    "coordinates": [
      35.29528,
      40.52
    ]
  }
}