{
  "type": "Feature",
  "properties": {
    "name": "Kakegawa",
    "country": "JP",
    "subdivision": "37",
    "timezone": "Asia/Tokyo"
  },
  "geometry": {
    "type": "Point",
    "coordinates": [
      138.01667,
      34.76667
    ]
  }
}