{
  "type": "Feature",
  "properties": {
    "name": "Kanaya",
    "country": "JP",
    "subdivision": "37",
    "timezone": "Asia/Tokyo"
  },
  "geometry": {
    "type": "Point",
    "coordinates": [
      138.12775,
      34.82022
    ]
  }
}