{
  "type": "Feature",
  "properties": {
    "name": "Prey Veng",
    "country": "KH",
    "subdivision": "14",
    "timezone": "Asia/Phnom_Penh"
  },
  "geometry": {
    "type": "Point",
    "coordinates": [
      105.32533,
      11.48682
    ]
  }
}