{
  "type": "Feature",
  "properties": {
    "name": "Remchi",
    "country": "DZ",
    "subdivision": "15",
    "timezone": "Africa/Algiers"
  },
  "geometry": {
    "type": "Point",
    "coordinates": [
      -1.43362,
      35.06196
    ]
  }
}