{
  "type": "Feature",
  "properties": {
    "name": "Sidi Senoussi سيدي سنوسي",
    "country": "DZ",
    "subdivision": "15",
    "timezone": "Africa/Algiers"
  },
  "geometry": {
    "type": "Point",
    "coordinates": [
      -1.09449,
      34.99691
    ]
  }
}