{
  "type": "Feature",
  "properties": {
    "name": "Affoltern/Oberdorf",
    "country": "CH",
    "subdivision": "ZH",
    "timezone": "Europe/Zurich"
  },
  "geometry": {
    "type": "Point",
    "coordinates": [
      8.45651,
      47.27852
    ]
  }
}