{
  "type": "Feature",
  "properties": {
    "name": "Affoltern/Sonnenberg",
    "country": "CH",
    "subdivision": "ZH",
    "timezone": "Europe/Zurich"
  },
  "geometry": {
    "type": "Point",
    "coordinates": [
      8.46008,
      47.28055
    ]
  }
}