{
  "type": "Feature",
  "properties": {
    "name": "Binzikon",
    "country": "CH",
    "subdivision": "ZH",
    "timezone": "Europe/Zurich"
  },
  "geometry": {
    "type": "Point",
    "coordinates": [
      8.75851,
      47.27632
    ]
  }
}