{
  "type": "Feature",
  "properties": {
    "name": "Dachsen",
    "country": "CH",
    "subdivision": "ZH",
    "timezone": "Europe/Zurich"
  },
  "geometry": {
    "type": "Point",
    "coordinates": [
      8.6179,
      47.66515
    ]
  }
}