{
  "type": "Feature",
  "properties": {
    "name": "Dällikon/Dällikon (Dorf)",
    "country": "CH",
    "subdivision": "ZH",
    "timezone": "Europe/Zurich"
  },
  "geometry": {
    "type": "Point",
    "coordinates": [
      8.43813,
      47.43983
    ]
  }
}