{
  "type": "Feature",
  "properties": {
    "name": "Dietikon/Almend",
    "country": "CH",
    "subdivision": "ZH",
    "timezone": "Europe/Zurich"
  },
  "geometry": {
    "type": "Point",
    "coordinates": [
      8.39168,
      47.40477
    ]
  }
}