{
  "type": "Feature",
  "properties": {
    "name": "Dietikon/Hofacker",
    "country": "CH",
    "subdivision": "ZH",
    "timezone": "Europe/Zurich"
  },
  "geometry": {
    "type": "Point",
    "coordinates": [
      8.41609,
      47.39718
    ]
  }
}