{
  "type": "Feature",
  "properties": {
    "name": "Dietlikon/Eichwiesen",
    "country": "CH",
    "subdivision": "ZH",
    "timezone": "Europe/Zurich"
  },
  "geometry": {
    "type": "Point",
    "coordinates": [
      8.62078,
      47.4191
    ]
  }
}