{
  "type": "Feature",
  "properties": {
    "name": "Elsau-Räterschen/Räterschen",
    "country": "CH",
    "subdivision": "ZH",
    "timezone": "Europe/Zurich"
  },
  "geometry": {
    "type": "Point",
    "coordinates": [
      8.796,
      47.49927
    ]
  }
}