{
  "type": "Feature",
  "properties": {
    "name": "Herrliberg",
    "country": "CH",
    "subdivision": "ZH",
    "timezone": "Europe/Zurich"
  },
  "geometry": {
    "type": "Point",
    "coordinates": [
      8.61464,
      47.29064
    ]
  }
}