{
  "type": "Feature",
  "properties": {
    "name": "Kilchberg",
    "country": "CH",
    "subdivision": "ZH",
    "timezone": "Europe/Zurich"
  },
  "geometry": {
    "type": "Point",
    "coordinates": [
      8.54548,
      47.32438
    ]
  }
}