{
  "type": "Feature",
  "properties": {
    "name": "Knonau",
    "country": "CH",
    "subdivision": "ZH",
    "timezone": "Europe/Zurich"
  },
  "geometry": {
    "type": "Point",
    "coordinates": [
      8.46197,
      47.2235
    ]
  }
}