{
  "type": "Feature",
  "properties": {
    "name": "Kollbrunn/Kollbrunn (Dorfkern)",
    "country": "CH",
    "subdivision": "ZH",
    "timezone": "Europe/Zurich"
  },
  "geometry": {
    "type": "Point",
    "coordinates": [
      8.77413,
      47.45748
    ]
  }
}