{
  "type": "Feature",
  "properties": {
    "name": "Nänikon",
    "country": "CH",
    "subdivision": "ZH",
    "timezone": "Europe/Zurich"
  },
  "geometry": {
    "type": "Point",
    "coordinates": [
      8.68894,
      47.36975
    ]
  }
}