{
  "type": "Feature",
  "properties": {
    "name": "Niederhasli",
    "country": "CH",
    "subdivision": "ZH",
    "timezone": "Europe/Zurich"
  },
  "geometry": {
    "type": "Point",
    "coordinates": [
      8.48576,
      47.48012
    ]
  }
}