{
  "type": "Feature",
  "properties": {
    "name": "Oberwinterthur (Kreis 2)/Zinzikon",
    "country": "CH",
    "subdivision": "ZH",
    "timezone": "Europe/Zurich"
  },
  "geometry": {
    "type": "Point",
    "coordinates": [
      8.7564,
      47.5195
    ]
  }
}