{
  "type": "Feature",
  "properties": {
    "name": "Oberglatt/Oberglatt (Dorfkern)",
    "country": "CH",
    "subdivision": "ZH",
    "timezone": "Europe/Zurich"
  },
  "geometry": {
    "type": "Point",
    "coordinates": [
      8.51929,
      47.47596
    ]
  }
}