{
  "type": "Feature",
  "properties": {
    "name": "Oberengstringen/Rauchacher",
    "country": "CH",
    "subdivision": "ZH",
    "timezone": "Europe/Zurich"
  },
  "geometry": {
    "type": "Point",
    "coordinates": [
      8.45627,
      47.40919
    ]
  }
}