{
  "type": "Feature",
  "properties": {
    "name": "Oberengstringen",
    "country": "CH",
    "subdivision": "ZH",
    "timezone": "Europe/Zurich"
  },
  "geometry": {
    "type": "Point",
    "coordinates": [
      8.46515,
      47.40841
    ]
  }
}