{
  "type": "Feature",
  "properties": {
    "name": "Obfelden",
    "country": "CH",
    "subdivision": "ZH",
    "timezone": "Europe/Zurich"
  },
  "geometry": {
    "type": "Point",
    "coordinates": [
      8.4215,
      47.26413
    ]
  }
}