{
  "type": "Feature",
  "properties": {
    "name": "Richterswil/Dorfkern",
    "country": "CH",
    "subdivision": "ZH",
    "timezone": "Europe/Zurich"
  },
  "geometry": {
    "type": "Point",
    "coordinates": [
      8.70607,
      47.20715
    ]
  }
}