{
  "type": "Feature",
  "properties": {
    "name": "Stadt Winterthur (Kreis 1)",
    "country": "CH",
    "subdivision": "ZH",
    "timezone": "Europe/Zurich"
  },
  "geometry": {
    "type": "Point",
    "coordinates": [
      8.71954,
      47.49494
    ]
  }
}