{
  "type": "Feature",
  "properties": {
    "name": "Thalwil/Nord",
    "country": "CH",
    "subdivision": "ZH",
    "timezone": "Europe/Zurich"
  },
  "geometry": {
    "type": "Point",
    "coordinates": [
      8.55634,
      47.29748
    ]
  }
}