{
  "type": "Feature",
  "properties": {
    "name": "Töss (Kreis 4)/Schlosstal",
    "country": "CH",
    "subdivision": "ZH",
    "timezone": "Europe/Zurich"
  },
  "geometry": {
    "type": "Point",
    "coordinates": [
      8.70223,
      47.49279
    ]
  }
}