{
  "type": "Feature",
  "properties": {
    "name": "Turbenthal",
    "country": "CH",
    "subdivision": "ZH",
    "timezone": "Europe/Zurich"
  },
  "geometry": {
    "type": "Point",
    "coordinates": [
      8.84629,
      47.43633
    ]
  }
}