{
  "type": "Feature",
  "properties": {
    "name": "Urdorf/Oberurdorf",
    "country": "CH",
    "subdivision": "ZH",
    "timezone": "Europe/Zurich"
  },
  "geometry": {
    "type": "Point",
    "coordinates": [
      8.42343,
      47.38072
    ]
  }
}