{
  "type": "Feature",
  "properties": {
    "name": "Uster",
    "country": "CH",
    "subdivision": "ZH",
    "timezone": "Europe/Zurich"
  },
  "geometry": {
    "type": "Point",
    "coordinates": [
      8.72091,
      47.34713
    ]
  }
}