{
  "type": "Feature",
  "properties": {
    "name": "Uster/Nossikon",
    "country": "CH",
    "subdivision": "ZH",
    "timezone": "Europe/Zurich"
  },
  "geometry": {
    "type": "Point",
    "coordinates": [
      8.72555,
      47.34088
    ]
  }
}