{
  "type": "Feature",
  "properties": {
    "name": "Veltheim (Kreis 5)/Blumenau",
    "country": "CH",
    "subdivision": "ZH",
    "timezone": "Europe/Zurich"
  },
  "geometry": {
    "type": "Point",
    "coordinates": [
      8.71563,
      47.50618
    ]
  }
}