{
  "type": "Feature",
  "properties": {
    "name": "Wädenswil/Leihof-Mühlebach",
    "country": "CH",
    "subdivision": "ZH",
    "timezone": "Europe/Zurich"
  },
  "geometry": {
    "type": "Point",
    "coordinates": [
      8.67149,
      47.22364
    ]
  }
}