{
  "type": "Feature",
  "properties": {
    "name": "Wädenswil/Eichweid",
    "country": "CH",
    "subdivision": "ZH",
    "timezone": "Europe/Zurich"
  },
  "geometry": {
    "type": "Point",
    "coordinates": [
      8.6744,
      47.21847
    ]
  }
}