{
  "type": "Feature",
  "properties": {
    "name": "Wallisellen/Rieden",
    "country": "CH",
    "subdivision": "ZH",
    "timezone": "Europe/Zurich"
  },
  "geometry": {
    "type": "Point",
    "coordinates": [
      8.60028,
      47.41738
    ]
  }
}