{
  "type": "Feature",
  "properties": {
    "name": "Weisslingen",
    "country": "CH",
    "subdivision": "ZH",
    "timezone": "Europe/Zurich"
  },
  "geometry": {
    "type": "Point",
    "coordinates": [
      8.76787,
      47.43063
    ]
  }
}