{
  "type": "Feature",
  "properties": {
    "name": "Wetzikon/Robenhausen",
    "country": "CH",
    "subdivision": "ZH",
    "timezone": "Europe/Zurich"
  },
  "geometry": {
    "type": "Point",
    "coordinates": [
      8.78762,
      47.33089
    ]
  }
}