{
  "type": "Feature",
  "properties": {
    "name": "Zumikon",
    "country": "CH",
    "subdivision": "ZH",
    "timezone": "Europe/Zurich"
  },
  "geometry": {
    "type": "Point",
    "coordinates": [
      8.62271,
      47.33158
    ]
  }
}