{
  "type": "Feature",
  "properties": {
    "name": "Zürich (Kreis 4)/Werd",
    "country": "CH",
    "subdivision": "ZH",
    "timezone": "Europe/Zurich"
  },
  "geometry": {
    "type": "Point",
    "coordinates": [
      8.52584,
      47.37178
    ]
  }
}