{
  "type": "Feature",
  "properties": {
    "name": "Zürich (Kreis 11)/Affoltern",
    "country": "CH",
    "subdivision": "ZH",
    "timezone": "Europe/Zurich"
  },
  "geometry": {
    "type": "Point",
    "coordinates": [
      8.5122,
      47.41814
    ]
  }
}