{
  "type": "Feature",
  "properties": {
    "name": "Zürich (Kreis 9)/Albisrieden",
    "country": "CH",
    "subdivision": "ZH",
    "timezone": "Europe/Zurich"
  },
  "geometry": {
    "type": "Point",
    "coordinates": [
      8.49007,
      47.37398
    ]
  }
}