{
  "type": "Feature",
  "properties": {
    "name": "Zürich (Kreis 12)/Schwamendingen-Mitte",
    "country": "CH",
    "subdivision": "ZH",
    "timezone": "Europe/Zurich"
  },
  "geometry": {
    "type": "Point",
    "coordinates": [
      8.57242,
      47.4063
    ]
  }
}