{
  "type": "Feature",
  "properties": {
    "name": "Zürich (Kreis 12)/Saatlen",
    "country": "CH",
    "subdivision": "ZH",
    "timezone": "Europe/Zurich"
  },
  "geometry": {
    "type": "Point",
    "coordinates": [
      8.5648,
      47.41127
    ]
  }
}