{
  "type": "Feature",
  "properties": {
    "name": "Zürich (Kreis 6)/Unterstrass",
    "country": "CH",
    "subdivision": "ZH",
    "timezone": "Europe/Zurich"
  },
  "geometry": {
    "type": "Point",
    "coordinates": [
      8.53721,
      47.3953
    ]
  }
}