{
  "type": "Feature",
  "properties": {
    "name": "Maizuru",
    "country": "JP",
    "subdivision": "22",
    "timezone": "Asia/Tokyo"
  },
  "geometry": {
    "type": "Point",
    "coordinates": [
      135.33333,
      35.45
    ]
  }
}