{
  "type": "Feature",
  "properties": {
    "name": "Mukō",
    "country": "JP",
    "subdivision": "22",
    "timezone": "Asia/Tokyo"
  },
  "geometry": {
    "type": "Point",
    "coordinates": [
      135.70415,
      34.96545
    ]
  }
}