{
  "type": "Feature",
  "properties": {
    "name": "Buitenpost",
    "country": "NL",
    "subdivision": "02",
    "timezone": "Europe/Amsterdam"
  },
  "geometry": {
    "type": "Point",
    "coordinates": [
      6.14483,
      53.25166
    ]
  }
}