{
  "type": "Feature",
  "properties": {
    "name": "Donkerbroek",
    "country": "NL",
    "subdivision": "02",
    "timezone": "Europe/Amsterdam"
  },
  "geometry": {
    "type": "Point",
    "coordinates": [
      6.23927,
      53.01734
    ]
  }
}