{
  "type": "Feature",
  "properties": {
    "name": "Ferwert",
    "country": "NL",
    "subdivision": "02",
    "timezone": "Europe/Amsterdam"
  },
  "geometry": {
    "type": "Point",
    "coordinates": [
      5.82533,
      53.33784
    ]
  }
}