{
  "type": "Feature",
  "properties": {
    "name": "Gorredijk",
    "country": "NL",
    "subdivision": "02",
    "timezone": "Europe/Amsterdam"
  },
  "geometry": {
    "type": "Point",
    "coordinates": [
      6.06402,
      53.00659
    ]
  }
}