{
  "type": "Feature",
  "properties": {
    "name": "Grou",
    "country": "NL",
    "subdivision": "02",
    "timezone": "Europe/Amsterdam"
  },
  "geometry": {
    "type": "Point",
    "coordinates": [
      5.83745,
      53.09456
    ]
  }
}