{
  "type": "Feature",
  "properties": {
    "name": "IJlst",
    "country": "NL",
    "subdivision": "02",
    "timezone": "Europe/Amsterdam"
  },
  "geometry": {
    "type": "Point",
    "coordinates": [
      5.62312,
      53.01009
    ]
  }
}