{
  "type": "Feature",
  "properties": {
    "name": "Marrum",
    "country": "NL",
    "subdivision": "02",
    "timezone": "Europe/Amsterdam"
  },
  "geometry": {
    "type": "Point",
    "coordinates": [
      5.80198,
      53.32277
    ]
  }
}