{
  "type": "Feature",
  "properties": {
    "name": "Opeinde",
    "country": "NL",
    "subdivision": "02",
    "timezone": "Europe/Amsterdam"
  },
  "geometry": {
    "type": "Point",
    "coordinates": [
      6.05656,
      53.1341
    ]
  }
}