{
  "type": "Feature",
  "properties": {
    "name": "Oranjewoud",
    "country": "NL",
    "subdivision": "02",
    "timezone": "Europe/Amsterdam"
  },
  "geometry": {
    "type": "Point",
    "coordinates": [
      5.95038,
      52.94579
    ]
  }
}