{
  "type": "Feature",
  "properties": {
    "name": "Sint Nicolaasga",
    "country": "NL",
    "subdivision": "02",
    "timezone": "Europe/Amsterdam"
  },
  "geometry": {
    "type": "Point",
    "coordinates": [
      5.74242,
      52.92293
    ]
  }
}