{
  "type": "Feature",
  "properties": {
    "name": "Sintjohannesga",
    "country": "NL",
    "subdivision": "02",
    "timezone": "Europe/Amsterdam"
  },
  "geometry": {
    "type": "Point",
    "coordinates": [
      5.85588,
      52.93157
    ]
  }
}