{
  "type": "Feature",
  "properties": {
    "name": "Stadsfenne",
    "country": "NL",
    "subdivision": "02",
    "timezone": "Europe/Amsterdam"
  },
  "geometry": {
    "type": "Point",
    "coordinates": [
      5.67844,
      53.03987
    ]
  }
}