{
  "type": "Feature",
  "properties": {
    "name": "Tijnje",
    "country": "NL",
    "subdivision": "02",
    "timezone": "Europe/Amsterdam"
  },
  "geometry": {
    "type": "Point",
    "coordinates": [
      5.99193,
      53.03058
    ]
  }
}