{
  "type": "Feature",
  "properties": {
    "name": "Tytsjerk",
    "country": "NL",
    "subdivision": "02",
    "timezone": "Europe/Amsterdam"
  },
  "geometry": {
    "type": "Point",
    "coordinates": [
      5.90961,
      53.21343
    ]
  }
}