{
  "type": "Feature",
  "properties": {
    "name": "West-Terschelling",
    "country": "NL",
    "subdivision": "02",
    "timezone": "Europe/Amsterdam"
  },
  "geometry": {
    "type": "Point",
    "coordinates": [
      5.21482,
      53.35911
    ]
  }
}