{
  "type": "Feature",
  "properties": {
    "name": "Kolonga",
    "country": "TO",
    "subdivision": "02",
    "timezone": "Pacific/Tongatapu"
  },
  "geometry": {
    "type": "Point",
    "coordinates": [
      -175.06667,
      -21.13333
    ]
  }
}