{
  "type": "Feature",
  "properties": {
    "name": "Nang Rong",
    "country": "TH",
    "subdivision": "28",
    "timezone": "Asia/Bangkok"
  },
  "geometry": {
    "type": "Point",
    "coordinates": [
      102.79138,
      14.6377
    ]
  }
}