{
  "type": "Feature",
  "properties": {
    "name": "Satuek",
    "country": "TH",
    "subdivision": "28",
    "timezone": "Asia/Bangkok"
  },
  "geometry": {
    "type": "Point",
    "coordinates": [
      103.29192,
      15.29703
    ]
  }
}