{
  "type": "Feature",
  "properties": {
    "name": "Mogadouro",
    "country": "PT",
    "subdivision": "05",
    "timezone": "Europe/Lisbon"
  },
  "geometry": {
    "type": "Point",
    "coordinates": [
      -6.71187,
      41.34034
    ]
  }
}