{
  "type": "Feature",
  "properties": {
    "name": "Torre de Moncorvo",
    "country": "PT",
    "subdivision": "05",
    "timezone": "Europe/Lisbon"
  },
  "geometry": {
    "type": "Point",
    "coordinates": [
      -7.05364,
      41.17454
    ]
  }
}