{
  "type": "Feature",
  "properties": {
    "name": "Addison",
    "country": "US",
    "subdivision": "VT",
    "timezone": "America/New_York"
  },
  "geometry": {
    "type": "Point",
    "coordinates": [
      -73.30262,
      44.08867
    ]
  }
}