{
  "type": "Feature",
  "properties": {
    "name": "Burlington",
    "country": "US",
    "subdivision": "VT",
    "timezone": "America/New_York"
  },
  "geometry": {
    "type": "Point",
    "coordinates": [
      -73.21207,
      44.47588
    ]
  }
}