{
  "type": "Feature",
  "properties": {
    "name": "Chelsea",
    "country": "US",
    "subdivision": "VT",
    "timezone": "America/New_York"
  },
  "geometry": {
    "type": "Point",
    "coordinates": [
      -72.4476,
      43.98979
    ]
  }
}