{
  "type": "Feature",
  "properties": {
    "name": "Hinesburg",
    "country": "US",
    "subdivision": "VT",
    "timezone": "America/New_York"
  },
  "geometry": {
    "type": "Point",
    "coordinates": [
      -73.11068,
      44.32922
    ]
  }
}