{
  "type": "Feature",
  "properties": {
    "name": "Lincoln",
    "country": "US",
    "subdivision": "VT",
    "timezone": "America/New_York"
  },
  "geometry": {
    "type": "Point",
    "coordinates": [
      -72.99706,
      44.10589
    ]
  }
}