{
  "type": "Feature",
  "properties": {
    "name": "Middlebury (village)",
    "country": "US",
    "subdivision": "VT",
    "timezone": "America/New_York"
  },
  "geometry": {
    "type": "Point",
    "coordinates": [
      -73.16937,
      44.01553
    ]
  }
}