{
  "type": "Feature",
  "properties": {
    "name": "Montgomery",
    "country": "US",
    "subdivision": "VT",
    "timezone": "America/New_York"
  },
  "geometry": {
    "type": "Point",
    "coordinates": [
      -72.63818,
      44.90255
    ]
  }
}