{
  "type": "Feature",
  "properties": {
    "name": "Morristown",
    "country": "US",
    "subdivision": "VT",
    "timezone": "America/New_York"
  },
  "geometry": {
    "type": "Point",
    "coordinates": [
      -72.62373,
      44.55727
    ]
  }
}