{
  "type": "Feature",
  "properties": {
    "name": "Rockingham",
    "country": "US",
    "subdivision": "VT",
    "timezone": "America/New_York"
  },
  "geometry": {
    "type": "Point",
    "coordinates": [
      -72.48898,
      43.18758
    ]
  }
}