{
  "type": "Feature",
  "properties": {
    "name": "Saint Albans",
    "country": "US",
    "subdivision": "VT",
    "timezone": "America/New_York"
  },
  "geometry": {
    "type": "Point",
    "coordinates": [
      -73.08319,
      44.81088
    ]
  }
}