{
  "type": "Feature",
  "properties": {
    "name": "Swanton",
    "country": "US",
    "subdivision": "VT",
    "timezone": "America/New_York"
  },
  "geometry": {
    "type": "Point",
    "coordinates": [
      -73.1243,
      44.9181
    ]
  }
}