{
  "type": "Feature",
  "properties": {
    "name": "West Rutland",
    "country": "US",
    "subdivision": "VT",
    "timezone": "America/New_York"
  },
  "geometry": {
    "type": "Point",
    "coordinates": [
      -73.04511,
      43.59312
    ]
  }
}