{
  "type": "Feature",
  "properties": {
    "name": "Longido",
    "country": "TZ",
    "subdivision": "26",
    "timezone": "Africa/Dar_es_Salaam"
  },
  "geometry": {
    "type": "Point",
    "coordinates": [
      36.69773,
      -2.73319
    ]
  }
}