{
  "type": "Feature",
  "properties": {
    "name": "Eggersriet",
    "country": "CH",
    "subdivision": "SG",
    "timezone": "Europe/Zurich"
  },
  "geometry": {
    "type": "Point",
    "coordinates": [
      9.46901,
      47.44202
    ]
  }
}