{
  "type": "Feature",
  "properties": {
    "name": "Goldingen",
    "country": "CH",
    "subdivision": "SG",
    "timezone": "Europe/Zurich"
  },
  "geometry": {
    "type": "Point",
    "coordinates": [
      8.96167,
      47.26477
    ]
  }
}