{
  "type": "Feature",
  "properties": {
    "name": "Gommiswald",
    "country": "CH",
    "subdivision": "SG",
    "timezone": "Europe/Zurich"
  },
  "geometry": {
    "type": "Point",
    "coordinates": [
      9.02355,
      47.23128
    ]
  }
}