{
  "type": "Feature",
  "properties": {
    "name": "Jona",
    "country": "CH",
    "subdivision": "SG",
    "timezone": "Europe/Zurich"
  },
  "geometry": {
    "type": "Point",
    "coordinates": [
      8.83884,
      47.22983
    ]
  }
}