{
  "type": "Feature",
  "properties": {
    "name": "Kirchberg",
    "country": "CH",
    "subdivision": "SG",
    "timezone": "Europe/Zurich"
  },
  "geometry": {
    "type": "Point",
    "coordinates": [
      9.0402,
      47.41159
    ]
  }
}