{
  "type": "Feature",
  "properties": {
    "name": "Rapperswil",
    "country": "CH",
    "subdivision": "SG",
    "timezone": "Europe/Zurich"
  },
  "geometry": {
    "type": "Point",
    "coordinates": [
      8.82228,
      47.22557
    ]
  }
}