{
  "type": "Feature",
  "properties": {
    "name": "Rheineck",
    "country": "CH",
    "subdivision": "SG",
    "timezone": "Europe/Zurich"
  },
  "geometry": {
    "type": "Point",
    "coordinates": [
      9.59028,
      47.4663
    ]
  }
}