{
  "type": "Feature",
  "properties": {
    "name": "Sankt Margrethen",
    "country": "CH",
    "subdivision": "SG",
    "timezone": "Europe/Zurich"
  },
  "geometry": {
    "type": "Point",
    "coordinates": [
      9.63741,
      47.45253
    ]
  }
}