{
  "type": "Feature",
  "properties": {
    "name": "Sankt Gallen",
    "country": "CH",
    "subdivision": "SG",
    "timezone": "Europe/Zurich"
  },
  "geometry": {
    "type": "Point",
    "coordinates": [
      9.37477,
      47.42391
    ]
  }
}