{
  "type": "Feature",
  "properties": {
    "name": "Walenstadt",
    "country": "CH",
    "subdivision": "SG",
    "timezone": "Europe/Zurich"
  },
  "geometry": {
    "type": "Point",
    "coordinates": [
      9.31194,
      47.12411
    ]
  }
}