{
  "type": "Feature",
  "properties": {
    "name": "Alaghsas",
    "country": "NE",
    "subdivision": "01",
    "timezone": "Africa/Niamey"
  },
  "geometry": {
    "type": "Point",
    "coordinates": [
      8.0168,
      17.0187
    ]
  }
}