{
  "type": "Feature",
  "properties": {
    "name": "Gorno Orizari",
    "country": "MK",
    "subdivision": "F1",
    "timezone": "Europe/Skopje"
  },
  "geometry": {
    "type": "Point",
    "coordinates": [
      21.73475,
      41.68583
    ]
  }
}