{
  "type": "Feature",
  "properties": {
    "name": "Daroot-Korgon",
    "country": "KG",
    "subdivision": "08",
    "timezone": "Asia/Bishkek"
  },
  "geometry": {
    "type": "Point",
    "coordinates": [
      72.20518,
      39.55274
    ]
  }
}