{
  "type": "Feature",
  "properties": {
    "name": "Koplik",
    "country": "AL",
    "subdivision": "49",
    "timezone": "Europe/Tirane"
  },
  "geometry": {
    "type": "Point",
    "coordinates": [
      19.43639,
      42.21361
    ]
  }
}