{
  "type": "Feature",
  "properties": {
    "name": "Les Geneveys-sur-Coffrane",
    "country": "CH",
    "subdivision": "NE",
    "timezone": "Europe/Zurich"
  },
  "geometry": {
    "type": "Point",
    "coordinates": [
      6.8513,
      47.01528
    ]
  }
}