{
  "type": "Feature",
  "properties": {
    "name": "Umm Al Quwain City",
    "country": "AE",
    "subdivision": "07",
    "timezone": "Asia/Dubai"
  },
  "geometry": {
    "type": "Point",
    "coordinates": [
      55.55517,
      25.56473
    ]
  }
}