{
  "type": "Feature",
  "properties": {
    "name": "Agulo",
    "country": "ES",
    "subdivision": "53",
    "timezone": "Atlantic/Canary"
  },
  "geometry": {
    "type": "Point",
    "coordinates": [
      -17.19678,
      28.18778
    ]
  }
}