{
  "type": "Feature",
  "properties": {
    "name": "Alajeró",
    "country": "ES",
    "subdivision": "53",
    "timezone": "Atlantic/Canary"
  },
  "geometry": {
    "type": "Point",
    "coordinates": [
      -17.24073,
      28.06205
    ]
  }
}