{
  "type": "Feature",
  "properties": {
    "name": "Antigua",
    "country": "ES",
    "subdivision": "53",
    "timezone": "Atlantic/Canary"
  },
  "geometry": {
    "type": "Point",
    "coordinates": [
      -14.01379,
      28.42307
    ]
  }
}