{
  "type": "Feature",
  "properties": {
    "name": "Arafo",
    "country": "ES",
    "subdivision": "53",
    "timezone": "Atlantic/Canary"
  },
  "geometry": {
    "type": "Point",
    "coordinates": [
      -16.42244,
      28.33971
    ]
  }
}