{
  "type": "Feature",
  "properties": {
    "name": "Costa Calma",
    "country": "ES",
    "subdivision": "53",
    "timezone": "Atlantic/Canary"
  },
  "geometry": {
    "type": "Point",
    "coordinates": [
      -14.22691,
      28.16155
    ]
  }
}