{
  "type": "Feature",
  "properties": {
    "name": "Firgas",
    "country": "ES",
    "subdivision": "53",
    "timezone": "Atlantic/Canary"
  },
  "geometry": {
    "type": "Point",
    "coordinates": [
      -15.56299,
      28.10711
    ]
  }
}