{
  "type": "Feature",
  "properties": {
    "name": "Guia",
    "country": "ES",
    "subdivision": "53",
    "timezone": "Atlantic/Canary"
  },
  "geometry": {
    "type": "Point",
    "coordinates": [
      -15.63294,
      28.13974
    ]
  }
}