{
  "type": "Feature",
  "properties": {
    "name": "Nazaret",
    "country": "ES",
    "subdivision": "53",
    "timezone": "Atlantic/Canary"
  },
  "geometry": {
    "type": "Point",
    "coordinates": [
      -13.56386,
      29.03818
    ]
  }
}