{
  "type": "Feature",
  "properties": {
    "name": "San Nicolás",
    "country": "ES",
    "subdivision": "53",
    "timezone": "Atlantic/Canary"
  },
  "geometry": {
    "type": "Point",
    "coordinates": [
      -15.78126,
      27.9891
    ]
  }
}