{
  "type": "Feature",
  "properties": {
    "name": "Tejeda",
    "country": "ES",
    "subdivision": "53",
    "timezone": "Atlantic/Canary"
  },
  "geometry": {
    "type": "Point",
    "coordinates": [
      -15.61543,
      27.99508
    ]
  }
}