{
  "type": "Feature",
  "properties": {
    "name": "Gia Nghĩa",
    "country": "VN",
    "subdivision": "91",
    "timezone": "Asia/Ho_Chi_Minh"
  },
  "geometry": {
    "type": "Point",
    "coordinates": [
      107.69074,
      12.00423
    ]
  }
}