{
  "type": "Feature",
  "properties": {
    "name": "Ambunti",
    "country": "PG",
    "subdivision": "11",
    "timezone": "Pacific/Port_Moresby"
  },
  "geometry": {
    "type": "Point",
    "coordinates": [
      142.81832,
      -4.21717
    ]
  }
}