{
  "type": "Feature",
  "properties": {
    "name": "Aiton",
    "country": "RO",
    "subdivision": "13",
    "timezone": "Europe/Bucharest"
  },
  "geometry": {
    "type": "Point",
    "coordinates": [
      23.73333,
      46.68333
    ]
  }
}