{
  "type": "Feature",
  "properties": {
    "name": "Borşa",
    "country": "RO",
    "subdivision": "13",
    "timezone": "Europe/Bucharest"
  },
  "geometry": {
    "type": "Point",
    "coordinates": [
      23.66667,
      46.93333
    ]
  }
}