{
  "type": "Feature",
  "properties": {
    "name": "Ciucea",
    "country": "RO",
    "subdivision": "13",
    "timezone": "Europe/Bucharest"
  },
  "geometry": {
    "type": "Point",
    "coordinates": [
      22.81667,
      46.95
    ]
  }
}