{
  "type": "Feature",
  "properties": {
    "name": "Iara",
    "country": "RO",
    "subdivision": "13",
    "timezone": "Europe/Bucharest"
  },
  "geometry": {
    "type": "Point",
    "coordinates": [
      23.51667,
      46.55
    ]
  }
}