{
  "type": "Feature",
  "properties": {
    "name": "Luncani",
    "country": "RO",
    "subdivision": "13",
    "timezone": "Europe/Bucharest"
  },
  "geometry": {
    "type": "Point",
    "coordinates": [
      23.95095,
      46.47274
    ]
  }
}