{
  "type": "Feature",
  "properties": {
    "name": "Mica",
    "country": "RO",
    "subdivision": "13",
    "timezone": "Europe/Bucharest"
  },
  "geometry": {
    "type": "Point",
    "coordinates": [
      23.93333,
      47.13333
    ]
  }
}