{
  "type": "Feature",
  "properties": {
    "name": "Panticeu",
    "country": "RO",
    "subdivision": "13",
    "timezone": "Europe/Bucharest"
  },
  "geometry": {
    "type": "Point",
    "coordinates": [
      23.56667,
      47.03333
    ]
  }
}