{
  "type": "Feature",
  "properties": {
    "name": "Recea Cristur",
    "country": "RO",
    "subdivision": "13",
    "timezone": "Europe/Bucharest"
  },
  "geometry": {
    "type": "Point",
    "coordinates": [
      23.53333,
      47.06667
    ]
  }
}