{
  "type": "Feature",
  "properties": {
    "name": "Suceagu",
    "country": "RO",
    "subdivision": "13",
    "timezone": "Europe/Bucharest"
  },
  "geometry": {
    "type": "Point",
    "coordinates": [
      23.46511,
      46.78432
    ]
  }
}