{
  "type": "Feature",
  "properties": {
    "name": "Tritenii de Sus",
    "country": "RO",
    "subdivision": "13",
    "timezone": "Europe/Bucharest"
  },
  "geometry": {
    "type": "Point",
    "coordinates": [
      23.99849,
      46.60544
    ]
  }
}