{
  "type": "Feature",
  "properties": {
    "name": "Pijao",
    "country": "CO",
    "subdivision": "23",
    "timezone": "America/Bogota"
  },
  "geometry": {
    "type": "Point",
    "coordinates": [
      -75.70463,
      4.3335
    ]
  }
}