{
  "type": "Feature",
  "properties": {
    "name": "Eskilstuna",
    "country": "SE",
    "subdivision": "18",
    "timezone": "Europe/Stockholm"
  },
  "geometry": {
    "type": "Point",
    "coordinates": [
      16.5077,
      59.36661
    ]
  }
}