{
  "type": "Feature",
  "properties": {
    "name": "Hällbybrunn",
    "country": "SE",
    "subdivision": "18",
    "timezone": "Europe/Stockholm"
  },
  "geometry": {
    "type": "Point",
    "coordinates": [
      16.42229,
      59.39152
    ]
  }
}