{
  "type": "Feature",
  "properties": {
    "name": "Nyköping",
    "country": "SE",
    "subdivision": "18",
    "timezone": "Europe/Stockholm"
  },
  "geometry": {
    "type": "Point",
    "coordinates": [
      17.00788,
      58.753
    ]
  }
}