{
  "type": "Feature",
  "properties": {
    "name": "Oxelösund",
    "country": "SE",
    "subdivision": "18",
    "timezone": "Europe/Stockholm"
  },
  "geometry": {
    "type": "Point",
    "coordinates": [
      17.10152,
      58.67057
    ]
  }
}