{
  "type": "Feature",
  "properties": {
    "name": "Torshälla",
    "country": "SE",
    "subdivision": "18",
    "timezone": "Europe/Stockholm"
  },
  "geometry": {
    "type": "Point",
    "coordinates": [
      16.46667,
      59.41667
    ]
  }
}