{
  "type": "Feature",
  "properties": {
    "name": "Vagnhärad",
    "country": "SE",
    "subdivision": "18",
    "timezone": "Europe/Stockholm"
  },
  "geometry": {
    "type": "Point",
    "coordinates": [
      17.48757,
      58.94587
    ]
  }
}