{
  "type": "Feature",
  "properties": {
    "name": "Adinkerke",
    "country": "BE",
    "subdivision": "VLG",
    "timezone": "Europe/Brussels"
  },
  "geometry": {
    "type": "Point",
    "coordinates": [
      2.59914,
      51.07409
    ]
  }
}