{
  "type": "Feature",
  "properties": {
    "name": "Alveringem",
    "country": "BE",
    "subdivision": "VLG",
    "timezone": "Europe/Brussels"
  },
  "geometry": {
    "type": "Point",
    "coordinates": [
      2.71117,
      51.01238
    ]
  }
}