{
  "type": "Feature",
  "properties": {
    "name": "Bazel",
    "country": "BE",
    "subdivision": "VLG",
    "timezone": "Europe/Brussels"
  },
  "geometry": {
    "type": "Point",
    "coordinates": [
      4.30129,
      51.14741
    ]
  }
}