{
  "type": "Feature",
  "properties": {
    "name": "Bellegem",
    "country": "BE",
    "subdivision": "VLG",
    "timezone": "Europe/Brussels"
  },
  "geometry": {
    "type": "Point",
    "coordinates": [
      3.27933,
      50.77686
    ]
  }
}