{
  "type": "Feature",
  "properties": {
    "name": "Blankenberge",
    "country": "BE",
    "subdivision": "VLG",
    "timezone": "Europe/Brussels"
  },
  "geometry": {
    "type": "Point",
    "coordinates": [
      3.13227,
      51.31306
    ]
  }
}