{
  "type": "Feature",
  "properties": {
    "name": "Bonheiden",
    "country": "BE",
    "subdivision": "VLG",
    "timezone": "Europe/Brussels"
  },
  "geometry": {
    "type": "Point",
    "coordinates": [
      4.54714,
      51.02261
    ]
  }
}