{
  "type": "Feature",
  "properties": {
    "name": "Boorsem",
    "country": "BE",
    "subdivision": "VLG",
    "timezone": "Europe/Brussels"
  },
  "geometry": {
    "type": "Point",
    "coordinates": [
      5.71898,
      50.94206
    ]
  }
}