{
  "type": "Feature",
  "properties": {
    "name": "Buggenhout",
    "country": "BE",
    "subdivision": "VLG",
    "timezone": "Europe/Brussels"
  },
  "geometry": {
    "type": "Point",
    "coordinates": [
      4.20173,
      51.0159
    ]
  }
}