{
  "type": "Feature",
  "properties": {
    "name": "Buizingen",
    "country": "BE",
    "subdivision": "VLG",
    "timezone": "Europe/Brussels"
  },
  "geometry": {
    "type": "Point",
    "coordinates": [
      4.25278,
      50.74227
    ]
  }
}