{
  "type": "Feature",
  "properties": {
    "name": "Damme",
    "country": "BE",
    "subdivision": "VLG",
    "timezone": "Europe/Brussels"
  },
  "geometry": {
    "type": "Point",
    "coordinates": [
      3.28144,
      51.25147
    ]
  }
}