{
  "type": "Feature",
  "properties": {
    "name": "De Haan",
    "country": "BE",
    "subdivision": "VLG",
    "timezone": "Europe/Brussels"
  },
  "geometry": {
    "type": "Point",
    "coordinates": [
      3.03446,
      51.27261
    ]
  }
}