{
  "type": "Feature",
  "properties": {
    "name": "Deerlijk",
    "country": "BE",
    "subdivision": "VLG",
    "timezone": "Europe/Brussels"
  },
  "geometry": {
    "type": "Point",
    "coordinates": [
      3.35416,
      50.85337
    ]
  }
}