{
  "type": "Feature",
  "properties": {
    "name": "Dendermonde",
    "country": "BE",
    "subdivision": "VLG",
    "timezone": "Europe/Brussels"
  },
  "geometry": {
    "type": "Point",
    "coordinates": [
      4.10106,
      51.02869
    ]
  }
}