{
  "type": "Feature",
  "properties": {
    "name": "Diksmuide",
    "country": "BE",
    "subdivision": "VLG",
    "timezone": "Europe/Brussels"
  },
  "geometry": {
    "type": "Point",
    "coordinates": [
      2.86384,
      51.03248
    ]
  }
}