{
  "type": "Feature",
  "properties": {
    "name": "Edegem",
    "country": "BE",
    "subdivision": "VLG",
    "timezone": "Europe/Brussels"
  },
  "geometry": {
    "type": "Point",
    "coordinates": [
      4.44504,
      51.15662
    ]
  }
}