{
  "type": "Feature",
  "properties": {
    "name": "Eernegem",
    "country": "BE",
    "subdivision": "VLG",
    "timezone": "Europe/Brussels"
  },
  "geometry": {
    "type": "Point",
    "coordinates": [
      3.02562,
      51.1326
    ]
  }
}