{
  "type": "Feature",
  "properties": {
    "name": "Erwetegem",
    "country": "BE",
    "subdivision": "VLG",
    "timezone": "Europe/Brussels"
  },
  "geometry": {
    "type": "Point",
    "coordinates": [
      3.81444,
      50.85547
    ]
  }
}