{
  "type": "Feature",
  "properties": {
    "name": "Esen",
    "country": "BE",
    "subdivision": "VLG",
    "timezone": "Europe/Brussels"
  },
  "geometry": {
    "type": "Point",
    "coordinates": [
      2.90189,
      51.0294
    ]
  }
}