{
  "type": "Feature",
  "properties": {
    "name": "Essene",
    "country": "BE",
    "subdivision": "VLG",
    "timezone": "Europe/Brussels"
  },
  "geometry": {
    "type": "Point",
    "coordinates": [
      4.13743,
      50.90163
    ]
  }
}