{
  "type": "Feature",
  "properties": {
    "name": "Glabbeek",
    "country": "BE",
    "subdivision": "VLG",
    "timezone": "Europe/Brussels"
  },
  "geometry": {
    "type": "Point",
    "coordinates": [
      4.95615,
      50.87267
    ]
  }
}