{
  "type": "Feature",
  "properties": {
    "name": "Goetsenhoven",
    "country": "BE",
    "subdivision": "VLG",
    "timezone": "Europe/Brussels"
  },
  "geometry": {
    "type": "Point",
    "coordinates": [
      4.95157,
      50.76882
    ]
  }
}