{
  "type": "Feature",
  "properties": {
    "name": "Grammene",
    "country": "BE",
    "subdivision": "VLG",
    "timezone": "Europe/Brussels"
  },
  "geometry": {
    "type": "Point",
    "coordinates": [
      3.46706,
      50.97779
    ]
  }
}