{
  "type": "Feature",
  "properties": {
    "name": "Haaltert",
    "country": "BE",
    "subdivision": "VLG",
    "timezone": "Europe/Brussels"
  },
  "geometry": {
    "type": "Point",
    "coordinates": [
      4.00093,
      50.90634
    ]
  }
}