{
  "type": "Feature",
  "properties": {
    "name": "Halen",
    "country": "BE",
    "subdivision": "VLG",
    "timezone": "Europe/Brussels"
  },
  "geometry": {
    "type": "Point",
    "coordinates": [
      5.11096,
      50.94837
    ]
  }
}