{
  "type": "Feature",
  "properties": {
    "name": "Hamont",
    "country": "BE",
    "subdivision": "VLG",
    "timezone": "Europe/Brussels"
  },
  "geometry": {
    "type": "Point",
    "coordinates": [
      5.54732,
      51.25332
    ]
  }
}