{
  "type": "Feature",
  "properties": {
    "name": "Heers",
    "country": "BE",
    "subdivision": "VLG",
    "timezone": "Europe/Brussels"
  },
  "geometry": {
    "type": "Point",
    "coordinates": [
      5.3021,
      50.75383
    ]
  }
}