{
  "type": "Feature",
  "properties": {
    "name": "Heist-op-den-Berg",
    "country": "BE",
    "subdivision": "VLG",
    "timezone": "Europe/Brussels"
  },
  "geometry": {
    "type": "Point",
    "coordinates": [
      4.72827,
      51.07537
    ]
  }
}