{
  "type": "Feature",
  "properties": {
    "name": "Helchteren",
    "country": "BE",
    "subdivision": "VLG",
    "timezone": "Europe/Brussels"
  },
  "geometry": {
    "type": "Point",
    "coordinates": [
      5.38244,
      51.05591
    ]
  }
}