{
  "type": "Feature",
  "properties": {
    "name": "Heldergem",
    "country": "BE",
    "subdivision": "VLG",
    "timezone": "Europe/Brussels"
  },
  "geometry": {
    "type": "Point",
    "coordinates": [
      3.95789,
      50.87799
    ]
  }
}