{
  "type": "Feature",
  "properties": {
    "name": "Herderen",
    "country": "BE",
    "subdivision": "VLG",
    "timezone": "Europe/Brussels"
  },
  "geometry": {
    "type": "Point",
    "coordinates": [
      5.5735,
      50.80734
    ]
  }
}