{
  "type": "Feature",
  "properties": {
    "name": "Herentals",
    "country": "BE",
    "subdivision": "VLG",
    "timezone": "Europe/Brussels"
  },
  "geometry": {
    "type": "Point",
    "coordinates": [
      4.83248,
      51.17655
    ]
  }
}