{
  "type": "Feature",
  "properties": {
    "name": "Herent",
    "country": "BE",
    "subdivision": "VLG",
    "timezone": "Europe/Brussels"
  },
  "geometry": {
    "type": "Point",
    "coordinates": [
      4.67056,
      50.90861
    ]
  }
}