{
  "type": "Feature",
  "properties": {
    "name": "Heule",
    "country": "BE",
    "subdivision": "VLG",
    "timezone": "Europe/Brussels"
  },
  "geometry": {
    "type": "Point",
    "coordinates": [
      3.23818,
      50.83752
    ]
  }
}