{
  "type": "Feature",
  "properties": {
    "name": "Heusden",
    "country": "BE",
    "subdivision": "VLG",
    "timezone": "Europe/Brussels"
  },
  "geometry": {
    "type": "Point",
    "coordinates": [
      5.28013,
      51.03664
    ]
  }
}