{
  "type": "Feature",
  "properties": {
    "name": "Hillegem",
    "country": "BE",
    "subdivision": "VLG",
    "timezone": "Europe/Brussels"
  },
  "geometry": {
    "type": "Point",
    "coordinates": [
      3.8531,
      50.89567
    ]
  }
}