{
  "type": "Feature",
  "properties": {
    "name": "Hoegaarden",
    "country": "BE",
    "subdivision": "VLG",
    "timezone": "Europe/Brussels"
  },
  "geometry": {
    "type": "Point",
    "coordinates": [
      4.88952,
      50.7756
    ]
  }
}