{
  "type": "Feature",
  "properties": {
    "name": "Hoeleden",
    "country": "BE",
    "subdivision": "VLG",
    "timezone": "Europe/Brussels"
  },
  "geometry": {
    "type": "Point",
    "coordinates": [
      4.98538,
      50.86662
    ]
  }
}