{
  "type": "Feature",
  "properties": {
    "name": "Hofstade",
    "country": "BE",
    "subdivision": "VLG",
    "timezone": "Europe/Brussels"
  },
  "geometry": {
    "type": "Point",
    "coordinates": [
      4.49229,
      50.99134
    ]
  }
}