{
  "type": "Feature",
  "properties": {
    "name": "Houthalen",
    "country": "BE",
    "subdivision": "VLG",
    "timezone": "Europe/Brussels"
  },
  "geometry": {
    "type": "Point",
    "coordinates": [
      5.37429,
      51.03427
    ]
  }
}