{
  "type": "Feature",
  "properties": {
    "name": "Hove",
    "country": "BE",
    "subdivision": "VLG",
    "timezone": "Europe/Brussels"
  },
  "geometry": {
    "type": "Point",
    "coordinates": [
      4.4707,
      51.15446
    ]
  }
}