{
  "type": "Feature",
  "properties": {
    "name": "Huise",
    "country": "BE",
    "subdivision": "VLG",
    "timezone": "Europe/Brussels"
  },
  "geometry": {
    "type": "Point",
    "coordinates": [
      3.59096,
      50.90059
    ]
  }
}