{
  "type": "Feature",
  "properties": {
    "name": "Huldenberg",
    "country": "BE",
    "subdivision": "VLG",
    "timezone": "Europe/Brussels"
  },
  "geometry": {
    "type": "Point",
    "coordinates": [
      4.5831,
      50.78939
    ]
  }
}