{
  "type": "Feature",
  "properties": {
    "name": "Iddergem",
    "country": "BE",
    "subdivision": "VLG",
    "timezone": "Europe/Brussels"
  },
  "geometry": {
    "type": "Point",
    "coordinates": [
      4.04434,
      50.87634
    ]
  }
}