{
  "type": "Feature",
  "properties": {
    "name": "Idegem",
    "country": "BE",
    "subdivision": "VLG",
    "timezone": "Europe/Brussels"
  },
  "geometry": {
    "type": "Point",
    "coordinates": [
      3.92595,
      50.80178
    ]
  }
}