{
  "type": "Feature",
  "properties": {
    "name": "Ingooigem",
    "country": "BE",
    "subdivision": "VLG",
    "timezone": "Europe/Brussels"
  },
  "geometry": {
    "type": "Point",
    "coordinates": [
      3.43373,
      50.82013
    ]
  }
}