{
  "type": "Feature",
  "properties": {
    "name": "Kanegem",
    "country": "BE",
    "subdivision": "VLG",
    "timezone": "Europe/Brussels"
  },
  "geometry": {
    "type": "Point",
    "coordinates": [
      3.40188,
      51.0129
    ]
  }
}