{
  "type": "Feature",
  "properties": {
    "name": "Kanne",
    "country": "BE",
    "subdivision": "VLG",
    "timezone": "Europe/Brussels"
  },
  "geometry": {
    "type": "Point",
    "coordinates": [
      5.66946,
      50.81331
    ]
  }
}