{
  "type": "Feature",
  "properties": {
    "name": "Kerkom",
    "country": "BE",
    "subdivision": "VLG",
    "timezone": "Europe/Brussels"
  },
  "geometry": {
    "type": "Point",
    "coordinates": [
      4.87422,
      50.85568
    ]
  }
}