{
  "type": "Feature",
  "properties": {
    "name": "Kessel",
    "country": "BE",
    "subdivision": "VLG",
    "timezone": "Europe/Brussels"
  },
  "geometry": {
    "type": "Point",
    "coordinates": [
      4.62962,
      51.13892
    ]
  }
}