{
  "type": "Feature",
  "properties": {
    "name": "Koningshooikt",
    "country": "BE",
    "subdivision": "VLG",
    "timezone": "Europe/Brussels"
  },
  "geometry": {
    "type": "Point",
    "coordinates": [
      4.60992,
      51.09607
    ]
  }
}