{
  "type": "Feature",
  "properties": {
    "name": "Kortrijk-Dutsel",
    "country": "BE",
    "subdivision": "VLG",
    "timezone": "Europe/Brussels"
  },
  "geometry": {
    "type": "Point",
    "coordinates": [
      4.80799,
      50.92676
    ]
  }
}