{
  "type": "Feature",
  "properties": {
    "name": "Laarne",
    "country": "BE",
    "subdivision": "VLG",
    "timezone": "Europe/Brussels"
  },
  "geometry": {
    "type": "Point",
    "coordinates": [
      3.85077,
      51.03078
    ]
  }
}