{
  "type": "Feature",
  "properties": {
    "name": "Lanaken",
    "country": "BE",
    "subdivision": "VLG",
    "timezone": "Europe/Brussels"
  },
  "geometry": {
    "type": "Point",
    "coordinates": [
      5.6468,
      50.89318
    ]
  }
}