{
  "type": "Feature",
  "properties": {
    "name": "Leke",
    "country": "BE",
    "subdivision": "VLG",
    "timezone": "Europe/Brussels"
  },
  "geometry": {
    "type": "Point",
    "coordinates": [
      2.89098,
      51.10022
    ]
  }
}