{
  "type": "Feature",
  "properties": {
    "name": "Leuven",
    "country": "BE",
    "subdivision": "VLG",
    "timezone": "Europe/Brussels"
  },
  "geometry": {
    "type": "Point",
    "coordinates": [
      4.70093,
      50.87959
    ]
  }
}