{
  "type": "Feature",
  "properties": {
    "name": "Lint",
    "country": "BE",
    "subdivision": "VLG",
    "timezone": "Europe/Brussels"
  },
  "geometry": {
    "type": "Point",
    "coordinates": [
      4.49669,
      51.12707
    ]
  }
}