{
  "type": "Feature",
  "properties": {
    "name": "Lippelo",
    "country": "BE",
    "subdivision": "VLG",
    "timezone": "Europe/Brussels"
  },
  "geometry": {
    "type": "Point",
    "coordinates": [
      4.259,
      51.04258
    ]
  }
}