{
  "type": "Feature",
  "properties": {
    "name": "Loonbeek",
    "country": "BE",
    "subdivision": "VLG",
    "timezone": "Europe/Brussels"
  },
  "geometry": {
    "type": "Point",
    "coordinates": [
      4.60971,
      50.80941
    ]
  }
}