{
  "type": "Feature",
  "properties": {
    "name": "Mariekerke",
    "country": "BE",
    "subdivision": "VLG",
    "timezone": "Europe/Brussels"
  },
  "geometry": {
    "type": "Point",
    "coordinates": [
      4.19249,
      51.06503
    ]
  }
}