{
  "type": "Feature",
  "properties": {
    "name": "Marke",
    "country": "BE",
    "subdivision": "VLG",
    "timezone": "Europe/Brussels"
  },
  "geometry": {
    "type": "Point",
    "coordinates": [
      3.23344,
      50.80678
    ]
  }
}