{
  "type": "Feature",
  "properties": {
    "name": "Mater",
    "country": "BE",
    "subdivision": "VLG",
    "timezone": "Europe/Brussels"
  },
  "geometry": {
    "type": "Point",
    "coordinates": [
      3.66258,
      50.84321
    ]
  }
}