{
  "type": "Feature",
  "properties": {
    "name": "Meerle",
    "country": "BE",
    "subdivision": "VLG",
    "timezone": "Europe/Brussels"
  },
  "geometry": {
    "type": "Point",
    "coordinates": [
      4.80316,
      51.47235
    ]
  }
}