{
  "type": "Feature",
  "properties": {
    "name": "Messelbroek",
    "country": "BE",
    "subdivision": "VLG",
    "timezone": "Europe/Brussels"
  },
  "geometry": {
    "type": "Point",
    "coordinates": [
      4.93664,
      50.9955
    ]
  }
}