{
  "type": "Feature",
  "properties": {
    "name": "Millen",
    "country": "BE",
    "subdivision": "VLG",
    "timezone": "Europe/Brussels"
  },
  "geometry": {
    "type": "Point",
    "coordinates": [
      5.55616,
      50.78619
    ]
  }
}