{
  "type": "Feature",
  "properties": {
    "name": "Moerkerke",
    "country": "BE",
    "subdivision": "VLG",
    "timezone": "Europe/Brussels"
  },
  "geometry": {
    "type": "Point",
    "coordinates": [
      3.34251,
      51.24547
    ]
  }
}