{
  "type": "Feature",
  "properties": {
    "name": "Molenbeersel",
    "country": "BE",
    "subdivision": "VLG",
    "timezone": "Europe/Brussels"
  },
  "geometry": {
    "type": "Point",
    "coordinates": [
      5.73761,
      51.17041
    ]
  }
}