{
  "type": "Feature",
  "properties": {
    "name": "Nederokkerzeel",
    "country": "BE",
    "subdivision": "VLG",
    "timezone": "Europe/Brussels"
  },
  "geometry": {
    "type": "Point",
    "coordinates": [
      4.56388,
      50.91943
    ]
  }
}