{
  "type": "Feature",
  "properties": {
    "name": "Nijlen",
    "country": "BE",
    "subdivision": "VLG",
    "timezone": "Europe/Brussels"
  },
  "geometry": {
    "type": "Point",
    "coordinates": [
      4.67008,
      51.16096
    ]
  }
}