{
  "type": "Feature",
  "properties": {
    "name": "Oevel",
    "country": "BE",
    "subdivision": "VLG",
    "timezone": "Europe/Brussels"
  },
  "geometry": {
    "type": "Point",
    "coordinates": [
      4.90471,
      51.13789
    ]
  }
}