{
  "type": "Feature",
  "properties": {
    "name": "Olmen",
    "country": "BE",
    "subdivision": "VLG",
    "timezone": "Europe/Brussels"
  },
  "geometry": {
    "type": "Point",
    "coordinates": [
      5.14999,
      51.14228
    ]
  }
}