{
  "type": "Feature",
  "properties": {
    "name": "Ophoven",
    "country": "BE",
    "subdivision": "VLG",
    "timezone": "Europe/Brussels"
  },
  "geometry": {
    "type": "Point",
    "coordinates": [
      5.80155,
      51.12571
    ]
  }
}