{
  "type": "Feature",
  "properties": {
    "name": "Outer",
    "country": "BE",
    "subdivision": "VLG",
    "timezone": "Europe/Brussels"
  },
  "geometry": {
    "type": "Point",
    "coordinates": [
      3.9987,
      50.84189
    ]
  }
}