{
  "type": "Feature",
  "properties": {
    "name": "Peutie",
    "country": "BE",
    "subdivision": "VLG",
    "timezone": "Europe/Brussels"
  },
  "geometry": {
    "type": "Point",
    "coordinates": [
      4.45187,
      50.92998
    ]
  }
}