{
  "type": "Feature",
  "properties": {
    "name": "Proven",
    "country": "BE",
    "subdivision": "VLG",
    "timezone": "Europe/Brussels"
  },
  "geometry": {
    "type": "Point",
    "coordinates": [
      2.65721,
      50.88976
    ]
  }
}