{
  "type": "Feature",
  "properties": {
    "name": "Pulderbos",
    "country": "BE",
    "subdivision": "VLG",
    "timezone": "Europe/Brussels"
  },
  "geometry": {
    "type": "Point",
    "coordinates": [
      4.69357,
      51.2171
    ]
  }
}