{
  "type": "Feature",
  "properties": {
    "name": "Ramsel",
    "country": "BE",
    "subdivision": "VLG",
    "timezone": "Europe/Brussels"
  },
  "geometry": {
    "type": "Point",
    "coordinates": [
      4.83242,
      51.0324
    ]
  }
}