{
  "type": "Feature",
  "properties": {
    "name": "Roesbrugge-Haringe",
    "country": "BE",
    "subdivision": "VLG",
    "timezone": "Europe/Brussels"
  },
  "geometry": {
    "type": "Point",
    "coordinates": [
      2.62538,
      50.9181
    ]
  }
}