{
  "type": "Feature",
  "properties": {
    "name": "Rollegem-Kapelle",
    "country": "BE",
    "subdivision": "VLG",
    "timezone": "Europe/Brussels"
  },
  "geometry": {
    "type": "Point",
    "coordinates": [
      3.14635,
      50.8687
    ]
  }
}