{
  "type": "Feature",
  "properties": {
    "name": "Ronse",
    "country": "BE",
    "subdivision": "VLG",
    "timezone": "Europe/Brussels"
  },
  "geometry": {
    "type": "Point",
    "coordinates": [
      3.6005,
      50.74574
    ]
  }
}