{
  "type": "Feature",
  "properties": {
    "name": "Rotselaar",
    "country": "BE",
    "subdivision": "VLG",
    "timezone": "Europe/Brussels"
  },
  "geometry": {
    "type": "Point",
    "coordinates": [
      4.71665,
      50.95302
    ]
  }
}