{
  "type": "Feature",
  "properties": {
    "name": "Scherpenheuvel",
    "country": "BE",
    "subdivision": "VLG",
    "timezone": "Europe/Brussels"
  },
  "geometry": {
    "type": "Point",
    "coordinates": [
      4.97552,
      50.98075
    ]
  }
}