{
  "type": "Feature",
  "properties": {
    "name": "Schellebelle",
    "country": "BE",
    "subdivision": "VLG",
    "timezone": "Europe/Brussels"
  },
  "geometry": {
    "type": "Point",
    "coordinates": [
      3.92843,
      51.01136
    ]
  }
}