{
  "type": "Feature",
  "properties": {
    "name": "Scheldewindeke",
    "country": "BE",
    "subdivision": "VLG",
    "timezone": "Europe/Brussels"
  },
  "geometry": {
    "type": "Point",
    "coordinates": [
      3.78663,
      50.93436
    ]
  }
}