{
  "type": "Feature",
  "properties": {
    "name": "Schelderode",
    "country": "BE",
    "subdivision": "VLG",
    "timezone": "Europe/Brussels"
  },
  "geometry": {
    "type": "Point",
    "coordinates": [
      3.7133,
      50.96922
    ]
  }
}