{
  "type": "Feature",
  "properties": {
    "name": "Schorisse",
    "country": "BE",
    "subdivision": "VLG",
    "timezone": "Europe/Brussels"
  },
  "geometry": {
    "type": "Point",
    "coordinates": [
      3.67632,
      50.80309
    ]
  }
}