{
  "type": "Feature",
  "properties": {
    "name": "Semmerzake",
    "country": "BE",
    "subdivision": "VLG",
    "timezone": "Europe/Brussels"
  },
  "geometry": {
    "type": "Point",
    "coordinates": [
      3.66318,
      50.94369
    ]
  }
}