{
  "type": "Feature",
  "properties": {
    "name": "Sint-Lambrechts-Herk",
    "country": "BE",
    "subdivision": "VLG",
    "timezone": "Europe/Brussels"
  },
  "geometry": {
    "type": "Point",
    "coordinates": [
      5.30786,
      50.89914
    ]
  }
}