{
  "type": "Feature",
  "properties": {
    "name": "Sint-Pieters-Voeren",
    "country": "BE",
    "subdivision": "VLG",
    "timezone": "Europe/Brussels"
  },
  "geometry": {
    "type": "Point",
    "coordinates": [
      5.82224,
      50.73863
    ]
  }
}