{
  "type": "Feature",
  "properties": {
    "name": "Smetlede",
    "country": "BE",
    "subdivision": "VLG",
    "timezone": "Europe/Brussels"
  },
  "geometry": {
    "type": "Point",
    "coordinates": [
      3.92796,
      50.9662
    ]
  }
}