{
  "type": "Feature",
  "properties": {
    "name": "Spalbeek",
    "country": "BE",
    "subdivision": "VLG",
    "timezone": "Europe/Brussels"
  },
  "geometry": {
    "type": "Point",
    "coordinates": [
      5.22391,
      50.94918
    ]
  }
}