{
  "type": "Feature",
  "properties": {
    "name": "Sterrebeek",
    "country": "BE",
    "subdivision": "VLG",
    "timezone": "Europe/Brussels"
  },
  "geometry": {
    "type": "Point",
    "coordinates": [
      4.49375,
      50.86171
    ]
  }
}