{
  "type": "Feature",
  "properties": {
    "name": "Strijpen",
    "country": "BE",
    "subdivision": "VLG",
    "timezone": "Europe/Brussels"
  },
  "geometry": {
    "type": "Point",
    "coordinates": [
      3.78797,
      50.86801
    ]
  }
}