{
  "type": "Feature",
  "properties": {
    "name": "Strombeek-Bever",
    "country": "BE",
    "subdivision": "VLG",
    "timezone": "Europe/Brussels"
  },
  "geometry": {
    "type": "Point",
    "coordinates": [
      4.35582,
      50.91039
    ]
  }
}