{
  "type": "Feature",
  "properties": {
    "name": "Testelt",
    "country": "BE",
    "subdivision": "VLG",
    "timezone": "Europe/Brussels"
  },
  "geometry": {
    "type": "Point",
    "coordinates": [
      4.95312,
      51.01084
    ]
  }
}