{
  "type": "Feature",
  "properties": {
    "name": "Tildonk",
    "country": "BE",
    "subdivision": "VLG",
    "timezone": "Europe/Brussels"
  },
  "geometry": {
    "type": "Point",
    "coordinates": [
      4.64481,
      50.94383
    ]
  }
}