{
  "type": "Feature",
  "properties": {
    "name": "Tongerlo",
    "country": "BE",
    "subdivision": "VLG",
    "timezone": "Europe/Brussels"
  },
  "geometry": {
    "type": "Point",
    "coordinates": [
      5.6609,
      51.12756
    ]
  }
}