{
  "type": "Feature",
  "properties": {
    "name": "Vlamertinge",
    "country": "BE",
    "subdivision": "VLG",
    "timezone": "Europe/Brussels"
  },
  "geometry": {
    "type": "Point",
    "coordinates": [
      2.82024,
      50.85485
    ]
  }
}