{
  "type": "Feature",
  "properties": {
    "name": "Wenduine",
    "country": "BE",
    "subdivision": "VLG",
    "timezone": "Europe/Brussels"
  },
  "geometry": {
    "type": "Point",
    "coordinates": [
      3.08213,
      51.2983
    ]
  }
}