{
  "type": "Feature",
  "properties": {
    "name": "Werchter",
    "country": "BE",
    "subdivision": "VLG",
    "timezone": "Europe/Brussels"
  },
  "geometry": {
    "type": "Point",
    "coordinates": [
      4.7012,
      50.97308
    ]
  }
}