{
  "type": "Feature",
  "properties": {
    "name": "Wijer",
    "country": "BE",
    "subdivision": "VLG",
    "timezone": "Europe/Brussels"
  },
  "geometry": {
    "type": "Point",
    "coordinates": [
      5.22446,
      50.89863
    ]
  }
}