{
  "type": "Feature",
  "properties": {
    "name": "Wijtschate",
    "country": "BE",
    "subdivision": "VLG",
    "timezone": "Europe/Brussels"
  },
  "geometry": {
    "type": "Point",
    "coordinates": [
      2.88369,
      50.78632
    ]
  }
}