{
  "type": "Feature",
  "properties": {
    "name": "Wondelgem",
    "country": "BE",
    "subdivision": "VLG",
    "timezone": "Europe/Brussels"
  },
  "geometry": {
    "type": "Point",
    "coordinates": [
      3.70909,
      51.08705
    ]
  }
}