{
  "type": "Feature",
  "properties": {
    "name": "Zaffelare",
    "country": "BE",
    "subdivision": "VLG",
    "timezone": "Europe/Brussels"
  },
  "geometry": {
    "type": "Point",
    "coordinates": [
      3.86357,
      51.13385
    ]
  }
}