{
  "type": "Feature",
  "properties": {
    "name": "Zelem",
    "country": "BE",
    "subdivision": "VLG",
    "timezone": "Europe/Brussels"
  },
  "geometry": {
    "type": "Point",
    "coordinates": [
      5.10687,
      50.97739
    ]
  }
}