{
  "type": "Feature",
  "properties": {
    "name": "Zonhoven",
    "country": "BE",
    "subdivision": "VLG",
    "timezone": "Europe/Brussels"
  },
  "geometry": {
    "type": "Point",
    "coordinates": [
      5.36819,
      50.99064
    ]
  }
}