{
  "type": "Feature",
  "properties": {
    "name": "Ashoknagar Kalyangarh",
    "country": "IN",
    "subdivision": "28",
    "timezone": "Asia/Kolkata"
  },
  "geometry": {
    "type": "Point",
    "coordinates": [
      88.63701,
      22.86416
    ]
  }
}