{
  "type": "Feature",
  "properties": {
    "name": "Bālurghāt",
    "country": "IN",
    "subdivision": "28",
    "timezone": "Asia/Kolkata"
  },
  "geometry": {
    "type": "Point",
    "coordinates": [
      88.77732,
      25.22099
    ]
  }
}