{
  "type": "Feature",
  "properties": {
    "name": "Bānsbāria",
    "country": "IN",
    "subdivision": "28",
    "timezone": "Asia/Kolkata"
  },
  "geometry": {
    "type": "Point",
    "coordinates": [
      88.40098,
      22.95387
    ]
  }
}