{
  "type": "Feature",
  "properties": {
    "name": "Baruipur",
    "country": "IN",
    "subdivision": "28",
    "timezone": "Asia/Kolkata"
  },
  "geometry": {
    "type": "Point",
    "coordinates": [
      88.4325,
      22.36544
    ]
  }
}