{
  "type": "Feature",
  "properties": {
    "name": "DÄrjiling",
    "country": "IN",
    "subdivision": "28",
    "timezone": "Asia/Kolkata"
  },
  "geometry": {
    "type": "Point",
    "coordinates": [
      88.26667,
      27.03333
    ]
  }
}