{
  "type": "Feature",
  "properties": {
    "name": "Diamond Harbour",
    "country": "IN",
    "subdivision": "28",
    "timezone": "Asia/Kolkata"
  },
  "geometry": {
    "type": "Point",
    "coordinates": [
      88.19047,
      22.19101
    ]
  }
}