{
  "type": "Feature",
  "properties": {
    "name": "GoyerkÄta",
    "country": "IN",
    "subdivision": "28",
    "timezone": "Asia/Kolkata"
  },
  "geometry": {
    "type": "Point",
    "coordinates": [
      89.02565,
      26.69984
    ]
  }
}