{
  "type": "Feature",
  "properties": {
    "name": "Gurdaha",
    "country": "IN",
    "subdivision": "28",
    "timezone": "Asia/Kolkata"
  },
  "geometry": {
    "type": "Point",
    "coordinates": [
      88.75944,
      22.73472
    ]
  }
}