{
  "type": "Feature",
  "properties": {
    "name": "Hāsimāra",
    "country": "IN",
    "subdivision": "28",
    "timezone": "Asia/Kolkata"
  },
  "geometry": {
    "type": "Point",
    "coordinates": [
      89.35385,
      26.7469
    ]
  }
}