{
  "type": "Feature",
  "properties": {
    "name": "JÄmuria",
    "country": "IN",
    "subdivision": "28",
    "timezone": "Asia/Kolkata"
  },
  "geometry": {
    "type": "Point",
    "coordinates": [
      87.07872,
      23.70468
    ]
  }
}