{
  "type": "Feature",
  "properties": {
    "name": "Jaynagar Majilpur",
    "country": "IN",
    "subdivision": "28",
    "timezone": "Asia/Kolkata"
  },
  "geometry": {
    "type": "Point",
    "coordinates": [
      88.41836,
      22.17449
    ]
  }
}