{
  "type": "Feature",
  "properties": {
    "name": "Kānchrāpāra",
    "country": "IN",
    "subdivision": "28",
    "timezone": "Asia/Kolkata"
  },
  "geometry": {
    "type": "Point",
    "coordinates": [
      88.42849,
      22.95998
    ]
  }
}