{
  "type": "Feature",
  "properties": {
    "name": "Kulti",
    "country": "IN",
    "subdivision": "28",
    "timezone": "Asia/Kolkata"
  },
  "geometry": {
    "type": "Point",
    "coordinates": [
      86.84372,
      23.73166
    ]
  }
}