{
  "type": "Feature",
  "properties": {
    "name": "Mirik",
    "country": "IN",
    "subdivision": "28",
    "timezone": "Asia/Kolkata"
  },
  "geometry": {
    "type": "Point",
    "coordinates": [
      88.19007,
      26.88817
    ]
  }
}