{
  "type": "Feature",
  "properties": {
    "name": "Murshidābād",
    "country": "IN",
    "subdivision": "28",
    "timezone": "Asia/Kolkata"
  },
  "geometry": {
    "type": "Point",
    "coordinates": [
      88.27171,
      24.1839
    ]
  }
}