{
  "type": "Feature",
  "properties": {
    "name": "Odlābāri",
    "country": "IN",
    "subdivision": "28",
    "timezone": "Asia/Kolkata"
  },
  "geometry": {
    "type": "Point",
    "coordinates": [
      88.62943,
      26.83644
    ]
  }
}