{
  "type": "Feature",
  "properties": {
    "name": "Raghunathpur",
    "country": "IN",
    "subdivision": "28",
    "timezone": "Asia/Kolkata"
  },
  "geometry": {
    "type": "Point",
    "coordinates": [
      86.6735,
      23.53878
    ]
  }
}