{
  "type": "Feature",
  "properties": {
    "name": "Sankarpur",
    "country": "IN",
    "subdivision": "28",
    "timezone": "Asia/Kolkata"
  },
  "geometry": {
    "type": "Point",
    "coordinates": [
      88.45126,
      22.84839
    ]
  }
}