{
  "type": "Feature",
  "properties": {
    "name": "Shyamnagar",
    "country": "IN",
    "subdivision": "28",
    "timezone": "Asia/Kolkata"
  },
  "geometry": {
    "type": "Point",
    "coordinates": [
      88.36667,
      22.83333
    ]
  }
}