{
  "type": "Feature",
  "properties": {
    "name": "Baardheere",
    "country": "SO",
    "subdivision": "06",
    "timezone": "Africa/Mogadishu"
  },
  "geometry": {
    "type": "Point",
    "coordinates": [
      42.27644,
      2.34464
    ]
  }
}