{
  "type": "Feature",
  "properties": {
    "name": "Garbahaarrey",
    "country": "SO",
    "subdivision": "06",
    "timezone": "Africa/Mogadishu"
  },
  "geometry": {
    "type": "Point",
    "coordinates": [
      42.22091,
      3.32892
    ]
  }
}