{
  "type": "Feature",
  "properties": {
    "name": "Andoain",
    "country": "ES",
    "subdivision": "59",
    "timezone": "Europe/Madrid"
  },
  "geometry": {
    "type": "Point",
    "coordinates": [
      -2.0253,
      43.21658
    ]
  }
}