{
  "type": "Feature",
  "properties": {
    "name": "Berriz",
    "country": "ES",
    "subdivision": "59",
    "timezone": "Europe/Madrid"
  },
  "geometry": {
    "type": "Point",
    "coordinates": [
      -2.56667,
      43.16667
    ]
  }
}