{
  "type": "Feature",
  "properties": {
    "name": "Gernika-Lumo",
    "country": "ES",
    "subdivision": "59",
    "timezone": "Europe/Madrid"
  },
  "geometry": {
    "type": "Point",
    "coordinates": [
      -2.68333,
      43.31667
    ]
  }
}