{
  "type": "Feature",
  "properties": {
    "name": "Idiazabal",
    "country": "ES",
    "subdivision": "59",
    "timezone": "Europe/Madrid"
  },
  "geometry": {
    "type": "Point",
    "coordinates": [
      -2.23356,
      43.01189
    ]
  }
}