{
  "type": "Feature",
  "properties": {
    "name": "Landa",
    "country": "ES",
    "subdivision": "59",
    "timezone": "Europe/Madrid"
  },
  "geometry": {
    "type": "Point",
    "coordinates": [
      -2.95,
      43.38333
    ]
  }
}