{
  "type": "Feature",
  "properties": {
    "name": "Lezama",
    "country": "ES",
    "subdivision": "59",
    "timezone": "Europe/Madrid"
  },
  "geometry": {
    "type": "Point",
    "coordinates": [
      -2.97257,
      43.02799
    ]
  }
}