{
  "type": "Feature",
  "properties": {
    "name": "Mungia",
    "country": "ES",
    "subdivision": "59",
    "timezone": "Europe/Madrid"
  },
  "geometry": {
    "type": "Point",
    "coordinates": [
      -2.84524,
      43.35461
    ]
  }
}