{
  "type": "Feature",
  "properties": {
    "name": "Mutriku",
    "country": "ES",
    "subdivision": "59",
    "timezone": "Europe/Madrid"
  },
  "geometry": {
    "type": "Point",
    "coordinates": [
      -2.38517,
      43.30643
    ]
  }
}