{
  "type": "Feature",
  "properties": {
    "name": "Oñati",
    "country": "ES",
    "subdivision": "59",
    "timezone": "Europe/Madrid"
  },
  "geometry": {
    "type": "Point",
    "coordinates": [
      -2.40997,
      43.03262
    ]
  }
}