{
  "type": "Feature",
  "properties": {
    "name": "Ortuella",
    "country": "ES",
    "subdivision": "59",
    "timezone": "Europe/Madrid"
  },
  "geometry": {
    "type": "Point",
    "coordinates": [
      -3.05617,
      43.31113
    ]
  }
}