{
  "type": "Feature",
  "properties": {
    "name": "Sopuerta",
    "country": "ES",
    "subdivision": "59",
    "timezone": "Europe/Madrid"
  },
  "geometry": {
    "type": "Point",
    "coordinates": [
      -3.15505,
      43.26239
    ]
  }
}