{
  "type": "Feature",
  "properties": {
    "name": "Usurbil",
    "country": "ES",
    "subdivision": "59",
    "timezone": "Europe/Madrid"
  },
  "geometry": {
    "type": "Point",
    "coordinates": [
      -2.04912,
      43.27164
    ]
  }
}