{
  "type": "Feature",
  "properties": {
    "name": "Zierbena",
    "country": "ES",
    "subdivision": "59",
    "timezone": "Europe/Madrid"
  },
  "geometry": {
    "type": "Point",
    "coordinates": [
      -3.08333,
      43.35
    ]
  }
}