{
  "type": "Feature",
  "properties": {
    "name": "Avanca",
    "country": "PT",
    "subdivision": "02",
    "timezone": "Europe/Lisbon"
  },
  "geometry": {
    "type": "Point",
    "coordinates": [
      -8.5722,
      40.80771
    ]
  }
}