{
  "type": "Feature",
  "properties": {
    "name": "Ílhavo",
    "country": "PT",
    "subdivision": "02",
    "timezone": "Europe/Lisbon"
  },
  "geometry": {
    "type": "Point",
    "coordinates": [
      -8.67021,
      40.60188
    ]
  }
}