{
  "type": "Feature",
  "properties": {
    "name": "Murtosa",
    "country": "PT",
    "subdivision": "02",
    "timezone": "Europe/Lisbon"
  },
  "geometry": {
    "type": "Point",
    "coordinates": [
      -8.6377,
      40.73695
    ]
  }
}