{
  "type": "Feature",
  "properties": {
    "name": "San Ġwann",
    "country": "MT",
    "subdivision": "48",
    "timezone": "Europe/Malta"
  },
  "geometry": {
    "type": "Point",
    "coordinates": [
      14.47611,
      35.90556
    ]
  }
}