{
  "type": "Feature",
  "properties": {
    "name": "Vieux Fort",
    "country": "LC",
    "subdivision": "10",
    "timezone": "America/St_Lucia"
  },
  "geometry": {
    "type": "Point",
    "coordinates": [
      -60.95,
      13.71667
    ]
  }
}