{
  "type": "Feature",
  "properties": {
    "name": "Shurugwi",
    "country": "ZW",
    "subdivision": "02",
    "timezone": "Africa/Harare"
  },
  "geometry": {
    "type": "Point",
    "coordinates": [
      30.00589,
      -19.67016
    ]
  }
}