{
  "type": "Feature",
  "properties": {
    "name": "Hamina",
    "country": "FI",
    "subdivision": "08",
    "timezone": "Europe/Helsinki"
  },
  "geometry": {
    "type": "Point",
    "coordinates": [
      27.19794,
      60.56974
    ]
  }
}