{
  "type": "Feature",
  "properties": {
    "name": "Adelheidsdorf",
    "country": "DE",
    "subdivision": "06",
    "timezone": "Europe/Berlin"
  },
  "geometry": {
    "type": "Point",
    "coordinates": [
      10.06039,
      52.56404
    ]
  }
}