{
  "type": "Feature",
  "properties": {
    "name": "Ahlden",
    "country": "DE",
    "subdivision": "06",
    "timezone": "Europe/Berlin"
  },
  "geometry": {
    "type": "Point",
    "coordinates": [
      9.55115,
      52.75968
    ]
  }
}