{
  "type": "Feature",
  "properties": {
    "name": "Algermissen",
    "country": "DE",
    "subdivision": "06",
    "timezone": "Europe/Berlin"
  },
  "geometry": {
    "type": "Point",
    "coordinates": [
      9.96915,
      52.25332
    ]
  }
}