{
  "type": "Feature",
  "properties": {
    "name": "Alt - Lehndorf",
    "country": "DE",
    "subdivision": "06",
    "timezone": "Europe/Berlin"
  },
  "geometry": {
    "type": "Point",
    "coordinates": [
      10.48035,
      52.26856
    ]
  }
}