{
  "type": "Feature",
  "properties": {
    "name": "Altenmedingen",
    "country": "DE",
    "subdivision": "06",
    "timezone": "Europe/Berlin"
  },
  "geometry": {
    "type": "Point",
    "coordinates": [
      10.60163,
      53.1305
    ]
  }
}