{
  "type": "Feature",
  "properties": {
    "name": "Bad Eilsen",
    "country": "DE",
    "subdivision": "06",
    "timezone": "Europe/Berlin"
  },
  "geometry": {
    "type": "Point",
    "coordinates": [
      9.09822,
      52.24215
    ]
  }
}