{
  "type": "Feature",
  "properties": {
    "name": "Bahrenborstel",
    "country": "DE",
    "subdivision": "06",
    "timezone": "Europe/Berlin"
  },
  "geometry": {
    "type": "Point",
    "coordinates": [
      8.80863,
      52.57009
    ]
  }
}