{
  "type": "Feature",
  "properties": {
    "name": "Bardowick",
    "country": "DE",
    "subdivision": "06",
    "timezone": "Europe/Berlin"
  },
  "geometry": {
    "type": "Point",
    "coordinates": [
      10.38811,
      53.29354
    ]
  }
}