{
  "type": "Feature",
  "properties": {
    "name": "Bergen an der Dumme",
    "country": "DE",
    "subdivision": "06",
    "timezone": "Europe/Berlin"
  },
  "geometry": {
    "type": "Point",
    "coordinates": [
      10.95629,
      52.89109
    ]
  }
}