{
  "type": "Feature",
  "properties": {
    "name": "Binnen",
    "country": "DE",
    "subdivision": "06",
    "timezone": "Europe/Berlin"
  },
  "geometry": {
    "type": "Point",
    "coordinates": [
      9.13333,
      52.61667
    ]
  }
}