{
  "type": "Feature",
  "properties": {
    "name": "Bissendorf",
    "country": "DE",
    "subdivision": "06",
    "timezone": "Europe/Berlin"
  },
  "geometry": {
    "type": "Point",
    "coordinates": [
      8.16667,
      52.23333
    ]
  }
}