{
  "type": "Feature",
  "properties": {
    "name": "Boffzen",
    "country": "DE",
    "subdivision": "06",
    "timezone": "Europe/Berlin"
  },
  "geometry": {
    "type": "Point",
    "coordinates": [
      9.39824,
      51.75065
    ]
  }
}