{
  "type": "Feature",
  "properties": {
    "name": "Borstel",
    "country": "DE",
    "subdivision": "06",
    "timezone": "Europe/Berlin"
  },
  "geometry": {
    "type": "Point",
    "coordinates": [
      8.96896,
      52.67034
    ]
  }
}