{
  "type": "Feature",
  "properties": {
    "name": "Börßum",
    "country": "DE",
    "subdivision": "06",
    "timezone": "Europe/Berlin"
  },
  "geometry": {
    "type": "Point",
    "coordinates": [
      10.58431,
      52.06921
    ]
  }
}