{
  "type": "Feature",
  "properties": {
    "name": "Bötersen",
    "country": "DE",
    "subdivision": "06",
    "timezone": "Europe/Berlin"
  },
  "geometry": {
    "type": "Point",
    "coordinates": [
      9.31667,
      53.13333
    ]
  }
}