{
  "type": "Feature",
  "properties": {
    "name": "Brüggen",
    "country": "DE",
    "subdivision": "06",
    "timezone": "Europe/Berlin"
  },
  "geometry": {
    "type": "Point",
    "coordinates": [
      9.7745,
      52.0425
    ]
  }
}