{
  "type": "Feature",
  "properties": {
    "name": "Burgdorf",
    "country": "DE",
    "subdivision": "06",
    "timezone": "Europe/Berlin"
  },
  "geometry": {
    "type": "Point",
    "coordinates": [
      10.0064,
      52.44628
    ]
  }
}