{
  "type": "Feature",
  "properties": {
    "name": "Cremlingen",
    "country": "DE",
    "subdivision": "06",
    "timezone": "Europe/Berlin"
  },
  "geometry": {
    "type": "Point",
    "coordinates": [
      10.65,
      52.25
    ]
  }
}