{
  "type": "Feature",
  "properties": {
    "name": "Danndorf",
    "country": "DE",
    "subdivision": "06",
    "timezone": "Europe/Berlin"
  },
  "geometry": {
    "type": "Point",
    "coordinates": [
      10.91286,
      52.42472
    ]
  }
}