{
  "type": "Feature",
  "properties": {
    "name": "Didderse",
    "country": "DE",
    "subdivision": "06",
    "timezone": "Europe/Berlin"
  },
  "geometry": {
    "type": "Point",
    "coordinates": [
      10.40294,
      52.38042
    ]
  }
}