{
  "type": "Feature",
  "properties": {
    "name": "Diekholzen",
    "country": "DE",
    "subdivision": "06",
    "timezone": "Europe/Berlin"
  },
  "geometry": {
    "type": "Point",
    "coordinates": [
      9.91945,
      52.09617
    ]
  }
}