{
  "type": "Feature",
  "properties": {
    "name": "Dissen",
    "country": "DE",
    "subdivision": "06",
    "timezone": "Europe/Berlin"
  },
  "geometry": {
    "type": "Point",
    "coordinates": [
      8.19956,
      52.11591
    ]
  }
}