{
  "type": "Feature",
  "properties": {
    "name": "Dohren",
    "country": "DE",
    "subdivision": "06",
    "timezone": "Europe/Berlin"
  },
  "geometry": {
    "type": "Point",
    "coordinates": [
      7.58333,
      52.65
    ]
  }
}