{
  "type": "Feature",
  "properties": {
    "name": "Drangstedt",
    "country": "DE",
    "subdivision": "06",
    "timezone": "Europe/Berlin"
  },
  "geometry": {
    "type": "Point",
    "coordinates": [
      8.75576,
      53.61359
    ]
  }
}