{
  "type": "Feature",
  "properties": {
    "name": "Eimen",
    "country": "DE",
    "subdivision": "06",
    "timezone": "Europe/Berlin"
  },
  "geometry": {
    "type": "Point",
    "coordinates": [
      9.78333,
      51.88333
    ]
  }
}