{
  "type": "Feature",
  "properties": {
    "name": "Eystrup",
    "country": "DE",
    "subdivision": "06",
    "timezone": "Europe/Berlin"
  },
  "geometry": {
    "type": "Point",
    "coordinates": [
      9.21315,
      52.77935
    ]
  }
}