{
  "type": "Feature",
  "properties": {
    "name": "Garstedt",
    "country": "DE",
    "subdivision": "06",
    "timezone": "Europe/Berlin"
  },
  "geometry": {
    "type": "Point",
    "coordinates": [
      10.16137,
      53.28467
    ]
  }
}