{
  "type": "Feature",
  "properties": {
    "name": "Grasberg",
    "country": "DE",
    "subdivision": "06",
    "timezone": "Europe/Berlin"
  },
  "geometry": {
    "type": "Point",
    "coordinates": [
      8.98333,
      53.18333
    ]
  }
}