{
  "type": "Feature",
  "properties": {
    "name": "Groß Oesingen",
    "country": "DE",
    "subdivision": "06",
    "timezone": "Europe/Berlin"
  },
  "geometry": {
    "type": "Point",
    "coordinates": [
      10.46366,
      52.64761
    ]
  }
}