{
  "type": "Feature",
  "properties": {
    "name": "Harpstedt",
    "country": "DE",
    "subdivision": "06",
    "timezone": "Europe/Berlin"
  },
  "geometry": {
    "type": "Point",
    "coordinates": [
      8.58962,
      52.90942
    ]
  }
}