{
  "type": "Feature",
  "properties": {
    "name": "Harsefeld",
    "country": "DE",
    "subdivision": "06",
    "timezone": "Europe/Berlin"
  },
  "geometry": {
    "type": "Point",
    "coordinates": [
      9.50297,
      53.45399
    ]
  }
}