{
  "type": "Feature",
  "properties": {
    "name": "Haselünne",
    "country": "DE",
    "subdivision": "06",
    "timezone": "Europe/Berlin"
  },
  "geometry": {
    "type": "Point",
    "coordinates": [
      7.4846,
      52.67412
    ]
  }
}