{
  "type": "Feature",
  "properties": {
    "name": "Hatten",
    "country": "DE",
    "subdivision": "06",
    "timezone": "Europe/Berlin"
  },
  "geometry": {
    "type": "Point",
    "coordinates": [
      8.38333,
      53.05
    ]
  }
}