{
  "type": "Feature",
  "properties": {
    "name": "Heeßen",
    "country": "DE",
    "subdivision": "06",
    "timezone": "Europe/Berlin"
  },
  "geometry": {
    "type": "Point",
    "coordinates": [
      9.09642,
      52.23211
    ]
  }
}