{
  "type": "Feature",
  "properties": {
    "name": "Holzminden",
    "country": "DE",
    "subdivision": "06",
    "timezone": "Europe/Berlin"
  },
  "geometry": {
    "type": "Point",
    "coordinates": [
      9.4455,
      51.82798
    ]
  }
}