{
  "type": "Feature",
  "properties": {
    "name": "Hondelage",
    "country": "DE",
    "subdivision": "06",
    "timezone": "Europe/Berlin"
  },
  "geometry": {
    "type": "Point",
    "coordinates": [
      10.60567,
      52.31444
    ]
  }
}