{
  "type": "Feature",
  "properties": {
    "name": "Kirchbrak",
    "country": "DE",
    "subdivision": "06",
    "timezone": "Europe/Berlin"
  },
  "geometry": {
    "type": "Point",
    "coordinates": [
      9.5751,
      51.96585
    ]
  }
}