{
  "type": "Feature",
  "properties": {
    "name": "Langenhagen",
    "country": "DE",
    "subdivision": "06",
    "timezone": "Europe/Berlin"
  },
  "geometry": {
    "type": "Point",
    "coordinates": [
      9.73741,
      52.44758
    ]
  }
}