{
  "type": "Feature",
  "properties": {
    "name": "Lehrte",
    "country": "DE",
    "subdivision": "06",
    "timezone": "Europe/Berlin"
  },
  "geometry": {
    "type": "Point",
    "coordinates": [
      9.97919,
      52.37193
    ]
  }
}