{
  "type": "Feature",
  "properties": {
    "name": "Lintig",
    "country": "DE",
    "subdivision": "06",
    "timezone": "Europe/Berlin"
  },
  "geometry": {
    "type": "Point",
    "coordinates": [
      8.87876,
      53.60341
    ]
  }
}