{
  "type": "Feature",
  "properties": {
    "name": "Lohne",
    "country": "DE",
    "subdivision": "06",
    "timezone": "Europe/Berlin"
  },
  "geometry": {
    "type": "Point",
    "coordinates": [
      8.2375,
      52.66625
    ]
  }
}