{
  "type": "Feature",
  "properties": {
    "name": "Lorup",
    "country": "DE",
    "subdivision": "06",
    "timezone": "Europe/Berlin"
  },
  "geometry": {
    "type": "Point",
    "coordinates": [
      7.64339,
      52.92495
    ]
  }
}