{
  "type": "Feature",
  "properties": {
    "name": "Lutter am Barenberge",
    "country": "DE",
    "subdivision": "06",
    "timezone": "Europe/Berlin"
  },
  "geometry": {
    "type": "Point",
    "coordinates": [
      10.2693,
      51.98943
    ]
  }
}