{
  "type": "Feature",
  "properties": {
    "name": "Meerdorf",
    "country": "DE",
    "subdivision": "06",
    "timezone": "Europe/Berlin"
  },
  "geometry": {
    "type": "Point",
    "coordinates": [
      10.31745,
      52.34583
    ]
  }
}