{
  "type": "Feature",
  "properties": {
    "name": "Melle",
    "country": "DE",
    "subdivision": "06",
    "timezone": "Europe/Berlin"
  },
  "geometry": {
    "type": "Point",
    "coordinates": [
      8.33826,
      52.20197
    ]
  }
}