{
  "type": "Feature",
  "properties": {
    "name": "Molbergen",
    "country": "DE",
    "subdivision": "06",
    "timezone": "Europe/Berlin"
  },
  "geometry": {
    "type": "Point",
    "coordinates": [
      7.92548,
      52.85805
    ]
  }
}