{
  "type": "Feature",
  "properties": {
    "name": "Nahrendorf",
    "country": "DE",
    "subdivision": "06",
    "timezone": "Europe/Berlin"
  },
  "geometry": {
    "type": "Point",
    "coordinates": [
      10.81381,
      53.17389
    ]
  }
}