{
  "type": "Feature",
  "properties": {
    "name": "Neuenkirchen",
    "country": "DE",
    "subdivision": "06",
    "timezone": "Europe/Berlin"
  },
  "geometry": {
    "type": "Point",
    "coordinates": [
      8.52665,
      53.23173
    ]
  }
}