{
  "type": "Feature",
  "properties": {
    "name": "Neues Hochschulviertel",
    "country": "DE",
    "subdivision": "06",
    "timezone": "Europe/Berlin"
  },
  "geometry": {
    "type": "Point",
    "coordinates": [
      10.5435,
      52.2812
    ]
  }
}