{
  "type": "Feature",
  "properties": {
    "name": "Nienstädt",
    "country": "DE",
    "subdivision": "06",
    "timezone": "Europe/Berlin"
  },
  "geometry": {
    "type": "Point",
    "coordinates": [
      9.1644,
      52.29242
    ]
  }
}