{
  "type": "Feature",
  "properties": {
    "name": "Nortrup",
    "country": "DE",
    "subdivision": "06",
    "timezone": "Europe/Berlin"
  },
  "geometry": {
    "type": "Point",
    "coordinates": [
      7.86072,
      52.61503
    ]
  }
}