{
  "type": "Feature",
  "properties": {
    "name": "Otterndorf",
    "country": "DE",
    "subdivision": "06",
    "timezone": "Europe/Berlin"
  },
  "geometry": {
    "type": "Point",
    "coordinates": [
      8.90068,
      53.80908
    ]
  }
}