{
  "type": "Feature",
  "properties": {
    "name": "Oyten",
    "country": "DE",
    "subdivision": "06",
    "timezone": "Europe/Berlin"
  },
  "geometry": {
    "type": "Point",
    "coordinates": [
      9.01667,
      53.05
    ]
  }
}