{
  "type": "Feature",
  "properties": {
    "name": "Petritor - West",
    "country": "DE",
    "subdivision": "06",
    "timezone": "Europe/Berlin"
  },
  "geometry": {
    "type": "Point",
    "coordinates": [
      10.49382,
      52.26609
    ]
  }
}