{
  "type": "Feature",
  "properties": {
    "name": "Pollhagen",
    "country": "DE",
    "subdivision": "06",
    "timezone": "Europe/Berlin"
  },
  "geometry": {
    "type": "Point",
    "coordinates": [
      9.18813,
      52.38529
    ]
  }
}