{
  "type": "Feature",
  "properties": {
    "name": "Querum -  Wabenkamp",
    "country": "DE",
    "subdivision": "06",
    "timezone": "Europe/Berlin"
  },
  "geometry": {
    "type": "Point",
    "coordinates": [
      10.56841,
      52.29462
    ]
  }
}