{
  "type": "Feature",
  "properties": {
    "name": "Raddestorf",
    "country": "DE",
    "subdivision": "06",
    "timezone": "Europe/Berlin"
  },
  "geometry": {
    "type": "Point",
    "coordinates": [
      8.96667,
      52.45
    ]
  }
}