{
  "type": "Feature",
  "properties": {
    "name": "Rethem",
    "country": "DE",
    "subdivision": "06",
    "timezone": "Europe/Berlin"
  },
  "geometry": {
    "type": "Point",
    "coordinates": [
      9.37862,
      52.78621
    ]
  }
}