{
  "type": "Feature",
  "properties": {
    "name": "Rhade",
    "country": "DE",
    "subdivision": "06",
    "timezone": "Europe/Berlin"
  },
  "geometry": {
    "type": "Point",
    "coordinates": [
      9.1135,
      53.32872
    ]
  }
}