{
  "type": "Feature",
  "properties": {
    "name": "Riede",
    "country": "DE",
    "subdivision": "06",
    "timezone": "Europe/Berlin"
  },
  "geometry": {
    "type": "Point",
    "coordinates": [
      8.95,
      52.96667
    ]
  }
}