{
  "type": "Feature",
  "properties": {
    "name": "Rotenburg",
    "country": "DE",
    "subdivision": "06",
    "timezone": "Europe/Berlin"
  },
  "geometry": {
    "type": "Point",
    "coordinates": [
      9.41082,
      53.11125
    ]
  }
}