{
  "type": "Feature",
  "properties": {
    "name": "Rötgesbüttel",
    "country": "DE",
    "subdivision": "06",
    "timezone": "Europe/Berlin"
  },
  "geometry": {
    "type": "Point",
    "coordinates": [
      10.53333,
      52.41667
    ]
  }
}