{
  "type": "Feature",
  "properties": {
    "name": "Rühme - Lincolnsdlg.",
    "country": "DE",
    "subdivision": "06",
    "timezone": "Europe/Berlin"
  },
  "geometry": {
    "type": "Point",
    "coordinates": [
      10.52032,
      52.3071
    ]
  }
}