{
  "type": "Feature",
  "properties": {
    "name": "Sachsenhagen",
    "country": "DE",
    "subdivision": "06",
    "timezone": "Europe/Berlin"
  },
  "geometry": {
    "type": "Point",
    "coordinates": [
      9.26791,
      52.39734
    ]
  }
}