{
  "type": "Feature",
  "properties": {
    "name": "Sande",
    "country": "DE",
    "subdivision": "06",
    "timezone": "Europe/Berlin"
  },
  "geometry": {
    "type": "Point",
    "coordinates": [
      8.01418,
      53.50489
    ]
  }
}