{
  "type": "Feature",
  "properties": {
    "name": "Schellerten",
    "country": "DE",
    "subdivision": "06",
    "timezone": "Europe/Berlin"
  },
  "geometry": {
    "type": "Point",
    "coordinates": [
      10.10227,
      52.1853
    ]
  }
}