{
  "type": "Feature",
  "properties": {
    "name": "Schillig",
    "country": "DE",
    "subdivision": "06",
    "timezone": "Europe/Berlin"
  },
  "geometry": {
    "type": "Point",
    "coordinates": [
      8.0217,
      53.70378
    ]
  }
}