{
  "type": "Feature",
  "properties": {
    "name": "Schneverdingen",
    "country": "DE",
    "subdivision": "06",
    "timezone": "Europe/Berlin"
  },
  "geometry": {
    "type": "Point",
    "coordinates": [
      9.79524,
      53.11685
    ]
  }
}