{
  "type": "Feature",
  "properties": {
    "name": "Schüttorf",
    "country": "DE",
    "subdivision": "06",
    "timezone": "Europe/Berlin"
  },
  "geometry": {
    "type": "Point",
    "coordinates": [
      7.22176,
      52.32281
    ]
  }
}