{
  "type": "Feature",
  "properties": {
    "name": "Siegfriedviertel",
    "country": "DE",
    "subdivision": "06",
    "timezone": "Europe/Berlin"
  },
  "geometry": {
    "type": "Point",
    "coordinates": [
      10.53257,
      52.28854
    ]
  }
}