{
  "type": "Feature",
  "properties": {
    "name": "Stedesdorf",
    "country": "DE",
    "subdivision": "06",
    "timezone": "Europe/Berlin"
  },
  "geometry": {
    "type": "Point",
    "coordinates": [
      7.66667,
      53.63333
    ]
  }
}