{
  "type": "Feature",
  "properties": {
    "name": "Sulingen",
    "country": "DE",
    "subdivision": "06",
    "timezone": "Europe/Berlin"
  },
  "geometry": {
    "type": "Point",
    "coordinates": [
      8.80949,
      52.68373
    ]
  }
}