{
  "type": "Feature",
  "properties": {
    "name": "Süpplingen",
    "country": "DE",
    "subdivision": "06",
    "timezone": "Europe/Berlin"
  },
  "geometry": {
    "type": "Point",
    "coordinates": [
      10.90393,
      52.22811
    ]
  }
}