{
  "type": "Feature",
  "properties": {
    "name": "Tappenbeck",
    "country": "DE",
    "subdivision": "06",
    "timezone": "Europe/Berlin"
  },
  "geometry": {
    "type": "Point",
    "coordinates": [
      10.74068,
      52.47055
    ]
  }
}