{
  "type": "Feature",
  "properties": {
    "name": "Toppenstedt",
    "country": "DE",
    "subdivision": "06",
    "timezone": "Europe/Berlin"
  },
  "geometry": {
    "type": "Point",
    "coordinates": [
      10.11451,
      53.2643
    ]
  }
}