{
  "type": "Feature",
  "properties": {
    "name": "Twistringen",
    "country": "DE",
    "subdivision": "06",
    "timezone": "Europe/Berlin"
  },
  "geometry": {
    "type": "Point",
    "coordinates": [
      8.64163,
      52.79926
    ]
  }
}