{
  "type": "Feature",
  "properties": {
    "name": "Vechta",
    "country": "DE",
    "subdivision": "06",
    "timezone": "Europe/Berlin"
  },
  "geometry": {
    "type": "Point",
    "coordinates": [
      8.28598,
      52.72632
    ]
  }
}