{
  "type": "Feature",
  "properties": {
    "name": "Veltenhof",
    "country": "DE",
    "subdivision": "06",
    "timezone": "Europe/Berlin"
  },
  "geometry": {
    "type": "Point",
    "coordinates": [
      10.48937,
      52.30774
    ]
  }
}