{
  "type": "Feature",
  "properties": {
    "name": "Vorwerk",
    "country": "DE",
    "subdivision": "06",
    "timezone": "Europe/Berlin"
  },
  "geometry": {
    "type": "Point",
    "coordinates": [
      9.15,
      53.18333
    ]
  }
}