{
  "type": "Feature",
  "properties": {
    "name": "Waake",
    "country": "DE",
    "subdivision": "06",
    "timezone": "Europe/Berlin"
  },
  "geometry": {
    "type": "Point",
    "coordinates": [
      10.05713,
      51.55637
    ]
  }
}