{
  "type": "Feature",
  "properties": {
    "name": "Wagenfeld",
    "country": "DE",
    "subdivision": "06",
    "timezone": "Europe/Berlin"
  },
  "geometry": {
    "type": "Point",
    "coordinates": [
      8.58333,
      52.55
    ]
  }
}