{
  "type": "Feature",
  "properties": {
    "name": "Wendeburg",
    "country": "DE",
    "subdivision": "06",
    "timezone": "Europe/Berlin"
  },
  "geometry": {
    "type": "Point",
    "coordinates": [
      10.39255,
      52.32957
    ]
  }
}