{
  "type": "Feature",
  "properties": {
    "name": "Werlte",
    "country": "DE",
    "subdivision": "06",
    "timezone": "Europe/Berlin"
  },
  "geometry": {
    "type": "Point",
    "coordinates": [
      7.68333,
      52.85
    ]
  }
}