{
  "type": "Feature",
  "properties": {
    "name": "Werpeloh",
    "country": "DE",
    "subdivision": "06",
    "timezone": "Europe/Berlin"
  },
  "geometry": {
    "type": "Point",
    "coordinates": [
      7.50831,
      52.87207
    ]
  }
}