{
  "type": "Feature",
  "properties": {
    "name": "Westergellersen",
    "country": "DE",
    "subdivision": "06",
    "timezone": "Europe/Berlin"
  },
  "geometry": {
    "type": "Point",
    "coordinates": [
      10.25,
      53.23333
    ]
  }
}