{
  "type": "Feature",
  "properties": {
    "name": "Wieda",
    "country": "DE",
    "subdivision": "06",
    "timezone": "Europe/Berlin"
  },
  "geometry": {
    "type": "Point",
    "coordinates": [
      10.58704,
      51.634
    ]
  }
}