{
  "type": "Feature",
  "properties": {
    "name": "Wilsum",
    "country": "DE",
    "subdivision": "06",
    "timezone": "Europe/Berlin"
  },
  "geometry": {
    "type": "Point",
    "coordinates": [
      6.85,
      52.53333
    ]
  }
}