{
  "type": "Feature",
  "properties": {
    "name": "Wilstedt",
    "country": "DE",
    "subdivision": "06",
    "timezone": "Europe/Berlin"
  },
  "geometry": {
    "type": "Point",
    "coordinates": [
      9.09595,
      53.19493
    ]
  }
}