{
  "type": "Feature",
  "properties": {
    "name": "Windhausen",
    "country": "DE",
    "subdivision": "06",
    "timezone": "Europe/Berlin"
  },
  "geometry": {
    "type": "Point",
    "coordinates": [
      10.21218,
      51.78544
    ]
  }
}