{
  "type": "Feature",
  "properties": {
    "name": "Winsen",
    "country": "DE",
    "subdivision": "06",
    "timezone": "Europe/Berlin"
  },
  "geometry": {
    "type": "Point",
    "coordinates": [
      10.21282,
      53.35753
    ]
  }
}