{
  "type": "Feature",
  "properties": {
    "name": "Wittmar",
    "country": "DE",
    "subdivision": "06",
    "timezone": "Europe/Berlin"
  },
  "geometry": {
    "type": "Point",
    "coordinates": [
      10.64,
      52.12969
    ]
  }
}