{
  "type": "Feature",
  "properties": {
    "name": "Zetel",
    "country": "DE",
    "subdivision": "06",
    "timezone": "Europe/Berlin"
  },
  "geometry": {
    "type": "Point",
    "coordinates": [
      7.98333,
      53.41667
    ]
  }
}