{
  "type": "Feature",
  "properties": {
    "name": "Zeven",
    "country": "DE",
    "subdivision": "06",
    "timezone": "Europe/Berlin"
  },
  "geometry": {
    "type": "Point",
    "coordinates": [
      9.27685,
      53.29657
    ]
  }
}