{
  "type": "Feature",
  "properties": {
    "name": "Vladimirovo",
    "country": "MK",
    "subdivision": "04",
    "timezone": "Europe/Skopje"
  },
  "geometry": {
    "type": "Point",
    "coordinates": [
      22.79278,
      41.71
    ]
  }
}