{
  "type": "Feature",
  "properties": {
    "name": "Bosaso",
    "country": "SO",
    "subdivision": "03",
    "timezone": "Africa/Mogadishu"
  },
  "geometry": {
    "type": "Point",
    "coordinates": [
      49.18158,
      11.28421
    ]
  }
}