{
  "type": "Feature",
  "properties": {
    "name": "Iskushuban",
    "country": "SO",
    "subdivision": "03",
    "timezone": "Africa/Mogadishu"
  },
  "geometry": {
    "type": "Point",
    "coordinates": [
      50.23,
      10.2837
    ]
  }
}