{
  "type": "Feature",
  "properties": {
    "name": "Djidiouia",
    "country": "DZ",
    "subdivision": "51",
    "timezone": "Africa/Algiers"
  },
  "geometry": {
    "type": "Point",
    "coordinates": [
      0.82871,
      35.92989
    ]
  }
}