{
  "type": "Feature",
  "properties": {
    "name": "Oued Rhiou",
    "country": "DZ",
    "subdivision": "51",
    "timezone": "Africa/Algiers"
  },
  "geometry": {
    "type": "Point",
    "coordinates": [
      0.91896,
      35.96124
    ]
  }
}