{
  "type": "Feature",
  "properties": {
    "name": "Dob",
    "country": "SI",
    "subdivision": "G7",
    "timezone": "Europe/Ljubljana"
  },
  "geometry": {
    "type": "Point",
    "coordinates": [
      14.62861,
      46.15194
    ]
  }
}