{
  "type": "Feature",
  "properties": {
    "name": "Correderos",
    "country": "HN",
    "subdivision": "16",
    "timezone": "America/Tegucigalpa"
  },
  "geometry": {
    "type": "Point",
    "coordinates": [
      -88.45,
      15.41667
    ]
  }
}