{
  "type": "Feature",
  "properties": {
    "name": "San Nicolás",
    "country": "HN",
    "subdivision": "16",
    "timezone": "America/Tegucigalpa"
  },
  "geometry": {
    "type": "Point",
    "coordinates": [
      -88.31667,
      14.93333
    ]
  }
}