{
  "type": "Feature",
  "properties": {
    "name": "Santa Rita",
    "country": "HN",
    "subdivision": "16",
    "timezone": "America/Tegucigalpa"
  },
  "geometry": {
    "type": "Point",
    "coordinates": [
      -88.21667,
      14.91667
    ]
  }
}