{
  "type": "Feature",
  "properties": {
    "name": "Santa Bárbara",
    "country": "HN",
    "subdivision": "16",
    "timezone": "America/Tegucigalpa"
  },
  "geometry": {
    "type": "Point",
    "coordinates": [
      -88.23611,
      14.91944
    ]
  }
}