{
  "type": "Feature",
  "properties": {
    "name": "Yasuj",
    "country": "IR",
    "subdivision": "05",
    "timezone": "Asia/Tehran"
  },
  "geometry": {
    "type": "Point",
    "coordinates": [
      51.58796,
      30.66824
    ]
  }
}