{
  "type": "Feature",
  "properties": {
    "name": "Nueva Esparta",
    "country": "SV",
    "subdivision": "07",
    "timezone": "America/El_Salvador"
  },
  "geometry": {
    "type": "Point",
    "coordinates": [
      -87.83861,
      13.78361
    ]
  }
}