{
  "type": "Feature",
  "properties": {
    "name": "Pasaquina",
    "country": "SV",
    "subdivision": "07",
    "timezone": "America/El_Salvador"
  },
  "geometry": {
    "type": "Point",
    "coordinates": [
      -87.84111,
      13.58444
    ]
  }
}