{
  "type": "Feature",
  "properties": {
    "name": "Sidi Alouane",
    "country": "TN",
    "subdivision": "15",
    "timezone": "Africa/Tunis"
  },
  "geometry": {
    "type": "Point",
    "coordinates": [
      10.93899,
      35.37505
    ]
  }
}