{
  "type": "Feature",
  "properties": {
    "name": "Ko Lanta",
    "country": "TH",
    "subdivision": "63",
    "timezone": "Asia/Bangkok"
  },
  "geometry": {
    "type": "Point",
    "coordinates": [
      99.08647,
      7.53362
    ]
  }
}