{
  "type": "Feature",
  "properties": {
    "name": "Loa Janan",
    "country": "ID",
    "subdivision": "14",
    "timezone": "Asia/Makassar"
  },
  "geometry": {
    "type": "Point",
    "coordinates": [
      117.09503,
      -0.58295
    ]
  }
}