{
  "type": "Feature",
  "properties": {
    "name": "Pueblo Nuevo",
    "country": "GT",
    "subdivision": "20",
    "timezone": "America/Guatemala"
  },
  "geometry": {
    "type": "Point",
    "coordinates": [
      -91.53946,
      14.64709
    ]
  }
}