{
  "type": "Feature",
  "properties": {
    "name": "Río Bravo",
    "country": "GT",
    "subdivision": "20",
    "timezone": "America/Guatemala"
  },
  "geometry": {
    "type": "Point",
    "coordinates": [
      -91.31713,
      14.40042
    ]
  }
}