{
  "type": "Feature",
  "properties": {
    "name": "San Francisco Zapotitlán",
    "country": "GT",
    "subdivision": "20",
    "timezone": "America/Guatemala"
  },
  "geometry": {
    "type": "Point",
    "coordinates": [
      -91.52144,
      14.58939
    ]
  }
}