{
  "type": "Feature",
  "properties": {
    "name": "Santo Domingo Suchitepéquez",
    "country": "GT",
    "subdivision": "20",
    "timezone": "America/Guatemala"
  },
  "geometry": {
    "type": "Point",
    "coordinates": [
      -91.48327,
      14.47901
    ]
  }
}