{
  "type": "Feature",
  "properties": {
    "name": "Davutlar",
    "country": "TR",
    "subdivision": "09",
    "timezone": "Europe/Istanbul"
  },
  "geometry": {
    "type": "Point",
    "coordinates": [
      27.29283,
      37.73392
    ]
  }
}