{
  "type": "Feature",
  "properties": {
    "name": "Sarıkemer",
    "country": "TR",
    "subdivision": "09",
    "timezone": "Europe/Istanbul"
  },
  "geometry": {
    "type": "Point",
    "coordinates": [
      27.3643,
      37.56609
    ]
  }
}