{
  "type": "Feature",
  "properties": {
    "name": "Maebaru-chūō",
    "country": "JP",
    "subdivision": "07",
    "timezone": "Asia/Tokyo"
  },
  "geometry": {
    "type": "Point",
    "coordinates": [
      130.20148,
      33.55916
    ]
  }
}