{
  "type": "Feature",
  "properties": {
    "name": "Ōkawa",
    "country": "JP",
    "subdivision": "07",
    "timezone": "Asia/Tokyo"
  },
  "geometry": {
    "type": "Point",
    "coordinates": [
      130.37527,
      33.20566
    ]
  }
}