{
  "type": "Feature",
  "properties": {
    "name": "Setakamachi-takayanagi",
    "country": "JP",
    "subdivision": "07",
    "timezone": "Asia/Tokyo"
  },
  "geometry": {
    "type": "Point",
    "coordinates": [
      130.46548,
      33.14858
    ]
  }
}