{
  "type": "Feature",
  "properties": {
    "name": "Achisu",
    "country": "RU",
    "subdivision": "17",
    "timezone": "Europe/Moscow"
  },
  "geometry": {
    "type": "Point",
    "coordinates": [
      47.68282,
      42.65197
    ]
  }
}