{
  "type": "Feature",
  "properties": {
    "name": "Bezhta",
    "country": "RU",
    "subdivision": "17",
    "timezone": "Europe/Moscow"
  },
  "geometry": {
    "type": "Point",
    "coordinates": [
      46.12828,
      42.1338
    ]
  }
}