{
  "type": "Feature",
  "properties": {
    "name": "Derbent",
    "country": "RU",
    "subdivision": "17",
    "timezone": "Europe/Moscow"
  },
  "geometry": {
    "type": "Point",
    "coordinates": [
      48.28987,
      42.06779
    ]
  }
}