{
  "type": "Feature",
  "properties": {
    "name": "Dorgeli",
    "country": "RU",
    "subdivision": "17",
    "timezone": "Europe/Moscow"
  },
  "geometry": {
    "type": "Point",
    "coordinates": [
      47.29435,
      42.667
    ]
  }
}