{
  "type": "Feature",
  "properties": {
    "name": "Druzhba",
    "country": "RU",
    "subdivision": "17",
    "timezone": "Europe/Moscow"
  },
  "geometry": {
    "type": "Point",
    "coordinates": [
      48.00145,
      42.242
    ]
  }
}