{
  "type": "Feature",
  "properties": {
    "name": "Dylym",
    "country": "RU",
    "subdivision": "17",
    "timezone": "Europe/Moscow"
  },
  "geometry": {
    "type": "Point",
    "coordinates": [
      46.63454,
      43.07099
    ]
  }
}