{
  "type": "Feature",
  "properties": {
    "name": "Gaptsakh",
    "country": "RU",
    "subdivision": "17",
    "timezone": "Europe/Moscow"
  },
  "geometry": {
    "type": "Point",
    "coordinates": [
      47.93027,
      41.45174
    ]
  }
}