{
  "type": "Feature",
  "properties": {
    "name": "Gurbuki",
    "country": "RU",
    "subdivision": "17",
    "timezone": "Europe/Moscow"
  },
  "geometry": {
    "type": "Point",
    "coordinates": [
      47.60067,
      42.61128
    ]
  }
}