{
  "type": "Feature",
  "properties": {
    "name": "Khamamatyurt",
    "country": "RU",
    "subdivision": "17",
    "timezone": "Europe/Moscow"
  },
  "geometry": {
    "type": "Point",
    "coordinates": [
      46.5006,
      43.60809
    ]
  }
}