{
  "type": "Feature",
  "properties": {
    "name": "Khiv",
    "country": "RU",
    "subdivision": "17",
    "timezone": "Europe/Moscow"
  },
  "geometry": {
    "type": "Point",
    "coordinates": [
      47.93063,
      41.75428
    ]
  }
}