{
  "type": "Feature",
  "properties": {
    "name": "Komsomol’skiy",
    "country": "RU",
    "subdivision": "17",
    "timezone": "Europe/Moscow"
  },
  "geometry": {
    "type": "Point",
    "coordinates": [
      46.69852,
      43.97833
    ]
  }
}