{
  "type": "Feature",
  "properties": {
    "name": "Kostek",
    "country": "RU",
    "subdivision": "17",
    "timezone": "Europe/Moscow"
  },
  "geometry": {
    "type": "Point",
    "coordinates": [
      46.85411,
      43.34387
    ]
  }
}