{
  "type": "Feature",
  "properties": {
    "name": "Magaramkent",
    "country": "RU",
    "subdivision": "17",
    "timezone": "Europe/Moscow"
  },
  "geometry": {
    "type": "Point",
    "coordinates": [
      48.34797,
      41.61586
    ]
  }
}