{
  "type": "Feature",
  "properties": {
    "name": "Novogagatli",
    "country": "RU",
    "subdivision": "17",
    "timezone": "Europe/Moscow"
  },
  "geometry": {
    "type": "Point",
    "coordinates": [
      46.48175,
      43.45677
    ]
  }
}