{
  "type": "Feature",
  "properties": {
    "name": "Novyy Khushet",
    "country": "RU",
    "subdivision": "17",
    "timezone": "Europe/Moscow"
  },
  "geometry": {
    "type": "Point",
    "coordinates": [
      47.5604,
      42.89941
    ]
  }
}