{
  "type": "Feature",
  "properties": {
    "name": "Nuradilovo",
    "country": "RU",
    "subdivision": "17",
    "timezone": "Europe/Moscow"
  },
  "geometry": {
    "type": "Point",
    "coordinates": [
      46.45763,
      43.28447
    ]
  }
}