{
  "type": "Feature",
  "properties": {
    "name": "Samur",
    "country": "RU",
    "subdivision": "17",
    "timezone": "Europe/Moscow"
  },
  "geometry": {
    "type": "Point",
    "coordinates": [
      48.48597,
      41.82527
    ]
  }
}