{
  "type": "Feature",
  "properties": {
    "name": "Solnechnoye",
    "country": "RU",
    "subdivision": "17",
    "timezone": "Europe/Moscow"
  },
  "geometry": {
    "type": "Point",
    "coordinates": [
      46.50697,
      43.276
    ]
  }
}