{
  "type": "Feature",
  "properties": {
    "name": "Terekli-Mekteb",
    "country": "RU",
    "subdivision": "17",
    "timezone": "Europe/Moscow"
  },
  "geometry": {
    "type": "Point",
    "coordinates": [
      45.86975,
      44.1671
    ]
  }
}