{
  "type": "Feature",
  "properties": {
    "name": "Uchkent",
    "country": "RU",
    "subdivision": "17",
    "timezone": "Europe/Moscow"
  },
  "geometry": {
    "type": "Point",
    "coordinates": [
      47.08255,
      43.11427
    ]
  }
}