{
  "type": "Feature",
  "properties": {
    "name": "Verkhneye Kazanishche",
    "country": "RU",
    "subdivision": "17",
    "timezone": "Europe/Moscow"
  },
  "geometry": {
    "type": "Point",
    "coordinates": [
      47.1378,
      42.73547
    ]
  }
}