{
  "type": "Feature",
  "properties": {
    "name": "Yuzhno-Sukhokumsk",
    "country": "RU",
    "subdivision": "17",
    "timezone": "Europe/Moscow"
  },
  "geometry": {
    "type": "Point",
    "coordinates": [
      45.6436,
      44.65811
    ]
  }
}