{
  "type": "Feature",
  "properties": {
    "name": "Zubutli-Miatli",
    "country": "RU",
    "subdivision": "17",
    "timezone": "Europe/Moscow"
  },
  "geometry": {
    "type": "Point",
    "coordinates": [
      46.81241,
      43.19886
    ]
  }
}