{
  "type": "Feature",
  "properties": {
    "name": "Bazar-Korgon",
    "country": "KG",
    "subdivision": "03",
    "timezone": "Asia/Bishkek"
  },
  "geometry": {
    "type": "Point",
    "coordinates": [
      72.74586,
      41.0376
    ]
  }
}