{
  "type": "Feature",
  "properties": {
    "name": "Al Arţāwīyah",
    "country": "SA",
    "subdivision": "10",
    "timezone": "Asia/Riyadh"
  },
  "geometry": {
    "type": "Point",
    "coordinates": [
      45.34813,
      26.50387
    ]
  }
}