{
  "type": "Feature",
  "properties": {
    "name": "MarÄt",
    "country": "SA",
    "subdivision": "10",
    "timezone": "Asia/Riyadh"
  },
  "geometry": {
    "type": "Point",
    "coordinates": [
      45.45775,
      25.07064
    ]
  }
}