{
  "type": "Feature",
  "properties": {
    "name": "Lüderitz",
    "country": "NA",
    "subdivision": "31",
    "timezone": "Africa/Windhoek"
  },
  "geometry": {
    "type": "Point",
    "coordinates": [
      15.15383,
      -26.64807
    ]
  }
}