{
  "type": "Feature",
  "properties": {
    "name": "Menen",
    "country": "NR",
    "subdivision": "11",
    "timezone": "Pacific/Nauru"
  },
  "geometry": {
    "type": "Point",
    "coordinates": [
      166.94871,
      -0.54539
    ]
  }
}