{
  "type": "Feature",
  "properties": {
    "name": "Martapura",
    "country": "ID",
    "subdivision": "12",
    "timezone": "Asia/Makassar"
  },
  "geometry": {
    "type": "Point",
    "coordinates": [
      114.8642,
      -3.4109
    ]
  }
}