{
  "type": "Feature",
  "properties": {
    "name": "Esuk Oron",
    "country": "NG",
    "subdivision": "21",
    "timezone": "Africa/Lagos"
  },
  "geometry": {
    "type": "Point",
    "coordinates": [
      8.25341,
      4.80293
    ]
  }
}