{
  "type": "Feature",
  "properties": {
    "name": "Rosa Zarate",
    "country": "EC",
    "subdivision": "09",
    "timezone": "America/Guayaquil"
  },
  "geometry": {
    "type": "Point",
    "coordinates": [
      -79.47407,
      0.32779
    ]
  }
}