{
  "type": "Feature",
  "properties": {
    "name": "Demir Kapija",
    "country": "MK",
    "subdivision": "25",
    "timezone": "Europe/Skopje"
  },
  "geometry": {
    "type": "Point",
    "coordinates": [
      22.24631,
      41.40613
    ]
  }
}