{
  "type": "Feature",
  "properties": {
    "name": "Goubétto",
    "country": "DJ",
    "subdivision": "01",
    "timezone": "Africa/Djibouti"
  },
  "geometry": {
    "type": "Point",
    "coordinates": [
      43.00028,
      11.42389
    ]
  }
}