{
  "type": "Feature",
  "properties": {
    "name": "Bayjī",
    "country": "IQ",
    "subdivision": "18",
    "timezone": "Asia/Baghdad"
  },
  "geometry": {
    "type": "Point",
    "coordinates": [
      43.48878,
      34.92915
    ]
  }
}