{
  "type": "Feature",
  "properties": {
    "name": "Ménaka",
    "country": "ML",
    "subdivision": "12070577",
    "timezone": "Africa/Bamako"
  },
  "geometry": {
    "type": "Point",
    "coordinates": [
      2.4022,
      15.9182
    ]
  }
}