{
  "type": "Feature",
  "properties": {
    "name": "Acarí",
    "country": "PE",
    "subdivision": "04",
    "timezone": "America/Lima"
  },
  "geometry": {
    "type": "Point",
    "coordinates": [
      -74.61361,
      -15.42393
    ]
  }
}