{
  "type": "Feature",
  "properties": {
    "name": "Ciudad Satelite",
    "country": "PE",
    "subdivision": "04",
    "timezone": "America/Lima"
  },
  "geometry": {
    "type": "Point",
    "coordinates": [
      -71.52921,
      -16.43085
    ]
  }
}