{
  "type": "Feature",
  "properties": {
    "name": "Vwawa",
    "country": "TZ",
    "subdivision": "32",
    "timezone": "Africa/Dar_es_Salaam"
  },
  "geometry": {
    "type": "Point",
    "coordinates": [
      32.93472,
      -9.10806
    ]
  }
}