{
  "type": "Feature",
  "properties": {
    "name": "Alfredo V. Bonfil",
    "country": "MX",
    "subdivision": "04",
    "timezone": "America/Merida"
  },
  "geometry": {
    "type": "Point",
    "coordinates": [
      -90.18214,
      19.53032
    ]
  }
}