{
  "type": "Feature",
  "properties": {
    "name": "Candelaria",
    "country": "MX",
    "subdivision": "04",
    "timezone": "America/Merida"
  },
  "geometry": {
    "type": "Point",
    "coordinates": [
      -91.04534,
      18.18574
    ]
  }
}