{
  "type": "Feature",
  "properties": {
    "name": "Carrillo Puerto",
    "country": "MX",
    "subdivision": "04",
    "timezone": "America/Merida"
  },
  "geometry": {
    "type": "Point",
    "coordinates": [
      -90.52279,
      19.094
    ]
  }
}