{
  "type": "Feature",
  "properties": {
    "name": "Champotón",
    "country": "MX",
    "subdivision": "04",
    "timezone": "America/Merida"
  },
  "geometry": {
    "type": "Point",
    "coordinates": [
      -90.72039,
      19.34745
    ]
  }
}