{
  "type": "Feature",
  "properties": {
    "name": "Chunchintok",
    "country": "MX",
    "subdivision": "04",
    "timezone": "America/Merida"
  },
  "geometry": {
    "type": "Point",
    "coordinates": [
      -89.58218,
      19.36145
    ]
  }
}