{
  "type": "Feature",
  "properties": {
    "name": "Colonia Emiliano Zapata",
    "country": "MX",
    "subdivision": "04",
    "timezone": "America/Merida"
  },
  "geometry": {
    "type": "Point",
    "coordinates": [
      -92.31088,
      18.66504
    ]
  }
}