{
  "type": "Feature",
  "properties": {
    "name": "División del Norte",
    "country": "MX",
    "subdivision": "04",
    "timezone": "America/Merida"
  },
  "geometry": {
    "type": "Point",
    "coordinates": [
      -90.76416,
      18.52946
    ]
  }
}