{
  "type": "Feature",
  "properties": {
    "name": "Hampolol",
    "country": "MX",
    "subdivision": "04",
    "timezone": "America/Merida"
  },
  "geometry": {
    "type": "Point",
    "coordinates": [
      -90.38924,
      19.92716
    ]
  }
}