{
  "type": "Feature",
  "properties": {
    "name": "Hopelchén",
    "country": "MX",
    "subdivision": "04",
    "timezone": "America/Merida"
  },
  "geometry": {
    "type": "Point",
    "coordinates": [
      -89.84437,
      19.74671
    ]
  }
}