{
  "type": "Feature",
  "properties": {
    "name": "La Joya",
    "country": "MX",
    "subdivision": "04",
    "timezone": "America/Merida"
  },
  "geometry": {
    "type": "Point",
    "coordinates": [
      -90.67333,
      19.48028
    ]
  }
}