{
  "type": "Feature",
  "properties": {
    "name": "Nuevo Progreso",
    "country": "MX",
    "subdivision": "04",
    "timezone": "America/Merida"
  },
  "geometry": {
    "type": "Point",
    "coordinates": [
      -92.29124,
      18.62294
    ]
  }
}