{
  "type": "Feature",
  "properties": {
    "name": "Pomuch",
    "country": "MX",
    "subdivision": "04",
    "timezone": "America/Merida"
  },
  "geometry": {
    "type": "Point",
    "coordinates": [
      -90.17488,
      20.13727
    ]
  }
}