{
  "type": "Feature",
  "properties": {
    "name": "Santa Cruz Ex-Hacienda",
    "country": "MX",
    "subdivision": "04",
    "timezone": "America/Merida"
  },
  "geometry": {
    "type": "Point",
    "coordinates": [
      -90.24068,
      20.39684
    ]
  }
}