{
  "type": "Feature",
  "properties": {
    "name": "Sihochac",
    "country": "MX",
    "subdivision": "04",
    "timezone": "America/Merida"
  },
  "geometry": {
    "type": "Point",
    "coordinates": [
      -90.58472,
      19.5012
    ]
  }
}