{
  "type": "Feature",
  "properties": {
    "name": "Tikinmul",
    "country": "MX",
    "subdivision": "04",
    "timezone": "America/Merida"
  },
  "geometry": {
    "type": "Point",
    "coordinates": [
      -90.22306,
      19.76611
    ]
  }
}