{
  "type": "Feature",
  "properties": {
    "name": "Oued Sly",
    "country": "DZ",
    "subdivision": "41",
    "timezone": "Africa/Algiers"
  },
  "geometry": {
    "type": "Point",
    "coordinates": [
      1.19949,
      36.10124
    ]
  }
}