{
  "type": "Feature",
  "properties": {
    "name": "Pelkosenniemi",
    "country": "FI",
    "subdivision": "19",
    "timezone": "Europe/Helsinki"
  },
  "geometry": {
    "type": "Point",
    "coordinates": [
      27.51056,
      67.11083
    ]
  }
}