{
  "type": "Feature",
  "properties": {
    "name": "Tornio",
    "country": "FI",
    "subdivision": "19",
    "timezone": "Europe/Helsinki"
  },
  "geometry": {
    "type": "Point",
    "coordinates": [
      24.14662,
      65.84811
    ]
  }
}