{
  "type": "Feature",
  "properties": {
    "name": "Beruwala",
    "country": "LK",
    "subdivision": "36",
    "timezone": "Asia/Colombo"
  },
  "geometry": {
    "type": "Point",
    "coordinates": [
      79.9828,
      6.4788
    ]
  }
}