{
  "type": "Feature",
  "properties": {
    "name": "Horawala Junction",
    "country": "LK",
    "subdivision": "36",
    "timezone": "Asia/Colombo"
  },
  "geometry": {
    "type": "Point",
    "coordinates": [
      80.12708,
      6.48088
    ]
  }
}