{
  "type": "Feature",
  "properties": {
    "name": "Maharagama",
    "country": "LK",
    "subdivision": "36",
    "timezone": "Asia/Colombo"
  },
  "geometry": {
    "type": "Point",
    "coordinates": [
      79.9265,
      6.848
    ]
  }
}