{
  "type": "Feature",
  "properties": {
    "name": "Panadura",
    "country": "LK",
    "subdivision": "36",
    "timezone": "Asia/Colombo"
  },
  "geometry": {
    "type": "Point",
    "coordinates": [
      79.9026,
      6.7132
    ]
  }
}