{
  "type": "Feature",
  "properties": {
    "name": "Peliyagoda",
    "country": "LK",
    "subdivision": "36",
    "timezone": "Asia/Colombo"
  },
  "geometry": {
    "type": "Point",
    "coordinates": [
      79.8836,
      6.9685
    ]
  }
}