{
  "type": "Feature",
  "properties": {
    "name": "Atolina",
    "country": "BY",
    "subdivision": "05",
    "timezone": "Europe/Minsk"
  },
  "geometry": {
    "type": "Point",
    "coordinates": [
      27.4346,
      53.7817
    ]
  }
}