{
  "type": "Feature",
  "properties": {
    "name": "Chyst’",
    "country": "BY",
    "subdivision": "05",
    "timezone": "Europe/Minsk"
  },
  "geometry": {
    "type": "Point",
    "coordinates": [
      27.1067,
      54.2698
    ]
  }
}