{
  "type": "Feature",
  "properties": {
    "name": "Dukora",
    "country": "BY",
    "subdivision": "05",
    "timezone": "Europe/Minsk"
  },
  "geometry": {
    "type": "Point",
    "coordinates": [
      27.94,
      53.6786
    ]
  }
}