{
  "type": "Feature",
  "properties": {
    "name": "Enyerhyetykaw",
    "country": "BY",
    "subdivision": "05",
    "timezone": "Europe/Minsk"
  },
  "geometry": {
    "type": "Point",
    "coordinates": [
      27.0535,
      53.5871
    ]
  }
}