{
  "type": "Feature",
  "properties": {
    "name": "Kapyl’",
    "country": "BY",
    "subdivision": "05",
    "timezone": "Europe/Minsk"
  },
  "geometry": {
    "type": "Point",
    "coordinates": [
      27.0913,
      53.1516
    ]
  }
}