{
  "type": "Feature",
  "properties": {
    "name": "Korolëv Stan",
    "country": "BY",
    "subdivision": "05",
    "timezone": "Europe/Minsk"
  },
  "geometry": {
    "type": "Point",
    "coordinates": [
      27.7982,
      53.9865
    ]
  }
}