{
  "type": "Feature",
  "properties": {
    "name": "Kryvichy",
    "country": "BY",
    "subdivision": "05",
    "timezone": "Europe/Minsk"
  },
  "geometry": {
    "type": "Point",
    "coordinates": [
      27.2886,
      54.7132
    ]
  }
}