{
  "type": "Feature",
  "properties": {
    "name": "Loshnitsa",
    "country": "BY",
    "subdivision": "05",
    "timezone": "Europe/Minsk"
  },
  "geometry": {
    "type": "Point",
    "coordinates": [
      28.7649,
      54.2796
    ]
  }
}