{
  "type": "Feature",
  "properties": {
    "name": "Mar’’ina Horka",
    "country": "BY",
    "subdivision": "05",
    "timezone": "Europe/Minsk"
  },
  "geometry": {
    "type": "Point",
    "coordinates": [
      28.147,
      53.509
    ]
  }
}