{
  "type": "Feature",
  "properties": {
    "name": "Puchavičy",
    "country": "BY",
    "subdivision": "05",
    "timezone": "Europe/Minsk"
  },
  "geometry": {
    "type": "Point",
    "coordinates": [
      28.2467,
      53.5297
    ]
  }
}