{
  "type": "Feature",
  "properties": {
    "name": "Pyatryshki",
    "country": "BY",
    "subdivision": "05",
    "timezone": "Europe/Minsk"
  },
  "geometry": {
    "type": "Point",
    "coordinates": [
      27.2179,
      54.0686
    ]
  }
}