{
  "type": "Feature",
  "properties": {
    "name": "Radaškovičy",
    "country": "BY",
    "subdivision": "05",
    "timezone": "Europe/Minsk"
  },
  "geometry": {
    "type": "Point",
    "coordinates": [
      27.2412,
      54.1554
    ]
  }
}