{
  "type": "Feature",
  "properties": {
    "name": "SmilaviÄy",
    "country": "BY",
    "subdivision": "05",
    "timezone": "Europe/Minsk"
  },
  "geometry": {
    "type": "Point",
    "coordinates": [
      28.0115,
      53.7496
    ]
  }
}