{
  "type": "Feature",
  "properties": {
    "name": "Stowbtsy",
    "country": "BY",
    "subdivision": "05",
    "timezone": "Europe/Minsk"
  },
  "geometry": {
    "type": "Point",
    "coordinates": [
      26.7434,
      53.4785
    ]
  }
}