{
  "type": "Feature",
  "properties": {
    "name": "Kabalo",
    "country": "CD",
    "subdivision": "29",
    "timezone": "Africa/Lubumbashi"
  },
  "geometry": {
    "type": "Point",
    "coordinates": [
      26.9143,
      -6.05255
    ]
  }
}