{
  "type": "Feature",
  "properties": {
    "name": "Posof",
    "country": "TR",
    "subdivision": "86",
    "timezone": "Europe/Istanbul"
  },
  "geometry": {
    "type": "Point",
    "coordinates": [
      42.72917,
      41.51111
    ]
  }
}