{
  "type": "Feature",
  "properties": {
    "name": "Kamalasai",
    "country": "TH",
    "subdivision": "23",
    "timezone": "Asia/Bangkok"
  },
  "geometry": {
    "type": "Point",
    "coordinates": [
      103.57564,
      16.33839
    ]
  }
}