{
  "type": "Feature",
  "properties": {
    "name": "Qasım İsmayılov",
    "country": "AZ",
    "subdivision": "51",
    "timezone": "Asia/Baku"
  },
  "geometry": {
    "type": "Point",
    "coordinates": [
      46.25938,
      40.81243
    ]
  }
}