{
  "type": "Feature",
  "properties": {
    "name": "San Vicente de Tagua Tagua",
    "country": "CL",
    "subdivision": "08",
    "timezone": "America/Santiago"
  },
  "geometry": {
    "type": "Point",
    "coordinates": [
      -71.07751,
      -34.43859
    ]
  }
}