{
  "type": "Feature",
  "properties": {
    "name": "Altenkrempe",
    "country": "DE",
    "subdivision": "10",
    "timezone": "Europe/Berlin"
  },
  "geometry": {
    "type": "Point",
    "coordinates": [
      10.83333,
      54.13333
    ]
  }
}