{
  "type": "Feature",
  "properties": {
    "name": "Aukrug",
    "country": "DE",
    "subdivision": "10",
    "timezone": "Europe/Berlin"
  },
  "geometry": {
    "type": "Point",
    "coordinates": [
      9.78333,
      54.08333
    ]
  }
}