{
  "type": "Feature",
  "properties": {
    "name": "Bad Segeberg",
    "country": "DE",
    "subdivision": "10",
    "timezone": "Europe/Berlin"
  },
  "geometry": {
    "type": "Point",
    "coordinates": [
      10.30215,
      53.94313
    ]
  }
}