{
  "type": "Feature",
  "properties": {
    "name": "Berkenthin",
    "country": "DE",
    "subdivision": "10",
    "timezone": "Europe/Berlin"
  },
  "geometry": {
    "type": "Point",
    "coordinates": [
      10.65,
      53.73333
    ]
  }
}