{
  "type": "Feature",
  "properties": {
    "name": "Böcklersiedlung-Bugenhagen",
    "country": "DE",
    "subdivision": "10",
    "timezone": "Europe/Berlin"
  },
  "geometry": {
    "type": "Point",
    "coordinates": [
      9.95533,
      54.07438
    ]
  }
}