{
  "type": "Feature",
  "properties": {
    "name": "Bovenau",
    "country": "DE",
    "subdivision": "10",
    "timezone": "Europe/Berlin"
  },
  "geometry": {
    "type": "Point",
    "coordinates": [
      9.83333,
      54.33333
    ]
  }
}