{
  "type": "Feature",
  "properties": {
    "name": "Brande-Hörnerkirchen",
    "country": "DE",
    "subdivision": "10",
    "timezone": "Europe/Berlin"
  },
  "geometry": {
    "type": "Point",
    "coordinates": [
      9.71667,
      53.85
    ]
  }
}