{
  "type": "Feature",
  "properties": {
    "name": "Breitenfelde",
    "country": "DE",
    "subdivision": "10",
    "timezone": "Europe/Berlin"
  },
  "geometry": {
    "type": "Point",
    "coordinates": [
      10.63339,
      53.60592
    ]
  }
}