{
  "type": "Feature",
  "properties": {
    "name": "Breitenburg",
    "country": "DE",
    "subdivision": "10",
    "timezone": "Europe/Berlin"
  },
  "geometry": {
    "type": "Point",
    "coordinates": [
      9.57041,
      53.90572
    ]
  }
}