{
  "type": "Feature",
  "properties": {
    "name": "Brokstedt",
    "country": "DE",
    "subdivision": "10",
    "timezone": "Europe/Berlin"
  },
  "geometry": {
    "type": "Point",
    "coordinates": [
      9.81667,
      53.98333
    ]
  }
}