{
  "type": "Feature",
  "properties": {
    "name": "Buchholz",
    "country": "DE",
    "subdivision": "10",
    "timezone": "Europe/Berlin"
  },
  "geometry": {
    "type": "Point",
    "coordinates": [
      9.22362,
      53.98829
    ]
  }
}