{
  "type": "Feature",
  "properties": {
    "name": "Elmshorn",
    "country": "DE",
    "subdivision": "10",
    "timezone": "Europe/Berlin"
  },
  "geometry": {
    "type": "Point",
    "coordinates": [
      9.65339,
      53.75396
    ]
  }
}