{
  "type": "Feature",
  "properties": {
    "name": "Fahrenkrug",
    "country": "DE",
    "subdivision": "10",
    "timezone": "Europe/Berlin"
  },
  "geometry": {
    "type": "Point",
    "coordinates": [
      10.25,
      53.95
    ]
  }
}