{
  "type": "Feature",
  "properties": {
    "name": "Felm",
    "country": "DE",
    "subdivision": "10",
    "timezone": "Europe/Berlin"
  },
  "geometry": {
    "type": "Point",
    "coordinates": [
      10.05,
      54.41667
    ]
  }
}