{
  "type": "Feature",
  "properties": {
    "name": "Grönwohld",
    "country": "DE",
    "subdivision": "10",
    "timezone": "Europe/Berlin"
  },
  "geometry": {
    "type": "Point",
    "coordinates": [
      10.40784,
      53.64162
    ]
  }
}