{
  "type": "Feature",
  "properties": {
    "name": "Hamdorf",
    "country": "DE",
    "subdivision": "10",
    "timezone": "Europe/Berlin"
  },
  "geometry": {
    "type": "Point",
    "coordinates": [
      9.51866,
      54.22522
    ]
  }
}