{
  "type": "Feature",
  "properties": {
    "name": "Hattstedt",
    "country": "DE",
    "subdivision": "10",
    "timezone": "Europe/Berlin"
  },
  "geometry": {
    "type": "Point",
    "coordinates": [
      9.03333,
      54.53333
    ]
  }
}