{
  "type": "Feature",
  "properties": {
    "name": "Herzhorn",
    "country": "DE",
    "subdivision": "10",
    "timezone": "Europe/Berlin"
  },
  "geometry": {
    "type": "Point",
    "coordinates": [
      9.48333,
      53.78333
    ]
  }
}