{
  "type": "Feature",
  "properties": {
    "name": "Hollingstedt",
    "country": "DE",
    "subdivision": "10",
    "timezone": "Europe/Berlin"
  },
  "geometry": {
    "type": "Point",
    "coordinates": [
      9.33695,
      54.45934
    ]
  }
}