{
  "type": "Feature",
  "properties": {
    "name": "Klein Nordende",
    "country": "DE",
    "subdivision": "10",
    "timezone": "Europe/Berlin"
  },
  "geometry": {
    "type": "Point",
    "coordinates": [
      9.65424,
      53.72219
    ]
  }
}