{
  "type": "Feature",
  "properties": {
    "name": "Kremperheide",
    "country": "DE",
    "subdivision": "10",
    "timezone": "Europe/Berlin"
  },
  "geometry": {
    "type": "Point",
    "coordinates": [
      9.47809,
      53.88721
    ]
  }
}