{
  "type": "Feature",
  "properties": {
    "name": "Lägerdorf",
    "country": "DE",
    "subdivision": "10",
    "timezone": "Europe/Berlin"
  },
  "geometry": {
    "type": "Point",
    "coordinates": [
      9.58333,
      53.88333
    ]
  }
}