{
  "type": "Feature",
  "properties": {
    "name": "Lentföhrden",
    "country": "DE",
    "subdivision": "10",
    "timezone": "Europe/Berlin"
  },
  "geometry": {
    "type": "Point",
    "coordinates": [
      9.88333,
      53.86667
    ]
  }
}