{
  "type": "Feature",
  "properties": {
    "name": "Molfsee",
    "country": "DE",
    "subdivision": "10",
    "timezone": "Europe/Berlin"
  },
  "geometry": {
    "type": "Point",
    "coordinates": [
      10.06667,
      54.26667
    ]
  }
}