{
  "type": "Feature",
  "properties": {
    "name": "Moorrege",
    "country": "DE",
    "subdivision": "10",
    "timezone": "Europe/Berlin"
  },
  "geometry": {
    "type": "Point",
    "coordinates": [
      9.66667,
      53.66667
    ]
  }
}