{
  "type": "Feature",
  "properties": {
    "name": "Oldendorf",
    "country": "DE",
    "subdivision": "10",
    "timezone": "Europe/Berlin"
  },
  "geometry": {
    "type": "Point",
    "coordinates": [
      9.45858,
      53.95341
    ]
  }
}