{
  "type": "Feature",
  "properties": {
    "name": "Oldenburg in Holstein",
    "country": "DE",
    "subdivision": "10",
    "timezone": "Europe/Berlin"
  },
  "geometry": {
    "type": "Point",
    "coordinates": [
      10.90156,
      54.29576
    ]
  }
}