{
  "type": "Feature",
  "properties": {
    "name": "Pinneberg",
    "country": "DE",
    "subdivision": "10",
    "timezone": "Europe/Berlin"
  },
  "geometry": {
    "type": "Point",
    "coordinates": [
      9.78936,
      53.66732
    ]
  }
}