{
  "type": "Feature",
  "properties": {
    "name": "Pölitz",
    "country": "DE",
    "subdivision": "10",
    "timezone": "Europe/Berlin"
  },
  "geometry": {
    "type": "Point",
    "coordinates": [
      10.38276,
      53.77303
    ]
  }
}