{
  "type": "Feature",
  "properties": {
    "name": "Preetz",
    "country": "DE",
    "subdivision": "10",
    "timezone": "Europe/Berlin"
  },
  "geometry": {
    "type": "Point",
    "coordinates": [
      10.27795,
      54.2354
    ]
  }
}