{
  "type": "Feature",
  "properties": {
    "name": "Rantrum",
    "country": "DE",
    "subdivision": "10",
    "timezone": "Europe/Berlin"
  },
  "geometry": {
    "type": "Point",
    "coordinates": [
      9.12872,
      54.44062
    ]
  }
}