{
  "type": "Feature",
  "properties": {
    "name": "Sankt Margarethen",
    "country": "DE",
    "subdivision": "10",
    "timezone": "Europe/Berlin"
  },
  "geometry": {
    "type": "Point",
    "coordinates": [
      9.25301,
      53.89199
    ]
  }
}