{
  "type": "Feature",
  "properties": {
    "name": "Schleswig",
    "country": "DE",
    "subdivision": "10",
    "timezone": "Europe/Berlin"
  },
  "geometry": {
    "type": "Point",
    "coordinates": [
      9.5586,
      54.52156
    ]
  }
}