{
  "type": "Feature",
  "properties": {
    "name": "Sieverstedt",
    "country": "DE",
    "subdivision": "10",
    "timezone": "Europe/Berlin"
  },
  "geometry": {
    "type": "Point",
    "coordinates": [
      9.46949,
      54.64145
    ]
  }
}