{
  "type": "Feature",
  "properties": {
    "name": "Travemünde",
    "country": "DE",
    "subdivision": "10",
    "timezone": "Europe/Berlin"
  },
  "geometry": {
    "type": "Point",
    "coordinates": [
      10.8709,
      53.96304
    ]
  }
}