{
  "type": "Feature",
  "properties": {
    "name": "Tremsbüttel",
    "country": "DE",
    "subdivision": "10",
    "timezone": "Europe/Berlin"
  },
  "geometry": {
    "type": "Point",
    "coordinates": [
      10.31024,
      53.74384
    ]
  }
}