{
  "type": "Feature",
  "properties": {
    "name": "Wangels",
    "country": "DE",
    "subdivision": "10",
    "timezone": "Europe/Berlin"
  },
  "geometry": {
    "type": "Point",
    "coordinates": [
      10.76667,
      54.26667
    ]
  }
}