{
  "type": "Feature",
  "properties": {
    "name": "Westerland",
    "country": "DE",
    "subdivision": "10",
    "timezone": "Europe/Berlin"
  },
  "geometry": {
    "type": "Point",
    "coordinates": [
      8.30326,
      54.9079
    ]
  }
}