{
  "type": "Feature",
  "properties": {
    "name": "Wyk auf Föhr",
    "country": "DE",
    "subdivision": "10",
    "timezone": "Europe/Berlin"
  },
  "geometry": {
    "type": "Point",
    "coordinates": [
      8.56702,
      54.6914
    ]
  }
}