{
  "type": "Feature",
  "properties": {
    "name": "Nyrkiv",
    "country": "UA",
    "subdivision": "22",
    "timezone": "Europe/Kiev"
  },
  "geometry": {
    "type": "Point",
    "coordinates": [
      25.59989,
      48.81492
    ]
  }
}