{
  "type": "Feature",
  "properties": {
    "name": "Shumsk",
    "country": "UA",
    "subdivision": "22",
    "timezone": "Europe/Kiev"
  },
  "geometry": {
    "type": "Point",
    "coordinates": [
      26.11792,
      50.11775
    ]
  }
}