{
  "type": "Feature",
  "properties": {
    "name": "Skala-Podilska",
    "country": "UA",
    "subdivision": "22",
    "timezone": "Europe/Kiev"
  },
  "geometry": {
    "type": "Point",
    "coordinates": [
      26.20064,
      48.85014
    ]
  }
}