{
  "type": "Feature",
  "properties": {
    "name": "Terebovlya",
    "country": "UA",
    "subdivision": "22",
    "timezone": "Europe/Kiev"
  },
  "geometry": {
    "type": "Point",
    "coordinates": [
      25.68886,
      49.29967
    ]
  }
}