{
  "type": "Feature",
  "properties": {
    "name": "Yahil’nytsya",
    "country": "UA",
    "subdivision": "22",
    "timezone": "Europe/Kiev"
  },
  "geometry": {
    "type": "Point",
    "coordinates": [
      25.74375,
      48.94248
    ]
  }
}