{
  "type": "Feature",
  "properties": {
    "name": "Carmen",
    "country": "MX",
    "subdivision": "19",
    "timezone": "America/Monterrey"
  },
  "geometry": {
    "type": "Point",
    "coordinates": [
      -100.36396,
      25.9365
    ]
  }
}