{
  "type": "Feature",
  "properties": {
    "name": "Ciénega de Flores",
    "country": "MX",
    "subdivision": "19",
    "timezone": "America/Monterrey"
  },
  "geometry": {
    "type": "Point",
    "coordinates": [
      -100.16695,
      25.95467
    ]
  }
}