{
  "type": "Feature",
  "properties": {
    "name": "Emiliano Zapata",
    "country": "MX",
    "subdivision": "19",
    "timezone": "America/Monterrey"
  },
  "geometry": {
    "type": "Point",
    "coordinates": [
      -100.28056,
      25.91028
    ]
  }
}