{
  "type": "Feature",
  "properties": {
    "name": "Fraccionamiento Misión de San Javier",
    "country": "MX",
    "subdivision": "19",
    "timezone": "America/Monterrey"
  },
  "geometry": {
    "type": "Point",
    "coordinates": [
      -100.15194,
      25.74556
    ]
  }
}