{
  "type": "Feature",
  "properties": {
    "name": "Fraccionamiento Real Palmas",
    "country": "MX",
    "subdivision": "19",
    "timezone": "America/Monterrey"
  },
  "geometry": {
    "type": "Point",
    "coordinates": [
      -100.15972,
      25.90417
    ]
  }
}