{
  "type": "Feature",
  "properties": {
    "name": "General Zuazua",
    "country": "MX",
    "subdivision": "19",
    "timezone": "America/Monterrey"
  },
  "geometry": {
    "type": "Point",
    "coordinates": [
      -100.108,
      25.89491
    ]
  }
}