{
  "type": "Feature",
  "properties": {
    "name": "General Treviño",
    "country": "MX",
    "subdivision": "19",
    "timezone": "America/Monterrey"
  },
  "geometry": {
    "type": "Point",
    "coordinates": [
      -99.48503,
      26.22316
    ]
  }
}