{
  "type": "Feature",
  "properties": {
    "name": "Héctor Caballero",
    "country": "MX",
    "subdivision": "19",
    "timezone": "America/Monterrey"
  },
  "geometry": {
    "type": "Point",
    "coordinates": [
      -100.12667,
      25.63556
    ]
  }
}