{
  "type": "Feature",
  "properties": {
    "name": "La Ascensión",
    "country": "MX",
    "subdivision": "19",
    "timezone": "America/Monterrey"
  },
  "geometry": {
    "type": "Point",
    "coordinates": [
      -99.9141,
      24.32392
    ]
  }
}