{
  "type": "Feature",
  "properties": {
    "name": "Portal de las Salinas",
    "country": "MX",
    "subdivision": "19",
    "timezone": "America/Monterrey"
  },
  "geometry": {
    "type": "Point",
    "coordinates": [
      -100.14333,
      25.98222
    ]
  }
}