{
  "type": "Feature",
  "properties": {
    "name": "Pueblo Nuevo",
    "country": "MX",
    "subdivision": "19",
    "timezone": "America/Monterrey"
  },
  "geometry": {
    "type": "Point",
    "coordinates": [
      -99.75987,
      25.48409
    ]
  }
}