{
  "type": "Feature",
  "properties": {
    "name": "San José de Raíces",
    "country": "MX",
    "subdivision": "19",
    "timezone": "America/Monterrey"
  },
  "geometry": {
    "type": "Point",
    "coordinates": [
      -100.24002,
      24.57145
    ]
  }
}