{
  "type": "Feature",
  "properties": {
    "name": "Karpathos",
    "country": "GR",
    "subdivision": "ESYE42",
    "timezone": "Europe/Athens"
  },
  "geometry": {
    "type": "Point",
    "coordinates": [
      27.21322,
      35.50701
    ]
  }
}