{
  "type": "Feature",
  "properties": {
    "name": "Kéfalos",
    "country": "GR",
    "subdivision": "ESYE42",
    "timezone": "Europe/Athens"
  },
  "geometry": {
    "type": "Point",
    "coordinates": [
      26.95961,
      36.74507
    ]
  }
}