{
  "type": "Feature",
  "properties": {
    "name": "Lakkí",
    "country": "GR",
    "subdivision": "ESYE42",
    "timezone": "Europe/Athens"
  },
  "geometry": {
    "type": "Point",
    "coordinates": [
      26.85237,
      37.13344
    ]
  }
}