{
  "type": "Feature",
  "properties": {
    "name": "Mesariá",
    "country": "GR",
    "subdivision": "ESYE42",
    "timezone": "Europe/Athens"
  },
  "geometry": {
    "type": "Point",
    "coordinates": [
      25.44807,
      36.39893
    ]
  }
}