{
  "type": "Feature",
  "properties": {
    "name": "Pylí",
    "country": "GR",
    "subdivision": "ESYE42",
    "timezone": "Europe/Athens"
  },
  "geometry": {
    "type": "Point",
    "coordinates": [
      27.15932,
      36.84472
    ]
  }
}