{
  "type": "Feature",
  "properties": {
    "name": "ZanjÄn",
    "country": "IR",
    "subdivision": "36",
    "timezone": "Asia/Tehran"
  },
  "geometry": {
    "type": "Point",
    "coordinates": [
      48.49628,
      36.67642
    ]
  }
}