{
  "type": "Feature",
  "properties": {
    "name": "Balinsacayao",
    "country": "PH",
    "subdivision": "08",
    "timezone": "Asia/Manila"
  },
  "geometry": {
    "type": "Point",
    "coordinates": [
      124.9595,
      10.681
    ]
  }
}