{
  "type": "Feature",
  "properties": {
    "name": "Biri",
    "country": "PH",
    "subdivision": "08",
    "timezone": "Asia/Manila"
  },
  "geometry": {
    "type": "Point",
    "coordinates": [
      124.36361,
      12.68333
    ]
  }
}