{
  "type": "Feature",
  "properties": {
    "name": "Bunga",
    "country": "PH",
    "subdivision": "08",
    "timezone": "Asia/Manila"
  },
  "geometry": {
    "type": "Point",
    "coordinates": [
      124.5918,
      11.4838
    ]
  }
}