{
  "type": "Feature",
  "properties": {
    "name": "Cabay",
    "country": "PH",
    "subdivision": "08",
    "timezone": "Asia/Manila"
  },
  "geometry": {
    "type": "Point",
    "coordinates": [
      125.49333,
      11.44556
    ]
  }
}