{
  "type": "Feature",
  "properties": {
    "name": "Calape",
    "country": "PH",
    "subdivision": "08",
    "timezone": "Asia/Manila"
  },
  "geometry": {
    "type": "Point",
    "coordinates": [
      125.02139,
      11.9425
    ]
  }
}