{
  "type": "Feature",
  "properties": {
    "name": "Culaba",
    "country": "PH",
    "subdivision": "08",
    "timezone": "Asia/Manila"
  },
  "geometry": {
    "type": "Point",
    "coordinates": [
      124.5425,
      11.65778
    ]
  }
}