{
  "type": "Feature",
  "properties": {
    "name": "Doos",
    "country": "PH",
    "subdivision": "08",
    "timezone": "Asia/Manila"
  },
  "geometry": {
    "type": "Point",
    "coordinates": [
      124.72944,
      10.46528
    ]
  }
}