{
  "type": "Feature",
  "properties": {
    "name": "Gamay",
    "country": "PH",
    "subdivision": "08",
    "timezone": "Asia/Manila"
  },
  "geometry": {
    "type": "Point",
    "coordinates": [
      125.29791,
      12.38542
    ]
  }
}