{
  "type": "Feature",
  "properties": {
    "name": "Hindang",
    "country": "PH",
    "subdivision": "08",
    "timezone": "Asia/Manila"
  },
  "geometry": {
    "type": "Point",
    "coordinates": [
      124.72917,
      10.43417
    ]
  }
}