{
  "type": "Feature",
  "properties": {
    "name": "Kananya",
    "country": "PH",
    "subdivision": "08",
    "timezone": "Asia/Manila"
  },
  "geometry": {
    "type": "Point",
    "coordinates": [
      124.5601,
      11.1867
    ]
  }
}