{
  "type": "Feature",
  "properties": {
    "name": "Las Navas",
    "country": "PH",
    "subdivision": "08",
    "timezone": "Asia/Manila"
  },
  "geometry": {
    "type": "Point",
    "coordinates": [
      125.0313,
      12.3392
    ]
  }
}