{
  "type": "Feature",
  "properties": {
    "name": "Liberty",
    "country": "PH",
    "subdivision": "08",
    "timezone": "Asia/Manila"
  },
  "geometry": {
    "type": "Point",
    "coordinates": [
      125.0025,
      10.87417
    ]
  }
}