{
  "type": "Feature",
  "properties": {
    "name": "Matalom",
    "country": "PH",
    "subdivision": "08",
    "timezone": "Asia/Manila"
  },
  "geometry": {
    "type": "Point",
    "coordinates": [
      124.78778,
      10.28306
    ]
  }
}