{
  "type": "Feature",
  "properties": {
    "name": "Naghalin",
    "country": "PH",
    "subdivision": "08",
    "timezone": "Asia/Manila"
  },
  "geometry": {
    "type": "Point",
    "coordinates": [
      124.5671,
      11.1456
    ]
  }
}