{
  "type": "Feature",
  "properties": {
    "name": "Naval",
    "country": "PH",
    "subdivision": "08",
    "timezone": "Asia/Manila"
  },
  "geometry": {
    "type": "Point",
    "coordinates": [
      124.3975,
      11.56056
    ]
  }
}