{
  "type": "Feature",
  "properties": {
    "name": "Nena",
    "country": "PH",
    "subdivision": "08",
    "timezone": "Asia/Manila"
  },
  "geometry": {
    "type": "Point",
    "coordinates": [
      125.41778,
      11.76583
    ]
  }
}