{
  "type": "Feature",
  "properties": {
    "name": "Palhi",
    "country": "PH",
    "subdivision": "08",
    "timezone": "Asia/Manila"
  },
  "geometry": {
    "type": "Point",
    "coordinates": [
      124.8062,
      10.6498
    ]
  }
}