{
  "type": "Feature",
  "properties": {
    "name": "Palompon",
    "country": "PH",
    "subdivision": "08",
    "timezone": "Asia/Manila"
  },
  "geometry": {
    "type": "Point",
    "coordinates": [
      124.3843,
      11.0508
    ]
  }
}