{
  "type": "Feature",
  "properties": {
    "name": "Panalanoy",
    "country": "PH",
    "subdivision": "08",
    "timezone": "Asia/Manila"
  },
  "geometry": {
    "type": "Point",
    "coordinates": [
      125.00639,
      11.25111
    ]
  }
}