{
  "type": "Feature",
  "properties": {
    "name": "Pangpang",
    "country": "PH",
    "subdivision": "08",
    "timezone": "Asia/Manila"
  },
  "geometry": {
    "type": "Point",
    "coordinates": [
      125.074,
      12.5692
    ]
  }
}