{
  "type": "Feature",
  "properties": {
    "name": "Pawing",
    "country": "PH",
    "subdivision": "08",
    "timezone": "Asia/Manila"
  },
  "geometry": {
    "type": "Point",
    "coordinates": [
      125.00278,
      11.18
    ]
  }
}