{
  "type": "Feature",
  "properties": {
    "name": "Plaridel",
    "country": "PH",
    "subdivision": "08",
    "timezone": "Asia/Manila"
  },
  "geometry": {
    "type": "Point",
    "coordinates": [
      124.7645,
      10.5667
    ]
  }
}