{
  "type": "Feature",
  "properties": {
    "name": "Silanga",
    "country": "PH",
    "subdivision": "08",
    "timezone": "Asia/Manila"
  },
  "geometry": {
    "type": "Point",
    "coordinates": [
      124.84306,
      11.81806
    ]
  }
}