{
  "type": "Feature",
  "properties": {
    "name": "Tinambacan",
    "country": "PH",
    "subdivision": "08",
    "timezone": "Asia/Manila"
  },
  "geometry": {
    "type": "Point",
    "coordinates": [
      124.5025,
      12.0943
    ]
  }
}