{
  "type": "Feature",
  "properties": {
    "name": "Tutubigan",
    "country": "PH",
    "subdivision": "08",
    "timezone": "Asia/Manila"
  },
  "geometry": {
    "type": "Point",
    "coordinates": [
      125.06139,
      11.83972
    ]
  }
}