{
  "type": "Feature",
  "properties": {
    "name": "Barker Heights",
    "country": "US",
    "subdivision": "NC",
    "timezone": "America/New_York"
  },
  "geometry": {
    "type": "Point",
    "coordinates": [
      -82.44401,
      35.31123
    ]
  }
}