{
  "type": "Feature",
  "properties": {
    "name": "Beulaville",
    "country": "US",
    "subdivision": "NC",
    "timezone": "America/New_York"
  },
  "geometry": {
    "type": "Point",
    "coordinates": [
      -77.77387,
      34.92378
    ]
  }
}