{
  "type": "Feature",
  "properties": {
    "name": "Blowing Rock",
    "country": "US",
    "subdivision": "NC",
    "timezone": "America/New_York"
  },
  "geometry": {
    "type": "Point",
    "coordinates": [
      -81.67761,
      36.13513
    ]
  }
}