{
  "type": "Feature",
  "properties": {
    "name": "Boonville",
    "country": "US",
    "subdivision": "NC",
    "timezone": "America/New_York"
  },
  "geometry": {
    "type": "Point",
    "coordinates": [
      -80.70812,
      36.23264
    ]
  }
}