{
  "type": "Feature",
  "properties": {
    "name": "Broadway",
    "country": "US",
    "subdivision": "NC",
    "timezone": "America/New_York"
  },
  "geometry": {
    "type": "Point",
    "coordinates": [
      -79.05308,
      35.45793
    ]
  }
}