{
  "type": "Feature",
  "properties": {
    "name": "Carrboro",
    "country": "US",
    "subdivision": "NC",
    "timezone": "America/New_York"
  },
  "geometry": {
    "type": "Point",
    "coordinates": [
      -79.07529,
      35.91014
    ]
  }
}