{
  "type": "Feature",
  "properties": {
    "name": "Chadbourn",
    "country": "US",
    "subdivision": "NC",
    "timezone": "America/New_York"
  },
  "geometry": {
    "type": "Point",
    "coordinates": [
      -78.82697,
      34.32211
    ]
  }
}