{
  "type": "Feature",
  "properties": {
    "name": "Claremont",
    "country": "US",
    "subdivision": "NC",
    "timezone": "America/New_York"
  },
  "geometry": {
    "type": "Point",
    "coordinates": [
      -81.14619,
      35.71458
    ]
  }
}