{
  "type": "Feature",
  "properties": {
    "name": "Clyde",
    "country": "US",
    "subdivision": "NC",
    "timezone": "America/New_York"
  },
  "geometry": {
    "type": "Point",
    "coordinates": [
      -82.91069,
      35.53344
    ]
  }
}