{
  "type": "Feature",
  "properties": {
    "name": "Concord",
    "country": "US",
    "subdivision": "NC",
    "timezone": "America/New_York"
  },
  "geometry": {
    "type": "Point",
    "coordinates": [
      -80.58158,
      35.40888
    ]
  }
}