{
  "type": "Feature",
  "properties": {
    "name": "Denver",
    "country": "US",
    "subdivision": "NC",
    "timezone": "America/New_York"
  },
  "geometry": {
    "type": "Point",
    "coordinates": [
      -81.0298,
      35.53125
    ]
  }
}