{
  "type": "Feature",
  "properties": {
    "name": "East Flat Rock",
    "country": "US",
    "subdivision": "NC",
    "timezone": "America/New_York"
  },
  "geometry": {
    "type": "Point",
    "coordinates": [
      -82.42206,
      35.28012
    ]
  }
}