{
  "type": "Feature",
  "properties": {
    "name": "Farmville",
    "country": "US",
    "subdivision": "NC",
    "timezone": "America/New_York"
  },
  "geometry": {
    "type": "Point",
    "coordinates": [
      -79.22002,
      35.57071
    ]
  }
}