{
  "type": "Feature",
  "properties": {
    "name": "Glen Alpine",
    "country": "US",
    "subdivision": "NC",
    "timezone": "America/New_York"
  },
  "geometry": {
    "type": "Point",
    "coordinates": [
      -81.77927,
      35.72902
    ]
  }
}