{
  "type": "Feature",
  "properties": {
    "name": "Granite Falls",
    "country": "US",
    "subdivision": "NC",
    "timezone": "America/New_York"
  },
  "geometry": {
    "type": "Point",
    "coordinates": [
      -81.43065,
      35.79652
    ]
  }
}