{
  "type": "Feature",
  "properties": {
    "name": "Haw River",
    "country": "US",
    "subdivision": "NC",
    "timezone": "America/New_York"
  },
  "geometry": {
    "type": "Point",
    "coordinates": [
      -79.36419,
      36.09153
    ]
  }
}