{
  "type": "Feature",
  "properties": {
    "name": "Hemby Bridge",
    "country": "US",
    "subdivision": "NC",
    "timezone": "America/New_York"
  },
  "geometry": {
    "type": "Point",
    "coordinates": [
      -80.62798,
      35.10371
    ]
  }
}