{
  "type": "Feature",
  "properties": {
    "name": "Mebane",
    "country": "US",
    "subdivision": "NC",
    "timezone": "America/New_York"
  },
  "geometry": {
    "type": "Point",
    "coordinates": [
      -79.26696,
      36.09597
    ]
  }
}