{
  "type": "Feature",
  "properties": {
    "name": "Morrisville",
    "country": "US",
    "subdivision": "NC",
    "timezone": "America/New_York"
  },
  "geometry": {
    "type": "Point",
    "coordinates": [
      -78.82556,
      35.82348
    ]
  }
}