{
  "type": "Feature",
  "properties": {
    "name": "Mount Holly",
    "country": "US",
    "subdivision": "NC",
    "timezone": "America/New_York"
  },
  "geometry": {
    "type": "Point",
    "coordinates": [
      -81.01591,
      35.29819
    ]
  }
}