{
  "type": "Feature",
  "properties": {
    "name": "Mountain Home",
    "country": "US",
    "subdivision": "NC",
    "timezone": "America/New_York"
  },
  "geometry": {
    "type": "Point",
    "coordinates": [
      -82.4929,
      35.36956
    ]
  }
}