{
  "type": "Feature",
  "properties": {
    "name": "Murphy",
    "country": "US",
    "subdivision": "NC",
    "timezone": "America/New_York"
  },
  "geometry": {
    "type": "Point",
    "coordinates": [
      -84.03463,
      35.08758
    ]
  }
}