{
  "type": "Feature",
  "properties": {
    "name": "Navassa",
    "country": "US",
    "subdivision": "NC",
    "timezone": "America/New_York"
  },
  "geometry": {
    "type": "Point",
    "coordinates": [
      -78.00749,
      34.25545
    ]
  }
}