{
  "type": "Feature",
  "properties": {
    "name": "Newport",
    "country": "US",
    "subdivision": "NC",
    "timezone": "America/New_York"
  },
  "geometry": {
    "type": "Point",
    "coordinates": [
      -76.85911,
      34.78655
    ]
  }
}