{
  "type": "Feature",
  "properties": {
    "name": "Piney Green",
    "country": "US",
    "subdivision": "NC",
    "timezone": "America/New_York"
  },
  "geometry": {
    "type": "Point",
    "coordinates": [
      -77.32024,
      34.716
    ]
  }
}