{
  "type": "Feature",
  "properties": {
    "name": "Pumpkin Center",
    "country": "US",
    "subdivision": "NC",
    "timezone": "America/New_York"
  },
  "geometry": {
    "type": "Point",
    "coordinates": [
      -81.14119,
      35.5193
    ]
  }
}