{
  "type": "Feature",
  "properties": {
    "name": "Rocky Point",
    "country": "US",
    "subdivision": "NC",
    "timezone": "America/New_York"
  },
  "geometry": {
    "type": "Point",
    "coordinates": [
      -77.88776,
      34.43517
    ]
  }
}