{
  "type": "Feature",
  "properties": {
    "name": "Rockingham",
    "country": "US",
    "subdivision": "NC",
    "timezone": "America/New_York"
  },
  "geometry": {
    "type": "Point",
    "coordinates": [
      -79.77395,
      34.93932
    ]
  }
}