{
  "type": "Feature",
  "properties": {
    "name": "Shallotte",
    "country": "US",
    "subdivision": "NC",
    "timezone": "America/New_York"
  },
  "geometry": {
    "type": "Point",
    "coordinates": [
      -78.38584,
      33.97323
    ]
  }
}