{
  "type": "Feature",
  "properties": {
    "name": "Spring Lake",
    "country": "US",
    "subdivision": "NC",
    "timezone": "America/New_York"
  },
  "geometry": {
    "type": "Point",
    "coordinates": [
      -78.97281,
      35.16794
    ]
  }
}