{
  "type": "Feature",
  "properties": {
    "name": "Stony Point",
    "country": "US",
    "subdivision": "NC",
    "timezone": "America/New_York"
  },
  "geometry": {
    "type": "Point",
    "coordinates": [
      -81.0473,
      35.86347
    ]
  }
}