{
  "type": "Feature",
  "properties": {
    "name": "Swannanoa",
    "country": "US",
    "subdivision": "NC",
    "timezone": "America/New_York"
  },
  "geometry": {
    "type": "Point",
    "coordinates": [
      -82.39984,
      35.59789
    ]
  }
}