{
  "type": "Feature",
  "properties": {
    "name": "Tryon",
    "country": "US",
    "subdivision": "NC",
    "timezone": "America/New_York"
  },
  "geometry": {
    "type": "Point",
    "coordinates": [
      -82.23845,
      35.20817
    ]
  }
}