{
  "type": "Feature",
  "properties": {
    "name": "Tyro",
    "country": "US",
    "subdivision": "NC",
    "timezone": "America/New_York"
  },
  "geometry": {
    "type": "Point",
    "coordinates": [
      -80.37283,
      35.80903
    ]
  }
}