{
  "type": "Feature",
  "properties": {
    "name": "Valdese",
    "country": "US",
    "subdivision": "NC",
    "timezone": "America/New_York"
  },
  "geometry": {
    "type": "Point",
    "coordinates": [
      -81.56315,
      35.74069
    ]
  }
}