{
  "type": "Feature",
  "properties": {
    "name": "Valley Hill",
    "country": "US",
    "subdivision": "NC",
    "timezone": "America/New_York"
  },
  "geometry": {
    "type": "Point",
    "coordinates": [
      -82.48318,
      35.29845
    ]
  }
}