{
  "type": "Feature",
  "properties": {
    "name": "Vander",
    "country": "US",
    "subdivision": "NC",
    "timezone": "America/New_York"
  },
  "geometry": {
    "type": "Point",
    "coordinates": [
      -78.79474,
      35.03211
    ]
  }
}