{
  "type": "Feature",
  "properties": {
    "name": "Wadesboro",
    "country": "US",
    "subdivision": "NC",
    "timezone": "America/New_York"
  },
  "geometry": {
    "type": "Point",
    "coordinates": [
      -80.07673,
      34.96821
    ]
  }
}