{
  "type": "Feature",
  "properties": {
    "name": "Walnut Cove",
    "country": "US",
    "subdivision": "NC",
    "timezone": "America/New_York"
  },
  "geometry": {
    "type": "Point",
    "coordinates": [
      -80.14171,
      36.29541
    ]
  }
}