{
  "type": "Feature",
  "properties": {
    "name": "Weddington",
    "country": "US",
    "subdivision": "NC",
    "timezone": "America/New_York"
  },
  "geometry": {
    "type": "Point",
    "coordinates": [
      -80.7609,
      35.02237
    ]
  }
}