{
  "type": "Feature",
  "properties": {
    "name": "West Jefferson",
    "country": "US",
    "subdivision": "NC",
    "timezone": "America/New_York"
  },
  "geometry": {
    "type": "Point",
    "coordinates": [
      -81.49288,
      36.40374
    ]
  }
}