{
  "type": "Feature",
  "properties": {
    "name": "Wilsons Mills",
    "country": "US",
    "subdivision": "NC",
    "timezone": "America/New_York"
  },
  "geometry": {
    "type": "Point",
    "coordinates": [
      -78.35583,
      35.58405
    ]
  }
}