{
  "type": "Feature",
  "properties": {
    "name": "Windsor",
    "country": "US",
    "subdivision": "NC",
    "timezone": "America/New_York"
  },
  "geometry": {
    "type": "Point",
    "coordinates": [
      -76.94606,
      35.99849
    ]
  }
}