{
  "type": "Feature",
  "properties": {
    "name": "Yanceyville",
    "country": "US",
    "subdivision": "NC",
    "timezone": "America/New_York"
  },
  "geometry": {
    "type": "Point",
    "coordinates": [
      -79.33613,
      36.40403
    ]
  }
}