{
  "type": "Feature",
  "properties": {
    "name": "Dalen",
    "country": "NL",
    "subdivision": "01",
    "timezone": "Europe/Amsterdam"
  },
  "geometry": {
    "type": "Point",
    "coordinates": [
      6.75556,
      52.69917
    ]
  }
}