{
  "type": "Feature",
  "properties": {
    "name": "Emmermeer",
    "country": "NL",
    "subdivision": "01",
    "timezone": "Europe/Amsterdam"
  },
  "geometry": {
    "type": "Point",
    "coordinates": [
      6.89315,
      52.80071
    ]
  }
}