{
  "type": "Feature",
  "properties": {
    "name": "Nieuw-Roden",
    "country": "NL",
    "subdivision": "01",
    "timezone": "Europe/Amsterdam"
  },
  "geometry": {
    "type": "Point",
    "coordinates": [
      6.39722,
      53.13167
    ]
  }
}