{
  "type": "Feature",
  "properties": {
    "name": "Norg",
    "country": "NL",
    "subdivision": "01",
    "timezone": "Europe/Amsterdam"
  },
  "geometry": {
    "type": "Point",
    "coordinates": [
      6.45833,
      53.06667
    ]
  }
}