{
  "type": "Feature",
  "properties": {
    "name": "Odoorn",
    "country": "NL",
    "subdivision": "01",
    "timezone": "Europe/Amsterdam"
  },
  "geometry": {
    "type": "Point",
    "coordinates": [
      6.85139,
      52.84917
    ]
  }
}