{
  "type": "Feature",
  "properties": {
    "name": "Schoonebeek",
    "country": "NL",
    "subdivision": "01",
    "timezone": "Europe/Amsterdam"
  },
  "geometry": {
    "type": "Point",
    "coordinates": [
      6.88472,
      52.6625
    ]
  }
}