{
  "type": "Feature",
  "properties": {
    "name": "Tynaarlo",
    "country": "NL",
    "subdivision": "01",
    "timezone": "Europe/Amsterdam"
  },
  "geometry": {
    "type": "Point",
    "coordinates": [
      6.61667,
      53.0775
    ]
  }
}