{
  "type": "Feature",
  "properties": {
    "name": "Westerbork",
    "country": "NL",
    "subdivision": "01",
    "timezone": "Europe/Amsterdam"
  },
  "geometry": {
    "type": "Point",
    "coordinates": [
      6.60833,
      52.85
    ]
  }
}