{
  "type": "Feature",
  "properties": {
    "name": "Akim Swedru",
    "country": "GH",
    "subdivision": "05",
    "timezone": "Africa/Accra"
  },
  "geometry": {
    "type": "Point",
    "coordinates": [
      -1.01636,
      5.8938
    ]
  }
}