{
  "type": "Feature",
  "properties": {
    "name": "Aksu-Ayuly",
    "country": "KZ",
    "subdivision": "12",
    "timezone": "Asia/Almaty"
  },
  "geometry": {
    "type": "Point",
    "coordinates": [
      73.67272,
      48.76788
    ]
  }
}