{
  "type": "Feature",
  "properties": {
    "name": "Prigorodnoye",
    "country": "KZ",
    "subdivision": "12",
    "timezone": "Asia/Almaty"
  },
  "geometry": {
    "type": "Point",
    "coordinates": [
      75.58438,
      49.69244
    ]
  }
}