{
  "type": "Feature",
  "properties": {
    "name": "Shubarköl",
    "country": "KZ",
    "subdivision": "12",
    "timezone": "Asia/Almaty"
  },
  "geometry": {
    "type": "Point",
    "coordinates": [
      68.80722,
      48.88222
    ]
  }
}