{
  "type": "Feature",
  "properties": {
    "name": "Baka",
    "country": "PH",
    "subdivision": "14",
    "timezone": "Asia/Manila"
  },
  "geometry": {
    "type": "Point",
    "coordinates": [
      124.26417,
      7.27611
    ]
  }
}