{
  "type": "Feature",
  "properties": {
    "name": "Bayanga",
    "country": "PH",
    "subdivision": "14",
    "timezone": "Asia/Manila"
  },
  "geometry": {
    "type": "Point",
    "coordinates": [
      124.25222,
      7.52139
    ]
  }
}