{
  "type": "Feature",
  "properties": {
    "name": "Colonia",
    "country": "PH",
    "subdivision": "14",
    "timezone": "Asia/Manila"
  },
  "geometry": {
    "type": "Point",
    "coordinates": [
      122.1575,
      6.64361
    ]
  }
}