{
  "type": "Feature",
  "properties": {
    "name": "Cotabato",
    "country": "PH",
    "subdivision": "14",
    "timezone": "Asia/Manila"
  },
  "geometry": {
    "type": "Point",
    "coordinates": [
      124.24639,
      7.22361
    ]
  }
}