{
  "type": "Feature",
  "properties": {
    "name": "Digal",
    "country": "PH",
    "subdivision": "14",
    "timezone": "Asia/Manila"
  },
  "geometry": {
    "type": "Point",
    "coordinates": [
      124.79639,
      6.75306
    ]
  }
}