{
  "type": "Feature",
  "properties": {
    "name": "Gang",
    "country": "PH",
    "subdivision": "14",
    "timezone": "Asia/Manila"
  },
  "geometry": {
    "type": "Point",
    "coordinates": [
      124.26639,
      7.24583
    ]
  }
}