{
  "type": "Feature",
  "properties": {
    "name": "Jolo",
    "country": "PH",
    "subdivision": "14",
    "timezone": "Asia/Manila"
  },
  "geometry": {
    "type": "Point",
    "coordinates": [
      121.00222,
      6.05222
    ]
  }
}