{
  "type": "Feature",
  "properties": {
    "name": "Kagay",
    "country": "PH",
    "subdivision": "14",
    "timezone": "Asia/Manila"
  },
  "geometry": {
    "type": "Point",
    "coordinates": [
      120.9074,
      6.0088
    ]
  }
}