{
  "type": "Feature",
  "properties": {
    "name": "Karungdong",
    "country": "PH",
    "subdivision": "14",
    "timezone": "Asia/Manila"
  },
  "geometry": {
    "type": "Point",
    "coordinates": [
      121.263,
      5.8844
    ]
  }
}