{
  "type": "Feature",
  "properties": {
    "name": "Kulay-Kulay",
    "country": "PH",
    "subdivision": "14",
    "timezone": "Asia/Manila"
  },
  "geometry": {
    "type": "Point",
    "coordinates": [
      121.2325,
      5.94528
    ]
  }
}