{
  "type": "Feature",
  "properties": {
    "name": "Labuñgan",
    "country": "PH",
    "subdivision": "14",
    "timezone": "Asia/Manila"
  },
  "geometry": {
    "type": "Point",
    "coordinates": [
      124.235,
      7.10306
    ]
  }
}