{
  "type": "Feature",
  "properties": {
    "name": "Langpas",
    "country": "PH",
    "subdivision": "14",
    "timezone": "Asia/Manila"
  },
  "geometry": {
    "type": "Point",
    "coordinates": [
      120.949,
      5.975
    ]
  }
}