{
  "type": "Feature",
  "properties": {
    "name": "Lugus",
    "country": "PH",
    "subdivision": "14",
    "timezone": "Asia/Manila"
  },
  "geometry": {
    "type": "Point",
    "coordinates": [
      120.82028,
      5.70361
    ]
  }
}