{
  "type": "Feature",
  "properties": {
    "name": "Parang",
    "country": "PH",
    "subdivision": "14",
    "timezone": "Asia/Manila"
  },
  "geometry": {
    "type": "Point",
    "coordinates": [
      124.26973,
      7.37035
    ]
  }
}