{
  "type": "Feature",
  "properties": {
    "name": "Parangan",
    "country": "PH",
    "subdivision": "14",
    "timezone": "Asia/Manila"
  },
  "geometry": {
    "type": "Point",
    "coordinates": [
      119.93833,
      5.08389
    ]
  }
}