{
  "type": "Feature",
  "properties": {
    "name": "Sagasa",
    "country": "PH",
    "subdivision": "14",
    "timezone": "Asia/Manila"
  },
  "geometry": {
    "type": "Point",
    "coordinates": [
      124.57408,
      6.77405
    ]
  }
}