{
  "type": "Feature",
  "properties": {
    "name": "Semut",
    "country": "PH",
    "subdivision": "14",
    "timezone": "Asia/Manila"
  },
  "geometry": {
    "type": "Point",
    "coordinates": [
      122.21889,
      6.66361
    ]
  }
}