{
  "type": "Feature",
  "properties": {
    "name": "Simunul",
    "country": "PH",
    "subdivision": "14",
    "timezone": "Asia/Manila"
  },
  "geometry": {
    "type": "Point",
    "coordinates": [
      119.84944,
      4.89833
    ]
  }
}