{
  "type": "Feature",
  "properties": {
    "name": "Tampakan",
    "country": "PH",
    "subdivision": "14",
    "timezone": "Asia/Manila"
  },
  "geometry": {
    "type": "Point",
    "coordinates": [
      119.79389,
      4.92278
    ]
  }
}