{
  "type": "Feature",
  "properties": {
    "name": "Tunggol",
    "country": "PH",
    "subdivision": "14",
    "timezone": "Asia/Manila"
  },
  "geometry": {
    "type": "Point",
    "coordinates": [
      121.15436,
      5.84458
    ]
  }
}