{
  "type": "Feature",
  "properties": {
    "name": "Dolavón",
    "country": "AR",
    "subdivision": "04",
    "timezone": "America/Argentina/Catamarca"
  },
  "geometry": {
    "type": "Point",
    "coordinates": [
      -65.70651,
      -43.30684
    ]
  }
}