{
  "type": "Feature",
  "properties": {
    "name": "Kelburn",
    "country": "NZ",
    "subdivision": "G2",
    "timezone": "Pacific/Auckland"
  },
  "geometry": {
    "type": "Point",
    "coordinates": [
      174.76667,
      -41.28333
    ]
  }
}