{
  "type": "Feature",
  "properties": {
    "name": "Al Khābūrah",
    "country": "OM",
    "subdivision": "11",
    "timezone": "Asia/Muscat"
  },
  "geometry": {
    "type": "Point",
    "coordinates": [
      57.09313,
      23.97144
    ]
  }
}