{
  "type": "Feature",
  "properties": {
    "name": "Thenia",
    "country": "DZ",
    "subdivision": "40",
    "timezone": "Africa/Algiers"
  },
  "geometry": {
    "type": "Point",
    "coordinates": [
      3.55665,
      36.72544
    ]
  }
}