{
  "type": "Feature",
  "properties": {
    "name": "KÄrsava",
    "country": "LV",
    "subdivision": "78",
    "timezone": "Europe/Riga"
  },
  "geometry": {
    "type": "Point",
    "coordinates": [
      27.68829,
      56.78405
    ]
  }
}