{
  "type": "Feature",
  "properties": {
    "name": "Bengkulu",
    "country": "ID",
    "subdivision": "03",
    "timezone": "Asia/Jakarta"
  },
  "geometry": {
    "type": "Point",
    "coordinates": [
      102.26554,
      -3.80044
    ]
  }
}