{
  "type": "Feature",
  "properties": {
    "name": "Mouila",
    "country": "GA",
    "subdivision": "04",
    "timezone": "Africa/Libreville"
  },
  "geometry": {
    "type": "Point",
    "coordinates": [
      11.05594,
      -1.86846
    ]
  }
}