{
  "type": "Feature",
  "properties": {
    "name": "Ndendé",
    "country": "GA",
    "subdivision": "04",
    "timezone": "Africa/Libreville"
  },
  "geometry": {
    "type": "Point",
    "coordinates": [
      11.35813,
      -2.40077
    ]
  }
}