{
  "type": "Feature",
  "properties": {
    "name": "Belo sur Tsiribihina",
    "country": "MG",
    "subdivision": "54",
    "timezone": "Indian/Antananarivo"
  },
  "geometry": {
    "type": "Point",
    "coordinates": [
      44.54587,
      -19.69787
    ]
  }
}