{
  "type": "Feature",
  "properties": {
    "name": "K’ulashi",
    "country": "GE",
    "subdivision": "66",
    "timezone": "Asia/Tbilisi"
  },
  "geometry": {
    "type": "Point",
    "coordinates": [
      42.34606,
      42.2064
    ]
  }
}