{
  "type": "Feature",
  "properties": {
    "name": "Tupambaé",
    "country": "UY",
    "subdivision": "03",
    "timezone": "America/Montevideo"
  },
  "geometry": {
    "type": "Point",
    "coordinates": [
      -54.76667,
      -32.83333
    ]
  }
}