{
  "type": "Feature",
  "properties": {
    "name": "Chechelnyk",
    "country": "UA",
    "subdivision": "23",
    "timezone": "Europe/Kiev"
  },
  "geometry": {
    "type": "Point",
    "coordinates": [
      29.36469,
      48.21558
    ]
  }
}