{
  "type": "Feature",
  "properties": {
    "name": "Haysyn",
    "country": "UA",
    "subdivision": "23",
    "timezone": "Europe/Kiev"
  },
  "geometry": {
    "type": "Point",
    "coordinates": [
      29.37917,
      48.81294
    ]
  }
}