{
  "type": "Feature",
  "properties": {
    "name": "Klembivka",
    "country": "UA",
    "subdivision": "23",
    "timezone": "Europe/Kiev"
  },
  "geometry": {
    "type": "Point",
    "coordinates": [
      28.40998,
      48.38732
    ]
  }
}