{
  "type": "Feature",
  "properties": {
    "name": "Kozyatyn",
    "country": "UA",
    "subdivision": "23",
    "timezone": "Europe/Kiev"
  },
  "geometry": {
    "type": "Point",
    "coordinates": [
      28.83858,
      49.7164
    ]
  }
}