{
  "type": "Feature",
  "properties": {
    "name": "Orativ",
    "country": "UA",
    "subdivision": "23",
    "timezone": "Europe/Kiev"
  },
  "geometry": {
    "type": "Point",
    "coordinates": [
      29.52889,
      49.18594
    ]
  }
}