{
  "type": "Feature",
  "properties": {
    "name": "Tyvriv",
    "country": "UA",
    "subdivision": "23",
    "timezone": "Europe/Kiev"
  },
  "geometry": {
    "type": "Point",
    "coordinates": [
      28.50044,
      49.01206
    ]
  }
}