{
  "type": "Feature",
  "properties": {
    "name": "Voronovytsya",
    "country": "UA",
    "subdivision": "23",
    "timezone": "Europe/Kiev"
  },
  "geometry": {
    "type": "Point",
    "coordinates": [
      28.68681,
      49.10903
    ]
  }
}