{
  "type": "Feature",
  "properties": {
    "name": "Acoapa",
    "country": "MX",
    "subdivision": "13",
    "timezone": "America/Mexico_City"
  },
  "geometry": {
    "type": "Point",
    "coordinates": [
      -98.48701,
      21.12116
    ]
  }
}