{
  "type": "Feature",
  "properties": {
    "name": "Atengo",
    "country": "MX",
    "subdivision": "13",
    "timezone": "America/Mexico_City"
  },
  "geometry": {
    "type": "Point",
    "coordinates": [
      -99.32714,
      20.17526
    ]
  }
}