{
  "type": "Feature",
  "properties": {
    "name": "Camelia (Barrio la Camelia)",
    "country": "MX",
    "subdivision": "13",
    "timezone": "America/Mexico_City"
  },
  "geometry": {
    "type": "Point",
    "coordinates": [
      -98.72222,
      20.14917
    ]
  }
}