{
  "type": "Feature",
  "properties": {
    "name": "Campestre Villas del Álamo",
    "country": "MX",
    "subdivision": "13",
    "timezone": "America/Mexico_City"
  },
  "geometry": {
    "type": "Point",
    "coordinates": [
      -98.70722,
      20.10167
    ]
  }
}