{
  "type": "Feature",
  "properties": {
    "name": "Cantera de Villagrán",
    "country": "MX",
    "subdivision": "13",
    "timezone": "America/Mexico_City"
  },
  "geometry": {
    "type": "Point",
    "coordinates": [
      -99.30917,
      19.84083
    ]
  }
}