{
  "type": "Feature",
  "properties": {
    "name": "Chicavasco",
    "country": "MX",
    "subdivision": "13",
    "timezone": "America/Mexico_City"
  },
  "geometry": {
    "type": "Point",
    "coordinates": [
      -98.95386,
      20.19715
    ]
  }
}