{
  "type": "Feature",
  "properties": {
    "name": "Chililico",
    "country": "MX",
    "subdivision": "13",
    "timezone": "America/Mexico_City"
  },
  "geometry": {
    "type": "Point",
    "coordinates": [
      -98.43556,
      21.13444
    ]
  }
}