{
  "type": "Feature",
  "properties": {
    "name": "Coyotillos",
    "country": "MX",
    "subdivision": "13",
    "timezone": "America/Mexico_City"
  },
  "geometry": {
    "type": "Point",
    "coordinates": [
      -99.15817,
      19.9998
    ]
  }
}