{
  "type": "Feature",
  "properties": {
    "name": "El Huaxtho",
    "country": "MX",
    "subdivision": "13",
    "timezone": "America/Mexico_City"
  },
  "geometry": {
    "type": "Point",
    "coordinates": [
      -98.96222,
      20.23444
    ]
  }
}