{
  "type": "Feature",
  "properties": {
    "name": "El Moreno (San Miguel Moreno)",
    "country": "MX",
    "subdivision": "13",
    "timezone": "America/Mexico_City"
  },
  "geometry": {
    "type": "Point",
    "coordinates": [
      -99.17361,
      20.30139
    ]
  }
}