{
  "type": "Feature",
  "properties": {
    "name": "El Saucillo (Fraccionamiento)",
    "country": "MX",
    "subdivision": "13",
    "timezone": "America/Mexico_City"
  },
  "geometry": {
    "type": "Point",
    "coordinates": [
      -98.73194,
      20.06778
    ]
  }
}