{
  "type": "Feature",
  "properties": {
    "name": "Huitzitzilingo",
    "country": "MX",
    "subdivision": "13",
    "timezone": "America/Mexico_City"
  },
  "geometry": {
    "type": "Point",
    "coordinates": [
      -98.65693,
      21.17295
    ]
  }
}