{
  "type": "Feature",
  "properties": {
    "name": "La Amistad",
    "country": "MX",
    "subdivision": "13",
    "timezone": "America/Mexico_City"
  },
  "geometry": {
    "type": "Point",
    "coordinates": [
      -99.32028,
      20.00833
    ]
  }
}