{
  "type": "Feature",
  "properties": {
    "name": "Llano Largo",
    "country": "MX",
    "subdivision": "13",
    "timezone": "America/Mexico_City"
  },
  "geometry": {
    "type": "Point",
    "coordinates": [
      -99.76556,
      20.30111
    ]
  }
}