{
  "type": "Feature",
  "properties": {
    "name": "Mamithi",
    "country": "MX",
    "subdivision": "13",
    "timezone": "America/Mexico_City"
  },
  "geometry": {
    "type": "Point",
    "coordinates": [
      -99.65797,
      20.41003
    ]
  }
}