{
  "type": "Feature",
  "properties": {
    "name": "Pachiquita",
    "country": "MX",
    "subdivision": "13",
    "timezone": "America/Mexico_City"
  },
  "geometry": {
    "type": "Point",
    "coordinates": [
      -98.33478,
      20.84608
    ]
  }
}