{
  "type": "Feature",
  "properties": {
    "name": "Pañhé",
    "country": "MX",
    "subdivision": "13",
    "timezone": "America/Mexico_City"
  },
  "geometry": {
    "type": "Point",
    "coordinates": [
      -99.69667,
      20.52167
    ]
  }
}