{
  "type": "Feature",
  "properties": {
    "name": "Parque Urbano Napateco",
    "country": "MX",
    "subdivision": "13",
    "timezone": "America/Mexico_City"
  },
  "geometry": {
    "type": "Point",
    "coordinates": [
      -98.34083,
      20.14278
    ]
  }
}