{
  "type": "Feature",
  "properties": {
    "name": "Presas",
    "country": "MX",
    "subdivision": "13",
    "timezone": "America/Mexico_City"
  },
  "geometry": {
    "type": "Point",
    "coordinates": [
      -99.25242,
      20.15946
    ]
  }
}