{
  "type": "Feature",
  "properties": {
    "name": "Residencial Arboledas",
    "country": "MX",
    "subdivision": "13",
    "timezone": "America/Mexico_City"
  },
  "geometry": {
    "type": "Point",
    "coordinates": [
      -99.30167,
      20.06444
    ]
  }
}