{
  "type": "Feature",
  "properties": {
    "name": "San Antonio",
    "country": "MX",
    "subdivision": "13",
    "timezone": "America/Mexico_City"
  },
  "geometry": {
    "type": "Point",
    "coordinates": [
      -99.71038,
      20.53204
    ]
  }
}