{
  "type": "Feature",
  "properties": {
    "name": "San Antonio el Paso",
    "country": "MX",
    "subdivision": "13",
    "timezone": "America/Mexico_City"
  },
  "geometry": {
    "type": "Point",
    "coordinates": [
      -98.61611,
      20.14722
    ]
  }
}