{
  "type": "Feature",
  "properties": {
    "name": "San Juan Tilcuautla",
    "country": "MX",
    "subdivision": "13",
    "timezone": "America/Mexico_City"
  },
  "geometry": {
    "type": "Point",
    "coordinates": [
      -98.80112,
      20.15873
    ]
  }
}