{
  "type": "Feature",
  "properties": {
    "name": "San Pablo el Grande",
    "country": "MX",
    "subdivision": "13",
    "timezone": "America/Mexico_City"
  },
  "geometry": {
    "type": "Point",
    "coordinates": [
      -98.15999,
      20.36127
    ]
  }
}