{
  "type": "Feature",
  "properties": {
    "name": "San Gabriel",
    "country": "MX",
    "subdivision": "13",
    "timezone": "America/Mexico_City"
  },
  "geometry": {
    "type": "Point",
    "coordinates": [
      -99.33502,
      20.17154
    ]
  }
}