{
  "type": "Feature",
  "properties": {
    "name": "San Bartolo Tutotepec",
    "country": "MX",
    "subdivision": "13",
    "timezone": "America/Mexico_City"
  },
  "geometry": {
    "type": "Point",
    "coordinates": [
      -98.2008,
      20.39841
    ]
  }
}