{
  "type": "Feature",
  "properties": {
    "name": "San Antonio el Grande",
    "country": "MX",
    "subdivision": "13",
    "timezone": "America/Mexico_City"
  },
  "geometry": {
    "type": "Point",
    "coordinates": [
      -98.03484,
      20.45683
    ]
  }
}