{
  "type": "Feature",
  "properties": {
    "name": "Santa Ana Hueytlalpan",
    "country": "MX",
    "subdivision": "13",
    "timezone": "America/Mexico_City"
  },
  "geometry": {
    "type": "Point",
    "coordinates": [
      -98.31209,
      20.17484
    ]
  }
}