{
  "type": "Feature",
  "properties": {
    "name": "Santiago Tlautla",
    "country": "MX",
    "subdivision": "13",
    "timezone": "America/Mexico_City"
  },
  "geometry": {
    "type": "Point",
    "coordinates": [
      -99.36909,
      19.96222
    ]
  }
}