{
  "type": "Feature",
  "properties": {
    "name": "Santiago Tlaltepoxco",
    "country": "MX",
    "subdivision": "13",
    "timezone": "America/Mexico_City"
  },
  "geometry": {
    "type": "Point",
    "coordinates": [
      -99.26046,
      19.88365
    ]
  }
}