{
  "type": "Feature",
  "properties": {
    "name": "Santa Ana de Allende",
    "country": "MX",
    "subdivision": "13",
    "timezone": "America/Mexico_City"
  },
  "geometry": {
    "type": "Point",
    "coordinates": [
      -98.98606,
      21.12301
    ]
  }
}