{
  "type": "Feature",
  "properties": {
    "name": "Santa Clara",
    "country": "MX",
    "subdivision": "13",
    "timezone": "America/Mexico_City"
  },
  "geometry": {
    "type": "Point",
    "coordinates": [
      -98.57778,
      19.69889
    ]
  }
}