{
  "type": "Feature",
  "properties": {
    "name": "Santa Ana Tlachiahualpa",
    "country": "MX",
    "subdivision": "13",
    "timezone": "America/Mexico_City"
  },
  "geometry": {
    "type": "Point",
    "coordinates": [
      -98.90885,
      19.76869
    ]
  }
}