{
  "type": "Feature",
  "properties": {
    "name": "Santiago Tepeyahualco",
    "country": "MX",
    "subdivision": "13",
    "timezone": "America/Mexico_City"
  },
  "geometry": {
    "type": "Point",
    "coordinates": [
      -98.6697,
      19.84864
    ]
  }
}