{
  "type": "Feature",
  "properties": {
    "name": "Tasquillo",
    "country": "MX",
    "subdivision": "13",
    "timezone": "America/Mexico_City"
  },
  "geometry": {
    "type": "Point",
    "coordinates": [
      -99.31352,
      20.54836
    ]
  }
}