{
  "type": "Feature",
  "properties": {
    "name": "Tecozautla",
    "country": "MX",
    "subdivision": "13",
    "timezone": "America/Mexico_City"
  },
  "geometry": {
    "type": "Point",
    "coordinates": [
      -99.63449,
      20.53359
    ]
  }
}