{
  "type": "Feature",
  "properties": {
    "name": "Tepeitic",
    "country": "MX",
    "subdivision": "13",
    "timezone": "America/Mexico_City"
  },
  "geometry": {
    "type": "Point",
    "coordinates": [
      -99.29084,
      20.24123
    ]
  }
}