{
  "type": "Feature",
  "properties": {
    "name": "Tepehuacán de Guerrero",
    "country": "MX",
    "subdivision": "13",
    "timezone": "America/Mexico_City"
  },
  "geometry": {
    "type": "Point",
    "coordinates": [
      -98.84184,
      21.0135
    ]
  }
}