{
  "type": "Feature",
  "properties": {
    "name": "Texcaltepec",
    "country": "MX",
    "subdivision": "13",
    "timezone": "America/Mexico_City"
  },
  "geometry": {
    "type": "Point",
    "coordinates": [
      -98.32417,
      20.03028
    ]
  }
}