{
  "type": "Feature",
  "properties": {
    "name": "Tianguistengo",
    "country": "MX",
    "subdivision": "13",
    "timezone": "America/Mexico_City"
  },
  "geometry": {
    "type": "Point",
    "coordinates": [
      -98.63209,
      20.72796
    ]
  }
}