{
  "type": "Feature",
  "properties": {
    "name": "Tlahuelompa (San Francisco Tlahuelompa)",
    "country": "MX",
    "subdivision": "13",
    "timezone": "America/Mexico_City"
  },
  "geometry": {
    "type": "Point",
    "coordinates": [
      -98.57522,
      20.65082
    ]
  }
}