{
  "type": "Feature",
  "properties": {
    "name": "Tlalchiyahualica",
    "country": "MX",
    "subdivision": "13",
    "timezone": "America/Mexico_City"
  },
  "geometry": {
    "type": "Point",
    "coordinates": [
      -98.39975,
      20.97086
    ]
  }
}