{
  "type": "Feature",
  "properties": {
    "name": "Tolcayuca",
    "country": "MX",
    "subdivision": "13",
    "timezone": "America/Mexico_City"
  },
  "geometry": {
    "type": "Point",
    "coordinates": [
      -98.91941,
      19.95814
    ]
  }
}