{
  "type": "Feature",
  "properties": {
    "name": "Tulancingo",
    "country": "MX",
    "subdivision": "13",
    "timezone": "America/Mexico_City"
  },
  "geometry": {
    "type": "Point",
    "coordinates": [
      -98.36288,
      20.08355
    ]
  }
}