{
  "type": "Feature",
  "properties": {
    "name": "Tula de Allende",
    "country": "MX",
    "subdivision": "13",
    "timezone": "America/Mexico_City"
  },
  "geometry": {
    "type": "Point",
    "coordinates": [
      -99.34397,
      20.05161
    ]
  }
}