{
  "type": "Feature",
  "properties": {
    "name": "Xiteje de Zapata",
    "country": "MX",
    "subdivision": "13",
    "timezone": "America/Mexico_City"
  },
  "geometry": {
    "type": "Point",
    "coordinates": [
      -99.38872,
      20.09728
    ]
  }
}