{
  "type": "Feature",
  "properties": {
    "name": "Xolostitla de Morelos (Xolostitla)",
    "country": "MX",
    "subdivision": "13",
    "timezone": "America/Mexico_City"
  },
  "geometry": {
    "type": "Point",
    "coordinates": [
      -98.63861,
      20.06639
    ]
  }
}