{
  "type": "Feature",
  "properties": {
    "name": "Zempoala",
    "country": "MX",
    "subdivision": "13",
    "timezone": "America/Mexico_City"
  },
  "geometry": {
    "type": "Point",
    "coordinates": [
      -98.666,
      19.91587
    ]
  }
}