{
  "type": "Feature",
  "properties": {
    "name": "Zocea",
    "country": "MX",
    "subdivision": "13",
    "timezone": "America/Mexico_City"
  },
  "geometry": {
    "type": "Point",
    "coordinates": [
      -99.35742,
      20.4376
    ]
  }
}