{
  "type": "Feature",
  "properties": {
    "name": "Zotoluca",
    "country": "MX",
    "subdivision": "13",
    "timezone": "America/Mexico_City"
  },
  "geometry": {
    "type": "Point",
    "coordinates": [
      -98.51094,
      19.61063
    ]
  }
}