{
  "type": "Feature",
  "properties": {
    "name": "Slepče",
    "country": "MK",
    "subdivision": "D3",
    "timezone": "Europe/Skopje"
  },
  "geometry": {
    "type": "Point",
    "coordinates": [
      21.175,
      41.23333
    ]
  }
}