{
  "type": "Feature",
  "properties": {
    "name": "Ban Na",
    "country": "TH",
    "subdivision": "09",
    "timezone": "Asia/Bangkok"
  },
  "geometry": {
    "type": "Point",
    "coordinates": [
      99.73283,
      17.01717
    ]
  }
}