{
  "type": "Feature",
  "properties": {
    "name": "Alice",
    "country": "ZA",
    "subdivision": "05",
    "timezone": "Africa/Johannesburg"
  },
  "geometry": {
    "type": "Point",
    "coordinates": [
      26.8344,
      -32.78749
    ]
  }
}