{
  "type": "Feature",
  "properties": {
    "name": "East London",
    "country": "ZA",
    "subdivision": "05",
    "timezone": "Africa/Johannesburg"
  },
  "geometry": {
    "type": "Point",
    "coordinates": [
      27.91162,
      -33.01529
    ]
  }
}