{
  "type": "Feature",
  "properties": {
    "name": "Fort Beaufort",
    "country": "ZA",
    "subdivision": "05",
    "timezone": "Africa/Johannesburg"
  },
  "geometry": {
    "type": "Point",
    "coordinates": [
      26.63376,
      -32.77477
    ]
  }
}