{
  "type": "Feature",
  "properties": {
    "name": "Kirkwood",
    "country": "ZA",
    "subdivision": "05",
    "timezone": "Africa/Johannesburg"
  },
  "geometry": {
    "type": "Point",
    "coordinates": [
      25.44279,
      -33.39829
    ]
  }
}