{
  "type": "Feature",
  "properties": {
    "name": "Port Elizabeth",
    "country": "ZA",
    "subdivision": "05",
    "timezone": "Africa/Johannesburg"
  },
  "geometry": {
    "type": "Point",
    "coordinates": [
      25.61494,
      -33.96109
    ]
  }
}