{
  "type": "Feature",
  "properties": {
    "name": "Port Alfred",
    "country": "ZA",
    "subdivision": "05",
    "timezone": "Africa/Johannesburg"
  },
  "geometry": {
    "type": "Point",
    "coordinates": [
      26.88329,
      -33.58601
    ]
  }
}