{
  "type": "Feature",
  "properties": {
    "name": "Sok Kwu Wan",
    "country": "HK",
    "subdivision": "NIS",
    "timezone": "Asia/Hong_Kong"
  },
  "geometry": {
    "type": "Point",
    "coordinates": [
      114.13159,
      22.20453
    ]
  }
}