{
  "type": "Feature",
  "properties": {
    "name": "Sekondi-Takoradi",
    "country": "GH",
    "subdivision": "09",
    "timezone": "Africa/Accra"
  },
  "geometry": {
    "type": "Point",
    "coordinates": [
      -1.75773,
      4.92678
    ]
  }
}