{
  "type": "Feature",
  "properties": {
    "name": "Shama Junction",
    "country": "GH",
    "subdivision": "09",
    "timezone": "Africa/Accra"
  },
  "geometry": {
    "type": "Point",
    "coordinates": [
      -1.66437,
      5.01806
    ]
  }
}