{
  "type": "Feature",
  "properties": {
    "name": "Tarkwa",
    "country": "GH",
    "subdivision": "09",
    "timezone": "Africa/Accra"
  },
  "geometry": {
    "type": "Point",
    "coordinates": [
      -1.98956,
      5.30383
    ]
  }
}