{
  "type": "Feature",
  "properties": {
    "name": "Engure",
    "country": "LV",
    "subdivision": "29",
    "timezone": "Europe/Riga"
  },
  "geometry": {
    "type": "Point",
    "coordinates": [
      23.22527,
      57.16061
    ]
  }
}