{
  "type": "Feature",
  "properties": {
    "name": "Tabuaço",
    "country": "PT",
    "subdivision": "22",
    "timezone": "Europe/Lisbon"
  },
  "geometry": {
    "type": "Point",
    "coordinates": [
      -7.56793,
      41.11615
    ]
  }
}