{
  "type": "Feature",
  "properties": {
    "name": "Askaniya-Nova",
    "country": "UA",
    "subdivision": "08",
    "timezone": "Europe/Kiev"
  },
  "geometry": {
    "type": "Point",
    "coordinates": [
      33.87128,
      46.45406
    ]
  }
}