{
  "type": "Feature",
  "properties": {
    "name": "Dnipryany",
    "country": "UA",
    "subdivision": "08",
    "timezone": "Europe/Kiev"
  },
  "geometry": {
    "type": "Point",
    "coordinates": [
      33.26632,
      46.74849
    ]
  }
}