{
  "type": "Feature",
  "properties": {
    "name": "Kherson",
    "country": "UA",
    "subdivision": "08",
    "timezone": "Europe/Kiev"
  },
  "geometry": {
    "type": "Point",
    "coordinates": [
      32.61458,
      46.63695
    ]
  }
}