{
  "type": "Feature",
  "properties": {
    "name": "Komyshany",
    "country": "UA",
    "subdivision": "08",
    "timezone": "Europe/Kiev"
  },
  "geometry": {
    "type": "Point",
    "coordinates": [
      32.50343,
      46.63995
    ]
  }
}