{
  "type": "Feature",
  "properties": {
    "name": "Kozachi Laheri",
    "country": "UA",
    "subdivision": "08",
    "timezone": "Europe/Kiev"
  },
  "geometry": {
    "type": "Point",
    "coordinates": [
      32.98194,
      46.70538
    ]
  }
}