{
  "type": "Feature",
  "properties": {
    "name": "Malokakhovka",
    "country": "UA",
    "subdivision": "08",
    "timezone": "Europe/Kiev"
  },
  "geometry": {
    "type": "Point",
    "coordinates": [
      33.44662,
      46.78292
    ]
  }
}