{
  "type": "Feature",
  "properties": {
    "name": "Naddnipryanske",
    "country": "UA",
    "subdivision": "08",
    "timezone": "Europe/Kiev"
  },
  "geometry": {
    "type": "Point",
    "coordinates": [
      32.7053,
      46.73591
    ]
  }
}