{
  "type": "Feature",
  "properties": {
    "name": "Novovorontsovka",
    "country": "UA",
    "subdivision": "08",
    "timezone": "Europe/Kiev"
  },
  "geometry": {
    "type": "Point",
    "coordinates": [
      33.92317,
      47.50499
    ]
  }
}