{
  "type": "Feature",
  "properties": {
    "name": "Syvaske",
    "country": "UA",
    "subdivision": "08",
    "timezone": "Europe/Kiev"
  },
  "geometry": {
    "type": "Point",
    "coordinates": [
      34.54683,
      46.38503
    ]
  }
}