{
  "type": "Feature",
  "properties": {
    "name": "Carmen De La Legua Reynoso",
    "country": "PE",
    "subdivision": "07",
    "timezone": "America/Lima"
  },
  "geometry": {
    "type": "Point",
    "coordinates": [
      -77.09802,
      -12.05354
    ]
  }
}