{
  "type": "Feature",
  "properties": {
    "name": "Bekovo",
    "country": "RU",
    "subdivision": "57",
    "timezone": "Europe/Moscow"
  },
  "geometry": {
    "type": "Point",
    "coordinates": [
      43.71199,
      52.46632
    ]
  }
}