{
  "type": "Feature",
  "properties": {
    "name": "Belinskiy",
    "country": "RU",
    "subdivision": "57",
    "timezone": "Europe/Moscow"
  },
  "geometry": {
    "type": "Point",
    "coordinates": [
      43.41647,
      52.96474
    ]
  }
}