{
  "type": "Feature",
  "properties": {
    "name": "Bessonovka",
    "country": "RU",
    "subdivision": "57",
    "timezone": "Europe/Moscow"
  },
  "geometry": {
    "type": "Point",
    "coordinates": [
      45.04069,
      53.30968
    ]
  }
}