{
  "type": "Feature",
  "properties": {
    "name": "Sursk",
    "country": "RU",
    "subdivision": "57",
    "timezone": "Europe/Moscow"
  },
  "geometry": {
    "type": "Point",
    "coordinates": [
      45.68461,
      53.07542
    ]
  }
}