{
  "type": "Feature",
  "properties": {
    "name": "Adășeni",
    "country": "RO",
    "subdivision": "07",
    "timezone": "Europe/Bucharest"
  },
  "geometry": {
    "type": "Point",
    "coordinates": [
      26.93789,
      48.0692
    ]
  }
}