{
  "type": "Feature",
  "properties": {
    "name": "Dimăcheni",
    "country": "RO",
    "subdivision": "07",
    "timezone": "Europe/Bucharest"
  },
  "geometry": {
    "type": "Point",
    "coordinates": [
      26.5456,
      47.91139
    ]
  }
}