{
  "type": "Feature",
  "properties": {
    "name": "Manoleasa",
    "country": "RO",
    "subdivision": "07",
    "timezone": "Europe/Bucharest"
  },
  "geometry": {
    "type": "Point",
    "coordinates": [
      27.06667,
      47.98333
    ]
  }
}