{
  "type": "Feature",
  "properties": {
    "name": "Oroftiana",
    "country": "RO",
    "subdivision": "07",
    "timezone": "Europe/Bucharest"
  },
  "geometry": {
    "type": "Point",
    "coordinates": [
      26.34856,
      48.17758
    ]
  }
}