{
  "type": "Feature",
  "properties": {
    "name": "Prăjeni",
    "country": "RO",
    "subdivision": "07",
    "timezone": "Europe/Bucharest"
  },
  "geometry": {
    "type": "Point",
    "coordinates": [
      27.01667,
      47.51667
    ]
  }
}