{
  "type": "Feature",
  "properties": {
    "name": "Rădeni",
    "country": "RO",
    "subdivision": "07",
    "timezone": "Europe/Bucharest"
  },
  "geometry": {
    "type": "Point",
    "coordinates": [
      26.89249,
      47.51186
    ]
  }
}