{
  "type": "Feature",
  "properties": {
    "name": "Românești",
    "country": "RO",
    "subdivision": "07",
    "timezone": "Europe/Bucharest"
  },
  "geometry": {
    "type": "Point",
    "coordinates": [
      27.24027,
      47.73141
    ]
  }
}