{
  "type": "Feature",
  "properties": {
    "name": "Bâsca Rozilei",
    "country": "RO",
    "subdivision": "11",
    "timezone": "Europe/Bucharest"
  },
  "geometry": {
    "type": "Point",
    "coordinates": [
      26.33714,
      45.45387
    ]
  }
}