{
  "type": "Feature",
  "properties": {
    "name": "Bâscenii de Jos",
    "country": "RO",
    "subdivision": "11",
    "timezone": "Europe/Bucharest"
  },
  "geometry": {
    "type": "Point",
    "coordinates": [
      26.32122,
      45.24708
    ]
  }
}