{
  "type": "Feature",
  "properties": {
    "name": "Cilibia",
    "country": "RO",
    "subdivision": "11",
    "timezone": "Europe/Bucharest"
  },
  "geometry": {
    "type": "Point",
    "coordinates": [
      27.06667,
      45.06667
    ]
  }
}