{
  "type": "Feature",
  "properties": {
    "name": "Cochirleanca",
    "country": "RO",
    "subdivision": "11",
    "timezone": "Europe/Bucharest"
  },
  "geometry": {
    "type": "Point",
    "coordinates": [
      27.03333,
      45.21667
    ]
  }
}