{
  "type": "Feature",
  "properties": {
    "name": "Costeşti",
    "country": "RO",
    "subdivision": "11",
    "timezone": "Europe/Bucharest"
  },
  "geometry": {
    "type": "Point",
    "coordinates": [
      26.76667,
      45.05
    ]
  }
}