{
  "type": "Feature",
  "properties": {
    "name": "Dedulești",
    "country": "RO",
    "subdivision": "11",
    "timezone": "Europe/Bucharest"
  },
  "geometry": {
    "type": "Point",
    "coordinates": [
      26.96737,
      45.47003
    ]
  }
}