{
  "type": "Feature",
  "properties": {
    "name": "Florica",
    "country": "RO",
    "subdivision": "11",
    "timezone": "Europe/Bucharest"
  },
  "geometry": {
    "type": "Point",
    "coordinates": [
      26.76627,
      44.90802
    ]
  }
}