{
  "type": "Feature",
  "properties": {
    "name": "Glodeanu-Sărat",
    "country": "RO",
    "subdivision": "11",
    "timezone": "Europe/Bucharest"
  },
  "geometry": {
    "type": "Point",
    "coordinates": [
      26.65,
      44.86667
    ]
  }
}