{
  "type": "Feature",
  "properties": {
    "name": "Lunca Jariștei",
    "country": "RO",
    "subdivision": "11",
    "timezone": "Europe/Bucharest"
  },
  "geometry": {
    "type": "Point",
    "coordinates": [
      26.25483,
      45.48231
    ]
  }
}