{
  "type": "Feature",
  "properties": {
    "name": "Mărunțișu",
    "country": "RO",
    "subdivision": "11",
    "timezone": "Europe/Bucharest"
  },
  "geometry": {
    "type": "Point",
    "coordinates": [
      26.35421,
      45.2861
    ]
  }
}