{
  "type": "Feature",
  "properties": {
    "name": "Tăbărăști",
    "country": "RO",
    "subdivision": "11",
    "timezone": "Europe/Bucharest"
  },
  "geometry": {
    "type": "Point",
    "coordinates": [
      26.91943,
      45.07948
    ]
  }
}