{
  "type": "Feature",
  "properties": {
    "name": "Vintileanca",
    "country": "RO",
    "subdivision": "11",
    "timezone": "Europe/Bucharest"
  },
  "geometry": {
    "type": "Point",
    "coordinates": [
      26.58005,
      44.985
    ]
  }
}