{
  "type": "Feature",
  "properties": {
    "name": "Boromlia",
    "country": "UA",
    "subdivision": "21",
    "timezone": "Europe/Kiev"
  },
  "geometry": {
    "type": "Point",
    "coordinates": [
      34.97042,
      50.61839
    ]
  }
}