{
  "type": "Feature",
  "properties": {
    "name": "Sumy",
    "country": "UA",
    "subdivision": "21",
    "timezone": "Europe/Kiev"
  },
  "geometry": {
    "type": "Point",
    "coordinates": [
      34.80029,
      50.9216
    ]
  }
}