{
  "type": "Feature",
  "properties": {
    "name": "Juncos",
    "country": "PR",
    "subdivision": "077",
    "timezone": "America/Puerto_Rico"
  },
  "geometry": {
    "type": "Point",
    "coordinates": [
      -65.921,
      18.22746
    ]
  }
}