{
  "type": "Feature",
  "properties": {
    "name": "Chelghoum el Aïd",
    "country": "DZ",
    "subdivision": "48",
    "timezone": "Africa/Algiers"
  },
  "geometry": {
    "type": "Point",
    "coordinates": [
      6.16651,
      36.16286
    ]
  }
}