{
  "type": "Feature",
  "properties": {
    "name": "Mila",
    "country": "DZ",
    "subdivision": "48",
    "timezone": "Africa/Algiers"
  },
  "geometry": {
    "type": "Point",
    "coordinates": [
      6.26444,
      36.45028
    ]
  }
}