{
  "type": "Feature",
  "properties": {
    "name": "Rāmshīr",
    "country": "IR",
    "subdivision": "15",
    "timezone": "Asia/Tehran"
  },
  "geometry": {
    "type": "Point",
    "coordinates": [
      49.40787,
      30.89315
    ]
  }
}