{
  "type": "Feature",
  "properties": {
    "name": "Shādegān",
    "country": "IR",
    "subdivision": "15",
    "timezone": "Asia/Tehran"
  },
  "geometry": {
    "type": "Point",
    "coordinates": [
      48.66497,
      30.64924
    ]
  }
}