{
  "type": "Feature",
  "properties": {
    "name": "Albrechtice nad Orlicí",
    "country": "CZ",
    "subdivision": "82",
    "timezone": "Europe/Prague"
  },
  "geometry": {
    "type": "Point",
    "coordinates": [
      16.06437,
      50.13979
    ]
  }
}