{
  "type": "Feature",
  "properties": {
    "name": "Hořice",
    "country": "CZ",
    "subdivision": "82",
    "timezone": "Europe/Prague"
  },
  "geometry": {
    "type": "Point",
    "coordinates": [
      15.63183,
      50.36609
    ]
  }
}