{
  "type": "Feature",
  "properties": {
    "name": "Kopidlno",
    "country": "CZ",
    "subdivision": "82",
    "timezone": "Europe/Prague"
  },
  "geometry": {
    "type": "Point",
    "coordinates": [
      15.27029,
      50.33085
    ]
  }
}