{
  "type": "Feature",
  "properties": {
    "name": "Machov",
    "country": "CZ",
    "subdivision": "82",
    "timezone": "Europe/Prague"
  },
  "geometry": {
    "type": "Point",
    "coordinates": [
      16.2769,
      50.49927
    ]
  }
}