{
  "type": "Feature",
  "properties": {
    "name": "Ostroměř",
    "country": "CZ",
    "subdivision": "82",
    "timezone": "Europe/Prague"
  },
  "geometry": {
    "type": "Point",
    "coordinates": [
      15.54949,
      50.37246
    ]
  }
}