{
  "type": "Feature",
  "properties": {
    "name": "Špindlerův Mlýn",
    "country": "CZ",
    "subdivision": "82",
    "timezone": "Europe/Prague"
  },
  "geometry": {
    "type": "Point",
    "coordinates": [
      15.60944,
      50.72615
    ]
  }
}