{
  "type": "Feature",
  "properties": {
    "name": "Stará Paka",
    "country": "CZ",
    "subdivision": "82",
    "timezone": "Europe/Prague"
  },
  "geometry": {
    "type": "Point",
    "coordinates": [
      15.49444,
      50.51032
    ]
  }
}