{
  "type": "Feature",
  "properties": {
    "name": "Úpice",
    "country": "CZ",
    "subdivision": "82",
    "timezone": "Europe/Prague"
  },
  "geometry": {
    "type": "Point",
    "coordinates": [
      16.01607,
      50.51237
    ]
  }
}