{
  "type": "Feature",
  "properties": {
    "name": "Velké Poříčí",
    "country": "CZ",
    "subdivision": "82",
    "timezone": "Europe/Prague"
  },
  "geometry": {
    "type": "Point",
    "coordinates": [
      16.18931,
      50.46177
    ]
  }
}