{
  "type": "Feature",
  "properties": {
    "name": "Všestary",
    "country": "CZ",
    "subdivision": "82",
    "timezone": "Europe/Prague"
  },
  "geometry": {
    "type": "Point",
    "coordinates": [
      15.75983,
      50.2566
    ]
  }
}