{
  "type": "Feature",
  "properties": {
    "name": "Alquízar",
    "country": "CU",
    "subdivision": "AR",
    "timezone": "America/Havana"
  },
  "geometry": {
    "type": "Point",
    "coordinates": [
      -82.58392,
      22.80517
    ]
  }
}