{
  "type": "Feature",
  "properties": {
    "name": "Cabañas",
    "country": "CU",
    "subdivision": "AR",
    "timezone": "America/Havana"
  },
  "geometry": {
    "type": "Point",
    "coordinates": [
      -82.92214,
      22.97944
    ]
  }
}