{
  "type": "Feature",
  "properties": {
    "name": "San Antonio de los Baños",
    "country": "CU",
    "subdivision": "AR",
    "timezone": "America/Havana"
  },
  "geometry": {
    "type": "Point",
    "coordinates": [
      -82.50099,
      22.89018
    ]
  }
}