{
  "type": "Feature",
  "properties": {
    "name": "Jendouba",
    "country": "TN",
    "subdivision": "06",
    "timezone": "Africa/Tunis"
  },
  "geometry": {
    "type": "Point",
    "coordinates": [
      8.78024,
      36.50114
    ]
  }
}