{
  "type": "Feature",
  "properties": {
    "name": "Wadi Maliz",
    "country": "TN",
    "subdivision": "06",
    "timezone": "Africa/Tunis"
  },
  "geometry": {
    "type": "Point",
    "coordinates": [
      8.54951,
      36.46813
    ]
  }
}