{
  "type": "Feature",
  "properties": {
    "name": "Sirdaryo",
    "country": "UZ",
    "subdivision": "16",
    "timezone": "Asia/Tashkent"
  },
  "geometry": {
    "type": "Point",
    "coordinates": [
      68.66167,
      40.84361
    ]
  }
}