{
  "type": "Feature",
  "properties": {
    "name": "Hämeenlinna",
    "country": "FI",
    "subdivision": "05",
    "timezone": "Europe/Helsinki"
  },
  "geometry": {
    "type": "Point",
    "coordinates": [
      24.46434,
      60.99596
    ]
  }
}