{
  "type": "Feature",
  "properties": {
    "name": "Humppila",
    "country": "FI",
    "subdivision": "05",
    "timezone": "Europe/Helsinki"
  },
  "geometry": {
    "type": "Point",
    "coordinates": [
      23.36667,
      60.93333
    ]
  }
}