{
  "type": "Feature",
  "properties": {
    "name": "Jaffna",
    "country": "LK",
    "subdivision": "38",
    "timezone": "Asia/Colombo"
  },
  "geometry": {
    "type": "Point",
    "coordinates": [
      80.00742,
      9.66845
    ]
  }
}