{
  "type": "Feature",
  "properties": {
    "name": "Kilinochchi",
    "country": "LK",
    "subdivision": "38",
    "timezone": "Asia/Colombo"
  },
  "geometry": {
    "type": "Point",
    "coordinates": [
      80.3982,
      9.3961
    ]
  }
}