{
  "type": "Feature",
  "properties": {
    "name": "Point Pedro",
    "country": "LK",
    "subdivision": "38",
    "timezone": "Asia/Colombo"
  },
  "geometry": {
    "type": "Point",
    "coordinates": [
      80.23333,
      9.81667
    ]
  }
}