{
  "type": "Feature",
  "properties": {
    "name": "Aggius",
    "country": "IT",
    "subdivision": "14",
    "timezone": "Europe/Rome"
  },
  "geometry": {
    "type": "Point",
    "coordinates": [
      9.06517,
      40.92995
    ]
  }
}