{
  "type": "Feature",
  "properties": {
    "name": "Alà dei Sardi",
    "country": "IT",
    "subdivision": "14",
    "timezone": "Europe/Rome"
  },
  "geometry": {
    "type": "Point",
    "coordinates": [
      9.32783,
      40.65007
    ]
  }
}