{
  "type": "Feature",
  "properties": {
    "name": "Atzara",
    "country": "IT",
    "subdivision": "14",
    "timezone": "Europe/Rome"
  },
  "geometry": {
    "type": "Point",
    "coordinates": [
      9.07616,
      39.99249
    ]
  }
}