{
  "type": "Feature",
  "properties": {
    "name": "Badesi",
    "country": "IT",
    "subdivision": "14",
    "timezone": "Europe/Rome"
  },
  "geometry": {
    "type": "Point",
    "coordinates": [
      8.88235,
      40.9646
    ]
  }
}