{
  "type": "Feature",
  "properties": {
    "name": "Bitti",
    "country": "IT",
    "subdivision": "14",
    "timezone": "Europe/Rome"
  },
  "geometry": {
    "type": "Point",
    "coordinates": [
      9.38403,
      40.47956
    ]
  }
}