{
  "type": "Feature",
  "properties": {
    "name": "Bono",
    "country": "IT",
    "subdivision": "14",
    "timezone": "Europe/Rome"
  },
  "geometry": {
    "type": "Point",
    "coordinates": [
      9.03187,
      40.41387
    ]
  }
}