{
  "type": "Feature",
  "properties": {
    "name": "Cuglieri",
    "country": "IT",
    "subdivision": "14",
    "timezone": "Europe/Rome"
  },
  "geometry": {
    "type": "Point",
    "coordinates": [
      8.56806,
      40.18804
    ]
  }
}