{
  "type": "Feature",
  "properties": {
    "name": "Decimomannu",
    "country": "IT",
    "subdivision": "14",
    "timezone": "Europe/Rome"
  },
  "geometry": {
    "type": "Point",
    "coordinates": [
      8.96964,
      39.31033
    ]
  }
}