{
  "type": "Feature",
  "properties": {
    "name": "Florinas",
    "country": "IT",
    "subdivision": "14",
    "timezone": "Europe/Rome"
  },
  "geometry": {
    "type": "Point",
    "coordinates": [
      8.66548,
      40.649
    ]
  }
}