{
  "type": "Feature",
  "properties": {
    "name": "Fonni",
    "country": "IT",
    "subdivision": "14",
    "timezone": "Europe/Rome"
  },
  "geometry": {
    "type": "Point",
    "coordinates": [
      9.25347,
      40.11932
    ]
  }
}