{
  "type": "Feature",
  "properties": {
    "name": "Galtellì",
    "country": "IT",
    "subdivision": "14",
    "timezone": "Europe/Rome"
  },
  "geometry": {
    "type": "Point",
    "coordinates": [
      9.61241,
      40.38451
    ]
  }
}