{
  "type": "Feature",
  "properties": {
    "name": "Gonnosfanadiga",
    "country": "IT",
    "subdivision": "14",
    "timezone": "Europe/Rome"
  },
  "geometry": {
    "type": "Point",
    "coordinates": [
      8.662,
      39.49426
    ]
  }
}