{
  "type": "Feature",
  "properties": {
    "name": "Li Punti-San Giovanni",
    "country": "IT",
    "subdivision": "14",
    "timezone": "Europe/Rome"
  },
  "geometry": {
    "type": "Point",
    "coordinates": [
      8.489,
      40.76338
    ]
  }
}