{
  "type": "Feature",
  "properties": {
    "name": "Loiri Porto San Paolo",
    "country": "IT",
    "subdivision": "14",
    "timezone": "Europe/Rome"
  },
  "geometry": {
    "type": "Point",
    "coordinates": [
      9.4982,
      40.84262
    ]
  }
}