{
  "type": "Feature",
  "properties": {
    "name": "Macomer",
    "country": "IT",
    "subdivision": "14",
    "timezone": "Europe/Rome"
  },
  "geometry": {
    "type": "Point",
    "coordinates": [
      8.76733,
      40.26233
    ]
  }
}