{
  "type": "Feature",
  "properties": {
    "name": "Milis",
    "country": "IT",
    "subdivision": "14",
    "timezone": "Europe/Rome"
  },
  "geometry": {
    "type": "Point",
    "coordinates": [
      8.63702,
      40.05045
    ]
  }
}