{
  "type": "Feature",
  "properties": {
    "name": "Monastir",
    "country": "IT",
    "subdivision": "14",
    "timezone": "Europe/Rome"
  },
  "geometry": {
    "type": "Point",
    "coordinates": [
      9.04445,
      39.3836
    ]
  }
}