{
  "type": "Feature",
  "properties": {
    "name": "Narcao",
    "country": "IT",
    "subdivision": "14",
    "timezone": "Europe/Rome"
  },
  "geometry": {
    "type": "Point",
    "coordinates": [
      8.675,
      39.1675
    ]
  }
}