{
  "type": "Feature",
  "properties": {
    "name": "Nurri",
    "country": "IT",
    "subdivision": "14",
    "timezone": "Europe/Rome"
  },
  "geometry": {
    "type": "Point",
    "coordinates": [
      9.2299,
      39.71122
    ]
  }
}