{
  "type": "Feature",
  "properties": {
    "name": "Nuxis",
    "country": "IT",
    "subdivision": "14",
    "timezone": "Europe/Rome"
  },
  "geometry": {
    "type": "Point",
    "coordinates": [
      8.73953,
      39.15456
    ]
  }
}