{
  "type": "Feature",
  "properties": {
    "name": "Orroli",
    "country": "IT",
    "subdivision": "14",
    "timezone": "Europe/Rome"
  },
  "geometry": {
    "type": "Point",
    "coordinates": [
      9.24995,
      39.69237
    ]
  }
}