{
  "type": "Feature",
  "properties": {
    "name": "Ortueri",
    "country": "IT",
    "subdivision": "14",
    "timezone": "Europe/Rome"
  },
  "geometry": {
    "type": "Point",
    "coordinates": [
      8.98591,
      40.03545
    ]
  }
}