{
  "type": "Feature",
  "properties": {
    "name": "Oschiri",
    "country": "IT",
    "subdivision": "14",
    "timezone": "Europe/Rome"
  },
  "geometry": {
    "type": "Point",
    "coordinates": [
      9.10102,
      40.71977
    ]
  }
}