{
  "type": "Feature",
  "properties": {
    "name": "Ozieri",
    "country": "IT",
    "subdivision": "14",
    "timezone": "Europe/Rome"
  },
  "geometry": {
    "type": "Point",
    "coordinates": [
      9.0034,
      40.5863
    ]
  }
}