{
  "type": "Feature",
  "properties": {
    "name": "Pabillonis",
    "country": "IT",
    "subdivision": "14",
    "timezone": "Europe/Rome"
  },
  "geometry": {
    "type": "Point",
    "coordinates": [
      8.72143,
      39.59228
    ]
  }
}