{
  "type": "Feature",
  "properties": {
    "name": "Pattada",
    "country": "IT",
    "subdivision": "14",
    "timezone": "Europe/Rome"
  },
  "geometry": {
    "type": "Point",
    "coordinates": [
      9.11129,
      40.58067
    ]
  }
}