{
  "type": "Feature",
  "properties": {
    "name": "Porto Torres",
    "country": "IT",
    "subdivision": "14",
    "timezone": "Europe/Rome"
  },
  "geometry": {
    "type": "Point",
    "coordinates": [
      8.40531,
      40.83375
    ]
  }
}