{
  "type": "Feature",
  "properties": {
    "name": "Posada",
    "country": "IT",
    "subdivision": "14",
    "timezone": "Europe/Rome"
  },
  "geometry": {
    "type": "Point",
    "coordinates": [
      9.71904,
      40.63203
    ]
  }
}