{
  "type": "Feature",
  "properties": {
    "name": "San Giovanni Suergiu",
    "country": "IT",
    "subdivision": "14",
    "timezone": "Europe/Rome"
  },
  "geometry": {
    "type": "Point",
    "coordinates": [
      8.52039,
      39.10955
    ]
  }
}