{
  "type": "Feature",
  "properties": {
    "name": "Santa Giusta",
    "country": "IT",
    "subdivision": "14",
    "timezone": "Europe/Rome"
  },
  "geometry": {
    "type": "Point",
    "coordinates": [
      8.60916,
      39.8807
    ]
  }
}