{
  "type": "Feature",
  "properties": {
    "name": "Sant'Antioco",
    "country": "IT",
    "subdivision": "14",
    "timezone": "Europe/Rome"
  },
  "geometry": {
    "type": "Point",
    "coordinates": [
      8.45243,
      39.07017
    ]
  }
}