{
  "type": "Feature",
  "properties": {
    "name": "Sarroch",
    "country": "IT",
    "subdivision": "14",
    "timezone": "Europe/Rome"
  },
  "geometry": {
    "type": "Point",
    "coordinates": [
      9.00937,
      39.06577
    ]
  }
}