{
  "type": "Feature",
  "properties": {
    "name": "Selargius",
    "country": "IT",
    "subdivision": "14",
    "timezone": "Europe/Rome"
  },
  "geometry": {
    "type": "Point",
    "coordinates": [
      9.16323,
      39.25779
    ]
  }
}