{
  "type": "Feature",
  "properties": {
    "name": "Sennori",
    "country": "IT",
    "subdivision": "14",
    "timezone": "Europe/Rome"
  },
  "geometry": {
    "type": "Point",
    "coordinates": [
      8.59285,
      40.7878
    ]
  }
}