{
  "type": "Feature",
  "properties": {
    "name": "Silius",
    "country": "IT",
    "subdivision": "14",
    "timezone": "Europe/Rome"
  },
  "geometry": {
    "type": "Point",
    "coordinates": [
      9.2936,
      39.51695
    ]
  }
}