{
  "type": "Feature",
  "properties": {
    "name": "Sinnai",
    "country": "IT",
    "subdivision": "14",
    "timezone": "Europe/Rome"
  },
  "geometry": {
    "type": "Point",
    "coordinates": [
      9.20283,
      39.30286
    ]
  }
}