{
  "type": "Feature",
  "properties": {
    "name": "Solarussa",
    "country": "IT",
    "subdivision": "14",
    "timezone": "Europe/Rome"
  },
  "geometry": {
    "type": "Point",
    "coordinates": [
      8.67393,
      39.95499
    ]
  }
}