{
  "type": "Feature",
  "properties": {
    "name": "Tempio Pausania",
    "country": "IT",
    "subdivision": "14",
    "timezone": "Europe/Rome"
  },
  "geometry": {
    "type": "Point",
    "coordinates": [
      9.10456,
      40.90068
    ]
  }
}