{
  "type": "Feature",
  "properties": {
    "name": "Ulassai",
    "country": "IT",
    "subdivision": "14",
    "timezone": "Europe/Rome"
  },
  "geometry": {
    "type": "Point",
    "coordinates": [
      9.49962,
      39.81033
    ]
  }
}