{
  "type": "Feature",
  "properties": {
    "name": "Viddalba",
    "country": "IT",
    "subdivision": "14",
    "timezone": "Europe/Rome"
  },
  "geometry": {
    "type": "Point",
    "coordinates": [
      8.89009,
      40.91259
    ]
  }
}