{
  "type": "Feature",
  "properties": {
    "name": "Villamar",
    "country": "IT",
    "subdivision": "14",
    "timezone": "Europe/Rome"
  },
  "geometry": {
    "type": "Point",
    "coordinates": [
      8.95877,
      39.61884
    ]
  }
}