{
  "type": "Feature",
  "properties": {
    "name": "Villagrande Strisaili",
    "country": "IT",
    "subdivision": "14",
    "timezone": "Europe/Rome"
  },
  "geometry": {
    "type": "Point",
    "coordinates": [
      9.50943,
      39.95929
    ]
  }
}