{
  "type": "Feature",
  "properties": {
    "name": "Xiajiang",
    "country": "CN",
    "subdivision": "18",
    "timezone": "Asia/Shanghai"
  },
  "geometry": {
    "type": "Point",
    "coordinates": [
      108.69194,
      25.75556
    ]
  }
}