{
  "type": "Feature",
  "properties": {
    "name": "Zunyi",
    "country": "CN",
    "subdivision": "18",
    "timezone": "Asia/Shanghai"
  },
  "geometry": {
    "type": "Point",
    "coordinates": [
      106.90722,
      27.68667
    ]
  }
}