{
  "type": "Feature",
  "properties": {
    "name": "Ngama",
    "country": "TD",
    "subdivision": "15",
    "timezone": "Africa/Ndjamena"
  },
  "geometry": {
    "type": "Point",
    "coordinates": [
      17.16667,
      11.78333
    ]
  }
}