{
  "type": "Feature",
  "properties": {
    "name": "Buochs",
    "country": "CH",
    "subdivision": "NW",
    "timezone": "Europe/Zurich"
  },
  "geometry": {
    "type": "Point",
    "coordinates": [
      8.42279,
      46.97398
    ]
  }
}