{
  "type": "Feature",
  "properties": {
    "name": "Emmetten",
    "country": "CH",
    "subdivision": "NW",
    "timezone": "Europe/Zurich"
  },
  "geometry": {
    "type": "Point",
    "coordinates": [
      8.51467,
      46.95658
    ]
  }
}