{
  "type": "Feature",
  "properties": {
    "name": "Stansstad",
    "country": "CH",
    "subdivision": "NW",
    "timezone": "Europe/Zurich"
  },
  "geometry": {
    "type": "Point",
    "coordinates": [
      8.33553,
      46.9768
    ]
  }
}