{
  "type": "Feature",
  "properties": {
    "name": "Majuro",
    "country": "MH",
    "subdivision": "190",
    "timezone": "Pacific/Majuro"
  },
  "geometry": {
    "type": "Point",
    "coordinates": [
      171.38027,
      7.08971
    ]
  }
}