{
  "type": "Feature",
  "properties": {
    "name": "Agios Dimítrios Kropiás",
    "country": "GR",
    "subdivision": "ESYE31",
    "timezone": "Europe/Athens"
  },
  "geometry": {
    "type": "Point",
    "coordinates": [
      23.85793,
      37.80612
    ]
  }
}