{
  "type": "Feature",
  "properties": {
    "name": "Anoixi",
    "country": "GR",
    "subdivision": "ESYE31",
    "timezone": "Europe/Athens"
  },
  "geometry": {
    "type": "Point",
    "coordinates": [
      23.85874,
      38.13267
    ]
  }
}