{
  "type": "Feature",
  "properties": {
    "name": "Dhafní",
    "country": "GR",
    "subdivision": "ESYE31",
    "timezone": "Europe/Athens"
  },
  "geometry": {
    "type": "Point",
    "coordinates": [
      23.73437,
      37.95002
    ]
  }
}