{
  "type": "Feature",
  "properties": {
    "name": "Drapetsóna",
    "country": "GR",
    "subdivision": "ESYE31",
    "timezone": "Europe/Athens"
  },
  "geometry": {
    "type": "Point",
    "coordinates": [
      23.62309,
      37.94988
    ]
  }
}