{
  "type": "Feature",
  "properties": {
    "name": "Elefsína",
    "country": "GR",
    "subdivision": "ESYE31",
    "timezone": "Europe/Athens"
  },
  "geometry": {
    "type": "Point",
    "coordinates": [
      23.54295,
      38.04135
    ]
  }
}