{
  "type": "Feature",
  "properties": {
    "name": "Grammatikó",
    "country": "GR",
    "subdivision": "ESYE31",
    "timezone": "Europe/Athens"
  },
  "geometry": {
    "type": "Point",
    "coordinates": [
      23.96504,
      38.20251
    ]
  }
}