{
  "type": "Feature",
  "properties": {
    "name": "Kapandríti",
    "country": "GR",
    "subdivision": "ESYE31",
    "timezone": "Europe/Athens"
  },
  "geometry": {
    "type": "Point",
    "coordinates": [
      23.87938,
      38.21579
    ]
  }
}