{
  "type": "Feature",
  "properties": {
    "name": "Káto Soúlion",
    "country": "GR",
    "subdivision": "ESYE31",
    "timezone": "Europe/Athens"
  },
  "geometry": {
    "type": "Point",
    "coordinates": [
      24.01628,
      38.16803
    ]
  }
}