{
  "type": "Feature",
  "properties": {
    "name": "Khalkoútsion",
    "country": "GR",
    "subdivision": "ESYE31",
    "timezone": "Europe/Athens"
  },
  "geometry": {
    "type": "Point",
    "coordinates": [
      23.73188,
      38.33263
    ]
  }
}