{
  "type": "Feature",
  "properties": {
    "name": "Limín Mesoyaías",
    "country": "GR",
    "subdivision": "ESYE31",
    "timezone": "Europe/Athens"
  },
  "geometry": {
    "type": "Point",
    "coordinates": [
      24.00307,
      37.89108
    ]
  }
}