{
  "type": "Feature",
  "properties": {
    "name": "Magoúla",
    "country": "GR",
    "subdivision": "ESYE31",
    "timezone": "Europe/Athens"
  },
  "geometry": {
    "type": "Point",
    "coordinates": [
      23.52108,
      38.07989
    ]
  }
}