{
  "type": "Feature",
  "properties": {
    "name": "Péfki",
    "country": "GR",
    "subdivision": "ESYE31",
    "timezone": "Europe/Athens"
  },
  "geometry": {
    "type": "Point",
    "coordinates": [
      23.79264,
      38.06019
    ]
  }
}