{
  "type": "Feature",
  "properties": {
    "name": "Pikérmi",
    "country": "GR",
    "subdivision": "ESYE31",
    "timezone": "Europe/Athens"
  },
  "geometry": {
    "type": "Point",
    "coordinates": [
      23.94075,
      38.00161
    ]
  }
}