{
  "type": "Feature",
  "properties": {
    "name": "Rodópoli",
    "country": "GR",
    "subdivision": "ESYE31",
    "timezone": "Europe/Athens"
  },
  "geometry": {
    "type": "Point",
    "coordinates": [
      23.87572,
      38.11669
    ]
  }
}