{
  "type": "Feature",
  "properties": {
    "name": "Salamína",
    "country": "GR",
    "subdivision": "ESYE31",
    "timezone": "Europe/Athens"
  },
  "geometry": {
    "type": "Point",
    "coordinates": [
      23.49649,
      37.96427
    ]
  }
}