{
  "type": "Feature",
  "properties": {
    "name": "Áno Lekhónia",
    "country": "GR",
    "subdivision": "ESYE14",
    "timezone": "Europe/Athens"
  },
  "geometry": {
    "type": "Point",
    "coordinates": [
      23.05395,
      39.32763
    ]
  }
}