{
  "type": "Feature",
  "properties": {
    "name": "Karditsomagoúla",
    "country": "GR",
    "subdivision": "ESYE14",
    "timezone": "Europe/Athens"
  },
  "geometry": {
    "type": "Point",
    "coordinates": [
      21.9233,
      39.39061
    ]
  }
}