{
  "type": "Feature",
  "properties": {
    "name": "Lárisa",
    "country": "GR",
    "subdivision": "ESYE14",
    "timezone": "Europe/Athens"
  },
  "geometry": {
    "type": "Point",
    "coordinates": [
      22.41761,
      39.63689
    ]
  }
}