{
  "type": "Feature",
  "properties": {
    "name": "Magoúla",
    "country": "GR",
    "subdivision": "ESYE14",
    "timezone": "Europe/Athens"
  },
  "geometry": {
    "type": "Point",
    "coordinates": [
      21.80351,
      39.45395
    ]
  }
}