{
  "type": "Feature",
  "properties": {
    "name": "Oichalía",
    "country": "GR",
    "subdivision": "ESYE14",
    "timezone": "Europe/Athens"
  },
  "geometry": {
    "type": "Point",
    "coordinates": [
      21.97996,
      39.60827
    ]
  }
}