{
  "type": "Feature",
  "properties": {
    "name": "Tríkala",
    "country": "GR",
    "subdivision": "ESYE14",
    "timezone": "Europe/Athens"
  },
  "geometry": {
    "type": "Point",
    "coordinates": [
      21.76837,
      39.55493
    ]
  }
}