{
  "type": "Feature",
  "properties": {
    "name": "Verdikoússa",
    "country": "GR",
    "subdivision": "ESYE14",
    "timezone": "Europe/Athens"
  },
  "geometry": {
    "type": "Point",
    "coordinates": [
      21.97728,
      39.78175
    ]
  }
}