{
  "type": "Feature",
  "properties": {
    "name": "Boinești",
    "country": "RO",
    "subdivision": "32",
    "timezone": "Europe/Bucharest"
  },
  "geometry": {
    "type": "Point",
    "coordinates": [
      23.35117,
      47.91567
    ]
  }
}