{
  "type": "Feature",
  "properties": {
    "name": "Ciumești",
    "country": "RO",
    "subdivision": "32",
    "timezone": "Europe/Bucharest"
  },
  "geometry": {
    "type": "Point",
    "coordinates": [
      22.34069,
      47.66382
    ]
  }
}