{
  "type": "Feature",
  "properties": {
    "name": "Decebal",
    "country": "RO",
    "subdivision": "32",
    "timezone": "Europe/Bucharest"
  },
  "geometry": {
    "type": "Point",
    "coordinates": [
      22.75603,
      47.7663
    ]
  }
}