{
  "type": "Feature",
  "properties": {
    "name": "Doba",
    "country": "RO",
    "subdivision": "32",
    "timezone": "Europe/Bucharest"
  },
  "geometry": {
    "type": "Point",
    "coordinates": [
      22.71667,
      47.73333
    ]
  }
}