{
  "type": "Feature",
  "properties": {
    "name": "Oar",
    "country": "RO",
    "subdivision": "32",
    "timezone": "Europe/Bucharest"
  },
  "geometry": {
    "type": "Point",
    "coordinates": [
      22.73085,
      47.80569
    ]
  }
}