{
  "type": "Feature",
  "properties": {
    "name": "Porumbești",
    "country": "RO",
    "subdivision": "32",
    "timezone": "Europe/Bucharest"
  },
  "geometry": {
    "type": "Point",
    "coordinates": [
      22.98076,
      47.98305
    ]
  }
}