{
  "type": "Feature",
  "properties": {
    "name": "Săuca",
    "country": "RO",
    "subdivision": "32",
    "timezone": "Europe/Bucharest"
  },
  "geometry": {
    "type": "Point",
    "coordinates": [
      22.48333,
      47.46667
    ]
  }
}