{
  "type": "Feature",
  "properties": {
    "name": "Tarna Mare",
    "country": "RO",
    "subdivision": "32",
    "timezone": "Europe/Bucharest"
  },
  "geometry": {
    "type": "Point",
    "coordinates": [
      23.19369,
      48.09175
    ]
  }
}