{
  "type": "Feature",
  "properties": {
    "name": "Tur",
    "country": "RO",
    "subdivision": "32",
    "timezone": "Europe/Bucharest"
  },
  "geometry": {
    "type": "Point",
    "coordinates": [
      23.39045,
      47.88231
    ]
  }
}