{
  "type": "Feature",
  "properties": {
    "name": "Niquinohomo",
    "country": "NI",
    "subdivision": "11",
    "timezone": "America/Managua"
  },
  "geometry": {
    "type": "Point",
    "coordinates": [
      -86.09446,
      11.90518
    ]
  }
}