{
  "type": "Feature",
  "properties": {
    "name": "Tisma",
    "country": "NI",
    "subdivision": "11",
    "timezone": "America/Managua"
  },
  "geometry": {
    "type": "Point",
    "coordinates": [
      -86.01739,
      12.08194
    ]
  }
}