{
  "type": "Feature",
  "properties": {
    "name": "Salamá",
    "country": "GT",
    "subdivision": "02",
    "timezone": "America/Guatemala"
  },
  "geometry": {
    "type": "Point",
    "coordinates": [
      -90.31806,
      15.10278
    ]
  }
}