{
  "type": "Feature",
  "properties": {
    "name": "Arklow",
    "country": "IE",
    "subdivision": "L",
    "timezone": "Europe/Dublin"
  },
  "geometry": {
    "type": "Point",
    "coordinates": [
      -6.14958,
      52.79443
    ]
  }
}