{
  "type": "Feature",
  "properties": {
    "name": "Ballyboden",
    "country": "IE",
    "subdivision": "L",
    "timezone": "Europe/Dublin"
  },
  "geometry": {
    "type": "Point",
    "coordinates": [
      -6.31639,
      53.28056
    ]
  }
}