{
  "type": "Feature",
  "properties": {
    "name": "Baltinglass",
    "country": "IE",
    "subdivision": "L",
    "timezone": "Europe/Dublin"
  },
  "geometry": {
    "type": "Point",
    "coordinates": [
      -6.70917,
      52.93722
    ]
  }
}