{
  "type": "Feature",
  "properties": {
    "name": "Beaumont",
    "country": "IE",
    "subdivision": "L",
    "timezone": "Europe/Dublin"
  },
  "geometry": {
    "type": "Point",
    "coordinates": [
      -6.22713,
      53.38721
    ]
  }
}