{
  "type": "Feature",
  "properties": {
    "name": "Cabinteely",
    "country": "IE",
    "subdivision": "L",
    "timezone": "Europe/Dublin"
  },
  "geometry": {
    "type": "Point",
    "coordinates": [
      -6.16058,
      53.26973
    ]
  }
}