{
  "type": "Feature",
  "properties": {
    "name": "Clane",
    "country": "IE",
    "subdivision": "L",
    "timezone": "Europe/Dublin"
  },
  "geometry": {
    "type": "Point",
    "coordinates": [
      -6.68917,
      53.29139
    ]
  }
}