{
  "type": "Feature",
  "properties": {
    "name": "Clondalkin",
    "country": "IE",
    "subdivision": "L",
    "timezone": "Europe/Dublin"
  },
  "geometry": {
    "type": "Point",
    "coordinates": [
      -6.39722,
      53.32444
    ]
  }
}