{
  "type": "Feature",
  "properties": {
    "name": "Derrinturn",
    "country": "IE",
    "subdivision": "L",
    "timezone": "Europe/Dublin"
  },
  "geometry": {
    "type": "Point",
    "coordinates": [
      -6.94111,
      53.34167
    ]
  }
}