{
  "type": "Feature",
  "properties": {
    "name": "Donaghmede",
    "country": "IE",
    "subdivision": "L",
    "timezone": "Europe/Dublin"
  },
  "geometry": {
    "type": "Point",
    "coordinates": [
      -6.16179,
      53.39845
    ]
  }
}