{
  "type": "Feature",
  "properties": {
    "name": "Donnycarney",
    "country": "IE",
    "subdivision": "L",
    "timezone": "Europe/Dublin"
  },
  "geometry": {
    "type": "Point",
    "coordinates": [
      -6.20976,
      53.3735
    ]
  }
}