{
  "type": "Feature",
  "properties": {
    "name": "Dunboyne",
    "country": "IE",
    "subdivision": "L",
    "timezone": "Europe/Dublin"
  },
  "geometry": {
    "type": "Point",
    "coordinates": [
      -6.47375,
      53.41901
    ]
  }
}