{
  "type": "Feature",
  "properties": {
    "name": "Enniscorthy",
    "country": "IE",
    "subdivision": "L",
    "timezone": "Europe/Dublin"
  },
  "geometry": {
    "type": "Point",
    "coordinates": [
      -6.55778,
      52.50083
    ]
  }
}