{
  "type": "Feature",
  "properties": {
    "name": "Enniskerry",
    "country": "IE",
    "subdivision": "L",
    "timezone": "Europe/Dublin"
  },
  "geometry": {
    "type": "Point",
    "coordinates": [
      -6.16917,
      53.1925
    ]
  }
}