{
  "type": "Feature",
  "properties": {
    "name": "Glasnevin",
    "country": "IE",
    "subdivision": "L",
    "timezone": "Europe/Dublin"
  },
  "geometry": {
    "type": "Point",
    "coordinates": [
      -6.28028,
      53.37851
    ]
  }
}