{
  "type": "Feature",
  "properties": {
    "name": "Granard",
    "country": "IE",
    "subdivision": "L",
    "timezone": "Europe/Dublin"
  },
  "geometry": {
    "type": "Point",
    "coordinates": [
      -7.49429,
      53.77928
    ]
  }
}