{
  "type": "Feature",
  "properties": {
    "name": "Laytown",
    "country": "IE",
    "subdivision": "L",
    "timezone": "Europe/Dublin"
  },
  "geometry": {
    "type": "Point",
    "coordinates": [
      -6.23917,
      53.68194
    ]
  }
}