{
  "type": "Feature",
  "properties": {
    "name": "Longwood",
    "country": "IE",
    "subdivision": "L",
    "timezone": "Europe/Dublin"
  },
  "geometry": {
    "type": "Point",
    "coordinates": [
      -6.92194,
      53.45389
    ]
  }
}