{
  "type": "Feature",
  "properties": {
    "name": "Longford",
    "country": "IE",
    "subdivision": "L",
    "timezone": "Europe/Dublin"
  },
  "geometry": {
    "type": "Point",
    "coordinates": [
      -7.79823,
      53.72536
    ]
  }
}