{
  "type": "Feature",
  "properties": {
    "name": "Portmarnock",
    "country": "IE",
    "subdivision": "L",
    "timezone": "Europe/Dublin"
  },
  "geometry": {
    "type": "Point",
    "coordinates": [
      -6.1375,
      53.42306
    ]
  }
}