{
  "type": "Feature",
  "properties": {
    "name": "Portarlington",
    "country": "IE",
    "subdivision": "L",
    "timezone": "Europe/Dublin"
  },
  "geometry": {
    "type": "Point",
    "coordinates": [
      -7.19111,
      53.16222
    ]
  }
}