{
  "type": "Feature",
  "properties": {
    "name": "Rathnew",
    "country": "IE",
    "subdivision": "L",
    "timezone": "Europe/Dublin"
  },
  "geometry": {
    "type": "Point",
    "coordinates": [
      -6.08528,
      52.99056
    ]
  }
}