{
  "type": "Feature",
  "properties": {
    "name": "Rosslare",
    "country": "IE",
    "subdivision": "L",
    "timezone": "Europe/Dublin"
  },
  "geometry": {
    "type": "Point",
    "coordinates": [
      -6.38989,
      52.27184
    ]
  }
}