{
  "type": "Feature",
  "properties": {
    "name": "Sallins",
    "country": "IE",
    "subdivision": "L",
    "timezone": "Europe/Dublin"
  },
  "geometry": {
    "type": "Point",
    "coordinates": [
      -6.66611,
      53.24889
    ]
  }
}