{
  "type": "Feature",
  "properties": {
    "name": "Kirkop",
    "country": "MT",
    "subdivision": "28",
    "timezone": "Europe/Malta"
  },
  "geometry": {
    "type": "Point",
    "coordinates": [
      14.48528,
      35.84222
    ]
  }
}