{
  "type": "Feature",
  "properties": {
    "name": "Allenby Gardens",
    "country": "AU",
    "subdivision": "05",
    "timezone": "Australia/Adelaide"
  },
  "geometry": {
    "type": "Point",
    "coordinates": [
      138.55425,
      -34.89766
    ]
  }
}