{
  "type": "Feature",
  "properties": {
    "name": "Angle Vale",
    "country": "AU",
    "subdivision": "05",
    "timezone": "Australia/Adelaide"
  },
  "geometry": {
    "type": "Point",
    "coordinates": [
      138.6461,
      -34.64098
    ]
  }
}