{
  "type": "Feature",
  "properties": {
    "name": "Ashford",
    "country": "AU",
    "subdivision": "05",
    "timezone": "Australia/Adelaide"
  },
  "geometry": {
    "type": "Point",
    "coordinates": [
      138.57457,
      -34.94859
    ]
  }
}