{
  "type": "Feature",
  "properties": {
    "name": "Balaklava",
    "country": "AU",
    "subdivision": "05",
    "timezone": "Australia/Adelaide"
  },
  "geometry": {
    "type": "Point",
    "coordinates": [
      138.41148,
      -34.14542
    ]
  }
}