{
  "type": "Feature",
  "properties": {
    "name": "Belair",
    "country": "AU",
    "subdivision": "05",
    "timezone": "Australia/Adelaide"
  },
  "geometry": {
    "type": "Point",
    "coordinates": [
      138.62077,
      -34.99766
    ]
  }
}