{
  "type": "Feature",
  "properties": {
    "name": "Blackwood",
    "country": "AU",
    "subdivision": "05",
    "timezone": "Australia/Adelaide"
  },
  "geometry": {
    "type": "Point",
    "coordinates": [
      138.61429,
      -35.02139
    ]
  }
}