{
  "type": "Feature",
  "properties": {
    "name": "Bordertown",
    "country": "AU",
    "subdivision": "05",
    "timezone": "Australia/Adelaide"
  },
  "geometry": {
    "type": "Point",
    "coordinates": [
      140.77167,
      -36.30768
    ]
  }
}