{
  "type": "Feature",
  "properties": {
    "name": "Coromandel Valley",
    "country": "AU",
    "subdivision": "05",
    "timezone": "Australia/Adelaide"
  },
  "geometry": {
    "type": "Point",
    "coordinates": [
      138.61667,
      -35.05
    ]
  }
}