{
  "type": "Feature",
  "properties": {
    "name": "Cowell",
    "country": "AU",
    "subdivision": "05",
    "timezone": "Australia/Adelaide"
  },
  "geometry": {
    "type": "Point",
    "coordinates": [
      136.92117,
      -33.68227
    ]
  }
}