{
  "type": "Feature",
  "properties": {
    "name": "Cumberland Park",
    "country": "AU",
    "subdivision": "05",
    "timezone": "Australia/Adelaide"
  },
  "geometry": {
    "type": "Point",
    "coordinates": [
      138.5867,
      -34.97204
    ]
  }
}