{
  "type": "Feature",
  "properties": {
    "name": "Edwardstown",
    "country": "AU",
    "subdivision": "05",
    "timezone": "Australia/Adelaide"
  },
  "geometry": {
    "type": "Point",
    "coordinates": [
      138.5694,
      -34.98018
    ]
  }
}