{
  "type": "Feature",
  "properties": {
    "name": "Freeling",
    "country": "AU",
    "subdivision": "05",
    "timezone": "Australia/Adelaide"
  },
  "geometry": {
    "type": "Point",
    "coordinates": [
      138.80868,
      -34.45407
    ]
  }
}