{
  "type": "Feature",
  "properties": {
    "name": "Fulham Gardens",
    "country": "AU",
    "subdivision": "05",
    "timezone": "Australia/Adelaide"
  },
  "geometry": {
    "type": "Point",
    "coordinates": [
      138.51324,
      -34.91483
    ]
  }
}