{
  "type": "Feature",
  "properties": {
    "name": "Fulham",
    "country": "AU",
    "subdivision": "05",
    "timezone": "Australia/Adelaide"
  },
  "geometry": {
    "type": "Point",
    "coordinates": [
      138.51368,
      -34.92737
    ]
  }
}