{
  "type": "Feature",
  "properties": {
    "name": "Gilberton",
    "country": "AU",
    "subdivision": "05",
    "timezone": "Australia/Adelaide"
  },
  "geometry": {
    "type": "Point",
    "coordinates": [
      138.6126,
      -34.90051
    ]
  }
}