{
  "type": "Feature",
  "properties": {
    "name": "Glenside",
    "country": "AU",
    "subdivision": "05",
    "timezone": "Australia/Adelaide"
  },
  "geometry": {
    "type": "Point",
    "coordinates": [
      138.63375,
      -34.94275
    ]
  }
}