{
  "type": "Feature",
  "properties": {
    "name": "Hallett Cove",
    "country": "AU",
    "subdivision": "05",
    "timezone": "Australia/Adelaide"
  },
  "geometry": {
    "type": "Point",
    "coordinates": [
      138.5146,
      -35.07923
    ]
  }
}