{
  "type": "Feature",
  "properties": {
    "name": "Ingle Farm",
    "country": "AU",
    "subdivision": "05",
    "timezone": "Australia/Adelaide"
  },
  "geometry": {
    "type": "Point",
    "coordinates": [
      138.63333,
      -34.83333
    ]
  }
}