{
  "type": "Feature",
  "properties": {
    "name": "Klemzig",
    "country": "AU",
    "subdivision": "05",
    "timezone": "Australia/Adelaide"
  },
  "geometry": {
    "type": "Point",
    "coordinates": [
      138.63562,
      -34.87928
    ]
  }
}