{
  "type": "Feature",
  "properties": {
    "name": "Kurralta Park",
    "country": "AU",
    "subdivision": "05",
    "timezone": "Australia/Adelaide"
  },
  "geometry": {
    "type": "Point",
    "coordinates": [
      138.56702,
      -34.95142
    ]
  }
}