{
  "type": "Feature",
  "properties": {
    "name": "Largs Bay",
    "country": "AU",
    "subdivision": "05",
    "timezone": "Australia/Adelaide"
  },
  "geometry": {
    "type": "Point",
    "coordinates": [
      138.48619,
      -34.82582
    ]
  }
}