{
  "type": "Feature",
  "properties": {
    "name": "Leabrook",
    "country": "AU",
    "subdivision": "05",
    "timezone": "Australia/Adelaide"
  },
  "geometry": {
    "type": "Point",
    "coordinates": [
      138.65862,
      -34.92976
    ]
  }
}