{
  "type": "Feature",
  "properties": {
    "name": "Marden",
    "country": "AU",
    "subdivision": "05",
    "timezone": "Australia/Adelaide"
  },
  "geometry": {
    "type": "Point",
    "coordinates": [
      138.6378,
      -34.89569
    ]
  }
}