{
  "type": "Feature",
  "properties": {
    "name": "Moana",
    "country": "AU",
    "subdivision": "05",
    "timezone": "Australia/Adelaide"
  },
  "geometry": {
    "type": "Point",
    "coordinates": [
      138.47614,
      -35.19394
    ]
  }
}