{
  "type": "Feature",
  "properties": {
    "name": "Moorak",
    "country": "AU",
    "subdivision": "05",
    "timezone": "Australia/Adelaide"
  },
  "geometry": {
    "type": "Point",
    "coordinates": [
      140.74263,
      -37.86381
    ]
  }
}