{
  "type": "Feature",
  "properties": {
    "name": "North Adelaide",
    "country": "AU",
    "subdivision": "05",
    "timezone": "Australia/Adelaide"
  },
  "geometry": {
    "type": "Point",
    "coordinates": [
      138.59141,
      -34.90733
    ]
  }
}