{
  "type": "Feature",
  "properties": {
    "name": "O’Halloran Hill",
    "country": "AU",
    "subdivision": "05",
    "timezone": "Australia/Adelaide"
  },
  "geometry": {
    "type": "Point",
    "coordinates": [
      138.55,
      -35.06667
    ]
  }
}