{
  "type": "Feature",
  "properties": {
    "name": "Paringa",
    "country": "AU",
    "subdivision": "05",
    "timezone": "Australia/Adelaide"
  },
  "geometry": {
    "type": "Point",
    "coordinates": [
      140.78579,
      -34.17644
    ]
  }
}