{
  "type": "Feature",
  "properties": {
    "name": "Penola",
    "country": "AU",
    "subdivision": "05",
    "timezone": "Australia/Adelaide"
  },
  "geometry": {
    "type": "Point",
    "coordinates": [
      140.83678,
      -37.3752
    ]
  }
}