{
  "type": "Feature",
  "properties": {
    "name": "Plympton Park",
    "country": "AU",
    "subdivision": "05",
    "timezone": "Australia/Adelaide"
  },
  "geometry": {
    "type": "Point",
    "coordinates": [
      138.54918,
      -34.98071
    ]
  }
}