{
  "type": "Feature",
  "properties": {
    "name": "Ridleyton",
    "country": "AU",
    "subdivision": "05",
    "timezone": "Australia/Adelaide"
  },
  "geometry": {
    "type": "Point",
    "coordinates": [
      138.57159,
      -34.8928
    ]
  }
}