{
  "type": "Feature",
  "properties": {
    "name": "Rostrevor",
    "country": "AU",
    "subdivision": "05",
    "timezone": "Australia/Adelaide"
  },
  "geometry": {
    "type": "Point",
    "coordinates": [
      138.69183,
      -34.89386
    ]
  }
}