{
  "type": "Feature",
  "properties": {
    "name": "Salisbury East",
    "country": "AU",
    "subdivision": "05",
    "timezone": "Australia/Adelaide"
  },
  "geometry": {
    "type": "Point",
    "coordinates": [
      138.6545,
      -34.79052
    ]
  }
}