{
  "type": "Feature",
  "properties": {
    "name": "Seacombe Gardens",
    "country": "AU",
    "subdivision": "05",
    "timezone": "Australia/Adelaide"
  },
  "geometry": {
    "type": "Point",
    "coordinates": [
      138.5458,
      -35.02336
    ]
  }
}