{
  "type": "Feature",
  "properties": {
    "name": "Semaphore South",
    "country": "AU",
    "subdivision": "05",
    "timezone": "Australia/Adelaide"
  },
  "geometry": {
    "type": "Point",
    "coordinates": [
      138.47949,
      -34.84975
    ]
  }
}