{
  "type": "Feature",
  "properties": {
    "name": "Semaphore",
    "country": "AU",
    "subdivision": "05",
    "timezone": "Australia/Adelaide"
  },
  "geometry": {
    "type": "Point",
    "coordinates": [
      138.48228,
      -34.83934
    ]
  }
}