{
  "type": "Feature",
  "properties": {
    "name": "Somerton Park",
    "country": "AU",
    "subdivision": "05",
    "timezone": "Australia/Adelaide"
  },
  "geometry": {
    "type": "Point",
    "coordinates": [
      138.52155,
      -34.99705
    ]
  }
}