{
  "type": "Feature",
  "properties": {
    "name": "South Brighton",
    "country": "AU",
    "subdivision": "05",
    "timezone": "Australia/Adelaide"
  },
  "geometry": {
    "type": "Point",
    "coordinates": [
      138.52798,
      -35.02765
    ]
  }
}