{
  "type": "Feature",
  "properties": {
    "name": "South Plympton",
    "country": "AU",
    "subdivision": "05",
    "timezone": "Australia/Adelaide"
  },
  "geometry": {
    "type": "Point",
    "coordinates": [
      138.55588,
      -34.97682
    ]
  }
}