{
  "type": "Feature",
  "properties": {
    "name": "Streaky Bay",
    "country": "AU",
    "subdivision": "05",
    "timezone": "Australia/Adelaide"
  },
  "geometry": {
    "type": "Point",
    "coordinates": [
      134.20928,
      -32.79554
    ]
  }
}