{
  "type": "Feature",
  "properties": {
    "name": "Taperoo",
    "country": "AU",
    "subdivision": "05",
    "timezone": "Australia/Adelaide"
  },
  "geometry": {
    "type": "Point",
    "coordinates": [
      138.49593,
      -34.80425
    ]
  }
}