{
  "type": "Feature",
  "properties": {
    "name": "Woodville West",
    "country": "AU",
    "subdivision": "05",
    "timezone": "Australia/Adelaide"
  },
  "geometry": {
    "type": "Point",
    "coordinates": [
      138.53095,
      -34.8864
    ]
  }
}