{
  "type": "Feature",
  "properties": {
    "name": "Bovec",
    "country": "SI",
    "subdivision": "06",
    "timezone": "Europe/Ljubljana"
  },
  "geometry": {
    "type": "Point",
    "coordinates": [
      13.55245,
      46.33808
    ]
  }
}