{
  "type": "Feature",
  "properties": {
    "name": "Bandiagara",
    "country": "ML",
    "subdivision": "04",
    "timezone": "Africa/Bamako"
  },
  "geometry": {
    "type": "Point",
    "coordinates": [
      -3.61038,
      14.35005
    ]
  }
}