{
  "type": "Feature",
  "properties": {
    "name": "Los Llanitos",
    "country": "HN",
    "subdivision": "02",
    "timezone": "America/Tegucigalpa"
  },
  "geometry": {
    "type": "Point",
    "coordinates": [
      -87.33444,
      13.28694
    ]
  }
}