{
  "type": "Feature",
  "properties": {
    "name": "Andong",
    "country": "KR",
    "subdivision": "14",
    "timezone": "Asia/Seoul"
  },
  "geometry": {
    "type": "Point",
    "coordinates": [
      128.72275,
      36.56636
    ]
  }
}