{
  "type": "Feature",
  "properties": {
    "name": "Cheongsong gun",
    "country": "KR",
    "subdivision": "14",
    "timezone": "Asia/Seoul"
  },
  "geometry": {
    "type": "Point",
    "coordinates": [
      129.057,
      36.43351
    ]
  }
}