{
  "type": "Feature",
  "properties": {
    "name": "Gimcheon",
    "country": "KR",
    "subdivision": "14",
    "timezone": "Asia/Seoul"
  },
  "geometry": {
    "type": "Point",
    "coordinates": [
      128.11981,
      36.12176
    ]
  }
}