{
  "type": "Feature",
  "properties": {
    "name": "AmbÄla",
    "country": "IN",
    "subdivision": "10",
    "timezone": "Asia/Kolkata"
  },
  "geometry": {
    "type": "Point",
    "coordinates": [
      76.79782,
      30.36099
    ]
  }
}