{
  "type": "Feature",
  "properties": {
    "name": "Farrukhnagar",
    "country": "IN",
    "subdivision": "10",
    "timezone": "Asia/Kolkata"
  },
  "geometry": {
    "type": "Point",
    "coordinates": [
      76.82391,
      28.44745
    ]
  }
}