{
  "type": "Feature",
  "properties": {
    "name": "Kaithal",
    "country": "IN",
    "subdivision": "10",
    "timezone": "Asia/Kolkata"
  },
  "geometry": {
    "type": "Point",
    "coordinates": [
      76.39959,
      29.80153
    ]
  }
}