{
  "type": "Feature",
  "properties": {
    "name": "NarÄyangarh",
    "country": "IN",
    "subdivision": "10",
    "timezone": "Asia/Kolkata"
  },
  "geometry": {
    "type": "Point",
    "coordinates": [
      77.12804,
      30.47798
    ]
  }
}