{
  "type": "Feature",
  "properties": {
    "name": "Sohna",
    "country": "IN",
    "subdivision": "10",
    "timezone": "Asia/Kolkata"
  },
  "geometry": {
    "type": "Point",
    "coordinates": [
      77.06544,
      28.24737
    ]
  }
}