{
  "type": "Feature",
  "properties": {
    "name": "TÄoru",
    "country": "IN",
    "subdivision": "10",
    "timezone": "Asia/Kolkata"
  },
  "geometry": {
    "type": "Point",
    "coordinates": [
      76.94984,
      28.21173
    ]
  }
}