{
  "type": "Feature",
  "properties": {
    "name": "Yerazgavors",
    "country": "AM",
    "subdivision": "07",
    "timezone": "Asia/Yerevan"
  },
  "geometry": {
    "type": "Point",
    "coordinates": [
      43.74722,
      40.69505
    ]
  }
}