{
  "type": "Feature",
  "properties": {
    "name": "Anger",
    "country": "AT",
    "subdivision": "05",
    "timezone": "Europe/Vienna"
  },
  "geometry": {
    "type": "Point",
    "coordinates": [
      13.10592,
      47.15593
    ]
  }
}