{
  "type": "Feature",
  "properties": {
    "name": "Bramberg am Wildkogel",
    "country": "AT",
    "subdivision": "05",
    "timezone": "Europe/Vienna"
  },
  "geometry": {
    "type": "Point",
    "coordinates": [
      12.3385,
      47.26979
    ]
  }
}