{
  "type": "Feature",
  "properties": {
    "name": "Eugendorf",
    "country": "AT",
    "subdivision": "05",
    "timezone": "Europe/Vienna"
  },
  "geometry": {
    "type": "Point",
    "coordinates": [
      13.12609,
      47.86765
    ]
  }
}