{
  "type": "Feature",
  "properties": {
    "name": "Glasenbach",
    "country": "AT",
    "subdivision": "05",
    "timezone": "Europe/Vienna"
  },
  "geometry": {
    "type": "Point",
    "coordinates": [
      13.08333,
      47.76667
    ]
  }
}