{
  "type": "Feature",
  "properties": {
    "name": "Grossgmain",
    "country": "AT",
    "subdivision": "05",
    "timezone": "Europe/Vienna"
  },
  "geometry": {
    "type": "Point",
    "coordinates": [
      12.90851,
      47.72416
    ]
  }
}