{
  "type": "Feature",
  "properties": {
    "name": "Plankenau",
    "country": "AT",
    "subdivision": "05",
    "timezone": "Europe/Vienna"
  },
  "geometry": {
    "type": "Point",
    "coordinates": [
      13.19282,
      47.32673
    ]
  }
}