{
  "type": "Feature",
  "properties": {
    "name": "Siezenheim",
    "country": "AT",
    "subdivision": "05",
    "timezone": "Europe/Vienna"
  },
  "geometry": {
    "type": "Point",
    "coordinates": [
      12.99039,
      47.81529
    ]
  }
}