{
  "type": "Feature",
  "properties": {
    "name": "Walserfeld",
    "country": "AT",
    "subdivision": "05",
    "timezone": "Europe/Vienna"
  },
  "geometry": {
    "type": "Point",
    "coordinates": [
      12.98,
      47.79222
    ]
  }
}