{
  "type": "Feature",
  "properties": {
    "name": "Arevashogh",
    "country": "AM",
    "subdivision": "06",
    "timezone": "Asia/Yerevan"
  },
  "geometry": {
    "type": "Point",
    "coordinates": [
      44.27438,
      40.86039
    ]
  }
}