{
  "type": "Feature",
  "properties": {
    "name": "Gugark’",
    "country": "AM",
    "subdivision": "06",
    "timezone": "Asia/Yerevan"
  },
  "geometry": {
    "type": "Point",
    "coordinates": [
      44.54025,
      40.8046
    ]
  }
}