{
  "type": "Feature",
  "properties": {
    "name": "Mets Parni",
    "country": "AM",
    "subdivision": "06",
    "timezone": "Asia/Yerevan"
  },
  "geometry": {
    "type": "Point",
    "coordinates": [
      44.11108,
      40.83472
    ]
  }
}