{
  "type": "Feature",
  "properties": {
    "name": "Step’anavan",
    "country": "AM",
    "subdivision": "06",
    "timezone": "Asia/Yerevan"
  },
  "geometry": {
    "type": "Point",
    "coordinates": [
      44.38531,
      41.00995
    ]
  }
}