{
  "type": "Feature",
  "properties": {
    "name": "Vardablur",
    "country": "AM",
    "subdivision": "06",
    "timezone": "Asia/Yerevan"
  },
  "geometry": {
    "type": "Point",
    "coordinates": [
      44.50889,
      40.97083
    ]
  }
}