{
  "type": "Feature",
  "properties": {
    "name": "Juntas",
    "country": "CR",
    "subdivision": "03",
    "timezone": "America/Costa_Rica"
  },
  "geometry": {
    "type": "Point",
    "coordinates": [
      -84.95951,
      10.28089
    ]
  }
}