{
  "type": "Feature",
  "properties": {
    "name": "Ulster Spring",
    "country": "JM",
    "subdivision": "15",
    "timezone": "America/Jamaica"
  },
  "geometry": {
    "type": "Point",
    "coordinates": [
      -77.52067,
      18.31482
    ]
  }
}