{
  "type": "Feature",
  "properties": {
    "name": "Muğla",
    "country": "TR",
    "subdivision": "48",
    "timezone": "Europe/Istanbul"
  },
  "geometry": {
    "type": "Point",
    "coordinates": [
      28.3665,
      37.21807
    ]
  }
}