{
  "type": "Feature",
  "properties": {
    "name": "Lutes Mountain",
    "country": "CA",
    "subdivision": "04",
    "timezone": "America/Moncton"
  },
  "geometry": {
    "type": "Point",
    "coordinates": [
      -64.90504,
      46.13544
    ]
  }
}