{
  "type": "Feature",
  "properties": {
    "name": "Miramichi",
    "country": "CA",
    "subdivision": "04",
    "timezone": "America/Moncton"
  },
  "geometry": {
    "type": "Point",
    "coordinates": [
      -65.50186,
      47.02895
    ]
  }
}