{
  "type": "Feature",
  "properties": {
    "name": "New Maryland",
    "country": "CA",
    "subdivision": "04",
    "timezone": "America/Moncton"
  },
  "geometry": {
    "type": "Point",
    "coordinates": [
      -66.68225,
      45.89662
    ]
  }
}