{
  "type": "Feature",
  "properties": {
    "name": "Saint-Antoine",
    "country": "CA",
    "subdivision": "04",
    "timezone": "America/Moncton"
  },
  "geometry": {
    "type": "Point",
    "coordinates": [
      -64.74985,
      46.36294
    ]
  }
}