{
  "type": "Feature",
  "properties": {
    "name": "Tracadie-Sheila",
    "country": "CA",
    "subdivision": "04",
    "timezone": "America/Moncton"
  },
  "geometry": {
    "type": "Point",
    "coordinates": [
      -64.91806,
      47.51444
    ]
  }
}