{
  "type": "Feature",
  "properties": {
    "name": "Ceek",
    "country": "SO",
    "subdivision": "19",
    "timezone": "Africa/Mogadishu"
  },
  "geometry": {
    "type": "Point",
    "coordinates": [
      45.35824,
      8.99907
    ]
  }
}