{
  "type": "Feature",
  "properties": {
    "name": "Fažana",
    "country": "HR",
    "subdivision": "04",
    "timezone": "Europe/Zagreb"
  },
  "geometry": {
    "type": "Point",
    "coordinates": [
      13.80349,
      44.92742
    ]
  }
}