{
  "type": "Feature",
  "properties": {
    "name": "PoreÄ",
    "country": "HR",
    "subdivision": "04",
    "timezone": "Europe/Zagreb"
  },
  "geometry": {
    "type": "Point",
    "coordinates": [
      13.59511,
      45.22567
    ]
  }
}