{
  "type": "Feature",
  "properties": {
    "name": "Valbandon",
    "country": "HR",
    "subdivision": "04",
    "timezone": "Europe/Zagreb"
  },
  "geometry": {
    "type": "Point",
    "coordinates": [
      13.81344,
      44.91879
    ]
  }
}