{
  "type": "Feature",
  "properties": {
    "name": "Vinež",
    "country": "HR",
    "subdivision": "04",
    "timezone": "Europe/Zagreb"
  },
  "geometry": {
    "type": "Point",
    "coordinates": [
      14.10694,
      45.09806
    ]
  }
}