{
  "type": "Feature",
  "properties": {
    "name": "Agua Buena",
    "country": "MX",
    "subdivision": "24",
    "timezone": "America/Mexico_City"
  },
  "geometry": {
    "type": "Point",
    "coordinates": [
      -99.39416,
      21.95791
    ]
  }
}