{
  "type": "Feature",
  "properties": {
    "name": "Ahuehueyo Primero Centro",
    "country": "MX",
    "subdivision": "24",
    "timezone": "America/Mexico_City"
  },
  "geometry": {
    "type": "Point",
    "coordinates": [
      -98.83722,
      21.345
    ]
  }
}