{
  "type": "Feature",
  "properties": {
    "name": "Carranco",
    "country": "MX",
    "subdivision": "24",
    "timezone": "America/Mexico_City"
  },
  "geometry": {
    "type": "Point",
    "coordinates": [
      -101.09699,
      21.82002
    ]
  }
}