{
  "type": "Feature",
  "properties": {
    "name": "Chalchocoyo",
    "country": "MX",
    "subdivision": "24",
    "timezone": "America/Mexico_City"
  },
  "geometry": {
    "type": "Point",
    "coordinates": [
      -98.79194,
      21.31444
    ]
  }
}