{
  "type": "Feature",
  "properties": {
    "name": "Damian Carmona",
    "country": "MX",
    "subdivision": "24",
    "timezone": "America/Mexico_City"
  },
  "geometry": {
    "type": "Point",
    "coordinates": [
      -99.29216,
      22.09723
    ]
  }
}