{
  "type": "Feature",
  "properties": {
    "name": "El Fuerte",
    "country": "MX",
    "subdivision": "24",
    "timezone": "America/Mexico_City"
  },
  "geometry": {
    "type": "Point",
    "coordinates": [
      -100.66445,
      21.71289
    ]
  }
}