{
  "type": "Feature",
  "properties": {
    "name": "El Peñasco",
    "country": "MX",
    "subdivision": "24",
    "timezone": "America/Mexico_City"
  },
  "geometry": {
    "type": "Point",
    "coordinates": [
      -100.95014,
      22.32534
    ]
  }
}