{
  "type": "Feature",
  "properties": {
    "name": "Hernández",
    "country": "MX",
    "subdivision": "24",
    "timezone": "America/Mexico_City"
  },
  "geometry": {
    "type": "Point",
    "coordinates": [
      -102.03763,
      23.03337
    ]
  }
}