{
  "type": "Feature",
  "properties": {
    "name": "Ojo de Agua de Solano",
    "country": "MX",
    "subdivision": "24",
    "timezone": "America/Mexico_City"
  },
  "geometry": {
    "type": "Point",
    "coordinates": [
      -100.07946,
      21.98533
    ]
  }
}