{
  "type": "Feature",
  "properties": {
    "name": "Portezuelo",
    "country": "MX",
    "subdivision": "24",
    "timezone": "America/Mexico_City"
  },
  "geometry": {
    "type": "Point",
    "coordinates": [
      -100.82559,
      22.1698
    ]
  }
}