{
  "type": "Feature",
  "properties": {
    "name": "San Martín Chalchicuautla",
    "country": "MX",
    "subdivision": "24",
    "timezone": "America/Mexico_City"
  },
  "geometry": {
    "type": "Point",
    "coordinates": [
      -98.65697,
      21.37033
    ]
  }
}