{
  "type": "Feature",
  "properties": {
    "name": "San Ciro de Acosta",
    "country": "MX",
    "subdivision": "24",
    "timezone": "America/Mexico_City"
  },
  "geometry": {
    "type": "Point",
    "coordinates": [
      -99.81916,
      21.65072
    ]
  }
}