{
  "type": "Feature",
  "properties": {
    "name": "Sánchez",
    "country": "MX",
    "subdivision": "24",
    "timezone": "America/Mexico_City"
  },
  "geometry": {
    "type": "Point",
    "coordinates": [
      -100.69615,
      21.78709
    ]
  }
}