{
  "type": "Feature",
  "properties": {
    "name": "Santa Martha",
    "country": "MX",
    "subdivision": "24",
    "timezone": "America/Mexico_City"
  },
  "geometry": {
    "type": "Point",
    "coordinates": [
      -98.70639,
      22.34278
    ]
  }
}