{
  "type": "Feature",
  "properties": {
    "name": "Suspiro Picacho",
    "country": "MX",
    "subdivision": "24",
    "timezone": "America/Mexico_City"
  },
  "geometry": {
    "type": "Point",
    "coordinates": [
      -101.08597,
      22.21103
    ]
  }
}