{
  "type": "Feature",
  "properties": {
    "name": "Tanlajás",
    "country": "MX",
    "subdivision": "24",
    "timezone": "America/Mexico_City"
  },
  "geometry": {
    "type": "Point",
    "coordinates": [
      -98.886,
      21.66518
    ]
  }
}