{
  "type": "Feature",
  "properties": {
    "name": "Villa Juárez",
    "country": "MX",
    "subdivision": "24",
    "timezone": "America/Mexico_City"
  },
  "geometry": {
    "type": "Point",
    "coordinates": [
      -100.26689,
      22.32617
    ]
  }
}