{
  "type": "Feature",
  "properties": {
    "name": "Ambalangoda",
    "country": "LK",
    "subdivision": "34",
    "timezone": "Asia/Colombo"
  },
  "geometry": {
    "type": "Point",
    "coordinates": [
      80.0538,
      6.2355
    ]
  }
}