{
  "type": "Feature",
  "properties": {
    "name": "Galle",
    "country": "LK",
    "subdivision": "34",
    "timezone": "Asia/Colombo"
  },
  "geometry": {
    "type": "Point",
    "coordinates": [
      80.2103,
      6.0461
    ]
  }
}