{
  "type": "Feature",
  "properties": {
    "name": "La Cocha",
    "country": "AR",
    "subdivision": "24",
    "timezone": "America/Argentina/Tucuman"
  },
  "geometry": {
    "type": "Point",
    "coordinates": [
      -65.58711,
      -27.76927
    ]
  }
}