{
  "type": "Feature",
  "properties": {
    "name": "Tafí Viejo",
    "country": "AR",
    "subdivision": "24",
    "timezone": "America/Argentina/Tucuman"
  },
  "geometry": {
    "type": "Point",
    "coordinates": [
      -65.25921,
      -26.73201
    ]
  }
}