{
  "type": "Feature",
  "properties": {
    "name": "Diego de Almagro",
    "country": "CL",
    "subdivision": "05",
    "timezone": "America/Santiago"
  },
  "geometry": {
    "type": "Point",
    "coordinates": [
      -70.05,
      -26.36667
    ]
  }
}