{
  "type": "Feature",
  "properties": {
    "name": "Oujda-Angad",
    "country": "MA",
    "subdivision": "02",
    "timezone": "Africa/Casablanca"
  },
  "geometry": {
    "type": "Point",
    "coordinates": [
      -1.90858,
      34.68139
    ]
  }
}