{
  "type": "Feature",
  "properties": {
    "name": "Chernyakhovsk",
    "country": "RU",
    "subdivision": "23",
    "timezone": "Europe/Kaliningrad"
  },
  "geometry": {
    "type": "Point",
    "coordinates": [
      21.81557,
      54.63345
    ]
  }
}