{
  "type": "Feature",
  "properties": {
    "name": "Schellenberg",
    "country": "LI",
    "subdivision": "08",
    "timezone": "Europe/Vaduz"
  },
  "geometry": {
    "type": "Point",
    "coordinates": [
      9.54678,
      47.23123
    ]
  }
}