{
  "type": "Feature",
  "properties": {
    "name": "Braník",
    "country": "CZ",
    "subdivision": "52",
    "timezone": "Europe/Prague"
  },
  "geometry": {
    "type": "Point",
    "coordinates": [
      14.41518,
      50.03498
    ]
  }
}