{
  "type": "Feature",
  "properties": {
    "name": "Satalice",
    "country": "CZ",
    "subdivision": "52",
    "timezone": "Europe/Prague"
  },
  "geometry": {
    "type": "Point",
    "coordinates": [
      14.57191,
      50.12484
    ]
  }
}