{
  "type": "Feature",
  "properties": {
    "name": "Střížkov",
    "country": "CZ",
    "subdivision": "52",
    "timezone": "Europe/Prague"
  },
  "geometry": {
    "type": "Point",
    "coordinates": [
      14.49363,
      50.12674
    ]
  }
}