{
  "type": "Feature",
  "properties": {
    "name": "Alcoy",
    "country": "PH",
    "subdivision": "07",
    "timezone": "Asia/Manila"
  },
  "geometry": {
    "type": "Point",
    "coordinates": [
      123.5067,
      9.7102
    ]
  }
}