{
  "type": "Feature",
  "properties": {
    "name": "Alpaco",
    "country": "PH",
    "subdivision": "07",
    "timezone": "Asia/Manila"
  },
  "geometry": {
    "type": "Point",
    "coordinates": [
      123.6825,
      10.24378
    ]
  }
}