{
  "type": "Feature",
  "properties": {
    "name": "Bagacay",
    "country": "PH",
    "subdivision": "07",
    "timezone": "Asia/Manila"
  },
  "geometry": {
    "type": "Point",
    "coordinates": [
      124.25857,
      10.15209
    ]
  }
}