{
  "type": "Feature",
  "properties": {
    "name": "Bogo",
    "country": "PH",
    "subdivision": "07",
    "timezone": "Asia/Manila"
  },
  "geometry": {
    "type": "Point",
    "coordinates": [
      124.0055,
      11.0517
    ]
  }
}