{
  "type": "Feature",
  "properties": {
    "name": "Cambanay",
    "country": "PH",
    "subdivision": "07",
    "timezone": "Asia/Manila"
  },
  "geometry": {
    "type": "Point",
    "coordinates": [
      123.98611,
      10.54361
    ]
  }
}