{
  "type": "Feature",
  "properties": {
    "name": "Cansuje",
    "country": "PH",
    "subdivision": "07",
    "timezone": "Asia/Manila"
  },
  "geometry": {
    "type": "Point",
    "coordinates": [
      123.49629,
      9.92314
    ]
  }
}