{
  "type": "Feature",
  "properties": {
    "name": "Cogtong",
    "country": "PH",
    "subdivision": "07",
    "timezone": "Asia/Manila"
  },
  "geometry": {
    "type": "Point",
    "coordinates": [
      124.5291,
      9.8374
    ]
  }
}