{
  "type": "Feature",
  "properties": {
    "name": "Daanbantayan",
    "country": "PH",
    "subdivision": "07",
    "timezone": "Asia/Manila"
  },
  "geometry": {
    "type": "Point",
    "coordinates": [
      124.01462,
      11.24681
    ]
  }
}