{
  "type": "Feature",
  "properties": {
    "name": "Datagon",
    "country": "PH",
    "subdivision": "07",
    "timezone": "Asia/Manila"
  },
  "geometry": {
    "type": "Point",
    "coordinates": [
      123.0891,
      9.4461
    ]
  }
}