{
  "type": "Feature",
  "properties": {
    "name": "Dumanjog",
    "country": "PH",
    "subdivision": "07",
    "timezone": "Asia/Manila"
  },
  "geometry": {
    "type": "Point",
    "coordinates": [
      123.4361,
      10.057
    ]
  }
}