{
  "type": "Feature",
  "properties": {
    "name": "Guiwanon",
    "country": "PH",
    "subdivision": "07",
    "timezone": "Asia/Manila"
  },
  "geometry": {
    "type": "Point",
    "coordinates": [
      123.708,
      11.1975
    ]
  }
}