{
  "type": "Feature",
  "properties": {
    "name": "Kabac",
    "country": "PH",
    "subdivision": "07",
    "timezone": "Asia/Manila"
  },
  "geometry": {
    "type": "Point",
    "coordinates": [
      123.6979,
      11.2353
    ]
  }
}