{
  "type": "Feature",
  "properties": {
    "name": "Kaongkod",
    "country": "PH",
    "subdivision": "07",
    "timezone": "Asia/Manila"
  },
  "geometry": {
    "type": "Point",
    "coordinates": [
      123.75556,
      11.25028
    ]
  }
}