{
  "type": "Feature",
  "properties": {
    "name": "Lanas",
    "country": "PH",
    "subdivision": "07",
    "timezone": "Asia/Manila"
  },
  "geometry": {
    "type": "Point",
    "coordinates": [
      123.73333,
      10.26667
    ]
  }
}