{
  "type": "Feature",
  "properties": {
    "name": "Lombog",
    "country": "PH",
    "subdivision": "07",
    "timezone": "Asia/Manila"
  },
  "geometry": {
    "type": "Point",
    "coordinates": [
      124.4174,
      9.7788
    ]
  }
}