{
  "type": "Feature",
  "properties": {
    "name": "Madridejos",
    "country": "PH",
    "subdivision": "07",
    "timezone": "Asia/Manila"
  },
  "geometry": {
    "type": "Point",
    "coordinates": [
      123.7339,
      11.298
    ]
  }
}