{
  "type": "Feature",
  "properties": {
    "name": "Manalongon",
    "country": "PH",
    "subdivision": "07",
    "timezone": "Asia/Manila"
  },
  "geometry": {
    "type": "Point",
    "coordinates": [
      122.886,
      9.2209
    ]
  }
}