{
  "type": "Feature",
  "properties": {
    "name": "Medellin",
    "country": "PH",
    "subdivision": "07",
    "timezone": "Asia/Manila"
  },
  "geometry": {
    "type": "Point",
    "coordinates": [
      123.9622,
      11.1286
    ]
  }
}