{
  "type": "Feature",
  "properties": {
    "name": "Mercedes",
    "country": "PH",
    "subdivision": "07",
    "timezone": "Asia/Manila"
  },
  "geometry": {
    "type": "Point",
    "coordinates": [
      124.4021,
      10.6686
    ]
  }
}