{
  "type": "Feature",
  "properties": {
    "name": "Nalundan",
    "country": "PH",
    "subdivision": "07",
    "timezone": "Asia/Manila"
  },
  "geometry": {
    "type": "Point",
    "coordinates": [
      123.06667,
      9.75
    ]
  }
}