{
  "type": "Feature",
  "properties": {
    "name": "Nangka",
    "country": "PH",
    "subdivision": "07",
    "timezone": "Asia/Manila"
  },
  "geometry": {
    "type": "Point",
    "coordinates": [
      123.96667,
      10.55
    ]
  }
}