{
  "type": "Feature",
  "properties": {
    "name": "Paypay",
    "country": "PH",
    "subdivision": "07",
    "timezone": "Asia/Manila"
  },
  "geometry": {
    "type": "Point",
    "coordinates": [
      123.9762,
      11.2152
    ]
  }
}