{
  "type": "Feature",
  "properties": {
    "name": "Pinamungahan",
    "country": "PH",
    "subdivision": "07",
    "timezone": "Asia/Manila"
  },
  "geometry": {
    "type": "Point",
    "coordinates": [
      123.5839,
      10.2708
    ]
  }
}