{
  "type": "Feature",
  "properties": {
    "name": "San Francisco",
    "country": "PH",
    "subdivision": "07",
    "timezone": "Asia/Manila"
  },
  "geometry": {
    "type": "Point",
    "coordinates": [
      124.3816,
      10.6461
    ]
  }
}