{
  "type": "Feature",
  "properties": {
    "name": "Santa Cruz",
    "country": "PH",
    "subdivision": "07",
    "timezone": "Asia/Manila"
  },
  "geometry": {
    "type": "Point",
    "coordinates": [
      124.3386,
      10.6514
    ]
  }
}