{
  "type": "Feature",
  "properties": {
    "name": "Sibulan",
    "country": "PH",
    "subdivision": "07",
    "timezone": "Asia/Manila"
  },
  "geometry": {
    "type": "Point",
    "coordinates": [
      123.285,
      9.3584
    ]
  }
}