{
  "type": "Feature",
  "properties": {
    "name": "Tajao",
    "country": "PH",
    "subdivision": "07",
    "timezone": "Asia/Manila"
  },
  "geometry": {
    "type": "Point",
    "coordinates": [
      123.5835,
      10.3148
    ]
  }
}