{
  "type": "Feature",
  "properties": {
    "name": "Tawala",
    "country": "PH",
    "subdivision": "07",
    "timezone": "Asia/Manila"
  },
  "geometry": {
    "type": "Point",
    "coordinates": [
      123.76955,
      9.55421
    ]
  }
}