{
  "type": "Feature",
  "properties": {
    "name": "Ubay",
    "country": "PH",
    "subdivision": "07",
    "timezone": "Asia/Manila"
  },
  "geometry": {
    "type": "Point",
    "coordinates": [
      124.47294,
      10.056
    ]
  }
}