{
  "type": "Feature",
  "properties": {
    "name": "Curuan",
    "country": "PH",
    "subdivision": "09",
    "timezone": "Asia/Manila"
  },
  "geometry": {
    "type": "Point",
    "coordinates": [
      122.23306,
      7.20528
    ]
  }
}