{
  "type": "Feature",
  "properties": {
    "name": "Dulian",
    "country": "PH",
    "subdivision": "09",
    "timezone": "Asia/Manila"
  },
  "geometry": {
    "type": "Point",
    "coordinates": [
      122.17889,
      7.12139
    ]
  }
}