{
  "type": "Feature",
  "properties": {
    "name": "East Migpulao",
    "country": "PH",
    "subdivision": "09",
    "timezone": "Asia/Manila"
  },
  "geometry": {
    "type": "Point",
    "coordinates": [
      123.35917,
      7.6325
    ]
  }
}