{
  "type": "Feature",
  "properties": {
    "name": "Labangan",
    "country": "PH",
    "subdivision": "09",
    "timezone": "Asia/Manila"
  },
  "geometry": {
    "type": "Point",
    "coordinates": [
      123.5123,
      7.8654
    ]
  }
}