{
  "type": "Feature",
  "properties": {
    "name": "Malayal",
    "country": "PH",
    "subdivision": "09",
    "timezone": "Asia/Manila"
  },
  "geometry": {
    "type": "Point",
    "coordinates": [
      121.94204,
      7.20801
    ]
  }
}