{
  "type": "Feature",
  "properties": {
    "name": "Muti",
    "country": "PH",
    "subdivision": "09",
    "timezone": "Asia/Manila"
  },
  "geometry": {
    "type": "Point",
    "coordinates": [
      122.28,
      7.27583
    ]
  }
}