{
  "type": "Feature",
  "properties": {
    "name": "Olingan",
    "country": "PH",
    "subdivision": "09",
    "timezone": "Asia/Manila"
  },
  "geometry": {
    "type": "Point",
    "coordinates": [
      123.3216,
      8.5381
    ]
  }
}