{
  "type": "Feature",
  "properties": {
    "name": "Olutanga",
    "country": "PH",
    "subdivision": "09",
    "timezone": "Asia/Manila"
  },
  "geometry": {
    "type": "Point",
    "coordinates": [
      122.84639,
      7.31056
    ]
  }
}