{
  "type": "Feature",
  "properties": {
    "name": "Polanco",
    "country": "PH",
    "subdivision": "09",
    "timezone": "Asia/Manila"
  },
  "geometry": {
    "type": "Point",
    "coordinates": [
      123.3617,
      8.5329
    ]
  }
}