{
  "type": "Feature",
  "properties": {
    "name": "Recodo",
    "country": "PH",
    "subdivision": "09",
    "timezone": "Asia/Manila"
  },
  "geometry": {
    "type": "Point",
    "coordinates": [
      121.96361,
      6.95194
    ]
  }
}