{
  "type": "Feature",
  "properties": {
    "name": "Robonkon",
    "country": "PH",
    "subdivision": "09",
    "timezone": "Asia/Manila"
  },
  "geometry": {
    "type": "Point",
    "coordinates": [
      123.4187,
      7.7535
    ]
  }
}