{
  "type": "Feature",
  "properties": {
    "name": "Tagasilay",
    "country": "PH",
    "subdivision": "09",
    "timezone": "Asia/Manila"
  },
  "geometry": {
    "type": "Point",
    "coordinates": [
      122.25861,
      7.3025
    ]
  }
}