{
  "type": "Feature",
  "properties": {
    "name": "Tigtabon",
    "country": "PH",
    "subdivision": "09",
    "timezone": "Asia/Manila"
  },
  "geometry": {
    "type": "Point",
    "coordinates": [
      122.16694,
      6.89556
    ]
  }
}