{
  "type": "Feature",
  "properties": {
    "name": "Tolosa",
    "country": "PH",
    "subdivision": "09",
    "timezone": "Asia/Manila"
  },
  "geometry": {
    "type": "Point",
    "coordinates": [
      122.16139,
      7.03222
    ]
  }
}