{
  "type": "Feature",
  "properties": {
    "name": "Opotiki",
    "country": "NZ",
    "subdivision": "E8",
    "timezone": "Pacific/Auckland"
  },
  "geometry": {
    "type": "Point",
    "coordinates": [
      177.28706,
      -38.00915
    ]
  }
}