{
  "type": "Feature",
  "properties": {
    "name": "Hasaki",
    "country": "JP",
    "subdivision": "04",
    "timezone": "Asia/Tokyo"
  },
  "geometry": {
    "type": "Point",
    "coordinates": [
      140.83333,
      35.73333
    ]
  }
}