{
  "type": "Feature",
  "properties": {
    "name": "Nagareyama",
    "country": "JP",
    "subdivision": "04",
    "timezone": "Asia/Tokyo"
  },
  "geometry": {
    "type": "Point",
    "coordinates": [
      139.90266,
      35.8563
    ]
  }
}