{
  "type": "Feature",
  "properties": {
    "name": "Cantuna",
    "country": "MX",
    "subdivision": "32",
    "timezone": "America/Mexico_City"
  },
  "geometry": {
    "type": "Point",
    "coordinates": [
      -103.3463,
      23.6246
    ]
  }
}