{
  "type": "Feature",
  "properties": {
    "name": "Colonia Montemariana (Colonia Mariana)",
    "country": "MX",
    "subdivision": "32",
    "timezone": "America/Mexico_City"
  },
  "geometry": {
    "type": "Point",
    "coordinates": [
      -103.11222,
      23.32639
    ]
  }
}