{
  "type": "Feature",
  "properties": {
    "name": "El Cazadero",
    "country": "MX",
    "subdivision": "32",
    "timezone": "America/Mexico_City"
  },
  "geometry": {
    "type": "Point",
    "coordinates": [
      -103.1222,
      23.6725
    ]
  }
}