{
  "type": "Feature",
  "properties": {
    "name": "El Salvador",
    "country": "MX",
    "subdivision": "32",
    "timezone": "America/Mexico_City"
  },
  "geometry": {
    "type": "Point",
    "coordinates": [
      -100.86631,
      24.52093
    ]
  }
}