{
  "type": "Feature",
  "properties": {
    "name": "Estancia de Ánimas",
    "country": "MX",
    "subdivision": "32",
    "timezone": "America/Mexico_City"
  },
  "geometry": {
    "type": "Point",
    "coordinates": [
      -101.99526,
      22.48795
    ]
  }
}