{
  "type": "Feature",
  "properties": {
    "name": "Hacienda Nueva",
    "country": "MX",
    "subdivision": "32",
    "timezone": "America/Mexico_City"
  },
  "geometry": {
    "type": "Point",
    "coordinates": [
      -102.60836,
      22.82461
    ]
  }
}