{
  "type": "Feature",
  "properties": {
    "name": "Lázaro Cárdenas (Rancho Grande)",
    "country": "MX",
    "subdivision": "32",
    "timezone": "America/Mexico_City"
  },
  "geometry": {
    "type": "Point",
    "coordinates": [
      -102.9625,
      23.45056
    ]
  }
}