{
  "type": "Feature",
  "properties": {
    "name": "Martínez Domínguez",
    "country": "MX",
    "subdivision": "32",
    "timezone": "America/Mexico_City"
  },
  "geometry": {
    "type": "Point",
    "coordinates": [
      -102.48111,
      22.74806
    ]
  }
}