{
  "type": "Feature",
  "properties": {
    "name": "Pastoría",
    "country": "MX",
    "subdivision": "32",
    "timezone": "America/Mexico_City"
  },
  "geometry": {
    "type": "Point",
    "coordinates": [
      -102.08184,
      22.48615
    ]
  }
}