{
  "type": "Feature",
  "properties": {
    "name": "Sain Bajo",
    "country": "MX",
    "subdivision": "32",
    "timezone": "America/Mexico_City"
  },
  "geometry": {
    "type": "Point",
    "coordinates": [
      -103.17447,
      23.61627
    ]
  }
}