{
  "type": "Feature",
  "properties": {
    "name": "San Blas",
    "country": "MX",
    "subdivision": "32",
    "timezone": "America/Mexico_City"
  },
  "geometry": {
    "type": "Point",
    "coordinates": [
      -101.95497,
      22.29899
    ]
  }
}