{
  "type": "Feature",
  "properties": {
    "name": "Santa Rita",
    "country": "MX",
    "subdivision": "32",
    "timezone": "America/Mexico_City"
  },
  "geometry": {
    "type": "Point",
    "coordinates": [
      -102.91629,
      23.94422
    ]
  }
}