{
  "type": "Feature",
  "properties": {
    "name": "Curicó",
    "country": "CL",
    "subdivision": "11",
    "timezone": "America/Santiago"
  },
  "geometry": {
    "type": "Point",
    "coordinates": [
      -71.23943,
      -34.98279
    ]
  }
}