{
  "type": "Feature",
  "properties": {
    "name": "Linares",
    "country": "CL",
    "subdivision": "11",
    "timezone": "America/Santiago"
  },
  "geometry": {
    "type": "Point",
    "coordinates": [
      -71.59308,
      -35.84667
    ]
  }
}