{
  "type": "Feature",
  "properties": {
    "name": "Boali",
    "country": "CF",
    "subdivision": "17",
    "timezone": "Africa/Bangui"
  },
  "geometry": {
    "type": "Point",
    "coordinates": [
      18.12747,
      4.80048
    ]
  }
}