{
  "type": "Feature",
  "properties": {
    "name": "Chongwe",
    "country": "ZM",
    "subdivision": "09",
    "timezone": "Africa/Lusaka"
  },
  "geometry": {
    "type": "Point",
    "coordinates": [
      28.68204,
      -15.32916
    ]
  }
}