{
  "type": "Feature",
  "properties": {
    "name": "Jebrail",
    "country": "AZ",
    "subdivision": "14",
    "timezone": "Asia/Baku"
  },
  "geometry": {
    "type": "Point",
    "coordinates": [
      47.02835,
      39.39917
    ]
  }
}