{
  "type": "Feature",
  "properties": {
    "name": "Acireale",
    "country": "IT",
    "subdivision": "15",
    "timezone": "Europe/Rome"
  },
  "geometry": {
    "type": "Point",
    "coordinates": [
      15.16577,
      37.60886
    ]
  }
}