{
  "type": "Feature",
  "properties": {
    "name": "Agira",
    "country": "IT",
    "subdivision": "15",
    "timezone": "Europe/Rome"
  },
  "geometry": {
    "type": "Point",
    "coordinates": [
      14.51972,
      37.6558
    ]
  }
}