{
  "type": "Feature",
  "properties": {
    "name": "Aidone",
    "country": "IT",
    "subdivision": "15",
    "timezone": "Europe/Rome"
  },
  "geometry": {
    "type": "Point",
    "coordinates": [
      14.44542,
      37.41468
    ]
  }
}