{
  "type": "Feature",
  "properties": {
    "name": "Alimena",
    "country": "IT",
    "subdivision": "15",
    "timezone": "Europe/Rome"
  },
  "geometry": {
    "type": "Point",
    "coordinates": [
      14.11369,
      37.6931
    ]
  }
}