{
  "type": "Feature",
  "properties": {
    "name": "Altavilla Milicia",
    "country": "IT",
    "subdivision": "15",
    "timezone": "Europe/Rome"
  },
  "geometry": {
    "type": "Point",
    "coordinates": [
      13.54947,
      38.038
    ]
  }
}