{
  "type": "Feature",
  "properties": {
    "name": "Aragona",
    "country": "IT",
    "subdivision": "15",
    "timezone": "Europe/Rome"
  },
  "geometry": {
    "type": "Point",
    "coordinates": [
      13.61974,
      37.39904
    ]
  }
}