{
  "type": "Feature",
  "properties": {
    "name": "Bivona",
    "country": "IT",
    "subdivision": "15",
    "timezone": "Europe/Rome"
  },
  "geometry": {
    "type": "Point",
    "coordinates": [
      13.43895,
      37.61797
    ]
  }
}