{
  "type": "Feature",
  "properties": {
    "name": "Calatafimi",
    "country": "IT",
    "subdivision": "15",
    "timezone": "Europe/Rome"
  },
  "geometry": {
    "type": "Point",
    "coordinates": [
      12.86364,
      37.9144
    ]
  }
}