{
  "type": "Feature",
  "properties": {
    "name": "Calatabiano",
    "country": "IT",
    "subdivision": "15",
    "timezone": "Europe/Rome"
  },
  "geometry": {
    "type": "Point",
    "coordinates": [
      15.23069,
      37.82049
    ]
  }
}