{
  "type": "Feature",
  "properties": {
    "name": "Campobello di Licata",
    "country": "IT",
    "subdivision": "15",
    "timezone": "Europe/Rome"
  },
  "geometry": {
    "type": "Point",
    "coordinates": [
      13.91811,
      37.25759
    ]
  }
}