{
  "type": "Feature",
  "properties": {
    "name": "Campofranco",
    "country": "IT",
    "subdivision": "15",
    "timezone": "Europe/Rome"
  },
  "geometry": {
    "type": "Point",
    "coordinates": [
      13.71213,
      37.51208
    ]
  }
}