{
  "type": "Feature",
  "properties": {
    "name": "Campobello di Mazara",
    "country": "IT",
    "subdivision": "15",
    "timezone": "Europe/Rome"
  },
  "geometry": {
    "type": "Point",
    "coordinates": [
      12.74946,
      37.63464
    ]
  }
}