{
  "type": "Feature",
  "properties": {
    "name": "Casteltermini",
    "country": "IT",
    "subdivision": "15",
    "timezone": "Europe/Rome"
  },
  "geometry": {
    "type": "Point",
    "coordinates": [
      13.64601,
      37.53874
    ]
  }
}