{
  "type": "Feature",
  "properties": {
    "name": "Centuripe",
    "country": "IT",
    "subdivision": "15",
    "timezone": "Europe/Rome"
  },
  "geometry": {
    "type": "Point",
    "coordinates": [
      14.74049,
      37.62336
    ]
  }
}