{
  "type": "Feature",
  "properties": {
    "name": "Cerza",
    "country": "IT",
    "subdivision": "15",
    "timezone": "Europe/Rome"
  },
  "geometry": {
    "type": "Point",
    "coordinates": [
      15.1051,
      37.54297
    ]
  }
}