{
  "type": "Feature",
  "properties": {
    "name": "Collesano",
    "country": "IT",
    "subdivision": "15",
    "timezone": "Europe/Rome"
  },
  "geometry": {
    "type": "Point",
    "coordinates": [
      13.93702,
      37.91809
    ]
  }
}