{
  "type": "Feature",
  "properties": {
    "name": "Gaggi",
    "country": "IT",
    "subdivision": "15",
    "timezone": "Europe/Rome"
  },
  "geometry": {
    "type": "Point",
    "coordinates": [
      15.22126,
      37.85995
    ]
  }
}