{
  "type": "Feature",
  "properties": {
    "name": "Gangi",
    "country": "IT",
    "subdivision": "15",
    "timezone": "Europe/Rome"
  },
  "geometry": {
    "type": "Point",
    "coordinates": [
      14.20437,
      37.79565
    ]
  }
}