{
  "type": "Feature",
  "properties": {
    "name": "Giarre",
    "country": "IT",
    "subdivision": "15",
    "timezone": "Europe/Rome"
  },
  "geometry": {
    "type": "Point",
    "coordinates": [
      15.18165,
      37.7244
    ]
  }
}