{
  "type": "Feature",
  "properties": {
    "name": "Gravina di Catania",
    "country": "IT",
    "subdivision": "15",
    "timezone": "Europe/Rome"
  },
  "geometry": {
    "type": "Point",
    "coordinates": [
      15.06292,
      37.56085
    ]
  }
}