{
  "type": "Feature",
  "properties": {
    "name": "Gualtieri Sicaminò",
    "country": "IT",
    "subdivision": "15",
    "timezone": "Europe/Rome"
  },
  "geometry": {
    "type": "Point",
    "coordinates": [
      15.31699,
      38.16267
    ]
  }
}