{
  "type": "Feature",
  "properties": {
    "name": "Ispica",
    "country": "IT",
    "subdivision": "15",
    "timezone": "Europe/Rome"
  },
  "geometry": {
    "type": "Point",
    "coordinates": [
      14.9053,
      36.78622
    ]
  }
}