{
  "type": "Feature",
  "properties": {
    "name": "Licodia Eubea",
    "country": "IT",
    "subdivision": "15",
    "timezone": "Europe/Rome"
  },
  "geometry": {
    "type": "Point",
    "coordinates": [
      14.70555,
      37.15674
    ]
  }
}