{
  "type": "Feature",
  "properties": {
    "name": "Maletto",
    "country": "IT",
    "subdivision": "15",
    "timezone": "Europe/Rome"
  },
  "geometry": {
    "type": "Point",
    "coordinates": [
      14.86403,
      37.82914
    ]
  }
}