{
  "type": "Feature",
  "properties": {
    "name": "Marianopoli",
    "country": "IT",
    "subdivision": "15",
    "timezone": "Europe/Rome"
  },
  "geometry": {
    "type": "Point",
    "coordinates": [
      13.9152,
      37.5984
    ]
  }
}