{
  "type": "Feature",
  "properties": {
    "name": "Mascali",
    "country": "IT",
    "subdivision": "15",
    "timezone": "Europe/Rome"
  },
  "geometry": {
    "type": "Point",
    "coordinates": [
      15.19662,
      37.75794
    ]
  }
}