{
  "type": "Feature",
  "properties": {
    "name": "Mazzarrà Sant'Andrea",
    "country": "IT",
    "subdivision": "15",
    "timezone": "Europe/Rome"
  },
  "geometry": {
    "type": "Point",
    "coordinates": [
      15.13535,
      38.08969
    ]
  }
}