{
  "type": "Feature",
  "properties": {
    "name": "Milazzo",
    "country": "IT",
    "subdivision": "15",
    "timezone": "Europe/Rome"
  },
  "geometry": {
    "type": "Point",
    "coordinates": [
      15.24023,
      38.22008
    ]
  }
}