{
  "type": "Feature",
  "properties": {
    "name": "Monforte San Giorgio",
    "country": "IT",
    "subdivision": "15",
    "timezone": "Europe/Rome"
  },
  "geometry": {
    "type": "Point",
    "coordinates": [
      15.38132,
      38.15733
    ]
  }
}