{
  "type": "Feature",
  "properties": {
    "name": "Monterosso Almo",
    "country": "IT",
    "subdivision": "15",
    "timezone": "Europe/Rome"
  },
  "geometry": {
    "type": "Point",
    "coordinates": [
      14.76498,
      37.08884
    ]
  }
}