{
  "type": "Feature",
  "properties": {
    "name": "Mussomeli",
    "country": "IT",
    "subdivision": "15",
    "timezone": "Europe/Rome"
  },
  "geometry": {
    "type": "Point",
    "coordinates": [
      13.75214,
      37.58067
    ]
  }
}