{
  "type": "Feature",
  "properties": {
    "name": "Naro",
    "country": "IT",
    "subdivision": "15",
    "timezone": "Europe/Rome"
  },
  "geometry": {
    "type": "Point",
    "coordinates": [
      13.79337,
      37.29248
    ]
  }
}