{
  "type": "Feature",
  "properties": {
    "name": "Nuova Gibellina",
    "country": "IT",
    "subdivision": "15",
    "timezone": "Europe/Rome"
  },
  "geometry": {
    "type": "Point",
    "coordinates": [
      12.86954,
      37.80704
    ]
  }
}