{
  "type": "Feature",
  "properties": {
    "name": "Nuovo Centro Urbano Poggioreale",
    "country": "IT",
    "subdivision": "15",
    "timezone": "Europe/Rome"
  },
  "geometry": {
    "type": "Point",
    "coordinates": [
      13.03594,
      37.76404
    ]
  }
}