{
  "type": "Feature",
  "properties": {
    "name": "Palazzo Adriano",
    "country": "IT",
    "subdivision": "15",
    "timezone": "Europe/Rome"
  },
  "geometry": {
    "type": "Point",
    "coordinates": [
      13.37941,
      37.68066
    ]
  }
}