{
  "type": "Feature",
  "properties": {
    "name": "Patti",
    "country": "IT",
    "subdivision": "15",
    "timezone": "Europe/Rome"
  },
  "geometry": {
    "type": "Point",
    "coordinates": [
      14.96409,
      38.14736
    ]
  }
}