{
  "type": "Feature",
  "properties": {
    "name": "Ragalna",
    "country": "IT",
    "subdivision": "15",
    "timezone": "Europe/Rome"
  },
  "geometry": {
    "type": "Point",
    "coordinates": [
      14.94698,
      37.63455
    ]
  }
}