{
  "type": "Feature",
  "properties": {
    "name": "Roccapalumba",
    "country": "IT",
    "subdivision": "15",
    "timezone": "Europe/Rome"
  },
  "geometry": {
    "type": "Point",
    "coordinates": [
      13.63671,
      37.80825
    ]
  }
}