{
  "type": "Feature",
  "properties": {
    "name": "Rodì",
    "country": "IT",
    "subdivision": "15",
    "timezone": "Europe/Rome"
  },
  "geometry": {
    "type": "Point",
    "coordinates": [
      15.16933,
      38.10823
    ]
  }
}