{
  "type": "Feature",
  "properties": {
    "name": "Salaparuta",
    "country": "IT",
    "subdivision": "15",
    "timezone": "Europe/Rome"
  },
  "geometry": {
    "type": "Point",
    "coordinates": [
      13.00981,
      37.75694
    ]
  }
}