{
  "type": "Feature",
  "properties": {
    "name": "Salemi",
    "country": "IT",
    "subdivision": "15",
    "timezone": "Europe/Rome"
  },
  "geometry": {
    "type": "Point",
    "coordinates": [
      12.80506,
      37.82199
    ]
  }
}