{
  "type": "Feature",
  "properties": {
    "name": "Sambuca di Sicilia",
    "country": "IT",
    "subdivision": "15",
    "timezone": "Europe/Rome"
  },
  "geometry": {
    "type": "Point",
    "coordinates": [
      13.11462,
      37.65294
    ]
  }
}