{
  "type": "Feature",
  "properties": {
    "name": "San Giuseppe Jato",
    "country": "IT",
    "subdivision": "15",
    "timezone": "Europe/Rome"
  },
  "geometry": {
    "type": "Point",
    "coordinates": [
      13.18889,
      37.97331
    ]
  }
}