{
  "type": "Feature",
  "properties": {
    "name": "San Teodoro",
    "country": "IT",
    "subdivision": "15",
    "timezone": "Europe/Rome"
  },
  "geometry": {
    "type": "Point",
    "coordinates": [
      14.69878,
      37.84797
    ]
  }
}