{
  "type": "Feature",
  "properties": {
    "name": "San Pietro Clarenza",
    "country": "IT",
    "subdivision": "15",
    "timezone": "Europe/Rome"
  },
  "geometry": {
    "type": "Point",
    "coordinates": [
      15.02289,
      37.56885
    ]
  }
}