{
  "type": "Feature",
  "properties": {
    "name": "Santa Domenica Vittoria",
    "country": "IT",
    "subdivision": "15",
    "timezone": "Europe/Rome"
  },
  "geometry": {
    "type": "Point",
    "coordinates": [
      14.96288,
      37.91624
    ]
  }
}