{
  "type": "Feature",
  "properties": {
    "name": "Santa Margherita di Belice",
    "country": "IT",
    "subdivision": "15",
    "timezone": "Europe/Rome"
  },
  "geometry": {
    "type": "Point",
    "coordinates": [
      13.01584,
      37.69281
    ]
  }
}