{
  "type": "Feature",
  "properties": {
    "name": "Santa Venerina",
    "country": "IT",
    "subdivision": "15",
    "timezone": "Europe/Rome"
  },
  "geometry": {
    "type": "Point",
    "coordinates": [
      15.1388,
      37.69103
    ]
  }
}