{
  "type": "Feature",
  "properties": {
    "name": "Scaletta Zanclea",
    "country": "IT",
    "subdivision": "15",
    "timezone": "Europe/Rome"
  },
  "geometry": {
    "type": "Point",
    "coordinates": [
      15.46769,
      38.04796
    ]
  }
}