{
  "type": "Feature",
  "properties": {
    "name": "Scicli",
    "country": "IT",
    "subdivision": "15",
    "timezone": "Europe/Rome"
  },
  "geometry": {
    "type": "Point",
    "coordinates": [
      14.7028,
      36.79014
    ]
  }
}