{
  "type": "Feature",
  "properties": {
    "name": "Sinagra",
    "country": "IT",
    "subdivision": "15",
    "timezone": "Europe/Rome"
  },
  "geometry": {
    "type": "Point",
    "coordinates": [
      14.85009,
      38.08191
    ]
  }
}