{
  "type": "Feature",
  "properties": {
    "name": "Spadafora",
    "country": "IT",
    "subdivision": "15",
    "timezone": "Europe/Rome"
  },
  "geometry": {
    "type": "Point",
    "coordinates": [
      15.38178,
      38.22349
    ]
  }
}