{
  "type": "Feature",
  "properties": {
    "name": "Torretta",
    "country": "IT",
    "subdivision": "15",
    "timezone": "Europe/Rome"
  },
  "geometry": {
    "type": "Point",
    "coordinates": [
      13.23549,
      38.13036
    ]
  }
}