{
  "type": "Feature",
  "properties": {
    "name": "Tre Fontane",
    "country": "IT",
    "subdivision": "15",
    "timezone": "Europe/Rome"
  },
  "geometry": {
    "type": "Point",
    "coordinates": [
      12.72423,
      37.56989
    ]
  }
}