{
  "type": "Feature",
  "properties": {
    "name": "Trecastagni",
    "country": "IT",
    "subdivision": "15",
    "timezone": "Europe/Rome"
  },
  "geometry": {
    "type": "Point",
    "coordinates": [
      15.07796,
      37.61543
    ]
  }
}