{
  "type": "Feature",
  "properties": {
    "name": "Valguarnera Caropepe",
    "country": "IT",
    "subdivision": "15",
    "timezone": "Europe/Rome"
  },
  "geometry": {
    "type": "Point",
    "coordinates": [
      14.39025,
      37.49527
    ]
  }
}