{
  "type": "Feature",
  "properties": {
    "name": "Villabate",
    "country": "IT",
    "subdivision": "15",
    "timezone": "Europe/Rome"
  },
  "geometry": {
    "type": "Point",
    "coordinates": [
      13.44275,
      38.07789
    ]
  }
}