{
  "type": "Feature",
  "properties": {
    "name": "Zafferana Etnea",
    "country": "IT",
    "subdivision": "15",
    "timezone": "Europe/Rome"
  },
  "geometry": {
    "type": "Point",
    "coordinates": [
      15.10432,
      37.67895
    ]
  }
}