{
  "type": "Feature",
  "properties": {
    "name": "Saray",
    "country": "AZ",
    "subdivision": "01",
    "timezone": "Asia/Baku"
  },
  "geometry": {
    "type": "Point",
    "coordinates": [
      49.71681,
      40.53299
    ]
  }
}