{
  "type": "Feature",
  "properties": {
    "name": "Affton",
    "country": "US",
    "subdivision": "MO",
    "timezone": "America/Chicago"
  },
  "geometry": {
    "type": "Point",
    "coordinates": [
      -90.33317,
      38.55061
    ]
  }
}