{
  "type": "Feature",
  "properties": {
    "name": "Ballwin",
    "country": "US",
    "subdivision": "MO",
    "timezone": "America/Chicago"
  },
  "geometry": {
    "type": "Point",
    "coordinates": [
      -90.54623,
      38.59505
    ]
  }
}