{
  "type": "Feature",
  "properties": {
    "name": "Bowling Green",
    "country": "US",
    "subdivision": "MO",
    "timezone": "America/Chicago"
  },
  "geometry": {
    "type": "Point",
    "coordinates": [
      -91.19514,
      39.34199
    ]
  }
}