{
  "type": "Feature",
  "properties": {
    "name": "Buffalo",
    "country": "US",
    "subdivision": "MO",
    "timezone": "America/Chicago"
  },
  "geometry": {
    "type": "Point",
    "coordinates": [
      -93.09241,
      37.64393
    ]
  }
}