{
  "type": "Feature",
  "properties": {
    "name": "California",
    "country": "US",
    "subdivision": "MO",
    "timezone": "America/Chicago"
  },
  "geometry": {
    "type": "Point",
    "coordinates": [
      -92.56658,
      38.62753
    ]
  }
}