{
  "type": "Feature",
  "properties": {
    "name": "Carl Junction",
    "country": "US",
    "subdivision": "MO",
    "timezone": "America/Chicago"
  },
  "geometry": {
    "type": "Point",
    "coordinates": [
      -94.56551,
      37.17672
    ]
  }
}