{
  "type": "Feature",
  "properties": {
    "name": "Centralia",
    "country": "US",
    "subdivision": "MO",
    "timezone": "America/Chicago"
  },
  "geometry": {
    "type": "Point",
    "coordinates": [
      -92.13795,
      39.21032
    ]
  }
}