{
  "type": "Feature",
  "properties": {
    "name": "Dixon",
    "country": "US",
    "subdivision": "MO",
    "timezone": "America/Chicago"
  },
  "geometry": {
    "type": "Point",
    "coordinates": [
      -92.09378,
      37.99171
    ]
  }
}