{
  "type": "Feature",
  "properties": {
    "name": "El Dorado Springs",
    "country": "US",
    "subdivision": "MO",
    "timezone": "America/Chicago"
  },
  "geometry": {
    "type": "Point",
    "coordinates": [
      -94.02133,
      37.87698
    ]
  }
}