{
  "type": "Feature",
  "properties": {
    "name": "Elsberry",
    "country": "US",
    "subdivision": "MO",
    "timezone": "America/Chicago"
  },
  "geometry": {
    "type": "Point",
    "coordinates": [
      -90.78096,
      39.16672
    ]
  }
}