{
  "type": "Feature",
  "properties": {
    "name": "Gerald",
    "country": "US",
    "subdivision": "MO",
    "timezone": "America/Chicago"
  },
  "geometry": {
    "type": "Point",
    "coordinates": [
      -91.33071,
      38.39977
    ]
  }
}