{
  "type": "Feature",
  "properties": {
    "name": "Gladstone",
    "country": "US",
    "subdivision": "MO",
    "timezone": "America/Chicago"
  },
  "geometry": {
    "type": "Point",
    "coordinates": [
      -94.55468,
      39.20389
    ]
  }
}