{
  "type": "Feature",
  "properties": {
    "name": "Higginsville",
    "country": "US",
    "subdivision": "MO",
    "timezone": "America/Chicago"
  },
  "geometry": {
    "type": "Point",
    "coordinates": [
      -93.71716,
      39.07251
    ]
  }
}