{
  "type": "Feature",
  "properties": {
    "name": "Holts Summit",
    "country": "US",
    "subdivision": "MO",
    "timezone": "America/Chicago"
  },
  "geometry": {
    "type": "Point",
    "coordinates": [
      -92.12241,
      38.64032
    ]
  }
}