{
  "type": "Feature",
  "properties": {
    "name": "Huntsville",
    "country": "US",
    "subdivision": "MO",
    "timezone": "America/Chicago"
  },
  "geometry": {
    "type": "Point",
    "coordinates": [
      -92.54518,
      39.44059
    ]
  }
}