{
  "type": "Feature",
  "properties": {
    "name": "Kirksville",
    "country": "US",
    "subdivision": "MO",
    "timezone": "America/Chicago"
  },
  "geometry": {
    "type": "Point",
    "coordinates": [
      -92.58325,
      40.19475
    ]
  }
}