{
  "type": "Feature",
  "properties": {
    "name": "Lexington",
    "country": "US",
    "subdivision": "MO",
    "timezone": "America/Chicago"
  },
  "geometry": {
    "type": "Point",
    "coordinates": [
      -93.87994,
      39.18473
    ]
  }
}