{
  "type": "Feature",
  "properties": {
    "name": "Liberty",
    "country": "US",
    "subdivision": "MO",
    "timezone": "America/Chicago"
  },
  "geometry": {
    "type": "Point",
    "coordinates": [
      -94.41912,
      39.24611
    ]
  }
}