{
  "type": "Feature",
  "properties": {
    "name": "Moberly",
    "country": "US",
    "subdivision": "MO",
    "timezone": "America/Chicago"
  },
  "geometry": {
    "type": "Point",
    "coordinates": [
      -92.43824,
      39.41837
    ]
  }
}