{
  "type": "Feature",
  "properties": {
    "name": "Monroe City",
    "country": "US",
    "subdivision": "MO",
    "timezone": "America/Chicago"
  },
  "geometry": {
    "type": "Point",
    "coordinates": [
      -91.73461,
      39.65365
    ]
  }
}