{
  "type": "Feature",
  "properties": {
    "name": "New Haven",
    "country": "US",
    "subdivision": "MO",
    "timezone": "America/Chicago"
  },
  "geometry": {
    "type": "Point",
    "coordinates": [
      -91.21904,
      38.60838
    ]
  }
}