{
  "type": "Feature",
  "properties": {
    "name": "Normandy",
    "country": "US",
    "subdivision": "MO",
    "timezone": "America/Chicago"
  },
  "geometry": {
    "type": "Point",
    "coordinates": [
      -90.29734,
      38.72088
    ]
  }
}