{
  "type": "Feature",
  "properties": {
    "name": "Odessa",
    "country": "US",
    "subdivision": "MO",
    "timezone": "America/Chicago"
  },
  "geometry": {
    "type": "Point",
    "coordinates": [
      -93.95356,
      38.99917
    ]
  }
}