{
  "type": "Feature",
  "properties": {
    "name": "Ozark",
    "country": "US",
    "subdivision": "MO",
    "timezone": "America/Chicago"
  },
  "geometry": {
    "type": "Point",
    "coordinates": [
      -93.20602,
      37.02089
    ]
  }
}