{
  "type": "Feature",
  "properties": {
    "name": "Park Hills",
    "country": "US",
    "subdivision": "MO",
    "timezone": "America/Chicago"
  },
  "geometry": {
    "type": "Point",
    "coordinates": [
      -90.51818,
      37.85422
    ]
  }
}