{
  "type": "Feature",
  "properties": {
    "name": "Raytown",
    "country": "US",
    "subdivision": "MO",
    "timezone": "America/Chicago"
  },
  "geometry": {
    "type": "Point",
    "coordinates": [
      -94.46356,
      39.00862
    ]
  }
}