{
  "type": "Feature",
  "properties": {
    "name": "Republic",
    "country": "US",
    "subdivision": "MO",
    "timezone": "America/Chicago"
  },
  "geometry": {
    "type": "Point",
    "coordinates": [
      -93.48019,
      37.12005
    ]
  }
}