{
  "type": "Feature",
  "properties": {
    "name": "Rock Port",
    "country": "US",
    "subdivision": "MO",
    "timezone": "America/Chicago"
  },
  "geometry": {
    "type": "Point",
    "coordinates": [
      -95.51693,
      40.41111
    ]
  }
}