{
  "type": "Feature",
  "properties": {
    "name": "St. Louis",
    "country": "US",
    "subdivision": "MO",
    "timezone": "America/Chicago"
  },
  "geometry": {
    "type": "Point",
    "coordinates": [
      -90.19789,
      38.62727
    ]
  }
}