{
  "type": "Feature",
  "properties": {
    "name": "Sunset Hills",
    "country": "US",
    "subdivision": "MO",
    "timezone": "America/Chicago"
  },
  "geometry": {
    "type": "Point",
    "coordinates": [
      -90.40734,
      38.53894
    ]
  }
}