{
  "type": "Feature",
  "properties": {
    "name": "Tipton",
    "country": "US",
    "subdivision": "MO",
    "timezone": "America/Chicago"
  },
  "geometry": {
    "type": "Point",
    "coordinates": [
      -92.77992,
      38.65558
    ]
  }
}