{
  "type": "Feature",
  "properties": {
    "name": "Town and Country",
    "country": "US",
    "subdivision": "MO",
    "timezone": "America/Chicago"
  },
  "geometry": {
    "type": "Point",
    "coordinates": [
      -90.46345,
      38.61228
    ]
  }
}