{
  "type": "Feature",
  "properties": {
    "name": "Troy",
    "country": "US",
    "subdivision": "MO",
    "timezone": "America/Chicago"
  },
  "geometry": {
    "type": "Point",
    "coordinates": [
      -90.9807,
      38.97949
    ]
  }
}