{
  "type": "Feature",
  "properties": {
    "name": "Union",
    "country": "US",
    "subdivision": "MO",
    "timezone": "America/Chicago"
  },
  "geometry": {
    "type": "Point",
    "coordinates": [
      -91.00848,
      38.45005
    ]
  }
}