{
  "type": "Feature",
  "properties": {
    "name": "Vandalia",
    "country": "US",
    "subdivision": "MO",
    "timezone": "America/Chicago"
  },
  "geometry": {
    "type": "Point",
    "coordinates": [
      -91.48849,
      39.31087
    ]
  }
}