{
  "type": "Feature",
  "properties": {
    "name": "Villa Ridge",
    "country": "US",
    "subdivision": "MO",
    "timezone": "America/Chicago"
  },
  "geometry": {
    "type": "Point",
    "coordinates": [
      -90.8868,
      38.47255
    ]
  }
}