{
  "type": "Feature",
  "properties": {
    "name": "Vinita Park",
    "country": "US",
    "subdivision": "MO",
    "timezone": "America/Chicago"
  },
  "geometry": {
    "type": "Point",
    "coordinates": [
      -90.34262,
      38.69005
    ]
  }
}