{
  "type": "Feature",
  "properties": {
    "name": "Warson Woods",
    "country": "US",
    "subdivision": "MO",
    "timezone": "America/Chicago"
  },
  "geometry": {
    "type": "Point",
    "coordinates": [
      -90.38345,
      38.60727
    ]
  }
}