{
  "type": "Feature",
  "properties": {
    "name": "Weston",
    "country": "US",
    "subdivision": "MO",
    "timezone": "America/Chicago"
  },
  "geometry": {
    "type": "Point",
    "coordinates": [
      -94.90163,
      39.41111
    ]
  }
}