{
  "type": "Feature",
  "properties": {
    "name": "Windsor",
    "country": "US",
    "subdivision": "MO",
    "timezone": "America/Chicago"
  },
  "geometry": {
    "type": "Point",
    "coordinates": [
      -93.52215,
      38.53224
    ]
  }
}