{
  "type": "Feature",
  "properties": {
    "name": "Bykivka",
    "country": "UA",
    "subdivision": "27",
    "timezone": "Europe/Kiev"
  },
  "geometry": {
    "type": "Point",
    "coordinates": [
      27.98314,
      50.29285
    ]
  }
}