{
  "type": "Feature",
  "properties": {
    "name": "Chornorudka",
    "country": "UA",
    "subdivision": "27",
    "timezone": "Europe/Kiev"
  },
  "geometry": {
    "type": "Point",
    "coordinates": [
      29.06143,
      49.8428
    ]
  }
}