{
  "type": "Feature",
  "properties": {
    "name": "Denyshi",
    "country": "UA",
    "subdivision": "27",
    "timezone": "Europe/Kiev"
  },
  "geometry": {
    "type": "Point",
    "coordinates": [
      28.40395,
      50.21415
    ]
  }
}