{
  "type": "Feature",
  "properties": {
    "name": "Korostyshiv",
    "country": "UA",
    "subdivision": "27",
    "timezone": "Europe/Kiev"
  },
  "geometry": {
    "type": "Point",
    "coordinates": [
      29.0563,
      50.31723
    ]
  }
}