{
  "type": "Feature",
  "properties": {
    "name": "Liubar",
    "country": "UA",
    "subdivision": "27",
    "timezone": "Europe/Kiev"
  },
  "geometry": {
    "type": "Point",
    "coordinates": [
      27.76323,
      49.92243
    ]
  }
}