{
  "type": "Feature",
  "properties": {
    "name": "Luhyny",
    "country": "UA",
    "subdivision": "27",
    "timezone": "Europe/Kiev"
  },
  "geometry": {
    "type": "Point",
    "coordinates": [
      28.40057,
      51.08203
    ]
  }
}