{
  "type": "Feature",
  "properties": {
    "name": "Pershotravneve",
    "country": "UA",
    "subdivision": "27",
    "timezone": "Europe/Kiev"
  },
  "geometry": {
    "type": "Point",
    "coordinates": [
      28.86837,
      51.39287
    ]
  }
}