{
  "type": "Feature",
  "properties": {
    "name": "Bor",
    "country": "SE",
    "subdivision": "08",
    "timezone": "Europe/Stockholm"
  },
  "geometry": {
    "type": "Point",
    "coordinates": [
      14.16667,
      57.11667
    ]
  }
}