{
  "type": "Feature",
  "properties": {
    "name": "Gränna",
    "country": "SE",
    "subdivision": "08",
    "timezone": "Europe/Stockholm"
  },
  "geometry": {
    "type": "Point",
    "coordinates": [
      14.46667,
      58.01667
    ]
  }
}