{
  "type": "Feature",
  "properties": {
    "name": "Marieholm",
    "country": "SE",
    "subdivision": "08",
    "timezone": "Europe/Stockholm"
  },
  "geometry": {
    "type": "Point",
    "coordinates": [
      13.85,
      57.38333
    ]
  }
}