{
  "type": "Feature",
  "properties": {
    "name": "Tenhult",
    "country": "SE",
    "subdivision": "08",
    "timezone": "Europe/Stockholm"
  },
  "geometry": {
    "type": "Point",
    "coordinates": [
      14.32205,
      57.70761
    ]
  }
}