{
  "type": "Feature",
  "properties": {
    "name": "Um Jar Al Gharbiyya",
    "country": "SD",
    "subdivision": "41",
    "timezone": "Africa/Khartoum"
  },
  "geometry": {
    "type": "Point",
    "coordinates": [
      32.4078,
      13.8013
    ]
  }
}