{
  "type": "Feature",
  "properties": {
    "name": "Balsorano Nuovo",
    "country": "IT",
    "subdivision": "01",
    "timezone": "Europe/Rome"
  },
  "geometry": {
    "type": "Point",
    "coordinates": [
      13.56069,
      41.80881
    ]
  }
}