{
  "type": "Feature",
  "properties": {
    "name": "Bussi sul Tirino",
    "country": "IT",
    "subdivision": "01",
    "timezone": "Europe/Rome"
  },
  "geometry": {
    "type": "Point",
    "coordinates": [
      13.82511,
      42.21321
    ]
  }
}