{
  "type": "Feature",
  "properties": {
    "name": "Castelnuovo Vomano",
    "country": "IT",
    "subdivision": "01",
    "timezone": "Europe/Rome"
  },
  "geometry": {
    "type": "Point",
    "coordinates": [
      13.85003,
      42.62933
    ]
  }
}