{
  "type": "Feature",
  "properties": {
    "name": "Collecorvino",
    "country": "IT",
    "subdivision": "01",
    "timezone": "Europe/Rome"
  },
  "geometry": {
    "type": "Point",
    "coordinates": [
      14.01564,
      42.46024
    ]
  }
}