{
  "type": "Feature",
  "properties": {
    "name": "Fonte Umano-San Martino Alta",
    "country": "IT",
    "subdivision": "01",
    "timezone": "Europe/Rome"
  },
  "geometry": {
    "type": "Point",
    "coordinates": [
      14.1076,
      42.52084
    ]
  }
}