{
  "type": "Feature",
  "properties": {
    "name": "Francavilla al Mare",
    "country": "IT",
    "subdivision": "01",
    "timezone": "Europe/Rome"
  },
  "geometry": {
    "type": "Point",
    "coordinates": [
      14.28217,
      42.42158
    ]
  }
}