{
  "type": "Feature",
  "properties": {
    "name": "Gessopalena",
    "country": "IT",
    "subdivision": "01",
    "timezone": "Europe/Rome"
  },
  "geometry": {
    "type": "Point",
    "coordinates": [
      14.27367,
      42.05521
    ]
  }
}