{
  "type": "Feature",
  "properties": {
    "name": "Guardiagrele",
    "country": "IT",
    "subdivision": "01",
    "timezone": "Europe/Rome"
  },
  "geometry": {
    "type": "Point",
    "coordinates": [
      14.21939,
      42.19406
    ]
  }
}