{
  "type": "Feature",
  "properties": {
    "name": "Magliano De'Marsi",
    "country": "IT",
    "subdivision": "01",
    "timezone": "Europe/Rome"
  },
  "geometry": {
    "type": "Point",
    "coordinates": [
      13.36379,
      42.09153
    ]
  }
}