{
  "type": "Feature",
  "properties": {
    "name": "Montorio al Vomano",
    "country": "IT",
    "subdivision": "01",
    "timezone": "Europe/Rome"
  },
  "geometry": {
    "type": "Point",
    "coordinates": [
      13.63715,
      42.58123
    ]
  }
}