{
  "type": "Feature",
  "properties": {
    "name": "Pescara",
    "country": "IT",
    "subdivision": "01",
    "timezone": "Europe/Rome"
  },
  "geometry": {
    "type": "Point",
    "coordinates": [
      14.20283,
      42.4584
    ]
  }
}