{
  "type": "Feature",
  "properties": {
    "name": "Pianella",
    "country": "IT",
    "subdivision": "01",
    "timezone": "Europe/Rome"
  },
  "geometry": {
    "type": "Point",
    "coordinates": [
      14.04781,
      42.39918
    ]
  }
}