{
  "type": "Feature",
  "properties": {
    "name": "Pineto",
    "country": "IT",
    "subdivision": "01",
    "timezone": "Europe/Rome"
  },
  "geometry": {
    "type": "Point",
    "coordinates": [
      14.06639,
      42.60879
    ]
  }
}