{
  "type": "Feature",
  "properties": {
    "name": "San Nicolò a Tordino",
    "country": "IT",
    "subdivision": "01",
    "timezone": "Europe/Rome"
  },
  "geometry": {
    "type": "Point",
    "coordinates": [
      13.79708,
      42.69648
    ]
  }
}