{
  "type": "Feature",
  "properties": {
    "name": "Santa Teresa",
    "country": "IT",
    "subdivision": "01",
    "timezone": "Europe/Rome"
  },
  "geometry": {
    "type": "Point",
    "coordinates": [
      14.15816,
      42.42753
    ]
  }
}