{
  "type": "Feature",
  "properties": {
    "name": "Sassa",
    "country": "IT",
    "subdivision": "01",
    "timezone": "Europe/Rome"
  },
  "geometry": {
    "type": "Point",
    "coordinates": [
      13.29924,
      42.35204
    ]
  }
}