{
  "type": "Feature",
  "properties": {
    "name": "Spoltore",
    "country": "IT",
    "subdivision": "01",
    "timezone": "Europe/Rome"
  },
  "geometry": {
    "type": "Point",
    "coordinates": [
      14.13988,
      42.45501
    ]
  }
}