{
  "type": "Feature",
  "properties": {
    "name": "Teramo",
    "country": "IT",
    "subdivision": "01",
    "timezone": "Europe/Rome"
  },
  "geometry": {
    "type": "Point",
    "coordinates": [
      13.69901,
      42.66123
    ]
  }
}