{
  "type": "Feature",
  "properties": {
    "name": "Tollo",
    "country": "IT",
    "subdivision": "01",
    "timezone": "Europe/Rome"
  },
  "geometry": {
    "type": "Point",
    "coordinates": [
      14.3236,
      42.34542
    ]
  }
}