{
  "type": "Feature",
  "properties": {
    "name": "Vasto",
    "country": "IT",
    "subdivision": "01",
    "timezone": "Europe/Rome"
  },
  "geometry": {
    "type": "Point",
    "coordinates": [
      14.70649,
      42.1115
    ]
  }
}