{
  "type": "Feature",
  "properties": {
    "name": "Villamagna",
    "country": "IT",
    "subdivision": "01",
    "timezone": "Europe/Rome"
  },
  "geometry": {
    "type": "Point",
    "coordinates": [
      14.23689,
      42.32984
    ]
  }
}