{
  "type": "Feature",
  "properties": {
    "name": "Shwebo",
    "country": "MM",
    "subdivision": "10",
    "timezone": "Asia/Yangon"
  },
  "geometry": {
    "type": "Point",
    "coordinates": [
      95.69818,
      22.56925
    ]
  }
}