{
  "type": "Feature",
  "properties": {
    "name": "Chajul",
    "country": "GT",
    "subdivision": "14",
    "timezone": "America/Guatemala"
  },
  "geometry": {
    "type": "Point",
    "coordinates": [
      -91.0352,
      15.48523
    ]
  }
}