{
  "type": "Feature",
  "properties": {
    "name": "San Bartolomé Jocotenango",
    "country": "GT",
    "subdivision": "14",
    "timezone": "America/Guatemala"
  },
  "geometry": {
    "type": "Point",
    "coordinates": [
      -91.07806,
      15.19153
    ]
  }
}