{
  "type": "Feature",
  "properties": {
    "name": "Chuāri Khās",
    "country": "IN",
    "subdivision": "11",
    "timezone": "Asia/Kolkata"
  },
  "geometry": {
    "type": "Point",
    "coordinates": [
      76.01428,
      32.43058
    ]
  }
}