{
  "type": "Feature",
  "properties": {
    "name": "Hamīrpur",
    "country": "IN",
    "subdivision": "11",
    "timezone": "Asia/Kolkata"
  },
  "geometry": {
    "type": "Point",
    "coordinates": [
      76.52506,
      31.68411
    ]
  }
}