{
  "type": "Feature",
  "properties": {
    "name": "Jubbal",
    "country": "IN",
    "subdivision": "11",
    "timezone": "Asia/Kolkata"
  },
  "geometry": {
    "type": "Point",
    "coordinates": [
      77.65085,
      31.10923
    ]
  }
}