{
  "type": "Feature",
  "properties": {
    "name": "SabÄthu",
    "country": "IN",
    "subdivision": "11",
    "timezone": "Asia/Kolkata"
  },
  "geometry": {
    "type": "Point",
    "coordinates": [
      76.99137,
      30.97494
    ]
  }
}