{
  "type": "Feature",
  "properties": {
    "name": "Sundarnagar",
    "country": "IN",
    "subdivision": "11",
    "timezone": "Asia/Kolkata"
  },
  "geometry": {
    "type": "Point",
    "coordinates": [
      76.905,
      31.53523
    ]
  }
}