{
  "type": "Feature",
  "properties": {
    "name": "Acamixtla",
    "country": "MX",
    "subdivision": "12",
    "timezone": "America/Mexico_City"
  },
  "geometry": {
    "type": "Point",
    "coordinates": [
      -99.56599,
      18.56512
    ]
  }
}