{
  "type": "Feature",
  "properties": {
    "name": "Acapetlahuaya",
    "country": "MX",
    "subdivision": "12",
    "timezone": "America/Mexico_City"
  },
  "geometry": {
    "type": "Point",
    "coordinates": [
      -100.07237,
      18.41942
    ]
  }
}