{
  "type": "Feature",
  "properties": {
    "name": "Alcozacán",
    "country": "MX",
    "subdivision": "12",
    "timezone": "America/Mexico_City"
  },
  "geometry": {
    "type": "Point",
    "coordinates": [
      -99.095,
      17.50444
    ]
  }
}