{
  "type": "Feature",
  "properties": {
    "name": "Alcozauca de Guerrero",
    "country": "MX",
    "subdivision": "12",
    "timezone": "America/Mexico_City"
  },
  "geometry": {
    "type": "Point",
    "coordinates": [
      -98.38428,
      17.46481
    ]
  }
}