{
  "type": "Feature",
  "properties": {
    "name": "Almolonga",
    "country": "MX",
    "subdivision": "12",
    "timezone": "America/Mexico_City"
  },
  "geometry": {
    "type": "Point",
    "coordinates": [
      -99.29502,
      17.63826
    ]
  }
}