{
  "type": "Feature",
  "properties": {
    "name": "Aratichanguío",
    "country": "MX",
    "subdivision": "12",
    "timezone": "America/Mexico_City"
  },
  "geometry": {
    "type": "Point",
    "coordinates": [
      -101.36211,
      18.47877
    ]
  }
}