{
  "type": "Feature",
  "properties": {
    "name": "Arcelia de Rodríguez",
    "country": "MX",
    "subdivision": "12",
    "timezone": "America/Mexico_City"
  },
  "geometry": {
    "type": "Point",
    "coordinates": [
      -98.64486,
      16.73668
    ]
  }
}