{
  "type": "Feature",
  "properties": {
    "name": "Atenango del Río",
    "country": "MX",
    "subdivision": "12",
    "timezone": "America/Mexico_City"
  },
  "geometry": {
    "type": "Point",
    "coordinates": [
      -99.10777,
      18.10526
    ]
  }
}