{
  "type": "Feature",
  "properties": {
    "name": "Atzacoaloya",
    "country": "MX",
    "subdivision": "12",
    "timezone": "America/Mexico_City"
  },
  "geometry": {
    "type": "Point",
    "coordinates": [
      -99.13757,
      17.54659
    ]
  }
}