{
  "type": "Feature",
  "properties": {
    "name": "Buenavista de Cuéllar",
    "country": "MX",
    "subdivision": "12",
    "timezone": "America/Mexico_City"
  },
  "geometry": {
    "type": "Point",
    "coordinates": [
      -99.40868,
      18.45958
    ]
  }
}