{
  "type": "Feature",
  "properties": {
    "name": "Cacalotenango",
    "country": "MX",
    "subdivision": "12",
    "timezone": "America/Mexico_City"
  },
  "geometry": {
    "type": "Point",
    "coordinates": [
      -99.64361,
      18.54639
    ]
  }
}