{
  "type": "Feature",
  "properties": {
    "name": "Cahuatache",
    "country": "MX",
    "subdivision": "12",
    "timezone": "America/Mexico_City"
  },
  "geometry": {
    "type": "Point",
    "coordinates": [
      -98.53184,
      17.41624
    ]
  }
}