{
  "type": "Feature",
  "properties": {
    "name": "Coahuayutla de Guerrero",
    "country": "MX",
    "subdivision": "12",
    "timezone": "America/Mexico_City"
  },
  "geometry": {
    "type": "Point",
    "coordinates": [
      -101.73574,
      18.31469
    ]
  }
}