{
  "type": "Feature",
  "properties": {
    "name": "Cochoapa el Grande",
    "country": "MX",
    "subdivision": "12",
    "timezone": "America/Mexico_City"
  },
  "geometry": {
    "type": "Point",
    "coordinates": [
      -98.45592,
      17.1928
    ]
  }
}