{
  "type": "Feature",
  "properties": {
    "name": "Colonia Alborada",
    "country": "MX",
    "subdivision": "12",
    "timezone": "America/Mexico_City"
  },
  "geometry": {
    "type": "Point",
    "coordinates": [
      -99.81779,
      16.88151
    ]
  }
}