{
  "type": "Feature",
  "properties": {
    "name": "Colotepec",
    "country": "MX",
    "subdivision": "12",
    "timezone": "America/Mexico_City"
  },
  "geometry": {
    "type": "Point",
    "coordinates": [
      -99.21273,
      17.04104
    ]
  }
}