{
  "type": "Feature",
  "properties": {
    "name": "Coyahualco",
    "country": "MX",
    "subdivision": "12",
    "timezone": "America/Mexico_City"
  },
  "geometry": {
    "type": "Point",
    "coordinates": [
      -98.56667,
      17.74139
    ]
  }
}