{
  "type": "Feature",
  "properties": {
    "name": "Cuatzoquitengo",
    "country": "MX",
    "subdivision": "12",
    "timezone": "America/Mexico_City"
  },
  "geometry": {
    "type": "Point",
    "coordinates": [
      -98.61523,
      17.28822
    ]
  }
}