{
  "type": "Feature",
  "properties": {
    "name": "Cuauhtenango",
    "country": "MX",
    "subdivision": "12",
    "timezone": "America/Mexico_City"
  },
  "geometry": {
    "type": "Point",
    "coordinates": [
      -99.20683,
      17.54625
    ]
  }
}