{
  "type": "Feature",
  "properties": {
    "name": "El Conchero",
    "country": "MX",
    "subdivision": "12",
    "timezone": "America/Mexico_City"
  },
  "geometry": {
    "type": "Point",
    "coordinates": [
      -99.96233,
      16.94266
    ]
  }
}