{
  "type": "Feature",
  "properties": {
    "name": "El Coacoyul",
    "country": "MX",
    "subdivision": "12",
    "timezone": "America/Mexico_City"
  },
  "geometry": {
    "type": "Point",
    "coordinates": [
      -101.47571,
      17.6381
    ]
  }
}