{
  "type": "Feature",
  "properties": {
    "name": "El Jicaral",
    "country": "MX",
    "subdivision": "12",
    "timezone": "America/Mexico_City"
  },
  "geometry": {
    "type": "Point",
    "coordinates": [
      -98.19697,
      17.12617
    ]
  }
}