{
  "type": "Feature",
  "properties": {
    "name": "El Mesón",
    "country": "MX",
    "subdivision": "12",
    "timezone": "America/Mexico_City"
  },
  "geometry": {
    "type": "Point",
    "coordinates": [
      -99.05868,
      16.8457
    ]
  }
}