{
  "type": "Feature",
  "properties": {
    "name": "El Pericón",
    "country": "MX",
    "subdivision": "12",
    "timezone": "America/Mexico_City"
  },
  "geometry": {
    "type": "Point",
    "coordinates": [
      -99.32573,
      16.98001
    ]
  }
}