{
  "type": "Feature",
  "properties": {
    "name": "El Rincón (Santa Cruz del Rincón)",
    "country": "MX",
    "subdivision": "12",
    "timezone": "America/Mexico_City"
  },
  "geometry": {
    "type": "Point",
    "coordinates": [
      -98.73528,
      16.99611
    ]
  }
}