{
  "type": "Feature",
  "properties": {
    "name": "Kilómetro 40",
    "country": "MX",
    "subdivision": "12",
    "timezone": "America/Mexico_City"
  },
  "geometry": {
    "type": "Point",
    "coordinates": [
      -99.77056,
      17.04944
    ]
  }
}