{
  "type": "Feature",
  "properties": {
    "name": "La Azozuca",
    "country": "MX",
    "subdivision": "12",
    "timezone": "America/Mexico_City"
  },
  "geometry": {
    "type": "Point",
    "coordinates": [
      -99.04194,
      16.82139
    ]
  }
}