{
  "type": "Feature",
  "properties": {
    "name": "La Concepción",
    "country": "MX",
    "subdivision": "12",
    "timezone": "America/Mexico_City"
  },
  "geometry": {
    "type": "Point",
    "coordinates": [
      -99.6514,
      16.87867
    ]
  }
}