{
  "type": "Feature",
  "properties": {
    "name": "La Unión",
    "country": "MX",
    "subdivision": "12",
    "timezone": "America/Mexico_City"
  },
  "geometry": {
    "type": "Point",
    "coordinates": [
      -101.80655,
      17.98561
    ]
  }
}