{
  "type": "Feature",
  "properties": {
    "name": "Los Mogotes",
    "country": "MX",
    "subdivision": "12",
    "timezone": "America/Mexico_City"
  },
  "geometry": {
    "type": "Point",
    "coordinates": [
      -100.07653,
      16.9417
    ]
  }
}