{
  "type": "Feature",
  "properties": {
    "name": "Los Liros",
    "country": "MX",
    "subdivision": "12",
    "timezone": "America/Mexico_City"
  },
  "geometry": {
    "type": "Point",
    "coordinates": [
      -98.21722,
      16.73972
    ]
  }
}