{
  "type": "Feature",
  "properties": {
    "name": "Los Almendros",
    "country": "MX",
    "subdivision": "12",
    "timezone": "America/Mexico_City"
  },
  "geometry": {
    "type": "Point",
    "coordinates": [
      -101.43917,
      17.61167
    ]
  }
}