{
  "type": "Feature",
  "properties": {
    "name": "Mazatlán",
    "country": "MX",
    "subdivision": "12",
    "timezone": "America/Mexico_City"
  },
  "geometry": {
    "type": "Point",
    "coordinates": [
      -99.46483,
      17.4362
    ]
  }
}