{
  "type": "Feature",
  "properties": {
    "name": "Palos Blancos",
    "country": "MX",
    "subdivision": "12",
    "timezone": "America/Mexico_City"
  },
  "geometry": {
    "type": "Point",
    "coordinates": [
      -101.3318,
      17.55851
    ]
  }
}