{
  "type": "Feature",
  "properties": {
    "name": "Paso Morelos",
    "country": "MX",
    "subdivision": "12",
    "timezone": "America/Mexico_City"
  },
  "geometry": {
    "type": "Point",
    "coordinates": [
      -99.20984,
      18.22123
    ]
  }
}