{
  "type": "Feature",
  "properties": {
    "name": "Rancho de las Lomas",
    "country": "MX",
    "subdivision": "12",
    "timezone": "America/Mexico_City"
  },
  "geometry": {
    "type": "Point",
    "coordinates": [
      -99.24583,
      17.73972
    ]
  }
}