{
  "type": "Feature",
  "properties": {
    "name": "San Martín",
    "country": "MX",
    "subdivision": "12",
    "timezone": "America/Mexico_City"
  },
  "geometry": {
    "type": "Point",
    "coordinates": [
      -99.29436,
      17.46311
    ]
  }
}