{
  "type": "Feature",
  "properties": {
    "name": "Santiago Tilapa",
    "country": "MX",
    "subdivision": "12",
    "timezone": "America/Mexico_City"
  },
  "geometry": {
    "type": "Point",
    "coordinates": [
      -98.26107,
      17.25889
    ]
  }
}