{
  "type": "Feature",
  "properties": {
    "name": "Santa Cruz Yucucani",
    "country": "MX",
    "subdivision": "12",
    "timezone": "America/Mexico_City"
  },
  "geometry": {
    "type": "Point",
    "coordinates": [
      -98.11298,
      17.0765
    ]
  }
}