{
  "type": "Feature",
  "properties": {
    "name": "Tlalchapa",
    "country": "MX",
    "subdivision": "12",
    "timezone": "America/Mexico_City"
  },
  "geometry": {
    "type": "Point",
    "coordinates": [
      -100.47623,
      18.41027
    ]
  }
}