{
  "type": "Feature",
  "properties": {
    "name": "Tlapehuala",
    "country": "MX",
    "subdivision": "12",
    "timezone": "America/Mexico_City"
  },
  "geometry": {
    "type": "Point",
    "coordinates": [
      -100.5379,
      18.24101
    ]
  }
}