{
  "type": "Feature",
  "properties": {
    "name": "Tonalapa",
    "country": "MX",
    "subdivision": "12",
    "timezone": "America/Mexico_City"
  },
  "geometry": {
    "type": "Point",
    "coordinates": [
      -99.24194,
      17.49056
    ]
  }
}