{
  "type": "Feature",
  "properties": {
    "name": "Tuxpan",
    "country": "MX",
    "subdivision": "12",
    "timezone": "America/Mexico_City"
  },
  "geometry": {
    "type": "Point",
    "coordinates": [
      -99.47965,
      18.34933
    ]
  }
}