{
  "type": "Feature",
  "properties": {
    "name": "Villa Rotaria",
    "country": "MX",
    "subdivision": "12",
    "timezone": "America/Mexico_City"
  },
  "geometry": {
    "type": "Point",
    "coordinates": [
      -100.66917,
      17.19444
    ]
  }
}