{
  "type": "Feature",
  "properties": {
    "name": "Xaltianguis",
    "country": "MX",
    "subdivision": "12",
    "timezone": "America/Mexico_City"
  },
  "geometry": {
    "type": "Point",
    "coordinates": [
      -99.71557,
      17.09834
    ]
  }
}