{
  "type": "Feature",
  "properties": {
    "name": "Zumpango",
    "country": "MX",
    "subdivision": "12",
    "timezone": "America/Mexico_City"
  },
  "geometry": {
    "type": "Point",
    "coordinates": [
      -98.68304,
      17.93521
    ]
  }
}