{
  "type": "Feature",
  "properties": {
    "name": "Anina",
    "country": "RO",
    "subdivision": "12",
    "timezone": "Europe/Bucharest"
  },
  "geometry": {
    "type": "Point",
    "coordinates": [
      21.85694,
      45.07944
    ]
  }
}