{
  "type": "Feature",
  "properties": {
    "name": "Borlova",
    "country": "RO",
    "subdivision": "12",
    "timezone": "Europe/Bucharest"
  },
  "geometry": {
    "type": "Point",
    "coordinates": [
      22.352,
      45.36738
    ]
  }
}