{
  "type": "Feature",
  "properties": {
    "name": "Constantin Daicoviciu",
    "country": "RO",
    "subdivision": "12",
    "timezone": "Europe/Bucharest"
  },
  "geometry": {
    "type": "Point",
    "coordinates": [
      22.15,
      45.55
    ]
  }
}