{
  "type": "Feature",
  "properties": {
    "name": "Greoni",
    "country": "RO",
    "subdivision": "12",
    "timezone": "Europe/Bucharest"
  },
  "geometry": {
    "type": "Point",
    "coordinates": [
      21.61731,
      45.08901
    ]
  }
}