{
  "type": "Feature",
  "properties": {
    "name": "Luncaviţa",
    "country": "RO",
    "subdivision": "12",
    "timezone": "Europe/Bucharest"
  },
  "geometry": {
    "type": "Point",
    "coordinates": [
      22.26667,
      45.08333
    ]
  }
}