{
  "type": "Feature",
  "properties": {
    "name": "Petroșnița",
    "country": "RO",
    "subdivision": "12",
    "timezone": "Europe/Bucharest"
  },
  "geometry": {
    "type": "Point",
    "coordinates": [
      22.2592,
      45.32351
    ]
  }
}