{
  "type": "Feature",
  "properties": {
    "name": "Răcăşdia",
    "country": "RO",
    "subdivision": "12",
    "timezone": "Europe/Bucharest"
  },
  "geometry": {
    "type": "Point",
    "coordinates": [
      21.61806,
      44.99306
    ]
  }
}