{
  "type": "Feature",
  "properties": {
    "name": "Vermeş",
    "country": "RO",
    "subdivision": "12",
    "timezone": "Europe/Bucharest"
  },
  "geometry": {
    "type": "Point",
    "coordinates": [
      21.65972,
      45.52056
    ]
  }
}