{
  "type": "Feature",
  "properties": {
    "name": "Nueva Guadalupe",
    "country": "SV",
    "subdivision": "09",
    "timezone": "America/El_Salvador"
  },
  "geometry": {
    "type": "Point",
    "coordinates": [
      -88.35,
      13.53333
    ]
  }
}