{
  "type": "Feature",
  "properties": {
    "name": "Zorgo",
    "country": "BF",
    "subdivision": "11",
    "timezone": "Africa/Ouagadougou"
  },
  "geometry": {
    "type": "Point",
    "coordinates": [
      -0.61527,
      12.24922
    ]
  }
}