{
  "type": "Feature",
  "properties": {
    "name": "Dêqên",
    "country": "CN",
    "subdivision": "14",
    "timezone": "Asia/Shanghai"
  },
  "geometry": {
    "type": "Point",
    "coordinates": [
      90.71875,
      29.96178
    ]
  }
}