{
  "type": "Feature",
  "properties": {
    "name": "Amărăştii de Jos",
    "country": "RO",
    "subdivision": "17",
    "timezone": "Europe/Bucharest"
  },
  "geometry": {
    "type": "Point",
    "coordinates": [
      24.16667,
      43.95
    ]
  }
}