{
  "type": "Feature",
  "properties": {
    "name": "Brabeți",
    "country": "RO",
    "subdivision": "17",
    "timezone": "Europe/Bucharest"
  },
  "geometry": {
    "type": "Point",
    "coordinates": [
      24.01339,
      43.96098
    ]
  }
}