{
  "type": "Feature",
  "properties": {
    "name": "Cerăt",
    "country": "RO",
    "subdivision": "17",
    "timezone": "Europe/Bucharest"
  },
  "geometry": {
    "type": "Point",
    "coordinates": [
      23.66667,
      44.06667
    ]
  }
}