{
  "type": "Feature",
  "properties": {
    "name": "Cernăteşti",
    "country": "RO",
    "subdivision": "17",
    "timezone": "Europe/Bucharest"
  },
  "geometry": {
    "type": "Point",
    "coordinates": [
      23.43333,
      44.45
    ]
  }
}