{
  "type": "Feature",
  "properties": {
    "name": "Desa",
    "country": "RO",
    "subdivision": "17",
    "timezone": "Europe/Bucharest"
  },
  "geometry": {
    "type": "Point",
    "coordinates": [
      23.03333,
      43.86667
    ]
  }
}