{
  "type": "Feature",
  "properties": {
    "name": "Fratoștița",
    "country": "RO",
    "subdivision": "17",
    "timezone": "Europe/Bucharest"
  },
  "geometry": {
    "type": "Point",
    "coordinates": [
      23.57044,
      44.58671
    ]
  }
}