{
  "type": "Feature",
  "properties": {
    "name": "Goiești",
    "country": "RO",
    "subdivision": "17",
    "timezone": "Europe/Bucharest"
  },
  "geometry": {
    "type": "Point",
    "coordinates": [
      23.76667,
      44.48333
    ]
  }
}