{
  "type": "Feature",
  "properties": {
    "name": "Întorsura",
    "country": "RO",
    "subdivision": "17",
    "timezone": "Europe/Bucharest"
  },
  "geometry": {
    "type": "Point",
    "coordinates": [
      23.57574,
      44.11226
    ]
  }
}