{
  "type": "Feature",
  "properties": {
    "name": "Mofleni",
    "country": "RO",
    "subdivision": "17",
    "timezone": "Europe/Bucharest"
  },
  "geometry": {
    "type": "Point",
    "coordinates": [
      23.75848,
      44.3022
    ]
  }
}