{
  "type": "Feature",
  "properties": {
    "name": "Pieleştí",
    "country": "RO",
    "subdivision": "17",
    "timezone": "Europe/Bucharest"
  },
  "geometry": {
    "type": "Point",
    "coordinates": [
      23.95,
      44.33333
    ]
  }
}