{
  "type": "Feature",
  "properties": {
    "name": "Rast",
    "country": "RO",
    "subdivision": "17",
    "timezone": "Europe/Bucharest"
  },
  "geometry": {
    "type": "Point",
    "coordinates": [
      23.28333,
      43.88333
    ]
  }
}