{
  "type": "Feature",
  "properties": {
    "name": "Ţuglui",
    "country": "RO",
    "subdivision": "17",
    "timezone": "Europe/Bucharest"
  },
  "geometry": {
    "type": "Point",
    "coordinates": [
      23.81667,
      44.18333
    ]
  }
}