{
  "type": "Feature",
  "properties": {
    "name": "Kamakwie",
    "country": "SL",
    "subdivision": "02",
    "timezone": "Africa/Freetown"
  },
  "geometry": {
    "type": "Point",
    "coordinates": [
      -12.24061,
      9.49689
    ]
  }
}