{
  "type": "Feature",
  "properties": {
    "name": "Mambolo",
    "country": "SL",
    "subdivision": "02",
    "timezone": "Africa/Freetown"
  },
  "geometry": {
    "type": "Point",
    "coordinates": [
      -13.03674,
      8.9186
    ]
  }
}