{
  "type": "Feature",
  "properties": {
    "name": "Rokupr",
    "country": "SL",
    "subdivision": "02",
    "timezone": "Africa/Freetown"
  },
  "geometry": {
    "type": "Point",
    "coordinates": [
      -12.38497,
      8.67121
    ]
  }
}