{
  "type": "Feature",
  "properties": {
    "name": "Casey",
    "country": "AU",
    "subdivision": "01",
    "timezone": "Australia/Sydney"
  },
  "geometry": {
    "type": "Point",
    "coordinates": [
      149.0947,
      -35.16701
    ]
  }
}