{
  "type": "Feature",
  "properties": {
    "name": "Downer",
    "country": "AU",
    "subdivision": "01",
    "timezone": "Australia/Sydney"
  },
  "geometry": {
    "type": "Point",
    "coordinates": [
      149.14468,
      -35.24457
    ]
  }
}