{
  "type": "Feature",
  "properties": {
    "name": "Harrison",
    "country": "AU",
    "subdivision": "01",
    "timezone": "Australia/Sydney"
  },
  "geometry": {
    "type": "Point",
    "coordinates": [
      149.15631,
      -35.19906
    ]
  }
}