{
  "type": "Feature",
  "properties": {
    "name": "Holt",
    "country": "AU",
    "subdivision": "01",
    "timezone": "Australia/Sydney"
  },
  "geometry": {
    "type": "Point",
    "coordinates": [
      149.01188,
      -35.22441
    ]
  }
}