{
  "type": "Feature",
  "properties": {
    "name": "Isaacs",
    "country": "AU",
    "subdivision": "01",
    "timezone": "Australia/Sydney"
  },
  "geometry": {
    "type": "Point",
    "coordinates": [
      149.11555,
      -35.36862
    ]
  }
}