{
  "type": "Feature",
  "properties": {
    "name": "Latham",
    "country": "AU",
    "subdivision": "01",
    "timezone": "Australia/Sydney"
  },
  "geometry": {
    "type": "Point",
    "coordinates": [
      149.03144,
      -35.21652
    ]
  }
}