{
  "type": "Feature",
  "properties": {
    "name": "Macquarie",
    "country": "AU",
    "subdivision": "01",
    "timezone": "Australia/Sydney"
  },
  "geometry": {
    "type": "Point",
    "coordinates": [
      149.06363,
      -35.25126
    ]
  }
}