{
  "type": "Feature",
  "properties": {
    "name": "Mawson",
    "country": "AU",
    "subdivision": "01",
    "timezone": "Australia/Sydney"
  },
  "geometry": {
    "type": "Point",
    "coordinates": [
      149.09863,
      -35.3634
    ]
  }
}