{
  "type": "Feature",
  "properties": {
    "name": "Monash",
    "country": "AU",
    "subdivision": "01",
    "timezone": "Australia/Sydney"
  },
  "geometry": {
    "type": "Point",
    "coordinates": [
      149.09063,
      -35.41577
    ]
  }
}