{
  "type": "Feature",
  "properties": {
    "name": "Narrabundah",
    "country": "AU",
    "subdivision": "01",
    "timezone": "Australia/Sydney"
  },
  "geometry": {
    "type": "Point",
    "coordinates": [
      149.14924,
      -35.3357
    ]
  }
}