{
  "type": "Feature",
  "properties": {
    "name": "Spence",
    "country": "AU",
    "subdivision": "01",
    "timezone": "Australia/Sydney"
  },
  "geometry": {
    "type": "Point",
    "coordinates": [
      149.06438,
      -35.19873
    ]
  }
}