{
  "type": "Feature",
  "properties": {
    "name": "Weston",
    "country": "AU",
    "subdivision": "01",
    "timezone": "Australia/Sydney"
  },
  "geometry": {
    "type": "Point",
    "coordinates": [
      149.05929,
      -35.33582
    ]
  }
}