{
  "type": "Feature",
  "properties": {
    "name": "Permatang Kuching",
    "country": "MY",
    "subdivision": "09",
    "timezone": "Asia/Kuala_Lumpur"
  },
  "geometry": {
    "type": "Point",
    "coordinates": [
      100.38144,
      5.46339
    ]
  }
}