{
  "type": "Feature",
  "properties": {
    "name": "Telaga Batu",
    "country": "MY",
    "subdivision": "09",
    "timezone": "Asia/Kuala_Lumpur"
  },
  "geometry": {
    "type": "Point",
    "coordinates": [
      100.23333,
      5.46667
    ]
  }
}