{
  "type": "Feature",
  "properties": {
    "name": "Boskamp",
    "country": "NL",
    "subdivision": "15",
    "timezone": "Europe/Amsterdam"
  },
  "geometry": {
    "type": "Point",
    "coordinates": [
      6.12778,
      52.33083
    ]
  }
}