{
  "type": "Feature",
  "properties": {
    "name": "Heino",
    "country": "NL",
    "subdivision": "15",
    "timezone": "Europe/Amsterdam"
  },
  "geometry": {
    "type": "Point",
    "coordinates": [
      6.23282,
      52.43661
    ]
  }
}