{
  "type": "Feature",
  "properties": {
    "name": "Hengelo",
    "country": "NL",
    "subdivision": "15",
    "timezone": "Europe/Amsterdam"
  },
  "geometry": {
    "type": "Point",
    "coordinates": [
      6.79306,
      52.26583
    ]
  }
}