{
  "type": "Feature",
  "properties": {
    "name": "Markelo",
    "country": "NL",
    "subdivision": "15",
    "timezone": "Europe/Amsterdam"
  },
  "geometry": {
    "type": "Point",
    "coordinates": [
      6.49861,
      52.235
    ]
  }
}