{
  "type": "Feature",
  "properties": {
    "name": "Mekkelholt",
    "country": "NL",
    "subdivision": "15",
    "timezone": "Europe/Amsterdam"
  },
  "geometry": {
    "type": "Point",
    "coordinates": [
      6.89058,
      52.23645
    ]
  }
}