{
  "type": "Feature",
  "properties": {
    "name": "Oosterholt",
    "country": "NL",
    "subdivision": "15",
    "timezone": "Europe/Amsterdam"
  },
  "geometry": {
    "type": "Point",
    "coordinates": [
      5.95556,
      52.55917
    ]
  }
}