{
  "type": "Feature",
  "properties": {
    "name": "Tubbergen",
    "country": "NL",
    "subdivision": "15",
    "timezone": "Europe/Amsterdam"
  },
  "geometry": {
    "type": "Point",
    "coordinates": [
      6.78472,
      52.4075
    ]
  }
}