{
  "type": "Feature",
  "properties": {
    "name": "Vriezenveen",
    "country": "NL",
    "subdivision": "15",
    "timezone": "Europe/Amsterdam"
  },
  "geometry": {
    "type": "Point",
    "coordinates": [
      6.62222,
      52.40833
    ]
  }
}