{
  "type": "Feature",
  "properties": {
    "name": "Cacaopera",
    "country": "SV",
    "subdivision": "08",
    "timezone": "America/El_Salvador"
  },
  "geometry": {
    "type": "Point",
    "coordinates": [
      -88.08333,
      13.76667
    ]
  }
}