{
  "type": "Feature",
  "properties": {
    "name": "Bou Hanifia el Hamamat",
    "country": "DZ",
    "subdivision": "26",
    "timezone": "Africa/Algiers"
  },
  "geometry": {
    "type": "Point",
    "coordinates": [
      -0.05037,
      35.31473
    ]
  }
}