{
  "type": "Feature",
  "properties": {
    "name": "Anao",
    "country": "PH",
    "subdivision": "03",
    "timezone": "Asia/Manila"
  },
  "geometry": {
    "type": "Point",
    "coordinates": [
      120.69136,
      15.1415
    ]
  }
}