{
  "type": "Feature",
  "properties": {
    "name": "Angeles City",
    "country": "PH",
    "subdivision": "03",
    "timezone": "Asia/Manila"
  },
  "geometry": {
    "type": "Point",
    "coordinates": [
      120.58333,
      15.15
    ]
  }
}