{
  "type": "Feature",
  "properties": {
    "name": "Balagtas",
    "country": "PH",
    "subdivision": "03",
    "timezone": "Asia/Manila"
  },
  "geometry": {
    "type": "Point",
    "coordinates": [
      120.86667,
      14.81667
    ]
  }
}