{
  "type": "Feature",
  "properties": {
    "name": "Balut",
    "country": "PH",
    "subdivision": "03",
    "timezone": "Asia/Manila"
  },
  "geometry": {
    "type": "Point",
    "coordinates": [
      120.55,
      14.68333
    ]
  }
}