{
  "type": "Feature",
  "properties": {
    "name": "Biga",
    "country": "PH",
    "subdivision": "03",
    "timezone": "Asia/Manila"
  },
  "geometry": {
    "type": "Point",
    "coordinates": [
      121.161,
      13.3106
    ]
  }
}