{
  "type": "Feature",
  "properties": {
    "name": "Buenlag",
    "country": "PH",
    "subdivision": "03",
    "timezone": "Asia/Manila"
  },
  "geometry": {
    "type": "Point",
    "coordinates": [
      120.58199,
      15.62743
    ]
  }
}