{
  "type": "Feature",
  "properties": {
    "name": "Bulualto",
    "country": "PH",
    "subdivision": "03",
    "timezone": "Asia/Manila"
  },
  "geometry": {
    "type": "Point",
    "coordinates": [
      120.95326,
      15.22127
    ]
  }
}