{
  "type": "Feature",
  "properties": {
    "name": "Cabog",
    "country": "PH",
    "subdivision": "03",
    "timezone": "Asia/Manila"
  },
  "geometry": {
    "type": "Point",
    "coordinates": [
      121.3703,
      15.3153
    ]
  }
}