{
  "type": "Feature",
  "properties": {
    "name": "Cafe",
    "country": "PH",
    "subdivision": "03",
    "timezone": "Asia/Manila"
  },
  "geometry": {
    "type": "Point",
    "coordinates": [
      120.70623,
      15.33686
    ]
  }
}