{
  "type": "Feature",
  "properties": {
    "name": "Calantas",
    "country": "PH",
    "subdivision": "03",
    "timezone": "Asia/Manila"
  },
  "geometry": {
    "type": "Point",
    "coordinates": [
      120.51793,
      15.01933
    ]
  }
}