{
  "type": "Feature",
  "properties": {
    "name": "Calibutbut",
    "country": "PH",
    "subdivision": "03",
    "timezone": "Asia/Manila"
  },
  "geometry": {
    "type": "Point",
    "coordinates": [
      120.59815,
      15.11494
    ]
  }
}