{
  "type": "Feature",
  "properties": {
    "name": "Cama Juan",
    "country": "PH",
    "subdivision": "03",
    "timezone": "Asia/Manila"
  },
  "geometry": {
    "type": "Point",
    "coordinates": [
      120.76848,
      15.39223
    ]
  }
}