{
  "type": "Feature",
  "properties": {
    "name": "Comillas",
    "country": "PH",
    "subdivision": "03",
    "timezone": "Asia/Manila"
  },
  "geometry": {
    "type": "Point",
    "coordinates": [
      120.70045,
      15.39833
    ]
  }
}