{
  "type": "Feature",
  "properties": {
    "name": "Conversion",
    "country": "PH",
    "subdivision": "03",
    "timezone": "Asia/Manila"
  },
  "geometry": {
    "type": "Point",
    "coordinates": [
      121.1277,
      15.8984
    ]
  }
}