{
  "type": "Feature",
  "properties": {
    "name": "Del Carmen",
    "country": "PH",
    "subdivision": "03",
    "timezone": "Asia/Manila"
  },
  "geometry": {
    "type": "Point",
    "coordinates": [
      120.53412,
      15.00544
    ]
  }
}