{
  "type": "Feature",
  "properties": {
    "name": "Estipona",
    "country": "PH",
    "subdivision": "03",
    "timezone": "Asia/Manila"
  },
  "geometry": {
    "type": "Point",
    "coordinates": [
      120.6377,
      15.5902
    ]
  }
}