{
  "type": "Feature",
  "properties": {
    "name": "Gapan",
    "country": "PH",
    "subdivision": "03",
    "timezone": "Asia/Manila"
  },
  "geometry": {
    "type": "Point",
    "coordinates": [
      120.9464,
      15.3072
    ]
  }
}