{
  "type": "Feature",
  "properties": {
    "name": "Lipay",
    "country": "PH",
    "subdivision": "03",
    "timezone": "Asia/Manila"
  },
  "geometry": {
    "type": "Point",
    "coordinates": [
      119.9208,
      15.4561
    ]
  }
}