{
  "type": "Feature",
  "properties": {
    "name": "Llanera",
    "country": "PH",
    "subdivision": "03",
    "timezone": "Asia/Manila"
  },
  "geometry": {
    "type": "Point",
    "coordinates": [
      121.0182,
      15.6635
    ]
  }
}