{
  "type": "Feature",
  "properties": {
    "name": "Mabayo",
    "country": "PH",
    "subdivision": "03",
    "timezone": "Asia/Manila"
  },
  "geometry": {
    "type": "Point",
    "coordinates": [
      120.2781,
      14.7318
    ]
  }
}