{
  "type": "Feature",
  "properties": {
    "name": "Magalang",
    "country": "PH",
    "subdivision": "03",
    "timezone": "Asia/Manila"
  },
  "geometry": {
    "type": "Point",
    "coordinates": [
      120.6596,
      15.2151
    ]
  }
}