{
  "type": "Feature",
  "properties": {
    "name": "Maloma",
    "country": "PH",
    "subdivision": "03",
    "timezone": "Asia/Manila"
  },
  "geometry": {
    "type": "Point",
    "coordinates": [
      120.0639,
      15.1135
    ]
  }
}