{
  "type": "Feature",
  "properties": {
    "name": "Malusac",
    "country": "PH",
    "subdivision": "03",
    "timezone": "Asia/Manila"
  },
  "geometry": {
    "type": "Point",
    "coordinates": [
      120.6212,
      14.85842
    ]
  }
}