{
  "type": "Feature",
  "properties": {
    "name": "Mandili",
    "country": "PH",
    "subdivision": "03",
    "timezone": "Asia/Manila"
  },
  "geometry": {
    "type": "Point",
    "coordinates": [
      120.87726,
      15.17912
    ]
  }
}