{
  "type": "Feature",
  "properties": {
    "name": "Mangga",
    "country": "PH",
    "subdivision": "03",
    "timezone": "Asia/Manila"
  },
  "geometry": {
    "type": "Point",
    "coordinates": [
      120.90876,
      15.25041
    ]
  }
}