{
  "type": "Feature",
  "properties": {
    "name": "Mapaniqui",
    "country": "PH",
    "subdivision": "03",
    "timezone": "Asia/Manila"
  },
  "geometry": {
    "type": "Point",
    "coordinates": [
      120.92287,
      15.10696
    ]
  }
}