{
  "type": "Feature",
  "properties": {
    "name": "Mapalacsiao",
    "country": "PH",
    "subdivision": "03",
    "timezone": "Asia/Manila"
  },
  "geometry": {
    "type": "Point",
    "coordinates": [
      120.65252,
      15.42831
    ]
  }
}