{
  "type": "Feature",
  "properties": {
    "name": "Maria Aurora",
    "country": "PH",
    "subdivision": "03",
    "timezone": "Asia/Manila"
  },
  "geometry": {
    "type": "Point",
    "coordinates": [
      121.4737,
      15.7967
    ]
  }
}