{
  "type": "Feature",
  "properties": {
    "name": "Nieves",
    "country": "PH",
    "subdivision": "03",
    "timezone": "Asia/Manila"
  },
  "geometry": {
    "type": "Point",
    "coordinates": [
      120.94892,
      15.32842
    ]
  }
}