{
  "type": "Feature",
  "properties": {
    "name": "Obando",
    "country": "PH",
    "subdivision": "03",
    "timezone": "Asia/Manila"
  },
  "geometry": {
    "type": "Point",
    "coordinates": [
      120.9362,
      14.7098
    ]
  }
}