{
  "type": "Feature",
  "properties": {
    "name": "Pio",
    "country": "PH",
    "subdivision": "03",
    "timezone": "Asia/Manila"
  },
  "geometry": {
    "type": "Point",
    "coordinates": [
      120.51891,
      15.04741
    ]
  }
}