{
  "type": "Feature",
  "properties": {
    "name": "Poblacion, San Felipe",
    "country": "PH",
    "subdivision": "03",
    "timezone": "Asia/Manila"
  },
  "geometry": {
    "type": "Point",
    "coordinates": [
      120.07,
      15.06222
    ]
  }
}