{
  "type": "Feature",
  "properties": {
    "name": "Pulong Gubat",
    "country": "PH",
    "subdivision": "03",
    "timezone": "Asia/Manila"
  },
  "geometry": {
    "type": "Point",
    "coordinates": [
      120.90599,
      14.85938
    ]
  }
}