{
  "type": "Feature",
  "properties": {
    "name": "San Benito",
    "country": "PH",
    "subdivision": "03",
    "timezone": "Asia/Manila"
  },
  "geometry": {
    "type": "Point",
    "coordinates": [
      120.42693,
      14.85155
    ]
  }
}