{
  "type": "Feature",
  "properties": {
    "name": "San Roque",
    "country": "PH",
    "subdivision": "03",
    "timezone": "Asia/Manila"
  },
  "geometry": {
    "type": "Point",
    "coordinates": [
      120.65183,
      15.26146
    ]
  }
}