{
  "type": "Feature",
  "properties": {
    "name": "San Roque Dau First",
    "country": "PH",
    "subdivision": "03",
    "timezone": "Asia/Manila"
  },
  "geometry": {
    "type": "Point",
    "coordinates": [
      120.57688,
      14.97711
    ]
  }
}