{
  "type": "Feature",
  "properties": {
    "name": "San Andres",
    "country": "PH",
    "subdivision": "03",
    "timezone": "Asia/Manila"
  },
  "geometry": {
    "type": "Point",
    "coordinates": [
      120.77752,
      15.71928
    ]
  }
}