{
  "type": "Feature",
  "properties": {
    "name": "San Narciso",
    "country": "PH",
    "subdivision": "03",
    "timezone": "Asia/Manila"
  },
  "geometry": {
    "type": "Point",
    "coordinates": [
      120.0803,
      15.0143
    ]
  }
}