{
  "type": "Feature",
  "properties": {
    "name": "San Ildefonso",
    "country": "PH",
    "subdivision": "03",
    "timezone": "Asia/Manila"
  },
  "geometry": {
    "type": "Point",
    "coordinates": [
      120.941,
      15.0809
    ]
  }
}