{
  "type": "Feature",
  "properties": {
    "name": "Santa Juliana",
    "country": "PH",
    "subdivision": "03",
    "timezone": "Asia/Manila"
  },
  "geometry": {
    "type": "Point",
    "coordinates": [
      120.42863,
      15.32826
    ]
  }
}