{
  "type": "Feature",
  "properties": {
    "name": "Santa Monica",
    "country": "PH",
    "subdivision": "03",
    "timezone": "Asia/Manila"
  },
  "geometry": {
    "type": "Point",
    "coordinates": [
      120.72006,
      15.35771
    ]
  }
}