{
  "type": "Feature",
  "properties": {
    "name": "Santa Lucia",
    "country": "PH",
    "subdivision": "03",
    "timezone": "Asia/Manila"
  },
  "geometry": {
    "type": "Point",
    "coordinates": [
      120.77456,
      15.48184
    ]
  }
}