{
  "type": "Feature",
  "properties": {
    "name": "Santa Rita",
    "country": "PH",
    "subdivision": "03",
    "timezone": "Asia/Manila"
  },
  "geometry": {
    "type": "Point",
    "coordinates": [
      120.86962,
      15.61923
    ]
  }
}