{
  "type": "Feature",
  "properties": {
    "name": "Sexmoan",
    "country": "PH",
    "subdivision": "03",
    "timezone": "Asia/Manila"
  },
  "geometry": {
    "type": "Point",
    "coordinates": [
      120.6229,
      14.9438
    ]
  }
}