{
  "type": "Feature",
  "properties": {
    "name": "Sulucan",
    "country": "PH",
    "subdivision": "03",
    "timezone": "Asia/Manila"
  },
  "geometry": {
    "type": "Point",
    "coordinates": [
      120.92594,
      14.79448
    ]
  }
}