{
  "type": "Feature",
  "properties": {
    "name": "Tabacao",
    "country": "PH",
    "subdivision": "03",
    "timezone": "Asia/Manila"
  },
  "geometry": {
    "type": "Point",
    "coordinates": [
      120.94066,
      15.64973
    ]
  }
}