{
  "type": "Feature",
  "properties": {
    "name": "Talaga",
    "country": "PH",
    "subdivision": "03",
    "timezone": "Asia/Manila"
  },
  "geometry": {
    "type": "Point",
    "coordinates": [
      120.58933,
      15.38403
    ]
  }
}