{
  "type": "Feature",
  "properties": {
    "name": "Talugtug",
    "country": "PH",
    "subdivision": "03",
    "timezone": "Asia/Manila"
  },
  "geometry": {
    "type": "Point",
    "coordinates": [
      120.8111,
      15.7778
    ]
  }
}