{
  "type": "Feature",
  "properties": {
    "name": "Umiray",
    "country": "PH",
    "subdivision": "03",
    "timezone": "Asia/Manila"
  },
  "geometry": {
    "type": "Point",
    "coordinates": [
      121.4111,
      15.2206
    ]
  }
}