{
  "type": "Feature",
  "properties": {
    "name": "Chiconi",
    "country": "YT",
    "subdivision": "97605",
    "timezone": "Indian/Mayotte"
  },
  "geometry": {
    "type": "Point",
    "coordinates": [
      45.11056,
      -12.83333
    ]
  }
}