{
  "type": "Feature",
  "properties": {
    "name": "Moyale",
    "country": "KE",
    "subdivision": "34",
    "timezone": "Africa/Nairobi"
  },
  "geometry": {
    "type": "Point",
    "coordinates": [
      39.0561,
      3.52661
    ]
  }
}