{
  "type": "Feature",
  "properties": {
    "name": "Aguas Corrientes",
    "country": "UY",
    "subdivision": "02",
    "timezone": "America/Montevideo"
  },
  "geometry": {
    "type": "Point",
    "coordinates": [
      -56.39361,
      -34.52194
    ]
  }
}