{
  "type": "Feature",
  "properties": {
    "name": "Canelones",
    "country": "UY",
    "subdivision": "02",
    "timezone": "America/Montevideo"
  },
  "geometry": {
    "type": "Point",
    "coordinates": [
      -56.27778,
      -34.52278
    ]
  }
}