{
  "type": "Feature",
  "properties": {
    "name": "Empalme Olmos",
    "country": "UY",
    "subdivision": "02",
    "timezone": "America/Montevideo"
  },
  "geometry": {
    "type": "Point",
    "coordinates": [
      -55.89268,
      -34.69753
    ]
  }
}