{
  "type": "Feature",
  "properties": {
    "name": "Juanicó",
    "country": "UY",
    "subdivision": "02",
    "timezone": "America/Montevideo"
  },
  "geometry": {
    "type": "Point",
    "coordinates": [
      -56.25334,
      -34.59454
    ]
  }
}