{
  "type": "Feature",
  "properties": {
    "name": "La Floresta",
    "country": "UY",
    "subdivision": "02",
    "timezone": "America/Montevideo"
  },
  "geometry": {
    "type": "Point",
    "coordinates": [
      -55.68141,
      -34.75572
    ]
  }
}