{
  "type": "Feature",
  "properties": {
    "name": "Acolman de Netzahualcóyotl",
    "country": "MX",
    "subdivision": "15",
    "timezone": "America/Mexico_City"
  },
  "geometry": {
    "type": "Point",
    "coordinates": [
      -98.90777,
      19.63976
    ]
  }
}