{
  "type": "Feature",
  "properties": {
    "name": "Atlacomulco de Fabela",
    "country": "MX",
    "subdivision": "15",
    "timezone": "America/Mexico_City"
  },
  "geometry": {
    "type": "Point",
    "coordinates": [
      -99.875,
      19.79919
    ]
  }
}