{
  "type": "Feature",
  "properties": {
    "name": "Barrio de Canales",
    "country": "MX",
    "subdivision": "15",
    "timezone": "America/Mexico_City"
  },
  "geometry": {
    "type": "Point",
    "coordinates": [
      -99.37556,
      19.37333
    ]
  }
}