{
  "type": "Feature",
  "properties": {
    "name": "Barrio de San Ramón",
    "country": "MX",
    "subdivision": "15",
    "timezone": "America/Mexico_City"
  },
  "geometry": {
    "type": "Point",
    "coordinates": [
      -99.33111,
      19.37361
    ]
  }
}