{
  "type": "Feature",
  "properties": {
    "name": "Barrio de España",
    "country": "MX",
    "subdivision": "15",
    "timezone": "America/Mexico_City"
  },
  "geometry": {
    "type": "Point",
    "coordinates": [
      -99.08167,
      19.86139
    ]
  }
}