{
  "type": "Feature",
  "properties": {
    "name": "Barrio la Joya",
    "country": "MX",
    "subdivision": "15",
    "timezone": "America/Mexico_City"
  },
  "geometry": {
    "type": "Point",
    "coordinates": [
      -100.09972,
      19.42
    ]
  }
}