{
  "type": "Feature",
  "properties": {
    "name": "Belem",
    "country": "MX",
    "subdivision": "15",
    "timezone": "America/Mexico_City"
  },
  "geometry": {
    "type": "Point",
    "coordinates": [
      -98.79664,
      19.63334
    ]
  }
}