{
  "type": "Feature",
  "properties": {
    "name": "Calixtlahuaca",
    "country": "MX",
    "subdivision": "15",
    "timezone": "America/Mexico_City"
  },
  "geometry": {
    "type": "Point",
    "coordinates": [
      -99.68923,
      19.33651
    ]
  }
}