{
  "type": "Feature",
  "properties": {
    "name": "Cañada de Guadarrama",
    "country": "MX",
    "subdivision": "15",
    "timezone": "America/Mexico_City"
  },
  "geometry": {
    "type": "Point",
    "coordinates": [
      -99.78972,
      19.31272
    ]
  }
}