{
  "type": "Feature",
  "properties": {
    "name": "Carapán",
    "country": "MX",
    "subdivision": "15",
    "timezone": "America/Mexico_City"
  },
  "geometry": {
    "type": "Point",
    "coordinates": [
      -102.03644,
      19.86003
    ]
  }
}