{
  "type": "Feature",
  "properties": {
    "name": "Casas Viejas",
    "country": "MX",
    "subdivision": "15",
    "timezone": "America/Mexico_City"
  },
  "geometry": {
    "type": "Point",
    "coordinates": [
      -100.10778,
      19.15167
    ]
  }
}