{
  "type": "Feature",
  "properties": {
    "name": "Cedro de la Manzana",
    "country": "MX",
    "subdivision": "15",
    "timezone": "America/Mexico_City"
  },
  "geometry": {
    "type": "Point",
    "coordinates": [
      -100.11656,
      19.69213
    ]
  }
}