{
  "type": "Feature",
  "properties": {
    "name": "Chalmita",
    "country": "MX",
    "subdivision": "15",
    "timezone": "America/Mexico_City"
  },
  "geometry": {
    "type": "Point",
    "coordinates": [
      -99.42325,
      18.93433
    ]
  }
}