{
  "type": "Feature",
  "properties": {
    "name": "Chaparaco",
    "country": "MX",
    "subdivision": "15",
    "timezone": "America/Mexico_City"
  },
  "geometry": {
    "type": "Point",
    "coordinates": [
      -102.26092,
      19.96061
    ]
  }
}