{
  "type": "Feature",
  "properties": {
    "name": "Chiconcuac",
    "country": "MX",
    "subdivision": "15",
    "timezone": "America/Mexico_City"
  },
  "geometry": {
    "type": "Point",
    "coordinates": [
      -98.89884,
      19.55939
    ]
  }
}