{
  "type": "Feature",
  "properties": {
    "name": "Chosto de los Jarros",
    "country": "MX",
    "subdivision": "15",
    "timezone": "America/Mexico_City"
  },
  "geometry": {
    "type": "Point",
    "coordinates": [
      -99.91,
      19.86333
    ]
  }
}