{
  "type": "Feature",
  "properties": {
    "name": "Ciudad Nezahualcoyotl",
    "country": "MX",
    "subdivision": "15",
    "timezone": "America/Mexico_City"
  },
  "geometry": {
    "type": "Point",
    "coordinates": [
      -99.01483,
      19.40061
    ]
  }
}