{
  "type": "Feature",
  "properties": {
    "name": "Coamilpa de Juárez",
    "country": "MX",
    "subdivision": "15",
    "timezone": "America/Mexico_City"
  },
  "geometry": {
    "type": "Point",
    "coordinates": [
      -99.44361,
      19.19778
    ]
  }
}