{
  "type": "Feature",
  "properties": {
    "name": "Colonia el Salado",
    "country": "MX",
    "subdivision": "15",
    "timezone": "America/Mexico_City"
  },
  "geometry": {
    "type": "Point",
    "coordinates": [
      -98.99139,
      19.58389
    ]
  }
}