{
  "type": "Feature",
  "properties": {
    "name": "Colonia Arboledas (San Andrés)",
    "country": "MX",
    "subdivision": "15",
    "timezone": "America/Mexico_City"
  },
  "geometry": {
    "type": "Point",
    "coordinates": [
      -99.58083,
      19.2025
    ]
  }
}