{
  "type": "Feature",
  "properties": {
    "name": "Colonia Río Lerma (Tic Ti)",
    "country": "MX",
    "subdivision": "15",
    "timezone": "America/Mexico_City"
  },
  "geometry": {
    "type": "Point",
    "coordinates": [
      -99.89722,
      19.80556
    ]
  }
}