{
  "type": "Feature",
  "properties": {
    "name": "Colonia Juárez",
    "country": "MX",
    "subdivision": "15",
    "timezone": "America/Mexico_City"
  },
  "geometry": {
    "type": "Point",
    "coordinates": [
      -99.46652,
      19.2855
    ]
  }
}