{
  "type": "Feature",
  "properties": {
    "name": "Colonia Lázaro Cárdenas",
    "country": "MX",
    "subdivision": "15",
    "timezone": "America/Mexico_City"
  },
  "geometry": {
    "type": "Point",
    "coordinates": [
      -98.92,
      19.51306
    ]
  }
}