{
  "type": "Feature",
  "properties": {
    "name": "Colonia Lázaro Cárdenas (Los Hornos)",
    "country": "MX",
    "subdivision": "15",
    "timezone": "America/Mexico_City"
  },
  "geometry": {
    "type": "Point",
    "coordinates": [
      -99.15333,
      19.63167
    ]
  }
}