{
  "type": "Feature",
  "properties": {
    "name": "Colonia Doctor Gustavo Baz",
    "country": "MX",
    "subdivision": "15",
    "timezone": "America/Mexico_City"
  },
  "geometry": {
    "type": "Point",
    "coordinates": [
      -99.92167,
      19.41056
    ]
  }
}