{
  "type": "Feature",
  "properties": {
    "name": "Concepción del Monte",
    "country": "MX",
    "subdivision": "15",
    "timezone": "America/Mexico_City"
  },
  "geometry": {
    "type": "Point",
    "coordinates": [
      -100.1544,
      19.65128
    ]
  }
}