{
  "type": "Feature",
  "properties": {
    "name": "Ejido San Cristóbal",
    "country": "MX",
    "subdivision": "15",
    "timezone": "America/Mexico_City"
  },
  "geometry": {
    "type": "Point",
    "coordinates": [
      -98.89417,
      19.5425
    ]
  }
}