{
  "type": "Feature",
  "properties": {
    "name": "Ejido Palma (Ejido San Francisco)",
    "country": "MX",
    "subdivision": "15",
    "timezone": "America/Mexico_City"
  },
  "geometry": {
    "type": "Point",
    "coordinates": [
      -99.40889,
      19.56889
    ]
  }
}