{
  "type": "Feature",
  "properties": {
    "name": "Ejido de San Mateo Coapexco",
    "country": "MX",
    "subdivision": "15",
    "timezone": "America/Mexico_City"
  },
  "geometry": {
    "type": "Point",
    "coordinates": [
      -99.64249,
      18.94889
    ]
  }
}