{
  "type": "Feature",
  "properties": {
    "name": "El Colorado",
    "country": "MX",
    "subdivision": "15",
    "timezone": "America/Mexico_City"
  },
  "geometry": {
    "type": "Point",
    "coordinates": [
      -99.76278,
      20.09639
    ]
  }
}