{
  "type": "Feature",
  "properties": {
    "name": "El Hielo",
    "country": "MX",
    "subdivision": "15",
    "timezone": "America/Mexico_City"
  },
  "geometry": {
    "type": "Point",
    "coordinates": [
      -99.35556,
      19.42583
    ]
  }
}