{
  "type": "Feature",
  "properties": {
    "name": "El Llano del Compromiso",
    "country": "MX",
    "subdivision": "15",
    "timezone": "America/Mexico_City"
  },
  "geometry": {
    "type": "Point",
    "coordinates": [
      -99.47917,
      19.25472
    ]
  }
}