{
  "type": "Feature",
  "properties": {
    "name": "El Ocotal",
    "country": "MX",
    "subdivision": "15",
    "timezone": "America/Mexico_City"
  },
  "geometry": {
    "type": "Point",
    "coordinates": [
      -99.47008,
      19.67983
    ]
  }
}