{
  "type": "Feature",
  "properties": {
    "name": "El Porvenir I",
    "country": "MX",
    "subdivision": "15",
    "timezone": "America/Mexico_City"
  },
  "geometry": {
    "type": "Point",
    "coordinates": [
      -99.72889,
      19.31694
    ]
  }
}