{
  "type": "Feature",
  "properties": {
    "name": "El Rincón de los Perales",
    "country": "MX",
    "subdivision": "15",
    "timezone": "America/Mexico_City"
  },
  "geometry": {
    "type": "Point",
    "coordinates": [
      -99.82806,
      19.54222
    ]
  }
}