{
  "type": "Feature",
  "properties": {
    "name": "El Recodo de San José Axalco",
    "country": "MX",
    "subdivision": "15",
    "timezone": "America/Mexico_City"
  },
  "geometry": {
    "type": "Point",
    "coordinates": [
      -98.90278,
      19.20278
    ]
  }
}