{
  "type": "Feature",
  "properties": {
    "name": "Guadalupe Buenavista",
    "country": "MX",
    "subdivision": "15",
    "timezone": "America/Mexico_City"
  },
  "geometry": {
    "type": "Point",
    "coordinates": [
      -100.1272,
      19.61194
    ]
  }
}