{
  "type": "Feature",
  "properties": {
    "name": "Hueypoxtla",
    "country": "MX",
    "subdivision": "15",
    "timezone": "America/Mexico_City"
  },
  "geometry": {
    "type": "Point",
    "coordinates": [
      -99.07384,
      19.91301
    ]
  }
}