{
  "type": "Feature",
  "properties": {
    "name": "Huixquilucan de Degollado",
    "country": "MX",
    "subdivision": "15",
    "timezone": "America/Mexico_City"
  },
  "geometry": {
    "type": "Point",
    "coordinates": [
      -99.3498,
      19.36028
    ]
  }
}