{
  "type": "Feature",
  "properties": {
    "name": "Jalmolonga (La Hacienda)",
    "country": "MX",
    "subdivision": "15",
    "timezone": "America/Mexico_City"
  },
  "geometry": {
    "type": "Point",
    "coordinates": [
      -99.49407,
      18.91835
    ]
  }
}