{
  "type": "Feature",
  "properties": {
    "name": "Jilotepec de Molina Enríquez",
    "country": "MX",
    "subdivision": "15",
    "timezone": "America/Mexico_City"
  },
  "geometry": {
    "type": "Point",
    "coordinates": [
      -99.53278,
      19.95194
    ]
  }
}