{
  "type": "Feature",
  "properties": {
    "name": "La Colonia",
    "country": "MX",
    "subdivision": "15",
    "timezone": "America/Mexico_City"
  },
  "geometry": {
    "type": "Point",
    "coordinates": [
      -98.78667,
      19.14444
    ]
  }
}