{
  "type": "Feature",
  "properties": {
    "name": "La Providencia",
    "country": "MX",
    "subdivision": "15",
    "timezone": "America/Mexico_City"
  },
  "geometry": {
    "type": "Point",
    "coordinates": [
      -99.14667,
      19.75833
    ]
  }
}