{
  "type": "Feature",
  "properties": {
    "name": "La Pastoría",
    "country": "MX",
    "subdivision": "15",
    "timezone": "America/Mexico_City"
  },
  "geometry": {
    "type": "Point",
    "coordinates": [
      -98.91111,
      19.54306
    ]
  }
}