{
  "type": "Feature",
  "properties": {
    "name": "Llano de Zacapexco",
    "country": "MX",
    "subdivision": "15",
    "timezone": "America/Mexico_City"
  },
  "geometry": {
    "type": "Point",
    "coordinates": [
      -99.48507,
      19.70405
    ]
  }
}