{
  "type": "Feature",
  "properties": {
    "name": "Loma del Río",
    "country": "MX",
    "subdivision": "15",
    "timezone": "America/Mexico_City"
  },
  "geometry": {
    "type": "Point",
    "coordinates": [
      -99.35056,
      19.60056
    ]
  }
}