{
  "type": "Feature",
  "properties": {
    "name": "Loma Larga (Barrio de Loma Larga)",
    "country": "MX",
    "subdivision": "15",
    "timezone": "America/Mexico_City"
  },
  "geometry": {
    "type": "Point",
    "coordinates": [
      -99.11611,
      19.86722
    ]
  }
}