{
  "type": "Feature",
  "properties": {
    "name": "Loma Alta",
    "country": "MX",
    "subdivision": "15",
    "timezone": "America/Mexico_City"
  },
  "geometry": {
    "type": "Point",
    "coordinates": [
      -99.44917,
      19.68944
    ]
  }
}