{
  "type": "Feature",
  "properties": {
    "name": "Los Saucos",
    "country": "MX",
    "subdivision": "15",
    "timezone": "America/Mexico_City"
  },
  "geometry": {
    "type": "Point",
    "coordinates": [
      -99.99895,
      19.1652
    ]
  }
}