{
  "type": "Feature",
  "properties": {
    "name": "Los Remedios",
    "country": "MX",
    "subdivision": "15",
    "timezone": "America/Mexico_City"
  },
  "geometry": {
    "type": "Point",
    "coordinates": [
      -102.67954,
      19.9781
    ]
  }
}