{
  "type": "Feature",
  "properties": {
    "name": "Miraflores",
    "country": "MX",
    "subdivision": "15",
    "timezone": "America/Mexico_City"
  },
  "geometry": {
    "type": "Point",
    "coordinates": [
      -98.80741,
      19.2221
    ]
  }
}