{
  "type": "Feature",
  "properties": {
    "name": "Molino Abajo",
    "country": "MX",
    "subdivision": "15",
    "timezone": "America/Mexico_City"
  },
  "geometry": {
    "type": "Point",
    "coordinates": [
      -99.60222,
      19.44972
    ]
  }
}