{
  "type": "Feature",
  "properties": {
    "name": "Oxtotipac",
    "country": "MX",
    "subdivision": "15",
    "timezone": "America/Mexico_City"
  },
  "geometry": {
    "type": "Point",
    "coordinates": [
      -98.79319,
      19.65521
    ]
  }
}