{
  "type": "Feature",
  "properties": {
    "name": "Ozumba de Alzate",
    "country": "MX",
    "subdivision": "15",
    "timezone": "America/Mexico_City"
  },
  "geometry": {
    "type": "Point",
    "coordinates": [
      -98.79516,
      19.03689
    ]
  }
}