{
  "type": "Feature",
  "properties": {
    "name": "Palmar Chico",
    "country": "MX",
    "subdivision": "15",
    "timezone": "America/Mexico_City"
  },
  "geometry": {
    "type": "Point",
    "coordinates": [
      -100.36852,
      18.69593
    ]
  }
}