{
  "type": "Feature",
  "properties": {
    "name": "Pathé",
    "country": "MX",
    "subdivision": "15",
    "timezone": "America/Mexico_City"
  },
  "geometry": {
    "type": "Point",
    "coordinates": [
      -99.83957,
      19.92695
    ]
  }
}