{
  "type": "Feature",
  "properties": {
    "name": "Polígonos",
    "country": "MX",
    "subdivision": "15",
    "timezone": "America/Mexico_City"
  },
  "geometry": {
    "type": "Point",
    "coordinates": [
      -98.99091,
      19.41612
    ]
  }
}