{
  "type": "Feature",
  "properties": {
    "name": "Puentecillas",
    "country": "MX",
    "subdivision": "15",
    "timezone": "America/Mexico_City"
  },
  "geometry": {
    "type": "Point",
    "coordinates": [
      -99.97806,
      20.02568
    ]
  }
}