{
  "type": "Feature",
  "properties": {
    "name": "Purísima Concepción Mayorazgo",
    "country": "MX",
    "subdivision": "15",
    "timezone": "America/Mexico_City"
  },
  "geometry": {
    "type": "Point",
    "coordinates": [
      -100.00211,
      19.69159
    ]
  }
}