{
  "type": "Feature",
  "properties": {
    "name": "Rincón Verde",
    "country": "MX",
    "subdivision": "15",
    "timezone": "America/Mexico_City"
  },
  "geometry": {
    "type": "Point",
    "coordinates": [
      -99.29083,
      19.49639
    ]
  }
}