{
  "type": "Feature",
  "properties": {
    "name": "San Pedro del Rosal",
    "country": "MX",
    "subdivision": "15",
    "timezone": "America/Mexico_City"
  },
  "geometry": {
    "type": "Point",
    "coordinates": [
      -99.8125,
      19.77806
    ]
  }
}