{
  "type": "Feature",
  "properties": {
    "name": "San Juan Totolapan",
    "country": "MX",
    "subdivision": "15",
    "timezone": "America/Mexico_City"
  },
  "geometry": {
    "type": "Point",
    "coordinates": [
      -98.72691,
      19.53093
    ]
  }
}