{
  "type": "Feature",
  "properties": {
    "name": "San Francisco Putla",
    "country": "MX",
    "subdivision": "15",
    "timezone": "America/Mexico_City"
  },
  "geometry": {
    "type": "Point",
    "coordinates": [
      -99.63556,
      19.12778
    ]
  }
}