{
  "type": "Feature",
  "properties": {
    "name": "San Bartolo el Viejo",
    "country": "MX",
    "subdivision": "15",
    "timezone": "America/Mexico_City"
  },
  "geometry": {
    "type": "Point",
    "coordinates": [
      -99.82389,
      19.29889
    ]
  }
}