{
  "type": "Feature",
  "properties": {
    "name": "San José las Lomas",
    "country": "MX",
    "subdivision": "15",
    "timezone": "America/Mexico_City"
  },
  "geometry": {
    "type": "Point",
    "coordinates": [
      -99.67052,
      19.47936
    ]
  }
}