{
  "type": "Feature",
  "properties": {
    "name": "San Pedro Nexapa",
    "country": "MX",
    "subdivision": "15",
    "timezone": "America/Mexico_City"
  },
  "geometry": {
    "type": "Point",
    "coordinates": [
      -98.73724,
      19.08365
    ]
  }
}