{
  "type": "Feature",
  "properties": {
    "name": "San José Tejamanil",
    "country": "MX",
    "subdivision": "15",
    "timezone": "America/Mexico_City"
  },
  "geometry": {
    "type": "Point",
    "coordinates": [
      -99.35889,
      19.43139
    ]
  }
}