{
  "type": "Feature",
  "properties": {
    "name": "San Mateo Texcalyacac",
    "country": "MX",
    "subdivision": "15",
    "timezone": "America/Mexico_City"
  },
  "geometry": {
    "type": "Point",
    "coordinates": [
      -99.46667,
      19.16667
    ]
  }
}