{
  "type": "Feature",
  "properties": {
    "name": "San Lucas Totolmaloya",
    "country": "MX",
    "subdivision": "15",
    "timezone": "America/Mexico_City"
  },
  "geometry": {
    "type": "Point",
    "coordinates": [
      -99.89722,
      20.16333
    ]
  }
}