{
  "type": "Feature",
  "properties": {
    "name": "San Antonio Enchisi",
    "country": "MX",
    "subdivision": "15",
    "timezone": "America/Mexico_City"
  },
  "geometry": {
    "type": "Point",
    "coordinates": [
      -99.81667,
      19.75472
    ]
  }
}