{
  "type": "Feature",
  "properties": {
    "name": "San Miguel Ixtapan",
    "country": "MX",
    "subdivision": "15",
    "timezone": "America/Mexico_City"
  },
  "geometry": {
    "type": "Point",
    "coordinates": [
      -100.15245,
      18.80728
    ]
  }
}