{
  "type": "Feature",
  "properties": {
    "name": "San Francisco Chalchihuapan",
    "country": "MX",
    "subdivision": "15",
    "timezone": "America/Mexico_City"
  },
  "geometry": {
    "type": "Point",
    "coordinates": [
      -99.82167,
      19.77
    ]
  }
}