{
  "type": "Feature",
  "properties": {
    "name": "San Pablo Tejalpa",
    "country": "MX",
    "subdivision": "15",
    "timezone": "America/Mexico_City"
  },
  "geometry": {
    "type": "Point",
    "coordinates": [
      -99.59111,
      18.86667
    ]
  }
}