{
  "type": "Feature",
  "properties": {
    "name": "San Antonio Bonixi",
    "country": "MX",
    "subdivision": "15",
    "timezone": "America/Mexico_City"
  },
  "geometry": {
    "type": "Point",
    "coordinates": [
      -99.72686,
      19.49226
    ]
  }
}