{
  "type": "Feature",
  "properties": {
    "name": "San Miguel Agua Bendita",
    "country": "MX",
    "subdivision": "15",
    "timezone": "America/Mexico_City"
  },
  "geometry": {
    "type": "Point",
    "coordinates": [
      -100.07933,
      19.63037
    ]
  }
}