{
  "type": "Feature",
  "properties": {
    "name": "San Francisco Tlalcilalcalpan",
    "country": "MX",
    "subdivision": "15",
    "timezone": "America/Mexico_City"
  },
  "geometry": {
    "type": "Point",
    "coordinates": [
      -99.76771,
      19.29474
    ]
  }
}