{
  "type": "Feature",
  "properties": {
    "name": "San José Toxi",
    "country": "MX",
    "subdivision": "15",
    "timezone": "America/Mexico_City"
  },
  "geometry": {
    "type": "Point",
    "coordinates": [
      -99.93736,
      19.86803
    ]
  }
}