{
  "type": "Feature",
  "properties": {
    "name": "San Nicolás Tolentino",
    "country": "MX",
    "subdivision": "15",
    "timezone": "America/Mexico_City"
  },
  "geometry": {
    "type": "Point",
    "coordinates": [
      -100.24111,
      19.18472
    ]
  }
}