{
  "type": "Feature",
  "properties": {
    "name": "San Lucas Ocotepec",
    "country": "MX",
    "subdivision": "15",
    "timezone": "America/Mexico_City"
  },
  "geometry": {
    "type": "Point",
    "coordinates": [
      -99.97194,
      19.67833
    ]
  }
}