{
  "type": "Feature",
  "properties": {
    "name": "San Joaquín Coapango",
    "country": "MX",
    "subdivision": "15",
    "timezone": "America/Mexico_City"
  },
  "geometry": {
    "type": "Point",
    "coordinates": [
      -98.82739,
      19.54043
    ]
  }
}