{
  "type": "Feature",
  "properties": {
    "name": "San Francisco Xochicuautla",
    "country": "MX",
    "subdivision": "15",
    "timezone": "America/Mexico_City"
  },
  "geometry": {
    "type": "Point",
    "coordinates": [
      -99.4453,
      19.37291
    ]
  }
}