{
  "type": "Feature",
  "properties": {
    "name": "San Marcos Huixtoco",
    "country": "MX",
    "subdivision": "15",
    "timezone": "America/Mexico_City"
  },
  "geometry": {
    "type": "Point",
    "coordinates": [
      -98.86369,
      19.29668
    ]
  }
}