{
  "type": "Feature",
  "properties": {
    "name": "San Bernardino",
    "country": "MX",
    "subdivision": "15",
    "timezone": "America/Mexico_City"
  },
  "geometry": {
    "type": "Point",
    "coordinates": [
      -98.89635,
      19.47667
    ]
  }
}