{
  "type": "Feature",
  "properties": {
    "name": "San Lucas",
    "country": "MX",
    "subdivision": "15",
    "timezone": "America/Mexico_City"
  },
  "geometry": {
    "type": "Point",
    "coordinates": [
      -100.00723,
      19.25955
    ]
  }
}