{
  "type": "Feature",
  "properties": {
    "name": "San Roque",
    "country": "MX",
    "subdivision": "15",
    "timezone": "America/Mexico_City"
  },
  "geometry": {
    "type": "Point",
    "coordinates": [
      -99.96056,
      19.48028
    ]
  }
}