{
  "type": "Feature",
  "properties": {
    "name": "San Juan Tuxtepec",
    "country": "MX",
    "subdivision": "15",
    "timezone": "America/Mexico_City"
  },
  "geometry": {
    "type": "Point",
    "coordinates": [
      -99.63289,
      19.85865
    ]
  }
}