{
  "type": "Feature",
  "properties": {
    "name": "San Bartolo del Llano (San Isidro)",
    "country": "MX",
    "subdivision": "15",
    "timezone": "America/Mexico_City"
  },
  "geometry": {
    "type": "Point",
    "coordinates": [
      -99.8275,
      19.30528
    ]
  }
}