{
  "type": "Feature",
  "properties": {
    "name": "San Marcos Tlazalpan",
    "country": "MX",
    "subdivision": "15",
    "timezone": "America/Mexico_City"
  },
  "geometry": {
    "type": "Point",
    "coordinates": [
      -99.7175,
      19.80611
    ]
  }
}