{
  "type": "Feature",
  "properties": {
    "name": "San Gaspar Tonatico",
    "country": "MX",
    "subdivision": "15",
    "timezone": "America/Mexico_City"
  },
  "geometry": {
    "type": "Point",
    "coordinates": [
      -99.66917,
      18.80671
    ]
  }
}