{
  "type": "Feature",
  "properties": {
    "name": "San Juan Coxtocan",
    "country": "MX",
    "subdivision": "15",
    "timezone": "America/Mexico_City"
  },
  "geometry": {
    "type": "Point",
    "coordinates": [
      -98.84728,
      19.13932
    ]
  }
}