{
  "type": "Feature",
  "properties": {
    "name": "Sanata Lucía",
    "country": "MX",
    "subdivision": "15",
    "timezone": "America/Mexico_City"
  },
  "geometry": {
    "type": "Point",
    "coordinates": [
      -98.98069,
      19.74807
    ]
  }
}