{
  "type": "Feature",
  "properties": {
    "name": "Santa Isabel Ixtapan",
    "country": "MX",
    "subdivision": "15",
    "timezone": "America/Mexico_City"
  },
  "geometry": {
    "type": "Point",
    "coordinates": [
      -98.94667,
      19.58655
    ]
  }
}