{
  "type": "Feature",
  "properties": {
    "name": "Santa Ana Ixtlahuatzingo (Santa Ana)",
    "country": "MX",
    "subdivision": "15",
    "timezone": "America/Mexico_City"
  },
  "geometry": {
    "type": "Point",
    "coordinates": [
      -99.62361,
      18.97056
    ]
  }
}