{
  "type": "Feature",
  "properties": {
    "name": "Santa Clara de Juárez",
    "country": "MX",
    "subdivision": "15",
    "timezone": "America/Mexico_City"
  },
  "geometry": {
    "type": "Point",
    "coordinates": [
      -99.60695,
      19.71909
    ]
  }
}