{
  "type": "Feature",
  "properties": {
    "name": "Santa María Mazatla",
    "country": "MX",
    "subdivision": "15",
    "timezone": "America/Mexico_City"
  },
  "geometry": {
    "type": "Point",
    "coordinates": [
      -99.38694,
      19.51528
    ]
  }
}