{
  "type": "Feature",
  "properties": {
    "name": "Santiago Yeché",
    "country": "MX",
    "subdivision": "15",
    "timezone": "America/Mexico_City"
  },
  "geometry": {
    "type": "Point",
    "coordinates": [
      -99.7119,
      19.70853
    ]
  }
}