{
  "type": "Feature",
  "properties": {
    "name": "Santiago Teyahualco",
    "country": "MX",
    "subdivision": "15",
    "timezone": "America/Mexico_City"
  },
  "geometry": {
    "type": "Point",
    "coordinates": [
      -99.12493,
      19.65985
    ]
  }
}