{
  "type": "Feature",
  "properties": {
    "name": "Santa Isabel Chalma",
    "country": "MX",
    "subdivision": "15",
    "timezone": "America/Mexico_City"
  },
  "geometry": {
    "type": "Point",
    "coordinates": [
      -98.76533,
      19.15712
    ]
  }
}