{
  "type": "Feature",
  "properties": {
    "name": "Santa Ana",
    "country": "MX",
    "subdivision": "15",
    "timezone": "America/Mexico_City"
  },
  "geometry": {
    "type": "Point",
    "coordinates": [
      -99.41333,
      18.9875
    ]
  }
}