{
  "type": "Feature",
  "properties": {
    "name": "Santa Lucía",
    "country": "MX",
    "subdivision": "15",
    "timezone": "America/Mexico_City"
  },
  "geometry": {
    "type": "Point",
    "coordinates": [
      -99.38683,
      19.02749
    ]
  }
}