{
  "type": "Feature",
  "properties": {
    "name": "Santiago Mamalhuazuca",
    "country": "MX",
    "subdivision": "15",
    "timezone": "America/Mexico_City"
  },
  "geometry": {
    "type": "Point",
    "coordinates": [
      -98.79602,
      18.99659
    ]
  }
}