{
  "type": "Feature",
  "properties": {
    "name": "Santiago Tepetitlán",
    "country": "MX",
    "subdivision": "15",
    "timezone": "America/Mexico_City"
  },
  "geometry": {
    "type": "Point",
    "coordinates": [
      -98.81841,
      19.63807
    ]
  }
}