{
  "type": "Feature",
  "properties": {
    "name": "Tecamachalco",
    "country": "MX",
    "subdivision": "15",
    "timezone": "America/Mexico_City"
  },
  "geometry": {
    "type": "Point",
    "coordinates": [
      -98.95957,
      19.35992
    ]
  }
}