{
  "type": "Feature",
  "properties": {
    "name": "Techachaltitla",
    "country": "MX",
    "subdivision": "15",
    "timezone": "America/Mexico_City"
  },
  "geometry": {
    "type": "Point",
    "coordinates": [
      -98.94056,
      19.365
    ]
  }
}