{
  "type": "Feature",
  "properties": {
    "name": "Tecoac (Santa María Nativitas)",
    "country": "MX",
    "subdivision": "15",
    "timezone": "America/Mexico_City"
  },
  "geometry": {
    "type": "Point",
    "coordinates": [
      -99.85306,
      19.78917
    ]
  }
}