{
  "type": "Feature",
  "properties": {
    "name": "Temascaltepec de González",
    "country": "MX",
    "subdivision": "15",
    "timezone": "America/Mexico_City"
  },
  "geometry": {
    "type": "Point",
    "coordinates": [
      -100.04236,
      19.04409
    ]
  }
}