{
  "type": "Feature",
  "properties": {
    "name": "Tepetongo",
    "country": "MX",
    "subdivision": "15",
    "timezone": "America/Mexico_City"
  },
  "geometry": {
    "type": "Point",
    "coordinates": [
      -100.13356,
      19.90877
    ]
  }
}