{
  "type": "Feature",
  "properties": {
    "name": "Tepetlaoxtoc de Hidalgo",
    "country": "MX",
    "subdivision": "15",
    "timezone": "America/Mexico_City"
  },
  "geometry": {
    "type": "Point",
    "coordinates": [
      -98.81835,
      19.57437
    ]
  }
}