{
  "type": "Feature",
  "properties": {
    "name": "Tequisistlán",
    "country": "MX",
    "subdivision": "15",
    "timezone": "America/Mexico_City"
  },
  "geometry": {
    "type": "Point",
    "coordinates": [
      -98.94105,
      19.59642
    ]
  }
}