{
  "type": "Feature",
  "properties": {
    "name": "Tixmadeje Chiquito",
    "country": "MX",
    "subdivision": "15",
    "timezone": "America/Mexico_City"
  },
  "geometry": {
    "type": "Point",
    "coordinates": [
      -99.91444,
      19.96556
    ]
  }
}