{
  "type": "Feature",
  "properties": {
    "name": "Tlalnepantla",
    "country": "MX",
    "subdivision": "15",
    "timezone": "America/Mexico_City"
  },
  "geometry": {
    "type": "Point",
    "coordinates": [
      -99.19538,
      19.54005
    ]
  }
}