{
  "type": "Feature",
  "properties": {
    "name": "Tultitlán de Mariano Escobedo",
    "country": "MX",
    "subdivision": "15",
    "timezone": "America/Mexico_City"
  },
  "geometry": {
    "type": "Point",
    "coordinates": [
      -99.16787,
      19.64655
    ]
  }
}