{
  "type": "Feature",
  "properties": {
    "name": "Turcio Segunda Sección",
    "country": "MX",
    "subdivision": "15",
    "timezone": "America/Mexico_City"
  },
  "geometry": {
    "type": "Point",
    "coordinates": [
      -99.96009,
      19.36527
    ]
  }
}