{
  "type": "Feature",
  "properties": {
    "name": "Valle de Bravo",
    "country": "MX",
    "subdivision": "15",
    "timezone": "America/Mexico_City"
  },
  "geometry": {
    "type": "Point",
    "coordinates": [
      -100.13132,
      19.19501
    ]
  }
}