{
  "type": "Feature",
  "properties": {
    "name": "Veintidós de Febrero",
    "country": "MX",
    "subdivision": "15",
    "timezone": "America/Mexico_City"
  },
  "geometry": {
    "type": "Point",
    "coordinates": [
      -99.34667,
      19.61139
    ]
  }
}