{
  "type": "Feature",
  "properties": {
    "name": "Xhixhata",
    "country": "MX",
    "subdivision": "15",
    "timezone": "America/Mexico_City"
  },
  "geometry": {
    "type": "Point",
    "coordinates": [
      -99.54611,
      19.97056
    ]
  }
}