{
  "type": "Feature",
  "properties": {
    "name": "Xometla",
    "country": "MX",
    "subdivision": "15",
    "timezone": "America/Mexico_City"
  },
  "geometry": {
    "type": "Point",
    "coordinates": [
      -98.88171,
      19.64281
    ]
  }
}