{
  "type": "Feature",
  "properties": {
    "name": "Zula",
    "country": "MX",
    "subdivision": "15",
    "timezone": "America/Mexico_City"
  },
  "geometry": {
    "type": "Point",
    "coordinates": [
      -98.8895,
      19.22011
    ]
  }
}