{
  "type": "Feature",
  "properties": {
    "name": "Zumpango",
    "country": "MX",
    "subdivision": "15",
    "timezone": "America/Mexico_City"
  },
  "geometry": {
    "type": "Point",
    "coordinates": [
      -99.09946,
      19.7967
    ]
  }
}