{
  "type": "Feature",
  "properties": {
    "name": "Naxxar",
    "country": "MT",
    "subdivision": "38",
    "timezone": "Europe/Malta"
  },
  "geometry": {
    "type": "Point",
    "coordinates": [
      14.44361,
      35.91361
    ]
  }
}