{
  "type": "Feature",
  "properties": {
    "name": "Galleh Manda",
    "country": "GM",
    "subdivision": "03",
    "timezone": "Africa/Banjul"
  },
  "geometry": {
    "type": "Point",
    "coordinates": [
      -14.78333,
      13.43333
    ]
  }
}