{
  "type": "Feature",
  "properties": {
    "name": "Janjanbureh",
    "country": "GM",
    "subdivision": "03",
    "timezone": "Africa/Banjul"
  },
  "geometry": {
    "type": "Point",
    "coordinates": [
      -14.76374,
      13.54039
    ]
  }
}