{
  "type": "Feature",
  "properties": {
    "name": "Saruja",
    "country": "GM",
    "subdivision": "03",
    "timezone": "Africa/Banjul"
  },
  "geometry": {
    "type": "Point",
    "coordinates": [
      -14.91667,
      13.55
    ]
  }
}