{
  "type": "Feature",
  "properties": {
    "name": "Doctor Juan Manuel Frutos",
    "country": "PY",
    "subdivision": "04",
    "timezone": "America/Asuncion"
  },
  "geometry": {
    "type": "Point",
    "coordinates": [
      -55.83215,
      -25.3838
    ]
  }
}