{
  "type": "Feature",
  "properties": {
    "name": "Qinhuangdao",
    "country": "CN",
    "subdivision": "10",
    "timezone": "Asia/Shanghai"
  },
  "geometry": {
    "type": "Point",
    "coordinates": [
      119.58833,
      39.93167
    ]
  }
}