{
  "type": "Feature",
  "properties": {
    "name": "Karnobat",
    "country": "BG",
    "subdivision": "39",
    "timezone": "Europe/Sofia"
  },
  "geometry": {
    "type": "Point",
    "coordinates": [
      26.98333,
      42.65
    ]
  }
}