{
  "type": "Feature",
  "properties": {
    "name": "Sungurlare",
    "country": "BG",
    "subdivision": "39",
    "timezone": "Europe/Sofia"
  },
  "geometry": {
    "type": "Point",
    "coordinates": [
      26.78333,
      42.76667
    ]
  }
}