{
  "type": "Feature",
  "properties": {
    "name": "Bakovci",
    "country": "SI",
    "subdivision": "80",
    "timezone": "Europe/Ljubljana"
  },
  "geometry": {
    "type": "Point",
    "coordinates": [
      16.15028,
      46.61889
    ]
  }
}