{
  "type": "Feature",
  "properties": {
    "name": "Al Kittah",
    "country": "JO",
    "subdivision": "22",
    "timezone": "Asia/Amman"
  },
  "geometry": {
    "type": "Point",
    "coordinates": [
      35.84114,
      32.27685
    ]
  }
}