{
  "type": "Feature",
  "properties": {
    "name": "Chattogram",
    "country": "BD",
    "subdivision": "84",
    "timezone": "Asia/Dhaka"
  },
  "geometry": {
    "type": "Point",
    "coordinates": [
      91.83168,
      22.3384
    ]
  }
}