{
  "type": "Feature",
  "properties": {
    "name": "Cox’s Bāzār",
    "country": "BD",
    "subdivision": "84",
    "timezone": "Asia/Dhaka"
  },
  "geometry": {
    "type": "Point",
    "coordinates": [
      92.00955,
      21.43973
    ]
  }
}