{
  "type": "Feature",
  "properties": {
    "name": "Lākshām",
    "country": "BD",
    "subdivision": "84",
    "timezone": "Asia/Dhaka"
  },
  "geometry": {
    "type": "Point",
    "coordinates": [
      91.12143,
      23.24018
    ]
  }
}