{
  "type": "Feature",
  "properties": {
    "name": "Manikchari",
    "country": "BD",
    "subdivision": "84",
    "timezone": "Asia/Dhaka"
  },
  "geometry": {
    "type": "Point",
    "coordinates": [
      91.84128,
      22.83957
    ]
  }
}