{
  "type": "Feature",
  "properties": {
    "name": "Kayl",
    "country": "LU",
    "subdivision": "ES",
    "timezone": "Europe/Luxembourg"
  },
  "geometry": {
    "type": "Point",
    "coordinates": [
      6.03972,
      49.48917
    ]
  }
}