{
  "type": "Feature",
  "properties": {
    "name": "Alma",
    "country": "US",
    "subdivision": "NE",
    "timezone": "America/Chicago"
  },
  "geometry": {
    "type": "Point",
    "coordinates": [
      -99.36204,
      40.09751
    ]
  }
}