{
  "type": "Feature",
  "properties": {
    "name": "Gordon",
    "country": "US",
    "subdivision": "NE",
    "timezone": "America/Denver"
  },
  "geometry": {
    "type": "Point",
    "coordinates": [
      -102.20322,
      42.80472
    ]
  }
}