{
  "type": "Feature",
  "properties": {
    "name": "Holdrege",
    "country": "US",
    "subdivision": "NE",
    "timezone": "America/Chicago"
  },
  "geometry": {
    "type": "Point",
    "coordinates": [
      -99.36982,
      40.44029
    ]
  }
}