{
  "type": "Feature",
  "properties": {
    "name": "Louisville",
    "country": "US",
    "subdivision": "NE",
    "timezone": "America/Chicago"
  },
  "geometry": {
    "type": "Point",
    "coordinates": [
      -96.16224,
      40.99778
    ]
  }
}