{
  "type": "Feature",
  "properties": {
    "name": "Milford",
    "country": "US",
    "subdivision": "NE",
    "timezone": "America/Chicago"
  },
  "geometry": {
    "type": "Point",
    "coordinates": [
      -97.05059,
      40.77445
    ]
  }
}