{
  "type": "Feature",
  "properties": {
    "name": "Oakland",
    "country": "US",
    "subdivision": "NE",
    "timezone": "America/Chicago"
  },
  "geometry": {
    "type": "Point",
    "coordinates": [
      -96.46697,
      41.83583
    ]
  }
}