{
  "type": "Feature",
  "properties": {
    "name": "Saint Paul",
    "country": "US",
    "subdivision": "NE",
    "timezone": "America/Chicago"
  },
  "geometry": {
    "type": "Point",
    "coordinates": [
      -98.45812,
      41.21473
    ]
  }
}