{
  "type": "Feature",
  "properties": {
    "name": "Valley",
    "country": "US",
    "subdivision": "NE",
    "timezone": "America/Chicago"
  },
  "geometry": {
    "type": "Point",
    "coordinates": [
      -96.34614,
      41.31278
    ]
  }
}