{
  "type": "Feature",
  "properties": {
    "name": "Aigues-Vives",
    "country": "FR",
    "subdivision": "76",
    "timezone": "Europe/Paris"
  },
  "geometry": {
    "type": "Point",
    "coordinates": [
      4.17976,
      43.7397
    ]
  }
}