{
  "type": "Feature",
  "properties": {
    "name": "Aubais",
    "country": "FR",
    "subdivision": "76",
    "timezone": "Europe/Paris"
  },
  "geometry": {
    "type": "Point",
    "coordinates": [
      4.14733,
      43.75524
    ]
  }
}