{
  "type": "Feature",
  "properties": {
    "name": "Ayguesvives",
    "country": "FR",
    "subdivision": "76",
    "timezone": "Europe/Paris"
  },
  "geometry": {
    "type": "Point",
    "coordinates": [
      1.59771,
      43.43733
    ]
  }
}