{
  "type": "Feature",
  "properties": {
    "name": "Bagnères-de-Bigorre",
    "country": "FR",
    "subdivision": "76",
    "timezone": "Europe/Paris"
  },
  "geometry": {
    "type": "Point",
    "coordinates": [
      0.14876,
      43.06497
    ]
  }
}