{
  "type": "Feature",
  "properties": {
    "name": "Balaruc-le-Vieux",
    "country": "FR",
    "subdivision": "76",
    "timezone": "Europe/Paris"
  },
  "geometry": {
    "type": "Point",
    "coordinates": [
      3.6853,
      43.4614
    ]
  }
}