{
  "type": "Feature",
  "properties": {
    "name": "Barbazan-Debat",
    "country": "FR",
    "subdivision": "76",
    "timezone": "Europe/Paris"
  },
  "geometry": {
    "type": "Point",
    "coordinates": [
      0.1206,
      43.1958
    ]
  }
}