{
  "type": "Feature",
  "properties": {
    "name": "Barcelonne-du-Gers",
    "country": "FR",
    "subdivision": "76",
    "timezone": "Europe/Paris"
  },
  "geometry": {
    "type": "Point",
    "coordinates": [
      -0.23632,
      43.70334
    ]
  }
}