{
  "type": "Feature",
  "properties": {
    "name": "Bassan",
    "country": "FR",
    "subdivision": "76",
    "timezone": "Europe/Paris"
  },
  "geometry": {
    "type": "Point",
    "coordinates": [
      3.25312,
      43.41126
    ]
  }
}