{
  "type": "Feature",
  "properties": {
    "name": "Beaupuy",
    "country": "FR",
    "subdivision": "76",
    "timezone": "Europe/Paris"
  },
  "geometry": {
    "type": "Point",
    "coordinates": [
      1.55517,
      43.64713
    ]
  }
}