{
  "type": "Feature",
  "properties": {
    "name": "Bellegarde",
    "country": "FR",
    "subdivision": "76",
    "timezone": "Europe/Paris"
  },
  "geometry": {
    "type": "Point",
    "coordinates": [
      4.51372,
      43.75401
    ]
  }
}