{
  "type": "Feature",
  "properties": {
    "name": "Boisset",
    "country": "FR",
    "subdivision": "76",
    "timezone": "Europe/Paris"
  },
  "geometry": {
    "type": "Point",
    "coordinates": [
      4.00908,
      44.0476
    ]
  }
}