{
  "type": "Feature",
  "properties": {
    "name": "Bout-du-Pont-de-Larn",
    "country": "FR",
    "subdivision": "76",
    "timezone": "Europe/Paris"
  },
  "geometry": {
    "type": "Point",
    "coordinates": [
      2.40417,
      43.50072
    ]
  }
}