{
  "type": "Feature",
  "properties": {
    "name": "Bozouls",
    "country": "FR",
    "subdivision": "76",
    "timezone": "Europe/Paris"
  },
  "geometry": {
    "type": "Point",
    "coordinates": [
      2.72534,
      44.47202
    ]
  }
}