{
  "type": "Feature",
  "properties": {
    "name": "Cahors",
    "country": "FR",
    "subdivision": "76",
    "timezone": "Europe/Paris"
  },
  "geometry": {
    "type": "Point",
    "coordinates": [
      1.43663,
      44.4491
    ]
  }
}