{
  "type": "Feature",
  "properties": {
    "name": "Calmont",
    "country": "FR",
    "subdivision": "76",
    "timezone": "Europe/Paris"
  },
  "geometry": {
    "type": "Point",
    "coordinates": [
      2.51201,
      44.24883
    ]
  }
}