{
  "type": "Feature",
  "properties": {
    "name": "Castelginest",
    "country": "FR",
    "subdivision": "76",
    "timezone": "Europe/Paris"
  },
  "geometry": {
    "type": "Point",
    "coordinates": [
      1.4344,
      43.69382
    ]
  }
}