{
  "type": "Feature",
  "properties": {
    "name": "Castres",
    "country": "FR",
    "subdivision": "76",
    "timezone": "Europe/Paris"
  },
  "geometry": {
    "type": "Point",
    "coordinates": [
      2.24088,
      43.60527
    ]
  }
}