{
  "type": "Feature",
  "properties": {
    "name": "Castelsarrasin",
    "country": "FR",
    "subdivision": "76",
    "timezone": "Europe/Paris"
  },
  "geometry": {
    "type": "Point",
    "coordinates": [
      1.10666,
      44.04042
    ]
  }
}