{
  "type": "Feature",
  "properties": {
    "name": "Caylus",
    "country": "FR",
    "subdivision": "76",
    "timezone": "Europe/Paris"
  },
  "geometry": {
    "type": "Point",
    "coordinates": [
      1.77105,
      44.23646
    ]
  }
}