{
  "type": "Feature",
  "properties": {
    "name": "Cazères",
    "country": "FR",
    "subdivision": "76",
    "timezone": "Europe/Paris"
  },
  "geometry": {
    "type": "Point",
    "coordinates": [
      1.08578,
      43.20718
    ]
  }
}