{
  "type": "Feature",
  "properties": {
    "name": "Cers",
    "country": "FR",
    "subdivision": "76",
    "timezone": "Europe/Paris"
  },
  "geometry": {
    "type": "Point",
    "coordinates": [
      3.30474,
      43.32345
    ]
  }
}