{
  "type": "Feature",
  "properties": {
    "name": "Condom",
    "country": "FR",
    "subdivision": "76",
    "timezone": "Europe/Paris"
  },
  "geometry": {
    "type": "Point",
    "coordinates": [
      0.37199,
      43.95816
    ]
  }
}