{
  "type": "Feature",
  "properties": {
    "name": "Elne",
    "country": "FR",
    "subdivision": "76",
    "timezone": "Europe/Paris"
  },
  "geometry": {
    "type": "Point",
    "coordinates": [
      2.97176,
      42.60432
    ]
  }
}