{
  "type": "Feature",
  "properties": {
    "name": "els Banys d'Arles",
    "country": "FR",
    "subdivision": "76",
    "timezone": "Europe/Paris"
  },
  "geometry": {
    "type": "Point",
    "coordinates": [
      2.66916,
      42.47289
    ]
  }
}