{
  "type": "Feature",
  "properties": {
    "name": "Ferrals-les-Corbières",
    "country": "FR",
    "subdivision": "76",
    "timezone": "Europe/Paris"
  },
  "geometry": {
    "type": "Point",
    "coordinates": [
      2.72759,
      43.14766
    ]
  }
}