{
  "type": "Feature",
  "properties": {
    "name": "Fonsorbes",
    "country": "FR",
    "subdivision": "76",
    "timezone": "Europe/Paris"
  },
  "geometry": {
    "type": "Point",
    "coordinates": [
      1.22882,
      43.539
    ]
  }
}