{
  "type": "Feature",
  "properties": {
    "name": "Fontenilles",
    "country": "FR",
    "subdivision": "76",
    "timezone": "Europe/Paris"
  },
  "geometry": {
    "type": "Point",
    "coordinates": [
      1.19142,
      43.5535
    ]
  }
}