{
  "type": "Feature",
  "properties": {
    "name": "Giroussens",
    "country": "FR",
    "subdivision": "76",
    "timezone": "Europe/Paris"
  },
  "geometry": {
    "type": "Point",
    "coordinates": [
      1.77556,
      43.76221
    ]
  }
}