{
  "type": "Feature",
  "properties": {
    "name": "Graulhet",
    "country": "FR",
    "subdivision": "76",
    "timezone": "Europe/Paris"
  },
  "geometry": {
    "type": "Point",
    "coordinates": [
      1.98938,
      43.76688
    ]
  }
}