{
  "type": "Feature",
  "properties": {
    "name": "Ille-sur-Têt",
    "country": "FR",
    "subdivision": "76",
    "timezone": "Europe/Paris"
  },
  "geometry": {
    "type": "Point",
    "coordinates": [
      2.62066,
      42.67083
    ]
  }
}