{
  "type": "Feature",
  "properties": {
    "name": "Labastide-Beauvoir",
    "country": "FR",
    "subdivision": "76",
    "timezone": "Europe/Paris"
  },
  "geometry": {
    "type": "Point",
    "coordinates": [
      1.66533,
      43.48166
    ]
  }
}