{
  "type": "Feature",
  "properties": {
    "name": "Lamalou-les-Bains",
    "country": "FR",
    "subdivision": "76",
    "timezone": "Europe/Paris"
  },
  "geometry": {
    "type": "Point",
    "coordinates": [
      3.07985,
      43.59758
    ]
  }
}