{
  "type": "Feature",
  "properties": {
    "name": "Lapeyrouse-Fossat",
    "country": "FR",
    "subdivision": "76",
    "timezone": "Europe/Paris"
  },
  "geometry": {
    "type": "Point",
    "coordinates": [
      1.51049,
      43.69973
    ]
  }
}