{
  "type": "Feature",
  "properties": {
    "name": "Laroque-d'Olmes",
    "country": "FR",
    "subdivision": "76",
    "timezone": "Europe/Paris"
  },
  "geometry": {
    "type": "Point",
    "coordinates": [
      1.87098,
      42.97033
    ]
  }
}