{
  "type": "Feature",
  "properties": {
    "name": "Lattes",
    "country": "FR",
    "subdivision": "76",
    "timezone": "Europe/Paris"
  },
  "geometry": {
    "type": "Point",
    "coordinates": [
      3.90279,
      43.56775
    ]
  }
}