{
  "type": "Feature",
  "properties": {
    "name": "Lavelanet",
    "country": "FR",
    "subdivision": "76",
    "timezone": "Europe/Paris"
  },
  "geometry": {
    "type": "Point",
    "coordinates": [
      1.84844,
      42.93267
    ]
  }
}