{
  "type": "Feature",
  "properties": {
    "name": "Le Bousquet-d'Orb",
    "country": "FR",
    "subdivision": "76",
    "timezone": "Europe/Paris"
  },
  "geometry": {
    "type": "Point",
    "coordinates": [
      3.16595,
      43.6925
    ]
  }
}