{
  "type": "Feature",
  "properties": {
    "name": "Le Pouget",
    "country": "FR",
    "subdivision": "76",
    "timezone": "Europe/Paris"
  },
  "geometry": {
    "type": "Point",
    "coordinates": [
      3.5245,
      43.59197
    ]
  }
}