{
  "type": "Feature",
  "properties": {
    "name": "Marseillan",
    "country": "FR",
    "subdivision": "76",
    "timezone": "Europe/Paris"
  },
  "geometry": {
    "type": "Point",
    "coordinates": [
      3.52804,
      43.35674
    ]
  }
}