{
  "type": "Feature",
  "properties": {
    "name": "Martres-Tolosane",
    "country": "FR",
    "subdivision": "76",
    "timezone": "Europe/Paris"
  },
  "geometry": {
    "type": "Point",
    "coordinates": [
      1.01104,
      43.19917
    ]
  }
}