{
  "type": "Feature",
  "properties": {
    "name": "Martel",
    "country": "FR",
    "subdivision": "76",
    "timezone": "Europe/Paris"
  },
  "geometry": {
    "type": "Point",
    "coordinates": [
      1.60851,
      44.93667
    ]
  }
}