{
  "type": "Feature",
  "properties": {
    "name": "Marvejols",
    "country": "FR",
    "subdivision": "76",
    "timezone": "Europe/Paris"
  },
  "geometry": {
    "type": "Point",
    "coordinates": [
      3.29041,
      44.55435
    ]
  }
}