{
  "type": "Feature",
  "properties": {
    "name": "Maureillas-las-Illas",
    "country": "FR",
    "subdivision": "76",
    "timezone": "Europe/Paris"
  },
  "geometry": {
    "type": "Point",
    "coordinates": [
      2.80752,
      42.49014
    ]
  }
}