{
  "type": "Feature",
  "properties": {
    "name": "Maureilhan",
    "country": "FR",
    "subdivision": "76",
    "timezone": "Europe/Paris"
  },
  "geometry": {
    "type": "Point",
    "coordinates": [
      3.12011,
      43.3576
    ]
  }
}