{
  "type": "Feature",
  "properties": {
    "name": "Mazères",
    "country": "FR",
    "subdivision": "76",
    "timezone": "Europe/Paris"
  },
  "geometry": {
    "type": "Point",
    "coordinates": [
      1.67816,
      43.25174
    ]
  }
}