{
  "type": "Feature",
  "properties": {
    "name": "Mende",
    "country": "FR",
    "subdivision": "76",
    "timezone": "Europe/Paris"
  },
  "geometry": {
    "type": "Point",
    "coordinates": [
      3.49978,
      44.52161
    ]
  }
}