{
  "type": "Feature",
  "properties": {
    "name": "Monclar-de-Quercy",
    "country": "FR",
    "subdivision": "76",
    "timezone": "Europe/Paris"
  },
  "geometry": {
    "type": "Point",
    "coordinates": [
      1.58457,
      43.96643
    ]
  }
}