{
  "type": "Feature",
  "properties": {
    "name": "Mondonville",
    "country": "FR",
    "subdivision": "76",
    "timezone": "Europe/Paris"
  },
  "geometry": {
    "type": "Point",
    "coordinates": [
      1.28592,
      43.67296
    ]
  }
}