{
  "type": "Feature",
  "properties": {
    "name": "Montréal",
    "country": "FR",
    "subdivision": "76",
    "timezone": "Europe/Paris"
  },
  "geometry": {
    "type": "Point",
    "coordinates": [
      0.20217,
      43.9502
    ]
  }
}