{
  "type": "Feature",
  "properties": {
    "name": "Montaigut-sur-Save",
    "country": "FR",
    "subdivision": "76",
    "timezone": "Europe/Paris"
  },
  "geometry": {
    "type": "Point",
    "coordinates": [
      1.23133,
      43.68947
    ]
  }
}