{
  "type": "Feature",
  "properties": {
    "name": "Montjoie-en-Couserans",
    "country": "FR",
    "subdivision": "76",
    "timezone": "Europe/Paris"
  },
  "geometry": {
    "type": "Point",
    "coordinates": [
      1.16,
      43.0025
    ]
  }
}