{
  "type": "Feature",
  "properties": {
    "name": "Montréjeau",
    "country": "FR",
    "subdivision": "76",
    "timezone": "Europe/Paris"
  },
  "geometry": {
    "type": "Point",
    "coordinates": [
      0.56839,
      43.08579
    ]
  }
}