{
  "type": "Feature",
  "properties": {
    "name": "Montberon",
    "country": "FR",
    "subdivision": "76",
    "timezone": "Europe/Paris"
  },
  "geometry": {
    "type": "Point",
    "coordinates": [
      1.4801,
      43.71602
    ]
  }
}