{
  "type": "Feature",
  "properties": {
    "name": "Monteils",
    "country": "FR",
    "subdivision": "76",
    "timezone": "Europe/Paris"
  },
  "geometry": {
    "type": "Point",
    "coordinates": [
      1.57608,
      44.16862
    ]
  }
}