{
  "type": "Feature",
  "properties": {
    "name": "Moussac",
    "country": "FR",
    "subdivision": "76",
    "timezone": "Europe/Paris"
  },
  "geometry": {
    "type": "Point",
    "coordinates": [
      4.22863,
      43.98244
    ]
  }
}