{
  "type": "Feature",
  "properties": {
    "name": "Narbonne",
    "country": "FR",
    "subdivision": "76",
    "timezone": "Europe/Paris"
  },
  "geometry": {
    "type": "Point",
    "coordinates": [
      3.00141,
      43.18396
    ]
  }
}