{
  "type": "Feature",
  "properties": {
    "name": "Nébian",
    "country": "FR",
    "subdivision": "76",
    "timezone": "Europe/Paris"
  },
  "geometry": {
    "type": "Point",
    "coordinates": [
      3.43083,
      43.60635
    ]
  }
}