{
  "type": "Feature",
  "properties": {
    "name": "Ondes",
    "country": "FR",
    "subdivision": "76",
    "timezone": "Europe/Paris"
  },
  "geometry": {
    "type": "Point",
    "coordinates": [
      1.30823,
      43.7825
    ]
  }
}