{
  "type": "Feature",
  "properties": {
    "name": "Osséja",
    "country": "FR",
    "subdivision": "76",
    "timezone": "Europe/Paris"
  },
  "geometry": {
    "type": "Point",
    "coordinates": [
      1.98192,
      42.41383
    ]
  }
}