{
  "type": "Feature",
  "properties": {
    "name": "Ouveillan",
    "country": "FR",
    "subdivision": "76",
    "timezone": "Europe/Paris"
  },
  "geometry": {
    "type": "Point",
    "coordinates": [
      2.97029,
      43.28858
    ]
  }
}