{
  "type": "Feature",
  "properties": {
    "name": "Pépieux",
    "country": "FR",
    "subdivision": "76",
    "timezone": "Europe/Paris"
  },
  "geometry": {
    "type": "Point",
    "coordinates": [
      2.67825,
      43.29755
    ]
  }
}