{
  "type": "Feature",
  "properties": {
    "name": "Pezens",
    "country": "FR",
    "subdivision": "76",
    "timezone": "Europe/Paris"
  },
  "geometry": {
    "type": "Point",
    "coordinates": [
      2.26868,
      43.25446
    ]
  }
}