{
  "type": "Feature",
  "properties": {
    "name": "Pibrac",
    "country": "FR",
    "subdivision": "76",
    "timezone": "Europe/Paris"
  },
  "geometry": {
    "type": "Point",
    "coordinates": [
      1.2854,
      43.62042
    ]
  }
}