{
  "type": "Feature",
  "properties": {
    "name": "Prades",
    "country": "FR",
    "subdivision": "76",
    "timezone": "Europe/Paris"
  },
  "geometry": {
    "type": "Point",
    "coordinates": [
      2.42177,
      42.61755
    ]
  }
}