{
  "type": "Feature",
  "properties": {
    "name": "Quillan",
    "country": "FR",
    "subdivision": "76",
    "timezone": "Europe/Paris"
  },
  "geometry": {
    "type": "Point",
    "coordinates": [
      2.18142,
      42.87549
    ]
  }
}