{
  "type": "Feature",
  "properties": {
    "name": "Rabastens",
    "country": "FR",
    "subdivision": "76",
    "timezone": "Europe/Paris"
  },
  "geometry": {
    "type": "Point",
    "coordinates": [
      1.72382,
      43.82512
    ]
  }
}