{
  "type": "Feature",
  "properties": {
    "name": "Remoulins",
    "country": "FR",
    "subdivision": "76",
    "timezone": "Europe/Paris"
  },
  "geometry": {
    "type": "Point",
    "coordinates": [
      4.56602,
      43.93965
    ]
  }
}