{
  "type": "Feature",
  "properties": {
    "name": "Rochefort-du-Gard",
    "country": "FR",
    "subdivision": "76",
    "timezone": "Europe/Paris"
  },
  "geometry": {
    "type": "Point",
    "coordinates": [
      4.68977,
      43.97452
    ]
  }
}