{
  "type": "Feature",
  "properties": {
    "name": "Saint-Lizier",
    "country": "FR",
    "subdivision": "76",
    "timezone": "Europe/Paris"
  },
  "geometry": {
    "type": "Point",
    "coordinates": [
      1.13739,
      43.00185
    ]
  }
}