{
  "type": "Feature",
  "properties": {
    "name": "Sainte-Foy-de-Peyrolières",
    "country": "FR",
    "subdivision": "76",
    "timezone": "Europe/Paris"
  },
  "geometry": {
    "type": "Point",
    "coordinates": [
      1.14588,
      43.49312
    ]
  }
}