{
  "type": "Feature",
  "properties": {
    "name": "Saint-Florent-sur-Auzonnet",
    "country": "FR",
    "subdivision": "76",
    "timezone": "Europe/Paris"
  },
  "geometry": {
    "type": "Point",
    "coordinates": [
      4.11151,
      44.24166
    ]
  }
}