{
  "type": "Feature",
  "properties": {
    "name": "Saint-Geniès-de-Fontedit",
    "country": "FR",
    "subdivision": "76",
    "timezone": "Europe/Paris"
  },
  "geometry": {
    "type": "Point",
    "coordinates": [
      3.1789,
      43.46881
    ]
  }
}