{
  "type": "Feature",
  "properties": {
    "name": "Saint-Pons-de-Thomières",
    "country": "FR",
    "subdivision": "76",
    "timezone": "Europe/Paris"
  },
  "geometry": {
    "type": "Point",
    "coordinates": [
      2.76667,
      43.48333
    ]
  }
}