{
  "type": "Feature",
  "properties": {
    "name": "Saint-Etienne-de-Tulmont",
    "country": "FR",
    "subdivision": "76",
    "timezone": "Europe/Paris"
  },
  "geometry": {
    "type": "Point",
    "coordinates": [
      1.46667,
      44.05
    ]
  }
}