{
  "type": "Feature",
  "properties": {
    "name": "Saint-Drézéry",
    "country": "FR",
    "subdivision": "76",
    "timezone": "Europe/Paris"
  },
  "geometry": {
    "type": "Point",
    "coordinates": [
      3.97809,
      43.73203
    ]
  }
}