{
  "type": "Feature",
  "properties": {
    "name": "Saint-Chinian",
    "country": "FR",
    "subdivision": "76",
    "timezone": "Europe/Paris"
  },
  "geometry": {
    "type": "Point",
    "coordinates": [
      2.94655,
      43.42207
    ]
  }
}