{
  "type": "Feature",
  "properties": {
    "name": "Saint-Féliu-d'Avall",
    "country": "FR",
    "subdivision": "76",
    "timezone": "Europe/Paris"
  },
  "geometry": {
    "type": "Point",
    "coordinates": [
      2.73814,
      42.68168
    ]
  }
}