{
  "type": "Feature",
  "properties": {
    "name": "Salles-Curan",
    "country": "FR",
    "subdivision": "76",
    "timezone": "Europe/Paris"
  },
  "geometry": {
    "type": "Point",
    "coordinates": [
      2.78714,
      44.18274
    ]
  }
}