{
  "type": "Feature",
  "properties": {
    "name": "Samatan",
    "country": "FR",
    "subdivision": "76",
    "timezone": "Europe/Paris"
  },
  "geometry": {
    "type": "Point",
    "coordinates": [
      0.93079,
      43.4926
    ]
  }
}