{
  "type": "Feature",
  "properties": {
    "name": "Sauvian",
    "country": "FR",
    "subdivision": "76",
    "timezone": "Europe/Paris"
  },
  "geometry": {
    "type": "Point",
    "coordinates": [
      3.2576,
      43.29308
    ]
  }
}