{
  "type": "Feature",
  "properties": {
    "name": "Sérignan",
    "country": "FR",
    "subdivision": "76",
    "timezone": "Europe/Paris"
  },
  "geometry": {
    "type": "Point",
    "coordinates": [
      3.27664,
      43.27924
    ]
  }
}