{
  "type": "Feature",
  "properties": {
    "name": "Sernhac",
    "country": "FR",
    "subdivision": "76",
    "timezone": "Europe/Paris"
  },
  "geometry": {
    "type": "Point",
    "coordinates": [
      4.55201,
      43.91149
    ]
  }
}