{
  "type": "Feature",
  "properties": {
    "name": "Soues",
    "country": "FR",
    "subdivision": "76",
    "timezone": "Europe/Paris"
  },
  "geometry": {
    "type": "Point",
    "coordinates": [
      0.0991,
      43.20687
    ]
  }
}