{
  "type": "Feature",
  "properties": {
    "name": "Sumène",
    "country": "FR",
    "subdivision": "76",
    "timezone": "Europe/Paris"
  },
  "geometry": {
    "type": "Point",
    "coordinates": [
      3.71563,
      43.98091
    ]
  }
}