{
  "type": "Feature",
  "properties": {
    "name": "Sussargues",
    "country": "FR",
    "subdivision": "76",
    "timezone": "Europe/Paris"
  },
  "geometry": {
    "type": "Point",
    "coordinates": [
      4.0031,
      43.7125
    ]
  }
}