{
  "type": "Feature",
  "properties": {
    "name": "Thuir",
    "country": "FR",
    "subdivision": "76",
    "timezone": "Europe/Paris"
  },
  "geometry": {
    "type": "Point",
    "coordinates": [
      2.75577,
      42.6322
    ]
  }
}