{
  "type": "Feature",
  "properties": {
    "name": "Valras-Plage",
    "country": "FR",
    "subdivision": "76",
    "timezone": "Europe/Paris"
  },
  "geometry": {
    "type": "Point",
    "coordinates": [
      3.29032,
      43.24808
    ]
  }
}