{
  "type": "Feature",
  "properties": {
    "name": "Valros",
    "country": "FR",
    "subdivision": "76",
    "timezone": "Europe/Paris"
  },
  "geometry": {
    "type": "Point",
    "coordinates": [
      3.36603,
      43.4201
    ]
  }
}