{
  "type": "Feature",
  "properties": {
    "name": "Vézénobres",
    "country": "FR",
    "subdivision": "76",
    "timezone": "Europe/Paris"
  },
  "geometry": {
    "type": "Point",
    "coordinates": [
      4.13628,
      44.0529
    ]
  }
}