{
  "type": "Feature",
  "properties": {
    "name": "Vic-Fezensac",
    "country": "FR",
    "subdivision": "76",
    "timezone": "Europe/Paris"
  },
  "geometry": {
    "type": "Point",
    "coordinates": [
      0.30319,
      43.75873
    ]
  }
}