{
  "type": "Feature",
  "properties": {
    "name": "Villelongue-de-la-Salanque",
    "country": "FR",
    "subdivision": "76",
    "timezone": "Europe/Paris"
  },
  "geometry": {
    "type": "Point",
    "coordinates": [
      2.98219,
      42.72657
    ]
  }
}