{
  "type": "Feature",
  "properties": {
    "name": "Villemolaque",
    "country": "FR",
    "subdivision": "76",
    "timezone": "Europe/Paris"
  },
  "geometry": {
    "type": "Point",
    "coordinates": [
      2.83815,
      42.58899
    ]
  }
}