{
  "type": "Feature",
  "properties": {
    "name": "Garðabær",
    "country": "IS",
    "subdivision": "39",
    "timezone": "Atlantic/Reykjavik"
  },
  "geometry": {
    "type": "Point",
    "coordinates": [
      -21.92298,
      64.08865
    ]
  }
}