{
  "type": "Feature",
  "properties": {
    "name": "Hlučín",
    "country": "CZ",
    "subdivision": "85",
    "timezone": "Europe/Prague"
  },
  "geometry": {
    "type": "Point",
    "coordinates": [
      18.19196,
      49.89795
    ]
  }
}