{
  "type": "Feature",
  "properties": {
    "name": "Kopřivnice",
    "country": "CZ",
    "subdivision": "85",
    "timezone": "Europe/Prague"
  },
  "geometry": {
    "type": "Point",
    "coordinates": [
      18.1448,
      49.59947
    ]
  }
}