{
  "type": "Feature",
  "properties": {
    "name": "Kunín",
    "country": "CZ",
    "subdivision": "85",
    "timezone": "Europe/Prague"
  },
  "geometry": {
    "type": "Point",
    "coordinates": [
      17.98965,
      49.63377
    ]
  }
}