{
  "type": "Feature",
  "properties": {
    "name": "Mořkov",
    "country": "CZ",
    "subdivision": "85",
    "timezone": "Europe/Prague"
  },
  "geometry": {
    "type": "Point",
    "coordinates": [
      18.05968,
      49.53684
    ]
  }
}