{
  "type": "Feature",
  "properties": {
    "name": "Pražmo",
    "country": "CZ",
    "subdivision": "85",
    "timezone": "Europe/Prague"
  },
  "geometry": {
    "type": "Point",
    "coordinates": [
      18.48617,
      49.60876
    ]
  }
}