{
  "type": "Feature",
  "properties": {
    "name": "Řepiště",
    "country": "CZ",
    "subdivision": "85",
    "timezone": "Europe/Prague"
  },
  "geometry": {
    "type": "Point",
    "coordinates": [
      18.31707,
      49.73338
    ]
  }
}