{
  "type": "Feature",
  "properties": {
    "name": "Starý Jičín",
    "country": "CZ",
    "subdivision": "85",
    "timezone": "Europe/Prague"
  },
  "geometry": {
    "type": "Point",
    "coordinates": [
      17.96169,
      49.57686
    ]
  }
}