{
  "type": "Feature",
  "properties": {
    "name": "Staré Město",
    "country": "CZ",
    "subdivision": "85",
    "timezone": "Europe/Prague"
  },
  "geometry": {
    "type": "Point",
    "coordinates": [
      18.36349,
      49.66992
    ]
  }
}