{
  "type": "Feature",
  "properties": {
    "name": "Stěbořice",
    "country": "CZ",
    "subdivision": "85",
    "timezone": "Europe/Prague"
  },
  "geometry": {
    "type": "Point",
    "coordinates": [
      17.80547,
      49.93708
    ]
  }
}