{
  "type": "Feature",
  "properties": {
    "name": "Štítina",
    "country": "CZ",
    "subdivision": "85",
    "timezone": "Europe/Prague"
  },
  "geometry": {
    "type": "Point",
    "coordinates": [
      18.01245,
      49.91487
    ]
  }
}