{
  "type": "Feature",
  "properties": {
    "name": "Vrbno pod Pradědem",
    "country": "CZ",
    "subdivision": "85",
    "timezone": "Europe/Prague"
  },
  "geometry": {
    "type": "Point",
    "coordinates": [
      17.38316,
      50.12095
    ]
  }
}