{
  "type": "Feature",
  "properties": {
    "name": "Langham",
    "country": "CA",
    "subdivision": "11",
    "timezone": "America/Regina"
  },
  "geometry": {
    "type": "Point",
    "coordinates": [
      -106.96793,
      52.3668
    ]
  }
}