{
  "type": "Feature",
  "properties": {
    "name": "Saskatoon",
    "country": "CA",
    "subdivision": "11",
    "timezone": "America/Regina"
  },
  "geometry": {
    "type": "Point",
    "coordinates": [
      -106.66892,
      52.13238
    ]
  }
}