{
  "type": "Feature",
  "properties": {
    "name": "Daga",
    "country": "BT",
    "subdivision": "08",
    "timezone": "Asia/Thimphu"
  },
  "geometry": {
    "type": "Point",
    "coordinates": [
      89.87688,
      27.07529
    ]
  }
}