{
  "type": "Feature",
  "properties": {
    "name": "Altay",
    "country": "CN",
    "subdivision": "13",
    "timezone": "Asia/Urumqi"
  },
  "geometry": {
    "type": "Point",
    "coordinates": [
      88.13361,
      47.84864
    ]
  }
}