{
  "type": "Feature",
  "properties": {
    "name": "Puerto Asís",
    "country": "CO",
    "subdivision": "22",
    "timezone": "America/Bogota"
  },
  "geometry": {
    "type": "Point",
    "coordinates": [
      -76.49571,
      0.50514
    ]
  }
}