{
  "type": "Feature",
  "properties": {
    "name": "Bafilo",
    "country": "TG",
    "subdivision": "23",
    "timezone": "Africa/Lome"
  },
  "geometry": {
    "type": "Point",
    "coordinates": [
      1.26667,
      9.35
    ]
  }
}