{
  "type": "Feature",
  "properties": {
    "name": "Chalinze",
    "country": "TZ",
    "subdivision": "02",
    "timezone": "Africa/Dar_es_Salaam"
  },
  "geometry": {
    "type": "Point",
    "coordinates": [
      38.35396,
      -6.63784
    ]
  }
}