{
  "type": "Feature",
  "properties": {
    "name": "Ikwiriri",
    "country": "TZ",
    "subdivision": "02",
    "timezone": "Africa/Dar_es_Salaam"
  },
  "geometry": {
    "type": "Point",
    "coordinates": [
      38.97164,
      -7.95618
    ]
  }
}