{
  "type": "Feature",
  "properties": {
    "name": "Athi River",
    "country": "KE",
    "subdivision": "31",
    "timezone": "Africa/Nairobi"
  },
  "geometry": {
    "type": "Point",
    "coordinates": [
      36.97826,
      -1.4563
    ]
  }
}