{
  "type": "Feature",
  "properties": {
    "name": "Argelia",
    "country": "CO",
    "subdivision": "09",
    "timezone": "America/Bogota"
  },
  "geometry": {
    "type": "Point",
    "coordinates": [
      -77.24876,
      2.25563
    ]
  }
}