{
  "type": "Feature",
  "properties": {
    "name": "Morales",
    "country": "CO",
    "subdivision": "09",
    "timezone": "America/Bogota"
  },
  "geometry": {
    "type": "Point",
    "coordinates": [
      -76.62791,
      2.75446
    ]
  }
}