{
  "type": "Feature",
  "properties": {
    "name": "Patía",
    "country": "CO",
    "subdivision": "09",
    "timezone": "America/Bogota"
  },
  "geometry": {
    "type": "Point",
    "coordinates": [
      -77.05273,
      2.06895
    ]
  }
}