{
  "type": "Feature",
  "properties": {
    "name": "Sucre",
    "country": "CO",
    "subdivision": "09",
    "timezone": "America/Bogota"
  },
  "geometry": {
    "type": "Point",
    "coordinates": [
      -76.92446,
      2.03805
    ]
  }
}