{
  "type": "Feature",
  "properties": {
    "name": "Villa Rica",
    "country": "CO",
    "subdivision": "09",
    "timezone": "America/Bogota"
  },
  "geometry": {
    "type": "Point",
    "coordinates": [
      -76.84939,
      2.5142
    ]
  }
}