{
  "type": "Feature",
  "properties": {
    "name": "Alsenz",
    "country": "DE",
    "subdivision": "08",
    "timezone": "Europe/Berlin"
  },
  "geometry": {
    "type": "Point",
    "coordinates": [
      7.81667,
      49.71667
    ]
  }
}