{
  "type": "Feature",
  "properties": {
    "name": "Annweiler am Trifels",
    "country": "DE",
    "subdivision": "08",
    "timezone": "Europe/Berlin"
  },
  "geometry": {
    "type": "Point",
    "coordinates": [
      7.97527,
      49.20613
    ]
  }
}