{
  "type": "Feature",
  "properties": {
    "name": "Ayl",
    "country": "DE",
    "subdivision": "08",
    "timezone": "Europe/Berlin"
  },
  "geometry": {
    "type": "Point",
    "coordinates": [
      6.55,
      49.63333
    ]
  }
}