{
  "type": "Feature",
  "properties": {
    "name": "Bad Neuenahr-Ahrweiler",
    "country": "DE",
    "subdivision": "08",
    "timezone": "Europe/Berlin"
  },
  "geometry": {
    "type": "Point",
    "coordinates": [
      7.1113,
      50.54322
    ]
  }
}