{
  "type": "Feature",
  "properties": {
    "name": "Billigheim-Ingenheim",
    "country": "DE",
    "subdivision": "08",
    "timezone": "Europe/Berlin"
  },
  "geometry": {
    "type": "Point",
    "coordinates": [
      8.09056,
      49.13667
    ]
  }
}