{
  "type": "Feature",
  "properties": {
    "name": "Bobenheim-Roxheim",
    "country": "DE",
    "subdivision": "08",
    "timezone": "Europe/Berlin"
  },
  "geometry": {
    "type": "Point",
    "coordinates": [
      8.35778,
      49.5875
    ]
  }
}