{
  "type": "Feature",
  "properties": {
    "name": "Bolanden",
    "country": "DE",
    "subdivision": "08",
    "timezone": "Europe/Berlin"
  },
  "geometry": {
    "type": "Point",
    "coordinates": [
      8.01194,
      49.63917
    ]
  }
}