{
  "type": "Feature",
  "properties": {
    "name": "Brohl-Lützing",
    "country": "DE",
    "subdivision": "08",
    "timezone": "Europe/Berlin"
  },
  "geometry": {
    "type": "Point",
    "coordinates": [
      7.32908,
      50.48296
    ]
  }
}