{
  "type": "Feature",
  "properties": {
    "name": "Bruttig-Fankel",
    "country": "DE",
    "subdivision": "08",
    "timezone": "Europe/Berlin"
  },
  "geometry": {
    "type": "Point",
    "coordinates": [
      7.23333,
      50.13333
    ]
  }
}