{
  "type": "Feature",
  "properties": {
    "name": "Busenberg",
    "country": "DE",
    "subdivision": "08",
    "timezone": "Europe/Berlin"
  },
  "geometry": {
    "type": "Point",
    "coordinates": [
      7.8293,
      49.13024
    ]
  }
}