{
  "type": "Feature",
  "properties": {
    "name": "Dahn",
    "country": "DE",
    "subdivision": "08",
    "timezone": "Europe/Berlin"
  },
  "geometry": {
    "type": "Point",
    "coordinates": [
      7.77843,
      49.15098
    ]
  }
}