{
  "type": "Feature",
  "properties": {
    "name": "Dellfeld",
    "country": "DE",
    "subdivision": "08",
    "timezone": "Europe/Berlin"
  },
  "geometry": {
    "type": "Point",
    "coordinates": [
      7.47399,
      49.23397
    ]
  }
}