{
  "type": "Feature",
  "properties": {
    "name": "Dernau",
    "country": "DE",
    "subdivision": "08",
    "timezone": "Europe/Berlin"
  },
  "geometry": {
    "type": "Point",
    "coordinates": [
      7.05,
      50.53333
    ]
  }
}