{
  "type": "Feature",
  "properties": {
    "name": "Dreis",
    "country": "DE",
    "subdivision": "08",
    "timezone": "Europe/Berlin"
  },
  "geometry": {
    "type": "Point",
    "coordinates": [
      6.81845,
      49.9409
    ]
  }
}