{
  "type": "Feature",
  "properties": {
    "name": "Enkirch",
    "country": "DE",
    "subdivision": "08",
    "timezone": "Europe/Berlin"
  },
  "geometry": {
    "type": "Point",
    "coordinates": [
      7.12997,
      49.98434
    ]
  }
}