{
  "type": "Feature",
  "properties": {
    "name": "Essenheim",
    "country": "DE",
    "subdivision": "08",
    "timezone": "Europe/Berlin"
  },
  "geometry": {
    "type": "Point",
    "coordinates": [
      8.15556,
      49.93056
    ]
  }
}