{
  "type": "Feature",
  "properties": {
    "name": "Fischbach",
    "country": "DE",
    "subdivision": "08",
    "timezone": "Europe/Berlin"
  },
  "geometry": {
    "type": "Point",
    "coordinates": [
      7.7116,
      49.08771
    ]
  }
}