{
  "type": "Feature",
  "properties": {
    "name": "Freudenburg",
    "country": "DE",
    "subdivision": "08",
    "timezone": "Europe/Berlin"
  },
  "geometry": {
    "type": "Point",
    "coordinates": [
      6.53292,
      49.54348
    ]
  }
}