{
  "type": "Feature",
  "properties": {
    "name": "Fußgönheim",
    "country": "DE",
    "subdivision": "08",
    "timezone": "Europe/Berlin"
  },
  "geometry": {
    "type": "Point",
    "coordinates": [
      8.29222,
      49.46111
    ]
  }
}