{
  "type": "Feature",
  "properties": {
    "name": "Gillenfeld",
    "country": "DE",
    "subdivision": "08",
    "timezone": "Europe/Berlin"
  },
  "geometry": {
    "type": "Point",
    "coordinates": [
      6.90383,
      50.1279
    ]
  }
}