{
  "type": "Feature",
  "properties": {
    "name": "Glan-Münchweiler",
    "country": "DE",
    "subdivision": "08",
    "timezone": "Europe/Berlin"
  },
  "geometry": {
    "type": "Point",
    "coordinates": [
      7.44204,
      49.47222
    ]
  }
}