{
  "type": "Feature",
  "properties": {
    "name": "Großniedesheim",
    "country": "DE",
    "subdivision": "08",
    "timezone": "Europe/Berlin"
  },
  "geometry": {
    "type": "Point",
    "coordinates": [
      8.31222,
      49.57528
    ]
  }
}