{
  "type": "Feature",
  "properties": {
    "name": "Guntersblum",
    "country": "DE",
    "subdivision": "08",
    "timezone": "Europe/Berlin"
  },
  "geometry": {
    "type": "Point",
    "coordinates": [
      8.34556,
      49.7975
    ]
  }
}