{
  "type": "Feature",
  "properties": {
    "name": "Hatzenbühl",
    "country": "DE",
    "subdivision": "08",
    "timezone": "Europe/Berlin"
  },
  "geometry": {
    "type": "Point",
    "coordinates": [
      8.24528,
      49.11111
    ]
  }
}