{
  "type": "Feature",
  "properties": {
    "name": "Heistenbach",
    "country": "DE",
    "subdivision": "08",
    "timezone": "Europe/Berlin"
  },
  "geometry": {
    "type": "Point",
    "coordinates": [
      7.98629,
      50.37933
    ]
  }
}