{
  "type": "Feature",
  "properties": {
    "name": "Hellenhahn-Schellenberg",
    "country": "DE",
    "subdivision": "08",
    "timezone": "Europe/Berlin"
  },
  "geometry": {
    "type": "Point",
    "coordinates": [
      8.02639,
      50.61278
    ]
  }
}