{
  "type": "Feature",
  "properties": {
    "name": "Hetzerath",
    "country": "DE",
    "subdivision": "08",
    "timezone": "Europe/Berlin"
  },
  "geometry": {
    "type": "Point",
    "coordinates": [
      6.81667,
      49.88333
    ]
  }
}