{
  "type": "Feature",
  "properties": {
    "name": "Heßheim",
    "country": "DE",
    "subdivision": "08",
    "timezone": "Europe/Berlin"
  },
  "geometry": {
    "type": "Point",
    "coordinates": [
      8.30778,
      49.54583
    ]
  }
}