{
  "type": "Feature",
  "properties": {
    "name": "Hochdorf-Assenheim",
    "country": "DE",
    "subdivision": "08",
    "timezone": "Europe/Berlin"
  },
  "geometry": {
    "type": "Point",
    "coordinates": [
      8.28167,
      49.41944
    ]
  }
}