{
  "type": "Feature",
  "properties": {
    "name": "Hundsangen",
    "country": "DE",
    "subdivision": "08",
    "timezone": "Europe/Berlin"
  },
  "geometry": {
    "type": "Point",
    "coordinates": [
      7.98333,
      50.45
    ]
  }
}