{
  "type": "Feature",
  "properties": {
    "name": "Jockgrim",
    "country": "DE",
    "subdivision": "08",
    "timezone": "Europe/Berlin"
  },
  "geometry": {
    "type": "Point",
    "coordinates": [
      8.27468,
      49.09288
    ]
  }
}