{
  "type": "Feature",
  "properties": {
    "name": "Kadenbach",
    "country": "DE",
    "subdivision": "08",
    "timezone": "Europe/Berlin"
  },
  "geometry": {
    "type": "Point",
    "coordinates": [
      7.73333,
      50.38333
    ]
  }
}