{
  "type": "Feature",
  "properties": {
    "name": "Kaiserslautern",
    "country": "DE",
    "subdivision": "08",
    "timezone": "Europe/Berlin"
  },
  "geometry": {
    "type": "Point",
    "coordinates": [
      7.77161,
      49.443
    ]
  }
}