{
  "type": "Feature",
  "properties": {
    "name": "Kasel",
    "country": "DE",
    "subdivision": "08",
    "timezone": "Europe/Berlin"
  },
  "geometry": {
    "type": "Point",
    "coordinates": [
      6.73222,
      49.7617
    ]
  }
}