{
  "type": "Feature",
  "properties": {
    "name": "Kirchberg",
    "country": "DE",
    "subdivision": "08",
    "timezone": "Europe/Berlin"
  },
  "geometry": {
    "type": "Point",
    "coordinates": [
      7.407,
      49.94395
    ]
  }
}