{
  "type": "Feature",
  "properties": {
    "name": "Kirchheim an der Weinstraße",
    "country": "DE",
    "subdivision": "08",
    "timezone": "Europe/Berlin"
  },
  "geometry": {
    "type": "Point",
    "coordinates": [
      8.18083,
      49.53722
    ]
  }
}