{
  "type": "Feature",
  "properties": {
    "name": "Kordel",
    "country": "DE",
    "subdivision": "08",
    "timezone": "Europe/Berlin"
  },
  "geometry": {
    "type": "Point",
    "coordinates": [
      6.63333,
      49.83333
    ]
  }
}