{
  "type": "Feature",
  "properties": {
    "name": "Limburgerhof",
    "country": "DE",
    "subdivision": "08",
    "timezone": "Europe/Berlin"
  },
  "geometry": {
    "type": "Point",
    "coordinates": [
      8.39194,
      49.42444
    ]
  }
}