{
  "type": "Feature",
  "properties": {
    "name": "Linden",
    "country": "DE",
    "subdivision": "08",
    "timezone": "Europe/Berlin"
  },
  "geometry": {
    "type": "Point",
    "coordinates": [
      7.65,
      49.35
    ]
  }
}