{
  "type": "Feature",
  "properties": {
    "name": "Maikammer",
    "country": "DE",
    "subdivision": "08",
    "timezone": "Europe/Berlin"
  },
  "geometry": {
    "type": "Point",
    "coordinates": [
      8.13167,
      49.30528
    ]
  }
}