{
  "type": "Feature",
  "properties": {
    "name": "Mainz",
    "country": "DE",
    "subdivision": "08",
    "timezone": "Europe/Berlin"
  },
  "geometry": {
    "type": "Point",
    "coordinates": [
      8.2791,
      49.98419
    ]
  }
}