{
  "type": "Feature",
  "properties": {
    "name": "Maxdorf",
    "country": "DE",
    "subdivision": "08",
    "timezone": "Europe/Berlin"
  },
  "geometry": {
    "type": "Point",
    "coordinates": [
      8.29167,
      49.48806
    ]
  }
}