{
  "type": "Feature",
  "properties": {
    "name": "Meddersheim",
    "country": "DE",
    "subdivision": "08",
    "timezone": "Europe/Berlin"
  },
  "geometry": {
    "type": "Point",
    "coordinates": [
      7.61708,
      49.77636
    ]
  }
}