{
  "type": "Feature",
  "properties": {
    "name": "Mehlbach",
    "country": "DE",
    "subdivision": "08",
    "timezone": "Europe/Berlin"
  },
  "geometry": {
    "type": "Point",
    "coordinates": [
      7.71667,
      49.51667
    ]
  }
}