{
  "type": "Feature",
  "properties": {
    "name": "Mehlingen",
    "country": "DE",
    "subdivision": "08",
    "timezone": "Europe/Berlin"
  },
  "geometry": {
    "type": "Point",
    "coordinates": [
      7.85467,
      49.49136
    ]
  }
}