{
  "type": "Feature",
  "properties": {
    "name": "Meisenheim",
    "country": "DE",
    "subdivision": "08",
    "timezone": "Europe/Berlin"
  },
  "geometry": {
    "type": "Point",
    "coordinates": [
      7.66765,
      49.70721
    ]
  }
}