{
  "type": "Feature",
  "properties": {
    "name": "Melsbach",
    "country": "DE",
    "subdivision": "08",
    "timezone": "Europe/Berlin"
  },
  "geometry": {
    "type": "Point",
    "coordinates": [
      7.48333,
      50.48333
    ]
  }
}