{
  "type": "Feature",
  "properties": {
    "name": "Miehlen",
    "country": "DE",
    "subdivision": "08",
    "timezone": "Europe/Berlin"
  },
  "geometry": {
    "type": "Point",
    "coordinates": [
      7.83196,
      50.22574
    ]
  }
}