{
  "type": "Feature",
  "properties": {
    "name": "Montabaur",
    "country": "DE",
    "subdivision": "08",
    "timezone": "Europe/Berlin"
  },
  "geometry": {
    "type": "Point",
    "coordinates": [
      7.8232,
      50.43588
    ]
  }
}