{
  "type": "Feature",
  "properties": {
    "name": "Mudersbach",
    "country": "DE",
    "subdivision": "08",
    "timezone": "Europe/Berlin"
  },
  "geometry": {
    "type": "Point",
    "coordinates": [
      7.94347,
      50.82515
    ]
  }
}