{
  "type": "Feature",
  "properties": {
    "name": "Nanzdietschweiler",
    "country": "DE",
    "subdivision": "08",
    "timezone": "Europe/Berlin"
  },
  "geometry": {
    "type": "Point",
    "coordinates": [
      7.45,
      49.45
    ]
  }
}