{
  "type": "Feature",
  "properties": {
    "name": "Nentershausen",
    "country": "DE",
    "subdivision": "08",
    "timezone": "Europe/Berlin"
  },
  "geometry": {
    "type": "Point",
    "coordinates": [
      7.93333,
      50.41667
    ]
  }
}