{
  "type": "Feature",
  "properties": {
    "name": "Niederdreisbach",
    "country": "DE",
    "subdivision": "08",
    "timezone": "Europe/Berlin"
  },
  "geometry": {
    "type": "Point",
    "coordinates": [
      7.92352,
      50.74955
    ]
  }
}