{
  "type": "Feature",
  "properties": {
    "name": "Ober-Flörsheim",
    "country": "DE",
    "subdivision": "08",
    "timezone": "Europe/Berlin"
  },
  "geometry": {
    "type": "Point",
    "coordinates": [
      8.15528,
      49.68306
    ]
  }
}