{
  "type": "Feature",
  "properties": {
    "name": "Oberotterbach",
    "country": "DE",
    "subdivision": "08",
    "timezone": "Europe/Berlin"
  },
  "geometry": {
    "type": "Point",
    "coordinates": [
      7.96955,
      49.07044
    ]
  }
}