{
  "type": "Feature",
  "properties": {
    "name": "Odernheim",
    "country": "DE",
    "subdivision": "08",
    "timezone": "Europe/Berlin"
  },
  "geometry": {
    "type": "Point",
    "coordinates": [
      7.70427,
      49.76511
    ]
  }
}