{
  "type": "Feature",
  "properties": {
    "name": "Olsbrücken",
    "country": "DE",
    "subdivision": "08",
    "timezone": "Europe/Berlin"
  },
  "geometry": {
    "type": "Point",
    "coordinates": [
      7.65857,
      49.53884
    ]
  }
}