{
  "type": "Feature",
  "properties": {
    "name": "Otterbach",
    "country": "DE",
    "subdivision": "08",
    "timezone": "Europe/Berlin"
  },
  "geometry": {
    "type": "Point",
    "coordinates": [
      7.7345,
      49.48554
    ]
  }
}