{
  "type": "Feature",
  "properties": {
    "name": "Partenheim",
    "country": "DE",
    "subdivision": "08",
    "timezone": "Europe/Berlin"
  },
  "geometry": {
    "type": "Point",
    "coordinates": [
      8.08222,
      49.88389
    ]
  }
}