{
  "type": "Feature",
  "properties": {
    "name": "Pelm",
    "country": "DE",
    "subdivision": "08",
    "timezone": "Europe/Berlin"
  },
  "geometry": {
    "type": "Point",
    "coordinates": [
      6.69076,
      50.23188
    ]
  }
}