{
  "type": "Feature",
  "properties": {
    "name": "Pracht",
    "country": "DE",
    "subdivision": "08",
    "timezone": "Europe/Berlin"
  },
  "geometry": {
    "type": "Point",
    "coordinates": [
      7.64871,
      50.76031
    ]
  }
}