{
  "type": "Feature",
  "properties": {
    "name": "Queidersbach",
    "country": "DE",
    "subdivision": "08",
    "timezone": "Europe/Berlin"
  },
  "geometry": {
    "type": "Point",
    "coordinates": [
      7.63333,
      49.36667
    ]
  }
}