{
  "type": "Feature",
  "properties": {
    "name": "Ramberg",
    "country": "DE",
    "subdivision": "08",
    "timezone": "Europe/Berlin"
  },
  "geometry": {
    "type": "Point",
    "coordinates": [
      8.00833,
      49.26028
    ]
  }
}