{
  "type": "Feature",
  "properties": {
    "name": "Rennerod",
    "country": "DE",
    "subdivision": "08",
    "timezone": "Europe/Berlin"
  },
  "geometry": {
    "type": "Point",
    "coordinates": [
      8.06697,
      50.6082
    ]
  }
}