{
  "type": "Feature",
  "properties": {
    "name": "Rheinböllen",
    "country": "DE",
    "subdivision": "08",
    "timezone": "Europe/Berlin"
  },
  "geometry": {
    "type": "Point",
    "coordinates": [
      7.67249,
      50.01127
    ]
  }
}