{
  "type": "Feature",
  "properties": {
    "name": "Rockenhausen",
    "country": "DE",
    "subdivision": "08",
    "timezone": "Europe/Berlin"
  },
  "geometry": {
    "type": "Point",
    "coordinates": [
      7.82134,
      49.62974
    ]
  }
}