{
  "type": "Feature",
  "properties": {
    "name": "Rodalben",
    "country": "DE",
    "subdivision": "08",
    "timezone": "Europe/Berlin"
  },
  "geometry": {
    "type": "Point",
    "coordinates": [
      7.63962,
      49.2394
    ]
  }
}