{
  "type": "Feature",
  "properties": {
    "name": "Ruppertsweiler",
    "country": "DE",
    "subdivision": "08",
    "timezone": "Europe/Berlin"
  },
  "geometry": {
    "type": "Point",
    "coordinates": [
      7.68957,
      49.19707
    ]
  }
}