{
  "type": "Feature",
  "properties": {
    "name": "Schornsheim",
    "country": "DE",
    "subdivision": "08",
    "timezone": "Europe/Berlin"
  },
  "geometry": {
    "type": "Point",
    "coordinates": [
      8.175,
      49.84583
    ]
  }
}