{
  "type": "Feature",
  "properties": {
    "name": "Schönenberg-Kübelberg",
    "country": "DE",
    "subdivision": "08",
    "timezone": "Europe/Berlin"
  },
  "geometry": {
    "type": "Point",
    "coordinates": [
      7.37233,
      49.4074
    ]
  }
}