{
  "type": "Feature",
  "properties": {
    "name": "Schweigen-Rechtenbach",
    "country": "DE",
    "subdivision": "08",
    "timezone": "Europe/Berlin"
  },
  "geometry": {
    "type": "Point",
    "coordinates": [
      7.95638,
      49.05314
    ]
  }
}