{
  "type": "Feature",
  "properties": {
    "name": "Siershahn",
    "country": "DE",
    "subdivision": "08",
    "timezone": "Europe/Berlin"
  },
  "geometry": {
    "type": "Point",
    "coordinates": [
      7.77972,
      50.48639
    ]
  }
}