{
  "type": "Feature",
  "properties": {
    "name": "Singhofen",
    "country": "DE",
    "subdivision": "08",
    "timezone": "Europe/Berlin"
  },
  "geometry": {
    "type": "Point",
    "coordinates": [
      7.83333,
      50.2744
    ]
  }
}