{
  "type": "Feature",
  "properties": {
    "name": "Stadtkyll",
    "country": "DE",
    "subdivision": "08",
    "timezone": "Europe/Berlin"
  },
  "geometry": {
    "type": "Point",
    "coordinates": [
      6.53333,
      50.35
    ]
  }
}