{
  "type": "Feature",
  "properties": {
    "name": "Steinfeld",
    "country": "DE",
    "subdivision": "08",
    "timezone": "Europe/Berlin"
  },
  "geometry": {
    "type": "Point",
    "coordinates": [
      8.03694,
      49.04833
    ]
  }
}