{
  "type": "Feature",
  "properties": {
    "name": "Unnau",
    "country": "DE",
    "subdivision": "08",
    "timezone": "Europe/Berlin"
  },
  "geometry": {
    "type": "Point",
    "coordinates": [
      7.90827,
      50.64881
    ]
  }
}