{
  "type": "Feature",
  "properties": {
    "name": "Vallendar",
    "country": "DE",
    "subdivision": "08",
    "timezone": "Europe/Berlin"
  },
  "geometry": {
    "type": "Point",
    "coordinates": [
      7.62427,
      50.39586
    ]
  }
}