{
  "type": "Feature",
  "properties": {
    "name": "Wasserliesch",
    "country": "DE",
    "subdivision": "08",
    "timezone": "Europe/Berlin"
  },
  "geometry": {
    "type": "Point",
    "coordinates": [
      6.53944,
      49.70739
    ]
  }
}