{
  "type": "Feature",
  "properties": {
    "name": "Wattenheim",
    "country": "DE",
    "subdivision": "08",
    "timezone": "Europe/Berlin"
  },
  "geometry": {
    "type": "Point",
    "coordinates": [
      8.06167,
      49.52167
    ]
  }
}