{
  "type": "Feature",
  "properties": {
    "name": "Waxweiler",
    "country": "DE",
    "subdivision": "08",
    "timezone": "Europe/Berlin"
  },
  "geometry": {
    "type": "Point",
    "coordinates": [
      6.36299,
      50.09257
    ]
  }
}