{
  "type": "Feature",
  "properties": {
    "name": "Wehr",
    "country": "DE",
    "subdivision": "08",
    "timezone": "Europe/Berlin"
  },
  "geometry": {
    "type": "Point",
    "coordinates": [
      7.21667,
      50.41667
    ]
  }
}