{
  "type": "Feature",
  "properties": {
    "name": "Weibern",
    "country": "DE",
    "subdivision": "08",
    "timezone": "Europe/Berlin"
  },
  "geometry": {
    "type": "Point",
    "coordinates": [
      7.14669,
      50.40808
    ]
  }
}