{
  "type": "Feature",
  "properties": {
    "name": "Weitefeld",
    "country": "DE",
    "subdivision": "08",
    "timezone": "Europe/Berlin"
  },
  "geometry": {
    "type": "Point",
    "coordinates": [
      7.92805,
      50.72541
    ]
  }
}