{
  "type": "Feature",
  "properties": {
    "name": "Welschbillig",
    "country": "DE",
    "subdivision": "08",
    "timezone": "Europe/Berlin"
  },
  "geometry": {
    "type": "Point",
    "coordinates": [
      6.56667,
      49.85
    ]
  }
}