{
  "type": "Feature",
  "properties": {
    "name": "Westerburg",
    "country": "DE",
    "subdivision": "08",
    "timezone": "Europe/Berlin"
  },
  "geometry": {
    "type": "Point",
    "coordinates": [
      7.97482,
      50.55938
    ]
  }
}