{
  "type": "Feature",
  "properties": {
    "name": "Wilgartswiesen",
    "country": "DE",
    "subdivision": "08",
    "timezone": "Europe/Berlin"
  },
  "geometry": {
    "type": "Point",
    "coordinates": [
      7.87346,
      49.20891
    ]
  }
}