{
  "type": "Feature",
  "properties": {
    "name": "Winnweiler",
    "country": "DE",
    "subdivision": "08",
    "timezone": "Europe/Berlin"
  },
  "geometry": {
    "type": "Point",
    "coordinates": [
      7.85,
      49.56667
    ]
  }
}