{
  "type": "Feature",
  "properties": {
    "name": "Wöllstein",
    "country": "DE",
    "subdivision": "08",
    "timezone": "Europe/Berlin"
  },
  "geometry": {
    "type": "Point",
    "coordinates": [
      7.96667,
      49.81667
    ]
  }
}