{
  "type": "Feature",
  "properties": {
    "name": "Kinango",
    "country": "KE",
    "subdivision": "28",
    "timezone": "Africa/Nairobi"
  },
  "geometry": {
    "type": "Point",
    "coordinates": [
      39.31528,
      -4.13723
    ]
  }
}