{
  "type": "Feature",
  "properties": {
    "name": "Coşeiu",
    "country": "RO",
    "subdivision": "31",
    "timezone": "Europe/Bucharest"
  },
  "geometry": {
    "type": "Point",
    "coordinates": [
      22.98333,
      47.31667
    ]
  }
}