{
  "type": "Feature",
  "properties": {
    "name": "Fildu de Jos",
    "country": "RO",
    "subdivision": "31",
    "timezone": "Europe/Bucharest"
  },
  "geometry": {
    "type": "Point",
    "coordinates": [
      23.06667,
      46.93333
    ]
  }
}