{
  "type": "Feature",
  "properties": {
    "name": "Strážske",
    "country": "SK",
    "subdivision": "03",
    "timezone": "Europe/Bratislava"
  },
  "geometry": {
    "type": "Point",
    "coordinates": [
      21.83668,
      48.8735
    ]
  }
}