{
  "type": "Feature",
  "properties": {
    "name": "İkizce",
    "country": "TR",
    "subdivision": "52",
    "timezone": "Europe/Istanbul"
  },
  "geometry": {
    "type": "Point",
    "coordinates": [
      37.08028,
      41.05833
    ]
  }
}