{
  "type": "Feature",
  "properties": {
    "name": "Neustadt",
    "country": "DE",
    "subdivision": "04",
    "timezone": "Europe/Berlin"
  },
  "geometry": {
    "type": "Point",
    "coordinates": [
      9.98558,
      53.55196
    ]
  }
}