{
  "type": "Feature",
  "properties": {
    "name": "Saḩāb",
    "country": "JO",
    "subdivision": "16",
    "timezone": "Asia/Amman"
  },
  "geometry": {
    "type": "Point",
    "coordinates": [
      36.00479,
      31.87032
    ]
  }
}