{
  "type": "Feature",
  "properties": {
    "name": "Andrăşeşti",
    "country": "RO",
    "subdivision": "22",
    "timezone": "Europe/Bucharest"
  },
  "geometry": {
    "type": "Point",
    "coordinates": [
      27.13333,
      44.56667
    ]
  }
}