{
  "type": "Feature",
  "properties": {
    "name": "Armăşeşti",
    "country": "RO",
    "subdivision": "22",
    "timezone": "Europe/Bucharest"
  },
  "geometry": {
    "type": "Point",
    "coordinates": [
      26.58333,
      44.75
    ]
  }
}