{
  "type": "Feature",
  "properties": {
    "name": "Bărcăneşti",
    "country": "RO",
    "subdivision": "22",
    "timezone": "Europe/Bucharest"
  },
  "geometry": {
    "type": "Point",
    "coordinates": [
      26.65,
      44.63333
    ]
  }
}