{
  "type": "Feature",
  "properties": {
    "name": "Colelia",
    "country": "RO",
    "subdivision": "22",
    "timezone": "Europe/Bucharest"
  },
  "geometry": {
    "type": "Point",
    "coordinates": [
      27.00693,
      44.76112
    ]
  }
}