{
  "type": "Feature",
  "properties": {
    "name": "Vlădeni",
    "country": "RO",
    "subdivision": "22",
    "timezone": "Europe/Bucharest"
  },
  "geometry": {
    "type": "Point",
    "coordinates": [
      27.88333,
      44.61667
    ]
  }
}