{
  "type": "Feature",
  "properties": {
    "name": "Embi",
    "country": "KZ",
    "subdivision": "04",
    "timezone": "Asia/Aqtobe"
  },
  "geometry": {
    "type": "Point",
    "coordinates": [
      58.15042,
      48.82981
    ]
  }
}