{
  "type": "Feature",
  "properties": {
    "name": "Temir",
    "country": "KZ",
    "subdivision": "04",
    "timezone": "Asia/Aqtobe"
  },
  "geometry": {
    "type": "Point",
    "coordinates": [
      57.12855,
      49.14132
    ]
  }
}