{
  "type": "Feature",
  "properties": {
    "name": "Binzhou",
    "country": "CN",
    "subdivision": "25",
    "timezone": "Asia/Shanghai"
  },
  "geometry": {
    "type": "Point",
    "coordinates": [
      118.01667,
      37.36667
    ]
  }
}