{
  "type": "Feature",
  "properties": {
    "name": "Dengzhou",
    "country": "CN",
    "subdivision": "25",
    "timezone": "Asia/Shanghai"
  },
  "geometry": {
    "type": "Point",
    "coordinates": [
      120.75908,
      37.80822
    ]
  }
}