{
  "type": "Feature",
  "properties": {
    "name": "Feicheng",
    "country": "CN",
    "subdivision": "25",
    "timezone": "Asia/Shanghai"
  },
  "geometry": {
    "type": "Point",
    "coordinates": [
      116.76583,
      36.24861
    ]
  }
}