{
  "type": "Feature",
  "properties": {
    "name": "Jiamaying",
    "country": "CN",
    "subdivision": "25",
    "timezone": "Asia/Shanghai"
  },
  "geometry": {
    "type": "Point",
    "coordinates": [
      115.95,
      37.20806
    ]
  }
}