{
  "type": "Feature",
  "properties": {
    "name": "Laixi",
    "country": "CN",
    "subdivision": "25",
    "timezone": "Asia/Shanghai"
  },
  "geometry": {
    "type": "Point",
    "coordinates": [
      120.52694,
      36.85917
    ]
  }
}