{
  "type": "Feature",
  "properties": {
    "name": "Qingdao",
    "country": "CN",
    "subdivision": "25",
    "timezone": "Asia/Shanghai"
  },
  "geometry": {
    "type": "Point",
    "coordinates": [
      120.38042,
      36.06488
    ]
  }
}