{
  "type": "Feature",
  "properties": {
    "name": "Qingnian",
    "country": "CN",
    "subdivision": "25",
    "timezone": "Asia/Shanghai"
  },
  "geometry": {
    "type": "Point",
    "coordinates": [
      115.71183,
      36.84032
    ]
  }
}