{
  "type": "Feature",
  "properties": {
    "name": "Yantai",
    "country": "CN",
    "subdivision": "25",
    "timezone": "Asia/Shanghai"
  },
  "geometry": {
    "type": "Point",
    "coordinates": [
      121.44081,
      37.47649
    ]
  }
}