{
  "type": "Feature",
  "properties": {
    "name": "Yinzhu",
    "country": "CN",
    "subdivision": "25",
    "timezone": "Asia/Shanghai"
  },
  "geometry": {
    "type": "Point",
    "coordinates": [
      119.97528,
      35.87861
    ]
  }
}