{
  "type": "Feature",
  "properties": {
    "name": "Zhoucun",
    "country": "CN",
    "subdivision": "25",
    "timezone": "Asia/Shanghai"
  },
  "geometry": {
    "type": "Point",
    "coordinates": [
      117.81667,
      36.81667
    ]
  }
}