{
  "type": "Feature",
  "properties": {
    "name": "Cireșoaia",
    "country": "RO",
    "subdivision": "06",
    "timezone": "Europe/Bucharest"
  },
  "geometry": {
    "type": "Point",
    "coordinates": [
      24.06217,
      47.14265
    ]
  }
}