{
  "type": "Feature",
  "properties": {
    "name": "Lunca Leșului",
    "country": "RO",
    "subdivision": "06",
    "timezone": "Europe/Bucharest"
  },
  "geometry": {
    "type": "Point",
    "coordinates": [
      24.77602,
      47.30943
    ]
  }
}