{
  "type": "Feature",
  "properties": {
    "name": "Mărişelu",
    "country": "RO",
    "subdivision": "06",
    "timezone": "Europe/Bucharest"
  },
  "geometry": {
    "type": "Point",
    "coordinates": [
      24.51667,
      47.01667
    ]
  }
}