{
  "type": "Feature",
  "properties": {
    "name": "Matei",
    "country": "RO",
    "subdivision": "06",
    "timezone": "Europe/Bucharest"
  },
  "geometry": {
    "type": "Point",
    "coordinates": [
      24.26667,
      46.98333
    ]
  }
}