{
  "type": "Feature",
  "properties": {
    "name": "Petriș",
    "country": "RO",
    "subdivision": "06",
    "timezone": "Europe/Bucharest"
  },
  "geometry": {
    "type": "Point",
    "coordinates": [
      24.62314,
      47.10301
    ]
  }
}