{
  "type": "Feature",
  "properties": {
    "name": "Telcișor",
    "country": "RO",
    "subdivision": "06",
    "timezone": "Europe/Bucharest"
  },
  "geometry": {
    "type": "Point",
    "coordinates": [
      24.45158,
      47.46
    ]
  }
}