{
  "type": "Feature",
  "properties": {
    "name": "Valea Borcutului",
    "country": "RO",
    "subdivision": "06",
    "timezone": "Europe/Bucharest"
  },
  "geometry": {
    "type": "Point",
    "coordinates": [
      24.65293,
      47.37483
    ]
  }
}