{
  "type": "Feature",
  "properties": {
    "name": "Aban",
    "country": "RU",
    "subdivision": "91",
    "timezone": "Asia/Krasnoyarsk"
  },
  "geometry": {
    "type": "Point",
    "coordinates": [
      96.0658,
      56.6787
    ]
  }
}