{
  "type": "Feature",
  "properties": {
    "name": "Krasnoyarsk",
    "country": "RU",
    "subdivision": "91",
    "timezone": "Asia/Krasnoyarsk"
  },
  "geometry": {
    "type": "Point",
    "coordinates": [
      92.86717,
      56.01839
    ]
  }
}