{
  "type": "Feature",
  "properties": {
    "name": "Uyar",
    "country": "RU",
    "subdivision": "91",
    "timezone": "Asia/Krasnoyarsk"
  },
  "geometry": {
    "type": "Point",
    "coordinates": [
      94.3247,
      55.8118
    ]
  }
}