{
  "type": "Feature",
  "properties": {
    "name": "Yemel’yanovo",
    "country": "RU",
    "subdivision": "91",
    "timezone": "Asia/Krasnoyarsk"
  },
  "geometry": {
    "type": "Point",
    "coordinates": [
      92.67539,
      56.16776
    ]
  }
}