{
  "type": "Feature",
  "properties": {
    "name": "Yermakovskoye",
    "country": "RU",
    "subdivision": "91",
    "timezone": "Asia/Krasnoyarsk"
  },
  "geometry": {
    "type": "Point",
    "coordinates": [
      92.40021,
      53.27545
    ]
  }
}