{
  "type": "Feature",
  "properties": {
    "name": "Zheleznogorsk",
    "country": "RU",
    "subdivision": "91",
    "timezone": "Asia/Krasnoyarsk"
  },
  "geometry": {
    "type": "Point",
    "coordinates": [
      93.53194,
      56.25111
    ]
  }
}