{
  "type": "Feature",
  "properties": {
    "name": "Al Ḩayy",
    "country": "IQ",
    "subdivision": "16",
    "timezone": "Asia/Baghdad"
  },
  "geometry": {
    "type": "Point",
    "coordinates": [
      46.04345,
      32.17419
    ]
  }
}