{
  "type": "Feature",
  "properties": {
    "name": "Al ‘Azīzīyah",
    "country": "IQ",
    "subdivision": "16",
    "timezone": "Asia/Baghdad"
  },
  "geometry": {
    "type": "Point",
    "coordinates": [
      45.06359,
      32.90941
    ]
  }
}