{
  "type": "Feature",
  "properties": {
    "name": "Alotenango",
    "country": "GT",
    "subdivision": "16",
    "timezone": "America/Guatemala"
  },
  "geometry": {
    "type": "Point",
    "coordinates": [
      -90.80437,
      14.48585
    ]
  }
}