{
  "type": "Feature",
  "properties": {
    "name": "San Miguel Dueñas",
    "country": "GT",
    "subdivision": "16",
    "timezone": "America/Guatemala"
  },
  "geometry": {
    "type": "Point",
    "coordinates": [
      -90.79938,
      14.52241
    ]
  }
}