{
  "type": "Feature",
  "properties": {
    "name": "Aardenburg",
    "country": "NL",
    "subdivision": "10",
    "timezone": "Europe/Amsterdam"
  },
  "geometry": {
    "type": "Point",
    "coordinates": [
      3.44722,
      51.27333
    ]
  }
}