{
  "type": "Feature",
  "properties": {
    "name": "Arnemuiden",
    "country": "NL",
    "subdivision": "10",
    "timezone": "Europe/Amsterdam"
  },
  "geometry": {
    "type": "Point",
    "coordinates": [
      3.675,
      51.50167
    ]
  }
}