{
  "type": "Feature",
  "properties": {
    "name": "Haamstede",
    "country": "NL",
    "subdivision": "10",
    "timezone": "Europe/Amsterdam"
  },
  "geometry": {
    "type": "Point",
    "coordinates": [
      3.74299,
      51.69682
    ]
  }
}