{
  "type": "Feature",
  "properties": {
    "name": "Meliskerke",
    "country": "NL",
    "subdivision": "10",
    "timezone": "Europe/Amsterdam"
  },
  "geometry": {
    "type": "Point",
    "coordinates": [
      3.50972,
      51.51417
    ]
  }
}