{
  "type": "Feature",
  "properties": {
    "name": "Othene",
    "country": "NL",
    "subdivision": "10",
    "timezone": "Europe/Amsterdam"
  },
  "geometry": {
    "type": "Point",
    "coordinates": [
      3.85972,
      51.33083
    ]
  }
}