{
  "type": "Feature",
  "properties": {
    "name": "Renesse",
    "country": "NL",
    "subdivision": "10",
    "timezone": "Europe/Amsterdam"
  },
  "geometry": {
    "type": "Point",
    "coordinates": [
      3.775,
      51.7325
    ]
  }
}