{
  "type": "Feature",
  "properties": {
    "name": "Scherpenisse",
    "country": "NL",
    "subdivision": "10",
    "timezone": "Europe/Amsterdam"
  },
  "geometry": {
    "type": "Point",
    "coordinates": [
      4.10556,
      51.54667
    ]
  }
}