{
  "type": "Feature",
  "properties": {
    "name": "Stavenisse",
    "country": "NL",
    "subdivision": "10",
    "timezone": "Europe/Amsterdam"
  },
  "geometry": {
    "type": "Point",
    "coordinates": [
      4.0125,
      51.5875
    ]
  }
}