{
  "type": "Feature",
  "properties": {
    "name": "Vlissingen",
    "country": "NL",
    "subdivision": "10",
    "timezone": "Europe/Amsterdam"
  },
  "geometry": {
    "type": "Point",
    "coordinates": [
      3.57361,
      51.4425
    ]
  }
}