{
  "type": "Feature",
  "properties": {
    "name": "Wemeldinge",
    "country": "NL",
    "subdivision": "10",
    "timezone": "Europe/Amsterdam"
  },
  "geometry": {
    "type": "Point",
    "coordinates": [
      3.99722,
      51.51833
    ]
  }
}