{
  "type": "Feature",
  "properties": {
    "name": "Wissenkerke",
    "country": "NL",
    "subdivision": "10",
    "timezone": "Europe/Amsterdam"
  },
  "geometry": {
    "type": "Point",
    "coordinates": [
      3.74722,
      51.585
    ]
  }
}