{
  "type": "Feature",
  "properties": {
    "name": "Konyshevka",
    "country": "RU",
    "subdivision": "41",
    "timezone": "Europe/Moscow"
  },
  "geometry": {
    "type": "Point",
    "coordinates": [
      35.2941,
      51.8418
    ]
  }
}