{
  "type": "Feature",
  "properties": {
    "name": "Kursk",
    "country": "RU",
    "subdivision": "41",
    "timezone": "Europe/Moscow"
  },
  "geometry": {
    "type": "Point",
    "coordinates": [
      36.18735,
      51.73733
    ]
  }
}