{
  "type": "Feature",
  "properties": {
    "name": "Pryamitsyno",
    "country": "RU",
    "subdivision": "41",
    "timezone": "Europe/Moscow"
  },
  "geometry": {
    "type": "Point",
    "coordinates": [
      35.9314,
      51.6561
    ]
  }
}