{
  "type": "Feature",
  "properties": {
    "name": "Solntsevo",
    "country": "RU",
    "subdivision": "41",
    "timezone": "Europe/Moscow"
  },
  "geometry": {
    "type": "Point",
    "coordinates": [
      36.7499,
      51.41853
    ]
  }
}