{
  "type": "Feature",
  "properties": {
    "name": "Aguas Claras",
    "country": "PR",
    "subdivision": "037",
    "timezone": "America/Puerto_Rico"
  },
  "geometry": {
    "type": "Point",
    "coordinates": [
      -65.6535,
      18.25273
    ]
  }
}