{
  "type": "Feature",
  "properties": {
    "name": "Machala",
    "country": "EC",
    "subdivision": "08",
    "timezone": "America/Guayaquil"
  },
  "geometry": {
    "type": "Point",
    "coordinates": [
      -79.96053,
      -3.25861
    ]
  }
}