{
  "type": "Feature",
  "properties": {
    "name": "Puerto Bolívar",
    "country": "EC",
    "subdivision": "08",
    "timezone": "America/Guayaquil"
  },
  "geometry": {
    "type": "Point",
    "coordinates": [
      -79.99749,
      -3.26649
    ]
  }
}