{
  "type": "Feature",
  "properties": {
    "name": "Ahualulco de Mercado",
    "country": "MX",
    "subdivision": "14",
    "timezone": "America/Mexico_City"
  },
  "geometry": {
    "type": "Point",
    "coordinates": [
      -103.97461,
      20.70137
    ]
  }
}