{
  "type": "Feature",
  "properties": {
    "name": "Amacueca",
    "country": "MX",
    "subdivision": "14",
    "timezone": "America/Mexico_City"
  },
  "geometry": {
    "type": "Point",
    "coordinates": [
      -103.59983,
      20.01069
    ]
  }
}