{
  "type": "Feature",
  "properties": {
    "name": "Atotonilco el Bajo",
    "country": "MX",
    "subdivision": "14",
    "timezone": "America/Mexico_City"
  },
  "geometry": {
    "type": "Point",
    "coordinates": [
      -103.67455,
      20.35151
    ]
  }
}