{
  "type": "Feature",
  "properties": {
    "name": "Barra de Navidad",
    "country": "MX",
    "subdivision": "14",
    "timezone": "America/Mexico_City"
  },
  "geometry": {
    "type": "Point",
    "coordinates": [
      -104.68228,
      19.20715
    ]
  }
}