{
  "type": "Feature",
  "properties": {
    "name": "Bellavista",
    "country": "MX",
    "subdivision": "14",
    "timezone": "America/Mexico_City"
  },
  "geometry": {
    "type": "Point",
    "coordinates": [
      -103.63742,
      20.43408
    ]
  }
}