{
  "type": "Feature",
  "properties": {
    "name": "Betania",
    "country": "MX",
    "subdivision": "14",
    "timezone": "America/Mexico_City"
  },
  "geometry": {
    "type": "Point",
    "coordinates": [
      -102.37914,
      20.58199
    ]
  }
}