{
  "type": "Feature",
  "properties": {
    "name": "Chacala",
    "country": "MX",
    "subdivision": "14",
    "timezone": "America/Mexico_City"
  },
  "geometry": {
    "type": "Point",
    "coordinates": [
      -104.28313,
      19.32741
    ]
  }
}