{
  "type": "Feature",
  "properties": {
    "name": "Ciudad Guzmán",
    "country": "MX",
    "subdivision": "14",
    "timezone": "America/Mexico_City"
  },
  "geometry": {
    "type": "Point",
    "coordinates": [
      -103.4617,
      19.70466
    ]
  }
}