{
  "type": "Feature",
  "properties": {
    "name": "Degollado",
    "country": "MX",
    "subdivision": "14",
    "timezone": "America/Mexico_City"
  },
  "geometry": {
    "type": "Point",
    "coordinates": [
      -102.14976,
      20.46702
    ]
  }
}