{
  "type": "Feature",
  "properties": {
    "name": "El Mentidero",
    "country": "MX",
    "subdivision": "14",
    "timezone": "America/Mexico_City"
  },
  "geometry": {
    "type": "Point",
    "coordinates": [
      -104.29313,
      19.7707
    ]
  }
}