{
  "type": "Feature",
  "properties": {
    "name": "El Plan",
    "country": "MX",
    "subdivision": "14",
    "timezone": "America/Mexico_City"
  },
  "geometry": {
    "type": "Point",
    "coordinates": [
      -103.60667,
      20.41836
    ]
  }
}