{
  "type": "Feature",
  "properties": {
    "name": "El Salvador",
    "country": "MX",
    "subdivision": "14",
    "timezone": "America/Mexico_City"
  },
  "geometry": {
    "type": "Point",
    "coordinates": [
      -103.71568,
      21.01659
    ]
  }
}