{
  "type": "Feature",
  "properties": {
    "name": "El Zapote",
    "country": "MX",
    "subdivision": "14",
    "timezone": "America/Mexico_City"
  },
  "geometry": {
    "type": "Point",
    "coordinates": [
      -102.80555,
      21.11257
    ]
  }
}