{
  "type": "Feature",
  "properties": {
    "name": "Emiliano Zapata",
    "country": "MX",
    "subdivision": "14",
    "timezone": "America/Mexico_City"
  },
  "geometry": {
    "type": "Point",
    "coordinates": [
      -104.96526,
      19.38595
    ]
  }
}