{
  "type": "Feature",
  "properties": {
    "name": "Huáscato",
    "country": "MX",
    "subdivision": "14",
    "timezone": "America/Mexico_City"
  },
  "geometry": {
    "type": "Point",
    "coordinates": [
      -102.24806,
      20.47951
    ]
  }
}