{
  "type": "Feature",
  "properties": {
    "name": "Huejuquilla el Alto",
    "country": "MX",
    "subdivision": "14",
    "timezone": "America/Mexico_City"
  },
  "geometry": {
    "type": "Point",
    "coordinates": [
      -103.89777,
      22.62547
    ]
  }
}