{
  "type": "Feature",
  "properties": {
    "name": "Jaluco",
    "country": "MX",
    "subdivision": "14",
    "timezone": "America/Mexico_City"
  },
  "geometry": {
    "type": "Point",
    "coordinates": [
      -104.68451,
      19.23041
    ]
  }
}