{
  "type": "Feature",
  "properties": {
    "name": "Juanacatlán",
    "country": "MX",
    "subdivision": "14",
    "timezone": "America/Mexico_City"
  },
  "geometry": {
    "type": "Point",
    "coordinates": [
      -103.17025,
      20.50888
    ]
  }
}