{
  "type": "Feature",
  "properties": {
    "name": "La Barca",
    "country": "MX",
    "subdivision": "14",
    "timezone": "America/Mexico_City"
  },
  "geometry": {
    "type": "Point",
    "coordinates": [
      -102.54514,
      20.28784
    ]
  }
}