{
  "type": "Feature",
  "properties": {
    "name": "La Concepción",
    "country": "MX",
    "subdivision": "14",
    "timezone": "America/Mexico_City"
  },
  "geometry": {
    "type": "Point",
    "coordinates": [
      -102.32959,
      20.35171
    ]
  }
}