{
  "type": "Feature",
  "properties": {
    "name": "La Paz de Ordaz",
    "country": "MX",
    "subdivision": "14",
    "timezone": "America/Mexico_City"
  },
  "geometry": {
    "type": "Point",
    "coordinates": [
      -102.53059,
      20.34489
    ]
  }
}