{
  "type": "Feature",
  "properties": {
    "name": "La Primavera",
    "country": "MX",
    "subdivision": "14",
    "timezone": "America/Mexico_City"
  },
  "geometry": {
    "type": "Point",
    "coordinates": [
      -103.56543,
      20.72302
    ]
  }
}