{
  "type": "Feature",
  "properties": {
    "name": "La Punta",
    "country": "MX",
    "subdivision": "14",
    "timezone": "America/Mexico_City"
  },
  "geometry": {
    "type": "Point",
    "coordinates": [
      -103.21147,
      20.57156
    ]
  }
}