{
  "type": "Feature",
  "properties": {
    "name": "Lomas de San Agustín",
    "country": "MX",
    "subdivision": "14",
    "timezone": "America/Mexico_City"
  },
  "geometry": {
    "type": "Point",
    "coordinates": [
      -103.46778,
      20.5275
    ]
  }
}