{
  "type": "Feature",
  "properties": {
    "name": "Mexticacán",
    "country": "MX",
    "subdivision": "14",
    "timezone": "America/Mexico_City"
  },
  "geometry": {
    "type": "Point",
    "coordinates": [
      -102.77985,
      21.26538
    ]
  }
}