{
  "type": "Feature",
  "properties": {
    "name": "Mezquitic",
    "country": "MX",
    "subdivision": "14",
    "timezone": "America/Mexico_City"
  },
  "geometry": {
    "type": "Point",
    "coordinates": [
      -103.7271,
      22.38896
    ]
  }
}