{
  "type": "Feature",
  "properties": {
    "name": "Mixtlán",
    "country": "MX",
    "subdivision": "14",
    "timezone": "America/Mexico_City"
  },
  "geometry": {
    "type": "Point",
    "coordinates": [
      -104.40867,
      20.439
    ]
  }
}