{
  "type": "Feature",
  "properties": {
    "name": "Nuevo México",
    "country": "MX",
    "subdivision": "14",
    "timezone": "America/Mexico_City"
  },
  "geometry": {
    "type": "Point",
    "coordinates": [
      -103.44297,
      20.7565
    ]
  }
}