{
  "type": "Feature",
  "properties": {
    "name": "Pihuamo",
    "country": "MX",
    "subdivision": "14",
    "timezone": "America/Mexico_City"
  },
  "geometry": {
    "type": "Point",
    "coordinates": [
      -103.38275,
      19.24991
    ]
  }
}