{
  "type": "Feature",
  "properties": {
    "name": "Puente de Camotlán",
    "country": "MX",
    "subdivision": "14",
    "timezone": "America/Mazatlan"
  },
  "geometry": {
    "type": "Point",
    "coordinates": [
      -104.07996,
      21.6987
    ]
  }
}