{
  "type": "Feature",
  "properties": {
    "name": "Rinconada la Loma [Fraccionamiento]",
    "country": "MX",
    "subdivision": "14",
    "timezone": "America/Mexico_City"
  },
  "geometry": {
    "type": "Point",
    "coordinates": [
      -103.21917,
      20.45417
    ]
  }
}