{
  "type": "Feature",
  "properties": {
    "name": "San Ignacio Cerro Gordo",
    "country": "MX",
    "subdivision": "14",
    "timezone": "America/Mexico_City"
  },
  "geometry": {
    "type": "Point",
    "coordinates": [
      -102.53466,
      20.74558
    ]
  }
}