{
  "type": "Feature",
  "properties": {
    "name": "San Miguel de la Paz",
    "country": "MX",
    "subdivision": "14",
    "timezone": "America/Mexico_City"
  },
  "geometry": {
    "type": "Point",
    "coordinates": [
      -102.66267,
      20.37051
    ]
  }
}