{
  "type": "Feature",
  "properties": {
    "name": "San Miguel Cuyutlán",
    "country": "MX",
    "subdivision": "14",
    "timezone": "America/Mexico_City"
  },
  "geometry": {
    "type": "Point",
    "coordinates": [
      -103.38987,
      20.41633
    ]
  }
}