{
  "type": "Feature",
  "properties": {
    "name": "San Andrés",
    "country": "MX",
    "subdivision": "14",
    "timezone": "America/Mexico_City"
  },
  "geometry": {
    "type": "Point",
    "coordinates": [
      -104.08803,
      20.92454
    ]
  }
}