{
  "type": "Feature",
  "properties": {
    "name": "San Juan Tecomatlán",
    "country": "MX",
    "subdivision": "14",
    "timezone": "America/Mexico_City"
  },
  "geometry": {
    "type": "Point",
    "coordinates": [
      -103.10035,
      20.32838
    ]
  }
}