{
  "type": "Feature",
  "properties": {
    "name": "San Marcos",
    "country": "MX",
    "subdivision": "14",
    "timezone": "America/Mexico_City"
  },
  "geometry": {
    "type": "Point",
    "coordinates": [
      -104.19682,
      20.79269
    ]
  }
}