{
  "type": "Feature",
  "properties": {
    "name": "Santa María Transpontina",
    "country": "MX",
    "subdivision": "14",
    "timezone": "America/Mexico_City"
  },
  "geometry": {
    "type": "Point",
    "coordinates": [
      -102.2572,
      21.4149
    ]
  }
}