{
  "type": "Feature",
  "properties": {
    "name": "Santiaguito (Santiaguito de Velázquez)",
    "country": "MX",
    "subdivision": "14",
    "timezone": "America/Mexico_City"
  },
  "geometry": {
    "type": "Point",
    "coordinates": [
      -102.23716,
      20.72533
    ]
  }
}