{
  "type": "Feature",
  "properties": {
    "name": "Santa Rosa",
    "country": "MX",
    "subdivision": "14",
    "timezone": "America/Mexico_City"
  },
  "geometry": {
    "type": "Point",
    "coordinates": [
      -103.23534,
      20.4144
    ]
  }
}