{
  "type": "Feature",
  "properties": {
    "name": "Sayula",
    "country": "MX",
    "subdivision": "14",
    "timezone": "America/Mexico_City"
  },
  "geometry": {
    "type": "Point",
    "coordinates": [
      -103.60027,
      19.88225
    ]
  }
}