{
  "type": "Feature",
  "properties": {
    "name": "Tepatitlán de Morelos",
    "country": "MX",
    "subdivision": "14",
    "timezone": "America/Mexico_City"
  },
  "geometry": {
    "type": "Point",
    "coordinates": [
      -102.76347,
      20.81692
    ]
  }
}