{
  "type": "Feature",
  "properties": {
    "name": "Tesistán",
    "country": "MX",
    "subdivision": "14",
    "timezone": "America/Mexico_City"
  },
  "geometry": {
    "type": "Point",
    "coordinates": [
      -103.46993,
      20.80051
    ]
  }
}