{
  "type": "Feature",
  "properties": {
    "name": "Tonila",
    "country": "MX",
    "subdivision": "14",
    "timezone": "America/Mexico_City"
  },
  "geometry": {
    "type": "Point",
    "coordinates": [
      -103.51657,
      19.43365
    ]
  }
}