{
  "type": "Feature",
  "properties": {
    "name": "Totatiche",
    "country": "MX",
    "subdivision": "14",
    "timezone": "America/Mexico_City"
  },
  "geometry": {
    "type": "Point",
    "coordinates": [
      -103.44405,
      21.9284
    ]
  }
}