{
  "type": "Feature",
  "properties": {
    "name": "Trejos",
    "country": "MX",
    "subdivision": "14",
    "timezone": "America/Mexico_City"
  },
  "geometry": {
    "type": "Point",
    "coordinates": [
      -103.19711,
      20.79439
    ]
  }
}