{
  "type": "Feature",
  "properties": {
    "name": "Valle de Guadalupe",
    "country": "MX",
    "subdivision": "14",
    "timezone": "America/Mexico_City"
  },
  "geometry": {
    "type": "Point",
    "coordinates": [
      -102.61683,
      21.01114
    ]
  }
}