{
  "type": "Feature",
  "properties": {
    "name": "Villas de la Hacienda [Fraccionamiento]",
    "country": "MX",
    "subdivision": "14",
    "timezone": "America/Mexico_City"
  },
  "geometry": {
    "type": "Point",
    "coordinates": [
      -103.38278,
      20.53111
    ]
  }
}