{
  "type": "Feature",
  "properties": {
    "name": "Agua Blanca",
    "country": "GT",
    "subdivision": "11",
    "timezone": "America/Guatemala"
  },
  "geometry": {
    "type": "Point",
    "coordinates": [
      -89.64961,
      14.49805
    ]
  }
}