{
  "type": "Feature",
  "properties": {
    "name": "Jutiapa",
    "country": "GT",
    "subdivision": "11",
    "timezone": "America/Guatemala"
  },
  "geometry": {
    "type": "Point",
    "coordinates": [
      -89.89583,
      14.29167
    ]
  }
}