{
  "type": "Feature",
  "properties": {
    "name": "Anajatuba",
    "country": "BR",
    "subdivision": "13",
    "timezone": "America/Fortaleza"
  },
  "geometry": {
    "type": "Point",
    "coordinates": [
      -44.61972,
      -3.26444
    ]
  }
}