{
  "type": "Feature",
  "properties": {
    "name": "Bacabal",
    "country": "BR",
    "subdivision": "13",
    "timezone": "America/Fortaleza"
  },
  "geometry": {
    "type": "Point",
    "coordinates": [
      -44.79167,
      -4.29167
    ]
  }
}