{
  "type": "Feature",
  "properties": {
    "name": "Buriti Bravo",
    "country": "BR",
    "subdivision": "13",
    "timezone": "America/Fortaleza"
  },
  "geometry": {
    "type": "Point",
    "coordinates": [
      -43.83361,
      -5.83722
    ]
  }
}