{
  "type": "Feature",
  "properties": {
    "name": "Carutapera",
    "country": "BR",
    "subdivision": "13",
    "timezone": "America/Fortaleza"
  },
  "geometry": {
    "type": "Point",
    "coordinates": [
      -46.0236,
      -1.20736
    ]
  }
}