{
  "type": "Feature",
  "properties": {
    "name": "Caxias",
    "country": "BR",
    "subdivision": "13",
    "timezone": "America/Fortaleza"
  },
  "geometry": {
    "type": "Point",
    "coordinates": [
      -43.35611,
      -4.85889
    ]
  }
}