{
  "type": "Feature",
  "properties": {
    "name": "Colinas",
    "country": "BR",
    "subdivision": "13",
    "timezone": "America/Fortaleza"
  },
  "geometry": {
    "type": "Point",
    "coordinates": [
      -44.24917,
      -6.02583
    ]
  }
}