{
  "type": "Feature",
  "properties": {
    "name": "Dom Pedro",
    "country": "BR",
    "subdivision": "13",
    "timezone": "America/Fortaleza"
  },
  "geometry": {
    "type": "Point",
    "coordinates": [
      -44.43857,
      -5.03749
    ]
  }
}