{
  "type": "Feature",
  "properties": {
    "name": "Itapecuru Mirim",
    "country": "BR",
    "subdivision": "13",
    "timezone": "America/Fortaleza"
  },
  "geometry": {
    "type": "Point",
    "coordinates": [
      -44.35861,
      -3.3925
    ]
  }
}