{
  "type": "Feature",
  "properties": {
    "name": "Monção",
    "country": "BR",
    "subdivision": "13",
    "timezone": "America/Fortaleza"
  },
  "geometry": {
    "type": "Point",
    "coordinates": [
      -45.25111,
      -3.49167
    ]
  }
}