{
  "type": "Feature",
  "properties": {
    "name": "Paulo Ramos",
    "country": "BR",
    "subdivision": "13",
    "timezone": "America/Fortaleza"
  },
  "geometry": {
    "type": "Point",
    "coordinates": [
      -45.18333,
      -4.21667
    ]
  }
}