{
  "type": "Feature",
  "properties": {
    "name": "Santa Rita",
    "country": "BR",
    "subdivision": "13",
    "timezone": "America/Fortaleza"
  },
  "geometry": {
    "type": "Point",
    "coordinates": [
      -43.85999,
      -3.86358
    ]
  }
}