{
  "type": "Feature",
  "properties": {
    "name": "São Benedito do Rio Preto",
    "country": "BR",
    "subdivision": "13",
    "timezone": "America/Fortaleza"
  },
  "geometry": {
    "type": "Point",
    "coordinates": [
      -43.52833,
      -3.33361
    ]
  }
}