{
  "type": "Feature",
  "properties": {
    "name": "São Luís",
    "country": "BR",
    "subdivision": "13",
    "timezone": "America/Fortaleza"
  },
  "geometry": {
    "type": "Point",
    "coordinates": [
      -44.30278,
      -2.52972
    ]
  }
}