{
  "type": "Feature",
  "properties": {
    "name": "Jepelacio",
    "country": "PE",
    "subdivision": "22",
    "timezone": "America/Lima"
  },
  "geometry": {
    "type": "Point",
    "coordinates": [
      -76.95,
      -6.11667
    ]
  }
}