{
  "type": "Feature",
  "properties": {
    "name": "San Jose De Sisa",
    "country": "PE",
    "subdivision": "22",
    "timezone": "America/Lima"
  },
  "geometry": {
    "type": "Point",
    "coordinates": [
      -76.69309,
      -6.61375
    ]
  }
}