{
  "type": "Feature",
  "properties": {
    "name": "Q’vareli",
    "country": "GE",
    "subdivision": "67",
    "timezone": "Asia/Tbilisi"
  },
  "geometry": {
    "type": "Point",
    "coordinates": [
      45.81716,
      41.95493
    ]
  }
}