{
  "type": "Feature",
  "properties": {
    "name": "Sighnaghi",
    "country": "GE",
    "subdivision": "67",
    "timezone": "Asia/Tbilisi"
  },
  "geometry": {
    "type": "Point",
    "coordinates": [
      45.92198,
      41.62046
    ]
  }
}