{
  "type": "Feature",
  "properties": {
    "name": "Yaruchel",
    "country": "HN",
    "subdivision": "14",
    "timezone": "America/Tegucigalpa"
  },
  "geometry": {
    "type": "Point",
    "coordinates": [
      -88.81667,
      14.53333
    ]
  }
}