{
  "type": "Feature",
  "properties": {
    "name": "Bugalagrande",
    "country": "CO",
    "subdivision": "29",
    "timezone": "America/Bogota"
  },
  "geometry": {
    "type": "Point",
    "coordinates": [
      -76.15564,
      4.21207
    ]
  }
}