{
  "type": "Feature",
  "properties": {
    "name": "El Águila",
    "country": "CO",
    "subdivision": "29",
    "timezone": "America/Bogota"
  },
  "geometry": {
    "type": "Point",
    "coordinates": [
      -76.04004,
      4.91345
    ]
  }
}