{
  "type": "Feature",
  "properties": {
    "name": "Guadalajara de Buga",
    "country": "CO",
    "subdivision": "29",
    "timezone": "America/Bogota"
  },
  "geometry": {
    "type": "Point",
    "coordinates": [
      -76.29783,
      3.90089
    ]
  }
}