{
  "type": "Feature",
  "properties": {
    "name": "Toro",
    "country": "CO",
    "subdivision": "29",
    "timezone": "America/Bogota"
  },
  "geometry": {
    "type": "Point",
    "coordinates": [
      -76.08139,
      4.61167
    ]
  }
}