{
  "type": "Feature",
  "properties": {
    "name": "Āq Qāyeh",
    "country": "IR",
    "subdivision": "37",
    "timezone": "Asia/Tehran"
  },
  "geometry": {
    "type": "Point",
    "coordinates": [
      55.15889,
      37.27472
    ]
  }
}