{
  "type": "Feature",
  "properties": {
    "name": "KalÄleh",
    "country": "IR",
    "subdivision": "37",
    "timezone": "Asia/Tehran"
  },
  "geometry": {
    "type": "Point",
    "coordinates": [
      55.493,
      37.37899
    ]
  }
}