{
  "type": "Feature",
  "properties": {
    "name": "Allendale",
    "country": "US",
    "subdivision": "NJ",
    "timezone": "America/New_York"
  },
  "geometry": {
    "type": "Point",
    "coordinates": [
      -74.12903,
      41.04149
    ]
  }
}