{
  "type": "Feature",
  "properties": {
    "name": "Alpine",
    "country": "US",
    "subdivision": "NJ",
    "timezone": "America/New_York"
  },
  "geometry": {
    "type": "Point",
    "coordinates": [
      -73.93125,
      40.95593
    ]
  }
}