{
  "type": "Feature",
  "properties": {
    "name": "Audubon",
    "country": "US",
    "subdivision": "NJ",
    "timezone": "America/New_York"
  },
  "geometry": {
    "type": "Point",
    "coordinates": [
      -75.07295,
      39.89095
    ]
  }
}