{
  "type": "Feature",
  "properties": {
    "name": "Beattystown",
    "country": "US",
    "subdivision": "NJ",
    "timezone": "America/New_York"
  },
  "geometry": {
    "type": "Point",
    "coordinates": [
      -74.84294,
      40.81315
    ]
  }
}