{
  "type": "Feature",
  "properties": {
    "name": "Beckett",
    "country": "US",
    "subdivision": "NJ",
    "timezone": "America/New_York"
  },
  "geometry": {
    "type": "Point",
    "coordinates": [
      -75.35741,
      39.754
    ]
  }
}