{
  "type": "Feature",
  "properties": {
    "name": "Bedminster",
    "country": "US",
    "subdivision": "NJ",
    "timezone": "America/New_York"
  },
  "geometry": {
    "type": "Point",
    "coordinates": [
      -74.64544,
      40.68066
    ]
  }
}