{
  "type": "Feature",
  "properties": {
    "name": "Berkeley Heights",
    "country": "US",
    "subdivision": "NJ",
    "timezone": "America/New_York"
  },
  "geometry": {
    "type": "Point",
    "coordinates": [
      -74.44265,
      40.68343
    ]
  }
}