{
  "type": "Feature",
  "properties": {
    "name": "Boonton",
    "country": "US",
    "subdivision": "NJ",
    "timezone": "America/New_York"
  },
  "geometry": {
    "type": "Point",
    "coordinates": [
      -74.4071,
      40.9026
    ]
  }
}