{
  "type": "Feature",
  "properties": {
    "name": "Brielle",
    "country": "US",
    "subdivision": "NJ",
    "timezone": "America/New_York"
  },
  "geometry": {
    "type": "Point",
    "coordinates": [
      -74.05653,
      40.10789
    ]
  }
}