{
  "type": "Feature",
  "properties": {
    "name": "Brigantine",
    "country": "US",
    "subdivision": "NJ",
    "timezone": "America/New_York"
  },
  "geometry": {
    "type": "Point",
    "coordinates": [
      -74.36459,
      39.41012
    ]
  }
}