{
  "type": "Feature",
  "properties": {
    "name": "Caldwell",
    "country": "US",
    "subdivision": "NJ",
    "timezone": "America/New_York"
  },
  "geometry": {
    "type": "Point",
    "coordinates": [
      -74.27654,
      40.83982
    ]
  }
}