{
  "type": "Feature",
  "properties": {
    "name": "Camden",
    "country": "US",
    "subdivision": "NJ",
    "timezone": "America/New_York"
  },
  "geometry": {
    "type": "Point",
    "coordinates": [
      -75.11962,
      39.92595
    ]
  }
}