{
  "type": "Feature",
  "properties": {
    "name": "Cedar Glen Lakes",
    "country": "US",
    "subdivision": "NJ",
    "timezone": "America/New_York"
  },
  "geometry": {
    "type": "Point",
    "coordinates": [
      -74.39987,
      39.95234
    ]
  }
}