{
  "type": "Feature",
  "properties": {
    "name": "Cinnaminson",
    "country": "US",
    "subdivision": "NJ",
    "timezone": "America/New_York"
  },
  "geometry": {
    "type": "Point",
    "coordinates": [
      -74.99267,
      39.99678
    ]
  }
}