{
  "type": "Feature",
  "properties": {
    "name": "Clifton",
    "country": "US",
    "subdivision": "NJ",
    "timezone": "America/New_York"
  },
  "geometry": {
    "type": "Point",
    "coordinates": [
      -74.16376,
      40.85843
    ]
  }
}