{
  "type": "Feature",
  "properties": {
    "name": "Delanco",
    "country": "US",
    "subdivision": "NJ",
    "timezone": "America/New_York"
  },
  "geometry": {
    "type": "Point",
    "coordinates": [
      -74.9535,
      40.05067
    ]
  }
}