{
  "type": "Feature",
  "properties": {
    "name": "Dover",
    "country": "US",
    "subdivision": "NJ",
    "timezone": "America/New_York"
  },
  "geometry": {
    "type": "Point",
    "coordinates": [
      -74.5621,
      40.88399
    ]
  }
}