{
  "type": "Feature",
  "properties": {
    "name": "Dover Beaches North",
    "country": "US",
    "subdivision": "NJ",
    "timezone": "America/New_York"
  },
  "geometry": {
    "type": "Point",
    "coordinates": [
      -74.06375,
      39.99123
    ]
  }
}