{
  "type": "Feature",
  "properties": {
    "name": "East Franklin",
    "country": "US",
    "subdivision": "NJ",
    "timezone": "America/New_York"
  },
  "geometry": {
    "type": "Point",
    "coordinates": [
      -74.4711,
      40.4933
    ]
  }
}