{
  "type": "Feature",
  "properties": {
    "name": "East Freehold",
    "country": "US",
    "subdivision": "NJ",
    "timezone": "America/New_York"
  },
  "geometry": {
    "type": "Point",
    "coordinates": [
      -74.25126,
      40.28094
    ]
  }
}