{
  "type": "Feature",
  "properties": {
    "name": "Eatontown",
    "country": "US",
    "subdivision": "NJ",
    "timezone": "America/New_York"
  },
  "geometry": {
    "type": "Point",
    "coordinates": [
      -74.05097,
      40.29622
    ]
  }
}