{
  "type": "Feature",
  "properties": {
    "name": "Elwood",
    "country": "US",
    "subdivision": "NJ",
    "timezone": "America/New_York"
  },
  "geometry": {
    "type": "Point",
    "coordinates": [
      -74.71683,
      39.57651
    ]
  }
}