{
  "type": "Feature",
  "properties": {
    "name": "Englishtown",
    "country": "US",
    "subdivision": "NJ",
    "timezone": "America/New_York"
  },
  "geometry": {
    "type": "Point",
    "coordinates": [
      -74.3582,
      40.29733
    ]
  }
}