{
  "type": "Feature",
  "properties": {
    "name": "Fairview",
    "country": "US",
    "subdivision": "NJ",
    "timezone": "America/New_York"
  },
  "geometry": {
    "type": "Point",
    "coordinates": [
      -73.99903,
      40.8126
    ]
  }
}