{
  "type": "Feature",
  "properties": {
    "name": "Fair Haven",
    "country": "US",
    "subdivision": "NJ",
    "timezone": "America/New_York"
  },
  "geometry": {
    "type": "Point",
    "coordinates": [
      -74.03819,
      40.36067
    ]
  }
}