{
  "type": "Feature",
  "properties": {
    "name": "Forked River",
    "country": "US",
    "subdivision": "NJ",
    "timezone": "America/New_York"
  },
  "geometry": {
    "type": "Point",
    "coordinates": [
      -74.19014,
      39.83984
    ]
  }
}