{
  "type": "Feature",
  "properties": {
    "name": "Guttenberg",
    "country": "US",
    "subdivision": "NJ",
    "timezone": "America/New_York"
  },
  "geometry": {
    "type": "Point",
    "coordinates": [
      -74.00375,
      40.79205
    ]
  }
}