{
  "type": "Feature",
  "properties": {
    "name": "Haddonfield",
    "country": "US",
    "subdivision": "NJ",
    "timezone": "America/New_York"
  },
  "geometry": {
    "type": "Point",
    "coordinates": [
      -75.03767,
      39.8915
    ]
  }
}