{
  "type": "Feature",
  "properties": {
    "name": "Haddon Heights",
    "country": "US",
    "subdivision": "NJ",
    "timezone": "America/New_York"
  },
  "geometry": {
    "type": "Point",
    "coordinates": [
      -75.06462,
      39.87734
    ]
  }
}