{
  "type": "Feature",
  "properties": {
    "name": "Harrington Park",
    "country": "US",
    "subdivision": "NJ",
    "timezone": "America/New_York"
  },
  "geometry": {
    "type": "Point",
    "coordinates": [
      -73.97986,
      40.98371
    ]
  }
}