{
  "type": "Feature",
  "properties": {
    "name": "Haworth",
    "country": "US",
    "subdivision": "NJ",
    "timezone": "America/New_York"
  },
  "geometry": {
    "type": "Point",
    "coordinates": [
      -73.99014,
      40.96093
    ]
  }
}