{
  "type": "Feature",
  "properties": {
    "name": "High Bridge",
    "country": "US",
    "subdivision": "NJ",
    "timezone": "America/New_York"
  },
  "geometry": {
    "type": "Point",
    "coordinates": [
      -74.89572,
      40.66705
    ]
  }
}