{
  "type": "Feature",
  "properties": {
    "name": "Highland Lake",
    "country": "US",
    "subdivision": "NJ",
    "timezone": "America/New_York"
  },
  "geometry": {
    "type": "Point",
    "coordinates": [
      -74.45655,
      41.17676
    ]
  }
}