{
  "type": "Feature",
  "properties": {
    "name": "Hopewell",
    "country": "US",
    "subdivision": "NJ",
    "timezone": "America/New_York"
  },
  "geometry": {
    "type": "Point",
    "coordinates": [
      -74.76183,
      40.38927
    ]
  }
}