{
  "type": "Feature",
  "properties": {
    "name": "Jamesburg",
    "country": "US",
    "subdivision": "NJ",
    "timezone": "America/New_York"
  },
  "geometry": {
    "type": "Point",
    "coordinates": [
      -74.44015,
      40.35261
    ]
  }
}