{
  "type": "Feature",
  "properties": {
    "name": "Kenilworth",
    "country": "US",
    "subdivision": "NJ",
    "timezone": "America/New_York"
  },
  "geometry": {
    "type": "Point",
    "coordinates": [
      -74.2907,
      40.67649
    ]
  }
}