{
  "type": "Feature",
  "properties": {
    "name": "Kingston",
    "country": "US",
    "subdivision": "NJ",
    "timezone": "America/New_York"
  },
  "geometry": {
    "type": "Point",
    "coordinates": [
      -74.61349,
      40.37538
    ]
  }
}