{
  "type": "Feature",
  "properties": {
    "name": "Laurel Springs",
    "country": "US",
    "subdivision": "NJ",
    "timezone": "America/New_York"
  },
  "geometry": {
    "type": "Point",
    "coordinates": [
      -75.00628,
      39.82011
    ]
  }
}