{
  "type": "Feature",
  "properties": {
    "name": "Lincoln Park",
    "country": "US",
    "subdivision": "NJ",
    "timezone": "America/New_York"
  },
  "geometry": {
    "type": "Point",
    "coordinates": [
      -74.30209,
      40.92427
    ]
  }
}