{
  "type": "Feature",
  "properties": {
    "name": "Livingston",
    "country": "US",
    "subdivision": "NJ",
    "timezone": "America/New_York"
  },
  "geometry": {
    "type": "Point",
    "coordinates": [
      -74.31487,
      40.79593
    ]
  }
}