{
  "type": "Feature",
  "properties": {
    "name": "Long Valley",
    "country": "US",
    "subdivision": "NJ",
    "timezone": "America/New_York"
  },
  "geometry": {
    "type": "Point",
    "coordinates": [
      -74.78016,
      40.78593
    ]
  }
}