{
  "type": "Feature",
  "properties": {
    "name": "Magnolia",
    "country": "US",
    "subdivision": "NJ",
    "timezone": "America/New_York"
  },
  "geometry": {
    "type": "Point",
    "coordinates": [
      -74.66071,
      39.94984
    ]
  }
}