{
  "type": "Feature",
  "properties": {
    "name": "McGuire AFB",
    "country": "US",
    "subdivision": "NJ",
    "timezone": "America/New_York"
  },
  "geometry": {
    "type": "Point",
    "coordinates": [
      -74.58174,
      40.03977
    ]
  }
}