{
  "type": "Feature",
  "properties": {
    "name": "Merchantville",
    "country": "US",
    "subdivision": "NJ",
    "timezone": "America/New_York"
  },
  "geometry": {
    "type": "Point",
    "coordinates": [
      -75.06656,
      39.94734
    ]
  }
}