{
  "type": "Feature",
  "properties": {
    "name": "Middlesex",
    "country": "US",
    "subdivision": "NJ",
    "timezone": "America/New_York"
  },
  "geometry": {
    "type": "Point",
    "coordinates": [
      -74.49265,
      40.5726
    ]
  }
}