{
  "type": "Feature",
  "properties": {
    "name": "Milltown",
    "country": "US",
    "subdivision": "NJ",
    "timezone": "America/New_York"
  },
  "geometry": {
    "type": "Point",
    "coordinates": [
      -74.44321,
      40.45622
    ]
  }
}