{
  "type": "Feature",
  "properties": {
    "name": "Mount Holly",
    "country": "US",
    "subdivision": "NJ",
    "timezone": "America/New_York"
  },
  "geometry": {
    "type": "Point",
    "coordinates": [
      -74.78766,
      39.99289
    ]
  }
}