{
  "type": "Feature",
  "properties": {
    "name": "Mount Arlington",
    "country": "US",
    "subdivision": "NJ",
    "timezone": "America/New_York"
  },
  "geometry": {
    "type": "Point",
    "coordinates": [
      -74.63488,
      40.92593
    ]
  }
}