{
  "type": "Feature",
  "properties": {
    "name": "New Egypt",
    "country": "US",
    "subdivision": "NJ",
    "timezone": "America/New_York"
  },
  "geometry": {
    "type": "Point",
    "coordinates": [
      -74.53071,
      40.06761
    ]
  }
}