{
  "type": "Feature",
  "properties": {
    "name": "Northvale",
    "country": "US",
    "subdivision": "NJ",
    "timezone": "America/New_York"
  },
  "geometry": {
    "type": "Point",
    "coordinates": [
      -73.94903,
      41.00649
    ]
  }
}