{
  "type": "Feature",
  "properties": {
    "name": "Nutley",
    "country": "US",
    "subdivision": "NJ",
    "timezone": "America/New_York"
  },
  "geometry": {
    "type": "Point",
    "coordinates": [
      -74.15987,
      40.82232
    ]
  }
}