{
  "type": "Feature",
  "properties": {
    "name": "Orange",
    "country": "US",
    "subdivision": "NJ",
    "timezone": "America/New_York"
  },
  "geometry": {
    "type": "Point",
    "coordinates": [
      -74.23265,
      40.77066
    ]
  }
}