{
  "type": "Feature",
  "properties": {
    "name": "Park Ridge",
    "country": "US",
    "subdivision": "NJ",
    "timezone": "America/New_York"
  },
  "geometry": {
    "type": "Point",
    "coordinates": [
      -74.0407,
      41.0376
    ]
  }
}