{
  "type": "Feature",
  "properties": {
    "name": "Passaic",
    "country": "US",
    "subdivision": "NJ",
    "timezone": "America/New_York"
  },
  "geometry": {
    "type": "Point",
    "coordinates": [
      -74.12848,
      40.85677
    ]
  }
}