{
  "type": "Feature",
  "properties": {
    "name": "Paterson",
    "country": "US",
    "subdivision": "NJ",
    "timezone": "America/New_York"
  },
  "geometry": {
    "type": "Point",
    "coordinates": [
      -74.17181,
      40.91677
    ]
  }
}