{
  "type": "Feature",
  "properties": {
    "name": "Perth Amboy",
    "country": "US",
    "subdivision": "NJ",
    "timezone": "America/New_York"
  },
  "geometry": {
    "type": "Point",
    "coordinates": [
      -74.26542,
      40.50677
    ]
  }
}