{
  "type": "Feature",
  "properties": {
    "name": "Pine Hill",
    "country": "US",
    "subdivision": "NJ",
    "timezone": "America/New_York"
  },
  "geometry": {
    "type": "Point",
    "coordinates": [
      -74.99211,
      39.78428
    ]
  }
}