{
  "type": "Feature",
  "properties": {
    "name": "Pitman",
    "country": "US",
    "subdivision": "NJ",
    "timezone": "America/New_York"
  },
  "geometry": {
    "type": "Point",
    "coordinates": [
      -75.13157,
      39.73289
    ]
  }
}