{
  "type": "Feature",
  "properties": {
    "name": "Princeton",
    "country": "US",
    "subdivision": "NJ",
    "timezone": "America/New_York"
  },
  "geometry": {
    "type": "Point",
    "coordinates": [
      -74.65905,
      40.34872
    ]
  }
}