{
  "type": "Feature",
  "properties": {
    "name": "Ramtown",
    "country": "US",
    "subdivision": "NJ",
    "timezone": "America/New_York"
  },
  "geometry": {
    "type": "Point",
    "coordinates": [
      -74.14375,
      40.12095
    ]
  }
}