{
  "type": "Feature",
  "properties": {
    "name": "Riverdale",
    "country": "US",
    "subdivision": "NJ",
    "timezone": "America/New_York"
  },
  "geometry": {
    "type": "Point",
    "coordinates": [
      -74.30348,
      40.99399
    ]
  }
}