{
  "type": "Feature",
  "properties": {
    "name": "Rochelle Park",
    "country": "US",
    "subdivision": "NJ",
    "timezone": "America/New_York"
  },
  "geometry": {
    "type": "Point",
    "coordinates": [
      -74.07514,
      40.90732
    ]
  }
}