{
  "type": "Feature",
  "properties": {
    "name": "Roebling",
    "country": "US",
    "subdivision": "NJ",
    "timezone": "America/New_York"
  },
  "geometry": {
    "type": "Point",
    "coordinates": [
      -74.78627,
      40.11594
    ]
  }
}