{
  "type": "Feature",
  "properties": {
    "name": "Runnemede",
    "country": "US",
    "subdivision": "NJ",
    "timezone": "America/New_York"
  },
  "geometry": {
    "type": "Point",
    "coordinates": [
      -75.06795,
      39.85234
    ]
  }
}