{
  "type": "Feature",
  "properties": {
    "name": "Rutherford",
    "country": "US",
    "subdivision": "NJ",
    "timezone": "America/New_York"
  },
  "geometry": {
    "type": "Point",
    "coordinates": [
      -74.10681,
      40.82649
    ]
  }
}