{
  "type": "Feature",
  "properties": {
    "name": "Sea Isle City",
    "country": "US",
    "subdivision": "NJ",
    "timezone": "America/New_York"
  },
  "geometry": {
    "type": "Point",
    "coordinates": [
      -74.69294,
      39.15345
    ]
  }
}