{
  "type": "Feature",
  "properties": {
    "name": "South Plainfield",
    "country": "US",
    "subdivision": "NJ",
    "timezone": "America/New_York"
  },
  "geometry": {
    "type": "Point",
    "coordinates": [
      -74.41154,
      40.57927
    ]
  }
}