{
  "type": "Feature",
  "properties": {
    "name": "South River",
    "country": "US",
    "subdivision": "NJ",
    "timezone": "America/New_York"
  },
  "geometry": {
    "type": "Point",
    "coordinates": [
      -74.38598,
      40.44649
    ]
  }
}