{
  "type": "Feature",
  "properties": {
    "name": "South Belmar",
    "country": "US",
    "subdivision": "NJ",
    "timezone": "America/New_York"
  },
  "geometry": {
    "type": "Point",
    "coordinates": [
      -74.02736,
      40.17095
    ]
  }
}