{
  "type": "Feature",
  "properties": {
    "name": "South Old Bridge",
    "country": "US",
    "subdivision": "NJ",
    "timezone": "America/New_York"
  },
  "geometry": {
    "type": "Point",
    "coordinates": [
      -74.35432,
      40.40816
    ]
  }
}