{
  "type": "Feature",
  "properties": {
    "name": "Strathmore",
    "country": "US",
    "subdivision": "NJ",
    "timezone": "America/New_York"
  },
  "geometry": {
    "type": "Point",
    "coordinates": [
      -74.21348,
      40.39594
    ]
  }
}