{
  "type": "Feature",
  "properties": {
    "name": "Tuckerton",
    "country": "US",
    "subdivision": "NJ",
    "timezone": "America/New_York"
  },
  "geometry": {
    "type": "Point",
    "coordinates": [
      -74.34015,
      39.60317
    ]
  }
}