{
  "type": "Feature",
  "properties": {
    "name": "Union City",
    "country": "US",
    "subdivision": "NJ",
    "timezone": "America/New_York"
  },
  "geometry": {
    "type": "Point",
    "coordinates": [
      -74.02375,
      40.77955
    ]
  }
}