{
  "type": "Feature",
  "properties": {
    "name": "Upper Saddle River",
    "country": "US",
    "subdivision": "NJ",
    "timezone": "America/New_York"
  },
  "geometry": {
    "type": "Point",
    "coordinates": [
      -74.09848,
      41.05843
    ]
  }
}