{
  "type": "Feature",
  "properties": {
    "name": "Wanamassa",
    "country": "US",
    "subdivision": "NJ",
    "timezone": "America/New_York"
  },
  "geometry": {
    "type": "Point",
    "coordinates": [
      -74.02542,
      40.23178
    ]
  }
}