{
  "type": "Feature",
  "properties": {
    "name": "Whitesboro-Burleigh",
    "country": "US",
    "subdivision": "NJ",
    "timezone": "America/New_York"
  },
  "geometry": {
    "type": "Point",
    "coordinates": [
      -74.86538,
      39.04305
    ]
  }
}