{
  "type": "Feature",
  "properties": {
    "name": "White Meadow Lake",
    "country": "US",
    "subdivision": "NJ",
    "timezone": "America/New_York"
  },
  "geometry": {
    "type": "Point",
    "coordinates": [
      -74.51071,
      40.92371
    ]
  }
}