{
  "type": "Feature",
  "properties": {
    "name": "Wood-Lynne",
    "country": "US",
    "subdivision": "NJ",
    "timezone": "America/New_York"
  },
  "geometry": {
    "type": "Point",
    "coordinates": [
      -75.09629,
      39.91734
    ]
  }
}