{
  "type": "Feature",
  "properties": {
    "name": "Artà",
    "country": "ES",
    "subdivision": "07",
    "timezone": "Europe/Madrid"
  },
  "geometry": {
    "type": "Point",
    "coordinates": [
      3.34979,
      39.69315
    ]
  }
}