{
  "type": "Feature",
  "properties": {
    "name": "Cala Rajada",
    "country": "ES",
    "subdivision": "07",
    "timezone": "Europe/Madrid"
  },
  "geometry": {
    "type": "Point",
    "coordinates": [
      3.4631,
      39.71174
    ]
  }
}