{
  "type": "Feature",
  "properties": {
    "name": "Campanet",
    "country": "ES",
    "subdivision": "07",
    "timezone": "Europe/Madrid"
  },
  "geometry": {
    "type": "Point",
    "coordinates": [
      2.96506,
      39.7747
    ]
  }
}