{
  "type": "Feature",
  "properties": {
    "name": "Peguera",
    "country": "ES",
    "subdivision": "07",
    "timezone": "Europe/Madrid"
  },
  "geometry": {
    "type": "Point",
    "coordinates": [
      2.44806,
      39.53751
    ]
  }
}