{
  "type": "Feature",
  "properties": {
    "name": "Porto Cristo",
    "country": "ES",
    "subdivision": "07",
    "timezone": "Europe/Madrid"
  },
  "geometry": {
    "type": "Point",
    "coordinates": [
      3.33302,
      39.53953
    ]
  }
}