{
  "type": "Feature",
  "properties": {
    "name": "Sant Antoni de Portmany",
    "country": "ES",
    "subdivision": "07",
    "timezone": "Europe/Madrid"
  },
  "geometry": {
    "type": "Point",
    "coordinates": [
      1.30362,
      38.98068
    ]
  }
}