{
  "type": "Feature",
  "properties": {
    "name": "Son Servera",
    "country": "ES",
    "subdivision": "07",
    "timezone": "Europe/Madrid"
  },
  "geometry": {
    "type": "Point",
    "coordinates": [
      3.36008,
      39.62073
    ]
  }
}