{
  "type": "Feature",
  "properties": {
    "name": "Cataño",
    "country": "PR",
    "subdivision": "033",
    "timezone": "America/Puerto_Rico"
  },
  "geometry": {
    "type": "Point",
    "coordinates": [
      -66.11822,
      18.44134
    ]
  }
}