{
  "type": "Feature",
  "properties": {
    "name": "Mihovljan",
    "country": "HR",
    "subdivision": "07",
    "timezone": "Europe/Zagreb"
  },
  "geometry": {
    "type": "Point",
    "coordinates": [
      15.97222,
      46.13306
    ]
  }
}