{
  "type": "Feature",
  "properties": {
    "name": "Marmato",
    "country": "CO",
    "subdivision": "37",
    "timezone": "America/Bogota"
  },
  "geometry": {
    "type": "Point",
    "coordinates": [
      -75.6004,
      5.47501
    ]
  }
}