{
  "type": "Feature",
  "properties": {
    "name": "Koungou",
    "country": "YT",
    "subdivision": "97610",
    "timezone": "Indian/Mayotte"
  },
  "geometry": {
    "type": "Point",
    "coordinates": [
      45.20417,
      -12.73361
    ]
  }
}