{
  "type": "Feature",
  "properties": {
    "name": "Akwanga",
    "country": "NG",
    "subdivision": "56",
    "timezone": "Africa/Lagos"
  },
  "geometry": {
    "type": "Point",
    "coordinates": [
      8.40655,
      8.91077
    ]
  }
}