{
  "type": "Feature",
  "properties": {
    "name": "Wamba",
    "country": "NG",
    "subdivision": "56",
    "timezone": "Africa/Lagos"
  },
  "geometry": {
    "type": "Point",
    "coordinates": [
      8.60315,
      8.94153
    ]
  }
}