{
  "type": "Feature",
  "properties": {
    "name": "Alcácer do Sal",
    "country": "PT",
    "subdivision": "19",
    "timezone": "Europe/Lisbon"
  },
  "geometry": {
    "type": "Point",
    "coordinates": [
      -8.51444,
      38.37326
    ]
  }
}