{
  "type": "Feature",
  "properties": {
    "name": "Corroios",
    "country": "PT",
    "subdivision": "19",
    "timezone": "Europe/Lisbon"
  },
  "geometry": {
    "type": "Point",
    "coordinates": [
      -9.1508,
      38.64004
    ]
  }
}