{
  "type": "Feature",
  "properties": {
    "name": "Quinta Do Conde",
    "country": "PT",
    "subdivision": "19",
    "timezone": "Europe/Lisbon"
  },
  "geometry": {
    "type": "Point",
    "coordinates": [
      -9.04316,
      38.56528
    ]
  }
}