{
  "type": "Feature",
  "properties": {
    "name": "Quinta do Anjo",
    "country": "PT",
    "subdivision": "19",
    "timezone": "Europe/Lisbon"
  },
  "geometry": {
    "type": "Point",
    "coordinates": [
      -8.94228,
      38.56753
    ]
  }
}