{
  "type": "Feature",
  "properties": {
    "name": "Sesimbra",
    "country": "PT",
    "subdivision": "19",
    "timezone": "Europe/Lisbon"
  },
  "geometry": {
    "type": "Point",
    "coordinates": [
      -9.10149,
      38.44451
    ]
  }
}