{
  "type": "Feature",
  "properties": {
    "name": "Igunga",
    "country": "TZ",
    "subdivision": "17",
    "timezone": "Africa/Dar_es_Salaam"
  },
  "geometry": {
    "type": "Point",
    "coordinates": [
      33.88333,
      -4.28333
    ]
  }
}