{
  "type": "Feature",
  "properties": {
    "name": "Alpnach",
    "country": "CH",
    "subdivision": "OW",
    "timezone": "Europe/Zurich"
  },
  "geometry": {
    "type": "Point",
    "coordinates": [
      8.2718,
      46.94227
    ]
  }
}