{
  "type": "Feature",
  "properties": {
    "name": "Ajak",
    "country": "HU",
    "subdivision": "18",
    "timezone": "Europe/Budapest"
  },
  "geometry": {
    "type": "Point",
    "coordinates": [
      22.06273,
      48.17664
    ]
  }
}