{
  "type": "Feature",
  "properties": {
    "name": "Gyulaháza",
    "country": "HU",
    "subdivision": "18",
    "timezone": "Europe/Budapest"
  },
  "geometry": {
    "type": "Point",
    "coordinates": [
      22.11667,
      48.13333
    ]
  }
}