{
  "type": "Feature",
  "properties": {
    "name": "Kisvárda",
    "country": "HU",
    "subdivision": "18",
    "timezone": "Europe/Budapest"
  },
  "geometry": {
    "type": "Point",
    "coordinates": [
      22.08333,
      48.21667
    ]
  }
}