{
  "type": "Feature",
  "properties": {
    "name": "Kótaj",
    "country": "HU",
    "subdivision": "18",
    "timezone": "Europe/Budapest"
  },
  "geometry": {
    "type": "Point",
    "coordinates": [
      21.71667,
      48.05
    ]
  }
}