{
  "type": "Feature",
  "properties": {
    "name": "Nyírbogdány",
    "country": "HU",
    "subdivision": "18",
    "timezone": "Europe/Budapest"
  },
  "geometry": {
    "type": "Point",
    "coordinates": [
      21.88242,
      48.05723
    ]
  }
}