{
  "type": "Feature",
  "properties": {
    "name": "Nyírbátor",
    "country": "HU",
    "subdivision": "18",
    "timezone": "Europe/Budapest"
  },
  "geometry": {
    "type": "Point",
    "coordinates": [
      22.13333,
      47.83333
    ]
  }
}