{
  "type": "Feature",
  "properties": {
    "name": "Ófehértó",
    "country": "HU",
    "subdivision": "18",
    "timezone": "Europe/Budapest"
  },
  "geometry": {
    "type": "Point",
    "coordinates": [
      22.05,
      47.93333
    ]
  }
}