{
  "type": "Feature",
  "properties": {
    "name": "Tiszalök",
    "country": "HU",
    "subdivision": "18",
    "timezone": "Europe/Budapest"
  },
  "geometry": {
    "type": "Point",
    "coordinates": [
      21.38333,
      48.01667
    ]
  }
}