{
  "type": "Feature",
  "properties": {
    "name": "Abingdon",
    "country": "US",
    "subdivision": "IL",
    "timezone": "America/Chicago"
  },
  "geometry": {
    "type": "Point",
    "coordinates": [
      -90.4018,
      40.80448
    ]
  }
}