{
  "type": "Feature",
  "properties": {
    "name": "Albers",
    "country": "US",
    "subdivision": "IL",
    "timezone": "America/Chicago"
  },
  "geometry": {
    "type": "Point",
    "coordinates": [
      -89.61231,
      38.54338
    ]
  }
}