{
  "type": "Feature",
  "properties": {
    "name": "Aledo",
    "country": "US",
    "subdivision": "IL",
    "timezone": "America/Chicago"
  },
  "geometry": {
    "type": "Point",
    "coordinates": [
      -90.74931,
      41.19976
    ]
  }
}