{
  "type": "Feature",
  "properties": {
    "name": "Algonquin",
    "country": "US",
    "subdivision": "IL",
    "timezone": "America/Chicago"
  },
  "geometry": {
    "type": "Point",
    "coordinates": [
      -88.29425,
      42.16558
    ]
  }
}