{
  "type": "Feature",
  "properties": {
    "name": "Andalusia",
    "country": "US",
    "subdivision": "IL",
    "timezone": "America/Chicago"
  },
  "geometry": {
    "type": "Point",
    "coordinates": [
      -90.71764,
      41.4392
    ]
  }
}