{
  "type": "Feature",
  "properties": {
    "name": "Auburn",
    "country": "US",
    "subdivision": "IL",
    "timezone": "America/Chicago"
  },
  "geometry": {
    "type": "Point",
    "coordinates": [
      -89.74649,
      39.59172
    ]
  }
}