{
  "type": "Feature",
  "properties": {
    "name": "Barry",
    "country": "US",
    "subdivision": "IL",
    "timezone": "America/Chicago"
  },
  "geometry": {
    "type": "Point",
    "coordinates": [
      -91.03902,
      39.69421
    ]
  }
}