{
  "type": "Feature",
  "properties": {
    "name": "Bartonville",
    "country": "US",
    "subdivision": "IL",
    "timezone": "America/Chicago"
  },
  "geometry": {
    "type": "Point",
    "coordinates": [
      -89.65205,
      40.65032
    ]
  }
}