{
  "type": "Feature",
  "properties": {
    "name": "Beecher",
    "country": "US",
    "subdivision": "IL",
    "timezone": "America/Chicago"
  },
  "geometry": {
    "type": "Point",
    "coordinates": [
      -87.62143,
      41.34059
    ]
  }
}