{
  "type": "Feature",
  "properties": {
    "name": "Belleville",
    "country": "US",
    "subdivision": "IL",
    "timezone": "America/Chicago"
  },
  "geometry": {
    "type": "Point",
    "coordinates": [
      -89.98399,
      38.52005
    ]
  }
}