{
  "type": "Feature",
  "properties": {
    "name": "Belvidere",
    "country": "US",
    "subdivision": "IL",
    "timezone": "America/Chicago"
  },
  "geometry": {
    "type": "Point",
    "coordinates": [
      -88.84427,
      42.26391
    ]
  }
}