{
  "type": "Feature",
  "properties": {
    "name": "Bloomingdale",
    "country": "US",
    "subdivision": "IL",
    "timezone": "America/Chicago"
  },
  "geometry": {
    "type": "Point",
    "coordinates": [
      -88.0809,
      41.95753
    ]
  }
}