{
  "type": "Feature",
  "properties": {
    "name": "Bridgeview",
    "country": "US",
    "subdivision": "IL",
    "timezone": "America/Chicago"
  },
  "geometry": {
    "type": "Point",
    "coordinates": [
      -87.80422,
      41.75003
    ]
  }
}