{
  "type": "Feature",
  "properties": {
    "name": "Brighton",
    "country": "US",
    "subdivision": "IL",
    "timezone": "America/Chicago"
  },
  "geometry": {
    "type": "Point",
    "coordinates": [
      -90.14066,
      39.03977
    ]
  }
}