{
  "type": "Feature",
  "properties": {
    "name": "Bull Valley",
    "country": "US",
    "subdivision": "IL",
    "timezone": "America/Chicago"
  },
  "geometry": {
    "type": "Point",
    "coordinates": [
      -88.35509,
      42.32058
    ]
  }
}