{
  "type": "Feature",
  "properties": {
    "name": "Byron",
    "country": "US",
    "subdivision": "IL",
    "timezone": "America/Chicago"
  },
  "geometry": {
    "type": "Point",
    "coordinates": [
      -89.25566,
      42.12697
    ]
  }
}