{
  "type": "Feature",
  "properties": {
    "name": "Carlinville",
    "country": "US",
    "subdivision": "IL",
    "timezone": "America/Chicago"
  },
  "geometry": {
    "type": "Point",
    "coordinates": [
      -89.88177,
      39.27977
    ]
  }
}