{
  "type": "Feature",
  "properties": {
    "name": "Carpentersville",
    "country": "US",
    "subdivision": "IL",
    "timezone": "America/Chicago"
  },
  "geometry": {
    "type": "Point",
    "coordinates": [
      -88.25786,
      42.12114
    ]
  }
}