{
  "type": "Feature",
  "properties": {
    "name": "Carterville",
    "country": "US",
    "subdivision": "IL",
    "timezone": "America/Chicago"
  },
  "geometry": {
    "type": "Point",
    "coordinates": [
      -89.0773,
      37.76005
    ]
  }
}