{
  "type": "Feature",
  "properties": {
    "name": "Charleston",
    "country": "US",
    "subdivision": "IL",
    "timezone": "America/Chicago"
  },
  "geometry": {
    "type": "Point",
    "coordinates": [
      -88.17615,
      39.49615
    ]
  }
}