{
  "type": "Feature",
  "properties": {
    "name": "Cherry Valley",
    "country": "US",
    "subdivision": "IL",
    "timezone": "America/Chicago"
  },
  "geometry": {
    "type": "Point",
    "coordinates": [
      -88.94899,
      42.23474
    ]
  }
}