{
  "type": "Feature",
  "properties": {
    "name": "Chester",
    "country": "US",
    "subdivision": "IL",
    "timezone": "America/Chicago"
  },
  "geometry": {
    "type": "Point",
    "coordinates": [
      -89.82205,
      37.91366
    ]
  }
}