{
  "type": "Feature",
  "properties": {
    "name": "Collinsville",
    "country": "US",
    "subdivision": "IL",
    "timezone": "America/Chicago"
  },
  "geometry": {
    "type": "Point",
    "coordinates": [
      -89.98455,
      38.67033
    ]
  }
}