{
  "type": "Feature",
  "properties": {
    "name": "Columbia",
    "country": "US",
    "subdivision": "IL",
    "timezone": "America/Chicago"
  },
  "geometry": {
    "type": "Point",
    "coordinates": [
      -90.20122,
      38.44366
    ]
  }
}