{
  "type": "Feature",
  "properties": {
    "name": "Cortland",
    "country": "US",
    "subdivision": "IL",
    "timezone": "America/Chicago"
  },
  "geometry": {
    "type": "Point",
    "coordinates": [
      -88.6887,
      41.92003
    ]
  }
}