{
  "type": "Feature",
  "properties": {
    "name": "Danvers",
    "country": "US",
    "subdivision": "IL",
    "timezone": "America/Chicago"
  },
  "geometry": {
    "type": "Point",
    "coordinates": [
      -89.17731,
      40.52948
    ]
  }
}