{
  "type": "Feature",
  "properties": {
    "name": "Decatur",
    "country": "US",
    "subdivision": "IL",
    "timezone": "America/Chicago"
  },
  "geometry": {
    "type": "Point",
    "coordinates": [
      -88.9548,
      39.84031
    ]
  }
}