{
  "type": "Feature",
  "properties": {
    "name": "DeKalb",
    "country": "US",
    "subdivision": "IL",
    "timezone": "America/Chicago"
  },
  "geometry": {
    "type": "Point",
    "coordinates": [
      -88.75036,
      41.92947
    ]
  }
}