{
  "type": "Feature",
  "properties": {
    "name": "Des Plaines",
    "country": "US",
    "subdivision": "IL",
    "timezone": "America/Chicago"
  },
  "geometry": {
    "type": "Point",
    "coordinates": [
      -87.8834,
      42.03336
    ]
  }
}