{
  "type": "Feature",
  "properties": {
    "name": "Dixmoor",
    "country": "US",
    "subdivision": "IL",
    "timezone": "America/Chicago"
  },
  "geometry": {
    "type": "Point",
    "coordinates": [
      -87.66088,
      41.6317
    ]
  }
}