{
  "type": "Feature",
  "properties": {
    "name": "Dwight",
    "country": "US",
    "subdivision": "IL",
    "timezone": "America/Chicago"
  },
  "geometry": {
    "type": "Point",
    "coordinates": [
      -88.42506,
      41.09448
    ]
  }
}