{
  "type": "Feature",
  "properties": {
    "name": "Edwardsville",
    "country": "US",
    "subdivision": "IL",
    "timezone": "America/Chicago"
  },
  "geometry": {
    "type": "Point",
    "coordinates": [
      -89.95316,
      38.81144
    ]
  }
}