{
  "type": "Feature",
  "properties": {
    "name": "Elgin",
    "country": "US",
    "subdivision": "IL",
    "timezone": "America/Chicago"
  },
  "geometry": {
    "type": "Point",
    "coordinates": [
      -88.28119,
      42.03725
    ]
  }
}