{
  "type": "Feature",
  "properties": {
    "name": "Englewood",
    "country": "US",
    "subdivision": "IL",
    "timezone": "America/Chicago"
  },
  "geometry": {
    "type": "Point",
    "coordinates": [
      -87.64588,
      41.77976
    ]
  }
}