{
  "type": "Feature",
  "properties": {
    "name": "Fairfield",
    "country": "US",
    "subdivision": "IL",
    "timezone": "America/Chicago"
  },
  "geometry": {
    "type": "Point",
    "coordinates": [
      -88.35977,
      38.37894
    ]
  }
}