{
  "type": "Feature",
  "properties": {
    "name": "Fisher",
    "country": "US",
    "subdivision": "IL",
    "timezone": "America/Chicago"
  },
  "geometry": {
    "type": "Point",
    "coordinates": [
      -88.35005,
      40.31476
    ]
  }
}