{
  "type": "Feature",
  "properties": {
    "name": "Flanagan",
    "country": "US",
    "subdivision": "IL",
    "timezone": "America/Chicago"
  },
  "geometry": {
    "type": "Point",
    "coordinates": [
      -88.86118,
      40.87809
    ]
  }
}