{
  "type": "Feature",
  "properties": {
    "name": "Gages Lake",
    "country": "US",
    "subdivision": "IL",
    "timezone": "America/Chicago"
  },
  "geometry": {
    "type": "Point",
    "coordinates": [
      -87.98258,
      42.35169
    ]
  }
}