{
  "type": "Feature",
  "properties": {
    "name": "Gardner",
    "country": "US",
    "subdivision": "IL",
    "timezone": "America/Chicago"
  },
  "geometry": {
    "type": "Point",
    "coordinates": [
      -88.30978,
      41.18559
    ]
  }
}