{
  "type": "Feature",
  "properties": {
    "name": "Georgetown",
    "country": "US",
    "subdivision": "IL",
    "timezone": "America/Chicago"
  },
  "geometry": {
    "type": "Point",
    "coordinates": [
      -87.63585,
      39.97531
    ]
  }
}