{
  "type": "Feature",
  "properties": {
    "name": "Gibson City",
    "country": "US",
    "subdivision": "IL",
    "timezone": "America/Chicago"
  },
  "geometry": {
    "type": "Point",
    "coordinates": [
      -88.3846,
      40.45843
    ]
  }
}