{
  "type": "Feature",
  "properties": {
    "name": "Grayville",
    "country": "US",
    "subdivision": "IL",
    "timezone": "America/Chicago"
  },
  "geometry": {
    "type": "Point",
    "coordinates": [
      -87.99364,
      38.25755
    ]
  }
}