{
  "type": "Feature",
  "properties": {
    "name": "Hartford",
    "country": "US",
    "subdivision": "IL",
    "timezone": "America/Chicago"
  },
  "geometry": {
    "type": "Point",
    "coordinates": [
      -90.09594,
      38.83338
    ]
  }
}