{
  "type": "Feature",
  "properties": {
    "name": "Hebron",
    "country": "US",
    "subdivision": "IL",
    "timezone": "America/Chicago"
  },
  "geometry": {
    "type": "Point",
    "coordinates": [
      -88.43232,
      42.47169
    ]
  }
}