{
  "type": "Feature",
  "properties": {
    "name": "Heritage Lake",
    "country": "US",
    "subdivision": "IL",
    "timezone": "America/Chicago"
  },
  "geometry": {
    "type": "Point",
    "coordinates": [
      -89.32581,
      40.54745
    ]
  }
}