{
  "type": "Feature",
  "properties": {
    "name": "Heyworth",
    "country": "US",
    "subdivision": "IL",
    "timezone": "America/Chicago"
  },
  "geometry": {
    "type": "Point",
    "coordinates": [
      -88.97369,
      40.31337
    ]
  }
}