{
  "type": "Feature",
  "properties": {
    "name": "Hillside",
    "country": "US",
    "subdivision": "IL",
    "timezone": "America/Chicago"
  },
  "geometry": {
    "type": "Point",
    "coordinates": [
      -87.90284,
      41.87781
    ]
  }
}