{
  "type": "Feature",
  "properties": {
    "name": "Homer Glen",
    "country": "US",
    "subdivision": "IL",
    "timezone": "America/Chicago"
  },
  "geometry": {
    "type": "Point",
    "coordinates": [
      -87.93811,
      41.60003
    ]
  }
}