{
  "type": "Feature",
  "properties": {
    "name": "Ina",
    "country": "US",
    "subdivision": "IL",
    "timezone": "America/Chicago"
  },
  "geometry": {
    "type": "Point",
    "coordinates": [
      -88.90396,
      38.15116
    ]
  }
}