{
  "type": "Feature",
  "properties": {
    "name": "Indian Head Park",
    "country": "US",
    "subdivision": "IL",
    "timezone": "America/Chicago"
  },
  "geometry": {
    "type": "Point",
    "coordinates": [
      -87.90228,
      41.77031
    ]
  }
}