{
  "type": "Feature",
  "properties": {
    "name": "Kenilworth",
    "country": "US",
    "subdivision": "IL",
    "timezone": "America/Chicago"
  },
  "geometry": {
    "type": "Point",
    "coordinates": [
      -87.71756,
      42.08586
    ]
  }
}