{
  "type": "Feature",
  "properties": {
    "name": "Lake Bluff",
    "country": "US",
    "subdivision": "IL",
    "timezone": "America/Chicago"
  },
  "geometry": {
    "type": "Point",
    "coordinates": [
      -87.83424,
      42.27891
    ]
  }
}