{
  "type": "Feature",
  "properties": {
    "name": "Lily Lake",
    "country": "US",
    "subdivision": "IL",
    "timezone": "America/Chicago"
  },
  "geometry": {
    "type": "Point",
    "coordinates": [
      -88.47786,
      41.94892
    ]
  }
}