{
  "type": "Feature",
  "properties": {
    "name": "Lincolnshire",
    "country": "US",
    "subdivision": "IL",
    "timezone": "America/Chicago"
  },
  "geometry": {
    "type": "Point",
    "coordinates": [
      -87.9084,
      42.19002
    ]
  }
}