{
  "type": "Feature",
  "properties": {
    "name": "Long Creek",
    "country": "US",
    "subdivision": "IL",
    "timezone": "America/Chicago"
  },
  "geometry": {
    "type": "Point",
    "coordinates": [
      -88.84757,
      39.81198
    ]
  }
}