{
  "type": "Feature",
  "properties": {
    "name": "Lower West Side",
    "country": "US",
    "subdivision": "IL",
    "timezone": "America/Chicago"
  },
  "geometry": {
    "type": "Point",
    "coordinates": [
      -87.66561,
      41.8542
    ]
  }
}