{
  "type": "Feature",
  "properties": {
    "name": "Machesney Park",
    "country": "US",
    "subdivision": "IL",
    "timezone": "America/Chicago"
  },
  "geometry": {
    "type": "Point",
    "coordinates": [
      -89.039,
      42.34724
    ]
  }
}