{
  "type": "Feature",
  "properties": {
    "name": "Macon",
    "country": "US",
    "subdivision": "IL",
    "timezone": "America/Chicago"
  },
  "geometry": {
    "type": "Point",
    "coordinates": [
      -88.99702,
      39.71282
    ]
  }
}