{
  "type": "Feature",
  "properties": {
    "name": "Malta",
    "country": "US",
    "subdivision": "IL",
    "timezone": "America/Chicago"
  },
  "geometry": {
    "type": "Point",
    "coordinates": [
      -88.86092,
      41.92975
    ]
  }
}