{
  "type": "Feature",
  "properties": {
    "name": "Martinsville",
    "country": "US",
    "subdivision": "IL",
    "timezone": "America/Chicago"
  },
  "geometry": {
    "type": "Point",
    "coordinates": [
      -87.88198,
      39.33559
    ]
  }
}