{
  "type": "Feature",
  "properties": {
    "name": "Milan",
    "country": "US",
    "subdivision": "IL",
    "timezone": "America/Chicago"
  },
  "geometry": {
    "type": "Point",
    "coordinates": [
      -90.57208,
      41.45309
    ]
  }
}