{
  "type": "Feature",
  "properties": {
    "name": "Monmouth",
    "country": "US",
    "subdivision": "IL",
    "timezone": "America/Chicago"
  },
  "geometry": {
    "type": "Point",
    "coordinates": [
      -90.64736,
      40.91143
    ]
  }
}