{
  "type": "Feature",
  "properties": {
    "name": "Monticello",
    "country": "US",
    "subdivision": "IL",
    "timezone": "America/Chicago"
  },
  "geometry": {
    "type": "Point",
    "coordinates": [
      -88.5734,
      40.02781
    ]
  }
}