{
  "type": "Feature",
  "properties": {
    "name": "Morris",
    "country": "US",
    "subdivision": "IL",
    "timezone": "America/Chicago"
  },
  "geometry": {
    "type": "Point",
    "coordinates": [
      -88.42118,
      41.35725
    ]
  }
}