{
  "type": "Feature",
  "properties": {
    "name": "Mundelein",
    "country": "US",
    "subdivision": "IL",
    "timezone": "America/Chicago"
  },
  "geometry": {
    "type": "Point",
    "coordinates": [
      -88.00397,
      42.26308
    ]
  }
}