{
  "type": "Feature",
  "properties": {
    "name": "Nashville",
    "country": "US",
    "subdivision": "IL",
    "timezone": "America/Chicago"
  },
  "geometry": {
    "type": "Point",
    "coordinates": [
      -89.38064,
      38.34366
    ]
  }
}