{
  "type": "Feature",
  "properties": {
    "name": "Near South Side",
    "country": "US",
    "subdivision": "IL",
    "timezone": "America/Chicago"
  },
  "geometry": {
    "type": "Point",
    "coordinates": [
      -87.62477,
      41.8567
    ]
  }
}