{
  "type": "Feature",
  "properties": {
    "name": "Near North Side",
    "country": "US",
    "subdivision": "IL",
    "timezone": "America/Chicago"
  },
  "geometry": {
    "type": "Point",
    "coordinates": [
      -87.6345,
      41.90003
    ]
  }
}