{
  "type": "Feature",
  "properties": {
    "name": "Nokomis",
    "country": "US",
    "subdivision": "IL",
    "timezone": "America/Chicago"
  },
  "geometry": {
    "type": "Point",
    "coordinates": [
      -89.28508,
      39.30116
    ]
  }
}