{
  "type": "Feature",
  "properties": {
    "name": "Olympia Fields",
    "country": "US",
    "subdivision": "IL",
    "timezone": "America/Chicago"
  },
  "geometry": {
    "type": "Point",
    "coordinates": [
      -87.67421,
      41.51337
    ]
  }
}