{
  "type": "Feature",
  "properties": {
    "name": "Oregon",
    "country": "US",
    "subdivision": "IL",
    "timezone": "America/Chicago"
  },
  "geometry": {
    "type": "Point",
    "coordinates": [
      -89.33233,
      42.01475
    ]
  }
}