{
  "type": "Feature",
  "properties": {
    "name": "Oswego",
    "country": "US",
    "subdivision": "IL",
    "timezone": "America/Chicago"
  },
  "geometry": {
    "type": "Point",
    "coordinates": [
      -88.35146,
      41.68281
    ]
  }
}