{
  "type": "Feature",
  "properties": {
    "name": "Peru",
    "country": "US",
    "subdivision": "IL",
    "timezone": "America/Chicago"
  },
  "geometry": {
    "type": "Point",
    "coordinates": [
      -89.12897,
      41.32753
    ]
  }
}