{
  "type": "Feature",
  "properties": {
    "name": "Portage Park",
    "country": "US",
    "subdivision": "IL",
    "timezone": "America/Chicago"
  },
  "geometry": {
    "type": "Point",
    "coordinates": [
      -87.76506,
      41.95781
    ]
  }
}