{
  "type": "Feature",
  "properties": {
    "name": "Riverton",
    "country": "US",
    "subdivision": "IL",
    "timezone": "America/Chicago"
  },
  "geometry": {
    "type": "Point",
    "coordinates": [
      -89.53954,
      39.84422
    ]
  }
}