{
  "type": "Feature",
  "properties": {
    "name": "Rome",
    "country": "US",
    "subdivision": "IL",
    "timezone": "America/Chicago"
  },
  "geometry": {
    "type": "Point",
    "coordinates": [
      -89.50259,
      40.88309
    ]
  }
}