{
  "type": "Feature",
  "properties": {
    "name": "Shawneetown",
    "country": "US",
    "subdivision": "IL",
    "timezone": "America/Chicago"
  },
  "geometry": {
    "type": "Point",
    "coordinates": [
      -88.1867,
      37.7131
    ]
  }
}