{
  "type": "Feature",
  "properties": {
    "name": "South Holland",
    "country": "US",
    "subdivision": "IL",
    "timezone": "America/Chicago"
  },
  "geometry": {
    "type": "Point",
    "coordinates": [
      -87.60699,
      41.60087
    ]
  }
}