{
  "type": "Feature",
  "properties": {
    "name": "South Shore",
    "country": "US",
    "subdivision": "IL",
    "timezone": "America/Chicago"
  },
  "geometry": {
    "type": "Point",
    "coordinates": [
      -87.57783,
      41.76198
    ]
  }
}