{
  "type": "Feature",
  "properties": {
    "name": "Steger",
    "country": "US",
    "subdivision": "IL",
    "timezone": "America/Chicago"
  },
  "geometry": {
    "type": "Point",
    "coordinates": [
      -87.63643,
      41.47003
    ]
  }
}