{
  "type": "Feature",
  "properties": {
    "name": "Summit",
    "country": "US",
    "subdivision": "IL",
    "timezone": "America/Chicago"
  },
  "geometry": {
    "type": "Point",
    "coordinates": [
      -87.81033,
      41.78809
    ]
  }
}