{
  "type": "Feature",
  "properties": {
    "name": "Teutopolis",
    "country": "US",
    "subdivision": "IL",
    "timezone": "America/Chicago"
  },
  "geometry": {
    "type": "Point",
    "coordinates": [
      -88.47199,
      39.1331
    ]
  }
}