{
  "type": "Feature",
  "properties": {
    "name": "The Galena Territory",
    "country": "US",
    "subdivision": "IL",
    "timezone": "America/Chicago"
  },
  "geometry": {
    "type": "Point",
    "coordinates": [
      -90.32582,
      42.39343
    ]
  }
}