{
  "type": "Feature",
  "properties": {
    "name": "Washington Park",
    "country": "US",
    "subdivision": "IL",
    "timezone": "America/Chicago"
  },
  "geometry": {
    "type": "Point",
    "coordinates": [
      -90.09289,
      38.63505
    ]
  }
}