{
  "type": "Feature",
  "properties": {
    "name": "Wayne City",
    "country": "US",
    "subdivision": "IL",
    "timezone": "America/Chicago"
  },
  "geometry": {
    "type": "Point",
    "coordinates": [
      -88.58783,
      38.34533
    ]
  }
}