{
  "type": "Feature",
  "properties": {
    "name": "West Elsdon",
    "country": "US",
    "subdivision": "IL",
    "timezone": "America/Chicago"
  },
  "geometry": {
    "type": "Point",
    "coordinates": [
      -87.7245,
      41.79392
    ]
  }
}