{
  "type": "Feature",
  "properties": {
    "name": "Western Springs",
    "country": "US",
    "subdivision": "IL",
    "timezone": "America/Chicago"
  },
  "geometry": {
    "type": "Point",
    "coordinates": [
      -87.90062,
      41.80975
    ]
  }
}