{
  "type": "Feature",
  "properties": {
    "name": "Williamsville",
    "country": "US",
    "subdivision": "IL",
    "timezone": "America/Chicago"
  },
  "geometry": {
    "type": "Point",
    "coordinates": [
      -89.54871,
      39.95422
    ]
  }
}