{
  "type": "Feature",
  "properties": {
    "name": "Wilmette",
    "country": "US",
    "subdivision": "IL",
    "timezone": "America/Chicago"
  },
  "geometry": {
    "type": "Point",
    "coordinates": [
      -87.72284,
      42.07225
    ]
  }
}