{
  "type": "Feature",
  "properties": {
    "name": "Winnebago",
    "country": "US",
    "subdivision": "IL",
    "timezone": "America/Chicago"
  },
  "geometry": {
    "type": "Point",
    "coordinates": [
      -89.24122,
      42.26613
    ]
  }
}