{
  "type": "Feature",
  "properties": {
    "name": "Wyoming",
    "country": "US",
    "subdivision": "IL",
    "timezone": "America/Chicago"
  },
  "geometry": {
    "type": "Point",
    "coordinates": [
      -89.77316,
      41.0617
    ]
  }
}