{
  "type": "Feature",
  "properties": {
    "name": "Arkul’",
    "country": "RU",
    "subdivision": "33",
    "timezone": "Europe/Kirov"
  },
  "geometry": {
    "type": "Point",
    "coordinates": [
      50.044,
      57.28085
    ]
  }
}