{
  "type": "Feature",
  "properties": {
    "name": "Falënki",
    "country": "RU",
    "subdivision": "33",
    "timezone": "Europe/Kirov"
  },
  "geometry": {
    "type": "Point",
    "coordinates": [
      51.59461,
      58.36127
    ]
  }
}