{
  "type": "Feature",
  "properties": {
    "name": "Kostino",
    "country": "RU",
    "subdivision": "33",
    "timezone": "Europe/Kirov"
  },
  "geometry": {
    "type": "Point",
    "coordinates": [
      53.26907,
      58.90966
    ]
  }
}