{
  "type": "Feature",
  "properties": {
    "name": "Kotel’nich",
    "country": "RU",
    "subdivision": "33",
    "timezone": "Europe/Kirov"
  },
  "geometry": {
    "type": "Point",
    "coordinates": [
      48.348,
      58.3089
    ]
  }
}