{
  "type": "Feature",
  "properties": {
    "name": "Orlov",
    "country": "RU",
    "subdivision": "33",
    "timezone": "Europe/Kirov"
  },
  "geometry": {
    "type": "Point",
    "coordinates": [
      48.89173,
      58.53946
    ]
  }
}