{
  "type": "Feature",
  "properties": {
    "name": "Sanchursk",
    "country": "RU",
    "subdivision": "33",
    "timezone": "Europe/Kirov"
  },
  "geometry": {
    "type": "Point",
    "coordinates": [
      47.24987,
      56.94125
    ]
  }
}