{
  "type": "Feature",
  "properties": {
    "name": "Stulovo",
    "country": "RU",
    "subdivision": "33",
    "timezone": "Europe/Kirov"
  },
  "geometry": {
    "type": "Point",
    "coordinates": [
      50.14389,
      58.7225
    ]
  }
}