{
  "type": "Feature",
  "properties": {
    "name": "Vyatskiye Polyany",
    "country": "RU",
    "subdivision": "33",
    "timezone": "Europe/Kirov"
  },
  "geometry": {
    "type": "Point",
    "coordinates": [
      51.06557,
      56.22602
    ]
  }
}