{
  "type": "Feature",
  "properties": {
    "name": "Jucuarán",
    "country": "SV",
    "subdivision": "14",
    "timezone": "America/El_Salvador"
  },
  "geometry": {
    "type": "Point",
    "coordinates": [
      -88.24778,
      13.25389
    ]
  }
}