{
  "type": "Feature",
  "properties": {
    "name": "Fond des Blancs",
    "country": "HT",
    "subdivision": "12",
    "timezone": "America/Port-au-Prince"
  },
  "geometry": {
    "type": "Point",
    "coordinates": [
      -73.12733,
      18.27782
    ]
  }
}