{
  "type": "Feature",
  "properties": {
    "name": "Port-à-Piment",
    "country": "HT",
    "subdivision": "12",
    "timezone": "America/Port-au-Prince"
  },
  "geometry": {
    "type": "Point",
    "coordinates": [
      -74.0971,
      18.24963
    ]
  }
}