{
  "type": "Feature",
  "properties": {
    "name": "Apastovo",
    "country": "RU",
    "subdivision": "73",
    "timezone": "Europe/Moscow"
  },
  "geometry": {
    "type": "Point",
    "coordinates": [
      48.51091,
      55.20293
    ]
  }
}