{
  "type": "Feature",
  "properties": {
    "name": "Bolgar",
    "country": "RU",
    "subdivision": "73",
    "timezone": "Europe/Moscow"
  },
  "geometry": {
    "type": "Point",
    "coordinates": [
      49.06667,
      54.95
    ]
  }
}