{
  "type": "Feature",
  "properties": {
    "name": "Karabash",
    "country": "RU",
    "subdivision": "73",
    "timezone": "Europe/Moscow"
  },
  "geometry": {
    "type": "Point",
    "coordinates": [
      52.58359,
      54.693
    ]
  }
}