{
  "type": "Feature",
  "properties": {
    "name": "Kukmor",
    "country": "RU",
    "subdivision": "73",
    "timezone": "Europe/Moscow"
  },
  "geometry": {
    "type": "Point",
    "coordinates": [
      50.8944,
      56.1855
    ]
  }
}