{
  "type": "Feature",
  "properties": {
    "name": "Kuybyshevskiy Zaton",
    "country": "RU",
    "subdivision": "73",
    "timezone": "Europe/Moscow"
  },
  "geometry": {
    "type": "Point",
    "coordinates": [
      49.1701,
      55.1593
    ]
  }
}