{
  "type": "Feature",
  "properties": {
    "name": "Laishevo",
    "country": "RU",
    "subdivision": "73",
    "timezone": "Europe/Moscow"
  },
  "geometry": {
    "type": "Point",
    "coordinates": [
      49.55037,
      55.40464
    ]
  }
}