{
  "type": "Feature",
  "properties": {
    "name": "Leninogorsk",
    "country": "RU",
    "subdivision": "73",
    "timezone": "Europe/Moscow"
  },
  "geometry": {
    "type": "Point",
    "coordinates": [
      52.46087,
      54.60256
    ]
  }
}