{
  "type": "Feature",
  "properties": {
    "name": "Nizhniye Vyazovyye",
    "country": "RU",
    "subdivision": "73",
    "timezone": "Europe/Moscow"
  },
  "geometry": {
    "type": "Point",
    "coordinates": [
      48.52476,
      55.79877
    ]
  }
}