{
  "type": "Feature",
  "properties": {
    "name": "Russkiy Aktash",
    "country": "RU",
    "subdivision": "73",
    "timezone": "Europe/Moscow"
  },
  "geometry": {
    "type": "Point",
    "coordinates": [
      52.1214,
      55.0384
    ]
  }
}