{
  "type": "Feature",
  "properties": {
    "name": "Vasil’yevo",
    "country": "RU",
    "subdivision": "73",
    "timezone": "Europe/Moscow"
  },
  "geometry": {
    "type": "Point",
    "coordinates": [
      48.71729,
      55.83007
    ]
  }
}