{
  "type": "Feature",
  "properties": {
    "name": "Lápithos",
    "country": "CY",
    "subdivision": "02",
    "timezone": "Asia/Famagusta"
  },
  "geometry": {
    "type": "Point",
    "coordinates": [
      33.17368,
      35.33823
    ]
  }
}