{
  "type": "Feature",
  "properties": {
    "name": "Gubakha",
    "country": "RU",
    "subdivision": "90",
    "timezone": "Asia/Yekaterinburg"
  },
  "geometry": {
    "type": "Point",
    "coordinates": [
      57.55325,
      58.83862
    ]
  }
}