{
  "type": "Feature",
  "properties": {
    "name": "Komarikhinskiy",
    "country": "RU",
    "subdivision": "90",
    "timezone": "Asia/Yekaterinburg"
  },
  "geometry": {
    "type": "Point",
    "coordinates": [
      57.1163,
      58.0979
    ]
  }
}