{
  "type": "Feature",
  "properties": {
    "name": "Krasnovishersk",
    "country": "RU",
    "subdivision": "90",
    "timezone": "Asia/Yekaterinburg"
  },
  "geometry": {
    "type": "Point",
    "coordinates": [
      57.08199,
      60.40783
    ]
  }
}