{
  "type": "Feature",
  "properties": {
    "name": "Nyrob",
    "country": "RU",
    "subdivision": "90",
    "timezone": "Asia/Yekaterinburg"
  },
  "geometry": {
    "type": "Point",
    "coordinates": [
      56.72024,
      60.733
    ]
  }
}