{
  "type": "Feature",
  "properties": {
    "name": "Pashiya",
    "country": "RU",
    "subdivision": "90",
    "timezone": "Asia/Yekaterinburg"
  },
  "geometry": {
    "type": "Point",
    "coordinates": [
      58.2562,
      58.4324
    ]
  }
}