{
  "type": "Feature",
  "properties": {
    "name": "Pavlovskiy",
    "country": "RU",
    "subdivision": "90",
    "timezone": "Asia/Yekaterinburg"
  },
  "geometry": {
    "type": "Point",
    "coordinates": [
      54.84357,
      57.8424
    ]
  }
}