{
  "type": "Feature",
  "properties": {
    "name": "Yurla",
    "country": "RU",
    "subdivision": "90",
    "timezone": "Asia/Yekaterinburg"
  },
  "geometry": {
    "type": "Point",
    "coordinates": [
      54.3278,
      59.3251
    ]
  }
}