{
  "type": "Feature",
  "properties": {
    "name": "Selfoss",
    "country": "IS",
    "subdivision": "42",
    "timezone": "Atlantic/Reykjavik"
  },
  "geometry": {
    "type": "Point",
    "coordinates": [
      -20.99712,
      63.93311
    ]
  }
}