{
  "type": "Feature",
  "properties": {
    "name": "Gurun",
    "country": "MY",
    "subdivision": "02",
    "timezone": "Asia/Kuala_Lumpur"
  },
  "geometry": {
    "type": "Point",
    "coordinates": [
      100.47381,
      5.81717
    ]
  }
}