{
  "type": "Feature",
  "properties": {
    "name": "Angresse",
    "country": "FR",
    "subdivision": "75",
    "timezone": "Europe/Paris"
  },
  "geometry": {
    "type": "Point",
    "coordinates": [
      -1.37242,
      43.65862
    ]
  }
}