{
  "type": "Feature",
  "properties": {
    "name": "Arette",
    "country": "FR",
    "subdivision": "75",
    "timezone": "Europe/Paris"
  },
  "geometry": {
    "type": "Point",
    "coordinates": [
      -0.71711,
      43.09529
    ]
  }
}