{
  "type": "Feature",
  "properties": {
    "name": "Arvert",
    "country": "FR",
    "subdivision": "75",
    "timezone": "Europe/Paris"
  },
  "geometry": {
    "type": "Point",
    "coordinates": [
      -1.12793,
      45.7406
    ]
  }
}