{
  "type": "Feature",
  "properties": {
    "name": "Ayguemorte-les-Graves",
    "country": "FR",
    "subdivision": "75",
    "timezone": "Europe/Paris"
  },
  "geometry": {
    "type": "Point",
    "coordinates": [
      -0.47645,
      44.71091
    ]
  }
}