{
  "type": "Feature",
  "properties": {
    "name": "Beauvoir-sur-Niort",
    "country": "FR",
    "subdivision": "75",
    "timezone": "Europe/Paris"
  },
  "geometry": {
    "type": "Point",
    "coordinates": [
      -0.47396,
      46.18198
    ]
  }
}