{
  "type": "Feature",
  "properties": {
    "name": "Bénesse-Maremne",
    "country": "FR",
    "subdivision": "75",
    "timezone": "Europe/Paris"
  },
  "geometry": {
    "type": "Point",
    "coordinates": [
      -1.36174,
      43.63474
    ]
  }
}