{
  "type": "Feature",
  "properties": {
    "name": "Bessines",
    "country": "FR",
    "subdivision": "75",
    "timezone": "Europe/Paris"
  },
  "geometry": {
    "type": "Point",
    "coordinates": [
      -0.51628,
      46.30207
    ]
  }
}