{
  "type": "Feature",
  "properties": {
    "name": "Biscarrosse",
    "country": "FR",
    "subdivision": "75",
    "timezone": "Europe/Paris"
  },
  "geometry": {
    "type": "Point",
    "coordinates": [
      -1.16721,
      44.39454
    ]
  }
}