{
  "type": "Feature",
  "properties": {
    "name": "Blanquefort",
    "country": "FR",
    "subdivision": "75",
    "timezone": "Europe/Paris"
  },
  "geometry": {
    "type": "Point",
    "coordinates": [
      -0.63758,
      44.91065
    ]
  }
}