{
  "type": "Feature",
  "properties": {
    "name": "Boeil-Bezing",
    "country": "FR",
    "subdivision": "75",
    "timezone": "Europe/Paris"
  },
  "geometry": {
    "type": "Point",
    "coordinates": [
      -0.2667,
      43.22154
    ]
  }
}