{
  "type": "Feature",
  "properties": {
    "name": "Boismé",
    "country": "FR",
    "subdivision": "75",
    "timezone": "Europe/Paris"
  },
  "geometry": {
    "type": "Point",
    "coordinates": [
      -0.43573,
      46.77472
    ]
  }
}