{
  "type": "Feature",
  "properties": {
    "name": "Bordeaux",
    "country": "FR",
    "subdivision": "75",
    "timezone": "Europe/Paris"
  },
  "geometry": {
    "type": "Point",
    "coordinates": [
      -0.5805,
      44.84044
    ]
  }
}