{
  "type": "Feature",
  "properties": {
    "name": "Bosdarros",
    "country": "FR",
    "subdivision": "75",
    "timezone": "Europe/Paris"
  },
  "geometry": {
    "type": "Point",
    "coordinates": [
      -0.36168,
      43.20996
    ]
  }
}