{
  "type": "Feature",
  "properties": {
    "name": "Breuillet",
    "country": "FR",
    "subdivision": "75",
    "timezone": "Europe/Paris"
  },
  "geometry": {
    "type": "Point",
    "coordinates": [
      -1.0548,
      45.69155
    ]
  }
}