{
  "type": "Feature",
  "properties": {
    "name": "Brioux-sur-Boutonne",
    "country": "FR",
    "subdivision": "75",
    "timezone": "Europe/Paris"
  },
  "geometry": {
    "type": "Point",
    "coordinates": [
      -0.22259,
      46.14206
    ]
  }
}