{
  "type": "Feature",
  "properties": {
    "name": "Bussière-Dunoise",
    "country": "FR",
    "subdivision": "75",
    "timezone": "Europe/Paris"
  },
  "geometry": {
    "type": "Point",
    "coordinates": [
      1.76228,
      46.25845
    ]
  }
}