{
  "type": "Feature",
  "properties": {
    "name": "Cabariot",
    "country": "FR",
    "subdivision": "75",
    "timezone": "Europe/Paris"
  },
  "geometry": {
    "type": "Point",
    "coordinates": [
      -0.85743,
      45.92553
    ]
  }
}