{
  "type": "Feature",
  "properties": {
    "name": "Carbon-Blanc",
    "country": "FR",
    "subdivision": "75",
    "timezone": "Europe/Paris"
  },
  "geometry": {
    "type": "Point",
    "coordinates": [
      -0.50175,
      44.89501
    ]
  }
}