{
  "type": "Feature",
  "properties": {
    "name": "Carcans",
    "country": "FR",
    "subdivision": "75",
    "timezone": "Europe/Paris"
  },
  "geometry": {
    "type": "Point",
    "coordinates": [
      -1.04479,
      45.07852
    ]
  }
}