{
  "type": "Feature",
  "properties": {
    "name": "Cézac",
    "country": "FR",
    "subdivision": "75",
    "timezone": "Europe/Paris"
  },
  "geometry": {
    "type": "Point",
    "coordinates": [
      -0.41963,
      45.09019
    ]
  }
}