{
  "type": "Feature",
  "properties": {
    "name": "Chaillevette",
    "country": "FR",
    "subdivision": "75",
    "timezone": "Europe/Paris"
  },
  "geometry": {
    "type": "Point",
    "coordinates": [
      -1.05839,
      45.73087
    ]
  }
}