{
  "type": "Feature",
  "properties": {
    "name": "Châtelaillon-Plage",
    "country": "FR",
    "subdivision": "75",
    "timezone": "Europe/Paris"
  },
  "geometry": {
    "type": "Point",
    "coordinates": [
      -1.08845,
      46.07287
    ]
  }
}