{
  "type": "Feature",
  "properties": {
    "name": "Chérac",
    "country": "FR",
    "subdivision": "75",
    "timezone": "Europe/Paris"
  },
  "geometry": {
    "type": "Point",
    "coordinates": [
      -0.43859,
      45.70456
    ]
  }
}