{
  "type": "Feature",
  "properties": {
    "name": "Chiché",
    "country": "FR",
    "subdivision": "75",
    "timezone": "Europe/Paris"
  },
  "geometry": {
    "type": "Point",
    "coordinates": [
      -0.35969,
      46.79713
    ]
  }
}