{
  "type": "Feature",
  "properties": {
    "name": "Clérac",
    "country": "FR",
    "subdivision": "75",
    "timezone": "Europe/Paris"
  },
  "geometry": {
    "type": "Point",
    "coordinates": [
      -0.22736,
      45.18157
    ]
  }
}