{
  "type": "Feature",
  "properties": {
    "name": "Cognac",
    "country": "FR",
    "subdivision": "75",
    "timezone": "Europe/Paris"
  },
  "geometry": {
    "type": "Point",
    "coordinates": [
      -0.32867,
      45.69581
    ]
  }
}