{
  "type": "Feature",
  "properties": {
    "name": "Combrand",
    "country": "FR",
    "subdivision": "75",
    "timezone": "Europe/Paris"
  },
  "geometry": {
    "type": "Point",
    "coordinates": [
      -0.68924,
      46.86451
    ]
  }
}