{
  "type": "Feature",
  "properties": {
    "name": "Couhé",
    "country": "FR",
    "subdivision": "75",
    "timezone": "Europe/Paris"
  },
  "geometry": {
    "type": "Point",
    "coordinates": [
      0.18199,
      46.29982
    ]
  }
}