{
  "type": "Feature",
  "properties": {
    "name": "Cublac",
    "country": "FR",
    "subdivision": "75",
    "timezone": "Europe/Paris"
  },
  "geometry": {
    "type": "Point",
    "coordinates": [
      1.30609,
      45.14488
    ]
  }
}