{
  "type": "Feature",
  "properties": {
    "name": "Étauliers",
    "country": "FR",
    "subdivision": "75",
    "timezone": "Europe/Paris"
  },
  "geometry": {
    "type": "Point",
    "coordinates": [
      -0.57358,
      45.22383
    ]
  }
}