{
  "type": "Feature",
  "properties": {
    "name": "Eymoutiers",
    "country": "FR",
    "subdivision": "75",
    "timezone": "Europe/Paris"
  },
  "geometry": {
    "type": "Point",
    "coordinates": [
      1.74215,
      45.73884
    ]
  }
}