{
  "type": "Feature",
  "properties": {
    "name": "Foulayronnes",
    "country": "FR",
    "subdivision": "75",
    "timezone": "Europe/Paris"
  },
  "geometry": {
    "type": "Point",
    "coordinates": [
      0.64516,
      44.24029
    ]
  }
}