{
  "type": "Feature",
  "properties": {
    "name": "Gironde-sur-Dropt",
    "country": "FR",
    "subdivision": "75",
    "timezone": "Europe/Paris"
  },
  "geometry": {
    "type": "Point",
    "coordinates": [
      -0.08333,
      44.58333
    ]
  }
}