{
  "type": "Feature",
  "properties": {
    "name": "Hagetmau",
    "country": "FR",
    "subdivision": "75",
    "timezone": "Europe/Paris"
  },
  "geometry": {
    "type": "Point",
    "coordinates": [
      -0.59172,
      43.65893
    ]
  }
}