{
  "type": "Feature",
  "properties": {
    "name": "Igon",
    "country": "FR",
    "subdivision": "75",
    "timezone": "Europe/Paris"
  },
  "geometry": {
    "type": "Point",
    "coordinates": [
      -0.23217,
      43.15992
    ]
  }
}