{
  "type": "Feature",
  "properties": {
    "name": "Jurançon",
    "country": "FR",
    "subdivision": "75",
    "timezone": "Europe/Paris"
  },
  "geometry": {
    "type": "Point",
    "coordinates": [
      -0.38694,
      43.2883
    ]
  }
}