{
  "type": "Feature",
  "properties": {
    "name": "La Couronne",
    "country": "FR",
    "subdivision": "75",
    "timezone": "Europe/Paris"
  },
  "geometry": {
    "type": "Point",
    "coordinates": [
      0.09948,
      45.61128
    ]
  }
}