{
  "type": "Feature",
  "properties": {
    "name": "La Réole",
    "country": "FR",
    "subdivision": "75",
    "timezone": "Europe/Paris"
  },
  "geometry": {
    "type": "Point",
    "coordinates": [
      -0.03857,
      44.58239
    ]
  }
}