{
  "type": "Feature",
  "properties": {
    "name": "Lagord",
    "country": "FR",
    "subdivision": "75",
    "timezone": "Europe/Paris"
  },
  "geometry": {
    "type": "Point",
    "coordinates": [
      -1.15387,
      46.18915
    ]
  }
}