{
  "type": "Feature",
  "properties": {
    "name": "Laguenne",
    "country": "FR",
    "subdivision": "75",
    "timezone": "Europe/Paris"
  },
  "geometry": {
    "type": "Point",
    "coordinates": [
      1.78135,
      45.24218
    ]
  }
}