{
  "type": "Feature",
  "properties": {
    "name": "Lalinde",
    "country": "FR",
    "subdivision": "75",
    "timezone": "Europe/Paris"
  },
  "geometry": {
    "type": "Point",
    "coordinates": [
      0.73777,
      44.8368
    ]
  }
}