{
  "type": "Feature",
  "properties": {
    "name": "Lamonzie",
    "country": "FR",
    "subdivision": "75",
    "timezone": "Europe/Paris"
  },
  "geometry": {
    "type": "Point",
    "coordinates": [
      0.39103,
      44.84723
    ]
  }
}