{
  "type": "Feature",
  "properties": {
    "name": "Laroque-Timbaut",
    "country": "FR",
    "subdivision": "75",
    "timezone": "Europe/Paris"
  },
  "geometry": {
    "type": "Point",
    "coordinates": [
      0.76181,
      44.28363
    ]
  }
}