{
  "type": "Feature",
  "properties": {
    "name": "Larressore",
    "country": "FR",
    "subdivision": "75",
    "timezone": "Europe/Paris"
  },
  "geometry": {
    "type": "Point",
    "coordinates": [
      -1.43924,
      43.37024
    ]
  }
}