{
  "type": "Feature",
  "properties": {
    "name": "Laruns",
    "country": "FR",
    "subdivision": "75",
    "timezone": "Europe/Paris"
  },
  "geometry": {
    "type": "Point",
    "coordinates": [
      -0.42658,
      42.98826
    ]
  }
}