{
  "type": "Feature",
  "properties": {
    "name": "Le Buisson-de-Cadouin",
    "country": "FR",
    "subdivision": "75",
    "timezone": "Europe/Paris"
  },
  "geometry": {
    "type": "Point",
    "coordinates": [
      0.91667,
      44.85
    ]
  }
}