{
  "type": "Feature",
  "properties": {
    "name": "Le Pizou",
    "country": "FR",
    "subdivision": "75",
    "timezone": "Europe/Paris"
  },
  "geometry": {
    "type": "Point",
    "coordinates": [
      0.06223,
      45.02514
    ]
  }
}