{
  "type": "Feature",
  "properties": {
    "name": "Le Vigen",
    "country": "FR",
    "subdivision": "75",
    "timezone": "Europe/Paris"
  },
  "geometry": {
    "type": "Point",
    "coordinates": [
      1.28856,
      45.75178
    ]
  }
}