{
  "type": "Feature",
  "properties": {
    "name": "Les Églisottes-et-Chalaures",
    "country": "FR",
    "subdivision": "75",
    "timezone": "Europe/Paris"
  },
  "geometry": {
    "type": "Point",
    "coordinates": [
      -0.03893,
      45.09811
    ]
  }
}