{
  "type": "Feature",
  "properties": {
    "name": "Loubert",
    "country": "FR",
    "subdivision": "75",
    "timezone": "Europe/Paris"
  },
  "geometry": {
    "type": "Point",
    "coordinates": [
      0.58617,
      45.91422
    ]
  }
}