{
  "type": "Feature",
  "properties": {
    "name": "Lugon-et-l'Île-du-Carnay",
    "country": "FR",
    "subdivision": "75",
    "timezone": "Europe/Paris"
  },
  "geometry": {
    "type": "Point",
    "coordinates": [
      -0.33611,
      44.95556
    ]
  }
}