{
  "type": "Feature",
  "properties": {
    "name": "Lussac",
    "country": "FR",
    "subdivision": "75",
    "timezone": "Europe/Paris"
  },
  "geometry": {
    "type": "Point",
    "coordinates": [
      -0.09606,
      44.95024
    ]
  }
}