{
  "type": "Feature",
  "properties": {
    "name": "Macau",
    "country": "FR",
    "subdivision": "75",
    "timezone": "Europe/Paris"
  },
  "geometry": {
    "type": "Point",
    "coordinates": [
      -0.61947,
      45.0064
    ]
  }
}