{
  "type": "Feature",
  "properties": {
    "name": "Mansle",
    "country": "FR",
    "subdivision": "75",
    "timezone": "Europe/Paris"
  },
  "geometry": {
    "type": "Point",
    "coordinates": [
      0.17838,
      45.876
    ]
  }
}