{
  "type": "Feature",
  "properties": {
    "name": "Marcillac",
    "country": "FR",
    "subdivision": "75",
    "timezone": "Europe/Paris"
  },
  "geometry": {
    "type": "Point",
    "coordinates": [
      -0.52379,
      45.2687
    ]
  }
}