{
  "type": "Feature",
  "properties": {
    "name": "Martillac",
    "country": "FR",
    "subdivision": "75",
    "timezone": "Europe/Paris"
  },
  "geometry": {
    "type": "Point",
    "coordinates": [
      -0.53747,
      44.711
    ]
  }
}