{
  "type": "Feature",
  "properties": {
    "name": "Matha",
    "country": "FR",
    "subdivision": "75",
    "timezone": "Europe/Paris"
  },
  "geometry": {
    "type": "Point",
    "coordinates": [
      -0.32009,
      45.86776
    ]
  }
}