{
  "type": "Feature",
  "properties": {
    "name": "Mensignac",
    "country": "FR",
    "subdivision": "75",
    "timezone": "Europe/Paris"
  },
  "geometry": {
    "type": "Point",
    "coordinates": [
      0.56054,
      45.22515
    ]
  }
}