{
  "type": "Feature",
  "properties": {
    "name": "Mimbaste",
    "country": "FR",
    "subdivision": "75",
    "timezone": "Europe/Paris"
  },
  "geometry": {
    "type": "Point",
    "coordinates": [
      -0.97383,
      43.64887
    ]
  }
}