{
  "type": "Feature",
  "properties": {
    "name": "Monein",
    "country": "FR",
    "subdivision": "75",
    "timezone": "Europe/Paris"
  },
  "geometry": {
    "type": "Point",
    "coordinates": [
      -0.57975,
      43.32049
    ]
  }
}