{
  "type": "Feature",
  "properties": {
    "name": "Montendre",
    "country": "FR",
    "subdivision": "75",
    "timezone": "Europe/Paris"
  },
  "geometry": {
    "type": "Point",
    "coordinates": [
      -0.40827,
      45.28557
    ]
  }
}