{
  "type": "Feature",
  "properties": {
    "name": "Montussan",
    "country": "FR",
    "subdivision": "75",
    "timezone": "Europe/Paris"
  },
  "geometry": {
    "type": "Point",
    "coordinates": [
      -0.4281,
      44.88213
    ]
  }
}