{
  "type": "Feature",
  "properties": {
    "name": "Mortagne-sur-Gironde",
    "country": "FR",
    "subdivision": "75",
    "timezone": "Europe/Paris"
  },
  "geometry": {
    "type": "Point",
    "coordinates": [
      -0.78936,
      45.48078
    ]
  }
}