{
  "type": "Feature",
  "properties": {
    "name": "Naintré",
    "country": "FR",
    "subdivision": "75",
    "timezone": "Europe/Paris"
  },
  "geometry": {
    "type": "Point",
    "coordinates": [
      0.48303,
      46.76285
    ]
  }
}