{
  "type": "Feature",
  "properties": {
    "name": "Neuvic",
    "country": "FR",
    "subdivision": "75",
    "timezone": "Europe/Paris"
  },
  "geometry": {
    "type": "Point",
    "coordinates": [
      2.27115,
      45.38134
    ]
  }
}