{
  "type": "Feature",
  "properties": {
    "name": "Nexon",
    "country": "FR",
    "subdivision": "75",
    "timezone": "Europe/Paris"
  },
  "geometry": {
    "type": "Point",
    "coordinates": [
      1.18491,
      45.67988
    ]
  }
}