{
  "type": "Feature",
  "properties": {
    "name": "Notre-Dame-de-Sanilhac",
    "country": "FR",
    "subdivision": "75",
    "timezone": "Europe/Paris"
  },
  "geometry": {
    "type": "Point",
    "coordinates": [
      0.71657,
      45.12089
    ]
  }
}