{
  "type": "Feature",
  "properties": {
    "name": "Oradour-sur-Vayres",
    "country": "FR",
    "subdivision": "75",
    "timezone": "Europe/Paris"
  },
  "geometry": {
    "type": "Point",
    "coordinates": [
      0.86677,
      45.73189
    ]
  }
}