{
  "type": "Feature",
  "properties": {
    "name": "Périgueux",
    "country": "FR",
    "subdivision": "75",
    "timezone": "Europe/Paris"
  },
  "geometry": {
    "type": "Point",
    "coordinates": [
      0.71439,
      45.18691
    ]
  }
}