{
  "type": "Feature",
  "properties": {
    "name": "Pierre-Buffière",
    "country": "FR",
    "subdivision": "75",
    "timezone": "Europe/Paris"
  },
  "geometry": {
    "type": "Point",
    "coordinates": [
      1.35895,
      45.69451
    ]
  }
}