{
  "type": "Feature",
  "properties": {
    "name": "Port-Sainte-Marie",
    "country": "FR",
    "subdivision": "75",
    "timezone": "Europe/Paris"
  },
  "geometry": {
    "type": "Point",
    "coordinates": [
      0.39283,
      44.25091
    ]
  }
}