{
  "type": "Feature",
  "properties": {
    "name": "Pouillon",
    "country": "FR",
    "subdivision": "75",
    "timezone": "Europe/Paris"
  },
  "geometry": {
    "type": "Point",
    "coordinates": [
      -0.99625,
      43.6049
    ]
  }
}