{
  "type": "Feature",
  "properties": {
    "name": "Preignac",
    "country": "FR",
    "subdivision": "75",
    "timezone": "Europe/Paris"
  },
  "geometry": {
    "type": "Point",
    "coordinates": [
      -0.29522,
      44.58489
    ]
  }
}