{
  "type": "Feature",
  "properties": {
    "name": "Rauzan",
    "country": "FR",
    "subdivision": "75",
    "timezone": "Europe/Paris"
  },
  "geometry": {
    "type": "Point",
    "coordinates": [
      -0.12506,
      44.77813
    ]
  }
}