{
  "type": "Feature",
  "properties": {
    "name": "Razac-sur-l'Isle",
    "country": "FR",
    "subdivision": "75",
    "timezone": "Europe/Paris"
  },
  "geometry": {
    "type": "Point",
    "coordinates": [
      0.59976,
      45.16382
    ]
  }
}