{
  "type": "Feature",
  "properties": {
    "name": "Rivière",
    "country": "FR",
    "subdivision": "75",
    "timezone": "Europe/Paris"
  },
  "geometry": {
    "type": "Point",
    "coordinates": [
      -1.15164,
      43.67958
    ]
  }
}