{
  "type": "Feature",
  "properties": {
    "name": "Saint-Porchaire",
    "country": "FR",
    "subdivision": "75",
    "timezone": "Europe/Paris"
  },
  "geometry": {
    "type": "Point",
    "coordinates": [
      -0.78414,
      45.82101
    ]
  }
}