{
  "type": "Feature",
  "properties": {
    "name": "Sainte-Terre",
    "country": "FR",
    "subdivision": "75",
    "timezone": "Europe/Paris"
  },
  "geometry": {
    "type": "Point",
    "coordinates": [
      -0.11289,
      44.82835
    ]
  }
}