{
  "type": "Feature",
  "properties": {
    "name": "Saint-Jean-de-Thouars",
    "country": "FR",
    "subdivision": "75",
    "timezone": "Europe/Paris"
  },
  "geometry": {
    "type": "Point",
    "coordinates": [
      -0.21161,
      46.96392
    ]
  }
}