{
  "type": "Feature",
  "properties": {
    "name": "Saint-Junien",
    "country": "FR",
    "subdivision": "75",
    "timezone": "Europe/Paris"
  },
  "geometry": {
    "type": "Point",
    "coordinates": [
      0.90158,
      45.88746
    ]
  }
}