{
  "type": "Feature",
  "properties": {
    "name": "Saint-Denis-de-Pile",
    "country": "FR",
    "subdivision": "75",
    "timezone": "Europe/Paris"
  },
  "geometry": {
    "type": "Point",
    "coordinates": [
      -0.20607,
      44.9915
    ]
  }
}