{
  "type": "Feature",
  "properties": {
    "name": "Saint-Ciers-sur-Gironde",
    "country": "FR",
    "subdivision": "75",
    "timezone": "Europe/Paris"
  },
  "geometry": {
    "type": "Point",
    "coordinates": [
      -0.61075,
      45.29097
    ]
  }
}