{
  "type": "Feature",
  "properties": {
    "name": "Saint-Gelais",
    "country": "FR",
    "subdivision": "75",
    "timezone": "Europe/Paris"
  },
  "geometry": {
    "type": "Point",
    "coordinates": [
      -0.38986,
      46.38292
    ]
  }
}