{
  "type": "Feature",
  "properties": {
    "name": "Saint-Jean-de-Sauves",
    "country": "FR",
    "subdivision": "75",
    "timezone": "Europe/Paris"
  },
  "geometry": {
    "type": "Point",
    "coordinates": [
      0.09224,
      46.84065
    ]
  }
}