{
  "type": "Feature",
  "properties": {
    "name": "Saint-Vaury",
    "country": "FR",
    "subdivision": "75",
    "timezone": "Europe/Paris"
  },
  "geometry": {
    "type": "Point",
    "coordinates": [
      1.7557,
      46.20424
    ]
  }
}