{
  "type": "Feature",
  "properties": {
    "name": "Saint-Yzan-de-Soudiac",
    "country": "FR",
    "subdivision": "75",
    "timezone": "Europe/Paris"
  },
  "geometry": {
    "type": "Point",
    "coordinates": [
      -0.4109,
      45.14054
    ]
  }
}