{
  "type": "Feature",
  "properties": {
    "name": "Saint-Genis-de-Saintonge",
    "country": "FR",
    "subdivision": "75",
    "timezone": "Europe/Paris"
  },
  "geometry": {
    "type": "Point",
    "coordinates": [
      -0.56832,
      45.48219
    ]
  }
}