{
  "type": "Feature",
  "properties": {
    "name": "Saint-Vincent-de-Tyrosse",
    "country": "FR",
    "subdivision": "75",
    "timezone": "Europe/Paris"
  },
  "geometry": {
    "type": "Point",
    "coordinates": [
      -1.30428,
      43.66071
    ]
  }
}