{
  "type": "Feature",
  "properties": {
    "name": "Saint-Laurent-de-la-Prée",
    "country": "FR",
    "subdivision": "75",
    "timezone": "Europe/Paris"
  },
  "geometry": {
    "type": "Point",
    "coordinates": [
      -1.04106,
      45.98181
    ]
  }
}