{
  "type": "Feature",
  "properties": {
    "name": "Sainte-Marie-de-Gosse",
    "country": "FR",
    "subdivision": "75",
    "timezone": "Europe/Paris"
  },
  "geometry": {
    "type": "Point",
    "coordinates": [
      -0.23333,
      43.55
    ]
  }
}