{
  "type": "Feature",
  "properties": {
    "name": "Saint-Martin-de-Hinx",
    "country": "FR",
    "subdivision": "75",
    "timezone": "Europe/Paris"
  },
  "geometry": {
    "type": "Point",
    "coordinates": [
      -1.2709,
      43.58171
    ]
  }
}