{
  "type": "Feature",
  "properties": {
    "name": "Saint-Julien-en-Born",
    "country": "FR",
    "subdivision": "75",
    "timezone": "Europe/Paris"
  },
  "geometry": {
    "type": "Point",
    "coordinates": [
      -1.22579,
      44.06287
    ]
  }
}