{
  "type": "Feature",
  "properties": {
    "name": "Samadet",
    "country": "FR",
    "subdivision": "75",
    "timezone": "Europe/Paris"
  },
  "geometry": {
    "type": "Point",
    "coordinates": [
      -0.48659,
      43.63906
    ]
  }
}