{
  "type": "Feature",
  "properties": {
    "name": "Sauveterre-de-Béarn",
    "country": "FR",
    "subdivision": "75",
    "timezone": "Europe/Paris"
  },
  "geometry": {
    "type": "Point",
    "coordinates": [
      -0.94011,
      43.3993
    ]
  }
}