{
  "type": "Feature",
  "properties": {
    "name": "Savigny-Lévescault",
    "country": "FR",
    "subdivision": "75",
    "timezone": "Europe/Paris"
  },
  "geometry": {
    "type": "Point",
    "coordinates": [
      0.47701,
      46.53575
    ]
  }
}