{
  "type": "Feature",
  "properties": {
    "name": "Scorbé-Clairvaux",
    "country": "FR",
    "subdivision": "75",
    "timezone": "Europe/Paris"
  },
  "geometry": {
    "type": "Point",
    "coordinates": [
      0.41344,
      46.81303
    ]
  }
}