{
  "type": "Feature",
  "properties": {
    "name": "Secondigny",
    "country": "FR",
    "subdivision": "75",
    "timezone": "Europe/Paris"
  },
  "geometry": {
    "type": "Point",
    "coordinates": [
      -0.41677,
      46.60967
    ]
  }
}