{
  "type": "Feature",
  "properties": {
    "name": "Semussac",
    "country": "FR",
    "subdivision": "75",
    "timezone": "Europe/Paris"
  },
  "geometry": {
    "type": "Point",
    "coordinates": [
      -0.91301,
      45.60035
    ]
  }
}