{
  "type": "Feature",
  "properties": {
    "name": "Serres-Castet",
    "country": "FR",
    "subdivision": "75",
    "timezone": "Europe/Paris"
  },
  "geometry": {
    "type": "Point",
    "coordinates": [
      -0.35497,
      43.38647
    ]
  }
}