{
  "type": "Feature",
  "properties": {
    "name": "Sorges",
    "country": "FR",
    "subdivision": "75",
    "timezone": "Europe/Paris"
  },
  "geometry": {
    "type": "Point",
    "coordinates": [
      0.87352,
      45.30743
    ]
  }
}