{
  "type": "Feature",
  "properties": {
    "name": "Targon",
    "country": "FR",
    "subdivision": "75",
    "timezone": "Europe/Paris"
  },
  "geometry": {
    "type": "Point",
    "coordinates": [
      -0.2637,
      44.73507
    ]
  }
}