{
  "type": "Feature",
  "properties": {
    "name": "Tonnay-Boutonne",
    "country": "FR",
    "subdivision": "75",
    "timezone": "Europe/Paris"
  },
  "geometry": {
    "type": "Point",
    "coordinates": [
      -0.70715,
      45.96787
    ]
  }
}