{
  "type": "Feature",
  "properties": {
    "name": "Toulenne",
    "country": "FR",
    "subdivision": "75",
    "timezone": "Europe/Paris"
  },
  "geometry": {
    "type": "Point",
    "coordinates": [
      -0.26259,
      44.55862
    ]
  }
}