{
  "type": "Feature",
  "properties": {
    "name": "Ussel",
    "country": "FR",
    "subdivision": "75",
    "timezone": "Europe/Paris"
  },
  "geometry": {
    "type": "Point",
    "coordinates": [
      2.30917,
      45.54804
    ]
  }
}