{
  "type": "Feature",
  "properties": {
    "name": "Vendays-Montalivet",
    "country": "FR",
    "subdivision": "75",
    "timezone": "Europe/Paris"
  },
  "geometry": {
    "type": "Point",
    "coordinates": [
      -1.06062,
      45.35588
    ]
  }
}