{
  "type": "Feature",
  "properties": {
    "name": "Vergt",
    "country": "FR",
    "subdivision": "75",
    "timezone": "Europe/Paris"
  },
  "geometry": {
    "type": "Point",
    "coordinates": [
      0.7178,
      45.0268
    ]
  }
}