{
  "type": "Feature",
  "properties": {
    "name": "Vianne",
    "country": "FR",
    "subdivision": "75",
    "timezone": "Europe/Paris"
  },
  "geometry": {
    "type": "Point",
    "coordinates": [
      0.32056,
      44.1972
    ]
  }
}