{
  "type": "Feature",
  "properties": {
    "name": "Villenave-d'Ornon",
    "country": "FR",
    "subdivision": "75",
    "timezone": "Europe/Paris"
  },
  "geometry": {
    "type": "Point",
    "coordinates": [
      -0.56707,
      44.77935
    ]
  }
}