{
  "type": "Feature",
  "properties": {
    "name": "Villeréal",
    "country": "FR",
    "subdivision": "75",
    "timezone": "Europe/Paris"
  },
  "geometry": {
    "type": "Point",
    "coordinates": [
      0.74306,
      44.63746
    ]
  }
}