{
  "type": "Feature",
  "properties": {
    "name": "Villefranque",
    "country": "FR",
    "subdivision": "75",
    "timezone": "Europe/Paris"
  },
  "geometry": {
    "type": "Point",
    "coordinates": [
      -1.45289,
      43.43742
    ]
  }
}