{
  "type": "Feature",
  "properties": {
    "name": "Virazeil",
    "country": "FR",
    "subdivision": "75",
    "timezone": "Europe/Paris"
  },
  "geometry": {
    "type": "Point",
    "coordinates": [
      0.21993,
      44.50695
    ]
  }
}