{
  "type": "Feature",
  "properties": {
    "name": "Ychoux",
    "country": "FR",
    "subdivision": "75",
    "timezone": "Europe/Paris"
  },
  "geometry": {
    "type": "Point",
    "coordinates": [
      -0.95796,
      44.32772
    ]
  }
}