{
  "type": "Feature",
  "properties": {
    "name": "Horadiz",
    "country": "AZ",
    "subdivision": "18",
    "timezone": "Asia/Baku"
  },
  "geometry": {
    "type": "Point",
    "coordinates": [
      47.33496,
      39.45015
    ]
  }
}