{
  "type": "Feature",
  "properties": {
    "name": "Görbeháza",
    "country": "HU",
    "subdivision": "10",
    "timezone": "Europe/Budapest"
  },
  "geometry": {
    "type": "Point",
    "coordinates": [
      21.23333,
      47.83333
    ]
  }
}