{
  "type": "Feature",
  "properties": {
    "name": "Polgár",
    "country": "HU",
    "subdivision": "10",
    "timezone": "Europe/Budapest"
  },
  "geometry": {
    "type": "Point",
    "coordinates": [
      21.11667,
      47.86667
    ]
  }
}