{
  "type": "Feature",
  "properties": {
    "name": "New Mirpur",
    "country": "PK",
    "subdivision": "06",
    "timezone": "Asia/Karachi"
  },
  "geometry": {
    "type": "Point",
    "coordinates": [
      73.75187,
      33.14782
    ]
  }
}