{
  "type": "Feature",
  "properties": {
    "name": "Balky",
    "country": "UA",
    "subdivision": "26",
    "timezone": "Europe/Zaporozhye"
  },
  "geometry": {
    "type": "Point",
    "coordinates": [
      34.93132,
      47.38596
    ]
  }
}