{
  "type": "Feature",
  "properties": {
    "name": "Kyrylivka",
    "country": "UA",
    "subdivision": "26",
    "timezone": "Europe/Zaporozhye"
  },
  "geometry": {
    "type": "Point",
    "coordinates": [
      35.3701,
      46.37179
    ]
  }
}