{
  "type": "Feature",
  "properties": {
    "name": "Mykhaylivka",
    "country": "UA",
    "subdivision": "26",
    "timezone": "Europe/Zaporozhye"
  },
  "geometry": {
    "type": "Point",
    "coordinates": [
      35.22207,
      47.26863
    ]
  }
}