{
  "type": "Feature",
  "properties": {
    "name": "Orikhiv",
    "country": "UA",
    "subdivision": "26",
    "timezone": "Europe/Zaporozhye"
  },
  "geometry": {
    "type": "Point",
    "coordinates": [
      35.78333,
      47.57613
    ]
  }
}