{
  "type": "Feature",
  "properties": {
    "name": "Pryazovske",
    "country": "UA",
    "subdivision": "26",
    "timezone": "Europe/Zaporozhye"
  },
  "geometry": {
    "type": "Point",
    "coordinates": [
      35.64082,
      46.73123
    ]
  }
}