{
  "type": "Feature",
  "properties": {
    "name": "Prymorsk",
    "country": "UA",
    "subdivision": "26",
    "timezone": "Europe/Zaporozhye"
  },
  "geometry": {
    "type": "Point",
    "coordinates": [
      36.34599,
      46.73415
    ]
  }
}