{
  "type": "Feature",
  "properties": {
    "name": "Pryshyb",
    "country": "UA",
    "subdivision": "26",
    "timezone": "Europe/Zaporozhye"
  },
  "geometry": {
    "type": "Point",
    "coordinates": [
      35.32426,
      47.25614
    ]
  }
}