{
  "type": "Feature",
  "properties": {
    "name": "Velyka Bilozerka",
    "country": "UA",
    "subdivision": "26",
    "timezone": "Europe/Zaporozhye"
  },
  "geometry": {
    "type": "Point",
    "coordinates": [
      34.68457,
      47.27572
    ]
  }
}