{
  "type": "Feature",
  "properties": {
    "name": "Vilnyansk",
    "country": "UA",
    "subdivision": "26",
    "timezone": "Europe/Zaporozhye"
  },
  "geometry": {
    "type": "Point",
    "coordinates": [
      35.44034,
      47.94768
    ]
  }
}