{
  "type": "Feature",
  "properties": {
    "name": "Lyefjell",
    "country": "NO",
    "subdivision": "14",
    "timezone": "Europe/Oslo"
  },
  "geometry": {
    "type": "Point",
    "coordinates": [
      5.73615,
      58.73539
    ]
  }
}