{
  "type": "Feature",
  "properties": {
    "name": "Sandnes",
    "country": "NO",
    "subdivision": "14",
    "timezone": "Europe/Oslo"
  },
  "geometry": {
    "type": "Point",
    "coordinates": [
      5.73521,
      58.85244
    ]
  }
}