{
  "type": "Feature",
  "properties": {
    "name": "Tây Ninh",
    "country": "VN",
    "subdivision": "33",
    "timezone": "Asia/Ho_Chi_Minh"
  },
  "geometry": {
    "type": "Point",
    "coordinates": [
      106.09828,
      11.31004
    ]
  }
}