{
  "type": "Feature",
  "properties": {
    "name": "Ansongo",
    "country": "ML",
    "subdivision": "09",
    "timezone": "Africa/Bamako"
  },
  "geometry": {
    "type": "Point",
    "coordinates": [
      0.5022,
      15.6597
    ]
  }
}