{
  "type": "Feature",
  "properties": {
    "name": "Samuil",
    "country": "BG",
    "subdivision": "52",
    "timezone": "Europe/Sofia"
  },
  "geometry": {
    "type": "Point",
    "coordinates": [
      26.75,
      43.51667
    ]
  }
}