{
  "type": "Feature",
  "properties": {
    "name": "Tsar Kaloyan",
    "country": "BG",
    "subdivision": "52",
    "timezone": "Europe/Sofia"
  },
  "geometry": {
    "type": "Point",
    "coordinates": [
      26.25,
      43.61667
    ]
  }
}