{
  "type": "Feature",
  "properties": {
    "name": "Ella Town",
    "country": "LK",
    "subdivision": "35",
    "timezone": "Asia/Colombo"
  },
  "geometry": {
    "type": "Point",
    "coordinates": [
      81.0463,
      6.8756
    ]
  }
}