{
  "type": "Feature",
  "properties": {
    "name": "Marabella",
    "country": "TT",
    "subdivision": "10",
    "timezone": "America/Port_of_Spain"
  },
  "geometry": {
    "type": "Point",
    "coordinates": [
      -61.44671,
      10.30618
    ]
  }
}