{
  "type": "Feature",
  "properties": {
    "name": "Mon Repos",
    "country": "TT",
    "subdivision": "10",
    "timezone": "America/Port_of_Spain"
  },
  "geometry": {
    "type": "Point",
    "coordinates": [
      -61.4459,
      10.27979
    ]
  }
}