{
  "type": "Feature",
  "properties": {
    "name": "Notre Dame",
    "country": "MU",
    "subdivision": "16",
    "timezone": "Indian/Mauritius"
  },
  "geometry": {
    "type": "Point",
    "coordinates": [
      57.55969,
      -20.14298
    ]
  }
}