{
  "type": "Feature",
  "properties": {
    "name": "Kēng Tung",
    "country": "MM",
    "subdivision": "11",
    "timezone": "Asia/Yangon"
  },
  "geometry": {
    "type": "Point",
    "coordinates": [
      99.92676,
      21.63093
    ]
  }
}