{
  "type": "Feature",
  "properties": {
    "name": "Cereté",
    "country": "CO",
    "subdivision": "12",
    "timezone": "America/Bogota"
  },
  "geometry": {
    "type": "Point",
    "coordinates": [
      -75.79052,
      8.88479
    ]
  }
}