{
  "type": "Feature",
  "properties": {
    "name": "Lorica",
    "country": "CO",
    "subdivision": "12",
    "timezone": "America/Bogota"
  },
  "geometry": {
    "type": "Point",
    "coordinates": [
      -75.8135,
      9.23648
    ]
  }
}