{
  "type": "Feature",
  "properties": {
    "name": "Montería",
    "country": "CO",
    "subdivision": "12",
    "timezone": "America/Bogota"
  },
  "geometry": {
    "type": "Point",
    "coordinates": [
      -75.88143,
      8.74798
    ]
  }
}