{
  "type": "Feature",
  "properties": {
    "name": "La Fermina",
    "country": "PR",
    "subdivision": "085",
    "timezone": "America/Puerto_Rico"
  },
  "geometry": {
    "type": "Point",
    "coordinates": [
      -65.8535,
      18.17551
    ]
  }
}