{
  "type": "Feature",
  "properties": {
    "name": "Cernavodă",
    "country": "RO",
    "subdivision": "14",
    "timezone": "Europe/Bucharest"
  },
  "geometry": {
    "type": "Point",
    "coordinates": [
      28.03273,
      44.33957
    ]
  }
}