{
  "type": "Feature",
  "properties": {
    "name": "Cogealac",
    "country": "RO",
    "subdivision": "14",
    "timezone": "Europe/Bucharest"
  },
  "geometry": {
    "type": "Point",
    "coordinates": [
      28.56667,
      44.55
    ]
  }
}