{
  "type": "Feature",
  "properties": {
    "name": "Crucea",
    "country": "RO",
    "subdivision": "14",
    "timezone": "Europe/Bucharest"
  },
  "geometry": {
    "type": "Point",
    "coordinates": [
      28.23333,
      44.53333
    ]
  }
}