{
  "type": "Feature",
  "properties": {
    "name": "Piatra",
    "country": "RO",
    "subdivision": "14",
    "timezone": "Europe/Bucharest"
  },
  "geometry": {
    "type": "Point",
    "coordinates": [
      28.56143,
      44.40492
    ]
  }
}