{
  "type": "Feature",
  "properties": {
    "name": "Satu Nou",
    "country": "RO",
    "subdivision": "14",
    "timezone": "Europe/Bucharest"
  },
  "geometry": {
    "type": "Point",
    "coordinates": [
      28.22579,
      44.26918
    ]
  }
}