{
  "type": "Feature",
  "properties": {
    "name": "Tortoman",
    "country": "RO",
    "subdivision": "14",
    "timezone": "Europe/Bucharest"
  },
  "geometry": {
    "type": "Point",
    "coordinates": [
      28.21667,
      44.35
    ]
  }
}