{
  "type": "Feature",
  "properties": {
    "name": "Aksakovo",
    "country": "RU",
    "subdivision": "08",
    "timezone": "Asia/Yekaterinburg"
  },
  "geometry": {
    "type": "Point",
    "coordinates": [
      54.15,
      54.03333
    ]
  }
}