{
  "type": "Feature",
  "properties": {
    "name": "Ak”yar",
    "country": "RU",
    "subdivision": "08",
    "timezone": "Asia/Yekaterinburg"
  },
  "geometry": {
    "type": "Point",
    "coordinates": [
      58.22136,
      51.85905
    ]
  }
}