{
  "type": "Feature",
  "properties": {
    "name": "Asanovo",
    "country": "RU",
    "subdivision": "08",
    "timezone": "Asia/Yekaterinburg"
  },
  "geometry": {
    "type": "Point",
    "coordinates": [
      55.49083,
      54.89418
    ]
  }
}