{
  "type": "Feature",
  "properties": {
    "name": "Askino",
    "country": "RU",
    "subdivision": "08",
    "timezone": "Asia/Yekaterinburg"
  },
  "geometry": {
    "type": "Point",
    "coordinates": [
      56.57831,
      56.09013
    ]
  }
}