{
  "type": "Feature",
  "properties": {
    "name": "Ishimbay",
    "country": "RU",
    "subdivision": "08",
    "timezone": "Asia/Yekaterinburg"
  },
  "geometry": {
    "type": "Point",
    "coordinates": [
      56.04149,
      53.45446
    ]
  }
}