{
  "type": "Feature",
  "properties": {
    "name": "Isyangulovo",
    "country": "RU",
    "subdivision": "08",
    "timezone": "Asia/Yekaterinburg"
  },
  "geometry": {
    "type": "Point",
    "coordinates": [
      56.58043,
      52.18584
    ]
  }
}