{
  "type": "Feature",
  "properties": {
    "name": "Maginsk",
    "country": "RU",
    "subdivision": "08",
    "timezone": "Asia/Yekaterinburg"
  },
  "geometry": {
    "type": "Point",
    "coordinates": [
      56.96583,
      55.76338
    ]
  }
}