{
  "type": "Feature",
  "properties": {
    "name": "Meleuz",
    "country": "RU",
    "subdivision": "08",
    "timezone": "Asia/Yekaterinburg"
  },
  "geometry": {
    "type": "Point",
    "coordinates": [
      55.93277,
      52.96467
    ]
  }
}