{
  "type": "Feature",
  "properties": {
    "name": "Mesyagutovo",
    "country": "RU",
    "subdivision": "08",
    "timezone": "Asia/Yekaterinburg"
  },
  "geometry": {
    "type": "Point",
    "coordinates": [
      58.25278,
      55.53028
    ]
  }
}