{
  "type": "Feature",
  "properties": {
    "name": "Mikhaylovka",
    "country": "RU",
    "subdivision": "08",
    "timezone": "Asia/Yekaterinburg"
  },
  "geometry": {
    "type": "Point",
    "coordinates": [
      55.89193,
      54.805
    ]
  }
}