{
  "type": "Feature",
  "properties": {
    "name": "Novobelokatay",
    "country": "RU",
    "subdivision": "08",
    "timezone": "Asia/Yekaterinburg"
  },
  "geometry": {
    "type": "Point",
    "coordinates": [
      58.9549,
      55.7062
    ]
  }
}