{
  "type": "Feature",
  "properties": {
    "name": "Starobaltachevo",
    "country": "RU",
    "subdivision": "08",
    "timezone": "Asia/Yekaterinburg"
  },
  "geometry": {
    "type": "Point",
    "coordinates": [
      55.928,
      56.0017
    ]
  }
}