{
  "type": "Feature",
  "properties": {
    "name": "Tolbazy",
    "country": "RU",
    "subdivision": "08",
    "timezone": "Asia/Yekaterinburg"
  },
  "geometry": {
    "type": "Point",
    "coordinates": [
      55.88248,
      54.02408
    ]
  }
}