{
  "type": "Feature",
  "properties": {
    "name": "Tuymazy",
    "country": "RU",
    "subdivision": "08",
    "timezone": "Asia/Yekaterinburg"
  },
  "geometry": {
    "type": "Point",
    "coordinates": [
      53.7097,
      54.60666
    ]
  }
}