{
  "type": "Feature",
  "properties": {
    "name": "Verkhniye Tatyshly",
    "country": "RU",
    "subdivision": "08",
    "timezone": "Asia/Yekaterinburg"
  },
  "geometry": {
    "type": "Point",
    "coordinates": [
      55.8575,
      56.29117
    ]
  }
}