{
  "type": "Feature",
  "properties": {
    "name": "Zirgan",
    "country": "RU",
    "subdivision": "08",
    "timezone": "Asia/Yekaterinburg"
  },
  "geometry": {
    "type": "Point",
    "coordinates": [
      55.9185,
      53.2222
    ]
  }
}