{
  "type": "Feature",
  "properties": {
    "name": "Bangolo",
    "country": "CI",
    "subdivision": "78",
    "timezone": "Africa/Abidjan"
  },
  "geometry": {
    "type": "Point",
    "coordinates": [
      -7.48639,
      7.01232
    ]
  }
}