{
  "type": "Feature",
  "properties": {
    "name": "Danané",
    "country": "CI",
    "subdivision": "78",
    "timezone": "Africa/Abidjan"
  },
  "geometry": {
    "type": "Point",
    "coordinates": [
      -8.15498,
      7.25957
    ]
  }
}