{
  "type": "Feature",
  "properties": {
    "name": "Deadwood",
    "country": "US",
    "subdivision": "SD",
    "timezone": "America/Denver"
  },
  "geometry": {
    "type": "Point",
    "coordinates": [
      -103.72964,
      44.37665
    ]
  }
}