{
  "type": "Feature",
  "properties": {
    "name": "Dell Rapids",
    "country": "US",
    "subdivision": "SD",
    "timezone": "America/Chicago"
  },
  "geometry": {
    "type": "Point",
    "coordinates": [
      -96.70616,
      43.82608
    ]
  }
}