{
  "type": "Feature",
  "properties": {
    "name": "Hot Springs",
    "country": "US",
    "subdivision": "SD",
    "timezone": "America/Denver"
  },
  "geometry": {
    "type": "Point",
    "coordinates": [
      -103.47436,
      43.43165
    ]
  }
}