{
  "type": "Feature",
  "properties": {
    "name": "Huron",
    "country": "US",
    "subdivision": "SD",
    "timezone": "America/Chicago"
  },
  "geometry": {
    "type": "Point",
    "coordinates": [
      -98.21426,
      44.36332
    ]
  }
}