{
  "type": "Feature",
  "properties": {
    "name": "Milbank",
    "country": "US",
    "subdivision": "SD",
    "timezone": "America/Chicago"
  },
  "geometry": {
    "type": "Point",
    "coordinates": [
      -96.63562,
      45.21913
    ]
  }
}