{
  "type": "Feature",
  "properties": {
    "name": "Oglala",
    "country": "US",
    "subdivision": "SD",
    "timezone": "America/Denver"
  },
  "geometry": {
    "type": "Point",
    "coordinates": [
      -102.73962,
      43.18859
    ]
  }
}