{
  "type": "Feature",
  "properties": {
    "name": "Pierre",
    "country": "US",
    "subdivision": "SD",
    "timezone": "America/Chicago"
  },
  "geometry": {
    "type": "Point",
    "coordinates": [
      -100.35097,
      44.36832
    ]
  }
}