{
  "type": "Feature",
  "properties": {
    "name": "Springfield",
    "country": "US",
    "subdivision": "SD",
    "timezone": "America/Chicago"
  },
  "geometry": {
    "type": "Point",
    "coordinates": [
      -97.89729,
      42.85417
    ]
  }
}