{
  "type": "Feature",
  "properties": {
    "name": "Tea",
    "country": "US",
    "subdivision": "SD",
    "timezone": "America/Chicago"
  },
  "geometry": {
    "type": "Point",
    "coordinates": [
      -96.83588,
      43.44637
    ]
  }
}