{
  "type": "Feature",
  "properties": {
    "name": "Albion",
    "country": "US",
    "subdivision": "NY",
    "timezone": "America/New_York"
  },
  "geometry": {
    "type": "Point",
    "coordinates": [
      -78.19363,
      43.24645
    ]
  }
}