{
  "type": "Feature",
  "properties": {
    "name": "Amagansett",
    "country": "US",
    "subdivision": "NY",
    "timezone": "America/New_York"
  },
  "geometry": {
    "type": "Point",
    "coordinates": [
      -72.14369,
      40.97371
    ]
  }
}