{
  "type": "Feature",
  "properties": {
    "name": "Aquebogue",
    "country": "US",
    "subdivision": "NY",
    "timezone": "America/New_York"
  },
  "geometry": {
    "type": "Point",
    "coordinates": [
      -72.62704,
      40.94454
    ]
  }
}