{
  "type": "Feature",
  "properties": {
    "name": "Athens",
    "country": "US",
    "subdivision": "NY",
    "timezone": "America/New_York"
  },
  "geometry": {
    "type": "Point",
    "coordinates": [
      -73.80957,
      42.26036
    ]
  }
}