{
  "type": "Feature",
  "properties": {
    "name": "Avon",
    "country": "US",
    "subdivision": "NY",
    "timezone": "America/New_York"
  },
  "geometry": {
    "type": "Point",
    "coordinates": [
      -77.74556,
      42.91201
    ]
  }
}