{
  "type": "Feature",
  "properties": {
    "name": "Barryville",
    "country": "US",
    "subdivision": "NY",
    "timezone": "America/New_York"
  },
  "geometry": {
    "type": "Point",
    "coordinates": [
      -74.911,
      41.47759
    ]
  }
}