{
  "type": "Feature",
  "properties": {
    "name": "Bayville",
    "country": "US",
    "subdivision": "NY",
    "timezone": "America/New_York"
  },
  "geometry": {
    "type": "Point",
    "coordinates": [
      -73.56207,
      40.91065
    ]
  }
}