{
  "type": "Feature",
  "properties": {
    "name": "Bellerose Terrace",
    "country": "US",
    "subdivision": "NY",
    "timezone": "America/New_York"
  },
  "geometry": {
    "type": "Point",
    "coordinates": [
      -73.72596,
      40.72066
    ]
  }
}