{
  "type": "Feature",
  "properties": {
    "name": "Blauvelt",
    "country": "US",
    "subdivision": "NY",
    "timezone": "America/New_York"
  },
  "geometry": {
    "type": "Point",
    "coordinates": [
      -73.95764,
      41.06343
    ]
  }
}