{
  "type": "Feature",
  "properties": {
    "name": "Bridgeport",
    "country": "US",
    "subdivision": "NY",
    "timezone": "America/New_York"
  },
  "geometry": {
    "type": "Point",
    "coordinates": [
      -75.96936,
      43.15535
    ]
  }
}