{
  "type": "Feature",
  "properties": {
    "name": "Brighton",
    "country": "US",
    "subdivision": "NY",
    "timezone": "America/New_York"
  },
  "geometry": {
    "type": "Point",
    "coordinates": [
      -77.55055,
      43.14756
    ]
  }
}