{
  "type": "Feature",
  "properties": {
    "name": "Brookville",
    "country": "US",
    "subdivision": "NY",
    "timezone": "America/New_York"
  },
  "geometry": {
    "type": "Point",
    "coordinates": [
      -73.56735,
      40.81316
    ]
  }
}