{
  "type": "Feature",
  "properties": {
    "name": "Brooklyn Heights",
    "country": "US",
    "subdivision": "NY",
    "timezone": "America/New_York"
  },
  "geometry": {
    "type": "Point",
    "coordinates": [
      -73.99375,
      40.69538
    ]
  }
}