{
  "type": "Feature",
  "properties": {
    "name": "Brownsville",
    "country": "US",
    "subdivision": "NY",
    "timezone": "America/New_York"
  },
  "geometry": {
    "type": "Point",
    "coordinates": [
      -73.92014,
      40.66094
    ]
  }
}