{
  "type": "Feature",
  "properties": {
    "name": "Bushwick",
    "country": "US",
    "subdivision": "NY",
    "timezone": "America/New_York"
  },
  "geometry": {
    "type": "Point",
    "coordinates": [
      -73.91875,
      40.69427
    ]
  }
}