{
  "type": "Feature",
  "properties": {
    "name": "Cairo",
    "country": "US",
    "subdivision": "NY",
    "timezone": "America/New_York"
  },
  "geometry": {
    "type": "Point",
    "coordinates": [
      -73.99847,
      42.29897
    ]
  }
}