{
  "type": "Feature",
  "properties": {
    "name": "Cassville",
    "country": "US",
    "subdivision": "NY",
    "timezone": "America/New_York"
  },
  "geometry": {
    "type": "Point",
    "coordinates": [
      -75.25433,
      42.9459
    ]
  }
}