{
  "type": "Feature",
  "properties": {
    "name": "Catskill",
    "country": "US",
    "subdivision": "NY",
    "timezone": "America/New_York"
  },
  "geometry": {
    "type": "Point",
    "coordinates": [
      -73.86457,
      42.21731
    ]
  }
}