{
  "type": "Feature",
  "properties": {
    "name": "Celoron",
    "country": "US",
    "subdivision": "NY",
    "timezone": "America/New_York"
  },
  "geometry": {
    "type": "Point",
    "coordinates": [
      -79.2831,
      42.1095
    ]
  }
}