{
  "type": "Feature",
  "properties": {
    "name": "Central Square",
    "country": "US",
    "subdivision": "NY",
    "timezone": "America/New_York"
  },
  "geometry": {
    "type": "Point",
    "coordinates": [
      -76.14604,
      43.28674
    ]
  }
}