{
  "type": "Feature",
  "properties": {
    "name": "Chinatown",
    "country": "US",
    "subdivision": "NY",
    "timezone": "America/New_York"
  },
  "geometry": {
    "type": "Point",
    "coordinates": [
      -73.99625,
      40.71649
    ]
  }
}