{
  "type": "Feature",
  "properties": {
    "name": "Clarence Center",
    "country": "US",
    "subdivision": "NY",
    "timezone": "America/New_York"
  },
  "geometry": {
    "type": "Point",
    "coordinates": [
      -78.63753,
      43.01061
    ]
  }
}