{
  "type": "Feature",
  "properties": {
    "name": "Colonie",
    "country": "US",
    "subdivision": "NY",
    "timezone": "America/New_York"
  },
  "geometry": {
    "type": "Point",
    "coordinates": [
      -73.83346,
      42.71786
    ]
  }
}