{
  "type": "Feature",
  "properties": {
    "name": "Coney Island",
    "country": "US",
    "subdivision": "NY",
    "timezone": "America/New_York"
  },
  "geometry": {
    "type": "Point",
    "coordinates": [
      -73.99403,
      40.57788
    ]
  }
}