{
  "type": "Feature",
  "properties": {
    "name": "Constantia",
    "country": "US",
    "subdivision": "NY",
    "timezone": "America/New_York"
  },
  "geometry": {
    "type": "Point",
    "coordinates": [
      -76.0002,
      43.24785
    ]
  }
}