{
  "type": "Feature",
  "properties": {
    "name": "Cornwall",
    "country": "US",
    "subdivision": "NY",
    "timezone": "America/New_York"
  },
  "geometry": {
    "type": "Point",
    "coordinates": [
      -74.0157,
      41.44482
    ]
  }
}