{
  "type": "Feature",
  "properties": {
    "name": "Cortland",
    "country": "US",
    "subdivision": "NY",
    "timezone": "America/New_York"
  },
  "geometry": {
    "type": "Point",
    "coordinates": [
      -76.18048,
      42.60118
    ]
  }
}