{
  "type": "Feature",
  "properties": {
    "name": "Cortland West",
    "country": "US",
    "subdivision": "NY",
    "timezone": "America/New_York"
  },
  "geometry": {
    "type": "Point",
    "coordinates": [
      -76.22587,
      42.59431
    ]
  }
}