{
  "type": "Feature",
  "properties": {
    "name": "Country Knolls",
    "country": "US",
    "subdivision": "NY",
    "timezone": "America/New_York"
  },
  "geometry": {
    "type": "Point",
    "coordinates": [
      -73.80512,
      42.91508
    ]
  }
}