{
  "type": "Feature",
  "properties": {
    "name": "Cutchogue",
    "country": "US",
    "subdivision": "NY",
    "timezone": "America/New_York"
  },
  "geometry": {
    "type": "Point",
    "coordinates": [
      -72.48509,
      41.01066
    ]
  }
}