{
  "type": "Feature",
  "properties": {
    "name": "Dansville",
    "country": "US",
    "subdivision": "NY",
    "timezone": "America/New_York"
  },
  "geometry": {
    "type": "Point",
    "coordinates": [
      -77.69611,
      42.5609
    ]
  }
}