{
  "type": "Feature",
  "properties": {
    "name": "Depew",
    "country": "US",
    "subdivision": "NY",
    "timezone": "America/New_York"
  },
  "geometry": {
    "type": "Point",
    "coordinates": [
      -78.69225,
      42.90395
    ]
  }
}