{
  "type": "Feature",
  "properties": {
    "name": "Deposit",
    "country": "US",
    "subdivision": "NY",
    "timezone": "America/New_York"
  },
  "geometry": {
    "type": "Point",
    "coordinates": [
      -75.42768,
      42.06008
    ]
  }
}