{
  "type": "Feature",
  "properties": {
    "name": "Dundee",
    "country": "US",
    "subdivision": "NY",
    "timezone": "America/New_York"
  },
  "geometry": {
    "type": "Point",
    "coordinates": [
      -76.97663,
      42.5234
    ]
  }
}