{
  "type": "Feature",
  "properties": {
    "name": "East Northport",
    "country": "US",
    "subdivision": "NY",
    "timezone": "America/New_York"
  },
  "geometry": {
    "type": "Point",
    "coordinates": [
      -73.32456,
      40.87676
    ]
  }
}