{
  "type": "Feature",
  "properties": {
    "name": "East New York",
    "country": "US",
    "subdivision": "NY",
    "timezone": "America/New_York"
  },
  "geometry": {
    "type": "Point",
    "coordinates": [
      -73.88236,
      40.66677
    ]
  }
}