{
  "type": "Feature",
  "properties": {
    "name": "East Rochester",
    "country": "US",
    "subdivision": "NY",
    "timezone": "America/New_York"
  },
  "geometry": {
    "type": "Point",
    "coordinates": [
      -77.4875,
      43.10867
    ]
  }
}