{
  "type": "Feature",
  "properties": {
    "name": "East Norwich",
    "country": "US",
    "subdivision": "NY",
    "timezone": "America/New_York"
  },
  "geometry": {
    "type": "Point",
    "coordinates": [
      -73.53512,
      40.84677
    ]
  }
}