{
  "type": "Feature",
  "properties": {
    "name": "East Massapequa",
    "country": "US",
    "subdivision": "NY",
    "timezone": "America/New_York"
  },
  "geometry": {
    "type": "Point",
    "coordinates": [
      -73.43651,
      40.67343
    ]
  }
}