{
  "type": "Feature",
  "properties": {
    "name": "East Garden City",
    "country": "US",
    "subdivision": "NY",
    "timezone": "America/New_York"
  },
  "geometry": {
    "type": "Point",
    "coordinates": [
      -73.59806,
      40.73083
    ]
  }
}