{
  "type": "Feature",
  "properties": {
    "name": "East Elmhurst",
    "country": "US",
    "subdivision": "NY",
    "timezone": "America/New_York"
  },
  "geometry": {
    "type": "Point",
    "coordinates": [
      -73.86514,
      40.76121
    ]
  }
}