{
  "type": "Feature",
  "properties": {
    "name": "East Glenville",
    "country": "US",
    "subdivision": "NY",
    "timezone": "America/New_York"
  },
  "geometry": {
    "type": "Point",
    "coordinates": [
      -73.9279,
      42.89452
    ]
  }
}