{
  "type": "Feature",
  "properties": {
    "name": "East Quogue",
    "country": "US",
    "subdivision": "NY",
    "timezone": "America/New_York"
  },
  "geometry": {
    "type": "Point",
    "coordinates": [
      -72.58148,
      40.84066
    ]
  }
}