{
  "type": "Feature",
  "properties": {
    "name": "Elmhurst",
    "country": "US",
    "subdivision": "NY",
    "timezone": "America/New_York"
  },
  "geometry": {
    "type": "Point",
    "coordinates": [
      -73.87791,
      40.73649
    ]
  }
}