{
  "type": "Feature",
  "properties": {
    "name": "Elmira",
    "country": "US",
    "subdivision": "NY",
    "timezone": "America/New_York"
  },
  "geometry": {
    "type": "Point",
    "coordinates": [
      -76.80773,
      42.0898
    ]
  }
}