{
  "type": "Feature",
  "properties": {
    "name": "Eltingville",
    "country": "US",
    "subdivision": "NY",
    "timezone": "America/New_York"
  },
  "geometry": {
    "type": "Point",
    "coordinates": [
      -74.1657,
      40.54538
    ]
  }
}