{
  "type": "Feature",
  "properties": {
    "name": "Endwell",
    "country": "US",
    "subdivision": "NY",
    "timezone": "America/New_York"
  },
  "geometry": {
    "type": "Point",
    "coordinates": [
      -76.02103,
      42.11285
    ]
  }
}