{
  "type": "Feature",
  "properties": {
    "name": "Fairview",
    "country": "US",
    "subdivision": "NY",
    "timezone": "America/New_York"
  },
  "geometry": {
    "type": "Point",
    "coordinates": [
      -73.91986,
      41.7237
    ]
  }
}