{
  "type": "Feature",
  "properties": {
    "name": "Fallsburg",
    "country": "US",
    "subdivision": "NY",
    "timezone": "America/New_York"
  },
  "geometry": {
    "type": "Point",
    "coordinates": [
      -74.60127,
      41.73204
    ]
  }
}