{
  "type": "Feature",
  "properties": {
    "name": "Florida",
    "country": "US",
    "subdivision": "NY",
    "timezone": "America/New_York"
  },
  "geometry": {
    "type": "Point",
    "coordinates": [
      -74.35682,
      41.33176
    ]
  }
}