{
  "type": "Feature",
  "properties": {
    "name": "Fort Covington Hamlet",
    "country": "US",
    "subdivision": "NY",
    "timezone": "America/New_York"
  },
  "geometry": {
    "type": "Point",
    "coordinates": [
      -74.50757,
      44.97178
    ]
  }
}