{
  "type": "Feature",
  "properties": {
    "name": "Franklinville",
    "country": "US",
    "subdivision": "NY",
    "timezone": "America/New_York"
  },
  "geometry": {
    "type": "Point",
    "coordinates": [
      -78.45808,
      42.33701
    ]
  }
}