{
  "type": "Feature",
  "properties": {
    "name": "Glens Falls",
    "country": "US",
    "subdivision": "NY",
    "timezone": "America/New_York"
  },
  "geometry": {
    "type": "Point",
    "coordinates": [
      -73.64401,
      43.30952
    ]
  }
}