{
  "type": "Feature",
  "properties": {
    "name": "Goshen",
    "country": "US",
    "subdivision": "NY",
    "timezone": "America/New_York"
  },
  "geometry": {
    "type": "Point",
    "coordinates": [
      -74.32432,
      41.40204
    ]
  }
}