{
  "type": "Feature",
  "properties": {
    "name": "Gouverneur",
    "country": "US",
    "subdivision": "NY",
    "timezone": "America/New_York"
  },
  "geometry": {
    "type": "Point",
    "coordinates": [
      -75.46299,
      44.33673
    ]
  }
}