{
  "type": "Feature",
  "properties": {
    "name": "Grand Island",
    "country": "US",
    "subdivision": "NY",
    "timezone": "America/New_York"
  },
  "geometry": {
    "type": "Point",
    "coordinates": [
      -78.96254,
      43.03311
    ]
  }
}