{
  "type": "Feature",
  "properties": {
    "name": "Greenpoint",
    "country": "US",
    "subdivision": "NY",
    "timezone": "America/New_York"
  },
  "geometry": {
    "type": "Point",
    "coordinates": [
      -73.95097,
      40.72371
    ]
  }
}