{
  "type": "Feature",
  "properties": {
    "name": "Greenwich",
    "country": "US",
    "subdivision": "NY",
    "timezone": "America/New_York"
  },
  "geometry": {
    "type": "Point",
    "coordinates": [
      -73.49873,
      43.09063
    ]
  }
}