{
  "type": "Feature",
  "properties": {
    "name": "Greene",
    "country": "US",
    "subdivision": "NY",
    "timezone": "America/New_York"
  },
  "geometry": {
    "type": "Point",
    "coordinates": [
      -75.76991,
      42.32924
    ]
  }
}