{
  "type": "Feature",
  "properties": {
    "name": "Greenlawn",
    "country": "US",
    "subdivision": "NY",
    "timezone": "America/New_York"
  },
  "geometry": {
    "type": "Point",
    "coordinates": [
      -73.36512,
      40.86899
    ]
  }
}