{
  "type": "Feature",
  "properties": {
    "name": "Halesite",
    "country": "US",
    "subdivision": "NY",
    "timezone": "America/New_York"
  },
  "geometry": {
    "type": "Point",
    "coordinates": [
      -73.4154,
      40.88843
    ]
  }
}