{
  "type": "Feature",
  "properties": {
    "name": "Hamilton",
    "country": "US",
    "subdivision": "NY",
    "timezone": "America/New_York"
  },
  "geometry": {
    "type": "Point",
    "coordinates": [
      -75.54462,
      42.82701
    ]
  }
}