{
  "type": "Feature",
  "properties": {
    "name": "Harlem",
    "country": "US",
    "subdivision": "NY",
    "timezone": "America/New_York"
  },
  "geometry": {
    "type": "Point",
    "coordinates": [
      -73.94542,
      40.80788
    ]
  }
}