{
  "type": "Feature",
  "properties": {
    "name": "Hastings-on-Hudson",
    "country": "US",
    "subdivision": "NY",
    "timezone": "America/New_York"
  },
  "geometry": {
    "type": "Point",
    "coordinates": [
      -73.87875,
      40.99454
    ]
  }
}