{
  "type": "Feature",
  "properties": {
    "name": "Hauppauge",
    "country": "US",
    "subdivision": "NY",
    "timezone": "America/New_York"
  },
  "geometry": {
    "type": "Point",
    "coordinates": [
      -73.20261,
      40.82565
    ]
  }
}