{
  "type": "Feature",
  "properties": {
    "name": "Hell's Kitchen",
    "country": "US",
    "subdivision": "NY",
    "timezone": "America/New_York"
  },
  "geometry": {
    "type": "Point",
    "coordinates": [
      -73.9909,
      40.76496
    ]
  }
}