{
  "type": "Feature",
  "properties": {
    "name": "Herkimer",
    "country": "US",
    "subdivision": "NY",
    "timezone": "America/New_York"
  },
  "geometry": {
    "type": "Point",
    "coordinates": [
      -74.98599,
      43.02563
    ]
  }
}