{
  "type": "Feature",
  "properties": {
    "name": "Horseheads North",
    "country": "US",
    "subdivision": "NY",
    "timezone": "America/New_York"
  },
  "geometry": {
    "type": "Point",
    "coordinates": [
      -76.80782,
      42.19278
    ]
  }
}