{
  "type": "Feature",
  "properties": {
    "name": "Hudson Falls",
    "country": "US",
    "subdivision": "NY",
    "timezone": "America/New_York"
  },
  "geometry": {
    "type": "Point",
    "coordinates": [
      -73.58595,
      43.30063
    ]
  }
}