{
  "type": "Feature",
  "properties": {
    "name": "Irondequoit",
    "country": "US",
    "subdivision": "NY",
    "timezone": "America/New_York"
  },
  "geometry": {
    "type": "Point",
    "coordinates": [
      -77.57972,
      43.2134
    ]
  }
}