{
  "type": "Feature",
  "properties": {
    "name": "Jamestown West",
    "country": "US",
    "subdivision": "NY",
    "timezone": "America/New_York"
  },
  "geometry": {
    "type": "Point",
    "coordinates": [
      -79.2811,
      42.08851
    ]
  }
}