{
  "type": "Feature",
  "properties": {
    "name": "Jefferson Valley-Yorktown",
    "country": "US",
    "subdivision": "NY",
    "timezone": "America/New_York"
  },
  "geometry": {
    "type": "Point",
    "coordinates": [
      -73.80066,
      41.31797
    ]
  }
}