{
  "type": "Feature",
  "properties": {
    "name": "Keeseville",
    "country": "US",
    "subdivision": "NY",
    "timezone": "America/New_York"
  },
  "geometry": {
    "type": "Point",
    "coordinates": [
      -73.48013,
      44.50505
    ]
  }
}