{
  "type": "Feature",
  "properties": {
    "name": "Keuka Park",
    "country": "US",
    "subdivision": "NY",
    "timezone": "America/New_York"
  },
  "geometry": {
    "type": "Point",
    "coordinates": [
      -77.09219,
      42.61535
    ]
  }
}