{
  "type": "Feature",
  "properties": {
    "name": "Kings Park",
    "country": "US",
    "subdivision": "NY",
    "timezone": "America/New_York"
  },
  "geometry": {
    "type": "Point",
    "coordinates": [
      -73.25734,
      40.88621
    ]
  }
}