{
  "type": "Feature",
  "properties": {
    "name": "Kings Bridge",
    "country": "US",
    "subdivision": "NY",
    "timezone": "America/New_York"
  },
  "geometry": {
    "type": "Point",
    "coordinates": [
      -73.90514,
      40.87871
    ]
  }
}