{
  "type": "Feature",
  "properties": {
    "name": "Lake Placid",
    "country": "US",
    "subdivision": "NY",
    "timezone": "America/New_York"
  },
  "geometry": {
    "type": "Point",
    "coordinates": [
      -73.98198,
      44.27962
    ]
  }
}