{
  "type": "Feature",
  "properties": {
    "name": "Lima",
    "country": "US",
    "subdivision": "NY",
    "timezone": "America/New_York"
  },
  "geometry": {
    "type": "Point",
    "coordinates": [
      -77.61139,
      42.90479
    ]
  }
}