{
  "type": "Feature",
  "properties": {
    "name": "Lincolndale",
    "country": "US",
    "subdivision": "NY",
    "timezone": "America/New_York"
  },
  "geometry": {
    "type": "Point",
    "coordinates": [
      -73.71819,
      41.32287
    ]
  }
}