{
  "type": "Feature",
  "properties": {
    "name": "Little Neck",
    "country": "US",
    "subdivision": "NY",
    "timezone": "America/New_York"
  },
  "geometry": {
    "type": "Point",
    "coordinates": [
      -73.73225,
      40.76289
    ]
  }
}