{
  "type": "Feature",
  "properties": {
    "name": "Locust Valley",
    "country": "US",
    "subdivision": "NY",
    "timezone": "America/New_York"
  },
  "geometry": {
    "type": "Point",
    "coordinates": [
      -73.59707,
      40.87593
    ]
  }
}