{
  "type": "Feature",
  "properties": {
    "name": "Lorenz Park",
    "country": "US",
    "subdivision": "NY",
    "timezone": "America/New_York"
  },
  "geometry": {
    "type": "Point",
    "coordinates": [
      -73.76846,
      42.2637
    ]
  }
}