{
  "type": "Feature",
  "properties": {
    "name": "Lyons",
    "country": "US",
    "subdivision": "NY",
    "timezone": "America/New_York"
  },
  "geometry": {
    "type": "Point",
    "coordinates": [
      -76.99025,
      43.06423
    ]
  }
}