{
  "type": "Feature",
  "properties": {
    "name": "Mahopac",
    "country": "US",
    "subdivision": "NY",
    "timezone": "America/New_York"
  },
  "geometry": {
    "type": "Point",
    "coordinates": [
      -73.73346,
      41.37232
    ]
  }
}