{
  "type": "Feature",
  "properties": {
    "name": "Malone",
    "country": "US",
    "subdivision": "NY",
    "timezone": "America/New_York"
  },
  "geometry": {
    "type": "Point",
    "coordinates": [
      -74.2949,
      44.84866
    ]
  }
}