{
  "type": "Feature",
  "properties": {
    "name": "Mamaroneck",
    "country": "US",
    "subdivision": "NY",
    "timezone": "America/New_York"
  },
  "geometry": {
    "type": "Point",
    "coordinates": [
      -73.73263,
      40.94871
    ]
  }
}