{
  "type": "Feature",
  "properties": {
    "name": "Manhasset",
    "country": "US",
    "subdivision": "NY",
    "timezone": "America/New_York"
  },
  "geometry": {
    "type": "Point",
    "coordinates": [
      -73.69957,
      40.79788
    ]
  }
}