{
  "type": "Feature",
  "properties": {
    "name": "Marlboro",
    "country": "US",
    "subdivision": "NY",
    "timezone": "America/New_York"
  },
  "geometry": {
    "type": "Point",
    "coordinates": [
      -73.97153,
      41.60565
    ]
  }
}