{
  "type": "Feature",
  "properties": {
    "name": "Melville",
    "country": "US",
    "subdivision": "NY",
    "timezone": "America/New_York"
  },
  "geometry": {
    "type": "Point",
    "coordinates": [
      -73.41512,
      40.79343
    ]
  }
}