{
  "type": "Feature",
  "properties": {
    "name": "Mexico",
    "country": "US",
    "subdivision": "NY",
    "timezone": "America/New_York"
  },
  "geometry": {
    "type": "Point",
    "coordinates": [
      -76.22882,
      43.45951
    ]
  }
}