{
  "type": "Feature",
  "properties": {
    "name": "Miller Place",
    "country": "US",
    "subdivision": "NY",
    "timezone": "America/New_York"
  },
  "geometry": {
    "type": "Point",
    "coordinates": [
      -72.99621,
      40.95982
    ]
  }
}