{
  "type": "Feature",
  "properties": {
    "name": "Minetto",
    "country": "US",
    "subdivision": "NY",
    "timezone": "America/New_York"
  },
  "geometry": {
    "type": "Point",
    "coordinates": [
      -76.47744,
      43.39812
    ]
  }
}