{
  "type": "Feature",
  "properties": {
    "name": "Moravia",
    "country": "US",
    "subdivision": "NY",
    "timezone": "America/New_York"
  },
  "geometry": {
    "type": "Point",
    "coordinates": [
      -76.4216,
      42.71257
    ]
  }
}