{
  "type": "Feature",
  "properties": {
    "name": "Napanoch",
    "country": "US",
    "subdivision": "NY",
    "timezone": "America/New_York"
  },
  "geometry": {
    "type": "Point",
    "coordinates": [
      -74.37154,
      41.74398
    ]
  }
}