{
  "type": "Feature",
  "properties": {
    "name": "Nedrow",
    "country": "US",
    "subdivision": "NY",
    "timezone": "America/New_York"
  },
  "geometry": {
    "type": "Point",
    "coordinates": [
      -76.14131,
      42.97507
    ]
  }
}