{
  "type": "Feature",
  "properties": {
    "name": "New Springville",
    "country": "US",
    "subdivision": "NY",
    "timezone": "America/New_York"
  },
  "geometry": {
    "type": "Point",
    "coordinates": [
      -74.1632,
      40.59344
    ]
  }
}