{
  "type": "Feature",
  "properties": {
    "name": "New Brighton",
    "country": "US",
    "subdivision": "NY",
    "timezone": "America/New_York"
  },
  "geometry": {
    "type": "Point",
    "coordinates": [
      -74.09292,
      40.64233
    ]
  }
}