{
  "type": "Feature",
  "properties": {
    "name": "New Hartford",
    "country": "US",
    "subdivision": "NY",
    "timezone": "America/New_York"
  },
  "geometry": {
    "type": "Point",
    "coordinates": [
      -75.28767,
      43.0734
    ]
  }
}