{
  "type": "Feature",
  "properties": {
    "name": "New Dorp",
    "country": "US",
    "subdivision": "NY",
    "timezone": "America/New_York"
  },
  "geometry": {
    "type": "Point",
    "coordinates": [
      -74.11598,
      40.57399
    ]
  }
}