{
  "type": "Feature",
  "properties": {
    "name": "New Dorp Beach",
    "country": "US",
    "subdivision": "NY",
    "timezone": "America/New_York"
  },
  "geometry": {
    "type": "Point",
    "coordinates": [
      -74.10292,
      40.56538
    ]
  }
}