{
  "type": "Feature",
  "properties": {
    "name": "North Collins",
    "country": "US",
    "subdivision": "NY",
    "timezone": "America/New_York"
  },
  "geometry": {
    "type": "Point",
    "coordinates": [
      -78.94115,
      42.59534
    ]
  }
}