{
  "type": "Feature",
  "properties": {
    "name": "North Merrick",
    "country": "US",
    "subdivision": "NY",
    "timezone": "America/New_York"
  },
  "geometry": {
    "type": "Point",
    "coordinates": [
      -73.56318,
      40.69121
    ]
  }
}