{
  "type": "Feature",
  "properties": {
    "name": "Northville",
    "country": "US",
    "subdivision": "NY",
    "timezone": "America/New_York"
  },
  "geometry": {
    "type": "Point",
    "coordinates": [
      -74.17208,
      43.22563
    ]
  }
}