{
  "type": "Feature",
  "properties": {
    "name": "North New Hyde Park",
    "country": "US",
    "subdivision": "NY",
    "timezone": "America/New_York"
  },
  "geometry": {
    "type": "Point",
    "coordinates": [
      -73.69319,
      40.74316
    ]
  }
}