{
  "type": "Feature",
  "properties": {
    "name": "Northwest Harbor",
    "country": "US",
    "subdivision": "NY",
    "timezone": "America/New_York"
  },
  "geometry": {
    "type": "Point",
    "coordinates": [
      -72.22119,
      41.00982
    ]
  }
}