{
  "type": "Feature",
  "properties": {
    "name": "Old Brookville",
    "country": "US",
    "subdivision": "NY",
    "timezone": "America/New_York"
  },
  "geometry": {
    "type": "Point",
    "coordinates": [
      -73.60485,
      40.83204
    ]
  }
}