{
  "type": "Feature",
  "properties": {
    "name": "Owego",
    "country": "US",
    "subdivision": "NY",
    "timezone": "America/New_York"
  },
  "geometry": {
    "type": "Point",
    "coordinates": [
      -76.26215,
      42.10341
    ]
  }
}