{
  "type": "Feature",
  "properties": {
    "name": "Perth",
    "country": "US",
    "subdivision": "NY",
    "timezone": "America/New_York"
  },
  "geometry": {
    "type": "Point",
    "coordinates": [
      -74.19402,
      43.01757
    ]
  }
}