{
  "type": "Feature",
  "properties": {
    "name": "Phoenix",
    "country": "US",
    "subdivision": "NY",
    "timezone": "America/New_York"
  },
  "geometry": {
    "type": "Point",
    "coordinates": [
      -76.30076,
      43.23118
    ]
  }
}