{
  "type": "Feature",
  "properties": {
    "name": "Piermont",
    "country": "US",
    "subdivision": "NY",
    "timezone": "America/New_York"
  },
  "geometry": {
    "type": "Point",
    "coordinates": [
      -73.91819,
      41.04204
    ]
  }
}