{
  "type": "Feature",
  "properties": {
    "name": "Plandome",
    "country": "US",
    "subdivision": "NY",
    "timezone": "America/New_York"
  },
  "geometry": {
    "type": "Point",
    "coordinates": [
      -73.70346,
      40.80677
    ]
  }
}