{
  "type": "Feature",
  "properties": {
    "name": "Plattekill",
    "country": "US",
    "subdivision": "NY",
    "timezone": "America/New_York"
  },
  "geometry": {
    "type": "Point",
    "coordinates": [
      -74.07598,
      41.61759
    ]
  }
}