{
  "type": "Feature",
  "properties": {
    "name": "Pleasantville",
    "country": "US",
    "subdivision": "NY",
    "timezone": "America/New_York"
  },
  "geometry": {
    "type": "Point",
    "coordinates": [
      -73.79263,
      41.13287
    ]
  }
}