{
  "type": "Feature",
  "properties": {
    "name": "Pleasant Valley",
    "country": "US",
    "subdivision": "NY",
    "timezone": "America/New_York"
  },
  "geometry": {
    "type": "Point",
    "coordinates": [
      -73.82124,
      41.74454
    ]
  }
}