{
  "type": "Feature",
  "properties": {
    "name": "Port Jervis",
    "country": "US",
    "subdivision": "NY",
    "timezone": "America/New_York"
  },
  "geometry": {
    "type": "Point",
    "coordinates": [
      -74.69266,
      41.37509
    ]
  }
}