{
  "type": "Feature",
  "properties": {
    "name": "Potsdam",
    "country": "US",
    "subdivision": "NY",
    "timezone": "America/New_York"
  },
  "geometry": {
    "type": "Point",
    "coordinates": [
      -74.98131,
      44.66978
    ]
  }
}