{
  "type": "Feature",
  "properties": {
    "name": "Pound Ridge",
    "country": "US",
    "subdivision": "NY",
    "timezone": "America/New_York"
  },
  "geometry": {
    "type": "Point",
    "coordinates": [
      -73.57485,
      41.20871
    ]
  }
}