{
  "type": "Feature",
  "properties": {
    "name": "Queens",
    "country": "US",
    "subdivision": "NY",
    "timezone": "America/New_York"
  },
  "geometry": {
    "type": "Point",
    "coordinates": [
      -73.83652,
      40.68149
    ]
  }
}