{
  "type": "Feature",
  "properties": {
    "name": "Red Oaks Mill",
    "country": "US",
    "subdivision": "NY",
    "timezone": "America/New_York"
  },
  "geometry": {
    "type": "Point",
    "coordinates": [
      -73.87486,
      41.65565
    ]
  }
}