{
  "type": "Feature",
  "properties": {
    "name": "Rome",
    "country": "US",
    "subdivision": "NY",
    "timezone": "America/New_York"
  },
  "geometry": {
    "type": "Point",
    "coordinates": [
      -75.45573,
      43.21285
    ]
  }
}