{
  "type": "Feature",
  "properties": {
    "name": "Roslyn Heights",
    "country": "US",
    "subdivision": "NY",
    "timezone": "America/New_York"
  },
  "geometry": {
    "type": "Point",
    "coordinates": [
      -73.64735,
      40.78871
    ]
  }
}