{
  "type": "Feature",
  "properties": {
    "name": "Sag Harbor",
    "country": "US",
    "subdivision": "NY",
    "timezone": "America/New_York"
  },
  "geometry": {
    "type": "Point",
    "coordinates": [
      -72.29258,
      40.99788
    ]
  }
}