{
  "type": "Feature",
  "properties": {
    "name": "Saranac Lake",
    "country": "US",
    "subdivision": "NY",
    "timezone": "America/New_York"
  },
  "geometry": {
    "type": "Point",
    "coordinates": [
      -74.13127,
      44.3295
    ]
  }
}