{
  "type": "Feature",
  "properties": {
    "name": "Seaside",
    "country": "US",
    "subdivision": "NY",
    "timezone": "America/New_York"
  },
  "geometry": {
    "type": "Point",
    "coordinates": [
      -73.82819,
      40.58316
    ]
  }
}