{
  "type": "Feature",
  "properties": {
    "name": "Seneca Knolls",
    "country": "US",
    "subdivision": "NY",
    "timezone": "America/New_York"
  },
  "geometry": {
    "type": "Point",
    "coordinates": [
      -76.28632,
      43.12007
    ]
  }
}