{
  "type": "Feature",
  "properties": {
    "name": "Shinnecock Hills",
    "country": "US",
    "subdivision": "NY",
    "timezone": "America/New_York"
  },
  "geometry": {
    "type": "Point",
    "coordinates": [
      -72.4637,
      40.89093
    ]
  }
}