{
  "type": "Feature",
  "properties": {
    "name": "Silver Creek",
    "country": "US",
    "subdivision": "NY",
    "timezone": "America/New_York"
  },
  "geometry": {
    "type": "Point",
    "coordinates": [
      -79.16671,
      42.54423
    ]
  }
}