{
  "type": "Feature",
  "properties": {
    "name": "Sleepy Hollow",
    "country": "US",
    "subdivision": "NY",
    "timezone": "America/New_York"
  },
  "geometry": {
    "type": "Point",
    "coordinates": [
      -73.85847,
      41.08565
    ]
  }
}