{
  "type": "Feature",
  "properties": {
    "name": "South Fallsburg",
    "country": "US",
    "subdivision": "NY",
    "timezone": "America/New_York"
  },
  "geometry": {
    "type": "Point",
    "coordinates": [
      -74.63433,
      41.72065
    ]
  }
}