{
  "type": "Feature",
  "properties": {
    "name": "Southport",
    "country": "US",
    "subdivision": "NY",
    "timezone": "America/New_York"
  },
  "geometry": {
    "type": "Point",
    "coordinates": [
      -76.81912,
      42.0548
    ]
  }
}