{
  "type": "Feature",
  "properties": {
    "name": "Springfield",
    "country": "US",
    "subdivision": "NY",
    "timezone": "America/New_York"
  },
  "geometry": {
    "type": "Point",
    "coordinates": [
      -74.85348,
      42.83618
    ]
  }
}