{
  "type": "Feature",
  "properties": {
    "name": "Spring Valley",
    "country": "US",
    "subdivision": "NY",
    "timezone": "America/New_York"
  },
  "geometry": {
    "type": "Point",
    "coordinates": [
      -74.04375,
      41.11315
    ]
  }
}