{
  "type": "Feature",
  "properties": {
    "name": "Thiells",
    "country": "US",
    "subdivision": "NY",
    "timezone": "America/New_York"
  },
  "geometry": {
    "type": "Point",
    "coordinates": [
      -74.01764,
      41.21065
    ]
  }
}