{
  "type": "Feature",
  "properties": {
    "name": "Thomaston",
    "country": "US",
    "subdivision": "NY",
    "timezone": "America/New_York"
  },
  "geometry": {
    "type": "Point",
    "coordinates": [
      -73.71374,
      40.78621
    ]
  }
}