{
  "type": "Feature",
  "properties": {
    "name": "Throgs Neck",
    "country": "US",
    "subdivision": "NY",
    "timezone": "America/New_York"
  },
  "geometry": {
    "type": "Point",
    "coordinates": [
      -73.81958,
      40.8226
    ]
  }
}