{
  "type": "Feature",
  "properties": {
    "name": "Tremont",
    "country": "US",
    "subdivision": "NY",
    "timezone": "America/New_York"
  },
  "geometry": {
    "type": "Point",
    "coordinates": [
      -73.90569,
      40.84954
    ]
  }
}