{
  "type": "Feature",
  "properties": {
    "name": "Tupper Lake",
    "country": "US",
    "subdivision": "NY",
    "timezone": "America/New_York"
  },
  "geometry": {
    "type": "Point",
    "coordinates": [
      -74.46406,
      44.22395
    ]
  }
}