{
  "type": "Feature",
  "properties": {
    "name": "Uniondale",
    "country": "US",
    "subdivision": "NY",
    "timezone": "America/New_York"
  },
  "geometry": {
    "type": "Point",
    "coordinates": [
      -73.59291,
      40.70038
    ]
  }
}