{
  "type": "Feature",
  "properties": {
    "name": "Viola",
    "country": "US",
    "subdivision": "NY",
    "timezone": "America/New_York"
  },
  "geometry": {
    "type": "Point",
    "coordinates": [
      -74.08236,
      41.13648
    ]
  }
}