{
  "type": "Feature",
  "properties": {
    "name": "Walton",
    "country": "US",
    "subdivision": "NY",
    "timezone": "America/New_York"
  },
  "geometry": {
    "type": "Point",
    "coordinates": [
      -75.12934,
      42.16953
    ]
  }
}