{
  "type": "Feature",
  "properties": {
    "name": "Waterford",
    "country": "US",
    "subdivision": "NY",
    "timezone": "America/New_York"
  },
  "geometry": {
    "type": "Point",
    "coordinates": [
      -73.68123,
      42.79258
    ]
  }
}