{
  "type": "Feature",
  "properties": {
    "name": "Water Mill",
    "country": "US",
    "subdivision": "NY",
    "timezone": "America/New_York"
  },
  "geometry": {
    "type": "Point",
    "coordinates": [
      -72.34274,
      40.91959
    ]
  }
}