{
  "type": "Feature",
  "properties": {
    "name": "Webster",
    "country": "US",
    "subdivision": "NY",
    "timezone": "America/New_York"
  },
  "geometry": {
    "type": "Point",
    "coordinates": [
      -77.42999,
      43.21229
    ]
  }
}