{
  "type": "Feature",
  "properties": {
    "name": "Weedsport",
    "country": "US",
    "subdivision": "NY",
    "timezone": "America/New_York"
  },
  "geometry": {
    "type": "Point",
    "coordinates": [
      -76.56272,
      43.04868
    ]
  }
}