{
  "type": "Feature",
  "properties": {
    "name": "West Nyack",
    "country": "US",
    "subdivision": "NY",
    "timezone": "America/New_York"
  },
  "geometry": {
    "type": "Point",
    "coordinates": [
      -73.97292,
      41.09649
    ]
  }
}