{
  "type": "Feature",
  "properties": {
    "name": "Worcester",
    "country": "US",
    "subdivision": "NY",
    "timezone": "America/New_York"
  },
  "geometry": {
    "type": "Point",
    "coordinates": [
      -74.75043,
      42.59146
    ]
  }
}