{
  "type": "Feature",
  "properties": {
    "name": "Bordighera",
    "country": "IT",
    "subdivision": "08",
    "timezone": "Europe/Rome"
  },
  "geometry": {
    "type": "Point",
    "coordinates": [
      7.66451,
      43.78064
    ]
  }
}