{
  "type": "Feature",
  "properties": {
    "name": "Camporosso",
    "country": "IT",
    "subdivision": "08",
    "timezone": "Europe/Rome"
  },
  "geometry": {
    "type": "Point",
    "coordinates": [
      7.62829,
      43.8131
    ]
  }
}