{
  "type": "Feature",
  "properties": {
    "name": "Mezzanego",
    "country": "IT",
    "subdivision": "08",
    "timezone": "Europe/Rome"
  },
  "geometry": {
    "type": "Point",
    "coordinates": [
      9.37667,
      44.38275
    ]
  }
}