{
  "type": "Feature",
  "properties": {
    "name": "Moconesi",
    "country": "IT",
    "subdivision": "08",
    "timezone": "Europe/Rome"
  },
  "geometry": {
    "type": "Point",
    "coordinates": [
      9.20977,
      44.42065
    ]
  }
}