{
  "type": "Feature",
  "properties": {
    "name": "Pitelli",
    "country": "IT",
    "subdivision": "08",
    "timezone": "Europe/Rome"
  },
  "geometry": {
    "type": "Point",
    "coordinates": [
      9.8849,
      44.09458
    ]
  }
}