{
  "type": "Feature",
  "properties": {
    "name": "Recco",
    "country": "IT",
    "subdivision": "08",
    "timezone": "Europe/Rome"
  },
  "geometry": {
    "type": "Point",
    "coordinates": [
      9.14354,
      44.36227
    ]
  }
}