{
  "type": "Feature",
  "properties": {
    "name": "Riva Ligure",
    "country": "IT",
    "subdivision": "08",
    "timezone": "Europe/Rome"
  },
  "geometry": {
    "type": "Point",
    "coordinates": [
      7.87935,
      43.83883
    ]
  }
}