{
  "type": "Feature",
  "properties": {
    "name": "San Terenzo",
    "country": "IT",
    "subdivision": "08",
    "timezone": "Europe/Rome"
  },
  "geometry": {
    "type": "Point",
    "coordinates": [
      9.89662,
      44.08543
    ]
  }
}