{
  "type": "Feature",
  "properties": {
    "name": "Santo Stefano al Mare",
    "country": "IT",
    "subdivision": "08",
    "timezone": "Europe/Rome"
  },
  "geometry": {
    "type": "Point",
    "coordinates": [
      7.89728,
      43.83855
    ]
  }
}