{
  "type": "Feature",
  "properties": {
    "name": "Sarzana",
    "country": "IT",
    "subdivision": "08",
    "timezone": "Europe/Rome"
  },
  "geometry": {
    "type": "Point",
    "coordinates": [
      9.9622,
      44.11178
    ]
  }
}