{
  "type": "Feature",
  "properties": {
    "name": "Savignone",
    "country": "IT",
    "subdivision": "08",
    "timezone": "Europe/Rome"
  },
  "geometry": {
    "type": "Point",
    "coordinates": [
      8.98726,
      44.56435
    ]
  }
}