{
  "type": "Feature",
  "properties": {
    "name": "Torriglia",
    "country": "IT",
    "subdivision": "08",
    "timezone": "Europe/Rome"
  },
  "geometry": {
    "type": "Point",
    "coordinates": [
      9.15811,
      44.51755
    ]
  }
}