{
  "type": "Feature",
  "properties": {
    "name": "Vallecrosia",
    "country": "IT",
    "subdivision": "08",
    "timezone": "Europe/Rome"
  },
  "geometry": {
    "type": "Point",
    "coordinates": [
      7.63902,
      43.78671
    ]
  }
}