{
  "type": "Feature",
  "properties": {
    "name": "Carcaliu",
    "country": "RO",
    "subdivision": "37",
    "timezone": "Europe/Bucharest"
  },
  "geometry": {
    "type": "Point",
    "coordinates": [
      28.15,
      45.18333
    ]
  }
}