{
  "type": "Feature",
  "properties": {
    "name": "Cataloi",
    "country": "RO",
    "subdivision": "37",
    "timezone": "Europe/Bucharest"
  },
  "geometry": {
    "type": "Point",
    "coordinates": [
      28.72856,
      45.09581
    ]
  }
}