{
  "type": "Feature",
  "properties": {
    "name": "Malcoci",
    "country": "RO",
    "subdivision": "37",
    "timezone": "Europe/Bucharest"
  },
  "geometry": {
    "type": "Point",
    "coordinates": [
      28.88824,
      45.13851
    ]
  }
}