{
  "type": "Feature",
  "properties": {
    "name": "Mihail Kogălniceanu",
    "country": "RO",
    "subdivision": "37",
    "timezone": "Europe/Bucharest"
  },
  "geometry": {
    "type": "Point",
    "coordinates": [
      28.73333,
      45.03333
    ]
  }
}