{
  "type": "Feature",
  "properties": {
    "name": "Mihai Bravu",
    "country": "RO",
    "subdivision": "37",
    "timezone": "Europe/Bucharest"
  },
  "geometry": {
    "type": "Point",
    "coordinates": [
      28.65,
      44.95
    ]
  }
}