{
  "type": "Feature",
  "properties": {
    "name": "Mineri",
    "country": "RO",
    "subdivision": "37",
    "timezone": "Europe/Bucharest"
  },
  "geometry": {
    "type": "Point",
    "coordinates": [
      28.71573,
      45.16472
    ]
  }
}