{
  "type": "Feature",
  "properties": {
    "name": "Rachelu",
    "country": "RO",
    "subdivision": "37",
    "timezone": "Europe/Bucharest"
  },
  "geometry": {
    "type": "Point",
    "coordinates": [
      28.32349,
      45.28667
    ]
  }
}