{
  "type": "Feature",
  "properties": {
    "name": "Văcăreni",
    "country": "RO",
    "subdivision": "37",
    "timezone": "Europe/Bucharest"
  },
  "geometry": {
    "type": "Point",
    "coordinates": [
      28.19512,
      45.32415
    ]
  }
}