{
  "type": "Feature",
  "properties": {
    "name": "Asahi",
    "country": "JP",
    "subdivision": "06",
    "timezone": "Asia/Tokyo"
  },
  "geometry": {
    "type": "Point",
    "coordinates": [
      136.12455,
      35.97259
    ]
  }
}