{
  "type": "Feature",
  "properties": {
    "name": "Fuvahmulah",
    "country": "MV",
    "subdivision": "42",
    "timezone": "Indian/Maldives"
  },
  "geometry": {
    "type": "Point",
    "coordinates": [
      73.42403,
      -0.29878
    ]
  }
}