{
  "type": "Feature",
  "properties": {
    "name": "Mansôa",
    "country": "GW",
    "subdivision": "04",
    "timezone": "Africa/Bissau"
  },
  "geometry": {
    "type": "Point",
    "coordinates": [
      -15.31889,
      12.07333
    ]
  }
}