{
  "type": "Feature",
  "properties": {
    "name": "Stephenville Crossing",
    "country": "CA",
    "subdivision": "05",
    "timezone": "America/St_Johns"
  },
  "geometry": {
    "type": "Point",
    "coordinates": [
      -58.4318,
      48.50001
    ]
  }
}