{
  "type": "Feature",
  "properties": {
    "name": "Dosquebradas",
    "country": "CO",
    "subdivision": "24",
    "timezone": "America/Bogota"
  },
  "geometry": {
    "type": "Point",
    "coordinates": [
      -75.66727,
      4.83916
    ]
  }
}