{
  "type": "Feature",
  "properties": {
    "name": "Santuario",
    "country": "CO",
    "subdivision": "24",
    "timezone": "America/Bogota"
  },
  "geometry": {
    "type": "Point",
    "coordinates": [
      -75.96423,
      5.07415
    ]
  }
}