{
  "type": "Feature",
  "properties": {
    "name": "Derā Nānak",
    "country": "IN",
    "subdivision": "23",
    "timezone": "Asia/Kolkata"
  },
  "geometry": {
    "type": "Point",
    "coordinates": [
      75.02787,
      32.03733
    ]
  }
}