{
  "type": "Feature",
  "properties": {
    "name": "Māchhīwāra",
    "country": "IN",
    "subdivision": "23",
    "timezone": "Asia/Kolkata"
  },
  "geometry": {
    "type": "Point",
    "coordinates": [
      76.20016,
      30.91557
    ]
  }
}