{
  "type": "Feature",
  "properties": {
    "name": "Maur",
    "country": "IN",
    "subdivision": "23",
    "timezone": "Asia/Kolkata"
  },
  "geometry": {
    "type": "Point",
    "coordinates": [
      75.25,
      30.08333
    ]
  }
}