{
  "type": "Feature",
  "properties": {
    "name": "Patti",
    "country": "IN",
    "subdivision": "23",
    "timezone": "Asia/Kolkata"
  },
  "geometry": {
    "type": "Point",
    "coordinates": [
      74.85849,
      31.28092
    ]
  }
}