{
  "type": "Feature",
  "properties": {
    "name": "Rāja Sānsi",
    "country": "IN",
    "subdivision": "23",
    "timezone": "Asia/Kolkata"
  },
  "geometry": {
    "type": "Point",
    "coordinates": [
      74.8008,
      31.72021
    ]
  }
}