{
  "type": "Feature",
  "properties": {
    "name": "Ropar",
    "country": "IN",
    "subdivision": "23",
    "timezone": "Asia/Kolkata"
  },
  "geometry": {
    "type": "Point",
    "coordinates": [
      76.52695,
      30.96896
    ]
  }
}