{
  "type": "Feature",
  "properties": {
    "name": "Pionerskiy",
    "country": "RU",
    "subdivision": "32",
    "timezone": "Asia/Yekaterinburg"
  },
  "geometry": {
    "type": "Point",
    "coordinates": [
      62.86889,
      61.19472
    ]
  }
}