{
  "type": "Feature",
  "properties": {
    "name": "Kasugai",
    "country": "JP",
    "subdivision": "01",
    "timezone": "Asia/Tokyo"
  },
  "geometry": {
    "type": "Point",
    "coordinates": [
      136.97229,
      35.24762
    ]
  }
}