{
  "type": "Feature",
  "properties": {
    "name": "Kuroda",
    "country": "JP",
    "subdivision": "01",
    "timezone": "Asia/Tokyo"
  },
  "geometry": {
    "type": "Point",
    "coordinates": [
      136.78333,
      35.35
    ]
  }
}