{
  "type": "Feature",
  "properties": {
    "name": "Tokoname",
    "country": "JP",
    "subdivision": "01",
    "timezone": "Asia/Tokyo"
  },
  "geometry": {
    "type": "Point",
    "coordinates": [
      136.85,
      34.88333
    ]
  }
}