{
  "type": "Feature",
  "properties": {
    "name": "Tsushima",
    "country": "JP",
    "subdivision": "01",
    "timezone": "Asia/Tokyo"
  },
  "geometry": {
    "type": "Point",
    "coordinates": [
      136.71667,
      35.16667
    ]
  }
}