{
  "type": "Feature",
  "properties": {
    "name": "Allapattah",
    "country": "US",
    "subdivision": "FL",
    "timezone": "America/New_York"
  },
  "geometry": {
    "type": "Point",
    "coordinates": [
      -80.22394,
      25.81454
    ]
  }
}