{
  "type": "Feature",
  "properties": {
    "name": "Apollo Beach",
    "country": "US",
    "subdivision": "FL",
    "timezone": "America/New_York"
  },
  "geometry": {
    "type": "Point",
    "coordinates": [
      -82.40759,
      27.77308
    ]
  }
}