{
  "type": "Feature",
  "properties": {
    "name": "Bokeelia",
    "country": "US",
    "subdivision": "FL",
    "timezone": "America/New_York"
  },
  "geometry": {
    "type": "Point",
    "coordinates": [
      -82.15898,
      26.70563
    ]
  }
}