{
  "type": "Feature",
  "properties": {
    "name": "Bonita Springs",
    "country": "US",
    "subdivision": "FL",
    "timezone": "America/New_York"
  },
  "geometry": {
    "type": "Point",
    "coordinates": [
      -81.7787,
      26.33981
    ]
  }
}