{
  "type": "Feature",
  "properties": {
    "name": "Boynton Beach",
    "country": "US",
    "subdivision": "FL",
    "timezone": "America/New_York"
  },
  "geometry": {
    "type": "Point",
    "coordinates": [
      -80.06643,
      26.52535
    ]
  }
}