{
  "type": "Feature",
  "properties": {
    "name": "Bronson",
    "country": "US",
    "subdivision": "FL",
    "timezone": "America/New_York"
  },
  "geometry": {
    "type": "Point",
    "coordinates": [
      -82.64233,
      29.44774
    ]
  }
}