{
  "type": "Feature",
  "properties": {
    "name": "Brooksville",
    "country": "US",
    "subdivision": "FL",
    "timezone": "America/New_York"
  },
  "geometry": {
    "type": "Point",
    "coordinates": [
      -82.38991,
      28.55554
    ]
  }
}