{
  "type": "Feature",
  "properties": {
    "name": "Bunche Park",
    "country": "US",
    "subdivision": "FL",
    "timezone": "America/New_York"
  },
  "geometry": {
    "type": "Point",
    "coordinates": [
      -80.23699,
      25.92065
    ]
  }
}