{
  "type": "Feature",
  "properties": {
    "name": "Cape Canaveral",
    "country": "US",
    "subdivision": "FL",
    "timezone": "America/New_York"
  },
  "geometry": {
    "type": "Point",
    "coordinates": [
      -80.60477,
      28.40584
    ]
  }
}