{
  "type": "Feature",
  "properties": {
    "name": "Carrollwood Village",
    "country": "US",
    "subdivision": "FL",
    "timezone": "America/New_York"
  },
  "geometry": {
    "type": "Point",
    "coordinates": [
      -82.52093,
      28.06752
    ]
  }
}