{
  "type": "Feature",
  "properties": {
    "name": "Chipley",
    "country": "US",
    "subdivision": "FL",
    "timezone": "America/Chicago"
  },
  "geometry": {
    "type": "Point",
    "coordinates": [
      -85.53854,
      30.78186
    ]
  }
}