{
  "type": "Feature",
  "properties": {
    "name": "Cocoa",
    "country": "US",
    "subdivision": "FL",
    "timezone": "America/New_York"
  },
  "geometry": {
    "type": "Point",
    "coordinates": [
      -80.742,
      28.38612
    ]
  }
}