{
  "type": "Feature",
  "properties": {
    "name": "Connerton",
    "country": "US",
    "subdivision": "FL",
    "timezone": "America/New_York"
  },
  "geometry": {
    "type": "Point",
    "coordinates": [
      -82.47539,
      28.31441
    ]
  }
}