{
  "type": "Feature",
  "properties": {
    "name": "Crestview",
    "country": "US",
    "subdivision": "FL",
    "timezone": "America/Chicago"
  },
  "geometry": {
    "type": "Point",
    "coordinates": [
      -86.57051,
      30.76213
    ]
  }
}