{
  "type": "Feature",
  "properties": {
    "name": "Cudjoe Key",
    "country": "US",
    "subdivision": "FL",
    "timezone": "America/New_York"
  },
  "geometry": {
    "type": "Point",
    "coordinates": [
      -81.49842,
      24.67153
    ]
  }
}