{
  "type": "Feature",
  "properties": {
    "name": "Doctor Phillips",
    "country": "US",
    "subdivision": "FL",
    "timezone": "America/New_York"
  },
  "geometry": {
    "type": "Point",
    "coordinates": [
      -81.49229,
      28.44945
    ]
  }
}