{
  "type": "Feature",
  "properties": {
    "name": "East Perrine",
    "country": "US",
    "subdivision": "FL",
    "timezone": "America/New_York"
  },
  "geometry": {
    "type": "Point",
    "coordinates": [
      -80.33894,
      25.60872
    ]
  }
}