{
  "type": "Feature",
  "properties": {
    "name": "Elfers",
    "country": "US",
    "subdivision": "FL",
    "timezone": "America/New_York"
  },
  "geometry": {
    "type": "Point",
    "coordinates": [
      -82.72232,
      28.21668
    ]
  }
}