{
  "type": "Feature",
  "properties": {
    "name": "Fairview Shores",
    "country": "US",
    "subdivision": "FL",
    "timezone": "America/New_York"
  },
  "geometry": {
    "type": "Point",
    "coordinates": [
      -81.39424,
      28.59111
    ]
  }
}