{
  "type": "Feature",
  "properties": {
    "name": "Fellsmere",
    "country": "US",
    "subdivision": "FL",
    "timezone": "America/New_York"
  },
  "geometry": {
    "type": "Point",
    "coordinates": [
      -80.60144,
      27.76781
    ]
  }
}