{
  "type": "Feature",
  "properties": {
    "name": "Fleming Island",
    "country": "US",
    "subdivision": "FL",
    "timezone": "America/New_York"
  },
  "geometry": {
    "type": "Point",
    "coordinates": [
      -81.71898,
      30.0933
    ]
  }
}