{
  "type": "Feature",
  "properties": {
    "name": "Floral City",
    "country": "US",
    "subdivision": "FL",
    "timezone": "America/New_York"
  },
  "geometry": {
    "type": "Point",
    "coordinates": [
      -82.29676,
      28.74999
    ]
  }
}