{
  "type": "Feature",
  "properties": {
    "name": "Fort Myers Shores",
    "country": "US",
    "subdivision": "FL",
    "timezone": "America/New_York"
  },
  "geometry": {
    "type": "Point",
    "coordinates": [
      -81.74592,
      26.70924
    ]
  }
}