{
  "type": "Feature",
  "properties": {
    "name": "Frostproof",
    "country": "US",
    "subdivision": "FL",
    "timezone": "America/New_York"
  },
  "geometry": {
    "type": "Point",
    "coordinates": [
      -81.53063,
      27.74586
    ]
  }
}