{
  "type": "Feature",
  "properties": {
    "name": "Fruitland Park",
    "country": "US",
    "subdivision": "FL",
    "timezone": "America/New_York"
  },
  "geometry": {
    "type": "Point",
    "coordinates": [
      -81.90647,
      28.86138
    ]
  }
}