{
  "type": "Feature",
  "properties": {
    "name": "Gainesville",
    "country": "US",
    "subdivision": "FL",
    "timezone": "America/New_York"
  },
  "geometry": {
    "type": "Point",
    "coordinates": [
      -82.32483,
      29.65163
    ]
  }
}