{
  "type": "Feature",
  "properties": {
    "name": "Gibsonia",
    "country": "US",
    "subdivision": "FL",
    "timezone": "America/New_York"
  },
  "geometry": {
    "type": "Point",
    "coordinates": [
      -81.97369,
      28.11474
    ]
  }
}