{
  "type": "Feature",
  "properties": {
    "name": "Gladeview",
    "country": "US",
    "subdivision": "FL",
    "timezone": "America/New_York"
  },
  "geometry": {
    "type": "Point",
    "coordinates": [
      -80.2356,
      25.83926
    ]
  }
}