{
  "type": "Feature",
  "properties": {
    "name": "Gotha",
    "country": "US",
    "subdivision": "FL",
    "timezone": "America/New_York"
  },
  "geometry": {
    "type": "Point",
    "coordinates": [
      -81.52313,
      28.52778
    ]
  }
}