{
  "type": "Feature",
  "properties": {
    "name": "Goulds",
    "country": "US",
    "subdivision": "FL",
    "timezone": "America/New_York"
  },
  "geometry": {
    "type": "Point",
    "coordinates": [
      -80.38228,
      25.56261
    ]
  }
}