{
  "type": "Feature",
  "properties": {
    "name": "Grant-Valkaria",
    "country": "US",
    "subdivision": "FL",
    "timezone": "America/New_York"
  },
  "geometry": {
    "type": "Point",
    "coordinates": [
      -80.57104,
      27.9398
    ]
  }
}