{
  "type": "Feature",
  "properties": {
    "name": "Hallandale Beach",
    "country": "US",
    "subdivision": "FL",
    "timezone": "America/New_York"
  },
  "geometry": {
    "type": "Point",
    "coordinates": [
      -80.14838,
      25.9812
    ]
  }
}