{
  "type": "Feature",
  "properties": {
    "name": "Hernando",
    "country": "US",
    "subdivision": "FL",
    "timezone": "America/New_York"
  },
  "geometry": {
    "type": "Point",
    "coordinates": [
      -82.37454,
      28.89998
    ]
  }
}