{
  "type": "Feature",
  "properties": {
    "name": "Holly Hill",
    "country": "US",
    "subdivision": "FL",
    "timezone": "America/New_York"
  },
  "geometry": {
    "type": "Point",
    "coordinates": [
      -81.03756,
      29.24359
    ]
  }
}