{
  "type": "Feature",
  "properties": {
    "name": "Howey-in-the-Hills",
    "country": "US",
    "subdivision": "FL",
    "timezone": "America/New_York"
  },
  "geometry": {
    "type": "Point",
    "coordinates": [
      -81.77341,
      28.71694
    ]
  }
}