{
  "type": "Feature",
  "properties": {
    "name": "Immokalee",
    "country": "US",
    "subdivision": "FL",
    "timezone": "America/New_York"
  },
  "geometry": {
    "type": "Point",
    "coordinates": [
      -81.4173,
      26.41869
    ]
  }
}