{
  "type": "Feature",
  "properties": {
    "name": "Indian Harbour Beach",
    "country": "US",
    "subdivision": "FL",
    "timezone": "America/New_York"
  },
  "geometry": {
    "type": "Point",
    "coordinates": [
      -80.58839,
      28.1489
    ]
  }
}