{
  "type": "Feature",
  "properties": {
    "name": "Interlachen",
    "country": "US",
    "subdivision": "FL",
    "timezone": "America/New_York"
  },
  "geometry": {
    "type": "Point",
    "coordinates": [
      -81.89256,
      29.62421
    ]
  }
}