{
  "type": "Feature",
  "properties": {
    "name": "Islamorada",
    "country": "US",
    "subdivision": "FL",
    "timezone": "America/New_York"
  },
  "geometry": {
    "type": "Point",
    "coordinates": [
      -80.62784,
      24.9243
    ]
  }
}