{
  "type": "Feature",
  "properties": {
    "name": "Jasper",
    "country": "US",
    "subdivision": "FL",
    "timezone": "America/New_York"
  },
  "geometry": {
    "type": "Point",
    "coordinates": [
      -82.94819,
      30.51827
    ]
  }
}