{
  "type": "Feature",
  "properties": {
    "name": "Kenneth City",
    "country": "US",
    "subdivision": "FL",
    "timezone": "America/New_York"
  },
  "geometry": {
    "type": "Point",
    "coordinates": [
      -82.7201,
      27.81558
    ]
  }
}