{
  "type": "Feature",
  "properties": {
    "name": "Keystone Heights",
    "country": "US",
    "subdivision": "FL",
    "timezone": "America/New_York"
  },
  "geometry": {
    "type": "Point",
    "coordinates": [
      -82.03149,
      29.78608
    ]
  }
}