{
  "type": "Feature",
  "properties": {
    "name": "Keystone",
    "country": "US",
    "subdivision": "FL",
    "timezone": "America/New_York"
  },
  "geometry": {
    "type": "Point",
    "coordinates": [
      -82.62121,
      28.15585
    ]
  }
}