{
  "type": "Feature",
  "properties": {
    "name": "Kings Point",
    "country": "US",
    "subdivision": "FL",
    "timezone": "America/New_York"
  },
  "geometry": {
    "type": "Point",
    "coordinates": [
      -80.13977,
      26.44535
    ]
  }
}