{
  "type": "Feature",
  "properties": {
    "name": "Lake Worth Corridor",
    "country": "US",
    "subdivision": "FL",
    "timezone": "America/New_York"
  },
  "geometry": {
    "type": "Point",
    "coordinates": [
      -80.10102,
      26.61649
    ]
  }
}