{
  "type": "Feature",
  "properties": {
    "name": "Lakes by the Bay",
    "country": "US",
    "subdivision": "FL",
    "timezone": "America/New_York"
  },
  "geometry": {
    "type": "Point",
    "coordinates": [
      -80.32533,
      25.57233
    ]
  }
}