{
  "type": "Feature",
  "properties": {
    "name": "Lealman",
    "country": "US",
    "subdivision": "FL",
    "timezone": "America/New_York"
  },
  "geometry": {
    "type": "Point",
    "coordinates": [
      -82.67927,
      27.82114
    ]
  }
}