{
  "type": "Feature",
  "properties": {
    "name": "Marianna",
    "country": "US",
    "subdivision": "FL",
    "timezone": "America/Chicago"
  },
  "geometry": {
    "type": "Point",
    "coordinates": [
      -85.22687,
      30.77436
    ]
  }
}