{
  "type": "Feature",
  "properties": {
    "name": "Mayo",
    "country": "US",
    "subdivision": "FL",
    "timezone": "America/New_York"
  },
  "geometry": {
    "type": "Point",
    "coordinates": [
      -83.17486,
      30.053
    ]
  }
}