{
  "type": "Feature",
  "properties": {
    "name": "Miami Shores",
    "country": "US",
    "subdivision": "FL",
    "timezone": "America/New_York"
  },
  "geometry": {
    "type": "Point",
    "coordinates": [
      -80.19283,
      25.86315
    ]
  }
}