{
  "type": "Feature",
  "properties": {
    "name": "Milton",
    "country": "US",
    "subdivision": "FL",
    "timezone": "America/Chicago"
  },
  "geometry": {
    "type": "Point",
    "coordinates": [
      -87.03969,
      30.63241
    ]
  }
}