{
  "type": "Feature",
  "properties": {
    "name": "Mims",
    "country": "US",
    "subdivision": "FL",
    "timezone": "America/New_York"
  },
  "geometry": {
    "type": "Point",
    "coordinates": [
      -80.84478,
      28.66527
    ]
  }
}