{
  "type": "Feature",
  "properties": {
    "name": "Newberry",
    "country": "US",
    "subdivision": "FL",
    "timezone": "America/New_York"
  },
  "geometry": {
    "type": "Point",
    "coordinates": [
      -82.6065,
      29.64635
    ]
  }
}