{
  "type": "Feature",
  "properties": {
    "name": "Nocatee",
    "country": "US",
    "subdivision": "FL",
    "timezone": "America/New_York"
  },
  "geometry": {
    "type": "Point",
    "coordinates": [
      -81.88231,
      27.16033
    ]
  }
}