{
  "type": "Feature",
  "properties": {
    "name": "North Miami",
    "country": "US",
    "subdivision": "FL",
    "timezone": "America/New_York"
  },
  "geometry": {
    "type": "Point",
    "coordinates": [
      -80.18671,
      25.89009
    ]
  }
}