{
  "type": "Feature",
  "properties": {
    "name": "North DeLand",
    "country": "US",
    "subdivision": "FL",
    "timezone": "America/New_York"
  },
  "geometry": {
    "type": "Point",
    "coordinates": [
      -81.29812,
      29.04943
    ]
  }
}