{
  "type": "Feature",
  "properties": {
    "name": "Oakland Park",
    "country": "US",
    "subdivision": "FL",
    "timezone": "America/New_York"
  },
  "geometry": {
    "type": "Point",
    "coordinates": [
      -80.13199,
      26.17231
    ]
  }
}