{
  "type": "Feature",
  "properties": {
    "name": "Olga",
    "country": "US",
    "subdivision": "FL",
    "timezone": "America/New_York"
  },
  "geometry": {
    "type": "Point",
    "coordinates": [
      -81.7123,
      26.71896
    ]
  }
}