{
  "type": "Feature",
  "properties": {
    "name": "Opa-locka",
    "country": "US",
    "subdivision": "FL",
    "timezone": "America/New_York"
  },
  "geometry": {
    "type": "Point",
    "coordinates": [
      -80.25033,
      25.90232
    ]
  }
}