{
  "type": "Feature",
  "properties": {
    "name": "Palm City",
    "country": "US",
    "subdivision": "FL",
    "timezone": "America/New_York"
  },
  "geometry": {
    "type": "Point",
    "coordinates": [
      -80.26616,
      27.16783
    ]
  }
}