{
  "type": "Feature",
  "properties": {
    "name": "Palm Springs",
    "country": "US",
    "subdivision": "FL",
    "timezone": "America/New_York"
  },
  "geometry": {
    "type": "Point",
    "coordinates": [
      -80.09615,
      26.6359
    ]
  }
}