{
  "type": "Feature",
  "properties": {
    "name": "Palm Valley",
    "country": "US",
    "subdivision": "FL",
    "timezone": "America/New_York"
  },
  "geometry": {
    "type": "Point",
    "coordinates": [
      -81.38758,
      30.17746
    ]
  }
}