{
  "type": "Feature",
  "properties": {
    "name": "Panama City Beach",
    "country": "US",
    "subdivision": "FL",
    "timezone": "America/Chicago"
  },
  "geometry": {
    "type": "Point",
    "coordinates": [
      -85.80549,
      30.17659
    ]
  }
}