{
  "type": "Feature",
  "properties": {
    "name": "Parker",
    "country": "US",
    "subdivision": "FL",
    "timezone": "America/Chicago"
  },
  "geometry": {
    "type": "Point",
    "coordinates": [
      -85.60326,
      30.13104
    ]
  }
}