{
  "type": "Feature",
  "properties": {
    "name": "Pine Hills",
    "country": "US",
    "subdivision": "FL",
    "timezone": "America/New_York"
  },
  "geometry": {
    "type": "Point",
    "coordinates": [
      -81.4534,
      28.55778
    ]
  }
}