{
  "type": "Feature",
  "properties": {
    "name": "Port LaBelle",
    "country": "US",
    "subdivision": "FL",
    "timezone": "America/New_York"
  },
  "geometry": {
    "type": "Point",
    "coordinates": [
      -81.40508,
      26.75645
    ]
  }
}