{
  "type": "Feature",
  "properties": {
    "name": "Punta Gorda Isles",
    "country": "US",
    "subdivision": "FL",
    "timezone": "America/New_York"
  },
  "geometry": {
    "type": "Point",
    "coordinates": [
      -82.07842,
      26.91756
    ]
  }
}