{
  "type": "Feature",
  "properties": {
    "name": "Saint George",
    "country": "US",
    "subdivision": "FL",
    "timezone": "America/New_York"
  },
  "geometry": {
    "type": "Point",
    "coordinates": [
      -82.72788,
      28.05641
    ]
  }
}