{
  "type": "Feature",
  "properties": {
    "name": "Seffner",
    "country": "US",
    "subdivision": "FL",
    "timezone": "America/New_York"
  },
  "geometry": {
    "type": "Point",
    "coordinates": [
      -82.27565,
      27.98363
    ]
  }
}