{
  "type": "Feature",
  "properties": {
    "name": "Sharpes",
    "country": "US",
    "subdivision": "FL",
    "timezone": "America/New_York"
  },
  "geometry": {
    "type": "Point",
    "coordinates": [
      -80.76005,
      28.43223
    ]
  }
}