{
  "type": "Feature",
  "properties": {
    "name": "Sky Lake",
    "country": "US",
    "subdivision": "FL",
    "timezone": "America/New_York"
  },
  "geometry": {
    "type": "Point",
    "coordinates": [
      -81.39146,
      28.45723
    ]
  }
}