{
  "type": "Feature",
  "properties": {
    "name": "South Venice",
    "country": "US",
    "subdivision": "FL",
    "timezone": "America/New_York"
  },
  "geometry": {
    "type": "Point",
    "coordinates": [
      -82.42426,
      27.05311
    ]
  }
}