{
  "type": "Feature",
  "properties": {
    "name": "South Miami Heights",
    "country": "US",
    "subdivision": "FL",
    "timezone": "America/New_York"
  },
  "geometry": {
    "type": "Point",
    "coordinates": [
      -80.38061,
      25.59761
    ]
  }
}