{
  "type": "Feature",
  "properties": {
    "name": "South Daytona",
    "country": "US",
    "subdivision": "FL",
    "timezone": "America/New_York"
  },
  "geometry": {
    "type": "Point",
    "coordinates": [
      -81.0045,
      29.16582
    ]
  }
}