{
  "type": "Feature",
  "properties": {
    "name": "South Patrick Shores",
    "country": "US",
    "subdivision": "FL",
    "timezone": "America/New_York"
  },
  "geometry": {
    "type": "Point",
    "coordinates": [
      -80.6095,
      28.20223
    ]
  }
}