{
  "type": "Feature",
  "properties": {
    "name": "Suncoast Estates",
    "country": "US",
    "subdivision": "FL",
    "timezone": "America/New_York"
  },
  "geometry": {
    "type": "Point",
    "coordinates": [
      -81.86897,
      26.71174
    ]
  }
}