{
  "type": "Feature",
  "properties": {
    "name": "Sunny Isles Beach",
    "country": "US",
    "subdivision": "FL",
    "timezone": "America/New_York"
  },
  "geometry": {
    "type": "Point",
    "coordinates": [
      -80.12282,
      25.95065
    ]
  }
}