{
  "type": "Feature",
  "properties": {
    "name": "Taft",
    "country": "US",
    "subdivision": "FL",
    "timezone": "America/New_York"
  },
  "geometry": {
    "type": "Point",
    "coordinates": [
      -81.36507,
      28.42973
    ]
  }
}