{
  "type": "Feature",
  "properties": {
    "name": "Tangelo Park",
    "country": "US",
    "subdivision": "FL",
    "timezone": "America/New_York"
  },
  "geometry": {
    "type": "Point",
    "coordinates": [
      -81.4459,
      28.45584
    ]
  }
}