{
  "type": "Feature",
  "properties": {
    "name": "Tierra Verde",
    "country": "US",
    "subdivision": "FL",
    "timezone": "America/New_York"
  },
  "geometry": {
    "type": "Point",
    "coordinates": [
      -82.72343,
      27.69197
    ]
  }
}