{
  "type": "Feature",
  "properties": {
    "name": "Trinity",
    "country": "US",
    "subdivision": "FL",
    "timezone": "America/New_York"
  },
  "geometry": {
    "type": "Point",
    "coordinates": [
      -82.68177,
      28.18085
    ]
  }
}