{
  "type": "Feature",
  "properties": {
    "name": "Wekiwa Springs",
    "country": "US",
    "subdivision": "FL",
    "timezone": "America/New_York"
  },
  "geometry": {
    "type": "Point",
    "coordinates": [
      -81.42563,
      28.69861
    ]
  }
}