{
  "type": "Feature",
  "properties": {
    "name": "Westwood Lake",
    "country": "US",
    "subdivision": "FL",
    "timezone": "America/New_York"
  },
  "geometry": {
    "type": "Point",
    "coordinates": [
      -80.37283,
      25.72927
    ]
  }
}