{
  "type": "Feature",
  "properties": {
    "name": "Windermere",
    "country": "US",
    "subdivision": "FL",
    "timezone": "America/New_York"
  },
  "geometry": {
    "type": "Point",
    "coordinates": [
      -81.5348,
      28.49556
    ]
  }
}