{
  "type": "Feature",
  "properties": {
    "name": "Youngstown",
    "country": "US",
    "subdivision": "FL",
    "timezone": "America/Chicago"
  },
  "geometry": {
    "type": "Point",
    "coordinates": [
      -85.43826,
      30.36436
    ]
  }
}