{
  "type": "Feature",
  "properties": {
    "name": "Covrigi",
    "country": "RO",
    "subdivision": "19",
    "timezone": "Europe/Bucharest"
  },
  "geometry": {
    "type": "Point",
    "coordinates": [
      23.14921,
      44.73825
    ]
  }
}