{
  "type": "Feature",
  "properties": {
    "name": "Dăneşti",
    "country": "RO",
    "subdivision": "19",
    "timezone": "Europe/Bucharest"
  },
  "geometry": {
    "type": "Point",
    "coordinates": [
      23.33333,
      44.96667
    ]
  }
}