{
  "type": "Feature",
  "properties": {
    "name": "Samarineşti",
    "country": "RO",
    "subdivision": "19",
    "timezone": "Europe/Bucharest"
  },
  "geometry": {
    "type": "Point",
    "coordinates": [
      23.05,
      44.75
    ]
  }
}