{
  "type": "Feature",
  "properties": {
    "name": "Sterpoaia",
    "country": "RO",
    "subdivision": "19",
    "timezone": "Europe/Bucharest"
  },
  "geometry": {
    "type": "Point",
    "coordinates": [
      23.43601,
      44.79058
    ]
  }
}