{
  "type": "Feature",
  "properties": {
    "name": "Turburea",
    "country": "RO",
    "subdivision": "19",
    "timezone": "Europe/Bucharest"
  },
  "geometry": {
    "type": "Point",
    "coordinates": [
      23.51667,
      44.71667
    ]
  }
}