{
  "type": "Feature",
  "properties": {
    "name": "Vlăduleni",
    "country": "RO",
    "subdivision": "19",
    "timezone": "Europe/Bucharest"
  },
  "geometry": {
    "type": "Point",
    "coordinates": [
      23.23727,
      44.88857
    ]
  }
}