{
  "type": "Feature",
  "properties": {
    "name": "Mezőhegyes",
    "country": "HU",
    "subdivision": "03",
    "timezone": "Europe/Budapest"
  },
  "geometry": {
    "type": "Point",
    "coordinates": [
      20.81667,
      46.31667
    ]
  }
}