{
  "type": "Feature",
  "properties": {
    "name": "Nagyszénás",
    "country": "HU",
    "subdivision": "03",
    "timezone": "Europe/Budapest"
  },
  "geometry": {
    "type": "Point",
    "coordinates": [
      20.66667,
      46.68333
    ]
  }
}