{
  "type": "Feature",
  "properties": {
    "name": "Vésztő",
    "country": "HU",
    "subdivision": "03",
    "timezone": "Europe/Budapest"
  },
  "geometry": {
    "type": "Point",
    "coordinates": [
      21.26667,
      46.91667
    ]
  }
}