{
  "type": "Feature",
  "properties": {
    "name": "Banī Suwayf",
    "country": "EG",
    "subdivision": "18",
    "timezone": "Africa/Cairo"
  },
  "geometry": {
    "type": "Point",
    "coordinates": [
      31.09785,
      29.07441
    ]
  }
}