{
  "type": "Feature",
  "properties": {
    "name": "Goa Velha",
    "country": "IN",
    "subdivision": "33",
    "timezone": "Asia/Kolkata"
  },
  "geometry": {
    "type": "Point",
    "coordinates": [
      73.88572,
      15.44384
    ]
  }
}