{
  "type": "Feature",
  "properties": {
    "name": "Solim",
    "country": "IN",
    "subdivision": "33",
    "timezone": "Asia/Kolkata"
  },
  "geometry": {
    "type": "Point",
    "coordinates": [
      73.7674,
      15.61521
    ]
  }
}