{
  "type": "Feature",
  "properties": {
    "name": "Nyamanari",
    "country": "GM",
    "subdivision": "04",
    "timezone": "Africa/Banjul"
  },
  "geometry": {
    "type": "Point",
    "coordinates": [
      -13.86667,
      13.33333
    ]
  }
}