{
  "type": "Feature",
  "properties": {
    "name": "Sun Kunda",
    "country": "GM",
    "subdivision": "04",
    "timezone": "Africa/Banjul"
  },
  "geometry": {
    "type": "Point",
    "coordinates": [
      -13.85,
      13.38333
    ]
  }
}