{
  "type": "Feature",
  "properties": {
    "name": "Boquerón",
    "country": "PR",
    "subdivision": "023",
    "timezone": "America/Puerto_Rico"
  },
  "geometry": {
    "type": "Point",
    "coordinates": [
      -67.16907,
      18.02691
    ]
  }
}