{
  "type": "Feature",
  "properties": {
    "name": "Bahate",
    "country": "UA",
    "subdivision": "17",
    "timezone": "Europe/Kiev"
  },
  "geometry": {
    "type": "Point",
    "coordinates": [
      28.94254,
      45.40718
    ]
  }
}