{
  "type": "Feature",
  "properties": {
    "name": "Bashtankiv",
    "country": "UA",
    "subdivision": "17",
    "timezone": "Europe/Kiev"
  },
  "geometry": {
    "type": "Point",
    "coordinates": [
      29.00075,
      48.10641
    ]
  }
}