{
  "type": "Feature",
  "properties": {
    "name": "Bendzary",
    "country": "UA",
    "subdivision": "17",
    "timezone": "Europe/Kiev"
  },
  "geometry": {
    "type": "Point",
    "coordinates": [
      29.67703,
      47.9288
    ]
  }
}