{
  "type": "Feature",
  "properties": {
    "name": "Bilhorod-Dnistrovskyi",
    "country": "UA",
    "subdivision": "17",
    "timezone": "Europe/Kiev"
  },
  "geometry": {
    "type": "Point",
    "coordinates": [
      30.34827,
      46.19484
    ]
  }
}