{
  "type": "Feature",
  "properties": {
    "name": "Broska",
    "country": "UA",
    "subdivision": "17",
    "timezone": "Europe/Kiev"
  },
  "geometry": {
    "type": "Point",
    "coordinates": [
      28.78805,
      45.36943
    ]
  }
}