{
  "type": "Feature",
  "properties": {
    "name": "Izmail",
    "country": "UA",
    "subdivision": "17",
    "timezone": "Europe/Kiev"
  },
  "geometry": {
    "type": "Point",
    "coordinates": [
      28.83751,
      45.35058
    ]
  }
}