{
  "type": "Feature",
  "properties": {
    "name": "Kaharlyk",
    "country": "UA",
    "subdivision": "17",
    "timezone": "Europe/Kiev"
  },
  "geometry": {
    "type": "Point",
    "coordinates": [
      30.1963,
      46.60044
    ]
  }
}