{
  "type": "Feature",
  "properties": {
    "name": "Karolino-Buhaz",
    "country": "UA",
    "subdivision": "17",
    "timezone": "Europe/Kiev"
  },
  "geometry": {
    "type": "Point",
    "coordinates": [
      30.54124,
      46.14993
    ]
  }
}