{
  "type": "Feature",
  "properties": {
    "name": "Kremidivka",
    "country": "UA",
    "subdivision": "17",
    "timezone": "Europe/Kiev"
  },
  "geometry": {
    "type": "Point",
    "coordinates": [
      30.78472,
      46.73351
    ]
  }
}