{
  "type": "Feature",
  "properties": {
    "name": "Krutoiarivka",
    "country": "UA",
    "subdivision": "17",
    "timezone": "Europe/Kiev"
  },
  "geometry": {
    "type": "Point",
    "coordinates": [
      29.82075,
      46.35744
    ]
  }
}