{
  "type": "Feature",
  "properties": {
    "name": "Kurisove",
    "country": "UA",
    "subdivision": "17",
    "timezone": "Europe/Kiev"
  },
  "geometry": {
    "type": "Point",
    "coordinates": [
      30.95914,
      46.96951
    ]
  }
}