{
  "type": "Feature",
  "properties": {
    "name": "Labushne",
    "country": "UA",
    "subdivision": "17",
    "timezone": "Europe/Kiev"
  },
  "geometry": {
    "type": "Point",
    "coordinates": [
      29.13654,
      48.02239
    ]
  }
}