{
  "type": "Feature",
  "properties": {
    "name": "Mykolayivka",
    "country": "UA",
    "subdivision": "17",
    "timezone": "Europe/Kiev"
  },
  "geometry": {
    "type": "Point",
    "coordinates": [
      30.76007,
      47.53898
    ]
  }
}