{
  "type": "Feature",
  "properties": {
    "name": "Myrne",
    "country": "UA",
    "subdivision": "17",
    "timezone": "Europe/Kiev"
  },
  "geometry": {
    "type": "Point",
    "coordinates": [
      30.37136,
      46.4681
    ]
  }
}