{
  "type": "Feature",
  "properties": {
    "name": "Novosilske",
    "country": "UA",
    "subdivision": "17",
    "timezone": "Europe/Kiev"
  },
  "geometry": {
    "type": "Point",
    "coordinates": [
      28.57169,
      45.33425
    ]
  }
}