{
  "type": "Feature",
  "properties": {
    "name": "Ostrivne",
    "country": "UA",
    "subdivision": "17",
    "timezone": "Europe/Kiev"
  },
  "geometry": {
    "type": "Point",
    "coordinates": [
      29.15348,
      45.76031
    ]
  }
}