{
  "type": "Feature",
  "properties": {
    "name": "Perekhrestove",
    "country": "UA",
    "subdivision": "17",
    "timezone": "Europe/Kiev"
  },
  "geometry": {
    "type": "Point",
    "coordinates": [
      29.79827,
      47.43529
    ]
  }
}