{
  "type": "Feature",
  "properties": {
    "name": "Pysarivka",
    "country": "UA",
    "subdivision": "17",
    "timezone": "Europe/Kiev"
  },
  "geometry": {
    "type": "Point",
    "coordinates": [
      29.04549,
      48.04988
    ]
  }
}