{
  "type": "Feature",
  "properties": {
    "name": "Reni",
    "country": "UA",
    "subdivision": "17",
    "timezone": "Europe/Kiev"
  },
  "geometry": {
    "type": "Point",
    "coordinates": [
      28.27731,
      45.45421
    ]
  }
}