{
  "type": "Feature",
  "properties": {
    "name": "Roksolany",
    "country": "UA",
    "subdivision": "17",
    "timezone": "Europe/Kiev"
  },
  "geometry": {
    "type": "Point",
    "coordinates": [
      30.4568,
      46.17608
    ]
  }
}