{
  "type": "Feature",
  "properties": {
    "name": "Rozkvit",
    "country": "UA",
    "subdivision": "17",
    "timezone": "Europe/Kiev"
  },
  "geometry": {
    "type": "Point",
    "coordinates": [
      30.61522,
      47.12322
    ]
  }
}