{
  "type": "Feature",
  "properties": {
    "name": "Serbka",
    "country": "UA",
    "subdivision": "17",
    "timezone": "Europe/Kiev"
  },
  "geometry": {
    "type": "Point",
    "coordinates": [
      30.76252,
      47.00502
    ]
  }
}