{
  "type": "Feature",
  "properties": {
    "name": "Serpneve",
    "country": "UA",
    "subdivision": "17",
    "timezone": "Europe/Kiev"
  },
  "geometry": {
    "type": "Point",
    "coordinates": [
      29.01519,
      46.30452
    ]
  }
}