{
  "type": "Feature",
  "properties": {
    "name": "Shershentsi",
    "country": "UA",
    "subdivision": "17",
    "timezone": "Europe/Kiev"
  },
  "geometry": {
    "type": "Point",
    "coordinates": [
      29.00876,
      47.98823
    ]
  }
}