{
  "type": "Feature",
  "properties": {
    "name": "Stari Troyany",
    "country": "UA",
    "subdivision": "17",
    "timezone": "Europe/Kiev"
  },
  "geometry": {
    "type": "Point",
    "coordinates": [
      29.1787,
      45.67264
    ]
  }
}