{
  "type": "Feature",
  "properties": {
    "name": "Stavkove",
    "country": "UA",
    "subdivision": "17",
    "timezone": "Europe/Kiev"
  },
  "geometry": {
    "type": "Point",
    "coordinates": [
      30.63545,
      47.17961
    ]
  }
}