{
  "type": "Feature",
  "properties": {
    "name": "Tatarbunary",
    "country": "UA",
    "subdivision": "17",
    "timezone": "Europe/Kiev"
  },
  "geometry": {
    "type": "Point",
    "coordinates": [
      29.61123,
      45.83861
    ]
  }
}