{
  "type": "Feature",
  "properties": {
    "name": "Tochylove",
    "country": "UA",
    "subdivision": "17",
    "timezone": "Europe/Kiev"
  },
  "geometry": {
    "type": "Point",
    "coordinates": [
      29.74867,
      47.7712
    ]
  }
}