{
  "type": "Feature",
  "properties": {
    "name": "Troyitske",
    "country": "UA",
    "subdivision": "17",
    "timezone": "Europe/Kiev"
  },
  "geometry": {
    "type": "Point",
    "coordinates": [
      30.29025,
      47.6394
    ]
  }
}