{
  "type": "Feature",
  "properties": {
    "name": "Vasylivka",
    "country": "UA",
    "subdivision": "17",
    "timezone": "Europe/Kiev"
  },
  "geometry": {
    "type": "Point",
    "coordinates": [
      30.30578,
      46.60835
    ]
  }
}