{
  "type": "Feature",
  "properties": {
    "name": "Voznesenka Persha",
    "country": "UA",
    "subdivision": "17",
    "timezone": "Europe/Kiev"
  },
  "geometry": {
    "type": "Point",
    "coordinates": [
      29.47882,
      46.1316
    ]
  }
}