{
  "type": "Feature",
  "properties": {
    "name": "Vynohradivka",
    "country": "UA",
    "subdivision": "17",
    "timezone": "Europe/Kiev"
  },
  "geometry": {
    "type": "Point",
    "coordinates": [
      29.12035,
      46.08029
    ]
  }
}