{
  "type": "Feature",
  "properties": {
    "name": "Zherebkove",
    "country": "UA",
    "subdivision": "17",
    "timezone": "Europe/Kiev"
  },
  "geometry": {
    "type": "Point",
    "coordinates": [
      29.87475,
      47.84021
    ]
  }
}