{
  "type": "Feature",
  "properties": {
    "name": "Heilbron",
    "country": "ZA",
    "subdivision": "03",
    "timezone": "Africa/Johannesburg"
  },
  "geometry": {
    "type": "Point",
    "coordinates": [
      27.9709,
      -27.28115
    ]
  }
}