{
  "type": "Feature",
  "properties": {
    "name": "Koppies",
    "country": "ZA",
    "subdivision": "03",
    "timezone": "Africa/Johannesburg"
  },
  "geometry": {
    "type": "Point",
    "coordinates": [
      27.57422,
      -27.24179
    ]
  }
}