{
  "type": "Feature",
  "properties": {
    "name": "Haeju",
    "country": "KP",
    "subdivision": "06",
    "timezone": "Asia/Pyongyang"
  },
  "geometry": {
    "type": "Point",
    "coordinates": [
      125.71472,
      38.04056
    ]
  }
}