{
  "type": "Feature",
  "properties": {
    "name": "Nioki",
    "country": "CD",
    "subdivision": "24",
    "timezone": "Africa/Kinshasa"
  },
  "geometry": {
    "type": "Point",
    "coordinates": [
      17.69001,
      -2.72037
    ]
  }
}