{
  "type": "Feature",
  "properties": {
    "name": "Albina",
    "country": "SR",
    "subdivision": "13",
    "timezone": "America/Paramaribo"
  },
  "geometry": {
    "type": "Point",
    "coordinates": [
      -54.05522,
      5.49788
    ]
  }
}