{
  "type": "Feature",
  "properties": {
    "name": "Moengo",
    "country": "SR",
    "subdivision": "13",
    "timezone": "America/Paramaribo"
  },
  "geometry": {
    "type": "Point",
    "coordinates": [
      -54.40121,
      5.61411
    ]
  }
}