{
  "type": "Feature",
  "properties": {
    "name": "Aztec",
    "country": "US",
    "subdivision": "NM",
    "timezone": "America/Denver"
  },
  "geometry": {
    "type": "Point",
    "coordinates": [
      -107.99285,
      36.82223
    ]
  }
}