{
  "type": "Feature",
  "properties": {
    "name": "Boles Acres",
    "country": "US",
    "subdivision": "NM",
    "timezone": "America/Denver"
  },
  "geometry": {
    "type": "Point",
    "coordinates": [
      -105.9861,
      32.80703
    ]
  }
}