{
  "type": "Feature",
  "properties": {
    "name": "Capitan",
    "country": "US",
    "subdivision": "NM",
    "timezone": "America/Denver"
  },
  "geometry": {
    "type": "Point",
    "coordinates": [
      -105.5722,
      33.54536
    ]
  }
}