{
  "type": "Feature",
  "properties": {
    "name": "Clovis",
    "country": "US",
    "subdivision": "NM",
    "timezone": "America/Denver"
  },
  "geometry": {
    "type": "Point",
    "coordinates": [
      -103.20523,
      34.4048
    ]
  }
}