{
  "type": "Feature",
  "properties": {
    "name": "Columbus",
    "country": "US",
    "subdivision": "NM",
    "timezone": "America/Denver"
  },
  "geometry": {
    "type": "Point",
    "coordinates": [
      -107.64002,
      31.8276
    ]
  }
}