{
  "type": "Feature",
  "properties": {
    "name": "Corrales",
    "country": "US",
    "subdivision": "NM",
    "timezone": "America/Denver"
  },
  "geometry": {
    "type": "Point",
    "coordinates": [
      -106.60669,
      35.23782
    ]
  }
}