{
  "type": "Feature",
  "properties": {
    "name": "Deming",
    "country": "US",
    "subdivision": "NM",
    "timezone": "America/Denver"
  },
  "geometry": {
    "type": "Point",
    "coordinates": [
      -107.75864,
      32.2687
    ]
  }
}