{
  "type": "Feature",
  "properties": {
    "name": "El Valle de Arroyo Seco",
    "country": "US",
    "subdivision": "NM",
    "timezone": "America/Denver"
  },
  "geometry": {
    "type": "Point",
    "coordinates": [
      -106.02947,
      35.9628
    ]
  }
}