{
  "type": "Feature",
  "properties": {
    "name": "Hatch",
    "country": "US",
    "subdivision": "NM",
    "timezone": "America/Denver"
  },
  "geometry": {
    "type": "Point",
    "coordinates": [
      -107.15307,
      32.66536
    ]
  }
}