{
  "type": "Feature",
  "properties": {
    "name": "La Cienega",
    "country": "US",
    "subdivision": "NM",
    "timezone": "America/Denver"
  },
  "geometry": {
    "type": "Point",
    "coordinates": [
      -106.13086,
      35.56281
    ]
  }
}