{
  "type": "Feature",
  "properties": {
    "name": "Lee Acres",
    "country": "US",
    "subdivision": "NM",
    "timezone": "America/Denver"
  },
  "geometry": {
    "type": "Point",
    "coordinates": [
      -106.64697,
      35.14866
    ]
  }
}