{
  "type": "Feature",
  "properties": {
    "name": "Ohkay Owingeh",
    "country": "US",
    "subdivision": "NM",
    "timezone": "America/Denver"
  },
  "geometry": {
    "type": "Point",
    "coordinates": [
      -106.06897,
      36.05082
    ]
  }
}