{
  "type": "Feature",
  "properties": {
    "name": "Ruidoso Downs",
    "country": "US",
    "subdivision": "NM",
    "timezone": "America/Denver"
  },
  "geometry": {
    "type": "Point",
    "coordinates": [
      -105.60443,
      33.32897
    ]
  }
}