{
  "type": "Feature",
  "properties": {
    "name": "Santa Rosa",
    "country": "US",
    "subdivision": "NM",
    "timezone": "America/Denver"
  },
  "geometry": {
    "type": "Point",
    "coordinates": [
      -104.68249,
      34.93867
    ]
  }
}