{
  "type": "Feature",
  "properties": {
    "name": "Socorro",
    "country": "US",
    "subdivision": "NM",
    "timezone": "America/Denver"
  },
  "geometry": {
    "type": "Point",
    "coordinates": [
      -106.89142,
      34.0584
    ]
  }
}