{
  "type": "Feature",
  "properties": {
    "name": "Vado",
    "country": "US",
    "subdivision": "NM",
    "timezone": "America/Denver"
  },
  "geometry": {
    "type": "Point",
    "coordinates": [
      -106.6625,
      32.11176
    ]
  }
}