{
  "type": "Feature",
  "properties": {
    "name": "Eflani",
    "country": "TR",
    "subdivision": "89",
    "timezone": "Europe/Istanbul"
  },
  "geometry": {
    "type": "Point",
    "coordinates": [
      32.95761,
      41.42289
    ]
  }
}