{
  "type": "Feature",
  "properties": {
    "name": "Sola",
    "country": "VU",
    "subdivision": "07",
    "timezone": "Pacific/Efate"
  },
  "geometry": {
    "type": "Point",
    "coordinates": [
      167.55167,
      -13.87611
    ]
  }
}