{
  "type": "Feature",
  "properties": {
    "name": "Finström",
    "country": "AX",
    "subdivision": "212",
    "timezone": "Europe/Mariehamn"
  },
  "geometry": {
    "type": "Point",
    "coordinates": [
      19.93333,
      60.26667
    ]
  }
}