{
  "type": "Feature",
  "properties": {
    "name": "Bad Sankt Leonhard im Lavanttal",
    "country": "AT",
    "subdivision": "02",
    "timezone": "Europe/Vienna"
  },
  "geometry": {
    "type": "Point",
    "coordinates": [
      14.79167,
      46.96278
    ]
  }
}