{
  "type": "Feature",
  "properties": {
    "name": "Föderlach I",
    "country": "AT",
    "subdivision": "02",
    "timezone": "Europe/Vienna"
  },
  "geometry": {
    "type": "Point",
    "coordinates": [
      13.96128,
      46.59998
    ]
  }
}