{
  "type": "Feature",
  "properties": {
    "name": "Klein Sankt Paul",
    "country": "AT",
    "subdivision": "02",
    "timezone": "Europe/Vienna"
  },
  "geometry": {
    "type": "Point",
    "coordinates": [
      14.54139,
      46.83611
    ]
  }
}