{
  "type": "Feature",
  "properties": {
    "name": "Sankt Paul im Levanttal",
    "country": "AT",
    "subdivision": "02",
    "timezone": "Europe/Vienna"
  },
  "geometry": {
    "type": "Point",
    "coordinates": [
      14.87556,
      46.70056
    ]
  }
}