{
  "type": "Feature",
  "properties": {
    "name": "St. Agathen und Perau",
    "country": "AT",
    "subdivision": "02",
    "timezone": "Europe/Vienna"
  },
  "geometry": {
    "type": "Point",
    "coordinates": [
      13.85615,
      46.60627
    ]
  }
}