{
  "type": "Feature",
  "properties": {
    "name": "Untere Fellach",
    "country": "AT",
    "subdivision": "02",
    "timezone": "Europe/Vienna"
  },
  "geometry": {
    "type": "Point",
    "coordinates": [
      13.82681,
      46.62504
    ]
  }
}