{
  "type": "Feature",
  "properties": {
    "name": "Viktring",
    "country": "AT",
    "subdivision": "02",
    "timezone": "Europe/Vienna"
  },
  "geometry": {
    "type": "Point",
    "coordinates": [
      14.26917,
      46.59194
    ]
  }
}