{
  "type": "Feature",
  "properties": {
    "name": "Nakano",
    "country": "JP",
    "subdivision": "26",
    "timezone": "Asia/Tokyo"
  },
  "geometry": {
    "type": "Point",
    "coordinates": [
      138.36667,
      36.75
    ]
  }
}