{
  "type": "Feature",
  "properties": {
    "name": "Afula",
    "country": "IL",
    "subdivision": "03",
    "timezone": "Asia/Jerusalem"
  },
  "geometry": {
    "type": "Point",
    "coordinates": [
      35.2892,
      32.60907
    ]
  }
}