{
  "type": "Feature",
  "properties": {
    "name": "Beit Jann",
    "country": "IL",
    "subdivision": "03",
    "timezone": "Asia/Jerusalem"
  },
  "geometry": {
    "type": "Point",
    "coordinates": [
      35.38152,
      32.96464
    ]
  }
}