{
  "type": "Feature",
  "properties": {
    "name": "Fassūta",
    "country": "IL",
    "subdivision": "03",
    "timezone": "Asia/Jerusalem"
  },
  "geometry": {
    "type": "Point",
    "coordinates": [
      35.30893,
      33.04895
    ]
  }
}