{
  "type": "Feature",
  "properties": {
    "name": "Judeida Makr",
    "country": "IL",
    "subdivision": "03",
    "timezone": "Asia/Jerusalem"
  },
  "geometry": {
    "type": "Point",
    "coordinates": [
      35.15705,
      32.9282
    ]
  }
}