{
  "type": "Feature",
  "properties": {
    "name": "Kammon",
    "country": "IL",
    "subdivision": "03",
    "timezone": "Asia/Jerusalem"
  },
  "geometry": {
    "type": "Point",
    "coordinates": [
      35.36075,
      32.90891
    ]
  }
}