{
  "type": "Feature",
  "properties": {
    "name": "maalot Tarshīhā",
    "country": "IL",
    "subdivision": "03",
    "timezone": "Asia/Jerusalem"
  },
  "geometry": {
    "type": "Point",
    "coordinates": [
      35.26667,
      33.01667
    ]
  }
}