{
  "type": "Feature",
  "properties": {
    "name": "MaghÄr",
    "country": "IL",
    "subdivision": "03",
    "timezone": "Asia/Jerusalem"
  },
  "geometry": {
    "type": "Point",
    "coordinates": [
      35.40703,
      32.88984
    ]
  }
}