{
  "type": "Feature",
  "properties": {
    "name": "Metulla",
    "country": "IL",
    "subdivision": "03",
    "timezone": "Asia/Jerusalem"
  },
  "geometry": {
    "type": "Point",
    "coordinates": [
      35.5795,
      33.27918
    ]
  }
}