{
  "type": "Feature",
  "properties": {
    "name": "Nā‘ūra",
    "country": "IL",
    "subdivision": "03",
    "timezone": "Asia/Jerusalem"
  },
  "geometry": {
    "type": "Point",
    "coordinates": [
      35.39168,
      32.61403
    ]
  }
}