{
  "type": "Feature",
  "properties": {
    "name": "Nein",
    "country": "IL",
    "subdivision": "03",
    "timezone": "Asia/Jerusalem"
  },
  "geometry": {
    "type": "Point",
    "coordinates": [
      35.34885,
      32.63063
    ]
  }
}