{
  "type": "Feature",
  "properties": {
    "name": "Qiryat Shemona",
    "country": "IL",
    "subdivision": "03",
    "timezone": "Asia/Jerusalem"
  },
  "geometry": {
    "type": "Point",
    "coordinates": [
      35.57212,
      33.20733
    ]
  }
}