{
  "type": "Feature",
  "properties": {
    "name": "Ramat Yishay",
    "country": "IL",
    "subdivision": "03",
    "timezone": "Asia/Jerusalem"
  },
  "geometry": {
    "type": "Point",
    "coordinates": [
      35.1707,
      32.70444
    ]
  }
}