{
  "type": "Feature",
  "properties": {
    "name": "Raqqefet",
    "country": "IL",
    "subdivision": "03",
    "timezone": "Asia/Jerusalem"
  },
  "geometry": {
    "type": "Point",
    "coordinates": [
      35.26142,
      32.85744
    ]
  }
}