{
  "type": "Feature",
  "properties": {
    "name": "Tiberias",
    "country": "IL",
    "subdivision": "03",
    "timezone": "Asia/Jerusalem"
  },
  "geometry": {
    "type": "Point",
    "coordinates": [
      35.53124,
      32.79221
    ]
  }
}