{
  "type": "Feature",
  "properties": {
    "name": "Yāfā",
    "country": "IL",
    "subdivision": "03",
    "timezone": "Asia/Jerusalem"
  },
  "geometry": {
    "type": "Point",
    "coordinates": [
      35.27832,
      32.68923
    ]
  }
}