{
  "type": "Feature",
  "properties": {
    "name": "Yanuah Jat",
    "country": "IL",
    "subdivision": "03",
    "timezone": "Asia/Jerusalem"
  },
  "geometry": {
    "type": "Point",
    "coordinates": [
      35.23806,
      32.9798
    ]
  }
}