{
  "type": "Feature",
  "properties": {
    "name": "Yif‘at",
    "country": "IL",
    "subdivision": "03",
    "timezone": "Asia/Jerusalem"
  },
  "geometry": {
    "type": "Point",
    "coordinates": [
      35.22333,
      32.6775
    ]
  }
}