{
  "type": "Feature",
  "properties": {
    "name": "Yuvallim",
    "country": "IL",
    "subdivision": "03",
    "timezone": "Asia/Jerusalem"
  },
  "geometry": {
    "type": "Point",
    "coordinates": [
      35.27031,
      32.87756
    ]
  }
}