{
  "type": "Feature",
  "properties": {
    "name": "‘Aramsha",
    "country": "IL",
    "subdivision": "03",
    "timezone": "Asia/Jerusalem"
  },
  "geometry": {
    "type": "Point",
    "coordinates": [
      35.22836,
      33.08781
    ]
  }
}