{
  "type": "Feature",
  "properties": {
    "name": "‘Ilūṭ",
    "country": "IL",
    "subdivision": "03",
    "timezone": "Asia/Jerusalem"
  },
  "geometry": {
    "type": "Point",
    "coordinates": [
      35.25944,
      32.71639
    ]
  }
}