{
  "type": "Feature",
  "properties": {
    "name": "Bellevue",
    "country": "US",
    "subdivision": "ID",
    "timezone": "America/Boise"
  },
  "geometry": {
    "type": "Point",
    "coordinates": [
      -114.2606,
      43.46352
    ]
  }
}