{
  "type": "Feature",
  "properties": {
    "name": "Glenns Ferry",
    "country": "US",
    "subdivision": "ID",
    "timezone": "America/Boise"
  },
  "geometry": {
    "type": "Point",
    "coordinates": [
      -115.3009,
      42.9549
    ]
  }
}