{
  "type": "Feature",
  "properties": {
    "name": "Hayden",
    "country": "US",
    "subdivision": "ID",
    "timezone": "America/Los_Angeles"
  },
  "geometry": {
    "type": "Point",
    "coordinates": [
      -116.78658,
      47.76602
    ]
  }
}