{
  "type": "Feature",
  "properties": {
    "name": "McCall",
    "country": "US",
    "subdivision": "ID",
    "timezone": "America/Boise"
  },
  "geometry": {
    "type": "Point",
    "coordinates": [
      -116.09874,
      44.91101
    ]
  }
}