{
  "type": "Feature",
  "properties": {
    "name": "Middleton",
    "country": "US",
    "subdivision": "ID",
    "timezone": "America/Boise"
  },
  "geometry": {
    "type": "Point",
    "coordinates": [
      -116.62014,
      43.70683
    ]
  }
}