{
  "type": "Feature",
  "properties": {
    "name": "Montpelier",
    "country": "US",
    "subdivision": "ID",
    "timezone": "America/Boise"
  },
  "geometry": {
    "type": "Point",
    "coordinates": [
      -111.2977,
      42.32215
    ]
  }
}