{
  "type": "Feature",
  "properties": {
    "name": "Moreland",
    "country": "US",
    "subdivision": "ID",
    "timezone": "America/Boise"
  },
  "geometry": {
    "type": "Point",
    "coordinates": [
      -112.44248,
      43.22269
    ]
  }
}