{
  "type": "Feature",
  "properties": {
    "name": "Paul",
    "country": "US",
    "subdivision": "ID",
    "timezone": "America/Boise"
  },
  "geometry": {
    "type": "Point",
    "coordinates": [
      -113.78335,
      42.60796
    ]
  }
}