{
  "type": "Feature",
  "properties": {
    "name": "Rupert",
    "country": "US",
    "subdivision": "ID",
    "timezone": "America/Boise"
  },
  "geometry": {
    "type": "Point",
    "coordinates": [
      -113.67723,
      42.61908
    ]
  }
}