{
  "type": "Feature",
  "properties": {
    "name": "Wendell",
    "country": "US",
    "subdivision": "ID",
    "timezone": "America/Boise"
  },
  "geometry": {
    "type": "Point",
    "coordinates": [
      -114.70422,
      42.77574
    ]
  }
}