{
  "type": "Feature",
  "properties": {
    "name": "Patzún",
    "country": "GT",
    "subdivision": "03",
    "timezone": "America/Guatemala"
  },
  "geometry": {
    "type": "Point",
    "coordinates": [
      -91.01397,
      14.68189
    ]
  }
}