{
  "type": "Feature",
  "properties": {
    "name": "Pochuta",
    "country": "GT",
    "subdivision": "03",
    "timezone": "America/Guatemala"
  },
  "geometry": {
    "type": "Point",
    "coordinates": [
      -91.08904,
      14.5445
    ]
  }
}