{
  "type": "Feature",
  "properties": {
    "name": "New Yekepa",
    "country": "LR",
    "subdivision": "09",
    "timezone": "Africa/Monrovia"
  },
  "geometry": {
    "type": "Point",
    "coordinates": [
      -8.53778,
      7.57944
    ]
  }
}