{
  "type": "Feature",
  "properties": {
    "name": "Grammenítsa",
    "country": "GR",
    "subdivision": "ESYE21",
    "timezone": "Europe/Athens"
  },
  "geometry": {
    "type": "Point",
    "coordinates": [
      20.97933,
      39.18444
    ]
  }
}