{
  "type": "Feature",
  "properties": {
    "name": "Kostakioí",
    "country": "GR",
    "subdivision": "ESYE21",
    "timezone": "Europe/Athens"
  },
  "geometry": {
    "type": "Point",
    "coordinates": [
      20.95761,
      39.13672
    ]
  }
}