{
  "type": "Feature",
  "properties": {
    "name": "Loúros",
    "country": "GR",
    "subdivision": "ESYE21",
    "timezone": "Europe/Athens"
  },
  "geometry": {
    "type": "Point",
    "coordinates": [
      20.75608,
      39.166
    ]
  }
}