{
  "type": "Feature",
  "properties": {
    "name": "Neochorópoulo",
    "country": "GR",
    "subdivision": "ESYE21",
    "timezone": "Europe/Athens"
  },
  "geometry": {
    "type": "Point",
    "coordinates": [
      20.83558,
      39.62553
    ]
  }
}