{
  "type": "Feature",
  "properties": {
    "name": "Pérama",
    "country": "GR",
    "subdivision": "ESYE21",
    "timezone": "Europe/Athens"
  },
  "geometry": {
    "type": "Point",
    "coordinates": [
      20.84656,
      39.69331
    ]
  }
}