{
  "type": "Feature",
  "properties": {
    "name": "Préveza",
    "country": "GR",
    "subdivision": "ESYE21",
    "timezone": "Europe/Athens"
  },
  "geometry": {
    "type": "Point",
    "coordinates": [
      20.7505,
      38.95617
    ]
  }
}