{
  "type": "Feature",
  "properties": {
    "name": "Rodotópi",
    "country": "GR",
    "subdivision": "ESYE21",
    "timezone": "Europe/Athens"
  },
  "geometry": {
    "type": "Point",
    "coordinates": [
      20.72656,
      39.70822
    ]
  }
}