{
  "type": "Feature",
  "properties": {
    "name": "Arroyo Seco",
    "country": "MX",
    "subdivision": "22",
    "timezone": "America/Mexico_City"
  },
  "geometry": {
    "type": "Point",
    "coordinates": [
      -99.68832,
      21.54777
    ]
  }
}