{
  "type": "Feature",
  "properties": {
    "name": "Cadereyta",
    "country": "MX",
    "subdivision": "22",
    "timezone": "America/Mexico_City"
  },
  "geometry": {
    "type": "Point",
    "coordinates": [
      -99.81624,
      20.69701
    ]
  }
}