{
  "type": "Feature",
  "properties": {
    "name": "Casa Blanca",
    "country": "MX",
    "subdivision": "22",
    "timezone": "America/Mexico_City"
  },
  "geometry": {
    "type": "Point",
    "coordinates": [
      -100.02009,
      20.38658
    ]
  }
}