{
  "type": "Feature",
  "properties": {
    "name": "Ceja de Bravo",
    "country": "MX",
    "subdivision": "22",
    "timezone": "America/Mexico_City"
  },
  "geometry": {
    "type": "Point",
    "coordinates": [
      -100.39423,
      20.37856
    ]
  }
}