{
  "type": "Feature",
  "properties": {
    "name": "Chichimequillas",
    "country": "MX",
    "subdivision": "22",
    "timezone": "America/Mexico_City"
  },
  "geometry": {
    "type": "Point",
    "coordinates": [
      -100.33588,
      20.76512
    ]
  }
}