{
  "type": "Feature",
  "properties": {
    "name": "Colón",
    "country": "MX",
    "subdivision": "22",
    "timezone": "America/Mexico_City"
  },
  "geometry": {
    "type": "Point",
    "coordinates": [
      -100.05149,
      20.78323
    ]
  }
}