{
  "type": "Feature",
  "properties": {
    "name": "El Lobo",
    "country": "MX",
    "subdivision": "22",
    "timezone": "America/Mexico_City"
  },
  "geometry": {
    "type": "Point",
    "coordinates": [
      -100.20226,
      20.72904
    ]
  }
}