{
  "type": "Feature",
  "properties": {
    "name": "Ignacio Pérez",
    "country": "MX",
    "subdivision": "22",
    "timezone": "America/Mexico_City"
  },
  "geometry": {
    "type": "Point",
    "coordinates": [
      -100.11129,
      20.52225
    ]
  }
}