{
  "type": "Feature",
  "properties": {
    "name": "Jalpan",
    "country": "MX",
    "subdivision": "22",
    "timezone": "America/Mexico_City"
  },
  "geometry": {
    "type": "Point",
    "coordinates": [
      -99.47152,
      21.21802
    ]
  }
}