{
  "type": "Feature",
  "properties": {
    "name": "Joaquín Herrera",
    "country": "MX",
    "subdivision": "22",
    "timezone": "America/Mexico_City"
  },
  "geometry": {
    "type": "Point",
    "coordinates": [
      -100.43854,
      20.483
    ]
  }
}