{
  "type": "Feature",
  "properties": {
    "name": "La Estacada",
    "country": "MX",
    "subdivision": "22",
    "timezone": "America/Mexico_City"
  },
  "geometry": {
    "type": "Point",
    "coordinates": [
      -100.40763,
      20.82151
    ]
  }
}