{
  "type": "Feature",
  "properties": {
    "name": "La Llave",
    "country": "MX",
    "subdivision": "22",
    "timezone": "America/Mexico_City"
  },
  "geometry": {
    "type": "Point",
    "coordinates": [
      -99.99373,
      20.46628
    ]
  }
}