{
  "type": "Feature",
  "properties": {
    "name": "La Piedad",
    "country": "MX",
    "subdivision": "22",
    "timezone": "America/Mexico_City"
  },
  "geometry": {
    "type": "Point",
    "coordinates": [
      -100.25573,
      20.5789
    ]
  }
}