{
  "type": "Feature",
  "properties": {
    "name": "La Tortuga",
    "country": "MX",
    "subdivision": "22",
    "timezone": "America/Mexico_City"
  },
  "geometry": {
    "type": "Point",
    "coordinates": [
      -99.92317,
      20.56703
    ]
  }
}