{
  "type": "Feature",
  "properties": {
    "name": "La Valla",
    "country": "MX",
    "subdivision": "22",
    "timezone": "America/Mexico_City"
  },
  "geometry": {
    "type": "Point",
    "coordinates": [
      -100.02689,
      20.49966
    ]
  }
}