{
  "type": "Feature",
  "properties": {
    "name": "Ninguno [CERESO]",
    "country": "MX",
    "subdivision": "22",
    "timezone": "America/Mexico_City"
  },
  "geometry": {
    "type": "Point",
    "coordinates": [
      -100.36028,
      20.67361
    ]
  }
}