{
  "type": "Feature",
  "properties": {
    "name": "Pinal de Amoles",
    "country": "MX",
    "subdivision": "22",
    "timezone": "America/Mexico_City"
  },
  "geometry": {
    "type": "Point",
    "coordinates": [
      -99.6259,
      21.13448
    ]
  }
}