{
  "type": "Feature",
  "properties": {
    "name": "Presa de Rayas",
    "country": "MX",
    "subdivision": "22",
    "timezone": "America/Mexico_City"
  },
  "geometry": {
    "type": "Point",
    "coordinates": [
      -100.22252,
      20.80712
    ]
  }
}