{
  "type": "Feature",
  "properties": {
    "name": "Puerto de Chiquihuite",
    "country": "MX",
    "subdivision": "22",
    "timezone": "America/Mexico_City"
  },
  "geometry": {
    "type": "Point",
    "coordinates": [
      -99.83528,
      20.70083
    ]
  }
}