{
  "type": "Feature",
  "properties": {
    "name": "Purísima de Cubos (La Purísima)",
    "country": "MX",
    "subdivision": "22",
    "timezone": "America/Mexico_City"
  },
  "geometry": {
    "type": "Point",
    "coordinates": [
      -100.11833,
      20.60028
    ]
  }
}