{
  "type": "Feature",
  "properties": {
    "name": "Rancho Bellavista [Fraccionamiento]",
    "country": "MX",
    "subdivision": "22",
    "timezone": "America/Mexico_City"
  },
  "geometry": {
    "type": "Point",
    "coordinates": [
      -100.44972,
      20.60667
    ]
  }
}