{
  "type": "Feature",
  "properties": {
    "name": "Saldarriaga",
    "country": "MX",
    "subdivision": "22",
    "timezone": "America/Mexico_City"
  },
  "geometry": {
    "type": "Point",
    "coordinates": [
      -100.29307,
      20.62781
    ]
  }
}