{
  "type": "Feature",
  "properties": {
    "name": "Santa María Begoña",
    "country": "MX",
    "subdivision": "22",
    "timezone": "America/Mexico_City"
  },
  "geometry": {
    "type": "Point",
    "coordinates": [
      -100.31765,
      20.74662
    ]
  }
}