{
  "type": "Feature",
  "properties": {
    "name": "Santillán",
    "country": "MX",
    "subdivision": "22",
    "timezone": "America/Mexico_City"
  },
  "geometry": {
    "type": "Point",
    "coordinates": [
      -99.93951,
      20.60073
    ]
  }
}