{
  "type": "Feature",
  "properties": {
    "name": "Sergio Villaseñor",
    "country": "MX",
    "subdivision": "22",
    "timezone": "America/Mexico_City"
  },
  "geometry": {
    "type": "Point",
    "coordinates": [
      -100.42083,
      20.645
    ]
  }
}