{
  "type": "Feature",
  "properties": {
    "name": "Tierra Blanca",
    "country": "MX",
    "subdivision": "22",
    "timezone": "America/Mexico_City"
  },
  "geometry": {
    "type": "Point",
    "coordinates": [
      -100.38,
      20.78026
    ]
  }
}