{
  "type": "Feature",
  "properties": {
    "name": "Zamorano",
    "country": "MX",
    "subdivision": "22",
    "timezone": "America/Mexico_City"
  },
  "geometry": {
    "type": "Point",
    "coordinates": [
      -100.11797,
      20.80819
    ]
  }
}