{
  "type": "Feature",
  "properties": {
    "name": "Esparza",
    "country": "CR",
    "subdivision": "07",
    "timezone": "America/Costa_Rica"
  },
  "geometry": {
    "type": "Point",
    "coordinates": [
      -84.66466,
      9.99447
    ]
  }
}