{
  "type": "Feature",
  "properties": {
    "name": "Paquera",
    "country": "CR",
    "subdivision": "07",
    "timezone": "America/Costa_Rica"
  },
  "geometry": {
    "type": "Point",
    "coordinates": [
      -84.93513,
      9.82005
    ]
  }
}