{
  "type": "Feature",
  "properties": {
    "name": "Puntarenas",
    "country": "CR",
    "subdivision": "07",
    "timezone": "America/Costa_Rica"
  },
  "geometry": {
    "type": "Point",
    "coordinates": [
      -84.83836,
      9.97625
    ]
  }
}