{
  "type": "Feature",
  "properties": {
    "name": "Acajutla",
    "country": "SV",
    "subdivision": "13",
    "timezone": "America/El_Salvador"
  },
  "geometry": {
    "type": "Point",
    "coordinates": [
      -89.8275,
      13.59278
    ]
  }
}