{
  "type": "Feature",
  "properties": {
    "name": "Anqing",
    "country": "CN",
    "subdivision": "01",
    "timezone": "Asia/Shanghai"
  },
  "geometry": {
    "type": "Point",
    "coordinates": [
      117.04723,
      30.51365
    ]
  }
}