{
  "type": "Feature",
  "properties": {
    "name": "Huoqiu Chengguanzhen",
    "country": "CN",
    "subdivision": "01",
    "timezone": "Asia/Shanghai"
  },
  "geometry": {
    "type": "Point",
    "coordinates": [
      116.2939,
      32.35473
    ]
  }
}