{
  "type": "Feature",
  "properties": {
    "name": "Suixi",
    "country": "CN",
    "subdivision": "01",
    "timezone": "Asia/Shanghai"
  },
  "geometry": {
    "type": "Point",
    "coordinates": [
      116.77473,
      33.89067
    ]
  }
}