{
  "type": "Feature",
  "properties": {
    "name": "Suzhou",
    "country": "CN",
    "subdivision": "01",
    "timezone": "Asia/Shanghai"
  },
  "geometry": {
    "type": "Point",
    "coordinates": [
      116.97889,
      33.63611
    ]
  }
}