{
  "type": "Feature",
  "properties": {
    "name": "Kolbäck",
    "country": "SE",
    "subdivision": "25",
    "timezone": "Europe/Stockholm"
  },
  "geometry": {
    "type": "Point",
    "coordinates": [
      16.23037,
      59.56516
    ]
  }
}