{
  "type": "Feature",
  "properties": {
    "name": "RehnÄn",
    "country": "IR",
    "subdivision": "28",
    "timezone": "Asia/Tehran"
  },
  "geometry": {
    "type": "Point",
    "coordinates": [
      51.60158,
      32.68325
    ]
  }
}