{
  "type": "Feature",
  "properties": {
    "name": "Yaté-Barrage",
    "country": "NC",
    "subdivision": "00",
    "timezone": "Pacific/Noumea"
  },
  "geometry": {
    "type": "Point",
    "coordinates": [
      166.88333,
      -22.15
    ]
  }
}