{
  "type": "Feature",
  "properties": {
    "name": "Tbeng Meanchey",
    "country": "KH",
    "subdivision": "13",
    "timezone": "Asia/Phnom_Penh"
  },
  "geometry": {
    "type": "Point",
    "coordinates": [
      104.98046,
      13.80731
    ]
  }
}