{
  "type": "Feature",
  "properties": {
    "name": "Biscoitos",
    "country": "PT",
    "subdivision": "23",
    "timezone": "Atlantic/Azores"
  },
  "geometry": {
    "type": "Point",
    "coordinates": [
      -27.25,
      38.78333
    ]
  }
}