{
  "type": "Feature",
  "properties": {
    "name": "Rabo de Peixe",
    "country": "PT",
    "subdivision": "23",
    "timezone": "Atlantic/Azores"
  },
  "geometry": {
    "type": "Point",
    "coordinates": [
      -25.58263,
      37.81022
    ]
  }
}