{
  "type": "Feature",
  "properties": {
    "name": "Bílovice nad Svitavou",
    "country": "CZ",
    "subdivision": "78",
    "timezone": "Europe/Prague"
  },
  "geometry": {
    "type": "Point",
    "coordinates": [
      16.67247,
      49.24708
    ]
  }
}