{
  "type": "Feature",
  "properties": {
    "name": "BluÄina",
    "country": "CZ",
    "subdivision": "78",
    "timezone": "Europe/Prague"
  },
  "geometry": {
    "type": "Point",
    "coordinates": [
      16.6445,
      49.05497
    ]
  }
}