{
  "type": "Feature",
  "properties": {
    "name": "Bošovice",
    "country": "CZ",
    "subdivision": "78",
    "timezone": "Europe/Prague"
  },
  "geometry": {
    "type": "Point",
    "coordinates": [
      16.83676,
      49.05351
    ]
  }
}