{
  "type": "Feature",
  "properties": {
    "name": "Černá Hora",
    "country": "CZ",
    "subdivision": "78",
    "timezone": "Europe/Prague"
  },
  "geometry": {
    "type": "Point",
    "coordinates": [
      16.5814,
      49.41361
    ]
  }
}