{
  "type": "Feature",
  "properties": {
    "name": "Dambořice",
    "country": "CZ",
    "subdivision": "78",
    "timezone": "Europe/Prague"
  },
  "geometry": {
    "type": "Point",
    "coordinates": [
      16.91757,
      49.03828
    ]
  }
}