{
  "type": "Feature",
  "properties": {
    "name": "Dolní Kounice",
    "country": "CZ",
    "subdivision": "78",
    "timezone": "Europe/Prague"
  },
  "geometry": {
    "type": "Point",
    "coordinates": [
      16.46492,
      49.07011
    ]
  }
}