{
  "type": "Feature",
  "properties": {
    "name": "Křepice",
    "country": "CZ",
    "subdivision": "78",
    "timezone": "Europe/Prague"
  },
  "geometry": {
    "type": "Point",
    "coordinates": [
      16.71989,
      48.99986
    ]
  }
}