{
  "type": "Feature",
  "properties": {
    "name": "Mikulov",
    "country": "CZ",
    "subdivision": "78",
    "timezone": "Europe/Prague"
  },
  "geometry": {
    "type": "Point",
    "coordinates": [
      16.6378,
      48.80556
    ]
  }
}