{
  "type": "Feature",
  "properties": {
    "name": "Moravský Písek",
    "country": "CZ",
    "subdivision": "78",
    "timezone": "Europe/Prague"
  },
  "geometry": {
    "type": "Point",
    "coordinates": [
      17.33269,
      48.99016
    ]
  }
}