{
  "type": "Feature",
  "properties": {
    "name": "Moutnice",
    "country": "CZ",
    "subdivision": "78",
    "timezone": "Europe/Prague"
  },
  "geometry": {
    "type": "Point",
    "coordinates": [
      16.73741,
      49.04924
    ]
  }
}