{
  "type": "Feature",
  "properties": {
    "name": "Nesovice",
    "country": "CZ",
    "subdivision": "78",
    "timezone": "Europe/Prague"
  },
  "geometry": {
    "type": "Point",
    "coordinates": [
      17.08095,
      49.15111
    ]
  }
}