{
  "type": "Feature",
  "properties": {
    "name": "Olbramovice",
    "country": "CZ",
    "subdivision": "78",
    "timezone": "Europe/Prague"
  },
  "geometry": {
    "type": "Point",
    "coordinates": [
      16.40239,
      48.9848
    ]
  }
}