{
  "type": "Feature",
  "properties": {
    "name": "Ořechov",
    "country": "CZ",
    "subdivision": "78",
    "timezone": "Europe/Prague"
  },
  "geometry": {
    "type": "Point",
    "coordinates": [
      16.52329,
      49.11118
    ]
  }
}