{
  "type": "Feature",
  "properties": {
    "name": "Oslavany",
    "country": "CZ",
    "subdivision": "78",
    "timezone": "Europe/Prague"
  },
  "geometry": {
    "type": "Point",
    "coordinates": [
      16.33653,
      49.12335
    ]
  }
}