{
  "type": "Feature",
  "properties": {
    "name": "Ostrov u Macochy",
    "country": "CZ",
    "subdivision": "78",
    "timezone": "Europe/Prague"
  },
  "geometry": {
    "type": "Point",
    "coordinates": [
      16.76268,
      49.38236
    ]
  }
}