{
  "type": "Feature",
  "properties": {
    "name": "Otnice",
    "country": "CZ",
    "subdivision": "78",
    "timezone": "Europe/Prague"
  },
  "geometry": {
    "type": "Point",
    "coordinates": [
      16.81443,
      49.08642
    ]
  }
}