{
  "type": "Feature",
  "properties": {
    "name": "Podolí",
    "country": "CZ",
    "subdivision": "78",
    "timezone": "Europe/Prague"
  },
  "geometry": {
    "type": "Point",
    "coordinates": [
      16.72084,
      49.19042
    ]
  }
}