{
  "type": "Feature",
  "properties": {
    "name": "Rajhrad",
    "country": "CZ",
    "subdivision": "78",
    "timezone": "Europe/Prague"
  },
  "geometry": {
    "type": "Point",
    "coordinates": [
      16.60388,
      49.09021
    ]
  }
}