{
  "type": "Feature",
  "properties": {
    "name": "Šakvice",
    "country": "CZ",
    "subdivision": "78",
    "timezone": "Europe/Prague"
  },
  "geometry": {
    "type": "Point",
    "coordinates": [
      16.71424,
      48.89746
    ]
  }
}