{
  "type": "Feature",
  "properties": {
    "name": "Tvarožná",
    "country": "CZ",
    "subdivision": "78",
    "timezone": "Europe/Prague"
  },
  "geometry": {
    "type": "Point",
    "coordinates": [
      16.77146,
      49.19177
    ]
  }
}