{
  "type": "Feature",
  "properties": {
    "name": "Višňové",
    "country": "CZ",
    "subdivision": "78",
    "timezone": "Europe/Prague"
  },
  "geometry": {
    "type": "Point",
    "coordinates": [
      16.15025,
      48.98241
    ]
  }
}