{
  "type": "Feature",
  "properties": {
    "name": "Zbraslav",
    "country": "CZ",
    "subdivision": "78",
    "timezone": "Europe/Prague"
  },
  "geometry": {
    "type": "Point",
    "coordinates": [
      16.29415,
      49.22155
    ]
  }
}