{
  "type": "Feature",
  "properties": {
    "name": "Žeravice",
    "country": "CZ",
    "subdivision": "78",
    "timezone": "Europe/Prague"
  },
  "geometry": {
    "type": "Point",
    "coordinates": [
      17.23726,
      49.02288
    ]
  }
}