{
  "type": "Feature",
  "properties": {
    "name": "Abu Fatira",
    "country": "KW",
    "subdivision": "09",
    "timezone": "Asia/Kuwait"
  },
  "geometry": {
    "type": "Point",
    "coordinates": [
      48.10278,
      29.19746
    ]
  }
}