{
  "type": "Feature",
  "properties": {
    "name": "Berëza",
    "country": "RU",
    "subdivision": "65",
    "timezone": "Europe/Samara"
  },
  "geometry": {
    "type": "Point",
    "coordinates": [
      50.13967,
      53.51833
    ]
  }
}