{
  "type": "Feature",
  "properties": {
    "name": "Khryashchevka",
    "country": "RU",
    "subdivision": "65",
    "timezone": "Europe/Samara"
  },
  "geometry": {
    "type": "Point",
    "coordinates": [
      49.0916,
      53.8119
    ]
  }
}