{
  "type": "Feature",
  "properties": {
    "name": "Kinel’",
    "country": "RU",
    "subdivision": "65",
    "timezone": "Europe/Samara"
  },
  "geometry": {
    "type": "Point",
    "coordinates": [
      50.62907,
      53.22571
    ]
  }
}