{
  "type": "Feature",
  "properties": {
    "name": "Novokuybyshevsk",
    "country": "RU",
    "subdivision": "65",
    "timezone": "Europe/Samara"
  },
  "geometry": {
    "type": "Point",
    "coordinates": [
      49.9462,
      53.0959
    ]
  }
}