{
  "type": "Feature",
  "properties": {
    "name": "Novosemeykino",
    "country": "RU",
    "subdivision": "65",
    "timezone": "Europe/Samara"
  },
  "geometry": {
    "type": "Point",
    "coordinates": [
      50.35428,
      53.37056
    ]
  }
}