{
  "type": "Feature",
  "properties": {
    "name": "Surgut",
    "country": "RU",
    "subdivision": "65",
    "timezone": "Europe/Samara"
  },
  "geometry": {
    "type": "Point",
    "coordinates": [
      51.20348,
      53.92498
    ]
  }
}