{
  "type": "Feature",
  "properties": {
    "name": "Zol’noye",
    "country": "RU",
    "subdivision": "65",
    "timezone": "Europe/Samara"
  },
  "geometry": {
    "type": "Point",
    "coordinates": [
      49.7978,
      53.4421
    ]
  }
}