{
  "type": "Feature",
  "properties": {
    "name": "ChÄmpa",
    "country": "IN",
    "subdivision": "37",
    "timezone": "Asia/Kolkata"
  },
  "geometry": {
    "type": "Point",
    "coordinates": [
      82.64234,
      22.03532
    ]
  }
}