{
  "type": "Feature",
  "properties": {
    "name": "Dhamtari",
    "country": "IN",
    "subdivision": "37",
    "timezone": "Asia/Kolkata"
  },
  "geometry": {
    "type": "Point",
    "coordinates": [
      81.54874,
      20.70718
    ]
  }
}