{
  "type": "Feature",
  "properties": {
    "name": "Durg",
    "country": "IN",
    "subdivision": "37",
    "timezone": "Asia/Kolkata"
  },
  "geometry": {
    "type": "Point",
    "coordinates": [
      81.27619,
      21.19147
    ]
  }
}