{
  "type": "Feature",
  "properties": {
    "name": "Gandai",
    "country": "IN",
    "subdivision": "37",
    "timezone": "Asia/Kolkata"
  },
  "geometry": {
    "type": "Point",
    "coordinates": [
      81.10013,
      21.66667
    ]
  }
}