{
  "type": "Feature",
  "properties": {
    "name": "Katghora",
    "country": "IN",
    "subdivision": "37",
    "timezone": "Asia/Kolkata"
  },
  "geometry": {
    "type": "Point",
    "coordinates": [
      82.54279,
      22.50247
    ]
  }
}