{
  "type": "Feature",
  "properties": {
    "name": "Kawardha",
    "country": "IN",
    "subdivision": "37",
    "timezone": "Asia/Kolkata"
  },
  "geometry": {
    "type": "Point",
    "coordinates": [
      81.23148,
      22.00853
    ]
  }
}