{
  "type": "Feature",
  "properties": {
    "name": "Kharsia",
    "country": "IN",
    "subdivision": "37",
    "timezone": "Asia/Kolkata"
  },
  "geometry": {
    "type": "Point",
    "coordinates": [
      83.10476,
      21.98953
    ]
  }
}