{
  "type": "Feature",
  "properties": {
    "name": "Kondagaon",
    "country": "IN",
    "subdivision": "37",
    "timezone": "Asia/Kolkata"
  },
  "geometry": {
    "type": "Point",
    "coordinates": [
      81.664,
      19.59083
    ]
  }
}