{
  "type": "Feature",
  "properties": {
    "name": "Korba",
    "country": "IN",
    "subdivision": "37",
    "timezone": "Asia/Kolkata"
  },
  "geometry": {
    "type": "Point",
    "coordinates": [
      82.69633,
      22.3458
    ]
  }
}