{
  "type": "Feature",
  "properties": {
    "name": "Pithora",
    "country": "IN",
    "subdivision": "37",
    "timezone": "Asia/Kolkata"
  },
  "geometry": {
    "type": "Point",
    "coordinates": [
      82.51707,
      21.25021
    ]
  }
}