{
  "type": "Feature",
  "properties": {
    "name": "Colón",
    "country": "CR",
    "subdivision": "08",
    "timezone": "America/Costa_Rica"
  },
  "geometry": {
    "type": "Point",
    "coordinates": [
      -84.2417,
      9.91491
    ]
  }
}