{
  "type": "Feature",
  "properties": {
    "name": "Granadilla",
    "country": "CR",
    "subdivision": "08",
    "timezone": "America/Costa_Rica"
  },
  "geometry": {
    "type": "Point",
    "coordinates": [
      -84.01688,
      9.93491
    ]
  }
}