{
  "type": "Feature",
  "properties": {
    "name": "Patarrá",
    "country": "CR",
    "subdivision": "08",
    "timezone": "America/Costa_Rica"
  },
  "geometry": {
    "type": "Point",
    "coordinates": [
      -84.03501,
      9.88071
    ]
  }
}