{
  "type": "Feature",
  "properties": {
    "name": "El Espino de Santa Rosa",
    "country": "PA",
    "subdivision": "10",
    "timezone": "America/Panama"
  },
  "geometry": {
    "type": "Point",
    "coordinates": [
      -80.8238,
      8.09286
    ]
  }
}