{
  "type": "Feature",
  "properties": {
    "name": "Danilovka",
    "country": "RU",
    "subdivision": "84",
    "timezone": "Europe/Volgograd"
  },
  "geometry": {
    "type": "Point",
    "coordinates": [
      44.11681,
      50.35573
    ]
  }
}