{
  "type": "Feature",
  "properties": {
    "name": "Leninsk",
    "country": "RU",
    "subdivision": "84",
    "timezone": "Europe/Volgograd"
  },
  "geometry": {
    "type": "Point",
    "coordinates": [
      45.19798,
      48.70233
    ]
  }
}