{
  "type": "Feature",
  "properties": {
    "name": "Volzhskiy",
    "country": "RU",
    "subdivision": "84",
    "timezone": "Europe/Volgograd"
  },
  "geometry": {
    "type": "Point",
    "coordinates": [
      44.77973,
      48.78583
    ]
  }
}