{
  "type": "Feature",
  "properties": {
    "name": "Zaplavnoye",
    "country": "RU",
    "subdivision": "84",
    "timezone": "Europe/Volgograd"
  },
  "geometry": {
    "type": "Point",
    "coordinates": [
      45.0229,
      48.7048
    ]
  }
}