{
  "type": "Feature",
  "properties": {
    "name": "Brezina",
    "country": "DZ",
    "subdivision": "42",
    "timezone": "Africa/Algiers"
  },
  "geometry": {
    "type": "Point",
    "coordinates": [
      1.26082,
      33.09892
    ]
  }
}