{
  "type": "Feature",
  "properties": {
    "name": "El Abiodh Sidi Cheikh",
    "country": "DZ",
    "subdivision": "42",
    "timezone": "Africa/Algiers"
  },
  "geometry": {
    "type": "Point",
    "coordinates": [
      0.54839,
      32.893
    ]
  }
}