{
  "type": "Feature",
  "properties": {
    "name": "Fnidek",
    "country": "MA",
    "subdivision": "01",
    "timezone": "Africa/Casablanca"
  },
  "geometry": {
    "type": "Point",
    "coordinates": [
      -5.35747,
      35.84906
    ]
  }
}