{
  "type": "Feature",
  "properties": {
    "name": "Aïn Kercha",
    "country": "DZ",
    "subdivision": "29",
    "timezone": "Africa/Algiers"
  },
  "geometry": {
    "type": "Point",
    "coordinates": [
      6.69528,
      35.92472
    ]
  }
}