{
  "type": "Feature",
  "properties": {
    "name": "Boungouéni",
    "country": "KM",
    "subdivision": "01",
    "timezone": "Indian/Comoro"
  },
  "geometry": {
    "type": "Point",
    "coordinates": [
      44.29944,
      -12.20556
    ]
  }
}