{
  "type": "Feature",
  "properties": {
    "name": "Hajoho",
    "country": "KM",
    "subdivision": "01",
    "timezone": "Indian/Comoro"
  },
  "geometry": {
    "type": "Point",
    "coordinates": [
      44.48881,
      -12.12434
    ]
  }
}