{
  "type": "Feature",
  "properties": {
    "name": "Kavani",
    "country": "KM",
    "subdivision": "01",
    "timezone": "Indian/Comoro"
  },
  "geometry": {
    "type": "Point",
    "coordinates": [
      44.26944,
      -12.19194
    ]
  }
}