{
  "type": "Feature",
  "properties": {
    "name": "Mirontsi",
    "country": "KM",
    "subdivision": "01",
    "timezone": "Indian/Comoro"
  },
  "geometry": {
    "type": "Point",
    "coordinates": [
      44.40806,
      -12.15667
    ]
  }
}