{
  "type": "Feature",
  "properties": {
    "name": "Bānāvar",
    "country": "IN",
    "subdivision": "19",
    "timezone": "Asia/Kolkata"
  },
  "geometry": {
    "type": "Point",
    "coordinates": [
      76.16314,
      13.41029
    ]
  }
}