{
  "type": "Feature",
  "properties": {
    "name": "Birūr",
    "country": "IN",
    "subdivision": "19",
    "timezone": "Asia/Kolkata"
  },
  "geometry": {
    "type": "Point",
    "coordinates": [
      75.97167,
      13.59723
    ]
  }
}