{
  "type": "Feature",
  "properties": {
    "name": "ByÄdgi",
    "country": "IN",
    "subdivision": "19",
    "timezone": "Asia/Kolkata"
  },
  "geometry": {
    "type": "Point",
    "coordinates": [
      75.4868,
      14.67325
    ]
  }
}