{
  "type": "Feature",
  "properties": {
    "name": "Gadag",
    "country": "IN",
    "subdivision": "19",
    "timezone": "Asia/Kolkata"
  },
  "geometry": {
    "type": "Point",
    "coordinates": [
      75.62971,
      15.42977
    ]
  }
}