{
  "type": "Feature",
  "properties": {
    "name": "GangÄwati",
    "country": "IN",
    "subdivision": "19",
    "timezone": "Asia/Kolkata"
  },
  "geometry": {
    "type": "Point",
    "coordinates": [
      76.52933,
      15.4313
    ]
  }
}