{
  "type": "Feature",
  "properties": {
    "name": "Guledagudda",
    "country": "IN",
    "subdivision": "19",
    "timezone": "Asia/Kolkata"
  },
  "geometry": {
    "type": "Point",
    "coordinates": [
      75.78997,
      16.05025
    ]
  }
}