{
  "type": "Feature",
  "properties": {
    "name": "Haliyal",
    "country": "IN",
    "subdivision": "19",
    "timezone": "Asia/Kolkata"
  },
  "geometry": {
    "type": "Point",
    "coordinates": [
      74.75638,
      15.32864
    ]
  }
}