{
  "type": "Feature",
  "properties": {
    "name": "Hukeri",
    "country": "IN",
    "subdivision": "19",
    "timezone": "Asia/Kolkata"
  },
  "geometry": {
    "type": "Point",
    "coordinates": [
      74.60244,
      16.23082
    ]
  }
}