{
  "type": "Feature",
  "properties": {
    "name": "Ilkal",
    "country": "IN",
    "subdivision": "19",
    "timezone": "Asia/Kolkata"
  },
  "geometry": {
    "type": "Point",
    "coordinates": [
      76.11351,
      15.95923
    ]
  }
}