{
  "type": "Feature",
  "properties": {
    "name": "Kalghatgi",
    "country": "IN",
    "subdivision": "19",
    "timezone": "Asia/Kolkata"
  },
  "geometry": {
    "type": "Point",
    "coordinates": [
      74.97099,
      15.18315
    ]
  }
}