{
  "type": "Feature",
  "properties": {
    "name": "Kerūr",
    "country": "IN",
    "subdivision": "19",
    "timezone": "Asia/Kolkata"
  },
  "geometry": {
    "type": "Point",
    "coordinates": [
      75.54631,
      16.01384
    ]
  }
}