{
  "type": "Feature",
  "properties": {
    "name": "Kudachi",
    "country": "IN",
    "subdivision": "19",
    "timezone": "Asia/Kolkata"
  },
  "geometry": {
    "type": "Point",
    "coordinates": [
      74.85408,
      16.62784
    ]
  }
}