{
  "type": "Feature",
  "properties": {
    "name": "Kurgunta",
    "country": "IN",
    "subdivision": "19",
    "timezone": "Asia/Kolkata"
  },
  "geometry": {
    "type": "Point",
    "coordinates": [
      77.35772,
      17.19321
    ]
  }
}