{
  "type": "Feature",
  "properties": {
    "name": "MahÄlingpur",
    "country": "IN",
    "subdivision": "19",
    "timezone": "Asia/Kolkata"
  },
  "geometry": {
    "type": "Point",
    "coordinates": [
      75.10873,
      16.3888
    ]
  }
}