{
  "type": "Feature",
  "properties": {
    "name": "Mangalore",
    "country": "IN",
    "subdivision": "19",
    "timezone": "Asia/Kolkata"
  },
  "geometry": {
    "type": "Point",
    "coordinates": [
      74.85603,
      12.91723
    ]
  }
}