{
  "type": "Feature",
  "properties": {
    "name": "Pāngāla",
    "country": "IN",
    "subdivision": "19",
    "timezone": "Asia/Kolkata"
  },
  "geometry": {
    "type": "Point",
    "coordinates": [
      74.75,
      13.25
    ]
  }
}