{
  "type": "Feature",
  "properties": {
    "name": "PiriyÄpatna",
    "country": "IN",
    "subdivision": "19",
    "timezone": "Asia/Kolkata"
  },
  "geometry": {
    "type": "Point",
    "coordinates": [
      76.10073,
      12.33497
    ]
  }
}