{
  "type": "Feature",
  "properties": {
    "name": "SÄgar",
    "country": "IN",
    "subdivision": "19",
    "timezone": "Asia/Kolkata"
  },
  "geometry": {
    "type": "Point",
    "coordinates": [
      75.02901,
      14.16498
    ]
  }
}