{
  "type": "Feature",
  "properties": {
    "name": "Saundatti",
    "country": "IN",
    "subdivision": "19",
    "timezone": "Asia/Kolkata"
  },
  "geometry": {
    "type": "Point",
    "coordinates": [
      75.11778,
      15.76615
    ]
  }
}