{
  "type": "Feature",
  "properties": {
    "name": "ShorÄpur",
    "country": "IN",
    "subdivision": "19",
    "timezone": "Asia/Kolkata"
  },
  "geometry": {
    "type": "Point",
    "coordinates": [
      76.75738,
      16.521
    ]
  }
}