{
  "type": "Feature",
  "properties": {
    "name": "SiddÄpur",
    "country": "IN",
    "subdivision": "19",
    "timezone": "Asia/Kolkata"
  },
  "geometry": {
    "type": "Point",
    "coordinates": [
      74.894,
      14.34322
    ]
  }
}