{
  "type": "Feature",
  "properties": {
    "name": "Sidlaghatta",
    "country": "IN",
    "subdivision": "19",
    "timezone": "Asia/Kolkata"
  },
  "geometry": {
    "type": "Point",
    "coordinates": [
      77.86444,
      13.38896
    ]
  }
}