{
  "type": "Feature",
  "properties": {
    "name": "Sorab",
    "country": "IN",
    "subdivision": "19",
    "timezone": "Asia/Kolkata"
  },
  "geometry": {
    "type": "Point",
    "coordinates": [
      75.09183,
      14.38144
    ]
  }
}