{
  "type": "Feature",
  "properties": {
    "name": "Sringeri",
    "country": "IN",
    "subdivision": "19",
    "timezone": "Asia/Kolkata"
  },
  "geometry": {
    "type": "Point",
    "coordinates": [
      75.25271,
      13.41698
    ]
  }
}