{
  "type": "Feature",
  "properties": {
    "name": "Tekkalakote",
    "country": "IN",
    "subdivision": "19",
    "timezone": "Asia/Kolkata"
  },
  "geometry": {
    "type": "Point",
    "coordinates": [
      76.87703,
      15.53444
    ]
  }
}