{
  "type": "Feature",
  "properties": {
    "name": "Tīrthahalli",
    "country": "IN",
    "subdivision": "19",
    "timezone": "Asia/Kolkata"
  },
  "geometry": {
    "type": "Point",
    "coordinates": [
      75.24548,
      13.68835
    ]
  }
}