{
  "type": "Feature",
  "properties": {
    "name": "Mäntyharju",
    "country": "FI",
    "subdivision": "10",
    "timezone": "Europe/Helsinki"
  },
  "geometry": {
    "type": "Point",
    "coordinates": [
      26.88333,
      61.41667
    ]
  }
}