{
  "type": "Feature",
  "properties": {
    "name": "Mikkeli",
    "country": "FI",
    "subdivision": "10",
    "timezone": "Europe/Helsinki"
  },
  "geometry": {
    "type": "Point",
    "coordinates": [
      27.27227,
      61.68857
    ]
  }
}