{
  "type": "Feature",
  "properties": {
    "name": "Sulkava",
    "country": "FI",
    "subdivision": "10",
    "timezone": "Europe/Helsinki"
  },
  "geometry": {
    "type": "Point",
    "coordinates": [
      28.37299,
      61.78691
    ]
  }
}