{
  "type": "Feature",
  "properties": {
    "name": "Kakunodatemachi",
    "country": "JP",
    "subdivision": "02",
    "timezone": "Asia/Tokyo"
  },
  "geometry": {
    "type": "Point",
    "coordinates": [
      140.56724,
      39.58926
    ]
  }
}