{
  "type": "Feature",
  "properties": {
    "name": "Karpogory",
    "country": "RU",
    "subdivision": "06",
    "timezone": "Europe/Moscow"
  },
  "geometry": {
    "type": "Point",
    "coordinates": [
      44.44513,
      64.00189
    ]
  }
}