{
  "type": "Feature",
  "properties": {
    "name": "Kizema",
    "country": "RU",
    "subdivision": "06",
    "timezone": "Europe/Moscow"
  },
  "geometry": {
    "type": "Point",
    "coordinates": [
      44.83017,
      61.11304
    ]
  }
}