{
  "type": "Feature",
  "properties": {
    "name": "Kodino",
    "country": "RU",
    "subdivision": "06",
    "timezone": "Europe/Moscow"
  },
  "geometry": {
    "type": "Point",
    "coordinates": [
      39.64465,
      63.71976
    ]
  }
}