{
  "type": "Feature",
  "properties": {
    "name": "Leshukonskoye",
    "country": "RU",
    "subdivision": "06",
    "timezone": "Europe/Moscow"
  },
  "geometry": {
    "type": "Point",
    "coordinates": [
      45.7655,
      64.8977
    ]
  }
}