{
  "type": "Feature",
  "properties": {
    "name": "Onega",
    "country": "RU",
    "subdivision": "06",
    "timezone": "Europe/Moscow"
  },
  "geometry": {
    "type": "Point",
    "coordinates": [
      38.09944,
      63.9057
    ]
  }
}