{
  "type": "Feature",
  "properties": {
    "name": "Shenkursk",
    "country": "RU",
    "subdivision": "06",
    "timezone": "Europe/Moscow"
  },
  "geometry": {
    "type": "Point",
    "coordinates": [
      42.89595,
      62.1091
    ]
  }
}