{
  "type": "Feature",
  "properties": {
    "name": "Solginskiy",
    "country": "RU",
    "subdivision": "06",
    "timezone": "Europe/Moscow"
  },
  "geometry": {
    "type": "Point",
    "coordinates": [
      41.34278,
      61.05
    ]
  }
}