{
  "type": "Feature",
  "properties": {
    "name": "Udimskiy",
    "country": "RU",
    "subdivision": "06",
    "timezone": "Europe/Moscow"
  },
  "geometry": {
    "type": "Point",
    "coordinates": [
      45.91443,
      61.14171
    ]
  }
}