{
  "type": "Feature",
  "properties": {
    "name": "BurhÄnuddin",
    "country": "BD",
    "subdivision": "85",
    "timezone": "Asia/Dhaka"
  },
  "geometry": {
    "type": "Point",
    "coordinates": [
      90.72391,
      22.49518
    ]
  }
}