{
  "type": "Feature",
  "properties": {
    "name": "Konče",
    "country": "MK",
    "subdivision": "47",
    "timezone": "Europe/Skopje"
  },
  "geometry": {
    "type": "Point",
    "coordinates": [
      22.38359,
      41.49511
    ]
  }
}