{
  "type": "Feature",
  "properties": {
    "name": "Andres Bonifacio",
    "country": "PH",
    "subdivision": "06",
    "timezone": "Asia/Manila"
  },
  "geometry": {
    "type": "Point",
    "coordinates": [
      123.25,
      10.91667
    ]
  }
}