{
  "type": "Feature",
  "properties": {
    "name": "Aranas Sur",
    "country": "PH",
    "subdivision": "06",
    "timezone": "Asia/Manila"
  },
  "geometry": {
    "type": "Point",
    "coordinates": [
      122.3901,
      11.5635
    ]
  }
}