{
  "type": "Feature",
  "properties": {
    "name": "Aurelliana",
    "country": "PH",
    "subdivision": "06",
    "timezone": "Asia/Manila"
  },
  "geometry": {
    "type": "Point",
    "coordinates": [
      121.9769,
      10.8849
    ]
  }
}