{
  "type": "Feature",
  "properties": {
    "name": "Balabag",
    "country": "PH",
    "subdivision": "06",
    "timezone": "Asia/Manila"
  },
  "geometry": {
    "type": "Point",
    "coordinates": [
      121.91917,
      11.97
    ]
  }
}