{
  "type": "Feature",
  "properties": {
    "name": "Barotac Viejo",
    "country": "PH",
    "subdivision": "06",
    "timezone": "Asia/Manila"
  },
  "geometry": {
    "type": "Point",
    "coordinates": [
      122.85222,
      11.04194
    ]
  }
}