{
  "type": "Feature",
  "properties": {
    "name": "Bay-ang",
    "country": "PH",
    "subdivision": "06",
    "timezone": "Asia/Manila"
  },
  "geometry": {
    "type": "Point",
    "coordinates": [
      122.94167,
      11.03472
    ]
  }
}