{
  "type": "Feature",
  "properties": {
    "name": "Bayas",
    "country": "PH",
    "subdivision": "06",
    "timezone": "Asia/Manila"
  },
  "geometry": {
    "type": "Point",
    "coordinates": [
      123.1816,
      11.4336
    ]
  }
}