{
  "type": "Feature",
  "properties": {
    "name": "Binantocan",
    "country": "PH",
    "subdivision": "06",
    "timezone": "Asia/Manila"
  },
  "geometry": {
    "type": "Point",
    "coordinates": [
      122.8602,
      11.4073
    ]
  }
}