{
  "type": "Feature",
  "properties": {
    "name": "Bitadtun",
    "country": "PH",
    "subdivision": "06",
    "timezone": "Asia/Manila"
  },
  "geometry": {
    "type": "Point",
    "coordinates": [
      122.08511,
      11.4969
    ]
  }
}