{
  "type": "Feature",
  "properties": {
    "name": "Buluangan",
    "country": "PH",
    "subdivision": "06",
    "timezone": "Asia/Manila"
  },
  "geometry": {
    "type": "Point",
    "coordinates": [
      123.3381,
      10.38707
    ]
  }
}