{
  "type": "Feature",
  "properties": {
    "name": "Burias",
    "country": "PH",
    "subdivision": "06",
    "timezone": "Asia/Manila"
  },
  "geometry": {
    "type": "Point",
    "coordinates": [
      122.5497,
      11.4463
    ]
  }
}