{
  "type": "Feature",
  "properties": {
    "name": "Camindangan",
    "country": "PH",
    "subdivision": "06",
    "timezone": "Asia/Manila"
  },
  "geometry": {
    "type": "Point",
    "coordinates": [
      122.6296,
      9.9184
    ]
  }
}