{
  "type": "Feature",
  "properties": {
    "name": "Cansilayan",
    "country": "PH",
    "subdivision": "06",
    "timezone": "Asia/Manila"
  },
  "geometry": {
    "type": "Point",
    "coordinates": [
      123.0184,
      10.55976
    ]
  }
}