{
  "type": "Feature",
  "properties": {
    "name": "Carles",
    "country": "PH",
    "subdivision": "06",
    "timezone": "Asia/Manila"
  },
  "geometry": {
    "type": "Point",
    "coordinates": [
      123.1342,
      11.5726
    ]
  }
}