{
  "type": "Feature",
  "properties": {
    "name": "Dos Hermanas",
    "country": "PH",
    "subdivision": "06",
    "timezone": "Asia/Manila"
  },
  "geometry": {
    "type": "Point",
    "coordinates": [
      123.0377,
      10.7421
    ]
  }
}