{
  "type": "Feature",
  "properties": {
    "name": "Getulio",
    "country": "PH",
    "subdivision": "06",
    "timezone": "Asia/Manila"
  },
  "geometry": {
    "type": "Point",
    "coordinates": [
      122.666,
      10.747
    ]
  }
}