{
  "type": "Feature",
  "properties": {
    "name": "Hamtic",
    "country": "PH",
    "subdivision": "06",
    "timezone": "Asia/Manila"
  },
  "geometry": {
    "type": "Point",
    "coordinates": [
      121.9824,
      10.7023
    ]
  }
}