{
  "type": "Feature",
  "properties": {
    "name": "Hinigaran",
    "country": "PH",
    "subdivision": "06",
    "timezone": "Asia/Manila"
  },
  "geometry": {
    "type": "Point",
    "coordinates": [
      122.8507,
      10.2706
    ]
  }
}