{
  "type": "Feature",
  "properties": {
    "name": "Hipona",
    "country": "PH",
    "subdivision": "06",
    "timezone": "Asia/Manila"
  },
  "geometry": {
    "type": "Point",
    "coordinates": [
      122.8825,
      11.4174
    ]
  }
}