{
  "type": "Feature",
  "properties": {
    "name": "Jayubó",
    "country": "PH",
    "subdivision": "06",
    "timezone": "Asia/Manila"
  },
  "geometry": {
    "type": "Point",
    "coordinates": [
      122.38333,
      11.05
    ]
  }
}