{
  "type": "Feature",
  "properties": {
    "name": "Lacaron",
    "country": "PH",
    "subdivision": "06",
    "timezone": "Asia/Manila"
  },
  "geometry": {
    "type": "Point",
    "coordinates": [
      122.7422,
      11.422
    ]
  }
}