{
  "type": "Feature",
  "properties": {
    "name": "Linabuan Sur",
    "country": "PH",
    "subdivision": "06",
    "timezone": "Asia/Manila"
  },
  "geometry": {
    "type": "Point",
    "coordinates": [
      122.345,
      11.65111
    ]
  }
}