{
  "type": "Feature",
  "properties": {
    "name": "Malocloc",
    "country": "PH",
    "subdivision": "06",
    "timezone": "Asia/Manila"
  },
  "geometry": {
    "type": "Point",
    "coordinates": [
      122.67833,
      11.50583
    ]
  }
}