{
  "type": "Feature",
  "properties": {
    "name": "Manika",
    "country": "PH",
    "subdivision": "06",
    "timezone": "Asia/Manila"
  },
  "geometry": {
    "type": "Point",
    "coordinates": [
      122.27931,
      11.38801
    ]
  }
}