{
  "type": "Feature",
  "properties": {
    "name": "Manjoy",
    "country": "PH",
    "subdivision": "06",
    "timezone": "Asia/Manila"
  },
  "geometry": {
    "type": "Point",
    "coordinates": [
      122.6663,
      11.3534
    ]
  }
}