{
  "type": "Feature",
  "properties": {
    "name": "Masaling",
    "country": "PH",
    "subdivision": "06",
    "timezone": "Asia/Manila"
  },
  "geometry": {
    "type": "Point",
    "coordinates": [
      122.5369,
      9.9818
    ]
  }
}