{
  "type": "Feature",
  "properties": {
    "name": "Morales",
    "country": "PH",
    "subdivision": "06",
    "timezone": "Asia/Manila"
  },
  "geometry": {
    "type": "Point",
    "coordinates": [
      122.3764,
      11.5456
    ]
  }
}