{
  "type": "Feature",
  "properties": {
    "name": "Ondoy",
    "country": "PH",
    "subdivision": "06",
    "timezone": "Asia/Manila"
  },
  "geometry": {
    "type": "Point",
    "coordinates": [
      122.12611,
      11.81917
    ]
  }
}