{
  "type": "Feature",
  "properties": {
    "name": "Prosperidad",
    "country": "PH",
    "subdivision": "06",
    "timezone": "Asia/Manila"
  },
  "geometry": {
    "type": "Point",
    "coordinates": [
      123.3085,
      10.51596
    ]
  }
}