{
  "type": "Feature",
  "properties": {
    "name": "Salamanca",
    "country": "PH",
    "subdivision": "06",
    "timezone": "Asia/Manila"
  },
  "geometry": {
    "type": "Point",
    "coordinates": [
      123.53,
      10.74655
    ]
  }
}