{
  "type": "Feature",
  "properties": {
    "name": "San Nicolas",
    "country": "PH",
    "subdivision": "06",
    "timezone": "Asia/Manila"
  },
  "geometry": {
    "type": "Point",
    "coordinates": [
      122.5184,
      11.3213
    ]
  }
}