{
  "type": "Feature",
  "properties": {
    "name": "Sipalay",
    "country": "PH",
    "subdivision": "06",
    "timezone": "Asia/Manila"
  },
  "geometry": {
    "type": "Point",
    "coordinates": [
      122.40417,
      9.75194
    ]
  }
}