{
  "type": "Feature",
  "properties": {
    "name": "Tarong",
    "country": "PH",
    "subdivision": "06",
    "timezone": "Asia/Manila"
  },
  "geometry": {
    "type": "Point",
    "coordinates": [
      123.132,
      11.5314
    ]
  }
}