{
  "type": "Feature",
  "properties": {
    "name": "Tiglauigan",
    "country": "PH",
    "subdivision": "06",
    "timezone": "Asia/Manila"
  },
  "geometry": {
    "type": "Point",
    "coordinates": [
      123.3575,
      10.9527
    ]
  }
}