{
  "type": "Feature",
  "properties": {
    "name": "Tigum",
    "country": "PH",
    "subdivision": "06",
    "timezone": "Asia/Manila"
  },
  "geometry": {
    "type": "Point",
    "coordinates": [
      122.56667,
      10.78333
    ]
  }
}