{
  "type": "Feature",
  "properties": {
    "name": "Ualog",
    "country": "PH",
    "subdivision": "06",
    "timezone": "Asia/Manila"
  },
  "geometry": {
    "type": "Point",
    "coordinates": [
      123.3933,
      10.57396
    ]
  }
}