{
  "type": "Feature",
  "properties": {
    "name": "Bělotín",
    "country": "CZ",
    "subdivision": "84",
    "timezone": "Europe/Prague"
  },
  "geometry": {
    "type": "Point",
    "coordinates": [
      17.80654,
      49.5912
    ]
  }
}