{
  "type": "Feature",
  "properties": {
    "name": "Bouzov",
    "country": "CZ",
    "subdivision": "84",
    "timezone": "Europe/Prague"
  },
  "geometry": {
    "type": "Point",
    "coordinates": [
      16.89288,
      49.70426
    ]
  }
}