{
  "type": "Feature",
  "properties": {
    "name": "Čelechovice na Hané",
    "country": "CZ",
    "subdivision": "84",
    "timezone": "Europe/Prague"
  },
  "geometry": {
    "type": "Point",
    "coordinates": [
      17.09379,
      49.51626
    ]
  }
}