{
  "type": "Feature",
  "properties": {
    "name": "Horní Štěpánov",
    "country": "CZ",
    "subdivision": "84",
    "timezone": "Europe/Prague"
  },
  "geometry": {
    "type": "Point",
    "coordinates": [
      16.79078,
      49.54901
    ]
  }
}