{
  "type": "Feature",
  "properties": {
    "name": "Hustopeče Nad Bečvou",
    "country": "CZ",
    "subdivision": "84",
    "timezone": "Europe/Prague"
  },
  "geometry": {
    "type": "Point",
    "coordinates": [
      17.86994,
      49.53053
    ]
  }
}