{
  "type": "Feature",
  "properties": {
    "name": "Javorník",
    "country": "CZ",
    "subdivision": "84",
    "timezone": "Europe/Prague"
  },
  "geometry": {
    "type": "Point",
    "coordinates": [
      17.00272,
      50.39077
    ]
  }
}