{
  "type": "Feature",
  "properties": {
    "name": "Kostelec na Hané",
    "country": "CZ",
    "subdivision": "84",
    "timezone": "Europe/Prague"
  },
  "geometry": {
    "type": "Point",
    "coordinates": [
      17.05824,
      49.51398
    ]
  }
}