{
  "type": "Feature",
  "properties": {
    "name": "Loučná nad Desnou",
    "country": "CZ",
    "subdivision": "84",
    "timezone": "Europe/Prague"
  },
  "geometry": {
    "type": "Point",
    "coordinates": [
      17.09052,
      50.07433
    ]
  }
}