{
  "type": "Feature",
  "properties": {
    "name": "Moravský Beroun",
    "country": "CZ",
    "subdivision": "84",
    "timezone": "Europe/Prague"
  },
  "geometry": {
    "type": "Point",
    "coordinates": [
      17.44212,
      49.79374
    ]
  }
}