{
  "type": "Feature",
  "properties": {
    "name": "Příkazy",
    "country": "CZ",
    "subdivision": "84",
    "timezone": "Europe/Prague"
  },
  "geometry": {
    "type": "Point",
    "coordinates": [
      17.14337,
      49.6436
    ]
  }
}