{
  "type": "Feature",
  "properties": {
    "name": "Senice na Hané",
    "country": "CZ",
    "subdivision": "84",
    "timezone": "Europe/Prague"
  },
  "geometry": {
    "type": "Point",
    "coordinates": [
      17.08578,
      49.62401
    ]
  }
}