{
  "type": "Feature",
  "properties": {
    "name": "Troubky",
    "country": "CZ",
    "subdivision": "84",
    "timezone": "Europe/Prague"
  },
  "geometry": {
    "type": "Point",
    "coordinates": [
      17.34914,
      49.43215
    ]
  }
}