{
  "type": "Feature",
  "properties": {
    "name": "Určice",
    "country": "CZ",
    "subdivision": "84",
    "timezone": "Europe/Prague"
  },
  "geometry": {
    "type": "Point",
    "coordinates": [
      17.07291,
      49.43045
    ]
  }
}