{
  "type": "Feature",
  "properties": {
    "name": "Žulová",
    "country": "CZ",
    "subdivision": "84",
    "timezone": "Europe/Prague"
  },
  "geometry": {
    "type": "Point",
    "coordinates": [
      17.09871,
      50.30933
    ]
  }
}