{
  "type": "Feature",
  "properties": {
    "name": "Nsoko",
    "country": "SZ",
    "subdivision": "02",
    "timezone": "Africa/Mbabane"
  },
  "geometry": {
    "type": "Point",
    "coordinates": [
      31.95,
      -27.03333
    ]
  }
}