{
  "type": "Feature",
  "properties": {
    "name": "Vuvulane",
    "country": "SZ",
    "subdivision": "02",
    "timezone": "Africa/Mbabane"
  },
  "geometry": {
    "type": "Point",
    "coordinates": [
      31.87672,
      -26.07427
    ]
  }
}