{
  "type": "Feature",
  "properties": {
    "name": "Chokwé",
    "country": "MZ",
    "subdivision": "02",
    "timezone": "Africa/Maputo"
  },
  "geometry": {
    "type": "Point",
    "coordinates": [
      32.98333,
      -24.53333
    ]
  }
}