{
  "type": "Feature",
  "properties": {
    "name": "Bayaguana",
    "country": "DO",
    "subdivision": "32",
    "timezone": "America/Santo_Domingo"
  },
  "geometry": {
    "type": "Point",
    "coordinates": [
      -69.63525,
      18.75031
    ]
  }
}