{
  "type": "Feature",
  "properties": {
    "name": "Sabana Grande de Boyá",
    "country": "DO",
    "subdivision": "32",
    "timezone": "America/Santo_Domingo"
  },
  "geometry": {
    "type": "Point",
    "coordinates": [
      -69.79331,
      18.94498
    ]
  }
}