{
  "type": "Feature",
  "properties": {
    "name": "Beni",
    "country": "CD",
    "subdivision": "11",
    "timezone": "Africa/Lubumbashi"
  },
  "geometry": {
    "type": "Point",
    "coordinates": [
      29.47306,
      0.49113
    ]
  }
}