{
  "type": "Feature",
  "properties": {
    "name": "Jämsänkoski",
    "country": "FI",
    "subdivision": "13",
    "timezone": "Europe/Helsinki"
  },
  "geometry": {
    "type": "Point",
    "coordinates": [
      25.17011,
      61.919
    ]
  }
}