{
  "type": "Feature",
  "properties": {
    "name": "Kuhmoinen",
    "country": "FI",
    "subdivision": "13",
    "timezone": "Europe/Helsinki"
  },
  "geometry": {
    "type": "Point",
    "coordinates": [
      25.18333,
      61.56667
    ]
  }
}