{
  "type": "Feature",
  "properties": {
    "name": "Abra de Ilog",
    "country": "PH",
    "subdivision": "41",
    "timezone": "Asia/Manila"
  },
  "geometry": {
    "type": "Point",
    "coordinates": [
      120.7291,
      13.4437
    ]
  }
}