{
  "type": "Feature",
  "properties": {
    "name": "Alibug",
    "country": "PH",
    "subdivision": "41",
    "timezone": "Asia/Manila"
  },
  "geometry": {
    "type": "Point",
    "coordinates": [
      121.22811,
      12.22906
    ]
  }
}