{
  "type": "Feature",
  "properties": {
    "name": "Bagong Sikat",
    "country": "PH",
    "subdivision": "41",
    "timezone": "Asia/Manila"
  },
  "geometry": {
    "type": "Point",
    "coordinates": [
      121.06171,
      12.36745
    ]
  }
}