{
  "type": "Feature",
  "properties": {
    "name": "Bansud",
    "country": "PH",
    "subdivision": "41",
    "timezone": "Asia/Manila"
  },
  "geometry": {
    "type": "Point",
    "coordinates": [
      121.45639,
      12.865
    ]
  }
}