{
  "type": "Feature",
  "properties": {
    "name": "Batarasa",
    "country": "PH",
    "subdivision": "41",
    "timezone": "Asia/Manila"
  },
  "geometry": {
    "type": "Point",
    "coordinates": [
      117.62795,
      8.67335
    ]
  }
}