{
  "type": "Feature",
  "properties": {
    "name": "Bayuin",
    "country": "PH",
    "subdivision": "41",
    "timezone": "Asia/Manila"
  },
  "geometry": {
    "type": "Point",
    "coordinates": [
      121.38852,
      13.0411
    ]
  }
}