{
  "type": "Feature",
  "properties": {
    "name": "Bunog",
    "country": "PH",
    "subdivision": "41",
    "timezone": "Asia/Manila"
  },
  "geometry": {
    "type": "Point",
    "coordinates": [
      117.78167,
      9.14028
    ]
  }
}