{
  "type": "Feature",
  "properties": {
    "name": "Coron",
    "country": "PH",
    "subdivision": "41",
    "timezone": "Asia/Manila"
  },
  "geometry": {
    "type": "Point",
    "coordinates": [
      120.2043,
      11.9986
    ]
  }
}