{
  "type": "Feature",
  "properties": {
    "name": "Cuyo",
    "country": "PH",
    "subdivision": "41",
    "timezone": "Asia/Manila"
  },
  "geometry": {
    "type": "Point",
    "coordinates": [
      121.00861,
      10.8525
    ]
  }
}