{
  "type": "Feature",
  "properties": {
    "name": "Dulangan",
    "country": "PH",
    "subdivision": "41",
    "timezone": "Asia/Manila"
  },
  "geometry": {
    "type": "Point",
    "coordinates": [
      120.9803,
      13.4685
    ]
  }
}