{
  "type": "Feature",
  "properties": {
    "name": "El Nido",
    "country": "PH",
    "subdivision": "41",
    "timezone": "Asia/Manila"
  },
  "geometry": {
    "type": "Point",
    "coordinates": [
      119.39556,
      11.18583
    ]
  }
}