{
  "type": "Feature",
  "properties": {
    "name": "Estrella",
    "country": "PH",
    "subdivision": "41",
    "timezone": "Asia/Manila"
  },
  "geometry": {
    "type": "Point",
    "coordinates": [
      121.31092,
      13.32898
    ]
  }
}