{
  "type": "Feature",
  "properties": {
    "name": "Gasan",
    "country": "PH",
    "subdivision": "41",
    "timezone": "Asia/Manila"
  },
  "geometry": {
    "type": "Point",
    "coordinates": [
      121.84675,
      13.32372
    ]
  }
}