{
  "type": "Feature",
  "properties": {
    "name": "Gloria",
    "country": "PH",
    "subdivision": "41",
    "timezone": "Asia/Manila"
  },
  "geometry": {
    "type": "Point",
    "coordinates": [
      121.46667,
      12.98333
    ]
  }
}