{
  "type": "Feature",
  "properties": {
    "name": "Isugod",
    "country": "PH",
    "subdivision": "41",
    "timezone": "Asia/Manila"
  },
  "geometry": {
    "type": "Point",
    "coordinates": [
      118.1196,
      9.34077
    ]
  }
}