{
  "type": "Feature",
  "properties": {
    "name": "Lubang",
    "country": "PH",
    "subdivision": "41",
    "timezone": "Asia/Manila"
  },
  "geometry": {
    "type": "Point",
    "coordinates": [
      120.12402,
      13.85835
    ]
  }
}