{
  "type": "Feature",
  "properties": {
    "name": "Mamburao",
    "country": "PH",
    "subdivision": "41",
    "timezone": "Asia/Manila"
  },
  "geometry": {
    "type": "Point",
    "coordinates": [
      120.596,
      13.2233
    ]
  }
}