{
  "type": "Feature",
  "properties": {
    "name": "Nagiba",
    "country": "PH",
    "subdivision": "41",
    "timezone": "Asia/Manila"
  },
  "geometry": {
    "type": "Point",
    "coordinates": [
      121.27432,
      13.33018
    ]
  }
}