{
  "type": "Feature",
  "properties": {
    "name": "Panlaitan",
    "country": "PH",
    "subdivision": "41",
    "timezone": "Asia/Manila"
  },
  "geometry": {
    "type": "Point",
    "coordinates": [
      119.84861,
      12.11907
    ]
  }
}