{
  "type": "Feature",
  "properties": {
    "name": "Ransang",
    "country": "PH",
    "subdivision": "41",
    "timezone": "Asia/Manila"
  },
  "geometry": {
    "type": "Point",
    "coordinates": [
      117.58278,
      8.96028
    ]
  }
}