{
  "type": "Feature",
  "properties": {
    "name": "Romblon",
    "country": "PH",
    "subdivision": "41",
    "timezone": "Asia/Manila"
  },
  "geometry": {
    "type": "Point",
    "coordinates": [
      122.27081,
      12.57513
    ]
  }
}