{
  "type": "Feature",
  "properties": {
    "name": "Saaban",
    "country": "PH",
    "subdivision": "41",
    "timezone": "Asia/Manila"
  },
  "geometry": {
    "type": "Point",
    "coordinates": [
      121.36872,
      13.13049
    ]
  }
}