{
  "type": "Feature",
  "properties": {
    "name": "San Jose",
    "country": "PH",
    "subdivision": "41",
    "timezone": "Asia/Manila"
  },
  "geometry": {
    "type": "Point",
    "coordinates": [
      121.06761,
      12.35275
    ]
  }
}