{
  "type": "Feature",
  "properties": {
    "name": "Akumal",
    "country": "MX",
    "subdivision": "23",
    "timezone": "America/Cancun"
  },
  "geometry": {
    "type": "Point",
    "coordinates": [
      -87.31444,
      20.39693
    ]
  }
}