{
  "type": "Feature",
  "properties": {
    "name": "Caobas",
    "country": "MX",
    "subdivision": "23",
    "timezone": "America/Cancun"
  },
  "geometry": {
    "type": "Point",
    "coordinates": [
      -89.10498,
      18.44497
    ]
  }
}