{
  "type": "Feature",
  "properties": {
    "name": "Chetumal",
    "country": "MX",
    "subdivision": "23",
    "timezone": "America/Cancun"
  },
  "geometry": {
    "type": "Point",
    "coordinates": [
      -88.30381,
      18.51413
    ]
  }
}