{
  "type": "Feature",
  "properties": {
    "name": "Dzula",
    "country": "MX",
    "subdivision": "23",
    "timezone": "America/Cancun"
  },
  "geometry": {
    "type": "Point",
    "coordinates": [
      -88.41566,
      19.60328
    ]
  }
}