{
  "type": "Feature",
  "properties": {
    "name": "Huay Max",
    "country": "MX",
    "subdivision": "23",
    "timezone": "America/Cancun"
  },
  "geometry": {
    "type": "Point",
    "coordinates": [
      -88.52588,
      20.04173
    ]
  }
}