{
  "type": "Feature",
  "properties": {
    "name": "Puerto Aventuras",
    "country": "MX",
    "subdivision": "23",
    "timezone": "America/Cancun"
  },
  "geometry": {
    "type": "Point",
    "coordinates": [
      -87.22647,
      20.50075
    ]
  }
}