{
  "type": "Feature",
  "properties": {
    "name": "Simmering",
    "country": "AT",
    "subdivision": "09",
    "timezone": "Europe/Vienna"
  },
  "geometry": {
    "type": "Point",
    "coordinates": [
      16.43333,
      48.18333
    ]
  }
}