{
  "type": "Feature",
  "properties": {
    "name": "Brčko",
    "country": "BA",
    "subdivision": "BRC",
    "timezone": "Europe/Sarajevo"
  },
  "geometry": {
    "type": "Point",
    "coordinates": [
      18.81012,
      44.86995
    ]
  }
}