{
  "type": "Feature",
  "properties": {
    "name": "Yendi",
    "country": "GH",
    "subdivision": "06",
    "timezone": "Africa/Accra"
  },
  "geometry": {
    "type": "Point",
    "coordinates": [
      -0.00991,
      9.44272
    ]
  }
}