{
  "type": "Feature",
  "properties": {
    "name": "Heredia",
    "country": "CR",
    "subdivision": "04",
    "timezone": "America/Costa_Rica"
  },
  "geometry": {
    "type": "Point",
    "coordinates": [
      -84.11651,
      10.00236
    ]
  }
}