{
  "type": "Feature",
  "properties": {
    "name": "Llorente",
    "country": "CR",
    "subdivision": "04",
    "timezone": "America/Costa_Rica"
  },
  "geometry": {
    "type": "Point",
    "coordinates": [
      -84.15448,
      9.99844
    ]
  }
}