{
  "type": "Feature",
  "properties": {
    "name": "San Antonio",
    "country": "CR",
    "subdivision": "04",
    "timezone": "America/Costa_Rica"
  },
  "geometry": {
    "type": "Point",
    "coordinates": [
      -84.18333,
      9.98333
    ]
  }
}