{
  "type": "Feature",
  "properties": {
    "name": "Santo Domingo",
    "country": "CR",
    "subdivision": "04",
    "timezone": "America/Costa_Rica"
  },
  "geometry": {
    "type": "Point",
    "coordinates": [
      -84.15499,
      10.06389
    ]
  }
}