{
  "type": "Feature",
  "properties": {
    "name": "Cerca la Source",
    "country": "HT",
    "subdivision": "07",
    "timezone": "America/Port-au-Prince"
  },
  "geometry": {
    "type": "Point",
    "coordinates": [
      -71.79015,
      19.16696
    ]
  }
}