{
  "type": "Feature",
  "properties": {
    "name": "Alcobendas",
    "country": "ES",
    "subdivision": "29",
    "timezone": "Europe/Madrid"
  },
  "geometry": {
    "type": "Point",
    "coordinates": [
      -3.64197,
      40.54746
    ]
  }
}