{
  "type": "Feature",
  "properties": {
    "name": "Aldea del Fresno",
    "country": "ES",
    "subdivision": "29",
    "timezone": "Europe/Madrid"
  },
  "geometry": {
    "type": "Point",
    "coordinates": [
      -4.20319,
      40.3236
    ]
  }
}