{
  "type": "Feature",
  "properties": {
    "name": "Arganda",
    "country": "ES",
    "subdivision": "29",
    "timezone": "Europe/Madrid"
  },
  "geometry": {
    "type": "Point",
    "coordinates": [
      -3.43722,
      40.30076
    ]
  }
}