{
  "type": "Feature",
  "properties": {
    "name": "Batres",
    "country": "ES",
    "subdivision": "29",
    "timezone": "Europe/Madrid"
  },
  "geometry": {
    "type": "Point",
    "coordinates": [
      -3.92331,
      40.20981
    ]
  }
}