{
  "type": "Feature",
  "properties": {
    "name": "Cercedilla",
    "country": "ES",
    "subdivision": "29",
    "timezone": "Europe/Madrid"
  },
  "geometry": {
    "type": "Point",
    "coordinates": [
      -4.05644,
      40.74101
    ]
  }
}