{
  "type": "Feature",
  "properties": {
    "name": "City Center",
    "country": "ES",
    "subdivision": "29",
    "timezone": "Europe/Madrid"
  },
  "geometry": {
    "type": "Point",
    "coordinates": [
      -3.70275,
      40.41831
    ]
  }
}