{
  "type": "Feature",
  "properties": {
    "name": "Collado-Villalba",
    "country": "ES",
    "subdivision": "29",
    "timezone": "Europe/Madrid"
  },
  "geometry": {
    "type": "Point",
    "coordinates": [
      -4.00486,
      40.63506
    ]
  }
}