{
  "type": "Feature",
  "properties": {
    "name": "Fuente el Saz",
    "country": "ES",
    "subdivision": "29",
    "timezone": "Europe/Madrid"
  },
  "geometry": {
    "type": "Point",
    "coordinates": [
      -3.51146,
      40.63215
    ]
  }
}