{
  "type": "Feature",
  "properties": {
    "name": "Hortaleza",
    "country": "ES",
    "subdivision": "29",
    "timezone": "Europe/Madrid"
  },
  "geometry": {
    "type": "Point",
    "coordinates": [
      -3.6411,
      40.47444
    ]
  }
}