{
  "type": "Feature",
  "properties": {
    "name": "Las Tablas",
    "country": "ES",
    "subdivision": "29",
    "timezone": "Europe/Madrid"
  },
  "geometry": {
    "type": "Point",
    "coordinates": [
      -3.67235,
      40.50649
    ]
  }
}