{
  "type": "Feature",
  "properties": {
    "name": "Miraflores de la Sierra",
    "country": "ES",
    "subdivision": "29",
    "timezone": "Europe/Madrid"
  },
  "geometry": {
    "type": "Point",
    "coordinates": [
      -3.76213,
      40.8155
    ]
  }
}