{
  "type": "Feature",
  "properties": {
    "name": "Moncloa-Aravaca",
    "country": "ES",
    "subdivision": "29",
    "timezone": "Europe/Madrid"
  },
  "geometry": {
    "type": "Point",
    "coordinates": [
      -3.7317,
      40.43547
    ]
  }
}