{
  "type": "Feature",
  "properties": {
    "name": "Moralzarzal",
    "country": "ES",
    "subdivision": "29",
    "timezone": "Europe/Madrid"
  },
  "geometry": {
    "type": "Point",
    "coordinates": [
      -3.9707,
      40.67816
    ]
  }
}