{
  "type": "Feature",
  "properties": {
    "name": "Navacerrada",
    "country": "ES",
    "subdivision": "29",
    "timezone": "Europe/Madrid"
  },
  "geometry": {
    "type": "Point",
    "coordinates": [
      -4.01696,
      40.72905
    ]
  }
}