{
  "type": "Feature",
  "properties": {
    "name": "Pelayos de la Presa",
    "country": "ES",
    "subdivision": "29",
    "timezone": "Europe/Madrid"
  },
  "geometry": {
    "type": "Point",
    "coordinates": [
      -4.33462,
      40.36051
    ]
  }
}