{
  "type": "Feature",
  "properties": {
    "name": "Pinar de Chamartín",
    "country": "ES",
    "subdivision": "29",
    "timezone": "Europe/Madrid"
  },
  "geometry": {
    "type": "Point",
    "coordinates": [
      -3.66836,
      40.47903
    ]
  }
}