{
  "type": "Feature",
  "properties": {
    "name": "San Sebastián de los Reyes",
    "country": "ES",
    "subdivision": "29",
    "timezone": "Europe/Madrid"
  },
  "geometry": {
    "type": "Point",
    "coordinates": [
      -3.62733,
      40.55555
    ]
  }
}