{
  "type": "Feature",
  "properties": {
    "name": "San Lorenzo de El Escorial",
    "country": "ES",
    "subdivision": "29",
    "timezone": "Europe/Madrid"
  },
  "geometry": {
    "type": "Point",
    "coordinates": [
      -4.14738,
      40.59144
    ]
  }
}