{
  "type": "Feature",
  "properties": {
    "name": "Villa del Prado",
    "country": "ES",
    "subdivision": "29",
    "timezone": "Europe/Madrid"
  },
  "geometry": {
    "type": "Point",
    "coordinates": [
      -4.30534,
      40.27852
    ]
  }
}