{
  "type": "Feature",
  "properties": {
    "name": "Bruna",
    "country": "IT",
    "subdivision": "18",
    "timezone": "Europe/Rome"
  },
  "geometry": {
    "type": "Point",
    "coordinates": [
      12.68851,
      42.82071
    ]
  }
}