{
  "type": "Feature",
  "properties": {
    "name": "Fabro Scalo",
    "country": "IT",
    "subdivision": "18",
    "timezone": "Europe/Rome"
  },
  "geometry": {
    "type": "Point",
    "coordinates": [
      12.04624,
      42.87605
    ]
  }
}