{
  "type": "Feature",
  "properties": {
    "name": "Norcia",
    "country": "IT",
    "subdivision": "18",
    "timezone": "Europe/Rome"
  },
  "geometry": {
    "type": "Point",
    "coordinates": [
      13.096,
      42.79105
    ]
  }
}