{
  "type": "Feature",
  "properties": {
    "name": "Palazzo",
    "country": "IT",
    "subdivision": "18",
    "timezone": "Europe/Rome"
  },
  "geometry": {
    "type": "Point",
    "coordinates": [
      12.56436,
      43.09708
    ]
  }
}