{
  "type": "Feature",
  "properties": {
    "name": "Ponterio-Pian di Porto",
    "country": "IT",
    "subdivision": "18",
    "timezone": "Europe/Rome"
  },
  "geometry": {
    "type": "Point",
    "coordinates": [
      12.41024,
      42.80769
    ]
  }
}