{
  "type": "Feature",
  "properties": {
    "name": "Rivotorto",
    "country": "IT",
    "subdivision": "18",
    "timezone": "Europe/Rome"
  },
  "geometry": {
    "type": "Point",
    "coordinates": [
      12.62069,
      43.04406
    ]
  }
}