{
  "type": "Feature",
  "properties": {
    "name": "Selci-Lama",
    "country": "IT",
    "subdivision": "18",
    "timezone": "Europe/Rome"
  },
  "geometry": {
    "type": "Point",
    "coordinates": [
      12.21293,
      43.51719
    ]
  }
}