{
  "type": "Feature",
  "properties": {
    "name": "Cibakháza",
    "country": "HU",
    "subdivision": "20",
    "timezone": "Europe/Budapest"
  },
  "geometry": {
    "type": "Point",
    "coordinates": [
      20.19753,
      46.95976
    ]
  }
}