{
  "type": "Feature",
  "properties": {
    "name": "J치sz치roksz치ll치s",
    "country": "HU",
    "subdivision": "20",
    "timezone": "Europe/Budapest"
  },
  "geometry": {
    "type": "Point",
    "coordinates": [
      19.98038,
      47.64238
    ]
  }
}