{
  "type": "Feature",
  "properties": {
    "name": "Kisújszállás",
    "country": "HU",
    "subdivision": "20",
    "timezone": "Europe/Budapest"
  },
  "geometry": {
    "type": "Point",
    "coordinates": [
      20.76667,
      47.21667
    ]
  }
}