{
  "type": "Feature",
  "properties": {
    "name": "Tiszaszentimre",
    "country": "HU",
    "subdivision": "20",
    "timezone": "Europe/Budapest"
  },
  "geometry": {
    "type": "Point",
    "coordinates": [
      20.73333,
      47.48333
    ]
  }
}