{
  "type": "Feature",
  "properties": {
    "name": "Tiszaszőlős",
    "country": "HU",
    "subdivision": "20",
    "timezone": "Europe/Budapest"
  },
  "geometry": {
    "type": "Point",
    "coordinates": [
      20.71949,
      47.55707
    ]
  }
}