{
  "type": "Feature",
  "properties": {
    "name": "El Rosario",
    "country": "NI",
    "subdivision": "02",
    "timezone": "America/Managua"
  },
  "geometry": {
    "type": "Point",
    "coordinates": [
      -86.37374,
      11.77756
    ]
  }
}