{
  "type": "Feature",
  "properties": {
    "name": "La Paz de Carazo",
    "country": "NI",
    "subdivision": "02",
    "timezone": "America/Managua"
  },
  "geometry": {
    "type": "Point",
    "coordinates": [
      -86.12781,
      11.82311
    ]
  }
}