{
  "type": "Feature",
  "properties": {
    "name": "Chernelytsya",
    "country": "UA",
    "subdivision": "06",
    "timezone": "Europe/Kiev"
  },
  "geometry": {
    "type": "Point",
    "coordinates": [
      25.42682,
      48.81302
    ]
  }
}