{
  "type": "Feature",
  "properties": {
    "name": "Dolyna",
    "country": "UA",
    "subdivision": "06",
    "timezone": "Europe/Kiev"
  },
  "geometry": {
    "type": "Point",
    "coordinates": [
      23.96558,
      48.97158
    ]
  }
}