{
  "type": "Feature",
  "properties": {
    "name": "Ivano-Frankivsk",
    "country": "UA",
    "subdivision": "06",
    "timezone": "Europe/Kiev"
  },
  "geometry": {
    "type": "Point",
    "coordinates": [
      24.71248,
      48.92312
    ]
  }
}