{
  "type": "Feature",
  "properties": {
    "name": "Krasna",
    "country": "UA",
    "subdivision": "06",
    "timezone": "Europe/Kiev"
  },
  "geometry": {
    "type": "Point",
    "coordinates": [
      24.69601,
      48.57459
    ]
  }
}