{
  "type": "Feature",
  "properties": {
    "name": "Kuty",
    "country": "UA",
    "subdivision": "06",
    "timezone": "Europe/Kiev"
  },
  "geometry": {
    "type": "Point",
    "coordinates": [
      25.17943,
      48.26249
    ]
  }
}