{
  "type": "Feature",
  "properties": {
    "name": "Pniv",
    "country": "UA",
    "subdivision": "06",
    "timezone": "Europe/Kiev"
  },
  "geometry": {
    "type": "Point",
    "coordinates": [
      24.52783,
      48.61487
    ]
  }
}