{
  "type": "Feature",
  "properties": {
    "name": "Rechka",
    "country": "UA",
    "subdivision": "06",
    "timezone": "Europe/Kiev"
  },
  "geometry": {
    "type": "Point",
    "coordinates": [
      24.9333,
      48.28034
    ]
  }
}