{
  "type": "Feature",
  "properties": {
    "name": "Rozhniv",
    "country": "UA",
    "subdivision": "06",
    "timezone": "Europe/Kiev"
  },
  "geometry": {
    "type": "Point",
    "coordinates": [
      25.23109,
      48.36465
    ]
  }
}