{
  "type": "Feature",
  "properties": {
    "name": "Sheshory",
    "country": "UA",
    "subdivision": "06",
    "timezone": "Europe/Kiev"
  },
  "geometry": {
    "type": "Point",
    "coordinates": [
      24.97016,
      48.32428
    ]
  }
}