{
  "type": "Feature",
  "properties": {
    "name": "Uhryniv",
    "country": "UA",
    "subdivision": "06",
    "timezone": "Europe/Kiev"
  },
  "geometry": {
    "type": "Point",
    "coordinates": [
      24.69292,
      48.9552
    ]
  }
}