{
  "type": "Feature",
  "properties": {
    "name": "Verkhniy Yasenov",
    "country": "UA",
    "subdivision": "06",
    "timezone": "Europe/Kiev"
  },
  "geometry": {
    "type": "Point",
    "coordinates": [
      24.94532,
      48.16156
    ]
  }
}