{
  "type": "Feature",
  "properties": {
    "name": "Ustia",
    "country": "MD",
    "subdivision": "72",
    "timezone": "Europe/Chisinau"
  },
  "geometry": {
    "type": "Point",
    "coordinates": [
      29.12406,
      47.25524
    ]
  }
}