{
  "type": "Feature",
  "properties": {
    "name": "Saurimo",
    "country": "AO",
    "subdivision": "18",
    "timezone": "Africa/Luanda"
  },
  "geometry": {
    "type": "Point",
    "coordinates": [
      20.39155,
      -9.66078
    ]
  }
}