{
  "type": "Feature",
  "properties": {
    "name": "Kokoshkino",
    "country": "RU",
    "subdivision": "48",
    "timezone": "Europe/Moscow"
  },
  "geometry": {
    "type": "Point",
    "coordinates": [
      37.1695,
      55.59769
    ]
  }
}