{
  "type": "Feature",
  "properties": {
    "name": "Kotlovka",
    "country": "RU",
    "subdivision": "48",
    "timezone": "Europe/Moscow"
  },
  "geometry": {
    "type": "Point",
    "coordinates": [
      37.60404,
      55.65928
    ]
  }
}