{
  "type": "Feature",
  "properties": {
    "name": "Leonovo",
    "country": "RU",
    "subdivision": "48",
    "timezone": "Europe/Moscow"
  },
  "geometry": {
    "type": "Point",
    "coordinates": [
      37.65,
      55.85
    ]
  }
}