{
  "type": "Feature",
  "properties": {
    "name": "Moskovskiy",
    "country": "RU",
    "subdivision": "48",
    "timezone": "Europe/Moscow"
  },
  "geometry": {
    "type": "Point",
    "coordinates": [
      37.35495,
      55.59911
    ]
  }
}