{
  "type": "Feature",
  "properties": {
    "name": "Nagornyy",
    "country": "RU",
    "subdivision": "48",
    "timezone": "Europe/Moscow"
  },
  "geometry": {
    "type": "Point",
    "coordinates": [
      37.61667,
      55.65
    ]
  }
}