{
  "type": "Feature",
  "properties": {
    "name": "Nekrasovka",
    "country": "RU",
    "subdivision": "48",
    "timezone": "Europe/Moscow"
  },
  "geometry": {
    "type": "Point",
    "coordinates": [
      37.91148,
      55.69328
    ]
  }
}