{
  "type": "Feature",
  "properties": {
    "name": "Nikulino",
    "country": "RU",
    "subdivision": "48",
    "timezone": "Europe/Moscow"
  },
  "geometry": {
    "type": "Point",
    "coordinates": [
      37.46598,
      55.66943
    ]
  }
}