{
  "type": "Feature",
  "properties": {
    "name": "Severnyy",
    "country": "RU",
    "subdivision": "48",
    "timezone": "Europe/Moscow"
  },
  "geometry": {
    "type": "Point",
    "coordinates": [
      37.54889,
      55.93583
    ]
  }
}