{
  "type": "Feature",
  "properties": {
    "name": "Strogino",
    "country": "RU",
    "subdivision": "48",
    "timezone": "Europe/Moscow"
  },
  "geometry": {
    "type": "Point",
    "coordinates": [
      37.41224,
      55.81838
    ]
  }
}