{
  "type": "Feature",
  "properties": {
    "name": "Vostochnyy",
    "country": "RU",
    "subdivision": "48",
    "timezone": "Europe/Moscow"
  },
  "geometry": {
    "type": "Point",
    "coordinates": [
      37.86667,
      55.81667
    ]
  }
}