{
  "type": "Feature",
  "properties": {
    "name": "Vykhino-Zhulebino",
    "country": "RU",
    "subdivision": "48",
    "timezone": "Europe/Moscow"
  },
  "geometry": {
    "type": "Point",
    "coordinates": [
      37.81178,
      55.70196
    ]
  }
}