{
  "type": "Feature",
  "properties": {
    "name": "Yaroslavskiy",
    "country": "RU",
    "subdivision": "48",
    "timezone": "Europe/Moscow"
  },
  "geometry": {
    "type": "Point",
    "coordinates": [
      37.71667,
      55.88333
    ]
  }
}