{
  "type": "Feature",
  "properties": {
    "name": "Nagarote",
    "country": "NI",
    "subdivision": "08",
    "timezone": "America/Managua"
  },
  "geometry": {
    "type": "Point",
    "coordinates": [
      -86.56474,
      12.26593
    ]
  }
}