{
  "type": "Feature",
  "properties": {
    "name": "Aars",
    "country": "DK",
    "subdivision": "19",
    "timezone": "Europe/Copenhagen"
  },
  "geometry": {
    "type": "Point",
    "coordinates": [
      9.51441,
      56.80399
    ]
  }
}