{
  "type": "Feature",
  "properties": {
    "name": "Brovst",
    "country": "DK",
    "subdivision": "19",
    "timezone": "Europe/Copenhagen"
  },
  "geometry": {
    "type": "Point",
    "coordinates": [
      9.52264,
      57.0975
    ]
  }
}