{
  "type": "Feature",
  "properties": {
    "name": "Fjerritslev",
    "country": "DK",
    "subdivision": "19",
    "timezone": "Europe/Copenhagen"
  },
  "geometry": {
    "type": "Point",
    "coordinates": [
      9.26622,
      57.08822
    ]
  }
}