{
  "type": "Feature",
  "properties": {
    "name": "Hobro",
    "country": "DK",
    "subdivision": "19",
    "timezone": "Europe/Copenhagen"
  },
  "geometry": {
    "type": "Point",
    "coordinates": [
      9.79029,
      56.64306
    ]
  }
}