{
  "type": "Feature",
  "properties": {
    "name": "Løgstør",
    "country": "DK",
    "subdivision": "19",
    "timezone": "Europe/Copenhagen"
  },
  "geometry": {
    "type": "Point",
    "coordinates": [
      9.2583,
      56.96245
    ]
  }
}