{
  "type": "Feature",
  "properties": {
    "name": "Skagen",
    "country": "DK",
    "subdivision": "19",
    "timezone": "Europe/Copenhagen"
  },
  "geometry": {
    "type": "Point",
    "coordinates": [
      10.58394,
      57.72093
    ]
  }
}