{
  "type": "Feature",
  "properties": {
    "name": "Skørping",
    "country": "DK",
    "subdivision": "19",
    "timezone": "Europe/Copenhagen"
  },
  "geometry": {
    "type": "Point",
    "coordinates": [
      9.89255,
      56.83626
    ]
  }
}