{
  "type": "Feature",
  "properties": {
    "name": "Vadum",
    "country": "DK",
    "subdivision": "19",
    "timezone": "Europe/Copenhagen"
  },
  "geometry": {
    "type": "Point",
    "coordinates": [
      9.857,
      57.1179
    ]
  }
}