{
  "type": "Feature",
  "properties": {
    "name": "Adamantina",
    "country": "BR",
    "subdivision": "27",
    "timezone": "America/Sao_Paulo"
  },
  "geometry": {
    "type": "Point",
    "coordinates": [
      -51.0725,
      -21.68528
    ]
  }
}