{
  "type": "Feature",
  "properties": {
    "name": "Américo Brasiliense",
    "country": "BR",
    "subdivision": "27",
    "timezone": "America/Sao_Paulo"
  },
  "geometry": {
    "type": "Point",
    "coordinates": [
      -48.10167,
      -21.72444
    ]
  }
}