{
  "type": "Feature",
  "properties": {
    "name": "Amparo",
    "country": "BR",
    "subdivision": "27",
    "timezone": "America/Sao_Paulo"
  },
  "geometry": {
    "type": "Point",
    "coordinates": [
      -46.76444,
      -22.70111
    ]
  }
}