{
  "type": "Feature",
  "properties": {
    "name": "Aparecida",
    "country": "BR",
    "subdivision": "27",
    "timezone": "America/Sao_Paulo"
  },
  "geometry": {
    "type": "Point",
    "coordinates": [
      -45.22972,
      -22.84694
    ]
  }
}