{
  "type": "Feature",
  "properties": {
    "name": "Araçatuba",
    "country": "BR",
    "subdivision": "27",
    "timezone": "America/Sao_Paulo"
  },
  "geometry": {
    "type": "Point",
    "coordinates": [
      -50.43278,
      -21.20889
    ]
  }
}