{
  "type": "Feature",
  "properties": {
    "name": "Barra Bonita",
    "country": "BR",
    "subdivision": "27",
    "timezone": "America/Sao_Paulo"
  },
  "geometry": {
    "type": "Point",
    "coordinates": [
      -48.55806,
      -22.49472
    ]
  }
}