{
  "type": "Feature",
  "properties": {
    "name": "Bauru",
    "country": "BR",
    "subdivision": "27",
    "timezone": "America/Sao_Paulo"
  },
  "geometry": {
    "type": "Point",
    "coordinates": [
      -49.06056,
      -22.31472
    ]
  }
}