{
  "type": "Feature",
  "properties": {
    "name": "Biritiba Mirim",
    "country": "BR",
    "subdivision": "27",
    "timezone": "America/Sao_Paulo"
  },
  "geometry": {
    "type": "Point",
    "coordinates": [
      -46.03861,
      -23.5725
    ]
  }
}