{
  "type": "Feature",
  "properties": {
    "name": "Bom Jesus dos Perdões",
    "country": "BR",
    "subdivision": "27",
    "timezone": "America/Sao_Paulo"
  },
  "geometry": {
    "type": "Point",
    "coordinates": [
      -46.46528,
      -23.135
    ]
  }
}