{
  "type": "Feature",
  "properties": {
    "name": "Capâo Bonito",
    "country": "BR",
    "subdivision": "27",
    "timezone": "America/Sao_Paulo"
  },
  "geometry": {
    "type": "Point",
    "coordinates": [
      -48.34944,
      -24.00583
    ]
  }
}