{
  "type": "Feature",
  "properties": {
    "name": "Capela do Alto",
    "country": "BR",
    "subdivision": "27",
    "timezone": "America/Sao_Paulo"
  },
  "geometry": {
    "type": "Point",
    "coordinates": [
      -47.73472,
      -23.47056
    ]
  }
}