{
  "type": "Feature",
  "properties": {
    "name": "Cardoso",
    "country": "BR",
    "subdivision": "27",
    "timezone": "America/Sao_Paulo"
  },
  "geometry": {
    "type": "Point",
    "coordinates": [
      -49.91417,
      -20.08194
    ]
  }
}