{
  "type": "Feature",
  "properties": {
    "name": "Catanduva",
    "country": "BR",
    "subdivision": "27",
    "timezone": "America/Sao_Paulo"
  },
  "geometry": {
    "type": "Point",
    "coordinates": [
      -48.97278,
      -21.13778
    ]
  }
}