{
  "type": "Feature",
  "properties": {
    "name": "Cerquilho",
    "country": "BR",
    "subdivision": "27",
    "timezone": "America/Sao_Paulo"
  },
  "geometry": {
    "type": "Point",
    "coordinates": [
      -47.74361,
      -23.165
    ]
  }
}