{
  "type": "Feature",
  "properties": {
    "name": "Cerqueira César",
    "country": "BR",
    "subdivision": "27",
    "timezone": "America/Sao_Paulo"
  },
  "geometry": {
    "type": "Point",
    "coordinates": [
      -49.16611,
      -23.03556
    ]
  }
}