{
  "type": "Feature",
  "properties": {
    "name": "Charqueada",
    "country": "BR",
    "subdivision": "27",
    "timezone": "America/Sao_Paulo"
  },
  "geometry": {
    "type": "Point",
    "coordinates": [
      -47.77806,
      -22.50972
    ]
  }
}