{
  "type": "Feature",
  "properties": {
    "name": "Conchas",
    "country": "BR",
    "subdivision": "27",
    "timezone": "America/Sao_Paulo"
  },
  "geometry": {
    "type": "Point",
    "coordinates": [
      -48.01056,
      -23.01528
    ]
  }
}