{
  "type": "Feature",
  "properties": {
    "name": "Espírito Santo do Pinhal",
    "country": "BR",
    "subdivision": "27",
    "timezone": "America/Sao_Paulo"
  },
  "geometry": {
    "type": "Point",
    "coordinates": [
      -46.68278,
      -22.11583
    ]
  }
}