{
  "type": "Feature",
  "properties": {
    "name": "Francisco Morato",
    "country": "BR",
    "subdivision": "27",
    "timezone": "America/Sao_Paulo"
  },
  "geometry": {
    "type": "Point",
    "coordinates": [
      -46.74528,
      -23.28167
    ]
  }
}