{
  "type": "Feature",
  "properties": {
    "name": "Garça",
    "country": "BR",
    "subdivision": "27",
    "timezone": "America/Sao_Paulo"
  },
  "geometry": {
    "type": "Point",
    "coordinates": [
      -49.65611,
      -22.21056
    ]
  }
}