{
  "type": "Feature",
  "properties": {
    "name": "Guarujá",
    "country": "BR",
    "subdivision": "27",
    "timezone": "America/Sao_Paulo"
  },
  "geometry": {
    "type": "Point",
    "coordinates": [
      -46.25639,
      -23.99306
    ]
  }
}