{
  "type": "Feature",
  "properties": {
    "name": "Guararema",
    "country": "BR",
    "subdivision": "27",
    "timezone": "America/Sao_Paulo"
  },
  "geometry": {
    "type": "Point",
    "coordinates": [
      -46.035,
      -23.415
    ]
  }
}