{
  "type": "Feature",
  "properties": {
    "name": "Ilha Solteira",
    "country": "BR",
    "subdivision": "27",
    "timezone": "America/Sao_Paulo"
  },
  "geometry": {
    "type": "Point",
    "coordinates": [
      -51.3425,
      -20.43278
    ]
  }
}