{
  "type": "Feature",
  "properties": {
    "name": "Iracemápolis",
    "country": "BR",
    "subdivision": "27",
    "timezone": "America/Sao_Paulo"
  },
  "geometry": {
    "type": "Point",
    "coordinates": [
      -47.51861,
      -22.58056
    ]
  }
}