{
  "type": "Feature",
  "properties": {
    "name": "Itaí",
    "country": "BR",
    "subdivision": "27",
    "timezone": "America/Sao_Paulo"
  },
  "geometry": {
    "type": "Point",
    "coordinates": [
      -49.09056,
      -23.41778
    ]
  }
}