{
  "type": "Feature",
  "properties": {
    "name": "Itaporanga",
    "country": "BR",
    "subdivision": "27",
    "timezone": "America/Sao_Paulo"
  },
  "geometry": {
    "type": "Point",
    "coordinates": [
      -49.48972,
      -23.70778
    ]
  }
}