{
  "type": "Feature",
  "properties": {
    "name": "Itatinga",
    "country": "BR",
    "subdivision": "27",
    "timezone": "America/Sao_Paulo"
  },
  "geometry": {
    "type": "Point",
    "coordinates": [
      -48.61583,
      -23.10167
    ]
  }
}