{
  "type": "Feature",
  "properties": {
    "name": "Itatiba",
    "country": "BR",
    "subdivision": "27",
    "timezone": "America/Sao_Paulo"
  },
  "geometry": {
    "type": "Point",
    "coordinates": [
      -46.83889,
      -23.00583
    ]
  }
}