{
  "type": "Feature",
  "properties": {
    "name": "Ituverava",
    "country": "BR",
    "subdivision": "27",
    "timezone": "America/Sao_Paulo"
  },
  "geometry": {
    "type": "Point",
    "coordinates": [
      -47.78056,
      -20.33944
    ]
  }
}