{
  "type": "Feature",
  "properties": {
    "name": "Lorena",
    "country": "BR",
    "subdivision": "27",
    "timezone": "America/Sao_Paulo"
  },
  "geometry": {
    "type": "Point",
    "coordinates": [
      -45.12472,
      -22.73083
    ]
  }
}