{
  "type": "Feature",
  "properties": {
    "name": "Miguelópolis",
    "country": "BR",
    "subdivision": "27",
    "timezone": "America/Sao_Paulo"
  },
  "geometry": {
    "type": "Point",
    "coordinates": [
      -48.03194,
      -20.17944
    ]
  }
}