{
  "type": "Feature",
  "properties": {
    "name": "Mirandopólis",
    "country": "BR",
    "subdivision": "27",
    "timezone": "America/Sao_Paulo"
  },
  "geometry": {
    "type": "Point",
    "coordinates": [
      -51.10167,
      -21.13361
    ]
  }
}