{
  "type": "Feature",
  "properties": {
    "name": "Nova Odessa",
    "country": "BR",
    "subdivision": "27",
    "timezone": "America/Sao_Paulo"
  },
  "geometry": {
    "type": "Point",
    "coordinates": [
      -47.29583,
      -22.7775
    ]
  }
}