{
  "type": "Feature",
  "properties": {
    "name": "Ourinhos",
    "country": "BR",
    "subdivision": "27",
    "timezone": "America/Sao_Paulo"
  },
  "geometry": {
    "type": "Point",
    "coordinates": [
      -49.87056,
      -22.97889
    ]
  }
}