{
  "type": "Feature",
  "properties": {
    "name": "Pereira Barreto",
    "country": "BR",
    "subdivision": "27",
    "timezone": "America/Sao_Paulo"
  },
  "geometry": {
    "type": "Point",
    "coordinates": [
      -51.10917,
      -20.63833
    ]
  }
}