{
  "type": "Feature",
  "properties": {
    "name": "Piedade",
    "country": "BR",
    "subdivision": "27",
    "timezone": "America/Sao_Paulo"
  },
  "geometry": {
    "type": "Point",
    "coordinates": [
      -47.42778,
      -23.71194
    ]
  }
}