{
  "type": "Feature",
  "properties": {
    "name": "Piracicaba",
    "country": "BR",
    "subdivision": "27",
    "timezone": "America/Sao_Paulo"
  },
  "geometry": {
    "type": "Point",
    "coordinates": [
      -47.64917,
      -22.72528
    ]
  }
}