{
  "type": "Feature",
  "properties": {
    "name": "Pitangueiras",
    "country": "BR",
    "subdivision": "27",
    "timezone": "America/Sao_Paulo"
  },
  "geometry": {
    "type": "Point",
    "coordinates": [
      -48.22167,
      -21.00944
    ]
  }
}