{
  "type": "Feature",
  "properties": {
    "name": "Porto Feliz",
    "country": "BR",
    "subdivision": "27",
    "timezone": "America/Sao_Paulo"
  },
  "geometry": {
    "type": "Point",
    "coordinates": [
      -47.52389,
      -23.21472
    ]
  }
}