{
  "type": "Feature",
  "properties": {
    "name": "Praia Grande",
    "country": "BR",
    "subdivision": "27",
    "timezone": "America/Sao_Paulo"
  },
  "geometry": {
    "type": "Point",
    "coordinates": [
      -46.40278,
      -24.00583
    ]
  }
}