{
  "type": "Feature",
  "properties": {
    "name": "Ribeirão Preto",
    "country": "BR",
    "subdivision": "27",
    "timezone": "America/Sao_Paulo"
  },
  "geometry": {
    "type": "Point",
    "coordinates": [
      -47.81028,
      -21.1775
    ]
  }
}