{
  "type": "Feature",
  "properties": {
    "name": "Rio Claro",
    "country": "BR",
    "subdivision": "27",
    "timezone": "America/Sao_Paulo"
  },
  "geometry": {
    "type": "Point",
    "coordinates": [
      -47.56139,
      -22.41139
    ]
  }
}