{
  "type": "Feature",
  "properties": {
    "name": "Santos",
    "country": "BR",
    "subdivision": "27",
    "timezone": "America/Sao_Paulo"
  },
  "geometry": {
    "type": "Point",
    "coordinates": [
      -46.33361,
      -23.96083
    ]
  }
}