{
  "type": "Feature",
  "properties": {
    "name": "Santana de Parnaíba",
    "country": "BR",
    "subdivision": "27",
    "timezone": "America/Sao_Paulo"
  },
  "geometry": {
    "type": "Point",
    "coordinates": [
      -46.91778,
      -23.44417
    ]
  }
}