{
  "type": "Feature",
  "properties": {
    "name": "São Joaquim da Barra",
    "country": "BR",
    "subdivision": "27",
    "timezone": "America/Sao_Paulo"
  },
  "geometry": {
    "type": "Point",
    "coordinates": [
      -47.85472,
      -20.58139
    ]
  }
}