{
  "type": "Feature",
  "properties": {
    "name": "São Carlos",
    "country": "BR",
    "subdivision": "27",
    "timezone": "America/Sao_Paulo"
  },
  "geometry": {
    "type": "Point",
    "coordinates": [
      -47.89083,
      -22.0175
    ]
  }
}