{
  "type": "Feature",
  "properties": {
    "name": "São Lourenço da Serra",
    "country": "BR",
    "subdivision": "27",
    "timezone": "America/Sao_Paulo"
  },
  "geometry": {
    "type": "Point",
    "coordinates": [
      -46.9425,
      -23.8525
    ]
  }
}