{
  "type": "Feature",
  "properties": {
    "name": "São José dos Campos",
    "country": "BR",
    "subdivision": "27",
    "timezone": "America/Sao_Paulo"
  },
  "geometry": {
    "type": "Point",
    "coordinates": [
      -45.88694,
      -23.17944
    ]
  }
}