{
  "type": "Feature",
  "properties": {
    "name": "Serra Negra",
    "country": "BR",
    "subdivision": "27",
    "timezone": "America/Sao_Paulo"
  },
  "geometry": {
    "type": "Point",
    "coordinates": [
      -46.70056,
      -22.61222
    ]
  }
}