{
  "type": "Feature",
  "properties": {
    "name": "Severínia",
    "country": "BR",
    "subdivision": "27",
    "timezone": "America/Sao_Paulo"
  },
  "geometry": {
    "type": "Point",
    "coordinates": [
      -48.80278,
      -20.80944
    ]
  }
}