{
  "type": "Feature",
  "properties": {
    "name": "Socorro",
    "country": "BR",
    "subdivision": "27",
    "timezone": "America/Sao_Paulo"
  },
  "geometry": {
    "type": "Point",
    "coordinates": [
      -46.52889,
      -22.59139
    ]
  }
}