{
  "type": "Feature",
  "properties": {
    "name": "Sorocaba",
    "country": "BR",
    "subdivision": "27",
    "timezone": "America/Sao_Paulo"
  },
  "geometry": {
    "type": "Point",
    "coordinates": [
      -47.45806,
      -23.50167
    ]
  }
}