{
  "type": "Feature",
  "properties": {
    "name": "Suzano",
    "country": "BR",
    "subdivision": "27",
    "timezone": "America/Sao_Paulo"
  },
  "geometry": {
    "type": "Point",
    "coordinates": [
      -46.31083,
      -23.5425
    ]
  }
}