{
  "type": "Feature",
  "properties": {
    "name": "Tambaú",
    "country": "BR",
    "subdivision": "27",
    "timezone": "America/Sao_Paulo"
  },
  "geometry": {
    "type": "Point",
    "coordinates": [
      -47.27444,
      -21.705
    ]
  }
}