{
  "type": "Feature",
  "properties": {
    "name": "Taubaté",
    "country": "BR",
    "subdivision": "27",
    "timezone": "America/Sao_Paulo"
  },
  "geometry": {
    "type": "Point",
    "coordinates": [
      -45.55528,
      -23.02639
    ]
  }
}