{
  "type": "Feature",
  "properties": {
    "name": "Ubatuba",
    "country": "BR",
    "subdivision": "27",
    "timezone": "America/Sao_Paulo"
  },
  "geometry": {
    "type": "Point",
    "coordinates": [
      -45.07111,
      -23.43389
    ]
  }
}