{
  "type": "Feature",
  "properties": {
    "name": "Hrytsiv",
    "country": "UA",
    "subdivision": "09",
    "timezone": "Europe/Kiev"
  },
  "geometry": {
    "type": "Point",
    "coordinates": [
      27.21687,
      49.97186
    ]
  }
}