{
  "type": "Feature",
  "properties": {
    "name": "Lozove",
    "country": "UA",
    "subdivision": "09",
    "timezone": "Europe/Kiev"
  },
  "geometry": {
    "type": "Point",
    "coordinates": [
      27.30208,
      49.29376
    ]
  }
}