{
  "type": "Feature",
  "properties": {
    "name": "Nova Ushytsya",
    "country": "UA",
    "subdivision": "09",
    "timezone": "Europe/Kiev"
  },
  "geometry": {
    "type": "Point",
    "coordinates": [
      27.27112,
      48.83699
    ]
  }
}