{
  "type": "Feature",
  "properties": {
    "name": "Smotrych",
    "country": "UA",
    "subdivision": "09",
    "timezone": "Europe/Kiev"
  },
  "geometry": {
    "type": "Point",
    "coordinates": [
      26.5586,
      48.94707
    ]
  }
}