{
  "type": "Feature",
  "properties": {
    "name": "Starokostyantyniv",
    "country": "UA",
    "subdivision": "09",
    "timezone": "Europe/Kiev"
  },
  "geometry": {
    "type": "Point",
    "coordinates": [
      27.21229,
      49.75522
    ]
  }
}