{
  "type": "Feature",
  "properties": {
    "name": "Vinkivtsi",
    "country": "UA",
    "subdivision": "09",
    "timezone": "Europe/Kiev"
  },
  "geometry": {
    "type": "Point",
    "coordinates": [
      27.23135,
      49.03403
    ]
  }
}