{
  "type": "Feature",
  "properties": {
    "name": "Vovkovyntsi",
    "country": "UA",
    "subdivision": "09",
    "timezone": "Europe/Kiev"
  },
  "geometry": {
    "type": "Point",
    "coordinates": [
      27.6556,
      49.20656
    ]
  }
}