{
  "type": "Feature",
  "properties": {
    "name": "Tecoluca",
    "country": "SV",
    "subdivision": "04",
    "timezone": "America/El_Salvador"
  },
  "geometry": {
    "type": "Point",
    "coordinates": [
      -89.00528,
      13.78917
    ]
  }
}