{
  "type": "Feature",
  "properties": {
    "name": "Ambalavao",
    "country": "MG",
    "subdivision": "21",
    "timezone": "Indian/Antananarivo"
  },
  "geometry": {
    "type": "Point",
    "coordinates": [
      46.93333,
      -21.83333
    ]
  }
}