{
  "type": "Feature",
  "properties": {
    "name": "Braço do Norte",
    "country": "BR",
    "subdivision": "26",
    "timezone": "America/Sao_Paulo"
  },
  "geometry": {
    "type": "Point",
    "coordinates": [
      -49.16556,
      -28.275
    ]
  }
}