{
  "type": "Feature",
  "properties": {
    "name": "Forquilhinha",
    "country": "BR",
    "subdivision": "26",
    "timezone": "America/Sao_Paulo"
  },
  "geometry": {
    "type": "Point",
    "coordinates": [
      -49.47222,
      -28.7475
    ]
  }
}