{
  "type": "Feature",
  "properties": {
    "name": "Ibirama",
    "country": "BR",
    "subdivision": "26",
    "timezone": "America/Sao_Paulo"
  },
  "geometry": {
    "type": "Point",
    "coordinates": [
      -49.51778,
      -27.05694
    ]
  }
}