{
  "type": "Feature",
  "properties": {
    "name": "Indaial",
    "country": "BR",
    "subdivision": "26",
    "timezone": "America/Sao_Paulo"
  },
  "geometry": {
    "type": "Point",
    "coordinates": [
      -49.23167,
      -26.89778
    ]
  }
}