{
  "type": "Feature",
  "properties": {
    "name": "Itacorubi",
    "country": "BR",
    "subdivision": "26",
    "timezone": "America/Sao_Paulo"
  },
  "geometry": {
    "type": "Point",
    "coordinates": [
      -48.49503,
      -27.58315
    ]
  }
}