{
  "type": "Feature",
  "properties": {
    "name": "Laguna",
    "country": "BR",
    "subdivision": "26",
    "timezone": "America/Sao_Paulo"
  },
  "geometry": {
    "type": "Point",
    "coordinates": [
      -48.78083,
      -28.4825
    ]
  }
}