{
  "type": "Feature",
  "properties": {
    "name": "Vnanje Gorice",
    "country": "SI",
    "subdivision": "09",
    "timezone": "Europe/Ljubljana"
  },
  "geometry": {
    "type": "Point",
    "coordinates": [
      14.42194,
      46.00722
    ]
  }
}