{
  "type": "Feature",
  "properties": {
    "name": "Abla",
    "country": "ES",
    "subdivision": "51",
    "timezone": "Europe/Madrid"
  },
  "geometry": {
    "type": "Point",
    "coordinates": [
      -2.77808,
      37.14245
    ]
  }
}