{
  "type": "Feature",
  "properties": {
    "name": "Adamuz",
    "country": "ES",
    "subdivision": "51",
    "timezone": "Europe/Madrid"
  },
  "geometry": {
    "type": "Point",
    "coordinates": [
      -4.52231,
      38.02674
    ]
  }
}