{
  "type": "Feature",
  "properties": {
    "name": "Albox",
    "country": "ES",
    "subdivision": "51",
    "timezone": "Europe/Madrid"
  },
  "geometry": {
    "type": "Point",
    "coordinates": [
      -2.14949,
      37.38856
    ]
  }
}