{
  "type": "Feature",
  "properties": {
    "name": "Alcaucín",
    "country": "ES",
    "subdivision": "51",
    "timezone": "Europe/Madrid"
  },
  "geometry": {
    "type": "Point",
    "coordinates": [
      -4.11406,
      36.90301
    ]
  }
}