{
  "type": "Feature",
  "properties": {
    "name": "Aljaraque",
    "country": "ES",
    "subdivision": "51",
    "timezone": "Europe/Madrid"
  },
  "geometry": {
    "type": "Point",
    "coordinates": [
      -7.02313,
      37.26989
    ]
  }
}