{
  "type": "Feature",
  "properties": {
    "name": "Alozaina",
    "country": "ES",
    "subdivision": "51",
    "timezone": "Europe/Madrid"
  },
  "geometry": {
    "type": "Point",
    "coordinates": [
      -4.85761,
      36.72736
    ]
  }
}