{
  "type": "Feature",
  "properties": {
    "name": "Arroyo de la Miel",
    "country": "ES",
    "subdivision": "51",
    "timezone": "Europe/Madrid"
  },
  "geometry": {
    "type": "Point",
    "coordinates": [
      -4.54242,
      36.60326
    ]
  }
}