{
  "type": "Feature",
  "properties": {
    "name": "Aznalcázar",
    "country": "ES",
    "subdivision": "51",
    "timezone": "Europe/Madrid"
  },
  "geometry": {
    "type": "Point",
    "coordinates": [
      -6.24963,
      37.30422
    ]
  }
}