{
  "type": "Feature",
  "properties": {
    "name": "Barbate",
    "country": "ES",
    "subdivision": "51",
    "timezone": "Europe/Madrid"
  },
  "geometry": {
    "type": "Point",
    "coordinates": [
      -5.92186,
      36.19237
    ]
  }
}