{
  "type": "Feature",
  "properties": {
    "name": "Beas",
    "country": "ES",
    "subdivision": "51",
    "timezone": "Europe/Madrid"
  },
  "geometry": {
    "type": "Point",
    "coordinates": [
      -6.79318,
      37.4257
    ]
  }
}