{
  "type": "Feature",
  "properties": {
    "name": "Belalcázar",
    "country": "ES",
    "subdivision": "51",
    "timezone": "Europe/Madrid"
  },
  "geometry": {
    "type": "Point",
    "coordinates": [
      -5.16653,
      38.57566
    ]
  }
}