{
  "type": "Feature",
  "properties": {
    "name": "Benamargosa",
    "country": "ES",
    "subdivision": "51",
    "timezone": "Europe/Madrid"
  },
  "geometry": {
    "type": "Point",
    "coordinates": [
      -4.19362,
      36.83499
    ]
  }
}