{
  "type": "Feature",
  "properties": {
    "name": "Burguillos",
    "country": "ES",
    "subdivision": "51",
    "timezone": "Europe/Madrid"
  },
  "geometry": {
    "type": "Point",
    "coordinates": [
      -5.96654,
      37.5844
    ]
  }
}