{
  "type": "Feature",
  "properties": {
    "name": "Cártama",
    "country": "ES",
    "subdivision": "51",
    "timezone": "Europe/Madrid"
  },
  "geometry": {
    "type": "Point",
    "coordinates": [
      -4.63297,
      36.71068
    ]
  }
}