{
  "type": "Feature",
  "properties": {
    "name": "Casabermeja",
    "country": "ES",
    "subdivision": "51",
    "timezone": "Europe/Madrid"
  },
  "geometry": {
    "type": "Point",
    "coordinates": [
      -4.42938,
      36.8926
    ]
  }
}