{
  "type": "Feature",
  "properties": {
    "name": "Churriana de la Vega",
    "country": "ES",
    "subdivision": "51",
    "timezone": "Europe/Madrid"
  },
  "geometry": {
    "type": "Point",
    "coordinates": [
      -3.64617,
      37.14499
    ]
  }
}