{
  "type": "Feature",
  "properties": {
    "name": "Cortes de la Frontera",
    "country": "ES",
    "subdivision": "51",
    "timezone": "Europe/Madrid"
  },
  "geometry": {
    "type": "Point",
    "coordinates": [
      -5.34266,
      36.6171
    ]
  }
}