{
  "type": "Feature",
  "properties": {
    "name": "Cortes de Baza",
    "country": "ES",
    "subdivision": "51",
    "timezone": "Europe/Madrid"
  },
  "geometry": {
    "type": "Point",
    "coordinates": [
      -2.77167,
      37.65514
    ]
  }
}