{
  "type": "Feature",
  "properties": {
    "name": "Cuevas del Campo",
    "country": "ES",
    "subdivision": "51",
    "timezone": "Europe/Madrid"
  },
  "geometry": {
    "type": "Point",
    "coordinates": [
      -2.92938,
      37.60755
    ]
  }
}