{
  "type": "Feature",
  "properties": {
    "name": "Dalías",
    "country": "ES",
    "subdivision": "51",
    "timezone": "Europe/Madrid"
  },
  "geometry": {
    "type": "Point",
    "coordinates": [
      -2.87138,
      36.82179
    ]
  }
}