{
  "type": "Feature",
  "properties": {
    "name": "Écija",
    "country": "ES",
    "subdivision": "51",
    "timezone": "Europe/Madrid"
  },
  "geometry": {
    "type": "Point",
    "coordinates": [
      -5.0826,
      37.5422
    ]
  }
}