{
  "type": "Feature",
  "properties": {
    "name": "El Puerto de Santa María",
    "country": "ES",
    "subdivision": "51",
    "timezone": "Europe/Madrid"
  },
  "geometry": {
    "type": "Point",
    "coordinates": [
      -6.23298,
      36.59389
    ]
  }
}