{
  "type": "Feature",
  "properties": {
    "name": "Escacena del Campo",
    "country": "ES",
    "subdivision": "51",
    "timezone": "Europe/Madrid"
  },
  "geometry": {
    "type": "Point",
    "coordinates": [
      -6.3887,
      37.40837
    ]
  }
}