{
  "type": "Feature",
  "properties": {
    "name": "Gérgal",
    "country": "ES",
    "subdivision": "51",
    "timezone": "Europe/Madrid"
  },
  "geometry": {
    "type": "Point",
    "coordinates": [
      -2.54012,
      37.11886
    ]
  }
}