{
  "type": "Feature",
  "properties": {
    "name": "Gibraleón",
    "country": "ES",
    "subdivision": "51",
    "timezone": "Europe/Madrid"
  },
  "geometry": {
    "type": "Point",
    "coordinates": [
      -6.96895,
      37.37628
    ]
  }
}