{
  "type": "Feature",
  "properties": {
    "name": "Granada",
    "country": "ES",
    "subdivision": "51",
    "timezone": "Europe/Madrid"
  },
  "geometry": {
    "type": "Point",
    "coordinates": [
      -3.60667,
      37.18817
    ]
  }
}