{
  "type": "Feature",
  "properties": {
    "name": "Guadix",
    "country": "ES",
    "subdivision": "51",
    "timezone": "Europe/Madrid"
  },
  "geometry": {
    "type": "Point",
    "coordinates": [
      -3.13922,
      37.29932
    ]
  }
}