{
  "type": "Feature",
  "properties": {
    "name": "Guaro",
    "country": "ES",
    "subdivision": "51",
    "timezone": "Europe/Madrid"
  },
  "geometry": {
    "type": "Point",
    "coordinates": [
      -4.83433,
      36.6563
    ]
  }
}