{
  "type": "Feature",
  "properties": {
    "name": "Güéjar-Sierra",
    "country": "ES",
    "subdivision": "51",
    "timezone": "Europe/Madrid"
  },
  "geometry": {
    "type": "Point",
    "coordinates": [
      -3.43863,
      37.15994
    ]
  }
}