{
  "type": "Feature",
  "properties": {
    "name": "Jimena de la Frontera",
    "country": "ES",
    "subdivision": "51",
    "timezone": "Europe/Madrid"
  },
  "geometry": {
    "type": "Point",
    "coordinates": [
      -5.45387,
      36.43517
    ]
  }
}