{
  "type": "Feature",
  "properties": {
    "name": "La Algaba",
    "country": "ES",
    "subdivision": "51",
    "timezone": "Europe/Madrid"
  },
  "geometry": {
    "type": "Point",
    "coordinates": [
      -6.01113,
      37.46325
    ]
  }
}