{
  "type": "Feature",
  "properties": {
    "name": "La Campana",
    "country": "ES",
    "subdivision": "51",
    "timezone": "Europe/Madrid"
  },
  "geometry": {
    "type": "Point",
    "coordinates": [
      -5.4267,
      37.56891
    ]
  }
}