{
  "type": "Feature",
  "properties": {
    "name": "La Guardia de Jaén",
    "country": "ES",
    "subdivision": "51",
    "timezone": "Europe/Madrid"
  },
  "geometry": {
    "type": "Point",
    "coordinates": [
      -3.69312,
      37.74303
    ]
  }
}