{
  "type": "Feature",
  "properties": {
    "name": "La Luisiana",
    "country": "ES",
    "subdivision": "51",
    "timezone": "Europe/Madrid"
  },
  "geometry": {
    "type": "Point",
    "coordinates": [
      -5.24883,
      37.52602
    ]
  }
}