{
  "type": "Feature",
  "properties": {
    "name": "La Puebla del Río",
    "country": "ES",
    "subdivision": "51",
    "timezone": "Europe/Madrid"
  },
  "geometry": {
    "type": "Point",
    "coordinates": [
      -6.06264,
      37.26787
    ]
  }
}