{
  "type": "Feature",
  "properties": {
    "name": "La Roda de Andalucía",
    "country": "ES",
    "subdivision": "51",
    "timezone": "Europe/Madrid"
  },
  "geometry": {
    "type": "Point",
    "coordinates": [
      -4.77802,
      37.20381
    ]
  }
}