{
  "type": "Feature",
  "properties": {
    "name": "Los Palacios y Villafranca",
    "country": "ES",
    "subdivision": "51",
    "timezone": "Europe/Madrid"
  },
  "geometry": {
    "type": "Point",
    "coordinates": [
      -5.92433,
      37.16181
    ]
  }
}