{
  "type": "Feature",
  "properties": {
    "name": "Manzanilla",
    "country": "ES",
    "subdivision": "51",
    "timezone": "Europe/Madrid"
  },
  "geometry": {
    "type": "Point",
    "coordinates": [
      -6.43295,
      37.38987
    ]
  }
}