{
  "type": "Feature",
  "properties": {
    "name": "Monachil",
    "country": "ES",
    "subdivision": "51",
    "timezone": "Europe/Madrid"
  },
  "geometry": {
    "type": "Point",
    "coordinates": [
      -3.53724,
      37.1332
    ]
  }
}