{
  "type": "Feature",
  "properties": {
    "name": "Montejicar",
    "country": "ES",
    "subdivision": "51",
    "timezone": "Europe/Madrid"
  },
  "geometry": {
    "type": "Point",
    "coordinates": [
      -3.50527,
      37.57223
    ]
  }
}