{
  "type": "Feature",
  "properties": {
    "name": "Montoro",
    "country": "ES",
    "subdivision": "51",
    "timezone": "Europe/Madrid"
  },
  "geometry": {
    "type": "Point",
    "coordinates": [
      -4.3834,
      38.02409
    ]
  }
}