{
  "type": "Feature",
  "properties": {
    "name": "Montefrío",
    "country": "ES",
    "subdivision": "51",
    "timezone": "Europe/Madrid"
  },
  "geometry": {
    "type": "Point",
    "coordinates": [
      -4.00898,
      37.32308
    ]
  }
}