{
  "type": "Feature",
  "properties": {
    "name": "Orce",
    "country": "ES",
    "subdivision": "51",
    "timezone": "Europe/Madrid"
  },
  "geometry": {
    "type": "Point",
    "coordinates": [
      -2.47752,
      37.7212
    ]
  }
}