{
  "type": "Feature",
  "properties": {
    "name": "Paymogo",
    "country": "ES",
    "subdivision": "51",
    "timezone": "Europe/Madrid"
  },
  "geometry": {
    "type": "Point",
    "coordinates": [
      -7.34499,
      37.73999
    ]
  }
}