{
  "type": "Feature",
  "properties": {
    "name": "Peligros",
    "country": "ES",
    "subdivision": "51",
    "timezone": "Europe/Madrid"
  },
  "geometry": {
    "type": "Point",
    "coordinates": [
      -3.62901,
      37.23231
    ]
  }
}