{
  "type": "Feature",
  "properties": {
    "name": "Pozo Alcón",
    "country": "ES",
    "subdivision": "51",
    "timezone": "Europe/Madrid"
  },
  "geometry": {
    "type": "Point",
    "coordinates": [
      -2.93367,
      37.70256
    ]
  }
}