{
  "type": "Feature",
  "properties": {
    "name": "Prado del Rey",
    "country": "ES",
    "subdivision": "51",
    "timezone": "Europe/Madrid"
  },
  "geometry": {
    "type": "Point",
    "coordinates": [
      -5.55589,
      36.78756
    ]
  }
}