{
  "type": "Feature",
  "properties": {
    "name": "Purchena",
    "country": "ES",
    "subdivision": "51",
    "timezone": "Europe/Madrid"
  },
  "geometry": {
    "type": "Point",
    "coordinates": [
      -2.3608,
      37.34744
    ]
  }
}