{
  "type": "Feature",
  "properties": {
    "name": "Ronda",
    "country": "ES",
    "subdivision": "51",
    "timezone": "Europe/Madrid"
  },
  "geometry": {
    "type": "Point",
    "coordinates": [
      -5.16709,
      36.74231
    ]
  }
}