{
  "type": "Feature",
  "properties": {
    "name": "Serón",
    "country": "ES",
    "subdivision": "51",
    "timezone": "Europe/Madrid"
  },
  "geometry": {
    "type": "Point",
    "coordinates": [
      -2.50913,
      37.34485
    ]
  }
}