{
  "type": "Feature",
  "properties": {
    "name": "Sevilla",
    "country": "ES",
    "subdivision": "51",
    "timezone": "Europe/Madrid"
  },
  "geometry": {
    "type": "Point",
    "coordinates": [
      -5.97317,
      37.38283
    ]
  }
}