{
  "type": "Feature",
  "properties": {
    "name": "Sorbas",
    "country": "ES",
    "subdivision": "51",
    "timezone": "Europe/Madrid"
  },
  "geometry": {
    "type": "Point",
    "coordinates": [
      -2.12349,
      37.09761
    ]
  }
}