{
  "type": "Feature",
  "properties": {
    "name": "Sorihuela del Guadalimar",
    "country": "ES",
    "subdivision": "51",
    "timezone": "Europe/Madrid"
  },
  "geometry": {
    "type": "Point",
    "coordinates": [
      -3.0536,
      38.24062
    ]
  }
}