{
  "type": "Feature",
  "properties": {
    "name": "Trebujena",
    "country": "ES",
    "subdivision": "51",
    "timezone": "Europe/Madrid"
  },
  "geometry": {
    "type": "Point",
    "coordinates": [
      -6.17586,
      36.87075
    ]
  }
}