{
  "type": "Feature",
  "properties": {
    "name": "Ubrique",
    "country": "ES",
    "subdivision": "51",
    "timezone": "Europe/Madrid"
  },
  "geometry": {
    "type": "Point",
    "coordinates": [
      -5.446,
      36.67777
    ]
  }
}