{
  "type": "Feature",
  "properties": {
    "name": "Valdés",
    "country": "ES",
    "subdivision": "51",
    "timezone": "Europe/Madrid"
  },
  "geometry": {
    "type": "Point",
    "coordinates": [
      -4.24235,
      36.75835
    ]
  }
}