{
  "type": "Feature",
  "properties": {
    "name": "Vejer de la Frontera",
    "country": "ES",
    "subdivision": "51",
    "timezone": "Europe/Madrid"
  },
  "geometry": {
    "type": "Point",
    "coordinates": [
      -5.96717,
      36.25213
    ]
  }
}