{
  "type": "Feature",
  "properties": {
    "name": "Vélez-Blanco",
    "country": "ES",
    "subdivision": "51",
    "timezone": "Europe/Madrid"
  },
  "geometry": {
    "type": "Point",
    "coordinates": [
      -2.09587,
      37.69178
    ]
  }
}