{
  "type": "Feature",
  "properties": {
    "name": "Villanueva de Tapia",
    "country": "ES",
    "subdivision": "51",
    "timezone": "Europe/Madrid"
  },
  "geometry": {
    "type": "Point",
    "coordinates": [
      -4.33383,
      37.18276
    ]
  }
}