{
  "type": "Feature",
  "properties": {
    "name": "Villanueva del Rosario",
    "country": "ES",
    "subdivision": "51",
    "timezone": "Europe/Madrid"
  },
  "geometry": {
    "type": "Point",
    "coordinates": [
      -4.36535,
      36.99679
    ]
  }
}