{
  "type": "Feature",
  "properties": {
    "name": "Viñuela",
    "country": "ES",
    "subdivision": "51",
    "timezone": "Europe/Madrid"
  },
  "geometry": {
    "type": "Point",
    "coordinates": [
      -4.14124,
      36.86307
    ]
  }
}