{
  "type": "Feature",
  "properties": {
    "name": "Umluj",
    "country": "SA",
    "subdivision": "19",
    "timezone": "Asia/Riyadh"
  },
  "geometry": {
    "type": "Point",
    "coordinates": [
      37.2685,
      25.02126
    ]
  }
}