{
  "type": "Feature",
  "properties": {
    "name": "Bodītī",
    "country": "ET",
    "subdivision": "54",
    "timezone": "Africa/Addis_Ababa"
  },
  "geometry": {
    "type": "Point",
    "coordinates": [
      37.86667,
      6.96667
    ]
  }
}