{
  "type": "Feature",
  "properties": {
    "name": "Trinity Ville",
    "country": "JM",
    "subdivision": "14",
    "timezone": "America/Jamaica"
  },
  "geometry": {
    "type": "Point",
    "coordinates": [
      -76.51427,
      17.96076
    ]
  }
}