{
  "type": "Feature",
  "properties": {
    "name": "Talodi",
    "country": "SD",
    "subdivision": "50",
    "timezone": "Africa/Khartoum"
  },
  "geometry": {
    "type": "Point",
    "coordinates": [
      30.3797,
      10.63246
    ]
  }
}