{
  "type": "Feature",
  "properties": {
    "name": "Balaclava",
    "country": "JM",
    "subdivision": "11",
    "timezone": "America/Jamaica"
  },
  "geometry": {
    "type": "Point",
    "coordinates": [
      -77.64375,
      18.17228
    ]
  }
}