{
  "type": "Feature",
  "properties": {
    "name": "Santa Cruz",
    "country": "JM",
    "subdivision": "11",
    "timezone": "America/Jamaica"
  },
  "geometry": {
    "type": "Point",
    "coordinates": [
      -77.69836,
      18.05336
    ]
  }
}