{
  "type": "Feature",
  "properties": {
    "name": "Koutiala",
    "country": "ML",
    "subdivision": "06",
    "timezone": "Africa/Bamako"
  },
  "geometry": {
    "type": "Point",
    "coordinates": [
      -5.46421,
      12.39173
    ]
  }
}