{
  "type": "Feature",
  "properties": {
    "name": "Yorosso",
    "country": "ML",
    "subdivision": "06",
    "timezone": "Africa/Bamako"
  },
  "geometry": {
    "type": "Point",
    "coordinates": [
      -4.77688,
      12.35811
    ]
  }
}