{
  "type": "Feature",
  "properties": {
    "name": "PÄveh",
    "country": "IR",
    "subdivision": "13",
    "timezone": "Asia/Tehran"
  },
  "geometry": {
    "type": "Point",
    "coordinates": [
      46.3565,
      35.0434
    ]
  }
}