{
  "type": "Feature",
  "properties": {
    "name": "Allen",
    "country": "AR",
    "subdivision": "16",
    "timezone": "America/Argentina/Salta"
  },
  "geometry": {
    "type": "Point",
    "coordinates": [
      -67.82714,
      -38.97736
    ]
  }
}