{
  "type": "Feature",
  "properties": {
    "name": "Catriel",
    "country": "AR",
    "subdivision": "16",
    "timezone": "America/Argentina/Salta"
  },
  "geometry": {
    "type": "Point",
    "coordinates": [
      -67.7956,
      -37.87907
    ]
  }
}