{
  "type": "Feature",
  "properties": {
    "name": "Contraalmirante Cordero",
    "country": "AR",
    "subdivision": "16",
    "timezone": "America/Argentina/Salta"
  },
  "geometry": {
    "type": "Point",
    "coordinates": [
      -68.15284,
      -38.72423
    ]
  }
}