{
  "type": "Feature",
  "properties": {
    "name": "General Roca",
    "country": "AR",
    "subdivision": "16",
    "timezone": "America/Argentina/Salta"
  },
  "geometry": {
    "type": "Point",
    "coordinates": [
      -67.58333,
      -39.03333
    ]
  }
}