{
  "type": "Feature",
  "properties": {
    "name": "Pilcaniyeu",
    "country": "AR",
    "subdivision": "16",
    "timezone": "America/Argentina/Salta"
  },
  "geometry": {
    "type": "Point",
    "coordinates": [
      -70.72152,
      -41.12288
    ]
  }
}