{
  "type": "Feature",
  "properties": {
    "name": "Mislesevo",
    "country": "MK",
    "subdivision": "E6",
    "timezone": "Europe/Skopje"
  },
  "geometry": {
    "type": "Point",
    "coordinates": [
      20.70861,
      41.185
    ]
  }
}