{
  "type": "Feature",
  "properties": {
    "name": "Kirov",
    "country": "TJ",
    "subdivision": "02",
    "timezone": "Asia/Dushanbe"
  },
  "geometry": {
    "type": "Point",
    "coordinates": [
      68.85905,
      37.81908
    ]
  }
}