{
  "type": "Feature",
  "properties": {
    "name": "Vakhsh",
    "country": "TJ",
    "subdivision": "02",
    "timezone": "Asia/Dushanbe"
  },
  "geometry": {
    "type": "Point",
    "coordinates": [
      68.83456,
      37.71485
    ]
  }
}