{
  "type": "Feature",
  "properties": {
    "name": "Erdenet",
    "country": "MN",
    "subdivision": "25",
    "timezone": "Asia/Ulaanbaatar"
  },
  "geometry": {
    "type": "Point",
    "coordinates": [
      104.08333,
      49.03333
    ]
  }
}