{
  "type": "Feature",
  "properties": {
    "name": "Fort McPherson",
    "country": "CA",
    "subdivision": "13",
    "timezone": "America/Yellowknife"
  },
  "geometry": {
    "type": "Point",
    "coordinates": [
      -134.88543,
      67.43863
    ]
  }
}