{
  "type": "Feature",
  "properties": {
    "name": "Gerede",
    "country": "TR",
    "subdivision": "14",
    "timezone": "Europe/Istanbul"
  },
  "geometry": {
    "type": "Point",
    "coordinates": [
      32.19694,
      40.80083
    ]
  }
}