{
  "type": "Feature",
  "properties": {
    "name": "Lalago",
    "country": "TZ",
    "subdivision": "31",
    "timezone": "Africa/Dar_es_Salaam"
  },
  "geometry": {
    "type": "Point",
    "coordinates": [
      33.95,
      -3.45
    ]
  }
}