{
  "type": "Feature",
  "properties": {
    "name": "Nyakabindi",
    "country": "TZ",
    "subdivision": "31",
    "timezone": "Africa/Dar_es_Salaam"
  },
  "geometry": {
    "type": "Point",
    "coordinates": [
      33.98333,
      -2.63333
    ]
  }
}