{
  "type": "Feature",
  "properties": {
    "name": "Abapó",
    "country": "BO",
    "subdivision": "08",
    "timezone": "America/La_Paz"
  },
  "geometry": {
    "type": "Point",
    "coordinates": [
      -63.38026,
      -18.88279
    ]
  }
}