{
  "type": "Feature",
  "properties": {
    "name": "Montero",
    "country": "BO",
    "subdivision": "08",
    "timezone": "America/La_Paz"
  },
  "geometry": {
    "type": "Point",
    "coordinates": [
      -63.2505,
      -17.33866
    ]
  }
}