{
  "type": "Feature",
  "properties": {
    "name": "Okinawa Número Uno",
    "country": "BO",
    "subdivision": "08",
    "timezone": "America/La_Paz"
  },
  "geometry": {
    "type": "Point",
    "coordinates": [
      -62.81667,
      -17.23333
    ]
  }
}