{
  "type": "Feature",
  "properties": {
    "name": "San Ignacio de Velasco",
    "country": "BO",
    "subdivision": "08",
    "timezone": "America/La_Paz"
  },
  "geometry": {
    "type": "Point",
    "coordinates": [
      -60.95,
      -16.36667
    ]
  }
}