{
  "type": "Feature",
  "properties": {
    "name": "Barichara",
    "country": "CO",
    "subdivision": "26",
    "timezone": "America/Bogota"
  },
  "geometry": {
    "type": "Point",
    "coordinates": [
      -73.22282,
      6.63572
    ]
  }
}