{
  "type": "Feature",
  "properties": {
    "name": "Capitanejo",
    "country": "CO",
    "subdivision": "26",
    "timezone": "America/Bogota"
  },
  "geometry": {
    "type": "Point",
    "coordinates": [
      -72.69595,
      6.52881
    ]
  }
}