{
  "type": "Feature",
  "properties": {
    "name": "Vetas",
    "country": "CO",
    "subdivision": "26",
    "timezone": "America/Bogota"
  },
  "geometry": {
    "type": "Point",
    "coordinates": [
      -72.87122,
      7.30911
    ]
  }
}