{
  "type": "Feature",
  "properties": {
    "name": "Zapatoca",
    "country": "CO",
    "subdivision": "26",
    "timezone": "America/Bogota"
  },
  "geometry": {
    "type": "Point",
    "coordinates": [
      -73.26768,
      6.81532
    ]
  }
}