{
  "type": "Feature",
  "properties": {
    "name": "Ambattūr",
    "country": "IN",
    "subdivision": "25",
    "timezone": "Asia/Kolkata"
  },
  "geometry": {
    "type": "Point",
    "coordinates": [
      80.16152,
      13.09818
    ]
  }
}