{
  "type": "Feature",
  "properties": {
    "name": "Avinashi",
    "country": "IN",
    "subdivision": "25",
    "timezone": "Asia/Kolkata"
  },
  "geometry": {
    "type": "Point",
    "coordinates": [
      77.26865,
      11.19297
    ]
  }
}