{
  "type": "Feature",
  "properties": {
    "name": "Bodināyakkanūr",
    "country": "IN",
    "subdivision": "25",
    "timezone": "Asia/Kolkata"
  },
  "geometry": {
    "type": "Point",
    "coordinates": [
      77.34976,
      10.01171
    ]
  }
}