{
  "type": "Feature",
  "properties": {
    "name": "Colachel",
    "country": "IN",
    "subdivision": "25",
    "timezone": "Asia/Kolkata"
  },
  "geometry": {
    "type": "Point",
    "coordinates": [
      77.25818,
      8.17938
    ]
  }
}