{
  "type": "Feature",
  "properties": {
    "name": "Dharmapuri",
    "country": "IN",
    "subdivision": "25",
    "timezone": "Asia/Kolkata"
  },
  "geometry": {
    "type": "Point",
    "coordinates": [
      78.15794,
      12.1277
    ]
  }
}