{
  "type": "Feature",
  "properties": {
    "name": "Eral",
    "country": "IN",
    "subdivision": "25",
    "timezone": "Asia/Kolkata"
  },
  "geometry": {
    "type": "Point",
    "coordinates": [
      78.02282,
      8.62584
    ]
  }
}