{
  "type": "Feature",
  "properties": {
    "name": "Gingee",
    "country": "IN",
    "subdivision": "25",
    "timezone": "Asia/Kolkata"
  },
  "geometry": {
    "type": "Point",
    "coordinates": [
      79.41727,
      12.25282
    ]
  }
}