{
  "type": "Feature",
  "properties": {
    "name": "Gudalur",
    "country": "IN",
    "subdivision": "25",
    "timezone": "Asia/Kolkata"
  },
  "geometry": {
    "type": "Point",
    "coordinates": [
      77.24951,
      9.67826
    ]
  }
}