{
  "type": "Feature",
  "properties": {
    "name": "Hosūr",
    "country": "IN",
    "subdivision": "25",
    "timezone": "Asia/Kolkata"
  },
  "geometry": {
    "type": "Point",
    "coordinates": [
      77.83264,
      12.73647
    ]
  }
}