{
  "type": "Feature",
  "properties": {
    "name": "Karambakkudi",
    "country": "IN",
    "subdivision": "25",
    "timezone": "Asia/Kolkata"
  },
  "geometry": {
    "type": "Point",
    "coordinates": [
      79.14101,
      10.45866
    ]
  }
}