{
  "type": "Feature",
  "properties": {
    "name": "Kātpādi",
    "country": "IN",
    "subdivision": "25",
    "timezone": "Asia/Kolkata"
  },
  "geometry": {
    "type": "Point",
    "coordinates": [
      79.14552,
      12.96951
    ]
  }
}