{
  "type": "Feature",
  "properties": {
    "name": "Kāttupputtūr",
    "country": "IN",
    "subdivision": "25",
    "timezone": "Asia/Kolkata"
  },
  "geometry": {
    "type": "Point",
    "coordinates": [
      78.21929,
      10.99385
    ]
  }
}