{
  "type": "Feature",
  "properties": {
    "name": "Kelamangalam",
    "country": "IN",
    "subdivision": "25",
    "timezone": "Asia/Kolkata"
  },
  "geometry": {
    "type": "Point",
    "coordinates": [
      77.85193,
      12.60307
    ]
  }
}