{
  "type": "Feature",
  "properties": {
    "name": "Kīl Bhuvanagiri",
    "country": "IN",
    "subdivision": "25",
    "timezone": "Asia/Kolkata"
  },
  "geometry": {
    "type": "Point",
    "coordinates": [
      79.64763,
      11.44216
    ]
  }
}