{
  "type": "Feature",
  "properties": {
    "name": "Koothanallur",
    "country": "IN",
    "subdivision": "25",
    "timezone": "Asia/Kolkata"
  },
  "geometry": {
    "type": "Point",
    "coordinates": [
      79.5157,
      10.7199
    ]
  }
}