{
  "type": "Feature",
  "properties": {
    "name": "Manamadurai",
    "country": "IN",
    "subdivision": "25",
    "timezone": "Asia/Kolkata"
  },
  "geometry": {
    "type": "Point",
    "coordinates": [
      78.47096,
      9.67318
    ]
  }
}