{
  "type": "Feature",
  "properties": {
    "name": "Manapparai",
    "country": "IN",
    "subdivision": "25",
    "timezone": "Asia/Kolkata"
  },
  "geometry": {
    "type": "Point",
    "coordinates": [
      78.42582,
      10.60772
    ]
  }
}