{
  "type": "Feature",
  "properties": {
    "name": "Mandapam",
    "country": "IN",
    "subdivision": "25",
    "timezone": "Asia/Kolkata"
  },
  "geometry": {
    "type": "Point",
    "coordinates": [
      79.12362,
      9.27571
    ]
  }
}