{
  "type": "Feature",
  "properties": {
    "name": "Mangalam",
    "country": "IN",
    "subdivision": "25",
    "timezone": "Asia/Kolkata"
  },
  "geometry": {
    "type": "Point",
    "coordinates": [
      78.64037,
      9.76473
    ]
  }
}