{
  "type": "Feature",
  "properties": {
    "name": "Mannargudi",
    "country": "IN",
    "subdivision": "25",
    "timezone": "Asia/Kolkata"
  },
  "geometry": {
    "type": "Point",
    "coordinates": [
      79.45064,
      10.66626
    ]
  }
}