{
  "type": "Feature",
  "properties": {
    "name": "MettuppÄlaiyam",
    "country": "IN",
    "subdivision": "25",
    "timezone": "Asia/Kolkata"
  },
  "geometry": {
    "type": "Point",
    "coordinates": [
      78.44944,
      11.16806
    ]
  }
}