{
  "type": "Feature",
  "properties": {
    "name": "Mohanūr",
    "country": "IN",
    "subdivision": "25",
    "timezone": "Asia/Kolkata"
  },
  "geometry": {
    "type": "Point",
    "coordinates": [
      78.13965,
      11.05936
    ]
  }
}