{
  "type": "Feature",
  "properties": {
    "name": "Palani",
    "country": "IN",
    "subdivision": "25",
    "timezone": "Asia/Kolkata"
  },
  "geometry": {
    "type": "Point",
    "coordinates": [
      77.5209,
      10.45034
    ]
  }
}