{
  "type": "Feature",
  "properties": {
    "name": "Panruti",
    "country": "IN",
    "subdivision": "25",
    "timezone": "Asia/Kolkata"
  },
  "geometry": {
    "type": "Point",
    "coordinates": [
      79.55269,
      11.77662
    ]
  }
}