{
  "type": "Feature",
  "properties": {
    "name": "Periyakulam",
    "country": "IN",
    "subdivision": "25",
    "timezone": "Asia/Kolkata"
  },
  "geometry": {
    "type": "Point",
    "coordinates": [
      77.54372,
      10.12268
    ]
  }
}