{
  "type": "Feature",
  "properties": {
    "name": "Sathyamangalam",
    "country": "IN",
    "subdivision": "25",
    "timezone": "Asia/Kolkata"
  },
  "geometry": {
    "type": "Point",
    "coordinates": [
      77.23826,
      11.50526
    ]
  }
}