{
  "type": "Feature",
  "properties": {
    "name": "Srivilliputhur",
    "country": "IN",
    "subdivision": "25",
    "timezone": "Asia/Kolkata"
  },
  "geometry": {
    "type": "Point",
    "coordinates": [
      77.63369,
      9.51272
    ]
  }
}