{
  "type": "Feature",
  "properties": {
    "name": "Thiruvaiyaru",
    "country": "IN",
    "subdivision": "25",
    "timezone": "Asia/Kolkata"
  },
  "geometry": {
    "type": "Point",
    "coordinates": [
      79.10362,
      10.88405
    ]
  }
}