{
  "type": "Feature",
  "properties": {
    "name": "Tiruchirappalli",
    "country": "IN",
    "subdivision": "25",
    "timezone": "Asia/Kolkata"
  },
  "geometry": {
    "type": "Point",
    "coordinates": [
      78.69651,
      10.8155
    ]
  }
}