{
  "type": "Feature",
  "properties": {
    "name": "TirumullaivÄsal",
    "country": "IN",
    "subdivision": "25",
    "timezone": "Asia/Kolkata"
  },
  "geometry": {
    "type": "Point",
    "coordinates": [
      79.83705,
      11.23996
    ]
  }
}