{
  "type": "Feature",
  "properties": {
    "name": "Tiruchchendur",
    "country": "IN",
    "subdivision": "25",
    "timezone": "Asia/Kolkata"
  },
  "geometry": {
    "type": "Point",
    "coordinates": [
      78.11906,
      8.49725
    ]
  }
}