{
  "type": "Feature",
  "properties": {
    "name": "Vallam",
    "country": "IN",
    "subdivision": "25",
    "timezone": "Asia/Kolkata"
  },
  "geometry": {
    "type": "Point",
    "coordinates": [
      79.05981,
      10.71988
    ]
  }
}