{
  "type": "Feature",
  "properties": {
    "name": "Vedasandūr",
    "country": "IN",
    "subdivision": "25",
    "timezone": "Asia/Kolkata"
  },
  "geometry": {
    "type": "Point",
    "coordinates": [
      77.95019,
      10.53102
    ]
  }
}