{
  "type": "Feature",
  "properties": {
    "name": "Vellānūr",
    "country": "IN",
    "subdivision": "25",
    "timezone": "Asia/Kolkata"
  },
  "geometry": {
    "type": "Point",
    "coordinates": [
      80.10634,
      13.15804
    ]
  }
}