{
  "type": "Feature",
  "properties": {
    "name": "Vilattikulam",
    "country": "IN",
    "subdivision": "25",
    "timezone": "Asia/Kolkata"
  },
  "geometry": {
    "type": "Point",
    "coordinates": [
      78.16635,
      9.13227
    ]
  }
}