{
  "type": "Feature",
  "properties": {
    "name": "Virudunagar",
    "country": "IN",
    "subdivision": "25",
    "timezone": "Asia/Kolkata"
  },
  "geometry": {
    "type": "Point",
    "coordinates": [
      77.95787,
      9.58509
    ]
  }
}