{
  "type": "Feature",
  "properties": {
    "name": "VriddhÄchalam",
    "country": "IN",
    "subdivision": "25",
    "timezone": "Asia/Kolkata"
  },
  "geometry": {
    "type": "Point",
    "coordinates": [
      79.32411,
      11.5183
    ]
  }
}