{
  "type": "Feature",
  "properties": {
    "name": "Ajā",
    "country": "EG",
    "subdivision": "01",
    "timezone": "Africa/Cairo"
  },
  "geometry": {
    "type": "Point",
    "coordinates": [
      31.29039,
      30.94162
    ]
  }
}