{
  "type": "Feature",
  "properties": {
    "name": "Minyat an Naşr",
    "country": "EG",
    "subdivision": "01",
    "timezone": "Africa/Cairo"
  },
  "geometry": {
    "type": "Point",
    "coordinates": [
      31.64313,
      31.12624
    ]
  }
}