{
  "type": "Feature",
  "properties": {
    "name": "Shirbīn",
    "country": "EG",
    "subdivision": "01",
    "timezone": "Africa/Cairo"
  },
  "geometry": {
    "type": "Point",
    "coordinates": [
      31.5243,
      31.19688
    ]
  }
}