{
  "type": "Feature",
  "properties": {
    "name": "Baldovinești",
    "country": "RO",
    "subdivision": "08",
    "timezone": "Europe/Bucharest"
  },
  "geometry": {
    "type": "Point",
    "coordinates": [
      27.91107,
      45.32182
    ]
  }
}