{
  "type": "Feature",
  "properties": {
    "name": "Dedulești",
    "country": "RO",
    "subdivision": "08",
    "timezone": "Europe/Bucharest"
  },
  "geometry": {
    "type": "Point",
    "coordinates": [
      27.38907,
      45.14679
    ]
  }
}