{
  "type": "Feature",
  "properties": {
    "name": "Perișoru",
    "country": "RO",
    "subdivision": "08",
    "timezone": "Europe/Bucharest"
  },
  "geometry": {
    "type": "Point",
    "coordinates": [
      27.49817,
      45.11268
    ]
  }
}