{
  "type": "Feature",
  "properties": {
    "name": "Plopu",
    "country": "RO",
    "subdivision": "08",
    "timezone": "Europe/Bucharest"
  },
  "geometry": {
    "type": "Point",
    "coordinates": [
      27.51387,
      45.14847
    ]
  }
}