{
  "type": "Feature",
  "properties": {
    "name": "Tufeşti",
    "country": "RO",
    "subdivision": "08",
    "timezone": "Europe/Bucharest"
  },
  "geometry": {
    "type": "Point",
    "coordinates": [
      27.81667,
      45.05
    ]
  }
}