{
  "type": "Feature",
  "properties": {
    "name": "Vădeni",
    "country": "RO",
    "subdivision": "08",
    "timezone": "Europe/Bucharest"
  },
  "geometry": {
    "type": "Point",
    "coordinates": [
      27.93333,
      45.36667
    ]
  }
}