{
  "type": "Feature",
  "properties": {
    "name": "Minas de Corrales",
    "country": "UY",
    "subdivision": "13",
    "timezone": "America/Montevideo"
  },
  "geometry": {
    "type": "Point",
    "coordinates": [
      -55.47075,
      -31.57375
    ]
  }
}