{
  "type": "Feature",
  "properties": {
    "name": "Bherāmāra",
    "country": "BD",
    "subdivision": "82",
    "timezone": "Asia/Dhaka"
  },
  "geometry": {
    "type": "Point",
    "coordinates": [
      88.99234,
      24.02452
    ]
  }
}