{
  "type": "Feature",
  "properties": {
    "name": "Kālīganj",
    "country": "BD",
    "subdivision": "82",
    "timezone": "Asia/Dhaka"
  },
  "geometry": {
    "type": "Point",
    "coordinates": [
      89.13801,
      23.40964
    ]
  }
}