{
  "type": "Feature",
  "properties": {
    "name": "Ujalpur",
    "country": "BD",
    "subdivision": "82",
    "timezone": "Asia/Dhaka"
  },
  "geometry": {
    "type": "Point",
    "coordinates": [
      88.62444,
      23.80562
    ]
  }
}