{
  "type": "Feature",
  "properties": {
    "name": "Colonia del Sol",
    "country": "MX",
    "subdivision": "03",
    "timezone": "America/Mazatlan"
  },
  "geometry": {
    "type": "Point",
    "coordinates": [
      -109.92655,
      22.91273
    ]
  }
}