{
  "type": "Feature",
  "properties": {
    "name": "La Playa",
    "country": "MX",
    "subdivision": "03",
    "timezone": "America/Mazatlan"
  },
  "geometry": {
    "type": "Point",
    "coordinates": [
      -109.66833,
      23.06417
    ]
  }
}