{
  "type": "Feature",
  "properties": {
    "name": "San José del Cabo",
    "country": "MX",
    "subdivision": "03",
    "timezone": "America/Mazatlan"
  },
  "geometry": {
    "type": "Point",
    "coordinates": [
      -109.69771,
      23.05888
    ]
  }
}