{
  "type": "Feature",
  "properties": {
    "name": "Aduana del Sásabe",
    "country": "MX",
    "subdivision": "26",
    "timezone": "America/Hermosillo"
  },
  "geometry": {
    "type": "Point",
    "coordinates": [
      -111.54608,
      31.47076
    ]
  }
}