{
  "type": "Feature",
  "properties": {
    "name": "Bacerac",
    "country": "MX",
    "subdivision": "26",
    "timezone": "America/Hermosillo"
  },
  "geometry": {
    "type": "Point",
    "coordinates": [
      -108.93147,
      30.35565
    ]
  }
}