{
  "type": "Feature",
  "properties": {
    "name": "Bacoachi",
    "country": "MX",
    "subdivision": "26",
    "timezone": "America/Hermosillo"
  },
  "geometry": {
    "type": "Point",
    "coordinates": [
      -109.96867,
      30.63168
    ]
  }
}