{
  "type": "Feature",
  "properties": {
    "name": "Bácum",
    "country": "MX",
    "subdivision": "26",
    "timezone": "America/Hermosillo"
  },
  "geometry": {
    "type": "Point",
    "coordinates": [
      -110.0833,
      27.55142
    ]
  }
}