{
  "type": "Feature",
  "properties": {
    "name": "Campo Carretero",
    "country": "MX",
    "subdivision": "26",
    "timezone": "America/Hermosillo"
  },
  "geometry": {
    "type": "Point",
    "coordinates": [
      -110.8538,
      30.77154
    ]
  }
}