{
  "type": "Feature",
  "properties": {
    "name": "El Sahuaral",
    "country": "MX",
    "subdivision": "26",
    "timezone": "America/Hermosillo"
  },
  "geometry": {
    "type": "Point",
    "coordinates": [
      -109.66643,
      26.92633
    ]
  }
}