{
  "type": "Feature",
  "properties": {
    "name": "Empalme",
    "country": "MX",
    "subdivision": "26",
    "timezone": "America/Hermosillo"
  },
  "geometry": {
    "type": "Point",
    "coordinates": [
      -110.81411,
      27.96166
    ]
  }
}