{
  "type": "Feature",
  "properties": {
    "name": "Estación Corral",
    "country": "MX",
    "subdivision": "26",
    "timezone": "America/Hermosillo"
  },
  "geometry": {
    "type": "Point",
    "coordinates": [
      -109.96611,
      27.62889
    ]
  }
}