{
  "type": "Feature",
  "properties": {
    "name": "La Mesa",
    "country": "MX",
    "subdivision": "26",
    "timezone": "America/Hermosillo"
  },
  "geometry": {
    "type": "Point",
    "coordinates": [
      -110.97444,
      31.15972
    ]
  }
}