{
  "type": "Feature",
  "properties": {
    "name": "La Providencia",
    "country": "MX",
    "subdivision": "26",
    "timezone": "America/Hermosillo"
  },
  "geometry": {
    "type": "Point",
    "coordinates": [
      -111.58687,
      28.72268
    ]
  }
}