{
  "type": "Feature",
  "properties": {
    "name": "Los Bahuises",
    "country": "MX",
    "subdivision": "26",
    "timezone": "America/Hermosillo"
  },
  "geometry": {
    "type": "Point",
    "coordinates": [
      -109.46722,
      27.11667
    ]
  }
}