{
  "type": "Feature",
  "properties": {
    "name": "Los Hoyos",
    "country": "MX",
    "subdivision": "26",
    "timezone": "America/Hermosillo"
  },
  "geometry": {
    "type": "Point",
    "coordinates": [
      -109.78222,
      30.12444
    ]
  }
}