{
  "type": "Feature",
  "properties": {
    "name": "Moctezuma",
    "country": "MX",
    "subdivision": "26",
    "timezone": "America/Hermosillo"
  },
  "geometry": {
    "type": "Point",
    "coordinates": [
      -109.67949,
      29.80615
    ]
  }
}