{
  "type": "Feature",
  "properties": {
    "name": "Potam",
    "country": "MX",
    "subdivision": "26",
    "timezone": "America/Hermosillo"
  },
  "geometry": {
    "type": "Point",
    "coordinates": [
      -110.4158,
      27.626
    ]
  }
}