{
  "type": "Feature",
  "properties": {
    "name": "Pueblo Yaqui",
    "country": "MX",
    "subdivision": "26",
    "timezone": "America/Hermosillo"
  },
  "geometry": {
    "type": "Point",
    "coordinates": [
      -110.03444,
      27.35521
    ]
  }
}