{
  "type": "Feature",
  "properties": {
    "name": "Puerto Peñasco",
    "country": "MX",
    "subdivision": "26",
    "timezone": "America/Hermosillo"
  },
  "geometry": {
    "type": "Point",
    "coordinates": [
      -113.53799,
      31.31716
    ]
  }
}