{
  "type": "Feature",
  "properties": {
    "name": "Sahuaral de Otero",
    "country": "MX",
    "subdivision": "26",
    "timezone": "America/Hermosillo"
  },
  "geometry": {
    "type": "Point",
    "coordinates": [
      -109.73175,
      26.88487
    ]
  }
}