{
  "type": "Feature",
  "properties": {
    "name": "San Bernardo",
    "country": "MX",
    "subdivision": "26",
    "timezone": "America/Hermosillo"
  },
  "geometry": {
    "type": "Point",
    "coordinates": [
      -108.8444,
      27.39909
    ]
  }
}