{
  "type": "Feature",
  "properties": {
    "name": "San José de Bacum",
    "country": "MX",
    "subdivision": "26",
    "timezone": "America/Hermosillo"
  },
  "geometry": {
    "type": "Point",
    "coordinates": [
      -110.14308,
      27.51477
    ]
  }
}