{
  "type": "Feature",
  "properties": {
    "name": "Yavaros",
    "country": "MX",
    "subdivision": "26",
    "timezone": "America/Hermosillo"
  },
  "geometry": {
    "type": "Point",
    "coordinates": [
      -109.52103,
      26.70483
    ]
  }
}