{
  "type": "Feature",
  "properties": {
    "name": "Baghdad",
    "country": "IQ",
    "subdivision": "07",
    "timezone": "Asia/Baghdad"
  },
  "geometry": {
    "type": "Point",
    "coordinates": [
      44.40088,
      33.34058
    ]
  }
}