{
  "type": "Feature",
  "properties": {
    "name": "Santiago de Chuco",
    "country": "PE",
    "subdivision": "13",
    "timezone": "America/Lima"
  },
  "geometry": {
    "type": "Point",
    "coordinates": [
      -78.17329,
      -8.14099
    ]
  }
}