{
  "type": "Feature",
  "properties": {
    "name": "Hatton",
    "country": "LK",
    "subdivision": "29",
    "timezone": "Asia/Colombo"
  },
  "geometry": {
    "type": "Point",
    "coordinates": [
      80.5955,
      6.8916
    ]
  }
}