{
  "type": "Feature",
  "properties": {
    "name": "Sarh",
    "country": "TD",
    "subdivision": "17",
    "timezone": "Africa/Ndjamena"
  },
  "geometry": {
    "type": "Point",
    "coordinates": [
      18.38331,
      9.14555
    ]
  }
}