{
  "type": "Feature",
  "properties": {
    "name": "Youssoufia",
    "country": "MA",
    "subdivision": "07",
    "timezone": "Africa/Casablanca"
  },
  "geometry": {
    "type": "Point",
    "coordinates": [
      -8.52941,
      32.24634
    ]
  }
}