{
  "type": "Feature",
  "properties": {
    "name": "Abondance",
    "country": "FR",
    "subdivision": "84",
    "timezone": "Europe/Paris"
  },
  "geometry": {
    "type": "Point",
    "coordinates": [
      6.72105,
      46.27874
    ]
  }
}