{
  "type": "Feature",
  "properties": {
    "name": "Alby-sur-Chéran",
    "country": "FR",
    "subdivision": "84",
    "timezone": "Europe/Paris"
  },
  "geometry": {
    "type": "Point",
    "coordinates": [
      6.01667,
      45.81667
    ]
  }
}