{
  "type": "Feature",
  "properties": {
    "name": "Alissas",
    "country": "FR",
    "subdivision": "84",
    "timezone": "Europe/Paris"
  },
  "geometry": {
    "type": "Point",
    "coordinates": [
      4.62936,
      44.71253
    ]
  }
}