{
  "type": "Feature",
  "properties": {
    "name": "Allex",
    "country": "FR",
    "subdivision": "84",
    "timezone": "Europe/Paris"
  },
  "geometry": {
    "type": "Point",
    "coordinates": [
      4.89837,
      44.76765
    ]
  }
}