{
  "type": "Feature",
  "properties": {
    "name": "Allinges",
    "country": "FR",
    "subdivision": "84",
    "timezone": "Europe/Paris"
  },
  "geometry": {
    "type": "Point",
    "coordinates": [
      6.4635,
      46.33547
    ]
  }
}