{
  "type": "Feature",
  "properties": {
    "name": "Ambert",
    "country": "FR",
    "subdivision": "84",
    "timezone": "Europe/Paris"
  },
  "geometry": {
    "type": "Point",
    "coordinates": [
      3.74164,
      45.54944
    ]
  }
}