{
  "type": "Feature",
  "properties": {
    "name": "Andrézieux-Bouthéon",
    "country": "FR",
    "subdivision": "84",
    "timezone": "Europe/Paris"
  },
  "geometry": {
    "type": "Point",
    "coordinates": [
      4.26021,
      45.52625
    ]
  }
}