{
  "type": "Feature",
  "properties": {
    "name": "Arnas",
    "country": "FR",
    "subdivision": "84",
    "timezone": "Europe/Paris"
  },
  "geometry": {
    "type": "Point",
    "coordinates": [
      4.7083,
      46.02361
    ]
  }
}