{
  "type": "Feature",
  "properties": {
    "name": "Aurillac",
    "country": "FR",
    "subdivision": "84",
    "timezone": "Europe/Paris"
  },
  "geometry": {
    "type": "Point",
    "coordinates": [
      2.43983,
      44.92539
    ]
  }
}