{
  "type": "Feature",
  "properties": {
    "name": "Beauvallon",
    "country": "FR",
    "subdivision": "84",
    "timezone": "Europe/Paris"
  },
  "geometry": {
    "type": "Point",
    "coordinates": [
      4.90756,
      44.85593
    ]
  }
}