{
  "type": "Feature",
  "properties": {
    "name": "Beauchastel",
    "country": "FR",
    "subdivision": "84",
    "timezone": "Europe/Paris"
  },
  "geometry": {
    "type": "Point",
    "coordinates": [
      4.80305,
      44.82587
    ]
  }
}