{
  "type": "Feature",
  "properties": {
    "name": "Beausemblant",
    "country": "FR",
    "subdivision": "84",
    "timezone": "Europe/Paris"
  },
  "geometry": {
    "type": "Point",
    "coordinates": [
      4.83241,
      45.21706
    ]
  }
}