{
  "type": "Feature",
  "properties": {
    "name": "Bellevaux",
    "country": "FR",
    "subdivision": "84",
    "timezone": "Europe/Paris"
  },
  "geometry": {
    "type": "Point",
    "coordinates": [
      6.53351,
      46.25875
    ]
  }
}