{
  "type": "Feature",
  "properties": {
    "name": "Bilieu",
    "country": "FR",
    "subdivision": "84",
    "timezone": "Europe/Paris"
  },
  "geometry": {
    "type": "Point",
    "coordinates": [
      5.54268,
      45.44809
    ]
  }
}