{
  "type": "Feature",
  "properties": {
    "name": "Blavozy",
    "country": "FR",
    "subdivision": "84",
    "timezone": "Europe/Paris"
  },
  "geometry": {
    "type": "Point",
    "coordinates": [
      3.97993,
      45.0572
    ]
  }
}