{
  "type": "Feature",
  "properties": {
    "name": "Bonnefamille",
    "country": "FR",
    "subdivision": "84",
    "timezone": "Europe/Paris"
  },
  "geometry": {
    "type": "Point",
    "coordinates": [
      5.12489,
      45.59956
    ]
  }
}