{
  "type": "Feature",
  "properties": {
    "name": "Boulieu-lès-Annonay",
    "country": "FR",
    "subdivision": "84",
    "timezone": "Europe/Paris"
  },
  "geometry": {
    "type": "Point",
    "coordinates": [
      4.66645,
      45.27065
    ]
  }
}