{
  "type": "Feature",
  "properties": {
    "name": "Bourbon-l'Archambault",
    "country": "FR",
    "subdivision": "84",
    "timezone": "Europe/Paris"
  },
  "geometry": {
    "type": "Point",
    "coordinates": [
      3.05652,
      46.58324
    ]
  }
}