{
  "type": "Feature",
  "properties": {
    "name": "Brignais",
    "country": "FR",
    "subdivision": "84",
    "timezone": "Europe/Paris"
  },
  "geometry": {
    "type": "Point",
    "coordinates": [
      4.75418,
      45.67383
    ]
  }
}