{
  "type": "Feature",
  "properties": {
    "name": "Brindas",
    "country": "FR",
    "subdivision": "84",
    "timezone": "Europe/Paris"
  },
  "geometry": {
    "type": "Point",
    "coordinates": [
      4.69349,
      45.72111
    ]
  }
}