{
  "type": "Feature",
  "properties": {
    "name": "Bussières",
    "country": "FR",
    "subdivision": "84",
    "timezone": "Europe/Paris"
  },
  "geometry": {
    "type": "Point",
    "coordinates": [
      4.27123,
      45.8357
    ]
  }
}