{
  "type": "Feature",
  "properties": {
    "name": "Cérilly",
    "country": "FR",
    "subdivision": "84",
    "timezone": "Europe/Paris"
  },
  "geometry": {
    "type": "Point",
    "coordinates": [
      2.8208,
      46.61791
    ]
  }
}