{
  "type": "Feature",
  "properties": {
    "name": "Ceyzériat",
    "country": "FR",
    "subdivision": "84",
    "timezone": "Europe/Paris"
  },
  "geometry": {
    "type": "Point",
    "coordinates": [
      5.31977,
      46.18126
    ]
  }
}