{
  "type": "Feature",
  "properties": {
    "name": "Challex",
    "country": "FR",
    "subdivision": "84",
    "timezone": "Europe/Paris"
  },
  "geometry": {
    "type": "Point",
    "coordinates": [
      5.97639,
      46.18458
    ]
  }
}