{
  "type": "Feature",
  "properties": {
    "name": "Champdieu",
    "country": "FR",
    "subdivision": "84",
    "timezone": "Europe/Paris"
  },
  "geometry": {
    "type": "Point",
    "coordinates": [
      4.04705,
      45.64533
    ]
  }
}