{
  "type": "Feature",
  "properties": {
    "name": "Chanas",
    "country": "FR",
    "subdivision": "84",
    "timezone": "Europe/Paris"
  },
  "geometry": {
    "type": "Point",
    "coordinates": [
      4.81849,
      45.31881
    ]
  }
}