{
  "type": "Feature",
  "properties": {
    "name": "Chaponnay",
    "country": "FR",
    "subdivision": "84",
    "timezone": "Europe/Paris"
  },
  "geometry": {
    "type": "Point",
    "coordinates": [
      4.93615,
      45.62762
    ]
  }
}