{
  "type": "Feature",
  "properties": {
    "name": "Charly",
    "country": "FR",
    "subdivision": "84",
    "timezone": "Europe/Paris"
  },
  "geometry": {
    "type": "Point",
    "coordinates": [
      4.79461,
      45.64887
    ]
  }
}