{
  "type": "Feature",
  "properties": {
    "name": "Charnay",
    "country": "FR",
    "subdivision": "84",
    "timezone": "Europe/Paris"
  },
  "geometry": {
    "type": "Point",
    "coordinates": [
      4.66821,
      45.89058
    ]
  }
}