{
  "type": "Feature",
  "properties": {
    "name": "Chavanod",
    "country": "FR",
    "subdivision": "84",
    "timezone": "Europe/Paris"
  },
  "geometry": {
    "type": "Point",
    "coordinates": [
      6.03928,
      45.89005
    ]
  }
}