{
  "type": "Feature",
  "properties": {
    "name": "Chuzelles",
    "country": "FR",
    "subdivision": "84",
    "timezone": "Europe/Paris"
  },
  "geometry": {
    "type": "Point",
    "coordinates": [
      4.87703,
      45.58481
    ]
  }
}