{
  "type": "Feature",
  "properties": {
    "name": "Claix",
    "country": "FR",
    "subdivision": "84",
    "timezone": "Europe/Paris"
  },
  "geometry": {
    "type": "Point",
    "coordinates": [
      5.67292,
      45.11994
    ]
  }
}