{
  "type": "Feature",
  "properties": {
    "name": "Cluses",
    "country": "FR",
    "subdivision": "84",
    "timezone": "Europe/Paris"
  },
  "geometry": {
    "type": "Point",
    "coordinates": [
      6.57497,
      46.06251
    ]
  }
}