{
  "type": "Feature",
  "properties": {
    "name": "Collonges-sous-Salève",
    "country": "FR",
    "subdivision": "84",
    "timezone": "Europe/Paris"
  },
  "geometry": {
    "type": "Point",
    "coordinates": [
      6.15372,
      46.1416
    ]
  }
}