{
  "type": "Feature",
  "properties": {
    "name": "Colombe",
    "country": "FR",
    "subdivision": "84",
    "timezone": "Europe/Paris"
  },
  "geometry": {
    "type": "Point",
    "coordinates": [
      5.45441,
      45.40024
    ]
  }
}