{
  "type": "Feature",
  "properties": {
    "name": "Condat",
    "country": "FR",
    "subdivision": "84",
    "timezone": "Europe/Paris"
  },
  "geometry": {
    "type": "Point",
    "coordinates": [
      2.75791,
      45.34093
    ]
  }
}