{
  "type": "Feature",
  "properties": {
    "name": "Coux",
    "country": "FR",
    "subdivision": "84",
    "timezone": "Europe/Paris"
  },
  "geometry": {
    "type": "Point",
    "coordinates": [
      4.62057,
      44.73484
    ]
  }
}