{
  "type": "Feature",
  "properties": {
    "name": "Crolles",
    "country": "FR",
    "subdivision": "84",
    "timezone": "Europe/Paris"
  },
  "geometry": {
    "type": "Point",
    "coordinates": [
      5.87837,
      45.27724
    ]
  }
}