{
  "type": "Feature",
  "properties": {
    "name": "Cunlhat",
    "country": "FR",
    "subdivision": "84",
    "timezone": "Europe/Paris"
  },
  "geometry": {
    "type": "Point",
    "coordinates": [
      3.55927,
      45.63198
    ]
  }
}