{
  "type": "Feature",
  "properties": {
    "name": "Denicé",
    "country": "FR",
    "subdivision": "84",
    "timezone": "Europe/Paris"
  },
  "geometry": {
    "type": "Point",
    "coordinates": [
      4.64555,
      46.00158
    ]
  }
}