{
  "type": "Feature",
  "properties": {
    "name": "Dolomieu",
    "country": "FR",
    "subdivision": "84",
    "timezone": "Europe/Paris"
  },
  "geometry": {
    "type": "Point",
    "coordinates": [
      5.48571,
      45.6054
    ]
  }
}