{
  "type": "Feature",
  "properties": {
    "name": "Domessin",
    "country": "FR",
    "subdivision": "84",
    "timezone": "Europe/Paris"
  },
  "geometry": {
    "type": "Point",
    "coordinates": [
      5.70495,
      45.54739
    ]
  }
}