{
  "type": "Feature",
  "properties": {
    "name": "Douvaine",
    "country": "FR",
    "subdivision": "84",
    "timezone": "Europe/Paris"
  },
  "geometry": {
    "type": "Point",
    "coordinates": [
      6.30375,
      46.30544
    ]
  }
}