{
  "type": "Feature",
  "properties": {
    "name": "Entre-Deux-Guiers",
    "country": "FR",
    "subdivision": "84",
    "timezone": "Europe/Paris"
  },
  "geometry": {
    "type": "Point",
    "coordinates": [
      5.75209,
      45.43061
    ]
  }
}