{
  "type": "Feature",
  "properties": {
    "name": "Enval",
    "country": "FR",
    "subdivision": "84",
    "timezone": "Europe/Paris"
  },
  "geometry": {
    "type": "Point",
    "coordinates": [
      3.04981,
      45.89921
    ]
  }
}