{
  "type": "Feature",
  "properties": {
    "name": "Estivareilles",
    "country": "FR",
    "subdivision": "84",
    "timezone": "Europe/Paris"
  },
  "geometry": {
    "type": "Point",
    "coordinates": [
      2.61872,
      46.42526
    ]
  }
}