{
  "type": "Feature",
  "properties": {
    "name": "Félines",
    "country": "FR",
    "subdivision": "84",
    "timezone": "Europe/Paris"
  },
  "geometry": {
    "type": "Point",
    "coordinates": [
      4.72836,
      45.31668
    ]
  }
}