{
  "type": "Feature",
  "properties": {
    "name": "Fontannes",
    "country": "FR",
    "subdivision": "84",
    "timezone": "Europe/Paris"
  },
  "geometry": {
    "type": "Point",
    "coordinates": [
      3.76366,
      45.30149
    ]
  }
}