{
  "type": "Feature",
  "properties": {
    "name": "Gelles",
    "country": "FR",
    "subdivision": "84",
    "timezone": "Europe/Paris"
  },
  "geometry": {
    "type": "Point",
    "coordinates": [
      2.76309,
      45.76947
    ]
  }
}