{
  "type": "Feature",
  "properties": {
    "name": "Gières",
    "country": "FR",
    "subdivision": "84",
    "timezone": "Europe/Paris"
  },
  "geometry": {
    "type": "Point",
    "coordinates": [
      5.78935,
      45.17997
    ]
  }
}