{
  "type": "Feature",
  "properties": {
    "name": "Grièges",
    "country": "FR",
    "subdivision": "84",
    "timezone": "Europe/Paris"
  },
  "geometry": {
    "type": "Point",
    "coordinates": [
      4.84856,
      46.25619
    ]
  }
}