{
  "type": "Feature",
  "properties": {
    "name": "Groisy",
    "country": "FR",
    "subdivision": "84",
    "timezone": "Europe/Paris"
  },
  "geometry": {
    "type": "Point",
    "coordinates": [
      6.16983,
      46.01008
    ]
  }
}