{
  "type": "Feature",
  "properties": {
    "name": "Gruffy",
    "country": "FR",
    "subdivision": "84",
    "timezone": "Europe/Paris"
  },
  "geometry": {
    "type": "Point",
    "coordinates": [
      6.05648,
      45.78897
    ]
  }
}