{
  "type": "Feature",
  "properties": {
    "name": "Guilherand-Granges",
    "country": "FR",
    "subdivision": "84",
    "timezone": "Europe/Paris"
  },
  "geometry": {
    "type": "Point",
    "coordinates": [
      4.87372,
      44.93278
    ]
  }
}