{
  "type": "Feature",
  "properties": {
    "name": "Jacob-Bellecombette",
    "country": "FR",
    "subdivision": "84",
    "timezone": "Europe/Paris"
  },
  "geometry": {
    "type": "Point",
    "coordinates": [
      5.91484,
      45.55763
    ]
  }
}