{
  "type": "Feature",
  "properties": {
    "name": "Janneyrias",
    "country": "FR",
    "subdivision": "84",
    "timezone": "Europe/Paris"
  },
  "geometry": {
    "type": "Point",
    "coordinates": [
      5.11277,
      45.75221
    ]
  }
}