{
  "type": "Feature",
  "properties": {
    "name": "Jaujac",
    "country": "FR",
    "subdivision": "84",
    "timezone": "Europe/Paris"
  },
  "geometry": {
    "type": "Point",
    "coordinates": [
      4.25638,
      44.63695
    ]
  }
}