{
  "type": "Feature",
  "properties": {
    "name": "La Côte-Saint-André",
    "country": "FR",
    "subdivision": "84",
    "timezone": "Europe/Paris"
  },
  "geometry": {
    "type": "Point",
    "coordinates": [
      5.25908,
      45.39447
    ]
  }
}