{
  "type": "Feature",
  "properties": {
    "name": "La Mulatière",
    "country": "FR",
    "subdivision": "84",
    "timezone": "Europe/Paris"
  },
  "geometry": {
    "type": "Point",
    "coordinates": [
      4.81213,
      45.72818
    ]
  }
}