{
  "type": "Feature",
  "properties": {
    "name": "La Voulte-sur-Rhône",
    "country": "FR",
    "subdivision": "84",
    "timezone": "Europe/Paris"
  },
  "geometry": {
    "type": "Point",
    "coordinates": [
      4.77925,
      44.79958
    ]
  }
}