{
  "type": "Feature",
  "properties": {
    "name": "Laroquebrou",
    "country": "FR",
    "subdivision": "84",
    "timezone": "Europe/Paris"
  },
  "geometry": {
    "type": "Point",
    "coordinates": [
      2.19158,
      44.96855
    ]
  }
}