{
  "type": "Feature",
  "properties": {
    "name": "Le Bourget-du-Lac",
    "country": "FR",
    "subdivision": "84",
    "timezone": "Europe/Paris"
  },
  "geometry": {
    "type": "Point",
    "coordinates": [
      5.8549,
      45.65362
    ]
  }
}