{
  "type": "Feature",
  "properties": {
    "name": "Le Cheylard",
    "country": "FR",
    "subdivision": "84",
    "timezone": "Europe/Paris"
  },
  "geometry": {
    "type": "Point",
    "coordinates": [
      4.42406,
      44.90623
    ]
  }
}