{
  "type": "Feature",
  "properties": {
    "name": "Le Grand-Lemps",
    "country": "FR",
    "subdivision": "84",
    "timezone": "Europe/Paris"
  },
  "geometry": {
    "type": "Point",
    "coordinates": [
      5.4201,
      45.39646
    ]
  }
}