{
  "type": "Feature",
  "properties": {
    "name": "Le Mayet-de-Montagne",
    "country": "FR",
    "subdivision": "84",
    "timezone": "Europe/Paris"
  },
  "geometry": {
    "type": "Point",
    "coordinates": [
      3.66665,
      46.07091
    ]
  }
}