{
  "type": "Feature",
  "properties": {
    "name": "Le Sappey-en-Chartreuse",
    "country": "FR",
    "subdivision": "84",
    "timezone": "Europe/Paris"
  },
  "geometry": {
    "type": "Point",
    "coordinates": [
      5.77476,
      45.26235
    ]
  }
}