{
  "type": "Feature",
  "properties": {
    "name": "Les Marches",
    "country": "FR",
    "subdivision": "84",
    "timezone": "Europe/Paris"
  },
  "geometry": {
    "type": "Point",
    "coordinates": [
      6.00381,
      45.50042
    ]
  }
}