{
  "type": "Feature",
  "properties": {
    "name": "Loisin",
    "country": "FR",
    "subdivision": "84",
    "timezone": "Europe/Paris"
  },
  "geometry": {
    "type": "Point",
    "coordinates": [
      6.3101,
      46.29227
    ]
  }
}