{
  "type": "Feature",
  "properties": {
    "name": "Loyettes",
    "country": "FR",
    "subdivision": "84",
    "timezone": "Europe/Paris"
  },
  "geometry": {
    "type": "Point",
    "coordinates": [
      5.20687,
      45.77663
    ]
  }
}