{
  "type": "Feature",
  "properties": {
    "name": "Mâcot-la-Plagne",
    "country": "FR",
    "subdivision": "84",
    "timezone": "Europe/Paris"
  },
  "geometry": {
    "type": "Point",
    "coordinates": [
      6.66667,
      45.55
    ]
  }
}