{
  "type": "Feature",
  "properties": {
    "name": "Mauriac",
    "country": "FR",
    "subdivision": "84",
    "timezone": "Europe/Paris"
  },
  "geometry": {
    "type": "Point",
    "coordinates": [
      2.33353,
      45.21899
    ]
  }
}