{
  "type": "Feature",
  "properties": {
    "name": "Mazet-Saint-Voy",
    "country": "FR",
    "subdivision": "84",
    "timezone": "Europe/Paris"
  },
  "geometry": {
    "type": "Point",
    "coordinates": [
      4.24414,
      45.04696
    ]
  }
}