{
  "type": "Feature",
  "properties": {
    "name": "Messimy",
    "country": "FR",
    "subdivision": "84",
    "timezone": "Europe/Paris"
  },
  "geometry": {
    "type": "Point",
    "coordinates": [
      4.67429,
      45.69816
    ]
  }
}