{
  "type": "Feature",
  "properties": {
    "name": "Mezel",
    "country": "FR",
    "subdivision": "84",
    "timezone": "Europe/Paris"
  },
  "geometry": {
    "type": "Point",
    "coordinates": [
      3.24225,
      45.75508
    ]
  }
}