{
  "type": "Feature",
  "properties": {
    "name": "Mirabel-aux-Baronnies",
    "country": "FR",
    "subdivision": "84",
    "timezone": "Europe/Paris"
  },
  "geometry": {
    "type": "Point",
    "coordinates": [
      5.09962,
      44.31002
    ]
  }
}