{
  "type": "Feature",
  "properties": {
    "name": "Montélimar",
    "country": "FR",
    "subdivision": "84",
    "timezone": "Europe/Paris"
  },
  "geometry": {
    "type": "Point",
    "coordinates": [
      4.75469,
      44.55468
    ]
  }
}