{
  "type": "Feature",
  "properties": {
    "name": "Montfaucon-en-Velay",
    "country": "FR",
    "subdivision": "84",
    "timezone": "Europe/Paris"
  },
  "geometry": {
    "type": "Point",
    "coordinates": [
      4.31376,
      45.18561
    ]
  }
}