{
  "type": "Feature",
  "properties": {
    "name": "Morancé",
    "country": "FR",
    "subdivision": "84",
    "timezone": "Europe/Paris"
  },
  "geometry": {
    "type": "Point",
    "coordinates": [
      4.70051,
      45.89815
    ]
  }
}