{
  "type": "Feature",
  "properties": {
    "name": "Mornant",
    "country": "FR",
    "subdivision": "84",
    "timezone": "Europe/Paris"
  },
  "geometry": {
    "type": "Point",
    "coordinates": [
      4.67231,
      45.61885
    ]
  }
}