{
  "type": "Feature",
  "properties": {
    "name": "Mours-Saint-Eusèbe",
    "country": "FR",
    "subdivision": "84",
    "timezone": "Europe/Paris"
  },
  "geometry": {
    "type": "Point",
    "coordinates": [
      5.05776,
      45.06513
    ]
  }
}