{
  "type": "Feature",
  "properties": {
    "name": "Murat",
    "country": "FR",
    "subdivision": "84",
    "timezone": "Europe/Paris"
  },
  "geometry": {
    "type": "Point",
    "coordinates": [
      2.86859,
      45.11011
    ]
  }
}