{
  "type": "Feature",
  "properties": {
    "name": "Neuilly-le-Réal",
    "country": "FR",
    "subdivision": "84",
    "timezone": "Europe/Paris"
  },
  "geometry": {
    "type": "Point",
    "coordinates": [
      3.43197,
      46.46413
    ]
  }
}