{
  "type": "Feature",
  "properties": {
    "name": "Paslières",
    "country": "FR",
    "subdivision": "84",
    "timezone": "Europe/Paris"
  },
  "geometry": {
    "type": "Point",
    "coordinates": [
      3.49736,
      45.92889
    ]
  }
}