{
  "type": "Feature",
  "properties": {
    "name": "Pélussin",
    "country": "FR",
    "subdivision": "84",
    "timezone": "Europe/Paris"
  },
  "geometry": {
    "type": "Point",
    "coordinates": [
      4.68365,
      45.41951
    ]
  }
}