{
  "type": "Feature",
  "properties": {
    "name": "Pérignat-sur-Allier",
    "country": "FR",
    "subdivision": "84",
    "timezone": "Europe/Paris"
  },
  "geometry": {
    "type": "Point",
    "coordinates": [
      3.23184,
      45.72843
    ]
  }
}