{
  "type": "Feature",
  "properties": {
    "name": "Péron",
    "country": "FR",
    "subdivision": "84",
    "timezone": "Europe/Paris"
  },
  "geometry": {
    "type": "Point",
    "coordinates": [
      5.92524,
      46.19053
    ]
  }
}