{
  "type": "Feature",
  "properties": {
    "name": "Pierre-Châtel",
    "country": "FR",
    "subdivision": "84",
    "timezone": "Europe/Paris"
  },
  "geometry": {
    "type": "Point",
    "coordinates": [
      5.77454,
      44.95735
    ]
  }
}