{
  "type": "Feature",
  "properties": {
    "name": "Plauzat",
    "country": "FR",
    "subdivision": "84",
    "timezone": "Europe/Paris"
  },
  "geometry": {
    "type": "Point",
    "coordinates": [
      3.14896,
      45.62157
    ]
  }
}