{
  "type": "Feature",
  "properties": {
    "name": "Pont-de-Chéruy",
    "country": "FR",
    "subdivision": "84",
    "timezone": "Europe/Paris"
  },
  "geometry": {
    "type": "Point",
    "coordinates": [
      5.17245,
      45.75344
    ]
  }
}