{
  "type": "Feature",
  "properties": {
    "name": "Pouilly-les-Nonains",
    "country": "FR",
    "subdivision": "84",
    "timezone": "Europe/Paris"
  },
  "geometry": {
    "type": "Point",
    "coordinates": [
      3.98247,
      46.04508
    ]
  }
}