{
  "type": "Feature",
  "properties": {
    "name": "Pringy",
    "country": "FR",
    "subdivision": "84",
    "timezone": "Europe/Paris"
  },
  "geometry": {
    "type": "Point",
    "coordinates": [
      6.12608,
      45.94622
    ]
  }
}