{
  "type": "Feature",
  "properties": {
    "name": "Quintenas",
    "country": "FR",
    "subdivision": "84",
    "timezone": "Europe/Paris"
  },
  "geometry": {
    "type": "Point",
    "coordinates": [
      4.68743,
      45.18892
    ]
  }
}