{
  "type": "Feature",
  "properties": {
    "name": "Renage",
    "country": "FR",
    "subdivision": "84",
    "timezone": "Europe/Paris"
  },
  "geometry": {
    "type": "Point",
    "coordinates": [
      5.48881,
      45.33346
    ]
  }
}