{
  "type": "Feature",
  "properties": {
    "name": "Retournac",
    "country": "FR",
    "subdivision": "84",
    "timezone": "Europe/Paris"
  },
  "geometry": {
    "type": "Point",
    "coordinates": [
      4.0333,
      45.2039
    ]
  }
}