{
  "type": "Feature",
  "properties": {
    "name": "Riotord",
    "country": "FR",
    "subdivision": "84",
    "timezone": "Europe/Paris"
  },
  "geometry": {
    "type": "Point",
    "coordinates": [
      4.40208,
      45.23159
    ]
  }
}