{
  "type": "Feature",
  "properties": {
    "name": "Roanne",
    "country": "FR",
    "subdivision": "84",
    "timezone": "Europe/Paris"
  },
  "geometry": {
    "type": "Point",
    "coordinates": [
      4.06802,
      46.03624
    ]
  }
}