{
  "type": "Feature",
  "properties": {
    "name": "Saint-Restitut",
    "country": "FR",
    "subdivision": "84",
    "timezone": "Europe/Paris"
  },
  "geometry": {
    "type": "Point",
    "coordinates": [
      4.79282,
      44.32446
    ]
  }
}