{
  "type": "Feature",
  "properties": {
    "name": "Saint-Jean-d'Aulps",
    "country": "FR",
    "subdivision": "84",
    "timezone": "Europe/Paris"
  },
  "geometry": {
    "type": "Point",
    "coordinates": [
      6.65327,
      46.23438
    ]
  }
}