{
  "type": "Feature",
  "properties": {
    "name": "Saint-Priest",
    "country": "FR",
    "subdivision": "84",
    "timezone": "Europe/Paris"
  },
  "geometry": {
    "type": "Point",
    "coordinates": [
      4.94385,
      45.69651
    ]
  }
}