{
  "type": "Feature",
  "properties": {
    "name": "Sain-Bel",
    "country": "FR",
    "subdivision": "84",
    "timezone": "Europe/Paris"
  },
  "geometry": {
    "type": "Point",
    "coordinates": [
      4.59797,
      45.81017
    ]
  }
}