{
  "type": "Feature",
  "properties": {
    "name": "Saint-Chef",
    "country": "FR",
    "subdivision": "84",
    "timezone": "Europe/Paris"
  },
  "geometry": {
    "type": "Point",
    "coordinates": [
      5.36465,
      45.63585
    ]
  }
}