{
  "type": "Feature",
  "properties": {
    "name": "Saint-André-le-Gaz",
    "country": "FR",
    "subdivision": "84",
    "timezone": "Europe/Paris"
  },
  "geometry": {
    "type": "Point",
    "coordinates": [
      5.52886,
      45.54546
    ]
  }
}