{
  "type": "Feature",
  "properties": {
    "name": "Saint-Sernin",
    "country": "FR",
    "subdivision": "84",
    "timezone": "Europe/Paris"
  },
  "geometry": {
    "type": "Point",
    "coordinates": [
      4.39186,
      44.57147
    ]
  }
}