{
  "type": "Feature",
  "properties": {
    "name": "Saint-Uze",
    "country": "FR",
    "subdivision": "84",
    "timezone": "Europe/Paris"
  },
  "geometry": {
    "type": "Point",
    "coordinates": [
      4.86,
      45.18409
    ]
  }
}