{
  "type": "Feature",
  "properties": {
    "name": "Saint-Ours",
    "country": "FR",
    "subdivision": "84",
    "timezone": "Europe/Paris"
  },
  "geometry": {
    "type": "Point",
    "coordinates": [
      2.89163,
      45.85024
    ]
  }
}