{
  "type": "Feature",
  "properties": {
    "name": "Sainte-Euphémie",
    "country": "FR",
    "subdivision": "84",
    "timezone": "Europe/Paris"
  },
  "geometry": {
    "type": "Point",
    "coordinates": [
      4.79853,
      45.97101
    ]
  }
}