{
  "type": "Feature",
  "properties": {
    "name": "Saint-Martin-de-Belleville",
    "country": "FR",
    "subdivision": "84",
    "timezone": "Europe/Paris"
  },
  "geometry": {
    "type": "Point",
    "coordinates": [
      6.50519,
      45.38175
    ]
  }
}