{
  "type": "Feature",
  "properties": {
    "name": "Saint-Germain-Laprade",
    "country": "FR",
    "subdivision": "84",
    "timezone": "Europe/Paris"
  },
  "geometry": {
    "type": "Point",
    "coordinates": [
      3.97004,
      45.03862
    ]
  }
}