{
  "type": "Feature",
  "properties": {
    "name": "Saint-Germain-Lembron",
    "country": "FR",
    "subdivision": "84",
    "timezone": "Europe/Paris"
  },
  "geometry": {
    "type": "Point",
    "coordinates": [
      3.23973,
      45.45793
    ]
  }
}