{
  "type": "Feature",
  "properties": {
    "name": "Saint-Chamond",
    "country": "FR",
    "subdivision": "84",
    "timezone": "Europe/Paris"
  },
  "geometry": {
    "type": "Point",
    "coordinates": [
      4.51294,
      45.4759
    ]
  }
}