{
  "type": "Feature",
  "properties": {
    "name": "Saint-Sorlin-en-Valloire",
    "country": "FR",
    "subdivision": "84",
    "timezone": "Europe/Paris"
  },
  "geometry": {
    "type": "Point",
    "coordinates": [
      4.94903,
      45.28774
    ]
  }
}