{
  "type": "Feature",
  "properties": {
    "name": "Saint-Privat",
    "country": "FR",
    "subdivision": "84",
    "timezone": "Europe/Paris"
  },
  "geometry": {
    "type": "Point",
    "coordinates": [
      4.41489,
      44.62859
    ]
  }
}