{
  "type": "Feature",
  "properties": {
    "name": "Saint-Laurent-en-Royans",
    "country": "FR",
    "subdivision": "84",
    "timezone": "Europe/Paris"
  },
  "geometry": {
    "type": "Point",
    "coordinates": [
      5.32669,
      45.02653
    ]
  }
}