{
  "type": "Feature",
  "properties": {
    "name": "Saint-Nazaire-les-Eymes",
    "country": "FR",
    "subdivision": "84",
    "timezone": "Europe/Paris"
  },
  "geometry": {
    "type": "Point",
    "coordinates": [
      5.85254,
      45.24921
    ]
  }
}