{
  "type": "Feature",
  "properties": {
    "name": "Saint-Joseph-de-Rivière",
    "country": "FR",
    "subdivision": "84",
    "timezone": "Europe/Paris"
  },
  "geometry": {
    "type": "Point",
    "coordinates": [
      5.69643,
      45.37572
    ]
  }
}