{
  "type": "Feature",
  "properties": {
    "name": "Saint-Genix-sur-Guiers",
    "country": "FR",
    "subdivision": "84",
    "timezone": "Europe/Paris"
  },
  "geometry": {
    "type": "Point",
    "coordinates": [
      5.63559,
      45.59864
    ]
  }
}