{
  "type": "Feature",
  "properties": {
    "name": "Saint-Joseph",
    "country": "FR",
    "subdivision": "84",
    "timezone": "Europe/Paris"
  },
  "geometry": {
    "type": "Point",
    "coordinates": [
      4.62076,
      45.55757
    ]
  }
}