{
  "type": "Feature",
  "properties": {
    "name": "Saint-Denis-de-Cabanne",
    "country": "FR",
    "subdivision": "84",
    "timezone": "Europe/Paris"
  },
  "geometry": {
    "type": "Point",
    "coordinates": [
      4.21447,
      46.17249
    ]
  }
}