{
  "type": "Feature",
  "properties": {
    "name": "Saint-Andéol-le-Château",
    "country": "FR",
    "subdivision": "84",
    "timezone": "Europe/Paris"
  },
  "geometry": {
    "type": "Point",
    "coordinates": [
      4.69504,
      45.58597
    ]
  }
}