{
  "type": "Feature",
  "properties": {
    "name": "Saint-Maurice-de-Beynost",
    "country": "FR",
    "subdivision": "84",
    "timezone": "Europe/Paris"
  },
  "geometry": {
    "type": "Point",
    "coordinates": [
      4.9775,
      45.8344
    ]
  }
}