{
  "type": "Feature",
  "properties": {
    "name": "Saint-Savin",
    "country": "FR",
    "subdivision": "84",
    "timezone": "Europe/Paris"
  },
  "geometry": {
    "type": "Point",
    "coordinates": [
      5.30856,
      45.62776
    ]
  }
}