{
  "type": "Feature",
  "properties": {
    "name": "Saint-Bon-Tarentaise",
    "country": "FR",
    "subdivision": "84",
    "timezone": "Europe/Paris"
  },
  "geometry": {
    "type": "Point",
    "coordinates": [
      6.63686,
      45.43373
    ]
  }
}