{
  "type": "Feature",
  "properties": {
    "name": "Saint-Priest-en-Jarez",
    "country": "FR",
    "subdivision": "84",
    "timezone": "Europe/Paris"
  },
  "geometry": {
    "type": "Point",
    "coordinates": [
      4.37678,
      45.4739
    ]
  }
}