{
  "type": "Feature",
  "properties": {
    "name": "Saint-Georges-de-Reneins",
    "country": "FR",
    "subdivision": "84",
    "timezone": "Europe/Paris"
  },
  "geometry": {
    "type": "Point",
    "coordinates": [
      4.72169,
      46.06185
    ]
  }
}