{
  "type": "Feature",
  "properties": {
    "name": "Saint-Genis-les-Ollières",
    "country": "FR",
    "subdivision": "84",
    "timezone": "Europe/Paris"
  },
  "geometry": {
    "type": "Point",
    "coordinates": [
      4.72625,
      45.7571
    ]
  }
}