{
  "type": "Feature",
  "properties": {
    "name": "Sansac-de-Marmiesse",
    "country": "FR",
    "subdivision": "84",
    "timezone": "Europe/Paris"
  },
  "geometry": {
    "type": "Point",
    "coordinates": [
      2.34768,
      44.88376
    ]
  }
}