{
  "type": "Feature",
  "properties": {
    "name": "Sury-le-Comtal",
    "country": "FR",
    "subdivision": "84",
    "timezone": "Europe/Paris"
  },
  "geometry": {
    "type": "Point",
    "coordinates": [
      4.18573,
      45.53735
    ]
  }
}