{
  "type": "Feature",
  "properties": {
    "name": "Ternay",
    "country": "FR",
    "subdivision": "84",
    "timezone": "Europe/Paris"
  },
  "geometry": {
    "type": "Point",
    "coordinates": [
      4.81064,
      45.60234
    ]
  }
}