{
  "type": "Feature",
  "properties": {
    "name": "Tignes",
    "country": "FR",
    "subdivision": "84",
    "timezone": "Europe/Paris"
  },
  "geometry": {
    "type": "Point",
    "coordinates": [
      6.92463,
      45.49604
    ]
  }
}