{
  "type": "Feature",
  "properties": {
    "name": "Unieux",
    "country": "FR",
    "subdivision": "84",
    "timezone": "Europe/Paris"
  },
  "geometry": {
    "type": "Point",
    "coordinates": [
      4.27094,
      45.40395
    ]
  }
}