{
  "type": "Feature",
  "properties": {
    "name": "Vaulnaveys-le-Haut",
    "country": "FR",
    "subdivision": "84",
    "timezone": "Europe/Paris"
  },
  "geometry": {
    "type": "Point",
    "coordinates": [
      5.81723,
      45.12524
    ]
  }
}