{
  "type": "Feature",
  "properties": {
    "name": "Vendat",
    "country": "FR",
    "subdivision": "84",
    "timezone": "Europe/Paris"
  },
  "geometry": {
    "type": "Point",
    "coordinates": [
      3.35366,
      46.16387
    ]
  }
}