{
  "type": "Feature",
  "properties": {
    "name": "Veyrier-du-Lac",
    "country": "FR",
    "subdivision": "84",
    "timezone": "Europe/Paris"
  },
  "geometry": {
    "type": "Point",
    "coordinates": [
      6.17709,
      45.88234
    ]
  }
}