{
  "type": "Feature",
  "properties": {
    "name": "Vieille-Brioude",
    "country": "FR",
    "subdivision": "84",
    "timezone": "Europe/Paris"
  },
  "geometry": {
    "type": "Point",
    "coordinates": [
      3.40479,
      45.2647
    ]
  }
}