{
  "type": "Feature",
  "properties": {
    "name": "Villeneuve",
    "country": "FR",
    "subdivision": "84",
    "timezone": "Europe/Paris"
  },
  "geometry": {
    "type": "Point",
    "coordinates": [
      4.83591,
      46.02096
    ]
  }
}