{
  "type": "Feature",
  "properties": {
    "name": "Vimines",
    "country": "FR",
    "subdivision": "84",
    "timezone": "Europe/Paris"
  },
  "geometry": {
    "type": "Point",
    "coordinates": [
      5.86523,
      45.5464
    ]
  }
}