{
  "type": "Feature",
  "properties": {
    "name": "Virieu",
    "country": "FR",
    "subdivision": "84",
    "timezone": "Europe/Paris"
  },
  "geometry": {
    "type": "Point",
    "coordinates": [
      5.47586,
      45.48404
    ]
  }
}