{
  "type": "Feature",
  "properties": {
    "name": "Voiron",
    "country": "FR",
    "subdivision": "84",
    "timezone": "Europe/Paris"
  },
  "geometry": {
    "type": "Point",
    "coordinates": [
      5.5856,
      45.36471
    ]
  }
}