{
  "type": "Feature",
  "properties": {
    "name": "Borensberg",
    "country": "SE",
    "subdivision": "16",
    "timezone": "Europe/Stockholm"
  },
  "geometry": {
    "type": "Point",
    "coordinates": [
      15.28333,
      58.56667
    ]
  }
}