{
  "type": "Feature",
  "properties": {
    "name": "Hluti",
    "country": "SZ",
    "subdivision": "04",
    "timezone": "Africa/Mbabane"
  },
  "geometry": {
    "type": "Point",
    "coordinates": [
      31.61667,
      -27.21667
    ]
  }
}