{
  "type": "Feature",
  "properties": {
    "name": "Lavumisa",
    "country": "SZ",
    "subdivision": "04",
    "timezone": "Africa/Mbabane"
  },
  "geometry": {
    "type": "Point",
    "coordinates": [
      31.89198,
      -27.31005
    ]
  }
}