{
  "type": "Feature",
  "properties": {
    "name": "Nhlangano",
    "country": "SZ",
    "subdivision": "04",
    "timezone": "Africa/Mbabane"
  },
  "geometry": {
    "type": "Point",
    "coordinates": [
      31.19833,
      -27.11222
    ]
  }
}