{
  "type": "Feature",
  "properties": {
    "name": "Avenches",
    "country": "CH",
    "subdivision": "VD",
    "timezone": "Europe/Zurich"
  },
  "geometry": {
    "type": "Point",
    "coordinates": [
      7.04071,
      46.88004
    ]
  }
}