{
  "type": "Feature",
  "properties": {
    "name": "Begnins",
    "country": "CH",
    "subdivision": "VD",
    "timezone": "Europe/Zurich"
  },
  "geometry": {
    "type": "Point",
    "coordinates": [
      6.24762,
      46.44152
    ]
  }
}