{
  "type": "Feature",
  "properties": {
    "name": "Chavannes",
    "country": "CH",
    "subdivision": "VD",
    "timezone": "Europe/Zurich"
  },
  "geometry": {
    "type": "Point",
    "coordinates": [
      6.57068,
      46.53005
    ]
  }
}