{
  "type": "Feature",
  "properties": {
    "name": "Coppet",
    "country": "CH",
    "subdivision": "VD",
    "timezone": "Europe/Zurich"
  },
  "geometry": {
    "type": "Point",
    "coordinates": [
      6.19114,
      46.31682
    ]
  }
}