{
  "type": "Feature",
  "properties": {
    "name": "Froideville",
    "country": "CH",
    "subdivision": "VD",
    "timezone": "Europe/Zurich"
  },
  "geometry": {
    "type": "Point",
    "coordinates": [
      6.68085,
      46.60123
    ]
  }
}