{
  "type": "Feature",
  "properties": {
    "name": "Gimel",
    "country": "CH",
    "subdivision": "VD",
    "timezone": "Europe/Zurich"
  },
  "geometry": {
    "type": "Point",
    "coordinates": [
      6.30736,
      46.50945
    ]
  }
}