{
  "type": "Feature",
  "properties": {
    "name": "Grandson",
    "country": "CH",
    "subdivision": "VD",
    "timezone": "Europe/Zurich"
  },
  "geometry": {
    "type": "Point",
    "coordinates": [
      6.646,
      46.80946
    ]
  }
}