{
  "type": "Feature",
  "properties": {
    "name": "Leysin",
    "country": "CH",
    "subdivision": "VD",
    "timezone": "Europe/Zurich"
  },
  "geometry": {
    "type": "Point",
    "coordinates": [
      7.01151,
      46.34183
    ]
  }
}