{
  "type": "Feature",
  "properties": {
    "name": "Morges",
    "country": "CH",
    "subdivision": "VD",
    "timezone": "Europe/Zurich"
  },
  "geometry": {
    "type": "Point",
    "coordinates": [
      6.49854,
      46.51127
    ]
  }
}