{
  "type": "Feature",
  "properties": {
    "name": "Oron-la-Ville",
    "country": "CH",
    "subdivision": "VD",
    "timezone": "Europe/Zurich"
  },
  "geometry": {
    "type": "Point",
    "coordinates": [
      6.82557,
      46.57094
    ]
  }
}