{
  "type": "Feature",
  "properties": {
    "name": "Puidoux",
    "country": "CH",
    "subdivision": "VD",
    "timezone": "Europe/Zurich"
  },
  "geometry": {
    "type": "Point",
    "coordinates": [
      6.78249,
      46.50093
    ]
  }
}