{
  "type": "Feature",
  "properties": {
    "name": "Yvonand",
    "country": "CH",
    "subdivision": "VD",
    "timezone": "Europe/Zurich"
  },
  "geometry": {
    "type": "Point",
    "coordinates": [
      6.74249,
      46.80034
    ]
  }
}