{
  "type": "Feature",
  "properties": {
    "name": "Langtang",
    "country": "NG",
    "subdivision": "49",
    "timezone": "Africa/Lagos"
  },
  "geometry": {
    "type": "Point",
    "coordinates": [
      9.79101,
      9.14164
    ]
  }
}