{
  "type": "Feature",
  "properties": {
    "name": "Jamao al Norte",
    "country": "DO",
    "subdivision": "08",
    "timezone": "America/Santo_Domingo"
  },
  "geometry": {
    "type": "Point",
    "coordinates": [
      -70.44664,
      19.63552
    ]
  }
}