{
  "type": "Feature",
  "properties": {
    "name": "Saedinenie",
    "country": "BG",
    "subdivision": "51",
    "timezone": "Europe/Sofia"
  },
  "geometry": {
    "type": "Point",
    "coordinates": [
      24.55,
      42.26667
    ]
  }
}