{
  "type": "Feature",
  "properties": {
    "name": "Stamboliyski",
    "country": "BG",
    "subdivision": "51",
    "timezone": "Europe/Sofia"
  },
  "geometry": {
    "type": "Point",
    "coordinates": [
      24.53333,
      42.13333
    ]
  }
}