{
  "type": "Feature",
  "properties": {
    "name": "Batsari",
    "country": "NG",
    "subdivision": "24",
    "timezone": "Africa/Lagos"
  },
  "geometry": {
    "type": "Point",
    "coordinates": [
      7.24809,
      12.75551
    ]
  }
}