{
  "type": "Feature",
  "properties": {
    "name": "Daura",
    "country": "NG",
    "subdivision": "24",
    "timezone": "Africa/Lagos"
  },
  "geometry": {
    "type": "Point",
    "coordinates": [
      8.32351,
      13.03299
    ]
  }
}