{
  "type": "Feature",
  "properties": {
    "name": "Jibia",
    "country": "NG",
    "subdivision": "24",
    "timezone": "Africa/Lagos"
  },
  "geometry": {
    "type": "Point",
    "coordinates": [
      7.22624,
      13.09378
    ]
  }
}