{
  "type": "Feature",
  "properties": {
    "name": "Musawa",
    "country": "NG",
    "subdivision": "24",
    "timezone": "Africa/Lagos"
  },
  "geometry": {
    "type": "Point",
    "coordinates": [
      7.67023,
      12.12949
    ]
  }
}