{
  "type": "Feature",
  "properties": {
    "name": "Arniston",
    "country": "ZA",
    "subdivision": "11",
    "timezone": "Africa/Johannesburg"
  },
  "geometry": {
    "type": "Point",
    "coordinates": [
      20.23086,
      -34.66739
    ]
  }
}