{
  "type": "Feature",
  "properties": {
    "name": "Calitzdorp",
    "country": "ZA",
    "subdivision": "11",
    "timezone": "Africa/Johannesburg"
  },
  "geometry": {
    "type": "Point",
    "coordinates": [
      21.6762,
      -33.52755
    ]
  }
}