{
  "type": "Feature",
  "properties": {
    "name": "Hermanus",
    "country": "ZA",
    "subdivision": "11",
    "timezone": "Africa/Johannesburg"
  },
  "geometry": {
    "type": "Point",
    "coordinates": [
      19.23446,
      -34.4187
    ]
  }
}