{
  "type": "Feature",
  "properties": {
    "name": "Newlands",
    "country": "ZA",
    "subdivision": "11",
    "timezone": "Africa/Johannesburg"
  },
  "geometry": {
    "type": "Point",
    "coordinates": [
      18.4481,
      -33.97846
    ]
  }
}