{
  "type": "Feature",
  "properties": {
    "name": "Saldanha",
    "country": "ZA",
    "subdivision": "11",
    "timezone": "Africa/Johannesburg"
  },
  "geometry": {
    "type": "Point",
    "coordinates": [
      17.9442,
      -33.01167
    ]
  }
}