{
  "type": "Feature",
  "properties": {
    "name": "Kiukainen",
    "country": "FI",
    "subdivision": "04",
    "timezone": "Europe/Helsinki"
  },
  "geometry": {
    "type": "Point",
    "coordinates": [
      22.08333,
      61.21667
    ]
  }
}