{
  "type": "Feature",
  "properties": {
    "name": "Câmara de Lobos",
    "country": "PT",
    "subdivision": "10",
    "timezone": "Atlantic/Madeira"
  },
  "geometry": {
    "type": "Point",
    "coordinates": [
      -16.97718,
      32.65043
    ]
  }
}