{
  "type": "Feature",
  "properties": {
    "name": "Porto Moniz",
    "country": "PT",
    "subdivision": "10",
    "timezone": "Atlantic/Madeira"
  },
  "geometry": {
    "type": "Point",
    "coordinates": [
      -17.16667,
      32.86681
    ]
  }
}