{
  "type": "Feature",
  "properties": {
    "name": "Ruse",
    "country": "BG",
    "subdivision": "53",
    "timezone": "Europe/Sofia"
  },
  "geometry": {
    "type": "Point",
    "coordinates": [
      25.9534,
      43.84872
    ]
  }
}