{
  "type": "Feature",
  "properties": {
    "name": "Senovo",
    "country": "BG",
    "subdivision": "53",
    "timezone": "Europe/Sofia"
  },
  "geometry": {
    "type": "Point",
    "coordinates": [
      26.36667,
      43.65
    ]
  }
}