{
  "type": "Feature",
  "properties": {
    "name": "Hukuntsi",
    "country": "BW",
    "subdivision": "04",
    "timezone": "Africa/Gaborone"
  },
  "geometry": {
    "type": "Point",
    "coordinates": [
      21.77962,
      -23.9988
    ]
  }
}