{
  "type": "Feature",
  "properties": {
    "name": "Sadjoavato",
    "country": "MG",
    "subdivision": "71",
    "timezone": "Indian/Antananarivo"
  },
  "geometry": {
    "type": "Point",
    "coordinates": [
      49.35,
      -12.61667
    ]
  }
}