{
  "type": "Feature",
  "properties": {
    "name": "Choyr",
    "country": "MN",
    "subdivision": "24",
    "timezone": "Asia/Ulaanbaatar"
  },
  "geometry": {
    "type": "Point",
    "coordinates": [
      108.36111,
      46.36111
    ]
  }
}