{
  "type": "Feature",
  "properties": {
    "name": "Staicele",
    "country": "LV",
    "subdivision": "39",
    "timezone": "Europe/Riga"
  },
  "geometry": {
    "type": "Point",
    "coordinates": [
      24.74706,
      57.83579
    ]
  }
}