{
  "type": "Feature",
  "properties": {
    "name": "Jisr ez Zarqā",
    "country": "IL",
    "subdivision": "04",
    "timezone": "Asia/Jerusalem"
  },
  "geometry": {
    "type": "Point",
    "coordinates": [
      34.9127,
      32.53684
    ]
  }
}