{
  "type": "Feature",
  "properties": {
    "name": "Sdot Yam",
    "country": "IL",
    "subdivision": "04",
    "timezone": "Asia/Jerusalem"
  },
  "geometry": {
    "type": "Point",
    "coordinates": [
      34.89224,
      32.49213
    ]
  }
}