{
  "type": "Feature",
  "properties": {
    "name": "Zikhron Ya‘aqov",
    "country": "IL",
    "subdivision": "04",
    "timezone": "Asia/Jerusalem"
  },
  "geometry": {
    "type": "Point",
    "coordinates": [
      34.95628,
      32.56645
    ]
  }
}