{
  "type": "Feature",
  "properties": {
    "name": "Alatri",
    "country": "IT",
    "subdivision": "07",
    "timezone": "Europe/Rome"
  },
  "geometry": {
    "type": "Point",
    "coordinates": [
      13.3412,
      41.73187
    ]
  }
}