{
  "type": "Feature",
  "properties": {
    "name": "Anagni",
    "country": "IT",
    "subdivision": "07",
    "timezone": "Europe/Rome"
  },
  "geometry": {
    "type": "Point",
    "coordinates": [
      13.15542,
      41.7435
    ]
  }
}