{
  "type": "Feature",
  "properties": {
    "name": "Anzio",
    "country": "IT",
    "subdivision": "07",
    "timezone": "Europe/Rome"
  },
  "geometry": {
    "type": "Point",
    "coordinates": [
      12.62157,
      41.45263
    ]
  }
}