{
  "type": "Feature",
  "properties": {
    "name": "Arce",
    "country": "IT",
    "subdivision": "07",
    "timezone": "Europe/Rome"
  },
  "geometry": {
    "type": "Point",
    "coordinates": [
      13.58571,
      41.57787
    ]
  }
}