{
  "type": "Feature",
  "properties": {
    "name": "Borgo Lotti",
    "country": "IT",
    "subdivision": "07",
    "timezone": "Europe/Rome"
  },
  "geometry": {
    "type": "Point",
    "coordinates": [
      12.555,
      41.76414
    ]
  }
}