{
  "type": "Feature",
  "properties": {
    "name": "Canale Monterano",
    "country": "IT",
    "subdivision": "07",
    "timezone": "Europe/Rome"
  },
  "geometry": {
    "type": "Point",
    "coordinates": [
      12.10284,
      42.13598
    ]
  }
}