{
  "type": "Feature",
  "properties": {
    "name": "Capranica",
    "country": "IT",
    "subdivision": "07",
    "timezone": "Europe/Rome"
  },
  "geometry": {
    "type": "Point",
    "coordinates": [
      12.17278,
      42.25849
    ]
  }
}