{
  "type": "Feature",
  "properties": {
    "name": "Casal de' Pazzi",
    "country": "IT",
    "subdivision": "07",
    "timezone": "Europe/Rome"
  },
  "geometry": {
    "type": "Point",
    "coordinates": [
      12.56582,
      41.92884
    ]
  }
}