{
  "type": "Feature",
  "properties": {
    "name": "Castel Madama",
    "country": "IT",
    "subdivision": "07",
    "timezone": "Europe/Rome"
  },
  "geometry": {
    "type": "Point",
    "coordinates": [
      12.86782,
      41.9735
    ]
  }
}