{
  "type": "Feature",
  "properties": {
    "name": "Castel Chiodato",
    "country": "IT",
    "subdivision": "07",
    "timezone": "Europe/Rome"
  },
  "geometry": {
    "type": "Point",
    "coordinates": [
      12.69764,
      42.05617
    ]
  }
}