{
  "type": "Feature",
  "properties": {
    "name": "Cerquotti-Madonna del Piano",
    "country": "IT",
    "subdivision": "07",
    "timezone": "Europe/Rome"
  },
  "geometry": {
    "type": "Point",
    "coordinates": [
      13.21316,
      41.64194
    ]
  }
}