{
  "type": "Feature",
  "properties": {
    "name": "Colleverde II",
    "country": "IT",
    "subdivision": "07",
    "timezone": "Europe/Rome"
  },
  "geometry": {
    "type": "Point",
    "coordinates": [
      12.63191,
      41.97533
    ]
  }
}