{
  "type": "Feature",
  "properties": {
    "name": "Corvaro",
    "country": "IT",
    "subdivision": "07",
    "timezone": "Europe/Rome"
  },
  "geometry": {
    "type": "Point",
    "coordinates": [
      13.26496,
      42.20538
    ]
  }
}