{
  "type": "Feature",
  "properties": {
    "name": "Isola del Liri",
    "country": "IT",
    "subdivision": "07",
    "timezone": "Europe/Rome"
  },
  "geometry": {
    "type": "Point",
    "coordinates": [
      13.59679,
      41.68678
    ]
  }
}