{
  "type": "Feature",
  "properties": {
    "name": "Itri",
    "country": "IT",
    "subdivision": "07",
    "timezone": "Europe/Rome"
  },
  "geometry": {
    "type": "Point",
    "coordinates": [
      13.53,
      41.29034
    ]
  }
}