{
  "type": "Feature",
  "properties": {
    "name": "La Massimina-Casal Lumbroso",
    "country": "IT",
    "subdivision": "07",
    "timezone": "Europe/Rome"
  },
  "geometry": {
    "type": "Point",
    "coordinates": [
      12.35694,
      41.87332
    ]
  }
}