{
  "type": "Feature",
  "properties": {
    "name": "Lariano",
    "country": "IT",
    "subdivision": "07",
    "timezone": "Europe/Rome"
  },
  "geometry": {
    "type": "Point",
    "coordinates": [
      12.82868,
      41.71847
    ]
  }
}