{
  "type": "Feature",
  "properties": {
    "name": "Marco Simone",
    "country": "IT",
    "subdivision": "07",
    "timezone": "Europe/Rome"
  },
  "geometry": {
    "type": "Point",
    "coordinates": [
      12.64775,
      41.95544
    ]
  }
}