{
  "type": "Feature",
  "properties": {
    "name": "Marcellina",
    "country": "IT",
    "subdivision": "07",
    "timezone": "Europe/Rome"
  },
  "geometry": {
    "type": "Point",
    "coordinates": [
      12.80445,
      42.02436
    ]
  }
}