{
  "type": "Feature",
  "properties": {
    "name": "Marina di Cerveteri",
    "country": "IT",
    "subdivision": "07",
    "timezone": "Europe/Rome"
  },
  "geometry": {
    "type": "Point",
    "coordinates": [
      12.05295,
      41.97997
    ]
  }
}