{
  "type": "Feature",
  "properties": {
    "name": "Minturno",
    "country": "IT",
    "subdivision": "07",
    "timezone": "Europe/Rome"
  },
  "geometry": {
    "type": "Point",
    "coordinates": [
      13.74583,
      41.26294
    ]
  }
}