{
  "type": "Feature",
  "properties": {
    "name": "Montelanico",
    "country": "IT",
    "subdivision": "07",
    "timezone": "Europe/Rome"
  },
  "geometry": {
    "type": "Point",
    "coordinates": [
      13.04027,
      41.65069
    ]
  }
}