{
  "type": "Feature",
  "properties": {
    "name": "Nazzano",
    "country": "IT",
    "subdivision": "07",
    "timezone": "Europe/Rome"
  },
  "geometry": {
    "type": "Point",
    "coordinates": [
      12.5944,
      42.23018
    ]
  }
}