{
  "type": "Feature",
  "properties": {
    "name": "Olevano Romano",
    "country": "IT",
    "subdivision": "07",
    "timezone": "Europe/Rome"
  },
  "geometry": {
    "type": "Point",
    "coordinates": [
      13.03601,
      41.85869
    ]
  }
}