{
  "type": "Feature",
  "properties": {
    "name": "Pavona",
    "country": "IT",
    "subdivision": "07",
    "timezone": "Europe/Rome"
  },
  "geometry": {
    "type": "Point",
    "coordinates": [
      12.61642,
      41.72629
    ]
  }
}