{
  "type": "Feature",
  "properties": {
    "name": "Piedimonte San Germano",
    "country": "IT",
    "subdivision": "07",
    "timezone": "Europe/Rome"
  },
  "geometry": {
    "type": "Point",
    "coordinates": [
      13.75017,
      41.49796
    ]
  }
}