{
  "type": "Feature",
  "properties": {
    "name": "Poggio Mirteto",
    "country": "IT",
    "subdivision": "07",
    "timezone": "Europe/Rome"
  },
  "geometry": {
    "type": "Point",
    "coordinates": [
      12.68837,
      42.26763
    ]
  }
}