{
  "type": "Feature",
  "properties": {
    "name": "Prato di Coppola",
    "country": "IT",
    "subdivision": "07",
    "timezone": "Europe/Rome"
  },
  "geometry": {
    "type": "Point",
    "coordinates": [
      12.88157,
      41.4175
    ]
  }
}