{
  "type": "Feature",
  "properties": {
    "name": "Regolelli",
    "country": "IT",
    "subdivision": "07",
    "timezone": "Europe/Rome"
  },
  "geometry": {
    "type": "Point",
    "coordinates": [
      12.35131,
      42.29315
    ]
  }
}