{
  "type": "Feature",
  "properties": {
    "name": "Rocca Priora",
    "country": "IT",
    "subdivision": "07",
    "timezone": "Europe/Rome"
  },
  "geometry": {
    "type": "Point",
    "coordinates": [
      12.76577,
      41.76585
    ]
  }
}