{
  "type": "Feature",
  "properties": {
    "name": "San Giovanni-Patoni",
    "country": "IT",
    "subdivision": "07",
    "timezone": "Europe/Rome"
  },
  "geometry": {
    "type": "Point",
    "coordinates": [
      13.2751,
      41.77223
    ]
  }
}