{
  "type": "Feature",
  "properties": {
    "name": "Segni",
    "country": "IT",
    "subdivision": "07",
    "timezone": "Europe/Rome"
  },
  "geometry": {
    "type": "Point",
    "coordinates": [
      13.01934,
      41.68893
    ]
  }
}