{
  "type": "Feature",
  "properties": {
    "name": "Terracina",
    "country": "IT",
    "subdivision": "07",
    "timezone": "Europe/Rome"
  },
  "geometry": {
    "type": "Point",
    "coordinates": [
      13.24359,
      41.29174
    ]
  }
}