{
  "type": "Feature",
  "properties": {
    "name": "Torvaianica",
    "country": "IT",
    "subdivision": "07",
    "timezone": "Europe/Rome"
  },
  "geometry": {
    "type": "Point",
    "coordinates": [
      12.46197,
      41.62112
    ]
  }
}