{
  "type": "Feature",
  "properties": {
    "name": "Vetralla",
    "country": "IT",
    "subdivision": "07",
    "timezone": "Europe/Rome"
  },
  "geometry": {
    "type": "Point",
    "coordinates": [
      12.07323,
      42.31787
    ]
  }
}