{
  "type": "Feature",
  "properties": {
    "name": "Zagarolo",
    "country": "IT",
    "subdivision": "07",
    "timezone": "Europe/Rome"
  },
  "geometry": {
    "type": "Point",
    "coordinates": [
      12.8154,
      41.84159
    ]
  }
}