{
  "type": "Feature",
  "properties": {
    "name": "Saint David’s",
    "country": "GD",
    "subdivision": "02",
    "timezone": "America/Grenada"
  },
  "geometry": {
    "type": "Point",
    "coordinates": [
      -61.66875,
      12.04903
    ]
  }
}