{
  "type": "Feature",
  "properties": {
    "name": "Salé Al Jadida",
    "country": "MA",
    "subdivision": "04",
    "timezone": "Africa/Casablanca"
  },
  "geometry": {
    "type": "Point",
    "coordinates": [
      -6.74047,
      33.99722
    ]
  }
}