{
  "type": "Feature",
  "properties": {
    "name": "Skhirate",
    "country": "MA",
    "subdivision": "04",
    "timezone": "Africa/Casablanca"
  },
  "geometry": {
    "type": "Point",
    "coordinates": [
      -7.03171,
      33.8527
    ]
  }
}