{
  "type": "Feature",
  "properties": {
    "name": "Souq Larb’a al Gharb",
    "country": "MA",
    "subdivision": "04",
    "timezone": "Africa/Casablanca"
  },
  "geometry": {
    "type": "Point",
    "coordinates": [
      -6.00272,
      34.68664
    ]
  }
}