{
  "type": "Feature",
  "properties": {
    "name": "Yangambi",
    "country": "CD",
    "subdivision": "30",
    "timezone": "Africa/Lubumbashi"
  },
  "geometry": {
    "type": "Point",
    "coordinates": [
      24.43973,
      0.76755
    ]
  }
}