{
  "type": "Feature",
  "properties": {
    "name": "Alchevsk",
    "country": "UA",
    "subdivision": "14",
    "timezone": "Europe/Zaporozhye"
  },
  "geometry": {
    "type": "Point",
    "coordinates": [
      38.81669,
      48.46893
    ]
  }
}