{
  "type": "Feature",
  "properties": {
    "name": "Antratsyt",
    "country": "UA",
    "subdivision": "14",
    "timezone": "Europe/Zaporozhye"
  },
  "geometry": {
    "type": "Point",
    "coordinates": [
      39.09128,
      48.11503
    ]
  }
}