{
  "type": "Feature",
  "properties": {
    "name": "Artemivsk",
    "country": "UA",
    "subdivision": "14",
    "timezone": "Europe/Zaporozhye"
  },
  "geometry": {
    "type": "Point",
    "coordinates": [
      38.732,
      48.44061
    ]
  }
}