{
  "type": "Feature",
  "properties": {
    "name": "Buran",
    "country": "UA",
    "subdivision": "14",
    "timezone": "Europe/Zaporozhye"
  },
  "geometry": {
    "type": "Point",
    "coordinates": [
      39.61526,
      48.30003
    ]
  }
}