{
  "type": "Feature",
  "properties": {
    "name": "Kamiane",
    "country": "UA",
    "subdivision": "14",
    "timezone": "Europe/Zaporozhye"
  },
  "geometry": {
    "type": "Point",
    "coordinates": [
      39.16537,
      48.16829
    ]
  }
}