{
  "type": "Feature",
  "properties": {
    "name": "Klenovyi",
    "country": "UA",
    "subdivision": "14",
    "timezone": "Europe/Zaporozhye"
  },
  "geometry": {
    "type": "Point",
    "coordinates": [
      39.4588,
      48.11934
    ]
  }
}