{
  "type": "Feature",
  "properties": {
    "name": "Novopskov",
    "country": "UA",
    "subdivision": "14",
    "timezone": "Europe/Zaporozhye"
  },
  "geometry": {
    "type": "Point",
    "coordinates": [
      39.08987,
      49.5464
    ]
  }
}