{
  "type": "Feature",
  "properties": {
    "name": "Sievierodonetsk",
    "country": "UA",
    "subdivision": "14",
    "timezone": "Europe/Zaporozhye"
  },
  "geometry": {
    "type": "Point",
    "coordinates": [
      38.49166,
      48.94832
    ]
  }
}