{
  "type": "Feature",
  "properties": {
    "name": "Sorokyne",
    "country": "UA",
    "subdivision": "14",
    "timezone": "Europe/Zaporozhye"
  },
  "geometry": {
    "type": "Point",
    "coordinates": [
      39.73921,
      48.29235
    ]
  }
}