{
  "type": "Feature",
  "properties": {
    "name": "Starobilsk",
    "country": "UA",
    "subdivision": "14",
    "timezone": "Europe/Zaporozhye"
  },
  "geometry": {
    "type": "Point",
    "coordinates": [
      38.91069,
      49.27832
    ]
  }
}