{
  "type": "Feature",
  "properties": {
    "name": "Kotel",
    "country": "BG",
    "subdivision": "56",
    "timezone": "Europe/Sofia"
  },
  "geometry": {
    "type": "Point",
    "coordinates": [
      26.45,
      42.88333
    ]
  }
}