{
  "type": "Feature",
  "properties": {
    "name": "Sliven",
    "country": "BG",
    "subdivision": "56",
    "timezone": "Europe/Sofia"
  },
  "geometry": {
    "type": "Point",
    "coordinates": [
      26.32917,
      42.68583
    ]
  }
}