{
  "type": "Feature",
  "properties": {
    "name": "Reitoca",
    "country": "HN",
    "subdivision": "08",
    "timezone": "America/Tegucigalpa"
  },
  "geometry": {
    "type": "Point",
    "coordinates": [
      -87.46528,
      13.82583
    ]
  }
}