{
  "type": "Feature",
  "properties": {
    "name": "Sabanagrande",
    "country": "HN",
    "subdivision": "08",
    "timezone": "America/Tegucigalpa"
  },
  "geometry": {
    "type": "Point",
    "coordinates": [
      -87.25917,
      13.80778
    ]
  }
}