{
  "type": "Feature",
  "properties": {
    "name": "Villa de San Francisco",
    "country": "HN",
    "subdivision": "08",
    "timezone": "America/Tegucigalpa"
  },
  "geometry": {
    "type": "Point",
    "coordinates": [
      -86.96667,
      14.16667
    ]
  }
}