{
  "type": "Feature",
  "properties": {
    "name": "Zasip",
    "country": "SI",
    "subdivision": "03",
    "timezone": "Europe/Ljubljana"
  },
  "geometry": {
    "type": "Point",
    "coordinates": [
      14.10869,
      46.39284
    ]
  }
}