{
  "type": "Feature",
  "properties": {
    "name": "Chust",
    "country": "UZ",
    "subdivision": "06",
    "timezone": "Asia/Tashkent"
  },
  "geometry": {
    "type": "Point",
    "coordinates": [
      71.23791,
      41.00329
    ]
  }
}