{
  "type": "Feature",
  "properties": {
    "name": "Haqqulobod",
    "country": "UZ",
    "subdivision": "06",
    "timezone": "Asia/Tashkent"
  },
  "geometry": {
    "type": "Point",
    "coordinates": [
      72.11667,
      40.91667
    ]
  }
}