{
  "type": "Feature",
  "properties": {
    "name": "Hämeenkyrö",
    "country": "FI",
    "subdivision": "06",
    "timezone": "Europe/Helsinki"
  },
  "geometry": {
    "type": "Point",
    "coordinates": [
      23.19531,
      61.63913
    ]
  }
}