{
  "type": "Feature",
  "properties": {
    "name": "Kylmäkoski",
    "country": "FI",
    "subdivision": "06",
    "timezone": "Europe/Helsinki"
  },
  "geometry": {
    "type": "Point",
    "coordinates": [
      23.68858,
      61.154
    ]
  }
}