{
  "type": "Feature",
  "properties": {
    "name": "Valkeakoski",
    "country": "FI",
    "subdivision": "06",
    "timezone": "Europe/Helsinki"
  },
  "geometry": {
    "type": "Point",
    "coordinates": [
      24.03122,
      61.26421
    ]
  }
}