{
  "type": "Feature",
  "properties": {
    "name": "Vilppula",
    "country": "FI",
    "subdivision": "06",
    "timezone": "Europe/Helsinki"
  },
  "geometry": {
    "type": "Point",
    "coordinates": [
      24.50483,
      62.02121
    ]
  }
}