{
  "type": "Feature",
  "properties": {
    "name": "Adolfo Ruiz Cortines",
    "country": "MX",
    "subdivision": "25",
    "timezone": "America/Mazatlan"
  },
  "geometry": {
    "type": "Point",
    "coordinates": [
      -108.71975,
      25.70275
    ]
  }
}