{
  "type": "Feature",
  "properties": {
    "name": "Baburia",
    "country": "MX",
    "subdivision": "25",
    "timezone": "America/Mazatlan"
  },
  "geometry": {
    "type": "Point",
    "coordinates": [
      -108.20276,
      25.84289
    ]
  }
}