{
  "type": "Feature",
  "properties": {
    "name": "Bachoco",
    "country": "MX",
    "subdivision": "25",
    "timezone": "America/Mazatlan"
  },
  "geometry": {
    "type": "Point",
    "coordinates": [
      -108.81437,
      25.69687
    ]
  }
}