{
  "type": "Feature",
  "properties": {
    "name": "Bacubirito",
    "country": "MX",
    "subdivision": "25",
    "timezone": "America/Mazatlan"
  },
  "geometry": {
    "type": "Point",
    "coordinates": [
      -107.915,
      25.80944
    ]
  }
}