{
  "type": "Feature",
  "properties": {
    "name": "Caimanero",
    "country": "MX",
    "subdivision": "25",
    "timezone": "America/Mazatlan"
  },
  "geometry": {
    "type": "Point",
    "coordinates": [
      -108.44247,
      25.60564
    ]
  }
}