{
  "type": "Feature",
  "properties": {
    "name": "Colonia 24 de Febrero",
    "country": "MX",
    "subdivision": "25",
    "timezone": "America/Mazatlan"
  },
  "geometry": {
    "type": "Point",
    "coordinates": [
      -108.64917,
      25.64722
    ]
  }
}