{
  "type": "Feature",
  "properties": {
    "name": "Cosalá",
    "country": "MX",
    "subdivision": "25",
    "timezone": "America/Mazatlan"
  },
  "geometry": {
    "type": "Point",
    "coordinates": [
      -106.69073,
      24.41501
    ]
  }
}