{
  "type": "Feature",
  "properties": {
    "name": "Cruz Blanca",
    "country": "MX",
    "subdivision": "25",
    "timezone": "America/Mazatlan"
  },
  "geometry": {
    "type": "Point",
    "coordinates": [
      -108.3709,
      25.6746
    ]
  }
}