{
  "type": "Feature",
  "properties": {
    "name": "El Castillo",
    "country": "MX",
    "subdivision": "25",
    "timezone": "America/Mazatlan"
  },
  "geometry": {
    "type": "Point",
    "coordinates": [
      -106.33909,
      23.19542
    ]
  }
}