{
  "type": "Feature",
  "properties": {
    "name": "El Huajote",
    "country": "MX",
    "subdivision": "25",
    "timezone": "America/Mazatlan"
  },
  "geometry": {
    "type": "Point",
    "coordinates": [
      -106.05889,
      23.12889
    ]
  }
}