{
  "type": "Feature",
  "properties": {
    "name": "El Potrero de Sataya",
    "country": "MX",
    "subdivision": "25",
    "timezone": "America/Mazatlan"
  },
  "geometry": {
    "type": "Point",
    "coordinates": [
      -107.70917,
      24.69
    ]
  }
}