{
  "type": "Feature",
  "properties": {
    "name": "El Roble",
    "country": "MX",
    "subdivision": "25",
    "timezone": "America/Mazatlan"
  },
  "geometry": {
    "type": "Point",
    "coordinates": [
      -106.20583,
      23.24556
    ]
  }
}