{
  "type": "Feature",
  "properties": {
    "name": "El Walamo",
    "country": "MX",
    "subdivision": "25",
    "timezone": "America/Mazatlan"
  },
  "geometry": {
    "type": "Point",
    "coordinates": [
      -106.245,
      23.14009
    ]
  }
}