{
  "type": "Feature",
  "properties": {
    "name": "Estación Chimaneco",
    "country": "MX",
    "subdivision": "25",
    "timezone": "America/Mazatlan"
  },
  "geometry": {
    "type": "Point",
    "coordinates": [
      -107.74913,
      24.9543
    ]
  }
}