{
  "type": "Feature",
  "properties": {
    "name": "Flor Azul",
    "country": "MX",
    "subdivision": "25",
    "timezone": "America/Mazatlan"
  },
  "geometry": {
    "type": "Point",
    "coordinates": [
      -109.00839,
      25.86987
    ]
  }
}