{
  "type": "Feature",
  "properties": {
    "name": "Gustavo Díaz Ordaz",
    "country": "MX",
    "subdivision": "25",
    "timezone": "America/Mazatlan"
  },
  "geometry": {
    "type": "Point",
    "coordinates": [
      -108.09486,
      25.26692
    ]
  }
}