{
  "type": "Feature",
  "properties": {
    "name": "Higuera de Zaragoza",
    "country": "MX",
    "subdivision": "25",
    "timezone": "America/Mazatlan"
  },
  "geometry": {
    "type": "Point",
    "coordinates": [
      -109.3042,
      25.96892
    ]
  }
}