{
  "type": "Feature",
  "properties": {
    "name": "Isla del Bosque",
    "country": "MX",
    "subdivision": "25",
    "timezone": "America/Mazatlan"
  },
  "geometry": {
    "type": "Point",
    "coordinates": [
      -105.84556,
      22.73306
    ]
  }
}