{
  "type": "Feature",
  "properties": {
    "name": "Juan Aldama (El Tigre)",
    "country": "MX",
    "subdivision": "25",
    "timezone": "America/Mazatlan"
  },
  "geometry": {
    "type": "Point",
    "coordinates": [
      -107.82083,
      24.93972
    ]
  }
}