{
  "type": "Feature",
  "properties": {
    "name": "Juan José Ríos",
    "country": "MX",
    "subdivision": "25",
    "timezone": "America/Mazatlan"
  },
  "geometry": {
    "type": "Point",
    "coordinates": [
      -108.8242,
      25.75781
    ]
  }
}