{
  "type": "Feature",
  "properties": {
    "name": "La Despensa",
    "country": "MX",
    "subdivision": "25",
    "timezone": "America/Mazatlan"
  },
  "geometry": {
    "type": "Point",
    "coordinates": [
      -109.27274,
      25.99137
    ]
  }
}