{
  "type": "Feature",
  "properties": {
    "name": "La Palmita y Anexos (La Presita)",
    "country": "MX",
    "subdivision": "25",
    "timezone": "America/Mazatlan"
  },
  "geometry": {
    "type": "Point",
    "coordinates": [
      -107.45194,
      24.90917
    ]
  }
}