{
  "type": "Feature",
  "properties": {
    "name": "La Trinidad",
    "country": "MX",
    "subdivision": "25",
    "timezone": "America/Mazatlan"
  },
  "geometry": {
    "type": "Point",
    "coordinates": [
      -108.48409,
      25.73367
    ]
  }
}