{
  "type": "Feature",
  "properties": {
    "name": "Las Quemazones",
    "country": "MX",
    "subdivision": "25",
    "timezone": "America/Mazatlan"
  },
  "geometry": {
    "type": "Point",
    "coordinates": [
      -108.45243,
      25.68583
    ]
  }
}