{
  "type": "Feature",
  "properties": {
    "name": "Mochis",
    "country": "MX",
    "subdivision": "25",
    "timezone": "America/Mazatlan"
  },
  "geometry": {
    "type": "Point",
    "coordinates": [
      -109.0512,
      25.8272
    ]
  }
}