{
  "type": "Feature",
  "properties": {
    "name": "Nuevo San Miguel",
    "country": "MX",
    "subdivision": "25",
    "timezone": "America/Mazatlan"
  },
  "geometry": {
    "type": "Point",
    "coordinates": [
      -109.05401,
      25.96306
    ]
  }
}