{
  "type": "Feature",
  "properties": {
    "name": "Portaceli",
    "country": "MX",
    "subdivision": "25",
    "timezone": "America/Mazatlan"
  },
  "geometry": {
    "type": "Point",
    "coordinates": [
      -107.30594,
      24.34809
    ]
  }
}