{
  "type": "Feature",
  "properties": {
    "name": "San Rafael",
    "country": "MX",
    "subdivision": "25",
    "timezone": "America/Mazatlan"
  },
  "geometry": {
    "type": "Point",
    "coordinates": [
      -108.30527,
      25.4939
    ]
  }
}