{
  "type": "Feature",
  "properties": {
    "name": "Sinaloa de Leyva",
    "country": "MX",
    "subdivision": "25",
    "timezone": "America/Mazatlan"
  },
  "geometry": {
    "type": "Point",
    "coordinates": [
      -108.22261,
      25.8219
    ]
  }
}