{
  "type": "Feature",
  "properties": {
    "name": "Topolobampo",
    "country": "MX",
    "subdivision": "25",
    "timezone": "America/Mazatlan"
  },
  "geometry": {
    "type": "Point",
    "coordinates": [
      -109.0523,
      25.60084
    ]
  }
}