{
  "type": "Feature",
  "properties": {
    "name": "Villa Unión",
    "country": "MX",
    "subdivision": "25",
    "timezone": "America/Mazatlan"
  },
  "geometry": {
    "type": "Point",
    "coordinates": [
      -106.21947,
      23.18992
    ]
  }
}