{
  "type": "Feature",
  "properties": {
    "name": "Cluny",
    "country": "MU",
    "subdivision": "14",
    "timezone": "Indian/Mauritius"
  },
  "geometry": {
    "type": "Point",
    "coordinates": [
      57.60389,
      -20.36694
    ]
  }
}