{
  "type": "Feature",
  "properties": {
    "name": "Santa Cruz De Succhabamba",
    "country": "PE",
    "subdivision": "06",
    "timezone": "America/Lima"
  },
  "geometry": {
    "type": "Point",
    "coordinates": [
      -78.94576,
      -6.62501
    ]
  }
}