{
  "type": "Feature",
  "properties": {
    "name": "Băbeni",
    "country": "RO",
    "subdivision": "39",
    "timezone": "Europe/Bucharest"
  },
  "geometry": {
    "type": "Point",
    "coordinates": [
      24.23333,
      44.96667
    ]
  }
}