{
  "type": "Feature",
  "properties": {
    "name": "Băile Govora",
    "country": "RO",
    "subdivision": "39",
    "timezone": "Europe/Bucharest"
  },
  "geometry": {
    "type": "Point",
    "coordinates": [
      24.18333,
      45.08333
    ]
  }
}