{
  "type": "Feature",
  "properties": {
    "name": "Dăeşti",
    "country": "RO",
    "subdivision": "39",
    "timezone": "Europe/Bucharest"
  },
  "geometry": {
    "type": "Point",
    "coordinates": [
      24.13333,
      44.96667
    ]
  }
}