{
  "type": "Feature",
  "properties": {
    "name": "Guşoeni",
    "country": "RO",
    "subdivision": "39",
    "timezone": "Europe/Bucharest"
  },
  "geometry": {
    "type": "Point",
    "coordinates": [
      24.11667,
      44.73333
    ]
  }
}