{
  "type": "Feature",
  "properties": {
    "name": "Oveselu",
    "country": "RO",
    "subdivision": "39",
    "timezone": "Europe/Bucharest"
  },
  "geometry": {
    "type": "Point",
    "coordinates": [
      24.01667,
      44.75
    ]
  }
}