{
  "type": "Feature",
  "properties": {
    "name": "Racoviţa",
    "country": "RO",
    "subdivision": "39",
    "timezone": "Europe/Bucharest"
  },
  "geometry": {
    "type": "Point",
    "coordinates": [
      24.31667,
      45.41667
    ]
  }
}