{
  "type": "Feature",
  "properties": {
    "name": "Esquipulas Palo Gordo",
    "country": "GT",
    "subdivision": "17",
    "timezone": "America/Guatemala"
  },
  "geometry": {
    "type": "Point",
    "coordinates": [
      -91.82564,
      14.94135
    ]
  }
}