{
  "type": "Feature",
  "properties": {
    "name": "Malacatán",
    "country": "GT",
    "subdivision": "17",
    "timezone": "America/Guatemala"
  },
  "geometry": {
    "type": "Point",
    "coordinates": [
      -92.05788,
      14.91132
    ]
  }
}