{
  "type": "Feature",
  "properties": {
    "name": "Nuevo Progreso",
    "country": "GT",
    "subdivision": "17",
    "timezone": "America/Guatemala"
  },
  "geometry": {
    "type": "Point",
    "coordinates": [
      -91.91946,
      14.79174
    ]
  }
}