{
  "type": "Feature",
  "properties": {
    "name": "San Miguel Ixtahuacán",
    "country": "GT",
    "subdivision": "17",
    "timezone": "America/Guatemala"
  },
  "geometry": {
    "type": "Point",
    "coordinates": [
      -91.74785,
      15.27247
    ]
  }
}