{
  "type": "Feature",
  "properties": {
    "name": "Araluen",
    "country": "AU",
    "subdivision": "03",
    "timezone": "Australia/Darwin"
  },
  "geometry": {
    "type": "Point",
    "coordinates": [
      133.854,
      -23.69601
    ]
  }
}