{
  "type": "Feature",
  "properties": {
    "name": "Bakewell",
    "country": "AU",
    "subdivision": "03",
    "timezone": "Australia/Darwin"
  },
  "geometry": {
    "type": "Point",
    "coordinates": [
      130.99344,
      -12.49684
    ]
  }
}