{
  "type": "Feature",
  "properties": {
    "name": "Braitling",
    "country": "AU",
    "subdivision": "03",
    "timezone": "Australia/Darwin"
  },
  "geometry": {
    "type": "Point",
    "coordinates": [
      133.86877,
      -23.68005
    ]
  }
}