{
  "type": "Feature",
  "properties": {
    "name": "Gray",
    "country": "AU",
    "subdivision": "03",
    "timezone": "Australia/Darwin"
  },
  "geometry": {
    "type": "Point",
    "coordinates": [
      130.98228,
      -12.49036
    ]
  }
}