{
  "type": "Feature",
  "properties": {
    "name": "Jingili",
    "country": "AU",
    "subdivision": "03",
    "timezone": "Australia/Darwin"
  },
  "geometry": {
    "type": "Point",
    "coordinates": [
      130.87281,
      -12.38895
    ]
  }
}