{
  "type": "Feature",
  "properties": {
    "name": "Marrara",
    "country": "AU",
    "subdivision": "03",
    "timezone": "Australia/Darwin"
  },
  "geometry": {
    "type": "Point",
    "coordinates": [
      130.8929,
      -12.40041
    ]
  }
}