{
  "type": "Feature",
  "properties": {
    "name": "Rapid Creek",
    "country": "AU",
    "subdivision": "03",
    "timezone": "Australia/Darwin"
  },
  "geometry": {
    "type": "Point",
    "coordinates": [
      130.85919,
      -12.38042
    ]
  }
}