{
  "type": "Feature",
  "properties": {
    "name": "Rosebery",
    "country": "AU",
    "subdivision": "03",
    "timezone": "Australia/Darwin"
  },
  "geometry": {
    "type": "Point",
    "coordinates": [
      130.9878,
      -12.51046
    ]
  }
}