{
  "type": "Feature",
  "properties": {
    "name": "Wadeye",
    "country": "AU",
    "subdivision": "03",
    "timezone": "Australia/Darwin"
  },
  "geometry": {
    "type": "Point",
    "coordinates": [
      129.52177,
      -14.23834
    ]
  }
}