{
  "type": "Feature",
  "properties": {
    "name": "Wurrumiyanga",
    "country": "AU",
    "subdivision": "03",
    "timezone": "Australia/Darwin"
  },
  "geometry": {
    "type": "Point",
    "coordinates": [
      130.62555,
      -11.76082
    ]
  }
}