{
  "type": "Feature",
  "properties": {
    "name": "Yulara",
    "country": "AU",
    "subdivision": "03",
    "timezone": "Australia/Darwin"
  },
  "geometry": {
    "type": "Point",
    "coordinates": [
      130.9889,
      -25.2406
    ]
  }
}