{
  "type": "Feature",
  "properties": {
    "name": "Zuccoli",
    "country": "AU",
    "subdivision": "03",
    "timezone": "Australia/Darwin"
  },
  "geometry": {
    "type": "Point",
    "coordinates": [
      131.00694,
      -12.50727
    ]
  }
}