{
  "type": "Feature",
  "properties": {
    "name": "Argavand",
    "country": "AM",
    "subdivision": "11",
    "timezone": "Asia/Yerevan"
  },
  "geometry": {
    "type": "Point",
    "coordinates": [
      44.4389,
      40.15289
    ]
  }
}