{
  "type": "Feature",
  "properties": {
    "name": "Kanáli",
    "country": "GR",
    "subdivision": "ESYE22",
    "timezone": "Europe/Athens"
  },
  "geometry": {
    "type": "Point",
    "coordinates": [
      19.8925,
      39.60556
    ]
  }
}