{
  "type": "Feature",
  "properties": {
    "name": "Mouzaki",
    "country": "GR",
    "subdivision": "ESYE22",
    "timezone": "Europe/Athens"
  },
  "geometry": {
    "type": "Point",
    "coordinates": [
      20.82291,
      37.73565
    ]
  }
}