{
  "type": "Feature",
  "properties": {
    "name": "Perama",
    "country": "GR",
    "subdivision": "ESYE22",
    "timezone": "Europe/Athens"
  },
  "geometry": {
    "type": "Point",
    "coordinates": [
      19.9122,
      39.58289
    ]
  }
}