{
  "type": "Feature",
  "properties": {
    "name": "Birżebbuġa",
    "country": "MT",
    "subdivision": "05",
    "timezone": "Europe/Malta"
  },
  "geometry": {
    "type": "Point",
    "coordinates": [
      14.52694,
      35.82583
    ]
  }
}