{
  "type": "Feature",
  "properties": {
    "name": "Bagumbayan",
    "country": "PH",
    "subdivision": "05",
    "timezone": "Asia/Manila"
  },
  "geometry": {
    "type": "Point",
    "coordinates": [
      123.66667,
      13.45
    ]
  }
}