{
  "type": "Feature",
  "properties": {
    "name": "Baleno",
    "country": "PH",
    "subdivision": "05",
    "timezone": "Asia/Manila"
  },
  "geometry": {
    "type": "Point",
    "coordinates": [
      123.4982,
      12.4739
    ]
  }
}