{
  "type": "Feature",
  "properties": {
    "name": "Balud",
    "country": "PH",
    "subdivision": "05",
    "timezone": "Asia/Manila"
  },
  "geometry": {
    "type": "Point",
    "coordinates": [
      123.19351,
      12.03686
    ]
  }
}