{
  "type": "Feature",
  "properties": {
    "name": "Batobalane",
    "country": "PH",
    "subdivision": "05",
    "timezone": "Asia/Manila"
  },
  "geometry": {
    "type": "Point",
    "coordinates": [
      122.75,
      14.23333
    ]
  }
}