{
  "type": "Feature",
  "properties": {
    "name": "Bombon",
    "country": "PH",
    "subdivision": "05",
    "timezone": "Asia/Manila"
  },
  "geometry": {
    "type": "Point",
    "coordinates": [
      123.2077,
      13.6887
    ]
  }
}