{
  "type": "Feature",
  "properties": {
    "name": "Bulusan",
    "country": "PH",
    "subdivision": "05",
    "timezone": "Asia/Manila"
  },
  "geometry": {
    "type": "Point",
    "coordinates": [
      124.12087,
      12.74936
    ]
  }
}