{
  "type": "Feature",
  "properties": {
    "name": "Cabusao",
    "country": "PH",
    "subdivision": "05",
    "timezone": "Asia/Manila"
  },
  "geometry": {
    "type": "Point",
    "coordinates": [
      123.1169,
      13.7227
    ]
  }
}