{
  "type": "Feature",
  "properties": {
    "name": "Cabugao",
    "country": "PH",
    "subdivision": "05",
    "timezone": "Asia/Manila"
  },
  "geometry": {
    "type": "Point",
    "coordinates": [
      124.2804,
      13.5962
    ]
  }
}