{
  "type": "Feature",
  "properties": {
    "name": "Castillo",
    "country": "PH",
    "subdivision": "05",
    "timezone": "Asia/Manila"
  },
  "geometry": {
    "type": "Point",
    "coordinates": [
      123.1166,
      13.7313
    ]
  }
}