{
  "type": "Feature",
  "properties": {
    "name": "Culacling",
    "country": "PH",
    "subdivision": "05",
    "timezone": "Asia/Manila"
  },
  "geometry": {
    "type": "Point",
    "coordinates": [
      122.8767,
      13.7815
    ]
  }
}