{
  "type": "Feature",
  "properties": {
    "name": "Daet",
    "country": "PH",
    "subdivision": "05",
    "timezone": "Asia/Manila"
  },
  "geometry": {
    "type": "Point",
    "coordinates": [
      122.9553,
      14.1122
    ]
  }
}