{
  "type": "Feature",
  "properties": {
    "name": "Dimasalang",
    "country": "PH",
    "subdivision": "05",
    "timezone": "Asia/Manila"
  },
  "geometry": {
    "type": "Point",
    "coordinates": [
      123.8592,
      12.1923
    ]
  }
}