{
  "type": "Feature",
  "properties": {
    "name": "Gigmoto",
    "country": "PH",
    "subdivision": "05",
    "timezone": "Asia/Manila"
  },
  "geometry": {
    "type": "Point",
    "coordinates": [
      124.39,
      13.7796
    ]
  }
}