{
  "type": "Feature",
  "properties": {
    "name": "Guijalo",
    "country": "PH",
    "subdivision": "05",
    "timezone": "Asia/Manila"
  },
  "geometry": {
    "type": "Point",
    "coordinates": [
      123.868,
      13.7373
    ]
  }
}