{
  "type": "Feature",
  "properties": {
    "name": "Herrera",
    "country": "PH",
    "subdivision": "05",
    "timezone": "Asia/Manila"
  },
  "geometry": {
    "type": "Point",
    "coordinates": [
      123.5769,
      13.2693
    ]
  }
}