{
  "type": "Feature",
  "properties": {
    "name": "Labo",
    "country": "PH",
    "subdivision": "05",
    "timezone": "Asia/Manila"
  },
  "geometry": {
    "type": "Point",
    "coordinates": [
      122.8303,
      14.1532
    ]
  }
}