{
  "type": "Feature",
  "properties": {
    "name": "Lacag",
    "country": "PH",
    "subdivision": "05",
    "timezone": "Asia/Manila"
  },
  "geometry": {
    "type": "Point",
    "coordinates": [
      123.6812,
      13.1553
    ]
  }
}