{
  "type": "Feature",
  "properties": {
    "name": "Magarao",
    "country": "PH",
    "subdivision": "05",
    "timezone": "Asia/Manila"
  },
  "geometry": {
    "type": "Point",
    "coordinates": [
      123.1869,
      13.6604
    ]
  }
}