{
  "type": "Feature",
  "properties": {
    "name": "Maonon",
    "country": "PH",
    "subdivision": "05",
    "timezone": "Asia/Manila"
  },
  "geometry": {
    "type": "Point",
    "coordinates": [
      123.37074,
      13.03643
    ]
  }
}