{
  "type": "Feature",
  "properties": {
    "name": "Marintoc",
    "country": "PH",
    "subdivision": "05",
    "timezone": "Asia/Manila"
  },
  "geometry": {
    "type": "Point",
    "coordinates": [
      123.72281,
      12.28554
    ]
  }
}