{
  "type": "Feature",
  "properties": {
    "name": "Mauraro",
    "country": "PH",
    "subdivision": "05",
    "timezone": "Asia/Manila"
  },
  "geometry": {
    "type": "Point",
    "coordinates": [
      123.5953,
      13.1494
    ]
  }
}