{
  "type": "Feature",
  "properties": {
    "name": "Miliroc",
    "country": "PH",
    "subdivision": "05",
    "timezone": "Asia/Manila"
  },
  "geometry": {
    "type": "Point",
    "coordinates": [
      123.702,
      13.3449
    ]
  }
}