{
  "type": "Feature",
  "properties": {
    "name": "Monbon",
    "country": "PH",
    "subdivision": "05",
    "timezone": "Asia/Manila"
  },
  "geometry": {
    "type": "Point",
    "coordinates": [
      124.0189,
      12.7307
    ]
  }
}