{
  "type": "Feature",
  "properties": {
    "name": "Naagas",
    "country": "PH",
    "subdivision": "05",
    "timezone": "Asia/Manila"
  },
  "geometry": {
    "type": "Point",
    "coordinates": [
      123.6781,
      13.4357
    ]
  }
}