{
  "type": "Feature",
  "properties": {
    "name": "Paulba",
    "country": "PH",
    "subdivision": "05",
    "timezone": "Asia/Manila"
  },
  "geometry": {
    "type": "Point",
    "coordinates": [
      123.46252,
      13.17875
    ]
  }
}