{
  "type": "Feature",
  "properties": {
    "name": "Putiao",
    "country": "PH",
    "subdivision": "05",
    "timezone": "Asia/Manila"
  },
  "geometry": {
    "type": "Point",
    "coordinates": [
      123.7148,
      13.0195
    ]
  }
}