{
  "type": "Feature",
  "properties": {
    "name": "Sabang",
    "country": "PH",
    "subdivision": "05",
    "timezone": "Asia/Manila"
  },
  "geometry": {
    "type": "Point",
    "coordinates": [
      123.5781,
      13.7218
    ]
  }
}