{
  "type": "Feature",
  "properties": {
    "name": "Sagrada Familia",
    "country": "PH",
    "subdivision": "05",
    "timezone": "Asia/Manila"
  },
  "geometry": {
    "type": "Point",
    "coordinates": [
      123.3977,
      13.269
    ]
  }
}