{
  "type": "Feature",
  "properties": {
    "name": "San Francisco",
    "country": "PH",
    "subdivision": "05",
    "timezone": "Asia/Manila"
  },
  "geometry": {
    "type": "Point",
    "coordinates": [
      123.75,
      13.31667
    ]
  }
}