{
  "type": "Feature",
  "properties": {
    "name": "San Antonio",
    "country": "PH",
    "subdivision": "05",
    "timezone": "Asia/Manila"
  },
  "geometry": {
    "type": "Point",
    "coordinates": [
      123.4202,
      13.371
    ]
  }
}