{
  "type": "Feature",
  "properties": {
    "name": "San Sebastian",
    "country": "PH",
    "subdivision": "05",
    "timezone": "Asia/Manila"
  },
  "geometry": {
    "type": "Point",
    "coordinates": [
      123.5939,
      13.7283
    ]
  }
}