{
  "type": "Feature",
  "properties": {
    "name": "Sipocot",
    "country": "PH",
    "subdivision": "05",
    "timezone": "Asia/Manila"
  },
  "geometry": {
    "type": "Point",
    "coordinates": [
      122.9762,
      13.768
    ]
  }
}