{
  "type": "Feature",
  "properties": {
    "name": "Talisay",
    "country": "PH",
    "subdivision": "05",
    "timezone": "Asia/Manila"
  },
  "geometry": {
    "type": "Point",
    "coordinates": [
      122.9226,
      14.1343
    ]
  }
}