{
  "type": "Feature",
  "properties": {
    "name": "Tumalaytay",
    "country": "PH",
    "subdivision": "05",
    "timezone": "Asia/Manila"
  },
  "geometry": {
    "type": "Point",
    "coordinates": [
      123.23201,
      12.27584
    ]
  }
}