{
  "type": "Feature",
  "properties": {
    "name": "Viga",
    "country": "PH",
    "subdivision": "05",
    "timezone": "Asia/Manila"
  },
  "geometry": {
    "type": "Point",
    "coordinates": [
      124.3091,
      13.8719
    ]
  }
}