{
  "type": "Feature",
  "properties": {
    "name": "Virac",
    "country": "PH",
    "subdivision": "05",
    "timezone": "Asia/Manila"
  },
  "geometry": {
    "type": "Point",
    "coordinates": [
      124.2374,
      13.5848
    ]
  }
}