{
  "type": "Feature",
  "properties": {
    "name": "Blama",
    "country": "SL",
    "subdivision": "01",
    "timezone": "Africa/Freetown"
  },
  "geometry": {
    "type": "Point",
    "coordinates": [
      -11.34548,
      7.87481
    ]
  }
}