{
  "type": "Feature",
  "properties": {
    "name": "Manowa",
    "country": "SL",
    "subdivision": "01",
    "timezone": "Africa/Freetown"
  },
  "geometry": {
    "type": "Point",
    "coordinates": [
      -10.74834,
      8.17392
    ]
  }
}