{
  "type": "Feature",
  "properties": {
    "name": "Panguma",
    "country": "SL",
    "subdivision": "01",
    "timezone": "Africa/Freetown"
  },
  "geometry": {
    "type": "Point",
    "coordinates": [
      -11.1329,
      8.18507
    ]
  }
}