{
  "type": "Feature",
  "properties": {
    "name": "Tombodu",
    "country": "SL",
    "subdivision": "01",
    "timezone": "Africa/Freetown"
  },
  "geometry": {
    "type": "Point",
    "coordinates": [
      -10.6196,
      8.13526
    ]
  }
}