{
  "type": "Feature",
  "properties": {
    "name": "Wima",
    "country": "SL",
    "subdivision": "01",
    "timezone": "Africa/Freetown"
  },
  "geometry": {
    "type": "Point",
    "coordinates": [
      -11.20455,
      8.30052
    ]
  }
}