{
  "type": "Feature",
  "properties": {
    "name": "Kaindy",
    "country": "KG",
    "subdivision": "02",
    "timezone": "Asia/Bishkek"
  },
  "geometry": {
    "type": "Point",
    "coordinates": [
      73.67585,
      42.82469
    ]
  }
}