{
  "type": "Feature",
  "properties": {
    "name": "Kokopo",
    "country": "PG",
    "subdivision": "10",
    "timezone": "Pacific/Port_Moresby"
  },
  "geometry": {
    "type": "Point",
    "coordinates": [
      152.26867,
      -4.3432
    ]
  }
}