{
  "type": "Feature",
  "properties": {
    "name": "Rabaul",
    "country": "PG",
    "subdivision": "10",
    "timezone": "Pacific/Port_Moresby"
  },
  "geometry": {
    "type": "Point",
    "coordinates": [
      152.16297,
      -4.20037
    ]
  }
}