{
  "type": "Feature",
  "properties": {
    "name": "Acquaviva",
    "country": "IT",
    "subdivision": "16",
    "timezone": "Europe/Rome"
  },
  "geometry": {
    "type": "Point",
    "coordinates": [
      11.86249,
      43.11566
    ]
  }
}