{
  "type": "Feature",
  "properties": {
    "name": "Anchione",
    "country": "IT",
    "subdivision": "16",
    "timezone": "Europe/Rome"
  },
  "geometry": {
    "type": "Point",
    "coordinates": [
      10.75844,
      43.82612
    ]
  }
}