{
  "type": "Feature",
  "properties": {
    "name": "Aulla",
    "country": "IT",
    "subdivision": "16",
    "timezone": "Europe/Rome"
  },
  "geometry": {
    "type": "Point",
    "coordinates": [
      9.97853,
      44.20632
    ]
  }
}