{
  "type": "Feature",
  "properties": {
    "name": "Bientina",
    "country": "IT",
    "subdivision": "16",
    "timezone": "Europe/Rome"
  },
  "geometry": {
    "type": "Point",
    "coordinates": [
      10.62116,
      43.70826
    ]
  }
}