{
  "type": "Feature",
  "properties": {
    "name": "Buti",
    "country": "IT",
    "subdivision": "16",
    "timezone": "Europe/Rome"
  },
  "geometry": {
    "type": "Point",
    "coordinates": [
      10.5845,
      43.72857
    ]
  }
}