{
  "type": "Feature",
  "properties": {
    "name": "Capannori",
    "country": "IT",
    "subdivision": "16",
    "timezone": "Europe/Rome"
  },
  "geometry": {
    "type": "Point",
    "coordinates": [
      10.57271,
      43.84171
    ]
  }
}