{
  "type": "Feature",
  "properties": {
    "name": "Capolona",
    "country": "IT",
    "subdivision": "16",
    "timezone": "Europe/Rome"
  },
  "geometry": {
    "type": "Point",
    "coordinates": [
      11.86374,
      43.56685
    ]
  }
}