{
  "type": "Feature",
  "properties": {
    "name": "Carrara",
    "country": "IT",
    "subdivision": "16",
    "timezone": "Europe/Rome"
  },
  "geometry": {
    "type": "Point",
    "coordinates": [
      10.09789,
      44.07926
    ]
  }
}