{
  "type": "Feature",
  "properties": {
    "name": "Cascina",
    "country": "IT",
    "subdivision": "16",
    "timezone": "Europe/Rome"
  },
  "geometry": {
    "type": "Point",
    "coordinates": [
      10.55494,
      43.67557
    ]
  }
}