{
  "type": "Feature",
  "properties": {
    "name": "Casciana Terme",
    "country": "IT",
    "subdivision": "16",
    "timezone": "Europe/Rome"
  },
  "geometry": {
    "type": "Point",
    "coordinates": [
      10.61812,
      43.52668
    ]
  }
}