{
  "type": "Feature",
  "properties": {
    "name": "Dicomano",
    "country": "IT",
    "subdivision": "16",
    "timezone": "Europe/Rome"
  },
  "geometry": {
    "type": "Point",
    "coordinates": [
      11.52182,
      43.89267
    ]
  }
}