{
  "type": "Feature",
  "properties": {
    "name": "Fornacelle",
    "country": "IT",
    "subdivision": "16",
    "timezone": "Europe/Rome"
  },
  "geometry": {
    "type": "Point",
    "coordinates": [
      11.03525,
      43.92377
    ]
  }
}