{
  "type": "Feature",
  "properties": {
    "name": "Luco Mugello",
    "country": "IT",
    "subdivision": "16",
    "timezone": "Europe/Rome"
  },
  "geometry": {
    "type": "Point",
    "coordinates": [
      11.39611,
      44.00032
    ]
  }
}