{
  "type": "Feature",
  "properties": {
    "name": "Marciana Marina",
    "country": "IT",
    "subdivision": "16",
    "timezone": "Europe/Rome"
  },
  "geometry": {
    "type": "Point",
    "coordinates": [
      10.19488,
      42.80256
    ]
  }
}