{
  "type": "Feature",
  "properties": {
    "name": "Margine Coperta-Traversagna",
    "country": "IT",
    "subdivision": "16",
    "timezone": "Europe/Rome"
  },
  "geometry": {
    "type": "Point",
    "coordinates": [
      10.75733,
      43.87977
    ]
  }
}