{
  "type": "Feature",
  "properties": {
    "name": "Marina di Carrara",
    "country": "IT",
    "subdivision": "16",
    "timezone": "Europe/Rome"
  },
  "geometry": {
    "type": "Point",
    "coordinates": [
      10.04142,
      44.03837
    ]
  }
}