{
  "type": "Feature",
  "properties": {
    "name": "Marradi",
    "country": "IT",
    "subdivision": "16",
    "timezone": "Europe/Rome"
  },
  "geometry": {
    "type": "Point",
    "coordinates": [
      11.61092,
      44.07353
    ]
  }
}