{
  "type": "Feature",
  "properties": {
    "name": "Molino del Piano",
    "country": "IT",
    "subdivision": "16",
    "timezone": "Europe/Rome"
  },
  "geometry": {
    "type": "Point",
    "coordinates": [
      11.39992,
      43.81098
    ]
  }
}