{
  "type": "Feature",
  "properties": {
    "name": "Montepulciano Stazione",
    "country": "IT",
    "subdivision": "16",
    "timezone": "Europe/Rome"
  },
  "geometry": {
    "type": "Point",
    "coordinates": [
      11.85545,
      43.1352
    ]
  }
}