{
  "type": "Feature",
  "properties": {
    "name": "Piano di Conca",
    "country": "IT",
    "subdivision": "16",
    "timezone": "Europe/Rome"
  },
  "geometry": {
    "type": "Point",
    "coordinates": [
      10.29493,
      43.89413
    ]
  }
}