{
  "type": "Feature",
  "properties": {
    "name": "Piancastagnaio",
    "country": "IT",
    "subdivision": "16",
    "timezone": "Europe/Rome"
  },
  "geometry": {
    "type": "Point",
    "coordinates": [
      11.69014,
      42.85067
    ]
  }
}