{
  "type": "Feature",
  "properties": {
    "name": "Piazza al Serchio-San Michele",
    "country": "IT",
    "subdivision": "16",
    "timezone": "Europe/Rome"
  },
  "geometry": {
    "type": "Point",
    "coordinates": [
      10.29689,
      44.18455
    ]
  }
}