{
  "type": "Feature",
  "properties": {
    "name": "Poggio A Caiano",
    "country": "IT",
    "subdivision": "16",
    "timezone": "Europe/Rome"
  },
  "geometry": {
    "type": "Point",
    "coordinates": [
      11.05186,
      43.81378
    ]
  }
}