{
  "type": "Feature",
  "properties": {
    "name": "Pomarance",
    "country": "IT",
    "subdivision": "16",
    "timezone": "Europe/Rome"
  },
  "geometry": {
    "type": "Point",
    "coordinates": [
      10.87223,
      43.29592
    ]
  }
}