{
  "type": "Feature",
  "properties": {
    "name": "Ponticino",
    "country": "IT",
    "subdivision": "16",
    "timezone": "Europe/Rome"
  },
  "geometry": {
    "type": "Point",
    "coordinates": [
      11.71622,
      43.48012
    ]
  }
}