{
  "type": "Feature",
  "properties": {
    "name": "Porcari",
    "country": "IT",
    "subdivision": "16",
    "timezone": "Europe/Rome"
  },
  "geometry": {
    "type": "Point",
    "coordinates": [
      10.61632,
      43.84152
    ]
  }
}