{
  "type": "Feature",
  "properties": {
    "name": "Pozzale-Case Nuove",
    "country": "IT",
    "subdivision": "16",
    "timezone": "Europe/Rome"
  },
  "geometry": {
    "type": "Point",
    "coordinates": [
      10.95651,
      43.69584
    ]
  }
}