{
  "type": "Feature",
  "properties": {
    "name": "Quarata",
    "country": "IT",
    "subdivision": "16",
    "timezone": "Europe/Rome"
  },
  "geometry": {
    "type": "Point",
    "coordinates": [
      11.82742,
      43.49859
    ]
  }
}