{
  "type": "Feature",
  "properties": {
    "name": "Saline",
    "country": "IT",
    "subdivision": "16",
    "timezone": "Europe/Rome"
  },
  "geometry": {
    "type": "Point",
    "coordinates": [
      10.81354,
      43.36185
    ]
  }
}