{
  "type": "Feature",
  "properties": {
    "name": "Sambuca",
    "country": "IT",
    "subdivision": "16",
    "timezone": "Europe/Rome"
  },
  "geometry": {
    "type": "Point",
    "coordinates": [
      11.21407,
      43.57344
    ]
  }
}