{
  "type": "Feature",
  "properties": {
    "name": "San Donato",
    "country": "IT",
    "subdivision": "16",
    "timezone": "Europe/Rome"
  },
  "geometry": {
    "type": "Point",
    "coordinates": [
      10.78754,
      43.70298
    ]
  }
}