{
  "type": "Feature",
  "properties": {
    "name": "San Giustino Valdarno",
    "country": "IT",
    "subdivision": "16",
    "timezone": "Europe/Rome"
  },
  "geometry": {
    "type": "Point",
    "coordinates": [
      11.70497,
      43.55269
    ]
  }
}