{
  "type": "Feature",
  "properties": {
    "name": "San Cipriano-S.Barbara-Centinale",
    "country": "IT",
    "subdivision": "16",
    "timezone": "Europe/Rome"
  },
  "geometry": {
    "type": "Point",
    "coordinates": [
      11.48467,
      43.56863
    ]
  }
}