{
  "type": "Feature",
  "properties": {
    "name": "San Vincenzo",
    "country": "IT",
    "subdivision": "16",
    "timezone": "Europe/Rome"
  },
  "geometry": {
    "type": "Point",
    "coordinates": [
      10.54246,
      43.09061
    ]
  }
}