{
  "type": "Feature",
  "properties": {
    "name": "Scarperia",
    "country": "IT",
    "subdivision": "16",
    "timezone": "Europe/Rome"
  },
  "geometry": {
    "type": "Point",
    "coordinates": [
      11.35415,
      43.99357
    ]
  }
}