{
  "type": "Feature",
  "properties": {
    "name": "Siena",
    "country": "IT",
    "subdivision": "16",
    "timezone": "Europe/Rome"
  },
  "geometry": {
    "type": "Point",
    "coordinates": [
      11.33064,
      43.31822
    ]
  }
}