{
  "type": "Feature",
  "properties": {
    "name": "Tavarnuzze",
    "country": "IT",
    "subdivision": "16",
    "timezone": "Europe/Rome"
  },
  "geometry": {
    "type": "Point",
    "coordinates": [
      11.21721,
      43.71019
    ]
  }
}