{
  "type": "Feature",
  "properties": {
    "name": "Valenzatico",
    "country": "IT",
    "subdivision": "16",
    "timezone": "Europe/Rome"
  },
  "geometry": {
    "type": "Point",
    "coordinates": [
      10.96497,
      43.8668
    ]
  }
}