{
  "type": "Feature",
  "properties": {
    "name": "Vecchiano-Nodica",
    "country": "IT",
    "subdivision": "16",
    "timezone": "Europe/Rome"
  },
  "geometry": {
    "type": "Point",
    "coordinates": [
      10.3844,
      43.78334
    ]
  }
}