{
  "type": "Feature",
  "properties": {
    "name": "Vignale Riotorto",
    "country": "IT",
    "subdivision": "16",
    "timezone": "Europe/Rome"
  },
  "geometry": {
    "type": "Point",
    "coordinates": [
      10.68471,
      42.97998
    ]
  }
}