{
  "type": "Feature",
  "properties": {
    "name": "Villafranca in Lunigiana",
    "country": "IT",
    "subdivision": "16",
    "timezone": "Europe/Rome"
  },
  "geometry": {
    "type": "Point",
    "coordinates": [
      9.95347,
      44.29844
    ]
  }
}