{
  "type": "Feature",
  "properties": {
    "name": "Hovd",
    "country": "MN",
    "subdivision": "15",
    "timezone": "Asia/Ulaanbaatar"
  },
  "geometry": {
    "type": "Point",
    "coordinates": [
      102.17491,
      44.67024
    ]
  }
}