{
  "type": "Feature",
  "properties": {
    "name": "Bouïra",
    "country": "DZ",
    "subdivision": "21",
    "timezone": "Africa/Algiers"
  },
  "geometry": {
    "type": "Point",
    "coordinates": [
      3.902,
      36.37489
    ]
  }
}