{
  "type": "Feature",
  "properties": {
    "name": "Kigoma",
    "country": "TZ",
    "subdivision": "05",
    "timezone": "Africa/Dar_es_Salaam"
  },
  "geometry": {
    "type": "Point",
    "coordinates": [
      29.62667,
      -4.87694
    ]
  }
}