{
  "type": "Feature",
  "properties": {
    "name": "Nikkō",
    "country": "JP",
    "subdivision": "38",
    "timezone": "Asia/Tokyo"
  },
  "geometry": {
    "type": "Point",
    "coordinates": [
      139.61667,
      36.75
    ]
  }
}