{
  "type": "Feature",
  "properties": {
    "name": "Ujiie",
    "country": "JP",
    "subdivision": "38",
    "timezone": "Asia/Tokyo"
  },
  "geometry": {
    "type": "Point",
    "coordinates": [
      139.96667,
      36.68333
    ]
  }
}