{
  "type": "Feature",
  "properties": {
    "name": "Municipio Hato Corozal",
    "country": "CO",
    "subdivision": "32",
    "timezone": "America/Bogota"
  },
  "geometry": {
    "type": "Point",
    "coordinates": [
      -71.76372,
      6.15676
    ]
  }
}