{
  "type": "Feature",
  "properties": {
    "name": "Orocué",
    "country": "CO",
    "subdivision": "32",
    "timezone": "America/Bogota"
  },
  "geometry": {
    "type": "Point",
    "coordinates": [
      -71.33917,
      4.79035
    ]
  }
}