{
  "type": "Feature",
  "properties": {
    "name": "Sabanalarga",
    "country": "CO",
    "subdivision": "32",
    "timezone": "America/Bogota"
  },
  "geometry": {
    "type": "Point",
    "coordinates": [
      -73.04003,
      4.8543
    ]
  }
}