{
  "type": "Feature",
  "properties": {
    "name": "Attingal",
    "country": "IN",
    "subdivision": "13",
    "timezone": "Asia/Kolkata"
  },
  "geometry": {
    "type": "Point",
    "coordinates": [
      76.81507,
      8.69609
    ]
  }
}