{
  "type": "Feature",
  "properties": {
    "name": "Avanoor",
    "country": "IN",
    "subdivision": "13",
    "timezone": "Asia/Kolkata"
  },
  "geometry": {
    "type": "Point",
    "coordinates": [
      76.1762,
      10.60826
    ]
  }
}