{
  "type": "Feature",
  "properties": {
    "name": "Edakkulam",
    "country": "IN",
    "subdivision": "13",
    "timezone": "Asia/Kolkata"
  },
  "geometry": {
    "type": "Point",
    "coordinates": [
      76.18352,
      10.6102
    ]
  }
}