{
  "type": "Feature",
  "properties": {
    "name": "Iringal",
    "country": "IN",
    "subdivision": "13",
    "timezone": "Asia/Kolkata"
  },
  "geometry": {
    "type": "Point",
    "coordinates": [
      75.61663,
      11.55929
    ]
  }
}