{
  "type": "Feature",
  "properties": {
    "name": "Kattanam",
    "country": "IN",
    "subdivision": "13",
    "timezone": "Asia/Kolkata"
  },
  "geometry": {
    "type": "Point",
    "coordinates": [
      76.56325,
      9.17614
    ]
  }
}