{
  "type": "Feature",
  "properties": {
    "name": "Mattanur",
    "country": "IN",
    "subdivision": "13",
    "timezone": "Asia/Kolkata"
  },
  "geometry": {
    "type": "Point",
    "coordinates": [
      75.57152,
      11.93018
    ]
  }
}