{
  "type": "Feature",
  "properties": {
    "name": "Muvattupuzha",
    "country": "IN",
    "subdivision": "13",
    "timezone": "Asia/Kolkata"
  },
  "geometry": {
    "type": "Point",
    "coordinates": [
      76.57381,
      9.97985
    ]
  }
}