{
  "type": "Feature",
  "properties": {
    "name": "PariyÄpuram",
    "country": "IN",
    "subdivision": "13",
    "timezone": "Asia/Kolkata"
  },
  "geometry": {
    "type": "Point",
    "coordinates": [
      75.86667,
      11.01667
    ]
  }
}