{
  "type": "Feature",
  "properties": {
    "name": "Perya",
    "country": "IN",
    "subdivision": "13",
    "timezone": "Asia/Kolkata"
  },
  "geometry": {
    "type": "Point",
    "coordinates": [
      75.85408,
      11.83334
    ]
  }
}