{
  "type": "Feature",
  "properties": {
    "name": "PonnÄni",
    "country": "IN",
    "subdivision": "13",
    "timezone": "Asia/Kolkata"
  },
  "geometry": {
    "type": "Point",
    "coordinates": [
      75.92523,
      10.76695
    ]
  }
}