{
  "type": "Feature",
  "properties": {
    "name": "Punalūr",
    "country": "IN",
    "subdivision": "13",
    "timezone": "Asia/Kolkata"
  },
  "geometry": {
    "type": "Point",
    "coordinates": [
      76.92261,
      9.01956
    ]
  }
}