{
  "type": "Feature",
  "properties": {
    "name": "Shertallai",
    "country": "IN",
    "subdivision": "13",
    "timezone": "Asia/Kolkata"
  },
  "geometry": {
    "type": "Point",
    "coordinates": [
      76.33996,
      9.68581
    ]
  }
}