{
  "type": "Feature",
  "properties": {
    "name": "Talipparamba",
    "country": "IN",
    "subdivision": "13",
    "timezone": "Asia/Kolkata"
  },
  "geometry": {
    "type": "Point",
    "coordinates": [
      75.35927,
      12.04161
    ]
  }
}