{
  "type": "Feature",
  "properties": {
    "name": "Tellicherry",
    "country": "IN",
    "subdivision": "13",
    "timezone": "Asia/Kolkata"
  },
  "geometry": {
    "type": "Point",
    "coordinates": [
      75.4929,
      11.74811
    ]
  }
}