{
  "type": "Feature",
  "properties": {
    "name": "Thiruvananthapuram",
    "country": "IN",
    "subdivision": "13",
    "timezone": "Asia/Kolkata"
  },
  "geometry": {
    "type": "Point",
    "coordinates": [
      76.94924,
      8.4855
    ]
  }
}