{
  "type": "Feature",
  "properties": {
    "name": "Cao Bằng",
    "country": "VN",
    "subdivision": "05",
    "timezone": "Asia/Bangkok"
  },
  "geometry": {
    "type": "Point",
    "coordinates": [
      106.25786,
      22.66568
    ]
  }
}