{
  "type": "Feature",
  "properties": {
    "name": "Alpu",
    "country": "TR",
    "subdivision": "26",
    "timezone": "Europe/Istanbul"
  },
  "geometry": {
    "type": "Point",
    "coordinates": [
      30.9606,
      39.76903
    ]
  }
}