{
  "type": "Feature",
  "properties": {
    "name": "Akkol’",
    "country": "KZ",
    "subdivision": "03",
    "timezone": "Asia/Almaty"
  },
  "geometry": {
    "type": "Point",
    "coordinates": [
      69.59997,
      53.29617
    ]
  }
}