{
  "type": "Feature",
  "properties": {
    "name": "Atbasar",
    "country": "KZ",
    "subdivision": "03",
    "timezone": "Asia/Almaty"
  },
  "geometry": {
    "type": "Point",
    "coordinates": [
      68.35996,
      51.80652
    ]
  }
}