{
  "type": "Feature",
  "properties": {
    "name": "Derzhavīnsk",
    "country": "KZ",
    "subdivision": "03",
    "timezone": "Asia/Almaty"
  },
  "geometry": {
    "type": "Point",
    "coordinates": [
      66.31557,
      51.09922
    ]
  }
}