{
  "type": "Feature",
  "properties": {
    "name": "Shortandy",
    "country": "KZ",
    "subdivision": "03",
    "timezone": "Asia/Almaty"
  },
  "geometry": {
    "type": "Point",
    "coordinates": [
      70.99457,
      51.69946
    ]
  }
}