{
  "type": "Feature",
  "properties": {
    "name": "Yermentau",
    "country": "KZ",
    "subdivision": "03",
    "timezone": "Asia/Almaty"
  },
  "geometry": {
    "type": "Point",
    "coordinates": [
      73.10265,
      51.62364
    ]
  }
}