{
  "type": "Feature",
  "properties": {
    "name": "El‘azar",
    "country": "IL",
    "subdivision": "06",
    "timezone": "Asia/Jerusalem"
  },
  "geometry": {
    "type": "Point",
    "coordinates": [
      35.14316,
      31.65977
    ]
  }
}