{
  "type": "Feature",
  "properties": {
    "name": "Kokhav HaShaẖar",
    "country": "IL",
    "subdivision": "06",
    "timezone": "Asia/Jerusalem"
  },
  "geometry": {
    "type": "Point",
    "coordinates": [
      35.34923,
      31.96028
    ]
  }
}