{
  "type": "Feature",
  "properties": {
    "name": "‘Amminadav",
    "country": "IL",
    "subdivision": "06",
    "timezone": "Asia/Jerusalem"
  },
  "geometry": {
    "type": "Point",
    "coordinates": [
      35.14733,
      31.75212
    ]
  }
}