{
  "type": "Feature",
  "properties": {
    "name": "‘Ein Naqūbā",
    "country": "IL",
    "subdivision": "06",
    "timezone": "Asia/Jerusalem"
  },
  "geometry": {
    "type": "Point",
    "coordinates": [
      35.12064,
      31.79366
    ]
  }
}