{
  "type": "Feature",
  "properties": {
    "name": "Shahrud",
    "country": "IR",
    "subdivision": "25",
    "timezone": "Asia/Tehran"
  },
  "geometry": {
    "type": "Point",
    "coordinates": [
      54.97628,
      36.41819
    ]
  }
}