{
  "type": "Feature",
  "properties": {
    "name": "Gifu-shi",
    "country": "JP",
    "subdivision": "09",
    "timezone": "Asia/Tokyo"
  },
  "geometry": {
    "type": "Point",
    "coordinates": [
      136.76039,
      35.42291
    ]
  }
}