{
  "type": "Feature",
  "properties": {
    "name": "Takayama",
    "country": "JP",
    "subdivision": "09",
    "timezone": "Asia/Tokyo"
  },
  "geometry": {
    "type": "Point",
    "coordinates": [
      137.25,
      36.13333
    ]
  }
}