{
  "type": "Feature",
  "properties": {
    "name": "Bet Gamli’él",
    "country": "IL",
    "subdivision": "02",
    "timezone": "Asia/Jerusalem"
  },
  "geometry": {
    "type": "Point",
    "coordinates": [
      34.76249,
      31.85555
    ]
  }
}