{
  "type": "Feature",
  "properties": {
    "name": "Bet Yehoshua‘",
    "country": "IL",
    "subdivision": "02",
    "timezone": "Asia/Jerusalem"
  },
  "geometry": {
    "type": "Point",
    "coordinates": [
      34.86414,
      32.25942
    ]
  }
}