{
  "type": "Feature",
  "properties": {
    "name": "Be’erotayim",
    "country": "IL",
    "subdivision": "02",
    "timezone": "Asia/Jerusalem"
  },
  "geometry": {
    "type": "Point",
    "coordinates": [
      34.98324,
      32.32111
    ]
  }
}