{
  "type": "Feature",
  "properties": {
    "name": "Ein Vered",
    "country": "IL",
    "subdivision": "02",
    "timezone": "Asia/Jerusalem"
  },
  "geometry": {
    "type": "Point",
    "coordinates": [
      34.93333,
      32.26667
    ]
  }
}