{
  "type": "Feature",
  "properties": {
    "name": "H̱emed",
    "country": "IL",
    "subdivision": "02",
    "timezone": "Asia/Jerusalem"
  },
  "geometry": {
    "type": "Point",
    "coordinates": [
      34.84284,
      32.0159
    ]
  }
}