{
  "type": "Feature",
  "properties": {
    "name": "Kafr Qāsim",
    "country": "IL",
    "subdivision": "02",
    "timezone": "Asia/Jerusalem"
  },
  "geometry": {
    "type": "Point",
    "coordinates": [
      34.97624,
      32.11406
    ]
  }
}