{
  "type": "Feature",
  "properties": {
    "name": "Kefar Netter",
    "country": "IL",
    "subdivision": "02",
    "timezone": "Asia/Jerusalem"
  },
  "geometry": {
    "type": "Point",
    "coordinates": [
      34.87349,
      32.273
    ]
  }
}