{
  "type": "Feature",
  "properties": {
    "name": "Kefar Bilu",
    "country": "IL",
    "subdivision": "02",
    "timezone": "Asia/Jerusalem"
  },
  "geometry": {
    "type": "Point",
    "coordinates": [
      34.82108,
      31.87702
    ]
  }
}