{
  "type": "Feature",
  "properties": {
    "name": "Kfar Hess",
    "country": "IL",
    "subdivision": "02",
    "timezone": "Asia/Jerusalem"
  },
  "geometry": {
    "type": "Point",
    "coordinates": [
      34.93562,
      32.24714
    ]
  }
}