{
  "type": "Feature",
  "properties": {
    "name": "Mazor",
    "country": "IL",
    "subdivision": "02",
    "timezone": "Asia/Jerusalem"
  },
  "geometry": {
    "type": "Point",
    "coordinates": [
      34.92291,
      32.05115
    ]
  }
}