{
  "type": "Feature",
  "properties": {
    "name": "Newé Yaraq",
    "country": "IL",
    "subdivision": "02",
    "timezone": "Asia/Jerusalem"
  },
  "geometry": {
    "type": "Point",
    "coordinates": [
      34.92447,
      32.13247
    ]
  }
}