{
  "type": "Feature",
  "properties": {
    "name": "Niẕẕané ‘Oz",
    "country": "IL",
    "subdivision": "02",
    "timezone": "Asia/Jerusalem"
  },
  "geometry": {
    "type": "Point",
    "coordinates": [
      35.00374,
      32.306
    ]
  }
}