{
  "type": "Feature",
  "properties": {
    "name": "Qiryat ‘Eqron",
    "country": "IL",
    "subdivision": "02",
    "timezone": "Asia/Jerusalem"
  },
  "geometry": {
    "type": "Point",
    "coordinates": [
      34.82275,
      31.86119
    ]
  }
}