{
  "type": "Feature",
  "properties": {
    "name": "Rishon LeẔiyyon",
    "country": "IL",
    "subdivision": "02",
    "timezone": "Asia/Jerusalem"
  },
  "geometry": {
    "type": "Point",
    "coordinates": [
      34.78939,
      31.97102
    ]
  }
}