{
  "type": "Feature",
  "properties": {
    "name": "Sde Warburg",
    "country": "IL",
    "subdivision": "02",
    "timezone": "Asia/Jerusalem"
  },
  "geometry": {
    "type": "Point",
    "coordinates": [
      34.90722,
      32.20361
    ]
  }
}