{
  "type": "Feature",
  "properties": {
    "name": "Zemer",
    "country": "IL",
    "subdivision": "02",
    "timezone": "Asia/Jerusalem"
  },
  "geometry": {
    "type": "Point",
    "coordinates": [
      35.03312,
      32.36658
    ]
  }
}