{
  "type": "Feature",
  "properties": {
    "name": "Ponta do Sol",
    "country": "CV",
    "subdivision": "07",
    "timezone": "Atlantic/Cape_Verde"
  },
  "geometry": {
    "type": "Point",
    "coordinates": [
      -25.09217,
      17.20171
    ]
  }
}