{
  "type": "Feature",
  "properties": {
    "name": "Altınekin",
    "country": "TR",
    "subdivision": "71",
    "timezone": "Europe/Istanbul"
  },
  "geometry": {
    "type": "Point",
    "coordinates": [
      32.86861,
      38.30778
    ]
  }
}