{
  "type": "Feature",
  "properties": {
    "name": "Beyşehir",
    "country": "TR",
    "subdivision": "71",
    "timezone": "Europe/Istanbul"
  },
  "geometry": {
    "type": "Point",
    "coordinates": [
      31.72458,
      37.67735
    ]
  }
}