{
  "type": "Feature",
  "properties": {
    "name": "Emirgazi",
    "country": "TR",
    "subdivision": "71",
    "timezone": "Europe/Istanbul"
  },
  "geometry": {
    "type": "Point",
    "coordinates": [
      33.83722,
      37.90222
    ]
  }
}