{
  "type": "Feature",
  "properties": {
    "name": "Yunak",
    "country": "TR",
    "subdivision": "71",
    "timezone": "Europe/Istanbul"
  },
  "geometry": {
    "type": "Point",
    "coordinates": [
      31.73223,
      38.81418
    ]
  }
}