{
  "type": "Feature",
  "properties": {
    "name": "Carrillos",
    "country": "CR",
    "subdivision": "01",
    "timezone": "America/Costa_Rica"
  },
  "geometry": {
    "type": "Point",
    "coordinates": [
      -84.27403,
      10.02918
    ]
  }
}