{
  "type": "Feature",
  "properties": {
    "name": "Desamparados",
    "country": "CR",
    "subdivision": "01",
    "timezone": "America/Costa_Rica"
  },
  "geometry": {
    "type": "Point",
    "coordinates": [
      -84.50626,
      9.94727
    ]
  }
}