{
  "type": "Feature",
  "properties": {
    "name": "Orotina",
    "country": "CR",
    "subdivision": "01",
    "timezone": "America/Costa_Rica"
  },
  "geometry": {
    "type": "Point",
    "coordinates": [
      -84.52337,
      9.91197
    ]
  }
}