{
  "type": "Feature",
  "properties": {
    "name": "Pital",
    "country": "CR",
    "subdivision": "01",
    "timezone": "America/Costa_Rica"
  },
  "geometry": {
    "type": "Point",
    "coordinates": [
      -84.27406,
      10.45056
    ]
  }
}