{
  "type": "Feature",
  "properties": {
    "name": "Sabanilla",
    "country": "CR",
    "subdivision": "01",
    "timezone": "America/Costa_Rica"
  },
  "geometry": {
    "type": "Point",
    "coordinates": [
      -84.21551,
      10.07404
    ]
  }
}