{
  "type": "Feature",
  "properties": {
    "name": "San José",
    "country": "CR",
    "subdivision": "01",
    "timezone": "America/Costa_Rica"
  },
  "geometry": {
    "type": "Point",
    "coordinates": [
      -85.1361,
      10.95173
    ]
  }
}