{
  "type": "Feature",
  "properties": {
    "name": "Kwangyang",
    "country": "KR",
    "subdivision": "16",
    "timezone": "Asia/Seoul"
  },
  "geometry": {
    "type": "Point",
    "coordinates": [
      127.58917,
      34.97528
    ]
  }
}