{
  "type": "Feature",
  "properties": {
    "name": "Camacupa",
    "country": "AO",
    "subdivision": "02",
    "timezone": "Africa/Luanda"
  },
  "geometry": {
    "type": "Point",
    "coordinates": [
      17.48333,
      -12.01667
    ]
  }
}