{
  "type": "Feature",
  "properties": {
    "name": "Catabola",
    "country": "AO",
    "subdivision": "02",
    "timezone": "Africa/Luanda"
  },
  "geometry": {
    "type": "Point",
    "coordinates": [
      17.28333,
      -12.15
    ]
  }
}