{
  "type": "Feature",
  "properties": {
    "name": "Cuito",
    "country": "AO",
    "subdivision": "02",
    "timezone": "Africa/Luanda"
  },
  "geometry": {
    "type": "Point",
    "coordinates": [
      16.93333,
      -12.38333
    ]
  }
}