{
  "type": "Feature",
  "properties": {
    "name": "Hryhoriopol",
    "country": "MD",
    "subdivision": "58",
    "timezone": "Europe/Chisinau"
  },
  "geometry": {
    "type": "Point",
    "coordinates": [
      29.30008,
      47.15413
    ]
  }
}