{
  "type": "Feature",
  "properties": {
    "name": "Pervomaisc",
    "country": "MD",
    "subdivision": "58",
    "timezone": "Europe/Chisinau"
  },
  "geometry": {
    "type": "Point",
    "coordinates": [
      29.9617,
      46.73253
    ]
  }
}