{
  "type": "Feature",
  "properties": {
    "name": "Atamyrat",
    "country": "TM",
    "subdivision": "04",
    "timezone": "Asia/Ashgabat"
  },
  "geometry": {
    "type": "Point",
    "coordinates": [
      65.21058,
      37.83573
    ]
  }
}