{
  "type": "Feature",
  "properties": {
    "name": "Balung",
    "country": "ID",
    "subdivision": "08",
    "timezone": "Asia/Jakarta"
  },
  "geometry": {
    "type": "Point",
    "coordinates": [
      113.91667,
      -7.73333
    ]
  }
}