{
  "type": "Feature",
  "properties": {
    "name": "Bangkalan",
    "country": "ID",
    "subdivision": "08",
    "timezone": "Asia/Jakarta"
  },
  "geometry": {
    "type": "Point",
    "coordinates": [
      112.7351,
      -7.0455
    ]
  }
}