{
  "type": "Feature",
  "properties": {
    "name": "Bondowoso",
    "country": "ID",
    "subdivision": "08",
    "timezone": "Asia/Jakarta"
  },
  "geometry": {
    "type": "Point",
    "coordinates": [
      113.82145,
      -7.91346
    ]
  }
}