{
  "type": "Feature",
  "properties": {
    "name": "Kencong",
    "country": "ID",
    "subdivision": "08",
    "timezone": "Asia/Jakarta"
  },
  "geometry": {
    "type": "Point",
    "coordinates": [
      113.36667,
      -8.28333
    ]
  }
}