{
  "type": "Feature",
  "properties": {
    "name": "Krian",
    "country": "ID",
    "subdivision": "08",
    "timezone": "Asia/Jakarta"
  },
  "geometry": {
    "type": "Point",
    "coordinates": [
      112.5792,
      -7.4104
    ]
  }
}