{
  "type": "Feature",
  "properties": {
    "name": "Mojoagung",
    "country": "ID",
    "subdivision": "08",
    "timezone": "Asia/Jakarta"
  },
  "geometry": {
    "type": "Point",
    "coordinates": [
      112.35,
      -7.56667
    ]
  }
}