{
  "type": "Feature",
  "properties": {
    "name": "Ponorogo",
    "country": "ID",
    "subdivision": "08",
    "timezone": "Asia/Jakarta"
  },
  "geometry": {
    "type": "Point",
    "coordinates": [
      111.462,
      -7.8685
    ]
  }
}