{
  "type": "Feature",
  "properties": {
    "name": "Soko",
    "country": "ID",
    "subdivision": "08",
    "timezone": "Asia/Jakarta"
  },
  "geometry": {
    "type": "Point",
    "coordinates": [
      112.42704,
      -7.48315
    ]
  }
}