{
  "type": "Feature",
  "properties": {
    "name": "Surabaya",
    "country": "ID",
    "subdivision": "08",
    "timezone": "Asia/Jakarta"
  },
  "geometry": {
    "type": "Point",
    "coordinates": [
      112.75083,
      -7.24917
    ]
  }
}