{
  "type": "Feature",
  "properties": {
    "name": "Lastoursville",
    "country": "GA",
    "subdivision": "07",
    "timezone": "Africa/Libreville"
  },
  "geometry": {
    "type": "Point",
    "coordinates": [
      12.70818,
      -0.81742
    ]
  }
}