{
  "type": "Feature",
  "properties": {
    "name": "Mirna",
    "country": "SI",
    "subdivision": "O6",
    "timezone": "Europe/Ljubljana"
  },
  "geometry": {
    "type": "Point",
    "coordinates": [
      15.06194,
      45.95528
    ]
  }
}