{
  "type": "Feature",
  "properties": {
    "name": "Dera Ismail Khan",
    "country": "PK",
    "subdivision": "03",
    "timezone": "Asia/Karachi"
  },
  "geometry": {
    "type": "Point",
    "coordinates": [
      70.9017,
      31.83129
    ]
  }
}