{
  "type": "Feature",
  "properties": {
    "name": "Karak",
    "country": "PK",
    "subdivision": "03",
    "timezone": "Asia/Karachi"
  },
  "geometry": {
    "type": "Point",
    "coordinates": [
      71.09354,
      33.11633
    ]
  }
}