{
  "type": "Feature",
  "properties": {
    "name": "Arisdorf",
    "country": "CH",
    "subdivision": "BL",
    "timezone": "Europe/Zurich"
  },
  "geometry": {
    "type": "Point",
    "coordinates": [
      7.76515,
      47.51323
    ]
  }
}