{
  "type": "Feature",
  "properties": {
    "name": "Diegten",
    "country": "CH",
    "subdivision": "BL",
    "timezone": "Europe/Zurich"
  },
  "geometry": {
    "type": "Point",
    "coordinates": [
      7.81085,
      47.4138
    ]
  }
}