{
  "type": "Feature",
  "properties": {
    "name": "Hölstein",
    "country": "CH",
    "subdivision": "BL",
    "timezone": "Europe/Zurich"
  },
  "geometry": {
    "type": "Point",
    "coordinates": [
      7.77041,
      47.4229
    ]
  }
}