{
  "type": "Feature",
  "properties": {
    "name": "Muttenz",
    "country": "CH",
    "subdivision": "BL",
    "timezone": "Europe/Zurich"
  },
  "geometry": {
    "type": "Point",
    "coordinates": [
      7.64511,
      47.52271
    ]
  }
}