{
  "type": "Feature",
  "properties": {
    "name": "Seltisberg",
    "country": "CH",
    "subdivision": "BL",
    "timezone": "Europe/Zurich"
  },
  "geometry": {
    "type": "Point",
    "coordinates": [
      7.72039,
      47.46249
    ]
  }
}