{
  "type": "Feature",
  "properties": {
    "name": "Wahlen",
    "country": "CH",
    "subdivision": "BL",
    "timezone": "Europe/Zurich"
  },
  "geometry": {
    "type": "Point",
    "coordinates": [
      7.51511,
      47.40226
    ]
  }
}