{
  "type": "Feature",
  "properties": {
    "name": "Waldenburg",
    "country": "CH",
    "subdivision": "BL",
    "timezone": "Europe/Zurich"
  },
  "geometry": {
    "type": "Point",
    "coordinates": [
      7.75,
      47.38333
    ]
  }
}