{
  "type": "Feature",
  "properties": {
    "name": "Dukwe",
    "country": "BW",
    "subdivision": "08",
    "timezone": "Africa/Gaborone"
  },
  "geometry": {
    "type": "Point",
    "coordinates": [
      26.41667,
      -20.58333
    ]
  }
}