{
  "type": "Feature",
  "properties": {
    "name": "Dover Base Housing",
    "country": "US",
    "subdivision": "DE",
    "timezone": "America/New_York"
  },
  "geometry": {
    "type": "Point",
    "coordinates": [
      -75.48393,
      39.11763
    ]
  }
}