{
  "type": "Feature",
  "properties": {
    "name": "Felton",
    "country": "US",
    "subdivision": "DE",
    "timezone": "America/New_York"
  },
  "geometry": {
    "type": "Point",
    "coordinates": [
      -75.57798,
      39.00845
    ]
  }
}