{
  "type": "Feature",
  "properties": {
    "name": "Greenville",
    "country": "US",
    "subdivision": "DE",
    "timezone": "America/New_York"
  },
  "geometry": {
    "type": "Point",
    "coordinates": [
      -75.59826,
      39.779
    ]
  }
}