{
  "type": "Feature",
  "properties": {
    "name": "Laurel",
    "country": "US",
    "subdivision": "DE",
    "timezone": "America/New_York"
  },
  "geometry": {
    "type": "Point",
    "coordinates": [
      -75.57131,
      38.5565
    ]
  }
}