{
  "type": "Feature",
  "properties": {
    "name": "Pike Creek",
    "country": "US",
    "subdivision": "DE",
    "timezone": "America/New_York"
  },
  "geometry": {
    "type": "Point",
    "coordinates": [
      -75.7041,
      39.73095
    ]
  }
}