{
  "type": "Feature",
  "properties": {
    "name": "Ivančna Gorica",
    "country": "SI",
    "subdivision": "39",
    "timezone": "Europe/Ljubljana"
  },
  "geometry": {
    "type": "Point",
    "coordinates": [
      14.80444,
      45.93833
    ]
  }
}