{
  "type": "Feature",
  "properties": {
    "name": "Seryshevo",
    "country": "RU",
    "subdivision": "05",
    "timezone": "Asia/Yakutsk"
  },
  "geometry": {
    "type": "Point",
    "coordinates": [
      128.38258,
      51.09391
    ]
  }
}