{
  "type": "Feature",
  "properties": {
    "name": "Skovorodino",
    "country": "RU",
    "subdivision": "05",
    "timezone": "Asia/Yakutsk"
  },
  "geometry": {
    "type": "Point",
    "coordinates": [
      123.9403,
      53.98473
    ]
  }
}