{
  "type": "Feature",
  "properties": {
    "name": "Banī Zayd",
    "country": "PS",
    "subdivision": "00",
    "timezone": "Asia/Hebron"
  },
  "geometry": {
    "type": "Point",
    "coordinates": [
      35.10316,
      32.03924
    ]
  }
}