{
  "type": "Feature",
  "properties": {
    "name": "Annot",
    "country": "FR",
    "subdivision": "93",
    "timezone": "Europe/Paris"
  },
  "geometry": {
    "type": "Point",
    "coordinates": [
      6.66879,
      43.96528
    ]
  }
}