{
  "type": "Feature",
  "properties": {
    "name": "Aubagne",
    "country": "FR",
    "subdivision": "93",
    "timezone": "Europe/Paris"
  },
  "geometry": {
    "type": "Point",
    "coordinates": [
      5.57067,
      43.29276
    ]
  }
}