{
  "type": "Feature",
  "properties": {
    "name": "Barbentane",
    "country": "FR",
    "subdivision": "93",
    "timezone": "Europe/Paris"
  },
  "geometry": {
    "type": "Point",
    "coordinates": [
      4.74756,
      43.89939
    ]
  }
}