{
  "type": "Feature",
  "properties": {
    "name": "Barjols",
    "country": "FR",
    "subdivision": "93",
    "timezone": "Europe/Paris"
  },
  "geometry": {
    "type": "Point",
    "coordinates": [
      6.00752,
      43.55805
    ]
  }
}