{
  "type": "Feature",
  "properties": {
    "name": "Bédoin",
    "country": "FR",
    "subdivision": "93",
    "timezone": "Europe/Paris"
  },
  "geometry": {
    "type": "Point",
    "coordinates": [
      5.1804,
      44.12432
    ]
  }
}