{
  "type": "Feature",
  "properties": {
    "name": "Belle de Mai",
    "country": "FR",
    "subdivision": "93",
    "timezone": "Europe/Paris"
  },
  "geometry": {
    "type": "Point",
    "coordinates": [
      5.38541,
      43.31184
    ]
  }
}