{
  "type": "Feature",
  "properties": {
    "name": "Berre-les-Alpes",
    "country": "FR",
    "subdivision": "93",
    "timezone": "Europe/Paris"
  },
  "geometry": {
    "type": "Point",
    "coordinates": [
      7.32877,
      43.83052
    ]
  }
}