{
  "type": "Feature",
  "properties": {
    "name": "Bon-Secours",
    "country": "FR",
    "subdivision": "93",
    "timezone": "Europe/Paris"
  },
  "geometry": {
    "type": "Point",
    "coordinates": [
      5.38426,
      43.31923
    ]
  }
}