{
  "type": "Feature",
  "properties": {
    "name": "Boulbon",
    "country": "FR",
    "subdivision": "93",
    "timezone": "Europe/Paris"
  },
  "geometry": {
    "type": "Point",
    "coordinates": [
      4.69391,
      43.86232
    ]
  }
}