{
  "type": "Feature",
  "properties": {
    "name": "Breil-sur-Roya",
    "country": "FR",
    "subdivision": "93",
    "timezone": "Europe/Paris"
  },
  "geometry": {
    "type": "Point",
    "coordinates": [
      7.51472,
      43.93755
    ]
  }
}