{
  "type": "Feature",
  "properties": {
    "name": "Cabannes",
    "country": "FR",
    "subdivision": "93",
    "timezone": "Europe/Paris"
  },
  "geometry": {
    "type": "Point",
    "coordinates": [
      4.95192,
      43.86015
    ]
  }
}