{
  "type": "Feature",
  "properties": {
    "name": "Châteauneuf-les-Martigues",
    "country": "FR",
    "subdivision": "93",
    "timezone": "Europe/Paris"
  },
  "geometry": {
    "type": "Point",
    "coordinates": [
      5.16403,
      43.38383
    ]
  }
}