{
  "type": "Feature",
  "properties": {
    "name": "Châteaurenard",
    "country": "FR",
    "subdivision": "93",
    "timezone": "Europe/Paris"
  },
  "geometry": {
    "type": "Point",
    "coordinates": [
      4.85493,
      43.88169
    ]
  }
}