{
  "type": "Feature",
  "properties": {
    "name": "Cogolin",
    "country": "FR",
    "subdivision": "93",
    "timezone": "Europe/Paris"
  },
  "geometry": {
    "type": "Point",
    "coordinates": [
      6.52981,
      43.25294
    ]
  }
}