{
  "type": "Feature",
  "properties": {
    "name": "Flayosc",
    "country": "FR",
    "subdivision": "93",
    "timezone": "Europe/Paris"
  },
  "geometry": {
    "type": "Point",
    "coordinates": [
      6.3966,
      43.53396
    ]
  }
}