{
  "type": "Feature",
  "properties": {
    "name": "Gémenos",
    "country": "FR",
    "subdivision": "93",
    "timezone": "Europe/Paris"
  },
  "geometry": {
    "type": "Point",
    "coordinates": [
      5.62843,
      43.29751
    ]
  }
}