{
  "type": "Feature",
  "properties": {
    "name": "Grambois",
    "country": "FR",
    "subdivision": "93",
    "timezone": "Europe/Paris"
  },
  "geometry": {
    "type": "Point",
    "coordinates": [
      5.5886,
      43.76233
    ]
  }
}