{
  "type": "Feature",
  "properties": {
    "name": "Gréasque",
    "country": "FR",
    "subdivision": "93",
    "timezone": "Europe/Paris"
  },
  "geometry": {
    "type": "Point",
    "coordinates": [
      5.54449,
      43.4331
    ]
  }
}