{
  "type": "Feature",
  "properties": {
    "name": "Jausiers",
    "country": "FR",
    "subdivision": "93",
    "timezone": "Europe/Paris"
  },
  "geometry": {
    "type": "Point",
    "coordinates": [
      6.72947,
      44.41705
    ]
  }
}