{
  "type": "Feature",
  "properties": {
    "name": "La Joliette",
    "country": "FR",
    "subdivision": "93",
    "timezone": "Europe/Paris"
  },
  "geometry": {
    "type": "Point",
    "coordinates": [
      5.36654,
      43.30485
    ]
  }
}