{
  "type": "Feature",
  "properties": {
    "name": "La Londe-les-Maures",
    "country": "FR",
    "subdivision": "93",
    "timezone": "Europe/Paris"
  },
  "geometry": {
    "type": "Point",
    "coordinates": [
      6.23362,
      43.13839
    ]
  }
}