{
  "type": "Feature",
  "properties": {
    "name": "La Roquebrussanne",
    "country": "FR",
    "subdivision": "93",
    "timezone": "Europe/Paris"
  },
  "geometry": {
    "type": "Point",
    "coordinates": [
      5.97603,
      43.3403
    ]
  }
}