{
  "type": "Feature",
  "properties": {
    "name": "Lamanon",
    "country": "FR",
    "subdivision": "93",
    "timezone": "Europe/Paris"
  },
  "geometry": {
    "type": "Point",
    "coordinates": [
      5.08871,
      43.69979
    ]
  }
}