{
  "type": "Feature",
  "properties": {
    "name": "Lançon-Provence",
    "country": "FR",
    "subdivision": "93",
    "timezone": "Europe/Paris"
  },
  "geometry": {
    "type": "Point",
    "coordinates": [
      5.12789,
      43.59266
    ]
  }
}