{
  "type": "Feature",
  "properties": {
    "name": "Le Cannet-des-Maures",
    "country": "FR",
    "subdivision": "93",
    "timezone": "Europe/Paris"
  },
  "geometry": {
    "type": "Point",
    "coordinates": [
      6.33966,
      43.39236
    ]
  }
}