{
  "type": "Feature",
  "properties": {
    "name": "Les Arnavaux",
    "country": "FR",
    "subdivision": "93",
    "timezone": "Europe/Paris"
  },
  "geometry": {
    "type": "Point",
    "coordinates": [
      5.37969,
      43.33506
    ]
  }
}