{
  "type": "Feature",
  "properties": {
    "name": "Les Crottes",
    "country": "FR",
    "subdivision": "93",
    "timezone": "Europe/Paris"
  },
  "geometry": {
    "type": "Point",
    "coordinates": [
      5.36809,
      43.32302
    ]
  }
}