{
  "type": "Feature",
  "properties": {
    "name": "Les Arcs",
    "country": "FR",
    "subdivision": "93",
    "timezone": "Europe/Paris"
  },
  "geometry": {
    "type": "Point",
    "coordinates": [
      6.47876,
      43.46328
    ]
  }
}