{
  "type": "Feature",
  "properties": {
    "name": "Maillane",
    "country": "FR",
    "subdivision": "93",
    "timezone": "Europe/Paris"
  },
  "geometry": {
    "type": "Point",
    "coordinates": [
      4.78209,
      43.83289
    ]
  }
}