{
  "type": "Feature",
  "properties": {
    "name": "Malemort-du-Comtat",
    "country": "FR",
    "subdivision": "93",
    "timezone": "Europe/Paris"
  },
  "geometry": {
    "type": "Point",
    "coordinates": [
      5.15961,
      44.02096
    ]
  }
}