{
  "type": "Feature",
  "properties": {
    "name": "Marseille 11",
    "country": "FR",
    "subdivision": "93",
    "timezone": "Europe/Paris"
  },
  "geometry": {
    "type": "Point",
    "coordinates": [
      5.4384,
      43.2907
    ]
  }
}