{
  "type": "Feature",
  "properties": {
    "name": "Marseille Saint-Victor",
    "country": "FR",
    "subdivision": "93",
    "timezone": "Europe/Paris"
  },
  "geometry": {
    "type": "Point",
    "coordinates": [
      5.36845,
      43.28955
    ]
  }
}