{
  "type": "Feature",
  "properties": {
    "name": "Marseille Prefecture",
    "country": "FR",
    "subdivision": "93",
    "timezone": "Europe/Paris"
  },
  "geometry": {
    "type": "Point",
    "coordinates": [
      5.37901,
      43.29092
    ]
  }
}