{
  "type": "Feature",
  "properties": {
    "name": "Marseille 08",
    "country": "FR",
    "subdivision": "93",
    "timezone": "Europe/Paris"
  },
  "geometry": {
    "type": "Point",
    "coordinates": [
      5.3821,
      43.27083
    ]
  }
}