{
  "type": "Feature",
  "properties": {
    "name": "Martigues",
    "country": "FR",
    "subdivision": "93",
    "timezone": "Europe/Paris"
  },
  "geometry": {
    "type": "Point",
    "coordinates": [
      5.05526,
      43.40735
    ]
  }
}