{
  "type": "Feature",
  "properties": {
    "name": "Méounes-lès-Montrieux",
    "country": "FR",
    "subdivision": "93",
    "timezone": "Europe/Paris"
  },
  "geometry": {
    "type": "Point",
    "coordinates": [
      5.96986,
      43.28102
    ]
  }
}