{
  "type": "Feature",
  "properties": {
    "name": "Miramas",
    "country": "FR",
    "subdivision": "93",
    "timezone": "Europe/Paris"
  },
  "geometry": {
    "type": "Point",
    "coordinates": [
      5.00268,
      43.58508
    ]
  }
}