{
  "type": "Feature",
  "properties": {
    "name": "Morières-lès-Avignon",
    "country": "FR",
    "subdivision": "93",
    "timezone": "Europe/Paris"
  },
  "geometry": {
    "type": "Point",
    "coordinates": [
      4.9011,
      43.9403
    ]
  }
}