{
  "type": "Feature",
  "properties": {
    "name": "Mormoiron",
    "country": "FR",
    "subdivision": "93",
    "timezone": "Europe/Paris"
  },
  "geometry": {
    "type": "Point",
    "coordinates": [
      5.18312,
      44.0681
    ]
  }
}