{
  "type": "Feature",
  "properties": {
    "name": "Mornas",
    "country": "FR",
    "subdivision": "93",
    "timezone": "Europe/Paris"
  },
  "geometry": {
    "type": "Point",
    "coordinates": [
      4.72763,
      44.20242
    ]
  }
}