{
  "type": "Feature",
  "properties": {
    "name": "Mouret",
    "country": "FR",
    "subdivision": "93",
    "timezone": "Europe/Paris"
  },
  "geometry": {
    "type": "Point",
    "coordinates": [
      5.43006,
      43.36126
    ]
  }
}