{
  "type": "Feature",
  "properties": {
    "name": "Pégomas",
    "country": "FR",
    "subdivision": "93",
    "timezone": "Europe/Paris"
  },
  "geometry": {
    "type": "Point",
    "coordinates": [
      6.93211,
      43.59662
    ]
  }
}