{
  "type": "Feature",
  "properties": {
    "name": "Peynier",
    "country": "FR",
    "subdivision": "93",
    "timezone": "Europe/Paris"
  },
  "geometry": {
    "type": "Point",
    "coordinates": [
      5.64139,
      43.44837
    ]
  }
}