{
  "type": "Feature",
  "properties": {
    "name": "Peyrolles-en-Provence",
    "country": "FR",
    "subdivision": "93",
    "timezone": "Europe/Paris"
  },
  "geometry": {
    "type": "Point",
    "coordinates": [
      5.58492,
      43.64545
    ]
  }
}