{
  "type": "Feature",
  "properties": {
    "name": "Pont de Vivaux",
    "country": "FR",
    "subdivision": "93",
    "timezone": "Europe/Paris"
  },
  "geometry": {
    "type": "Point",
    "coordinates": [
      5.41586,
      43.27604
    ]
  }
}