{
  "type": "Feature",
  "properties": {
    "name": "Puget-Théniers",
    "country": "FR",
    "subdivision": "93",
    "timezone": "Europe/Paris"
  },
  "geometry": {
    "type": "Point",
    "coordinates": [
      6.89378,
      43.95598
    ]
  }
}