{
  "type": "Feature",
  "properties": {
    "name": "Ramatuelle",
    "country": "FR",
    "subdivision": "93",
    "timezone": "Europe/Paris"
  },
  "geometry": {
    "type": "Point",
    "coordinates": [
      6.61156,
      43.21599
    ]
  }
}