{
  "type": "Feature",
  "properties": {
    "name": "Robion",
    "country": "FR",
    "subdivision": "93",
    "timezone": "Europe/Paris"
  },
  "geometry": {
    "type": "Point",
    "coordinates": [
      5.11017,
      43.84697
    ]
  }
}