{
  "type": "Feature",
  "properties": {
    "name": "Roquefort-la-Bédoule",
    "country": "FR",
    "subdivision": "93",
    "timezone": "Europe/Paris"
  },
  "geometry": {
    "type": "Point",
    "coordinates": [
      5.59015,
      43.24883
    ]
  }
}