{
  "type": "Feature",
  "properties": {
    "name": "Rougiers",
    "country": "FR",
    "subdivision": "93",
    "timezone": "Europe/Paris"
  },
  "geometry": {
    "type": "Point",
    "coordinates": [
      5.85112,
      43.39233
    ]
  }
}