{
  "type": "Feature",
  "properties": {
    "name": "Saint-Rémy-de-Provence",
    "country": "FR",
    "subdivision": "93",
    "timezone": "Europe/Paris"
  },
  "geometry": {
    "type": "Point",
    "coordinates": [
      4.83167,
      43.78848
    ]
  }
}