{
  "type": "Feature",
  "properties": {
    "name": "Saint-Étienne-du-Grès",
    "country": "FR",
    "subdivision": "93",
    "timezone": "Europe/Paris"
  },
  "geometry": {
    "type": "Point",
    "coordinates": [
      4.72534,
      43.78045
    ]
  }
}