{
  "type": "Feature",
  "properties": {
    "name": "Saint-Zacharie",
    "country": "FR",
    "subdivision": "93",
    "timezone": "Europe/Paris"
  },
  "geometry": {
    "type": "Point",
    "coordinates": [
      5.70808,
      43.38521
    ]
  }
}