{
  "type": "Feature",
  "properties": {
    "name": "Saint-Jean-Cap-Ferrat",
    "country": "FR",
    "subdivision": "93",
    "timezone": "Europe/Paris"
  },
  "geometry": {
    "type": "Point",
    "coordinates": [
      7.33361,
      43.68843
    ]
  }
}