{
  "type": "Feature",
  "properties": {
    "name": "Saint-Just",
    "country": "FR",
    "subdivision": "93",
    "timezone": "Europe/Paris"
  },
  "geometry": {
    "type": "Point",
    "coordinates": [
      5.40587,
      43.317
    ]
  }
}