{
  "type": "Feature",
  "properties": {
    "name": "Sainte-Tulle",
    "country": "FR",
    "subdivision": "93",
    "timezone": "Europe/Paris"
  },
  "geometry": {
    "type": "Point",
    "coordinates": [
      5.76513,
      43.78619
    ]
  }
}