{
  "type": "Feature",
  "properties": {
    "name": "Saint-Tropez",
    "country": "FR",
    "subdivision": "93",
    "timezone": "Europe/Paris"
  },
  "geometry": {
    "type": "Point",
    "coordinates": [
      6.64049,
      43.26764
    ]
  }
}