{
  "type": "Feature",
  "properties": {
    "name": "Saint-Lambert",
    "country": "FR",
    "subdivision": "93",
    "timezone": "Europe/Paris"
  },
  "geometry": {
    "type": "Point",
    "coordinates": [
      5.36,
      43.28606
    ]
  }
}