{
  "type": "Feature",
  "properties": {
    "name": "Saint-Henri",
    "country": "FR",
    "subdivision": "93",
    "timezone": "Europe/Paris"
  },
  "geometry": {
    "type": "Point",
    "coordinates": [
      5.33069,
      43.36151
    ]
  }
}