{
  "type": "Feature",
  "properties": {
    "name": "Saint-Michel-l'Observatoire",
    "country": "FR",
    "subdivision": "93",
    "timezone": "Europe/Paris"
  },
  "geometry": {
    "type": "Point",
    "coordinates": [
      5.71584,
      43.90977
    ]
  }
}