{
  "type": "Feature",
  "properties": {
    "name": "Saint-Cézaire-sur-Siagne",
    "country": "FR",
    "subdivision": "93",
    "timezone": "Europe/Paris"
  },
  "geometry": {
    "type": "Point",
    "coordinates": [
      6.79219,
      43.65015
    ]
  }
}