{
  "type": "Feature",
  "properties": {
    "name": "Saint-Martin-de-Crau",
    "country": "FR",
    "subdivision": "93",
    "timezone": "Europe/Paris"
  },
  "geometry": {
    "type": "Point",
    "coordinates": [
      4.8127,
      43.63955
    ]
  }
}