{
  "type": "Feature",
  "properties": {
    "name": "Sarrians",
    "country": "FR",
    "subdivision": "93",
    "timezone": "Europe/Paris"
  },
  "geometry": {
    "type": "Point",
    "coordinates": [
      4.97111,
      44.08312
    ]
  }
}