{
  "type": "Feature",
  "properties": {
    "name": "Tanneron",
    "country": "FR",
    "subdivision": "93",
    "timezone": "Europe/Paris"
  },
  "geometry": {
    "type": "Point",
    "coordinates": [
      6.87541,
      43.59057
    ]
  }
}