{
  "type": "Feature",
  "properties": {
    "name": "Tourrettes-sur-Loup",
    "country": "FR",
    "subdivision": "93",
    "timezone": "Europe/Paris"
  },
  "geometry": {
    "type": "Point",
    "coordinates": [
      7.05892,
      43.71569
    ]
  }
}