{
  "type": "Feature",
  "properties": {
    "name": "Valréas",
    "country": "FR",
    "subdivision": "93",
    "timezone": "Europe/Paris"
  },
  "geometry": {
    "type": "Point",
    "coordinates": [
      4.99125,
      44.3849
    ]
  }
}