{
  "type": "Feature",
  "properties": {
    "name": "Vedène",
    "country": "FR",
    "subdivision": "93",
    "timezone": "Europe/Paris"
  },
  "geometry": {
    "type": "Point",
    "coordinates": [
      4.90428,
      43.97744
    ]
  }
}