{
  "type": "Feature",
  "properties": {
    "name": "Villar-Saint-Pancrace",
    "country": "FR",
    "subdivision": "93",
    "timezone": "Europe/Paris"
  },
  "geometry": {
    "type": "Point",
    "coordinates": [
      6.62669,
      44.87318
    ]
  }
}