{
  "type": "Feature",
  "properties": {
    "name": "Villefranche-sur-Mer",
    "country": "FR",
    "subdivision": "93",
    "timezone": "Europe/Paris"
  },
  "geometry": {
    "type": "Point",
    "coordinates": [
      7.31088,
      43.70392
    ]
  }
}