{
  "type": "Feature",
  "properties": {
    "name": "Visan",
    "country": "FR",
    "subdivision": "93",
    "timezone": "Europe/Paris"
  },
  "geometry": {
    "type": "Point",
    "coordinates": [
      4.95033,
      44.31468
    ]
  }
}