{
  "type": "Feature",
  "properties": {
    "name": "Volonne",
    "country": "FR",
    "subdivision": "93",
    "timezone": "Europe/Paris"
  },
  "geometry": {
    "type": "Point",
    "coordinates": [
      6.01424,
      44.11039
    ]
  }
}