{
  "type": "Feature",
  "properties": {
    "name": "Bachatskiy",
    "country": "RU",
    "subdivision": "29",
    "timezone": "Asia/Novokuznetsk"
  },
  "geometry": {
    "type": "Point",
    "coordinates": [
      86.1285,
      54.2927
    ]
  }
}