{
  "type": "Feature",
  "properties": {
    "name": "Borovoy",
    "country": "RU",
    "subdivision": "29",
    "timezone": "Asia/Novokuznetsk"
  },
  "geometry": {
    "type": "Point",
    "coordinates": [
      86.08333,
      55.43333
    ]
  }
}