{
  "type": "Feature",
  "properties": {
    "name": "Itatskiy",
    "country": "RU",
    "subdivision": "29",
    "timezone": "Asia/Novokuznetsk"
  },
  "geometry": {
    "type": "Point",
    "coordinates": [
      89.03694,
      56.07
    ]
  }
}