{
  "type": "Feature",
  "properties": {
    "name": "Kaltan",
    "country": "RU",
    "subdivision": "29",
    "timezone": "Asia/Novokuznetsk"
  },
  "geometry": {
    "type": "Point",
    "coordinates": [
      87.2457,
      53.5347
    ]
  }
}