{
  "type": "Feature",
  "properties": {
    "name": "Plotnikovo",
    "country": "RU",
    "subdivision": "29",
    "timezone": "Asia/Novokuznetsk"
  },
  "geometry": {
    "type": "Point",
    "coordinates": [
      85.94361,
      55.02472
    ]
  }
}