{
  "type": "Feature",
  "properties": {
    "name": "Tayga",
    "country": "RU",
    "subdivision": "29",
    "timezone": "Asia/Novokuznetsk"
  },
  "geometry": {
    "type": "Point",
    "coordinates": [
      85.62238,
      56.06402
    ]
  }
}