{
  "type": "Feature",
  "properties": {
    "name": "Tisul’",
    "country": "RU",
    "subdivision": "29",
    "timezone": "Asia/Novokuznetsk"
  },
  "geometry": {
    "type": "Point",
    "coordinates": [
      88.31228,
      55.76173
    ]
  }
}