{
  "type": "Feature",
  "properties": {
    "name": "Parika",
    "country": "GY",
    "subdivision": "14",
    "timezone": "America/Guyana"
  },
  "geometry": {
    "type": "Point",
    "coordinates": [
      -58.42941,
      6.83712
    ]
  }
}