{
  "type": "Feature",
  "properties": {
    "name": "Bitam",
    "country": "GA",
    "subdivision": "09",
    "timezone": "Africa/Libreville"
  },
  "geometry": {
    "type": "Point",
    "coordinates": [
      11.50065,
      2.07597
    ]
  }
}