{
  "type": "Feature",
  "properties": {
    "name": "Redondo",
    "country": "PT",
    "subdivision": "08",
    "timezone": "Europe/Lisbon"
  },
  "geometry": {
    "type": "Point",
    "coordinates": [
      -7.54708,
      38.64872
    ]
  }
}