{
  "type": "Feature",
  "properties": {
    "name": "Lessebo",
    "country": "SE",
    "subdivision": "12",
    "timezone": "Europe/Stockholm"
  },
  "geometry": {
    "type": "Point",
    "coordinates": [
      15.26969,
      56.75185
    ]
  }
}