{
  "type": "Feature",
  "properties": {
    "name": "Ryd",
    "country": "SE",
    "subdivision": "12",
    "timezone": "Europe/Stockholm"
  },
  "geometry": {
    "type": "Point",
    "coordinates": [
      14.68333,
      56.46667
    ]
  }
}