{
  "type": "Feature",
  "properties": {
    "name": "Yoshkar-Ola",
    "country": "RU",
    "subdivision": "45",
    "timezone": "Europe/Moscow"
  },
  "geometry": {
    "type": "Point",
    "coordinates": [
      47.89078,
      56.63877
    ]
  }
}