{
  "type": "Feature",
  "properties": {
    "name": "Ilovays’k",
    "country": "UA",
    "subdivision": "05",
    "timezone": "Europe/Kiev"
  },
  "geometry": {
    "type": "Point",
    "coordinates": [
      38.20235,
      47.92498
    ]
  }
}