{
  "type": "Feature",
  "properties": {
    "name": "Kostiantynivka",
    "country": "UA",
    "subdivision": "05",
    "timezone": "Europe/Kiev"
  },
  "geometry": {
    "type": "Point",
    "coordinates": [
      37.7069,
      48.5277
    ]
  }
}