{
  "type": "Feature",
  "properties": {
    "name": "Kramatorsk",
    "country": "UA",
    "subdivision": "05",
    "timezone": "Europe/Kiev"
  },
  "geometry": {
    "type": "Point",
    "coordinates": [
      37.55629,
      48.72305
    ]
  }
}