{
  "type": "Feature",
  "properties": {
    "name": "Luhanske",
    "country": "UA",
    "subdivision": "05",
    "timezone": "Europe/Kiev"
  },
  "geometry": {
    "type": "Point",
    "coordinates": [
      38.26153,
      48.44574
    ]
  }
}