{
  "type": "Feature",
  "properties": {
    "name": "Mospyne",
    "country": "UA",
    "subdivision": "05",
    "timezone": "Europe/Kiev"
  },
  "geometry": {
    "type": "Point",
    "coordinates": [
      38.06395,
      47.89081
    ]
  }
}