{
  "type": "Feature",
  "properties": {
    "name": "Novodonetske",
    "country": "UA",
    "subdivision": "05",
    "timezone": "Europe/Kiev"
  },
  "geometry": {
    "type": "Point",
    "coordinates": [
      36.98477,
      48.63526
    ]
  }
}