{
  "type": "Feature",
  "properties": {
    "name": "Rodynske",
    "country": "UA",
    "subdivision": "05",
    "timezone": "Europe/Kiev"
  },
  "geometry": {
    "type": "Point",
    "coordinates": [
      37.20602,
      48.35199
    ]
  }
}