{
  "type": "Feature",
  "properties": {
    "name": "Rozsypne",
    "country": "UA",
    "subdivision": "05",
    "timezone": "Europe/Kiev"
  },
  "geometry": {
    "type": "Point",
    "coordinates": [
      38.57619,
      48.14966
    ]
  }
}