{
  "type": "Feature",
  "properties": {
    "name": "Soledar",
    "country": "UA",
    "subdivision": "05",
    "timezone": "Europe/Kiev"
  },
  "geometry": {
    "type": "Point",
    "coordinates": [
      38.08902,
      48.67935
    ]
  }
}