{
  "type": "Feature",
  "properties": {
    "name": "Staryi Krym",
    "country": "UA",
    "subdivision": "05",
    "timezone": "Europe/Kiev"
  },
  "geometry": {
    "type": "Point",
    "coordinates": [
      37.48808,
      47.16105
    ]
  }
}