{
  "type": "Feature",
  "properties": {
    "name": "Volnovakha",
    "country": "UA",
    "subdivision": "05",
    "timezone": "Europe/Kiev"
  },
  "geometry": {
    "type": "Point",
    "coordinates": [
      37.49674,
      47.60103
    ]
  }
}