{
  "type": "Feature",
  "properties": {
    "name": "Belp",
    "country": "CH",
    "subdivision": "BE",
    "timezone": "Europe/Zurich"
  },
  "geometry": {
    "type": "Point",
    "coordinates": [
      7.49825,
      46.89129
    ]
  }
}