{
  "type": "Feature",
  "properties": {
    "name": "Buchholterberg",
    "country": "CH",
    "subdivision": "BE",
    "timezone": "Europe/Zurich"
  },
  "geometry": {
    "type": "Point",
    "coordinates": [
      7.67463,
      46.81351
    ]
  }
}