{
  "type": "Feature",
  "properties": {
    "name": "Courtelary",
    "country": "CH",
    "subdivision": "BE",
    "timezone": "Europe/Zurich"
  },
  "geometry": {
    "type": "Point",
    "coordinates": [
      7.07236,
      47.17822
    ]
  }
}