{
  "type": "Feature",
  "properties": {
    "name": "Ferenbalm",
    "country": "CH",
    "subdivision": "BE",
    "timezone": "Europe/Zurich"
  },
  "geometry": {
    "type": "Point",
    "coordinates": [
      7.21124,
      46.9488
    ]
  }
}