{
  "type": "Feature",
  "properties": {
    "name": "Fraubrunnen",
    "country": "CH",
    "subdivision": "BE",
    "timezone": "Europe/Zurich"
  },
  "geometry": {
    "type": "Point",
    "coordinates": [
      7.52727,
      47.0862
    ]
  }
}