{
  "type": "Feature",
  "properties": {
    "name": "Frutigen",
    "country": "CH",
    "subdivision": "BE",
    "timezone": "Europe/Zurich"
  },
  "geometry": {
    "type": "Point",
    "coordinates": [
      7.64945,
      46.58723
    ]
  }
}