{
  "type": "Feature",
  "properties": {
    "name": "Kallnach",
    "country": "CH",
    "subdivision": "BE",
    "timezone": "Europe/Zurich"
  },
  "geometry": {
    "type": "Point",
    "coordinates": [
      7.23545,
      47.02032
    ]
  }
}