{
  "type": "Feature",
  "properties": {
    "name": "Kappelen",
    "country": "CH",
    "subdivision": "BE",
    "timezone": "Europe/Zurich"
  },
  "geometry": {
    "type": "Point",
    "coordinates": [
      7.2686,
      47.06015
    ]
  }
}