{
  "type": "Feature",
  "properties": {
    "name": "Lauperswil",
    "country": "CH",
    "subdivision": "BE",
    "timezone": "Europe/Zurich"
  },
  "geometry": {
    "type": "Point",
    "coordinates": [
      7.74214,
      46.96564
    ]
  }
}