{
  "type": "Feature",
  "properties": {
    "name": "Leuzigen",
    "country": "CH",
    "subdivision": "BE",
    "timezone": "Europe/Zurich"
  },
  "geometry": {
    "type": "Point",
    "coordinates": [
      7.45775,
      47.17458
    ]
  }
}