{
  "type": "Feature",
  "properties": {
    "name": "Lotzwil",
    "country": "CH",
    "subdivision": "BE",
    "timezone": "Europe/Zurich"
  },
  "geometry": {
    "type": "Point",
    "coordinates": [
      7.79102,
      47.19135
    ]
  }
}