{
  "type": "Feature",
  "properties": {
    "name": "Madiswil",
    "country": "CH",
    "subdivision": "BE",
    "timezone": "Europe/Zurich"
  },
  "geometry": {
    "type": "Point",
    "coordinates": [
      7.79858,
      47.16463
    ]
  }
}