{
  "type": "Feature",
  "properties": {
    "name": "Malleray",
    "country": "CH",
    "subdivision": "BE",
    "timezone": "Europe/Zurich"
  },
  "geometry": {
    "type": "Point",
    "coordinates": [
      7.27286,
      47.23839
    ]
  }
}