{
  "type": "Feature",
  "properties": {
    "name": "Melchnau",
    "country": "CH",
    "subdivision": "BE",
    "timezone": "Europe/Zurich"
  },
  "geometry": {
    "type": "Point",
    "coordinates": [
      7.85128,
      47.18213
    ]
  }
}