{
  "type": "Feature",
  "properties": {
    "name": "Radelfingen",
    "country": "CH",
    "subdivision": "BE",
    "timezone": "Europe/Zurich"
  },
  "geometry": {
    "type": "Point",
    "coordinates": [
      7.27178,
      47.02146
    ]
  }
}