{
  "type": "Feature",
  "properties": {
    "name": "Schüpfen",
    "country": "CH",
    "subdivision": "BE",
    "timezone": "Europe/Zurich"
  },
  "geometry": {
    "type": "Point",
    "coordinates": [
      7.37723,
      47.03661
    ]
  }
}