{
  "type": "Feature",
  "properties": {
    "name": "Trubschachen",
    "country": "CH",
    "subdivision": "BE",
    "timezone": "Europe/Zurich"
  },
  "geometry": {
    "type": "Point",
    "coordinates": [
      7.8452,
      46.92228
    ]
  }
}