{
  "type": "Feature",
  "properties": {
    "name": "Wohlen",
    "country": "CH",
    "subdivision": "BE",
    "timezone": "Europe/Zurich"
  },
  "geometry": {
    "type": "Point",
    "coordinates": [
      7.35685,
      46.97118
    ]
  }
}