{
  "type": "Feature",
  "properties": {
    "name": "Wynau",
    "country": "CH",
    "subdivision": "BE",
    "timezone": "Europe/Zurich"
  },
  "geometry": {
    "type": "Point",
    "coordinates": [
      7.81626,
      47.2557
    ]
  }
}