{
  "type": "Feature",
  "properties": {
    "name": "Yeşilova",
    "country": "TR",
    "subdivision": "15",
    "timezone": "Europe/Istanbul"
  },
  "geometry": {
    "type": "Point",
    "coordinates": [
      29.75472,
      37.50806
    ]
  }
}