{
  "type": "Feature",
  "properties": {
    "name": "Amet",
    "country": "IN",
    "subdivision": "24",
    "timezone": "Asia/Kolkata"
  },
  "geometry": {
    "type": "Point",
    "coordinates": [
      73.9258,
      25.30609
    ]
  }
}