{
  "type": "Feature",
  "properties": {
    "name": "Bāndīkūi",
    "country": "IN",
    "subdivision": "24",
    "timezone": "Asia/Kolkata"
  },
  "geometry": {
    "type": "Point",
    "coordinates": [
      76.57325,
      27.05087
    ]
  }
}