{
  "type": "Feature",
  "properties": {
    "name": "BÄri",
    "country": "IN",
    "subdivision": "24",
    "timezone": "Asia/Kolkata"
  },
  "geometry": {
    "type": "Point",
    "coordinates": [
      77.61634,
      26.64661
    ]
  }
}