{
  "type": "Feature",
  "properties": {
    "name": "BilÄra",
    "country": "IN",
    "subdivision": "24",
    "timezone": "Asia/Kolkata"
  },
  "geometry": {
    "type": "Point",
    "coordinates": [
      73.7055,
      26.18067
    ]
  }
}