{
  "type": "Feature",
  "properties": {
    "name": "Deoli",
    "country": "IN",
    "subdivision": "24",
    "timezone": "Asia/Kolkata"
  },
  "geometry": {
    "type": "Point",
    "coordinates": [
      75.37991,
      25.75728
    ]
  }
}