{
  "type": "Feature",
  "properties": {
    "name": "Deshnoke",
    "country": "IN",
    "subdivision": "24",
    "timezone": "Asia/Kolkata"
  },
  "geometry": {
    "type": "Point",
    "coordinates": [
      73.34297,
      27.79836
    ]
  }
}