{
  "type": "Feature",
  "properties": {
    "name": "GangÄnagar",
    "country": "IN",
    "subdivision": "24",
    "timezone": "Asia/Kolkata"
  },
  "geometry": {
    "type": "Point",
    "coordinates": [
      73.87496,
      29.92009
    ]
  }
}