{
  "type": "Feature",
  "properties": {
    "name": "Hindaun",
    "country": "IN",
    "subdivision": "24",
    "timezone": "Asia/Kolkata"
  },
  "geometry": {
    "type": "Point",
    "coordinates": [
      77.03519,
      26.73411
    ]
  }
}