{
  "type": "Feature",
  "properties": {
    "name": "KÄnor",
    "country": "IN",
    "subdivision": "24",
    "timezone": "Asia/Kolkata"
  },
  "geometry": {
    "type": "Point",
    "coordinates": [
      74.26546,
      24.43437
    ]
  }
}