{
  "type": "Feature",
  "properties": {
    "name": "Mūndwa",
    "country": "IN",
    "subdivision": "24",
    "timezone": "Asia/Kolkata"
  },
  "geometry": {
    "type": "Point",
    "coordinates": [
      73.82304,
      27.0631
    ]
  }
}