{
  "type": "Feature",
  "properties": {
    "name": "NapÄsar",
    "country": "IN",
    "subdivision": "24",
    "timezone": "Asia/Kolkata"
  },
  "geometry": {
    "type": "Point",
    "coordinates": [
      73.55913,
      27.96059
    ]
  }
}