{
  "type": "Feature",
  "properties": {
    "name": "Nīmāj",
    "country": "IN",
    "subdivision": "24",
    "timezone": "Asia/Kolkata"
  },
  "geometry": {
    "type": "Point",
    "coordinates": [
      74.00094,
      26.14995
    ]
  }
}