{
  "type": "Feature",
  "properties": {
    "name": "Niwai",
    "country": "IN",
    "subdivision": "24",
    "timezone": "Asia/Kolkata"
  },
  "geometry": {
    "type": "Point",
    "coordinates": [
      75.91836,
      26.36073
    ]
  }
}