{
  "type": "Feature",
  "properties": {
    "name": "Padampur",
    "country": "IN",
    "subdivision": "24",
    "timezone": "Asia/Kolkata"
  },
  "geometry": {
    "type": "Point",
    "coordinates": [
      73.62539,
      29.70885
    ]
  }
}