{
  "type": "Feature",
  "properties": {
    "name": "Raipur",
    "country": "IN",
    "subdivision": "24",
    "timezone": "Asia/Kolkata"
  },
  "geometry": {
    "type": "Point",
    "coordinates": [
      74.02373,
      26.04259
    ]
  }
}