{
  "type": "Feature",
  "properties": {
    "name": "RÄni",
    "country": "IN",
    "subdivision": "24",
    "timezone": "Asia/Kolkata"
  },
  "geometry": {
    "type": "Point",
    "coordinates": [
      73.30885,
      25.35031
    ]
  }
}