{
  "type": "Feature",
  "properties": {
    "name": "SardÄrshahr",
    "country": "IN",
    "subdivision": "24",
    "timezone": "Asia/Kolkata"
  },
  "geometry": {
    "type": "Point",
    "coordinates": [
      74.491,
      28.44062
    ]
  }
}