{
  "type": "Feature",
  "properties": {
    "name": "Sirohi",
    "country": "IN",
    "subdivision": "24",
    "timezone": "Asia/Kolkata"
  },
  "geometry": {
    "type": "Point",
    "coordinates": [
      72.84794,
      24.88838
    ]
  }
}