{
  "type": "Feature",
  "properties": {
    "name": "Tārānagar",
    "country": "IN",
    "subdivision": "24",
    "timezone": "Asia/Kolkata"
  },
  "geometry": {
    "type": "Point",
    "coordinates": [
      75.03207,
      28.6686
    ]
  }
}