{
  "type": "Feature",
  "properties": {
    "name": "Kovylkino",
    "country": "RU",
    "subdivision": "46",
    "timezone": "Europe/Moscow"
  },
  "geometry": {
    "type": "Point",
    "coordinates": [
      43.91385,
      54.03876
    ]
  }
}