{
  "type": "Feature",
  "properties": {
    "name": "Krasnoslobodsk",
    "country": "RU",
    "subdivision": "46",
    "timezone": "Europe/Moscow"
  },
  "geometry": {
    "type": "Point",
    "coordinates": [
      43.78963,
      54.4253
    ]
  }
}