{
  "type": "Feature",
  "properties": {
    "name": "Dessalines",
    "country": "HT",
    "subdivision": "06",
    "timezone": "America/Port-au-Prince"
  },
  "geometry": {
    "type": "Point",
    "coordinates": [
      -72.51611,
      19.26177
    ]
  }
}