{
  "type": "Feature",
  "properties": {
    "name": "Grande Saline",
    "country": "HT",
    "subdivision": "06",
    "timezone": "America/Port-au-Prince"
  },
  "geometry": {
    "type": "Point",
    "coordinates": [
      -72.76897,
      19.26513
    ]
  }
}