{
  "type": "Feature",
  "properties": {
    "name": "Vittoriosa",
    "country": "MT",
    "subdivision": "03",
    "timezone": "Europe/Malta"
  },
  "geometry": {
    "type": "Point",
    "coordinates": [
      14.51833,
      35.89222
    ]
  }
}