{
  "type": "Feature",
  "properties": {
    "name": "Dadiya",
    "country": "NG",
    "subdivision": "55",
    "timezone": "Africa/Lagos"
  },
  "geometry": {
    "type": "Point",
    "coordinates": [
      11.43333,
      9.61667
    ]
  }
}