{
  "type": "Feature",
  "properties": {
    "name": "Dukku",
    "country": "NG",
    "subdivision": "55",
    "timezone": "Africa/Lagos"
  },
  "geometry": {
    "type": "Point",
    "coordinates": [
      10.77221,
      10.82379
    ]
  }
}