{
  "type": "Feature",
  "properties": {
    "name": "Kafarati",
    "country": "NG",
    "subdivision": "55",
    "timezone": "Africa/Lagos"
  },
  "geometry": {
    "type": "Point",
    "coordinates": [
      11.09567,
      10.38304
    ]
  }
}