{
  "type": "Feature",
  "properties": {
    "name": "Pindiga",
    "country": "NG",
    "subdivision": "55",
    "timezone": "Africa/Lagos"
  },
  "geometry": {
    "type": "Point",
    "coordinates": [
      10.95229,
      9.98433
    ]
  }
}