{
  "type": "Feature",
  "properties": {
    "name": "Ciputat",
    "country": "ID",
    "subdivision": "30",
    "timezone": "Asia/Jakarta"
  },
  "geometry": {
    "type": "Point",
    "coordinates": [
      106.69556,
      -6.2375
    ]
  }
}