{
  "type": "Feature",
  "properties": {
    "name": "Jatiwangi",
    "country": "ID",
    "subdivision": "30",
    "timezone": "Asia/Jakarta"
  },
  "geometry": {
    "type": "Point",
    "coordinates": [
      108.26278,
      -6.73361
    ]
  }
}