{
  "type": "Feature",
  "properties": {
    "name": "Kuningan",
    "country": "ID",
    "subdivision": "30",
    "timezone": "Asia/Jakarta"
  },
  "geometry": {
    "type": "Point",
    "coordinates": [
      108.48306,
      -6.97583
    ]
  }
}