{
  "type": "Feature",
  "properties": {
    "name": "Majalengka",
    "country": "ID",
    "subdivision": "30",
    "timezone": "Asia/Jakarta"
  },
  "geometry": {
    "type": "Point",
    "coordinates": [
      108.22778,
      -6.83611
    ]
  }
}