{
  "type": "Feature",
  "properties": {
    "name": "Pamanukan",
    "country": "ID",
    "subdivision": "30",
    "timezone": "Asia/Jakarta"
  },
  "geometry": {
    "type": "Point",
    "coordinates": [
      107.81056,
      -6.28417
    ]
  }
}