{
  "type": "Feature",
  "properties": {
    "name": "Pameungpeuk",
    "country": "ID",
    "subdivision": "30",
    "timezone": "Asia/Jakarta"
  },
  "geometry": {
    "type": "Point",
    "coordinates": [
      107.60389,
      -7.01833
    ]
  }
}