{
  "type": "Feature",
  "properties": {
    "name": "Parung",
    "country": "ID",
    "subdivision": "30",
    "timezone": "Asia/Jakarta"
  },
  "geometry": {
    "type": "Point",
    "coordinates": [
      106.73306,
      -6.42139
    ]
  }
}