{
  "type": "Feature",
  "properties": {
    "name": "Sawangan",
    "country": "ID",
    "subdivision": "30",
    "timezone": "Asia/Jakarta"
  },
  "geometry": {
    "type": "Point",
    "coordinates": [
      106.77444,
      -6.40278
    ]
  }
}