{
  "type": "Feature",
  "properties": {
    "name": "Guananico",
    "country": "DO",
    "subdivision": "18",
    "timezone": "America/Santo_Domingo"
  },
  "geometry": {
    "type": "Point",
    "coordinates": [
      -70.92294,
      19.72693
    ]
  }
}