{
  "type": "Feature",
  "properties": {
    "name": "Puerto Plata",
    "country": "DO",
    "subdivision": "18",
    "timezone": "America/Santo_Domingo"
  },
  "geometry": {
    "type": "Point",
    "coordinates": [
      -70.6884,
      19.79344
    ]
  }
}