{
  "type": "Feature",
  "properties": {
    "name": "Pădureni",
    "country": "RO",
    "subdivision": "42",
    "timezone": "Europe/Bucharest"
  },
  "geometry": {
    "type": "Point",
    "coordinates": [
      25.80469,
      44.34576
    ]
  }
}