{
  "type": "Feature",
  "properties": {
    "name": "Singureni",
    "country": "RO",
    "subdivision": "42",
    "timezone": "Europe/Bucharest"
  },
  "geometry": {
    "type": "Point",
    "coordinates": [
      25.94333,
      44.23361
    ]
  }
}