{
  "type": "Feature",
  "properties": {
    "name": "Al Fandaqūmīyah",
    "country": "PS",
    "subdivision": "WE",
    "timezone": "Asia/Hebron"
  },
  "geometry": {
    "type": "Point",
    "coordinates": [
      35.20329,
      32.3206
    ]
  }
}