{
  "type": "Feature",
  "properties": {
    "name": "Al Lubban ash Sharqīyah",
    "country": "PS",
    "subdivision": "WE",
    "timezone": "Asia/Hebron"
  },
  "geometry": {
    "type": "Point",
    "coordinates": [
      35.2403,
      32.07011
    ]
  }
}