{
  "type": "Feature",
  "properties": {
    "name": "Al ‘Araqa",
    "country": "PS",
    "subdivision": "WE",
    "timezone": "Asia/Hebron"
  },
  "geometry": {
    "type": "Point",
    "coordinates": [
      35.20027,
      32.47057
    ]
  }
}