{
  "type": "Feature",
  "properties": {
    "name": "Alfe Menashe",
    "country": "PS",
    "subdivision": "WE",
    "timezone": "Asia/Hebron"
  },
  "geometry": {
    "type": "Point",
    "coordinates": [
      35.01179,
      32.17265
    ]
  }
}