{
  "type": "Feature",
  "properties": {
    "name": "An Nāqūrah",
    "country": "PS",
    "subdivision": "WE",
    "timezone": "Asia/Hebron"
  },
  "geometry": {
    "type": "Point",
    "coordinates": [
      35.20135,
      32.26506
    ]
  }
}