{
  "type": "Feature",
  "properties": {
    "name": "Ar Ramāḑīn",
    "country": "PS",
    "subdivision": "WE",
    "timezone": "Asia/Hebron"
  },
  "geometry": {
    "type": "Point",
    "coordinates": [
      34.91246,
      31.37952
    ]
  }
}