{
  "type": "Feature",
  "properties": {
    "name": "Az Zaytūnīyah",
    "country": "PS",
    "subdivision": "WE",
    "timezone": "Asia/Hebron"
  },
  "geometry": {
    "type": "Point",
    "coordinates": [
      35.1624,
      31.95403
    ]
  }
}