{
  "type": "Feature",
  "properties": {
    "name": "Barţa‘ah ash Sharqīyah",
    "country": "PS",
    "subdivision": "WE",
    "timezone": "Asia/Hebron"
  },
  "geometry": {
    "type": "Point",
    "coordinates": [
      35.0936,
      32.47304
    ]
  }
}