{
  "type": "Feature",
  "properties": {
    "name": "Bayt Ībā",
    "country": "PS",
    "subdivision": "WE",
    "timezone": "Asia/Hebron"
  },
  "geometry": {
    "type": "Point",
    "coordinates": [
      35.20977,
      32.23719
    ]
  }
}