{
  "type": "Feature",
  "properties": {
    "name": "Bayt Imrīn",
    "country": "PS",
    "subdivision": "WE",
    "timezone": "Asia/Hebron"
  },
  "geometry": {
    "type": "Point",
    "coordinates": [
      35.2161,
      32.29301
    ]
  }
}