{
  "type": "Feature",
  "properties": {
    "name": "Bayt Duqqū",
    "country": "PS",
    "subdivision": "WE",
    "timezone": "Asia/Hebron"
  },
  "geometry": {
    "type": "Point",
    "coordinates": [
      35.13124,
      31.85911
    ]
  }
}