{
  "type": "Feature",
  "properties": {
    "name": "Bayt Dajan",
    "country": "PS",
    "subdivision": "WE",
    "timezone": "Asia/Hebron"
  },
  "geometry": {
    "type": "Point",
    "coordinates": [
      35.37127,
      32.19303
    ]
  }
}