{
  "type": "Feature",
  "properties": {
    "name": "Bayt Liqyā",
    "country": "PS",
    "subdivision": "WE",
    "timezone": "Asia/Hebron"
  },
  "geometry": {
    "type": "Point",
    "coordinates": [
      35.0654,
      31.86958
    ]
  }
}