{
  "type": "Feature",
  "properties": {
    "name": "Bayt Jālā",
    "country": "PS",
    "subdivision": "WE",
    "timezone": "Asia/Hebron"
  },
  "geometry": {
    "type": "Point",
    "coordinates": [
      35.18788,
      31.71545
    ]
  }
}