{
  "type": "Feature",
  "properties": {
    "name": "Bethlehem",
    "country": "PS",
    "subdivision": "WE",
    "timezone": "Asia/Hebron"
  },
  "geometry": {
    "type": "Point",
    "coordinates": [
      35.20376,
      31.70487
    ]
  }
}