{
  "type": "Feature",
  "properties": {
    "name": "Dayr Istiyā",
    "country": "PS",
    "subdivision": "WE",
    "timezone": "Asia/Hebron"
  },
  "geometry": {
    "type": "Point",
    "coordinates": [
      35.13963,
      32.13096
    ]
  }
}