{
  "type": "Feature",
  "properties": {
    "name": "Dayr al Ḩaţab",
    "country": "PS",
    "subdivision": "WE",
    "timezone": "Asia/Hebron"
  },
  "geometry": {
    "type": "Point",
    "coordinates": [
      35.32127,
      32.21734
    ]
  }
}