{
  "type": "Feature",
  "properties": {
    "name": "Dayr Sharaf",
    "country": "PS",
    "subdivision": "WE",
    "timezone": "Asia/Hebron"
  },
  "geometry": {
    "type": "Point",
    "coordinates": [
      35.18893,
      32.25326
    ]
  }
}