{
  "type": "Feature",
  "properties": {
    "name": "Dūrā al Qar‘",
    "country": "PS",
    "subdivision": "WE",
    "timezone": "Asia/Hebron"
  },
  "geometry": {
    "type": "Point",
    "coordinates": [
      35.22714,
      31.95863
    ]
  }
}