{
  "type": "Feature",
  "properties": {
    "name": "Faqqū‘ah",
    "country": "PS",
    "subdivision": "WE",
    "timezone": "Asia/Hebron"
  },
  "geometry": {
    "type": "Point",
    "coordinates": [
      35.40163,
      32.48998
    ]
  }
}