{
  "type": "Feature",
  "properties": {
    "name": "Farkhah",
    "country": "PS",
    "subdivision": "WE",
    "timezone": "Asia/Hebron"
  },
  "geometry": {
    "type": "Point",
    "coordinates": [
      35.15286,
      32.06878
    ]
  }
}