{
  "type": "Feature",
  "properties": {
    "name": "Geva Binyamin",
    "country": "PS",
    "subdivision": "WE",
    "timezone": "Asia/Hebron"
  },
  "geometry": {
    "type": "Point",
    "coordinates": [
      35.27405,
      31.85031
    ]
  }
}