{
  "type": "Feature",
  "properties": {
    "name": "Ḩizmā",
    "country": "PS",
    "subdivision": "WE",
    "timezone": "Asia/Hebron"
  },
  "geometry": {
    "type": "Point",
    "coordinates": [
      35.26315,
      31.83337
    ]
  }
}