{
  "type": "Feature",
  "properties": {
    "name": "Itamar",
    "country": "PS",
    "subdivision": "WE",
    "timezone": "Asia/Hebron"
  },
  "geometry": {
    "type": "Point",
    "coordinates": [
      35.30941,
      32.17474
    ]
  }
}