{
  "type": "Feature",
  "properties": {
    "name": "Jayyūs",
    "country": "PS",
    "subdivision": "WE",
    "timezone": "Asia/Hebron"
  },
  "geometry": {
    "type": "Point",
    "coordinates": [
      35.03416,
      32.20125
    ]
  }
}