{
  "type": "Feature",
  "properties": {
    "name": "Kafr Qaddūm",
    "country": "PS",
    "subdivision": "WE",
    "timezone": "Asia/Hebron"
  },
  "geometry": {
    "type": "Point",
    "coordinates": [
      35.14471,
      32.22162
    ]
  }
}