{
  "type": "Feature",
  "properties": {
    "name": "Khallat al Mayyah",
    "country": "PS",
    "subdivision": "WE",
    "timezone": "Asia/Hebron"
  },
  "geometry": {
    "type": "Point",
    "coordinates": [
      35.14286,
      31.44222
    ]
  }
}