{
  "type": "Feature",
  "properties": {
    "name": "Khallat Ḩamāmah",
    "country": "PS",
    "subdivision": "WE",
    "timezone": "Asia/Hebron"
  },
  "geometry": {
    "type": "Point",
    "coordinates": [
      35.19243,
      31.7216
    ]
  }
}