{
  "type": "Feature",
  "properties": {
    "name": "Majdal Banī Fāḑil",
    "country": "PS",
    "subdivision": "WE",
    "timezone": "Asia/Hebron"
  },
  "geometry": {
    "type": "Point",
    "coordinates": [
      35.36378,
      32.08357
    ]
  }
}