{
  "type": "Feature",
  "properties": {
    "name": "MardÄ",
    "country": "PS",
    "subdivision": "WE",
    "timezone": "Asia/Hebron"
  },
  "geometry": {
    "type": "Point",
    "coordinates": [
      35.19536,
      32.11381
    ]
  }
}