{
  "type": "Feature",
  "properties": {
    "name": "Mirkah",
    "country": "PS",
    "subdivision": "WE",
    "timezone": "Asia/Hebron"
  },
  "geometry": {
    "type": "Point",
    "coordinates": [
      35.23807,
      32.39583
    ]
  }
}