{
  "type": "Feature",
  "properties": {
    "name": "Qabalān",
    "country": "PS",
    "subdivision": "WE",
    "timezone": "Asia/Hebron"
  },
  "geometry": {
    "type": "Point",
    "coordinates": [
      35.28938,
      32.10182
    ]
  }
}