{
  "type": "Feature",
  "properties": {
    "name": "Qalqīlyah",
    "country": "PS",
    "subdivision": "WE",
    "timezone": "Asia/Hebron"
  },
  "geometry": {
    "type": "Point",
    "coordinates": [
      34.97063,
      32.18966
    ]
  }
}