{
  "type": "Feature",
  "properties": {
    "name": "Sal‘it",
    "country": "PS",
    "subdivision": "WE",
    "timezone": "Asia/Hebron"
  },
  "geometry": {
    "type": "Point",
    "coordinates": [
      35.05272,
      32.24295
    ]
  }
}