{
  "type": "Feature",
  "properties": {
    "name": "Şarrah",
    "country": "PS",
    "subdivision": "WE",
    "timezone": "Asia/Hebron"
  },
  "geometry": {
    "type": "Point",
    "coordinates": [
      35.19147,
      32.2097
    ]
  }
}