{
  "type": "Feature",
  "properties": {
    "name": "Şarţah",
    "country": "PS",
    "subdivision": "WE",
    "timezone": "Asia/Hebron"
  },
  "geometry": {
    "type": "Point",
    "coordinates": [
      35.09198,
      32.10447
    ]
  }
}