{
  "type": "Feature",
  "properties": {
    "name": "Şūrīf",
    "country": "PS",
    "subdivision": "WE",
    "timezone": "Asia/Hebron"
  },
  "geometry": {
    "type": "Point",
    "coordinates": [
      35.06439,
      31.65078
    ]
  }
}