{
  "type": "Feature",
  "properties": {
    "name": "Ţallūzah",
    "country": "PS",
    "subdivision": "WE",
    "timezone": "Asia/Hebron"
  },
  "geometry": {
    "type": "Point",
    "coordinates": [
      35.29496,
      32.27056
    ]
  }
}