{
  "type": "Feature",
  "properties": {
    "name": "Yaqqir",
    "country": "PS",
    "subdivision": "WE",
    "timezone": "Asia/Hebron"
  },
  "geometry": {
    "type": "Point",
    "coordinates": [
      35.11528,
      32.14969
    ]
  }
}