{
  "type": "Feature",
  "properties": {
    "name": "Yaţţā",
    "country": "PS",
    "subdivision": "WE",
    "timezone": "Asia/Hebron"
  },
  "geometry": {
    "type": "Point",
    "coordinates": [
      35.09443,
      31.4459
    ]
  }
}