{
  "type": "Feature",
  "properties": {
    "name": "Zawātā",
    "country": "PS",
    "subdivision": "WE",
    "timezone": "Asia/Hebron"
  },
  "geometry": {
    "type": "Point",
    "coordinates": [
      35.2265,
      32.24611
    ]
  }
}