{
  "type": "Feature",
  "properties": {
    "name": "‘Arrābah",
    "country": "PS",
    "subdivision": "WE",
    "timezone": "Asia/Hebron"
  },
  "geometry": {
    "type": "Point",
    "coordinates": [
      35.20189,
      32.40517
    ]
  }
}