{
  "type": "Feature",
  "properties": {
    "name": "Fokino",
    "country": "RU",
    "subdivision": "59",
    "timezone": "Asia/Vladivostok"
  },
  "geometry": {
    "type": "Point",
    "coordinates": [
      132.40574,
      42.97429
    ]
  }
}