{
  "type": "Feature",
  "properties": {
    "name": "Gornorechenskiy",
    "country": "RU",
    "subdivision": "59",
    "timezone": "Asia/Vladivostok"
  },
  "geometry": {
    "type": "Point",
    "coordinates": [
      135.11465,
      44.26555
    ]
  }
}