{
  "type": "Feature",
  "properties": {
    "name": "Knevichi",
    "country": "RU",
    "subdivision": "59",
    "timezone": "Asia/Vladivostok"
  },
  "geometry": {
    "type": "Point",
    "coordinates": [
      132.18808,
      43.39975
    ]
  }
}