{
  "type": "Feature",
  "properties": {
    "name": "Plastun",
    "country": "RU",
    "subdivision": "59",
    "timezone": "Asia/Vladivostok"
  },
  "geometry": {
    "type": "Point",
    "coordinates": [
      136.28048,
      44.76077
    ]
  }
}