{
  "type": "Feature",
  "properties": {
    "name": "Uglovoye",
    "country": "RU",
    "subdivision": "59",
    "timezone": "Asia/Vladivostok"
  },
  "geometry": {
    "type": "Point",
    "coordinates": [
      132.08832,
      43.32807
    ]
  }
}