{
  "type": "Feature",
  "properties": {
    "name": "Vol’no-Nadezhdinskoye",
    "country": "RU",
    "subdivision": "59",
    "timezone": "Asia/Vladivostok"
  },
  "geometry": {
    "type": "Point",
    "coordinates": [
      131.99675,
      43.37496
    ]
  }
}