{
  "type": "Feature",
  "properties": {
    "name": "Vozdvizhenka",
    "country": "RU",
    "subdivision": "59",
    "timezone": "Asia/Vladivostok"
  },
  "geometry": {
    "type": "Point",
    "coordinates": [
      131.94589,
      43.89413
    ]
  }
}