{
  "type": "Feature",
  "properties": {
    "name": "Yakovlevka",
    "country": "RU",
    "subdivision": "59",
    "timezone": "Asia/Vladivostok"
  },
  "geometry": {
    "type": "Point",
    "coordinates": [
      133.47406,
      44.42588
    ]
  }
}