{
  "type": "Feature",
  "properties": {
    "name": "Mashtūl as Sūq",
    "country": "EG",
    "subdivision": "14",
    "timezone": "Africa/Cairo"
  },
  "geometry": {
    "type": "Point",
    "coordinates": [
      31.3776,
      30.36056
    ]
  }
}