{
  "type": "Feature",
  "properties": {
    "name": "Murbaḩ",
    "country": "AE",
    "subdivision": "06",
    "timezone": "Asia/Dubai"
  },
  "geometry": {
    "type": "Point",
    "coordinates": [
      56.36256,
      25.27623
    ]
  }
}