{
  "type": "Feature",
  "properties": {
    "name": "Itatí",
    "country": "AR",
    "subdivision": "06",
    "timezone": "America/Argentina/Cordoba"
  },
  "geometry": {
    "type": "Point",
    "coordinates": [
      -58.24458,
      -27.27043
    ]
  }
}