{
  "type": "Feature",
  "properties": {
    "name": "Nueve de Julio",
    "country": "AR",
    "subdivision": "06",
    "timezone": "America/Argentina/Cordoba"
  },
  "geometry": {
    "type": "Point",
    "coordinates": [
      -58.8265,
      -28.84051
    ]
  }
}