{
  "type": "Feature",
  "properties": {
    "name": "Pueblo Libertador",
    "country": "AR",
    "subdivision": "06",
    "timezone": "America/Argentina/Cordoba"
  },
  "geometry": {
    "type": "Point",
    "coordinates": [
      -59.38981,
      -30.22087
    ]
  }
}