{
  "type": "Feature",
  "properties": {
    "name": "Saladas",
    "country": "AR",
    "subdivision": "06",
    "timezone": "America/Argentina/Cordoba"
  },
  "geometry": {
    "type": "Point",
    "coordinates": [
      -58.62591,
      -28.25384
    ]
  }
}