{
  "type": "Feature",
  "properties": {
    "name": "San Carlos",
    "country": "AR",
    "subdivision": "06",
    "timezone": "America/Argentina/Cordoba"
  },
  "geometry": {
    "type": "Point",
    "coordinates": [
      -55.89731,
      -27.74586
    ]
  }
}