{
  "type": "Feature",
  "properties": {
    "name": "Yapeyú",
    "country": "AR",
    "subdivision": "06",
    "timezone": "America/Argentina/Cordoba"
  },
  "geometry": {
    "type": "Point",
    "coordinates": [
      -56.81841,
      -29.46914
    ]
  }
}