{
  "type": "Feature",
  "properties": {
    "name": "Kukës",
    "country": "AL",
    "subdivision": "47",
    "timezone": "Europe/Tirane"
  },
  "geometry": {
    "type": "Point",
    "coordinates": [
      20.42194,
      42.07694
    ]
  }
}