{
  "type": "Feature",
  "properties": {
    "name": "Kryvyy Rih",
    "country": "UA",
    "subdivision": "04",
    "timezone": "Europe/Kiev"
  },
  "geometry": {
    "type": "Point",
    "coordinates": [
      33.39404,
      47.90572
    ]
  }
}