{
  "type": "Feature",
  "properties": {
    "name": "Lykhivka",
    "country": "UA",
    "subdivision": "04",
    "timezone": "Europe/Kiev"
  },
  "geometry": {
    "type": "Point",
    "coordinates": [
      33.93197,
      48.67739
    ]
  }
}