{
  "type": "Feature",
  "properties": {
    "name": "Marhanets",
    "country": "UA",
    "subdivision": "04",
    "timezone": "Europe/Kiev"
  },
  "geometry": {
    "type": "Point",
    "coordinates": [
      34.6245,
      47.63088
    ]
  }
}