{
  "type": "Feature",
  "properties": {
    "name": "Partyzanske",
    "country": "UA",
    "subdivision": "04",
    "timezone": "Europe/Kiev"
  },
  "geometry": {
    "type": "Point",
    "coordinates": [
      34.81465,
      48.58792
    ]
  }
}