{
  "type": "Feature",
  "properties": {
    "name": "Pidhorodne",
    "country": "UA",
    "subdivision": "04",
    "timezone": "Europe/Kiev"
  },
  "geometry": {
    "type": "Point",
    "coordinates": [
      35.09702,
      48.57422
    ]
  }
}