{
  "type": "Feature",
  "properties": {
    "name": "Prosyana",
    "country": "UA",
    "subdivision": "04",
    "timezone": "Europe/Kiev"
  },
  "geometry": {
    "type": "Point",
    "coordinates": [
      36.37175,
      48.11368
    ]
  }
}