{
  "type": "Feature",
  "properties": {
    "name": "Radushne",
    "country": "UA",
    "subdivision": "04",
    "timezone": "Europe/Kiev"
  },
  "geometry": {
    "type": "Point",
    "coordinates": [
      33.51015,
      47.81548
    ]
  }
}