{
  "type": "Feature",
  "properties": {
    "name": "Spas’ke",
    "country": "UA",
    "subdivision": "04",
    "timezone": "Europe/Kiev"
  },
  "geometry": {
    "type": "Point",
    "coordinates": [
      35.05385,
      48.66667
    ]
  }
}