{
  "type": "Feature",
  "properties": {
    "name": "Tsarychanka",
    "country": "UA",
    "subdivision": "04",
    "timezone": "Europe/Kiev"
  },
  "geometry": {
    "type": "Point",
    "coordinates": [
      34.48601,
      48.94186
    ]
  }
}