{
  "type": "Feature",
  "properties": {
    "name": "Verkhnodniprovsk",
    "country": "UA",
    "subdivision": "04",
    "timezone": "Europe/Kiev"
  },
  "geometry": {
    "type": "Point",
    "coordinates": [
      34.3262,
      48.65557
    ]
  }
}