{
  "type": "Feature",
  "properties": {
    "name": "Vecumnieki",
    "country": "LV",
    "subdivision": "E4",
    "timezone": "Europe/Riga"
  },
  "geometry": {
    "type": "Point",
    "coordinates": [
      24.52232,
      56.60608
    ]
  }
}