{
  "type": "Feature",
  "properties": {
    "name": "Garoua Boulaï",
    "country": "CM",
    "subdivision": "04",
    "timezone": "Africa/Douala"
  },
  "geometry": {
    "type": "Point",
    "coordinates": [
      14.55,
      5.88333
    ]
  }
}