{
  "type": "Feature",
  "properties": {
    "name": "Yokadouma",
    "country": "CM",
    "subdivision": "04",
    "timezone": "Africa/Douala"
  },
  "geometry": {
    "type": "Point",
    "coordinates": [
      15.05,
      3.51667
    ]
  }
}