{
  "type": "Feature",
  "properties": {
    "name": "Sultanköy",
    "country": "TR",
    "subdivision": "59",
    "timezone": "Europe/Istanbul"
  },
  "geometry": {
    "type": "Point",
    "coordinates": [
      27.98861,
      41.02139
    ]
  }
}