{
  "type": "Feature",
  "properties": {
    "name": "Aichelberg",
    "country": "DE",
    "subdivision": "01",
    "timezone": "Europe/Berlin"
  },
  "geometry": {
    "type": "Point",
    "coordinates": [
      9.56373,
      48.63557
    ]
  }
}