{
  "type": "Feature",
  "properties": {
    "name": "Aitrach",
    "country": "DE",
    "subdivision": "01",
    "timezone": "Europe/Berlin"
  },
  "geometry": {
    "type": "Point",
    "coordinates": [
      10.08333,
      47.93333
    ]
  }
}