{
  "type": "Feature",
  "properties": {
    "name": "Asperg",
    "country": "DE",
    "subdivision": "01",
    "timezone": "Europe/Berlin"
  },
  "geometry": {
    "type": "Point",
    "coordinates": [
      9.13502,
      48.90525
    ]
  }
}