{
  "type": "Feature",
  "properties": {
    "name": "Au am Rhein",
    "country": "DE",
    "subdivision": "01",
    "timezone": "Europe/Berlin"
  },
  "geometry": {
    "type": "Point",
    "coordinates": [
      8.23333,
      48.95
    ]
  }
}