{
  "type": "Feature",
  "properties": {
    "name": "Bad Urach",
    "country": "DE",
    "subdivision": "01",
    "timezone": "Europe/Berlin"
  },
  "geometry": {
    "type": "Point",
    "coordinates": [
      9.40009,
      48.49107
    ]
  }
}