{
  "type": "Feature",
  "properties": {
    "name": "Bad Dürrheim",
    "country": "DE",
    "subdivision": "01",
    "timezone": "Europe/Berlin"
  },
  "geometry": {
    "type": "Point",
    "coordinates": [
      8.53056,
      48.02093
    ]
  }
}