{
  "type": "Feature",
  "properties": {
    "name": "Bad Saulgau",
    "country": "DE",
    "subdivision": "01",
    "timezone": "Europe/Berlin"
  },
  "geometry": {
    "type": "Point",
    "coordinates": [
      9.50064,
      48.01676
    ]
  }
}