{
  "type": "Feature",
  "properties": {
    "name": "Bad Rippoldsau-Schapbach",
    "country": "DE",
    "subdivision": "01",
    "timezone": "Europe/Berlin"
  },
  "geometry": {
    "type": "Point",
    "coordinates": [
      8.32584,
      48.42883
    ]
  }
}