{
  "type": "Feature",
  "properties": {
    "name": "Bad Ditzenbach",
    "country": "DE",
    "subdivision": "01",
    "timezone": "Europe/Berlin"
  },
  "geometry": {
    "type": "Point",
    "coordinates": [
      9.70393,
      48.5883
    ]
  }
}