{
  "type": "Feature",
  "properties": {
    "name": "Bad Buchau",
    "country": "DE",
    "subdivision": "01",
    "timezone": "Europe/Berlin"
  },
  "geometry": {
    "type": "Point",
    "coordinates": [
      9.61244,
      48.06231
    ]
  }
}