{
  "type": "Feature",
  "properties": {
    "name": "Bad Säckingen",
    "country": "DE",
    "subdivision": "01",
    "timezone": "Europe/Berlin"
  },
  "geometry": {
    "type": "Point",
    "coordinates": [
      7.94612,
      47.55371
    ]
  }
}