{
  "type": "Feature",
  "properties": {
    "name": "Baiersbronn",
    "country": "DE",
    "subdivision": "01",
    "timezone": "Europe/Berlin"
  },
  "geometry": {
    "type": "Point",
    "coordinates": [
      8.37699,
      48.50318
    ]
  }
}