{
  "type": "Feature",
  "properties": {
    "name": "Birenbach",
    "country": "DE",
    "subdivision": "01",
    "timezone": "Europe/Berlin"
  },
  "geometry": {
    "type": "Point",
    "coordinates": [
      9.66115,
      48.74732
    ]
  }
}