{
  "type": "Feature",
  "properties": {
    "name": "Böhmenkirch",
    "country": "DE",
    "subdivision": "01",
    "timezone": "Europe/Berlin"
  },
  "geometry": {
    "type": "Point",
    "coordinates": [
      9.93333,
      48.68333
    ]
  }
}