{
  "type": "Feature",
  "properties": {
    "name": "Breitnau",
    "country": "DE",
    "subdivision": "01",
    "timezone": "Europe/Berlin"
  },
  "geometry": {
    "type": "Point",
    "coordinates": [
      8.08333,
      47.93333
    ]
  }
}