{
  "type": "Feature",
  "properties": {
    "name": "Bubsheim",
    "country": "DE",
    "subdivision": "01",
    "timezone": "Europe/Berlin"
  },
  "geometry": {
    "type": "Point",
    "coordinates": [
      8.83333,
      48.11667
    ]
  }
}