{
  "type": "Feature",
  "properties": {
    "name": "Denkendorf",
    "country": "DE",
    "subdivision": "01",
    "timezone": "Europe/Berlin"
  },
  "geometry": {
    "type": "Point",
    "coordinates": [
      9.31675,
      48.69555
    ]
  }
}