{
  "type": "Feature",
  "properties": {
    "name": "Denkingen",
    "country": "DE",
    "subdivision": "01",
    "timezone": "Europe/Berlin"
  },
  "geometry": {
    "type": "Point",
    "coordinates": [
      8.7382,
      48.1111
    ]
  }
}