{
  "type": "Feature",
  "properties": {
    "name": "Dettingen",
    "country": "DE",
    "subdivision": "01",
    "timezone": "Europe/Berlin"
  },
  "geometry": {
    "type": "Point",
    "coordinates": [
      9.72161,
      48.26246
    ]
  }
}