{
  "type": "Feature",
  "properties": {
    "name": "Dettingen unter Teck",
    "country": "DE",
    "subdivision": "01",
    "timezone": "Europe/Berlin"
  },
  "geometry": {
    "type": "Point",
    "coordinates": [
      9.45,
      48.61667
    ]
  }
}