{
  "type": "Feature",
  "properties": {
    "name": "Donaueschingen",
    "country": "DE",
    "subdivision": "01",
    "timezone": "Europe/Berlin"
  },
  "geometry": {
    "type": "Point",
    "coordinates": [
      8.49707,
      47.95514
    ]
  }
}