{
  "type": "Feature",
  "properties": {
    "name": "Dormettingen",
    "country": "DE",
    "subdivision": "01",
    "timezone": "Europe/Berlin"
  },
  "geometry": {
    "type": "Point",
    "coordinates": [
      8.77327,
      48.23688
    ]
  }
}