{
  "type": "Feature",
  "properties": {
    "name": "Eberstadt",
    "country": "DE",
    "subdivision": "01",
    "timezone": "Europe/Berlin"
  },
  "geometry": {
    "type": "Point",
    "coordinates": [
      9.32111,
      49.18028
    ]
  }
}