{
  "type": "Feature",
  "properties": {
    "name": "Edingen-Neckarhausen",
    "country": "DE",
    "subdivision": "01",
    "timezone": "Europe/Berlin"
  },
  "geometry": {
    "type": "Point",
    "coordinates": [
      8.60639,
      49.45722
    ]
  }
}