{
  "type": "Feature",
  "properties": {
    "name": "Ellhofen",
    "country": "DE",
    "subdivision": "01",
    "timezone": "Europe/Berlin"
  },
  "geometry": {
    "type": "Point",
    "coordinates": [
      9.32194,
      49.14667
    ]
  }
}