{
  "type": "Feature",
  "properties": {
    "name": "Enzklösterle",
    "country": "DE",
    "subdivision": "01",
    "timezone": "Europe/Berlin"
  },
  "geometry": {
    "type": "Point",
    "coordinates": [
      8.47083,
      48.66638
    ]
  }
}