{
  "type": "Feature",
  "properties": {
    "name": "Eppelheim",
    "country": "DE",
    "subdivision": "01",
    "timezone": "Europe/Berlin"
  },
  "geometry": {
    "type": "Point",
    "coordinates": [
      8.63644,
      49.4019
    ]
  }
}