{
  "type": "Feature",
  "properties": {
    "name": "Erligheim",
    "country": "DE",
    "subdivision": "01",
    "timezone": "Europe/Berlin"
  },
  "geometry": {
    "type": "Point",
    "coordinates": [
      9.09722,
      49.0225
    ]
  }
}