{
  "type": "Feature",
  "properties": {
    "name": "Forst",
    "country": "DE",
    "subdivision": "01",
    "timezone": "Europe/Berlin"
  },
  "geometry": {
    "type": "Point",
    "coordinates": [
      8.58083,
      49.15861
    ]
  }
}