{
  "type": "Feature",
  "properties": {
    "name": "Freudental",
    "country": "DE",
    "subdivision": "01",
    "timezone": "Europe/Berlin"
  },
  "geometry": {
    "type": "Point",
    "coordinates": [
      9.05917,
      49.00972
    ]
  }
}