{
  "type": "Feature",
  "properties": {
    "name": "Friedenweiler",
    "country": "DE",
    "subdivision": "01",
    "timezone": "Europe/Berlin"
  },
  "geometry": {
    "type": "Point",
    "coordinates": [
      8.25627,
      47.91778
    ]
  }
}