{
  "type": "Feature",
  "properties": {
    "name": "Gärtringen",
    "country": "DE",
    "subdivision": "01",
    "timezone": "Europe/Berlin"
  },
  "geometry": {
    "type": "Point",
    "coordinates": [
      8.90073,
      48.64176
    ]
  }
}