{
  "type": "Feature",
  "properties": {
    "name": "Gengenbach",
    "country": "DE",
    "subdivision": "01",
    "timezone": "Europe/Berlin"
  },
  "geometry": {
    "type": "Point",
    "coordinates": [
      8.01433,
      48.40476
    ]
  }
}