{
  "type": "Feature",
  "properties": {
    "name": "Gerlingen",
    "country": "DE",
    "subdivision": "01",
    "timezone": "Europe/Berlin"
  },
  "geometry": {
    "type": "Point",
    "coordinates": [
      9.06316,
      48.79954
    ]
  }
}