{
  "type": "Feature",
  "properties": {
    "name": "Gingen an der Fils",
    "country": "DE",
    "subdivision": "01",
    "timezone": "Europe/Berlin"
  },
  "geometry": {
    "type": "Point",
    "coordinates": [
      9.78092,
      48.65979
    ]
  }
}