{
  "type": "Feature",
  "properties": {
    "name": "Graben-Neudorf",
    "country": "DE",
    "subdivision": "01",
    "timezone": "Europe/Berlin"
  },
  "geometry": {
    "type": "Point",
    "coordinates": [
      8.49243,
      49.16695
    ]
  }
}