{
  "type": "Feature",
  "properties": {
    "name": "Grafenau",
    "country": "DE",
    "subdivision": "01",
    "timezone": "Europe/Berlin"
  },
  "geometry": {
    "type": "Point",
    "coordinates": [
      8.91219,
      48.71427
    ]
  }
}