{
  "type": "Feature",
  "properties": {
    "name": "Grafenhausen",
    "country": "DE",
    "subdivision": "01",
    "timezone": "Europe/Berlin"
  },
  "geometry": {
    "type": "Point",
    "coordinates": [
      7.76678,
      48.28427
    ]
  }
}