{
  "type": "Feature",
  "properties": {
    "name": "Großbottwar",
    "country": "DE",
    "subdivision": "01",
    "timezone": "Europe/Berlin"
  },
  "geometry": {
    "type": "Point",
    "coordinates": [
      9.29348,
      49.00147
    ]
  }
}