{
  "type": "Feature",
  "properties": {
    "name": "Großbettlingen",
    "country": "DE",
    "subdivision": "01",
    "timezone": "Europe/Berlin"
  },
  "geometry": {
    "type": "Point",
    "coordinates": [
      9.30782,
      48.59052
    ]
  }
}