{
  "type": "Feature",
  "properties": {
    "name": "Gruibingen",
    "country": "DE",
    "subdivision": "01",
    "timezone": "Europe/Berlin"
  },
  "geometry": {
    "type": "Point",
    "coordinates": [
      9.64389,
      48.59483
    ]
  }
}