{
  "type": "Feature",
  "properties": {
    "name": "Güglingen",
    "country": "DE",
    "subdivision": "01",
    "timezone": "Europe/Berlin"
  },
  "geometry": {
    "type": "Point",
    "coordinates": [
      9.00175,
      49.06642
    ]
  }
}