{
  "type": "Feature",
  "properties": {
    "name": "Häusern",
    "country": "DE",
    "subdivision": "01",
    "timezone": "Europe/Berlin"
  },
  "geometry": {
    "type": "Point",
    "coordinates": [
      8.16667,
      47.75
    ]
  }
}