{
  "type": "Feature",
  "properties": {
    "name": "Hausen",
    "country": "DE",
    "subdivision": "01",
    "timezone": "Europe/Berlin"
  },
  "geometry": {
    "type": "Point",
    "coordinates": [
      7.83986,
      47.68128
    ]
  }
}