{
  "type": "Feature",
  "properties": {
    "name": "Heitersheim",
    "country": "DE",
    "subdivision": "01",
    "timezone": "Europe/Berlin"
  },
  "geometry": {
    "type": "Point",
    "coordinates": [
      7.65721,
      47.87468
    ]
  }
}