{
  "type": "Feature",
  "properties": {
    "name": "Helmstadt-Bargen",
    "country": "DE",
    "subdivision": "01",
    "timezone": "Europe/Berlin"
  },
  "geometry": {
    "type": "Point",
    "coordinates": [
      8.99712,
      49.31427
    ]
  }
}