{
  "type": "Feature",
  "properties": {
    "name": "Herbolzheim",
    "country": "DE",
    "subdivision": "01",
    "timezone": "Europe/Berlin"
  },
  "geometry": {
    "type": "Point",
    "coordinates": [
      7.77746,
      48.21884
    ]
  }
}