{
  "type": "Feature",
  "properties": {
    "name": "Herbertingen",
    "country": "DE",
    "subdivision": "01",
    "timezone": "Europe/Berlin"
  },
  "geometry": {
    "type": "Point",
    "coordinates": [
      9.43333,
      48.06667
    ]
  }
}