{
  "type": "Feature",
  "properties": {
    "name": "Hohentengen",
    "country": "DE",
    "subdivision": "01",
    "timezone": "Europe/Berlin"
  },
  "geometry": {
    "type": "Point",
    "coordinates": [
      9.37739,
      48.02946
    ]
  }
}