{
  "type": "Feature",
  "properties": {
    "name": "Höpfingen",
    "country": "DE",
    "subdivision": "01",
    "timezone": "Europe/Berlin"
  },
  "geometry": {
    "type": "Point",
    "coordinates": [
      9.42861,
      49.6025
    ]
  }
}