{
  "type": "Feature",
  "properties": {
    "name": "Hornberg",
    "country": "DE",
    "subdivision": "01",
    "timezone": "Europe/Berlin"
  },
  "geometry": {
    "type": "Point",
    "coordinates": [
      8.23275,
      48.21068
    ]
  }
}