{
  "type": "Feature",
  "properties": {
    "name": "Hüffenhardt",
    "country": "DE",
    "subdivision": "01",
    "timezone": "Europe/Berlin"
  },
  "geometry": {
    "type": "Point",
    "coordinates": [
      9.08167,
      49.29194
    ]
  }
}