{
  "type": "Feature",
  "properties": {
    "name": "Iffezheim",
    "country": "DE",
    "subdivision": "01",
    "timezone": "Europe/Berlin"
  },
  "geometry": {
    "type": "Point",
    "coordinates": [
      8.1431,
      48.82167
    ]
  }
}