{
  "type": "Feature",
  "properties": {
    "name": "Illingen",
    "country": "DE",
    "subdivision": "01",
    "timezone": "Europe/Berlin"
  },
  "geometry": {
    "type": "Point",
    "coordinates": [
      8.92459,
      48.95616
    ]
  }
}