{
  "type": "Feature",
  "properties": {
    "name": "Inzigkofen",
    "country": "DE",
    "subdivision": "01",
    "timezone": "Europe/Berlin"
  },
  "geometry": {
    "type": "Point",
    "coordinates": [
      9.17998,
      48.07034
    ]
  }
}