{
  "type": "Feature",
  "properties": {
    "name": "Kaisersbach",
    "country": "DE",
    "subdivision": "01",
    "timezone": "Europe/Berlin"
  },
  "geometry": {
    "type": "Point",
    "coordinates": [
      9.63898,
      48.93023
    ]
  }
}