{
  "type": "Feature",
  "properties": {
    "name": "Kirchdorf",
    "country": "DE",
    "subdivision": "01",
    "timezone": "Europe/Berlin"
  },
  "geometry": {
    "type": "Point",
    "coordinates": [
      10.12629,
      48.07667
    ]
  }
}