{
  "type": "Feature",
  "properties": {
    "name": "Kißlegg",
    "country": "DE",
    "subdivision": "01",
    "timezone": "Europe/Berlin"
  },
  "geometry": {
    "type": "Point",
    "coordinates": [
      9.88383,
      47.78894
    ]
  }
}