{
  "type": "Feature",
  "properties": {
    "name": "Krautheim",
    "country": "DE",
    "subdivision": "01",
    "timezone": "Europe/Berlin"
  },
  "geometry": {
    "type": "Point",
    "coordinates": [
      9.63553,
      49.38789
    ]
  }
}