{
  "type": "Feature",
  "properties": {
    "name": "Kuchen",
    "country": "DE",
    "subdivision": "01",
    "timezone": "Europe/Berlin"
  },
  "geometry": {
    "type": "Point",
    "coordinates": [
      9.79989,
      48.63583
    ]
  }
}