{
  "type": "Feature",
  "properties": {
    "name": "Ladenburg",
    "country": "DE",
    "subdivision": "01",
    "timezone": "Europe/Berlin"
  },
  "geometry": {
    "type": "Point",
    "coordinates": [
      8.60896,
      49.47307
    ]
  }
}