{
  "type": "Feature",
  "properties": {
    "name": "Langenau",
    "country": "DE",
    "subdivision": "01",
    "timezone": "Europe/Berlin"
  },
  "geometry": {
    "type": "Point",
    "coordinates": [
      10.11849,
      48.49616
    ]
  }
}