{
  "type": "Feature",
  "properties": {
    "name": "Lauchringen",
    "country": "DE",
    "subdivision": "01",
    "timezone": "Europe/Berlin"
  },
  "geometry": {
    "type": "Point",
    "coordinates": [
      8.31442,
      47.62699
    ]
  }
}