{
  "type": "Feature",
  "properties": {
    "name": "Lautenbach",
    "country": "DE",
    "subdivision": "01",
    "timezone": "Europe/Berlin"
  },
  "geometry": {
    "type": "Point",
    "coordinates": [
      8.02732,
      48.48185
    ]
  }
}