{
  "type": "Feature",
  "properties": {
    "name": "Lonsee",
    "country": "DE",
    "subdivision": "01",
    "timezone": "Europe/Berlin"
  },
  "geometry": {
    "type": "Point",
    "coordinates": [
      9.91999,
      48.5434
    ]
  }
}