{
  "type": "Feature",
  "properties": {
    "name": "Löwenstein",
    "country": "DE",
    "subdivision": "01",
    "timezone": "Europe/Berlin"
  },
  "geometry": {
    "type": "Point",
    "coordinates": [
      9.38,
      49.09558
    ]
  }
}