{
  "type": "Feature",
  "properties": {
    "name": "Mahlberg",
    "country": "DE",
    "subdivision": "01",
    "timezone": "Europe/Berlin"
  },
  "geometry": {
    "type": "Point",
    "coordinates": [
      7.81411,
      48.28639
    ]
  }
}