{
  "type": "Feature",
  "properties": {
    "name": "Meersburg",
    "country": "DE",
    "subdivision": "01",
    "timezone": "Europe/Berlin"
  },
  "geometry": {
    "type": "Point",
    "coordinates": [
      9.27113,
      47.69419
    ]
  }
}