{
  "type": "Feature",
  "properties": {
    "name": "Merklingen",
    "country": "DE",
    "subdivision": "01",
    "timezone": "Europe/Berlin"
  },
  "geometry": {
    "type": "Point",
    "coordinates": [
      9.75496,
      48.51135
    ]
  }
}