{
  "type": "Feature",
  "properties": {
    "name": "Michelfeld",
    "country": "DE",
    "subdivision": "01",
    "timezone": "Europe/Berlin"
  },
  "geometry": {
    "type": "Point",
    "coordinates": [
      9.67861,
      49.0975
    ]
  }
}