{
  "type": "Feature",
  "properties": {
    "name": "Mönsheim",
    "country": "DE",
    "subdivision": "01",
    "timezone": "Europe/Berlin"
  },
  "geometry": {
    "type": "Point",
    "coordinates": [
      8.86667,
      48.86667
    ]
  }
}