{
  "type": "Feature",
  "properties": {
    "name": "Moos",
    "country": "DE",
    "subdivision": "01",
    "timezone": "Europe/Berlin"
  },
  "geometry": {
    "type": "Point",
    "coordinates": [
      8.93479,
      47.72439
    ]
  }
}