{
  "type": "Feature",
  "properties": {
    "name": "Mühlhausen-Ehingen",
    "country": "DE",
    "subdivision": "01",
    "timezone": "Europe/Berlin"
  },
  "geometry": {
    "type": "Point",
    "coordinates": [
      8.81224,
      47.81102
    ]
  }
}