{
  "type": "Feature",
  "properties": {
    "name": "Neckartailfingen",
    "country": "DE",
    "subdivision": "01",
    "timezone": "Europe/Berlin"
  },
  "geometry": {
    "type": "Point",
    "coordinates": [
      9.26371,
      48.61172
    ]
  }
}