{
  "type": "Feature",
  "properties": {
    "name": "Neidenstein",
    "country": "DE",
    "subdivision": "01",
    "timezone": "Europe/Berlin"
  },
  "geometry": {
    "type": "Point",
    "coordinates": [
      8.88472,
      49.31667
    ]
  }
}