{
  "type": "Feature",
  "properties": {
    "name": "Nellingen",
    "country": "DE",
    "subdivision": "01",
    "timezone": "Europe/Berlin"
  },
  "geometry": {
    "type": "Point",
    "coordinates": [
      9.79053,
      48.54196
    ]
  }
}