{
  "type": "Feature",
  "properties": {
    "name": "Neudenau",
    "country": "DE",
    "subdivision": "01",
    "timezone": "Europe/Berlin"
  },
  "geometry": {
    "type": "Point",
    "coordinates": [
      9.26975,
      49.29181
    ]
  }
}