{
  "type": "Feature",
  "properties": {
    "name": "Neuler",
    "country": "DE",
    "subdivision": "01",
    "timezone": "Europe/Berlin"
  },
  "geometry": {
    "type": "Point",
    "coordinates": [
      10.06888,
      48.92803
    ]
  }
}