{
  "type": "Feature",
  "properties": {
    "name": "Nürtingen",
    "country": "DE",
    "subdivision": "01",
    "timezone": "Europe/Berlin"
  },
  "geometry": {
    "type": "Point",
    "coordinates": [
      9.34203,
      48.62565
    ]
  }
}