{
  "type": "Feature",
  "properties": {
    "name": "Oberrotweil",
    "country": "DE",
    "subdivision": "01",
    "timezone": "Europe/Berlin"
  },
  "geometry": {
    "type": "Point",
    "coordinates": [
      7.63601,
      48.0899
    ]
  }
}