{
  "type": "Feature",
  "properties": {
    "name": "Oberstadion",
    "country": "DE",
    "subdivision": "01",
    "timezone": "Europe/Berlin"
  },
  "geometry": {
    "type": "Point",
    "coordinates": [
      9.69241,
      48.18596
    ]
  }
}