{
  "type": "Feature",
  "properties": {
    "name": "Oberderdingen",
    "country": "DE",
    "subdivision": "01",
    "timezone": "Europe/Berlin"
  },
  "geometry": {
    "type": "Point",
    "coordinates": [
      8.80306,
      49.06556
    ]
  }
}