{
  "type": "Feature",
  "properties": {
    "name": "Oberjettingen",
    "country": "DE",
    "subdivision": "01",
    "timezone": "Europe/Berlin"
  },
  "geometry": {
    "type": "Point",
    "coordinates": [
      8.77636,
      48.57468
    ]
  }
}