{
  "type": "Feature",
  "properties": {
    "name": "Oberharmersbach",
    "country": "DE",
    "subdivision": "01",
    "timezone": "Europe/Berlin"
  },
  "geometry": {
    "type": "Point",
    "coordinates": [
      8.12542,
      48.37358
    ]
  }
}