{
  "type": "Feature",
  "properties": {
    "name": "Obrigheim",
    "country": "DE",
    "subdivision": "01",
    "timezone": "Europe/Berlin"
  },
  "geometry": {
    "type": "Point",
    "coordinates": [
      9.09083,
      49.35194
    ]
  }
}