{
  "type": "Feature",
  "properties": {
    "name": "Osterburken",
    "country": "DE",
    "subdivision": "01",
    "timezone": "Europe/Berlin"
  },
  "geometry": {
    "type": "Point",
    "coordinates": [
      9.42252,
      49.42997
    ]
  }
}