{
  "type": "Feature",
  "properties": {
    "name": "Pfullendorf",
    "country": "DE",
    "subdivision": "01",
    "timezone": "Europe/Berlin"
  },
  "geometry": {
    "type": "Point",
    "coordinates": [
      9.2578,
      47.9261
    ]
  }
}