{
  "type": "Feature",
  "properties": {
    "name": "Pleidelsheim",
    "country": "DE",
    "subdivision": "01",
    "timezone": "Europe/Berlin"
  },
  "geometry": {
    "type": "Point",
    "coordinates": [
      9.20311,
      48.9592
    ]
  }
}