{
  "type": "Feature",
  "properties": {
    "name": "Pliezhausen",
    "country": "DE",
    "subdivision": "01",
    "timezone": "Europe/Berlin"
  },
  "geometry": {
    "type": "Point",
    "coordinates": [
      9.20749,
      48.55934
    ]
  }
}