{
  "type": "Feature",
  "properties": {
    "name": "Rammingen",
    "country": "DE",
    "subdivision": "01",
    "timezone": "Europe/Berlin"
  },
  "geometry": {
    "type": "Point",
    "coordinates": [
      10.17197,
      48.51814
    ]
  }
}