{
  "type": "Feature",
  "properties": {
    "name": "Rosenberg",
    "country": "DE",
    "subdivision": "01",
    "timezone": "Europe/Berlin"
  },
  "geometry": {
    "type": "Point",
    "coordinates": [
      10.0296,
      49.01892
    ]
  }
}