{
  "type": "Feature",
  "properties": {
    "name": "Rudersberg",
    "country": "DE",
    "subdivision": "01",
    "timezone": "Europe/Berlin"
  },
  "geometry": {
    "type": "Point",
    "coordinates": [
      9.52927,
      48.88515
    ]
  }
}