{
  "type": "Feature",
  "properties": {
    "name": "Salach",
    "country": "DE",
    "subdivision": "01",
    "timezone": "Europe/Berlin"
  },
  "geometry": {
    "type": "Point",
    "coordinates": [
      9.73715,
      48.69198
    ]
  }
}