{
  "type": "Feature",
  "properties": {
    "name": "Sankt Peter",
    "country": "DE",
    "subdivision": "01",
    "timezone": "Europe/Berlin"
  },
  "geometry": {
    "type": "Point",
    "coordinates": [
      8.03294,
      48.01475
    ]
  }
}