{
  "type": "Feature",
  "properties": {
    "name": "Sankt Leon-Rot",
    "country": "DE",
    "subdivision": "01",
    "timezone": "Europe/Berlin"
  },
  "geometry": {
    "type": "Point",
    "coordinates": [
      8.61803,
      49.26593
    ]
  }
}