{
  "type": "Feature",
  "properties": {
    "name": "Schelklingen",
    "country": "DE",
    "subdivision": "01",
    "timezone": "Europe/Berlin"
  },
  "geometry": {
    "type": "Point",
    "coordinates": [
      9.73273,
      48.37575
    ]
  }
}