{
  "type": "Feature",
  "properties": {
    "name": "Scheer",
    "country": "DE",
    "subdivision": "01",
    "timezone": "Europe/Berlin"
  },
  "geometry": {
    "type": "Point",
    "coordinates": [
      9.29486,
      48.07292
    ]
  }
}