{
  "type": "Feature",
  "properties": {
    "name": "Schlaitdorf",
    "country": "DE",
    "subdivision": "01",
    "timezone": "Europe/Berlin"
  },
  "geometry": {
    "type": "Point",
    "coordinates": [
      9.22268,
      48.60431
    ]
  }
}