{
  "type": "Feature",
  "properties": {
    "name": "Schluchsee",
    "country": "DE",
    "subdivision": "01",
    "timezone": "Europe/Berlin"
  },
  "geometry": {
    "type": "Point",
    "coordinates": [
      8.18333,
      47.81667
    ]
  }
}