{
  "type": "Feature",
  "properties": {
    "name": "Schwaikheim",
    "country": "DE",
    "subdivision": "01",
    "timezone": "Europe/Berlin"
  },
  "geometry": {
    "type": "Point",
    "coordinates": [
      9.34958,
      48.87733
    ]
  }
}