{
  "type": "Feature",
  "properties": {
    "name": "Schwörstadt",
    "country": "DE",
    "subdivision": "01",
    "timezone": "Europe/Berlin"
  },
  "geometry": {
    "type": "Point",
    "coordinates": [
      7.8784,
      47.59314
    ]
  }
}