{
  "type": "Feature",
  "properties": {
    "name": "Seebach",
    "country": "DE",
    "subdivision": "01",
    "timezone": "Europe/Berlin"
  },
  "geometry": {
    "type": "Point",
    "coordinates": [
      8.17048,
      48.57621
    ]
  }
}