{
  "type": "Feature",
  "properties": {
    "name": "Sigmaringen",
    "country": "DE",
    "subdivision": "01",
    "timezone": "Europe/Berlin"
  },
  "geometry": {
    "type": "Point",
    "coordinates": [
      9.23033,
      48.08829
    ]
  }
}