{
  "type": "Feature",
  "properties": {
    "name": "Steinheim am Albuch",
    "country": "DE",
    "subdivision": "01",
    "timezone": "Europe/Berlin"
  },
  "geometry": {
    "type": "Point",
    "coordinates": [
      10.06382,
      48.6909
    ]
  }
}