{
  "type": "Feature",
  "properties": {
    "name": "Steinen",
    "country": "DE",
    "subdivision": "01",
    "timezone": "Europe/Berlin"
  },
  "geometry": {
    "type": "Point",
    "coordinates": [
      7.73914,
      47.64446
    ]
  }
}