{
  "type": "Feature",
  "properties": {
    "name": "Sternenfels",
    "country": "DE",
    "subdivision": "01",
    "timezone": "Europe/Berlin"
  },
  "geometry": {
    "type": "Point",
    "coordinates": [
      8.85083,
      49.05139
    ]
  }
}