{
  "type": "Feature",
  "properties": {
    "name": "Stuttgart Mühlhausen",
    "country": "DE",
    "subdivision": "01",
    "timezone": "Europe/Berlin"
  },
  "geometry": {
    "type": "Point",
    "coordinates": [
      9.23028,
      48.84232
    ]
  }
}