{
  "type": "Feature",
  "properties": {
    "name": "Sulz am Neckar",
    "country": "DE",
    "subdivision": "01",
    "timezone": "Europe/Berlin"
  },
  "geometry": {
    "type": "Point",
    "coordinates": [
      8.63309,
      48.36241
    ]
  }
}