{
  "type": "Feature",
  "properties": {
    "name": "Teningen",
    "country": "DE",
    "subdivision": "01",
    "timezone": "Europe/Berlin"
  },
  "geometry": {
    "type": "Point",
    "coordinates": [
      7.81205,
      48.12952
    ]
  }
}