{
  "type": "Feature",
  "properties": {
    "name": "Tennenbronn",
    "country": "DE",
    "subdivision": "01",
    "timezone": "Europe/Berlin"
  },
  "geometry": {
    "type": "Point",
    "coordinates": [
      8.35176,
      48.19041
    ]
  }
}