{
  "type": "Feature",
  "properties": {
    "name": "Ubstadt-Weiher",
    "country": "DE",
    "subdivision": "01",
    "timezone": "Europe/Berlin"
  },
  "geometry": {
    "type": "Point",
    "coordinates": [
      8.63165,
      49.16296
    ]
  }
}