{
  "type": "Feature",
  "properties": {
    "name": "Ulm",
    "country": "DE",
    "subdivision": "01",
    "timezone": "Europe/Berlin"
  },
  "geometry": {
    "type": "Point",
    "coordinates": [
      9.99155,
      48.39841
    ]
  }
}