{
  "type": "Feature",
  "properties": {
    "name": "Umkirch",
    "country": "DE",
    "subdivision": "01",
    "timezone": "Europe/Berlin"
  },
  "geometry": {
    "type": "Point",
    "coordinates": [
      7.76667,
      48.03333
    ]
  }
}