{
  "type": "Feature",
  "properties": {
    "name": "Villingen-Schwenningen",
    "country": "DE",
    "subdivision": "01",
    "timezone": "Europe/Berlin"
  },
  "geometry": {
    "type": "Point",
    "coordinates": [
      8.49358,
      48.06226
    ]
  }
}