{
  "type": "Feature",
  "properties": {
    "name": "Waibstadt",
    "country": "DE",
    "subdivision": "01",
    "timezone": "Europe/Berlin"
  },
  "geometry": {
    "type": "Point",
    "coordinates": [
      8.91771,
      49.29505
    ]
  }
}