{
  "type": "Feature",
  "properties": {
    "name": "Waldshut-Tiengen",
    "country": "DE",
    "subdivision": "01",
    "timezone": "Europe/Berlin"
  },
  "geometry": {
    "type": "Point",
    "coordinates": [
      8.21717,
      47.62323
    ]
  }
}