{
  "type": "Feature",
  "properties": {
    "name": "Wallhausen",
    "country": "DE",
    "subdivision": "01",
    "timezone": "Europe/Berlin"
  },
  "geometry": {
    "type": "Point",
    "coordinates": [
      10.06219,
      49.21042
    ]
  }
}