{
  "type": "Feature",
  "properties": {
    "name": "Walldorf",
    "country": "DE",
    "subdivision": "01",
    "timezone": "Europe/Berlin"
  },
  "geometry": {
    "type": "Point",
    "coordinates": [
      8.64236,
      49.30637
    ]
  }
}