{
  "type": "Feature",
  "properties": {
    "name": "Warthausen",
    "country": "DE",
    "subdivision": "01",
    "timezone": "Europe/Berlin"
  },
  "geometry": {
    "type": "Point",
    "coordinates": [
      9.79749,
      48.12863
    ]
  }
}