{
  "type": "Feature",
  "properties": {
    "name": "Weinsberg",
    "country": "DE",
    "subdivision": "01",
    "timezone": "Europe/Berlin"
  },
  "geometry": {
    "type": "Point",
    "coordinates": [
      9.28762,
      49.15127
    ]
  }
}