{
  "type": "Feature",
  "properties": {
    "name": "Weinstadt-Endersbach",
    "country": "DE",
    "subdivision": "01",
    "timezone": "Europe/Berlin"
  },
  "geometry": {
    "type": "Point",
    "coordinates": [
      9.36387,
      48.81311
    ]
  }
}