{
  "type": "Feature",
  "properties": {
    "name": "Welzheim",
    "country": "DE",
    "subdivision": "01",
    "timezone": "Europe/Berlin"
  },
  "geometry": {
    "type": "Point",
    "coordinates": [
      9.63434,
      48.87675
    ]
  }
}