{
  "type": "Feature",
  "properties": {
    "name": "Westerstetten",
    "country": "DE",
    "subdivision": "01",
    "timezone": "Europe/Berlin"
  },
  "geometry": {
    "type": "Point",
    "coordinates": [
      9.95494,
      48.51916
    ]
  }
}