{
  "type": "Feature",
  "properties": {
    "name": "Wiernsheim",
    "country": "DE",
    "subdivision": "01",
    "timezone": "Europe/Berlin"
  },
  "geometry": {
    "type": "Point",
    "coordinates": [
      8.85,
      48.88333
    ]
  }
}