{
  "type": "Feature",
  "properties": {
    "name": "Wiesensteig",
    "country": "DE",
    "subdivision": "01",
    "timezone": "Europe/Berlin"
  },
  "geometry": {
    "type": "Point",
    "coordinates": [
      9.6254,
      48.56127
    ]
  }
}