{
  "type": "Feature",
  "properties": {
    "name": "Wittnau",
    "country": "DE",
    "subdivision": "01",
    "timezone": "Europe/Berlin"
  },
  "geometry": {
    "type": "Point",
    "coordinates": [
      7.81667,
      47.95
    ]
  }
}