{
  "type": "Feature",
  "properties": {
    "name": "Wolfschlugen",
    "country": "DE",
    "subdivision": "01",
    "timezone": "Europe/Berlin"
  },
  "geometry": {
    "type": "Point",
    "coordinates": [
      9.28333,
      48.65
    ]
  }
}