{
  "type": "Feature",
  "properties": {
    "name": "Wolfegg",
    "country": "DE",
    "subdivision": "01",
    "timezone": "Europe/Berlin"
  },
  "geometry": {
    "type": "Point",
    "coordinates": [
      9.79491,
      47.8203
    ]
  }
}