{
  "type": "Feature",
  "properties": {
    "name": "Wurmberg",
    "country": "DE",
    "subdivision": "01",
    "timezone": "Europe/Berlin"
  },
  "geometry": {
    "type": "Point",
    "coordinates": [
      8.81667,
      48.86667
    ]
  }
}