{
  "type": "Feature",
  "properties": {
    "name": "Wutöschingen",
    "country": "DE",
    "subdivision": "01",
    "timezone": "Europe/Berlin"
  },
  "geometry": {
    "type": "Point",
    "coordinates": [
      8.36755,
      47.66019
    ]
  }
}