{
  "type": "Feature",
  "properties": {
    "name": "Soran",
    "country": "IQ",
    "subdivision": "11",
    "timezone": "Asia/Baghdad"
  },
  "geometry": {
    "type": "Point",
    "coordinates": [
      44.54407,
      36.6532
    ]
  }
}