{
  "type": "Feature",
  "properties": {
    "name": "Dekani",
    "country": "SI",
    "subdivision": "50",
    "timezone": "Europe/Ljubljana"
  },
  "geometry": {
    "type": "Point",
    "coordinates": [
      13.81361,
      45.54972
    ]
  }
}