{
  "type": "Feature",
  "properties": {
    "name": "Prade",
    "country": "SI",
    "subdivision": "50",
    "timezone": "Europe/Ljubljana"
  },
  "geometry": {
    "type": "Point",
    "coordinates": [
      13.77607,
      45.54003
    ]
  }
}