{
  "type": "Feature",
  "properties": {
    "name": "Hoogland",
    "country": "NL",
    "subdivision": "09",
    "timezone": "Europe/Amsterdam"
  },
  "geometry": {
    "type": "Point",
    "coordinates": [
      5.37361,
      52.1825
    ]
  }
}