{
  "type": "Feature",
  "properties": {
    "name": "Leersum",
    "country": "NL",
    "subdivision": "09",
    "timezone": "Europe/Amsterdam"
  },
  "geometry": {
    "type": "Point",
    "coordinates": [
      5.42778,
      52.01167
    ]
  }
}