{
  "type": "Feature",
  "properties": {
    "name": "Leerdam",
    "country": "NL",
    "subdivision": "09",
    "timezone": "Europe/Amsterdam"
  },
  "geometry": {
    "type": "Point",
    "coordinates": [
      5.09167,
      51.89333
    ]
  }
}