{
  "type": "Feature",
  "properties": {
    "name": "Oudewater",
    "country": "NL",
    "subdivision": "09",
    "timezone": "Europe/Amsterdam"
  },
  "geometry": {
    "type": "Point",
    "coordinates": [
      4.86806,
      52.025
    ]
  }
}