{
  "type": "Feature",
  "properties": {
    "name": "Demba",
    "country": "CD",
    "subdivision": "23",
    "timezone": "Africa/Lubumbashi"
  },
  "geometry": {
    "type": "Point",
    "coordinates": [
      22.26962,
      -5.49573
    ]
  }
}