{
  "type": "Feature",
  "properties": {
    "name": "Allangigan Primero",
    "country": "PH",
    "subdivision": "01",
    "timezone": "Asia/Manila"
  },
  "geometry": {
    "type": "Point",
    "coordinates": [
      120.49195,
      17.17393
    ]
  }
}