{
  "type": "Feature",
  "properties": {
    "name": "Bactad Proper",
    "country": "PH",
    "subdivision": "01",
    "timezone": "Asia/Manila"
  },
  "geometry": {
    "type": "Point",
    "coordinates": [
      120.61026,
      15.97842
    ]
  }
}