{
  "type": "Feature",
  "properties": {
    "name": "Bantog",
    "country": "PH",
    "subdivision": "01",
    "timezone": "Asia/Manila"
  },
  "geometry": {
    "type": "Point",
    "coordinates": [
      120.6929,
      16.0091
    ]
  }
}