{
  "type": "Feature",
  "properties": {
    "name": "Baro",
    "country": "PH",
    "subdivision": "01",
    "timezone": "Asia/Manila"
  },
  "geometry": {
    "type": "Point",
    "coordinates": [
      120.6735,
      15.99895
    ]
  }
}