{
  "type": "Feature",
  "properties": {
    "name": "Bauang",
    "country": "PH",
    "subdivision": "01",
    "timezone": "Asia/Manila"
  },
  "geometry": {
    "type": "Point",
    "coordinates": [
      120.33306,
      16.53083
    ]
  }
}