{
  "type": "Feature",
  "properties": {
    "name": "Bayambang",
    "country": "PH",
    "subdivision": "01",
    "timezone": "Asia/Manila"
  },
  "geometry": {
    "type": "Point",
    "coordinates": [
      120.4557,
      15.8127
    ]
  }
}