{
  "type": "Feature",
  "properties": {
    "name": "Binmaley",
    "country": "PH",
    "subdivision": "01",
    "timezone": "Asia/Manila"
  },
  "geometry": {
    "type": "Point",
    "coordinates": [
      120.26904,
      16.03232
    ]
  }
}