{
  "type": "Feature",
  "properties": {
    "name": "Bolaoit",
    "country": "PH",
    "subdivision": "01",
    "timezone": "Asia/Manila"
  },
  "geometry": {
    "type": "Point",
    "coordinates": [
      120.43073,
      15.93218
    ]
  }
}