{
  "type": "Feature",
  "properties": {
    "name": "Bolingit",
    "country": "PH",
    "subdivision": "01",
    "timezone": "Asia/Manila"
  },
  "geometry": {
    "type": "Point",
    "coordinates": [
      120.3496,
      15.95873
    ]
  }
}