{
  "type": "Feature",
  "properties": {
    "name": "Buenlag",
    "country": "PH",
    "subdivision": "01",
    "timezone": "Asia/Manila"
  },
  "geometry": {
    "type": "Point",
    "coordinates": [
      120.51139,
      15.82976
    ]
  }
}