{
  "type": "Feature",
  "properties": {
    "name": "Bugallon",
    "country": "PH",
    "subdivision": "01",
    "timezone": "Asia/Manila"
  },
  "geometry": {
    "type": "Point",
    "coordinates": [
      120.2155,
      15.9528
    ]
  }
}