{
  "type": "Feature",
  "properties": {
    "name": "Caba",
    "country": "PH",
    "subdivision": "01",
    "timezone": "Asia/Manila"
  },
  "geometry": {
    "type": "Point",
    "coordinates": [
      120.3446,
      16.4316
    ]
  }
}