{
  "type": "Feature",
  "properties": {
    "name": "Cantoria",
    "country": "PH",
    "subdivision": "01",
    "timezone": "Asia/Manila"
  },
  "geometry": {
    "type": "Point",
    "coordinates": [
      120.4045,
      16.8441
    ]
  }
}