{
  "type": "Feature",
  "properties": {
    "name": "Catablan",
    "country": "PH",
    "subdivision": "01",
    "timezone": "Asia/Manila"
  },
  "geometry": {
    "type": "Point",
    "coordinates": [
      120.4953,
      15.9757
    ]
  }
}