{
  "type": "Feature",
  "properties": {
    "name": "Cayungnan",
    "country": "PH",
    "subdivision": "01",
    "timezone": "Asia/Manila"
  },
  "geometry": {
    "type": "Point",
    "coordinates": [
      119.8375,
      16.1332
    ]
  }
}