{
  "type": "Feature",
  "properties": {
    "name": "Diaz",
    "country": "PH",
    "subdivision": "01",
    "timezone": "Asia/Manila"
  },
  "geometry": {
    "type": "Point",
    "coordinates": [
      120.8347,
      15.8463
    ]
  }
}