{
  "type": "Feature",
  "properties": {
    "name": "Espiritu",
    "country": "PH",
    "subdivision": "01",
    "timezone": "Asia/Manila"
  },
  "geometry": {
    "type": "Point",
    "coordinates": [
      120.6569,
      17.9809
    ]
  }
}