{
  "type": "Feature",
  "properties": {
    "name": "Infanta",
    "country": "PH",
    "subdivision": "01",
    "timezone": "Asia/Manila"
  },
  "geometry": {
    "type": "Point",
    "coordinates": [
      119.9077,
      15.8264
    ]
  }
}