{
  "type": "Feature",
  "properties": {
    "name": "Leones East",
    "country": "PH",
    "subdivision": "01",
    "timezone": "Asia/Manila"
  },
  "geometry": {
    "type": "Point",
    "coordinates": [
      120.3919,
      16.3633
    ]
  }
}