{
  "type": "Feature",
  "properties": {
    "name": "Lloren",
    "country": "PH",
    "subdivision": "01",
    "timezone": "Asia/Manila"
  },
  "geometry": {
    "type": "Point",
    "coordinates": [
      120.4329,
      16.3331
    ]
  }
}