{
  "type": "Feature",
  "properties": {
    "name": "Lobong",
    "country": "PH",
    "subdivision": "01",
    "timezone": "Asia/Manila"
  },
  "geometry": {
    "type": "Point",
    "coordinates": [
      120.4704,
      16.0815
    ]
  }
}