{
  "type": "Feature",
  "properties": {
    "name": "Macayug",
    "country": "PH",
    "subdivision": "01",
    "timezone": "Asia/Manila"
  },
  "geometry": {
    "type": "Point",
    "coordinates": [
      120.43201,
      16.09376
    ]
  }
}