{
  "type": "Feature",
  "properties": {
    "name": "Malanay",
    "country": "PH",
    "subdivision": "01",
    "timezone": "Asia/Manila"
  },
  "geometry": {
    "type": "Point",
    "coordinates": [
      120.4094,
      16.00865
    ]
  }
}