{
  "type": "Feature",
  "properties": {
    "name": "Polo",
    "country": "PH",
    "subdivision": "01",
    "timezone": "Asia/Manila"
  },
  "geometry": {
    "type": "Point",
    "coordinates": [
      119.9491,
      16.1963
    ]
  }
}