{
  "type": "Feature",
  "properties": {
    "name": "Pudoc",
    "country": "PH",
    "subdivision": "01",
    "timezone": "Asia/Manila"
  },
  "geometry": {
    "type": "Point",
    "coordinates": [
      120.4235,
      16.9215
    ]
  }
}