{
  "type": "Feature",
  "properties": {
    "name": "Quintong",
    "country": "PH",
    "subdivision": "01",
    "timezone": "Asia/Manila"
  },
  "geometry": {
    "type": "Point",
    "coordinates": [
      120.32171,
      15.95581
    ]
  }
}