{
  "type": "Feature",
  "properties": {
    "name": "Rosales",
    "country": "PH",
    "subdivision": "01",
    "timezone": "Asia/Manila"
  },
  "geometry": {
    "type": "Point",
    "coordinates": [
      120.63278,
      15.89444
    ]
  }
}