{
  "type": "Feature",
  "properties": {
    "name": "Samon",
    "country": "PH",
    "subdivision": "01",
    "timezone": "Asia/Manila"
  },
  "geometry": {
    "type": "Point",
    "coordinates": [
      120.65074,
      15.93495
    ]
  }
}