{
  "type": "Feature",
  "properties": {
    "name": "San Lorenzo",
    "country": "PH",
    "subdivision": "01",
    "timezone": "Asia/Manila"
  },
  "geometry": {
    "type": "Point",
    "coordinates": [
      120.6305,
      18.1323
    ]
  }
}