{
  "type": "Feature",
  "properties": {
    "name": "San Sebastian",
    "country": "PH",
    "subdivision": "01",
    "timezone": "Asia/Manila"
  },
  "geometry": {
    "type": "Point",
    "coordinates": [
      120.36352,
      17.62327
    ]
  }
}