{
  "type": "Feature",
  "properties": {
    "name": "San Eugenio",
    "country": "PH",
    "subdivision": "01",
    "timezone": "Asia/Manila"
  },
  "geometry": {
    "type": "Point",
    "coordinates": [
      120.357,
      16.3598
    ]
  }
}