{
  "type": "Feature",
  "properties": {
    "name": "Santa Cruz",
    "country": "PH",
    "subdivision": "01",
    "timezone": "Asia/Manila"
  },
  "geometry": {
    "type": "Point",
    "coordinates": [
      120.45222,
      17.08556
    ]
  }
}