{
  "type": "Feature",
  "properties": {
    "name": "Suso",
    "country": "PH",
    "subdivision": "01",
    "timezone": "Asia/Manila"
  },
  "geometry": {
    "type": "Point",
    "coordinates": [
      120.4611,
      17.3594
    ]
  }
}