{
  "type": "Feature",
  "properties": {
    "name": "Tabug",
    "country": "PH",
    "subdivision": "01",
    "timezone": "Asia/Manila"
  },
  "geometry": {
    "type": "Point",
    "coordinates": [
      120.5488,
      18.0343
    ]
  }
}