{
  "type": "Feature",
  "properties": {
    "name": "Tebag East",
    "country": "PH",
    "subdivision": "01",
    "timezone": "Asia/Manila"
  },
  "geometry": {
    "type": "Point",
    "coordinates": [
      120.4674,
      15.98123
    ]
  }
}