{
  "type": "Feature",
  "properties": {
    "name": "Tobuan",
    "country": "PH",
    "subdivision": "01",
    "timezone": "Asia/Manila"
  },
  "geometry": {
    "type": "Point",
    "coordinates": [
      120.11024,
      16.05562
    ]
  }
}