{
  "type": "Feature",
  "properties": {
    "name": "Umanday Centro",
    "country": "PH",
    "subdivision": "01",
    "timezone": "Asia/Manila"
  },
  "geometry": {
    "type": "Point",
    "coordinates": [
      120.2153,
      15.938
    ]
  }
}