{
  "type": "Feature",
  "properties": {
    "name": "Uyong",
    "country": "PH",
    "subdivision": "01",
    "timezone": "Asia/Manila"
  },
  "geometry": {
    "type": "Point",
    "coordinates": [
      120.12074,
      16.05002
    ]
  }
}