{
  "type": "Feature",
  "properties": {
    "name": "Abertillery",
    "country": "GB",
    "subdivision": "WLS",
    "timezone": "Europe/London"
  },
  "geometry": {
    "type": "Point",
    "coordinates": [
      -3.13432,
      51.72981
    ]
  }
}