{
  "type": "Feature",
  "properties": {
    "name": "Aberporth",
    "country": "GB",
    "subdivision": "WLS",
    "timezone": "Europe/London"
  },
  "geometry": {
    "type": "Point",
    "coordinates": [
      -4.54173,
      52.13248
    ]
  }
}