{
  "type": "Feature",
  "properties": {
    "name": "Aberdare",
    "country": "GB",
    "subdivision": "WLS",
    "timezone": "Europe/London"
  },
  "geometry": {
    "type": "Point",
    "coordinates": [
      -3.44918,
      51.71438
    ]
  }
}