{
  "type": "Feature",
  "properties": {
    "name": "Aberkenfig",
    "country": "GB",
    "subdivision": "WLS",
    "timezone": "Europe/London"
  },
  "geometry": {
    "type": "Point",
    "coordinates": [
      -3.59556,
      51.54
    ]
  }
}