{
  "type": "Feature",
  "properties": {
    "name": "Barry",
    "country": "GB",
    "subdivision": "WLS",
    "timezone": "Europe/London"
  },
  "geometry": {
    "type": "Point",
    "coordinates": [
      -3.2838,
      51.39979
    ]
  }
}