{
  "type": "Feature",
  "properties": {
    "name": "Beaumaris",
    "country": "GB",
    "subdivision": "WLS",
    "timezone": "Europe/London"
  },
  "geometry": {
    "type": "Point",
    "coordinates": [
      -4.09233,
      53.26315
    ]
  }
}