{
  "type": "Feature",
  "properties": {
    "name": "Blaenavon",
    "country": "GB",
    "subdivision": "WLS",
    "timezone": "Europe/London"
  },
  "geometry": {
    "type": "Point",
    "coordinates": [
      -3.08537,
      51.77402
    ]
  }
}