{
  "type": "Feature",
  "properties": {
    "name": "Builth Wells",
    "country": "GB",
    "subdivision": "WLS",
    "timezone": "Europe/London"
  },
  "geometry": {
    "type": "Point",
    "coordinates": [
      -3.40469,
      52.1494
    ]
  }
}