{
  "type": "Feature",
  "properties": {
    "name": "Caldicot",
    "country": "GB",
    "subdivision": "WLS",
    "timezone": "Europe/London"
  },
  "geometry": {
    "type": "Point",
    "coordinates": [
      -2.75736,
      51.58661
    ]
  }
}