{
  "type": "Feature",
  "properties": {
    "name": "Conwy",
    "country": "GB",
    "subdivision": "WLS",
    "timezone": "Europe/London"
  },
  "geometry": {
    "type": "Point",
    "coordinates": [
      -3.83039,
      53.28077
    ]
  }
}