{
  "type": "Feature",
  "properties": {
    "name": "Crofty",
    "country": "GB",
    "subdivision": "WLS",
    "timezone": "Europe/London"
  },
  "geometry": {
    "type": "Point",
    "coordinates": [
      -4.12937,
      51.63448
    ]
  }
}