{
  "type": "Feature",
  "properties": {
    "name": "Crynant",
    "country": "GB",
    "subdivision": "WLS",
    "timezone": "Europe/London"
  },
  "geometry": {
    "type": "Point",
    "coordinates": [
      -3.74806,
      51.72889
    ]
  }
}