{
  "type": "Feature",
  "properties": {
    "name": "Cwm",
    "country": "GB",
    "subdivision": "WLS",
    "timezone": "Europe/London"
  },
  "geometry": {
    "type": "Point",
    "coordinates": [
      -3.18028,
      51.74
    ]
  }
}