{
  "type": "Feature",
  "properties": {
    "name": "Fishguard",
    "country": "GB",
    "subdivision": "WLS",
    "timezone": "Europe/London"
  },
  "geometry": {
    "type": "Point",
    "coordinates": [
      -4.97631,
      51.99376
    ]
  }
}