{
  "type": "Feature",
  "properties": {
    "name": "Flint",
    "country": "GB",
    "subdivision": "WLS",
    "timezone": "Europe/London"
  },
  "geometry": {
    "type": "Point",
    "coordinates": [
      -3.13231,
      53.24488
    ]
  }
}