{
  "type": "Feature",
  "properties": {
    "name": "Gilfach Goch",
    "country": "GB",
    "subdivision": "WLS",
    "timezone": "Europe/London"
  },
  "geometry": {
    "type": "Point",
    "coordinates": [
      -3.47296,
      51.59213
    ]
  }
}