{
  "type": "Feature",
  "properties": {
    "name": "Haverfordwest",
    "country": "GB",
    "subdivision": "WLS",
    "timezone": "Europe/London"
  },
  "geometry": {
    "type": "Point",
    "coordinates": [
      -4.96914,
      51.80169
    ]
  }
}