{
  "type": "Feature",
  "properties": {
    "name": "Llandeilo",
    "country": "GB",
    "subdivision": "WLS",
    "timezone": "Europe/London"
  },
  "geometry": {
    "type": "Point",
    "coordinates": [
      -3.99154,
      51.88459
    ]
  }
}