{
  "type": "Feature",
  "properties": {
    "name": "Llanrwst",
    "country": "GB",
    "subdivision": "WLS",
    "timezone": "Europe/London"
  },
  "geometry": {
    "type": "Point",
    "coordinates": [
      -3.79527,
      53.14021
    ]
  }
}