{
  "type": "Feature",
  "properties": {
    "name": "Llanfairpwllgwyngyll",
    "country": "GB",
    "subdivision": "WLS",
    "timezone": "Europe/London"
  },
  "geometry": {
    "type": "Point",
    "coordinates": [
      -4.20329,
      53.22141
    ]
  }
}