{
  "type": "Feature",
  "properties": {
    "name": "Llantwit Major",
    "country": "GB",
    "subdivision": "WLS",
    "timezone": "Europe/London"
  },
  "geometry": {
    "type": "Point",
    "coordinates": [
      -3.48632,
      51.4107
    ]
  }
}