{
  "type": "Feature",
  "properties": {
    "name": "Llanharan",
    "country": "GB",
    "subdivision": "WLS",
    "timezone": "Europe/London"
  },
  "geometry": {
    "type": "Point",
    "coordinates": [
      -3.43906,
      51.53805
    ]
  }
}