{
  "type": "Feature",
  "properties": {
    "name": "Machen",
    "country": "GB",
    "subdivision": "WLS",
    "timezone": "Europe/London"
  },
  "geometry": {
    "type": "Point",
    "coordinates": [
      -3.1419,
      51.59599
    ]
  }
}