{
  "type": "Feature",
  "properties": {
    "name": "Magor",
    "country": "GB",
    "subdivision": "WLS",
    "timezone": "Europe/London"
  },
  "geometry": {
    "type": "Point",
    "coordinates": [
      -2.83139,
      51.57944
    ]
  }
}