{
  "type": "Feature",
  "properties": {
    "name": "Monmouth",
    "country": "GB",
    "subdivision": "WLS",
    "timezone": "Europe/London"
  },
  "geometry": {
    "type": "Point",
    "coordinates": [
      -2.71363,
      51.81265
    ]
  }
}