{
  "type": "Feature",
  "properties": {
    "name": "Northop",
    "country": "GB",
    "subdivision": "WLS",
    "timezone": "Europe/London"
  },
  "geometry": {
    "type": "Point",
    "coordinates": [
      -3.13277,
      53.20692
    ]
  }
}