{
  "type": "Feature",
  "properties": {
    "name": "Penparcau",
    "country": "GB",
    "subdivision": "WLS",
    "timezone": "Europe/London"
  },
  "geometry": {
    "type": "Point",
    "coordinates": [
      -4.07417,
      52.40333
    ]
  }
}