{
  "type": "Feature",
  "properties": {
    "name": "Pontyclun",
    "country": "GB",
    "subdivision": "WLS",
    "timezone": "Europe/London"
  },
  "geometry": {
    "type": "Point",
    "coordinates": [
      -3.39145,
      51.52162
    ]
  }
}