{
  "type": "Feature",
  "properties": {
    "name": "Pontypridd",
    "country": "GB",
    "subdivision": "WLS",
    "timezone": "Europe/London"
  },
  "geometry": {
    "type": "Point",
    "coordinates": [
      -3.34211,
      51.6021
    ]
  }
}