{
  "type": "Feature",
  "properties": {
    "name": "Rhuddlan",
    "country": "GB",
    "subdivision": "WLS",
    "timezone": "Europe/London"
  },
  "geometry": {
    "type": "Point",
    "coordinates": [
      -3.46996,
      53.29203
    ]
  }
}