{
  "type": "Feature",
  "properties": {
    "name": "Saint Clears",
    "country": "GB",
    "subdivision": "WLS",
    "timezone": "Europe/London"
  },
  "geometry": {
    "type": "Point",
    "coordinates": [
      -4.49783,
      51.81989
    ]
  }
}