{
  "type": "Feature",
  "properties": {
    "name": "Tal-y-bont",
    "country": "GB",
    "subdivision": "WLS",
    "timezone": "Europe/London"
  },
  "geometry": {
    "type": "Point",
    "coordinates": [
      -4.09224,
      52.77471
    ]
  }
}