{
  "type": "Feature",
  "properties": {
    "name": "Tonypandy",
    "country": "GB",
    "subdivision": "WLS",
    "timezone": "Europe/London"
  },
  "geometry": {
    "type": "Point",
    "coordinates": [
      -3.45544,
      51.62202
    ]
  }
}