{
  "type": "Feature",
  "properties": {
    "name": "Tonyrefail",
    "country": "GB",
    "subdivision": "WLS",
    "timezone": "Europe/London"
  },
  "geometry": {
    "type": "Point",
    "coordinates": [
      -3.43041,
      51.58402
    ]
  }
}