{
  "type": "Feature",
  "properties": {
    "name": "Treharris",
    "country": "GB",
    "subdivision": "WLS",
    "timezone": "Europe/London"
  },
  "geometry": {
    "type": "Point",
    "coordinates": [
      -3.30725,
      51.66457
    ]
  }
}