{
  "type": "Feature",
  "properties": {
    "name": "Wrexham",
    "country": "GB",
    "subdivision": "WLS",
    "timezone": "Europe/London"
  },
  "geometry": {
    "type": "Point",
    "coordinates": [
      -2.99132,
      53.04664
    ]
  }
}