{
  "type": "Feature",
  "properties": {
    "name": "Altglienicke",
    "country": "DE",
    "subdivision": "16",
    "timezone": "Europe/Berlin"
  },
  "geometry": {
    "type": "Point",
    "coordinates": [
      13.5355,
      52.41116
    ]
  }
}