{
  "type": "Feature",
  "properties": {
    "name": "Buch",
    "country": "DE",
    "subdivision": "16",
    "timezone": "Europe/Berlin"
  },
  "geometry": {
    "type": "Point",
    "coordinates": [
      13.49679,
      52.6347
    ]
  }
}