{
  "type": "Feature",
  "properties": {
    "name": "Buckow",
    "country": "DE",
    "subdivision": "16",
    "timezone": "Europe/Berlin"
  },
  "geometry": {
    "type": "Point",
    "coordinates": [
      13.46018,
      52.432
    ]
  }
}