{
  "type": "Feature",
  "properties": {
    "name": "Charlottenburg-Nord",
    "country": "DE",
    "subdivision": "16",
    "timezone": "Europe/Berlin"
  },
  "geometry": {
    "type": "Point",
    "coordinates": [
      13.29371,
      52.53048
    ]
  }
}