{
  "type": "Feature",
  "properties": {
    "name": "Karlshorst",
    "country": "DE",
    "subdivision": "16",
    "timezone": "Europe/Berlin"
  },
  "geometry": {
    "type": "Point",
    "coordinates": [
      13.53185,
      52.48419
    ]
  }
}