{
  "type": "Feature",
  "properties": {
    "name": "Kaulsdorf",
    "country": "DE",
    "subdivision": "16",
    "timezone": "Europe/Berlin"
  },
  "geometry": {
    "type": "Point",
    "coordinates": [
      13.58871,
      52.51732
    ]
  }
}