{
  "type": "Feature",
  "properties": {
    "name": "Lichtenrade",
    "country": "DE",
    "subdivision": "16",
    "timezone": "Europe/Berlin"
  },
  "geometry": {
    "type": "Point",
    "coordinates": [
      13.40637,
      52.39844
    ]
  }
}