{
  "type": "Feature",
  "properties": {
    "name": "Müggelheim",
    "country": "DE",
    "subdivision": "16",
    "timezone": "Europe/Berlin"
  },
  "geometry": {
    "type": "Point",
    "coordinates": [
      13.66403,
      52.41137
    ]
  }
}