{
  "type": "Feature",
  "properties": {
    "name": "Neu-Hohenschönhausen",
    "country": "DE",
    "subdivision": "16",
    "timezone": "Europe/Berlin"
  },
  "geometry": {
    "type": "Point",
    "coordinates": [
      13.51255,
      52.56681
    ]
  }
}