{
  "type": "Feature",
  "properties": {
    "name": "Spandau",
    "country": "DE",
    "subdivision": "16",
    "timezone": "Europe/Berlin"
  },
  "geometry": {
    "type": "Point",
    "coordinates": [
      13.19921,
      52.5511
    ]
  }
}