{
  "type": "Feature",
  "properties": {
    "name": "Staaken",
    "country": "DE",
    "subdivision": "16",
    "timezone": "Europe/Berlin"
  },
  "geometry": {
    "type": "Point",
    "coordinates": [
      13.15057,
      52.53661
    ]
  }
}