{
  "type": "Feature",
  "properties": {
    "name": "Wilhelmstadt",
    "country": "DE",
    "subdivision": "16",
    "timezone": "Europe/Berlin"
  },
  "geometry": {
    "type": "Point",
    "coordinates": [
      13.17707,
      52.52462
    ]
  }
}