{
  "type": "Feature",
  "properties": {
    "name": "Acquanegra sul Chiese",
    "country": "IT",
    "subdivision": "09",
    "timezone": "Europe/Rome"
  },
  "geometry": {
    "type": "Point",
    "coordinates": [
      10.43323,
      45.16404
    ]
  }
}