{
  "type": "Feature",
  "properties": {
    "name": "Albese Con Cassano",
    "country": "IT",
    "subdivision": "09",
    "timezone": "Europe/Rome"
  },
  "geometry": {
    "type": "Point",
    "coordinates": [
      9.16364,
      45.79488
    ]
  }
}