{
  "type": "Feature",
  "properties": {
    "name": "Alzate Brianza",
    "country": "IT",
    "subdivision": "09",
    "timezone": "Europe/Rome"
  },
  "geometry": {
    "type": "Point",
    "coordinates": [
      9.18204,
      45.76978
    ]
  }
}