{
  "type": "Feature",
  "properties": {
    "name": "Alzano Lombardo",
    "country": "IT",
    "subdivision": "09",
    "timezone": "Europe/Rome"
  },
  "geometry": {
    "type": "Point",
    "coordinates": [
      9.72638,
      45.73681
    ]
  }
}