{
  "type": "Feature",
  "properties": {
    "name": "Arlate",
    "country": "IT",
    "subdivision": "09",
    "timezone": "Europe/Rome"
  },
  "geometry": {
    "type": "Point",
    "coordinates": [
      9.44242,
      45.72363
    ]
  }
}