{
  "type": "Feature",
  "properties": {
    "name": "Arzago d'Adda",
    "country": "IT",
    "subdivision": "09",
    "timezone": "Europe/Rome"
  },
  "geometry": {
    "type": "Point",
    "coordinates": [
      9.56415,
      45.48137
    ]
  }
}