{
  "type": "Feature",
  "properties": {
    "name": "Barzago",
    "country": "IT",
    "subdivision": "09",
    "timezone": "Europe/Rome"
  },
  "geometry": {
    "type": "Point",
    "coordinates": [
      9.31424,
      45.75548
    ]
  }
}