{
  "type": "Feature",
  "properties": {
    "name": "Basiano",
    "country": "IT",
    "subdivision": "09",
    "timezone": "Europe/Rome"
  },
  "geometry": {
    "type": "Point",
    "coordinates": [
      9.46325,
      45.58248
    ]
  }
}