{
  "type": "Feature",
  "properties": {
    "name": "Battaglione-Bagnara",
    "country": "IT",
    "subdivision": "09",
    "timezone": "Europe/Rome"
  },
  "geometry": {
    "type": "Point",
    "coordinates": [
      10.06726,
      45.11638
    ]
  }
}