{
  "type": "Feature",
  "properties": {
    "name": "Bellusco",
    "country": "IT",
    "subdivision": "09",
    "timezone": "Europe/Rome"
  },
  "geometry": {
    "type": "Point",
    "coordinates": [
      9.41905,
      45.61958
    ]
  }
}