{
  "type": "Feature",
  "properties": {
    "name": "Besana in Brianza",
    "country": "IT",
    "subdivision": "09",
    "timezone": "Europe/Rome"
  },
  "geometry": {
    "type": "Point",
    "coordinates": [
      9.2947,
      45.70235
    ]
  }
}