{
  "type": "Feature",
  "properties": {
    "name": "Besnate",
    "country": "IT",
    "subdivision": "09",
    "timezone": "Europe/Rome"
  },
  "geometry": {
    "type": "Point",
    "coordinates": [
      8.76734,
      45.69858
    ]
  }
}