{
  "type": "Feature",
  "properties": {
    "name": "Bienno",
    "country": "IT",
    "subdivision": "09",
    "timezone": "Europe/Rome"
  },
  "geometry": {
    "type": "Point",
    "coordinates": [
      10.29232,
      45.93526
    ]
  }
}