{
  "type": "Feature",
  "properties": {
    "name": "Bizzarone",
    "country": "IT",
    "subdivision": "09",
    "timezone": "Europe/Rome"
  },
  "geometry": {
    "type": "Point",
    "coordinates": [
      8.94274,
      45.83428
    ]
  }
}