{
  "type": "Feature",
  "properties": {
    "name": "Bodio Lomnago",
    "country": "IT",
    "subdivision": "09",
    "timezone": "Europe/Rome"
  },
  "geometry": {
    "type": "Point",
    "coordinates": [
      8.75083,
      45.78867
    ]
  }
}