{
  "type": "Feature",
  "properties": {
    "name": "Boffalora d'Adda",
    "country": "IT",
    "subdivision": "09",
    "timezone": "Europe/Rome"
  },
  "geometry": {
    "type": "Point",
    "coordinates": [
      9.49628,
      45.35851
    ]
  }
}