{
  "type": "Feature",
  "properties": {
    "name": "Borgosatollo",
    "country": "IT",
    "subdivision": "09",
    "timezone": "Europe/Rome"
  },
  "geometry": {
    "type": "Point",
    "coordinates": [
      10.2403,
      45.4769
    ]
  }
}