{
  "type": "Feature",
  "properties": {
    "name": "Borgoforte",
    "country": "IT",
    "subdivision": "09",
    "timezone": "Europe/Rome"
  },
  "geometry": {
    "type": "Point",
    "coordinates": [
      10.75018,
      45.05185
    ]
  }
}