{
  "type": "Feature",
  "properties": {
    "name": "Borgarello",
    "country": "IT",
    "subdivision": "09",
    "timezone": "Europe/Rome"
  },
  "geometry": {
    "type": "Point",
    "coordinates": [
      9.14055,
      45.24066
    ]
  }
}