{
  "type": "Feature",
  "properties": {
    "name": "Bottanuco",
    "country": "IT",
    "subdivision": "09",
    "timezone": "Europe/Rome"
  },
  "geometry": {
    "type": "Point",
    "coordinates": [
      9.50903,
      45.63931
    ]
  }
}