{
  "type": "Feature",
  "properties": {
    "name": "Bovisio-Masciago",
    "country": "IT",
    "subdivision": "09",
    "timezone": "Europe/Rome"
  },
  "geometry": {
    "type": "Point",
    "coordinates": [
      9.15301,
      45.61019
    ]
  }
}