{
  "type": "Feature",
  "properties": {
    "name": "Brembio",
    "country": "IT",
    "subdivision": "09",
    "timezone": "Europe/Rome"
  },
  "geometry": {
    "type": "Point",
    "coordinates": [
      9.57244,
      45.21234
    ]
  }
}