{
  "type": "Feature",
  "properties": {
    "name": "Brembate",
    "country": "IT",
    "subdivision": "09",
    "timezone": "Europe/Rome"
  },
  "geometry": {
    "type": "Point",
    "coordinates": [
      9.5548,
      45.60468
    ]
  }
}