{
  "type": "Feature",
  "properties": {
    "name": "Brembilla",
    "country": "IT",
    "subdivision": "09",
    "timezone": "Europe/Rome"
  },
  "geometry": {
    "type": "Point",
    "coordinates": [
      9.59679,
      45.82154
    ]
  }
}