{
  "type": "Feature",
  "properties": {
    "name": "Brunate",
    "country": "IT",
    "subdivision": "09",
    "timezone": "Europe/Rome"
  },
  "geometry": {
    "type": "Point",
    "coordinates": [
      9.09869,
      45.82096
    ]
  }
}