{
  "type": "Feature",
  "properties": {
    "name": "Bulgarograsso",
    "country": "IT",
    "subdivision": "09",
    "timezone": "Europe/Rome"
  },
  "geometry": {
    "type": "Point",
    "coordinates": [
      9.00644,
      45.74708
    ]
  }
}