{
  "type": "Feature",
  "properties": {
    "name": "Cadrezzate",
    "country": "IT",
    "subdivision": "09",
    "timezone": "Europe/Rome"
  },
  "geometry": {
    "type": "Point",
    "coordinates": [
      8.64333,
      45.79927
    ]
  }
}