{
  "type": "Feature",
  "properties": {
    "name": "Calvatone",
    "country": "IT",
    "subdivision": "09",
    "timezone": "Europe/Rome"
  },
  "geometry": {
    "type": "Point",
    "coordinates": [
      10.44057,
      45.12697
    ]
  }
}