{
  "type": "Feature",
  "properties": {
    "name": "Cambiago",
    "country": "IT",
    "subdivision": "09",
    "timezone": "Europe/Rome"
  },
  "geometry": {
    "type": "Point",
    "coordinates": [
      9.43528,
      45.58035
    ]
  }
}