{
  "type": "Feature",
  "properties": {
    "name": "Cantalupo",
    "country": "IT",
    "subdivision": "09",
    "timezone": "Europe/Rome"
  },
  "geometry": {
    "type": "Point",
    "coordinates": [
      8.98261,
      45.57813
    ]
  }
}