{
  "type": "Feature",
  "properties": {
    "name": "Capriano del Colle",
    "country": "IT",
    "subdivision": "09",
    "timezone": "Europe/Rome"
  },
  "geometry": {
    "type": "Point",
    "coordinates": [
      10.13227,
      45.47478
    ]
  }
}