{
  "type": "Feature",
  "properties": {
    "name": "Carate Brianza",
    "country": "IT",
    "subdivision": "09",
    "timezone": "Europe/Rome"
  },
  "geometry": {
    "type": "Point",
    "coordinates": [
      9.23723,
      45.67574
    ]
  }
}