{
  "type": "Feature",
  "properties": {
    "name": "Casazza",
    "country": "IT",
    "subdivision": "09",
    "timezone": "Europe/Rome"
  },
  "geometry": {
    "type": "Point",
    "coordinates": [
      9.90627,
      45.74855
    ]
  }
}