{
  "type": "Feature",
  "properties": {
    "name": "Casone",
    "country": "IT",
    "subdivision": "09",
    "timezone": "Europe/Rome"
  },
  "geometry": {
    "type": "Point",
    "coordinates": [
      8.87635,
      45.49818
    ]
  }
}