{
  "type": "Feature",
  "properties": {
    "name": "Cassolnovo",
    "country": "IT",
    "subdivision": "09",
    "timezone": "Europe/Rome"
  },
  "geometry": {
    "type": "Point",
    "coordinates": [
      8.8123,
      45.36106
    ]
  }
}