{
  "type": "Feature",
  "properties": {
    "name": "Castelcovati",
    "country": "IT",
    "subdivision": "09",
    "timezone": "Europe/Rome"
  },
  "geometry": {
    "type": "Point",
    "coordinates": [
      9.94596,
      45.50198
    ]
  }
}