{
  "type": "Feature",
  "properties": {
    "name": "Castelverde",
    "country": "IT",
    "subdivision": "09",
    "timezone": "Europe/Rome"
  },
  "geometry": {
    "type": "Point",
    "coordinates": [
      9.99693,
      45.18753
    ]
  }
}