{
  "type": "Feature",
  "properties": {
    "name": "Castrezzato",
    "country": "IT",
    "subdivision": "09",
    "timezone": "Europe/Rome"
  },
  "geometry": {
    "type": "Point",
    "coordinates": [
      9.98086,
      45.51128
    ]
  }
}