{
  "type": "Feature",
  "properties": {
    "name": "Castel Goffredo",
    "country": "IT",
    "subdivision": "09",
    "timezone": "Europe/Rome"
  },
  "geometry": {
    "type": "Point",
    "coordinates": [
      10.473,
      45.29403
    ]
  }
}