{
  "type": "Feature",
  "properties": {
    "name": "Cavriana",
    "country": "IT",
    "subdivision": "09",
    "timezone": "Europe/Rome"
  },
  "geometry": {
    "type": "Point",
    "coordinates": [
      10.59598,
      45.34766
    ]
  }
}