{
  "type": "Feature",
  "properties": {
    "name": "Ceranova",
    "country": "IT",
    "subdivision": "09",
    "timezone": "Europe/Rome"
  },
  "geometry": {
    "type": "Point",
    "coordinates": [
      9.24315,
      45.26027
    ]
  }
}