{
  "type": "Feature",
  "properties": {
    "name": "Cerello-Battuello",
    "country": "IT",
    "subdivision": "09",
    "timezone": "Europe/Rome"
  },
  "geometry": {
    "type": "Point",
    "coordinates": [
      8.93105,
      45.44716
    ]
  }
}