{
  "type": "Feature",
  "properties": {
    "name": "Cerro al Lambro",
    "country": "IT",
    "subdivision": "09",
    "timezone": "Europe/Rome"
  },
  "geometry": {
    "type": "Point",
    "coordinates": [
      9.33905,
      45.32997
    ]
  }
}