{
  "type": "Feature",
  "properties": {
    "name": "Cesana Brianza",
    "country": "IT",
    "subdivision": "09",
    "timezone": "Europe/Rome"
  },
  "geometry": {
    "type": "Point",
    "coordinates": [
      9.29954,
      45.81678
    ]
  }
}