{
  "type": "Feature",
  "properties": {
    "name": "Chiaravalle",
    "country": "IT",
    "subdivision": "09",
    "timezone": "Europe/Rome"
  },
  "geometry": {
    "type": "Point",
    "coordinates": [
      9.23985,
      45.41731
    ]
  }
}