{
  "type": "Feature",
  "properties": {
    "name": "Chiari",
    "country": "IT",
    "subdivision": "09",
    "timezone": "Europe/Rome"
  },
  "geometry": {
    "type": "Point",
    "coordinates": [
      9.92699,
      45.53763
    ]
  }
}