{
  "type": "Feature",
  "properties": {
    "name": "Chiavenna",
    "country": "IT",
    "subdivision": "09",
    "timezone": "Europe/Rome"
  },
  "geometry": {
    "type": "Point",
    "coordinates": [
      9.39816,
      46.32063
    ]
  }
}