{
  "type": "Feature",
  "properties": {
    "name": "Cologne",
    "country": "IT",
    "subdivision": "09",
    "timezone": "Europe/Rome"
  },
  "geometry": {
    "type": "Point",
    "coordinates": [
      9.9418,
      45.57862
    ]
  }
}