{
  "type": "Feature",
  "properties": {
    "name": "Cormano",
    "country": "IT",
    "subdivision": "09",
    "timezone": "Europe/Rome"
  },
  "geometry": {
    "type": "Point",
    "coordinates": [
      9.15964,
      45.54917
    ]
  }
}