{
  "type": "Feature",
  "properties": {
    "name": "Costa-Barco",
    "country": "IT",
    "subdivision": "09",
    "timezone": "Europe/Rome"
  },
  "geometry": {
    "type": "Point",
    "coordinates": [
      10.03907,
      45.58337
    ]
  }
}