{
  "type": "Feature",
  "properties": {
    "name": "Cuasso al Piano",
    "country": "IT",
    "subdivision": "09",
    "timezone": "Europe/Rome"
  },
  "geometry": {
    "type": "Point",
    "coordinates": [
      8.87951,
      45.89454
    ]
  }
}