{
  "type": "Feature",
  "properties": {
    "name": "Delebio",
    "country": "IT",
    "subdivision": "09",
    "timezone": "Europe/Rome"
  },
  "geometry": {
    "type": "Point",
    "coordinates": [
      9.46157,
      46.13648
    ]
  }
}