{
  "type": "Feature",
  "properties": {
    "name": "Desio",
    "country": "IT",
    "subdivision": "09",
    "timezone": "Europe/Rome"
  },
  "geometry": {
    "type": "Point",
    "coordinates": [
      9.20249,
      45.61831
    ]
  }
}