{
  "type": "Feature",
  "properties": {
    "name": "Dosolo",
    "country": "IT",
    "subdivision": "09",
    "timezone": "Europe/Rome"
  },
  "geometry": {
    "type": "Point",
    "coordinates": [
      10.6355,
      44.95259
    ]
  }
}