{
  "type": "Feature",
  "properties": {
    "name": "Duomo",
    "country": "IT",
    "subdivision": "09",
    "timezone": "Europe/Rome"
  },
  "geometry": {
    "type": "Point",
    "coordinates": [
      10.02118,
      45.5324
    ]
  }
}