{
  "type": "Feature",
  "properties": {
    "name": "Flero",
    "country": "IT",
    "subdivision": "09",
    "timezone": "Europe/Rome"
  },
  "geometry": {
    "type": "Point",
    "coordinates": [
      10.17694,
      45.48254
    ]
  }
}