{
  "type": "Feature",
  "properties": {
    "name": "Gallo-Tre Re-Mezzana Corti",
    "country": "IT",
    "subdivision": "09",
    "timezone": "Europe/Rome"
  },
  "geometry": {
    "type": "Point",
    "coordinates": [
      9.12227,
      45.12563
    ]
  }
}