{
  "type": "Feature",
  "properties": {
    "name": "Gerenzano",
    "country": "IT",
    "subdivision": "09",
    "timezone": "Europe/Rome"
  },
  "geometry": {
    "type": "Point",
    "coordinates": [
      9.00104,
      45.63967
    ]
  }
}