{
  "type": "Feature",
  "properties": {
    "name": "Geromina",
    "country": "IT",
    "subdivision": "09",
    "timezone": "Europe/Rome"
  },
  "geometry": {
    "type": "Point",
    "coordinates": [
      9.5754,
      45.53645
    ]
  }
}