{
  "type": "Feature",
  "properties": {
    "name": "Gessate",
    "country": "IT",
    "subdivision": "09",
    "timezone": "Europe/Rome"
  },
  "geometry": {
    "type": "Point",
    "coordinates": [
      9.43775,
      45.54838
    ]
  }
}