{
  "type": "Feature",
  "properties": {
    "name": "Giussano",
    "country": "IT",
    "subdivision": "09",
    "timezone": "Europe/Rome"
  },
  "geometry": {
    "type": "Point",
    "coordinates": [
      9.2089,
      45.70004
    ]
  }
}