{
  "type": "Feature",
  "properties": {
    "name": "Gorla Maggiore",
    "country": "IT",
    "subdivision": "09",
    "timezone": "Europe/Rome"
  },
  "geometry": {
    "type": "Point",
    "coordinates": [
      8.89537,
      45.66388
    ]
  }
}