{
  "type": "Feature",
  "properties": {
    "name": "Gorlago",
    "country": "IT",
    "subdivision": "09",
    "timezone": "Europe/Rome"
  },
  "geometry": {
    "type": "Point",
    "coordinates": [
      9.82296,
      45.67408
    ]
  }
}