{
  "type": "Feature",
  "properties": {
    "name": "Gorno",
    "country": "IT",
    "subdivision": "09",
    "timezone": "Europe/Rome"
  },
  "geometry": {
    "type": "Point",
    "coordinates": [
      9.84155,
      45.86249
    ]
  }
}