{
  "type": "Feature",
  "properties": {
    "name": "Gottolengo",
    "country": "IT",
    "subdivision": "09",
    "timezone": "Europe/Rome"
  },
  "geometry": {
    "type": "Point",
    "coordinates": [
      10.26855,
      45.29278
    ]
  }
}