{
  "type": "Feature",
  "properties": {
    "name": "Grantola",
    "country": "IT",
    "subdivision": "09",
    "timezone": "Europe/Rome"
  },
  "geometry": {
    "type": "Point",
    "coordinates": [
      8.77433,
      45.94918
    ]
  }
}