{
  "type": "Feature",
  "properties": {
    "name": "Grumello del Monte",
    "country": "IT",
    "subdivision": "09",
    "timezone": "Europe/Rome"
  },
  "geometry": {
    "type": "Point",
    "coordinates": [
      9.87526,
      45.63535
    ]
  }
}