{
  "type": "Feature",
  "properties": {
    "name": "Gussola",
    "country": "IT",
    "subdivision": "09",
    "timezone": "Europe/Rome"
  },
  "geometry": {
    "type": "Point",
    "coordinates": [
      10.34894,
      45.01165
    ]
  }
}