{
  "type": "Feature",
  "properties": {
    "name": "Gussago",
    "country": "IT",
    "subdivision": "09",
    "timezone": "Europe/Rome"
  },
  "geometry": {
    "type": "Point",
    "coordinates": [
      10.15717,
      45.58358
    ]
  }
}