{
  "type": "Feature",
  "properties": {
    "name": "Imbersago",
    "country": "IT",
    "subdivision": "09",
    "timezone": "Europe/Rome"
  },
  "geometry": {
    "type": "Point",
    "coordinates": [
      9.44445,
      45.70588
    ]
  }
}