{
  "type": "Feature",
  "properties": {
    "name": "Izano",
    "country": "IT",
    "subdivision": "09",
    "timezone": "Europe/Rome"
  },
  "geometry": {
    "type": "Point",
    "coordinates": [
      9.75138,
      45.35552
    ]
  }
}