{
  "type": "Feature",
  "properties": {
    "name": "Lavena Ponte Tresa",
    "country": "IT",
    "subdivision": "09",
    "timezone": "Europe/Rome"
  },
  "geometry": {
    "type": "Point",
    "coordinates": [
      8.85725,
      45.9671
    ]
  }
}