{
  "type": "Feature",
  "properties": {
    "name": "Lierna",
    "country": "IT",
    "subdivision": "09",
    "timezone": "Europe/Rome"
  },
  "geometry": {
    "type": "Point",
    "coordinates": [
      9.30513,
      45.95818
    ]
  }
}