{
  "type": "Feature",
  "properties": {
    "name": "Lipomo",
    "country": "IT",
    "subdivision": "09",
    "timezone": "Europe/Rome"
  },
  "geometry": {
    "type": "Point",
    "coordinates": [
      9.12024,
      45.79288
    ]
  }
}