{
  "type": "Feature",
  "properties": {
    "name": "Locate Varesino",
    "country": "IT",
    "subdivision": "09",
    "timezone": "Europe/Rome"
  },
  "geometry": {
    "type": "Point",
    "coordinates": [
      8.92992,
      45.68969
    ]
  }
}