{
  "type": "Feature",
  "properties": {
    "name": "Lodetto",
    "country": "IT",
    "subdivision": "09",
    "timezone": "Europe/Rome"
  },
  "geometry": {
    "type": "Point",
    "coordinates": [
      10.03175,
      45.55099
    ]
  }
}