{
  "type": "Feature",
  "properties": {
    "name": "Lograto",
    "country": "IT",
    "subdivision": "09",
    "timezone": "Europe/Rome"
  },
  "geometry": {
    "type": "Point",
    "coordinates": [
      10.05664,
      45.48458
    ]
  }
}