{
  "type": "Feature",
  "properties": {
    "name": "Ludriano",
    "country": "IT",
    "subdivision": "09",
    "timezone": "Europe/Rome"
  },
  "geometry": {
    "type": "Point",
    "coordinates": [
      9.93276,
      45.44846
    ]
  }
}