{
  "type": "Feature",
  "properties": {
    "name": "Lurago d'Erba",
    "country": "IT",
    "subdivision": "09",
    "timezone": "Europe/Rome"
  },
  "geometry": {
    "type": "Point",
    "coordinates": [
      9.21817,
      45.75097
    ]
  }
}