{
  "type": "Feature",
  "properties": {
    "name": "Macherio",
    "country": "IT",
    "subdivision": "09",
    "timezone": "Europe/Rome"
  },
  "geometry": {
    "type": "Point",
    "coordinates": [
      9.27394,
      45.63974
    ]
  }
}