{
  "type": "Feature",
  "properties": {
    "name": "Madone",
    "country": "IT",
    "subdivision": "09",
    "timezone": "Europe/Rome"
  },
  "geometry": {
    "type": "Point",
    "coordinates": [
      9.55015,
      45.65028
    ]
  }
}