{
  "type": "Feature",
  "properties": {
    "name": "Mantova",
    "country": "IT",
    "subdivision": "09",
    "timezone": "Europe/Rome"
  },
  "geometry": {
    "type": "Point",
    "coordinates": [
      10.79784,
      45.16031
    ]
  }
}