{
  "type": "Feature",
  "properties": {
    "name": "Marcignago",
    "country": "IT",
    "subdivision": "09",
    "timezone": "Europe/Rome"
  },
  "geometry": {
    "type": "Point",
    "coordinates": [
      9.07935,
      45.25306
    ]
  }
}