{
  "type": "Feature",
  "properties": {
    "name": "Mariano Comense",
    "country": "IT",
    "subdivision": "09",
    "timezone": "Europe/Rome"
  },
  "geometry": {
    "type": "Point",
    "coordinates": [
      9.1818,
      45.69651
    ]
  }
}