{
  "type": "Feature",
  "properties": {
    "name": "Marudo",
    "country": "IT",
    "subdivision": "09",
    "timezone": "Europe/Rome"
  },
  "geometry": {
    "type": "Point",
    "coordinates": [
      9.37716,
      45.25297
    ]
  }
}