{
  "type": "Feature",
  "properties": {
    "name": "Medolago",
    "country": "IT",
    "subdivision": "09",
    "timezone": "Europe/Rome"
  },
  "geometry": {
    "type": "Point",
    "coordinates": [
      9.49807,
      45.67129
    ]
  }
}