{
  "type": "Feature",
  "properties": {
    "name": "Milzano",
    "country": "IT",
    "subdivision": "09",
    "timezone": "Europe/Rome"
  },
  "geometry": {
    "type": "Point",
    "coordinates": [
      10.19927,
      45.27358
    ]
  }
}