{
  "type": "Feature",
  "properties": {
    "name": "Moglia",
    "country": "IT",
    "subdivision": "09",
    "timezone": "Europe/Rome"
  },
  "geometry": {
    "type": "Point",
    "coordinates": [
      10.91463,
      44.93561
    ]
  }
}