{
  "type": "Feature",
  "properties": {
    "name": "Molteno",
    "country": "IT",
    "subdivision": "09",
    "timezone": "Europe/Rome"
  },
  "geometry": {
    "type": "Point",
    "coordinates": [
      9.30386,
      45.77819
    ]
  }
}