{
  "type": "Feature",
  "properties": {
    "name": "Moncucco",
    "country": "IT",
    "subdivision": "09",
    "timezone": "Europe/Rome"
  },
  "geometry": {
    "type": "Point",
    "coordinates": [
      9.0392,
      45.31032
    ]
  }
}