{
  "type": "Feature",
  "properties": {
    "name": "Monte Marenzo",
    "country": "IT",
    "subdivision": "09",
    "timezone": "Europe/Rome"
  },
  "geometry": {
    "type": "Point",
    "coordinates": [
      9.45476,
      45.77213
    ]
  }
}