{
  "type": "Feature",
  "properties": {
    "name": "Montanaso Lombardo",
    "country": "IT",
    "subdivision": "09",
    "timezone": "Europe/Rome"
  },
  "geometry": {
    "type": "Point",
    "coordinates": [
      9.46551,
      45.33522
    ]
  }
}