{
  "type": "Feature",
  "properties": {
    "name": "Montano Lucino",
    "country": "IT",
    "subdivision": "09",
    "timezone": "Europe/Rome"
  },
  "geometry": {
    "type": "Point",
    "coordinates": [
      9.04244,
      45.78378
    ]
  }
}