{
  "type": "Feature",
  "properties": {
    "name": "Morbegno",
    "country": "IT",
    "subdivision": "09",
    "timezone": "Europe/Rome"
  },
  "geometry": {
    "type": "Point",
    "coordinates": [
      9.57415,
      46.1372
    ]
  }
}