{
  "type": "Feature",
  "properties": {
    "name": "Nigoline-Bonomelli",
    "country": "IT",
    "subdivision": "09",
    "timezone": "Europe/Rome"
  },
  "geometry": {
    "type": "Point",
    "coordinates": [
      9.98682,
      45.62908
    ]
  }
}