{
  "type": "Feature",
  "properties": {
    "name": "Novegro-Tregarezzo-San Felice",
    "country": "IT",
    "subdivision": "09",
    "timezone": "Europe/Rome"
  },
  "geometry": {
    "type": "Point",
    "coordinates": [
      9.28122,
      45.46778
    ]
  }
}