{
  "type": "Feature",
  "properties": {
    "name": "Noviglio",
    "country": "IT",
    "subdivision": "09",
    "timezone": "Europe/Rome"
  },
  "geometry": {
    "type": "Point",
    "coordinates": [
      9.05215,
      45.35907
    ]
  }
}