{
  "type": "Feature",
  "properties": {
    "name": "Nuvolento",
    "country": "IT",
    "subdivision": "09",
    "timezone": "Europe/Rome"
  },
  "geometry": {
    "type": "Point",
    "coordinates": [
      10.38809,
      45.54599
    ]
  }
}