{
  "type": "Feature",
  "properties": {
    "name": "Oggiono",
    "country": "IT",
    "subdivision": "09",
    "timezone": "Europe/Rome"
  },
  "geometry": {
    "type": "Point",
    "coordinates": [
      9.34815,
      45.79133
    ]
  }
}