{
  "type": "Feature",
  "properties": {
    "name": "Orio al Serio",
    "country": "IT",
    "subdivision": "09",
    "timezone": "Europe/Rome"
  },
  "geometry": {
    "type": "Point",
    "coordinates": [
      9.69083,
      45.6749
    ]
  }
}