{
  "type": "Feature",
  "properties": {
    "name": "Ostiglia",
    "country": "IT",
    "subdivision": "09",
    "timezone": "Europe/Rome"
  },
  "geometry": {
    "type": "Point",
    "coordinates": [
      11.13499,
      45.06978
    ]
  }
}