{
  "type": "Feature",
  "properties": {
    "name": "Ottobiano",
    "country": "IT",
    "subdivision": "09",
    "timezone": "Europe/Rome"
  },
  "geometry": {
    "type": "Point",
    "coordinates": [
      8.83198,
      45.15418
    ]
  }
}