{
  "type": "Feature",
  "properties": {
    "name": "Paderno Dugnano",
    "country": "IT",
    "subdivision": "09",
    "timezone": "Europe/Rome"
  },
  "geometry": {
    "type": "Point",
    "coordinates": [
      9.16483,
      45.56899
    ]
  }
}