{
  "type": "Feature",
  "properties": {
    "name": "Parmezzana Calzana",
    "country": "IT",
    "subdivision": "09",
    "timezone": "Europe/Rome"
  },
  "geometry": {
    "type": "Point",
    "coordinates": [
      10.0954,
      45.6335
    ]
  }
}