{
  "type": "Feature",
  "properties": {
    "name": "Pavia",
    "country": "IT",
    "subdivision": "09",
    "timezone": "Europe/Rome"
  },
  "geometry": {
    "type": "Point",
    "coordinates": [
      9.15917,
      45.19205
    ]
  }
}