{
  "type": "Feature",
  "properties": {
    "name": "Peia",
    "country": "IT",
    "subdivision": "09",
    "timezone": "Europe/Rome"
  },
  "geometry": {
    "type": "Point",
    "coordinates": [
      9.89926,
      45.79949
    ]
  }
}