{
  "type": "Feature",
  "properties": {
    "name": "Pianico",
    "country": "IT",
    "subdivision": "09",
    "timezone": "Europe/Rome"
  },
  "geometry": {
    "type": "Point",
    "coordinates": [
      10.04306,
      45.80989
    ]
  }
}