{
  "type": "Feature",
  "properties": {
    "name": "Pieve del Cairo",
    "country": "IT",
    "subdivision": "09",
    "timezone": "Europe/Rome"
  },
  "geometry": {
    "type": "Point",
    "coordinates": [
      8.80322,
      45.0492
    ]
  }
}