{
  "type": "Feature",
  "properties": {
    "name": "Poggio Rusco",
    "country": "IT",
    "subdivision": "09",
    "timezone": "Europe/Rome"
  },
  "geometry": {
    "type": "Point",
    "coordinates": [
      11.10419,
      44.96693
    ]
  }
}