{
  "type": "Feature",
  "properties": {
    "name": "Pogliano Milanese",
    "country": "IT",
    "subdivision": "09",
    "timezone": "Europe/Rome"
  },
  "geometry": {
    "type": "Point",
    "coordinates": [
      8.99403,
      45.53786
    ]
  }
}