{
  "type": "Feature",
  "properties": {
    "name": "Polpenazze del Garda",
    "country": "IT",
    "subdivision": "09",
    "timezone": "Europe/Rome"
  },
  "geometry": {
    "type": "Point",
    "coordinates": [
      10.50488,
      45.55118
    ]
  }
}