{
  "type": "Feature",
  "properties": {
    "name": "Pompiano",
    "country": "IT",
    "subdivision": "09",
    "timezone": "Europe/Rome"
  },
  "geometry": {
    "type": "Point",
    "coordinates": [
      9.9891,
      45.43116
    ]
  }
}