{
  "type": "Feature",
  "properties": {
    "name": "Ponte Nossa",
    "country": "IT",
    "subdivision": "09",
    "timezone": "Europe/Rome"
  },
  "geometry": {
    "type": "Point",
    "coordinates": [
      9.88364,
      45.86611
    ]
  }
}