{
  "type": "Feature",
  "properties": {
    "name": "Pontirolo Nuovo",
    "country": "IT",
    "subdivision": "09",
    "timezone": "Europe/Rome"
  },
  "geometry": {
    "type": "Point",
    "coordinates": [
      9.56935,
      45.56918
    ]
  }
}