{
  "type": "Feature",
  "properties": {
    "name": "Ponte San Pietro",
    "country": "IT",
    "subdivision": "09",
    "timezone": "Europe/Rome"
  },
  "geometry": {
    "type": "Point",
    "coordinates": [
      9.5905,
      45.70596
    ]
  }
}