{
  "type": "Feature",
  "properties": {
    "name": "Ponte in Valtellina",
    "country": "IT",
    "subdivision": "09",
    "timezone": "Europe/Rome"
  },
  "geometry": {
    "type": "Point",
    "coordinates": [
      9.97785,
      46.175
    ]
  }
}