{
  "type": "Feature",
  "properties": {
    "name": "Porto d'Adda",
    "country": "IT",
    "subdivision": "09",
    "timezone": "Europe/Rome"
  },
  "geometry": {
    "type": "Point",
    "coordinates": [
      9.47563,
      45.66241
    ]
  }
}