{
  "type": "Feature",
  "properties": {
    "name": "Puginate",
    "country": "IT",
    "subdivision": "09",
    "timezone": "Europe/Rome"
  },
  "geometry": {
    "type": "Point",
    "coordinates": [
      9.05772,
      45.71095
    ]
  }
}