{
  "type": "Feature",
  "properties": {
    "name": "Quartiano",
    "country": "IT",
    "subdivision": "09",
    "timezone": "Europe/Rome"
  },
  "geometry": {
    "type": "Point",
    "coordinates": [
      9.4176,
      45.358
    ]
  }
}