{
  "type": "Feature",
  "properties": {
    "name": "Raffa",
    "country": "IT",
    "subdivision": "09",
    "timezone": "Europe/Rome"
  },
  "geometry": {
    "type": "Point",
    "coordinates": [
      10.52962,
      45.57047
    ]
  }
}