{
  "type": "Feature",
  "properties": {
    "name": "Roncadelle",
    "country": "IT",
    "subdivision": "09",
    "timezone": "Europe/Rome"
  },
  "geometry": {
    "type": "Point",
    "coordinates": [
      10.15407,
      45.52718
    ]
  }
}