{
  "type": "Feature",
  "properties": {
    "name": "Roncoferraro",
    "country": "IT",
    "subdivision": "09",
    "timezone": "Europe/Rome"
  },
  "geometry": {
    "type": "Point",
    "coordinates": [
      10.9421,
      45.13812
    ]
  }
}