{
  "type": "Feature",
  "properties": {
    "name": "Salerano sul Lambro",
    "country": "IT",
    "subdivision": "09",
    "timezone": "Europe/Rome"
  },
  "geometry": {
    "type": "Point",
    "coordinates": [
      9.38515,
      45.29657
    ]
  }
}