{
  "type": "Feature",
  "properties": {
    "name": "Salice Terme",
    "country": "IT",
    "subdivision": "09",
    "timezone": "Europe/Rome"
  },
  "geometry": {
    "type": "Point",
    "coordinates": [
      9.0263,
      44.9151
    ]
  }
}