{
  "type": "Feature",
  "properties": {
    "name": "Samarate",
    "country": "IT",
    "subdivision": "09",
    "timezone": "Europe/Rome"
  },
  "geometry": {
    "type": "Point",
    "coordinates": [
      8.78507,
      45.6241
    ]
  }
}