{
  "type": "Feature",
  "properties": {
    "name": "Samolaco",
    "country": "IT",
    "subdivision": "09",
    "timezone": "Europe/Rome"
  },
  "geometry": {
    "type": "Point",
    "coordinates": [
      9.39404,
      46.24249
    ]
  }
}