{
  "type": "Feature",
  "properties": {
    "name": "San Fiorano",
    "country": "IT",
    "subdivision": "09",
    "timezone": "Europe/Rome"
  },
  "geometry": {
    "type": "Point",
    "coordinates": [
      9.72063,
      45.13815
    ]
  }
}