{
  "type": "Feature",
  "properties": {
    "name": "San Martino in Strada",
    "country": "IT",
    "subdivision": "09",
    "timezone": "Europe/Rome"
  },
  "geometry": {
    "type": "Point",
    "coordinates": [
      9.52636,
      45.27497
    ]
  }
}