{
  "type": "Feature",
  "properties": {
    "name": "San Giacomo",
    "country": "IT",
    "subdivision": "09",
    "timezone": "Europe/Rome"
  },
  "geometry": {
    "type": "Point",
    "coordinates": [
      10.02532,
      46.16019
    ]
  }
}