{
  "type": "Feature",
  "properties": {
    "name": "Sannazzaro de' Burgondi",
    "country": "IT",
    "subdivision": "09",
    "timezone": "Europe/Rome"
  },
  "geometry": {
    "type": "Point",
    "coordinates": [
      8.90635,
      45.10226
    ]
  }
}