{
  "type": "Feature",
  "properties": {
    "name": "Santa Corinna",
    "country": "IT",
    "subdivision": "09",
    "timezone": "Europe/Rome"
  },
  "geometry": {
    "type": "Point",
    "coordinates": [
      9.08878,
      45.34018
    ]
  }
}