{
  "type": "Feature",
  "properties": {
    "name": "Scano al Brembo",
    "country": "IT",
    "subdivision": "09",
    "timezone": "Europe/Rome"
  },
  "geometry": {
    "type": "Point",
    "coordinates": [
      9.60905,
      45.71858
    ]
  }
}