{
  "type": "Feature",
  "properties": {
    "name": "Schivenoglia",
    "country": "IT",
    "subdivision": "09",
    "timezone": "Europe/Rome"
  },
  "geometry": {
    "type": "Point",
    "coordinates": [
      11.073,
      44.99498
    ]
  }
}