{
  "type": "Feature",
  "properties": {
    "name": "Seriate",
    "country": "IT",
    "subdivision": "09",
    "timezone": "Europe/Rome"
  },
  "geometry": {
    "type": "Point",
    "coordinates": [
      9.72487,
      45.68532
    ]
  }
}