{
  "type": "Feature",
  "properties": {
    "name": "Seveso",
    "country": "IT",
    "subdivision": "09",
    "timezone": "Europe/Rome"
  },
  "geometry": {
    "type": "Point",
    "coordinates": [
      9.14296,
      45.6467
    ]
  }
}