{
  "type": "Feature",
  "properties": {
    "name": "Solaro",
    "country": "IT",
    "subdivision": "09",
    "timezone": "Europe/Rome"
  },
  "geometry": {
    "type": "Point",
    "coordinates": [
      9.08304,
      45.61427
    ]
  }
}