{
  "type": "Feature",
  "properties": {
    "name": "Solbiate",
    "country": "IT",
    "subdivision": "09",
    "timezone": "Europe/Rome"
  },
  "geometry": {
    "type": "Point",
    "coordinates": [
      8.93314,
      45.78968
    ]
  }
}