{
  "type": "Feature",
  "properties": {
    "name": "Spino d'Adda",
    "country": "IT",
    "subdivision": "09",
    "timezone": "Europe/Rome"
  },
  "geometry": {
    "type": "Point",
    "coordinates": [
      9.48674,
      45.40086
    ]
  }
}