{
  "type": "Feature",
  "properties": {
    "name": "Suello",
    "country": "IT",
    "subdivision": "09",
    "timezone": "Europe/Rome"
  },
  "geometry": {
    "type": "Point",
    "coordinates": [
      9.31154,
      45.81678
    ]
  }
}