{
  "type": "Feature",
  "properties": {
    "name": "Torbole Casaglia",
    "country": "IT",
    "subdivision": "09",
    "timezone": "Europe/Rome"
  },
  "geometry": {
    "type": "Point",
    "coordinates": [
      10.117,
      45.51279
    ]
  }
}