{
  "type": "Feature",
  "properties": {
    "name": "Trescore Cremasco",
    "country": "IT",
    "subdivision": "09",
    "timezone": "Europe/Rome"
  },
  "geometry": {
    "type": "Point",
    "coordinates": [
      9.62278,
      45.40298
    ]
  }
}