{
  "type": "Feature",
  "properties": {
    "name": "Treviglio",
    "country": "IT",
    "subdivision": "09",
    "timezone": "Europe/Rome"
  },
  "geometry": {
    "type": "Point",
    "coordinates": [
      9.59102,
      45.52081
    ]
  }
}