{
  "type": "Feature",
  "properties": {
    "name": "Triuggio",
    "country": "IT",
    "subdivision": "09",
    "timezone": "Europe/Rome"
  },
  "geometry": {
    "type": "Point",
    "coordinates": [
      9.26691,
      45.66144
    ]
  }
}