{
  "type": "Feature",
  "properties": {
    "name": "Uboldo",
    "country": "IT",
    "subdivision": "09",
    "timezone": "Europe/Rome"
  },
  "geometry": {
    "type": "Point",
    "coordinates": [
      9.00394,
      45.61527
    ]
  }
}