{
  "type": "Feature",
  "properties": {
    "name": "Valdisotto",
    "country": "IT",
    "subdivision": "09",
    "timezone": "Europe/Rome"
  },
  "geometry": {
    "type": "Point",
    "coordinates": [
      10.35695,
      46.43441
    ]
  }
}