{
  "type": "Feature",
  "properties": {
    "name": "Valera Fratta",
    "country": "IT",
    "subdivision": "09",
    "timezone": "Europe/Rome"
  },
  "geometry": {
    "type": "Point",
    "coordinates": [
      9.33615,
      45.25717
    ]
  }
}