{
  "type": "Feature",
  "properties": {
    "name": "Vaprio d'Adda",
    "country": "IT",
    "subdivision": "09",
    "timezone": "Europe/Rome"
  },
  "geometry": {
    "type": "Point",
    "coordinates": [
      9.52407,
      45.5764
    ]
  }
}