{
  "type": "Feature",
  "properties": {
    "name": "Varedo",
    "country": "IT",
    "subdivision": "09",
    "timezone": "Europe/Rome"
  },
  "geometry": {
    "type": "Point",
    "coordinates": [
      9.16323,
      45.59761
    ]
  }
}