{
  "type": "Feature",
  "properties": {
    "name": "Velasca",
    "country": "IT",
    "subdivision": "09",
    "timezone": "Europe/Rome"
  },
  "geometry": {
    "type": "Point",
    "coordinates": [
      9.35519,
      45.63165
    ]
  }
}