{
  "type": "Feature",
  "properties": {
    "name": "Vellezzo Bellini",
    "country": "IT",
    "subdivision": "09",
    "timezone": "Europe/Rome"
  },
  "geometry": {
    "type": "Point",
    "coordinates": [
      9.10088,
      45.26948
    ]
  }
}