{
  "type": "Feature",
  "properties": {
    "name": "Vertemate Con Minoprio",
    "country": "IT",
    "subdivision": "09",
    "timezone": "Europe/Rome"
  },
  "geometry": {
    "type": "Point",
    "coordinates": [
      9.073,
      45.72518
    ]
  }
}