{
  "type": "Feature",
  "properties": {
    "name": "Villa Pedergnano",
    "country": "IT",
    "subdivision": "09",
    "timezone": "Europe/Rome"
  },
  "geometry": {
    "type": "Point",
    "coordinates": [
      9.99381,
      45.58528
    ]
  }
}