{
  "type": "Feature",
  "properties": {
    "name": "Villa Raverio",
    "country": "IT",
    "subdivision": "09",
    "timezone": "Europe/Rome"
  },
  "geometry": {
    "type": "Point",
    "coordinates": [
      9.26239,
      45.69189
    ]
  }
}