{
  "type": "Feature",
  "properties": {
    "name": "Villasanta",
    "country": "IT",
    "subdivision": "09",
    "timezone": "Europe/Rome"
  },
  "geometry": {
    "type": "Point",
    "coordinates": [
      9.30797,
      45.60634
    ]
  }
}