{
  "type": "Feature",
  "properties": {
    "name": "Voghera",
    "country": "IT",
    "subdivision": "09",
    "timezone": "Europe/Rome"
  },
  "geometry": {
    "type": "Point",
    "coordinates": [
      9.01175,
      44.99151
    ]
  }
}