{
  "type": "Feature",
  "properties": {
    "name": "Zanica",
    "country": "IT",
    "subdivision": "09",
    "timezone": "Europe/Rome"
  },
  "geometry": {
    "type": "Point",
    "coordinates": [
      9.68566,
      45.64088
    ]
  }
}