{
  "type": "Feature",
  "properties": {
    "name": "Atani",
    "country": "NG",
    "subdivision": "25",
    "timezone": "Africa/Lagos"
  },
  "geometry": {
    "type": "Point",
    "coordinates": [
      6.74768,
      6.01277
    ]
  }
}