{
  "type": "Feature",
  "properties": {
    "name": "Ozubulu",
    "country": "NG",
    "subdivision": "25",
    "timezone": "Africa/Lagos"
  },
  "geometry": {
    "type": "Point",
    "coordinates": [
      6.85305,
      5.95753
    ]
  }
}