{
  "type": "Feature",
  "properties": {
    "name": "Uruobo-Okija",
    "country": "NG",
    "subdivision": "25",
    "timezone": "Africa/Lagos"
  },
  "geometry": {
    "type": "Point",
    "coordinates": [
      6.84312,
      5.90016
    ]
  }
}