{
  "type": "Feature",
  "properties": {
    "name": "Dubreuil",
    "country": "MU",
    "subdivision": "15",
    "timezone": "Indian/Mauritius"
  },
  "geometry": {
    "type": "Point",
    "coordinates": [
      57.59861,
      -20.30132
    ]
  }
}