{
  "type": "Feature",
  "properties": {
    "name": "Pailles",
    "country": "MU",
    "subdivision": "15",
    "timezone": "Indian/Mauritius"
  },
  "geometry": {
    "type": "Point",
    "coordinates": [
      57.48826,
      -20.19271
    ]
  }
}