{
  "type": "Feature",
  "properties": {
    "name": "Caconda",
    "country": "AO",
    "subdivision": "09",
    "timezone": "Africa/Luanda"
  },
  "geometry": {
    "type": "Point",
    "coordinates": [
      15.06667,
      -13.73333
    ]
  }
}