{
  "type": "Feature",
  "properties": {
    "name": "Lubango",
    "country": "AO",
    "subdivision": "09",
    "timezone": "Africa/Luanda"
  },
  "geometry": {
    "type": "Point",
    "coordinates": [
      13.4925,
      -14.91717
    ]
  }
}