{
  "type": "Feature",
  "properties": {
    "name": "Albota",
    "country": "RO",
    "subdivision": "03",
    "timezone": "Europe/Bucharest"
  },
  "geometry": {
    "type": "Point",
    "coordinates": [
      24.85,
      44.78333
    ]
  }
}