{
  "type": "Feature",
  "properties": {
    "name": "Albota de Jos",
    "country": "RO",
    "subdivision": "03",
    "timezone": "Europe/Bucharest"
  },
  "geometry": {
    "type": "Point",
    "coordinates": [
      24.83333,
      44.76667
    ]
  }
}