{
  "type": "Feature",
  "properties": {
    "name": "Dâmbovicioara",
    "country": "RO",
    "subdivision": "03",
    "timezone": "Europe/Bucharest"
  },
  "geometry": {
    "type": "Point",
    "coordinates": [
      25.23333,
      45.45
    ]
  }
}