{
  "type": "Feature",
  "properties": {
    "name": "Gălășești",
    "country": "RO",
    "subdivision": "03",
    "timezone": "Europe/Bucharest"
  },
  "geometry": {
    "type": "Point",
    "coordinates": [
      24.78602,
      44.95593
    ]
  }
}