{
  "type": "Feature",
  "properties": {
    "name": "Lereşti",
    "country": "RO",
    "subdivision": "03",
    "timezone": "Europe/Bucharest"
  },
  "geometry": {
    "type": "Point",
    "coordinates": [
      25.06667,
      45.33333
    ]
  }
}