{
  "type": "Feature",
  "properties": {
    "name": "Miroşi",
    "country": "RO",
    "subdivision": "03",
    "timezone": "Europe/Bucharest"
  },
  "geometry": {
    "type": "Point",
    "coordinates": [
      24.93333,
      44.41667
    ]
  }
}