{
  "type": "Feature",
  "properties": {
    "name": "Piteşti",
    "country": "RO",
    "subdivision": "03",
    "timezone": "Europe/Bucharest"
  },
  "geometry": {
    "type": "Point",
    "coordinates": [
      24.86667,
      44.85
    ]
  }
}