{
  "type": "Feature",
  "properties": {
    "name": "Poienari",
    "country": "RO",
    "subdivision": "03",
    "timezone": "Europe/Bucharest"
  },
  "geometry": {
    "type": "Point",
    "coordinates": [
      25.05,
      45.21667
    ]
  }
}