{
  "type": "Feature",
  "properties": {
    "name": "Șerbănești",
    "country": "RO",
    "subdivision": "03",
    "timezone": "Europe/Bucharest"
  },
  "geometry": {
    "type": "Point",
    "coordinates": [
      24.99236,
      44.68142
    ]
  }
}