{
  "type": "Feature",
  "properties": {
    "name": "Șerboeni",
    "country": "RO",
    "subdivision": "03",
    "timezone": "Europe/Bucharest"
  },
  "geometry": {
    "type": "Point",
    "coordinates": [
      24.89355,
      44.63818
    ]
  }
}