{
  "type": "Feature",
  "properties": {
    "name": "Tigveni",
    "country": "RO",
    "subdivision": "03",
    "timezone": "Europe/Bucharest"
  },
  "geometry": {
    "type": "Point",
    "coordinates": [
      24.58333,
      45.13333
    ]
  }
}