{
  "type": "Feature",
  "properties": {
    "name": "Valea Popii",
    "country": "RO",
    "subdivision": "03",
    "timezone": "Europe/Bucharest"
  },
  "geometry": {
    "type": "Point",
    "coordinates": [
      25.0224,
      45.09253
    ]
  }
}