{
  "type": "Feature",
  "properties": {
    "name": "Vlădești",
    "country": "RO",
    "subdivision": "03",
    "timezone": "Europe/Bucharest"
  },
  "geometry": {
    "type": "Point",
    "coordinates": [
      24.91667,
      45.15
    ]
  }
}