{
  "type": "Feature",
  "properties": {
    "name": "Furukawa",
    "country": "JP",
    "subdivision": "24",
    "timezone": "Asia/Tokyo"
  },
  "geometry": {
    "type": "Point",
    "coordinates": [
      140.95556,
      38.57167
    ]
  }
}