{
  "type": "Feature",
  "properties": {
    "name": "Rifu",
    "country": "JP",
    "subdivision": "24",
    "timezone": "Asia/Tokyo"
  },
  "geometry": {
    "type": "Point",
    "coordinates": [
      140.97691,
      38.33092
    ]
  }
}