{
  "type": "Feature",
  "properties": {
    "name": "BeÄov",
    "country": "CZ",
    "subdivision": "89",
    "timezone": "Europe/Prague"
  },
  "geometry": {
    "type": "Point",
    "coordinates": [
      13.71784,
      50.44972
    ]
  }
}