{
  "type": "Feature",
  "properties": {
    "name": "Chomutov",
    "country": "CZ",
    "subdivision": "89",
    "timezone": "Europe/Prague"
  },
  "geometry": {
    "type": "Point",
    "coordinates": [
      13.41779,
      50.46048
    ]
  }
}