{
  "type": "Feature",
  "properties": {
    "name": "Chřibská",
    "country": "CZ",
    "subdivision": "89",
    "timezone": "Europe/Prague"
  },
  "geometry": {
    "type": "Point",
    "coordinates": [
      14.48444,
      50.86079
    ]
  }
}