{
  "type": "Feature",
  "properties": {
    "name": "Čížkovice",
    "country": "CZ",
    "subdivision": "89",
    "timezone": "Europe/Prague"
  },
  "geometry": {
    "type": "Point",
    "coordinates": [
      14.02839,
      50.48418
    ]
  }
}