{
  "type": "Feature",
  "properties": {
    "name": "Děčín",
    "country": "CZ",
    "subdivision": "89",
    "timezone": "Europe/Prague"
  },
  "geometry": {
    "type": "Point",
    "coordinates": [
      14.21478,
      50.78215
    ]
  }
}