{
  "type": "Feature",
  "properties": {
    "name": "Dolní Podluží",
    "country": "CZ",
    "subdivision": "89",
    "timezone": "Europe/Prague"
  },
  "geometry": {
    "type": "Point",
    "coordinates": [
      14.59503,
      50.87988
    ]
  }
}