{
  "type": "Feature",
  "properties": {
    "name": "Horní Jiřetín",
    "country": "CZ",
    "subdivision": "89",
    "timezone": "Europe/Prague"
  },
  "geometry": {
    "type": "Point",
    "coordinates": [
      13.54717,
      50.57309
    ]
  }
}