{
  "type": "Feature",
  "properties": {
    "name": "Hrob",
    "country": "CZ",
    "subdivision": "89",
    "timezone": "Europe/Prague"
  },
  "geometry": {
    "type": "Point",
    "coordinates": [
      13.72676,
      50.65919
    ]
  }
}