{
  "type": "Feature",
  "properties": {
    "name": "Lenešice",
    "country": "CZ",
    "subdivision": "89",
    "timezone": "Europe/Prague"
  },
  "geometry": {
    "type": "Point",
    "coordinates": [
      13.7659,
      50.37516
    ]
  }
}