{
  "type": "Feature",
  "properties": {
    "name": "Libochovice",
    "country": "CZ",
    "subdivision": "89",
    "timezone": "Europe/Prague"
  },
  "geometry": {
    "type": "Point",
    "coordinates": [
      14.04439,
      50.40626
    ]
  }
}