{
  "type": "Feature",
  "properties": {
    "name": "Litvínov",
    "country": "CZ",
    "subdivision": "89",
    "timezone": "Europe/Prague"
  },
  "geometry": {
    "type": "Point",
    "coordinates": [
      13.61812,
      50.6042
    ]
  }
}