{
  "type": "Feature",
  "properties": {
    "name": "Mikulášovice",
    "country": "CZ",
    "subdivision": "89",
    "timezone": "Europe/Prague"
  },
  "geometry": {
    "type": "Point",
    "coordinates": [
      14.36368,
      50.96507
    ]
  }
}