{
  "type": "Feature",
  "properties": {
    "name": "Novosedlice",
    "country": "CZ",
    "subdivision": "89",
    "timezone": "Europe/Prague"
  },
  "geometry": {
    "type": "Point",
    "coordinates": [
      13.82304,
      50.65633
    ]
  }
}