{
  "type": "Feature",
  "properties": {
    "name": "Velemín",
    "country": "CZ",
    "subdivision": "89",
    "timezone": "Europe/Prague"
  },
  "geometry": {
    "type": "Point",
    "coordinates": [
      13.97675,
      50.53898
    ]
  }
}