{
  "type": "Feature",
  "properties": {
    "name": "Velké Březno",
    "country": "CZ",
    "subdivision": "89",
    "timezone": "Europe/Prague"
  },
  "geometry": {
    "type": "Point",
    "coordinates": [
      14.14174,
      50.6627
    ]
  }
}