{
  "type": "Feature",
  "properties": {
    "name": "Astudillo",
    "country": "ES",
    "subdivision": "55",
    "timezone": "Europe/Madrid"
  },
  "geometry": {
    "type": "Point",
    "coordinates": [
      -4.29394,
      42.1933
    ]
  }
}