{
  "type": "Feature",
  "properties": {
    "name": "Ávila",
    "country": "ES",
    "subdivision": "55",
    "timezone": "Europe/Madrid"
  },
  "geometry": {
    "type": "Point",
    "coordinates": [
      -4.69951,
      40.65724
    ]
  }
}