{
  "type": "Feature",
  "properties": {
    "name": "Ayllón",
    "country": "ES",
    "subdivision": "55",
    "timezone": "Europe/Madrid"
  },
  "geometry": {
    "type": "Point",
    "coordinates": [
      -3.37537,
      41.41899
    ]
  }
}