{
  "type": "Feature",
  "properties": {
    "name": "Bembibre",
    "country": "ES",
    "subdivision": "55",
    "timezone": "Europe/Madrid"
  },
  "geometry": {
    "type": "Point",
    "coordinates": [
      -6.41545,
      42.61771
    ]
  }
}