{
  "type": "Feature",
  "properties": {
    "name": "Bustillo del Páramo",
    "country": "ES",
    "subdivision": "55",
    "timezone": "Europe/Madrid"
  },
  "geometry": {
    "type": "Point",
    "coordinates": [
      -5.7928,
      42.44126
    ]
  }
}