{
  "type": "Feature",
  "properties": {
    "name": "Calvarrasa de Abajo",
    "country": "ES",
    "subdivision": "55",
    "timezone": "Europe/Madrid"
  },
  "geometry": {
    "type": "Point",
    "coordinates": [
      -5.55258,
      40.94638
    ]
  }
}