{
  "type": "Feature",
  "properties": {
    "name": "Cantalpino",
    "country": "ES",
    "subdivision": "55",
    "timezone": "Europe/Madrid"
  },
  "geometry": {
    "type": "Point",
    "coordinates": [
      -5.33045,
      41.05341
    ]
  }
}