{
  "type": "Feature",
  "properties": {
    "name": "Castrocontrigo",
    "country": "ES",
    "subdivision": "55",
    "timezone": "Europe/Madrid"
  },
  "geometry": {
    "type": "Point",
    "coordinates": [
      -6.19022,
      42.18363
    ]
  }
}