{
  "type": "Feature",
  "properties": {
    "name": "Cigales",
    "country": "ES",
    "subdivision": "55",
    "timezone": "Europe/Madrid"
  },
  "geometry": {
    "type": "Point",
    "coordinates": [
      -4.69848,
      41.7578
    ]
  }
}