{
  "type": "Feature",
  "properties": {
    "name": "Galende",
    "country": "ES",
    "subdivision": "55",
    "timezone": "Europe/Madrid"
  },
  "geometry": {
    "type": "Point",
    "coordinates": [
      -6.66252,
      42.1044
    ]
  }
}