{
  "type": "Feature",
  "properties": {
    "name": "Ledesma",
    "country": "ES",
    "subdivision": "55",
    "timezone": "Europe/Madrid"
  },
  "geometry": {
    "type": "Point",
    "coordinates": [
      -6.00178,
      41.08829
    ]
  }
}