{
  "type": "Feature",
  "properties": {
    "name": "Matallana de Torío",
    "country": "ES",
    "subdivision": "55",
    "timezone": "Europe/Madrid"
  },
  "geometry": {
    "type": "Point",
    "coordinates": [
      -5.52034,
      42.8656
    ]
  }
}