{
  "type": "Feature",
  "properties": {
    "name": "Matapozuelos",
    "country": "ES",
    "subdivision": "55",
    "timezone": "Europe/Madrid"
  },
  "geometry": {
    "type": "Point",
    "coordinates": [
      -4.79122,
      41.41423
    ]
  }
}