{
  "type": "Feature",
  "properties": {
    "name": "Navalperal de Pinares",
    "country": "ES",
    "subdivision": "55",
    "timezone": "Europe/Madrid"
  },
  "geometry": {
    "type": "Point",
    "coordinates": [
      -4.41149,
      40.59398
    ]
  }
}