{
  "type": "Feature",
  "properties": {
    "name": "Pedrajas de San Esteban",
    "country": "ES",
    "subdivision": "55",
    "timezone": "Europe/Madrid"
  },
  "geometry": {
    "type": "Point",
    "coordinates": [
      -4.58225,
      41.34145
    ]
  }
}