{
  "type": "Feature",
  "properties": {
    "name": "Quintanar de la Sierra",
    "country": "ES",
    "subdivision": "55",
    "timezone": "Europe/Madrid"
  },
  "geometry": {
    "type": "Point",
    "coordinates": [
      -3.03765,
      41.98288
    ]
  }
}