{
  "type": "Feature",
  "properties": {
    "name": "Salas de los Infantes",
    "country": "ES",
    "subdivision": "55",
    "timezone": "Europe/Madrid"
  },
  "geometry": {
    "type": "Point",
    "coordinates": [
      -3.28631,
      42.02242
    ]
  }
}