{
  "type": "Feature",
  "properties": {
    "name": "San Andrés del Rabanedo",
    "country": "ES",
    "subdivision": "55",
    "timezone": "Europe/Madrid"
  },
  "geometry": {
    "type": "Point",
    "coordinates": [
      -5.61671,
      42.61174
    ]
  }
}