{
  "type": "Feature",
  "properties": {
    "name": "San Cristóbal de Segovia",
    "country": "ES",
    "subdivision": "55",
    "timezone": "Europe/Madrid"
  },
  "geometry": {
    "type": "Point",
    "coordinates": [
      -4.07652,
      40.95225
    ]
  }
}