{
  "type": "Feature",
  "properties": {
    "name": "Soto de la Vega",
    "country": "ES",
    "subdivision": "55",
    "timezone": "Europe/Madrid"
  },
  "geometry": {
    "type": "Point",
    "coordinates": [
      -5.88225,
      42.33227
    ]
  }
}