{
  "type": "Feature",
  "properties": {
    "name": "Torre del Bierzo",
    "country": "ES",
    "subdivision": "55",
    "timezone": "Europe/Madrid"
  },
  "geometry": {
    "type": "Point",
    "coordinates": [
      -6.36675,
      42.60769
    ]
  }
}