{
  "type": "Feature",
  "properties": {
    "name": "Valverde de la Virgen",
    "country": "ES",
    "subdivision": "55",
    "timezone": "Europe/Madrid"
  },
  "geometry": {
    "type": "Point",
    "coordinates": [
      -5.68461,
      42.56823
    ]
  }
}