{
  "type": "Feature",
  "properties": {
    "name": "Villabrágima",
    "country": "ES",
    "subdivision": "55",
    "timezone": "Europe/Madrid"
  },
  "geometry": {
    "type": "Point",
    "coordinates": [
      -5.11546,
      41.82178
    ]
  }
}