{
  "type": "Feature",
  "properties": {
    "name": "Villamanín",
    "country": "ES",
    "subdivision": "55",
    "timezone": "Europe/Madrid"
  },
  "geometry": {
    "type": "Point",
    "coordinates": [
      -5.65669,
      42.93864
    ]
  }
}