{
  "type": "Feature",
  "properties": {
    "name": "Villasana de Mena",
    "country": "ES",
    "subdivision": "55",
    "timezone": "Europe/Madrid"
  },
  "geometry": {
    "type": "Point",
    "coordinates": [
      -3.28253,
      43.10017
    ]
  }
}