{
  "type": "Feature",
  "properties": {
    "name": "Villadiego",
    "country": "ES",
    "subdivision": "55",
    "timezone": "Europe/Madrid"
  },
  "geometry": {
    "type": "Point",
    "coordinates": [
      -4.00958,
      42.51589
    ]
  }
}