{
  "type": "Feature",
  "properties": {
    "name": "Embarcación",
    "country": "AR",
    "subdivision": "17",
    "timezone": "America/Argentina/Salta"
  },
  "geometry": {
    "type": "Point",
    "coordinates": [
      -64.09965,
      -23.21003
    ]
  }
}