{
  "type": "Feature",
  "properties": {
    "name": "Santa Rosa de Tastil",
    "country": "AR",
    "subdivision": "17",
    "timezone": "America/Argentina/Salta"
  },
  "geometry": {
    "type": "Point",
    "coordinates": [
      -65.97452,
      -24.45166
    ]
  }
}