{
  "type": "Feature",
  "properties": {
    "name": "Barrancas",
    "country": "CO",
    "subdivision": "17",
    "timezone": "America/Bogota"
  },
  "geometry": {
    "type": "Point",
    "coordinates": [
      -72.79456,
      10.95672
    ]
  }
}