{
  "type": "Feature",
  "properties": {
    "name": "San Sebastián de Yalí",
    "country": "NI",
    "subdivision": "07",
    "timezone": "America/Managua"
  },
  "geometry": {
    "type": "Point",
    "coordinates": [
      -86.18641,
      13.3054
    ]
  }
}