{
  "type": "Feature",
  "properties": {
    "name": "Marneuli",
    "country": "GE",
    "subdivision": "68",
    "timezone": "Asia/Tbilisi"
  },
  "geometry": {
    "type": "Point",
    "coordinates": [
      44.80195,
      41.48713
    ]
  }
}