{
  "type": "Feature",
  "properties": {
    "name": "Aiud",
    "country": "RO",
    "subdivision": "01",
    "timezone": "Europe/Bucharest"
  },
  "geometry": {
    "type": "Point",
    "coordinates": [
      23.72128,
      46.31006
    ]
  }
}