{
  "type": "Feature",
  "properties": {
    "name": "Blaj",
    "country": "RO",
    "subdivision": "01",
    "timezone": "Europe/Bucharest"
  },
  "geometry": {
    "type": "Point",
    "coordinates": [
      23.91578,
      46.17508
    ]
  }
}