{
  "type": "Feature",
  "properties": {
    "name": "Ciuruleasa",
    "country": "RO",
    "subdivision": "01",
    "timezone": "Europe/Bucharest"
  },
  "geometry": {
    "type": "Point",
    "coordinates": [
      23.03333,
      46.25
    ]
  }
}