{
  "type": "Feature",
  "properties": {
    "name": "Ighiu",
    "country": "RO",
    "subdivision": "01",
    "timezone": "Europe/Bucharest"
  },
  "geometry": {
    "type": "Point",
    "coordinates": [
      23.51667,
      46.15
    ]
  }
}