{
  "type": "Feature",
  "properties": {
    "name": "Lancrăm",
    "country": "RO",
    "subdivision": "01",
    "timezone": "Europe/Bucharest"
  },
  "geometry": {
    "type": "Point",
    "coordinates": [
      23.55665,
      45.98708
    ]
  }
}