{
  "type": "Feature",
  "properties": {
    "name": "Poşaga de Sus",
    "country": "RO",
    "subdivision": "01",
    "timezone": "Europe/Bucharest"
  },
  "geometry": {
    "type": "Point",
    "coordinates": [
      23.38333,
      46.46667
    ]
  }
}