{
  "type": "Feature",
  "properties": {
    "name": "Şugag",
    "country": "RO",
    "subdivision": "01",
    "timezone": "Europe/Bucharest"
  },
  "geometry": {
    "type": "Point",
    "coordinates": [
      23.63333,
      45.76667
    ]
  }
}