{
  "type": "Feature",
  "properties": {
    "name": "Benthuizen",
    "country": "NL",
    "subdivision": "11",
    "timezone": "Europe/Amsterdam"
  },
  "geometry": {
    "type": "Point",
    "coordinates": [
      4.54444,
      52.0775
    ]
  }
}