{
  "type": "Feature",
  "properties": {
    "name": "Bergschenhoek",
    "country": "NL",
    "subdivision": "11",
    "timezone": "Europe/Amsterdam"
  },
  "geometry": {
    "type": "Point",
    "coordinates": [
      4.49861,
      51.99
    ]
  }
}