{
  "type": "Feature",
  "properties": {
    "name": "Berkenwoude",
    "country": "NL",
    "subdivision": "11",
    "timezone": "Europe/Amsterdam"
  },
  "geometry": {
    "type": "Point",
    "coordinates": [
      4.70694,
      51.945
    ]
  }
}