{
  "type": "Feature",
  "properties": {
    "name": "Binnenhof",
    "country": "NL",
    "subdivision": "11",
    "timezone": "Europe/Amsterdam"
  },
  "geometry": {
    "type": "Point",
    "coordinates": [
      4.53644,
      52.16418
    ]
  }
}