{
  "type": "Feature",
  "properties": {
    "name": "Carnisse",
    "country": "NL",
    "subdivision": "11",
    "timezone": "Europe/Amsterdam"
  },
  "geometry": {
    "type": "Point",
    "coordinates": [
      4.47758,
      51.88932
    ]
  }
}