{
  "type": "Feature",
  "properties": {
    "name": "Essesteijn",
    "country": "NL",
    "subdivision": "11",
    "timezone": "Europe/Amsterdam"
  },
  "geometry": {
    "type": "Point",
    "coordinates": [
      4.37263,
      52.08534
    ]
  }
}