{
  "type": "Feature",
  "properties": {
    "name": "Gouwsluis",
    "country": "NL",
    "subdivision": "11",
    "timezone": "Europe/Amsterdam"
  },
  "geometry": {
    "type": "Point",
    "coordinates": [
      4.66899,
      52.11943
    ]
  }
}