{
  "type": "Feature",
  "properties": {
    "name": "Hoogvliet",
    "country": "NL",
    "subdivision": "11",
    "timezone": "Europe/Amsterdam"
  },
  "geometry": {
    "type": "Point",
    "coordinates": [
      4.3625,
      51.86333
    ]
  }
}