{
  "type": "Feature",
  "properties": {
    "name": "Liesveld",
    "country": "NL",
    "subdivision": "11",
    "timezone": "Europe/Amsterdam"
  },
  "geometry": {
    "type": "Point",
    "coordinates": [
      4.83194,
      51.9325
    ]
  }
}