{
  "type": "Feature",
  "properties": {
    "name": "Noordwijkerhout",
    "country": "NL",
    "subdivision": "11",
    "timezone": "Europe/Amsterdam"
  },
  "geometry": {
    "type": "Point",
    "coordinates": [
      4.49306,
      52.26167
    ]
  }
}