{
  "type": "Feature",
  "properties": {
    "name": "Oude Wetering",
    "country": "NL",
    "subdivision": "11",
    "timezone": "Europe/Amsterdam"
  },
  "geometry": {
    "type": "Point",
    "coordinates": [
      4.64444,
      52.21417
    ]
  }
}