{
  "type": "Feature",
  "properties": {
    "name": "Reeuwijk",
    "country": "NL",
    "subdivision": "11",
    "timezone": "Europe/Amsterdam"
  },
  "geometry": {
    "type": "Point",
    "coordinates": [
      4.725,
      52.04667
    ]
  }
}