{
  "type": "Feature",
  "properties": {
    "name": "Spangen",
    "country": "NL",
    "subdivision": "11",
    "timezone": "Europe/Amsterdam"
  },
  "geometry": {
    "type": "Point",
    "coordinates": [
      4.43539,
      51.91688
    ]
  }
}