{
  "type": "Feature",
  "properties": {
    "name": "Stein",
    "country": "NL",
    "subdivision": "11",
    "timezone": "Europe/Amsterdam"
  },
  "geometry": {
    "type": "Point",
    "coordinates": [
      4.78194,
      52.00333
    ]
  }
}