{
  "type": "Feature",
  "properties": {
    "name": "Tuindorp",
    "country": "NL",
    "subdivision": "11",
    "timezone": "Europe/Amsterdam"
  },
  "geometry": {
    "type": "Point",
    "coordinates": [
      4.3784,
      51.93032
    ]
  }
}