{
  "type": "Feature",
  "properties": {
    "name": "Vogelwijk",
    "country": "NL",
    "subdivision": "11",
    "timezone": "Europe/Amsterdam"
  },
  "geometry": {
    "type": "Point",
    "coordinates": [
      4.2479,
      52.07631
    ]
  }
}