{
  "type": "Feature",
  "properties": {
    "name": "Waddinxveen",
    "country": "NL",
    "subdivision": "11",
    "timezone": "Europe/Amsterdam"
  },
  "geometry": {
    "type": "Point",
    "coordinates": [
      4.65139,
      52.045
    ]
  }
}