{
  "type": "Feature",
  "properties": {
    "name": "Santiago",
    "country": "PE",
    "subdivision": "11",
    "timezone": "America/Lima"
  },
  "geometry": {
    "type": "Point",
    "coordinates": [
      -75.71124,
      -14.18469
    ]
  }
}