{
  "type": "Feature",
  "properties": {
    "name": "Astara",
    "country": "AZ",
    "subdivision": "08",
    "timezone": "Asia/Baku"
  },
  "geometry": {
    "type": "Point",
    "coordinates": [
      48.87498,
      38.45598
    ]
  }
}