{
  "type": "Feature",
  "properties": {
    "name": "Alvorninha",
    "country": "PT",
    "subdivision": "13",
    "timezone": "Europe/Lisbon"
  },
  "geometry": {
    "type": "Point",
    "coordinates": [
      -9.03674,
      39.38224
    ]
  }
}