{
  "type": "Feature",
  "properties": {
    "name": "Cela",
    "country": "PT",
    "subdivision": "13",
    "timezone": "Europe/Lisbon"
  },
  "geometry": {
    "type": "Point",
    "coordinates": [
      -9.03449,
      39.54075
    ]
  }
}