{
  "type": "Feature",
  "properties": {
    "name": "Foz do Arelho",
    "country": "PT",
    "subdivision": "13",
    "timezone": "Europe/Lisbon"
  },
  "geometry": {
    "type": "Point",
    "coordinates": [
      -9.21374,
      39.43672
    ]
  }
}