{
  "type": "Feature",
  "properties": {
    "name": "Maceira",
    "country": "PT",
    "subdivision": "13",
    "timezone": "Europe/Lisbon"
  },
  "geometry": {
    "type": "Point",
    "coordinates": [
      -8.89423,
      39.68853
    ]
  }
}