{
  "type": "Feature",
  "properties": {
    "name": "Pedrógão Grande",
    "country": "PT",
    "subdivision": "13",
    "timezone": "Europe/Lisbon"
  },
  "geometry": {
    "type": "Point",
    "coordinates": [
      -8.1459,
      39.91835
    ]
  }
}