{
  "type": "Feature",
  "properties": {
    "name": "Anār Darah",
    "country": "AF",
    "subdivision": "06",
    "timezone": "Asia/Kabul"
  },
  "geometry": {
    "type": "Point",
    "coordinates": [
      61.65397,
      32.7587
    ]
  }
}