{
  "type": "Feature",
  "properties": {
    "name": "Dārchulā",
    "country": "NP",
    "subdivision": "7",
    "timezone": "Asia/Kathmandu"
  },
  "geometry": {
    "type": "Point",
    "coordinates": [
      80.55,
      29.83
    ]
  }
}