{
  "type": "Feature",
  "properties": {
    "name": "Dhangaḍhi̇̄",
    "country": "NP",
    "subdivision": "7",
    "timezone": "Asia/Kathmandu"
  },
  "geometry": {
    "type": "Point",
    "coordinates": [
      80.58975,
      28.70137
    ]
  }
}