{
  "type": "Feature",
  "properties": {
    "name": "Mahendranagar",
    "country": "NP",
    "subdivision": "7",
    "timezone": "Asia/Kathmandu"
  },
  "geometry": {
    "type": "Point",
    "coordinates": [
      80.17715,
      28.96399
    ]
  }
}