{
  "type": "Feature",
  "properties": {
    "name": "Slavyanovo",
    "country": "BG",
    "subdivision": "50",
    "timezone": "Europe/Sofia"
  },
  "geometry": {
    "type": "Point",
    "coordinates": [
      24.86667,
      43.46667
    ]
  }
}