{
  "type": "Feature",
  "properties": {
    "name": "Beau Vallon",
    "country": "SC",
    "subdivision": "08",
    "timezone": "Indian/Mahe"
  },
  "geometry": {
    "type": "Point",
    "coordinates": [
      55.43015,
      -4.62091
    ]
  }
}