{
  "type": "Feature",
  "properties": {
    "name": "Horšovský Týn",
    "country": "CZ",
    "subdivision": "87",
    "timezone": "Europe/Prague"
  },
  "geometry": {
    "type": "Point",
    "coordinates": [
      12.94405,
      49.52965
    ]
  }
}