{
  "type": "Feature",
  "properties": {
    "name": "Kdyně",
    "country": "CZ",
    "subdivision": "87",
    "timezone": "Europe/Prague"
  },
  "geometry": {
    "type": "Point",
    "coordinates": [
      13.03968,
      49.39077
    ]
  }
}