{
  "type": "Feature",
  "properties": {
    "name": "Nezvěstice",
    "country": "CZ",
    "subdivision": "87",
    "timezone": "Europe/Prague"
  },
  "geometry": {
    "type": "Point",
    "coordinates": [
      13.51962,
      49.64043
    ]
  }
}