{
  "type": "Feature",
  "properties": {
    "name": "Pilsen",
    "country": "CZ",
    "subdivision": "87",
    "timezone": "Europe/Prague"
  },
  "geometry": {
    "type": "Point",
    "coordinates": [
      13.37759,
      49.74747
    ]
  }
}