{
  "type": "Feature",
  "properties": {
    "name": "Třemošná",
    "country": "CZ",
    "subdivision": "87",
    "timezone": "Europe/Prague"
  },
  "geometry": {
    "type": "Point",
    "coordinates": [
      13.39499,
      49.81584
    ]
  }
}