{
  "type": "Feature",
  "properties": {
    "name": "Všeruby",
    "country": "CZ",
    "subdivision": "87",
    "timezone": "Europe/Prague"
  },
  "geometry": {
    "type": "Point",
    "coordinates": [
      13.22943,
      49.84167
    ]
  }
}