{
  "type": "Feature",
  "properties": {
    "name": "Žihle",
    "country": "CZ",
    "subdivision": "87",
    "timezone": "Europe/Prague"
  },
  "geometry": {
    "type": "Point",
    "coordinates": [
      13.37502,
      50.04491
    ]
  }
}