{
  "type": "Feature",
  "properties": {
    "name": "Achicourt",
    "country": "FR",
    "subdivision": "32",
    "timezone": "Europe/Paris"
  },
  "geometry": {
    "type": "Point",
    "coordinates": [
      2.75779,
      50.27429
    ]
  }
}