{
  "type": "Feature",
  "properties": {
    "name": "Anhiers",
    "country": "FR",
    "subdivision": "32",
    "timezone": "Europe/Paris"
  },
  "geometry": {
    "type": "Point",
    "coordinates": [
      3.15512,
      50.40737
    ]
  }
}