{
  "type": "Feature",
  "properties": {
    "name": "Annay",
    "country": "FR",
    "subdivision": "32",
    "timezone": "Europe/Paris"
  },
  "geometry": {
    "type": "Point",
    "coordinates": [
      2.88122,
      50.46303
    ]
  }
}