{
  "type": "Feature",
  "properties": {
    "name": "Aubigny-au-Bac",
    "country": "FR",
    "subdivision": "32",
    "timezone": "Europe/Paris"
  },
  "geometry": {
    "type": "Point",
    "coordinates": [
      3.16448,
      50.2637
    ]
  }
}