{
  "type": "Feature",
  "properties": {
    "name": "Aulnoye-Aymeries",
    "country": "FR",
    "subdivision": "32",
    "timezone": "Europe/Paris"
  },
  "geometry": {
    "type": "Point",
    "coordinates": [
      3.83844,
      50.20141
    ]
  }
}