{
  "type": "Feature",
  "properties": {
    "name": "Avesnelles",
    "country": "FR",
    "subdivision": "32",
    "timezone": "Europe/Paris"
  },
  "geometry": {
    "type": "Point",
    "coordinates": [
      3.94674,
      50.11782
    ]
  }
}