{
  "type": "Feature",
  "properties": {
    "name": "Avesnes-le-Comte",
    "country": "FR",
    "subdivision": "32",
    "timezone": "Europe/Paris"
  },
  "geometry": {
    "type": "Point",
    "coordinates": [
      2.52957,
      50.27767
    ]
  }
}