{
  "type": "Feature",
  "properties": {
    "name": "Bailleval",
    "country": "FR",
    "subdivision": "32",
    "timezone": "Europe/Paris"
  },
  "geometry": {
    "type": "Point",
    "coordinates": [
      2.45695,
      49.34605
    ]
  }
}