{
  "type": "Feature",
  "properties": {
    "name": "Beautor",
    "country": "FR",
    "subdivision": "32",
    "timezone": "Europe/Paris"
  },
  "geometry": {
    "type": "Point",
    "coordinates": [
      3.34475,
      49.65214
    ]
  }
}