{
  "type": "Feature",
  "properties": {
    "name": "Beaurevoir",
    "country": "FR",
    "subdivision": "32",
    "timezone": "Europe/Paris"
  },
  "geometry": {
    "type": "Point",
    "coordinates": [
      3.30855,
      49.99714
    ]
  }
}