{
  "type": "Feature",
  "properties": {
    "name": "Bertry",
    "country": "FR",
    "subdivision": "32",
    "timezone": "Europe/Paris"
  },
  "geometry": {
    "type": "Point",
    "coordinates": [
      3.44298,
      50.08718
    ]
  }
}