{
  "type": "Feature",
  "properties": {
    "name": "Blaringhem",
    "country": "FR",
    "subdivision": "32",
    "timezone": "Europe/Paris"
  },
  "geometry": {
    "type": "Point",
    "coordinates": [
      2.40321,
      50.6911
    ]
  }
}