{
  "type": "Feature",
  "properties": {
    "name": "Blendecques",
    "country": "FR",
    "subdivision": "32",
    "timezone": "Europe/Paris"
  },
  "geometry": {
    "type": "Point",
    "coordinates": [
      2.28601,
      50.71843
    ]
  }
}