{
  "type": "Feature",
  "properties": {
    "name": "Bollezeele",
    "country": "FR",
    "subdivision": "32",
    "timezone": "Europe/Paris"
  },
  "geometry": {
    "type": "Point",
    "coordinates": [
      2.34751,
      50.86687
    ]
  }
}