{
  "type": "Feature",
  "properties": {
    "name": "Bornel",
    "country": "FR",
    "subdivision": "32",
    "timezone": "Europe/Paris"
  },
  "geometry": {
    "type": "Point",
    "coordinates": [
      2.20912,
      49.1982
    ]
  }
}