{
  "type": "Feature",
  "properties": {
    "name": "Bourlon",
    "country": "FR",
    "subdivision": "32",
    "timezone": "Europe/Paris"
  },
  "geometry": {
    "type": "Point",
    "coordinates": [
      3.11425,
      50.17692
    ]
  }
}