{
  "type": "Feature",
  "properties": {
    "name": "Boussois",
    "country": "FR",
    "subdivision": "32",
    "timezone": "Europe/Paris"
  },
  "geometry": {
    "type": "Point",
    "coordinates": [
      4.04117,
      50.28907
    ]
  }
}