{
  "type": "Feature",
  "properties": {
    "name": "Bousies",
    "country": "FR",
    "subdivision": "32",
    "timezone": "Europe/Paris"
  },
  "geometry": {
    "type": "Point",
    "coordinates": [
      3.61752,
      50.15097
    ]
  }
}