{
  "type": "Feature",
  "properties": {
    "name": "Braine",
    "country": "FR",
    "subdivision": "32",
    "timezone": "Europe/Paris"
  },
  "geometry": {
    "type": "Point",
    "coordinates": [
      3.53262,
      49.34261
    ]
  }
}