{
  "type": "Feature",
  "properties": {
    "name": "Brenouille",
    "country": "FR",
    "subdivision": "32",
    "timezone": "Europe/Paris"
  },
  "geometry": {
    "type": "Point",
    "coordinates": [
      2.54437,
      49.30551
    ]
  }
}