{
  "type": "Feature",
  "properties": {
    "name": "Breteuil",
    "country": "FR",
    "subdivision": "32",
    "timezone": "Europe/Paris"
  },
  "geometry": {
    "type": "Point",
    "coordinates": [
      2.29509,
      49.63357
    ]
  }
}