{
  "type": "Feature",
  "properties": {
    "name": "Buironfosse",
    "country": "FR",
    "subdivision": "32",
    "timezone": "Europe/Paris"
  },
  "geometry": {
    "type": "Point",
    "coordinates": [
      3.83587,
      49.96659
    ]
  }
}