{
  "type": "Feature",
  "properties": {
    "name": "Cambronne-lès-Ribécourt",
    "country": "FR",
    "subdivision": "32",
    "timezone": "Europe/Paris"
  },
  "geometry": {
    "type": "Point",
    "coordinates": [
      2.89797,
      49.50711
    ]
  }
}