{
  "type": "Feature",
  "properties": {
    "name": "Cantin",
    "country": "FR",
    "subdivision": "32",
    "timezone": "Europe/Paris"
  },
  "geometry": {
    "type": "Point",
    "coordinates": [
      3.12765,
      50.30885
    ]
  }
}