{
  "type": "Feature",
  "properties": {
    "name": "Chézy-sur-Marne",
    "country": "FR",
    "subdivision": "32",
    "timezone": "Europe/Paris"
  },
  "geometry": {
    "type": "Point",
    "coordinates": [
      3.36786,
      48.98881
    ]
  }
}