{
  "type": "Feature",
  "properties": {
    "name": "Chocques",
    "country": "FR",
    "subdivision": "32",
    "timezone": "Europe/Paris"
  },
  "geometry": {
    "type": "Point",
    "coordinates": [
      2.57193,
      50.54084
    ]
  }
}