{
  "type": "Feature",
  "properties": {
    "name": "Cires-lès-Mello",
    "country": "FR",
    "subdivision": "32",
    "timezone": "Europe/Paris"
  },
  "geometry": {
    "type": "Point",
    "coordinates": [
      2.3584,
      49.27242
    ]
  }
}