{
  "type": "Feature",
  "properties": {
    "name": "Clairoix",
    "country": "FR",
    "subdivision": "32",
    "timezone": "Europe/Paris"
  },
  "geometry": {
    "type": "Point",
    "coordinates": [
      2.84628,
      49.44264
    ]
  }
}