{
  "type": "Feature",
  "properties": {
    "name": "Clary",
    "country": "FR",
    "subdivision": "32",
    "timezone": "Europe/Paris"
  },
  "geometry": {
    "type": "Point",
    "coordinates": [
      3.39943,
      50.07789
    ]
  }
}