{
  "type": "Feature",
  "properties": {
    "name": "Clermont",
    "country": "FR",
    "subdivision": "32",
    "timezone": "Europe/Paris"
  },
  "geometry": {
    "type": "Point",
    "coordinates": [
      2.41258,
      49.37897
    ]
  }
}