{
  "type": "Feature",
  "properties": {
    "name": "Creil",
    "country": "FR",
    "subdivision": "32",
    "timezone": "Europe/Paris"
  },
  "geometry": {
    "type": "Point",
    "coordinates": [
      2.48477,
      49.25672
    ]
  }
}