{
  "type": "Feature",
  "properties": {
    "name": "Croisilles",
    "country": "FR",
    "subdivision": "32",
    "timezone": "Europe/Paris"
  },
  "geometry": {
    "type": "Point",
    "coordinates": [
      2.87935,
      50.19978
    ]
  }
}