{
  "type": "Feature",
  "properties": {
    "name": "Croix",
    "country": "FR",
    "subdivision": "32",
    "timezone": "Europe/Paris"
  },
  "geometry": {
    "type": "Point",
    "coordinates": [
      3.1493,
      50.67846
    ]
  }
}