{
  "type": "Feature",
  "properties": {
    "name": "Curgies",
    "country": "FR",
    "subdivision": "32",
    "timezone": "Europe/Paris"
  },
  "geometry": {
    "type": "Point",
    "coordinates": [
      3.60299,
      50.32975
    ]
  }
}