{
  "type": "Feature",
  "properties": {
    "name": "Cysoing",
    "country": "FR",
    "subdivision": "32",
    "timezone": "Europe/Paris"
  },
  "geometry": {
    "type": "Point",
    "coordinates": [
      3.21627,
      50.56939
    ]
  }
}