{
  "type": "Feature",
  "properties": {
    "name": "Deûlémont",
    "country": "FR",
    "subdivision": "32",
    "timezone": "Europe/Paris"
  },
  "geometry": {
    "type": "Point",
    "coordinates": [
      2.95,
      50.73333
    ]
  }
}