{
  "type": "Feature",
  "properties": {
    "name": "Douvrin",
    "country": "FR",
    "subdivision": "32",
    "timezone": "Europe/Paris"
  },
  "geometry": {
    "type": "Point",
    "coordinates": [
      2.83053,
      50.50916
    ]
  }
}