{
  "type": "Feature",
  "properties": {
    "name": "Ennetières-en-Weppes",
    "country": "FR",
    "subdivision": "32",
    "timezone": "Europe/Paris"
  },
  "geometry": {
    "type": "Point",
    "coordinates": [
      2.94012,
      50.6353
    ]
  }
}