{
  "type": "Feature",
  "properties": {
    "name": "Esquerdes",
    "country": "FR",
    "subdivision": "32",
    "timezone": "Europe/Paris"
  },
  "geometry": {
    "type": "Point",
    "coordinates": [
      2.18851,
      50.70414
    ]
  }
}