{
  "type": "Feature",
  "properties": {
    "name": "Étampes-sur-Marne",
    "country": "FR",
    "subdivision": "32",
    "timezone": "Europe/Paris"
  },
  "geometry": {
    "type": "Point",
    "coordinates": [
      3.41893,
      49.03464
    ]
  }
}