{
  "type": "Feature",
  "properties": {
    "name": "Féchain",
    "country": "FR",
    "subdivision": "32",
    "timezone": "Europe/Paris"
  },
  "geometry": {
    "type": "Point",
    "coordinates": [
      3.21024,
      50.26638
    ]
  }
}