{
  "type": "Feature",
  "properties": {
    "name": "Feuquières-en-Vimeu",
    "country": "FR",
    "subdivision": "32",
    "timezone": "Europe/Paris"
  },
  "geometry": {
    "type": "Point",
    "coordinates": [
      1.60465,
      50.05982
    ]
  }
}