{
  "type": "Feature",
  "properties": {
    "name": "Fouquières-lès-Lens",
    "country": "FR",
    "subdivision": "32",
    "timezone": "Europe/Paris"
  },
  "geometry": {
    "type": "Point",
    "coordinates": [
      2.91321,
      50.42842
    ]
  }
}