{
  "type": "Feature",
  "properties": {
    "name": "Fresnes-sur-Escaut",
    "country": "FR",
    "subdivision": "32",
    "timezone": "Europe/Paris"
  },
  "geometry": {
    "type": "Point",
    "coordinates": [
      3.57752,
      50.43382
    ]
  }
}