{
  "type": "Feature",
  "properties": {
    "name": "Goincourt",
    "country": "FR",
    "subdivision": "32",
    "timezone": "Europe/Paris"
  },
  "geometry": {
    "type": "Point",
    "coordinates": [
      2.03621,
      49.42614
    ]
  }
}