{
  "type": "Feature",
  "properties": {
    "name": "Guignicourt",
    "country": "FR",
    "subdivision": "32",
    "timezone": "Europe/Paris"
  },
  "geometry": {
    "type": "Point",
    "coordinates": [
      3.96755,
      49.43714
    ]
  }
}