{
  "type": "Feature",
  "properties": {
    "name": "Hallencourt",
    "country": "FR",
    "subdivision": "32",
    "timezone": "Europe/Paris"
  },
  "geometry": {
    "type": "Point",
    "coordinates": [
      1.87649,
      49.99201
    ]
  }
}