{
  "type": "Feature",
  "properties": {
    "name": "Hallines",
    "country": "FR",
    "subdivision": "32",
    "timezone": "Europe/Paris"
  },
  "geometry": {
    "type": "Point",
    "coordinates": [
      2.22629,
      50.71087
    ]
  }
}