{
  "type": "Feature",
  "properties": {
    "name": "Hardinghen",
    "country": "FR",
    "subdivision": "32",
    "timezone": "Europe/Paris"
  },
  "geometry": {
    "type": "Point",
    "coordinates": [
      1.82122,
      50.80414
    ]
  }
}