{
  "type": "Feature",
  "properties": {
    "name": "Hasnon",
    "country": "FR",
    "subdivision": "32",
    "timezone": "Europe/Paris"
  },
  "geometry": {
    "type": "Point",
    "coordinates": [
      3.38657,
      50.42472
    ]
  }
}