{
  "type": "Feature",
  "properties": {
    "name": "Haubourdin",
    "country": "FR",
    "subdivision": "32",
    "timezone": "Europe/Paris"
  },
  "geometry": {
    "type": "Point",
    "coordinates": [
      2.99143,
      50.60826
    ]
  }
}