{
  "type": "Feature",
  "properties": {
    "name": "Haussy",
    "country": "FR",
    "subdivision": "32",
    "timezone": "Europe/Paris"
  },
  "geometry": {
    "type": "Point",
    "coordinates": [
      3.47683,
      50.2183
    ]
  }
}