{
  "type": "Feature",
  "properties": {
    "name": "Herzeele",
    "country": "FR",
    "subdivision": "32",
    "timezone": "Europe/Paris"
  },
  "geometry": {
    "type": "Point",
    "coordinates": [
      2.5351,
      50.88584
    ]
  }
}