{
  "type": "Feature",
  "properties": {
    "name": "Illies",
    "country": "FR",
    "subdivision": "32",
    "timezone": "Europe/Paris"
  },
  "geometry": {
    "type": "Point",
    "coordinates": [
      2.83011,
      50.56144
    ]
  }
}