{
  "type": "Feature",
  "properties": {
    "name": "Lambersart",
    "country": "FR",
    "subdivision": "32",
    "timezone": "Europe/Paris"
  },
  "geometry": {
    "type": "Point",
    "coordinates": [
      3.03333,
      50.65
    ]
  }
}