{
  "type": "Feature",
  "properties": {
    "name": "Le Crotoy",
    "country": "FR",
    "subdivision": "32",
    "timezone": "Europe/Paris"
  },
  "geometry": {
    "type": "Point",
    "coordinates": [
      1.625,
      50.216
    ]
  }
}