{
  "type": "Feature",
  "properties": {
    "name": "Le Nouvion-en-Thiérache",
    "country": "FR",
    "subdivision": "32",
    "timezone": "Europe/Paris"
  },
  "geometry": {
    "type": "Point",
    "coordinates": [
      3.78509,
      50.01625
    ]
  }
}