{
  "type": "Feature",
  "properties": {
    "name": "Leforest",
    "country": "FR",
    "subdivision": "32",
    "timezone": "Europe/Paris"
  },
  "geometry": {
    "type": "Point",
    "coordinates": [
      3.0648,
      50.43866
    ]
  }
}