{
  "type": "Feature",
  "properties": {
    "name": "Lens",
    "country": "FR",
    "subdivision": "32",
    "timezone": "Europe/Paris"
  },
  "geometry": {
    "type": "Point",
    "coordinates": [
      2.82791,
      50.43302
    ]
  }
}