{
  "type": "Feature",
  "properties": {
    "name": "Lezennes",
    "country": "FR",
    "subdivision": "32",
    "timezone": "Europe/Paris"
  },
  "geometry": {
    "type": "Point",
    "coordinates": [
      3.11354,
      50.61553
    ]
  }
}