{
  "type": "Feature",
  "properties": {
    "name": "Licques",
    "country": "FR",
    "subdivision": "32",
    "timezone": "Europe/Paris"
  },
  "geometry": {
    "type": "Point",
    "coordinates": [
      1.93844,
      50.78416
    ]
  }
}