{
  "type": "Feature",
  "properties": {
    "name": "Linselles",
    "country": "FR",
    "subdivision": "32",
    "timezone": "Europe/Paris"
  },
  "geometry": {
    "type": "Point",
    "coordinates": [
      3.07878,
      50.73708
    ]
  }
}