{
  "type": "Feature",
  "properties": {
    "name": "Longueil-Annel",
    "country": "FR",
    "subdivision": "32",
    "timezone": "Europe/Paris"
  },
  "geometry": {
    "type": "Point",
    "coordinates": [
      2.86464,
      49.46908
    ]
  }
}