{
  "type": "Feature",
  "properties": {
    "name": "Loos-en-Gohelle",
    "country": "FR",
    "subdivision": "32",
    "timezone": "Europe/Paris"
  },
  "geometry": {
    "type": "Point",
    "coordinates": [
      2.79215,
      50.45786
    ]
  }
}