{
  "type": "Feature",
  "properties": {
    "name": "Lys-lez-Lannoy",
    "country": "FR",
    "subdivision": "32",
    "timezone": "Europe/Paris"
  },
  "geometry": {
    "type": "Point",
    "coordinates": [
      3.21667,
      50.66667
    ]
  }
}