{
  "type": "Feature",
  "properties": {
    "name": "Marconne",
    "country": "FR",
    "subdivision": "32",
    "timezone": "Europe/Paris"
  },
  "geometry": {
    "type": "Point",
    "coordinates": [
      2.04669,
      50.37143
    ]
  }
}