{
  "type": "Feature",
  "properties": {
    "name": "Marcoing",
    "country": "FR",
    "subdivision": "32",
    "timezone": "Europe/Paris"
  },
  "geometry": {
    "type": "Point",
    "coordinates": [
      3.17321,
      50.1211
    ]
  }
}