{
  "type": "Feature",
  "properties": {
    "name": "Maretz",
    "country": "FR",
    "subdivision": "32",
    "timezone": "Europe/Paris"
  },
  "geometry": {
    "type": "Point",
    "coordinates": [
      3.41808,
      50.0453
    ]
  }
}