{
  "type": "Feature",
  "properties": {
    "name": "Merville",
    "country": "FR",
    "subdivision": "32",
    "timezone": "Europe/Paris"
  },
  "geometry": {
    "type": "Point",
    "coordinates": [
      2.64125,
      50.64329
    ]
  }
}