{
  "type": "Feature",
  "properties": {
    "name": "Monchy-Saint-Éloi",
    "country": "FR",
    "subdivision": "32",
    "timezone": "Europe/Paris"
  },
  "geometry": {
    "type": "Point",
    "coordinates": [
      2.46739,
      49.29042
    ]
  }
}