{
  "type": "Feature",
  "properties": {
    "name": "Mons-en-Barœul",
    "country": "FR",
    "subdivision": "32",
    "timezone": "Europe/Paris"
  },
  "geometry": {
    "type": "Point",
    "coordinates": [
      3.11667,
      50.63333
    ]
  }
}