{
  "type": "Feature",
  "properties": {
    "name": "Montdidier",
    "country": "FR",
    "subdivision": "32",
    "timezone": "Europe/Paris"
  },
  "geometry": {
    "type": "Point",
    "coordinates": [
      2.56991,
      49.648
    ]
  }
}