{
  "type": "Feature",
  "properties": {
    "name": "Moreuil",
    "country": "FR",
    "subdivision": "32",
    "timezone": "Europe/Paris"
  },
  "geometry": {
    "type": "Point",
    "coordinates": [
      2.48273,
      49.77457
    ]
  }
}