{
  "type": "Feature",
  "properties": {
    "name": "Neufchâtel-Hardelot",
    "country": "FR",
    "subdivision": "32",
    "timezone": "Europe/Paris"
  },
  "geometry": {
    "type": "Point",
    "coordinates": [
      1.64223,
      50.62018
    ]
  }
}