{
  "type": "Feature",
  "properties": {
    "name": "Noyelles-Godault",
    "country": "FR",
    "subdivision": "32",
    "timezone": "Europe/Paris"
  },
  "geometry": {
    "type": "Point",
    "coordinates": [
      2.99306,
      50.41753
    ]
  }
}