{
  "type": "Feature",
  "properties": {
    "name": "Oisemont",
    "country": "FR",
    "subdivision": "32",
    "timezone": "Europe/Paris"
  },
  "geometry": {
    "type": "Point",
    "coordinates": [
      1.76703,
      49.95587
    ]
  }
}