{
  "type": "Feature",
  "properties": {
    "name": "Origny-en-Thiérache",
    "country": "FR",
    "subdivision": "32",
    "timezone": "Europe/Paris"
  },
  "geometry": {
    "type": "Point",
    "coordinates": [
      4.01644,
      49.89327
    ]
  }
}