{
  "type": "Feature",
  "properties": {
    "name": "Pérenchies",
    "country": "FR",
    "subdivision": "32",
    "timezone": "Europe/Paris"
  },
  "geometry": {
    "type": "Point",
    "coordinates": [
      2.97024,
      50.67013
    ]
  }
}