{
  "type": "Feature",
  "properties": {
    "name": "Picquigny",
    "country": "FR",
    "subdivision": "32",
    "timezone": "Europe/Paris"
  },
  "geometry": {
    "type": "Point",
    "coordinates": [
      2.14376,
      49.94413
    ]
  }
}