{
  "type": "Feature",
  "properties": {
    "name": "Plailly",
    "country": "FR",
    "subdivision": "32",
    "timezone": "Europe/Paris"
  },
  "geometry": {
    "type": "Point",
    "coordinates": [
      2.58549,
      49.10288
    ]
  }
}