{
  "type": "Feature",
  "properties": {
    "name": "Poulainville",
    "country": "FR",
    "subdivision": "32",
    "timezone": "Europe/Paris"
  },
  "geometry": {
    "type": "Point",
    "coordinates": [
      2.31373,
      49.94745
    ]
  }
}