{
  "type": "Feature",
  "properties": {
    "name": "Prémesques",
    "country": "FR",
    "subdivision": "32",
    "timezone": "Europe/Paris"
  },
  "geometry": {
    "type": "Point",
    "coordinates": [
      2.95162,
      50.65572
    ]
  }
}