{
  "type": "Feature",
  "properties": {
    "name": "Quend",
    "country": "FR",
    "subdivision": "32",
    "timezone": "Europe/Paris"
  },
  "geometry": {
    "type": "Point",
    "coordinates": [
      1.63609,
      50.31584
    ]
  }
}