{
  "type": "Feature",
  "properties": {
    "name": "Raillencourt-Sainte-Olle",
    "country": "FR",
    "subdivision": "32",
    "timezone": "Europe/Paris"
  },
  "geometry": {
    "type": "Point",
    "coordinates": [
      3.16667,
      50.18333
    ]
  }
}