{
  "type": "Feature",
  "properties": {
    "name": "Renescure",
    "country": "FR",
    "subdivision": "32",
    "timezone": "Europe/Paris"
  },
  "geometry": {
    "type": "Point",
    "coordinates": [
      2.36801,
      50.72754
    ]
  }
}