{
  "type": "Feature",
  "properties": {
    "name": "Ribemont",
    "country": "FR",
    "subdivision": "32",
    "timezone": "Europe/Paris"
  },
  "geometry": {
    "type": "Point",
    "coordinates": [
      3.45893,
      49.7954
    ]
  }
}