{
  "type": "Feature",
  "properties": {
    "name": "Rieux-en-Cambrésis",
    "country": "FR",
    "subdivision": "32",
    "timezone": "Europe/Paris"
  },
  "geometry": {
    "type": "Point",
    "coordinates": [
      3.35232,
      50.20069
    ]
  }
}