{
  "type": "Feature",
  "properties": {
    "name": "Ruitz",
    "country": "FR",
    "subdivision": "32",
    "timezone": "Europe/Paris"
  },
  "geometry": {
    "type": "Point",
    "coordinates": [
      2.58876,
      50.46643
    ]
  }
}