{
  "type": "Feature",
  "properties": {
    "name": "Saint-Valery-sur-Somme",
    "country": "FR",
    "subdivision": "32",
    "timezone": "Europe/Paris"
  },
  "geometry": {
    "type": "Point",
    "coordinates": [
      1.63333,
      50.18333
    ]
  }
}