{
  "type": "Feature",
  "properties": {
    "name": "Saint-Quentin",
    "country": "FR",
    "subdivision": "32",
    "timezone": "Europe/Paris"
  },
  "geometry": {
    "type": "Point",
    "coordinates": [
      3.28757,
      49.84889
    ]
  }
}