{
  "type": "Feature",
  "properties": {
    "name": "Sainte-Geneviève",
    "country": "FR",
    "subdivision": "32",
    "timezone": "Europe/Paris"
  },
  "geometry": {
    "type": "Point",
    "coordinates": [
      2.19904,
      49.2892
    ]
  }
}