{
  "type": "Feature",
  "properties": {
    "name": "Sainte-Catherine",
    "country": "FR",
    "subdivision": "32",
    "timezone": "Europe/Paris"
  },
  "geometry": {
    "type": "Point",
    "coordinates": [
      2.76404,
      50.30757
    ]
  }
}