{
  "type": "Feature",
  "properties": {
    "name": "Saint-Paul",
    "country": "FR",
    "subdivision": "32",
    "timezone": "Europe/Paris"
  },
  "geometry": {
    "type": "Point",
    "coordinates": [
      2.00755,
      49.42962
    ]
  }
}