{
  "type": "Feature",
  "properties": {
    "name": "Saint-Just-en-Chaussée",
    "country": "FR",
    "subdivision": "32",
    "timezone": "Europe/Paris"
  },
  "geometry": {
    "type": "Point",
    "coordinates": [
      2.43285,
      49.50503
    ]
  }
}