{
  "type": "Feature",
  "properties": {
    "name": "Saint-Jans-Cappel",
    "country": "FR",
    "subdivision": "32",
    "timezone": "Europe/Paris"
  },
  "geometry": {
    "type": "Point",
    "coordinates": [
      2.72227,
      50.76387
    ]
  }
}