{
  "type": "Feature",
  "properties": {
    "name": "Samer",
    "country": "FR",
    "subdivision": "32",
    "timezone": "Europe/Paris"
  },
  "geometry": {
    "type": "Point",
    "coordinates": [
      1.74628,
      50.6384
    ]
  }
}