{
  "type": "Feature",
  "properties": {
    "name": "Saméon",
    "country": "FR",
    "subdivision": "32",
    "timezone": "Europe/Paris"
  },
  "geometry": {
    "type": "Point",
    "coordinates": [
      3.33544,
      50.47135
    ]
  }
}