{
  "type": "Feature",
  "properties": {
    "name": "Seclin",
    "country": "FR",
    "subdivision": "32",
    "timezone": "Europe/Paris"
  },
  "geometry": {
    "type": "Point",
    "coordinates": [
      3.02731,
      50.54873
    ]
  }
}