{
  "type": "Feature",
  "properties": {
    "name": "Sissonne",
    "country": "FR",
    "subdivision": "32",
    "timezone": "Europe/Paris"
  },
  "geometry": {
    "type": "Point",
    "coordinates": [
      3.89369,
      49.57107
    ]
  }
}