{
  "type": "Feature",
  "properties": {
    "name": "Thérouanne",
    "country": "FR",
    "subdivision": "32",
    "timezone": "Europe/Paris"
  },
  "geometry": {
    "type": "Point",
    "coordinates": [
      2.25838,
      50.63695
    ]
  }
}