{
  "type": "Feature",
  "properties": {
    "name": "Thiant",
    "country": "FR",
    "subdivision": "32",
    "timezone": "Europe/Paris"
  },
  "geometry": {
    "type": "Point",
    "coordinates": [
      3.44796,
      50.3048
    ]
  }
}