{
  "type": "Feature",
  "properties": {
    "name": "Tracy-le-Mont",
    "country": "FR",
    "subdivision": "32",
    "timezone": "Europe/Paris"
  },
  "geometry": {
    "type": "Point",
    "coordinates": [
      3.00939,
      49.47225
    ]
  }
}