{
  "type": "Feature",
  "properties": {
    "name": "Trie-Château",
    "country": "FR",
    "subdivision": "32",
    "timezone": "Europe/Paris"
  },
  "geometry": {
    "type": "Point",
    "coordinates": [
      1.82129,
      49.2854
    ]
  }
}