{
  "type": "Feature",
  "properties": {
    "name": "Valenciennes",
    "country": "FR",
    "subdivision": "32",
    "timezone": "Europe/Paris"
  },
  "geometry": {
    "type": "Point",
    "coordinates": [
      3.52506,
      50.35909
    ]
  }
}