{
  "type": "Feature",
  "properties": {
    "name": "Venizel",
    "country": "FR",
    "subdivision": "32",
    "timezone": "Europe/Paris"
  },
  "geometry": {
    "type": "Point",
    "coordinates": [
      3.39321,
      49.36583
    ]
  }
}