{
  "type": "Feature",
  "properties": {
    "name": "Verton",
    "country": "FR",
    "subdivision": "32",
    "timezone": "Europe/Paris"
  },
  "geometry": {
    "type": "Point",
    "coordinates": [
      1.64766,
      50.40234
    ]
  }
}