{
  "type": "Feature",
  "properties": {
    "name": "Vicq",
    "country": "FR",
    "subdivision": "32",
    "timezone": "Europe/Paris"
  },
  "geometry": {
    "type": "Point",
    "coordinates": [
      3.60348,
      50.40738
    ]
  }
}