{
  "type": "Feature",
  "properties": {
    "name": "Villers-Bocage",
    "country": "FR",
    "subdivision": "32",
    "timezone": "Europe/Paris"
  },
  "geometry": {
    "type": "Point",
    "coordinates": [
      2.31683,
      49.9981
    ]
  }
}