{
  "type": "Feature",
  "properties": {
    "name": "Vitry-en-Artois",
    "country": "FR",
    "subdivision": "32",
    "timezone": "Europe/Paris"
  },
  "geometry": {
    "type": "Point",
    "coordinates": [
      2.97999,
      50.3266
    ]
  }
}