{
  "type": "Feature",
  "properties": {
    "name": "Wallers",
    "country": "FR",
    "subdivision": "32",
    "timezone": "Europe/Paris"
  },
  "geometry": {
    "type": "Point",
    "coordinates": [
      3.39188,
      50.37432
    ]
  }
}