{
  "type": "Feature",
  "properties": {
    "name": "Wargnies-le-Grand",
    "country": "FR",
    "subdivision": "32",
    "timezone": "Europe/Paris"
  },
  "geometry": {
    "type": "Point",
    "coordinates": [
      3.66038,
      50.30751
    ]
  }
}