{
  "type": "Feature",
  "properties": {
    "name": "Wavignies",
    "country": "FR",
    "subdivision": "32",
    "timezone": "Europe/Paris"
  },
  "geometry": {
    "type": "Point",
    "coordinates": [
      2.36032,
      49.54748
    ]
  }
}