{
  "type": "Feature",
  "properties": {
    "name": "Zuydcoote",
    "country": "FR",
    "subdivision": "32",
    "timezone": "Europe/Paris"
  },
  "geometry": {
    "type": "Point",
    "coordinates": [
      2.49338,
      51.06096
    ]
  }
}