{
  "type": "Feature",
  "properties": {
    "name": "Güzelyurt",
    "country": "TR",
    "subdivision": "75",
    "timezone": "Europe/Istanbul"
  },
  "geometry": {
    "type": "Point",
    "coordinates": [
      34.37194,
      38.27722
    ]
  }
}