{
  "type": "Feature",
  "properties": {
    "name": "Batu Gajah",
    "country": "MY",
    "subdivision": "07",
    "timezone": "Asia/Kuala_Lumpur"
  },
  "geometry": {
    "type": "Point",
    "coordinates": [
      101.04107,
      4.46916
    ]
  }
}