{
  "type": "Feature",
  "properties": {
    "name": "Csengele",
    "country": "HU",
    "subdivision": "06",
    "timezone": "Europe/Budapest"
  },
  "geometry": {
    "type": "Point",
    "coordinates": [
      19.86358,
      46.54234
    ]
  }
}