{
  "type": "Feature",
  "properties": {
    "name": "Deszk",
    "country": "HU",
    "subdivision": "06",
    "timezone": "Europe/Budapest"
  },
  "geometry": {
    "type": "Point",
    "coordinates": [
      20.24322,
      46.21802
    ]
  }
}