{
  "type": "Feature",
  "properties": {
    "name": "Hódmezővásárhely",
    "country": "HU",
    "subdivision": "06",
    "timezone": "Europe/Budapest"
  },
  "geometry": {
    "type": "Point",
    "coordinates": [
      20.33333,
      46.41667
    ]
  }
}