{
  "type": "Feature",
  "properties": {
    "name": "Banovo Polje",
    "country": "RS",
    "subdivision": "SE",
    "timezone": "Europe/Belgrade"
  },
  "geometry": {
    "type": "Point",
    "coordinates": [
      19.44916,
      44.9104
    ]
  }
}