{
  "type": "Feature",
  "properties": {
    "name": "Belotić",
    "country": "RS",
    "subdivision": "SE",
    "timezone": "Europe/Belgrade"
  },
  "geometry": {
    "type": "Point",
    "coordinates": [
      19.54801,
      44.81782
    ]
  }
}