{
  "type": "Feature",
  "properties": {
    "name": "Bor",
    "country": "RS",
    "subdivision": "SE",
    "timezone": "Europe/Belgrade"
  },
  "geometry": {
    "type": "Point",
    "coordinates": [
      22.09591,
      44.07488
    ]
  }
}