{
  "type": "Feature",
  "properties": {
    "name": "Dobrić",
    "country": "RS",
    "subdivision": "SE",
    "timezone": "Europe/Belgrade"
  },
  "geometry": {
    "type": "Point",
    "coordinates": [
      19.57931,
      44.70224
    ]
  }
}