{
  "type": "Feature",
  "properties": {
    "name": "Golubac",
    "country": "RS",
    "subdivision": "SE",
    "timezone": "Europe/Belgrade"
  },
  "geometry": {
    "type": "Point",
    "coordinates": [
      21.63199,
      44.65296
    ]
  }
}