{
  "type": "Feature",
  "properties": {
    "name": "Jevremovac",
    "country": "RS",
    "subdivision": "SE",
    "timezone": "Europe/Belgrade"
  },
  "geometry": {
    "type": "Point",
    "coordinates": [
      19.66364,
      44.72172
    ]
  }
}