{
  "type": "Feature",
  "properties": {
    "name": "Klenje",
    "country": "RS",
    "subdivision": "SE",
    "timezone": "Europe/Belgrade"
  },
  "geometry": {
    "type": "Point",
    "coordinates": [
      19.43508,
      44.80794
    ]
  }
}