{
  "type": "Feature",
  "properties": {
    "name": "Lapovo",
    "country": "RS",
    "subdivision": "SE",
    "timezone": "Europe/Belgrade"
  },
  "geometry": {
    "type": "Point",
    "coordinates": [
      21.09727,
      44.18424
    ]
  }
}