{
  "type": "Feature",
  "properties": {
    "name": "LugavÄina",
    "country": "RS",
    "subdivision": "SE",
    "timezone": "Europe/Belgrade"
  },
  "geometry": {
    "type": "Point",
    "coordinates": [
      21.07083,
      44.52314
    ]
  }
}