{
  "type": "Feature",
  "properties": {
    "name": "OseÄina",
    "country": "RS",
    "subdivision": "SE",
    "timezone": "Europe/Belgrade"
  },
  "geometry": {
    "type": "Point",
    "coordinates": [
      19.60139,
      44.37306
    ]
  }
}