{
  "type": "Feature",
  "properties": {
    "name": "Pirot",
    "country": "RS",
    "subdivision": "SE",
    "timezone": "Europe/Belgrade"
  },
  "geometry": {
    "type": "Point",
    "coordinates": [
      22.58611,
      43.15306
    ]
  }
}