{
  "type": "Feature",
  "properties": {
    "name": "Ribari",
    "country": "RS",
    "subdivision": "SE",
    "timezone": "Europe/Belgrade"
  },
  "geometry": {
    "type": "Point",
    "coordinates": [
      19.42472,
      44.70961
    ]
  }
}