{
  "type": "Feature",
  "properties": {
    "name": "Štitar",
    "country": "RS",
    "subdivision": "SE",
    "timezone": "Europe/Belgrade"
  },
  "geometry": {
    "type": "Point",
    "coordinates": [
      19.59529,
      44.79415
    ]
  }
}