{
  "type": "Feature",
  "properties": {
    "name": "Tabanović",
    "country": "RS",
    "subdivision": "SE",
    "timezone": "Europe/Belgrade"
  },
  "geometry": {
    "type": "Point",
    "coordinates": [
      19.64128,
      44.82018
    ]
  }
}