{
  "type": "Feature",
  "properties": {
    "name": "Trstenik",
    "country": "RS",
    "subdivision": "SE",
    "timezone": "Europe/Belgrade"
  },
  "geometry": {
    "type": "Point",
    "coordinates": [
      21.0025,
      43.61694
    ]
  }
}