{
  "type": "Feature",
  "properties": {
    "name": "Umka",
    "country": "RS",
    "subdivision": "SE",
    "timezone": "Europe/Belgrade"
  },
  "geometry": {
    "type": "Point",
    "coordinates": [
      20.30472,
      44.67806
    ]
  }
}