{
  "type": "Feature",
  "properties": {
    "name": "Velika Moštanica",
    "country": "RS",
    "subdivision": "SE",
    "timezone": "Europe/Belgrade"
  },
  "geometry": {
    "type": "Point",
    "coordinates": [
      20.35395,
      44.66486
    ]
  }
}