{
  "type": "Feature",
  "properties": {
    "name": "Letterkenny",
    "country": "IE",
    "subdivision": "U",
    "timezone": "Europe/Dublin"
  },
  "geometry": {
    "type": "Point",
    "coordinates": [
      -7.73333,
      54.95
    ]
  }
}