{
  "type": "Feature",
  "properties": {
    "name": "Raphoe",
    "country": "IE",
    "subdivision": "U",
    "timezone": "Europe/Dublin"
  },
  "geometry": {
    "type": "Point",
    "coordinates": [
      -7.59833,
      54.87472
    ]
  }
}