{
  "type": "Feature",
  "properties": {
    "name": "Donja Bistra",
    "country": "HR",
    "subdivision": "20",
    "timezone": "Europe/Zagreb"
  },
  "geometry": {
    "type": "Point",
    "coordinates": [
      15.85444,
      45.90778
    ]
  }
}