{
  "type": "Feature",
  "properties": {
    "name": "Gornji Stupnik",
    "country": "HR",
    "subdivision": "20",
    "timezone": "Europe/Zagreb"
  },
  "geometry": {
    "type": "Point",
    "coordinates": [
      15.84314,
      45.75261
    ]
  }
}