{
  "type": "Feature",
  "properties": {
    "name": "Kerestinec",
    "country": "HR",
    "subdivision": "20",
    "timezone": "Europe/Zagreb"
  },
  "geometry": {
    "type": "Point",
    "coordinates": [
      15.80864,
      45.7701
    ]
  }
}