{
  "type": "Feature",
  "properties": {
    "name": "Kuče",
    "country": "HR",
    "subdivision": "20",
    "timezone": "Europe/Zagreb"
  },
  "geometry": {
    "type": "Point",
    "coordinates": [
      16.14265,
      45.67618
    ]
  }
}