{
  "type": "Feature",
  "properties": {
    "name": "Lukavec",
    "country": "HR",
    "subdivision": "20",
    "timezone": "Europe/Zagreb"
  },
  "geometry": {
    "type": "Point",
    "coordinates": [
      15.99,
      45.70444
    ]
  }
}