{
  "type": "Feature",
  "properties": {
    "name": "MiÄevec",
    "country": "HR",
    "subdivision": "20",
    "timezone": "Europe/Zagreb"
  },
  "geometry": {
    "type": "Point",
    "coordinates": [
      16.05831,
      45.7521
    ]
  }
}