{
  "type": "Feature",
  "properties": {
    "name": "Velika Mlaka",
    "country": "HR",
    "subdivision": "20",
    "timezone": "Europe/Zagreb"
  },
  "geometry": {
    "type": "Point",
    "coordinates": [
      16.03111,
      45.73639
    ]
  }
}