{
  "type": "Feature",
  "properties": {
    "name": "Bilicenii Vechi",
    "country": "MD",
    "subdivision": "85",
    "timezone": "Europe/Chisinau"
  },
  "geometry": {
    "type": "Point",
    "coordinates": [
      28.04734,
      47.6558
    ]
  }
}