{
  "type": "Feature",
  "properties": {
    "name": "Muyuka",
    "country": "CM",
    "subdivision": "09",
    "timezone": "Africa/Douala"
  },
  "geometry": {
    "type": "Point",
    "coordinates": [
      9.4103,
      4.2898
    ]
  }
}