{
  "type": "Feature",
  "properties": {
    "name": "Blato",
    "country": "HR",
    "subdivision": "03",
    "timezone": "Europe/Zagreb"
  },
  "geometry": {
    "type": "Point",
    "coordinates": [
      16.79167,
      42.94083
    ]
  }
}