{
  "type": "Feature",
  "properties": {
    "name": "Azov",
    "country": "RU",
    "subdivision": "61",
    "timezone": "Europe/Moscow"
  },
  "geometry": {
    "type": "Point",
    "coordinates": [
      39.41648,
      47.10779
    ]
  }
}