{
  "type": "Feature",
  "properties": {
    "name": "Dubovskoye",
    "country": "RU",
    "subdivision": "61",
    "timezone": "Europe/Moscow"
  },
  "geometry": {
    "type": "Point",
    "coordinates": [
      42.7697,
      47.4142
    ]
  }
}