{
  "type": "Feature",
  "properties": {
    "name": "Gornyatskiy",
    "country": "RU",
    "subdivision": "61",
    "timezone": "Europe/Moscow"
  },
  "geometry": {
    "type": "Point",
    "coordinates": [
      40.92404,
      48.29649
    ]
  }
}