{
  "type": "Feature",
  "properties": {
    "name": "Gukovo",
    "country": "RU",
    "subdivision": "61",
    "timezone": "Europe/Moscow"
  },
  "geometry": {
    "type": "Point",
    "coordinates": [
      39.9355,
      48.06212
    ]
  }
}