{
  "type": "Feature",
  "properties": {
    "name": "Kamenolomni",
    "country": "RU",
    "subdivision": "61",
    "timezone": "Europe/Moscow"
  },
  "geometry": {
    "type": "Point",
    "coordinates": [
      40.2051,
      47.66853
    ]
  }
}