{
  "type": "Feature",
  "properties": {
    "name": "Matveyev Kurgan",
    "country": "RU",
    "subdivision": "61",
    "timezone": "Europe/Moscow"
  },
  "geometry": {
    "type": "Point",
    "coordinates": [
      38.86947,
      47.5645
    ]
  }
}