{
  "type": "Feature",
  "properties": {
    "name": "Novyy Yegorlyk",
    "country": "RU",
    "subdivision": "61",
    "timezone": "Europe/Moscow"
  },
  "geometry": {
    "type": "Point",
    "coordinates": [
      41.87162,
      46.3927
    ]
  }
}