{
  "type": "Feature",
  "properties": {
    "name": "Samarskoye",
    "country": "RU",
    "subdivision": "61",
    "timezone": "Europe/Moscow"
  },
  "geometry": {
    "type": "Point",
    "coordinates": [
      39.6881,
      46.937
    ]
  }
}