{
  "type": "Feature",
  "properties": {
    "name": "Veshenskaya",
    "country": "RU",
    "subdivision": "61",
    "timezone": "Europe/Moscow"
  },
  "geometry": {
    "type": "Point",
    "coordinates": [
      41.7245,
      49.6352
    ]
  }
}