{
  "type": "Feature",
  "properties": {
    "name": "Zimovniki",
    "country": "RU",
    "subdivision": "61",
    "timezone": "Europe/Moscow"
  },
  "geometry": {
    "type": "Point",
    "coordinates": [
      42.4721,
      47.1474
    ]
  }
}