{
  "type": "Feature",
  "properties": {
    "name": "Baotou",
    "country": "CN",
    "subdivision": "20",
    "timezone": "Asia/Shanghai"
  },
  "geometry": {
    "type": "Point",
    "coordinates": [
      109.84389,
      40.6516
    ]
  }
}