{
  "type": "Feature",
  "properties": {
    "name": "Hohhot",
    "country": "CN",
    "subdivision": "20",
    "timezone": "Asia/Shanghai"
  },
  "geometry": {
    "type": "Point",
    "coordinates": [
      111.65222,
      40.81056
    ]
  }
}