{
  "type": "Feature",
  "properties": {
    "name": "El Tarter",
    "country": "AD",
    "subdivision": "02",
    "timezone": "Europe/Andorra"
  },
  "geometry": {
    "type": "Point",
    "coordinates": [
      1.65362,
      42.57952
    ]
  }
}