{
  "type": "Feature",
  "properties": {
    "name": "Blahodatne",
    "country": "UA",
    "subdivision": "24",
    "timezone": "Europe/Kiev"
  },
  "geometry": {
    "type": "Point",
    "coordinates": [
      24.24918,
      50.66365
    ]
  }
}