{
  "type": "Feature",
  "properties": {
    "name": "Lokachi",
    "country": "UA",
    "subdivision": "24",
    "timezone": "Europe/Kiev"
  },
  "geometry": {
    "type": "Point",
    "coordinates": [
      24.64944,
      50.737
    ]
  }
}