{
  "type": "Feature",
  "properties": {
    "name": "Stara Vyzhivka",
    "country": "UA",
    "subdivision": "24",
    "timezone": "Europe/Kiev"
  },
  "geometry": {
    "type": "Point",
    "coordinates": [
      24.43997,
      51.43762
    ]
  }
}