{
  "type": "Feature",
  "properties": {
    "name": "Kota Belud",
    "country": "MY",
    "subdivision": "16",
    "timezone": "Asia/Kuching"
  },
  "geometry": {
    "type": "Point",
    "coordinates": [
      116.4305,
      6.351
    ]
  }
}