{
  "type": "Feature",
  "properties": {
    "name": "Kota Kinabalu",
    "country": "MY",
    "subdivision": "16",
    "timezone": "Asia/Kuching"
  },
  "geometry": {
    "type": "Point",
    "coordinates": [
      116.0724,
      5.9749
    ]
  }
}