{
  "type": "Feature",
  "properties": {
    "name": "Papar",
    "country": "MY",
    "subdivision": "16",
    "timezone": "Asia/Kuching"
  },
  "geometry": {
    "type": "Point",
    "coordinates": [
      115.93333,
      5.73333
    ]
  }
}