{
  "type": "Feature",
  "properties": {
    "name": "Sandakan",
    "country": "MY",
    "subdivision": "16",
    "timezone": "Asia/Kuching"
  },
  "geometry": {
    "type": "Point",
    "coordinates": [
      118.1179,
      5.8402
    ]
  }
}