{
  "type": "Feature",
  "properties": {
    "name": "Borlänge",
    "country": "SE",
    "subdivision": "10",
    "timezone": "Europe/Stockholm"
  },
  "geometry": {
    "type": "Point",
    "coordinates": [
      15.43714,
      60.4858
    ]
  }
}