{
  "type": "Feature",
  "properties": {
    "name": "Falun",
    "country": "SE",
    "subdivision": "10",
    "timezone": "Europe/Stockholm"
  },
  "geometry": {
    "type": "Point",
    "coordinates": [
      15.62597,
      60.60357
    ]
  }
}