{
  "type": "Feature",
  "properties": {
    "name": "Järna",
    "country": "SE",
    "subdivision": "10",
    "timezone": "Europe/Stockholm"
  },
  "geometry": {
    "type": "Point",
    "coordinates": [
      14.36667,
      60.53333
    ]
  }
}