{
  "type": "Feature",
  "properties": {
    "name": "Krylbo",
    "country": "SE",
    "subdivision": "10",
    "timezone": "Europe/Stockholm"
  },
  "geometry": {
    "type": "Point",
    "coordinates": [
      16.21667,
      60.13333
    ]
  }
}