{
  "type": "Feature",
  "properties": {
    "name": "Långshyttan",
    "country": "SE",
    "subdivision": "10",
    "timezone": "Europe/Stockholm"
  },
  "geometry": {
    "type": "Point",
    "coordinates": [
      16.03831,
      60.45238
    ]
  }
}