{
  "type": "Feature",
  "properties": {
    "name": "Vikarbyn",
    "country": "SE",
    "subdivision": "10",
    "timezone": "Europe/Stockholm"
  },
  "geometry": {
    "type": "Point",
    "coordinates": [
      15.01667,
      60.91667
    ]
  }
}