{
  "type": "Feature",
  "properties": {
    "name": "Eydhafushi",
    "country": "MV",
    "subdivision": "31",
    "timezone": "Indian/Maldives"
  },
  "geometry": {
    "type": "Point",
    "coordinates": [
      73.07078,
      5.10327
    ]
  }
}