{
  "type": "Feature",
  "properties": {
    "name": "Kem’",
    "country": "RU",
    "subdivision": "28",
    "timezone": "Europe/Moscow"
  },
  "geometry": {
    "type": "Point",
    "coordinates": [
      34.57929,
      64.95546
    ]
  }
}