{
  "type": "Feature",
  "properties": {
    "name": "Kharlu",
    "country": "RU",
    "subdivision": "28",
    "timezone": "Europe/Moscow"
  },
  "geometry": {
    "type": "Point",
    "coordinates": [
      30.93783,
      61.80869
    ]
  }
}