{
  "type": "Feature",
  "properties": {
    "name": "Shuya",
    "country": "RU",
    "subdivision": "28",
    "timezone": "Europe/Moscow"
  },
  "geometry": {
    "type": "Point",
    "coordinates": [
      34.23271,
      61.95251
    ]
  }
}