{
  "type": "Feature",
  "properties": {
    "name": "Sortavala",
    "country": "RU",
    "subdivision": "28",
    "timezone": "Europe/Moscow"
  },
  "geometry": {
    "type": "Point",
    "coordinates": [
      30.70953,
      61.71233
    ]
  }
}