{
  "type": "Feature",
  "properties": {
    "name": "Yanishpole",
    "country": "RU",
    "subdivision": "28",
    "timezone": "Europe/Moscow"
  },
  "geometry": {
    "type": "Point",
    "coordinates": [
      34.27013,
      62.11095
    ]
  }
}