{
  "type": "Feature",
  "properties": {
    "name": "Alexandru Odobescu",
    "country": "RO",
    "subdivision": "41",
    "timezone": "Europe/Bucharest"
  },
  "geometry": {
    "type": "Point",
    "coordinates": [
      27.08333,
      44.26667
    ]
  }
}