{
  "type": "Feature",
  "properties": {
    "name": "Căscioarele",
    "country": "RO",
    "subdivision": "41",
    "timezone": "Europe/Bucharest"
  },
  "geometry": {
    "type": "Point",
    "coordinates": [
      26.46972,
      44.12611
    ]
  }
}