{
  "type": "Feature",
  "properties": {
    "name": "Ceacu",
    "country": "RO",
    "subdivision": "41",
    "timezone": "Europe/Bucharest"
  },
  "geometry": {
    "type": "Point",
    "coordinates": [
      27.25213,
      44.2653
    ]
  }
}