{
  "type": "Feature",
  "properties": {
    "name": "Dor Mărunt",
    "country": "RO",
    "subdivision": "41",
    "timezone": "Europe/Bucharest"
  },
  "geometry": {
    "type": "Point",
    "coordinates": [
      26.91667,
      44.45
    ]
  }
}