{
  "type": "Feature",
  "properties": {
    "name": "Dorobanțu",
    "country": "RO",
    "subdivision": "41",
    "timezone": "Europe/Bucharest"
  },
  "geometry": {
    "type": "Point",
    "coordinates": [
      26.39341,
      44.35416
    ]
  }
}