{
  "type": "Feature",
  "properties": {
    "name": "Nicolae Bălcescu",
    "country": "RO",
    "subdivision": "41",
    "timezone": "Europe/Bucharest"
  },
  "geometry": {
    "type": "Point",
    "coordinates": [
      26.76667,
      44.45
    ]
  }
}