{
  "type": "Feature",
  "properties": {
    "name": "Potcoava",
    "country": "RO",
    "subdivision": "41",
    "timezone": "Europe/Bucharest"
  },
  "geometry": {
    "type": "Point",
    "coordinates": [
      27.13223,
      44.26332
    ]
  }
}