{
  "type": "Feature",
  "properties": {
    "name": "Radu Vodă",
    "country": "RO",
    "subdivision": "41",
    "timezone": "Europe/Bucharest"
  },
  "geometry": {
    "type": "Point",
    "coordinates": [
      26.92541,
      44.38563
    ]
  }
}