{
  "type": "Feature",
  "properties": {
    "name": "Rasa",
    "country": "RO",
    "subdivision": "41",
    "timezone": "Europe/Bucharest"
  },
  "geometry": {
    "type": "Point",
    "coordinates": [
      27.14717,
      44.21404
    ]
  }
}