{
  "type": "Feature",
  "properties": {
    "name": "Valea Argovei",
    "country": "RO",
    "subdivision": "41",
    "timezone": "Europe/Bucharest"
  },
  "geometry": {
    "type": "Point",
    "coordinates": [
      26.78333,
      44.35
    ]
  }
}