{
  "type": "Feature",
  "properties": {
    "name": "Mollis",
    "country": "CH",
    "subdivision": "GL",
    "timezone": "Europe/Zurich"
  },
  "geometry": {
    "type": "Point",
    "coordinates": [
      9.07242,
      47.08878
    ]
  }
}