{
  "type": "Feature",
  "properties": {
    "name": "Thongwa",
    "country": "MM",
    "subdivision": "17",
    "timezone": "Asia/Yangon"
  },
  "geometry": {
    "type": "Point",
    "coordinates": [
      96.52498,
      16.75998
    ]
  }
}