{
  "type": "Feature",
  "properties": {
    "name": "Güneysu",
    "country": "TR",
    "subdivision": "53",
    "timezone": "Europe/Istanbul"
  },
  "geometry": {
    "type": "Point",
    "coordinates": [
      40.60465,
      40.9813
    ]
  }
}