{
  "type": "Feature",
  "properties": {
    "name": "Aeroflotskiy",
    "country": "UA",
    "subdivision": "11",
    "timezone": "Europe/Simferopol"
  },
  "geometry": {
    "type": "Point",
    "coordinates": [
      33.99961,
      45.01816
    ]
  }
}