{
  "type": "Feature",
  "properties": {
    "name": "Berezovka",
    "country": "UA",
    "subdivision": "11",
    "timezone": "Europe/Simferopol"
  },
  "geometry": {
    "type": "Point",
    "coordinates": [
      33.34397,
      45.57471
    ]
  }
}