{
  "type": "Feature",
  "properties": {
    "name": "Botanicheskoye",
    "country": "UA",
    "subdivision": "11",
    "timezone": "Europe/Simferopol"
  },
  "geometry": {
    "type": "Point",
    "coordinates": [
      33.54856,
      45.78656
    ]
  }
}