{
  "type": "Feature",
  "properties": {
    "name": "Bratskoye",
    "country": "UA",
    "subdivision": "11",
    "timezone": "Europe/Simferopol"
  },
  "geometry": {
    "type": "Point",
    "coordinates": [
      33.92151,
      45.8317
    ]
  }
}