{
  "type": "Feature",
  "properties": {
    "name": "Chaykino",
    "country": "UA",
    "subdivision": "11",
    "timezone": "Europe/Simferopol"
  },
  "geometry": {
    "type": "Point",
    "coordinates": [
      34.59538,
      45.81111
    ]
  }
}