{
  "type": "Feature",
  "properties": {
    "name": "Geroyskoye",
    "country": "UA",
    "subdivision": "11",
    "timezone": "Europe/Simferopol"
  },
  "geometry": {
    "type": "Point",
    "coordinates": [
      33.74675,
      45.13857
    ]
  }
}