{
  "type": "Feature",
  "properties": {
    "name": "Grishino",
    "country": "UA",
    "subdivision": "11",
    "timezone": "Europe/Simferopol"
  },
  "geometry": {
    "type": "Point",
    "coordinates": [
      33.83098,
      45.64219
    ]
  }
}