{
  "type": "Feature",
  "properties": {
    "name": "Izumrudnoye",
    "country": "UA",
    "subdivision": "11",
    "timezone": "Europe/Simferopol"
  },
  "geometry": {
    "type": "Point",
    "coordinates": [
      34.41299,
      45.73704
    ]
  }
}