{
  "type": "Feature",
  "properties": {
    "name": "Kerch",
    "country": "UA",
    "subdivision": "11",
    "timezone": "Europe/Simferopol"
  },
  "geometry": {
    "type": "Point",
    "coordinates": [
      36.47542,
      45.35675
    ]
  }
}