{
  "type": "Feature",
  "properties": {
    "name": "Komsomol’skoye",
    "country": "UA",
    "subdivision": "11",
    "timezone": "Europe/Simferopol"
  },
  "geometry": {
    "type": "Point",
    "coordinates": [
      34.03049,
      45.019
    ]
  }
}