{
  "type": "Feature",
  "properties": {
    "name": "Krasnolesye",
    "country": "UA",
    "subdivision": "11",
    "timezone": "Europe/Simferopol"
  },
  "geometry": {
    "type": "Point",
    "coordinates": [
      34.23086,
      44.83259
    ]
  }
}