{
  "type": "Feature",
  "properties": {
    "name": "Livadia",
    "country": "UA",
    "subdivision": "11",
    "timezone": "Europe/Simferopol"
  },
  "geometry": {
    "type": "Point",
    "coordinates": [
      34.14272,
      44.47021
    ]
  }
}