{
  "type": "Feature",
  "properties": {
    "name": "Malen’koye",
    "country": "UA",
    "subdivision": "11",
    "timezone": "Europe/Simferopol"
  },
  "geometry": {
    "type": "Point",
    "coordinates": [
      33.99942,
      45.07585
    ]
  }
}