{
  "type": "Feature",
  "properties": {
    "name": "Maly Mayak",
    "country": "UA",
    "subdivision": "11",
    "timezone": "Europe/Simferopol"
  },
  "geometry": {
    "type": "Point",
    "coordinates": [
      34.36469,
      44.61356
    ]
  }
}