{
  "type": "Feature",
  "properties": {
    "name": "Mikhaylovka",
    "country": "UA",
    "subdivision": "11",
    "timezone": "Europe/Simferopol"
  },
  "geometry": {
    "type": "Point",
    "coordinates": [
      34.64058,
      45.52838
    ]
  }
}