{
  "type": "Feature",
  "properties": {
    "name": "Nekrasovka",
    "country": "UA",
    "subdivision": "11",
    "timezone": "Europe/Simferopol"
  },
  "geometry": {
    "type": "Point",
    "coordinates": [
      34.98584,
      45.44085
    ]
  }
}