{
  "type": "Feature",
  "properties": {
    "name": "Novoandreyevka",
    "country": "UA",
    "subdivision": "11",
    "timezone": "Europe/Simferopol"
  },
  "geometry": {
    "type": "Point",
    "coordinates": [
      34.09384,
      45.19904
    ]
  }
}