{
  "type": "Feature",
  "properties": {
    "name": "Okhotskoye",
    "country": "UA",
    "subdivision": "11",
    "timezone": "Europe/Simferopol"
  },
  "geometry": {
    "type": "Point",
    "coordinates": [
      34.86401,
      45.48612
    ]
  }
}