{
  "type": "Feature",
  "properties": {
    "name": "Pereval'noye",
    "country": "UA",
    "subdivision": "11",
    "timezone": "Europe/Simferopol"
  },
  "geometry": {
    "type": "Point",
    "coordinates": [
      34.31271,
      44.84838
    ]
  }
}