{
  "type": "Feature",
  "properties": {
    "name": "Petrovka",
    "country": "UA",
    "subdivision": "11",
    "timezone": "Europe/Simferopol"
  },
  "geometry": {
    "type": "Point",
    "coordinates": [
      34.28816,
      45.49776
    ]
  }
}