{
  "type": "Feature",
  "properties": {
    "name": "Pobednoye",
    "country": "UA",
    "subdivision": "11",
    "timezone": "Europe/Simferopol"
  },
  "geometry": {
    "type": "Point",
    "coordinates": [
      34.44805,
      45.70109
    ]
  }
}