{
  "type": "Feature",
  "properties": {
    "name": "Prudy",
    "country": "UA",
    "subdivision": "11",
    "timezone": "Europe/Simferopol"
  },
  "geometry": {
    "type": "Point",
    "coordinates": [
      34.70217,
      45.23922
    ]
  }
}