{
  "type": "Feature",
  "properties": {
    "name": "Razdol’noye",
    "country": "UA",
    "subdivision": "11",
    "timezone": "Europe/Simferopol"
  },
  "geometry": {
    "type": "Point",
    "coordinates": [
      33.48777,
      45.77083
    ]
  }
}