{
  "type": "Feature",
  "properties": {
    "name": "Romashkino",
    "country": "UA",
    "subdivision": "11",
    "timezone": "Europe/Simferopol"
  },
  "geometry": {
    "type": "Point",
    "coordinates": [
      33.25517,
      45.25647
    ]
  }
}