{
  "type": "Feature",
  "properties": {
    "name": "Sadovoye",
    "country": "UA",
    "subdivision": "11",
    "timezone": "Europe/Simferopol"
  },
  "geometry": {
    "type": "Point",
    "coordinates": [
      34.6526,
      45.31037
    ]
  }
}