{
  "type": "Feature",
  "properties": {
    "name": "Slavyanskoye",
    "country": "UA",
    "subdivision": "11",
    "timezone": "Europe/Simferopol"
  },
  "geometry": {
    "type": "Point",
    "coordinates": [
      33.32165,
      45.72768
    ]
  }
}