{
  "type": "Feature",
  "properties": {
    "name": "Sokolinoye",
    "country": "UA",
    "subdivision": "11",
    "timezone": "Europe/Simferopol"
  },
  "geometry": {
    "type": "Point",
    "coordinates": [
      33.95897,
      44.55041
    ]
  }
}