{
  "type": "Feature",
  "properties": {
    "name": "Strogonovka",
    "country": "UA",
    "subdivision": "11",
    "timezone": "Europe/Simferopol"
  },
  "geometry": {
    "type": "Point",
    "coordinates": [
      34.17924,
      44.9497
    ]
  }
}