{
  "type": "Feature",
  "properties": {
    "name": "Turgenevka",
    "country": "UA",
    "subdivision": "11",
    "timezone": "Europe/Simferopol"
  },
  "geometry": {
    "type": "Point",
    "coordinates": [
      33.83007,
      44.69747
    ]
  }
}