{
  "type": "Feature",
  "properties": {
    "name": "Veselovka",
    "country": "UA",
    "subdivision": "11",
    "timezone": "Europe/Simferopol"
  },
  "geometry": {
    "type": "Point",
    "coordinates": [
      33.21385,
      45.37733
    ]
  }
}