{
  "type": "Feature",
  "properties": {
    "name": "Vinnitskoye",
    "country": "UA",
    "subdivision": "11",
    "timezone": "Europe/Simferopol"
  },
  "geometry": {
    "type": "Point",
    "coordinates": [
      33.7392,
      44.98129
    ]
  }
}