{
  "type": "Feature",
  "properties": {
    "name": "Voinka",
    "country": "UA",
    "subdivision": "11",
    "timezone": "Europe/Simferopol"
  },
  "geometry": {
    "type": "Point",
    "coordinates": [
      33.99138,
      45.8699
    ]
  }
}