{
  "type": "Feature",
  "properties": {
    "name": "Yalta",
    "country": "UA",
    "subdivision": "11",
    "timezone": "Europe/Simferopol"
  },
  "geometry": {
    "type": "Point",
    "coordinates": [
      34.16624,
      44.50218
    ]
  }
}