{
  "type": "Feature",
  "properties": {
    "name": "Yevpatoriya",
    "country": "UA",
    "subdivision": "11",
    "timezone": "Europe/Simferopol"
  },
  "geometry": {
    "type": "Point",
    "coordinates": [
      33.36655,
      45.20091
    ]
  }
}