{
  "type": "Feature",
  "properties": {
    "name": "Zuya",
    "country": "UA",
    "subdivision": "11",
    "timezone": "Europe/Simferopol"
  },
  "geometry": {
    "type": "Point",
    "coordinates": [
      34.32152,
      45.05418
    ]
  }
}