{
  "type": "Feature",
  "properties": {
    "name": "Anloga",
    "country": "GH",
    "subdivision": "08",
    "timezone": "Africa/Accra"
  },
  "geometry": {
    "type": "Point",
    "coordinates": [
      0.89728,
      5.79473
    ]
  }
}