{
  "type": "Feature",
  "properties": {
    "name": "An Nimāş",
    "country": "SA",
    "subdivision": "11",
    "timezone": "Asia/Riyadh"
  },
  "geometry": {
    "type": "Point",
    "coordinates": [
      42.12009,
      19.14547
    ]
  }
}