{
  "type": "Feature",
  "properties": {
    "name": "Ivanja Reka",
    "country": "HR",
    "subdivision": "21",
    "timezone": "Europe/Zagreb"
  },
  "geometry": {
    "type": "Point",
    "coordinates": [
      16.11889,
      45.80222
    ]
  }
}