{
  "type": "Feature",
  "properties": {
    "name": "Kašina",
    "country": "HR",
    "subdivision": "21",
    "timezone": "Europe/Zagreb"
  },
  "geometry": {
    "type": "Point",
    "coordinates": [
      16.12436,
      45.91134
    ]
  }
}