{
  "type": "Feature",
  "properties": {
    "name": "Strmec",
    "country": "HR",
    "subdivision": "21",
    "timezone": "Europe/Zagreb"
  },
  "geometry": {
    "type": "Point",
    "coordinates": [
      15.91674,
      45.70843
    ]
  }
}