{
  "type": "Feature",
  "properties": {
    "name": "Düzköy",
    "country": "TR",
    "subdivision": "61",
    "timezone": "Europe/Istanbul"
  },
  "geometry": {
    "type": "Point",
    "coordinates": [
      39.41536,
      40.87461
    ]
  }
}