{
  "type": "Feature",
  "properties": {
    "name": "Alimănești",
    "country": "RO",
    "subdivision": "29",
    "timezone": "Europe/Bucharest"
  },
  "geometry": {
    "type": "Point",
    "coordinates": [
      24.53895,
      44.25693
    ]
  }
}