{
  "type": "Feature",
  "properties": {
    "name": "Călinești",
    "country": "RO",
    "subdivision": "29",
    "timezone": "Europe/Bucharest"
  },
  "geometry": {
    "type": "Point",
    "coordinates": [
      24.68796,
      44.07727
    ]
  }
}