{
  "type": "Feature",
  "properties": {
    "name": "Cezieni",
    "country": "RO",
    "subdivision": "29",
    "timezone": "Europe/Bucharest"
  },
  "geometry": {
    "type": "Point",
    "coordinates": [
      24.26667,
      44.18333
    ]
  }
}