{
  "type": "Feature",
  "properties": {
    "name": "Coloneşti",
    "country": "RO",
    "subdivision": "29",
    "timezone": "Europe/Bucharest"
  },
  "geometry": {
    "type": "Point",
    "coordinates": [
      24.66667,
      44.65
    ]
  }
}