{
  "type": "Feature",
  "properties": {
    "name": "Corbu",
    "country": "RO",
    "subdivision": "29",
    "timezone": "Europe/Bucharest"
  },
  "geometry": {
    "type": "Point",
    "coordinates": [
      24.71667,
      44.48333
    ]
  }
}