{
  "type": "Feature",
  "properties": {
    "name": "Drăghiceni",
    "country": "RO",
    "subdivision": "29",
    "timezone": "Europe/Bucharest"
  },
  "geometry": {
    "type": "Point",
    "coordinates": [
      24.25,
      44.13333
    ]
  }
}