{
  "type": "Feature",
  "properties": {
    "name": "Ghimpați",
    "country": "RO",
    "subdivision": "29",
    "timezone": "Europe/Bucharest"
  },
  "geometry": {
    "type": "Point",
    "coordinates": [
      24.42698,
      44.15359
    ]
  }
}