{
  "type": "Feature",
  "properties": {
    "name": "Ipotești",
    "country": "RO",
    "subdivision": "29",
    "timezone": "Europe/Bucharest"
  },
  "geometry": {
    "type": "Point",
    "coordinates": [
      24.40089,
      44.32529
    ]
  }
}