{
  "type": "Feature",
  "properties": {
    "name": "Orlea Nouă",
    "country": "RO",
    "subdivision": "29",
    "timezone": "Europe/Bucharest"
  },
  "geometry": {
    "type": "Point",
    "coordinates": [
      24.35834,
      43.75522
    ]
  }
}