{
  "type": "Feature",
  "properties": {
    "name": "Priseaca",
    "country": "RO",
    "subdivision": "29",
    "timezone": "Europe/Bucharest"
  },
  "geometry": {
    "type": "Point",
    "coordinates": [
      24.45,
      44.51667
    ]
  }
}