{
  "type": "Feature",
  "properties": {
    "name": "Schitu",
    "country": "RO",
    "subdivision": "29",
    "timezone": "Europe/Bucharest"
  },
  "geometry": {
    "type": "Point",
    "coordinates": [
      24.56667,
      44.35
    ]
  }
}