{
  "type": "Feature",
  "properties": {
    "name": "Strejeștii de Sus",
    "country": "RO",
    "subdivision": "29",
    "timezone": "Europe/Bucharest"
  },
  "geometry": {
    "type": "Point",
    "coordinates": [
      24.22772,
      44.54389
    ]
  }
}