{
  "type": "Feature",
  "properties": {
    "name": "Studina",
    "country": "RO",
    "subdivision": "29",
    "timezone": "Europe/Bucharest"
  },
  "geometry": {
    "type": "Point",
    "coordinates": [
      24.41667,
      43.96667
    ]
  }
}