{
  "type": "Feature",
  "properties": {
    "name": "Ursa",
    "country": "RO",
    "subdivision": "29",
    "timezone": "Europe/Bucharest"
  },
  "geometry": {
    "type": "Point",
    "coordinates": [
      24.63787,
      43.78783
    ]
  }
}