{
  "type": "Feature",
  "properties": {
    "name": "Yamethin",
    "country": "MM",
    "subdivision": "08",
    "timezone": "Asia/Yangon"
  },
  "geometry": {
    "type": "Point",
    "coordinates": [
      96.13875,
      20.43189
    ]
  }
}