{
  "type": "Feature",
  "properties": {
    "name": "Aldama",
    "country": "MX",
    "subdivision": "28",
    "timezone": "America/Monterrey"
  },
  "geometry": {
    "type": "Point",
    "coordinates": [
      -98.07519,
      22.92157
    ]
  }
}