{
  "type": "Feature",
  "properties": {
    "name": "Burgos",
    "country": "MX",
    "subdivision": "28",
    "timezone": "America/Monterrey"
  },
  "geometry": {
    "type": "Point",
    "coordinates": [
      -98.79921,
      24.94722
    ]
  }
}