{
  "type": "Feature",
  "properties": {
    "name": "Carboneras",
    "country": "MX",
    "subdivision": "28",
    "timezone": "America/Monterrey"
  },
  "geometry": {
    "type": "Point",
    "coordinates": [
      -97.71755,
      24.62766
    ]
  }
}