{
  "type": "Feature",
  "properties": {
    "name": "Ciudad Mante",
    "country": "MX",
    "subdivision": "28",
    "timezone": "America/Monterrey"
  },
  "geometry": {
    "type": "Point",
    "coordinates": [
      -98.9739,
      22.74304
    ]
  }
}