{
  "type": "Feature",
  "properties": {
    "name": "Ciudad Tula",
    "country": "MX",
    "subdivision": "28",
    "timezone": "America/Monterrey"
  },
  "geometry": {
    "type": "Point",
    "coordinates": [
      -99.71101,
      22.99732
    ]
  }
}