{
  "type": "Feature",
  "properties": {
    "name": "El Galaneño",
    "country": "MX",
    "subdivision": "28",
    "timezone": "America/Matamoros"
  },
  "geometry": {
    "type": "Point",
    "coordinates": [
      -97.54507,
      25.76091
    ]
  }
}