{
  "type": "Feature",
  "properties": {
    "name": "Ricardo Flores Magón",
    "country": "MX",
    "subdivision": "28",
    "timezone": "America/Monterrey"
  },
  "geometry": {
    "type": "Point",
    "coordinates": [
      -97.90739,
      22.45115
    ]
  }
}