{
  "type": "Feature",
  "properties": {
    "name": "San Fernando",
    "country": "MX",
    "subdivision": "28",
    "timezone": "America/Monterrey"
  },
  "geometry": {
    "type": "Point",
    "coordinates": [
      -98.14828,
      24.84749
    ]
  }
}