{
  "type": "Feature",
  "properties": {
    "name": "Soto la Marina",
    "country": "MX",
    "subdivision": "28",
    "timezone": "America/Monterrey"
  },
  "geometry": {
    "type": "Point",
    "coordinates": [
      -98.20442,
      23.76953
    ]
  }
}