{
  "type": "Feature",
  "properties": {
    "name": "Ursulo Galván",
    "country": "MX",
    "subdivision": "28",
    "timezone": "America/Monterrey"
  },
  "geometry": {
    "type": "Point",
    "coordinates": [
      -98.32191,
      22.72779
    ]
  }
}