{
  "type": "Feature",
  "properties": {
    "name": "Djibouti",
    "country": "DJ",
    "subdivision": "07",
    "timezone": "Africa/Djibouti"
  },
  "geometry": {
    "type": "Point",
    "coordinates": [
      43.14503,
      11.58901
    ]
  }
}