{
  "type": "Feature",
  "properties": {
    "name": "Sertã",
    "country": "PT",
    "subdivision": "06",
    "timezone": "Europe/Lisbon"
  },
  "geometry": {
    "type": "Point",
    "coordinates": [
      -8.09589,
      39.80205
    ]
  }
}