{
  "type": "Feature",
  "properties": {
    "name": "Gualaceo",
    "country": "EC",
    "subdivision": "02",
    "timezone": "America/Guayaquil"
  },
  "geometry": {
    "type": "Point",
    "coordinates": [
      -78.77814,
      -2.89264
    ]
  }
}