{
  "type": "Feature",
  "properties": {
    "name": "Sorong",
    "country": "ID",
    "subdivision": "39",
    "timezone": "Asia/Jayapura"
  },
  "geometry": {
    "type": "Point",
    "coordinates": [
      131.26104,
      -0.87956
    ]
  }
}