{
  "type": "Feature",
  "properties": {
    "name": "Bluffdale",
    "country": "US",
    "subdivision": "UT",
    "timezone": "America/Denver"
  },
  "geometry": {
    "type": "Point",
    "coordinates": [
      -111.93882,
      40.48967
    ]
  }
}