{
  "type": "Feature",
  "properties": {
    "name": "Carbonville",
    "country": "US",
    "subdivision": "UT",
    "timezone": "America/Denver"
  },
  "geometry": {
    "type": "Point",
    "coordinates": [
      -110.83433,
      39.61996
    ]
  }
}