{
  "type": "Feature",
  "properties": {
    "name": "East Carbon City",
    "country": "US",
    "subdivision": "UT",
    "timezone": "America/Denver"
  },
  "geometry": {
    "type": "Point",
    "coordinates": [
      -110.41488,
      39.54774
    ]
  }
}