{
  "type": "Feature",
  "properties": {
    "name": "Farmington",
    "country": "US",
    "subdivision": "UT",
    "timezone": "America/Denver"
  },
  "geometry": {
    "type": "Point",
    "coordinates": [
      -111.88744,
      40.9805
    ]
  }
}