{
  "type": "Feature",
  "properties": {
    "name": "Fillmore",
    "country": "US",
    "subdivision": "UT",
    "timezone": "America/Denver"
  },
  "geometry": {
    "type": "Point",
    "coordinates": [
      -112.32355,
      38.96885
    ]
  }
}