{
  "type": "Feature",
  "properties": {
    "name": "Holladay",
    "country": "US",
    "subdivision": "UT",
    "timezone": "America/Denver"
  },
  "geometry": {
    "type": "Point",
    "coordinates": [
      -111.82466,
      40.66884
    ]
  }
}