{
  "type": "Feature",
  "properties": {
    "name": "Honeyville",
    "country": "US",
    "subdivision": "UT",
    "timezone": "America/Denver"
  },
  "geometry": {
    "type": "Point",
    "coordinates": [
      -112.07939,
      41.63854
    ]
  }
}