{
  "type": "Feature",
  "properties": {
    "name": "Huntington",
    "country": "US",
    "subdivision": "UT",
    "timezone": "America/Denver"
  },
  "geometry": {
    "type": "Point",
    "coordinates": [
      -110.96461,
      39.32664
    ]
  }
}