{
  "type": "Feature",
  "properties": {
    "name": "Mapleton",
    "country": "US",
    "subdivision": "UT",
    "timezone": "America/Denver"
  },
  "geometry": {
    "type": "Point",
    "coordinates": [
      -111.57853,
      40.13023
    ]
  }
}