{
  "type": "Feature",
  "properties": {
    "name": "Provo",
    "country": "US",
    "subdivision": "UT",
    "timezone": "America/Denver"
  },
  "geometry": {
    "type": "Point",
    "coordinates": [
      -111.65853,
      40.23384
    ]
  }
}