{
  "type": "Feature",
  "properties": {
    "name": "River Heights",
    "country": "US",
    "subdivision": "UT",
    "timezone": "America/Denver"
  },
  "geometry": {
    "type": "Point",
    "coordinates": [
      -111.82133,
      41.7216
    ]
  }
}