{
  "type": "Feature",
  "properties": {
    "name": "Santaquin",
    "country": "US",
    "subdivision": "UT",
    "timezone": "America/Denver"
  },
  "geometry": {
    "type": "Point",
    "coordinates": [
      -111.78521,
      39.97551
    ]
  }
}