{
  "type": "Feature",
  "properties": {
    "name": "Sunset",
    "country": "US",
    "subdivision": "UT",
    "timezone": "America/Denver"
  },
  "geometry": {
    "type": "Point",
    "coordinates": [
      -112.03105,
      41.13633
    ]
  }
}