{
  "type": "Feature",
  "properties": {
    "name": "Syracuse",
    "country": "US",
    "subdivision": "UT",
    "timezone": "America/Denver"
  },
  "geometry": {
    "type": "Point",
    "coordinates": [
      -112.06467,
      41.08939
    ]
  }
}