{
  "type": "Feature",
  "properties": {
    "name": "Washington Terrace",
    "country": "US",
    "subdivision": "UT",
    "timezone": "America/Denver"
  },
  "geometry": {
    "type": "Point",
    "coordinates": [
      -111.97661,
      41.17272
    ]
  }
}