{
  "type": "Feature",
  "properties": {
    "name": "Washington",
    "country": "US",
    "subdivision": "UT",
    "timezone": "America/Denver"
  },
  "geometry": {
    "type": "Point",
    "coordinates": [
      -113.50829,
      37.13054
    ]
  }
}