{
  "type": "Feature",
  "properties": {
    "name": "Gantiadi",
    "country": "GE",
    "subdivision": "02",
    "timezone": "Asia/Tbilisi"
  },
  "geometry": {
    "type": "Point",
    "coordinates": [
      40.07944,
      43.38111
    ]
  }
}