{
  "type": "Feature",
  "properties": {
    "name": "Kelasuri",
    "country": "GE",
    "subdivision": "02",
    "timezone": "Asia/Tbilisi"
  },
  "geometry": {
    "type": "Point",
    "coordinates": [
      41.07067,
      42.97877
    ]
  }
}