{
  "type": "Feature",
  "properties": {
    "name": "Khowai",
    "country": "IN",
    "subdivision": "26",
    "timezone": "Asia/Kolkata"
  },
  "geometry": {
    "type": "Point",
    "coordinates": [
      91.59972,
      24.07964
    ]
  }
}