{
  "type": "Feature",
  "properties": {
    "name": "R훮n카r B훮z훮r",
    "country": "IN",
    "subdivision": "26",
    "timezone": "Asia/Kolkata"
  },
  "geometry": {
    "type": "Point",
    "coordinates": [
      91.36614,
      23.83463
    ]
  }
}