{
  "type": "Feature",
  "properties": {
    "name": "Akhalk’alak’i",
    "country": "GE",
    "subdivision": "72",
    "timezone": "Asia/Tbilisi"
  },
  "geometry": {
    "type": "Point",
    "coordinates": [
      43.48629,
      41.40514
    ]
  }
}