{
  "type": "Feature",
  "properties": {
    "name": "Borjomi",
    "country": "GE",
    "subdivision": "72",
    "timezone": "Asia/Tbilisi"
  },
  "geometry": {
    "type": "Point",
    "coordinates": [
      43.39771,
      41.84694
    ]
  }
}