{
  "type": "Feature",
  "properties": {
    "name": "Agar",
    "country": "IN",
    "subdivision": "35",
    "timezone": "Asia/Kolkata"
  },
  "geometry": {
    "type": "Point",
    "coordinates": [
      76.01571,
      23.71177
    ]
  }
}