{
  "type": "Feature",
  "properties": {
    "name": "BÄgli",
    "country": "IN",
    "subdivision": "35",
    "timezone": "Asia/Kolkata"
  },
  "geometry": {
    "type": "Point",
    "coordinates": [
      76.34877,
      22.64124
    ]
  }
}