{
  "type": "Feature",
  "properties": {
    "name": "Baikunthpur",
    "country": "IN",
    "subdivision": "35",
    "timezone": "Asia/Kolkata"
  },
  "geometry": {
    "type": "Point",
    "coordinates": [
      81.40975,
      24.72768
    ]
  }
}