{
  "type": "Feature",
  "properties": {
    "name": "Burhar",
    "country": "IN",
    "subdivision": "35",
    "timezone": "Asia/Kolkata"
  },
  "geometry": {
    "type": "Point",
    "coordinates": [
      81.53204,
      23.21494
    ]
  }
}