{
  "type": "Feature",
  "properties": {
    "name": "Chandia",
    "country": "IN",
    "subdivision": "35",
    "timezone": "Asia/Kolkata"
  },
  "geometry": {
    "type": "Point",
    "coordinates": [
      80.70911,
      23.65647
    ]
  }
}