{
  "type": "Feature",
  "properties": {
    "name": "Dabra",
    "country": "IN",
    "subdivision": "35",
    "timezone": "Asia/Kolkata"
  },
  "geometry": {
    "type": "Point",
    "coordinates": [
      78.33221,
      25.88572
    ]
  }
}