{
  "type": "Feature",
  "properties": {
    "name": "DepÄlpur",
    "country": "IN",
    "subdivision": "35",
    "timezone": "Asia/Kolkata"
  },
  "geometry": {
    "type": "Point",
    "coordinates": [
      75.54224,
      22.85095
    ]
  }
}