{
  "type": "Feature",
  "properties": {
    "name": "HarpÄlpur",
    "country": "IN",
    "subdivision": "35",
    "timezone": "Asia/Kolkata"
  },
  "geometry": {
    "type": "Point",
    "coordinates": [
      79.33279,
      25.28773
    ]
  }
}