{
  "type": "Feature",
  "properties": {
    "name": "JhÄbua",
    "country": "IN",
    "subdivision": "35",
    "timezone": "Asia/Kolkata"
  },
  "geometry": {
    "type": "Point",
    "coordinates": [
      74.59087,
      22.76772
    ]
  }
}