{
  "type": "Feature",
  "properties": {
    "name": "Jobat",
    "country": "IN",
    "subdivision": "35",
    "timezone": "Asia/Kolkata"
  },
  "geometry": {
    "type": "Point",
    "coordinates": [
      74.56828,
      22.41599
    ]
  }
}