{
  "type": "Feature",
  "properties": {
    "name": "LahÄr",
    "country": "IN",
    "subdivision": "35",
    "timezone": "Asia/Kolkata"
  },
  "geometry": {
    "type": "Point",
    "coordinates": [
      78.94137,
      26.19401
    ]
  }
}