{
  "type": "Feature",
  "properties": {
    "name": "MahgawÄn",
    "country": "IN",
    "subdivision": "35",
    "timezone": "Asia/Kolkata"
  },
  "geometry": {
    "type": "Point",
    "coordinates": [
      78.61593,
      26.49471
    ]
  }
}