{
  "type": "Feature",
  "properties": {
    "name": "ManÄsa",
    "country": "IN",
    "subdivision": "35",
    "timezone": "Asia/Kolkata"
  },
  "geometry": {
    "type": "Point",
    "coordinates": [
      75.14095,
      24.47764
    ]
  }
}