{
  "type": "Feature",
  "properties": {
    "name": "ManÄwar",
    "country": "IN",
    "subdivision": "35",
    "timezone": "Asia/Kolkata"
  },
  "geometry": {
    "type": "Point",
    "coordinates": [
      75.08917,
      22.23566
    ]
  }
}