{
  "type": "Feature",
  "properties": {
    "name": "Mandideep",
    "country": "IN",
    "subdivision": "35",
    "timezone": "Asia/Kolkata"
  },
  "geometry": {
    "type": "Point",
    "coordinates": [
      77.53328,
      23.08166
    ]
  }
}