{
  "type": "Feature",
  "properties": {
    "name": "NÄgod",
    "country": "IN",
    "subdivision": "35",
    "timezone": "Asia/Kolkata"
  },
  "geometry": {
    "type": "Point",
    "coordinates": [
      80.58809,
      24.56924
    ]
  }
}