{
  "type": "Feature",
  "properties": {
    "name": "Narsinghgarh",
    "country": "IN",
    "subdivision": "35",
    "timezone": "Asia/Kolkata"
  },
  "geometry": {
    "type": "Point",
    "coordinates": [
      77.09319,
      23.70758
    ]
  }
}