{
  "type": "Feature",
  "properties": {
    "name": "Pachmarhi",
    "country": "IN",
    "subdivision": "35",
    "timezone": "Asia/Kolkata"
  },
  "geometry": {
    "type": "Point",
    "coordinates": [
      78.43312,
      22.46791
    ]
  }
}