{
  "type": "Feature",
  "properties": {
    "name": "ParÄsia",
    "country": "IN",
    "subdivision": "35",
    "timezone": "Asia/Kolkata"
  },
  "geometry": {
    "type": "Point",
    "coordinates": [
      78.75904,
      22.1913
    ]
  }
}