{
  "type": "Feature",
  "properties": {
    "name": "Porsa",
    "country": "IN",
    "subdivision": "35",
    "timezone": "Asia/Kolkata"
  },
  "geometry": {
    "type": "Point",
    "coordinates": [
      78.37081,
      26.67444
    ]
  }
}