{
  "type": "Feature",
  "properties": {
    "name": "RÄjnagar",
    "country": "IN",
    "subdivision": "35",
    "timezone": "Asia/Kolkata"
  },
  "geometry": {
    "type": "Point",
    "coordinates": [
      79.91178,
      24.88929
    ]
  }
}