{
  "type": "Feature",
  "properties": {
    "name": "Satna",
    "country": "IN",
    "subdivision": "35",
    "timezone": "Asia/Kolkata"
  },
  "geometry": {
    "type": "Point",
    "coordinates": [
      80.82719,
      24.57726
    ]
  }
}