{
  "type": "Feature",
  "properties": {
    "name": "Sausar",
    "country": "IN",
    "subdivision": "35",
    "timezone": "Asia/Kolkata"
  },
  "geometry": {
    "type": "Point",
    "coordinates": [
      78.79669,
      21.65576
    ]
  }
}