{
  "type": "Feature",
  "properties": {
    "name": "Sendhwa",
    "country": "IN",
    "subdivision": "35",
    "timezone": "Asia/Kolkata"
  },
  "geometry": {
    "type": "Point",
    "coordinates": [
      75.09622,
      21.68562
    ]
  }
}