{
  "type": "Feature",
  "properties": {
    "name": "ShÄhgarh",
    "country": "IN",
    "subdivision": "35",
    "timezone": "Asia/Kolkata"
  },
  "geometry": {
    "type": "Point",
    "coordinates": [
      79.11806,
      24.31365
    ]
  }
}