{
  "type": "Feature",
  "properties": {
    "name": "Shahdol",
    "country": "IN",
    "subdivision": "35",
    "timezone": "Asia/Kolkata"
  },
  "geometry": {
    "type": "Point",
    "coordinates": [
      81.3619,
      23.29356
    ]
  }
}