{
  "type": "Feature",
  "properties": {
    "name": "Shājāpur",
    "country": "IN",
    "subdivision": "35",
    "timezone": "Asia/Kolkata"
  },
  "geometry": {
    "type": "Point",
    "coordinates": [
      76.27775,
      23.42637
    ]
  }
}