{
  "type": "Feature",
  "properties": {
    "name": "ShujÄlpur",
    "country": "IN",
    "subdivision": "35",
    "timezone": "Asia/Kolkata"
  },
  "geometry": {
    "type": "Point",
    "coordinates": [
      76.7098,
      23.40673
    ]
  }
}