{
  "type": "Feature",
  "properties": {
    "name": "Sītāmau",
    "country": "IN",
    "subdivision": "35",
    "timezone": "Asia/Kolkata"
  },
  "geometry": {
    "type": "Point",
    "coordinates": [
      75.35324,
      24.01473
    ]
  }
}