{
  "type": "Feature",
  "properties": {
    "name": "Ujjain",
    "country": "IN",
    "subdivision": "35",
    "timezone": "Asia/Kolkata"
  },
  "geometry": {
    "type": "Point",
    "coordinates": [
      75.77643,
      23.18239
    ]
  }
}