{
  "type": "Feature",
  "properties": {
    "name": "Vidisha",
    "country": "IN",
    "subdivision": "35",
    "timezone": "Asia/Kolkata"
  },
  "geometry": {
    "type": "Point",
    "coordinates": [
      77.81092,
      23.52604
    ]
  }
}