{
  "type": "Feature",
  "properties": {
    "name": "Dange",
    "country": "NG",
    "subdivision": "51",
    "timezone": "Africa/Lagos"
  },
  "geometry": {
    "type": "Point",
    "coordinates": [
      5.34572,
      12.85313
    ]
  }
}