{
  "type": "Feature",
  "properties": {
    "name": "Wurno",
    "country": "NG",
    "subdivision": "51",
    "timezone": "Africa/Lagos"
  },
  "geometry": {
    "type": "Point",
    "coordinates": [
      5.42373,
      13.29048
    ]
  }
}