{
  "type": "Feature",
  "properties": {
    "name": "Remedios",
    "country": "CU",
    "subdivision": "16",
    "timezone": "America/Havana"
  },
  "geometry": {
    "type": "Point",
    "coordinates": [
      -79.54548,
      22.49502
    ]
  }
}