{
  "type": "Feature",
  "properties": {
    "name": "Balerna",
    "country": "CH",
    "subdivision": "TI",
    "timezone": "Europe/Zurich"
  },
  "geometry": {
    "type": "Point",
    "coordinates": [
      9.00724,
      45.84638
    ]
  }
}