{
  "type": "Feature",
  "properties": {
    "name": "Castel San Pietro",
    "country": "CH",
    "subdivision": "TI",
    "timezone": "Europe/Zurich"
  },
  "geometry": {
    "type": "Point",
    "coordinates": [
      9.00843,
      45.86211
    ]
  }
}