{
  "type": "Feature",
  "properties": {
    "name": "Chiasso",
    "country": "CH",
    "subdivision": "TI",
    "timezone": "Europe/Zurich"
  },
  "geometry": {
    "type": "Point",
    "coordinates": [
      9.03119,
      45.83203
    ]
  }
}