{
  "type": "Feature",
  "properties": {
    "name": "Claro",
    "country": "CH",
    "subdivision": "TI",
    "timezone": "Europe/Zurich"
  },
  "geometry": {
    "type": "Point",
    "coordinates": [
      9.02252,
      46.25763
    ]
  }
}