{
  "type": "Feature",
  "properties": {
    "name": "Comano",
    "country": "CH",
    "subdivision": "TI",
    "timezone": "Europe/Zurich"
  },
  "geometry": {
    "type": "Point",
    "coordinates": [
      8.95526,
      46.03635
    ]
  }
}