{
  "type": "Feature",
  "properties": {
    "name": "Melide",
    "country": "CH",
    "subdivision": "TI",
    "timezone": "Europe/Zurich"
  },
  "geometry": {
    "type": "Point",
    "coordinates": [
      8.94725,
      45.95455
    ]
  }
}