{
  "type": "Feature",
  "properties": {
    "name": "Monte Carasso",
    "country": "CH",
    "subdivision": "TI",
    "timezone": "Europe/Zurich"
  },
  "geometry": {
    "type": "Point",
    "coordinates": [
      8.99892,
      46.18649
    ]
  }
}