{
  "type": "Feature",
  "properties": {
    "name": "Morbio Inferiore",
    "country": "CH",
    "subdivision": "TI",
    "timezone": "Europe/Zurich"
  },
  "geometry": {
    "type": "Point",
    "coordinates": [
      9.01907,
      45.84915
    ]
  }
}