{
  "type": "Feature",
  "properties": {
    "name": "Muralto",
    "country": "CH",
    "subdivision": "TI",
    "timezone": "Europe/Zurich"
  },
  "geometry": {
    "type": "Point",
    "coordinates": [
      8.80219,
      46.17323
    ]
  }
}