{
  "type": "Feature",
  "properties": {
    "name": "Pregassona",
    "country": "CH",
    "subdivision": "TI",
    "timezone": "Europe/Zurich"
  },
  "geometry": {
    "type": "Point",
    "coordinates": [
      8.97429,
      46.02021
    ]
  }
}