{
  "type": "Feature",
  "properties": {
    "name": "Nkwerre",
    "country": "NG",
    "subdivision": "28",
    "timezone": "Africa/Lagos"
  },
  "geometry": {
    "type": "Point",
    "coordinates": [
      7.10384,
      5.75917
    ]
  }
}