{
  "type": "Feature",
  "properties": {
    "name": "Porus",
    "country": "JM",
    "subdivision": "04",
    "timezone": "America/Jamaica"
  },
  "geometry": {
    "type": "Point",
    "coordinates": [
      -77.41166,
      18.03535
    ]
  }
}