{
  "type": "Feature",
  "properties": {
    "name": "Mayqayyng",
    "country": "KZ",
    "subdivision": "11",
    "timezone": "Asia/Almaty"
  },
  "geometry": {
    "type": "Point",
    "coordinates": [
      75.80232,
      51.45981
    ]
  }
}