{
  "type": "Feature",
  "properties": {
    "name": "Adéane",
    "country": "SN",
    "subdivision": "12",
    "timezone": "Africa/Dakar"
  },
  "geometry": {
    "type": "Point",
    "coordinates": [
      -16.01694,
      12.63
    ]
  }
}