{
  "type": "Feature",
  "properties": {
    "name": "Postojna",
    "country": "SI",
    "subdivision": "94",
    "timezone": "Europe/Ljubljana"
  },
  "geometry": {
    "type": "Point",
    "coordinates": [
      14.21528,
      45.77435
    ]
  }
}