{
  "type": "Feature",
  "properties": {
    "name": "Apomu",
    "country": "NG",
    "subdivision": "42",
    "timezone": "Africa/Lagos"
  },
  "geometry": {
    "type": "Point",
    "coordinates": [
      4.18335,
      7.35156
    ]
  }
}