{
  "type": "Feature",
  "properties": {
    "name": "Ikirun",
    "country": "NG",
    "subdivision": "42",
    "timezone": "Africa/Lagos"
  },
  "geometry": {
    "type": "Point",
    "coordinates": [
      4.66741,
      7.91283
    ]
  }
}