{
  "type": "Feature",
  "properties": {
    "name": "Ila Orangun",
    "country": "NG",
    "subdivision": "42",
    "timezone": "Africa/Lagos"
  },
  "geometry": {
    "type": "Point",
    "coordinates": [
      4.90421,
      8.01714
    ]
  }
}