{
  "type": "Feature",
  "properties": {
    "name": "Ilobu",
    "country": "NG",
    "subdivision": "42",
    "timezone": "Africa/Lagos"
  },
  "geometry": {
    "type": "Point",
    "coordinates": [
      4.48557,
      7.84036
    ]
  }
}