{
  "type": "Feature",
  "properties": {
    "name": "Modakeke",
    "country": "NG",
    "subdivision": "42",
    "timezone": "Africa/Lagos"
  },
  "geometry": {
    "type": "Point",
    "coordinates": [
      4.26031,
      7.38299
    ]
  }
}