{
  "type": "Feature",
  "properties": {
    "name": "General Elizardo Aquino",
    "country": "PY",
    "subdivision": "17",
    "timezone": "America/Asuncion"
  },
  "geometry": {
    "type": "Point",
    "coordinates": [
      -56.89942,
      -24.44548
    ]
  }
}