{
  "type": "Feature",
  "properties": {
    "name": "Lima",
    "country": "PY",
    "subdivision": "17",
    "timezone": "America/Asuncion"
  },
  "geometry": {
    "type": "Point",
    "coordinates": [
      -56.47891,
      -23.88496
    ]
  }
}