{
  "type": "Feature",
  "properties": {
    "name": "Tacuatí",
    "country": "PY",
    "subdivision": "17",
    "timezone": "America/Asuncion"
  },
  "geometry": {
    "type": "Point",
    "coordinates": [
      -56.73672,
      -23.45767
    ]
  }
}