{
  "type": "Feature",
  "properties": {
    "name": "Borgo Santa Maria",
    "country": "IT",
    "subdivision": "10",
    "timezone": "Europe/Rome"
  },
  "geometry": {
    "type": "Point",
    "coordinates": [
      12.80235,
      43.87582
    ]
  }
}