{
  "type": "Feature",
  "properties": {
    "name": "Borgo Stazione",
    "country": "IT",
    "subdivision": "10",
    "timezone": "Europe/Rome"
  },
  "geometry": {
    "type": "Point",
    "coordinates": [
      13.6442,
      43.28461
    ]
  }
}