{
  "type": "Feature",
  "properties": {
    "name": "Cupramontana",
    "country": "IT",
    "subdivision": "10",
    "timezone": "Europe/Rome"
  },
  "geometry": {
    "type": "Point",
    "coordinates": [
      13.11312,
      43.44975
    ]
  }
}