{
  "type": "Feature",
  "properties": {
    "name": "Cupra Marittima",
    "country": "IT",
    "subdivision": "10",
    "timezone": "Europe/Rome"
  },
  "geometry": {
    "type": "Point",
    "coordinates": [
      13.86171,
      43.01905
    ]
  }
}