{
  "type": "Feature",
  "properties": {
    "name": "Filottrano",
    "country": "IT",
    "subdivision": "10",
    "timezone": "Europe/Rome"
  },
  "geometry": {
    "type": "Point",
    "coordinates": [
      13.35141,
      43.43553
    ]
  }
}