{
  "type": "Feature",
  "properties": {
    "name": "Fossombrone",
    "country": "IT",
    "subdivision": "10",
    "timezone": "Europe/Rome"
  },
  "geometry": {
    "type": "Point",
    "coordinates": [
      12.81173,
      43.69017
    ]
  }
}