{
  "type": "Feature",
  "properties": {
    "name": "Macine-Borgo Loreto",
    "country": "IT",
    "subdivision": "10",
    "timezone": "Europe/Rome"
  },
  "geometry": {
    "type": "Point",
    "coordinates": [
      13.08725,
      43.48611
    ]
  }
}