{
  "type": "Feature",
  "properties": {
    "name": "Monte San Pietrangeli",
    "country": "IT",
    "subdivision": "10",
    "timezone": "Europe/Rome"
  },
  "geometry": {
    "type": "Point",
    "coordinates": [
      13.57718,
      43.18959
    ]
  }
}