{
  "type": "Feature",
  "properties": {
    "name": "Offida",
    "country": "IT",
    "subdivision": "10",
    "timezone": "Europe/Rome"
  },
  "geometry": {
    "type": "Point",
    "coordinates": [
      13.69773,
      42.93499
    ]
  }
}