{
  "type": "Feature",
  "properties": {
    "name": "Orciano di Pesaro",
    "country": "IT",
    "subdivision": "10",
    "timezone": "Europe/Rome"
  },
  "geometry": {
    "type": "Point",
    "coordinates": [
      12.97206,
      43.68938
    ]
  }
}