{
  "type": "Feature",
  "properties": {
    "name": "Piane di Morro",
    "country": "IT",
    "subdivision": "10",
    "timezone": "Europe/Rome"
  },
  "geometry": {
    "type": "Point",
    "coordinates": [
      13.653,
      42.82317
    ]
  }
}