{
  "type": "Feature",
  "properties": {
    "name": "Piediripa",
    "country": "IT",
    "subdivision": "10",
    "timezone": "Europe/Rome"
  },
  "geometry": {
    "type": "Point",
    "coordinates": [
      13.48712,
      43.27751
    ]
  }
}