{
  "type": "Feature",
  "properties": {
    "name": "Polverigi",
    "country": "IT",
    "subdivision": "10",
    "timezone": "Europe/Rome"
  },
  "geometry": {
    "type": "Point",
    "coordinates": [
      13.38294,
      43.52876
    ]
  }
}