{
  "type": "Feature",
  "properties": {
    "name": "Rosciano",
    "country": "IT",
    "subdivision": "10",
    "timezone": "Europe/Rome"
  },
  "geometry": {
    "type": "Point",
    "coordinates": [
      12.99992,
      43.8162
    ]
  }
}