{
  "type": "Feature",
  "properties": {
    "name": "San Benedetto del Tronto",
    "country": "IT",
    "subdivision": "10",
    "timezone": "Europe/Rome"
  },
  "geometry": {
    "type": "Point",
    "coordinates": [
      13.87676,
      42.9568
    ]
  }
}