{
  "type": "Feature",
  "properties": {
    "name": "Strada",
    "country": "IT",
    "subdivision": "10",
    "timezone": "Europe/Rome"
  },
  "geometry": {
    "type": "Point",
    "coordinates": [
      13.22077,
      43.40337
    ]
  }
}