{
  "type": "Feature",
  "properties": {
    "name": "Tolentino",
    "country": "IT",
    "subdivision": "10",
    "timezone": "Europe/Rome"
  },
  "geometry": {
    "type": "Point",
    "coordinates": [
      13.28524,
      43.20918
    ]
  }
}