{
  "type": "Feature",
  "properties": {
    "name": "Villa Musone",
    "country": "IT",
    "subdivision": "10",
    "timezone": "Europe/Rome"
  },
  "geometry": {
    "type": "Point",
    "coordinates": [
      13.60312,
      43.44624
    ]
  }
}