{
  "type": "Feature",
  "properties": {
    "name": "Villa Potenza",
    "country": "IT",
    "subdivision": "10",
    "timezone": "Europe/Rome"
  },
  "geometry": {
    "type": "Point",
    "coordinates": [
      13.42649,
      43.32149
    ]
  }
}