{
  "type": "Feature",
  "properties": {
    "name": "Allende",
    "country": "MX",
    "subdivision": "21",
    "timezone": "America/Mexico_City"
  },
  "geometry": {
    "type": "Point",
    "coordinates": [
      -97.59711,
      19.53879
    ]
  }
}