{
  "type": "Feature",
  "properties": {
    "name": "Atzala",
    "country": "MX",
    "subdivision": "21",
    "timezone": "America/Mexico_City"
  },
  "geometry": {
    "type": "Point",
    "coordinates": [
      -98.55306,
      18.54639
    ]
  }
}