{
  "type": "Feature",
  "properties": {
    "name": "Atzitzintla",
    "country": "MX",
    "subdivision": "21",
    "timezone": "America/Mexico_City"
  },
  "geometry": {
    "type": "Point",
    "coordinates": [
      -97.3244,
      18.89915
    ]
  }
}