{
  "type": "Feature",
  "properties": {
    "name": "Buenavista de Juárez",
    "country": "MX",
    "subdivision": "21",
    "timezone": "America/Mexico_City"
  },
  "geometry": {
    "type": "Point",
    "coordinates": [
      -97.82778,
      18.945
    ]
  }
}