{
  "type": "Feature",
  "properties": {
    "name": "Buenavista Tetela",
    "country": "MX",
    "subdivision": "21",
    "timezone": "America/Mexico_City"
  },
  "geometry": {
    "type": "Point",
    "coordinates": [
      -98.17632,
      18.91967
    ]
  }
}