{
  "type": "Feature",
  "properties": {
    "name": "Calpanería Atezquilla",
    "country": "MX",
    "subdivision": "21",
    "timezone": "America/Mexico_City"
  },
  "geometry": {
    "type": "Point",
    "coordinates": [
      -97.99528,
      19.65556
    ]
  }
}