{
  "type": "Feature",
  "properties": {
    "name": "Chichicuautla",
    "country": "MX",
    "subdivision": "21",
    "timezone": "America/Mexico_City"
  },
  "geometry": {
    "type": "Point",
    "coordinates": [
      -97.39394,
      19.39073
    ]
  }
}