{
  "type": "Feature",
  "properties": {
    "name": "Chiconcuautla",
    "country": "MX",
    "subdivision": "21",
    "timezone": "America/Mexico_City"
  },
  "geometry": {
    "type": "Point",
    "coordinates": [
      -97.93896,
      20.09517
    ]
  }
}