{
  "type": "Feature",
  "properties": {
    "name": "Coatzingo",
    "country": "MX",
    "subdivision": "21",
    "timezone": "America/Mexico_City"
  },
  "geometry": {
    "type": "Point",
    "coordinates": [
      -98.17267,
      18.61199
    ]
  }
}