{
  "type": "Feature",
  "properties": {
    "name": "Colonia Agrícola de Ocotepec (Colonia San José)",
    "country": "MX",
    "subdivision": "21",
    "timezone": "America/Mexico_City"
  },
  "geometry": {
    "type": "Point",
    "coordinates": [
      -98.54444,
      18.92972
    ]
  }
}