{
  "type": "Feature",
  "properties": {
    "name": "Colonia Obrera",
    "country": "MX",
    "subdivision": "21",
    "timezone": "America/Mexico_City"
  },
  "geometry": {
    "type": "Point",
    "coordinates": [
      -97.7975,
      19.22944
    ]
  }
}