{
  "type": "Feature",
  "properties": {
    "name": "Comaltepec",
    "country": "MX",
    "subdivision": "21",
    "timezone": "America/Mexico_City"
  },
  "geometry": {
    "type": "Point",
    "coordinates": [
      -97.59938,
      19.85893
    ]
  }
}