{
  "type": "Feature",
  "properties": {
    "name": "Cuatro Caminos",
    "country": "MX",
    "subdivision": "21",
    "timezone": "America/Mexico_City"
  },
  "geometry": {
    "type": "Point",
    "coordinates": [
      -97.12901,
      18.4913
    ]
  }
}