{
  "type": "Feature",
  "properties": {
    "name": "Cuautempan",
    "country": "MX",
    "subdivision": "21",
    "timezone": "America/Mexico_City"
  },
  "geometry": {
    "type": "Point",
    "coordinates": [
      -97.79498,
      19.9138
    ]
  }
}