{
  "type": "Feature",
  "properties": {
    "name": "Cuaxuxpa",
    "country": "MX",
    "subdivision": "21",
    "timezone": "America/Mexico_City"
  },
  "geometry": {
    "type": "Point",
    "coordinates": [
      -97.03556,
      18.46211
    ]
  }
}