{
  "type": "Feature",
  "properties": {
    "name": "Cuetzalan",
    "country": "MX",
    "subdivision": "21",
    "timezone": "America/Mexico_City"
  },
  "geometry": {
    "type": "Point",
    "coordinates": [
      -97.52277,
      20.01766
    ]
  }
}