{
  "type": "Feature",
  "properties": {
    "name": "Cuyoaco",
    "country": "MX",
    "subdivision": "21",
    "timezone": "America/Mexico_City"
  },
  "geometry": {
    "type": "Point",
    "coordinates": [
      -97.62024,
      19.60192
    ]
  }
}