{
  "type": "Feature",
  "properties": {
    "name": "El Molino",
    "country": "MX",
    "subdivision": "21",
    "timezone": "America/Mexico_City"
  },
  "geometry": {
    "type": "Point",
    "coordinates": [
      -97.58028,
      19.81333
    ]
  }
}