{
  "type": "Feature",
  "properties": {
    "name": "Guadalupe Zaragoza",
    "country": "MX",
    "subdivision": "21",
    "timezone": "America/Mexico_City"
  },
  "geometry": {
    "type": "Point",
    "coordinates": [
      -98.5375,
      19.35833
    ]
  }
}