{
  "type": "Feature",
  "properties": {
    "name": "Huauchinango",
    "country": "MX",
    "subdivision": "21",
    "timezone": "America/Mexico_City"
  },
  "geometry": {
    "type": "Point",
    "coordinates": [
      -98.05491,
      20.17376
    ]
  }
}