{
  "type": "Feature",
  "properties": {
    "name": "Huautla de Jiménez",
    "country": "MX",
    "subdivision": "21",
    "timezone": "America/Mexico_City"
  },
  "geometry": {
    "type": "Point",
    "coordinates": [
      -96.84088,
      18.1315
    ]
  }
}