{
  "type": "Feature",
  "properties": {
    "name": "Ignacio Allende (Concepción)",
    "country": "MX",
    "subdivision": "21",
    "timezone": "America/Mexico_City"
  },
  "geometry": {
    "type": "Point",
    "coordinates": [
      -97.63448,
      20.01055
    ]
  }
}