{
  "type": "Feature",
  "properties": {
    "name": "Itzoteno",
    "country": "MX",
    "subdivision": "21",
    "timezone": "America/Mexico_City"
  },
  "geometry": {
    "type": "Point",
    "coordinates": [
      -97.43776,
      19.41656
    ]
  }
}