{
  "type": "Feature",
  "properties": {
    "name": "Ixtahuiata (La Legua)",
    "country": "MX",
    "subdivision": "21",
    "timezone": "America/Mexico_City"
  },
  "geometry": {
    "type": "Point",
    "coordinates": [
      -97.33556,
      19.84389
    ]
  }
}