{
  "type": "Feature",
  "properties": {
    "name": "Ixtlahuaca Barrio",
    "country": "MX",
    "subdivision": "21",
    "timezone": "America/Mexico_City"
  },
  "geometry": {
    "type": "Point",
    "coordinates": [
      -98.01444,
      19.83889
    ]
  }
}