{
  "type": "Feature",
  "properties": {
    "name": "Jolalpan",
    "country": "MX",
    "subdivision": "21",
    "timezone": "America/Mexico_City"
  },
  "geometry": {
    "type": "Point",
    "coordinates": [
      -98.84489,
      18.32495
    ]
  }
}