{
  "type": "Feature",
  "properties": {
    "name": "Juárez Coronaco",
    "country": "MX",
    "subdivision": "21",
    "timezone": "America/Mexico_City"
  },
  "geometry": {
    "type": "Point",
    "coordinates": [
      -98.525,
      19.36056
    ]
  }
}