{
  "type": "Feature",
  "properties": {
    "name": "La Galarza",
    "country": "MX",
    "subdivision": "21",
    "timezone": "America/Mexico_City"
  },
  "geometry": {
    "type": "Point",
    "coordinates": [
      -98.45528,
      18.66778
    ]
  }
}