{
  "type": "Feature",
  "properties": {
    "name": "Las Lajas",
    "country": "MX",
    "subdivision": "21",
    "timezone": "America/Mexico_City"
  },
  "geometry": {
    "type": "Point",
    "coordinates": [
      -98.07332,
      19.99831
    ]
  }
}