{
  "type": "Feature",
  "properties": {
    "name": "Los Reyes Tlanechicolpan",
    "country": "MX",
    "subdivision": "21",
    "timezone": "America/Mexico_City"
  },
  "geometry": {
    "type": "Point",
    "coordinates": [
      -98.3525,
      19.0325
    ]
  }
}