{
  "type": "Feature",
  "properties": {
    "name": "Manuel Edgardo Ávalos (San Isidro)",
    "country": "MX",
    "subdivision": "21",
    "timezone": "America/Mexico_City"
  },
  "geometry": {
    "type": "Point",
    "coordinates": [
      -97.39194,
      19.06778
    ]
  }
}