{
  "type": "Feature",
  "properties": {
    "name": "Matzaco",
    "country": "MX",
    "subdivision": "21",
    "timezone": "America/Mexico_City"
  },
  "geometry": {
    "type": "Point",
    "coordinates": [
      -98.4882,
      18.55953
    ]
  }
}