{
  "type": "Feature",
  "properties": {
    "name": "Necoxtla",
    "country": "MX",
    "subdivision": "21",
    "timezone": "America/Mexico_City"
  },
  "geometry": {
    "type": "Point",
    "coordinates": [
      -97.35999,
      18.39811
    ]
  }
}