{
  "type": "Feature",
  "properties": {
    "name": "Oriental",
    "country": "MX",
    "subdivision": "21",
    "timezone": "America/Mexico_City"
  },
  "geometry": {
    "type": "Point",
    "coordinates": [
      -97.62051,
      19.37614
    ]
  }
}