{
  "type": "Feature",
  "properties": {
    "name": "Oyameles de Hidalgo",
    "country": "MX",
    "subdivision": "21",
    "timezone": "America/Mexico_City"
  },
  "geometry": {
    "type": "Point",
    "coordinates": [
      -97.53376,
      19.69736
    ]
  }
}