{
  "type": "Feature",
  "properties": {
    "name": "Palmar de Bravo",
    "country": "MX",
    "subdivision": "21",
    "timezone": "America/Mexico_City"
  },
  "geometry": {
    "type": "Point",
    "coordinates": [
      -97.54704,
      18.83573
    ]
  }
}