{
  "type": "Feature",
  "properties": {
    "name": "Pezmatlán",
    "country": "MX",
    "subdivision": "21",
    "timezone": "America/Mexico_City"
  },
  "geometry": {
    "type": "Point",
    "coordinates": [
      -97.48529,
      19.84664
    ]
  }
}