{
  "type": "Feature",
  "properties": {
    "name": "Ricardo Flores Magón",
    "country": "MX",
    "subdivision": "21",
    "timezone": "America/Mexico_City"
  },
  "geometry": {
    "type": "Point",
    "coordinates": [
      -97.61961,
      20.19224
    ]
  }
}