{
  "type": "Feature",
  "properties": {
    "name": "San Jerónimo Almoloya",
    "country": "MX",
    "subdivision": "21",
    "timezone": "America/Mexico_City"
  },
  "geometry": {
    "type": "Point",
    "coordinates": [
      -98.01056,
      18.94111
    ]
  }
}