{
  "type": "Feature",
  "properties": {
    "name": "San Andrés Calpan",
    "country": "MX",
    "subdivision": "21",
    "timezone": "America/Mexico_City"
  },
  "geometry": {
    "type": "Point",
    "coordinates": [
      -98.46188,
      19.10356
    ]
  }
}