{
  "type": "Feature",
  "properties": {
    "name": "San Lorenzo Joya de Rodríguez",
    "country": "MX",
    "subdivision": "21",
    "timezone": "America/Mexico_City"
  },
  "geometry": {
    "type": "Point",
    "coordinates": [
      -97.85333,
      19.05444
    ]
  }
}