{
  "type": "Feature",
  "properties": {
    "name": "San Pedro Temamatla",
    "country": "MX",
    "subdivision": "21",
    "timezone": "America/Mexico_City"
  },
  "geometry": {
    "type": "Point",
    "coordinates": [
      -97.51198,
      18.92553
    ]
  }
}