{
  "type": "Feature",
  "properties": {
    "name": "San Nicolás Zecalacoayan",
    "country": "MX",
    "subdivision": "21",
    "timezone": "America/Mexico_City"
  },
  "geometry": {
    "type": "Point",
    "coordinates": [
      -98.48833,
      19.19917
    ]
  }
}