{
  "type": "Feature",
  "properties": {
    "name": "San Félix Rijo",
    "country": "MX",
    "subdivision": "21",
    "timezone": "America/Mexico_City"
  },
  "geometry": {
    "type": "Point",
    "coordinates": [
      -98.55028,
      18.62028
    ]
  }
}