{
  "type": "Feature",
  "properties": {
    "name": "San Miguel Zozutla",
    "country": "MX",
    "subdivision": "21",
    "timezone": "America/Mexico_City"
  },
  "geometry": {
    "type": "Point",
    "coordinates": [
      -97.65478,
      18.7543
    ]
  }
}