{
  "type": "Feature",
  "properties": {
    "name": "San Andrés",
    "country": "MX",
    "subdivision": "21",
    "timezone": "America/Mexico_City"
  },
  "geometry": {
    "type": "Point",
    "coordinates": [
      -97.33889,
      19.79
    ]
  }
}