{
  "type": "Feature",
  "properties": {
    "name": "San Juan Xiutetelco",
    "country": "MX",
    "subdivision": "21",
    "timezone": "America/Mexico_City"
  },
  "geometry": {
    "type": "Point",
    "coordinates": [
      -97.32578,
      19.79563
    ]
  }
}