{
  "type": "Feature",
  "properties": {
    "name": "San Luis Tehuiloyocan",
    "country": "MX",
    "subdivision": "21",
    "timezone": "America/Mexico_City"
  },
  "geometry": {
    "type": "Point",
    "coordinates": [
      -98.33749,
      19.03924
    ]
  }
}