{
  "type": "Feature",
  "properties": {
    "name": "San Jerónimo Coaltepec",
    "country": "MX",
    "subdivision": "21",
    "timezone": "America/Mexico_City"
  },
  "geometry": {
    "type": "Point",
    "coordinates": [
      -97.86639,
      20.00389
    ]
  }
}