{
  "type": "Feature",
  "properties": {
    "name": "San Mateo Ozolco",
    "country": "MX",
    "subdivision": "21",
    "timezone": "America/Mexico_City"
  },
  "geometry": {
    "type": "Point",
    "coordinates": [
      -98.51566,
      19.09994
    ]
  }
}