{
  "type": "Feature",
  "properties": {
    "name": "San Andrés Yahuitlalpan",
    "country": "MX",
    "subdivision": "21",
    "timezone": "America/Mexico_City"
  },
  "geometry": {
    "type": "Point",
    "coordinates": [
      -97.72694,
      19.67333
    ]
  }
}