{
  "type": "Feature",
  "properties": {
    "name": "San Juan Raboso",
    "country": "MX",
    "subdivision": "21",
    "timezone": "America/Mexico_City"
  },
  "geometry": {
    "type": "Point",
    "coordinates": [
      -98.43962,
      18.57153
    ]
  }
}