{
  "type": "Feature",
  "properties": {
    "name": "San Hipólito",
    "country": "MX",
    "subdivision": "21",
    "timezone": "America/Mexico_City"
  },
  "geometry": {
    "type": "Point",
    "coordinates": [
      -97.87322,
      18.94069
    ]
  }
}