{
  "type": "Feature",
  "properties": {
    "name": "San Gabriel Chilac",
    "country": "MX",
    "subdivision": "21",
    "timezone": "America/Mexico_City"
  },
  "geometry": {
    "type": "Point",
    "coordinates": [
      -97.34697,
      18.32596
    ]
  }
}