{
  "type": "Feature",
  "properties": {
    "name": "San José Tilapa",
    "country": "MX",
    "subdivision": "21",
    "timezone": "America/Mexico_City"
  },
  "geometry": {
    "type": "Point",
    "coordinates": [
      -97.10137,
      18.16361
    ]
  }
}