{
  "type": "Feature",
  "properties": {
    "name": "San Marcos Eloxochitlán",
    "country": "MX",
    "subdivision": "21",
    "timezone": "America/Mexico_City"
  },
  "geometry": {
    "type": "Point",
    "coordinates": [
      -97.87194,
      20.02528
    ]
  }
}