{
  "type": "Feature",
  "properties": {
    "name": "San Juan Tejupa",
    "country": "MX",
    "subdivision": "21",
    "timezone": "America/Mexico_City"
  },
  "geometry": {
    "type": "Point",
    "coordinates": [
      -98.54124,
      18.85519
    ]
  }
}