{
  "type": "Feature",
  "properties": {
    "name": "Santa Cruz Xaltetela",
    "country": "MX",
    "subdivision": "21",
    "timezone": "America/Mexico_City"
  },
  "geometry": {
    "type": "Point",
    "coordinates": [
      -97.58083,
      19.87417
    ]
  }
}