{
  "type": "Feature",
  "properties": {
    "name": "Santa Rosa",
    "country": "MX",
    "subdivision": "21",
    "timezone": "America/Mexico_City"
  },
  "geometry": {
    "type": "Point",
    "coordinates": [
      -97.78122,
      18.87704
    ]
  }
}