{
  "type": "Feature",
  "properties": {
    "name": "Santiago Yancuictlalpan",
    "country": "MX",
    "subdivision": "21",
    "timezone": "America/Mexico_City"
  },
  "geometry": {
    "type": "Point",
    "coordinates": [
      -97.47223,
      20.06092
    ]
  }
}