{
  "type": "Feature",
  "properties": {
    "name": "Santa María Nenetzintla",
    "country": "MX",
    "subdivision": "21",
    "timezone": "America/Mexico_City"
  },
  "geometry": {
    "type": "Point",
    "coordinates": [
      -97.96664,
      19.05413
    ]
  }
}