{
  "type": "Feature",
  "properties": {
    "name": "Santa Cruz Cuautomatitla",
    "country": "MX",
    "subdivision": "21",
    "timezone": "America/Mexico_City"
  },
  "geometry": {
    "type": "Point",
    "coordinates": [
      -98.65917,
      18.88917
    ]
  }
}