{
  "type": "Feature",
  "properties": {
    "name": "Teotlalco",
    "country": "MX",
    "subdivision": "21",
    "timezone": "America/Mexico_City"
  },
  "geometry": {
    "type": "Point",
    "coordinates": [
      -98.77822,
      18.4691
    ]
  }
}