{
  "type": "Feature",
  "properties": {
    "name": "Tepazolco",
    "country": "MX",
    "subdivision": "21",
    "timezone": "America/Mexico_City"
  },
  "geometry": {
    "type": "Point",
    "coordinates": [
      -97.69637,
      18.69967
    ]
  }
}