{
  "type": "Feature",
  "properties": {
    "name": "Tepeojuma",
    "country": "MX",
    "subdivision": "21",
    "timezone": "America/Mexico_City"
  },
  "geometry": {
    "type": "Point",
    "coordinates": [
      -98.44633,
      18.72468
    ]
  }
}