{
  "type": "Feature",
  "properties": {
    "name": "Tepetzitzintla",
    "country": "MX",
    "subdivision": "21",
    "timezone": "America/Mexico_City"
  },
  "geometry": {
    "type": "Point",
    "coordinates": [
      -98.07305,
      18.68715
    ]
  }
}