{
  "type": "Feature",
  "properties": {
    "name": "Tlaxpanaloya",
    "country": "MX",
    "subdivision": "21",
    "timezone": "America/Mexico_City"
  },
  "geometry": {
    "type": "Point",
    "coordinates": [
      -98.12036,
      20.22589
    ]
  }
}