{
  "type": "Feature",
  "properties": {
    "name": "Tomatlán",
    "country": "MX",
    "subdivision": "21",
    "timezone": "America/Mexico_City"
  },
  "geometry": {
    "type": "Point",
    "coordinates": [
      -97.97346,
      19.89399
    ]
  }
}