{
  "type": "Feature",
  "properties": {
    "name": "Tomaquilapa",
    "country": "MX",
    "subdivision": "21",
    "timezone": "America/Mexico_City"
  },
  "geometry": {
    "type": "Point",
    "coordinates": [
      -97.32161,
      19.75635
    ]
  }
}