{
  "type": "Feature",
  "properties": {
    "name": "Tula",
    "country": "MX",
    "subdivision": "21",
    "timezone": "America/Mexico_City"
  },
  "geometry": {
    "type": "Point",
    "coordinates": [
      -97.90935,
      18.53857
    ]
  }
}