{
  "type": "Feature",
  "properties": {
    "name": "Tulimanca",
    "country": "MX",
    "subdivision": "21",
    "timezone": "America/Mexico_City"
  },
  "geometry": {
    "type": "Point",
    "coordinates": [
      -97.14,
      18.46944
    ]
  }
}