{
  "type": "Feature",
  "properties": {
    "name": "Tzinacapan",
    "country": "MX",
    "subdivision": "21",
    "timezone": "America/Mexico_City"
  },
  "geometry": {
    "type": "Point",
    "coordinates": [
      -97.54047,
      20.02944
    ]
  }
}