{
  "type": "Feature",
  "properties": {
    "name": "Venustiano Carranza",
    "country": "MX",
    "subdivision": "21",
    "timezone": "America/Mexico_City"
  },
  "geometry": {
    "type": "Point",
    "coordinates": [
      -97.66806,
      20.50667
    ]
  }
}