{
  "type": "Feature",
  "properties": {
    "name": "Vicente Guerrero",
    "country": "MX",
    "subdivision": "21",
    "timezone": "America/Mexico_City"
  },
  "geometry": {
    "type": "Point",
    "coordinates": [
      -97.65417,
      20.12322
    ]
  }
}