{
  "type": "Feature",
  "properties": {
    "name": "Xalticpac",
    "country": "MX",
    "subdivision": "21",
    "timezone": "America/Mexico_City"
  },
  "geometry": {
    "type": "Point",
    "coordinates": [
      -97.59556,
      19.84301
    ]
  }
}