{
  "type": "Feature",
  "properties": {
    "name": "Xochitepec",
    "country": "MX",
    "subdivision": "21",
    "timezone": "America/Mexico_City"
  },
  "geometry": {
    "type": "Point",
    "coordinates": [
      -98.87611,
      18.22833
    ]
  }
}