{
  "type": "Feature",
  "properties": {
    "name": "Xuchapa",
    "country": "MX",
    "subdivision": "21",
    "timezone": "America/Mexico_City"
  },
  "geometry": {
    "type": "Point",
    "coordinates": [
      -98.45705,
      18.5265
    ]
  }
}