{
  "type": "Feature",
  "properties": {
    "name": "Zacatlán",
    "country": "MX",
    "subdivision": "21",
    "timezone": "America/Mexico_City"
  },
  "geometry": {
    "type": "Point",
    "coordinates": [
      -97.96125,
      19.9355
    ]
  }
}