{
  "type": "Feature",
  "properties": {
    "name": "Fertőszentmiklós",
    "country": "HU",
    "subdivision": "09",
    "timezone": "Europe/Budapest"
  },
  "geometry": {
    "type": "Point",
    "coordinates": [
      16.87517,
      47.58996
    ]
  }
}