{
  "type": "Feature",
  "properties": {
    "name": "Győrszemere",
    "country": "HU",
    "subdivision": "09",
    "timezone": "Europe/Budapest"
  },
  "geometry": {
    "type": "Point",
    "coordinates": [
      17.56356,
      47.55256
    ]
  }
}