{
  "type": "Feature",
  "properties": {
    "name": "Kóny",
    "country": "HU",
    "subdivision": "09",
    "timezone": "Europe/Budapest"
  },
  "geometry": {
    "type": "Point",
    "coordinates": [
      17.35717,
      47.63053
    ]
  }
}