{
  "type": "Feature",
  "properties": {
    "name": "Mihályi",
    "country": "HU",
    "subdivision": "09",
    "timezone": "Europe/Budapest"
  },
  "geometry": {
    "type": "Point",
    "coordinates": [
      17.09507,
      47.51384
    ]
  }
}