{
  "type": "Feature",
  "properties": {
    "name": "Rábapatona",
    "country": "HU",
    "subdivision": "09",
    "timezone": "Europe/Budapest"
  },
  "geometry": {
    "type": "Point",
    "coordinates": [
      17.48004,
      47.63224
    ]
  }
}