{
  "type": "Feature",
  "properties": {
    "name": "Akure",
    "country": "NG",
    "subdivision": "48",
    "timezone": "Africa/Lagos"
  },
  "geometry": {
    "type": "Point",
    "coordinates": [
      5.19312,
      7.25256
    ]
  }
}