{
  "type": "Feature",
  "properties": {
    "name": "Guayaramerín",
    "country": "BO",
    "subdivision": "03",
    "timezone": "America/La_Paz"
  },
  "geometry": {
    "type": "Point",
    "coordinates": [
      -65.3581,
      -10.8258
    ]
  }
}