{
  "type": "Feature",
  "properties": {
    "name": "Pınarbaşı",
    "country": "TR",
    "subdivision": "37",
    "timezone": "Europe/Istanbul"
  },
  "geometry": {
    "type": "Point",
    "coordinates": [
      33.11099,
      41.60388
    ]
  }
}