{
  "type": "Feature",
  "properties": {
    "name": "Seydiler",
    "country": "TR",
    "subdivision": "37",
    "timezone": "Europe/Istanbul"
  },
  "geometry": {
    "type": "Point",
    "coordinates": [
      33.71815,
      41.62005
    ]
  }
}