{
  "type": "Feature",
  "properties": {
    "name": "Ust’-Kamchatsk Staryy",
    "country": "RU",
    "subdivision": "92",
    "timezone": "Asia/Kamchatka"
  },
  "geometry": {
    "type": "Point",
    "coordinates": [
      162.47778,
      56.22778
    ]
  }
}