{
  "type": "Feature",
  "properties": {
    "name": "Çamlıdere",
    "country": "TR",
    "subdivision": "68",
    "timezone": "Europe/Istanbul"
  },
  "geometry": {
    "type": "Point",
    "coordinates": [
      32.47499,
      40.48958
    ]
  }
}