{
  "type": "Feature",
  "properties": {
    "name": "Şereflikoçhisar",
    "country": "TR",
    "subdivision": "68",
    "timezone": "Europe/Istanbul"
  },
  "geometry": {
    "type": "Point",
    "coordinates": [
      33.5386,
      38.93925
    ]
  }
}