{
  "type": "Feature",
  "properties": {
    "name": "Naujamiestis",
    "country": "LT",
    "subdivision": "65",
    "timezone": "Europe/Vilnius"
  },
  "geometry": {
    "type": "Point",
    "coordinates": [
      25.26855,
      54.67951
    ]
  }
}