{
  "type": "Feature",
  "properties": {
    "name": "Švenčionėliai",
    "country": "LT",
    "subdivision": "65",
    "timezone": "Europe/Vilnius"
  },
  "geometry": {
    "type": "Point",
    "coordinates": [
      26.00177,
      55.16163
    ]
  }
}