{
  "type": "Feature",
  "properties": {
    "name": "Vilkpėdė",
    "country": "LT",
    "subdivision": "65",
    "timezone": "Europe/Vilnius"
  },
  "geometry": {
    "type": "Point",
    "coordinates": [
      25.2477,
      54.66969
    ]
  }
}