{
  "type": "Feature",
  "properties": {
    "name": "Dobri Dol",
    "country": "MK",
    "subdivision": "B7",
    "timezone": "Europe/Skopje"
  },
  "geometry": {
    "type": "Point",
    "coordinates": [
      20.89009,
      41.8652
    ]
  }
}