{
  "type": "Feature",
  "properties": {
    "name": "Cuauhtémoc",
    "country": "MX",
    "subdivision": "09",
    "timezone": "America/Mexico_City"
  },
  "geometry": {
    "type": "Point",
    "coordinates": [
      -99.14612,
      19.44506
    ]
  }
}