{
  "type": "Feature",
  "properties": {
    "name": "Delegación Cuajimalpa de Morelos",
    "country": "MX",
    "subdivision": "09",
    "timezone": "America/Mexico_City"
  },
  "geometry": {
    "type": "Point",
    "coordinates": [
      -99.29089,
      19.3692
    ]
  }
}