{
  "type": "Feature",
  "properties": {
    "name": "Gustavo Adolfo Madero",
    "country": "MX",
    "subdivision": "09",
    "timezone": "America/Mexico_City"
  },
  "geometry": {
    "type": "Point",
    "coordinates": [
      -99.11075,
      19.49392
    ]
  }
}