{
  "type": "Feature",
  "properties": {
    "name": "Miguel Hidalgo",
    "country": "MX",
    "subdivision": "09",
    "timezone": "America/Mexico_City"
  },
  "geometry": {
    "type": "Point",
    "coordinates": [
      -99.20024,
      19.43411
    ]
  }
}