{
  "type": "Feature",
  "properties": {
    "name": "Santa Catarina Yecahuizotl",
    "country": "MX",
    "subdivision": "09",
    "timezone": "America/Mexico_City"
  },
  "geometry": {
    "type": "Point",
    "coordinates": [
      -98.96461,
      19.31205
    ]
  }
}