{
  "type": "Feature",
  "properties": {
    "name": "Betanzos",
    "country": "BO",
    "subdivision": "07",
    "timezone": "America/La_Paz"
  },
  "geometry": {
    "type": "Point",
    "coordinates": [
      -65.45395,
      -19.55293
    ]
  }
}