{
  "type": "Feature",
  "properties": {
    "name": "Santa Bárbara",
    "country": "BO",
    "subdivision": "07",
    "timezone": "America/La_Paz"
  },
  "geometry": {
    "type": "Point",
    "coordinates": [
      -66.05,
      -20.91667
    ]
  }
}