{
  "type": "Feature",
  "properties": {
    "name": "Guararé",
    "country": "PA",
    "subdivision": "07",
    "timezone": "America/Panama"
  },
  "geometry": {
    "type": "Point",
    "coordinates": [
      -80.2809,
      7.8198
    ]
  }
}