{
  "type": "Feature",
  "properties": {
    "name": "Pedasí",
    "country": "PA",
    "subdivision": "07",
    "timezone": "America/Panama"
  },
  "geometry": {
    "type": "Point",
    "coordinates": [
      -80.02699,
      7.53034
    ]
  }
}