{
  "type": "Feature",
  "properties": {
    "name": "Ash Shajarah",
    "country": "JO",
    "subdivision": "18",
    "timezone": "Asia/Amman"
  },
  "geometry": {
    "type": "Point",
    "coordinates": [
      35.94175,
      32.64391
    ]
  }
}