{
  "type": "Feature",
  "properties": {
    "name": "Dayr Yūsuf",
    "country": "JO",
    "subdivision": "18",
    "timezone": "Asia/Amman"
  },
  "geometry": {
    "type": "Point",
    "coordinates": [
      35.79635,
      32.48701
    ]
  }
}