{
  "type": "Feature",
  "properties": {
    "name": "Kafr Abīl",
    "country": "JO",
    "subdivision": "18",
    "timezone": "Asia/Amman"
  },
  "geometry": {
    "type": "Point",
    "coordinates": [
      35.66305,
      32.41752
    ]
  }
}