{
  "type": "Feature",
  "properties": {
    "name": "Samux",
    "country": "AZ",
    "subdivision": "52",
    "timezone": "Asia/Baku"
  },
  "geometry": {
    "type": "Point",
    "coordinates": [
      46.40868,
      40.76485
    ]
  }
}