{
  "type": "Feature",
  "properties": {
    "name": "Tengréla",
    "country": "CI",
    "subdivision": "87",
    "timezone": "Africa/Abidjan"
  },
  "geometry": {
    "type": "Point",
    "coordinates": [
      -6.40694,
      10.48115
    ]
  }
}