{
  "type": "Feature",
  "properties": {
    "name": "Apsheronsk",
    "country": "RU",
    "subdivision": "38",
    "timezone": "Europe/Moscow"
  },
  "geometry": {
    "type": "Point",
    "coordinates": [
      39.73417,
      44.46472
    ]
  }
}