{
  "type": "Feature",
  "properties": {
    "name": "Armavir",
    "country": "RU",
    "subdivision": "38",
    "timezone": "Europe/Moscow"
  },
  "geometry": {
    "type": "Point",
    "coordinates": [
      41.1234,
      44.9892
    ]
  }
}