{
  "type": "Feature",
  "properties": {
    "name": "Azovskaya",
    "country": "RU",
    "subdivision": "38",
    "timezone": "Europe/Moscow"
  },
  "geometry": {
    "type": "Point",
    "coordinates": [
      38.62639,
      44.79083
    ]
  }
}