{
  "type": "Feature",
  "properties": {
    "name": "Belozërnyy",
    "country": "RU",
    "subdivision": "38",
    "timezone": "Europe/Moscow"
  },
  "geometry": {
    "type": "Point",
    "coordinates": [
      38.72527,
      45.06748
    ]
  }
}