{
  "type": "Feature",
  "properties": {
    "name": "Chamlykskaya",
    "country": "RU",
    "subdivision": "38",
    "timezone": "Europe/Moscow"
  },
  "geometry": {
    "type": "Point",
    "coordinates": [
      40.87861,
      44.71583
    ]
  }
}