{
  "type": "Feature",
  "properties": {
    "name": "Chernoyerkovskaya",
    "country": "RU",
    "subdivision": "38",
    "timezone": "Europe/Moscow"
  },
  "geometry": {
    "type": "Point",
    "coordinates": [
      37.76861,
      45.43306
    ]
  }
}