{
  "type": "Feature",
  "properties": {
    "name": "Gelendzhik",
    "country": "RU",
    "subdivision": "38",
    "timezone": "Europe/Moscow"
  },
  "geometry": {
    "type": "Point",
    "coordinates": [
      38.0848,
      44.5622
    ]
  }
}