{
  "type": "Feature",
  "properties": {
    "name": "Irkliyevskaya",
    "country": "RU",
    "subdivision": "38",
    "timezone": "Europe/Moscow"
  },
  "geometry": {
    "type": "Point",
    "coordinates": [
      39.65381,
      45.85635
    ]
  }
}