{
  "type": "Feature",
  "properties": {
    "name": "Kushchëvskaya",
    "country": "RU",
    "subdivision": "38",
    "timezone": "Europe/Moscow"
  },
  "geometry": {
    "type": "Point",
    "coordinates": [
      39.6321,
      46.5599
    ]
  }
}