{
  "type": "Feature",
  "properties": {
    "name": "Nekrasovskaya",
    "country": "RU",
    "subdivision": "38",
    "timezone": "Europe/Moscow"
  },
  "geometry": {
    "type": "Point",
    "coordinates": [
      39.74868,
      45.14468
    ]
  }
}