{
  "type": "Feature",
  "properties": {
    "name": "Novoukrainskoye",
    "country": "RU",
    "subdivision": "38",
    "timezone": "Europe/Moscow"
  },
  "geometry": {
    "type": "Point",
    "coordinates": [
      40.52972,
      45.37833
    ]
  }
}