{
  "type": "Feature",
  "properties": {
    "name": "Novoshcherbinovskaya",
    "country": "RU",
    "subdivision": "38",
    "timezone": "Europe/Moscow"
  },
  "geometry": {
    "type": "Point",
    "coordinates": [
      38.64757,
      46.47669
    ]
  }
}