{
  "type": "Feature",
  "properties": {
    "name": "Novomalorossiyskaya",
    "country": "RU",
    "subdivision": "38",
    "timezone": "Europe/Moscow"
  },
  "geometry": {
    "type": "Point",
    "coordinates": [
      39.89481,
      45.63483
    ]
  }
}