{
  "type": "Feature",
  "properties": {
    "name": "Novominskaya",
    "country": "RU",
    "subdivision": "38",
    "timezone": "Europe/Moscow"
  },
  "geometry": {
    "type": "Point",
    "coordinates": [
      38.9586,
      46.3163
    ]
  }
}