{
  "type": "Feature",
  "properties": {
    "name": "Otrado-Kubanskoye",
    "country": "RU",
    "subdivision": "38",
    "timezone": "Europe/Moscow"
  },
  "geometry": {
    "type": "Point",
    "coordinates": [
      40.84083,
      45.24417
    ]
  }
}