{
  "type": "Feature",
  "properties": {
    "name": "Plastunovskaya",
    "country": "RU",
    "subdivision": "38",
    "timezone": "Europe/Moscow"
  },
  "geometry": {
    "type": "Point",
    "coordinates": [
      39.26505,
      45.29432
    ]
  }
}