{
  "type": "Feature",
  "properties": {
    "name": "Prikubanskiy",
    "country": "RU",
    "subdivision": "38",
    "timezone": "Europe/Moscow"
  },
  "geometry": {
    "type": "Point",
    "coordinates": [
      41.1795,
      45.0015
    ]
  }
}