{
  "type": "Feature",
  "properties": {
    "name": "Rodnikovskaya",
    "country": "RU",
    "subdivision": "38",
    "timezone": "Europe/Moscow"
  },
  "geometry": {
    "type": "Point",
    "coordinates": [
      40.66556,
      44.76444
    ]
  }
}