{
  "type": "Feature",
  "properties": {
    "name": "Sochi",
    "country": "RU",
    "subdivision": "38",
    "timezone": "Europe/Moscow"
  },
  "geometry": {
    "type": "Point",
    "coordinates": [
      39.72569,
      43.59917
    ]
  }
}