{
  "type": "Feature",
  "properties": {
    "name": "Spokoynaya",
    "country": "RU",
    "subdivision": "38",
    "timezone": "Europe/Moscow"
  },
  "geometry": {
    "type": "Point",
    "coordinates": [
      41.4015,
      44.2468
    ]
  }
}