{
  "type": "Feature",
  "properties": {
    "name": "Staroleushkovskaya",
    "country": "RU",
    "subdivision": "38",
    "timezone": "Europe/Moscow"
  },
  "geometry": {
    "type": "Point",
    "coordinates": [
      39.75987,
      45.98666
    ]
  }
}