{
  "type": "Feature",
  "properties": {
    "name": "Taman’",
    "country": "RU",
    "subdivision": "38",
    "timezone": "Europe/Moscow"
  },
  "geometry": {
    "type": "Point",
    "coordinates": [
      36.71609,
      45.2117
    ]
  }
}