{
  "type": "Feature",
  "properties": {
    "name": "Temirgoyevskaya",
    "country": "RU",
    "subdivision": "38",
    "timezone": "Europe/Moscow"
  },
  "geometry": {
    "type": "Point",
    "coordinates": [
      40.28027,
      45.11414
    ]
  }
}