{
  "type": "Feature",
  "properties": {
    "name": "Vysokoye",
    "country": "RU",
    "subdivision": "38",
    "timezone": "Europe/Moscow"
  },
  "geometry": {
    "type": "Point",
    "coordinates": [
      39.96701,
      43.46304
    ]
  }
}