{
  "type": "Feature",
  "properties": {
    "name": "Yurovka",
    "country": "RU",
    "subdivision": "38",
    "timezone": "Europe/Moscow"
  },
  "geometry": {
    "type": "Point",
    "coordinates": [
      37.41882,
      45.1147
    ]
  }
}