{
  "type": "Feature",
  "properties": {
    "name": "Yuzhnyy",
    "country": "RU",
    "subdivision": "38",
    "timezone": "Europe/Moscow"
  },
  "geometry": {
    "type": "Point",
    "coordinates": [
      40.47472,
      45.0025
    ]
  }
}