{
  "type": "Feature",
  "properties": {
    "name": "Fernando de la Mora",
    "country": "PY",
    "subdivision": "06",
    "timezone": "America/Asuncion"
  },
  "geometry": {
    "type": "Point",
    "coordinates": [
      -57.52167,
      -25.3386
    ]
  }
}