{
  "type": "Feature",
  "properties": {
    "name": "Mariano Roque Alonso",
    "country": "PY",
    "subdivision": "06",
    "timezone": "America/Asuncion"
  },
  "geometry": {
    "type": "Point",
    "coordinates": [
      -57.53202,
      -25.20791
    ]
  }
}