{
  "type": "Feature",
  "properties": {
    "name": "Ypacarai",
    "country": "PY",
    "subdivision": "06",
    "timezone": "America/Asuncion"
  },
  "geometry": {
    "type": "Point",
    "coordinates": [
      -57.28889,
      -25.40777
    ]
  }
}