{
  "type": "Feature",
  "properties": {
    "name": "Arandis",
    "country": "NA",
    "subdivision": "29",
    "timezone": "Africa/Windhoek"
  },
  "geometry": {
    "type": "Point",
    "coordinates": [
      14.96667,
      -22.41667
    ]
  }
}