{
  "type": "Feature",
  "properties": {
    "name": "Karibib",
    "country": "NA",
    "subdivision": "29",
    "timezone": "Africa/Windhoek"
  },
  "geometry": {
    "type": "Point",
    "coordinates": [
      15.83333,
      -21.93333
    ]
  }
}