{
  "type": "Feature",
  "properties": {
    "name": "Walvis Bay",
    "country": "NA",
    "subdivision": "29",
    "timezone": "Africa/Windhoek"
  },
  "geometry": {
    "type": "Point",
    "coordinates": [
      14.50528,
      -22.9575
    ]
  }
}