{
  "type": "Feature",
  "properties": {
    "name": "Namsos",
    "country": "NO",
    "subdivision": "21",
    "timezone": "Europe/Oslo"
  },
  "geometry": {
    "type": "Point",
    "coordinates": [
      11.49572,
      64.46624
    ]
  }
}