{
  "type": "Feature",
  "properties": {
    "name": "Skogn",
    "country": "NO",
    "subdivision": "21",
    "timezone": "Europe/Oslo"
  },
  "geometry": {
    "type": "Point",
    "coordinates": [
      11.19262,
      63.70374
    ]
  }
}