{
  "type": "Feature",
  "properties": {
    "name": "Verdal",
    "country": "NO",
    "subdivision": "21",
    "timezone": "Europe/Oslo"
  },
  "geometry": {
    "type": "Point",
    "coordinates": [
      11.4817,
      63.79332
    ]
  }
}