{
  "type": "Feature",
  "properties": {
    "name": "Agnibilékrou",
    "country": "CI",
    "subdivision": "94",
    "timezone": "Africa/Abidjan"
  },
  "geometry": {
    "type": "Point",
    "coordinates": [
      -3.20415,
      7.13113
    ]
  }
}