{
  "type": "Feature",
  "properties": {
    "name": "Viljandi",
    "country": "EE",
    "subdivision": "20",
    "timezone": "Europe/Tallinn"
  },
  "geometry": {
    "type": "Point",
    "coordinates": [
      25.59,
      58.36389
    ]
  }
}