{
  "type": "Feature",
  "properties": {
    "name": "Tamayo",
    "country": "DO",
    "subdivision": "02",
    "timezone": "America/Santo_Domingo"
  },
  "geometry": {
    "type": "Point",
    "coordinates": [
      -71.2029,
      18.3947
    ]
  }
}