{
  "type": "Feature",
  "properties": {
    "name": "KidriÄevo",
    "country": "SI",
    "subdivision": "45",
    "timezone": "Europe/Ljubljana"
  },
  "geometry": {
    "type": "Point",
    "coordinates": [
      15.79111,
      46.40361
    ]
  }
}