{
  "type": "Feature",
  "properties": {
    "name": "Bethel Town",
    "country": "JM",
    "subdivision": "16",
    "timezone": "America/Jamaica"
  },
  "geometry": {
    "type": "Point",
    "coordinates": [
      -77.95112,
      18.29503
    ]
  }
}