{
  "type": "Feature",
  "properties": {
    "name": "Bluefields",
    "country": "JM",
    "subdivision": "16",
    "timezone": "America/Jamaica"
  },
  "geometry": {
    "type": "Point",
    "coordinates": [
      -78.02702,
      18.16602
    ]
  }
}