{
  "type": "Feature",
  "properties": {
    "name": "Åneby",
    "country": "NO",
    "subdivision": "30",
    "timezone": "Europe/Oslo"
  },
  "geometry": {
    "type": "Point",
    "coordinates": [
      10.86998,
      60.08926
    ]
  }
}