{
  "type": "Feature",
  "properties": {
    "name": "Billingstad",
    "country": "NO",
    "subdivision": "30",
    "timezone": "Europe/Oslo"
  },
  "geometry": {
    "type": "Point",
    "coordinates": [
      10.4823,
      59.87548
    ]
  }
}