{
  "type": "Feature",
  "properties": {
    "name": "Drøbak",
    "country": "NO",
    "subdivision": "30",
    "timezone": "Europe/Oslo"
  },
  "geometry": {
    "type": "Point",
    "coordinates": [
      10.62975,
      59.66333
    ]
  }
}