{
  "type": "Feature",
  "properties": {
    "name": "Flateby",
    "country": "NO",
    "subdivision": "30",
    "timezone": "Europe/Oslo"
  },
  "geometry": {
    "type": "Point",
    "coordinates": [
      11.15345,
      59.82951
    ]
  }
}