{
  "type": "Feature",
  "properties": {
    "name": "Gol",
    "country": "NO",
    "subdivision": "30",
    "timezone": "Europe/Oslo"
  },
  "geometry": {
    "type": "Point",
    "coordinates": [
      8.94572,
      60.7014
    ]
  }
}