{
  "type": "Feature",
  "properties": {
    "name": "Kongsberg",
    "country": "NO",
    "subdivision": "30",
    "timezone": "Europe/Oslo"
  },
  "geometry": {
    "type": "Point",
    "coordinates": [
      9.65017,
      59.66858
    ]
  }
}