{
  "type": "Feature",
  "properties": {
    "name": "Lervik",
    "country": "NO",
    "subdivision": "30",
    "timezone": "Europe/Oslo"
  },
  "geometry": {
    "type": "Point",
    "coordinates": [
      10.7461,
      59.27119
    ]
  }
}