{
  "type": "Feature",
  "properties": {
    "name": "Nesoddtangen",
    "country": "NO",
    "subdivision": "30",
    "timezone": "Europe/Oslo"
  },
  "geometry": {
    "type": "Point",
    "coordinates": [
      10.66308,
      59.86244
    ]
  }
}