{
  "type": "Feature",
  "properties": {
    "name": "Rotnes",
    "country": "NO",
    "subdivision": "30",
    "timezone": "Europe/Oslo"
  },
  "geometry": {
    "type": "Point",
    "coordinates": [
      10.86135,
      60.05707
    ]
  }
}