{
  "type": "Feature",
  "properties": {
    "name": "Ski",
    "country": "NO",
    "subdivision": "30",
    "timezone": "Europe/Oslo"
  },
  "geometry": {
    "type": "Point",
    "coordinates": [
      10.83576,
      59.71949
    ]
  }
}