{
  "type": "Feature",
  "properties": {
    "name": "Ntoum",
    "country": "GA",
    "subdivision": "01",
    "timezone": "Africa/Libreville"
  },
  "geometry": {
    "type": "Point",
    "coordinates": [
      9.76096,
      0.39051
    ]
  }
}