{
  "type": "Feature",
  "properties": {
    "name": "Andelsbuch",
    "country": "AT",
    "subdivision": "08",
    "timezone": "Europe/Vienna"
  },
  "geometry": {
    "type": "Point",
    "coordinates": [
      9.89326,
      47.41167
    ]
  }
}