{
  "type": "Feature",
  "properties": {
    "name": "Ausserbraz",
    "country": "AT",
    "subdivision": "08",
    "timezone": "Europe/Vienna"
  },
  "geometry": {
    "type": "Point",
    "coordinates": [
      9.90066,
      47.14875
    ]
  }
}