{
  "type": "Feature",
  "properties": {
    "name": "Egg",
    "country": "AT",
    "subdivision": "08",
    "timezone": "Europe/Vienna"
  },
  "geometry": {
    "type": "Point",
    "coordinates": [
      9.89762,
      47.43154
    ]
  }
}