{
  "type": "Feature",
  "properties": {
    "name": "Großdorf",
    "country": "AT",
    "subdivision": "08",
    "timezone": "Europe/Vienna"
  },
  "geometry": {
    "type": "Point",
    "coordinates": [
      9.91528,
      47.43361
    ]
  }
}