{
  "type": "Feature",
  "properties": {
    "name": "Kennelbach",
    "country": "AT",
    "subdivision": "08",
    "timezone": "Europe/Vienna"
  },
  "geometry": {
    "type": "Point",
    "coordinates": [
      9.76667,
      47.48306
    ]
  }
}