{
  "type": "Feature",
  "properties": {
    "name": "Lustenau",
    "country": "AT",
    "subdivision": "08",
    "timezone": "Europe/Vienna"
  },
  "geometry": {
    "type": "Point",
    "coordinates": [
      9.65851,
      47.42642
    ]
  }
}