{
  "type": "Feature",
  "properties": {
    "name": "Riezlern",
    "country": "AT",
    "subdivision": "08",
    "timezone": "Europe/Vienna"
  },
  "geometry": {
    "type": "Point",
    "coordinates": [
      10.18759,
      47.35778
    ]
  }
}