{
  "type": "Feature",
  "properties": {
    "name": "Alámpra",
    "country": "CY",
    "subdivision": "04",
    "timezone": "Asia/Nicosia"
  },
  "geometry": {
    "type": "Point",
    "coordinates": [
      33.39887,
      34.98898
    ]
  }
}