{
  "type": "Feature",
  "properties": {
    "name": "Léfka",
    "country": "CY",
    "subdivision": "04",
    "timezone": "Asia/Nicosia"
  },
  "geometry": {
    "type": "Point",
    "coordinates": [
      32.84997,
      35.11199
    ]
  }
}