{
  "type": "Feature",
  "properties": {
    "name": "Badeggi",
    "country": "NG",
    "subdivision": "31",
    "timezone": "Africa/Lagos"
  },
  "geometry": {
    "type": "Point",
    "coordinates": [
      6.143,
      9.0563
    ]
  }
}