{
  "type": "Feature",
  "properties": {
    "name": "Zungeru",
    "country": "NG",
    "subdivision": "31",
    "timezone": "Africa/Lagos"
  },
  "geometry": {
    "type": "Point",
    "coordinates": [
      6.15238,
      9.80726
    ]
  }
}