{
  "type": "Feature",
  "properties": {
    "name": "Nikolayevskiy",
    "country": "RU",
    "subdivision": "11",
    "timezone": "Asia/Irkutsk"
  },
  "geometry": {
    "type": "Point",
    "coordinates": [
      107.80068,
      51.65526
    ]
  }
}