{
  "type": "Feature",
  "properties": {
    "name": "Nizhneangarsk",
    "country": "RU",
    "subdivision": "11",
    "timezone": "Asia/Irkutsk"
  },
  "geometry": {
    "type": "Point",
    "coordinates": [
      109.58029,
      55.79326
    ]
  }
}