{
  "type": "Feature",
  "properties": {
    "name": "Onokhoy",
    "country": "RU",
    "subdivision": "11",
    "timezone": "Asia/Irkutsk"
  },
  "geometry": {
    "type": "Point",
    "coordinates": [
      108.06693,
      51.92859
    ]
  }
}