{
  "type": "Feature",
  "properties": {
    "name": "Sokol",
    "country": "RU",
    "subdivision": "11",
    "timezone": "Asia/Irkutsk"
  },
  "geometry": {
    "type": "Point",
    "coordinates": [
      107.44437,
      51.80036
    ]
  }
}