{
  "type": "Feature",
  "properties": {
    "name": "Zhemchug",
    "country": "RU",
    "subdivision": "11",
    "timezone": "Asia/Irkutsk"
  },
  "geometry": {
    "type": "Point",
    "coordinates": [
      102.459,
      51.6861
    ]
  }
}