{
  "type": "Feature",
  "properties": {
    "name": "Al Qaryatayn",
    "country": "SY",
    "subdivision": "11",
    "timezone": "Asia/Damascus"
  },
  "geometry": {
    "type": "Point",
    "coordinates": [
      37.24066,
      34.22956
    ]
  }
}