{
  "type": "Feature",
  "properties": {
    "name": "Birkirkara",
    "country": "MT",
    "subdivision": "04",
    "timezone": "Europe/Malta"
  },
  "geometry": {
    "type": "Point",
    "coordinates": [
      14.46111,
      35.89722
    ]
  }
}