{
  "type": "Feature",
  "properties": {
    "name": "Mae Chai",
    "country": "TH",
    "subdivision": "41",
    "timezone": "Asia/Bangkok"
  },
  "geometry": {
    "type": "Point",
    "coordinates": [
      99.814,
      19.34597
    ]
  }
}