{
  "type": "Feature",
  "properties": {
    "name": "Mbuyapey",
    "country": "PY",
    "subdivision": "15",
    "timezone": "America/Asuncion"
  },
  "geometry": {
    "type": "Point",
    "coordinates": [
      -56.75777,
      -26.21921
    ]
  }
}