{
  "type": "Feature",
  "properties": {
    "name": "Akhtubinsk",
    "country": "RU",
    "subdivision": "07",
    "timezone": "Europe/Astrakhan"
  },
  "geometry": {
    "type": "Point",
    "coordinates": [
      46.17217,
      48.27955
    ]
  }
}