{
  "type": "Feature",
  "properties": {
    "name": "Mumra",
    "country": "RU",
    "subdivision": "07",
    "timezone": "Europe/Astrakhan"
  },
  "geometry": {
    "type": "Point",
    "coordinates": [
      47.65398,
      45.77251
    ]
  }
}