{
  "type": "Feature",
  "properties": {
    "name": "Narimanov",
    "country": "RU",
    "subdivision": "07",
    "timezone": "Europe/Astrakhan"
  },
  "geometry": {
    "type": "Point",
    "coordinates": [
      47.8498,
      46.6927
    ]
  }
}