{
  "type": "Feature",
  "properties": {
    "name": "Trudfront",
    "country": "RU",
    "subdivision": "07",
    "timezone": "Europe/Astrakhan"
  },
  "geometry": {
    "type": "Point",
    "coordinates": [
      47.66929,
      45.9346
    ]
  }
}