{
  "type": "Feature",
  "properties": {
    "name": "Zenzeli",
    "country": "RU",
    "subdivision": "07",
    "timezone": "Europe/Astrakhan"
  },
  "geometry": {
    "type": "Point",
    "coordinates": [
      47.04739,
      45.92407
    ]
  }
}