{
  "type": "Feature",
  "properties": {
    "name": "Kirundo",
    "country": "BI",
    "subdivision": "16",
    "timezone": "Africa/Bujumbura"
  },
  "geometry": {
    "type": "Point",
    "coordinates": [
      30.0959,
      -2.5845
    ]
  }
}