{
  "type": "Feature",
  "properties": {
    "name": "Al Ḩawātah",
    "country": "SD",
    "subdivision": "39",
    "timezone": "Africa/Khartoum"
  },
  "geometry": {
    "type": "Point",
    "coordinates": [
      34.63333,
      13.41667
    ]
  }
}