{
  "type": "Feature",
  "properties": {
    "name": "Taloqan",
    "country": "AF",
    "subdivision": "26",
    "timezone": "Asia/Kabul"
  },
  "geometry": {
    "type": "Point",
    "coordinates": [
      69.53451,
      36.73605
    ]
  }
}