{
  "type": "Feature",
  "properties": {
    "name": "Bramming",
    "country": "DK",
    "subdivision": "21",
    "timezone": "Europe/Copenhagen"
  },
  "geometry": {
    "type": "Point",
    "coordinates": [
      8.70007,
      55.46946
    ]
  }
}