{
  "type": "Feature",
  "properties": {
    "name": "Christiansfeld",
    "country": "DK",
    "subdivision": "21",
    "timezone": "Europe/Copenhagen"
  },
  "geometry": {
    "type": "Point",
    "coordinates": [
      9.48701,
      55.35817
    ]
  }
}