{
  "type": "Feature",
  "properties": {
    "name": "Glamsbjerg",
    "country": "DK",
    "subdivision": "21",
    "timezone": "Europe/Copenhagen"
  },
  "geometry": {
    "type": "Point",
    "coordinates": [
      10.10483,
      55.27237
    ]
  }
}