{
  "type": "Feature",
  "properties": {
    "name": "Gråsten",
    "country": "DK",
    "subdivision": "21",
    "timezone": "Europe/Copenhagen"
  },
  "geometry": {
    "type": "Point",
    "coordinates": [
      9.59523,
      54.91918
    ]
  }
}