{
  "type": "Feature",
  "properties": {
    "name": "Haderslev",
    "country": "DK",
    "subdivision": "21",
    "timezone": "Europe/Copenhagen"
  },
  "geometry": {
    "type": "Point",
    "coordinates": [
      9.48771,
      55.24943
    ]
  }
}