{
  "type": "Feature",
  "properties": {
    "name": "Skaerbaek",
    "country": "DK",
    "subdivision": "21",
    "timezone": "Europe/Copenhagen"
  },
  "geometry": {
    "type": "Point",
    "coordinates": [
      8.76901,
      55.15735
    ]
  }
}