{
  "type": "Feature",
  "properties": {
    "name": "Starup",
    "country": "DK",
    "subdivision": "21",
    "timezone": "Europe/Copenhagen"
  },
  "geometry": {
    "type": "Point",
    "coordinates": [
      9.53503,
      55.24097
    ]
  }
}