{
  "type": "Feature",
  "properties": {
    "name": "Tinglev",
    "country": "DK",
    "subdivision": "21",
    "timezone": "Europe/Copenhagen"
  },
  "geometry": {
    "type": "Point",
    "coordinates": [
      9.25547,
      54.93788
    ]
  }
}