{
  "type": "Feature",
  "properties": {
    "name": "Tommerup",
    "country": "DK",
    "subdivision": "21",
    "timezone": "Europe/Copenhagen"
  },
  "geometry": {
    "type": "Point",
    "coordinates": [
      10.20659,
      55.31952
    ]
  }
}