{
  "type": "Feature",
  "properties": {
    "name": "Vindeby",
    "country": "DK",
    "subdivision": "21",
    "timezone": "Europe/Copenhagen"
  },
  "geometry": {
    "type": "Point",
    "coordinates": [
      10.61309,
      55.04489
    ]
  }
}