{
  "type": "Feature",
  "properties": {
    "name": "RenÄe",
    "country": "SI",
    "subdivision": "P1",
    "timezone": "Europe/Ljubljana"
  },
  "geometry": {
    "type": "Point",
    "coordinates": [
      13.66861,
      45.89
    ]
  }
}