{
  "type": "Feature",
  "properties": {
    "name": "Agadir",
    "country": "MA",
    "subdivision": "09",
    "timezone": "Africa/Casablanca"
  },
  "geometry": {
    "type": "Point",
    "coordinates": [
      -9.59815,
      30.42018
    ]
  }
}