{
  "type": "Feature",
  "properties": {
    "name": "Sidi Ifni",
    "country": "MA",
    "subdivision": "09",
    "timezone": "Africa/Casablanca"
  },
  "geometry": {
    "type": "Point",
    "coordinates": [
      -10.17299,
      29.37975
    ]
  }
}