{
  "type": "Feature",
  "properties": {
    "name": "Alta Gracia",
    "country": "AR",
    "subdivision": "05",
    "timezone": "America/Argentina/Cordoba"
  },
  "geometry": {
    "type": "Point",
    "coordinates": [
      -64.42826,
      -31.65292
    ]
  }
}