{
  "type": "Feature",
  "properties": {
    "name": "Arias",
    "country": "AR",
    "subdivision": "05",
    "timezone": "America/Argentina/Cordoba"
  },
  "geometry": {
    "type": "Point",
    "coordinates": [
      -62.40272,
      -33.64411
    ]
  }
}