{
  "type": "Feature",
  "properties": {
    "name": "Balnearia",
    "country": "AR",
    "subdivision": "05",
    "timezone": "America/Argentina/Cordoba"
  },
  "geometry": {
    "type": "Point",
    "coordinates": [
      -62.66733,
      -31.0088
    ]
  }
}