{
  "type": "Feature",
  "properties": {
    "name": "Córdoba",
    "country": "AR",
    "subdivision": "05",
    "timezone": "America/Argentina/Cordoba"
  },
  "geometry": {
    "type": "Point",
    "coordinates": [
      -64.18105,
      -31.4135
    ]
  }
}