{
  "type": "Feature",
  "properties": {
    "name": "Coronel Moldes",
    "country": "AR",
    "subdivision": "05",
    "timezone": "America/Argentina/Cordoba"
  },
  "geometry": {
    "type": "Point",
    "coordinates": [
      -64.59711,
      -33.6227
    ]
  }
}