{
  "type": "Feature",
  "properties": {
    "name": "Cuesta Blanca",
    "country": "AR",
    "subdivision": "05",
    "timezone": "America/Argentina/Cordoba"
  },
  "geometry": {
    "type": "Point",
    "coordinates": [
      -64.5715,
      -31.48658
    ]
  }
}