{
  "type": "Feature",
  "properties": {
    "name": "General Baldissera",
    "country": "AR",
    "subdivision": "05",
    "timezone": "America/Argentina/Cordoba"
  },
  "geometry": {
    "type": "Point",
    "coordinates": [
      -62.3063,
      -33.12246
    ]
  }
}