{
  "type": "Feature",
  "properties": {
    "name": "Inriville",
    "country": "AR",
    "subdivision": "05",
    "timezone": "America/Argentina/Cordoba"
  },
  "geometry": {
    "type": "Point",
    "coordinates": [
      -62.23028,
      -32.94424
    ]
  }
}