{
  "type": "Feature",
  "properties": {
    "name": "La Granja",
    "country": "AR",
    "subdivision": "05",
    "timezone": "America/Argentina/Cordoba"
  },
  "geometry": {
    "type": "Point",
    "coordinates": [
      -64.26869,
      -31.00919
    ]
  }
}