{
  "type": "Feature",
  "properties": {
    "name": "Mendiolaza",
    "country": "AR",
    "subdivision": "05",
    "timezone": "America/Argentina/Cordoba"
  },
  "geometry": {
    "type": "Point",
    "coordinates": [
      -64.30087,
      -31.26738
    ]
  }
}