{
  "type": "Feature",
  "properties": {
    "name": "Morteros",
    "country": "AR",
    "subdivision": "05",
    "timezone": "America/Argentina/Cordoba"
  },
  "geometry": {
    "type": "Point",
    "coordinates": [
      -61.99862,
      -30.71164
    ]
  }
}