{
  "type": "Feature",
  "properties": {
    "name": "San Basilio",
    "country": "AR",
    "subdivision": "05",
    "timezone": "America/Argentina/Cordoba"
  },
  "geometry": {
    "type": "Point",
    "coordinates": [
      -64.31495,
      -33.49763
    ]
  }
}