{
  "type": "Feature",
  "properties": {
    "name": "Santiago Temple",
    "country": "AR",
    "subdivision": "05",
    "timezone": "America/Argentina/Cordoba"
  },
  "geometry": {
    "type": "Point",
    "coordinates": [
      -63.41821,
      -31.38731
    ]
  }
}