{
  "type": "Feature",
  "properties": {
    "name": "Villa Rumipal",
    "country": "AR",
    "subdivision": "05",
    "timezone": "America/Argentina/Cordoba"
  },
  "geometry": {
    "type": "Point",
    "coordinates": [
      -64.48027,
      -32.1879
    ]
  }
}