{
  "type": "Feature",
  "properties": {
    "name": "Villa de Soto",
    "country": "AR",
    "subdivision": "05",
    "timezone": "America/Argentina/Cordoba"
  },
  "geometry": {
    "type": "Point",
    "coordinates": [
      -64.99947,
      -30.85523
    ]
  }
}