{
  "type": "Feature",
  "properties": {
    "name": "Kédougou",
    "country": "SN",
    "subdivision": "17",
    "timezone": "Africa/Dakar"
  },
  "geometry": {
    "type": "Point",
    "coordinates": [
      -12.18076,
      12.55561
    ]
  }
}