{
  "type": "Feature",
  "properties": {
    "name": "Borovo",
    "country": "HR",
    "subdivision": "18",
    "timezone": "Europe/Zagreb"
  },
  "geometry": {
    "type": "Point",
    "coordinates": [
      18.96694,
      45.37639
    ]
  }
}