{
  "type": "Feature",
  "properties": {
    "name": "Gradište",
    "country": "HR",
    "subdivision": "18",
    "timezone": "Europe/Zagreb"
  },
  "geometry": {
    "type": "Point",
    "coordinates": [
      18.70667,
      45.14806
    ]
  }
}