{
  "type": "Feature",
  "properties": {
    "name": "Nuštar",
    "country": "HR",
    "subdivision": "18",
    "timezone": "Europe/Zagreb"
  },
  "geometry": {
    "type": "Point",
    "coordinates": [
      18.84139,
      45.3325
    ]
  }
}