{
  "type": "Feature",
  "properties": {
    "name": "Aralık",
    "country": "TR",
    "subdivision": "21",
    "timezone": "Europe/Istanbul"
  },
  "geometry": {
    "type": "Point",
    "coordinates": [
      40.68025,
      37.82945
    ]
  }
}