{
  "type": "Feature",
  "properties": {
    "name": "Çermik",
    "country": "TR",
    "subdivision": "21",
    "timezone": "Europe/Istanbul"
  },
  "geometry": {
    "type": "Point",
    "coordinates": [
      39.445,
      38.13538
    ]
  }
}