{
  "type": "Feature",
  "properties": {
    "name": "Hani",
    "country": "TR",
    "subdivision": "21",
    "timezone": "Europe/Istanbul"
  },
  "geometry": {
    "type": "Point",
    "coordinates": [
      40.38578,
      38.40741
    ]
  }
}