{
  "type": "Feature",
  "properties": {
    "name": "Kulp",
    "country": "TR",
    "subdivision": "21",
    "timezone": "Europe/Istanbul"
  },
  "geometry": {
    "type": "Point",
    "coordinates": [
      41.00668,
      38.49754
    ]
  }
}