{
  "type": "Feature",
  "properties": {
    "name": "Sheki",
    "country": "AZ",
    "subdivision": "48",
    "timezone": "Asia/Baku"
  },
  "geometry": {
    "type": "Point",
    "coordinates": [
      47.17056,
      41.19194
    ]
  }
}