{
  "type": "Feature",
  "properties": {
    "name": "Odensbacken",
    "country": "SE",
    "subdivision": "15",
    "timezone": "Europe/Stockholm"
  },
  "geometry": {
    "type": "Point",
    "coordinates": [
      15.53333,
      59.16667
    ]
  }
}