{
  "type": "Feature",
  "properties": {
    "name": "Storå",
    "country": "SE",
    "subdivision": "15",
    "timezone": "Europe/Stockholm"
  },
  "geometry": {
    "type": "Point",
    "coordinates": [
      15.13169,
      59.71409
    ]
  }
}