{
  "type": "Feature",
  "properties": {
    "name": "Altavista",
    "country": "US",
    "subdivision": "VA",
    "timezone": "America/New_York"
  },
  "geometry": {
    "type": "Point",
    "coordinates": [
      -79.28558,
      37.11181
    ]
  }
}