{
  "type": "Feature",
  "properties": {
    "name": "Arlington",
    "country": "US",
    "subdivision": "VA",
    "timezone": "America/New_York"
  },
  "geometry": {
    "type": "Point",
    "coordinates": [
      -77.10428,
      38.88101
    ]
  }
}