{
  "type": "Feature",
  "properties": {
    "name": "Belmont",
    "country": "US",
    "subdivision": "VA",
    "timezone": "America/New_York"
  },
  "geometry": {
    "type": "Point",
    "coordinates": [
      -77.50999,
      39.06483
    ]
  }
}