{
  "type": "Feature",
  "properties": {
    "name": "Broadway",
    "country": "US",
    "subdivision": "VA",
    "timezone": "America/New_York"
  },
  "geometry": {
    "type": "Point",
    "coordinates": [
      -78.79891,
      38.61317
    ]
  }
}