{
  "type": "Feature",
  "properties": {
    "name": "Castlewood",
    "country": "US",
    "subdivision": "VA",
    "timezone": "America/New_York"
  },
  "geometry": {
    "type": "Point",
    "coordinates": [
      -82.27959,
      36.8901
    ]
  }
}