{
  "type": "Feature",
  "properties": {
    "name": "Chesapeake",
    "country": "US",
    "subdivision": "VA",
    "timezone": "America/New_York"
  },
  "geometry": {
    "type": "Point",
    "coordinates": [
      -76.27494,
      36.81904
    ]
  }
}