{
  "type": "Feature",
  "properties": {
    "name": "Dale City",
    "country": "US",
    "subdivision": "VA",
    "timezone": "America/New_York"
  },
  "geometry": {
    "type": "Point",
    "coordinates": [
      -77.31109,
      38.63706
    ]
  }
}