{
  "type": "Feature",
  "properties": {
    "name": "Dayton",
    "country": "US",
    "subdivision": "VA",
    "timezone": "America/New_York"
  },
  "geometry": {
    "type": "Point",
    "coordinates": [
      -78.93864,
      38.41485
    ]
  }
}