{
  "type": "Feature",
  "properties": {
    "name": "East Lexington",
    "country": "US",
    "subdivision": "VA",
    "timezone": "America/New_York"
  },
  "geometry": {
    "type": "Point",
    "coordinates": [
      -79.42532,
      37.79291
    ]
  }
}