{
  "type": "Feature",
  "properties": {
    "name": "Ettrick",
    "country": "US",
    "subdivision": "VA",
    "timezone": "America/New_York"
  },
  "geometry": {
    "type": "Point",
    "coordinates": [
      -77.42998,
      37.24015
    ]
  }
}