{
  "type": "Feature",
  "properties": {
    "name": "Franklin",
    "country": "US",
    "subdivision": "VA",
    "timezone": "America/New_York"
  },
  "geometry": {
    "type": "Point",
    "coordinates": [
      -76.92246,
      36.67765
    ]
  }
}