{
  "type": "Feature",
  "properties": {
    "name": "Gainesville",
    "country": "US",
    "subdivision": "VA",
    "timezone": "America/New_York"
  },
  "geometry": {
    "type": "Point",
    "coordinates": [
      -77.61388,
      38.79567
    ]
  }
}