{
  "type": "Feature",
  "properties": {
    "name": "Gate City",
    "country": "US",
    "subdivision": "VA",
    "timezone": "America/New_York"
  },
  "geometry": {
    "type": "Point",
    "coordinates": [
      -82.58099,
      36.63788
    ]
  }
}