{
  "type": "Feature",
  "properties": {
    "name": "Glade Spring",
    "country": "US",
    "subdivision": "VA",
    "timezone": "America/New_York"
  },
  "geometry": {
    "type": "Point",
    "coordinates": [
      -81.77123,
      36.79122
    ]
  }
}