{
  "type": "Feature",
  "properties": {
    "name": "Glen Allen",
    "country": "US",
    "subdivision": "VA",
    "timezone": "America/New_York"
  },
  "geometry": {
    "type": "Point",
    "coordinates": [
      -77.50637,
      37.66598
    ]
  }
}