{
  "type": "Feature",
  "properties": {
    "name": "Highland Springs",
    "country": "US",
    "subdivision": "VA",
    "timezone": "America/New_York"
  },
  "geometry": {
    "type": "Point",
    "coordinates": [
      -77.32776,
      37.54598
    ]
  }
}