{
  "type": "Feature",
  "properties": {
    "name": "King George",
    "country": "US",
    "subdivision": "VA",
    "timezone": "America/New_York"
  },
  "geometry": {
    "type": "Point",
    "coordinates": [
      -77.18442,
      38.26818
    ]
  }
}