{
  "type": "Feature",
  "properties": {
    "name": "Lake Ridge",
    "country": "US",
    "subdivision": "VA",
    "timezone": "America/New_York"
  },
  "geometry": {
    "type": "Point",
    "coordinates": [
      -77.29776,
      38.68789
    ]
  }
}