{
  "type": "Feature",
  "properties": {
    "name": "Lexington",
    "country": "US",
    "subdivision": "VA",
    "timezone": "America/New_York"
  },
  "geometry": {
    "type": "Point",
    "coordinates": [
      -79.44282,
      37.78402
    ]
  }
}