{
  "type": "Feature",
  "properties": {
    "name": "Luray",
    "country": "US",
    "subdivision": "VA",
    "timezone": "America/New_York"
  },
  "geometry": {
    "type": "Point",
    "coordinates": [
      -78.45945,
      38.6654
    ]
  }
}