{
  "type": "Feature",
  "properties": {
    "name": "Middletown",
    "country": "US",
    "subdivision": "VA",
    "timezone": "America/New_York"
  },
  "geometry": {
    "type": "Point",
    "coordinates": [
      -78.28056,
      39.02761
    ]
  }
}