{
  "type": "Feature",
  "properties": {
    "name": "Mount Vernon",
    "country": "US",
    "subdivision": "VA",
    "timezone": "America/New_York"
  },
  "geometry": {
    "type": "Point",
    "coordinates": [
      -77.10082,
      38.71412
    ]
  }
}