{
  "type": "Feature",
  "properties": {
    "name": "North Springfield",
    "country": "US",
    "subdivision": "VA",
    "timezone": "America/New_York"
  },
  "geometry": {
    "type": "Point",
    "coordinates": [
      -77.2047,
      38.80428
    ]
  }
}