{
  "type": "Feature",
  "properties": {
    "name": "Oakton",
    "country": "US",
    "subdivision": "VA",
    "timezone": "America/New_York"
  },
  "geometry": {
    "type": "Point",
    "coordinates": [
      -77.30082,
      38.88095
    ]
  }
}