{
  "type": "Feature",
  "properties": {
    "name": "Poquoson",
    "country": "US",
    "subdivision": "VA",
    "timezone": "America/New_York"
  },
  "geometry": {
    "type": "Point",
    "coordinates": [
      -76.34578,
      37.12237
    ]
  }
}