{
  "type": "Feature",
  "properties": {
    "name": "Portsmouth Heights",
    "country": "US",
    "subdivision": "VA",
    "timezone": "America/New_York"
  },
  "geometry": {
    "type": "Point",
    "coordinates": [
      -76.36883,
      36.82098
    ]
  }
}