{
  "type": "Feature",
  "properties": {
    "name": "Quantico Station",
    "country": "US",
    "subdivision": "VA",
    "timezone": "America/New_York"
  },
  "geometry": {
    "type": "Point",
    "coordinates": [
      -77.31834,
      38.52263
    ]
  }
}