{
  "type": "Feature",
  "properties": {
    "name": "Ruckersville",
    "country": "US",
    "subdivision": "VA",
    "timezone": "America/New_York"
  },
  "geometry": {
    "type": "Point",
    "coordinates": [
      -78.36917,
      38.23319
    ]
  }
}