{
  "type": "Feature",
  "properties": {
    "name": "Smithfield",
    "country": "US",
    "subdivision": "VA",
    "timezone": "America/New_York"
  },
  "geometry": {
    "type": "Point",
    "coordinates": [
      -76.63107,
      36.98237
    ]
  }
}