{
  "type": "Feature",
  "properties": {
    "name": "South Suffolk",
    "country": "US",
    "subdivision": "VA",
    "timezone": "America/New_York"
  },
  "geometry": {
    "type": "Point",
    "coordinates": [
      -76.59023,
      36.71709
    ]
  }
}