{
  "type": "Feature",
  "properties": {
    "name": "Stafford",
    "country": "US",
    "subdivision": "VA",
    "timezone": "America/New_York"
  },
  "geometry": {
    "type": "Point",
    "coordinates": [
      -77.40832,
      38.42207
    ]
  }
}