{
  "type": "Feature",
  "properties": {
    "name": "Stanley",
    "country": "US",
    "subdivision": "VA",
    "timezone": "America/New_York"
  },
  "geometry": {
    "type": "Point",
    "coordinates": [
      -78.50251,
      38.5754
    ]
  }
}