{
  "type": "Feature",
  "properties": {
    "name": "Timberville",
    "country": "US",
    "subdivision": "VA",
    "timezone": "America/New_York"
  },
  "geometry": {
    "type": "Point",
    "coordinates": [
      -78.77391,
      38.63901
    ]
  }
}