{
  "type": "Feature",
  "properties": {
    "name": "Union Hall",
    "country": "US",
    "subdivision": "VA",
    "timezone": "America/New_York"
  },
  "geometry": {
    "type": "Point",
    "coordinates": [
      -79.68642,
      37.01875
    ]
  }
}