{
  "type": "Feature",
  "properties": {
    "name": "Hoshcha",
    "country": "UA",
    "subdivision": "19",
    "timezone": "Europe/Kiev"
  },
  "geometry": {
    "type": "Point",
    "coordinates": [
      26.67435,
      50.6003
    ]
  }
}