{
  "type": "Feature",
  "properties": {
    "name": "Tagāw-Bāy",
    "country": "AF",
    "subdivision": "33",
    "timezone": "Asia/Kabul"
  },
  "geometry": {
    "type": "Point",
    "coordinates": [
      66.06164,
      35.69941
    ]
  }
}