{
  "type": "Feature",
  "properties": {
    "name": "Agua Caliente",
    "country": "MX",
    "subdivision": "16",
    "timezone": "America/Mexico_City"
  },
  "geometry": {
    "type": "Point",
    "coordinates": [
      -101.73466,
      20.06519
    ]
  }
}