{
  "type": "Feature",
  "properties": {
    "name": "Ansihuacuaro",
    "country": "MX",
    "subdivision": "16",
    "timezone": "America/Mexico_City"
  },
  "geometry": {
    "type": "Point",
    "coordinates": [
      -101.8067,
      20.19984
    ]
  }
}