{
  "type": "Feature",
  "properties": {
    "name": "Atacheo de Regalado",
    "country": "MX",
    "subdivision": "16",
    "timezone": "America/Mexico_City"
  },
  "geometry": {
    "type": "Point",
    "coordinates": [
      -102.18703,
      20.05874
    ]
  }
}