{
  "type": "Feature",
  "properties": {
    "name": "Atapán",
    "country": "MX",
    "subdivision": "16",
    "timezone": "America/Mexico_City"
  },
  "geometry": {
    "type": "Point",
    "coordinates": [
      -102.42463,
      19.65057
    ]
  }
}