{
  "type": "Feature",
  "properties": {
    "name": "Belisario Domínguez",
    "country": "MX",
    "subdivision": "16",
    "timezone": "America/Mexico_City"
  },
  "geometry": {
    "type": "Point",
    "coordinates": [
      -100.97184,
      19.8714
    ]
  }
}