{
  "type": "Feature",
  "properties": {
    "name": "Bocaneo (San Pedro)",
    "country": "MX",
    "subdivision": "16",
    "timezone": "America/Mexico_City"
  },
  "geometry": {
    "type": "Point",
    "coordinates": [
      -100.81722,
      19.83861
    ]
  }
}