{
  "type": "Feature",
  "properties": {
    "name": "Bonifacio Moreno (El Aguaje)",
    "country": "MX",
    "subdivision": "16",
    "timezone": "America/Mexico_City"
  },
  "geometry": {
    "type": "Point",
    "coordinates": [
      -102.71083,
      18.99167
    ]
  }
}