{
  "type": "Feature",
  "properties": {
    "name": "Cañada de Ramírez",
    "country": "MX",
    "subdivision": "16",
    "timezone": "America/Mexico_City"
  },
  "geometry": {
    "type": "Point",
    "coordinates": [
      -101.9636,
      20.29637
    ]
  }
}