{
  "type": "Feature",
  "properties": {
    "name": "Caurio de Guadalupe",
    "country": "MX",
    "subdivision": "16",
    "timezone": "America/Mexico_City"
  },
  "geometry": {
    "type": "Point",
    "coordinates": [
      -101.86067,
      19.92455
    ]
  }
}