{
  "type": "Feature",
  "properties": {
    "name": "Churumuco de Morelos",
    "country": "MX",
    "subdivision": "16",
    "timezone": "America/Mexico_City"
  },
  "geometry": {
    "type": "Point",
    "coordinates": [
      -101.64741,
      18.66333
    ]
  }
}