{
  "type": "Feature",
  "properties": {
    "name": "Ciudad Hidalgo",
    "country": "MX",
    "subdivision": "16",
    "timezone": "America/Mexico_City"
  },
  "geometry": {
    "type": "Point",
    "coordinates": [
      -100.55445,
      19.6927
    ]
  }
}