{
  "type": "Feature",
  "properties": {
    "name": "Colonia de Guadalupe",
    "country": "MX",
    "subdivision": "16",
    "timezone": "America/Mexico_City"
  },
  "geometry": {
    "type": "Point",
    "coordinates": [
      -100.91556,
      19.80083
    ]
  }
}