{
  "type": "Feature",
  "properties": {
    "name": "Colonia Emiliano Zapata (San Juan Zitácuaro)",
    "country": "MX",
    "subdivision": "16",
    "timezone": "America/Mexico_City"
  },
  "geometry": {
    "type": "Point",
    "coordinates": [
      -100.30583,
      19.44778
    ]
  }
}