{
  "type": "Feature",
  "properties": {
    "name": "Comanjá",
    "country": "MX",
    "subdivision": "16",
    "timezone": "America/Mexico_City"
  },
  "geometry": {
    "type": "Point",
    "coordinates": [
      -101.6908,
      19.74696
    ]
  }
}