{
  "type": "Feature",
  "properties": {
    "name": "Conjunto Habitacional Villas del Pedregal",
    "country": "MX",
    "subdivision": "16",
    "timezone": "America/Mexico_City"
  },
  "geometry": {
    "type": "Point",
    "coordinates": [
      -101.30361,
      19.68361
    ]
  }
}