{
  "type": "Feature",
  "properties": {
    "name": "Dieciocho de Marzo",
    "country": "MX",
    "subdivision": "16",
    "timezone": "America/Mexico_City"
  },
  "geometry": {
    "type": "Point",
    "coordinates": [
      -102.7057,
      19.23138
    ]
  }
}