{
  "type": "Feature",
  "properties": {
    "name": "El Chauz",
    "country": "MX",
    "subdivision": "16",
    "timezone": "America/Mexico_City"
  },
  "geometry": {
    "type": "Point",
    "coordinates": [
      -102.03978,
      18.89195
    ]
  }
}