{
  "type": "Feature",
  "properties": {
    "name": "El Platanal",
    "country": "MX",
    "subdivision": "16",
    "timezone": "America/Mexico_City"
  },
  "geometry": {
    "type": "Point",
    "coordinates": [
      -102.57779,
      20.062
    ]
  }
}