{
  "type": "Feature",
  "properties": {
    "name": "Ex-Hacienda de Guadalupe",
    "country": "MX",
    "subdivision": "16",
    "timezone": "America/Mexico_City"
  },
  "geometry": {
    "type": "Point",
    "coordinates": [
      -101.21472,
      19.78417
    ]
  }
}