{
  "type": "Feature",
  "properties": {
    "name": "Fraccionamiento Monte Olivo",
    "country": "MX",
    "subdivision": "16",
    "timezone": "America/Mexico_City"
  },
  "geometry": {
    "type": "Point",
    "coordinates": [
      -102.25111,
      19.98472
    ]
  }
}