{
  "type": "Feature",
  "properties": {
    "name": "Francisco Sarabia (Cerrito Pelón)",
    "country": "MX",
    "subdivision": "16",
    "timezone": "America/Mexico_City"
  },
  "geometry": {
    "type": "Point",
    "coordinates": [
      -102.70158,
      20.03086
    ]
  }
}