{
  "type": "Feature",
  "properties": {
    "name": "Héroes de Chapultepec (Rodeo de San Antonio)",
    "country": "MX",
    "subdivision": "16",
    "timezone": "America/Mexico_City"
  },
  "geometry": {
    "type": "Point",
    "coordinates": [
      -101.5025,
      20.31111
    ]
  }
}