{
  "type": "Feature",
  "properties": {
    "name": "Huandacareo",
    "country": "MX",
    "subdivision": "16",
    "timezone": "America/Mexico_City"
  },
  "geometry": {
    "type": "Point",
    "coordinates": [
      -101.2761,
      19.99136
    ]
  }
}