{
  "type": "Feature",
  "properties": {
    "name": "Huetamo de Núñez",
    "country": "MX",
    "subdivision": "16",
    "timezone": "America/Mexico_City"
  },
  "geometry": {
    "type": "Point",
    "coordinates": [
      -100.897,
      18.62926
    ]
  }
}