{
  "type": "Feature",
  "properties": {
    "name": "J. Jesús Díaz Tzirio",
    "country": "MX",
    "subdivision": "16",
    "timezone": "America/Mexico_City"
  },
  "geometry": {
    "type": "Point",
    "coordinates": [
      -102.39722,
      19.76667
    ]
  }
}