{
  "type": "Feature",
  "properties": {
    "name": "La Esperanza",
    "country": "MX",
    "subdivision": "16",
    "timezone": "America/Mexico_City"
  },
  "geometry": {
    "type": "Point",
    "coordinates": [
      -102.41104,
      20.05559
    ]
  }
}