{
  "type": "Feature",
  "properties": {
    "name": "La Fundición (Quinta Manzana)",
    "country": "MX",
    "subdivision": "16",
    "timezone": "America/Mexico_City"
  },
  "geometry": {
    "type": "Point",
    "coordinates": [
      -100.30361,
      19.45528
    ]
  }
}