{
  "type": "Feature",
  "properties": {
    "name": "La Huacana",
    "country": "MX",
    "subdivision": "16",
    "timezone": "America/Mexico_City"
  },
  "geometry": {
    "type": "Point",
    "coordinates": [
      -101.8072,
      18.96312
    ]
  }
}