{
  "type": "Feature",
  "properties": {
    "name": "La Luz",
    "country": "MX",
    "subdivision": "16",
    "timezone": "America/Mexico_City"
  },
  "geometry": {
    "type": "Point",
    "coordinates": [
      -102.48528,
      20.15234
    ]
  }
}