{
  "type": "Feature",
  "properties": {
    "name": "La Sauceda",
    "country": "MX",
    "subdivision": "16",
    "timezone": "America/Mexico_City"
  },
  "geometry": {
    "type": "Point",
    "coordinates": [
      -102.34512,
      20.0939
    ]
  }
}