{
  "type": "Feature",
  "properties": {
    "name": "Las Cañadas",
    "country": "MX",
    "subdivision": "16",
    "timezone": "America/Mexico_City"
  },
  "geometry": {
    "type": "Point",
    "coordinates": [
      -101.97806,
      20.2975
    ]
  }
}