{
  "type": "Feature",
  "properties": {
    "name": "Macutzio",
    "country": "MX",
    "subdivision": "16",
    "timezone": "America/Mexico_City"
  },
  "geometry": {
    "type": "Point",
    "coordinates": [
      -100.355,
      19.49917
    ]
  }
}