{
  "type": "Feature",
  "properties": {
    "name": "Manzana de San Luis",
    "country": "MX",
    "subdivision": "16",
    "timezone": "America/Mexico_City"
  },
  "geometry": {
    "type": "Point",
    "coordinates": [
      -100.27703,
      19.56236
    ]
  }
}