{
  "type": "Feature",
  "properties": {
    "name": "Mineral de Angangueo",
    "country": "MX",
    "subdivision": "16",
    "timezone": "America/Mexico_City"
  },
  "geometry": {
    "type": "Point",
    "coordinates": [
      -100.28436,
      19.62056
    ]
  }
}