{
  "type": "Feature",
  "properties": {
    "name": "Pastor Ortíz",
    "country": "MX",
    "subdivision": "16",
    "timezone": "America/Mexico_City"
  },
  "geometry": {
    "type": "Point",
    "coordinates": [
      -101.59588,
      20.30552
    ]
  }
}