{
  "type": "Feature",
  "properties": {
    "name": "Pátzcuaro",
    "country": "MX",
    "subdivision": "16",
    "timezone": "America/Mexico_City"
  },
  "geometry": {
    "type": "Point",
    "coordinates": [
      -101.60887,
      19.51594
    ]
  }
}