{
  "type": "Feature",
  "properties": {
    "name": "Puentecillas (Tercera Manzana de Zirahuato)",
    "country": "MX",
    "subdivision": "16",
    "timezone": "America/Mexico_City"
  },
  "geometry": {
    "type": "Point",
    "coordinates": [
      -100.405,
      19.505
    ]
  }
}