{
  "type": "Feature",
  "properties": {
    "name": "Puerto de Buenavista (Lázaro Cárdenas)",
    "country": "MX",
    "subdivision": "16",
    "timezone": "America/Mexico_City"
  },
  "geometry": {
    "type": "Point",
    "coordinates": [
      -101.12722,
      19.68806
    ]
  }
}