{
  "type": "Feature",
  "properties": {
    "name": "Rincón de Cedeños (Rincón de Dolores)",
    "country": "MX",
    "subdivision": "16",
    "timezone": "America/Mexico_City"
  },
  "geometry": {
    "type": "Point",
    "coordinates": [
      -100.57639,
      19.67806
    ]
  }
}