{
  "type": "Feature",
  "properties": {
    "name": "Río Grande",
    "country": "MX",
    "subdivision": "16",
    "timezone": "America/Mexico_City"
  },
  "geometry": {
    "type": "Point",
    "coordinates": [
      -102.00556,
      20.34417
    ]
  }
}