{
  "type": "Feature",
  "properties": {
    "name": "Romero de Guzmán",
    "country": "MX",
    "subdivision": "16",
    "timezone": "America/Mexico_City"
  },
  "geometry": {
    "type": "Point",
    "coordinates": [
      -102.25876,
      20.02974
    ]
  }
}