{
  "type": "Feature",
  "properties": {
    "name": "San Francisco Peribán",
    "country": "MX",
    "subdivision": "16",
    "timezone": "America/Mexico_City"
  },
  "geometry": {
    "type": "Point",
    "coordinates": [
      -102.39844,
      19.55601
    ]
  }
}