{
  "type": "Feature",
  "properties": {
    "name": "San Juanito Itzícuaro",
    "country": "MX",
    "subdivision": "16",
    "timezone": "America/Mexico_City"
  },
  "geometry": {
    "type": "Point",
    "coordinates": [
      -101.25457,
      19.67572
    ]
  }
}