{
  "type": "Feature",
  "properties": {
    "name": "San Antonio",
    "country": "MX",
    "subdivision": "16",
    "timezone": "America/Mexico_City"
  },
  "geometry": {
    "type": "Point",
    "coordinates": [
      -101.26806,
      19.66722
    ]
  }
}