{
  "type": "Feature",
  "properties": {
    "name": "San Andrés Ziróndaro",
    "country": "MX",
    "subdivision": "16",
    "timezone": "America/Mexico_City"
  },
  "geometry": {
    "type": "Point",
    "coordinates": [
      -101.63221,
      19.66943
    ]
  }
}