{
  "type": "Feature",
  "properties": {
    "name": "San Isidro Alta Huerta",
    "country": "MX",
    "subdivision": "16",
    "timezone": "America/Mexico_City"
  },
  "geometry": {
    "type": "Point",
    "coordinates": [
      -100.63889,
      19.72472
    ]
  }
}