{
  "type": "Feature",
  "properties": {
    "name": "Santiago Azajo",
    "country": "MX",
    "subdivision": "16",
    "timezone": "America/Mexico_City"
  },
  "geometry": {
    "type": "Point",
    "coordinates": [
      -101.68659,
      19.70666
    ]
  }
}