{
  "type": "Feature",
  "properties": {
    "name": "Santa Clara del Cobre",
    "country": "MX",
    "subdivision": "16",
    "timezone": "America/Mexico_City"
  },
  "geometry": {
    "type": "Point",
    "coordinates": [
      -101.63998,
      19.4058
    ]
  }
}