{
  "type": "Feature",
  "properties": {
    "name": "Santa Rosa (Santa Bárbara)",
    "country": "MX",
    "subdivision": "16",
    "timezone": "America/Mexico_City"
  },
  "geometry": {
    "type": "Point",
    "coordinates": [
      -102.03611,
      19.38333
    ]
  }
}