{
  "type": "Feature",
  "properties": {
    "name": "Santa Ana",
    "country": "MX",
    "subdivision": "16",
    "timezone": "America/Mexico_City"
  },
  "geometry": {
    "type": "Point",
    "coordinates": [
      -100.46889,
      19.58222
    ]
  }
}