{
  "type": "Feature",
  "properties": {
    "name": "Tacámbaro de Codallos",
    "country": "MX",
    "subdivision": "16",
    "timezone": "America/Mexico_City"
  },
  "geometry": {
    "type": "Point",
    "coordinates": [
      -101.45824,
      19.23502
    ]
  }
}