{
  "type": "Feature",
  "properties": {
    "name": "Tafetán",
    "country": "MX",
    "subdivision": "16",
    "timezone": "America/Mexico_City"
  },
  "geometry": {
    "type": "Point",
    "coordinates": [
      -100.90817,
      19.41876
    ]
  }
}