{
  "type": "Feature",
  "properties": {
    "name": "Tarejero",
    "country": "MX",
    "subdivision": "16",
    "timezone": "America/Mexico_City"
  },
  "geometry": {
    "type": "Point",
    "coordinates": [
      -101.71564,
      19.81941
    ]
  }
}