{
  "type": "Feature",
  "properties": {
    "name": "Tlalpujahua de Rayón",
    "country": "MX",
    "subdivision": "16",
    "timezone": "America/Mexico_City"
  },
  "geometry": {
    "type": "Point",
    "coordinates": [
      -100.17409,
      19.80523
    ]
  }
}