{
  "type": "Feature",
  "properties": {
    "name": "Uripitio",
    "country": "MX",
    "subdivision": "16",
    "timezone": "America/Mexico_City"
  },
  "geometry": {
    "type": "Point",
    "coordinates": [
      -100.538,
      19.95338
    ]
  }
}