{
  "type": "Feature",
  "properties": {
    "name": "Villa Victoria",
    "country": "MX",
    "subdivision": "16",
    "timezone": "America/Mexico_City"
  },
  "geometry": {
    "type": "Point",
    "coordinates": [
      -103.36967,
      18.75749
    ]
  }
}