{
  "type": "Feature",
  "properties": {
    "name": "Zamora",
    "country": "MX",
    "subdivision": "16",
    "timezone": "America/Mexico_City"
  },
  "geometry": {
    "type": "Point",
    "coordinates": [
      -102.28387,
      19.9855
    ]
  }
}