{
  "type": "Feature",
  "properties": {
    "name": "Arcade",
    "country": "US",
    "subdivision": "GA",
    "timezone": "America/New_York"
  },
  "geometry": {
    "type": "Point",
    "coordinates": [
      -83.56155,
      34.07789
    ]
  }
}