{
  "type": "Feature",
  "properties": {
    "name": "Bloomingdale",
    "country": "US",
    "subdivision": "GA",
    "timezone": "America/New_York"
  },
  "geometry": {
    "type": "Point",
    "coordinates": [
      -81.299,
      32.13242
    ]
  }
}