{
  "type": "Feature",
  "properties": {
    "name": "Dacula",
    "country": "US",
    "subdivision": "GA",
    "timezone": "America/New_York"
  },
  "geometry": {
    "type": "Point",
    "coordinates": [
      -83.89796,
      33.98872
    ]
  }
}