{
  "type": "Feature",
  "properties": {
    "name": "Dahlonega",
    "country": "US",
    "subdivision": "GA",
    "timezone": "America/New_York"
  },
  "geometry": {
    "type": "Point",
    "coordinates": [
      -83.98491,
      34.53259
    ]
  }
}