{
  "type": "Feature",
  "properties": {
    "name": "Darien",
    "country": "US",
    "subdivision": "GA",
    "timezone": "America/New_York"
  },
  "geometry": {
    "type": "Point",
    "coordinates": [
      -81.43399,
      31.37023
    ]
  }
}