{
  "type": "Feature",
  "properties": {
    "name": "Decatur",
    "country": "US",
    "subdivision": "GA",
    "timezone": "America/New_York"
  },
  "geometry": {
    "type": "Point",
    "coordinates": [
      -84.29631,
      33.77483
    ]
  }
}