{
  "type": "Feature",
  "properties": {
    "name": "Donalsonville",
    "country": "US",
    "subdivision": "GA",
    "timezone": "America/New_York"
  },
  "geometry": {
    "type": "Point",
    "coordinates": [
      -84.87909,
      31.04046
    ]
  }
}