{
  "type": "Feature",
  "properties": {
    "name": "Douglas",
    "country": "US",
    "subdivision": "GA",
    "timezone": "America/New_York"
  },
  "geometry": {
    "type": "Point",
    "coordinates": [
      -82.84987,
      31.50881
    ]
  }
}