{
  "type": "Feature",
  "properties": {
    "name": "Douglasville",
    "country": "US",
    "subdivision": "GA",
    "timezone": "America/New_York"
  },
  "geometry": {
    "type": "Point",
    "coordinates": [
      -84.74771,
      33.7515
    ]
  }
}