{
  "type": "Feature",
  "properties": {
    "name": "Euharlee",
    "country": "US",
    "subdivision": "GA",
    "timezone": "America/New_York"
  },
  "geometry": {
    "type": "Point",
    "coordinates": [
      -84.933,
      34.14482
    ]
  }
}