{
  "type": "Feature",
  "properties": {
    "name": "Fayetteville",
    "country": "US",
    "subdivision": "GA",
    "timezone": "America/New_York"
  },
  "geometry": {
    "type": "Point",
    "coordinates": [
      -84.45493,
      33.44873
    ]
  }
}