{
  "type": "Feature",
  "properties": {
    "name": "Forest Park",
    "country": "US",
    "subdivision": "GA",
    "timezone": "America/New_York"
  },
  "geometry": {
    "type": "Point",
    "coordinates": [
      -84.36909,
      33.62205
    ]
  }
}