{
  "type": "Feature",
  "properties": {
    "name": "Forsyth",
    "country": "US",
    "subdivision": "GA",
    "timezone": "America/New_York"
  },
  "geometry": {
    "type": "Point",
    "coordinates": [
      -83.93824,
      33.0343
    ]
  }
}