{
  "type": "Feature",
  "properties": {
    "name": "Gray",
    "country": "US",
    "subdivision": "GA",
    "timezone": "America/New_York"
  },
  "geometry": {
    "type": "Point",
    "coordinates": [
      -83.53378,
      33.00958
    ]
  }
}