{
  "type": "Feature",
  "properties": {
    "name": "Gumlog",
    "country": "US",
    "subdivision": "GA",
    "timezone": "America/New_York"
  },
  "geometry": {
    "type": "Point",
    "coordinates": [
      -83.09654,
      34.49177
    ]
  }
}