{
  "type": "Feature",
  "properties": {
    "name": "Hawkinsville",
    "country": "US",
    "subdivision": "GA",
    "timezone": "America/New_York"
  },
  "geometry": {
    "type": "Point",
    "coordinates": [
      -83.47212,
      32.28377
    ]
  }
}