{
  "type": "Feature",
  "properties": {
    "name": "Hogansville",
    "country": "US",
    "subdivision": "GA",
    "timezone": "America/New_York"
  },
  "geometry": {
    "type": "Point",
    "coordinates": [
      -84.91494,
      33.17318
    ]
  }
}