{
  "type": "Feature",
  "properties": {
    "name": "Johns Creek",
    "country": "US",
    "subdivision": "GA",
    "timezone": "America/New_York"
  },
  "geometry": {
    "type": "Point",
    "coordinates": [
      -84.19858,
      34.02893
    ]
  }
}