{
  "type": "Feature",
  "properties": {
    "name": "Kennesaw",
    "country": "US",
    "subdivision": "GA",
    "timezone": "America/New_York"
  },
  "geometry": {
    "type": "Point",
    "coordinates": [
      -84.61549,
      34.02343
    ]
  }
}