{
  "type": "Feature",
  "properties": {
    "name": "Lovejoy",
    "country": "US",
    "subdivision": "GA",
    "timezone": "America/New_York"
  },
  "geometry": {
    "type": "Point",
    "coordinates": [
      -84.31437,
      33.43622
    ]
  }
}