{
  "type": "Feature",
  "properties": {
    "name": "Madison",
    "country": "US",
    "subdivision": "GA",
    "timezone": "America/New_York"
  },
  "geometry": {
    "type": "Point",
    "coordinates": [
      -83.46794,
      33.59568
    ]
  }
}