{
  "type": "Feature",
  "properties": {
    "name": "Milledgeville",
    "country": "US",
    "subdivision": "GA",
    "timezone": "America/New_York"
  },
  "geometry": {
    "type": "Point",
    "coordinates": [
      -83.2321,
      33.08014
    ]
  }
}