{
  "type": "Feature",
  "properties": {
    "name": "Milton",
    "country": "US",
    "subdivision": "GA",
    "timezone": "America/New_York"
  },
  "geometry": {
    "type": "Point",
    "coordinates": [
      -84.30067,
      34.13216
    ]
  }
}