{
  "type": "Feature",
  "properties": {
    "name": "Nashville",
    "country": "US",
    "subdivision": "GA",
    "timezone": "America/New_York"
  },
  "geometry": {
    "type": "Point",
    "coordinates": [
      -83.25015,
      31.20742
    ]
  }
}