{
  "type": "Feature",
  "properties": {
    "name": "Panthersville",
    "country": "US",
    "subdivision": "GA",
    "timezone": "America/New_York"
  },
  "geometry": {
    "type": "Point",
    "coordinates": [
      -84.27187,
      33.70733
    ]
  }
}