{
  "type": "Feature",
  "properties": {
    "name": "Powder Springs",
    "country": "US",
    "subdivision": "GA",
    "timezone": "America/New_York"
  },
  "geometry": {
    "type": "Point",
    "coordinates": [
      -84.68382,
      33.85955
    ]
  }
}