{
  "type": "Feature",
  "properties": {
    "name": "Putney",
    "country": "US",
    "subdivision": "GA",
    "timezone": "America/New_York"
  },
  "geometry": {
    "type": "Point",
    "coordinates": [
      -84.11768,
      31.47018
    ]
  }
}