{
  "type": "Feature",
  "properties": {
    "name": "Ringgold",
    "country": "US",
    "subdivision": "GA",
    "timezone": "America/New_York"
  },
  "geometry": {
    "type": "Point",
    "coordinates": [
      -85.10912,
      34.91591
    ]
  }
}