{
  "type": "Feature",
  "properties": {
    "name": "Saint Simons Island",
    "country": "US",
    "subdivision": "GA",
    "timezone": "America/New_York"
  },
  "geometry": {
    "type": "Point",
    "coordinates": [
      -81.36954,
      31.15051
    ]
  }
}