{
  "type": "Feature",
  "properties": {
    "name": "Sardis",
    "country": "US",
    "subdivision": "GA",
    "timezone": "America/New_York"
  },
  "geometry": {
    "type": "Point",
    "coordinates": [
      -84.63881,
      32.79652
    ]
  }
}