{
  "type": "Feature",
  "properties": {
    "name": "Scottdale",
    "country": "US",
    "subdivision": "GA",
    "timezone": "America/New_York"
  },
  "geometry": {
    "type": "Point",
    "coordinates": [
      -84.26409,
      33.78983
    ]
  }
}