{
  "type": "Feature",
  "properties": {
    "name": "Skidaway Island",
    "country": "US",
    "subdivision": "GA",
    "timezone": "America/New_York"
  },
  "geometry": {
    "type": "Point",
    "coordinates": [
      -81.04705,
      31.93494
    ]
  }
}