{
  "type": "Feature",
  "properties": {
    "name": "Statesboro",
    "country": "US",
    "subdivision": "GA",
    "timezone": "America/New_York"
  },
  "geometry": {
    "type": "Point",
    "coordinates": [
      -81.78317,
      32.44879
    ]
  }
}