{
  "type": "Feature",
  "properties": {
    "name": "Stockbridge",
    "country": "US",
    "subdivision": "GA",
    "timezone": "America/New_York"
  },
  "geometry": {
    "type": "Point",
    "coordinates": [
      -84.23381,
      33.54428
    ]
  }
}