{
  "type": "Feature",
  "properties": {
    "name": "Stonecrest",
    "country": "US",
    "subdivision": "GA",
    "timezone": "America/New_York"
  },
  "geometry": {
    "type": "Point",
    "coordinates": [
      -84.13485,
      33.70849
    ]
  }
}