{
  "type": "Feature",
  "properties": {
    "name": "Summerville",
    "country": "US",
    "subdivision": "GA",
    "timezone": "America/New_York"
  },
  "geometry": {
    "type": "Point",
    "coordinates": [
      -85.34773,
      34.48064
    ]
  }
}