{
  "type": "Feature",
  "properties": {
    "name": "Thomson",
    "country": "US",
    "subdivision": "GA",
    "timezone": "America/New_York"
  },
  "geometry": {
    "type": "Point",
    "coordinates": [
      -82.50457,
      33.47069
    ]
  }
}