{
  "type": "Feature",
  "properties": {
    "name": "Twin City",
    "country": "US",
    "subdivision": "GA",
    "timezone": "America/New_York"
  },
  "geometry": {
    "type": "Point",
    "coordinates": [
      -82.15512,
      32.58294
    ]
  }
}