{
  "type": "Feature",
  "properties": {
    "name": "Unadilla",
    "country": "US",
    "subdivision": "GA",
    "timezone": "America/New_York"
  },
  "geometry": {
    "type": "Point",
    "coordinates": [
      -83.73657,
      32.26155
    ]
  }
}