{
  "type": "Feature",
  "properties": {
    "name": "Vienna",
    "country": "US",
    "subdivision": "GA",
    "timezone": "America/New_York"
  },
  "geometry": {
    "type": "Point",
    "coordinates": [
      -83.79545,
      32.09156
    ]
  }
}