{
  "type": "Feature",
  "properties": {
    "name": "Vinings",
    "country": "US",
    "subdivision": "GA",
    "timezone": "America/New_York"
  },
  "geometry": {
    "type": "Point",
    "coordinates": [
      -84.46437,
      33.86483
    ]
  }
}