{
  "type": "Feature",
  "properties": {
    "name": "Wadley",
    "country": "US",
    "subdivision": "GA",
    "timezone": "America/New_York"
  },
  "geometry": {
    "type": "Point",
    "coordinates": [
      -82.40402,
      32.86682
    ]
  }
}