{
  "type": "Feature",
  "properties": {
    "name": "Warrenton",
    "country": "US",
    "subdivision": "GA",
    "timezone": "America/New_York"
  },
  "geometry": {
    "type": "Point",
    "coordinates": [
      -82.66208,
      33.40708
    ]
  }
}