{
  "type": "Feature",
  "properties": {
    "name": "Watkinsville",
    "country": "US",
    "subdivision": "GA",
    "timezone": "America/New_York"
  },
  "geometry": {
    "type": "Point",
    "coordinates": [
      -83.40877,
      33.8629
    ]
  }
}