{
  "type": "Feature",
  "properties": {
    "name": "Waynesboro",
    "country": "US",
    "subdivision": "GA",
    "timezone": "America/New_York"
  },
  "geometry": {
    "type": "Point",
    "coordinates": [
      -82.01567,
      33.08987
    ]
  }
}