{
  "type": "Feature",
  "properties": {
    "name": "Winterville",
    "country": "US",
    "subdivision": "GA",
    "timezone": "America/New_York"
  },
  "geometry": {
    "type": "Point",
    "coordinates": [
      -83.27821,
      33.96706
    ]
  }
}