{
  "type": "Feature",
  "properties": {
    "name": "Nonsan",
    "country": "KR",
    "subdivision": "17",
    "timezone": "Asia/Seoul"
  },
  "geometry": {
    "type": "Point",
    "coordinates": [
      127.08472,
      36.20389
    ]
  }
}