{
  "type": "Feature",
  "properties": {
    "name": "Amboise",
    "country": "FR",
    "subdivision": "24",
    "timezone": "Europe/Paris"
  },
  "geometry": {
    "type": "Point",
    "coordinates": [
      0.98266,
      47.41249
    ]
  }
}