{
  "type": "Feature",
  "properties": {
    "name": "Armenonville-les-Gâtineaux",
    "country": "FR",
    "subdivision": "24",
    "timezone": "Europe/Paris"
  },
  "geometry": {
    "type": "Point",
    "coordinates": [
      1.6475,
      48.54365
    ]
  }
}