{
  "type": "Feature",
  "properties": {
    "name": "Athée-sur-Cher",
    "country": "FR",
    "subdivision": "24",
    "timezone": "Europe/Paris"
  },
  "geometry": {
    "type": "Point",
    "coordinates": [
      0.91659,
      47.32023
    ]
  }
}