{
  "type": "Feature",
  "properties": {
    "name": "Bourgueil",
    "country": "FR",
    "subdivision": "24",
    "timezone": "Europe/Paris"
  },
  "geometry": {
    "type": "Point",
    "coordinates": [
      0.16612,
      47.28333
    ]
  }
}