{
  "type": "Feature",
  "properties": {
    "name": "Brezolles",
    "country": "FR",
    "subdivision": "24",
    "timezone": "Europe/Paris"
  },
  "geometry": {
    "type": "Point",
    "coordinates": [
      1.07404,
      48.69033
    ]
  }
}