{
  "type": "Feature",
  "properties": {
    "name": "Cerdon",
    "country": "FR",
    "subdivision": "24",
    "timezone": "Europe/Paris"
  },
  "geometry": {
    "type": "Point",
    "coordinates": [
      2.36277,
      47.63571
    ]
  }
}