{
  "type": "Feature",
  "properties": {
    "name": "Chanceaux-sur-Choisille",
    "country": "FR",
    "subdivision": "24",
    "timezone": "Europe/Paris"
  },
  "geometry": {
    "type": "Point",
    "coordinates": [
      0.70539,
      47.47145
    ]
  }
}