{
  "type": "Feature",
  "properties": {
    "name": "Chargé",
    "country": "FR",
    "subdivision": "24",
    "timezone": "Europe/Paris"
  },
  "geometry": {
    "type": "Point",
    "coordinates": [
      1.03037,
      47.4327
    ]
  }
}