{
  "type": "Feature",
  "properties": {
    "name": "Château-Renault",
    "country": "FR",
    "subdivision": "24",
    "timezone": "Europe/Paris"
  },
  "geometry": {
    "type": "Point",
    "coordinates": [
      0.91143,
      47.59188
    ]
  }
}