{
  "type": "Feature",
  "properties": {
    "name": "Château-Renard",
    "country": "FR",
    "subdivision": "24",
    "timezone": "Europe/Paris"
  },
  "geometry": {
    "type": "Point",
    "coordinates": [
      2.93333,
      47.93333
    ]
  }
}