{
  "type": "Feature",
  "properties": {
    "name": "Chaumont-sur-Tharonne",
    "country": "FR",
    "subdivision": "24",
    "timezone": "Europe/Paris"
  },
  "geometry": {
    "type": "Point",
    "coordinates": [
      1.90514,
      47.61039
    ]
  }
}