{
  "type": "Feature",
  "properties": {
    "name": "Chinon",
    "country": "FR",
    "subdivision": "24",
    "timezone": "Europe/Paris"
  },
  "geometry": {
    "type": "Point",
    "coordinates": [
      0.24284,
      47.16701
    ]
  }
}