{
  "type": "Feature",
  "properties": {
    "name": "Chitenay",
    "country": "FR",
    "subdivision": "24",
    "timezone": "Europe/Paris"
  },
  "geometry": {
    "type": "Point",
    "coordinates": [
      1.37139,
      47.49753
    ]
  }
}