{
  "type": "Feature",
  "properties": {
    "name": "Cléry-Saint-André",
    "country": "FR",
    "subdivision": "24",
    "timezone": "Europe/Paris"
  },
  "geometry": {
    "type": "Point",
    "coordinates": [
      1.75091,
      47.82218
    ]
  }
}