{
  "type": "Feature",
  "properties": {
    "name": "Cour-Cheverny",
    "country": "FR",
    "subdivision": "24",
    "timezone": "Europe/Paris"
  },
  "geometry": {
    "type": "Point",
    "coordinates": [
      1.45583,
      47.51033
    ]
  }
}