{
  "type": "Feature",
  "properties": {
    "name": "Écueillé",
    "country": "FR",
    "subdivision": "24",
    "timezone": "Europe/Paris"
  },
  "geometry": {
    "type": "Point",
    "coordinates": [
      1.34668,
      47.08462
    ]
  }
}