{
  "type": "Feature",
  "properties": {
    "name": "Hanches",
    "country": "FR",
    "subdivision": "24",
    "timezone": "Europe/Paris"
  },
  "geometry": {
    "type": "Point",
    "coordinates": [
      1.65137,
      48.60115
    ]
  }
}