{
  "type": "Feature",
  "properties": {
    "name": "Huisseau-sur-Cosson",
    "country": "FR",
    "subdivision": "24",
    "timezone": "Europe/Paris"
  },
  "geometry": {
    "type": "Point",
    "coordinates": [
      1.45333,
      47.59335
    ]
  }
}