{
  "type": "Feature",
  "properties": {
    "name": "Ingré",
    "country": "FR",
    "subdivision": "24",
    "timezone": "Europe/Paris"
  },
  "geometry": {
    "type": "Point",
    "coordinates": [
      1.82778,
      47.91995
    ]
  }
}