{
  "type": "Feature",
  "properties": {
    "name": "Jouy-le-Potier",
    "country": "FR",
    "subdivision": "24",
    "timezone": "Europe/Paris"
  },
  "geometry": {
    "type": "Point",
    "coordinates": [
      1.81115,
      47.74553
    ]
  }
}