{
  "type": "Feature",
  "properties": {
    "name": "La Châtre",
    "country": "FR",
    "subdivision": "24",
    "timezone": "Europe/Paris"
  },
  "geometry": {
    "type": "Point",
    "coordinates": [
      1.98734,
      46.58228
    ]
  }
}