{
  "type": "Feature",
  "properties": {
    "name": "Les Montils",
    "country": "FR",
    "subdivision": "24",
    "timezone": "Europe/Paris"
  },
  "geometry": {
    "type": "Point",
    "coordinates": [
      1.29775,
      47.49499
    ]
  }
}