{
  "type": "Feature",
  "properties": {
    "name": "Martizay",
    "country": "FR",
    "subdivision": "24",
    "timezone": "Europe/Paris"
  },
  "geometry": {
    "type": "Point",
    "coordinates": [
      1.04324,
      46.80767
    ]
  }
}