{
  "type": "Feature",
  "properties": {
    "name": "Montierchaume",
    "country": "FR",
    "subdivision": "24",
    "timezone": "Europe/Paris"
  },
  "geometry": {
    "type": "Point",
    "coordinates": [
      1.77181,
      46.86362
    ]
  }
}