{
  "type": "Feature",
  "properties": {
    "name": "Morancez",
    "country": "FR",
    "subdivision": "24",
    "timezone": "Europe/Paris"
  },
  "geometry": {
    "type": "Point",
    "coordinates": [
      1.49388,
      48.40051
    ]
  }
}