{
  "type": "Feature",
  "properties": {
    "name": "Niherne",
    "country": "FR",
    "subdivision": "24",
    "timezone": "Europe/Paris"
  },
  "geometry": {
    "type": "Point",
    "coordinates": [
      1.56384,
      46.82768
    ]
  }
}