{
  "type": "Feature",
  "properties": {
    "name": "Nogent-le-Phaye",
    "country": "FR",
    "subdivision": "24",
    "timezone": "Europe/Paris"
  },
  "geometry": {
    "type": "Point",
    "coordinates": [
      1.57777,
      48.44528
    ]
  }
}