{
  "type": "Feature",
  "properties": {
    "name": "Nouzilly",
    "country": "FR",
    "subdivision": "24",
    "timezone": "Europe/Paris"
  },
  "geometry": {
    "type": "Point",
    "coordinates": [
      0.74623,
      47.54499
    ]
  }
}