{
  "type": "Feature",
  "properties": {
    "name": "Noyers-sur-Cher",
    "country": "FR",
    "subdivision": "24",
    "timezone": "Europe/Paris"
  },
  "geometry": {
    "type": "Point",
    "coordinates": [
      1.4032,
      47.27701
    ]
  }
}