{
  "type": "Feature",
  "properties": {
    "name": "Onzain",
    "country": "FR",
    "subdivision": "24",
    "timezone": "Europe/Paris"
  },
  "geometry": {
    "type": "Point",
    "coordinates": [
      1.17701,
      47.49956
    ]
  }
}