{
  "type": "Feature",
  "properties": {
    "name": "Orgères-en-Beauce",
    "country": "FR",
    "subdivision": "24",
    "timezone": "Europe/Paris"
  },
  "geometry": {
    "type": "Point",
    "coordinates": [
      1.6838,
      48.14636
    ]
  }
}