{
  "type": "Feature",
  "properties": {
    "name": "Plaimpied-Givaudins",
    "country": "FR",
    "subdivision": "24",
    "timezone": "Europe/Paris"
  },
  "geometry": {
    "type": "Point",
    "coordinates": [
      2.45428,
      46.998
    ]
  }
}