{
  "type": "Feature",
  "properties": {
    "name": "Reignac-sur-Indre",
    "country": "FR",
    "subdivision": "24",
    "timezone": "Europe/Paris"
  },
  "geometry": {
    "type": "Point",
    "coordinates": [
      0.91587,
      47.22662
    ]
  }
}