{
  "type": "Feature",
  "properties": {
    "name": "Sainte-Maure-de-Touraine",
    "country": "FR",
    "subdivision": "24",
    "timezone": "Europe/Paris"
  },
  "geometry": {
    "type": "Point",
    "coordinates": [
      0.62236,
      47.1113
    ]
  }
}