{
  "type": "Feature",
  "properties": {
    "name": "Saint-Doulchard",
    "country": "FR",
    "subdivision": "24",
    "timezone": "Europe/Paris"
  },
  "geometry": {
    "type": "Point",
    "coordinates": [
      2.352,
      47.10371
    ]
  }
}