{
  "type": "Feature",
  "properties": {
    "name": "Saint-Ouen",
    "country": "FR",
    "subdivision": "24",
    "timezone": "Europe/Paris"
  },
  "geometry": {
    "type": "Point",
    "coordinates": [
      1.08067,
      47.81404
    ]
  }
}