{
  "type": "Feature",
  "properties": {
    "name": "Saint-Georges-sur-Eure",
    "country": "FR",
    "subdivision": "24",
    "timezone": "Europe/Paris"
  },
  "geometry": {
    "type": "Point",
    "coordinates": [
      1.3546,
      48.41869
    ]
  }
}