{
  "type": "Feature",
  "properties": {
    "name": "Saint-Maur",
    "country": "FR",
    "subdivision": "24",
    "timezone": "Europe/Paris"
  },
  "geometry": {
    "type": "Point",
    "coordinates": [
      1.63904,
      46.80657
    ]
  }
}