{
  "type": "Feature",
  "properties": {
    "name": "Saint-Pierre-des-Corps",
    "country": "FR",
    "subdivision": "24",
    "timezone": "Europe/Paris"
  },
  "geometry": {
    "type": "Point",
    "coordinates": [
      0.74849,
      47.38623
    ]
  }
}