{
  "type": "Feature",
  "properties": {
    "name": "Salbris",
    "country": "FR",
    "subdivision": "24",
    "timezone": "Europe/Paris"
  },
  "geometry": {
    "type": "Point",
    "coordinates": [
      2.05124,
      47.4242
    ]
  }
}