{
  "type": "Feature",
  "properties": {
    "name": "Savigny-en-Véron",
    "country": "FR",
    "subdivision": "24",
    "timezone": "Europe/Paris"
  },
  "geometry": {
    "type": "Point",
    "coordinates": [
      0.14457,
      47.20071
    ]
  }
}