{
  "type": "Feature",
  "properties": {
    "name": "Sonzay",
    "country": "FR",
    "subdivision": "24",
    "timezone": "Europe/Paris"
  },
  "geometry": {
    "type": "Point",
    "coordinates": [
      0.46203,
      47.52687
    ]
  }
}