{
  "type": "Feature",
  "properties": {
    "name": "Thilouze",
    "country": "FR",
    "subdivision": "24",
    "timezone": "Europe/Paris"
  },
  "geometry": {
    "type": "Point",
    "coordinates": [
      0.57963,
      47.22415
    ]
  }
}