{
  "type": "Feature",
  "properties": {
    "name": "Tours",
    "country": "FR",
    "subdivision": "24",
    "timezone": "Europe/Paris"
  },
  "geometry": {
    "type": "Point",
    "coordinates": [
      0.70398,
      47.39484
    ]
  }
}