{
  "type": "Feature",
  "properties": {
    "name": "Valençay",
    "country": "FR",
    "subdivision": "24",
    "timezone": "Europe/Paris"
  },
  "geometry": {
    "type": "Point",
    "coordinates": [
      1.56852,
      47.16207
    ]
  }
}