{
  "type": "Feature",
  "properties": {
    "name": "Vierzon",
    "country": "FR",
    "subdivision": "24",
    "timezone": "Europe/Paris"
  },
  "geometry": {
    "type": "Point",
    "coordinates": [
      2.0684,
      47.22186
    ]
  }
}