{
  "type": "Feature",
  "properties": {
    "name": "Vouzon",
    "country": "FR",
    "subdivision": "24",
    "timezone": "Europe/Paris"
  },
  "geometry": {
    "type": "Point",
    "coordinates": [
      2.05609,
      47.64515
    ]
  }
}