{
  "type": "Feature",
  "properties": {
    "name": "Pototano",
    "country": "ID",
    "subdivision": "17",
    "timezone": "Asia/Makassar"
  },
  "geometry": {
    "type": "Point",
    "coordinates": [
      117.4811,
      -8.4126
    ]
  }
}