{
  "type": "Feature",
  "properties": {
    "name": "Praya",
    "country": "ID",
    "subdivision": "17",
    "timezone": "Asia/Makassar"
  },
  "geometry": {
    "type": "Point",
    "coordinates": [
      116.27036,
      -8.70536
    ]
  }
}