{
  "type": "Feature",
  "properties": {
    "name": "Senggigi",
    "country": "ID",
    "subdivision": "17",
    "timezone": "Asia/Makassar"
  },
  "geometry": {
    "type": "Point",
    "coordinates": [
      116.0424,
      -8.4919
    ]
  }
}