{
  "type": "Feature",
  "properties": {
    "name": "Iganga",
    "country": "UG",
    "subdivision": "E",
    "timezone": "Africa/Kampala"
  },
  "geometry": {
    "type": "Point",
    "coordinates": [
      33.46861,
      0.60917
    ]
  }
}