{
  "type": "Feature",
  "properties": {
    "name": "Boujniba",
    "country": "MA",
    "subdivision": "05",
    "timezone": "Africa/Casablanca"
  },
  "geometry": {
    "type": "Point",
    "coordinates": [
      -6.77464,
      32.90046
    ]
  }
}