{
  "type": "Feature",
  "properties": {
    "name": "Georgiyevskoye",
    "country": "RU",
    "subdivision": "37",
    "timezone": "Europe/Moscow"
  },
  "geometry": {
    "type": "Point",
    "coordinates": [
      45.02404,
      58.73101
    ]
  }
}