{
  "type": "Feature",
  "properties": {
    "name": "Songgangdong",
    "country": "KR",
    "subdivision": "19",
    "timezone": "Asia/Seoul"
  },
  "geometry": {
    "type": "Point",
    "coordinates": [
      127.37587,
      36.43387
    ]
  }
}