{
  "type": "Feature",
  "properties": {
    "name": "Kankan",
    "country": "GN",
    "subdivision": "K",
    "timezone": "Africa/Conakry"
  },
  "geometry": {
    "type": "Point",
    "coordinates": [
      -9.30568,
      10.38542
    ]
  }
}