{
  "type": "Feature",
  "properties": {
    "name": "Mandiana",
    "country": "GN",
    "subdivision": "K",
    "timezone": "Africa/Conakry"
  },
  "geometry": {
    "type": "Point",
    "coordinates": [
      -8.69413,
      10.62577
    ]
  }
}