{
  "type": "Feature",
  "properties": {
    "name": "Katueté",
    "country": "PY",
    "subdivision": "19",
    "timezone": "America/Asuncion"
  },
  "geometry": {
    "type": "Point",
    "coordinates": [
      -54.75961,
      -24.24829
    ]
  }
}