{
  "type": "Feature",
  "properties": {
    "name": "Belaya Gora",
    "country": "RU",
    "subdivision": "63",
    "timezone": "Asia/Magadan"
  },
  "geometry": {
    "type": "Point",
    "coordinates": [
      146.18583,
      68.53805
    ]
  }
}