{
  "type": "Feature",
  "properties": {
    "name": "Berdigestyakh",
    "country": "RU",
    "subdivision": "63",
    "timezone": "Asia/Yakutsk"
  },
  "geometry": {
    "type": "Point",
    "coordinates": [
      126.69573,
      62.09842
    ]
  }
}