{
  "type": "Feature",
  "properties": {
    "name": "Chul’man",
    "country": "RU",
    "subdivision": "63",
    "timezone": "Asia/Yakutsk"
  },
  "geometry": {
    "type": "Point",
    "coordinates": [
      124.90812,
      56.84735
    ]
  }
}