{
  "type": "Feature",
  "properties": {
    "name": "Khandyga",
    "country": "RU",
    "subdivision": "63",
    "timezone": "Asia/Vladivostok"
  },
  "geometry": {
    "type": "Point",
    "coordinates": [
      135.5667,
      62.65333
    ]
  }
}