{
  "type": "Feature",
  "properties": {
    "name": "Olyokminsk",
    "country": "RU",
    "subdivision": "63",
    "timezone": "Asia/Yakutsk"
  },
  "geometry": {
    "type": "Point",
    "coordinates": [
      120.4203,
      60.3743
    ]
  }
}