{
  "type": "Feature",
  "properties": {
    "name": "Sangar",
    "country": "RU",
    "subdivision": "63",
    "timezone": "Asia/Yakutsk"
  },
  "geometry": {
    "type": "Point",
    "coordinates": [
      127.47135,
      63.92301
    ]
  }
}