{
  "type": "Feature",
  "properties": {
    "name": "Ust-Nera",
    "country": "RU",
    "subdivision": "63",
    "timezone": "Asia/Magadan"
  },
  "geometry": {
    "type": "Point",
    "coordinates": [
      143.237,
      64.56968
    ]
  }
}