{
  "type": "Feature",
  "properties": {
    "name": "Ytyk-Kyuyël’",
    "country": "RU",
    "subdivision": "63",
    "timezone": "Asia/Yakutsk"
  },
  "geometry": {
    "type": "Point",
    "coordinates": [
      133.56044,
      62.36119
    ]
  }
}