{
  "type": "Feature",
  "properties": {
    "name": "Dawukou",
    "country": "CN",
    "subdivision": "21",
    "timezone": "Asia/Shanghai"
  },
  "geometry": {
    "type": "Point",
    "coordinates": [
      106.39583,
      39.04194
    ]
  }
}