{
  "type": "Feature",
  "properties": {
    "name": "Burnham",
    "country": "NZ",
    "subdivision": "E9",
    "timezone": "Pacific/Auckland"
  },
  "geometry": {
    "type": "Point",
    "coordinates": [
      172.31667,
      -43.61667
    ]
  }
}