{
  "type": "Feature",
  "properties": {
    "name": "Christchurch",
    "country": "NZ",
    "subdivision": "E9",
    "timezone": "Pacific/Auckland"
  },
  "geometry": {
    "type": "Point",
    "coordinates": [
      172.63333,
      -43.53333
    ]
  }
}