{
  "type": "Feature",
  "properties": {
    "name": "Geraldine",
    "country": "NZ",
    "subdivision": "E9",
    "timezone": "Pacific/Auckland"
  },
  "geometry": {
    "type": "Point",
    "coordinates": [
      171.24458,
      -44.09061
    ]
  }
}