{
  "type": "Feature",
  "properties": {
    "name": "Moerewa",
    "country": "NZ",
    "subdivision": "F6",
    "timezone": "Pacific/Auckland"
  },
  "geometry": {
    "type": "Point",
    "coordinates": [
      174.03333,
      -35.38333
    ]
  }
}