{
  "type": "Feature",
  "properties": {
    "name": "Mermoz Boabab",
    "country": "SN",
    "subdivision": "01",
    "timezone": "Africa/Dakar"
  },
  "geometry": {
    "type": "Point",
    "coordinates": [
      -17.47581,
      14.70649
    ]
  }
}