{
  "type": "Feature",
  "properties": {
    "name": "Mella",
    "country": "DO",
    "subdivision": "09",
    "timezone": "America/Santo_Domingo"
  },
  "geometry": {
    "type": "Point",
    "coordinates": [
      -71.41716,
      18.35871
    ]
  }
}