{
  "type": "Feature",
  "properties": {
    "name": "Allingåbro",
    "country": "DK",
    "subdivision": "18",
    "timezone": "Europe/Copenhagen"
  },
  "geometry": {
    "type": "Point",
    "coordinates": [
      10.31957,
      56.46432
    ]
  }
}