{
  "type": "Feature",
  "properties": {
    "name": "Århus",
    "country": "DK",
    "subdivision": "18",
    "timezone": "Europe/Copenhagen"
  },
  "geometry": {
    "type": "Point",
    "coordinates": [
      10.21076,
      56.15674
    ]
  }
}