{
  "type": "Feature",
  "properties": {
    "name": "Framlev",
    "country": "DK",
    "subdivision": "18",
    "timezone": "Europe/Copenhagen"
  },
  "geometry": {
    "type": "Point",
    "coordinates": [
      10.01318,
      56.15664
    ]
  }
}