{
  "type": "Feature",
  "properties": {
    "name": "Grenaa",
    "country": "DK",
    "subdivision": "18",
    "timezone": "Europe/Copenhagen"
  },
  "geometry": {
    "type": "Point",
    "coordinates": [
      10.87825,
      56.41578
    ]
  }
}