{
  "type": "Feature",
  "properties": {
    "name": "Hadsten",
    "country": "DK",
    "subdivision": "18",
    "timezone": "Europe/Copenhagen"
  },
  "geometry": {
    "type": "Point",
    "coordinates": [
      10.04931,
      56.32819
    ]
  }
}