{
  "type": "Feature",
  "properties": {
    "name": "Lystrup",
    "country": "DK",
    "subdivision": "18",
    "timezone": "Europe/Copenhagen"
  },
  "geometry": {
    "type": "Point",
    "coordinates": [
      10.23778,
      56.2375
    ]
  }
}