{
  "type": "Feature",
  "properties": {
    "name": "Stavtrup",
    "country": "DK",
    "subdivision": "18",
    "timezone": "Europe/Copenhagen"
  },
  "geometry": {
    "type": "Point",
    "coordinates": [
      10.11987,
      56.13124
    ]
  }
}