{
  "type": "Feature",
  "properties": {
    "name": "Ulstrup",
    "country": "DK",
    "subdivision": "18",
    "timezone": "Europe/Copenhagen"
  },
  "geometry": {
    "type": "Point",
    "coordinates": [
      9.79354,
      56.38994
    ]
  }
}