{
  "type": "Feature",
  "properties": {
    "name": "Ashmyany",
    "country": "BY",
    "subdivision": "03",
    "timezone": "Europe/Minsk"
  },
  "geometry": {
    "type": "Point",
    "coordinates": [
      25.936,
      54.421
    ]
  }
}