{
  "type": "Feature",
  "properties": {
    "name": "Hrodna",
    "country": "BY",
    "subdivision": "03",
    "timezone": "Europe/Minsk"
  },
  "geometry": {
    "type": "Point",
    "coordinates": [
      23.8258,
      53.6884
    ]
  }
}