{
  "type": "Feature",
  "properties": {
    "name": "Iwye",
    "country": "BY",
    "subdivision": "03",
    "timezone": "Europe/Minsk"
  },
  "geometry": {
    "type": "Point",
    "coordinates": [
      25.7727,
      53.9299
    ]
  }
}