{
  "type": "Feature",
  "properties": {
    "name": "Soly",
    "country": "BY",
    "subdivision": "03",
    "timezone": "Europe/Minsk"
  },
  "geometry": {
    "type": "Point",
    "coordinates": [
      26.19381,
      54.51301
    ]
  }
}