{
  "type": "Feature",
  "properties": {
    "name": "Zel’va",
    "country": "BY",
    "subdivision": "03",
    "timezone": "Europe/Minsk"
  },
  "geometry": {
    "type": "Point",
    "coordinates": [
      24.81338,
      53.15064
    ]
  }
}