{
  "type": "Feature",
  "properties": {
    "name": "Mahaica Village",
    "country": "GY",
    "subdivision": "12",
    "timezone": "America/Guyana"
  },
  "geometry": {
    "type": "Point",
    "coordinates": [
      -57.92181,
      6.68405
    ]
  }
}