{
  "type": "Feature",
  "properties": {
    "name": "Chervona Sloboda",
    "country": "UA",
    "subdivision": "01",
    "timezone": "Europe/Kiev"
  },
  "geometry": {
    "type": "Point",
    "coordinates": [
      32.15742,
      49.37281
    ]
  }
}