{
  "type": "Feature",
  "properties": {
    "name": "Katerynopil",
    "country": "UA",
    "subdivision": "01",
    "timezone": "Europe/Kiev"
  },
  "geometry": {
    "type": "Point",
    "coordinates": [
      30.97187,
      48.94563
    ]
  }
}