{
  "type": "Feature",
  "properties": {
    "name": "Nove-Misto",
    "country": "UA",
    "subdivision": "01",
    "timezone": "Europe/Kiev"
  },
  "geometry": {
    "type": "Point",
    "coordinates": [
      29.82813,
      48.98113
    ]
  }
}