{
  "type": "Feature",
  "properties": {
    "name": "Berg",
    "country": "CH",
    "subdivision": "TG",
    "timezone": "Europe/Zurich"
  },
  "geometry": {
    "type": "Point",
    "coordinates": [
      9.16635,
      47.57879
    ]
  }
}