{
  "type": "Feature",
  "properties": {
    "name": "Bottighofen",
    "country": "CH",
    "subdivision": "TG",
    "timezone": "Europe/Zurich"
  },
  "geometry": {
    "type": "Point",
    "coordinates": [
      9.20882,
      47.63643
    ]
  }
}