{
  "type": "Feature",
  "properties": {
    "name": "Romanshorn",
    "country": "CH",
    "subdivision": "TG",
    "timezone": "Europe/Zurich"
  },
  "geometry": {
    "type": "Point",
    "coordinates": [
      9.37869,
      47.56586
    ]
  }
}