{
  "type": "Feature",
  "properties": {
    "name": "Wagenhausen",
    "country": "CH",
    "subdivision": "TG",
    "timezone": "Europe/Zurich"
  },
  "geometry": {
    "type": "Point",
    "coordinates": [
      8.84782,
      47.66003
    ]
  }
}