{
  "type": "Feature",
  "properties": {
    "name": "Bădeni",
    "country": "RO",
    "subdivision": "23",
    "timezone": "Europe/Bucharest"
  },
  "geometry": {
    "type": "Point",
    "coordinates": [
      26.94898,
      47.40581
    ]
  }
}