{
  "type": "Feature",
  "properties": {
    "name": "Balș",
    "country": "RO",
    "subdivision": "23",
    "timezone": "Europe/Bucharest"
  },
  "geometry": {
    "type": "Point",
    "coordinates": [
      26.97856,
      47.29628
    ]
  }
}