{
  "type": "Feature",
  "properties": {
    "name": "Bivolari",
    "country": "RO",
    "subdivision": "23",
    "timezone": "Europe/Bucharest"
  },
  "geometry": {
    "type": "Point",
    "coordinates": [
      27.43333,
      47.53333
    ]
  }
}