{
  "type": "Feature",
  "properties": {
    "name": "Budăi",
    "country": "RO",
    "subdivision": "23",
    "timezone": "Europe/Bucharest"
  },
  "geometry": {
    "type": "Point",
    "coordinates": [
      27.22282,
      47.21773
    ]
  }
}