{
  "type": "Feature",
  "properties": {
    "name": "Dumeşti",
    "country": "RO",
    "subdivision": "23",
    "timezone": "Europe/Bucharest"
  },
  "geometry": {
    "type": "Point",
    "coordinates": [
      27.35,
      47.18333
    ]
  }
}