{
  "type": "Feature",
  "properties": {
    "name": "Glodenii Gândului",
    "country": "RO",
    "subdivision": "23",
    "timezone": "Europe/Bucharest"
  },
  "geometry": {
    "type": "Point",
    "coordinates": [
      27.29938,
      46.95158
    ]
  }
}