{
  "type": "Feature",
  "properties": {
    "name": "Miroslava",
    "country": "RO",
    "subdivision": "23",
    "timezone": "Europe/Bucharest"
  },
  "geometry": {
    "type": "Point",
    "coordinates": [
      27.51667,
      47.15
    ]
  }
}