{
  "type": "Feature",
  "properties": {
    "name": "Osoi",
    "country": "RO",
    "subdivision": "23",
    "timezone": "Europe/Bucharest"
  },
  "geometry": {
    "type": "Point",
    "coordinates": [
      27.80091,
      47.09479
    ]
  }
}