{
  "type": "Feature",
  "properties": {
    "name": "Oţeleni",
    "country": "RO",
    "subdivision": "23",
    "timezone": "Europe/Bucharest"
  },
  "geometry": {
    "type": "Point",
    "coordinates": [
      27.03333,
      47.08333
    ]
  }
}