{
  "type": "Feature",
  "properties": {
    "name": "Poienile",
    "country": "RO",
    "subdivision": "23",
    "timezone": "Europe/Bucharest"
  },
  "geometry": {
    "type": "Point",
    "coordinates": [
      27.18333,
      46.93333
    ]
  }
}