{
  "type": "Feature",
  "properties": {
    "name": "Sticlăria",
    "country": "RO",
    "subdivision": "23",
    "timezone": "Europe/Bucharest"
  },
  "geometry": {
    "type": "Point",
    "coordinates": [
      26.83797,
      47.40115
    ]
  }
}