{
  "type": "Feature",
  "properties": {
    "name": "Tansa",
    "country": "RO",
    "subdivision": "23",
    "timezone": "Europe/Bucharest"
  },
  "geometry": {
    "type": "Point",
    "coordinates": [
      27.07653,
      47.30139
    ]
  }
}