{
  "type": "Feature",
  "properties": {
    "name": "Voineşti",
    "country": "RO",
    "subdivision": "23",
    "timezone": "Europe/Bucharest"
  },
  "geometry": {
    "type": "Point",
    "coordinates": [
      27.41667,
      47.06667
    ]
  }
}