{
  "type": "Feature",
  "properties": {
    "name": "Ahmadnagar",
    "country": "IN",
    "subdivision": "16",
    "timezone": "Asia/Kolkata"
  },
  "geometry": {
    "type": "Point",
    "coordinates": [
      74.73843,
      19.09457
    ]
  }
}