{
  "type": "Feature",
  "properties": {
    "name": "Ārvi",
    "country": "IN",
    "subdivision": "16",
    "timezone": "Asia/Kolkata"
  },
  "geometry": {
    "type": "Point",
    "coordinates": [
      78.22914,
      20.99585
    ]
  }
}