{
  "type": "Feature",
  "properties": {
    "name": "Ashti",
    "country": "IN",
    "subdivision": "16",
    "timezone": "Asia/Kolkata"
  },
  "geometry": {
    "type": "Point",
    "coordinates": [
      76.2252,
      19.37671
    ]
  }
}