{
  "type": "Feature",
  "properties": {
    "name": "Ausa",
    "country": "IN",
    "subdivision": "16",
    "timezone": "Asia/Kolkata"
  },
  "geometry": {
    "type": "Point",
    "coordinates": [
      76.4993,
      18.24728
    ]
  }
}