{
  "type": "Feature",
  "properties": {
    "name": "BÄrsi",
    "country": "IN",
    "subdivision": "16",
    "timezone": "Asia/Kolkata"
  },
  "geometry": {
    "type": "Point",
    "coordinates": [
      75.69275,
      18.23454
    ]
  }
}