{
  "type": "Feature",
  "properties": {
    "name": "BhandÄra",
    "country": "IN",
    "subdivision": "16",
    "timezone": "Asia/Kolkata"
  },
  "geometry": {
    "type": "Point",
    "coordinates": [
      79.64885,
      21.16817
    ]
  }
}