{
  "type": "Feature",
  "properties": {
    "name": "ChÄlisgaon",
    "country": "IN",
    "subdivision": "16",
    "timezone": "Asia/Kolkata"
  },
  "geometry": {
    "type": "Point",
    "coordinates": [
      75.01596,
      20.45781
    ]
  }
}