{
  "type": "Feature",
  "properties": {
    "name": "Chāndūr",
    "country": "IN",
    "subdivision": "16",
    "timezone": "Asia/Kolkata"
  },
  "geometry": {
    "type": "Point",
    "coordinates": [
      77.98015,
      20.81408
    ]
  }
}