{
  "type": "Feature",
  "properties": {
    "name": "Chikhli",
    "country": "IN",
    "subdivision": "16",
    "timezone": "Asia/Kolkata"
  },
  "geometry": {
    "type": "Point",
    "coordinates": [
      76.25774,
      20.35046
    ]
  }
}