{
  "type": "Feature",
  "properties": {
    "name": "Deoli",
    "country": "IN",
    "subdivision": "16",
    "timezone": "Asia/Kolkata"
  },
  "geometry": {
    "type": "Point",
    "coordinates": [
      78.48023,
      20.6492
    ]
  }
}