{
  "type": "Feature",
  "properties": {
    "name": "GangÄpur",
    "country": "IN",
    "subdivision": "16",
    "timezone": "Asia/Kolkata"
  },
  "geometry": {
    "type": "Point",
    "coordinates": [
      75.01045,
      19.69718
    ]
  }
}