{
  "type": "Feature",
  "properties": {
    "name": "Khadki",
    "country": "IN",
    "subdivision": "16",
    "timezone": "Asia/Kolkata"
  },
  "geometry": {
    "type": "Point",
    "coordinates": [
      73.85205,
      18.5635
    ]
  }
}