{
  "type": "Feature",
  "properties": {
    "name": "KhÄmgaon",
    "country": "IN",
    "subdivision": "16",
    "timezone": "Asia/Kolkata"
  },
  "geometry": {
    "type": "Point",
    "coordinates": [
      76.56827,
      20.70738
    ]
  }
}