{
  "type": "Feature",
  "properties": {
    "name": "LÄsalgaon",
    "country": "IN",
    "subdivision": "16",
    "timezone": "Asia/Kolkata"
  },
  "geometry": {
    "type": "Point",
    "coordinates": [
      74.23946,
      20.1427
    ]
  }
}