{
  "type": "Feature",
  "properties": {
    "name": "Latur",
    "country": "IN",
    "subdivision": "16",
    "timezone": "Asia/Kolkata"
  },
  "geometry": {
    "type": "Point",
    "coordinates": [
      76.56784,
      18.39721
    ]
  }
}