{
  "type": "Feature",
  "properties": {
    "name": "Maindargi",
    "country": "IN",
    "subdivision": "16",
    "timezone": "Asia/Kolkata"
  },
  "geometry": {
    "type": "Point",
    "coordinates": [
      76.2932,
      17.45739
    ]
  }
}