{
  "type": "Feature",
  "properties": {
    "name": "MÄlegaon",
    "country": "IN",
    "subdivision": "16",
    "timezone": "Asia/Kolkata"
  },
  "geometry": {
    "type": "Point",
    "coordinates": [
      74.53462,
      20.54966
    ]
  }
}