{
  "type": "Feature",
  "properties": {
    "name": "Mansar",
    "country": "IN",
    "subdivision": "16",
    "timezone": "Asia/Kolkata"
  },
  "geometry": {
    "type": "Point",
    "coordinates": [
      79.2635,
      21.39602
    ]
  }
}