{
  "type": "Feature",
  "properties": {
    "name": "Mhāsvād",
    "country": "IN",
    "subdivision": "16",
    "timezone": "Asia/Kolkata"
  },
  "geometry": {
    "type": "Point",
    "coordinates": [
      74.78773,
      17.63359
    ]
  }
}