{
  "type": "Feature",
  "properties": {
    "name": "Neral",
    "country": "IN",
    "subdivision": "16",
    "timezone": "Asia/Kolkata"
  },
  "geometry": {
    "type": "Point",
    "coordinates": [
      73.31688,
      19.02475
    ]
  }
}