{
  "type": "Feature",
  "properties": {
    "name": "Paithan",
    "country": "IN",
    "subdivision": "16",
    "timezone": "Asia/Kolkata"
  },
  "geometry": {
    "type": "Point",
    "coordinates": [
      75.38558,
      19.47506
    ]
  }
}