{
  "type": "Feature",
  "properties": {
    "name": "Parli VaijnÄth",
    "country": "IN",
    "subdivision": "16",
    "timezone": "Asia/Kolkata"
  },
  "geometry": {
    "type": "Point",
    "coordinates": [
      76.53163,
      18.85057
    ]
  }
}