{
  "type": "Feature",
  "properties": {
    "name": "Pimpri",
    "country": "IN",
    "subdivision": "16",
    "timezone": "Asia/Kolkata"
  },
  "geometry": {
    "type": "Point",
    "coordinates": [
      73.80696,
      18.62292
    ]
  }
}