{
  "type": "Feature",
  "properties": {
    "name": "Powai",
    "country": "IN",
    "subdivision": "16",
    "timezone": "Asia/Kolkata"
  },
  "geometry": {
    "type": "Point",
    "coordinates": [
      72.90471,
      19.1164
    ]
  }
}