{
  "type": "Feature",
  "properties": {
    "name": "Pusad",
    "country": "IN",
    "subdivision": "16",
    "timezone": "Asia/Kolkata"
  },
  "geometry": {
    "type": "Point",
    "coordinates": [
      77.57838,
      19.91274
    ]
  }
}