{
  "type": "Feature",
  "properties": {
    "name": "Rājāpur",
    "country": "IN",
    "subdivision": "16",
    "timezone": "Asia/Kolkata"
  },
  "geometry": {
    "type": "Point",
    "coordinates": [
      73.51701,
      16.65679
    ]
  }
}