{
  "type": "Feature",
  "properties": {
    "name": "Sindi",
    "country": "IN",
    "subdivision": "16",
    "timezone": "Asia/Kolkata"
  },
  "geometry": {
    "type": "Point",
    "coordinates": [
      78.88752,
      20.80509
    ]
  }
}