{
  "type": "Feature",
  "properties": {
    "name": "SolÄpur",
    "country": "IN",
    "subdivision": "16",
    "timezone": "Asia/Kolkata"
  },
  "geometry": {
    "type": "Point",
    "coordinates": [
      75.91044,
      17.67152
    ]
  }
}