{
  "type": "Feature",
  "properties": {
    "name": "Taloda",
    "country": "IN",
    "subdivision": "16",
    "timezone": "Asia/Kolkata"
  },
  "geometry": {
    "type": "Point",
    "coordinates": [
      74.21238,
      21.56128
    ]
  }
}