{
  "type": "Feature",
  "properties": {
    "name": "Trimbak",
    "country": "IN",
    "subdivision": "16",
    "timezone": "Asia/Kolkata"
  },
  "geometry": {
    "type": "Point",
    "coordinates": [
      73.52907,
      19.93268
    ]
  }
}