{
  "type": "Feature",
  "properties": {
    "name": "TuljÄpur",
    "country": "IN",
    "subdivision": "16",
    "timezone": "Asia/Kolkata"
  },
  "geometry": {
    "type": "Point",
    "coordinates": [
      76.07011,
      18.00804
    ]
  }
}