{
  "type": "Feature",
  "properties": {
    "name": "Umred",
    "country": "IN",
    "subdivision": "16",
    "timezone": "Asia/Kolkata"
  },
  "geometry": {
    "type": "Point",
    "coordinates": [
      79.32466,
      20.85396
    ]
  }
}