{
  "type": "Feature",
  "properties": {
    "name": "VaijÄpur",
    "country": "IN",
    "subdivision": "16",
    "timezone": "Asia/Kolkata"
  },
  "geometry": {
    "type": "Point",
    "coordinates": [
      74.7275,
      19.92672
    ]
  }
}