{
  "type": "Feature",
  "properties": {
    "name": "Wani",
    "country": "IN",
    "subdivision": "16",
    "timezone": "Asia/Kolkata"
  },
  "geometry": {
    "type": "Point",
    "coordinates": [
      78.95313,
      20.05507
    ]
  }
}