{
  "type": "Feature",
  "properties": {
    "name": "Warora",
    "country": "IN",
    "subdivision": "16",
    "timezone": "Asia/Kolkata"
  },
  "geometry": {
    "type": "Point",
    "coordinates": [
      79.00277,
      20.22885
    ]
  }
}