{
  "type": "Feature",
  "properties": {
    "name": "Işıklar",
    "country": "TR",
    "subdivision": "63",
    "timezone": "Europe/Istanbul"
  },
  "geometry": {
    "type": "Point",
    "coordinates": [
      40.12639,
      36.99417
    ]
  }
}