{
  "type": "Feature",
  "properties": {
    "name": "Bada Barabīl",
    "country": "IN",
    "subdivision": "21",
    "timezone": "Asia/Kolkata"
  },
  "geometry": {
    "type": "Point",
    "coordinates": [
      85.38684,
      22.11186
    ]
  }
}