{
  "type": "Feature",
  "properties": {
    "name": "Balāngīr",
    "country": "IN",
    "subdivision": "21",
    "timezone": "Asia/Kolkata"
  },
  "geometry": {
    "type": "Point",
    "coordinates": [
      83.49029,
      20.70419
    ]
  }
}