{
  "type": "Feature",
  "properties": {
    "name": "BÄlugaon",
    "country": "IN",
    "subdivision": "21",
    "timezone": "Asia/Kolkata"
  },
  "geometry": {
    "type": "Point",
    "coordinates": [
      85.11327,
      20.17838
    ]
  }
}