{
  "type": "Feature",
  "properties": {
    "name": "Bargarh",
    "country": "IN",
    "subdivision": "21",
    "timezone": "Asia/Kolkata"
  },
  "geometry": {
    "type": "Point",
    "coordinates": [
      83.61905,
      21.33348
    ]
  }
}