{
  "type": "Feature",
  "properties": {
    "name": "Buguda",
    "country": "IN",
    "subdivision": "21",
    "timezone": "Asia/Kolkata"
  },
  "geometry": {
    "type": "Point",
    "coordinates": [
      84.79084,
      19.80806
    ]
  }
}