{
  "type": "Feature",
  "properties": {
    "name": "Chikitigarh",
    "country": "IN",
    "subdivision": "21",
    "timezone": "Asia/Kolkata"
  },
  "geometry": {
    "type": "Point",
    "coordinates": [
      84.6145,
      19.20233
    ]
  }
}