{
  "type": "Feature",
  "properties": {
    "name": "Chittarkonda",
    "country": "IN",
    "subdivision": "21",
    "timezone": "Asia/Kolkata"
  },
  "geometry": {
    "type": "Point",
    "coordinates": [
      82.1089,
      18.12533
    ]
  }
}