{
  "type": "Feature",
  "properties": {
    "name": "Padampur",
    "country": "IN",
    "subdivision": "21",
    "timezone": "Asia/Kolkata"
  },
  "geometry": {
    "type": "Point",
    "coordinates": [
      83.06325,
      20.99932
    ]
  }
}