{
  "type": "Feature",
  "properties": {
    "name": "PhulbÄni",
    "country": "IN",
    "subdivision": "21",
    "timezone": "Asia/Kolkata"
  },
  "geometry": {
    "type": "Point",
    "coordinates": [
      84.23063,
      20.48101
    ]
  }
}