{
  "type": "Feature",
  "properties": {
    "name": "Sambalpur",
    "country": "IN",
    "subdivision": "21",
    "timezone": "Asia/Kolkata"
  },
  "geometry": {
    "type": "Point",
    "coordinates": [
      83.97573,
      21.46527
    ]
  }
}