{
  "type": "Feature",
  "properties": {
    "name": "Sonepur",
    "country": "IN",
    "subdivision": "21",
    "timezone": "Asia/Kolkata"
  },
  "geometry": {
    "type": "Point",
    "coordinates": [
      83.91667,
      20.83333
    ]
  }
}