{
  "type": "Feature",
  "properties": {
    "name": "TitlÄgarh",
    "country": "IN",
    "subdivision": "21",
    "timezone": "Asia/Kolkata"
  },
  "geometry": {
    "type": "Point",
    "coordinates": [
      83.15233,
      20.28961
    ]
  }
}