{
  "type": "Feature",
  "properties": {
    "name": "Cổ Lóa",
    "country": "VN",
    "subdivision": "44",
    "timezone": "Asia/Bangkok"
  },
  "geometry": {
    "type": "Point",
    "coordinates": [
      105.86667,
      21.11667
    ]
  }
}