{
  "type": "Feature",
  "properties": {
    "name": "Agbannawag",
    "country": "PH",
    "subdivision": "15",
    "timezone": "Asia/Manila"
  },
  "geometry": {
    "type": "Point",
    "coordinates": [
      121.5478,
      17.37641
    ]
  }
}