{
  "type": "Feature",
  "properties": {
    "name": "Baguinge",
    "country": "PH",
    "subdivision": "15",
    "timezone": "Asia/Manila"
  },
  "geometry": {
    "type": "Point",
    "coordinates": [
      121.10624,
      16.77767
    ]
  }
}