{
  "type": "Feature",
  "properties": {
    "name": "Baguio",
    "country": "PH",
    "subdivision": "15",
    "timezone": "Asia/Manila"
  },
  "geometry": {
    "type": "Point",
    "coordinates": [
      120.59306,
      16.41639
    ]
  }
}