{
  "type": "Feature",
  "properties": {
    "name": "Banaue",
    "country": "PH",
    "subdivision": "15",
    "timezone": "Asia/Manila"
  },
  "geometry": {
    "type": "Point",
    "coordinates": [
      121.06184,
      16.91356
    ]
  }
}