{
  "type": "Feature",
  "properties": {
    "name": "Bangao",
    "country": "PH",
    "subdivision": "15",
    "timezone": "Asia/Manila"
  },
  "geometry": {
    "type": "Point",
    "coordinates": [
      120.8404,
      16.8211
    ]
  }
}