{
  "type": "Feature",
  "properties": {
    "name": "Bantay",
    "country": "PH",
    "subdivision": "15",
    "timezone": "Asia/Manila"
  },
  "geometry": {
    "type": "Point",
    "coordinates": [
      120.75775,
      17.43793
    ]
  }
}