{
  "type": "Feature",
  "properties": {
    "name": "Besao",
    "country": "PH",
    "subdivision": "15",
    "timezone": "Asia/Manila"
  },
  "geometry": {
    "type": "Point",
    "coordinates": [
      120.8579,
      17.095
    ]
  }
}