{
  "type": "Feature",
  "properties": {
    "name": "Itogon",
    "country": "PH",
    "subdivision": "15",
    "timezone": "Asia/Manila"
  },
  "geometry": {
    "type": "Point",
    "coordinates": [
      120.67694,
      16.36389
    ]
  }
}