{
  "type": "Feature",
  "properties": {
    "name": "Bulungu",
    "country": "CD",
    "subdivision": "20",
    "timezone": "Africa/Kinshasa"
  },
  "geometry": {
    "type": "Point",
    "coordinates": [
      18.60364,
      -4.54437
    ]
  }
}