{
  "type": "Feature",
  "properties": {
    "name": "Kikwit",
    "country": "CD",
    "subdivision": "20",
    "timezone": "Africa/Kinshasa"
  },
  "geometry": {
    "type": "Point",
    "coordinates": [
      18.81619,
      -5.04098
    ]
  }
}