{
  "type": "Feature",
  "properties": {
    "name": "Mangai",
    "country": "CD",
    "subdivision": "20",
    "timezone": "Africa/Kinshasa"
  },
  "geometry": {
    "type": "Point",
    "coordinates": [
      19.53385,
      -4.02328
    ]
  }
}