{
  "type": "Feature",
  "properties": {
    "name": "Jadder Cemetery",
    "country": "YE",
    "subdivision": "26",
    "timezone": "Asia/Aden"
  },
  "geometry": {
    "type": "Point",
    "coordinates": [
      44.17787,
      15.467
    ]
  }
}