{
  "type": "Feature",
  "properties": {
    "name": "Sanaa",
    "country": "YE",
    "subdivision": "26",
    "timezone": "Asia/Aden"
  },
  "geometry": {
    "type": "Point",
    "coordinates": [
      44.20667,
      15.35472
    ]
  }
}