{
  "type": "Feature",
  "properties": {
    "name": "Xuddur",
    "country": "SO",
    "subdivision": "01",
    "timezone": "Africa/Mogadishu"
  },
  "geometry": {
    "type": "Point",
    "coordinates": [
      43.88945,
      4.12129
    ]
  }
}