{
  "type": "Feature",
  "properties": {
    "name": "Yeed",
    "country": "SO",
    "subdivision": "01",
    "timezone": "Africa/Mogadishu"
  },
  "geometry": {
    "type": "Point",
    "coordinates": [
      43.03333,
      4.55
    ]
  }
}