{
  "type": "Feature",
  "properties": {
    "name": "Çakırlı",
    "country": "TR",
    "subdivision": "16",
    "timezone": "Europe/Istanbul"
  },
  "geometry": {
    "type": "Point",
    "coordinates": [
      29.45222,
      40.51806
    ]
  }
}