{
  "type": "Feature",
  "properties": {
    "name": "Çakırca",
    "country": "TR",
    "subdivision": "16",
    "timezone": "Europe/Istanbul"
  },
  "geometry": {
    "type": "Point",
    "coordinates": [
      29.66333,
      40.47056
    ]
  }
}