{
  "type": "Feature",
  "properties": {
    "name": "Cerrah",
    "country": "TR",
    "subdivision": "16",
    "timezone": "Europe/Istanbul"
  },
  "geometry": {
    "type": "Point",
    "coordinates": [
      29.44661,
      40.07124
    ]
  }
}