{
  "type": "Feature",
  "properties": {
    "name": "Elbeyli",
    "country": "TR",
    "subdivision": "16",
    "timezone": "Europe/Istanbul"
  },
  "geometry": {
    "type": "Point",
    "coordinates": [
      29.72472,
      40.48611
    ]
  }
}