{
  "type": "Feature",
  "properties": {
    "name": "Orhangazi",
    "country": "TR",
    "subdivision": "16",
    "timezone": "Europe/Istanbul"
  },
  "geometry": {
    "type": "Point",
    "coordinates": [
      29.30889,
      40.48917
    ]
  }
}