{
  "type": "Feature",
  "properties": {
    "name": "Piltene",
    "country": "LV",
    "subdivision": "33",
    "timezone": "Europe/Riga"
  },
  "geometry": {
    "type": "Point",
    "coordinates": [
      21.67439,
      57.22426
    ]
  }
}