{
  "type": "Feature",
  "properties": {
    "name": "Dazhong",
    "country": "CN",
    "subdivision": "04",
    "timezone": "Asia/Shanghai"
  },
  "geometry": {
    "type": "Point",
    "coordinates": [
      120.4578,
      33.19973
    ]
  }
}