{
  "type": "Feature",
  "properties": {
    "name": "Haizhou",
    "country": "CN",
    "subdivision": "04",
    "timezone": "Asia/Shanghai"
  },
  "geometry": {
    "type": "Point",
    "coordinates": [
      119.12889,
      34.58167
    ]
  }
}