{
  "type": "Feature",
  "properties": {
    "name": "Qinnan",
    "country": "CN",
    "subdivision": "04",
    "timezone": "Asia/Shanghai"
  },
  "geometry": {
    "type": "Point",
    "coordinates": [
      119.91333,
      33.25306
    ]
  }
}