{
  "type": "Feature",
  "properties": {
    "name": "Taixing",
    "country": "CN",
    "subdivision": "04",
    "timezone": "Asia/Shanghai"
  },
  "geometry": {
    "type": "Point",
    "coordinates": [
      120.01361,
      32.16667
    ]
  }
}