{
  "type": "Feature",
  "properties": {
    "name": "Xiannü",
    "country": "CN",
    "subdivision": "04",
    "timezone": "Asia/Shanghai"
  },
  "geometry": {
    "type": "Point",
    "coordinates": [
      119.56048,
      32.42806
    ]
  }
}