{
  "type": "Feature",
  "properties": {
    "name": "Yangzhou",
    "country": "CN",
    "subdivision": "04",
    "timezone": "Asia/Shanghai"
  },
  "geometry": {
    "type": "Point",
    "coordinates": [
      119.43583,
      32.39722
    ]
  }
}