{
  "type": "Feature",
  "properties": {
    "name": "Fakel",
    "country": "RU",
    "subdivision": "80",
    "timezone": "Europe/Samara"
  },
  "geometry": {
    "type": "Point",
    "coordinates": [
      53.0251,
      57.631
    ]
  }
}