{
  "type": "Feature",
  "properties": {
    "name": "Karakulino",
    "country": "RU",
    "subdivision": "80",
    "timezone": "Europe/Samara"
  },
  "geometry": {
    "type": "Point",
    "coordinates": [
      53.70669,
      56.012
    ]
  }
}