{
  "type": "Feature",
  "properties": {
    "name": "Malaya Purga",
    "country": "RU",
    "subdivision": "80",
    "timezone": "Europe/Samara"
  },
  "geometry": {
    "type": "Point",
    "coordinates": [
      53.00434,
      56.55666
    ]
  }
}