{
  "type": "Feature",
  "properties": {
    "name": "Sharkan",
    "country": "RU",
    "subdivision": "80",
    "timezone": "Europe/Samara"
  },
  "geometry": {
    "type": "Point",
    "coordinates": [
      53.87122,
      57.29885
    ]
  }
}