{
  "type": "Feature",
  "properties": {
    "name": "Lagunillas",
    "country": "VE",
    "subdivision": "23",
    "timezone": "America/Caracas"
  },
  "geometry": {
    "type": "Point",
    "coordinates": [
      -71.25946,
      10.13008
    ]
  }
}