{
  "type": "Feature",
  "properties": {
    "name": "Barrière",
    "country": "CA",
    "subdivision": "02",
    "timezone": "America/Vancouver"
  },
  "geometry": {
    "type": "Point",
    "coordinates": [
      -120.1192,
      51.18308
    ]
  }
}