{
  "type": "Feature",
  "properties": {
    "name": "Ladysmith",
    "country": "CA",
    "subdivision": "02",
    "timezone": "America/Vancouver"
  },
  "geometry": {
    "type": "Point",
    "coordinates": [
      -123.81699,
      48.99016
    ]
  }
}