{
  "type": "Feature",
  "properties": {
    "name": "Nanaimo",
    "country": "CA",
    "subdivision": "02",
    "timezone": "America/Vancouver"
  },
  "geometry": {
    "type": "Point",
    "coordinates": [
      -123.94003,
      49.16638
    ]
  }
}