{
  "type": "Feature",
  "properties": {
    "name": "Princeton",
    "country": "CA",
    "subdivision": "02",
    "timezone": "America/Vancouver"
  },
  "geometry": {
    "type": "Point",
    "coordinates": [
      -120.51076,
      49.45802
    ]
  }
}