{
  "type": "Feature",
  "properties": {
    "name": "Richmond",
    "country": "CA",
    "subdivision": "02",
    "timezone": "America/Vancouver"
  },
  "geometry": {
    "type": "Point",
    "coordinates": [
      -123.13683,
      49.17003
    ]
  }
}