{
  "type": "Feature",
  "properties": {
    "name": "Sicamous",
    "country": "CA",
    "subdivision": "02",
    "timezone": "America/Vancouver"
  },
  "geometry": {
    "type": "Point",
    "coordinates": [
      -118.98565,
      50.83312
    ]
  }
}