{
  "type": "Feature",
  "properties": {
    "name": "Six Mile",
    "country": "CA",
    "subdivision": "02",
    "timezone": "America/Vancouver"
  },
  "geometry": {
    "type": "Point",
    "coordinates": [
      -123.46088,
      48.45767
    ]
  }
}