{
  "type": "Feature",
  "properties": {
    "name": "Summerland",
    "country": "CA",
    "subdivision": "02",
    "timezone": "America/Vancouver"
  },
  "geometry": {
    "type": "Point",
    "coordinates": [
      -119.66911,
      49.59977
    ]
  }
}