{
  "type": "Feature",
  "properties": {
    "name": "West Vancouver",
    "country": "CA",
    "subdivision": "02",
    "timezone": "America/Vancouver"
  },
  "geometry": {
    "type": "Point",
    "coordinates": [
      -123.16652,
      49.36672
    ]
  }
}