{
  "type": "Feature",
  "properties": {
    "name": "Fiditi",
    "country": "NG",
    "subdivision": "32",
    "timezone": "Africa/Lagos"
  },
  "geometry": {
    "type": "Point",
    "coordinates": [
      3.91722,
      7.71361
    ]
  }
}