{
  "type": "Feature",
  "properties": {
    "name": "Lalupon",
    "country": "NG",
    "subdivision": "32",
    "timezone": "Africa/Lagos"
  },
  "geometry": {
    "type": "Point",
    "coordinates": [
      4.06594,
      7.46791
    ]
  }
}