{
  "type": "Feature",
  "properties": {
    "name": "Orita-Eruwa",
    "country": "NG",
    "subdivision": "32",
    "timezone": "Africa/Lagos"
  },
  "geometry": {
    "type": "Point",
    "coordinates": [
      3.44107,
      7.55632
    ]
  }
}