{
  "type": "Feature",
  "properties": {
    "name": "Mae Tha",
    "country": "TH",
    "subdivision": "05",
    "timezone": "Asia/Bangkok"
  },
  "geometry": {
    "type": "Point",
    "coordinates": [
      99.14026,
      18.46456
    ]
  }
}