{
  "type": "Feature",
  "properties": {
    "name": "Oracabessa",
    "country": "JM",
    "subdivision": "13",
    "timezone": "America/Jamaica"
  },
  "geometry": {
    "type": "Point",
    "coordinates": [
      -76.94641,
      18.40319
    ]
  }
}