{
  "type": "Feature",
  "properties": {
    "name": "Port Maria",
    "country": "JM",
    "subdivision": "13",
    "timezone": "America/Jamaica"
  },
  "geometry": {
    "type": "Point",
    "coordinates": [
      -76.88946,
      18.36849
    ]
  }
}