{
  "type": "Feature",
  "properties": {
    "name": "Arroyo Seco",
    "country": "AR",
    "subdivision": "21",
    "timezone": "America/Argentina/Cordoba"
  },
  "geometry": {
    "type": "Point",
    "coordinates": [
      -60.50863,
      -33.15489
    ]
  }
}