{
  "type": "Feature",
  "properties": {
    "name": "Esperanza",
    "country": "AR",
    "subdivision": "21",
    "timezone": "America/Argentina/Cordoba"
  },
  "geometry": {
    "type": "Point",
    "coordinates": [
      -60.93173,
      -31.4488
    ]
  }
}