{
  "type": "Feature",
  "properties": {
    "name": "Rufino",
    "country": "AR",
    "subdivision": "21",
    "timezone": "America/Argentina/Cordoba"
  },
  "geometry": {
    "type": "Point",
    "coordinates": [
      -62.71262,
      -34.26827
    ]
  }
}