{
  "type": "Feature",
  "properties": {
    "name": "San Javier",
    "country": "AR",
    "subdivision": "21",
    "timezone": "America/Argentina/Cordoba"
  },
  "geometry": {
    "type": "Point",
    "coordinates": [
      -59.9317,
      -30.57781
    ]
  }
}