{
  "type": "Feature",
  "properties": {
    "name": "San Cristóbal",
    "country": "AR",
    "subdivision": "21",
    "timezone": "America/Argentina/Cordoba"
  },
  "geometry": {
    "type": "Point",
    "coordinates": [
      -61.23724,
      -30.31053
    ]
  }
}