{
  "type": "Feature",
  "properties": {
    "name": "Santa Fe",
    "country": "AR",
    "subdivision": "21",
    "timezone": "America/Argentina/Cordoba"
  },
  "geometry": {
    "type": "Point",
    "coordinates": [
      -60.70868,
      -31.64881
    ]
  }
}