{
  "type": "Feature",
  "properties": {
    "name": "Santo Tomé",
    "country": "AR",
    "subdivision": "21",
    "timezone": "America/Argentina/Cordoba"
  },
  "geometry": {
    "type": "Point",
    "coordinates": [
      -60.7653,
      -31.66274
    ]
  }
}