{
  "type": "Feature",
  "properties": {
    "name": "Thap Khlo",
    "country": "TH",
    "subdivision": "13",
    "timezone": "Asia/Bangkok"
  },
  "geometry": {
    "type": "Point",
    "coordinates": [
      100.59656,
      16.16003
    ]
  }
}