{
  "type": "Feature",
  "properties": {
    "name": "Nyaungdon",
    "country": "MM",
    "subdivision": "03",
    "timezone": "Asia/Yangon"
  },
  "geometry": {
    "type": "Point",
    "coordinates": [
      95.63957,
      17.04459
    ]
  }
}