{
  "type": "Feature",
  "properties": {
    "name": "Pyapon",
    "country": "MM",
    "subdivision": "03",
    "timezone": "Asia/Yangon"
  },
  "geometry": {
    "type": "Point",
    "coordinates": [
      95.67882,
      16.28543
    ]
  }
}