{
  "type": "Feature",
  "properties": {
    "name": "Älvsbyn",
    "country": "SE",
    "subdivision": "14",
    "timezone": "Europe/Stockholm"
  },
  "geometry": {
    "type": "Point",
    "coordinates": [
      21.00162,
      65.67624
    ]
  }
}