{
  "type": "Feature",
  "properties": {
    "name": "Pajala",
    "country": "SE",
    "subdivision": "14",
    "timezone": "Europe/Stockholm"
  },
  "geometry": {
    "type": "Point",
    "coordinates": [
      23.36607,
      67.21284
    ]
  }
}