{
  "type": "Feature",
  "properties": {
    "name": "Rolfs",
    "country": "SE",
    "subdivision": "14",
    "timezone": "Europe/Stockholm"
  },
  "geometry": {
    "type": "Point",
    "coordinates": [
      23.11667,
      65.85
    ]
  }
}