{
  "type": "Feature",
  "properties": {
    "name": "Ali-Yurt",
    "country": "RU",
    "subdivision": "19",
    "timezone": "Europe/Moscow"
  },
  "geometry": {
    "type": "Point",
    "coordinates": [
      44.8525,
      43.1425
    ]
  }
}