{
  "type": "Feature",
  "properties": {
    "name": "Alkhan-Churt",
    "country": "RU",
    "subdivision": "19",
    "timezone": "Europe/Moscow"
  },
  "geometry": {
    "type": "Point",
    "coordinates": [
      44.78694,
      43.35194
    ]
  }
}