{
  "type": "Feature",
  "properties": {
    "name": "Dalakovo",
    "country": "RU",
    "subdivision": "19",
    "timezone": "Europe/Moscow"
  },
  "geometry": {
    "type": "Point",
    "coordinates": [
      44.58964,
      43.23759
    ]
  }
}