{
  "type": "Feature",
  "properties": {
    "name": "Malgobek",
    "country": "RU",
    "subdivision": "19",
    "timezone": "Europe/Moscow"
  },
  "geometry": {
    "type": "Point",
    "coordinates": [
      44.58821,
      43.51118
    ]
  }
}