{
  "type": "Feature",
  "properties": {
    "name": "Nesterovskaya",
    "country": "RU",
    "subdivision": "19",
    "timezone": "Europe/Moscow"
  },
  "geometry": {
    "type": "Point",
    "coordinates": [
      45.05028,
      43.23861
    ]
  }
}