{
  "type": "Feature",
  "properties": {
    "name": "Sagopshi",
    "country": "RU",
    "subdivision": "19",
    "timezone": "Europe/Moscow"
  },
  "geometry": {
    "type": "Point",
    "coordinates": [
      44.59063,
      43.48515
    ]
  }
}