{
  "type": "Feature",
  "properties": {
    "name": "Calvillo",
    "country": "MX",
    "subdivision": "01",
    "timezone": "America/Mexico_City"
  },
  "geometry": {
    "type": "Point",
    "coordinates": [
      -102.71849,
      21.84583
    ]
  }
}