{
  "type": "Feature",
  "properties": {
    "name": "Carboneras",
    "country": "MX",
    "subdivision": "01",
    "timezone": "America/Mexico_City"
  },
  "geometry": {
    "type": "Point",
    "coordinates": [
      -102.24601,
      22.18311
    ]
  }
}