{
  "type": "Feature",
  "properties": {
    "name": "Corral de Barrancos",
    "country": "MX",
    "subdivision": "01",
    "timezone": "America/Mexico_City"
  },
  "geometry": {
    "type": "Point",
    "coordinates": [
      -102.33222,
      21.95028
    ]
  }
}