{
  "type": "Feature",
  "properties": {
    "name": "El Bajío",
    "country": "MX",
    "subdivision": "01",
    "timezone": "America/Mexico_City"
  },
  "geometry": {
    "type": "Point",
    "coordinates": [
      -102.30825,
      22.24558
    ]
  }
}