{
  "type": "Feature",
  "properties": {
    "name": "Jarillas",
    "country": "MX",
    "subdivision": "01",
    "timezone": "America/Mexico_City"
  },
  "geometry": {
    "type": "Point",
    "coordinates": [
      -102.06333,
      22.29611
    ]
  }
}