{
  "type": "Feature",
  "properties": {
    "name": "Las Ánimas",
    "country": "MX",
    "subdivision": "01",
    "timezone": "America/Mexico_City"
  },
  "geometry": {
    "type": "Point",
    "coordinates": [
      -102.26684,
      22.09057
    ]
  }
}