{
  "type": "Feature",
  "properties": {
    "name": "Los Arquitos",
    "country": "MX",
    "subdivision": "01",
    "timezone": "America/Mexico_City"
  },
  "geometry": {
    "type": "Point",
    "coordinates": [
      -102.38554,
      21.92299
    ]
  }
}