{
  "type": "Feature",
  "properties": {
    "name": "Pabellón de Arteaga",
    "country": "MX",
    "subdivision": "01",
    "timezone": "America/Mexico_City"
  },
  "geometry": {
    "type": "Point",
    "coordinates": [
      -102.2769,
      22.14642
    ]
  }
}