{
  "type": "Feature",
  "properties": {
    "name": "Pilotos",
    "country": "MX",
    "subdivision": "01",
    "timezone": "America/Mexico_City"
  },
  "geometry": {
    "type": "Point",
    "coordinates": [
      -101.95917,
      22.03722
    ]
  }
}