{
  "type": "Feature",
  "properties": {
    "name": "San Antonio de Peñuelas",
    "country": "MX",
    "subdivision": "01",
    "timezone": "America/Mexico_City"
  },
  "geometry": {
    "type": "Point",
    "coordinates": [
      -102.3001,
      21.67471
    ]
  }
}