{
  "type": "Feature",
  "properties": {
    "name": "Sansare",
    "country": "GT",
    "subdivision": "05",
    "timezone": "America/Guatemala"
  },
  "geometry": {
    "type": "Point",
    "coordinates": [
      -90.11615,
      14.74572
    ]
  }
}