{
  "type": "Feature",
  "properties": {
    "name": "Carberry",
    "country": "CA",
    "subdivision": "03",
    "timezone": "America/Winnipeg"
  },
  "geometry": {
    "type": "Point",
    "coordinates": [
      -99.36021,
      49.86893
    ]
  }
}