{
  "type": "Feature",
  "properties": {
    "name": "Headingley",
    "country": "CA",
    "subdivision": "03",
    "timezone": "America/Winnipeg"
  },
  "geometry": {
    "type": "Point",
    "coordinates": [
      -97.40896,
      49.8753
    ]
  }
}