{
  "type": "Feature",
  "properties": {
    "name": "The Pas",
    "country": "CA",
    "subdivision": "03",
    "timezone": "America/Winnipeg"
  },
  "geometry": {
    "type": "Point",
    "coordinates": [
      -101.24488,
      53.82159
    ]
  }
}