{
  "type": "Feature",
  "properties": {
    "name": "Winnipeg",
    "country": "CA",
    "subdivision": "03",
    "timezone": "America/Winnipeg"
  },
  "geometry": {
    "type": "Point",
    "coordinates": [
      -97.14704,
      49.8844
    ]
  }
}