{
  "type": "Feature",
  "properties": {
    "name": "Ginir",
    "country": "ET",
    "subdivision": "51",
    "timezone": "Africa/Addis_Ababa"
  },
  "geometry": {
    "type": "Point",
    "coordinates": [
      40.71083,
      7.13952
    ]
  }
}