{
  "type": "Feature",
  "properties": {
    "name": "Kibre Mengist",
    "country": "ET",
    "subdivision": "51",
    "timezone": "Africa/Addis_Ababa"
  },
  "geometry": {
    "type": "Point",
    "coordinates": [
      38.98333,
      5.88333
    ]
  }
}