{
  "type": "Feature",
  "properties": {
    "name": "Dombarovskiy",
    "country": "RU",
    "subdivision": "55",
    "timezone": "Asia/Yekaterinburg"
  },
  "geometry": {
    "type": "Point",
    "coordinates": [
      59.5386,
      50.7587
    ]
  }
}