{
  "type": "Feature",
  "properties": {
    "name": "Krasnyy Kommunar",
    "country": "RU",
    "subdivision": "55",
    "timezone": "Asia/Yekaterinburg"
  },
  "geometry": {
    "type": "Point",
    "coordinates": [
      55.3668,
      51.96436
    ]
  }
}