{
  "type": "Feature",
  "properties": {
    "name": "Shil’da",
    "country": "RU",
    "subdivision": "55",
    "timezone": "Asia/Yekaterinburg"
  },
  "geometry": {
    "type": "Point",
    "coordinates": [
      59.7744,
      51.8143
    ]
  }
}