{
  "type": "Feature",
  "properties": {
    "name": "Totskoye",
    "country": "RU",
    "subdivision": "55",
    "timezone": "Asia/Yekaterinburg"
  },
  "geometry": {
    "type": "Point",
    "coordinates": [
      52.76228,
      52.52478
    ]
  }
}