{
  "type": "Feature",
  "properties": {
    "name": "Tyul’gan",
    "country": "RU",
    "subdivision": "55",
    "timezone": "Asia/Yekaterinburg"
  },
  "geometry": {
    "type": "Point",
    "coordinates": [
      56.16604,
      52.34049
    ]
  }
}