{
  "type": "Feature",
  "properties": {
    "name": "Abdissenbosch",
    "country": "NL",
    "subdivision": "05",
    "timezone": "Europe/Amsterdam"
  },
  "geometry": {
    "type": "Point",
    "coordinates": [
      6.03333,
      50.91667
    ]
  }
}