{
  "type": "Feature",
  "properties": {
    "name": "Berg",
    "country": "NL",
    "subdivision": "05",
    "timezone": "Europe/Amsterdam"
  },
  "geometry": {
    "type": "Point",
    "coordinates": [
      5.77083,
      51.00417
    ]
  }
}