{
  "type": "Feature",
  "properties": {
    "name": "Borgharen",
    "country": "NL",
    "subdivision": "05",
    "timezone": "Europe/Amsterdam"
  },
  "geometry": {
    "type": "Point",
    "coordinates": [
      5.6875,
      50.8775
    ]
  }
}