{
  "type": "Feature",
  "properties": {
    "name": "Brachterbeek",
    "country": "NL",
    "subdivision": "05",
    "timezone": "Europe/Amsterdam"
  },
  "geometry": {
    "type": "Point",
    "coordinates": [
      5.90446,
      51.14694
    ]
  }
}