{
  "type": "Feature",
  "properties": {
    "name": "Bunde",
    "country": "NL",
    "subdivision": "05",
    "timezone": "Europe/Amsterdam"
  },
  "geometry": {
    "type": "Point",
    "coordinates": [
      5.73194,
      50.89667
    ]
  }
}