{
  "type": "Feature",
  "properties": {
    "name": "Eijsden",
    "country": "NL",
    "subdivision": "05",
    "timezone": "Europe/Amsterdam"
  },
  "geometry": {
    "type": "Point",
    "coordinates": [
      5.7177,
      50.78
    ]
  }
}