{
  "type": "Feature",
  "properties": {
    "name": "Grevenbicht",
    "country": "NL",
    "subdivision": "05",
    "timezone": "Europe/Amsterdam"
  },
  "geometry": {
    "type": "Point",
    "coordinates": [
      5.775,
      51.03833
    ]
  }
}