{
  "type": "Feature",
  "properties": {
    "name": "Haanrade",
    "country": "NL",
    "subdivision": "05",
    "timezone": "Europe/Amsterdam"
  },
  "geometry": {
    "type": "Point",
    "coordinates": [
      6.07411,
      50.87981
    ]
  }
}