{
  "type": "Feature",
  "properties": {
    "name": "Heythuysen",
    "country": "NL",
    "subdivision": "05",
    "timezone": "Europe/Amsterdam"
  },
  "geometry": {
    "type": "Point",
    "coordinates": [
      5.89861,
      51.25
    ]
  }
}