{
  "type": "Feature",
  "properties": {
    "name": "Kelpen-Oler",
    "country": "NL",
    "subdivision": "05",
    "timezone": "Europe/Amsterdam"
  },
  "geometry": {
    "type": "Point",
    "coordinates": [
      5.82602,
      51.21817
    ]
  }
}