{
  "type": "Feature",
  "properties": {
    "name": "Kerensheide",
    "country": "NL",
    "subdivision": "05",
    "timezone": "Europe/Amsterdam"
  },
  "geometry": {
    "type": "Point",
    "coordinates": [
      5.77666,
      50.9721
    ]
  }
}