{
  "type": "Feature",
  "properties": {
    "name": "Maastricht",
    "country": "NL",
    "subdivision": "05",
    "timezone": "Europe/Amsterdam"
  },
  "geometry": {
    "type": "Point",
    "coordinates": [
      5.68889,
      50.84833
    ]
  }
}