{
  "type": "Feature",
  "properties": {
    "name": "Nieuwdorp",
    "country": "NL",
    "subdivision": "05",
    "timezone": "Europe/Amsterdam"
  },
  "geometry": {
    "type": "Point",
    "coordinates": [
      5.77297,
      50.96216
    ]
  }
}