{
  "type": "Feature",
  "properties": {
    "name": "Passart",
    "country": "NL",
    "subdivision": "05",
    "timezone": "Europe/Amsterdam"
  },
  "geometry": {
    "type": "Point",
    "coordinates": [
      5.94674,
      50.92389
    ]
  }
}