{
  "type": "Feature",
  "properties": {
    "name": "Rothem",
    "country": "NL",
    "subdivision": "05",
    "timezone": "Europe/Amsterdam"
  },
  "geometry": {
    "type": "Point",
    "coordinates": [
      5.73889,
      50.87667
    ]
  }
}