{
  "type": "Feature",
  "properties": {
    "name": "Scharn",
    "country": "NL",
    "subdivision": "05",
    "timezone": "Europe/Amsterdam"
  },
  "geometry": {
    "type": "Point",
    "coordinates": [
      5.73333,
      50.85
    ]
  }
}