{
  "type": "Feature",
  "properties": {
    "name": "Schinnen",
    "country": "NL",
    "subdivision": "05",
    "timezone": "Europe/Amsterdam"
  },
  "geometry": {
    "type": "Point",
    "coordinates": [
      5.88889,
      50.94333
    ]
  }
}