{
  "type": "Feature",
  "properties": {
    "name": "Sevenum",
    "country": "NL",
    "subdivision": "05",
    "timezone": "Europe/Amsterdam"
  },
  "geometry": {
    "type": "Point",
    "coordinates": [
      6.0375,
      51.4125
    ]
  }
}