{
  "type": "Feature",
  "properties": {
    "name": "Sibbe",
    "country": "NL",
    "subdivision": "05",
    "timezone": "Europe/Amsterdam"
  },
  "geometry": {
    "type": "Point",
    "coordinates": [
      5.82639,
      50.84417
    ]
  }
}