{
  "type": "Feature",
  "properties": {
    "name": "Venlo",
    "country": "NL",
    "subdivision": "05",
    "timezone": "Europe/Amsterdam"
  },
  "geometry": {
    "type": "Point",
    "coordinates": [
      6.16806,
      51.37
    ]
  }
}