{
  "type": "Feature",
  "properties": {
    "name": "Wijnandsrade",
    "country": "NL",
    "subdivision": "05",
    "timezone": "Europe/Amsterdam"
  },
  "geometry": {
    "type": "Point",
    "coordinates": [
      5.88333,
      50.90583
    ]
  }
}