{
  "type": "Feature",
  "properties": {
    "name": "Cinco de Mayo",
    "country": "MX",
    "subdivision": "10",
    "timezone": "America/Monterrey"
  },
  "geometry": {
    "type": "Point",
    "coordinates": [
      -104.57449,
      24.10181
    ]
  }
}