{
  "type": "Feature",
  "properties": {
    "name": "Cuencamé de Ceniceros",
    "country": "MX",
    "subdivision": "10",
    "timezone": "America/Monterrey"
  },
  "geometry": {
    "type": "Point",
    "coordinates": [
      -103.69731,
      24.87116
    ]
  }
}