{
  "type": "Feature",
  "properties": {
    "name": "El Huarache (El Guarache)",
    "country": "MX",
    "subdivision": "10",
    "timezone": "America/Monterrey"
  },
  "geometry": {
    "type": "Point",
    "coordinates": [
      -103.48667,
      25.52
    ]
  }
}