{
  "type": "Feature",
  "properties": {
    "name": "El Nayar",
    "country": "MX",
    "subdivision": "10",
    "timezone": "America/Monterrey"
  },
  "geometry": {
    "type": "Point",
    "coordinates": [
      -104.69541,
      23.96422
    ]
  }
}