{
  "type": "Feature",
  "properties": {
    "name": "El Rayo",
    "country": "MX",
    "subdivision": "10",
    "timezone": "America/Monterrey"
  },
  "geometry": {
    "type": "Point",
    "coordinates": [
      -103.60821,
      25.52112
    ]
  }
}