{
  "type": "Feature",
  "properties": {
    "name": "Emiliano Zapata",
    "country": "MX",
    "subdivision": "10",
    "timezone": "America/Monterrey"
  },
  "geometry": {
    "type": "Point",
    "coordinates": [
      -103.88784,
      24.44218
    ]
  }
}