{
  "type": "Feature",
  "properties": {
    "name": "Ignacio Allende",
    "country": "MX",
    "subdivision": "10",
    "timezone": "America/Monterrey"
  },
  "geometry": {
    "type": "Point",
    "coordinates": [
      -103.9971,
      24.47432
    ]
  }
}