{
  "type": "Feature",
  "properties": {
    "name": "José Guadalupe Rodríguez",
    "country": "MX",
    "subdivision": "10",
    "timezone": "America/Monterrey"
  },
  "geometry": {
    "type": "Point",
    "coordinates": [
      -104.08002,
      24.31912
    ]
  }
}