{
  "type": "Feature",
  "properties": {
    "name": "La Joya",
    "country": "MX",
    "subdivision": "10",
    "timezone": "America/Monterrey"
  },
  "geometry": {
    "type": "Point",
    "coordinates": [
      -103.99861,
      23.8375
    ]
  }
}