{
  "type": "Feature",
  "properties": {
    "name": "Nazareno",
    "country": "MX",
    "subdivision": "10",
    "timezone": "America/Monterrey"
  },
  "geometry": {
    "type": "Point",
    "coordinates": [
      -103.42065,
      25.39916
    ]
  }
}