{
  "type": "Feature",
  "properties": {
    "name": "San Francisco del Mezquital",
    "country": "MX",
    "subdivision": "10",
    "timezone": "America/Monterrey"
  },
  "geometry": {
    "type": "Point",
    "coordinates": [
      -104.3949,
      23.47444
    ]
  }
}