{
  "type": "Feature",
  "properties": {
    "name": "Santa Catarina de Tepehuanes",
    "country": "MX",
    "subdivision": "10",
    "timezone": "America/Monterrey"
  },
  "geometry": {
    "type": "Point",
    "coordinates": [
      -105.72445,
      25.33961
    ]
  }
}