{
  "type": "Feature",
  "properties": {
    "name": "Santiago Bayacora",
    "country": "MX",
    "subdivision": "10",
    "timezone": "America/Monterrey"
  },
  "geometry": {
    "type": "Point",
    "coordinates": [
      -104.61276,
      23.89373
    ]
  }
}