{
  "type": "Feature",
  "properties": {
    "name": "Santa Cruz Luján",
    "country": "MX",
    "subdivision": "10",
    "timezone": "America/Monterrey"
  },
  "geometry": {
    "type": "Point",
    "coordinates": [
      -103.3586,
      25.72478
    ]
  }
}