{
  "type": "Feature",
  "properties": {
    "name": "Tayoltita",
    "country": "MX",
    "subdivision": "10",
    "timezone": "America/Monterrey"
  },
  "geometry": {
    "type": "Point",
    "coordinates": [
      -105.93083,
      24.10278
    ]
  }
}