{
  "type": "Feature",
  "properties": {
    "name": "Velardeña",
    "country": "MX",
    "subdivision": "10",
    "timezone": "America/Monterrey"
  },
  "geometry": {
    "type": "Point",
    "coordinates": [
      -103.73668,
      25.06472
    ]
  }
}