{
  "type": "Feature",
  "properties": {
    "name": "Vicente Guerrero",
    "country": "MX",
    "subdivision": "10",
    "timezone": "America/Monterrey"
  },
  "geometry": {
    "type": "Point",
    "coordinates": [
      -103.98487,
      23.73429
    ]
  }
}