{
  "type": "Feature",
  "properties": {
    "name": "Villa Ocampo",
    "country": "MX",
    "subdivision": "10",
    "timezone": "America/Monterrey"
  },
  "geometry": {
    "type": "Point",
    "coordinates": [
      -105.5064,
      26.44085
    ]
  }
}