{
  "type": "Feature",
  "properties": {
    "name": "Csávoly",
    "country": "HU",
    "subdivision": "01",
    "timezone": "Europe/Budapest"
  },
  "geometry": {
    "type": "Point",
    "coordinates": [
      19.14667,
      46.18917
    ]
  }
}