{
  "type": "Feature",
  "properties": {
    "name": "Harta",
    "country": "HU",
    "subdivision": "01",
    "timezone": "Europe/Budapest"
  },
  "geometry": {
    "type": "Point",
    "coordinates": [
      19.0311,
      46.69758
    ]
  }
}