{
  "type": "Feature",
  "properties": {
    "name": "Kecel",
    "country": "HU",
    "subdivision": "01",
    "timezone": "Europe/Budapest"
  },
  "geometry": {
    "type": "Point",
    "coordinates": [
      19.25194,
      46.52528
    ]
  }
}