{
  "type": "Feature",
  "properties": {
    "name": "Madaras",
    "country": "HU",
    "subdivision": "01",
    "timezone": "Europe/Budapest"
  },
  "geometry": {
    "type": "Point",
    "coordinates": [
      19.26121,
      46.0587
    ]
  }
}