{
  "type": "Feature",
  "properties": {
    "name": "Mélykút",
    "country": "HU",
    "subdivision": "01",
    "timezone": "Europe/Budapest"
  },
  "geometry": {
    "type": "Point",
    "coordinates": [
      19.38102,
      46.21509
    ]
  }
}