{
  "type": "Feature",
  "properties": {
    "name": "Cantemir",
    "country": "MD",
    "subdivision": "65",
    "timezone": "Europe/Chisinau"
  },
  "geometry": {
    "type": "Point",
    "coordinates": [
      28.2027,
      46.27743
    ]
  }
}