{
  "type": "Feature",
  "properties": {
    "name": "Alipur",
    "country": "PK",
    "subdivision": "04",
    "timezone": "Asia/Karachi"
  },
  "geometry": {
    "type": "Point",
    "coordinates": [
      70.91106,
      29.38242
    ]
  }
}