{
  "type": "Feature",
  "properties": {
    "name": "Arifwala",
    "country": "PK",
    "subdivision": "04",
    "timezone": "Asia/Karachi"
  },
  "geometry": {
    "type": "Point",
    "coordinates": [
      73.06574,
      30.29058
    ]
  }
}