{
  "type": "Feature",
  "properties": {
    "name": "Chiniot",
    "country": "PK",
    "subdivision": "04",
    "timezone": "Asia/Karachi"
  },
  "geometry": {
    "type": "Point",
    "coordinates": [
      72.97836,
      31.72091
    ]
  }
}