{
  "type": "Feature",
  "properties": {
    "name": "Daira Din Panah",
    "country": "PK",
    "subdivision": "04",
    "timezone": "Asia/Karachi"
  },
  "geometry": {
    "type": "Point",
    "coordinates": [
      70.93722,
      30.57053
    ]
  }
}