{
  "type": "Feature",
  "properties": {
    "name": "Daultala",
    "country": "PK",
    "subdivision": "04",
    "timezone": "Asia/Karachi"
  },
  "geometry": {
    "type": "Point",
    "coordinates": [
      73.14099,
      33.19282
    ]
  }
}