{
  "type": "Feature",
  "properties": {
    "name": "Dipalpur",
    "country": "PK",
    "subdivision": "04",
    "timezone": "Asia/Karachi"
  },
  "geometry": {
    "type": "Point",
    "coordinates": [
      73.65306,
      30.66984
    ]
  }
}