{
  "type": "Feature",
  "properties": {
    "name": "Hafizabad",
    "country": "PK",
    "subdivision": "04",
    "timezone": "Asia/Karachi"
  },
  "geometry": {
    "type": "Point",
    "coordinates": [
      73.68802,
      32.07095
    ]
  }
}