{
  "type": "Feature",
  "properties": {
    "name": "Haveli Lakha",
    "country": "PK",
    "subdivision": "04",
    "timezone": "Asia/Karachi"
  },
  "geometry": {
    "type": "Point",
    "coordinates": [
      73.69371,
      30.45097
    ]
  }
}