{
  "type": "Feature",
  "properties": {
    "name": "Jampur",
    "country": "PK",
    "subdivision": "04",
    "timezone": "Asia/Karachi"
  },
  "geometry": {
    "type": "Point",
    "coordinates": [
      70.59518,
      29.64235
    ]
  }
}