{
  "type": "Feature",
  "properties": {
    "name": "Jhang Sadr",
    "country": "PK",
    "subdivision": "04",
    "timezone": "Asia/Karachi"
  },
  "geometry": {
    "type": "Point",
    "coordinates": [
      72.31687,
      31.26981
    ]
  }
}