{
  "type": "Feature",
  "properties": {
    "name": "Kahror Pakka",
    "country": "PK",
    "subdivision": "04",
    "timezone": "Asia/Karachi"
  },
  "geometry": {
    "type": "Point",
    "coordinates": [
      71.91437,
      29.6243
    ]
  }
}