{
  "type": "Feature",
  "properties": {
    "name": "Kamalia",
    "country": "PK",
    "subdivision": "04",
    "timezone": "Asia/Karachi"
  },
  "geometry": {
    "type": "Point",
    "coordinates": [
      72.64607,
      30.72708
    ]
  }
}