{
  "type": "Feature",
  "properties": {
    "name": "Mailsi",
    "country": "PK",
    "subdivision": "04",
    "timezone": "Asia/Karachi"
  },
  "geometry": {
    "type": "Point",
    "coordinates": [
      72.17398,
      29.80123
    ]
  }
}