{
  "type": "Feature",
  "properties": {
    "name": "Malakwal City",
    "country": "PK",
    "subdivision": "04",
    "timezone": "Asia/Karachi"
  },
  "geometry": {
    "type": "Point",
    "coordinates": [
      73.2122,
      32.55492
    ]
  }
}