{
  "type": "Feature",
  "properties": {
    "name": "Mianke Mor",
    "country": "PK",
    "subdivision": "04",
    "timezone": "Asia/Karachi"
  },
  "geometry": {
    "type": "Point",
    "coordinates": [
      73.94857,
      31.2024
    ]
  }
}