{
  "type": "Feature",
  "properties": {
    "name": "Murree",
    "country": "PK",
    "subdivision": "04",
    "timezone": "Asia/Karachi"
  },
  "geometry": {
    "type": "Point",
    "coordinates": [
      73.3903,
      33.90836
    ]
  }
}