{
  "type": "Feature",
  "properties": {
    "name": "Phalia",
    "country": "PK",
    "subdivision": "04",
    "timezone": "Asia/Karachi"
  },
  "geometry": {
    "type": "Point",
    "coordinates": [
      73.579,
      32.43104
    ]
  }
}