{
  "type": "Feature",
  "properties": {
    "name": "Pir Mahal",
    "country": "PK",
    "subdivision": "04",
    "timezone": "Asia/Karachi"
  },
  "geometry": {
    "type": "Point",
    "coordinates": [
      72.43455,
      30.76663
    ]
  }
}