{
  "type": "Feature",
  "properties": {
    "name": "Sangla Hill",
    "country": "PK",
    "subdivision": "04",
    "timezone": "Asia/Karachi"
  },
  "geometry": {
    "type": "Point",
    "coordinates": [
      73.38333,
      31.71667
    ]
  }
}