{
  "type": "Feature",
  "properties": {
    "name": "Sargodha",
    "country": "PK",
    "subdivision": "04",
    "timezone": "Asia/Karachi"
  },
  "geometry": {
    "type": "Point",
    "coordinates": [
      72.67418,
      32.08586
    ]
  }
}