{
  "type": "Feature",
  "properties": {
    "name": "Wazirabad",
    "country": "PK",
    "subdivision": "04",
    "timezone": "Asia/Karachi"
  },
  "geometry": {
    "type": "Point",
    "coordinates": [
      74.12,
      32.44324
    ]
  }
}