{
  "type": "Feature",
  "properties": {
    "name": "Yazman",
    "country": "PK",
    "subdivision": "04",
    "timezone": "Asia/Karachi"
  },
  "geometry": {
    "type": "Point",
    "coordinates": [
      71.74459,
      29.12122
    ]
  }
}