{
  "type": "Feature",
  "properties": {
    "name": "Baflo",
    "country": "NL",
    "subdivision": "04",
    "timezone": "Europe/Amsterdam"
  },
  "geometry": {
    "type": "Point",
    "coordinates": [
      6.51389,
      53.3625
    ]
  }
}