{
  "type": "Feature",
  "properties": {
    "name": "Haren",
    "country": "NL",
    "subdivision": "04",
    "timezone": "Europe/Amsterdam"
  },
  "geometry": {
    "type": "Point",
    "coordinates": [
      6.60931,
      53.17209
    ]
  }
}