{
  "type": "Feature",
  "properties": {
    "name": "Marum",
    "country": "NL",
    "subdivision": "04",
    "timezone": "Europe/Amsterdam"
  },
  "geometry": {
    "type": "Point",
    "coordinates": [
      6.2625,
      53.14417
    ]
  }
}