{
  "type": "Feature",
  "properties": {
    "name": "Meeden",
    "country": "NL",
    "subdivision": "04",
    "timezone": "Europe/Amsterdam"
  },
  "geometry": {
    "type": "Point",
    "coordinates": [
      6.92639,
      53.14
    ]
  }
}