{
  "type": "Feature",
  "properties": {
    "name": "Oude Pekela",
    "country": "NL",
    "subdivision": "04",
    "timezone": "Europe/Amsterdam"
  },
  "geometry": {
    "type": "Point",
    "coordinates": [
      7.00972,
      53.10417
    ]
  }
}