{
  "type": "Feature",
  "properties": {
    "name": "Schildwolde",
    "country": "NL",
    "subdivision": "04",
    "timezone": "Europe/Amsterdam"
  },
  "geometry": {
    "type": "Point",
    "coordinates": [
      6.81566,
      53.23327
    ]
  }
}