{
  "type": "Feature",
  "properties": {
    "name": "Vlagtwedde",
    "country": "NL",
    "subdivision": "04",
    "timezone": "Europe/Amsterdam"
  },
  "geometry": {
    "type": "Point",
    "coordinates": [
      7.10833,
      53.0275
    ]
  }
}