{
  "type": "Feature",
  "properties": {
    "name": "Gazimurskiy Zavod",
    "country": "RU",
    "subdivision": "93",
    "timezone": "Asia/Chita"
  },
  "geometry": {
    "type": "Point",
    "coordinates": [
      118.3446,
      51.55352
    ]
  }
}