{
  "type": "Feature",
  "properties": {
    "name": "Klichka",
    "country": "RU",
    "subdivision": "93",
    "timezone": "Asia/Chita"
  },
  "geometry": {
    "type": "Point",
    "coordinates": [
      117.996,
      50.4457
    ]
  }
}