{
  "type": "Feature",
  "properties": {
    "name": "Kokuy",
    "country": "RU",
    "subdivision": "93",
    "timezone": "Asia/Chita"
  },
  "geometry": {
    "type": "Point",
    "coordinates": [
      117.55412,
      52.20634
    ]
  }
}