{
  "type": "Feature",
  "properties": {
    "name": "Petrovsk-Zabaykal’skiy",
    "country": "RU",
    "subdivision": "93",
    "timezone": "Asia/Chita"
  },
  "geometry": {
    "type": "Point",
    "coordinates": [
      108.84301,
      51.2753
    ]
  }
}