{
  "type": "Feature",
  "properties": {
    "name": "Priiskovyy",
    "country": "RU",
    "subdivision": "93",
    "timezone": "Asia/Chita"
  },
  "geometry": {
    "type": "Point",
    "coordinates": [
      116.63333,
      51.93333
    ]
  }
}