{
  "type": "Feature",
  "properties": {
    "name": "Vershino-Shakhtaminskiy",
    "country": "RU",
    "subdivision": "93",
    "timezone": "Asia/Chita"
  },
  "geometry": {
    "type": "Point",
    "coordinates": [
      117.88762,
      51.30024
    ]
  }
}