{
  "type": "Feature",
  "properties": {
    "name": "A Pobra do Caramiñal",
    "country": "ES",
    "subdivision": "58",
    "timezone": "Europe/Madrid"
  },
  "geometry": {
    "type": "Point",
    "coordinates": [
      -8.93824,
      42.60295
    ]
  }
}