{
  "type": "Feature",
  "properties": {
    "name": "Arzúa",
    "country": "ES",
    "subdivision": "58",
    "timezone": "Europe/Madrid"
  },
  "geometry": {
    "type": "Point",
    "coordinates": [
      -8.15,
      42.93333
    ]
  }
}