{
  "type": "Feature",
  "properties": {
    "name": "Bueu",
    "country": "ES",
    "subdivision": "58",
    "timezone": "Europe/Madrid"
  },
  "geometry": {
    "type": "Point",
    "coordinates": [
      -8.78497,
      42.32458
    ]
  }
}