{
  "type": "Feature",
  "properties": {
    "name": "Carballeda de Avia",
    "country": "ES",
    "subdivision": "58",
    "timezone": "Europe/Madrid"
  },
  "geometry": {
    "type": "Point",
    "coordinates": [
      -8.16456,
      42.3214
    ]
  }
}