{
  "type": "Feature",
  "properties": {
    "name": "Carral",
    "country": "ES",
    "subdivision": "58",
    "timezone": "Europe/Madrid"
  },
  "geometry": {
    "type": "Point",
    "coordinates": [
      -8.35545,
      43.2286
    ]
  }
}