{
  "type": "Feature",
  "properties": {
    "name": "Castro",
    "country": "ES",
    "subdivision": "58",
    "timezone": "Europe/Madrid"
  },
  "geometry": {
    "type": "Point",
    "coordinates": [
      -7.58333,
      42.76667
    ]
  }
}