{
  "type": "Feature",
  "properties": {
    "name": "Cedeira",
    "country": "ES",
    "subdivision": "58",
    "timezone": "Europe/Madrid"
  },
  "geometry": {
    "type": "Point",
    "coordinates": [
      -8.05719,
      43.66044
    ]
  }
}