{
  "type": "Feature",
  "properties": {
    "name": "Cenlle",
    "country": "ES",
    "subdivision": "58",
    "timezone": "Europe/Madrid"
  },
  "geometry": {
    "type": "Point",
    "coordinates": [
      -8.08982,
      42.34183
    ]
  }
}