{
  "type": "Feature",
  "properties": {
    "name": "Cervo",
    "country": "ES",
    "subdivision": "58",
    "timezone": "Europe/Madrid"
  },
  "geometry": {
    "type": "Point",
    "coordinates": [
      -7.41013,
      43.67019
    ]
  }
}