{
  "type": "Feature",
  "properties": {
    "name": "Culleredo",
    "country": "ES",
    "subdivision": "58",
    "timezone": "Europe/Madrid"
  },
  "geometry": {
    "type": "Point",
    "coordinates": [
      -8.38858,
      43.28788
    ]
  }
}