{
  "type": "Feature",
  "properties": {
    "name": "Friol",
    "country": "ES",
    "subdivision": "58",
    "timezone": "Europe/Madrid"
  },
  "geometry": {
    "type": "Point",
    "coordinates": [
      -7.79514,
      43.03213
    ]
  }
}