{
  "type": "Feature",
  "properties": {
    "name": "Lousame",
    "country": "ES",
    "subdivision": "58",
    "timezone": "Europe/Madrid"
  },
  "geometry": {
    "type": "Point",
    "coordinates": [
      -8.84926,
      42.76477
    ]
  }
}