{
  "type": "Feature",
  "properties": {
    "name": "Ordes",
    "country": "ES",
    "subdivision": "58",
    "timezone": "Europe/Madrid"
  },
  "geometry": {
    "type": "Point",
    "coordinates": [
      -8.409,
      43.07654
    ]
  }
}