{
  "type": "Feature",
  "properties": {
    "name": "Porriño",
    "country": "ES",
    "subdivision": "58",
    "timezone": "Europe/Madrid"
  },
  "geometry": {
    "type": "Point",
    "coordinates": [
      -8.6198,
      42.16156
    ]
  }
}