{
  "type": "Feature",
  "properties": {
    "name": "Portas",
    "country": "ES",
    "subdivision": "58",
    "timezone": "Europe/Madrid"
  },
  "geometry": {
    "type": "Point",
    "coordinates": [
      -8.65573,
      42.58531
    ]
  }
}