{
  "type": "Feature",
  "properties": {
    "name": "Rairiz de Veiga",
    "country": "ES",
    "subdivision": "58",
    "timezone": "Europe/Madrid"
  },
  "geometry": {
    "type": "Point",
    "coordinates": [
      -7.83503,
      42.08364
    ]
  }
}