{
  "type": "Feature",
  "properties": {
    "name": "Ribadeo",
    "country": "ES",
    "subdivision": "58",
    "timezone": "Europe/Madrid"
  },
  "geometry": {
    "type": "Point",
    "coordinates": [
      -7.04095,
      43.53704
    ]
  }
}