{
  "type": "Feature",
  "properties": {
    "name": "Santa Marta de Ortigueira",
    "country": "ES",
    "subdivision": "58",
    "timezone": "Europe/Madrid"
  },
  "geometry": {
    "type": "Point",
    "coordinates": [
      -7.85,
      43.68333
    ]
  }
}