{
  "type": "Feature",
  "properties": {
    "name": "Verín",
    "country": "ES",
    "subdivision": "58",
    "timezone": "Europe/Madrid"
  },
  "geometry": {
    "type": "Point",
    "coordinates": [
      -7.43809,
      41.94149
    ]
  }
}