{
  "type": "Feature",
  "properties": {
    "name": "Vigo",
    "country": "ES",
    "subdivision": "58",
    "timezone": "Europe/Madrid"
  },
  "geometry": {
    "type": "Point",
    "coordinates": [
      -8.72264,
      42.23282
    ]
  }
}