{
  "type": "Feature",
  "properties": {
    "name": "Booué",
    "country": "GA",
    "subdivision": "06",
    "timezone": "Africa/Libreville"
  },
  "geometry": {
    "type": "Point",
    "coordinates": [
      11.93846,
      -0.09207
    ]
  }
}