{
  "type": "Feature",
  "properties": {
    "name": "Alacranes",
    "country": "CU",
    "subdivision": "03",
    "timezone": "America/Havana"
  },
  "geometry": {
    "type": "Point",
    "coordinates": [
      -81.56803,
      22.76719
    ]
  }
}