{
  "type": "Feature",
  "properties": {
    "name": "Pedro Betancourt",
    "country": "CU",
    "subdivision": "03",
    "timezone": "America/Havana"
  },
  "geometry": {
    "type": "Point",
    "coordinates": [
      -81.28963,
      22.72709
    ]
  }
}