{
  "type": "Feature",
  "properties": {
    "name": "Candela",
    "country": "MX",
    "subdivision": "07",
    "timezone": "America/Monterrey"
  },
  "geometry": {
    "type": "Point",
    "coordinates": [
      -100.6663,
      26.8384
    ]
  }
}