{
  "type": "Feature",
  "properties": {
    "name": "Ciudad Melchor Múzquiz",
    "country": "MX",
    "subdivision": "07",
    "timezone": "America/Monterrey"
  },
  "geometry": {
    "type": "Point",
    "coordinates": [
      -101.51615,
      27.87933
    ]
  }
}