{
  "type": "Feature",
  "properties": {
    "name": "Concordia",
    "country": "MX",
    "subdivision": "07",
    "timezone": "America/Monterrey"
  },
  "geometry": {
    "type": "Point",
    "coordinates": [
      -103.11696,
      25.77982
    ]
  }
}