{
  "type": "Feature",
  "properties": {
    "name": "Cuatro Ciénegas de Carranza",
    "country": "MX",
    "subdivision": "07",
    "timezone": "America/Monterrey"
  },
  "geometry": {
    "type": "Point",
    "coordinates": [
      -102.06386,
      26.98542
    ]
  }
}