{
  "type": "Feature",
  "properties": {
    "name": "El Lequeitio",
    "country": "MX",
    "subdivision": "07",
    "timezone": "America/Monterrey"
  },
  "geometry": {
    "type": "Point",
    "coordinates": [
      -103.2789,
      25.84673
    ]
  }
}