{
  "type": "Feature",
  "properties": {
    "name": "Escuadrón Doscientos Uno",
    "country": "MX",
    "subdivision": "07",
    "timezone": "America/Monterrey"
  },
  "geometry": {
    "type": "Point",
    "coordinates": [
      -103.34829,
      25.67433
    ]
  }
}