{
  "type": "Feature",
  "properties": {
    "name": "Gilita",
    "country": "MX",
    "subdivision": "07",
    "timezone": "America/Monterrey"
  },
  "geometry": {
    "type": "Point",
    "coordinates": [
      -103.19976,
      25.39314
    ]
  }
}