{
  "type": "Feature",
  "properties": {
    "name": "Hércules",
    "country": "MX",
    "subdivision": "07",
    "timezone": "America/Monterrey"
  },
  "geometry": {
    "type": "Point",
    "coordinates": [
      -103.79111,
      28.04306
    ]
  }
}