{
  "type": "Feature",
  "properties": {
    "name": "Lamadrid",
    "country": "MX",
    "subdivision": "07",
    "timezone": "America/Monterrey"
  },
  "geometry": {
    "type": "Point",
    "coordinates": [
      -101.79552,
      27.05087
    ]
  }
}