{
  "type": "Feature",
  "properties": {
    "name": "Luchanas",
    "country": "MX",
    "subdivision": "07",
    "timezone": "America/Monterrey"
  },
  "geometry": {
    "type": "Point",
    "coordinates": [
      -103.19384,
      25.79091
    ]
  }
}