{
  "type": "Feature",
  "properties": {
    "name": "Nava",
    "country": "MX",
    "subdivision": "07",
    "timezone": "America/Monterrey"
  },
  "geometry": {
    "type": "Point",
    "coordinates": [
      -100.76565,
      28.42071
    ]
  }
}