{
  "type": "Feature",
  "properties": {
    "name": "Nueva Rosita",
    "country": "MX",
    "subdivision": "07",
    "timezone": "America/Monterrey"
  },
  "geometry": {
    "type": "Point",
    "coordinates": [
      -101.21812,
      27.94028
    ]
  }
}