{
  "type": "Feature",
  "properties": {
    "name": "Parras de la Fuente",
    "country": "MX",
    "subdivision": "07",
    "timezone": "America/Monterrey"
  },
  "geometry": {
    "type": "Point",
    "coordinates": [
      -102.17808,
      25.44185
    ]
  }
}