{
  "type": "Feature",
  "properties": {
    "name": "Primero de Mayo",
    "country": "MX",
    "subdivision": "07",
    "timezone": "America/Monterrey"
  },
  "geometry": {
    "type": "Point",
    "coordinates": [
      -101.2236,
      27.23675
    ]
  }
}