{
  "type": "Feature",
  "properties": {
    "name": "Río Bravo",
    "country": "MX",
    "subdivision": "07",
    "timezone": "America/Monterrey"
  },
  "geometry": {
    "type": "Point",
    "coordinates": [
      -100.91668,
      28.31254
    ]
  }
}