{
  "type": "Feature",
  "properties": {
    "name": "Sabinas",
    "country": "MX",
    "subdivision": "07",
    "timezone": "America/Monterrey"
  },
  "geometry": {
    "type": "Point",
    "coordinates": [
      -101.11738,
      27.85591
    ]
  }
}