{
  "type": "Feature",
  "properties": {
    "name": "San Esteban de Abajo",
    "country": "MX",
    "subdivision": "07",
    "timezone": "America/Monterrey"
  },
  "geometry": {
    "type": "Point",
    "coordinates": [
      -103.00047,
      25.70903
    ]
  }
}