{
  "type": "Feature",
  "properties": {
    "name": "San Ignacio",
    "country": "MX",
    "subdivision": "07",
    "timezone": "America/Monterrey"
  },
  "geometry": {
    "type": "Point",
    "coordinates": [
      -103.09049,
      25.73643
    ]
  }
}