{
  "type": "Feature",
  "properties": {
    "name": "Tacubaya",
    "country": "MX",
    "subdivision": "07",
    "timezone": "America/Monterrey"
  },
  "geometry": {
    "type": "Point",
    "coordinates": [
      -103.06861,
      25.68361
    ]
  }
}