{
  "type": "Feature",
  "properties": {
    "name": "Bayanhongor",
    "country": "MN",
    "subdivision": "02",
    "timezone": "Asia/Ulaanbaatar"
  },
  "geometry": {
    "type": "Point",
    "coordinates": [
      100.71806,
      46.19444
    ]
  }
}