{
  "type": "Feature",
  "properties": {
    "name": "Alfenas",
    "country": "BR",
    "subdivision": "15",
    "timezone": "America/Sao_Paulo"
  },
  "geometry": {
    "type": "Point",
    "coordinates": [
      -45.94722,
      -21.42917
    ]
  }
}