{
  "type": "Feature",
  "properties": {
    "name": "Araçuaí",
    "country": "BR",
    "subdivision": "15",
    "timezone": "America/Sao_Paulo"
  },
  "geometry": {
    "type": "Point",
    "coordinates": [
      -42.07028,
      -16.84972
    ]
  }
}