{
  "type": "Feature",
  "properties": {
    "name": "Baependi",
    "country": "BR",
    "subdivision": "15",
    "timezone": "America/Sao_Paulo"
  },
  "geometry": {
    "type": "Point",
    "coordinates": [
      -44.89,
      -21.95889
    ]
  }
}