{
  "type": "Feature",
  "properties": {
    "name": "Barbacena",
    "country": "BR",
    "subdivision": "15",
    "timezone": "America/Sao_Paulo"
  },
  "geometry": {
    "type": "Point",
    "coordinates": [
      -43.77361,
      -21.22583
    ]
  }
}