{
  "type": "Feature",
  "properties": {
    "name": "Belo Oriente",
    "country": "BR",
    "subdivision": "15",
    "timezone": "America/Sao_Paulo"
  },
  "geometry": {
    "type": "Point",
    "coordinates": [
      -42.48361,
      -19.22
    ]
  }
}