{
  "type": "Feature",
  "properties": {
    "name": "Bicas",
    "country": "BR",
    "subdivision": "15",
    "timezone": "America/Sao_Paulo"
  },
  "geometry": {
    "type": "Point",
    "coordinates": [
      -43.05944,
      -21.72528
    ]
  }
}