{
  "type": "Feature",
  "properties": {
    "name": "Bom Sucesso",
    "country": "BR",
    "subdivision": "15",
    "timezone": "America/Sao_Paulo"
  },
  "geometry": {
    "type": "Point",
    "coordinates": [
      -44.75806,
      -21.03306
    ]
  }
}