{
  "type": "Feature",
  "properties": {
    "name": "Buritis",
    "country": "BR",
    "subdivision": "15",
    "timezone": "America/Sao_Paulo"
  },
  "geometry": {
    "type": "Point",
    "coordinates": [
      -46.42333,
      -15.61778
    ]
  }
}