{
  "type": "Feature",
  "properties": {
    "name": "Campestre",
    "country": "BR",
    "subdivision": "15",
    "timezone": "America/Sao_Paulo"
  },
  "geometry": {
    "type": "Point",
    "coordinates": [
      -46.24639,
      -21.71111
    ]
  }
}