{
  "type": "Feature",
  "properties": {
    "name": "Conceição das Alagoas",
    "country": "BR",
    "subdivision": "15",
    "timezone": "America/Sao_Paulo"
  },
  "geometry": {
    "type": "Point",
    "coordinates": [
      -48.38833,
      -19.91472
    ]
  }
}