{
  "type": "Feature",
  "properties": {
    "name": "Contagem",
    "country": "BR",
    "subdivision": "15",
    "timezone": "America/Sao_Paulo"
  },
  "geometry": {
    "type": "Point",
    "coordinates": [
      -44.05361,
      -19.93167
    ]
  }
}