{
  "type": "Feature",
  "properties": {
    "name": "Cruzília",
    "country": "BR",
    "subdivision": "15",
    "timezone": "America/Sao_Paulo"
  },
  "geometry": {
    "type": "Point",
    "coordinates": [
      -44.80833,
      -21.83861
    ]
  }
}