{
  "type": "Feature",
  "properties": {
    "name": "Curvelo",
    "country": "BR",
    "subdivision": "15",
    "timezone": "America/Sao_Paulo"
  },
  "geometry": {
    "type": "Point",
    "coordinates": [
      -44.43083,
      -18.75639
    ]
  }
}