{
  "type": "Feature",
  "properties": {
    "name": "Elói Mendes",
    "country": "BR",
    "subdivision": "15",
    "timezone": "America/Sao_Paulo"
  },
  "geometry": {
    "type": "Point",
    "coordinates": [
      -45.56528,
      -21.61
    ]
  }
}