{
  "type": "Feature",
  "properties": {
    "name": "Esmeraldas",
    "country": "BR",
    "subdivision": "15",
    "timezone": "America/Sao_Paulo"
  },
  "geometry": {
    "type": "Point",
    "coordinates": [
      -44.31389,
      -19.7625
    ]
  }
}