{
  "type": "Feature",
  "properties": {
    "name": "Francisco Sá",
    "country": "BR",
    "subdivision": "15",
    "timezone": "America/Sao_Paulo"
  },
  "geometry": {
    "type": "Point",
    "coordinates": [
      -43.48833,
      -16.47583
    ]
  }
}