{
  "type": "Feature",
  "properties": {
    "name": "Igarapé",
    "country": "BR",
    "subdivision": "15",
    "timezone": "America/Sao_Paulo"
  },
  "geometry": {
    "type": "Point",
    "coordinates": [
      -44.30167,
      -20.07028
    ]
  }
}