{
  "type": "Feature",
  "properties": {
    "name": "Itaú de Minas",
    "country": "BR",
    "subdivision": "15",
    "timezone": "America/Sao_Paulo"
  },
  "geometry": {
    "type": "Point",
    "coordinates": [
      -46.75222,
      -20.73944
    ]
  }
}