{
  "type": "Feature",
  "properties": {
    "name": "Joaíma",
    "country": "BR",
    "subdivision": "15",
    "timezone": "America/Sao_Paulo"
  },
  "geometry": {
    "type": "Point",
    "coordinates": [
      -41.03056,
      -16.65417
    ]
  }
}