{
  "type": "Feature",
  "properties": {
    "name": "Lavras",
    "country": "BR",
    "subdivision": "15",
    "timezone": "America/Sao_Paulo"
  },
  "geometry": {
    "type": "Point",
    "coordinates": [
      -44.99972,
      -21.24528
    ]
  }
}