{
  "type": "Feature",
  "properties": {
    "name": "Lima Duarte",
    "country": "BR",
    "subdivision": "15",
    "timezone": "America/Sao_Paulo"
  },
  "geometry": {
    "type": "Point",
    "coordinates": [
      -43.79306,
      -21.8425
    ]
  }
}