{
  "type": "Feature",
  "properties": {
    "name": "Manhuaçu",
    "country": "BR",
    "subdivision": "15",
    "timezone": "America/Sao_Paulo"
  },
  "geometry": {
    "type": "Point",
    "coordinates": [
      -42.03361,
      -20.25806
    ]
  }
}