{
  "type": "Feature",
  "properties": {
    "name": "Mar de Espanha",
    "country": "BR",
    "subdivision": "15",
    "timezone": "America/Sao_Paulo"
  },
  "geometry": {
    "type": "Point",
    "coordinates": [
      -43.00972,
      -21.86722
    ]
  }
}