{
  "type": "Feature",
  "properties": {
    "name": "Mato Verde",
    "country": "BR",
    "subdivision": "15",
    "timezone": "America/Sao_Paulo"
  },
  "geometry": {
    "type": "Point",
    "coordinates": [
      -42.86639,
      -15.39722
    ]
  }
}