{
  "type": "Feature",
  "properties": {
    "name": "Monte Santo de Minas",
    "country": "BR",
    "subdivision": "15",
    "timezone": "America/Sao_Paulo"
  },
  "geometry": {
    "type": "Point",
    "coordinates": [
      -46.98028,
      -21.18972
    ]
  }
}