{
  "type": "Feature",
  "properties": {
    "name": "Nanuque",
    "country": "BR",
    "subdivision": "15",
    "timezone": "America/Sao_Paulo"
  },
  "geometry": {
    "type": "Point",
    "coordinates": [
      -40.35389,
      -17.83917
    ]
  }
}