{
  "type": "Feature",
  "properties": {
    "name": "Nova Era",
    "country": "BR",
    "subdivision": "15",
    "timezone": "America/Sao_Paulo"
  },
  "geometry": {
    "type": "Point",
    "coordinates": [
      -43.0375,
      -19.75
    ]
  }
}