{
  "type": "Feature",
  "properties": {
    "name": "Oliveira",
    "country": "BR",
    "subdivision": "15",
    "timezone": "America/Sao_Paulo"
  },
  "geometry": {
    "type": "Point",
    "coordinates": [
      -44.82722,
      -20.69639
    ]
  }
}