{
  "type": "Feature",
  "properties": {
    "name": "Passa Quatro",
    "country": "BR",
    "subdivision": "15",
    "timezone": "America/Sao_Paulo"
  },
  "geometry": {
    "type": "Point",
    "coordinates": [
      -44.96667,
      -22.39028
    ]
  }
}