{
  "type": "Feature",
  "properties": {
    "name": "Peçanha",
    "country": "BR",
    "subdivision": "15",
    "timezone": "America/Sao_Paulo"
  },
  "geometry": {
    "type": "Point",
    "coordinates": [
      -42.55694,
      -18.54861
    ]
  }
}