{
  "type": "Feature",
  "properties": {
    "name": "Sacramento",
    "country": "BR",
    "subdivision": "15",
    "timezone": "America/Sao_Paulo"
  },
  "geometry": {
    "type": "Point",
    "coordinates": [
      -47.44,
      -19.86528
    ]
  }
}