{
  "type": "Feature",
  "properties": {
    "name": "Salinas",
    "country": "BR",
    "subdivision": "15",
    "timezone": "America/Sao_Paulo"
  },
  "geometry": {
    "type": "Point",
    "coordinates": [
      -42.29028,
      -16.17028
    ]
  }
}