{
  "type": "Feature",
  "properties": {
    "name": "Santa Vitória",
    "country": "BR",
    "subdivision": "15",
    "timezone": "America/Sao_Paulo"
  },
  "geometry": {
    "type": "Point",
    "coordinates": [
      -50.12139,
      -18.83861
    ]
  }
}