{
  "type": "Feature",
  "properties": {
    "name": "São João Nepomuceno",
    "country": "BR",
    "subdivision": "15",
    "timezone": "America/Sao_Paulo"
  },
  "geometry": {
    "type": "Point",
    "coordinates": [
      -43.01056,
      -21.54
    ]
  }
}