{
  "type": "Feature",
  "properties": {
    "name": "São Sebastião do Paraíso",
    "country": "BR",
    "subdivision": "15",
    "timezone": "America/Sao_Paulo"
  },
  "geometry": {
    "type": "Point",
    "coordinates": [
      -46.99139,
      -20.91694
    ]
  }
}