{
  "type": "Feature",
  "properties": {
    "name": "São João da Ponte",
    "country": "BR",
    "subdivision": "15",
    "timezone": "America/Sao_Paulo"
  },
  "geometry": {
    "type": "Point",
    "coordinates": [
      -44.00778,
      -15.92917
    ]
  }
}