{
  "type": "Feature",
  "properties": {
    "name": "Sarzedo",
    "country": "BR",
    "subdivision": "15",
    "timezone": "America/Sao_Paulo"
  },
  "geometry": {
    "type": "Point",
    "coordinates": [
      -44.14472,
      -20.03528
    ]
  }
}