{
  "type": "Feature",
  "properties": {
    "name": "Três Pontas",
    "country": "BR",
    "subdivision": "15",
    "timezone": "America/Sao_Paulo"
  },
  "geometry": {
    "type": "Point",
    "coordinates": [
      -45.5125,
      -21.36667
    ]
  }
}