{
  "type": "Feature",
  "properties": {
    "name": "Uberlândia",
    "country": "BR",
    "subdivision": "15",
    "timezone": "America/Sao_Paulo"
  },
  "geometry": {
    "type": "Point",
    "coordinates": [
      -48.27722,
      -18.91861
    ]
  }
}