{
  "type": "Feature",
  "properties": {
    "name": "Vazante",
    "country": "BR",
    "subdivision": "15",
    "timezone": "America/Sao_Paulo"
  },
  "geometry": {
    "type": "Point",
    "coordinates": [
      -46.90778,
      -17.98694
    ]
  }
}