{
  "type": "Feature",
  "properties": {
    "name": "Visconde do Rio Branco",
    "country": "BR",
    "subdivision": "15",
    "timezone": "America/Sao_Paulo"
  },
  "geometry": {
    "type": "Point",
    "coordinates": [
      -42.84056,
      -21.01028
    ]
  }
}