{
  "type": "Feature",
  "properties": {
    "name": "Hamhŭng",
    "country": "KP",
    "subdivision": "03",
    "timezone": "Asia/Pyongyang"
  },
  "geometry": {
    "type": "Point",
    "coordinates": [
      127.53639,
      39.91833
    ]
  }
}