{
  "type": "Feature",
  "properties": {
    "name": "Hongwŏn",
    "country": "KP",
    "subdivision": "03",
    "timezone": "Asia/Pyongyang"
  },
  "geometry": {
    "type": "Point",
    "coordinates": [
      127.95583,
      40.02528
    ]
  }
}