{
  "type": "Feature",
  "properties": {
    "name": "Affi",
    "country": "IT",
    "subdivision": "20",
    "timezone": "Europe/Rome"
  },
  "geometry": {
    "type": "Point",
    "coordinates": [
      10.7864,
      45.55297
    ]
  }
}