{
  "type": "Feature",
  "properties": {
    "name": "Arcade",
    "country": "IT",
    "subdivision": "20",
    "timezone": "Europe/Rome"
  },
  "geometry": {
    "type": "Point",
    "coordinates": [
      12.21972,
      45.78428
    ]
  }
}