{
  "type": "Feature",
  "properties": {
    "name": "Arcole",
    "country": "IT",
    "subdivision": "20",
    "timezone": "Europe/Rome"
  },
  "geometry": {
    "type": "Point",
    "coordinates": [
      11.2875,
      45.36125
    ]
  }
}