{
  "type": "Feature",
  "properties": {
    "name": "Bagnolo",
    "country": "IT",
    "subdivision": "20",
    "timezone": "Europe/Rome"
  },
  "geometry": {
    "type": "Point",
    "coordinates": [
      10.89081,
      45.27238
    ]
  }
}