{
  "type": "Feature",
  "properties": {
    "name": "Beccacivetta-Azzano",
    "country": "IT",
    "subdivision": "20",
    "timezone": "Europe/Rome"
  },
  "geometry": {
    "type": "Point",
    "coordinates": [
      10.96133,
      45.37435
    ]
  }
}