{
  "type": "Feature",
  "properties": {
    "name": "Bevilacqua",
    "country": "IT",
    "subdivision": "20",
    "timezone": "Europe/Rome"
  },
  "geometry": {
    "type": "Point",
    "coordinates": [
      11.39496,
      45.23249
    ]
  }
}