{
  "type": "Feature",
  "properties": {
    "name": "Bosaro",
    "country": "IT",
    "subdivision": "20",
    "timezone": "Europe/Rome"
  },
  "geometry": {
    "type": "Point",
    "coordinates": [
      11.76471,
      44.99878
    ]
  }
}