{
  "type": "Feature",
  "properties": {
    "name": "Bovolone",
    "country": "IT",
    "subdivision": "20",
    "timezone": "Europe/Rome"
  },
  "geometry": {
    "type": "Point",
    "coordinates": [
      11.11786,
      45.26142
    ]
  }
}