{
  "type": "Feature",
  "properties": {
    "name": "Brentino Belluno",
    "country": "IT",
    "subdivision": "20",
    "timezone": "Europe/Rome"
  },
  "geometry": {
    "type": "Point",
    "coordinates": [
      10.89368,
      45.65689
    ]
  }
}