{
  "type": "Feature",
  "properties": {
    "name": "Bussolengo",
    "country": "IT",
    "subdivision": "20",
    "timezone": "Europe/Rome"
  },
  "geometry": {
    "type": "Point",
    "coordinates": [
      10.85371,
      45.46903
    ]
  }
}