{
  "type": "Feature",
  "properties": {
    "name": "Cadoneghe",
    "country": "IT",
    "subdivision": "20",
    "timezone": "Europe/Rome"
  },
  "geometry": {
    "type": "Point",
    "coordinates": [
      11.92749,
      45.44282
    ]
  }
}