{
  "type": "Feature",
  "properties": {
    "name": "Caldogno-Rettorgole-Cresole",
    "country": "IT",
    "subdivision": "20",
    "timezone": "Europe/Rome"
  },
  "geometry": {
    "type": "Point",
    "coordinates": [
      11.5028,
      45.6078
    ]
  }
}