{
  "type": "Feature",
  "properties": {
    "name": "Camalò",
    "country": "IT",
    "subdivision": "20",
    "timezone": "Europe/Rome"
  },
  "geometry": {
    "type": "Point",
    "coordinates": [
      12.17165,
      45.75324
    ]
  }
}