{
  "type": "Feature",
  "properties": {
    "name": "Camponogara",
    "country": "IT",
    "subdivision": "20",
    "timezone": "Europe/Rome"
  },
  "geometry": {
    "type": "Point",
    "coordinates": [
      12.08638,
      45.37954
    ]
  }
}