{
  "type": "Feature",
  "properties": {
    "name": "Camposampiero",
    "country": "IT",
    "subdivision": "20",
    "timezone": "Europe/Rome"
  },
  "geometry": {
    "type": "Point",
    "coordinates": [
      11.93534,
      45.56368
    ]
  }
}