{
  "type": "Feature",
  "properties": {
    "name": "Candelù",
    "country": "IT",
    "subdivision": "20",
    "timezone": "Europe/Rome"
  },
  "geometry": {
    "type": "Point",
    "coordinates": [
      12.37224,
      45.73499
    ]
  }
}