{
  "type": "Feature",
  "properties": {
    "name": "Caniezza",
    "country": "IT",
    "subdivision": "20",
    "timezone": "Europe/Rome"
  },
  "geometry": {
    "type": "Point",
    "coordinates": [
      11.899,
      45.85274
    ]
  }
}