{
  "type": "Feature",
  "properties": {
    "name": "Canove di Roana",
    "country": "IT",
    "subdivision": "20",
    "timezone": "Europe/Rome"
  },
  "geometry": {
    "type": "Point",
    "coordinates": [
      11.4735,
      45.8635
    ]
  }
}