{
  "type": "Feature",
  "properties": {
    "name": "Caprino Veronese",
    "country": "IT",
    "subdivision": "20",
    "timezone": "Europe/Rome"
  },
  "geometry": {
    "type": "Point",
    "coordinates": [
      10.79518,
      45.60489
    ]
  }
}