{
  "type": "Feature",
  "properties": {
    "name": "Carrè",
    "country": "IT",
    "subdivision": "20",
    "timezone": "Europe/Rome"
  },
  "geometry": {
    "type": "Point",
    "coordinates": [
      11.45779,
      45.7488
    ]
  }
}