{
  "type": "Feature",
  "properties": {
    "name": "Carrara San Giorgio",
    "country": "IT",
    "subdivision": "20",
    "timezone": "Europe/Rome"
  },
  "geometry": {
    "type": "Point",
    "coordinates": [
      11.81841,
      45.29259
    ]
  }
}