{
  "type": "Feature",
  "properties": {
    "name": "Castion",
    "country": "IT",
    "subdivision": "20",
    "timezone": "Europe/Rome"
  },
  "geometry": {
    "type": "Point",
    "coordinates": [
      12.23507,
      46.12147
    ]
  }
}