{
  "type": "Feature",
  "properties": {
    "name": "Cencenighe Agordino",
    "country": "IT",
    "subdivision": "20",
    "timezone": "Europe/Rome"
  },
  "geometry": {
    "type": "Point",
    "coordinates": [
      11.96823,
      46.35184
    ]
  }
}