{
  "type": "Feature",
  "properties": {
    "name": "Ciano",
    "country": "IT",
    "subdivision": "20",
    "timezone": "Europe/Rome"
  },
  "geometry": {
    "type": "Point",
    "coordinates": [
      12.05417,
      45.82389
    ]
  }
}