{
  "type": "Feature",
  "properties": {
    "name": "Colle Umberto",
    "country": "IT",
    "subdivision": "20",
    "timezone": "Europe/Rome"
  },
  "geometry": {
    "type": "Point",
    "coordinates": [
      12.34228,
      45.94238
    ]
  }
}