{
  "type": "Feature",
  "properties": {
    "name": "Cosniga-Zoppè",
    "country": "IT",
    "subdivision": "20",
    "timezone": "Europe/Rome"
  },
  "geometry": {
    "type": "Point",
    "coordinates": [
      12.36028,
      45.8875
    ]
  }
}