{
  "type": "Feature",
  "properties": {
    "name": "Crispi Cavour",
    "country": "IT",
    "subdivision": "20",
    "timezone": "Europe/Rome"
  },
  "geometry": {
    "type": "Point",
    "coordinates": [
      11.50113,
      45.5819
    ]
  }
}