{
  "type": "Feature",
  "properties": {
    "name": "Crocetta-Nogarè",
    "country": "IT",
    "subdivision": "20",
    "timezone": "Europe/Rome"
  },
  "geometry": {
    "type": "Point",
    "coordinates": [
      12.03013,
      45.82707
    ]
  }
}