{
  "type": "Feature",
  "properties": {
    "name": "Curtarolo",
    "country": "IT",
    "subdivision": "20",
    "timezone": "Europe/Rome"
  },
  "geometry": {
    "type": "Point",
    "coordinates": [
      11.83691,
      45.52366
    ]
  }
}