{
  "type": "Feature",
  "properties": {
    "name": "Erbè",
    "country": "IT",
    "subdivision": "20",
    "timezone": "Europe/Rome"
  },
  "geometry": {
    "type": "Point",
    "coordinates": [
      10.97135,
      45.24231
    ]
  }
}