{
  "type": "Feature",
  "properties": {
    "name": "Falzè di Piave",
    "country": "IT",
    "subdivision": "20",
    "timezone": "Europe/Rome"
  },
  "geometry": {
    "type": "Point",
    "coordinates": [
      12.17891,
      45.86796
    ]
  }
}