{
  "type": "Feature",
  "properties": {
    "name": "Galzignano",
    "country": "IT",
    "subdivision": "20",
    "timezone": "Europe/Rome"
  },
  "geometry": {
    "type": "Point",
    "coordinates": [
      11.73134,
      45.30798
    ]
  }
}