{
  "type": "Feature",
  "properties": {
    "name": "Isola della Scala",
    "country": "IT",
    "subdivision": "20",
    "timezone": "Europe/Rome"
  },
  "geometry": {
    "type": "Point",
    "coordinates": [
      11.00824,
      45.26943
    ]
  }
}