{
  "type": "Feature",
  "properties": {
    "name": "Lavagno",
    "country": "IT",
    "subdivision": "20",
    "timezone": "Europe/Rome"
  },
  "geometry": {
    "type": "Point",
    "coordinates": [
      11.13409,
      45.43869
    ]
  }
}