{
  "type": "Feature",
  "properties": {
    "name": "Lazise",
    "country": "IT",
    "subdivision": "20",
    "timezone": "Europe/Rome"
  },
  "geometry": {
    "type": "Point",
    "coordinates": [
      10.73923,
      45.50499
    ]
  }
}