{
  "type": "Feature",
  "properties": {
    "name": "Legnago",
    "country": "IT",
    "subdivision": "20",
    "timezone": "Europe/Rome"
  },
  "geometry": {
    "type": "Point",
    "coordinates": [
      11.30227,
      45.19365
    ]
  }
}