{
  "type": "Feature",
  "properties": {
    "name": "Lentiai",
    "country": "IT",
    "subdivision": "20",
    "timezone": "Europe/Rome"
  },
  "geometry": {
    "type": "Point",
    "coordinates": [
      12.02053,
      46.04504
    ]
  }
}