{
  "type": "Feature",
  "properties": {
    "name": "Levada",
    "country": "IT",
    "subdivision": "20",
    "timezone": "Europe/Rome"
  },
  "geometry": {
    "type": "Point",
    "coordinates": [
      12.47128,
      45.73442
    ]
  }
}