{
  "type": "Feature",
  "properties": {
    "name": "Lido di Jesolo",
    "country": "IT",
    "subdivision": "20",
    "timezone": "Europe/Rome"
  },
  "geometry": {
    "type": "Point",
    "coordinates": [
      12.64694,
      45.50694
    ]
  }
}