{
  "type": "Feature",
  "properties": {
    "name": "Livinallongo del Col di Lana",
    "country": "IT",
    "subdivision": "20",
    "timezone": "Europe/Rome"
  },
  "geometry": {
    "type": "Point",
    "coordinates": [
      11.95399,
      46.48162
    ]
  }
}