{
  "type": "Feature",
  "properties": {
    "name": "Locara",
    "country": "IT",
    "subdivision": "20",
    "timezone": "Europe/Rome"
  },
  "geometry": {
    "type": "Point",
    "coordinates": [
      11.33262,
      45.41207
    ]
  }
}