{
  "type": "Feature",
  "properties": {
    "name": "Lonigo",
    "country": "IT",
    "subdivision": "20",
    "timezone": "Europe/Rome"
  },
  "geometry": {
    "type": "Point",
    "coordinates": [
      11.38402,
      45.38576
    ]
  }
}