{
  "type": "Feature",
  "properties": {
    "name": "Lughignano",
    "country": "IT",
    "subdivision": "20",
    "timezone": "Europe/Rome"
  },
  "geometry": {
    "type": "Point",
    "coordinates": [
      12.32478,
      45.62533
    ]
  }
}