{
  "type": "Feature",
  "properties": {
    "name": "Maser",
    "country": "IT",
    "subdivision": "20",
    "timezone": "Europe/Rome"
  },
  "geometry": {
    "type": "Point",
    "coordinates": [
      11.975,
      45.8074
    ]
  }
}