{
  "type": "Feature",
  "properties": {
    "name": "Mirano",
    "country": "IT",
    "subdivision": "20",
    "timezone": "Europe/Rome"
  },
  "geometry": {
    "type": "Point",
    "coordinates": [
      12.10775,
      45.49458
    ]
  }
}