{
  "type": "Feature",
  "properties": {
    "name": "Monteviale",
    "country": "IT",
    "subdivision": "20",
    "timezone": "Europe/Rome"
  },
  "geometry": {
    "type": "Point",
    "coordinates": [
      11.45715,
      45.5592
    ]
  }
}