{
  "type": "Feature",
  "properties": {
    "name": "Montagnana",
    "country": "IT",
    "subdivision": "20",
    "timezone": "Europe/Rome"
  },
  "geometry": {
    "type": "Point",
    "coordinates": [
      11.46483,
      45.23229
    ]
  }
}