{
  "type": "Feature",
  "properties": {
    "name": "Montorio",
    "country": "IT",
    "subdivision": "20",
    "timezone": "Europe/Rome"
  },
  "geometry": {
    "type": "Point",
    "coordinates": [
      11.06589,
      45.45826
    ]
  }
}