{
  "type": "Feature",
  "properties": {
    "name": "Noventa di Piave",
    "country": "IT",
    "subdivision": "20",
    "timezone": "Europe/Rome"
  },
  "geometry": {
    "type": "Point",
    "coordinates": [
      12.53322,
      45.65981
    ]
  }
}