{
  "type": "Feature",
  "properties": {
    "name": "Pedavena",
    "country": "IT",
    "subdivision": "20",
    "timezone": "Europe/Rome"
  },
  "geometry": {
    "type": "Point",
    "coordinates": [
      11.8831,
      46.03951
    ]
  }
}