{
  "type": "Feature",
  "properties": {
    "name": "Piacenza d'Adige",
    "country": "IT",
    "subdivision": "20",
    "timezone": "Europe/Rome"
  },
  "geometry": {
    "type": "Point",
    "coordinates": [
      11.54333,
      45.12749
    ]
  }
}