{
  "type": "Feature",
  "properties": {
    "name": "Pontelongo",
    "country": "IT",
    "subdivision": "20",
    "timezone": "Europe/Rome"
  },
  "geometry": {
    "type": "Point",
    "coordinates": [
      12.02582,
      45.2459
    ]
  }
}