{
  "type": "Feature",
  "properties": {
    "name": "Povegliano Veronese",
    "country": "IT",
    "subdivision": "20",
    "timezone": "Europe/Rome"
  },
  "geometry": {
    "type": "Point",
    "coordinates": [
      10.88056,
      45.3473
    ]
  }
}