{
  "type": "Feature",
  "properties": {
    "name": "Preara-Moraro-Levà Nord",
    "country": "IT",
    "subdivision": "20",
    "timezone": "Europe/Rome"
  },
  "geometry": {
    "type": "Point",
    "coordinates": [
      11.54286,
      45.67996
    ]
  }
}