{
  "type": "Feature",
  "properties": {
    "name": "Pressana",
    "country": "IT",
    "subdivision": "20",
    "timezone": "Europe/Rome"
  },
  "geometry": {
    "type": "Point",
    "coordinates": [
      11.40724,
      45.28258
    ]
  }
}