{
  "type": "Feature",
  "properties": {
    "name": "Puos d'Alpago",
    "country": "IT",
    "subdivision": "20",
    "timezone": "Europe/Rome"
  },
  "geometry": {
    "type": "Point",
    "coordinates": [
      12.36176,
      46.14154
    ]
  }
}