{
  "type": "Feature",
  "properties": {
    "name": "Ramon",
    "country": "IT",
    "subdivision": "20",
    "timezone": "Europe/Rome"
  },
  "geometry": {
    "type": "Point",
    "coordinates": [
      11.86828,
      45.71386
    ]
  }
}