{
  "type": "Feature",
  "properties": {
    "name": "Revine",
    "country": "IT",
    "subdivision": "20",
    "timezone": "Europe/Rome"
  },
  "geometry": {
    "type": "Point",
    "coordinates": [
      12.25561,
      45.99935
    ]
  }
}