{
  "type": "Feature",
  "properties": {
    "name": "Ronchi di Campanile",
    "country": "IT",
    "subdivision": "20",
    "timezone": "Europe/Rome"
  },
  "geometry": {
    "type": "Point",
    "coordinates": [
      11.77483,
      45.4579
    ]
  }
}