{
  "type": "Feature",
  "properties": {
    "name": "Salionze",
    "country": "IT",
    "subdivision": "20",
    "timezone": "Europe/Rome"
  },
  "geometry": {
    "type": "Point",
    "coordinates": [
      10.72259,
      45.40493
    ]
  }
}