{
  "type": "Feature",
  "properties": {
    "name": "San Martino di Lupari",
    "country": "IT",
    "subdivision": "20",
    "timezone": "Europe/Rome"
  },
  "geometry": {
    "type": "Point",
    "coordinates": [
      11.86004,
      45.65128
    ]
  }
}