{
  "type": "Feature",
  "properties": {
    "name": "San Martino Buon Albergo",
    "country": "IT",
    "subdivision": "20",
    "timezone": "Europe/Rome"
  },
  "geometry": {
    "type": "Point",
    "coordinates": [
      11.09562,
      45.42083
    ]
  }
}