{
  "type": "Feature",
  "properties": {
    "name": "San Biagio di Callalta",
    "country": "IT",
    "subdivision": "20",
    "timezone": "Europe/Rome"
  },
  "geometry": {
    "type": "Point",
    "coordinates": [
      12.37722,
      45.68361
    ]
  }
}