{
  "type": "Feature",
  "properties": {
    "name": "San Quirico",
    "country": "IT",
    "subdivision": "20",
    "timezone": "Europe/Rome"
  },
  "geometry": {
    "type": "Point",
    "coordinates": [
      11.2726,
      45.67685
    ]
  }
}