{
  "type": "Feature",
  "properties": {
    "name": "San Pietro in Cariano",
    "country": "IT",
    "subdivision": "20",
    "timezone": "Europe/Rome"
  },
  "geometry": {
    "type": "Point",
    "coordinates": [
      10.88624,
      45.51751
    ]
  }
}