{
  "type": "Feature",
  "properties": {
    "name": "San Michele di Piave",
    "country": "IT",
    "subdivision": "20",
    "timezone": "Europe/Rome"
  },
  "geometry": {
    "type": "Point",
    "coordinates": [
      12.34634,
      45.79667
    ]
  }
}