{
  "type": "Feature",
  "properties": {
    "name": "Sant'Elena",
    "country": "IT",
    "subdivision": "20",
    "timezone": "Europe/Rome"
  },
  "geometry": {
    "type": "Point",
    "coordinates": [
      11.71169,
      45.18744
    ]
  }
}