{
  "type": "Feature",
  "properties": {
    "name": "Santa Maria di Sala",
    "country": "IT",
    "subdivision": "20",
    "timezone": "Europe/Rome"
  },
  "geometry": {
    "type": "Point",
    "coordinates": [
      12.03565,
      45.50699
    ]
  }
}