{
  "type": "Feature",
  "properties": {
    "name": "Santo Stefano-Bonaldo",
    "country": "IT",
    "subdivision": "20",
    "timezone": "Europe/Rome"
  },
  "geometry": {
    "type": "Point",
    "coordinates": [
      11.33199,
      45.36718
    ]
  }
}