{
  "type": "Feature",
  "properties": {
    "name": "Sarmeola",
    "country": "IT",
    "subdivision": "20",
    "timezone": "Europe/Rome"
  },
  "geometry": {
    "type": "Point",
    "coordinates": [
      11.81674,
      45.424
    ]
  }
}