{
  "type": "Feature",
  "properties": {
    "name": "Seren del Grappa",
    "country": "IT",
    "subdivision": "20",
    "timezone": "Europe/Rome"
  },
  "geometry": {
    "type": "Point",
    "coordinates": [
      11.85624,
      45.99594
    ]
  }
}