{
  "type": "Feature",
  "properties": {
    "name": "Solesino",
    "country": "IT",
    "subdivision": "20",
    "timezone": "Europe/Rome"
  },
  "geometry": {
    "type": "Point",
    "coordinates": [
      11.74647,
      45.17922
    ]
  }
}