{
  "type": "Feature",
  "properties": {
    "name": "Sona",
    "country": "IT",
    "subdivision": "20",
    "timezone": "Europe/Rome"
  },
  "geometry": {
    "type": "Point",
    "coordinates": [
      10.8399,
      45.43271
    ]
  }
}