{
  "type": "Feature",
  "properties": {
    "name": "Sovizzo",
    "country": "IT",
    "subdivision": "20",
    "timezone": "Europe/Rome"
  },
  "geometry": {
    "type": "Point",
    "coordinates": [
      11.4461,
      45.52669
    ]
  }
}