{
  "type": "Feature",
  "properties": {
    "name": "Summaga",
    "country": "IT",
    "subdivision": "20",
    "timezone": "Europe/Rome"
  },
  "geometry": {
    "type": "Point",
    "coordinates": [
      12.79792,
      45.77406
    ]
  }
}