{
  "type": "Feature",
  "properties": {
    "name": "Taggì",
    "country": "IT",
    "subdivision": "20",
    "timezone": "Europe/Rome"
  },
  "geometry": {
    "type": "Point",
    "coordinates": [
      11.81865,
      45.4607
    ]
  }
}