{
  "type": "Feature",
  "properties": {
    "name": "Tarzo",
    "country": "IT",
    "subdivision": "20",
    "timezone": "Europe/Rome"
  },
  "geometry": {
    "type": "Point",
    "coordinates": [
      12.22917,
      45.97711
    ]
  }
}