{
  "type": "Feature",
  "properties": {
    "name": "Terrossa",
    "country": "IT",
    "subdivision": "20",
    "timezone": "Europe/Rome"
  },
  "geometry": {
    "type": "Point",
    "coordinates": [
      11.3186,
      45.4634
    ]
  }
}