{
  "type": "Feature",
  "properties": {
    "name": "Tessera",
    "country": "IT",
    "subdivision": "20",
    "timezone": "Europe/Rome"
  },
  "geometry": {
    "type": "Point",
    "coordinates": [
      12.32632,
      45.50241
    ]
  }
}