{
  "type": "Feature",
  "properties": {
    "name": "Trissino",
    "country": "IT",
    "subdivision": "20",
    "timezone": "Europe/Rome"
  },
  "geometry": {
    "type": "Point",
    "coordinates": [
      11.37678,
      45.55994
    ]
  }
}