{
  "type": "Feature",
  "properties": {
    "name": "Vallese",
    "country": "IT",
    "subdivision": "20",
    "timezone": "Europe/Rome"
  },
  "geometry": {
    "type": "Point",
    "coordinates": [
      11.08608,
      45.32827
    ]
  }
}