{
  "type": "Feature",
  "properties": {
    "name": "Vallà",
    "country": "IT",
    "subdivision": "20",
    "timezone": "Europe/Rome"
  },
  "geometry": {
    "type": "Point",
    "coordinates": [
      11.93271,
      45.70711
    ]
  }
}