{
  "type": "Feature",
  "properties": {
    "name": "Venegazzù",
    "country": "IT",
    "subdivision": "20",
    "timezone": "Europe/Rome"
  },
  "geometry": {
    "type": "Point",
    "coordinates": [
      12.09148,
      45.77934
    ]
  }
}