{
  "type": "Feature",
  "properties": {
    "name": "Veronella",
    "country": "IT",
    "subdivision": "20",
    "timezone": "Europe/Rome"
  },
  "geometry": {
    "type": "Point",
    "coordinates": [
      11.32582,
      45.32378
    ]
  }
}