{
  "type": "Feature",
  "properties": {
    "name": "Veternigo",
    "country": "IT",
    "subdivision": "20",
    "timezone": "Europe/Rome"
  },
  "geometry": {
    "type": "Point",
    "coordinates": [
      12.05793,
      45.51765
    ]
  }
}