{
  "type": "Feature",
  "properties": {
    "name": "Villabruna-Umin",
    "country": "IT",
    "subdivision": "20",
    "timezone": "Europe/Rome"
  },
  "geometry": {
    "type": "Point",
    "coordinates": [
      11.927,
      46.05675
    ]
  }
}