{
  "type": "Feature",
  "properties": {
    "name": "Villa Estense",
    "country": "IT",
    "subdivision": "20",
    "timezone": "Europe/Rome"
  },
  "geometry": {
    "type": "Point",
    "coordinates": [
      11.67022,
      45.17465
    ]
  }
}