{
  "type": "Feature",
  "properties": {
    "name": "Villaguattera",
    "country": "IT",
    "subdivision": "20",
    "timezone": "Europe/Rome"
  },
  "geometry": {
    "type": "Point",
    "coordinates": [
      11.81767,
      45.44409
    ]
  }
}