{
  "type": "Feature",
  "properties": {
    "name": "Villanova",
    "country": "IT",
    "subdivision": "20",
    "timezone": "Europe/Rome"
  },
  "geometry": {
    "type": "Point",
    "coordinates": [
      11.97471,
      45.4889
    ]
  }
}