{
  "type": "Feature",
  "properties": {
    "name": "Villaggio Montegrappa",
    "country": "IT",
    "subdivision": "20",
    "timezone": "Europe/Rome"
  },
  "geometry": {
    "type": "Point",
    "coordinates": [
      11.61428,
      45.54643
    ]
  }
}