{
  "type": "Feature",
  "properties": {
    "name": "Zevio",
    "country": "IT",
    "subdivision": "20",
    "timezone": "Europe/Rome"
  },
  "geometry": {
    "type": "Point",
    "coordinates": [
      11.12929,
      45.37209
    ]
  }
}