{
  "type": "Feature",
  "properties": {
    "name": "Harsány",
    "country": "HU",
    "subdivision": "04",
    "timezone": "Europe/Budapest"
  },
  "geometry": {
    "type": "Point",
    "coordinates": [
      20.75,
      47.96667
    ]
  }
}