{
  "type": "Feature",
  "properties": {
    "name": "Karcsa",
    "country": "HU",
    "subdivision": "04",
    "timezone": "Europe/Budapest"
  },
  "geometry": {
    "type": "Point",
    "coordinates": [
      21.80537,
      48.3113
    ]
  }
}