{
  "type": "Feature",
  "properties": {
    "name": "Kazincbarcika",
    "country": "HU",
    "subdivision": "04",
    "timezone": "Europe/Budapest"
  },
  "geometry": {
    "type": "Point",
    "coordinates": [
      20.63333,
      48.25
    ]
  }
}