{
  "type": "Feature",
  "properties": {
    "name": "Megyaszó",
    "country": "HU",
    "subdivision": "04",
    "timezone": "Europe/Budapest"
  },
  "geometry": {
    "type": "Point",
    "coordinates": [
      21.05,
      48.18333
    ]
  }
}