{
  "type": "Feature",
  "properties": {
    "name": "Miskolc",
    "country": "HU",
    "subdivision": "04",
    "timezone": "Europe/Budapest"
  },
  "geometry": {
    "type": "Point",
    "coordinates": [
      20.77806,
      48.10306
    ]
  }
}