{
  "type": "Feature",
  "properties": {
    "name": "Olaszliszka",
    "country": "HU",
    "subdivision": "04",
    "timezone": "Europe/Budapest"
  },
  "geometry": {
    "type": "Point",
    "coordinates": [
      21.43333,
      48.25
    ]
  }
}