{
  "type": "Feature",
  "properties": {
    "name": "Medina Estates",
    "country": "GH",
    "subdivision": "01",
    "timezone": "Africa/Accra"
  },
  "geometry": {
    "type": "Point",
    "coordinates": [
      -0.16307,
      5.6658
    ]
  }
}