{
  "type": "Feature",
  "properties": {
    "name": "Achau",
    "country": "AT",
    "subdivision": "03",
    "timezone": "Europe/Vienna"
  },
  "geometry": {
    "type": "Point",
    "coordinates": [
      16.38611,
      48.08026
    ]
  }
}