{
  "type": "Feature",
  "properties": {
    "name": "Alland",
    "country": "AT",
    "subdivision": "03",
    "timezone": "Europe/Vienna"
  },
  "geometry": {
    "type": "Point",
    "coordinates": [
      16.07901,
      48.05829
    ]
  }
}