{
  "type": "Feature",
  "properties": {
    "name": "Allentsteig",
    "country": "AT",
    "subdivision": "03",
    "timezone": "Europe/Vienna"
  },
  "geometry": {
    "type": "Point",
    "coordinates": [
      15.32756,
      48.69725
    ]
  }
}