{
  "type": "Feature",
  "properties": {
    "name": "Biberbach",
    "country": "AT",
    "subdivision": "03",
    "timezone": "Europe/Vienna"
  },
  "geometry": {
    "type": "Point",
    "coordinates": [
      14.70795,
      48.03006
    ]
  }
}