{
  "type": "Feature",
  "properties": {
    "name": "Blindenmarkt",
    "country": "AT",
    "subdivision": "03",
    "timezone": "Europe/Vienna"
  },
  "geometry": {
    "type": "Point",
    "coordinates": [
      14.98647,
      48.12749
    ]
  }
}