{
  "type": "Feature",
  "properties": {
    "name": "Ebergassing",
    "country": "AT",
    "subdivision": "03",
    "timezone": "Europe/Vienna"
  },
  "geometry": {
    "type": "Point",
    "coordinates": [
      16.51709,
      48.04567
    ]
  }
}