{
  "type": "Feature",
  "properties": {
    "name": "Eggendorf",
    "country": "AT",
    "subdivision": "03",
    "timezone": "Europe/Vienna"
  },
  "geometry": {
    "type": "Point",
    "coordinates": [
      16.32182,
      47.85809
    ]
  }
}