{
  "type": "Feature",
  "properties": {
    "name": "Enzersdorf an der Fischa",
    "country": "AT",
    "subdivision": "03",
    "timezone": "Europe/Vienna"
  },
  "geometry": {
    "type": "Point",
    "coordinates": [
      16.60832,
      48.08502
    ]
  }
}