{
  "type": "Feature",
  "properties": {
    "name": "Gablitz",
    "country": "AT",
    "subdivision": "03",
    "timezone": "Europe/Vienna"
  },
  "geometry": {
    "type": "Point",
    "coordinates": [
      16.15437,
      48.22856
    ]
  }
}