{
  "type": "Feature",
  "properties": {
    "name": "Gaming",
    "country": "AT",
    "subdivision": "03",
    "timezone": "Europe/Vienna"
  },
  "geometry": {
    "type": "Point",
    "coordinates": [
      15.08818,
      47.929
    ]
  }
}