{
  "type": "Feature",
  "properties": {
    "name": "Gaweinstal",
    "country": "AT",
    "subdivision": "03",
    "timezone": "Europe/Vienna"
  },
  "geometry": {
    "type": "Point",
    "coordinates": [
      16.5879,
      48.48003
    ]
  }
}