{
  "type": "Feature",
  "properties": {
    "name": "Groß-Enzersdorf",
    "country": "AT",
    "subdivision": "03",
    "timezone": "Europe/Vienna"
  },
  "geometry": {
    "type": "Point",
    "coordinates": [
      16.55083,
      48.20278
    ]
  }
}