{
  "type": "Feature",
  "properties": {
    "name": "Harland",
    "country": "AT",
    "subdivision": "03",
    "timezone": "Europe/Vienna"
  },
  "geometry": {
    "type": "Point",
    "coordinates": [
      15.63835,
      48.16162
    ]
  }
}