{
  "type": "Feature",
  "properties": {
    "name": "Kirchberg am Wechsel",
    "country": "AT",
    "subdivision": "03",
    "timezone": "Europe/Vienna"
  },
  "geometry": {
    "type": "Point",
    "coordinates": [
      15.99103,
      47.60738
    ]
  }
}