{
  "type": "Feature",
  "properties": {
    "name": "Krumbach Markt",
    "country": "AT",
    "subdivision": "03",
    "timezone": "Europe/Vienna"
  },
  "geometry": {
    "type": "Point",
    "coordinates": [
      16.19419,
      47.52183
    ]
  }
}