{
  "type": "Feature",
  "properties": {
    "name": "Langenzersdorf",
    "country": "AT",
    "subdivision": "03",
    "timezone": "Europe/Vienna"
  },
  "geometry": {
    "type": "Point",
    "coordinates": [
      16.36143,
      48.30432
    ]
  }
}