{
  "type": "Feature",
  "properties": {
    "name": "Lerchenfeld",
    "country": "AT",
    "subdivision": "03",
    "timezone": "Europe/Vienna"
  },
  "geometry": {
    "type": "Point",
    "coordinates": [
      15.63183,
      48.41234
    ]
  }
}