{
  "type": "Feature",
  "properties": {
    "name": "Litschau",
    "country": "AT",
    "subdivision": "03",
    "timezone": "Europe/Vienna"
  },
  "geometry": {
    "type": "Point",
    "coordinates": [
      15.04483,
      48.94409
    ]
  }
}