{
  "type": "Feature",
  "properties": {
    "name": "Mautern",
    "country": "AT",
    "subdivision": "03",
    "timezone": "Europe/Vienna"
  },
  "geometry": {
    "type": "Point",
    "coordinates": [
      15.57793,
      48.39319
    ]
  }
}