{
  "type": "Feature",
  "properties": {
    "name": "Michelhausen",
    "country": "AT",
    "subdivision": "03",
    "timezone": "Europe/Vienna"
  },
  "geometry": {
    "type": "Point",
    "coordinates": [
      15.93893,
      48.29085
    ]
  }
}