{
  "type": "Feature",
  "properties": {
    "name": "Oberwaltersdorf",
    "country": "AT",
    "subdivision": "03",
    "timezone": "Europe/Vienna"
  },
  "geometry": {
    "type": "Point",
    "coordinates": [
      16.32191,
      47.97567
    ]
  }
}