{
  "type": "Feature",
  "properties": {
    "name": "Oberhausen",
    "country": "AT",
    "subdivision": "03",
    "timezone": "Europe/Vienna"
  },
  "geometry": {
    "type": "Point",
    "coordinates": [
      16.58506,
      48.1769
    ]
  }
}