{
  "type": "Feature",
  "properties": {
    "name": "Oeynhausen",
    "country": "AT",
    "subdivision": "03",
    "timezone": "Europe/Vienna"
  },
  "geometry": {
    "type": "Point",
    "coordinates": [
      16.29187,
      47.98533
    ]
  }
}