{
  "type": "Feature",
  "properties": {
    "name": "Prellenkirchen",
    "country": "AT",
    "subdivision": "03",
    "timezone": "Europe/Vienna"
  },
  "geometry": {
    "type": "Point",
    "coordinates": [
      16.95233,
      48.07401
    ]
  }
}