{
  "type": "Feature",
  "properties": {
    "name": "Ratzersdorf an der Traisen",
    "country": "AT",
    "subdivision": "03",
    "timezone": "Europe/Vienna"
  },
  "geometry": {
    "type": "Point",
    "coordinates": [
      15.66629,
      48.22639
    ]
  }
}