{
  "type": "Feature",
  "properties": {
    "name": "Sankt Leonhard am Forst",
    "country": "AT",
    "subdivision": "03",
    "timezone": "Europe/Vienna"
  },
  "geometry": {
    "type": "Point",
    "coordinates": [
      15.28464,
      48.14232
    ]
  }
}