{
  "type": "Feature",
  "properties": {
    "name": "Sankt Valentin",
    "country": "AT",
    "subdivision": "03",
    "timezone": "Europe/Vienna"
  },
  "geometry": {
    "type": "Point",
    "coordinates": [
      14.51667,
      48.16667
    ]
  }
}