{
  "type": "Feature",
  "properties": {
    "name": "Scheibbs",
    "country": "AT",
    "subdivision": "03",
    "timezone": "Europe/Vienna"
  },
  "geometry": {
    "type": "Point",
    "coordinates": [
      15.16817,
      48.00474
    ]
  }
}