{
  "type": "Feature",
  "properties": {
    "name": "Schönau an der Triesting",
    "country": "AT",
    "subdivision": "03",
    "timezone": "Europe/Vienna"
  },
  "geometry": {
    "type": "Point",
    "coordinates": [
      16.25376,
      47.93452
    ]
  }
}