{
  "type": "Feature",
  "properties": {
    "name": "Schwadorf",
    "country": "AT",
    "subdivision": "03",
    "timezone": "Europe/Vienna"
  },
  "geometry": {
    "type": "Point",
    "coordinates": [
      16.57957,
      48.06936
    ]
  }
}