{
  "type": "Feature",
  "properties": {
    "name": "Sollenau",
    "country": "AT",
    "subdivision": "03",
    "timezone": "Europe/Vienna"
  },
  "geometry": {
    "type": "Point",
    "coordinates": [
      16.24833,
      47.89834
    ]
  }
}