{
  "type": "Feature",
  "properties": {
    "name": "Wiener Neudorf",
    "country": "AT",
    "subdivision": "03",
    "timezone": "Europe/Vienna"
  },
  "geometry": {
    "type": "Point",
    "coordinates": [
      16.31384,
      48.08278
    ]
  }
}