{
  "type": "Feature",
  "properties": {
    "name": "Wilfleinsdorf",
    "country": "AT",
    "subdivision": "03",
    "timezone": "Europe/Vienna"
  },
  "geometry": {
    "type": "Point",
    "coordinates": [
      16.71667,
      48.01667
    ]
  }
}