{
  "type": "Feature",
  "properties": {
    "name": "Windhag",
    "country": "AT",
    "subdivision": "03",
    "timezone": "Europe/Vienna"
  },
  "geometry": {
    "type": "Point",
    "coordinates": [
      14.80245,
      47.97906
    ]
  }
}