{
  "type": "Feature",
  "properties": {
    "name": "Wolkersdorf im Weinviertel",
    "country": "AT",
    "subdivision": "03",
    "timezone": "Europe/Vienna"
  },
  "geometry": {
    "type": "Point",
    "coordinates": [
      16.51667,
      48.38333
    ]
  }
}