{
  "type": "Feature",
  "properties": {
    "name": "Würflach",
    "country": "AT",
    "subdivision": "03",
    "timezone": "Europe/Vienna"
  },
  "geometry": {
    "type": "Point",
    "coordinates": [
      16.05463,
      47.77648
    ]
  }
}