{
  "type": "Feature",
  "properties": {
    "name": "Ziersdorf",
    "country": "AT",
    "subdivision": "03",
    "timezone": "Europe/Vienna"
  },
  "geometry": {
    "type": "Point",
    "coordinates": [
      15.92691,
      48.5303
    ]
  }
}