{
  "type": "Feature",
  "properties": {
    "name": "Jalqani",
    "country": "SD",
    "subdivision": "58",
    "timezone": "Africa/Khartoum"
  },
  "geometry": {
    "type": "Point",
    "coordinates": [
      34.2186,
      12.4486
    ]
  }
}