{
  "type": "Feature",
  "properties": {
    "name": "Vila Praia de Âncora",
    "country": "PT",
    "subdivision": "20",
    "timezone": "Europe/Lisbon"
  },
  "geometry": {
    "type": "Point",
    "coordinates": [
      -8.85255,
      41.81098
    ]
  }
}