{
  "type": "Feature",
  "properties": {
    "name": "Bouznika",
    "country": "MA",
    "subdivision": "06",
    "timezone": "Africa/Casablanca"
  },
  "geometry": {
    "type": "Point",
    "coordinates": [
      -7.15968,
      33.78942
    ]
  }
}