{
  "type": "Feature",
  "properties": {
    "name": "Zawyat an Nwaçer",
    "country": "MA",
    "subdivision": "06",
    "timezone": "Africa/Casablanca"
  },
  "geometry": {
    "type": "Point",
    "coordinates": [
      -7.61932,
      33.37981
    ]
  }
}