{
  "type": "Feature",
  "properties": {
    "name": "BÄglung",
    "country": "NP",
    "subdivision": "4",
    "timezone": "Asia/Kathmandu"
  },
  "geometry": {
    "type": "Point",
    "coordinates": [
      83.58975,
      28.27189
    ]
  }
}