{
  "type": "Feature",
  "properties": {
    "name": "Taiz",
    "country": "YE",
    "subdivision": "25",
    "timezone": "Asia/Aden"
  },
  "geometry": {
    "type": "Point",
    "coordinates": [
      44.02091,
      13.57952
    ]
  }
}