{
  "type": "Feature",
  "properties": {
    "name": "Sidi Moussa",
    "country": "DZ",
    "subdivision": "01",
    "timezone": "Africa/Algiers"
  },
  "geometry": {
    "type": "Point",
    "coordinates": [
      3.08783,
      36.60637
    ]
  }
}