{
  "type": "Feature",
  "properties": {
    "name": "Zeralda",
    "country": "DZ",
    "subdivision": "01",
    "timezone": "Africa/Algiers"
  },
  "geometry": {
    "type": "Point",
    "coordinates": [
      2.84244,
      36.71169
    ]
  }
}