{
  "type": "Feature",
  "properties": {
    "name": "Briceño",
    "country": "CO",
    "subdivision": "02",
    "timezone": "America/Bogota"
  },
  "geometry": {
    "type": "Point",
    "coordinates": [
      -75.55152,
      7.11096
    ]
  }
}