{
  "type": "Feature",
  "properties": {
    "name": "Concordia",
    "country": "CO",
    "subdivision": "02",
    "timezone": "America/Bogota"
  },
  "geometry": {
    "type": "Point",
    "coordinates": [
      -75.90705,
      6.04639
    ]
  }
}