{
  "type": "Feature",
  "properties": {
    "name": "Envigado",
    "country": "CO",
    "subdivision": "02",
    "timezone": "America/Bogota"
  },
  "geometry": {
    "type": "Point",
    "coordinates": [
      -75.59174,
      6.17591
    ]
  }
}