{
  "type": "Feature",
  "properties": {
    "name": "Jardín",
    "country": "CO",
    "subdivision": "02",
    "timezone": "America/Bogota"
  },
  "geometry": {
    "type": "Point",
    "coordinates": [
      -75.81976,
      5.59902
    ]
  }
}