{
  "type": "Feature",
  "properties": {
    "name": "La Ceja",
    "country": "CO",
    "subdivision": "02",
    "timezone": "America/Bogota"
  },
  "geometry": {
    "type": "Point",
    "coordinates": [
      -75.43333,
      6.03131
    ]
  }
}