{
  "type": "Feature",
  "properties": {
    "name": "Santuario",
    "country": "CO",
    "subdivision": "02",
    "timezone": "America/Bogota"
  },
  "geometry": {
    "type": "Point",
    "coordinates": [
      -75.26417,
      6.13833
    ]
  }
}