{
  "type": "Feature",
  "properties": {
    "name": "Vegachí",
    "country": "CO",
    "subdivision": "02",
    "timezone": "America/Bogota"
  },
  "geometry": {
    "type": "Point",
    "coordinates": [
      -74.79473,
      6.76141
    ]
  }
}