{
  "type": "Feature",
  "properties": {
    "name": "Yalí",
    "country": "CO",
    "subdivision": "02",
    "timezone": "America/Bogota"
  },
  "geometry": {
    "type": "Point",
    "coordinates": [
      -74.8343,
      6.67457
    ]
  }
}