{
  "type": "Feature",
  "properties": {
    "name": "Egvekinot",
    "country": "RU",
    "subdivision": "15",
    "timezone": "Asia/Anadyr"
  },
  "geometry": {
    "type": "Point",
    "coordinates": [
      -179.12198,
      66.32166
    ]
  }
}