{
  "type": "Feature",
  "properties": {
    "name": "Lorino",
    "country": "RU",
    "subdivision": "15",
    "timezone": "Asia/Anadyr"
  },
  "geometry": {
    "type": "Point",
    "coordinates": [
      -171.70387,
      65.50306
    ]
  }
}