{
  "type": "Feature",
  "properties": {
    "name": "Pevek",
    "country": "RU",
    "subdivision": "15",
    "timezone": "Asia/Anadyr"
  },
  "geometry": {
    "type": "Point",
    "coordinates": [
      170.29993,
      69.70287
    ]
  }
}