{
  "type": "Feature",
  "properties": {
    "name": "Merchweiler",
    "country": "DE",
    "subdivision": "09",
    "timezone": "Europe/Berlin"
  },
  "geometry": {
    "type": "Point",
    "coordinates": [
      7.05,
      49.35
    ]
  }
}