{
  "type": "Feature",
  "properties": {
    "name": "Namborn",
    "country": "DE",
    "subdivision": "09",
    "timezone": "Europe/Berlin"
  },
  "geometry": {
    "type": "Point",
    "coordinates": [
      7.1407,
      49.52166
    ]
  }
}