{
  "type": "Feature",
  "properties": {
    "name": "Neunkirchen",
    "country": "DE",
    "subdivision": "09",
    "timezone": "Europe/Berlin"
  },
  "geometry": {
    "type": "Point",
    "coordinates": [
      7.18045,
      49.34449
    ]
  }
}