{
  "type": "Feature",
  "properties": {
    "name": "Schiffweiler",
    "country": "DE",
    "subdivision": "09",
    "timezone": "Europe/Berlin"
  },
  "geometry": {
    "type": "Point",
    "coordinates": [
      7.13333,
      49.36667
    ]
  }
}