{
  "type": "Feature",
  "properties": {
    "name": "Barturyn",
    "country": "UA",
    "subdivision": "02",
    "timezone": "Europe/Kiev"
  },
  "geometry": {
    "type": "Point",
    "coordinates": [
      32.87794,
      51.34567
    ]
  }
}