{
  "type": "Feature",
  "properties": {
    "name": "Kholmy",
    "country": "UA",
    "subdivision": "02",
    "timezone": "Europe/Kiev"
  },
  "geometry": {
    "type": "Point",
    "coordinates": [
      32.60063,
      51.87096
    ]
  }
}