{
  "type": "Feature",
  "properties": {
    "name": "Ripky",
    "country": "UA",
    "subdivision": "02",
    "timezone": "Europe/Kiev"
  },
  "geometry": {
    "type": "Point",
    "coordinates": [
      31.08383,
      51.80105
    ]
  }
}