{
  "type": "Feature",
  "properties": {
    "name": "Talalaivka",
    "country": "UA",
    "subdivision": "02",
    "timezone": "Europe/Kiev"
  },
  "geometry": {
    "type": "Point",
    "coordinates": [
      31.92085,
      50.95783
    ]
  }
}