{
  "type": "Feature",
  "properties": {
    "name": "Zhuravka",
    "country": "UA",
    "subdivision": "02",
    "timezone": "Europe/Kiev"
  },
  "geometry": {
    "type": "Point",
    "coordinates": [
      32.5949,
      50.48108
    ]
  }
}