{
  "type": "Feature",
  "properties": {
    "name": "Courfaivre",
    "country": "CH",
    "subdivision": "JU",
    "timezone": "Europe/Zurich"
  },
  "geometry": {
    "type": "Point",
    "coordinates": [
      7.28186,
      47.33461
    ]
  }
}