{
  "type": "Feature",
  "properties": {
    "name": "Altamont",
    "country": "US",
    "subdivision": "KS",
    "timezone": "America/Chicago"
  },
  "geometry": {
    "type": "Point",
    "coordinates": [
      -95.29719,
      37.19034
    ]
  }
}