{
  "type": "Feature",
  "properties": {
    "name": "Goddard",
    "country": "US",
    "subdivision": "KS",
    "timezone": "America/Chicago"
  },
  "geometry": {
    "type": "Point",
    "coordinates": [
      -97.57533,
      37.65974
    ]
  }
}