{
  "type": "Feature",
  "properties": {
    "name": "Haysville",
    "country": "US",
    "subdivision": "KS",
    "timezone": "America/Chicago"
  },
  "geometry": {
    "type": "Point",
    "coordinates": [
      -97.35227,
      37.56446
    ]
  }
}