{
  "type": "Feature",
  "properties": {
    "name": "Kinsley",
    "country": "US",
    "subdivision": "KS",
    "timezone": "America/Chicago"
  },
  "geometry": {
    "type": "Point",
    "coordinates": [
      -99.40984,
      37.92307
    ]
  }
}