{
  "type": "Feature",
  "properties": {
    "name": "Minneapolis",
    "country": "US",
    "subdivision": "KS",
    "timezone": "America/Chicago"
  },
  "geometry": {
    "type": "Point",
    "coordinates": [
      -97.7067,
      39.12194
    ]
  }
}