{
  "type": "Feature",
  "properties": {
    "name": "Mission",
    "country": "US",
    "subdivision": "KS",
    "timezone": "America/Chicago"
  },
  "geometry": {
    "type": "Point",
    "coordinates": [
      -94.65579,
      39.02778
    ]
  }
}