{
  "type": "Feature",
  "properties": {
    "name": "Newton",
    "country": "US",
    "subdivision": "KS",
    "timezone": "America/Chicago"
  },
  "geometry": {
    "type": "Point",
    "coordinates": [
      -97.34504,
      38.04668
    ]
  }
}