{
  "type": "Feature",
  "properties": {
    "name": "Oberlin",
    "country": "US",
    "subdivision": "KS",
    "timezone": "America/Chicago"
  },
  "geometry": {
    "type": "Point",
    "coordinates": [
      -100.5282,
      39.81834
    ]
  }
}