{
  "type": "Feature",
  "properties": {
    "name": "Ottawa",
    "country": "US",
    "subdivision": "KS",
    "timezone": "America/Chicago"
  },
  "geometry": {
    "type": "Point",
    "coordinates": [
      -95.26775,
      38.61557
    ]
  }
}