{
  "type": "Feature",
  "properties": {
    "name": "Pratt",
    "country": "US",
    "subdivision": "KS",
    "timezone": "America/Chicago"
  },
  "geometry": {
    "type": "Point",
    "coordinates": [
      -98.73759,
      37.64391
    ]
  }
}