{
  "type": "Feature",
  "properties": {
    "name": "Roeland Park",
    "country": "US",
    "subdivision": "KS",
    "timezone": "America/Chicago"
  },
  "geometry": {
    "type": "Point",
    "coordinates": [
      -94.63218,
      39.03751
    ]
  }
}