{
  "type": "Feature",
  "properties": {
    "name": "Saint Marys",
    "country": "US",
    "subdivision": "KS",
    "timezone": "America/Chicago"
  },
  "geometry": {
    "type": "Point",
    "coordinates": [
      -96.0711,
      39.19416
    ]
  }
}