{
  "type": "Feature",
  "properties": {
    "name": "Satanta",
    "country": "US",
    "subdivision": "KS",
    "timezone": "America/Chicago"
  },
  "geometry": {
    "type": "Point",
    "coordinates": [
      -100.97211,
      37.43725
    ]
  }
}