{
  "type": "Feature",
  "properties": {
    "name": "Smith Center",
    "country": "US",
    "subdivision": "KS",
    "timezone": "America/Chicago"
  },
  "geometry": {
    "type": "Point",
    "coordinates": [
      -98.78507,
      39.77918
    ]
  }
}