{
  "type": "Feature",
  "properties": {
    "name": "Valley Falls",
    "country": "US",
    "subdivision": "KS",
    "timezone": "America/Chicago"
  },
  "geometry": {
    "type": "Point",
    "coordinates": [
      -95.46025,
      39.34333
    ]
  }
}