{
  "type": "Feature",
  "properties": {
    "name": "Wellington",
    "country": "US",
    "subdivision": "KS",
    "timezone": "America/Chicago"
  },
  "geometry": {
    "type": "Point",
    "coordinates": [
      -97.37171,
      37.2653
    ]
  }
}