{
  "type": "Feature",
  "properties": {
    "name": "Cornwall",
    "country": "CA",
    "subdivision": "09",
    "timezone": "America/Halifax"
  },
  "geometry": {
    "type": "Point",
    "coordinates": [
      -63.21809,
      46.22652
    ]
  }
}