{
  "type": "Feature",
  "properties": {
    "name": "Barboursville",
    "country": "US",
    "subdivision": "WV",
    "timezone": "America/New_York"
  },
  "geometry": {
    "type": "Point",
    "coordinates": [
      -82.29459,
      38.40953
    ]
  }
}