{
  "type": "Feature",
  "properties": {
    "name": "Bridgeport",
    "country": "US",
    "subdivision": "WV",
    "timezone": "America/New_York"
  },
  "geometry": {
    "type": "Point",
    "coordinates": [
      -80.2562,
      39.28648
    ]
  }
}