{
  "type": "Feature",
  "properties": {
    "name": "Brookhaven",
    "country": "US",
    "subdivision": "WV",
    "timezone": "America/New_York"
  },
  "geometry": {
    "type": "Point",
    "coordinates": [
      -79.90451,
      39.61175
    ]
  }
}