{
  "type": "Feature",
  "properties": {
    "name": "Dunbar",
    "country": "US",
    "subdivision": "WV",
    "timezone": "America/New_York"
  },
  "geometry": {
    "type": "Point",
    "coordinates": [
      -81.73735,
      38.36065
    ]
  }
}