{
  "type": "Feature",
  "properties": {
    "name": "Follansbee",
    "country": "US",
    "subdivision": "WV",
    "timezone": "America/New_York"
  },
  "geometry": {
    "type": "Point",
    "coordinates": [
      -80.59591,
      40.32757
    ]
  }
}