{
  "type": "Feature",
  "properties": {
    "name": "Gilbert Creek",
    "country": "US",
    "subdivision": "WV",
    "timezone": "America/New_York"
  },
  "geometry": {
    "type": "Point",
    "coordinates": [
      -81.89484,
      37.57594
    ]
  }
}