{
  "type": "Feature",
  "properties": {
    "name": "Granville",
    "country": "US",
    "subdivision": "WV",
    "timezone": "America/New_York"
  },
  "geometry": {
    "type": "Point",
    "coordinates": [
      -79.98729,
      39.64591
    ]
  }
}