{
  "type": "Feature",
  "properties": {
    "name": "Kingwood",
    "country": "US",
    "subdivision": "WV",
    "timezone": "America/New_York"
  },
  "geometry": {
    "type": "Point",
    "coordinates": [
      -79.68339,
      39.47176
    ]
  }
}