{
  "type": "Feature",
  "properties": {
    "name": "Lubeck",
    "country": "US",
    "subdivision": "WV",
    "timezone": "America/New_York"
  },
  "geometry": {
    "type": "Point",
    "coordinates": [
      -81.63124,
      39.23535
    ]
  }
}