{
  "type": "Feature",
  "properties": {
    "name": "Mannington",
    "country": "US",
    "subdivision": "WV",
    "timezone": "America/New_York"
  },
  "geometry": {
    "type": "Point",
    "coordinates": [
      -80.34342,
      39.53092
    ]
  }
}