{
  "type": "Feature",
  "properties": {
    "name": "McMechen",
    "country": "US",
    "subdivision": "WV",
    "timezone": "America/New_York"
  },
  "geometry": {
    "type": "Point",
    "coordinates": [
      -80.73147,
      39.98813
    ]
  }
}