{
  "type": "Feature",
  "properties": {
    "name": "Moundsville",
    "country": "US",
    "subdivision": "WV",
    "timezone": "America/New_York"
  },
  "geometry": {
    "type": "Point",
    "coordinates": [
      -80.74314,
      39.92035
    ]
  }
}