{
  "type": "Feature",
  "properties": {
    "name": "Oceana",
    "country": "US",
    "subdivision": "WV",
    "timezone": "America/New_York"
  },
  "geometry": {
    "type": "Point",
    "coordinates": [
      -81.624,
      37.69206
    ]
  }
}