{
  "type": "Feature",
  "properties": {
    "name": "Princeton",
    "country": "US",
    "subdivision": "WV",
    "timezone": "America/New_York"
  },
  "geometry": {
    "type": "Point",
    "coordinates": [
      -81.10259,
      37.36623
    ]
  }
}