{
  "type": "Feature",
  "properties": {
    "name": "Prosperity",
    "country": "US",
    "subdivision": "WV",
    "timezone": "America/New_York"
  },
  "geometry": {
    "type": "Point",
    "coordinates": [
      -81.20177,
      37.8365
    ]
  }
}