{
  "type": "Feature",
  "properties": {
    "name": "Rainelle",
    "country": "US",
    "subdivision": "WV",
    "timezone": "America/New_York"
  },
  "geometry": {
    "type": "Point",
    "coordinates": [
      -80.76703,
      37.96873
    ]
  }
}