{
  "type": "Feature",
  "properties": {
    "name": "Rand",
    "country": "US",
    "subdivision": "WV",
    "timezone": "America/New_York"
  },
  "geometry": {
    "type": "Point",
    "coordinates": [
      -81.56234,
      38.2826
    ]
  }
}