{
  "type": "Feature",
  "properties": {
    "name": "Ronceverte",
    "country": "US",
    "subdivision": "WV",
    "timezone": "America/New_York"
  },
  "geometry": {
    "type": "Point",
    "coordinates": [
      -80.46285,
      37.74984
    ]
  }
}