{
  "type": "Feature",
  "properties": {
    "name": "Saint Marys",
    "country": "US",
    "subdivision": "WV",
    "timezone": "America/New_York"
  },
  "geometry": {
    "type": "Point",
    "coordinates": [
      -81.20511,
      39.39174
    ]
  }
}