{
  "type": "Feature",
  "properties": {
    "name": "South Charleston",
    "country": "US",
    "subdivision": "WV",
    "timezone": "America/New_York"
  },
  "geometry": {
    "type": "Point",
    "coordinates": [
      -81.69957,
      38.36843
    ]
  }
}