{
  "type": "Feature",
  "properties": {
    "name": "Washington",
    "country": "US",
    "subdivision": "WV",
    "timezone": "America/New_York"
  },
  "geometry": {
    "type": "Point",
    "coordinates": [
      -81.6718,
      39.26119
    ]
  }
}