{
  "type": "Feature",
  "properties": {
    "name": "Weirton",
    "country": "US",
    "subdivision": "WV",
    "timezone": "America/New_York"
  },
  "geometry": {
    "type": "Point",
    "coordinates": [
      -80.58952,
      40.41896
    ]
  }
}