{
  "type": "Feature",
  "properties": {
    "name": "Welch",
    "country": "US",
    "subdivision": "WV",
    "timezone": "America/New_York"
  },
  "geometry": {
    "type": "Point",
    "coordinates": [
      -81.58455,
      37.43289
    ]
  }
}