{
  "type": "Feature",
  "properties": {
    "name": "Winfield",
    "country": "US",
    "subdivision": "WV",
    "timezone": "America/New_York"
  },
  "geometry": {
    "type": "Point",
    "coordinates": [
      -81.89347,
      38.53314
    ]
  }
}