{
  "type": "Feature",
  "properties": {
    "name": "Chaoyang",
    "country": "CN",
    "subdivision": "05",
    "timezone": "Asia/Shanghai"
  },
  "geometry": {
    "type": "Point",
    "coordinates": [
      126.0263,
      42.66223
    ]
  }
}