{
  "type": "Feature",
  "properties": {
    "name": "Kaitong",
    "country": "CN",
    "subdivision": "05",
    "timezone": "Asia/Shanghai"
  },
  "geometry": {
    "type": "Point",
    "coordinates": [
      123.08108,
      44.80913
    ]
  }
}