{
  "type": "Feature",
  "properties": {
    "name": "Lishu",
    "country": "CN",
    "subdivision": "05",
    "timezone": "Asia/Shanghai"
  },
  "geometry": {
    "type": "Point",
    "coordinates": [
      124.32778,
      43.30472
    ]
  }
}