{
  "type": "Feature",
  "properties": {
    "name": "Meihekou",
    "country": "CN",
    "subdivision": "05",
    "timezone": "Asia/Shanghai"
  },
  "geometry": {
    "type": "Point",
    "coordinates": [
      125.67528,
      42.52722
    ]
  }
}