{
  "type": "Feature",
  "properties": {
    "name": "Songyuan",
    "country": "CN",
    "subdivision": "05",
    "timezone": "Asia/Shanghai"
  },
  "geometry": {
    "type": "Point",
    "coordinates": [
      124.82769,
      45.12902
    ]
  }
}