{
  "type": "Feature",
  "properties": {
    "name": "Caraballeda",
    "country": "VE",
    "subdivision": "26",
    "timezone": "America/Caracas"
  },
  "geometry": {
    "type": "Point",
    "coordinates": [
      -66.85192,
      10.61216
    ]
  }
}