{
  "type": "Feature",
  "properties": {
    "name": "Kızılcasöğüt",
    "country": "TR",
    "subdivision": "64",
    "timezone": "Europe/Istanbul"
  },
  "geometry": {
    "type": "Point",
    "coordinates": [
      29.66611,
      38.65111
    ]
  }
}