{
  "type": "Feature",
  "properties": {
    "name": "Sivaslı",
    "country": "TR",
    "subdivision": "64",
    "timezone": "Europe/Istanbul"
  },
  "geometry": {
    "type": "Point",
    "coordinates": [
      29.68361,
      38.49944
    ]
  }
}