{
  "type": "Feature",
  "properties": {
    "name": "Trongsa",
    "country": "BT",
    "subdivision": "21",
    "timezone": "Asia/Thimphu"
  },
  "geometry": {
    "type": "Point",
    "coordinates": [
      90.50716,
      27.5026
    ]
  }
}