{
  "type": "Feature",
  "properties": {
    "name": "Chester Center",
    "country": "US",
    "subdivision": "CT",
    "timezone": "America/New_York"
  },
  "geometry": {
    "type": "Point",
    "coordinates": [
      -72.4527,
      41.40132
    ]
  }
}