{
  "type": "Feature",
  "properties": {
    "name": "Hartford",
    "country": "US",
    "subdivision": "CT",
    "timezone": "America/New_York"
  },
  "geometry": {
    "type": "Point",
    "coordinates": [
      -72.68509,
      41.76371
    ]
  }
}