{
  "type": "Feature",
  "properties": {
    "name": "Hebron",
    "country": "US",
    "subdivision": "CT",
    "timezone": "America/New_York"
  },
  "geometry": {
    "type": "Point",
    "coordinates": [
      -72.36592,
      41.65788
    ]
  }
}