{
  "type": "Feature",
  "properties": {
    "name": "Moodus",
    "country": "US",
    "subdivision": "CT",
    "timezone": "America/New_York"
  },
  "geometry": {
    "type": "Point",
    "coordinates": [
      -72.45009,
      41.50288
    ]
  }
}