{
  "type": "Feature",
  "properties": {
    "name": "Mystic",
    "country": "US",
    "subdivision": "CT",
    "timezone": "America/New_York"
  },
  "geometry": {
    "type": "Point",
    "coordinates": [
      -71.96646,
      41.35427
    ]
  }
}