{
  "type": "Feature",
  "properties": {
    "name": "Naugatuck",
    "country": "US",
    "subdivision": "CT",
    "timezone": "America/New_York"
  },
  "geometry": {
    "type": "Point",
    "coordinates": [
      -73.05066,
      41.48593
    ]
  }
}