{
  "type": "Feature",
  "properties": {
    "name": "Oakville",
    "country": "US",
    "subdivision": "CT",
    "timezone": "America/New_York"
  },
  "geometry": {
    "type": "Point",
    "coordinates": [
      -73.08539,
      41.59343
    ]
  }
}