{
  "type": "Feature",
  "properties": {
    "name": "Oxford",
    "country": "US",
    "subdivision": "CT",
    "timezone": "America/New_York"
  },
  "geometry": {
    "type": "Point",
    "coordinates": [
      -73.11678,
      41.43399
    ]
  }
}