{
  "type": "Feature",
  "properties": {
    "name": "Pemberwick",
    "country": "US",
    "subdivision": "CT",
    "timezone": "America/New_York"
  },
  "geometry": {
    "type": "Point",
    "coordinates": [
      -73.66068,
      41.02565
    ]
  }
}