{
  "type": "Feature",
  "properties": {
    "name": "Plainville",
    "country": "US",
    "subdivision": "CT",
    "timezone": "America/New_York"
  },
  "geometry": {
    "type": "Point",
    "coordinates": [
      -72.85816,
      41.67454
    ]
  }
}