{
  "type": "Feature",
  "properties": {
    "name": "Seymour",
    "country": "US",
    "subdivision": "CT",
    "timezone": "America/New_York"
  },
  "geometry": {
    "type": "Point",
    "coordinates": [
      -73.07594,
      41.39676
    ]
  }
}