{
  "type": "Feature",
  "properties": {
    "name": "Southport",
    "country": "US",
    "subdivision": "CT",
    "timezone": "America/New_York"
  },
  "geometry": {
    "type": "Point",
    "coordinates": [
      -73.28345,
      41.13649
    ]
  }
}