{
  "type": "Feature",
  "properties": {
    "name": "Storrs",
    "country": "US",
    "subdivision": "CT",
    "timezone": "America/New_York"
  },
  "geometry": {
    "type": "Point",
    "coordinates": [
      -72.24952,
      41.80843
    ]
  }
}