{
  "type": "Feature",
  "properties": {
    "name": "Tariffville",
    "country": "US",
    "subdivision": "CT",
    "timezone": "America/New_York"
  },
  "geometry": {
    "type": "Point",
    "coordinates": [
      -72.7601,
      41.90871
    ]
  }
}