{
  "type": "Feature",
  "properties": {
    "name": "Thompsonville",
    "country": "US",
    "subdivision": "CT",
    "timezone": "America/New_York"
  },
  "geometry": {
    "type": "Point",
    "coordinates": [
      -72.59898,
      41.99704
    ]
  }
}