{
  "type": "Feature",
  "properties": {
    "name": "Kilis",
    "country": "TR",
    "subdivision": "90",
    "timezone": "Europe/Istanbul"
  },
  "geometry": {
    "type": "Point",
    "coordinates": [
      37.115,
      36.71611
    ]
  }
}