{
  "type": "Feature",
  "properties": {
    "name": "Baru Mic",
    "country": "RO",
    "subdivision": "21",
    "timezone": "Europe/Bucharest"
  },
  "geometry": {
    "type": "Point",
    "coordinates": [
      23.15,
      45.46667
    ]
  }
}