{
  "type": "Feature",
  "properties": {
    "name": "Lunca Cernii de Jos",
    "country": "RO",
    "subdivision": "21",
    "timezone": "Europe/Bucharest"
  },
  "geometry": {
    "type": "Point",
    "coordinates": [
      22.61667,
      45.63333
    ]
  }
}