{
  "type": "Feature",
  "properties": {
    "name": "Lupeni",
    "country": "RO",
    "subdivision": "21",
    "timezone": "Europe/Bucharest"
  },
  "geometry": {
    "type": "Point",
    "coordinates": [
      23.23832,
      45.36029
    ]
  }
}