{
  "type": "Feature",
  "properties": {
    "name": "Uricani",
    "country": "RO",
    "subdivision": "21",
    "timezone": "Europe/Bucharest"
  },
  "geometry": {
    "type": "Point",
    "coordinates": [
      23.1524,
      45.33731
    ]
  }
}