{
  "type": "Feature",
  "properties": {
    "name": "Vălişoara",
    "country": "RO",
    "subdivision": "21",
    "timezone": "Europe/Bucharest"
  },
  "geometry": {
    "type": "Point",
    "coordinates": [
      22.85,
      46.05
    ]
  }
}