{
  "type": "Feature",
  "properties": {
    "name": "Djamaa",
    "country": "DZ",
    "subdivision": "MG",
    "timezone": "Africa/Algiers"
  },
  "geometry": {
    "type": "Point",
    "coordinates": [
      5.99306,
      33.53388
    ]
  }
}