{
  "type": "Feature",
  "properties": {
    "name": "El Meghaïer",
    "country": "DZ",
    "subdivision": "MG",
    "timezone": "Africa/Algiers"
  },
  "geometry": {
    "type": "Point",
    "coordinates": [
      5.92927,
      33.95304
    ]
  }
}