{
  "type": "Feature",
  "properties": {
    "name": "Anadarko",
    "country": "US",
    "subdivision": "OK",
    "timezone": "America/Chicago"
  },
  "geometry": {
    "type": "Point",
    "coordinates": [
      -98.24366,
      35.07256
    ]
  }
}