{
  "type": "Feature",
  "properties": {
    "name": "Catoosa",
    "country": "US",
    "subdivision": "OK",
    "timezone": "America/Chicago"
  },
  "geometry": {
    "type": "Point",
    "coordinates": [
      -95.74582,
      36.18899
    ]
  }
}