{
  "type": "Feature",
  "properties": {
    "name": "Claremore",
    "country": "US",
    "subdivision": "OK",
    "timezone": "America/Chicago"
  },
  "geometry": {
    "type": "Point",
    "coordinates": [
      -95.61609,
      36.3126
    ]
  }
}