{
  "type": "Feature",
  "properties": {
    "name": "Collinsville",
    "country": "US",
    "subdivision": "OK",
    "timezone": "America/Chicago"
  },
  "geometry": {
    "type": "Point",
    "coordinates": [
      -95.83888,
      36.36454
    ]
  }
}