{
  "type": "Feature",
  "properties": {
    "name": "Drumright",
    "country": "US",
    "subdivision": "OK",
    "timezone": "America/Chicago"
  },
  "geometry": {
    "type": "Point",
    "coordinates": [
      -96.60113,
      35.9884
    ]
  }
}