{
  "type": "Feature",
  "properties": {
    "name": "Enid",
    "country": "US",
    "subdivision": "OK",
    "timezone": "America/Chicago"
  },
  "geometry": {
    "type": "Point",
    "coordinates": [
      -97.87839,
      36.39559
    ]
  }
}