{
  "type": "Feature",
  "properties": {
    "name": "Fairview",
    "country": "US",
    "subdivision": "OK",
    "timezone": "America/Chicago"
  },
  "geometry": {
    "type": "Point",
    "coordinates": [
      -98.4798,
      36.26892
    ]
  }
}