{
  "type": "Feature",
  "properties": {
    "name": "Fairfax",
    "country": "US",
    "subdivision": "OK",
    "timezone": "America/Chicago"
  },
  "geometry": {
    "type": "Point",
    "coordinates": [
      -96.7042,
      36.57366
    ]
  }
}