{
  "type": "Feature",
  "properties": {
    "name": "Goldsby",
    "country": "US",
    "subdivision": "OK",
    "timezone": "America/Chicago"
  },
  "geometry": {
    "type": "Point",
    "coordinates": [
      -97.47698,
      35.14118
    ]
  }
}