{
  "type": "Feature",
  "properties": {
    "name": "Granite",
    "country": "US",
    "subdivision": "OK",
    "timezone": "America/Chicago"
  },
  "geometry": {
    "type": "Point",
    "coordinates": [
      -99.38064,
      34.96228
    ]
  }
}