{
  "type": "Feature",
  "properties": {
    "name": "Grove",
    "country": "US",
    "subdivision": "OK",
    "timezone": "America/Chicago"
  },
  "geometry": {
    "type": "Point",
    "coordinates": [
      -94.76912,
      36.59369
    ]
  }
}