{
  "type": "Feature",
  "properties": {
    "name": "Hall Park",
    "country": "US",
    "subdivision": "OK",
    "timezone": "America/Chicago"
  },
  "geometry": {
    "type": "Point",
    "coordinates": [
      -97.40642,
      35.23701
    ]
  }
}