{
  "type": "Feature",
  "properties": {
    "name": "Harrah",
    "country": "US",
    "subdivision": "OK",
    "timezone": "America/Chicago"
  },
  "geometry": {
    "type": "Point",
    "coordinates": [
      -97.16364,
      35.48951
    ]
  }
}