{
  "type": "Feature",
  "properties": {
    "name": "Hennessey",
    "country": "US",
    "subdivision": "OK",
    "timezone": "America/Chicago"
  },
  "geometry": {
    "type": "Point",
    "coordinates": [
      -97.89867,
      36.1092
    ]
  }
}