{
  "type": "Feature",
  "properties": {
    "name": "Kellyville",
    "country": "US",
    "subdivision": "OK",
    "timezone": "America/Chicago"
  },
  "geometry": {
    "type": "Point",
    "coordinates": [
      -96.21361,
      35.9437
    ]
  }
}