{
  "type": "Feature",
  "properties": {
    "name": "Kenwood",
    "country": "US",
    "subdivision": "OK",
    "timezone": "America/Chicago"
  },
  "geometry": {
    "type": "Point",
    "coordinates": [
      -94.98579,
      36.31453
    ]
  }
}