{
  "type": "Feature",
  "properties": {
    "name": "Kiefer",
    "country": "US",
    "subdivision": "OK",
    "timezone": "America/Chicago"
  },
  "geometry": {
    "type": "Point",
    "coordinates": [
      -96.06528,
      35.94482
    ]
  }
}