{
  "type": "Feature",
  "properties": {
    "name": "Konawa",
    "country": "US",
    "subdivision": "OK",
    "timezone": "America/Chicago"
  },
  "geometry": {
    "type": "Point",
    "coordinates": [
      -96.7528,
      34.95953
    ]
  }
}