{
  "type": "Feature",
  "properties": {
    "name": "Mangum",
    "country": "US",
    "subdivision": "OK",
    "timezone": "America/Chicago"
  },
  "geometry": {
    "type": "Point",
    "coordinates": [
      -99.50426,
      34.872
    ]
  }
}