{
  "type": "Feature",
  "properties": {
    "name": "McLoud",
    "country": "US",
    "subdivision": "OK",
    "timezone": "America/Chicago"
  },
  "geometry": {
    "type": "Point",
    "coordinates": [
      -97.09142,
      35.4359
    ]
  }
}