{
  "type": "Feature",
  "properties": {
    "name": "Meridian",
    "country": "US",
    "subdivision": "OK",
    "timezone": "America/Chicago"
  },
  "geometry": {
    "type": "Point",
    "coordinates": [
      -97.97809,
      34.42731
    ]
  }
}