{
  "type": "Feature",
  "properties": {
    "name": "Mooreland",
    "country": "US",
    "subdivision": "OK",
    "timezone": "America/Chicago"
  },
  "geometry": {
    "type": "Point",
    "coordinates": [
      -99.20482,
      36.4392
    ]
  }
}