{
  "type": "Feature",
  "properties": {
    "name": "Oklahoma City",
    "country": "US",
    "subdivision": "OK",
    "timezone": "America/Chicago"
  },
  "geometry": {
    "type": "Point",
    "coordinates": [
      -97.51643,
      35.46756
    ]
  }
}