{
  "type": "Feature",
  "properties": {
    "name": "Panama",
    "country": "US",
    "subdivision": "OK",
    "timezone": "America/Chicago"
  },
  "geometry": {
    "type": "Point",
    "coordinates": [
      -94.67245,
      35.16732
    ]
  }
}