{
  "type": "Feature",
  "properties": {
    "name": "Park Hill",
    "country": "US",
    "subdivision": "OK",
    "timezone": "America/Chicago"
  },
  "geometry": {
    "type": "Point",
    "coordinates": [
      -94.95884,
      35.8612
    ]
  }
}