{
  "type": "Feature",
  "properties": {
    "name": "Perry",
    "country": "US",
    "subdivision": "OK",
    "timezone": "America/Chicago"
  },
  "geometry": {
    "type": "Point",
    "coordinates": [
      -97.2881,
      36.28949
    ]
  }
}