{
  "type": "Feature",
  "properties": {
    "name": "Rush Springs",
    "country": "US",
    "subdivision": "OK",
    "timezone": "America/Chicago"
  },
  "geometry": {
    "type": "Point",
    "coordinates": [
      -97.95698,
      34.78257
    ]
  }
}