{
  "type": "Feature",
  "properties": {
    "name": "Shawnee",
    "country": "US",
    "subdivision": "OK",
    "timezone": "America/Chicago"
  },
  "geometry": {
    "type": "Point",
    "coordinates": [
      -96.9253,
      35.32729
    ]
  }
}