{
  "type": "Feature",
  "properties": {
    "name": "Slaughterville",
    "country": "US",
    "subdivision": "OK",
    "timezone": "America/Chicago"
  },
  "geometry": {
    "type": "Point",
    "coordinates": [
      -97.33503,
      35.08729
    ]
  }
}