{
  "type": "Feature",
  "properties": {
    "name": "Spencer",
    "country": "US",
    "subdivision": "OK",
    "timezone": "America/Chicago"
  },
  "geometry": {
    "type": "Point",
    "coordinates": [
      -97.37726,
      35.52284
    ]
  }
}