{
  "type": "Feature",
  "properties": {
    "name": "Stillwater",
    "country": "US",
    "subdivision": "OK",
    "timezone": "America/Chicago"
  },
  "geometry": {
    "type": "Point",
    "coordinates": [
      -97.05837,
      36.11561
    ]
  }
}