{
  "type": "Feature",
  "properties": {
    "name": "Tulsa",
    "country": "US",
    "subdivision": "OK",
    "timezone": "America/Chicago"
  },
  "geometry": {
    "type": "Point",
    "coordinates": [
      -95.99277,
      36.15398
    ]
  }
}