{
  "type": "Feature",
  "properties": {
    "name": "Turley",
    "country": "US",
    "subdivision": "OK",
    "timezone": "America/Chicago"
  },
  "geometry": {
    "type": "Point",
    "coordinates": [
      -95.97583,
      36.24204
    ]
  }
}