{
  "type": "Feature",
  "properties": {
    "name": "Weatherford",
    "country": "US",
    "subdivision": "OK",
    "timezone": "America/Chicago"
  },
  "geometry": {
    "type": "Point",
    "coordinates": [
      -98.70757,
      35.52616
    ]
  }
}