{
  "type": "Feature",
  "properties": {
    "name": "Isieke",
    "country": "NG",
    "subdivision": "53",
    "timezone": "Africa/Lagos"
  },
  "geometry": {
    "type": "Point",
    "coordinates": [
      8.03736,
      6.38186
    ]
  }
}