{
  "type": "Feature",
  "properties": {
    "name": "Banfora",
    "country": "BF",
    "subdivision": "02",
    "timezone": "Africa/Ouagadougou"
  },
  "geometry": {
    "type": "Point",
    "coordinates": [
      -4.76667,
      10.63333
    ]
  }
}