{
  "type": "Feature",
  "properties": {
    "name": "Berkley",
    "country": "US",
    "subdivision": "CO",
    "timezone": "America/Denver"
  },
  "geometry": {
    "type": "Point",
    "coordinates": [
      -105.02609,
      39.80443
    ]
  }
}