{
  "type": "Feature",
  "properties": {
    "name": "Boulder",
    "country": "US",
    "subdivision": "CO",
    "timezone": "America/Denver"
  },
  "geometry": {
    "type": "Point",
    "coordinates": [
      -105.27055,
      40.01499
    ]
  }
}