{
  "type": "Feature",
  "properties": {
    "name": "Buena Vista",
    "country": "US",
    "subdivision": "CO",
    "timezone": "America/Denver"
  },
  "geometry": {
    "type": "Point",
    "coordinates": [
      -106.13113,
      38.84222
    ]
  }
}