{
  "type": "Feature",
  "properties": {
    "name": "Centennial",
    "country": "US",
    "subdivision": "CO",
    "timezone": "America/Denver"
  },
  "geometry": {
    "type": "Point",
    "coordinates": [
      -104.87692,
      39.57916
    ]
  }
}