{
  "type": "Feature",
  "properties": {
    "name": "Cortez",
    "country": "US",
    "subdivision": "CO",
    "timezone": "America/Denver"
  },
  "geometry": {
    "type": "Point",
    "coordinates": [
      -108.58593,
      37.34888
    ]
  }
}