{
  "type": "Feature",
  "properties": {
    "name": "Crested Butte",
    "country": "US",
    "subdivision": "CO",
    "timezone": "America/Denver"
  },
  "geometry": {
    "type": "Point",
    "coordinates": [
      -106.98782,
      38.86971
    ]
  }
}