{
  "type": "Feature",
  "properties": {
    "name": "Eagle",
    "country": "US",
    "subdivision": "CO",
    "timezone": "America/Denver"
  },
  "geometry": {
    "type": "Point",
    "coordinates": [
      -106.82865,
      39.65526
    ]
  }
}