{
  "type": "Feature",
  "properties": {
    "name": "Eaton",
    "country": "US",
    "subdivision": "CO",
    "timezone": "America/Denver"
  },
  "geometry": {
    "type": "Point",
    "coordinates": [
      -104.71135,
      40.53026
    ]
  }
}