{
  "type": "Feature",
  "properties": {
    "name": "Fowler",
    "country": "US",
    "subdivision": "CO",
    "timezone": "America/Denver"
  },
  "geometry": {
    "type": "Point",
    "coordinates": [
      -104.02329,
      38.12917
    ]
  }
}