{
  "type": "Feature",
  "properties": {
    "name": "Greeley",
    "country": "US",
    "subdivision": "CO",
    "timezone": "America/Denver"
  },
  "geometry": {
    "type": "Point",
    "coordinates": [
      -104.70913,
      40.42331
    ]
  }
}