{
  "type": "Feature",
  "properties": {
    "name": "Keenesburg",
    "country": "US",
    "subdivision": "CO",
    "timezone": "America/Denver"
  },
  "geometry": {
    "type": "Point",
    "coordinates": [
      -104.51996,
      40.10832
    ]
  }
}