{
  "type": "Feature",
  "properties": {
    "name": "Limon",
    "country": "US",
    "subdivision": "CO",
    "timezone": "America/Denver"
  },
  "geometry": {
    "type": "Point",
    "coordinates": [
      -103.69217,
      39.26388
    ]
  }
}