{
  "type": "Feature",
  "properties": {
    "name": "Louisville",
    "country": "US",
    "subdivision": "CO",
    "timezone": "America/Denver"
  },
  "geometry": {
    "type": "Point",
    "coordinates": [
      -105.13193,
      39.97776
    ]
  }
}