{
  "type": "Feature",
  "properties": {
    "name": "Lyons",
    "country": "US",
    "subdivision": "CO",
    "timezone": "America/Denver"
  },
  "geometry": {
    "type": "Point",
    "coordinates": [
      -105.27138,
      40.22471
    ]
  }
}