{
  "type": "Feature",
  "properties": {
    "name": "Meeker",
    "country": "US",
    "subdivision": "CO",
    "timezone": "America/Denver"
  },
  "geometry": {
    "type": "Point",
    "coordinates": [
      -107.91313,
      40.03747
    ]
  }
}