{
  "type": "Feature",
  "properties": {
    "name": "Meridian",
    "country": "US",
    "subdivision": "CO",
    "timezone": "America/Denver"
  },
  "geometry": {
    "type": "Point",
    "coordinates": [
      -104.84528,
      39.53957
    ]
  }
}