{
  "type": "Feature",
  "properties": {
    "name": "Milliken",
    "country": "US",
    "subdivision": "CO",
    "timezone": "America/Denver"
  },
  "geometry": {
    "type": "Point",
    "coordinates": [
      -104.85525,
      40.32943
    ]
  }
}