{
  "type": "Feature",
  "properties": {
    "name": "Ouray",
    "country": "US",
    "subdivision": "CO",
    "timezone": "America/Denver"
  },
  "geometry": {
    "type": "Point",
    "coordinates": [
      -107.67145,
      38.02277
    ]
  }
}