{
  "type": "Feature",
  "properties": {
    "name": "Pueblo West",
    "country": "US",
    "subdivision": "CO",
    "timezone": "America/Denver"
  },
  "geometry": {
    "type": "Point",
    "coordinates": [
      -104.72275,
      38.35
    ]
  }
}