{
  "type": "Feature",
  "properties": {
    "name": "Shaw Heights",
    "country": "US",
    "subdivision": "CO",
    "timezone": "America/Denver"
  },
  "geometry": {
    "type": "Point",
    "coordinates": [
      -105.04306,
      39.8525
    ]
  }
}