{
  "type": "Feature",
  "properties": {
    "name": "Sherrelwood",
    "country": "US",
    "subdivision": "CO",
    "timezone": "America/Denver"
  },
  "geometry": {
    "type": "Point",
    "coordinates": [
      -105.00137,
      39.83776
    ]
  }
}