{
  "type": "Feature",
  "properties": {
    "name": "Snowmass Village",
    "country": "US",
    "subdivision": "CO",
    "timezone": "America/Denver"
  },
  "geometry": {
    "type": "Point",
    "coordinates": [
      -106.93782,
      39.21304
    ]
  }
}