{
  "type": "Feature",
  "properties": {
    "name": "Southglenn",
    "country": "US",
    "subdivision": "CO",
    "timezone": "America/Denver"
  },
  "geometry": {
    "type": "Point",
    "coordinates": [
      -104.95276,
      39.58721
    ]
  }
}