{
  "type": "Feature",
  "properties": {
    "name": "The Pinery",
    "country": "US",
    "subdivision": "CO",
    "timezone": "America/Denver"
  },
  "geometry": {
    "type": "Point",
    "coordinates": [
      -104.73442,
      39.45527
    ]
  }
}