{
  "type": "Feature",
  "properties": {
    "name": "Wellington",
    "country": "US",
    "subdivision": "CO",
    "timezone": "America/Denver"
  },
  "geometry": {
    "type": "Point",
    "coordinates": [
      -105.00859,
      40.70387
    ]
  }
}