{
  "type": "Feature",
  "properties": {
    "name": "Biẕẕaron",
    "country": "IL",
    "subdivision": "01",
    "timezone": "Asia/Jerusalem"
  },
  "geometry": {
    "type": "Point",
    "coordinates": [
      34.72806,
      31.79446
    ]
  }
}