{
  "type": "Feature",
  "properties": {
    "name": "Nir Gallim",
    "country": "IL",
    "subdivision": "01",
    "timezone": "Asia/Jerusalem"
  },
  "geometry": {
    "type": "Point",
    "coordinates": [
      34.68282,
      31.82542
    ]
  }
}