{
  "type": "Feature",
  "properties": {
    "name": "Revivim",
    "country": "IL",
    "subdivision": "01",
    "timezone": "Asia/Jerusalem"
  },
  "geometry": {
    "type": "Point",
    "coordinates": [
      34.72183,
      31.04395
    ]
  }
}