{
  "type": "Feature",
  "properties": {
    "name": "Tirabin al-Sana",
    "country": "IL",
    "subdivision": "01",
    "timezone": "Asia/Jerusalem"
  },
  "geometry": {
    "type": "Point",
    "coordinates": [
      34.73867,
      31.34479
    ]
  }
}