{
  "type": "Feature",
  "properties": {
    "name": "Babag",
    "country": "PH",
    "subdivision": "11",
    "timezone": "Asia/Manila"
  },
  "geometry": {
    "type": "Point",
    "coordinates": [
      126.0713,
      7.73309
    ]
  }
}