{
  "type": "Feature",
  "properties": {
    "name": "Bincoñgan",
    "country": "PH",
    "subdivision": "11",
    "timezone": "Asia/Manila"
  },
  "geometry": {
    "type": "Point",
    "coordinates": [
      125.75,
      7.36667
    ]
  }
}