{
  "type": "Feature",
  "properties": {
    "name": "Bungabon",
    "country": "PH",
    "subdivision": "11",
    "timezone": "Asia/Manila"
  },
  "geometry": {
    "type": "Point",
    "coordinates": [
      125.8731,
      7.2221
    ]
  }
}