{
  "type": "Feature",
  "properties": {
    "name": "Compostela",
    "country": "PH",
    "subdivision": "11",
    "timezone": "Asia/Manila"
  },
  "geometry": {
    "type": "Point",
    "coordinates": [
      126.08889,
      7.67306
    ]
  }
}