{
  "type": "Feature",
  "properties": {
    "name": "Cuambog",
    "country": "PH",
    "subdivision": "11",
    "timezone": "Asia/Manila"
  },
  "geometry": {
    "type": "Point",
    "coordinates": [
      125.84806,
      7.30861
    ]
  }
}