{
  "type": "Feature",
  "properties": {
    "name": "Dolo",
    "country": "PH",
    "subdivision": "11",
    "timezone": "Asia/Manila"
  },
  "geometry": {
    "type": "Point",
    "coordinates": [
      125.19167,
      6.81028
    ]
  }
}