{
  "type": "Feature",
  "properties": {
    "name": "Gabi",
    "country": "PH",
    "subdivision": "11",
    "timezone": "Asia/Manila"
  },
  "geometry": {
    "type": "Point",
    "coordinates": [
      126.092,
      7.6215
    ]
  }
}