{
  "type": "Feature",
  "properties": {
    "name": "Kiblawan",
    "country": "PH",
    "subdivision": "11",
    "timezone": "Asia/Manila"
  },
  "geometry": {
    "type": "Point",
    "coordinates": [
      125.23667,
      6.61417
    ]
  }
}