{
  "type": "Feature",
  "properties": {
    "name": "Lais",
    "country": "PH",
    "subdivision": "11",
    "timezone": "Asia/Manila"
  },
  "geometry": {
    "type": "Point",
    "coordinates": [
      125.64639,
      6.33278
    ]
  }
}