{
  "type": "Feature",
  "properties": {
    "name": "Lasang",
    "country": "PH",
    "subdivision": "11",
    "timezone": "Asia/Manila"
  },
  "geometry": {
    "type": "Point",
    "coordinates": [
      125.665,
      7.26694
    ]
  }
}