{
  "type": "Feature",
  "properties": {
    "name": "Limot",
    "country": "PH",
    "subdivision": "11",
    "timezone": "Asia/Manila"
  },
  "geometry": {
    "type": "Point",
    "coordinates": [
      126.27268,
      7.0405
    ]
  }
}