{
  "type": "Feature",
  "properties": {
    "name": "Linao",
    "country": "PH",
    "subdivision": "11",
    "timezone": "Asia/Manila"
  },
  "geometry": {
    "type": "Point",
    "coordinates": [
      125.992,
      7.0172
    ]
  }
}