{
  "type": "Feature",
  "properties": {
    "name": "Linoan",
    "country": "PH",
    "subdivision": "11",
    "timezone": "Asia/Manila"
  },
  "geometry": {
    "type": "Point",
    "coordinates": [
      125.9741,
      7.626
    ]
  }
}