{
  "type": "Feature",
  "properties": {
    "name": "Luna",
    "country": "PH",
    "subdivision": "11",
    "timezone": "Asia/Manila"
  },
  "geometry": {
    "type": "Point",
    "coordinates": [
      125.66722,
      7.57639
    ]
  }
}