{
  "type": "Feature",
  "properties": {
    "name": "Manay",
    "country": "PH",
    "subdivision": "11",
    "timezone": "Asia/Manila"
  },
  "geometry": {
    "type": "Point",
    "coordinates": [
      125.575,
      7.34167
    ]
  }
}