{
  "type": "Feature",
  "properties": {
    "name": "Monkayo",
    "country": "PH",
    "subdivision": "11",
    "timezone": "Asia/Manila"
  },
  "geometry": {
    "type": "Point",
    "coordinates": [
      126.05444,
      7.81528
    ]
  }
}