{
  "type": "Feature",
  "properties": {
    "name": "Nanyo",
    "country": "PH",
    "subdivision": "11",
    "timezone": "Asia/Manila"
  },
  "geometry": {
    "type": "Point",
    "coordinates": [
      125.63778,
      7.33306
    ]
  }
}