{
  "type": "Feature",
  "properties": {
    "name": "New Baclayon",
    "country": "PH",
    "subdivision": "11",
    "timezone": "Asia/Manila"
  },
  "geometry": {
    "type": "Point",
    "coordinates": [
      125.36944,
      6.58417
    ]
  }
}