{
  "type": "Feature",
  "properties": {
    "name": "Pagsabangan",
    "country": "PH",
    "subdivision": "11",
    "timezone": "Asia/Manila"
  },
  "geometry": {
    "type": "Point",
    "coordinates": [
      125.74944,
      7.48111
    ]
  }
}