{
  "type": "Feature",
  "properties": {
    "name": "San Miguel",
    "country": "PH",
    "subdivision": "11",
    "timezone": "Asia/Manila"
  },
  "geometry": {
    "type": "Point",
    "coordinates": [
      125.67639,
      7.485
    ]
  }
}