{
  "type": "Feature",
  "properties": {
    "name": "San Antonio",
    "country": "PH",
    "subdivision": "11",
    "timezone": "Asia/Manila"
  },
  "geometry": {
    "type": "Point",
    "coordinates": [
      125.73972,
      7.12
    ]
  }
}