{
  "type": "Feature",
  "properties": {
    "name": "San Ignacio",
    "country": "PH",
    "subdivision": "11",
    "timezone": "Asia/Manila"
  },
  "geometry": {
    "type": "Point",
    "coordinates": [
      126.48838,
      7.1189
    ]
  }
}