{
  "type": "Feature",
  "properties": {
    "name": "Tagakpan",
    "country": "PH",
    "subdivision": "11",
    "timezone": "Asia/Manila"
  },
  "geometry": {
    "type": "Point",
    "coordinates": [
      125.42917,
      7.11278
    ]
  }
}