{
  "type": "Feature",
  "properties": {
    "name": "Takub",
    "country": "PH",
    "subdivision": "11",
    "timezone": "Asia/Manila"
  },
  "geometry": {
    "type": "Point",
    "coordinates": [
      125.4225,
      6.85639
    ]
  }
}