{
  "type": "Feature",
  "properties": {
    "name": "Talisay",
    "country": "PH",
    "subdivision": "11",
    "timezone": "Asia/Manila"
  },
  "geometry": {
    "type": "Point",
    "coordinates": [
      126.09998,
      6.71973
    ]
  }
}