{
  "type": "Feature",
  "properties": {
    "name": "Tibanbang",
    "country": "PH",
    "subdivision": "11",
    "timezone": "Asia/Manila"
  },
  "geometry": {
    "type": "Point",
    "coordinates": [
      126.10548,
      6.63153
    ]
  }
}