{
  "type": "Feature",
  "properties": {
    "name": "Addison",
    "country": "US",
    "subdivision": "ME",
    "timezone": "America/New_York"
  },
  "geometry": {
    "type": "Point",
    "coordinates": [
      -67.74416,
      44.61841
    ]
  }
}