{
  "type": "Feature",
  "properties": {
    "name": "Alfred",
    "country": "US",
    "subdivision": "ME",
    "timezone": "America/New_York"
  },
  "geometry": {
    "type": "Point",
    "coordinates": [
      -70.71839,
      43.47647
    ]
  }
}