{
  "type": "Feature",
  "properties": {
    "name": "Appleton",
    "country": "US",
    "subdivision": "ME",
    "timezone": "America/New_York"
  },
  "geometry": {
    "type": "Point",
    "coordinates": [
      -69.25088,
      44.28924
    ]
  }
}