{
  "type": "Feature",
  "properties": {
    "name": "Bar Harbor",
    "country": "US",
    "subdivision": "ME",
    "timezone": "America/New_York"
  },
  "geometry": {
    "type": "Point",
    "coordinates": [
      -68.2039,
      44.38758
    ]
  }
}