{
  "type": "Feature",
  "properties": {
    "name": "Cherryfield",
    "country": "US",
    "subdivision": "ME",
    "timezone": "America/New_York"
  },
  "geometry": {
    "type": "Point",
    "coordinates": [
      -67.92584,
      44.6073
    ]
  }
}