{
  "type": "Feature",
  "properties": {
    "name": "Chesterville",
    "country": "US",
    "subdivision": "ME",
    "timezone": "America/New_York"
  },
  "geometry": {
    "type": "Point",
    "coordinates": [
      -70.08617,
      44.55117
    ]
  }
}