{
  "type": "Feature",
  "properties": {
    "name": "Cornville",
    "country": "US",
    "subdivision": "ME",
    "timezone": "America/New_York"
  },
  "geometry": {
    "type": "Point",
    "coordinates": [
      -69.67311,
      44.83673
    ]
  }
}