{
  "type": "Feature",
  "properties": {
    "name": "Denmark",
    "country": "US",
    "subdivision": "ME",
    "timezone": "America/New_York"
  },
  "geometry": {
    "type": "Point",
    "coordinates": [
      -70.8034,
      43.97035
    ]
  }
}