{
  "type": "Feature",
  "properties": {
    "name": "Dexter",
    "country": "US",
    "subdivision": "ME",
    "timezone": "America/New_York"
  },
  "geometry": {
    "type": "Point",
    "coordinates": [
      -69.28977,
      45.02395
    ]
  }
}