{
  "type": "Feature",
  "properties": {
    "name": "Farmingdale",
    "country": "US",
    "subdivision": "ME",
    "timezone": "America/New_York"
  },
  "geometry": {
    "type": "Point",
    "coordinates": [
      -69.77143,
      44.24451
    ]
  }
}