{
  "type": "Feature",
  "properties": {
    "name": "Fort Fairfield",
    "country": "US",
    "subdivision": "ME",
    "timezone": "America/New_York"
  },
  "geometry": {
    "type": "Point",
    "coordinates": [
      -67.83391,
      46.77227
    ]
  }
}