{
  "type": "Feature",
  "properties": {
    "name": "Hallowell",
    "country": "US",
    "subdivision": "ME",
    "timezone": "America/New_York"
  },
  "geometry": {
    "type": "Point",
    "coordinates": [
      -69.79088,
      44.2859
    ]
  }
}