{
  "type": "Feature",
  "properties": {
    "name": "Hudson",
    "country": "US",
    "subdivision": "ME",
    "timezone": "America/New_York"
  },
  "geometry": {
    "type": "Point",
    "coordinates": [
      -68.88059,
      45.00118
    ]
  }
}