{
  "type": "Feature",
  "properties": {
    "name": "Limerick",
    "country": "US",
    "subdivision": "ME",
    "timezone": "America/New_York"
  },
  "geometry": {
    "type": "Point",
    "coordinates": [
      -70.79367,
      43.68841
    ]
  }
}