{
  "type": "Feature",
  "properties": {
    "name": "Lincolnville",
    "country": "US",
    "subdivision": "ME",
    "timezone": "America/New_York"
  },
  "geometry": {
    "type": "Point",
    "coordinates": [
      -69.00865,
      44.28119
    ]
  }
}