{
  "type": "Feature",
  "properties": {
    "name": "Lincoln",
    "country": "US",
    "subdivision": "ME",
    "timezone": "America/New_York"
  },
  "geometry": {
    "type": "Point",
    "coordinates": [
      -68.50502,
      45.36228
    ]
  }
}