{
  "type": "Feature",
  "properties": {
    "name": "Milbridge",
    "country": "US",
    "subdivision": "ME",
    "timezone": "America/New_York"
  },
  "geometry": {
    "type": "Point",
    "coordinates": [
      -67.88083,
      44.53536
    ]
  }
}