{
  "type": "Feature",
  "properties": {
    "name": "Millinocket",
    "country": "US",
    "subdivision": "ME",
    "timezone": "America/New_York"
  },
  "geometry": {
    "type": "Point",
    "coordinates": [
      -68.70976,
      45.65727
    ]
  }
}