{
  "type": "Feature",
  "properties": {
    "name": "Old Town",
    "country": "US",
    "subdivision": "ME",
    "timezone": "America/New_York"
  },
  "geometry": {
    "type": "Point",
    "coordinates": [
      -68.64531,
      44.93423
    ]
  }
}