{
  "type": "Feature",
  "properties": {
    "name": "Parsonsfield",
    "country": "US",
    "subdivision": "ME",
    "timezone": "America/New_York"
  },
  "geometry": {
    "type": "Point",
    "coordinates": [
      -70.92868,
      43.72702
    ]
  }
}