{
  "type": "Feature",
  "properties": {
    "name": "Penobscot",
    "country": "US",
    "subdivision": "ME",
    "timezone": "America/New_York"
  },
  "geometry": {
    "type": "Point",
    "coordinates": [
      -68.71114,
      44.46452
    ]
  }
}