{
  "type": "Feature",
  "properties": {
    "name": "Phippsburg",
    "country": "US",
    "subdivision": "ME",
    "timezone": "America/New_York"
  },
  "geometry": {
    "type": "Point",
    "coordinates": [
      -69.81477,
      43.82064
    ]
  }
}