{
  "type": "Feature",
  "properties": {
    "name": "Raymond",
    "country": "US",
    "subdivision": "ME",
    "timezone": "America/New_York"
  },
  "geometry": {
    "type": "Point",
    "coordinates": [
      -70.47033,
      43.90146
    ]
  }
}