{
  "type": "Feature",
  "properties": {
    "name": "Rome",
    "country": "US",
    "subdivision": "ME",
    "timezone": "America/New_York"
  },
  "geometry": {
    "type": "Point",
    "coordinates": [
      -69.86922,
      44.58506
    ]
  }
}