{
  "type": "Feature",
  "properties": {
    "name": "Sangerville",
    "country": "US",
    "subdivision": "ME",
    "timezone": "America/New_York"
  },
  "geometry": {
    "type": "Point",
    "coordinates": [
      -69.35644,
      45.16478
    ]
  }
}