{
  "type": "Feature",
  "properties": {
    "name": "South Portland Gardens",
    "country": "US",
    "subdivision": "ME",
    "timezone": "America/New_York"
  },
  "geometry": {
    "type": "Point",
    "coordinates": [
      -70.31533,
      43.63897
    ]
  }
}