{
  "type": "Feature",
  "properties": {
    "name": "Vinalhaven",
    "country": "US",
    "subdivision": "ME",
    "timezone": "America/New_York"
  },
  "geometry": {
    "type": "Point",
    "coordinates": [
      -68.8317,
      44.04814
    ]
  }
}