{
  "type": "Feature",
  "properties": {
    "name": "Waterville",
    "country": "US",
    "subdivision": "ME",
    "timezone": "America/New_York"
  },
  "geometry": {
    "type": "Point",
    "coordinates": [
      -69.63171,
      44.55201
    ]
  }
}