{
  "type": "Feature",
  "properties": {
    "name": "Wayne",
    "country": "US",
    "subdivision": "ME",
    "timezone": "America/New_York"
  },
  "geometry": {
    "type": "Point",
    "coordinates": [
      -70.06616,
      44.34868
    ]
  }
}