{
  "type": "Feature",
  "properties": {
    "name": "West Scarborough",
    "country": "US",
    "subdivision": "ME",
    "timezone": "America/New_York"
  },
  "geometry": {
    "type": "Point",
    "coordinates": [
      -70.38783,
      43.57036
    ]
  }
}