{
  "type": "Feature",
  "properties": {
    "name": "Woodstock",
    "country": "US",
    "subdivision": "ME",
    "timezone": "America/New_York"
  },
  "geometry": {
    "type": "Point",
    "coordinates": [
      -70.60849,
      44.37494
    ]
  }
}