{
  "type": "Feature",
  "properties": {
    "name": "Bisee",
    "country": "LC",
    "subdivision": "03",
    "timezone": "America/St_Lucia"
  },
  "geometry": {
    "type": "Point",
    "coordinates": [
      -60.97445,
      14.02429
    ]
  }
}