{
  "type": "Feature",
  "properties": {
    "name": "Isnā",
    "country": "EG",
    "subdivision": "23",
    "timezone": "Africa/Cairo"
  },
  "geometry": {
    "type": "Point",
    "coordinates": [
      32.55402,
      25.29336
    ]
  }
}