{
  "type": "Feature",
  "properties": {
    "name": "Acurenam",
    "country": "GQ",
    "subdivision": "06",
    "timezone": "Africa/Malabo"
  },
  "geometry": {
    "type": "Point",
    "coordinates": [
      10.64882,
      1.03225
    ]
  }
}