{
  "type": "Feature",
  "properties": {
    "name": "Veteli",
    "country": "FI",
    "subdivision": "16",
    "timezone": "Europe/Helsinki"
  },
  "geometry": {
    "type": "Point",
    "coordinates": [
      23.78285,
      63.47839
    ]
  }
}