{
  "type": "Feature",
  "properties": {
    "name": "Nurdağı",
    "country": "TR",
    "subdivision": "83",
    "timezone": "Europe/Istanbul"
  },
  "geometry": {
    "type": "Point",
    "coordinates": [
      36.73623,
      37.16821
    ]
  }
}