{
  "type": "Feature",
  "properties": {
    "name": "Središče ob Dravi",
    "country": "SI",
    "subdivision": "P4",
    "timezone": "Europe/Ljubljana"
  },
  "geometry": {
    "type": "Point",
    "coordinates": [
      16.26806,
      46.39417
    ]
  }
}