{
  "type": "Feature",
  "properties": {
    "name": "Al ManÄqil",
    "country": "SD",
    "subdivision": "38",
    "timezone": "Africa/Khartoum"
  },
  "geometry": {
    "type": "Point",
    "coordinates": [
      32.9891,
      14.2459
    ]
  }
}