{
  "type": "Feature",
  "properties": {
    "name": "Djoyézi",
    "country": "KM",
    "subdivision": "03",
    "timezone": "Indian/Comoro"
  },
  "geometry": {
    "type": "Point",
    "coordinates": [
      43.77425,
      -12.30587
    ]
  }
}