{
  "type": "Feature",
  "properties": {
    "name": "Hoani",
    "country": "KM",
    "subdivision": "03",
    "timezone": "Indian/Comoro"
  },
  "geometry": {
    "type": "Point",
    "coordinates": [
      43.67472,
      -12.25083
    ]
  }
}