{
  "type": "Feature",
  "properties": {
    "name": "Kilmia",
    "country": "YE",
    "subdivision": "04",
    "timezone": "Asia/Aden"
  },
  "geometry": {
    "type": "Point",
    "coordinates": [
      52.23332,
      12.18576
    ]
  }
}