{
  "type": "Feature",
  "properties": {
    "name": "Alanib",
    "country": "PH",
    "subdivision": "10",
    "timezone": "Asia/Manila"
  },
  "geometry": {
    "type": "Point",
    "coordinates": [
      124.98611,
      8.02778
    ]
  }
}