{
  "type": "Feature",
  "properties": {
    "name": "Anakan",
    "country": "PH",
    "subdivision": "10",
    "timezone": "Asia/Manila"
  },
  "geometry": {
    "type": "Point",
    "coordinates": [
      125.15139,
      8.84778
    ]
  }
}