{
  "type": "Feature",
  "properties": {
    "name": "Balingasag",
    "country": "PH",
    "subdivision": "10",
    "timezone": "Asia/Manila"
  },
  "geometry": {
    "type": "Point",
    "coordinates": [
      124.77694,
      8.74417
    ]
  }
}