{
  "type": "Feature",
  "properties": {
    "name": "Canayan",
    "country": "PH",
    "subdivision": "10",
    "timezone": "Asia/Manila"
  },
  "geometry": {
    "type": "Point",
    "coordinates": [
      125.14472,
      8.19556
    ]
  }
}