{
  "type": "Feature",
  "properties": {
    "name": "Dalwangan",
    "country": "PH",
    "subdivision": "10",
    "timezone": "Asia/Manila"
  },
  "geometry": {
    "type": "Point",
    "coordinates": [
      125.04056,
      8.20056
    ]
  }
}