{
  "type": "Feature",
  "properties": {
    "name": "Dorsalanam",
    "country": "PH",
    "subdivision": "10",
    "timezone": "Asia/Manila"
  },
  "geometry": {
    "type": "Point",
    "coordinates": [
      124.58556,
      8.30667
    ]
  }
}