{
  "type": "Feature",
  "properties": {
    "name": "Gitagum",
    "country": "PH",
    "subdivision": "10",
    "timezone": "Asia/Manila"
  },
  "geometry": {
    "type": "Point",
    "coordinates": [
      124.40639,
      8.59667
    ]
  }
}