{
  "type": "Feature",
  "properties": {
    "name": "Inobulan",
    "country": "PH",
    "subdivision": "10",
    "timezone": "Asia/Manila"
  },
  "geometry": {
    "type": "Point",
    "coordinates": [
      124.79472,
      8.88639
    ]
  }
}