{
  "type": "Feature",
  "properties": {
    "name": "Jimenez",
    "country": "PH",
    "subdivision": "10",
    "timezone": "Asia/Manila"
  },
  "geometry": {
    "type": "Point",
    "coordinates": [
      123.8383,
      8.3365
    ]
  }
}