{
  "type": "Feature",
  "properties": {
    "name": "Kisolon",
    "country": "PH",
    "subdivision": "10",
    "timezone": "Asia/Manila"
  },
  "geometry": {
    "type": "Point",
    "coordinates": [
      124.97694,
      8.33
    ]
  }
}