{
  "type": "Feature",
  "properties": {
    "name": "Libertad",
    "country": "PH",
    "subdivision": "10",
    "timezone": "Asia/Manila"
  },
  "geometry": {
    "type": "Point",
    "coordinates": [
      124.35139,
      8.56111
    ]
  }
}