{
  "type": "Feature",
  "properties": {
    "name": "Liboran",
    "country": "PH",
    "subdivision": "10",
    "timezone": "Asia/Manila"
  },
  "geometry": {
    "type": "Point",
    "coordinates": [
      124.64889,
      8.35472
    ]
  }
}