{
  "type": "Feature",
  "properties": {
    "name": "Lourdes",
    "country": "PH",
    "subdivision": "10",
    "timezone": "Asia/Manila"
  },
  "geometry": {
    "type": "Point",
    "coordinates": [
      124.43222,
      8.525
    ]
  }
}