{
  "type": "Feature",
  "properties": {
    "name": "Lugait",
    "country": "PH",
    "subdivision": "10",
    "timezone": "Asia/Manila"
  },
  "geometry": {
    "type": "Point",
    "coordinates": [
      124.25917,
      8.34111
    ]
  }
}