{
  "type": "Feature",
  "properties": {
    "name": "Lumbayao",
    "country": "PH",
    "subdivision": "10",
    "timezone": "Asia/Manila"
  },
  "geometry": {
    "type": "Point",
    "coordinates": [
      125.16667,
      8.01667
    ]
  }
}