{
  "type": "Feature",
  "properties": {
    "name": "Managok",
    "country": "PH",
    "subdivision": "10",
    "timezone": "Asia/Manila"
  },
  "geometry": {
    "type": "Point",
    "coordinates": [
      125.18861,
      8.02889
    ]
  }
}