{
  "type": "Feature",
  "properties": {
    "name": "Manticao",
    "country": "PH",
    "subdivision": "10",
    "timezone": "Asia/Manila"
  },
  "geometry": {
    "type": "Point",
    "coordinates": [
      124.28667,
      8.40417
    ]
  }
}