{
  "type": "Feature",
  "properties": {
    "name": "Maria Cristina",
    "country": "PH",
    "subdivision": "10",
    "timezone": "Asia/Manila"
  },
  "geometry": {
    "type": "Point",
    "coordinates": [
      124.20396,
      8.16604
    ]
  }
}