{
  "type": "Feature",
  "properties": {
    "name": "Mat-i",
    "country": "PH",
    "subdivision": "10",
    "timezone": "Asia/Manila"
  },
  "geometry": {
    "type": "Point",
    "coordinates": [
      124.34528,
      8.40194
    ]
  }
}