{
  "type": "Feature",
  "properties": {
    "name": "Matangad",
    "country": "PH",
    "subdivision": "10",
    "timezone": "Asia/Manila"
  },
  "geometry": {
    "type": "Point",
    "coordinates": [
      124.37,
      8.57694
    ]
  }
}