{
  "type": "Feature",
  "properties": {
    "name": "Napalitan",
    "country": "PH",
    "subdivision": "10",
    "timezone": "Asia/Manila"
  },
  "geometry": {
    "type": "Point",
    "coordinates": [
      124.80222,
      8.77528
    ]
  }
}