{
  "type": "Feature",
  "properties": {
    "name": "Punta Silum",
    "country": "PH",
    "subdivision": "10",
    "timezone": "Asia/Manila"
  },
  "geometry": {
    "type": "Point",
    "coordinates": [
      124.26944,
      8.38167
    ]
  }
}