{
  "type": "Feature",
  "properties": {
    "name": "Rebe",
    "country": "PH",
    "subdivision": "10",
    "timezone": "Asia/Manila"
  },
  "geometry": {
    "type": "Point",
    "coordinates": [
      123.8155,
      7.9076
    ]
  }
}