{
  "type": "Feature",
  "properties": {
    "name": "Tacub",
    "country": "PH",
    "subdivision": "10",
    "timezone": "Asia/Manila"
  },
  "geometry": {
    "type": "Point",
    "coordinates": [
      124.10806,
      8.1875
    ]
  }
}