{
  "type": "Feature",
  "properties": {
    "name": "Ticala-an",
    "country": "PH",
    "subdivision": "10",
    "timezone": "Asia/Manila"
  },
  "geometry": {
    "type": "Point",
    "coordinates": [
      124.62083,
      8.03528
    ]
  }
}