{
  "type": "Feature",
  "properties": {
    "name": "Tubao",
    "country": "PH",
    "subdivision": "10",
    "timezone": "Asia/Manila"
  },
  "geometry": {
    "type": "Point",
    "coordinates": [
      123.8547,
      8.334
    ]
  }
}