{
  "type": "Feature",
  "properties": {
    "name": "Tubigan",
    "country": "PH",
    "subdivision": "10",
    "timezone": "Asia/Manila"
  },
  "geometry": {
    "type": "Point",
    "coordinates": [
      124.31222,
      8.53222
    ]
  }
}