{
  "type": "Feature",
  "properties": {
    "name": "Yumbing",
    "country": "PH",
    "subdivision": "10",
    "timezone": "Asia/Manila"
  },
  "geometry": {
    "type": "Point",
    "coordinates": [
      124.65778,
      9.23933
    ]
  }
}