{
  "type": "Feature",
  "properties": {
    "name": "Fundong",
    "country": "CM",
    "subdivision": "07",
    "timezone": "Africa/Douala"
  },
  "geometry": {
    "type": "Point",
    "coordinates": [
      10.26667,
      6.25
    ]
  }
}