{
  "type": "Feature",
  "properties": {
    "name": "Mme-Bafumen",
    "country": "CM",
    "subdivision": "07",
    "timezone": "Africa/Douala"
  },
  "geometry": {
    "type": "Point",
    "coordinates": [
      10.23333,
      6.33333
    ]
  }
}