{
  "type": "Feature",
  "properties": {
    "name": "Juan de Acosta",
    "country": "CO",
    "subdivision": "04",
    "timezone": "America/Bogota"
  },
  "geometry": {
    "type": "Point",
    "coordinates": [
      -75.03346,
      10.8293
    ]
  }
}