{
  "type": "Feature",
  "properties": {
    "name": "Ponedera",
    "country": "CO",
    "subdivision": "04",
    "timezone": "America/Bogota"
  },
  "geometry": {
    "type": "Point",
    "coordinates": [
      -74.75393,
      10.64297
    ]
  }
}