{
  "type": "Feature",
  "properties": {
    "name": "Sabanalarga",
    "country": "CO",
    "subdivision": "04",
    "timezone": "America/Bogota"
  },
  "geometry": {
    "type": "Point",
    "coordinates": [
      -74.92214,
      10.63072
    ]
  }
}