{
  "type": "Feature",
  "properties": {
    "name": "Sabanagrande",
    "country": "CO",
    "subdivision": "04",
    "timezone": "America/Bogota"
  },
  "geometry": {
    "type": "Point",
    "coordinates": [
      -74.76059,
      10.79115
    ]
  }
}