{
  "type": "Feature",
  "properties": {
    "name": "Santo Tomás",
    "country": "CO",
    "subdivision": "04",
    "timezone": "America/Bogota"
  },
  "geometry": {
    "type": "Point",
    "coordinates": [
      -74.75451,
      10.75773
    ]
  }
}