{
  "type": "Feature",
  "properties": {
    "name": "Chern’",
    "country": "RU",
    "subdivision": "76",
    "timezone": "Europe/Moscow"
  },
  "geometry": {
    "type": "Point",
    "coordinates": [
      36.9145,
      53.45232
    ]
  }
}