{
  "type": "Feature",
  "properties": {
    "name": "Dubna",
    "country": "RU",
    "subdivision": "76",
    "timezone": "Europe/Moscow"
  },
  "geometry": {
    "type": "Point",
    "coordinates": [
      36.96173,
      54.15416
    ]
  }
}