{
  "type": "Feature",
  "properties": {
    "name": "Kireyevsk",
    "country": "RU",
    "subdivision": "76",
    "timezone": "Europe/Moscow"
  },
  "geometry": {
    "type": "Point",
    "coordinates": [
      37.92792,
      53.93361
    ]
  }
}