{
  "type": "Feature",
  "properties": {
    "name": "Novomoskovsk",
    "country": "RU",
    "subdivision": "76",
    "timezone": "Europe/Moscow"
  },
  "geometry": {
    "type": "Point",
    "coordinates": [
      38.2846,
      54.0105
    ]
  }
}