{
  "type": "Feature",
  "properties": {
    "name": "Partizan",
    "country": "RU",
    "subdivision": "76",
    "timezone": "Europe/Moscow"
  },
  "geometry": {
    "type": "Point",
    "coordinates": [
      38.09801,
      53.95017
    ]
  }
}