{
  "type": "Feature",
  "properties": {
    "name": "Priupskiy",
    "country": "RU",
    "subdivision": "76",
    "timezone": "Europe/Moscow"
  },
  "geometry": {
    "type": "Point",
    "coordinates": [
      37.736,
      53.9096
    ]
  }
}