{
  "type": "Feature",
  "properties": {
    "name": "Shvartsevskiy",
    "country": "RU",
    "subdivision": "76",
    "timezone": "Europe/Moscow"
  },
  "geometry": {
    "type": "Point",
    "coordinates": [
      37.99053,
      54.09174
    ]
  }
}