{
  "type": "Feature",
  "properties": {
    "name": "Tovarkovskiy",
    "country": "RU",
    "subdivision": "76",
    "timezone": "Europe/Moscow"
  },
  "geometry": {
    "type": "Point",
    "coordinates": [
      38.2092,
      53.68217
    ]
  }
}