{
  "type": "Feature",
  "properties": {
    "name": "Zhdankovskiy",
    "country": "RU",
    "subdivision": "76",
    "timezone": "Europe/Moscow"
  },
  "geometry": {
    "type": "Point",
    "coordinates": [
      38.17951,
      53.75321
    ]
  }
}