{
  "type": "Feature",
  "properties": {
    "name": "Grobiņa",
    "country": "LV",
    "subdivision": "65",
    "timezone": "Europe/Riga"
  },
  "geometry": {
    "type": "Point",
    "coordinates": [
      21.16782,
      56.53521
    ]
  }
}