{
  "type": "Feature",
  "properties": {
    "name": "Akunk’",
    "country": "AM",
    "subdivision": "05",
    "timezone": "Asia/Yerevan"
  },
  "geometry": {
    "type": "Point",
    "coordinates": [
      44.6861,
      40.26672
    ]
  }
}