{
  "type": "Feature",
  "properties": {
    "name": "Byureghavan",
    "country": "AM",
    "subdivision": "05",
    "timezone": "Asia/Yerevan"
  },
  "geometry": {
    "type": "Point",
    "coordinates": [
      44.59333,
      40.31417
    ]
  }
}