{
  "type": "Feature",
  "properties": {
    "name": "Dzoraghbyur",
    "country": "AM",
    "subdivision": "05",
    "timezone": "Asia/Yerevan"
  },
  "geometry": {
    "type": "Point",
    "coordinates": [
      44.6415,
      40.20412
    ]
  }
}