{
  "type": "Feature",
  "properties": {
    "name": "Hrazdan",
    "country": "AM",
    "subdivision": "05",
    "timezone": "Asia/Yerevan"
  },
  "geometry": {
    "type": "Point",
    "coordinates": [
      44.7662,
      40.49748
    ]
  }
}