{
  "type": "Feature",
  "properties": {
    "name": "Prroshyan",
    "country": "AM",
    "subdivision": "05",
    "timezone": "Asia/Yerevan"
  },
  "geometry": {
    "type": "Point",
    "coordinates": [
      44.41949,
      40.24731
    ]
  }
}