{
  "type": "Feature",
  "properties": {
    "name": "Zoravan",
    "country": "AM",
    "subdivision": "05",
    "timezone": "Asia/Yerevan"
  },
  "geometry": {
    "type": "Point",
    "coordinates": [
      44.52228,
      40.35553
    ]
  }
}