{
  "type": "Feature",
  "properties": {
    "name": "Botlhapatlou",
    "country": "BW",
    "subdivision": "06",
    "timezone": "Africa/Gaborone"
  },
  "geometry": {
    "type": "Point",
    "coordinates": [
      25.48976,
      -24.02591
    ]
  }
}