{
  "type": "Feature",
  "properties": {
    "name": "Mmopone",
    "country": "BW",
    "subdivision": "06",
    "timezone": "Africa/Gaborone"
  },
  "geometry": {
    "type": "Point",
    "coordinates": [
      25.87417,
      -24.56694
    ]
  }
}