{
  "type": "Feature",
  "properties": {
    "name": "Mogoditshane",
    "country": "BW",
    "subdivision": "06",
    "timezone": "Africa/Gaborone"
  },
  "geometry": {
    "type": "Point",
    "coordinates": [
      25.86556,
      -24.62694
    ]
  }
}