{
  "type": "Feature",
  "properties": {
    "name": "Ikedachō",
    "country": "JP",
    "subdivision": "39",
    "timezone": "Asia/Tokyo"
  },
  "geometry": {
    "type": "Point",
    "coordinates": [
      133.80616,
      34.02849
    ]
  }
}