{
  "type": "Feature",
  "properties": {
    "name": "Kamojimachō-jōgejima",
    "country": "JP",
    "subdivision": "39",
    "timezone": "Asia/Tokyo"
  },
  "geometry": {
    "type": "Point",
    "coordinates": [
      134.35033,
      34.06803
    ]
  }
}