{
  "type": "Feature",
  "properties": {
    "name": "Sorgun",
    "country": "TR",
    "subdivision": "66",
    "timezone": "Europe/Istanbul"
  },
  "geometry": {
    "type": "Point",
    "coordinates": [
      35.18596,
      39.81012
    ]
  }
}