{
  "type": "Feature",
  "properties": {
    "name": "Charef",
    "country": "DZ",
    "subdivision": "22",
    "timezone": "Africa/Algiers"
  },
  "geometry": {
    "type": "Point",
    "coordinates": [
      2.79503,
      34.62098
    ]
  }
}