{
  "type": "Feature",
  "properties": {
    "name": "Dar Chioukh",
    "country": "DZ",
    "subdivision": "22",
    "timezone": "Africa/Algiers"
  },
  "geometry": {
    "type": "Point",
    "coordinates": [
      3.48543,
      34.89638
    ]
  }
}