{
  "type": "Feature",
  "properties": {
    "name": "Andreiaşu de Jos",
    "country": "RO",
    "subdivision": "40",
    "timezone": "Europe/Bucharest"
  },
  "geometry": {
    "type": "Point",
    "coordinates": [
      26.83333,
      45.75
    ]
  }
}