{
  "type": "Feature",
  "properties": {
    "name": "Bogza",
    "country": "RO",
    "subdivision": "40",
    "timezone": "Europe/Bucharest"
  },
  "geometry": {
    "type": "Point",
    "coordinates": [
      27.19773,
      45.50798
    ]
  }
}