{
  "type": "Feature",
  "properties": {
    "name": "Burca",
    "country": "RO",
    "subdivision": "40",
    "timezone": "Europe/Bucharest"
  },
  "geometry": {
    "type": "Point",
    "coordinates": [
      26.94905,
      45.91224
    ]
  }
}