{
  "type": "Feature",
  "properties": {
    "name": "Dumbrăveni",
    "country": "RO",
    "subdivision": "40",
    "timezone": "Europe/Bucharest"
  },
  "geometry": {
    "type": "Point",
    "coordinates": [
      27.11667,
      45.53333
    ]
  }
}