{
  "type": "Feature",
  "properties": {
    "name": "Găgești",
    "country": "RO",
    "subdivision": "40",
    "timezone": "Europe/Bucharest"
  },
  "geometry": {
    "type": "Point",
    "coordinates": [
      27.0554,
      45.85598
    ]
  }
}