{
  "type": "Feature",
  "properties": {
    "name": "Jorăști",
    "country": "RO",
    "subdivision": "40",
    "timezone": "Europe/Bucharest"
  },
  "geometry": {
    "type": "Point",
    "coordinates": [
      27.26335,
      45.71477
    ]
  }
}