{
  "type": "Feature",
  "properties": {
    "name": "Mera",
    "country": "RO",
    "subdivision": "40",
    "timezone": "Europe/Bucharest"
  },
  "geometry": {
    "type": "Point",
    "coordinates": [
      26.95,
      45.76667
    ]
  }
}