{
  "type": "Feature",
  "properties": {
    "name": "Ploscuțeni",
    "country": "RO",
    "subdivision": "40",
    "timezone": "Europe/Bucharest"
  },
  "geometry": {
    "type": "Point",
    "coordinates": [
      27.27032,
      46.07859
    ]
  }
}