{
  "type": "Feature",
  "properties": {
    "name": "Răstoaca",
    "country": "RO",
    "subdivision": "40",
    "timezone": "Europe/Bucharest"
  },
  "geometry": {
    "type": "Point",
    "coordinates": [
      27.28723,
      45.66083
    ]
  }
}