{
  "type": "Feature",
  "properties": {
    "name": "Taounate",
    "country": "MA",
    "subdivision": "03",
    "timezone": "Africa/Casablanca"
  },
  "geometry": {
    "type": "Point",
    "coordinates": [
      -4.64009,
      34.53661
    ]
  }
}