{
  "type": "Feature",
  "properties": {
    "name": "Guisa",
    "country": "CU",
    "subdivision": "09",
    "timezone": "America/Havana"
  },
  "geometry": {
    "type": "Point",
    "coordinates": [
      -76.5393,
      20.25494
    ]
  }
}