{
  "type": "Feature",
  "properties": {
    "name": "Niquero",
    "country": "CU",
    "subdivision": "09",
    "timezone": "America/Havana"
  },
  "geometry": {
    "type": "Point",
    "coordinates": [
      -77.58089,
      20.04698
    ]
  }
}