{
  "type": "Feature",
  "properties": {
    "name": "Kambileyevskoye",
    "country": "RU",
    "subdivision": "68",
    "timezone": "Europe/Moscow"
  },
  "geometry": {
    "type": "Point",
    "coordinates": [
      44.75216,
      43.07858
    ]
  }
}