{
  "type": "Feature",
  "properties": {
    "name": "Mizur",
    "country": "RU",
    "subdivision": "68",
    "timezone": "Europe/Moscow"
  },
  "geometry": {
    "type": "Point",
    "coordinates": [
      44.0544,
      42.85133
    ]
  }
}