{
  "type": "Feature",
  "properties": {
    "name": "Nogir",
    "country": "RU",
    "subdivision": "68",
    "timezone": "Europe/Moscow"
  },
  "geometry": {
    "type": "Point",
    "coordinates": [
      44.6365,
      43.08162
    ]
  }
}