{
  "type": "Feature",
  "properties": {
    "name": "Geita",
    "country": "TZ",
    "subdivision": "28",
    "timezone": "Africa/Dar_es_Salaam"
  },
  "geometry": {
    "type": "Point",
    "coordinates": [
      32.2325,
      -2.8725
    ]
  }
}