{
  "type": "Feature",
  "properties": {
    "name": "Okahao",
    "country": "NA",
    "subdivision": "36",
    "timezone": "Africa/Windhoek"
  },
  "geometry": {
    "type": "Point",
    "coordinates": [
      15.06677,
      -17.88758
    ]
  }
}