{
  "type": "Feature",
  "properties": {
    "name": "Belozërsk",
    "country": "RU",
    "subdivision": "85",
    "timezone": "Europe/Moscow"
  },
  "geometry": {
    "type": "Point",
    "coordinates": [
      37.8084,
      60.0288
    ]
  }
}