{
  "type": "Feature",
  "properties": {
    "name": "Myaksa",
    "country": "RU",
    "subdivision": "85",
    "timezone": "Europe/Moscow"
  },
  "geometry": {
    "type": "Point",
    "coordinates": [
      38.1938,
      58.8889
    ]
  }
}