{
  "type": "Feature",
  "properties": {
    "name": "Verkhovazh’ye",
    "country": "RU",
    "subdivision": "85",
    "timezone": "Europe/Moscow"
  },
  "geometry": {
    "type": "Point",
    "coordinates": [
      42.04652,
      60.74717
    ]
  }
}