{
  "type": "Feature",
  "properties": {
    "name": "Frohnleiten",
    "country": "AT",
    "subdivision": "06",
    "timezone": "Europe/Vienna"
  },
  "geometry": {
    "type": "Point",
    "coordinates": [
      15.31667,
      47.26667
    ]
  }
}