{
  "type": "Feature",
  "properties": {
    "name": "Kalsdorf bei Graz",
    "country": "AT",
    "subdivision": "06",
    "timezone": "Europe/Vienna"
  },
  "geometry": {
    "type": "Point",
    "coordinates": [
      15.48028,
      46.96528
    ]
  }
}