{
  "type": "Feature",
  "properties": {
    "name": "Lannach",
    "country": "AT",
    "subdivision": "06",
    "timezone": "Europe/Vienna"
  },
  "geometry": {
    "type": "Point",
    "coordinates": [
      15.33722,
      46.94611
    ]
  }
}