{
  "type": "Feature",
  "properties": {
    "name": "Lieboch",
    "country": "AT",
    "subdivision": "06",
    "timezone": "Europe/Vienna"
  },
  "geometry": {
    "type": "Point",
    "coordinates": [
      15.3375,
      46.97417
    ]
  }
}