{
  "type": "Feature",
  "properties": {
    "name": "Liezen",
    "country": "AT",
    "subdivision": "06",
    "timezone": "Europe/Vienna"
  },
  "geometry": {
    "type": "Point",
    "coordinates": [
      14.23333,
      47.56667
    ]
  }
}