{
  "type": "Feature",
  "properties": {
    "name": "Sankt Stefan ob Leoben",
    "country": "AT",
    "subdivision": "06",
    "timezone": "Europe/Vienna"
  },
  "geometry": {
    "type": "Point",
    "coordinates": [
      14.97831,
      47.31672
    ]
  }
}