{
  "type": "Feature",
  "properties": {
    "name": "Sankt Lorenzen im Mürztal",
    "country": "AT",
    "subdivision": "06",
    "timezone": "Europe/Vienna"
  },
  "geometry": {
    "type": "Point",
    "coordinates": [
      15.36667,
      47.48333
    ]
  }
}