{
  "type": "Feature",
  "properties": {
    "name": "Sankt Leonhard",
    "country": "AT",
    "subdivision": "06",
    "timezone": "Europe/Vienna"
  },
  "geometry": {
    "type": "Point",
    "coordinates": [
      15.45784,
      47.06924
    ]
  }
}