{
  "type": "Feature",
  "properties": {
    "name": "Weiz",
    "country": "AT",
    "subdivision": "06",
    "timezone": "Europe/Vienna"
  },
  "geometry": {
    "type": "Point",
    "coordinates": [
      15.61667,
      47.21667
    ]
  }
}