{
  "type": "Feature",
  "properties": {
    "name": "Amagasaki",
    "country": "JP",
    "subdivision": "13",
    "timezone": "Asia/Tokyo"
  },
  "geometry": {
    "type": "Point",
    "coordinates": [
      135.41667,
      34.71667
    ]
  }
}