{
  "type": "Feature",
  "properties": {
    "name": "Nishiwaki",
    "country": "JP",
    "subdivision": "13",
    "timezone": "Asia/Tokyo"
  },
  "geometry": {
    "type": "Point",
    "coordinates": [
      134.97407,
      34.98419
    ]
  }
}