{
  "type": "Feature",
  "properties": {
    "name": "Sumoto",
    "country": "JP",
    "subdivision": "13",
    "timezone": "Asia/Tokyo"
  },
  "geometry": {
    "type": "Point",
    "coordinates": [
      134.88911,
      34.34322
    ]
  }
}