{
  "type": "Feature",
  "properties": {
    "name": "Yashiro",
    "country": "JP",
    "subdivision": "13",
    "timezone": "Asia/Tokyo"
  },
  "geometry": {
    "type": "Point",
    "coordinates": [
      134.96667,
      34.91667
    ]
  }
}