{
  "type": "Feature",
  "properties": {
    "name": "Al Quţayfah",
    "country": "SY",
    "subdivision": "08",
    "timezone": "Asia/Damascus"
  },
  "geometry": {
    "type": "Point",
    "coordinates": [
      36.60071,
      33.73848
    ]
  }
}