{
  "type": "Feature",
  "properties": {
    "name": "Dārayyā",
    "country": "SY",
    "subdivision": "08",
    "timezone": "Asia/Damascus"
  },
  "geometry": {
    "type": "Point",
    "coordinates": [
      36.23256,
      33.45835
    ]
  }
}