{
  "type": "Feature",
  "properties": {
    "name": "Ḩarastā",
    "country": "SY",
    "subdivision": "08",
    "timezone": "Asia/Damascus"
  },
  "geometry": {
    "type": "Point",
    "coordinates": [
      36.36515,
      33.55869
    ]
  }
}