{
  "type": "Feature",
  "properties": {
    "name": "‘Irbīn",
    "country": "SY",
    "subdivision": "08",
    "timezone": "Asia/Damascus"
  },
  "geometry": {
    "type": "Point",
    "coordinates": [
      36.36635,
      33.53719
    ]
  }
}