{
  "type": "Feature",
  "properties": {
    "name": "Tan-Tan",
    "country": "MA",
    "subdivision": "10",
    "timezone": "Africa/Casablanca"
  },
  "geometry": {
    "type": "Point",
    "coordinates": [
      -11.10321,
      28.43799
    ]
  }
}