{
  "type": "Feature",
  "properties": {
    "name": "Zag",
    "country": "MA",
    "subdivision": "10",
    "timezone": "Africa/Casablanca"
  },
  "geometry": {
    "type": "Point",
    "coordinates": [
      -9.29397,
      28.0221
    ]
  }
}