{
  "type": "Feature",
  "properties": {
    "name": "Mercedes",
    "country": "AR",
    "subdivision": "01",
    "timezone": "America/Argentina/Buenos_Aires"
  },
  "geometry": {
    "type": "Point",
    "coordinates": [
      -59.43068,
      -34.65145
    ]
  }
}