{
  "type": "Feature",
  "properties": {
    "name": "Punta Alta",
    "country": "AR",
    "subdivision": "01",
    "timezone": "America/Argentina/Buenos_Aires"
  },
  "geometry": {
    "type": "Point",
    "coordinates": [
      -62.07359,
      -38.87588
    ]
  }
}