{
  "type": "Feature",
  "properties": {
    "name": "San Isidro",
    "country": "AR",
    "subdivision": "01",
    "timezone": "America/Argentina/Buenos_Aires"
  },
  "geometry": {
    "type": "Point",
    "coordinates": [
      -58.52708,
      -34.4721
    ]
  }
}