{
  "type": "Feature",
  "properties": {
    "name": "Tres Algarrobos",
    "country": "AR",
    "subdivision": "01",
    "timezone": "America/Argentina/Buenos_Aires"
  },
  "geometry": {
    "type": "Point",
    "coordinates": [
      -62.77396,
      -35.19471
    ]
  }
}