{
  "type": "Feature",
  "properties": {
    "name": "Villa Gesell",
    "country": "AR",
    "subdivision": "01",
    "timezone": "America/Argentina/Buenos_Aires"
  },
  "geometry": {
    "type": "Point",
    "coordinates": [
      -56.97304,
      -37.26394
    ]
  }
}