{
  "type": "Feature",
  "properties": {
    "name": "Villa de Mayo",
    "country": "AR",
    "subdivision": "01",
    "timezone": "America/Argentina/Buenos_Aires"
  },
  "geometry": {
    "type": "Point",
    "coordinates": [
      -58.68059,
      -34.5108
    ]
  }
}