{
  "type": "Feature",
  "properties": {
    "name": "Guayabo Dulce",
    "country": "DO",
    "subdivision": "29",
    "timezone": "America/Santo_Domingo"
  },
  "geometry": {
    "type": "Point",
    "coordinates": [
      -69.28333,
      18.65
    ]
  }
}