{
  "type": "Feature",
  "properties": {
    "name": "Sabana de la Mar",
    "country": "DO",
    "subdivision": "29",
    "timezone": "America/Santo_Domingo"
  },
  "geometry": {
    "type": "Point",
    "coordinates": [
      -69.38843,
      19.05934
    ]
  }
}