{
  "type": "Feature",
  "properties": {
    "name": "Gundinci",
    "country": "HR",
    "subdivision": "02",
    "timezone": "Europe/Zagreb"
  },
  "geometry": {
    "type": "Point",
    "coordinates": [
      18.49139,
      45.15833
    ]
  }
}