{
  "type": "Feature",
  "properties": {
    "name": "Podvinje",
    "country": "HR",
    "subdivision": "02",
    "timezone": "Europe/Zagreb"
  },
  "geometry": {
    "type": "Point",
    "coordinates": [
      18.02694,
      45.19028
    ]
  }
}