{
  "type": "Feature",
  "properties": {
    "name": "Sikirevci",
    "country": "HR",
    "subdivision": "02",
    "timezone": "Europe/Zagreb"
  },
  "geometry": {
    "type": "Point",
    "coordinates": [
      18.46444,
      45.10889
    ]
  }
}