{
  "type": "Feature",
  "properties": {
    "name": "Stari Perkovci",
    "country": "HR",
    "subdivision": "02",
    "timezone": "Europe/Zagreb"
  },
  "geometry": {
    "type": "Point",
    "coordinates": [
      18.34861,
      45.2175
    ]
  }
}