{
  "type": "Feature",
  "properties": {
    "name": "Deli Tua",
    "country": "ID",
    "subdivision": "26",
    "timezone": "Asia/Jakarta"
  },
  "geometry": {
    "type": "Point",
    "coordinates": [
      98.6839,
      3.5078
    ]
  }
}