{
  "type": "Feature",
  "properties": {
    "name": "Tuktuk Sonak",
    "country": "ID",
    "subdivision": "26",
    "timezone": "Asia/Jakarta"
  },
  "geometry": {
    "type": "Point",
    "coordinates": [
      98.8576,
      2.6689
    ]
  }
}