{
  "type": "Feature",
  "properties": {
    "name": "Adânca",
    "country": "RO",
    "subdivision": "16",
    "timezone": "Europe/Bucharest"
  },
  "geometry": {
    "type": "Point",
    "coordinates": [
      25.61005,
      44.9225
    ]
  }
}