{
  "type": "Feature",
  "properties": {
    "name": "Bălteni",
    "country": "RO",
    "subdivision": "16",
    "timezone": "Europe/Bucharest"
  },
  "geometry": {
    "type": "Point",
    "coordinates": [
      25.69339,
      44.66488
    ]
  }
}