{
  "type": "Feature",
  "properties": {
    "name": "Brezoaele",
    "country": "RO",
    "subdivision": "16",
    "timezone": "Europe/Bucharest"
  },
  "geometry": {
    "type": "Point",
    "coordinates": [
      25.73333,
      44.58333
    ]
  }
}