{
  "type": "Feature",
  "properties": {
    "name": "Bungetu",
    "country": "RO",
    "subdivision": "16",
    "timezone": "Europe/Bucharest"
  },
  "geometry": {
    "type": "Point",
    "coordinates": [
      25.53816,
      44.84323
    ]
  }
}