{
  "type": "Feature",
  "properties": {
    "name": "Căprioru",
    "country": "RO",
    "subdivision": "16",
    "timezone": "Europe/Bucharest"
  },
  "geometry": {
    "type": "Point",
    "coordinates": [
      25.28116,
      44.98236
    ]
  }
}