{
  "type": "Feature",
  "properties": {
    "name": "Costeştii din Vale",
    "country": "RO",
    "subdivision": "16",
    "timezone": "Europe/Bucharest"
  },
  "geometry": {
    "type": "Point",
    "coordinates": [
      25.48333,
      44.65
    ]
  }
}