{
  "type": "Feature",
  "properties": {
    "name": "Crovu",
    "country": "RO",
    "subdivision": "16",
    "timezone": "Europe/Bucharest"
  },
  "geometry": {
    "type": "Point",
    "coordinates": [
      25.53684,
      44.58947
    ]
  }
}