{
  "type": "Feature",
  "properties": {
    "name": "Greci",
    "country": "RO",
    "subdivision": "16",
    "timezone": "Europe/Bucharest"
  },
  "geometry": {
    "type": "Point",
    "coordinates": [
      25.34346,
      44.66132
    ]
  }
}