{
  "type": "Feature",
  "properties": {
    "name": "Iedera de Jos",
    "country": "RO",
    "subdivision": "16",
    "timezone": "Europe/Bucharest"
  },
  "geometry": {
    "type": "Point",
    "coordinates": [
      25.63333,
      45.03333
    ]
  }
}