{
  "type": "Feature",
  "properties": {
    "name": "Ionești",
    "country": "RO",
    "subdivision": "16",
    "timezone": "Europe/Bucharest"
  },
  "geometry": {
    "type": "Point",
    "coordinates": [
      25.2778,
      44.69374
    ]
  }
}