{
  "type": "Feature",
  "properties": {
    "name": "Lunca",
    "country": "RO",
    "subdivision": "16",
    "timezone": "Europe/Bucharest"
  },
  "geometry": {
    "type": "Point",
    "coordinates": [
      25.44351,
      45.20022
    ]
  }
}