{
  "type": "Feature",
  "properties": {
    "name": "Lunguleţu",
    "country": "RO",
    "subdivision": "16",
    "timezone": "Europe/Bucharest"
  },
  "geometry": {
    "type": "Point",
    "coordinates": [
      25.65,
      44.61667
    ]
  }
}