{
  "type": "Feature",
  "properties": {
    "name": "Mărcești",
    "country": "RO",
    "subdivision": "16",
    "timezone": "Europe/Bucharest"
  },
  "geometry": {
    "type": "Point",
    "coordinates": [
      25.70951,
      44.80537
    ]
  }
}