{
  "type": "Feature",
  "properties": {
    "name": "Nucet",
    "country": "RO",
    "subdivision": "16",
    "timezone": "Europe/Bucharest"
  },
  "geometry": {
    "type": "Point",
    "coordinates": [
      25.55,
      44.78333
    ]
  }
}