{
  "type": "Feature",
  "properties": {
    "name": "Odaia Turcului",
    "country": "RO",
    "subdivision": "16",
    "timezone": "Europe/Bucharest"
  },
  "geometry": {
    "type": "Point",
    "coordinates": [
      25.45082,
      44.69777
    ]
  }
}