{
  "type": "Feature",
  "properties": {
    "name": "Petreşti",
    "country": "RO",
    "subdivision": "16",
    "timezone": "Europe/Bucharest"
  },
  "geometry": {
    "type": "Point",
    "coordinates": [
      25.33333,
      44.65
    ]
  }
}