{
  "type": "Feature",
  "properties": {
    "name": "Răscăeți",
    "country": "RO",
    "subdivision": "16",
    "timezone": "Europe/Bucharest"
  },
  "geometry": {
    "type": "Point",
    "coordinates": [
      25.2699,
      44.59221
    ]
  }
}