{
  "type": "Feature",
  "properties": {
    "name": "Sălcuța",
    "country": "RO",
    "subdivision": "16",
    "timezone": "Europe/Bucharest"
  },
  "geometry": {
    "type": "Point",
    "coordinates": [
      25.58103,
      44.64374
    ]
  }
}