{
  "type": "Feature",
  "properties": {
    "name": "Scheiu de Jos",
    "country": "RO",
    "subdivision": "16",
    "timezone": "Europe/Bucharest"
  },
  "geometry": {
    "type": "Point",
    "coordinates": [
      25.19986,
      44.9346
    ]
  }
}