{
  "type": "Feature",
  "properties": {
    "name": "Vulcana de Sus",
    "country": "RO",
    "subdivision": "16",
    "timezone": "Europe/Bucharest"
  },
  "geometry": {
    "type": "Point",
    "coordinates": [
      25.35826,
      45.10125
    ]
  }
}