{
  "type": "Feature",
  "properties": {
    "name": "Vulcana Băi",
    "country": "RO",
    "subdivision": "16",
    "timezone": "Europe/Bucharest"
  },
  "geometry": {
    "type": "Point",
    "coordinates": [
      25.38219,
      45.07982
    ]
  }
}