{
  "type": "Feature",
  "properties": {
    "name": "Zăvoiu",
    "country": "RO",
    "subdivision": "16",
    "timezone": "Europe/Bucharest"
  },
  "geometry": {
    "type": "Point",
    "coordinates": [
      25.4035,
      44.66038
    ]
  }
}