{
  "type": "Feature",
  "properties": {
    "name": "El Juncal",
    "country": "HN",
    "subdivision": "18",
    "timezone": "America/Tegucigalpa"
  },
  "geometry": {
    "type": "Point",
    "coordinates": [
      -86.43333,
      15.45
    ]
  }
}