{
  "type": "Feature",
  "properties": {
    "name": "La Rosa",
    "country": "HN",
    "subdivision": "18",
    "timezone": "America/Tegucigalpa"
  },
  "geometry": {
    "type": "Point",
    "coordinates": [
      -87.06667,
      15.35
    ]
  }
}