{
  "type": "Feature",
  "properties": {
    "name": "La Sarrosa",
    "country": "HN",
    "subdivision": "18",
    "timezone": "America/Tegucigalpa"
  },
  "geometry": {
    "type": "Point",
    "coordinates": [
      -87.83333,
      15.23333
    ]
  }
}