{
  "type": "Feature",
  "properties": {
    "name": "Nombre de Jesús",
    "country": "HN",
    "subdivision": "18",
    "timezone": "America/Tegucigalpa"
  },
  "geometry": {
    "type": "Point",
    "coordinates": [
      -86.68333,
      15.35
    ]
  }
}