{
  "type": "Feature",
  "properties": {
    "name": "San José",
    "country": "HN",
    "subdivision": "18",
    "timezone": "America/Tegucigalpa"
  },
  "geometry": {
    "type": "Point",
    "coordinates": [
      -87.16667,
      15.31667
    ]
  }
}