{
  "type": "Feature",
  "properties": {
    "name": "Santa Rita",
    "country": "HN",
    "subdivision": "18",
    "timezone": "America/Tegucigalpa"
  },
  "geometry": {
    "type": "Point",
    "coordinates": [
      -87.28333,
      15.16667
    ]
  }
}