{
  "type": "Feature",
  "properties": {
    "name": "Toyós",
    "country": "HN",
    "subdivision": "18",
    "timezone": "America/Tegucigalpa"
  },
  "geometry": {
    "type": "Point",
    "coordinates": [
      -87.65,
      15.55
    ]
  }
}