{
  "type": "Feature",
  "properties": {
    "name": "Çeşme",
    "country": "TR",
    "subdivision": "35",
    "timezone": "Europe/Istanbul"
  },
  "geometry": {
    "type": "Point",
    "coordinates": [
      26.30574,
      38.32614
    ]
  }
}