{
  "type": "Feature",
  "properties": {
    "name": "Karaburun",
    "country": "TR",
    "subdivision": "35",
    "timezone": "Europe/Istanbul"
  },
  "geometry": {
    "type": "Point",
    "coordinates": [
      26.51094,
      38.6364
    ]
  }
}