{
  "type": "Feature",
  "properties": {
    "name": "Kemalpaşa",
    "country": "TR",
    "subdivision": "35",
    "timezone": "Europe/Istanbul"
  },
  "geometry": {
    "type": "Point",
    "coordinates": [
      27.41731,
      38.42621
    ]
  }
}