{
  "type": "Feature",
  "properties": {
    "name": "Konaklı",
    "country": "TR",
    "subdivision": "35",
    "timezone": "Europe/Istanbul"
  },
  "geometry": {
    "type": "Point",
    "coordinates": [
      27.99611,
      38.11278
    ]
  }
}