{
  "type": "Feature",
  "properties": {
    "name": "Seferihisar",
    "country": "TR",
    "subdivision": "35",
    "timezone": "Europe/Istanbul"
  },
  "geometry": {
    "type": "Point",
    "coordinates": [
      26.83881,
      38.1975
    ]
  }
}