{
  "type": "Feature",
  "properties": {
    "name": "Selçuk",
    "country": "TR",
    "subdivision": "35",
    "timezone": "Europe/Istanbul"
  },
  "geometry": {
    "type": "Point",
    "coordinates": [
      27.36849,
      37.95137
    ]
  }
}