{
  "type": "Feature",
  "properties": {
    "name": "Yenifoça",
    "country": "TR",
    "subdivision": "35",
    "timezone": "Europe/Istanbul"
  },
  "geometry": {
    "type": "Point",
    "coordinates": [
      26.83333,
      38.73333
    ]
  }
}