{
  "type": "Feature",
  "properties": {
    "name": "Aristóbulo del Valle",
    "country": "AR",
    "subdivision": "14",
    "timezone": "America/Argentina/Cordoba"
  },
  "geometry": {
    "type": "Point",
    "coordinates": [
      -54.89626,
      -27.09625
    ]
  }
}