{
  "type": "Feature",
  "properties": {
    "name": "Cerro Azul",
    "country": "AR",
    "subdivision": "14",
    "timezone": "America/Argentina/Cordoba"
  },
  "geometry": {
    "type": "Point",
    "coordinates": [
      -55.4962,
      -27.6331
    ]
  }
}