{
  "type": "Feature",
  "properties": {
    "name": "Florentino Ameghino",
    "country": "AR",
    "subdivision": "14",
    "timezone": "America/Argentina/Cordoba"
  },
  "geometry": {
    "type": "Point",
    "coordinates": [
      -55.13333,
      -27.56667
    ]
  }
}