{
  "type": "Feature",
  "properties": {
    "name": "General Alvear",
    "country": "AR",
    "subdivision": "14",
    "timezone": "America/Argentina/Cordoba"
  },
  "geometry": {
    "type": "Point",
    "coordinates": [
      -55.16916,
      -27.42611
    ]
  }
}