{
  "type": "Feature",
  "properties": {
    "name": "Guaraní",
    "country": "AR",
    "subdivision": "14",
    "timezone": "America/Argentina/Cordoba"
  },
  "geometry": {
    "type": "Point",
    "coordinates": [
      -55.16077,
      -27.52323
    ]
  }
}