{
  "type": "Feature",
  "properties": {
    "name": "Oberá",
    "country": "AR",
    "subdivision": "14",
    "timezone": "America/Argentina/Cordoba"
  },
  "geometry": {
    "type": "Point",
    "coordinates": [
      -55.11994,
      -27.48706
    ]
  }
}