{
  "type": "Feature",
  "properties": {
    "name": "Veinticinco de Mayo",
    "country": "AR",
    "subdivision": "14",
    "timezone": "America/Argentina/Cordoba"
  },
  "geometry": {
    "type": "Point",
    "coordinates": [
      -54.74312,
      -27.37679
    ]
  }
}