{
  "type": "Feature",
  "properties": {
    "name": "Santiago de Baney",
    "country": "GQ",
    "subdivision": "04",
    "timezone": "Africa/Malabo"
  },
  "geometry": {
    "type": "Point",
    "coordinates": [
      8.9084,
      3.6992
    ]
  }
}