{
  "type": "Feature",
  "properties": {
    "name": "Mianyang",
    "country": "CN",
    "subdivision": "32",
    "timezone": "Asia/Shanghai"
  },
  "geometry": {
    "type": "Point",
    "coordinates": [
      104.68168,
      31.46784
    ]
  }
}