{
  "type": "Feature",
  "properties": {
    "name": "Taiping",
    "country": "CN",
    "subdivision": "32",
    "timezone": "Asia/Shanghai"
  },
  "geometry": {
    "type": "Point",
    "coordinates": [
      106.03771,
      28.14083
    ]
  }
}