{
  "type": "Feature",
  "properties": {
    "name": "Xichang",
    "country": "CN",
    "subdivision": "32",
    "timezone": "Asia/Shanghai"
  },
  "geometry": {
    "type": "Point",
    "coordinates": [
      102.26341,
      27.89642
    ]
  }
}