{
  "type": "Feature",
  "properties": {
    "name": "Vodice",
    "country": "SI",
    "subdivision": "E3",
    "timezone": "Europe/Ljubljana"
  },
  "geometry": {
    "type": "Point",
    "coordinates": [
      14.49492,
      46.18987
    ]
  }
}