{
  "type": "Feature",
  "properties": {
    "name": "Abbottstown",
    "country": "US",
    "subdivision": "PA",
    "timezone": "America/New_York"
  },
  "geometry": {
    "type": "Point",
    "coordinates": [
      -76.9847,
      39.88649
    ]
  }
}