{
  "type": "Feature",
  "properties": {
    "name": "Abington",
    "country": "US",
    "subdivision": "PA",
    "timezone": "America/New_York"
  },
  "geometry": {
    "type": "Point",
    "coordinates": [
      -75.11795,
      40.12067
    ]
  }
}