{
  "type": "Feature",
  "properties": {
    "name": "Adamstown",
    "country": "US",
    "subdivision": "PA",
    "timezone": "America/New_York"
  },
  "geometry": {
    "type": "Point",
    "coordinates": [
      -76.05633,
      40.2412
    ]
  }
}