{
  "type": "Feature",
  "properties": {
    "name": "Ambler",
    "country": "US",
    "subdivision": "PA",
    "timezone": "America/New_York"
  },
  "geometry": {
    "type": "Point",
    "coordinates": [
      -75.22157,
      40.15455
    ]
  }
}