{
  "type": "Feature",
  "properties": {
    "name": "Annville",
    "country": "US",
    "subdivision": "PA",
    "timezone": "America/New_York"
  },
  "geometry": {
    "type": "Point",
    "coordinates": [
      -76.51524,
      40.32954
    ]
  }
}