{
  "type": "Feature",
  "properties": {
    "name": "Archbald",
    "country": "US",
    "subdivision": "PA",
    "timezone": "America/New_York"
  },
  "geometry": {
    "type": "Point",
    "coordinates": [
      -75.53685,
      41.4948
    ]
  }
}