{
  "type": "Feature",
  "properties": {
    "name": "Atglen",
    "country": "US",
    "subdivision": "PA",
    "timezone": "America/New_York"
  },
  "geometry": {
    "type": "Point",
    "coordinates": [
      -75.97356,
      39.94927
    ]
  }
}