{
  "type": "Feature",
  "properties": {
    "name": "Athens",
    "country": "US",
    "subdivision": "PA",
    "timezone": "America/New_York"
  },
  "geometry": {
    "type": "Point",
    "coordinates": [
      -76.518,
      41.9573
    ]
  }
}