{
  "type": "Feature",
  "properties": {
    "name": "Back Mountain",
    "country": "US",
    "subdivision": "PA",
    "timezone": "America/New_York"
  },
  "geometry": {
    "type": "Point",
    "coordinates": [
      -75.99631,
      41.33591
    ]
  }
}