{
  "type": "Feature",
  "properties": {
    "name": "Bell Acres",
    "country": "US",
    "subdivision": "PA",
    "timezone": "America/New_York"
  },
  "geometry": {
    "type": "Point",
    "coordinates": [
      -80.16645,
      40.59007
    ]
  }
}