{
  "type": "Feature",
  "properties": {
    "name": "Belleville",
    "country": "US",
    "subdivision": "PA",
    "timezone": "America/New_York"
  },
  "geometry": {
    "type": "Point",
    "coordinates": [
      -77.72555,
      40.60507
    ]
  }
}