{
  "type": "Feature",
  "properties": {
    "name": "Bethel Park",
    "country": "US",
    "subdivision": "PA",
    "timezone": "America/New_York"
  },
  "geometry": {
    "type": "Point",
    "coordinates": [
      -80.0395,
      40.32757
    ]
  }
}