{
  "type": "Feature",
  "properties": {
    "name": "Birchwood Lakes",
    "country": "US",
    "subdivision": "PA",
    "timezone": "America/New_York"
  },
  "geometry": {
    "type": "Point",
    "coordinates": [
      -74.9185,
      41.25454
    ]
  }
}