{
  "type": "Feature",
  "properties": {
    "name": "Blawnox",
    "country": "US",
    "subdivision": "PA",
    "timezone": "America/New_York"
  },
  "geometry": {
    "type": "Point",
    "coordinates": [
      -79.86061,
      40.4934
    ]
  }
}