{
  "type": "Feature",
  "properties": {
    "name": "Brackenridge",
    "country": "US",
    "subdivision": "PA",
    "timezone": "America/New_York"
  },
  "geometry": {
    "type": "Point",
    "coordinates": [
      -79.74116,
      40.60812
    ]
  }
}