{
  "type": "Feature",
  "properties": {
    "name": "Breinigsville",
    "country": "US",
    "subdivision": "PA",
    "timezone": "America/New_York"
  },
  "geometry": {
    "type": "Point",
    "coordinates": [
      -75.6313,
      40.53676
    ]
  }
}