{
  "type": "Feature",
  "properties": {
    "name": "Broomall",
    "country": "US",
    "subdivision": "PA",
    "timezone": "America/New_York"
  },
  "geometry": {
    "type": "Point",
    "coordinates": [
      -75.35658,
      39.9815
    ]
  }
}