{
  "type": "Feature",
  "properties": {
    "name": "Canadensis",
    "country": "US",
    "subdivision": "PA",
    "timezone": "America/New_York"
  },
  "geometry": {
    "type": "Point",
    "coordinates": [
      -75.25129,
      41.19204
    ]
  }
}