{
  "type": "Feature",
  "properties": {
    "name": "Castle Shannon",
    "country": "US",
    "subdivision": "PA",
    "timezone": "America/New_York"
  },
  "geometry": {
    "type": "Point",
    "coordinates": [
      -80.02228,
      40.36479
    ]
  }
}