{
  "type": "Feature",
  "properties": {
    "name": "Centerville",
    "country": "US",
    "subdivision": "PA",
    "timezone": "America/New_York"
  },
  "geometry": {
    "type": "Point",
    "coordinates": [
      -79.97561,
      40.04535
    ]
  }
}