{
  "type": "Feature",
  "properties": {
    "name": "Chambersburg",
    "country": "US",
    "subdivision": "PA",
    "timezone": "America/New_York"
  },
  "geometry": {
    "type": "Point",
    "coordinates": [
      -77.6611,
      39.93759
    ]
  }
}