{
  "type": "Feature",
  "properties": {
    "name": "Cherryville",
    "country": "US",
    "subdivision": "PA",
    "timezone": "America/New_York"
  },
  "geometry": {
    "type": "Point",
    "coordinates": [
      -75.53852,
      40.75398
    ]
  }
}