{
  "type": "Feature",
  "properties": {
    "name": "Chevy Chase Heights",
    "country": "US",
    "subdivision": "PA",
    "timezone": "America/New_York"
  },
  "geometry": {
    "type": "Point",
    "coordinates": [
      -79.1442,
      40.63673
    ]
  }
}