{
  "type": "Feature",
  "properties": {
    "name": "Chinchilla",
    "country": "US",
    "subdivision": "PA",
    "timezone": "America/New_York"
  },
  "geometry": {
    "type": "Point",
    "coordinates": [
      -75.67713,
      41.47508
    ]
  }
}