{
  "type": "Feature",
  "properties": {
    "name": "Clarks Summit",
    "country": "US",
    "subdivision": "PA",
    "timezone": "America/New_York"
  },
  "geometry": {
    "type": "Point",
    "coordinates": [
      -75.70852,
      41.48869
    ]
  }
}