{
  "type": "Feature",
  "properties": {
    "name": "Cochranton",
    "country": "US",
    "subdivision": "PA",
    "timezone": "America/New_York"
  },
  "geometry": {
    "type": "Point",
    "coordinates": [
      -80.04839,
      41.52005
    ]
  }
}