{
  "type": "Feature",
  "properties": {
    "name": "Collinsburg",
    "country": "US",
    "subdivision": "PA",
    "timezone": "America/New_York"
  },
  "geometry": {
    "type": "Point",
    "coordinates": [
      -79.76838,
      40.22424
    ]
  }
}