{
  "type": "Feature",
  "properties": {
    "name": "Colonial Park",
    "country": "US",
    "subdivision": "PA",
    "timezone": "America/New_York"
  },
  "geometry": {
    "type": "Point",
    "coordinates": [
      -76.80969,
      40.30064
    ]
  }
}