{
  "type": "Feature",
  "properties": {
    "name": "Colwyn",
    "country": "US",
    "subdivision": "PA",
    "timezone": "America/New_York"
  },
  "geometry": {
    "type": "Point",
    "coordinates": [
      -75.25379,
      39.91234
    ]
  }
}