{
  "type": "Feature",
  "properties": {
    "name": "Conneaut Lakeshore",
    "country": "US",
    "subdivision": "PA",
    "timezone": "America/New_York"
  },
  "geometry": {
    "type": "Point",
    "coordinates": [
      -80.31008,
      41.62711
    ]
  }
}