{
  "type": "Feature",
  "properties": {
    "name": "Cranberry Township",
    "country": "US",
    "subdivision": "PA",
    "timezone": "America/New_York"
  },
  "geometry": {
    "type": "Point",
    "coordinates": [
      -80.10714,
      40.68496
    ]
  }
}