{
  "type": "Feature",
  "properties": {
    "name": "Cresco",
    "country": "US",
    "subdivision": "PA",
    "timezone": "America/New_York"
  },
  "geometry": {
    "type": "Point",
    "coordinates": [
      -75.28046,
      41.15398
    ]
  }
}