{
  "type": "Feature",
  "properties": {
    "name": "Curtisville",
    "country": "US",
    "subdivision": "PA",
    "timezone": "America/New_York"
  },
  "geometry": {
    "type": "Point",
    "coordinates": [
      -79.85089,
      40.64229
    ]
  }
}