{
  "type": "Feature",
  "properties": {
    "name": "Darby",
    "country": "US",
    "subdivision": "PA",
    "timezone": "America/New_York"
  },
  "geometry": {
    "type": "Point",
    "coordinates": [
      -75.25907,
      39.91845
    ]
  }
}