{
  "type": "Feature",
  "properties": {
    "name": "Dormont",
    "country": "US",
    "subdivision": "PA",
    "timezone": "America/New_York"
  },
  "geometry": {
    "type": "Point",
    "coordinates": [
      -80.03311,
      40.3959
    ]
  }
}