{
  "type": "Feature",
  "properties": {
    "name": "Dorneyville",
    "country": "US",
    "subdivision": "PA",
    "timezone": "America/New_York"
  },
  "geometry": {
    "type": "Point",
    "coordinates": [
      -75.51963,
      40.5751
    ]
  }
}