{
  "type": "Feature",
  "properties": {
    "name": "Downingtown",
    "country": "US",
    "subdivision": "PA",
    "timezone": "America/New_York"
  },
  "geometry": {
    "type": "Point",
    "coordinates": [
      -75.70327,
      40.0065
    ]
  }
}