{
  "type": "Feature",
  "properties": {
    "name": "DuBois",
    "country": "US",
    "subdivision": "PA",
    "timezone": "America/New_York"
  },
  "geometry": {
    "type": "Point",
    "coordinates": [
      -78.76003,
      41.11923
    ]
  }
}