{
  "type": "Feature",
  "properties": {
    "name": "Duncansville",
    "country": "US",
    "subdivision": "PA",
    "timezone": "America/New_York"
  },
  "geometry": {
    "type": "Point",
    "coordinates": [
      -78.4339,
      40.42341
    ]
  }
}