{
  "type": "Feature",
  "properties": {
    "name": "Eagleview",
    "country": "US",
    "subdivision": "PA",
    "timezone": "America/New_York"
  },
  "geometry": {
    "type": "Point",
    "coordinates": [
      -75.68076,
      40.05938
    ]
  }
}