{
  "type": "Feature",
  "properties": {
    "name": "East Conemaugh",
    "country": "US",
    "subdivision": "PA",
    "timezone": "America/New_York"
  },
  "geometry": {
    "type": "Point",
    "coordinates": [
      -78.88364,
      40.34868
    ]
  }
}