{
  "type": "Feature",
  "properties": {
    "name": "Eastlawn Gardens",
    "country": "US",
    "subdivision": "PA",
    "timezone": "America/New_York"
  },
  "geometry": {
    "type": "Point",
    "coordinates": [
      -75.29573,
      40.75065
    ]
  }
}