{
  "type": "Feature",
  "properties": {
    "name": "East Bangor",
    "country": "US",
    "subdivision": "PA",
    "timezone": "America/New_York"
  },
  "geometry": {
    "type": "Point",
    "coordinates": [
      -75.18379,
      40.87954
    ]
  }
}