{
  "type": "Feature",
  "properties": {
    "name": "East Uniontown",
    "country": "US",
    "subdivision": "PA",
    "timezone": "America/New_York"
  },
  "geometry": {
    "type": "Point",
    "coordinates": [
      -79.69782,
      39.8998
    ]
  }
}