{
  "type": "Feature",
  "properties": {
    "name": "East Pittsburgh",
    "country": "US",
    "subdivision": "PA",
    "timezone": "America/New_York"
  },
  "geometry": {
    "type": "Point",
    "coordinates": [
      -79.83866,
      40.39562
    ]
  }
}