{
  "type": "Feature",
  "properties": {
    "name": "Edgeworth",
    "country": "US",
    "subdivision": "PA",
    "timezone": "America/New_York"
  },
  "geometry": {
    "type": "Point",
    "coordinates": [
      -80.19284,
      40.55118
    ]
  }
}