{
  "type": "Feature",
  "properties": {
    "name": "Ellwood City",
    "country": "US",
    "subdivision": "PA",
    "timezone": "America/New_York"
  },
  "geometry": {
    "type": "Point",
    "coordinates": [
      -80.28645,
      40.86173
    ]
  }
}