{
  "type": "Feature",
  "properties": {
    "name": "Enhaut",
    "country": "US",
    "subdivision": "PA",
    "timezone": "America/New_York"
  },
  "geometry": {
    "type": "Point",
    "coordinates": [
      -76.82692,
      40.23176
    ]
  }
}