{
  "type": "Feature",
  "properties": {
    "name": "Evansburg",
    "country": "US",
    "subdivision": "PA",
    "timezone": "America/New_York"
  },
  "geometry": {
    "type": "Point",
    "coordinates": [
      -75.42907,
      40.18094
    ]
  }
}