{
  "type": "Feature",
  "properties": {
    "name": "Falls Creek",
    "country": "US",
    "subdivision": "PA",
    "timezone": "America/New_York"
  },
  "geometry": {
    "type": "Point",
    "coordinates": [
      -78.80447,
      41.14506
    ]
  }
}