{
  "type": "Feature",
  "properties": {
    "name": "Fernway",
    "country": "US",
    "subdivision": "PA",
    "timezone": "America/New_York"
  },
  "geometry": {
    "type": "Point",
    "coordinates": [
      -80.13089,
      40.69479
    ]
  }
}