{
  "type": "Feature",
  "properties": {
    "name": "Flying Hills",
    "country": "US",
    "subdivision": "PA",
    "timezone": "America/New_York"
  },
  "geometry": {
    "type": "Point",
    "coordinates": [
      -75.9141,
      40.27676
    ]
  }
}