{
  "type": "Feature",
  "properties": {
    "name": "Forest Hills",
    "country": "US",
    "subdivision": "PA",
    "timezone": "America/New_York"
  },
  "geometry": {
    "type": "Point",
    "coordinates": [
      -79.85005,
      40.41979
    ]
  }
}