{
  "type": "Feature",
  "properties": {
    "name": "Freemansburg",
    "country": "US",
    "subdivision": "PA",
    "timezone": "America/New_York"
  },
  "geometry": {
    "type": "Point",
    "coordinates": [
      -75.34574,
      40.62649
    ]
  }
}