{
  "type": "Feature",
  "properties": {
    "name": "Friedens",
    "country": "US",
    "subdivision": "PA",
    "timezone": "America/New_York"
  },
  "geometry": {
    "type": "Point",
    "coordinates": [
      -78.99836,
      40.05008
    ]
  }
}