{
  "type": "Feature",
  "properties": {
    "name": "Fullerton",
    "country": "US",
    "subdivision": "PA",
    "timezone": "America/New_York"
  },
  "geometry": {
    "type": "Point",
    "coordinates": [
      -75.47324,
      40.63176
    ]
  }
}