{
  "type": "Feature",
  "properties": {
    "name": "Galeton",
    "country": "US",
    "subdivision": "PA",
    "timezone": "America/New_York"
  },
  "geometry": {
    "type": "Point",
    "coordinates": [
      -77.64193,
      41.73312
    ]
  }
}