{
  "type": "Feature",
  "properties": {
    "name": "Glen Lyon",
    "country": "US",
    "subdivision": "PA",
    "timezone": "America/New_York"
  },
  "geometry": {
    "type": "Point",
    "coordinates": [
      -76.07465,
      41.17508
    ]
  }
}