{
  "type": "Feature",
  "properties": {
    "name": "Glen Rock",
    "country": "US",
    "subdivision": "PA",
    "timezone": "America/New_York"
  },
  "geometry": {
    "type": "Point",
    "coordinates": [
      -76.73025,
      39.79316
    ]
  }
}