{
  "type": "Feature",
  "properties": {
    "name": "Green Tree",
    "country": "US",
    "subdivision": "PA",
    "timezone": "America/New_York"
  },
  "geometry": {
    "type": "Point",
    "coordinates": [
      -80.04561,
      40.41174
    ]
  }
}