{
  "type": "Feature",
  "properties": {
    "name": "Greenwood",
    "country": "US",
    "subdivision": "PA",
    "timezone": "America/New_York"
  },
  "geometry": {
    "type": "Point",
    "coordinates": [
      -78.35751,
      40.5359
    ]
  }
}