{
  "type": "Feature",
  "properties": {
    "name": "Grill",
    "country": "US",
    "subdivision": "PA",
    "timezone": "America/New_York"
  },
  "geometry": {
    "type": "Point",
    "coordinates": [
      -75.94049,
      40.2987
    ]
  }
}