{
  "type": "Feature",
  "properties": {
    "name": "Harrisburg",
    "country": "US",
    "subdivision": "PA",
    "timezone": "America/New_York"
  },
  "geometry": {
    "type": "Point",
    "coordinates": [
      -76.88442,
      40.2737
    ]
  }
}