{
  "type": "Feature",
  "properties": {
    "name": "Hawley",
    "country": "US",
    "subdivision": "PA",
    "timezone": "America/New_York"
  },
  "geometry": {
    "type": "Point",
    "coordinates": [
      -75.18212,
      41.47592
    ]
  }
}