{
  "type": "Feature",
  "properties": {
    "name": "Hebron",
    "country": "US",
    "subdivision": "PA",
    "timezone": "America/New_York"
  },
  "geometry": {
    "type": "Point",
    "coordinates": [
      -76.3994,
      40.33898
    ]
  }
}