{
  "type": "Feature",
  "properties": {
    "name": "Homer City",
    "country": "US",
    "subdivision": "PA",
    "timezone": "America/New_York"
  },
  "geometry": {
    "type": "Point",
    "coordinates": [
      -79.16226,
      40.5434
    ]
  }
}