{
  "type": "Feature",
  "properties": {
    "name": "Horsham",
    "country": "US",
    "subdivision": "PA",
    "timezone": "America/New_York"
  },
  "geometry": {
    "type": "Point",
    "coordinates": [
      -75.12851,
      40.17844
    ]
  }
}