{
  "type": "Feature",
  "properties": {
    "name": "Hummels Wharf",
    "country": "US",
    "subdivision": "PA",
    "timezone": "America/New_York"
  },
  "geometry": {
    "type": "Point",
    "coordinates": [
      -76.8358,
      40.83175
    ]
  }
}