{
  "type": "Feature",
  "properties": {
    "name": "Jacksonwald",
    "country": "US",
    "subdivision": "PA",
    "timezone": "America/New_York"
  },
  "geometry": {
    "type": "Point",
    "coordinates": [
      -75.84965,
      40.32454
    ]
  }
}