{
  "type": "Feature",
  "properties": {
    "name": "Jefferson Hills",
    "country": "US",
    "subdivision": "PA",
    "timezone": "America/New_York"
  },
  "geometry": {
    "type": "Point",
    "coordinates": [
      -79.93199,
      40.29118
    ]
  }
}