{
  "type": "Feature",
  "properties": {
    "name": "Johnsonburg",
    "country": "US",
    "subdivision": "PA",
    "timezone": "America/New_York"
  },
  "geometry": {
    "type": "Point",
    "coordinates": [
      -78.67503,
      41.49062
    ]
  }
}