{
  "type": "Feature",
  "properties": {
    "name": "Lake Latonka",
    "country": "US",
    "subdivision": "PA",
    "timezone": "America/New_York"
  },
  "geometry": {
    "type": "Point",
    "coordinates": [
      -80.18129,
      41.29039
    ]
  }
}