{
  "type": "Feature",
  "properties": {
    "name": "Lansford",
    "country": "US",
    "subdivision": "PA",
    "timezone": "America/New_York"
  },
  "geometry": {
    "type": "Point",
    "coordinates": [
      -75.88242,
      40.83176
    ]
  }
}