{
  "type": "Feature",
  "properties": {
    "name": "Lawrence Park",
    "country": "US",
    "subdivision": "PA",
    "timezone": "America/New_York"
  },
  "geometry": {
    "type": "Point",
    "coordinates": [
      -76.8008,
      40.34564
    ]
  }
}