{
  "type": "Feature",
  "properties": {
    "name": "Lehighton",
    "country": "US",
    "subdivision": "PA",
    "timezone": "America/New_York"
  },
  "geometry": {
    "type": "Point",
    "coordinates": [
      -75.7138,
      40.8337
    ]
  }
}