{
  "type": "Feature",
  "properties": {
    "name": "Lewistown",
    "country": "US",
    "subdivision": "PA",
    "timezone": "America/New_York"
  },
  "geometry": {
    "type": "Point",
    "coordinates": [
      -77.57138,
      40.59924
    ]
  }
}