{
  "type": "Feature",
  "properties": {
    "name": "Lincoln Park",
    "country": "US",
    "subdivision": "PA",
    "timezone": "America/New_York"
  },
  "geometry": {
    "type": "Point",
    "coordinates": [
      -75.98549,
      40.31481
    ]
  }
}