{
  "type": "Feature",
  "properties": {
    "name": "Loyalhanna",
    "country": "US",
    "subdivision": "PA",
    "timezone": "America/New_York"
  },
  "geometry": {
    "type": "Point",
    "coordinates": [
      -79.36226,
      40.32257
    ]
  }
}