{
  "type": "Feature",
  "properties": {
    "name": "Lynnwood-Pricedale",
    "country": "US",
    "subdivision": "PA",
    "timezone": "America/New_York"
  },
  "geometry": {
    "type": "Point",
    "coordinates": [
      -79.85135,
      40.13071
    ]
  }
}