{
  "type": "Feature",
  "properties": {
    "name": "Macungie",
    "country": "US",
    "subdivision": "PA",
    "timezone": "America/New_York"
  },
  "geometry": {
    "type": "Point",
    "coordinates": [
      -75.55519,
      40.51593
    ]
  }
}