{
  "type": "Feature",
  "properties": {
    "name": "Marcus Hook",
    "country": "US",
    "subdivision": "PA",
    "timezone": "America/New_York"
  },
  "geometry": {
    "type": "Point",
    "coordinates": [
      -75.41853,
      39.81928
    ]
  }
}