{
  "type": "Feature",
  "properties": {
    "name": "Marshallton",
    "country": "US",
    "subdivision": "PA",
    "timezone": "America/New_York"
  },
  "geometry": {
    "type": "Point",
    "coordinates": [
      -76.5394,
      40.78675
    ]
  }
}