{
  "type": "Feature",
  "properties": {
    "name": "McDonald",
    "country": "US",
    "subdivision": "PA",
    "timezone": "America/New_York"
  },
  "geometry": {
    "type": "Point",
    "coordinates": [
      -80.23478,
      40.3709
    ]
  }
}