{
  "type": "Feature",
  "properties": {
    "name": "McSherrystown",
    "country": "US",
    "subdivision": "PA",
    "timezone": "America/New_York"
  },
  "geometry": {
    "type": "Point",
    "coordinates": [
      -77.01137,
      39.80732
    ]
  }
}