{
  "type": "Feature",
  "properties": {
    "name": "Meadville",
    "country": "US",
    "subdivision": "PA",
    "timezone": "America/New_York"
  },
  "geometry": {
    "type": "Point",
    "coordinates": [
      -80.15145,
      41.64144
    ]
  }
}