{
  "type": "Feature",
  "properties": {
    "name": "Middleburg",
    "country": "US",
    "subdivision": "PA",
    "timezone": "America/New_York"
  },
  "geometry": {
    "type": "Point",
    "coordinates": [
      -77.0472,
      40.78592
    ]
  }
}