{
  "type": "Feature",
  "properties": {
    "name": "Midway",
    "country": "US",
    "subdivision": "PA",
    "timezone": "America/New_York"
  },
  "geometry": {
    "type": "Point",
    "coordinates": [
      -77.00276,
      39.80843
    ]
  }
}