{
  "type": "Feature",
  "properties": {
    "name": "Millbourne",
    "country": "US",
    "subdivision": "PA",
    "timezone": "America/New_York"
  },
  "geometry": {
    "type": "Point",
    "coordinates": [
      -75.25018,
      39.96345
    ]
  }
}