{
  "type": "Feature",
  "properties": {
    "name": "Moscow",
    "country": "US",
    "subdivision": "PA",
    "timezone": "America/New_York"
  },
  "geometry": {
    "type": "Point",
    "coordinates": [
      -75.51852,
      41.33675
    ]
  }
}