{
  "type": "Feature",
  "properties": {
    "name": "Muhlenberg Park",
    "country": "US",
    "subdivision": "PA",
    "timezone": "America/New_York"
  },
  "geometry": {
    "type": "Point",
    "coordinates": [
      -75.94132,
      40.38482
    ]
  }
}