{
  "type": "Feature",
  "properties": {
    "name": "Mundys Corner",
    "country": "US",
    "subdivision": "PA",
    "timezone": "America/New_York"
  },
  "geometry": {
    "type": "Point",
    "coordinates": [
      -78.84113,
      40.44479
    ]
  }
}