{
  "type": "Feature",
  "properties": {
    "name": "Nanticoke",
    "country": "US",
    "subdivision": "PA",
    "timezone": "America/New_York"
  },
  "geometry": {
    "type": "Point",
    "coordinates": [
      -76.00492,
      41.20536
    ]
  }
}