{
  "type": "Feature",
  "properties": {
    "name": "Nazareth",
    "country": "US",
    "subdivision": "PA",
    "timezone": "America/New_York"
  },
  "geometry": {
    "type": "Point",
    "coordinates": [
      -75.30962,
      40.74038
    ]
  }
}