{
  "type": "Feature",
  "properties": {
    "name": "New Castle",
    "country": "US",
    "subdivision": "PA",
    "timezone": "America/New_York"
  },
  "geometry": {
    "type": "Point",
    "coordinates": [
      -80.34701,
      41.00367
    ]
  }
}