{
  "type": "Feature",
  "properties": {
    "name": "New Berlinville",
    "country": "US",
    "subdivision": "PA",
    "timezone": "America/New_York"
  },
  "geometry": {
    "type": "Point",
    "coordinates": [
      -75.63296,
      40.34537
    ]
  }
}