{
  "type": "Feature",
  "properties": {
    "name": "New Bloomfield",
    "country": "US",
    "subdivision": "PA",
    "timezone": "America/New_York"
  },
  "geometry": {
    "type": "Point",
    "coordinates": [
      -77.18637,
      40.41981
    ]
  }
}