{
  "type": "Feature",
  "properties": {
    "name": "Northumberland",
    "country": "US",
    "subdivision": "PA",
    "timezone": "America/New_York"
  },
  "geometry": {
    "type": "Point",
    "coordinates": [
      -76.79747,
      40.89175
    ]
  }
}