{
  "type": "Feature",
  "properties": {
    "name": "North Apollo",
    "country": "US",
    "subdivision": "PA",
    "timezone": "America/New_York"
  },
  "geometry": {
    "type": "Point",
    "coordinates": [
      -79.5556,
      40.59618
    ]
  }
}