{
  "type": "Feature",
  "properties": {
    "name": "Oakland",
    "country": "US",
    "subdivision": "PA",
    "timezone": "America/New_York"
  },
  "geometry": {
    "type": "Point",
    "coordinates": [
      -78.88752,
      40.30646
    ]
  }
}