{
  "type": "Feature",
  "properties": {
    "name": "Oakwood",
    "country": "US",
    "subdivision": "PA",
    "timezone": "America/New_York"
  },
  "geometry": {
    "type": "Point",
    "coordinates": [
      -80.37951,
      41.01062
    ]
  }
}