{
  "type": "Feature",
  "properties": {
    "name": "Oliver",
    "country": "US",
    "subdivision": "PA",
    "timezone": "America/New_York"
  },
  "geometry": {
    "type": "Point",
    "coordinates": [
      -79.71782,
      39.91869
    ]
  }
}