{
  "type": "Feature",
  "properties": {
    "name": "Orchard Hills",
    "country": "US",
    "subdivision": "PA",
    "timezone": "America/New_York"
  },
  "geometry": {
    "type": "Point",
    "coordinates": [
      -79.53143,
      40.58618
    ]
  }
}