{
  "type": "Feature",
  "properties": {
    "name": "Oreland",
    "country": "US",
    "subdivision": "PA",
    "timezone": "America/New_York"
  },
  "geometry": {
    "type": "Point",
    "coordinates": [
      -75.17768,
      40.11844
    ]
  }
}