{
  "type": "Feature",
  "properties": {
    "name": "Palmdale",
    "country": "US",
    "subdivision": "PA",
    "timezone": "America/New_York"
  },
  "geometry": {
    "type": "Point",
    "coordinates": [
      -76.61858,
      40.29787
    ]
  }
}