{
  "type": "Feature",
  "properties": {
    "name": "Paoli",
    "country": "US",
    "subdivision": "PA",
    "timezone": "America/New_York"
  },
  "geometry": {
    "type": "Point",
    "coordinates": [
      -75.47631,
      40.04205
    ]
  }
}