{
  "type": "Feature",
  "properties": {
    "name": "Penryn",
    "country": "US",
    "subdivision": "PA",
    "timezone": "America/New_York"
  },
  "geometry": {
    "type": "Point",
    "coordinates": [
      -76.36829,
      40.20509
    ]
  }
}