{
  "type": "Feature",
  "properties": {
    "name": "Pittston",
    "country": "US",
    "subdivision": "PA",
    "timezone": "America/New_York"
  },
  "geometry": {
    "type": "Point",
    "coordinates": [
      -75.78936,
      41.32591
    ]
  }
}