{
  "type": "Feature",
  "properties": {
    "name": "Plymouth",
    "country": "US",
    "subdivision": "PA",
    "timezone": "America/New_York"
  },
  "geometry": {
    "type": "Point",
    "coordinates": [
      -75.94464,
      41.24036
    ]
  }
}