{
  "type": "Feature",
  "properties": {
    "name": "Port Carbon",
    "country": "US",
    "subdivision": "PA",
    "timezone": "America/New_York"
  },
  "geometry": {
    "type": "Point",
    "coordinates": [
      -76.16883,
      40.69648
    ]
  }
}