{
  "type": "Feature",
  "properties": {
    "name": "Prospect Park",
    "country": "US",
    "subdivision": "PA",
    "timezone": "America/New_York"
  },
  "geometry": {
    "type": "Point",
    "coordinates": [
      -75.30824,
      39.88789
    ]
  }
}