{
  "type": "Feature",
  "properties": {
    "name": "Pymatuning Central",
    "country": "US",
    "subdivision": "PA",
    "timezone": "America/New_York"
  },
  "geometry": {
    "type": "Point",
    "coordinates": [
      -80.4796,
      41.58546
    ]
  }
}