{
  "type": "Feature",
  "properties": {
    "name": "Rankin",
    "country": "US",
    "subdivision": "PA",
    "timezone": "America/New_York"
  },
  "geometry": {
    "type": "Point",
    "coordinates": [
      -79.87922,
      40.41257
    ]
  }
}