{
  "type": "Feature",
  "properties": {
    "name": "Reynoldsville",
    "country": "US",
    "subdivision": "PA",
    "timezone": "America/New_York"
  },
  "geometry": {
    "type": "Point",
    "coordinates": [
      -78.88864,
      41.09701
    ]
  }
}