{
  "type": "Feature",
  "properties": {
    "name": "Robesonia",
    "country": "US",
    "subdivision": "PA",
    "timezone": "America/New_York"
  },
  "geometry": {
    "type": "Point",
    "coordinates": [
      -76.13439,
      40.35176
    ]
  }
}