{
  "type": "Feature",
  "properties": {
    "name": "Sanatoga",
    "country": "US",
    "subdivision": "PA",
    "timezone": "America/New_York"
  },
  "geometry": {
    "type": "Point",
    "coordinates": [
      -75.59518,
      40.2451
    ]
  }
}