{
  "type": "Feature",
  "properties": {
    "name": "Saylorsburg",
    "country": "US",
    "subdivision": "PA",
    "timezone": "America/New_York"
  },
  "geometry": {
    "type": "Point",
    "coordinates": [
      -75.32352,
      40.89565
    ]
  }
}