{
  "type": "Feature",
  "properties": {
    "name": "Seven Fields",
    "country": "US",
    "subdivision": "PA",
    "timezone": "America/New_York"
  },
  "geometry": {
    "type": "Point",
    "coordinates": [
      -80.06256,
      40.69173
    ]
  }
}