{
  "type": "Feature",
  "properties": {
    "name": "Shamokin Dam",
    "country": "US",
    "subdivision": "PA",
    "timezone": "America/New_York"
  },
  "geometry": {
    "type": "Point",
    "coordinates": [
      -76.81969,
      40.8487
    ]
  }
}