{
  "type": "Feature",
  "properties": {
    "name": "Shanor-Northvue",
    "country": "US",
    "subdivision": "PA",
    "timezone": "America/New_York"
  },
  "geometry": {
    "type": "Point",
    "coordinates": [
      -79.91562,
      40.91045
    ]
  }
}