{
  "type": "Feature",
  "properties": {
    "name": "Sharon",
    "country": "US",
    "subdivision": "PA",
    "timezone": "America/New_York"
  },
  "geometry": {
    "type": "Point",
    "coordinates": [
      -80.4934,
      41.23311
    ]
  }
}