{
  "type": "Feature",
  "properties": {
    "name": "Shiloh",
    "country": "US",
    "subdivision": "PA",
    "timezone": "America/New_York"
  },
  "geometry": {
    "type": "Point",
    "coordinates": [
      -76.79719,
      39.97815
    ]
  }
}