{
  "type": "Feature",
  "properties": {
    "name": "Shillington",
    "country": "US",
    "subdivision": "PA",
    "timezone": "America/New_York"
  },
  "geometry": {
    "type": "Point",
    "coordinates": [
      -75.96549,
      40.30787
    ]
  }
}