{
  "type": "Feature",
  "properties": {
    "name": "Shrewsbury",
    "country": "US",
    "subdivision": "PA",
    "timezone": "America/New_York"
  },
  "geometry": {
    "type": "Point",
    "coordinates": [
      -76.67969,
      39.76871
    ]
  }
}