{
  "type": "Feature",
  "properties": {
    "name": "Slatington",
    "country": "US",
    "subdivision": "PA",
    "timezone": "America/New_York"
  },
  "geometry": {
    "type": "Point",
    "coordinates": [
      -75.61185,
      40.74843
    ]
  }
}