{
  "type": "Feature",
  "properties": {
    "name": "South Williamsport",
    "country": "US",
    "subdivision": "PA",
    "timezone": "America/New_York"
  },
  "geometry": {
    "type": "Point",
    "coordinates": [
      -76.99913,
      41.23202
    ]
  }
}