{
  "type": "Feature",
  "properties": {
    "name": "South Park Township",
    "country": "US",
    "subdivision": "PA",
    "timezone": "America/New_York"
  },
  "geometry": {
    "type": "Point",
    "coordinates": [
      -79.99405,
      40.29864
    ]
  }
}