{
  "type": "Feature",
  "properties": {
    "name": "Spinnerstown",
    "country": "US",
    "subdivision": "PA",
    "timezone": "America/New_York"
  },
  "geometry": {
    "type": "Point",
    "coordinates": [
      -75.43712,
      40.43899
    ]
  }
}