{
  "type": "Feature",
  "properties": {
    "name": "Spring Grove",
    "country": "US",
    "subdivision": "PA",
    "timezone": "America/New_York"
  },
  "geometry": {
    "type": "Point",
    "coordinates": [
      -76.86581,
      39.87454
    ]
  }
}