{
  "type": "Feature",
  "properties": {
    "name": "Stiles",
    "country": "US",
    "subdivision": "PA",
    "timezone": "America/New_York"
  },
  "geometry": {
    "type": "Point",
    "coordinates": [
      -75.50824,
      40.66537
    ]
  }
}