{
  "type": "Feature",
  "properties": {
    "name": "Stony Creek Mills",
    "country": "US",
    "subdivision": "PA",
    "timezone": "America/New_York"
  },
  "geometry": {
    "type": "Point",
    "coordinates": [
      -75.86993,
      40.34565
    ]
  }
}