{
  "type": "Feature",
  "properties": {
    "name": "Sugarcreek",
    "country": "US",
    "subdivision": "PA",
    "timezone": "America/New_York"
  },
  "geometry": {
    "type": "Point",
    "coordinates": [
      -79.88117,
      41.42145
    ]
  }
}