{
  "type": "Feature",
  "properties": {
    "name": "Sun Valley",
    "country": "US",
    "subdivision": "PA",
    "timezone": "America/New_York"
  },
  "geometry": {
    "type": "Point",
    "coordinates": [
      -75.46602,
      40.98203
    ]
  }
}