{
  "type": "Feature",
  "properties": {
    "name": "Susquehanna Trails",
    "country": "US",
    "subdivision": "PA",
    "timezone": "America/New_York"
  },
  "geometry": {
    "type": "Point",
    "coordinates": [
      -76.36802,
      39.75872
    ]
  }
}