{
  "type": "Feature",
  "properties": {
    "name": "Trucksville",
    "country": "US",
    "subdivision": "PA",
    "timezone": "America/New_York"
  },
  "geometry": {
    "type": "Point",
    "coordinates": [
      -75.93214,
      41.30397
    ]
  }
}