{
  "type": "Feature",
  "properties": {
    "name": "Tyrone",
    "country": "US",
    "subdivision": "PA",
    "timezone": "America/New_York"
  },
  "geometry": {
    "type": "Point",
    "coordinates": [
      -78.23862,
      40.67062
    ]
  }
}