{
  "type": "Feature",
  "properties": {
    "name": "Valley View",
    "country": "US",
    "subdivision": "PA",
    "timezone": "America/New_York"
  },
  "geometry": {
    "type": "Point",
    "coordinates": [
      -76.70108,
      39.9501
    ]
  }
}