{
  "type": "Feature",
  "properties": {
    "name": "Walnutport",
    "country": "US",
    "subdivision": "PA",
    "timezone": "America/New_York"
  },
  "geometry": {
    "type": "Point",
    "coordinates": [
      -75.5988,
      40.75426
    ]
  }
}