{
  "type": "Feature",
  "properties": {
    "name": "Watsontown",
    "country": "US",
    "subdivision": "PA",
    "timezone": "America/New_York"
  },
  "geometry": {
    "type": "Point",
    "coordinates": [
      -76.86385,
      41.08453
    ]
  }
}