{
  "type": "Feature",
  "properties": {
    "name": "Waynesboro",
    "country": "US",
    "subdivision": "PA",
    "timezone": "America/New_York"
  },
  "geometry": {
    "type": "Point",
    "coordinates": [
      -77.57777,
      39.75593
    ]
  }
}