{
  "type": "Feature",
  "properties": {
    "name": "Weissport East",
    "country": "US",
    "subdivision": "PA",
    "timezone": "America/New_York"
  },
  "geometry": {
    "type": "Point",
    "coordinates": [
      -75.68643,
      40.83697
    ]
  }
}