{
  "type": "Feature",
  "properties": {
    "name": "West Fairview",
    "country": "US",
    "subdivision": "PA",
    "timezone": "America/New_York"
  },
  "geometry": {
    "type": "Point",
    "coordinates": [
      -76.91553,
      40.27509
    ]
  }
}