{
  "type": "Feature",
  "properties": {
    "name": "West Leechburg",
    "country": "US",
    "subdivision": "PA",
    "timezone": "America/New_York"
  },
  "geometry": {
    "type": "Point",
    "coordinates": [
      -79.61282,
      40.62229
    ]
  }
}