{
  "type": "Feature",
  "properties": {
    "name": "White Haven",
    "country": "US",
    "subdivision": "PA",
    "timezone": "America/New_York"
  },
  "geometry": {
    "type": "Point",
    "coordinates": [
      -75.77408,
      41.06064
    ]
  }
}