{
  "type": "Feature",
  "properties": {
    "name": "Wolfdale",
    "country": "US",
    "subdivision": "PA",
    "timezone": "America/New_York"
  },
  "geometry": {
    "type": "Point",
    "coordinates": [
      -80.28784,
      40.19285
    ]
  }
}