{
  "type": "Feature",
  "properties": {
    "name": "Wyndmoor",
    "country": "US",
    "subdivision": "PA",
    "timezone": "America/New_York"
  },
  "geometry": {
    "type": "Point",
    "coordinates": [
      -75.18934,
      40.08122
    ]
  }
}