{
  "type": "Feature",
  "properties": {
    "name": "Wyomissing Hills",
    "country": "US",
    "subdivision": "PA",
    "timezone": "America/New_York"
  },
  "geometry": {
    "type": "Point",
    "coordinates": [
      -75.97966,
      40.33759
    ]
  }
}