{
  "type": "Feature",
  "properties": {
    "name": "Yeadon",
    "country": "US",
    "subdivision": "PA",
    "timezone": "America/New_York"
  },
  "geometry": {
    "type": "Point",
    "coordinates": [
      -75.25546,
      39.939
    ]
  }
}