{
  "type": "Feature",
  "properties": {
    "name": "Kocahasanlı",
    "country": "TR",
    "subdivision": "32",
    "timezone": "Europe/Istanbul"
  },
  "geometry": {
    "type": "Point",
    "coordinates": [
      34.27359,
      36.58417
    ]
  }
}