{
  "type": "Feature",
  "properties": {
    "name": "Pınarbaşı",
    "country": "TR",
    "subdivision": "32",
    "timezone": "Europe/Istanbul"
  },
  "geometry": {
    "type": "Point",
    "coordinates": [
      34.3627,
      36.7034
    ]
  }
}