{
  "type": "Feature",
  "properties": {
    "name": "Abram",
    "country": "GB",
    "subdivision": "ENG",
    "timezone": "Europe/London"
  },
  "geometry": {
    "type": "Point",
    "coordinates": [
      -2.59266,
      53.50855
    ]
  }
}