{
  "type": "Feature",
  "properties": {
    "name": "Accrington",
    "country": "GB",
    "subdivision": "ENG",
    "timezone": "Europe/London"
  },
  "geometry": {
    "type": "Point",
    "coordinates": [
      -2.35863,
      53.75379
    ]
  }
}