{
  "type": "Feature",
  "properties": {
    "name": "Addingham",
    "country": "GB",
    "subdivision": "ENG",
    "timezone": "Europe/London"
  },
  "geometry": {
    "type": "Point",
    "coordinates": [
      -1.88424,
      53.94452
    ]
  }
}