{
  "type": "Feature",
  "properties": {
    "name": "Addlestone",
    "country": "GB",
    "subdivision": "ENG",
    "timezone": "Europe/London"
  },
  "geometry": {
    "type": "Point",
    "coordinates": [
      -0.49353,
      51.37135
    ]
  }
}