{
  "type": "Feature",
  "properties": {
    "name": "Albrighton",
    "country": "GB",
    "subdivision": "ENG",
    "timezone": "Europe/London"
  },
  "geometry": {
    "type": "Point",
    "coordinates": [
      -2.27966,
      52.6364
    ]
  }
}