{
  "type": "Feature",
  "properties": {
    "name": "Allhallows",
    "country": "GB",
    "subdivision": "ENG",
    "timezone": "Europe/London"
  },
  "geometry": {
    "type": "Point",
    "coordinates": [
      0.63686,
      51.46866
    ]
  }
}