{
  "type": "Feature",
  "properties": {
    "name": "Alton",
    "country": "GB",
    "subdivision": "ENG",
    "timezone": "Europe/London"
  },
  "geometry": {
    "type": "Point",
    "coordinates": [
      -0.97469,
      51.14931
    ]
  }
}