{
  "type": "Feature",
  "properties": {
    "name": "Alveston",
    "country": "GB",
    "subdivision": "ENG",
    "timezone": "Europe/London"
  },
  "geometry": {
    "type": "Point",
    "coordinates": [
      -2.53139,
      51.58806
    ]
  }
}