{
  "type": "Feature",
  "properties": {
    "name": "Amersham on the Hill",
    "country": "GB",
    "subdivision": "ENG",
    "timezone": "Europe/London"
  },
  "geometry": {
    "type": "Point",
    "coordinates": [
      -0.60742,
      51.67468
    ]
  }
}