{
  "type": "Feature",
  "properties": {
    "name": "Arlesey",
    "country": "GB",
    "subdivision": "ENG",
    "timezone": "Europe/London"
  },
  "geometry": {
    "type": "Point",
    "coordinates": [
      -0.26565,
      52.00713
    ]
  }
}