{
  "type": "Feature",
  "properties": {
    "name": "Ascot",
    "country": "GB",
    "subdivision": "ENG",
    "timezone": "Europe/London"
  },
  "geometry": {
    "type": "Point",
    "coordinates": [
      -0.6748,
      51.41082
    ]
  }
}