{
  "type": "Feature",
  "properties": {
    "name": "Attleborough",
    "country": "GB",
    "subdivision": "ENG",
    "timezone": "Europe/London"
  },
  "geometry": {
    "type": "Point",
    "coordinates": [
      1.01572,
      52.51779
    ]
  }
}