{
  "type": "Feature",
  "properties": {
    "name": "Atworth",
    "country": "GB",
    "subdivision": "ENG",
    "timezone": "Europe/London"
  },
  "geometry": {
    "type": "Point",
    "coordinates": [
      -2.19297,
      51.39234
    ]
  }
}