{
  "type": "Feature",
  "properties": {
    "name": "Aveley",
    "country": "GB",
    "subdivision": "ENG",
    "timezone": "Europe/London"
  },
  "geometry": {
    "type": "Point",
    "coordinates": [
      0.25174,
      51.49987
    ]
  }
}