{
  "type": "Feature",
  "properties": {
    "name": "Avening",
    "country": "GB",
    "subdivision": "ENG",
    "timezone": "Europe/London"
  },
  "geometry": {
    "type": "Point",
    "coordinates": [
      -2.16903,
      51.6801
    ]
  }
}