{
  "type": "Feature",
  "properties": {
    "name": "Bacup",
    "country": "GB",
    "subdivision": "ENG",
    "timezone": "Europe/London"
  },
  "geometry": {
    "type": "Point",
    "coordinates": [
      -2.2007,
      53.70336
    ]
  }
}