{
  "type": "Feature",
  "properties": {
    "name": "Banwell",
    "country": "GB",
    "subdivision": "ENG",
    "timezone": "Europe/London"
  },
  "geometry": {
    "type": "Point",
    "coordinates": [
      -2.86914,
      51.32894
    ]
  }
}