{
  "type": "Feature",
  "properties": {
    "name": "Barrowby",
    "country": "GB",
    "subdivision": "ENG",
    "timezone": "Europe/London"
  },
  "geometry": {
    "type": "Point",
    "coordinates": [
      -0.69094,
      52.91636
    ]
  }
}