{
  "type": "Feature",
  "properties": {
    "name": "Barrow in Furness",
    "country": "GB",
    "subdivision": "ENG",
    "timezone": "Europe/London"
  },
  "geometry": {
    "type": "Point",
    "coordinates": [
      -3.22758,
      54.11094
    ]
  }
}