{
  "type": "Feature",
  "properties": {
    "name": "Barton under Needwood",
    "country": "GB",
    "subdivision": "ENG",
    "timezone": "Europe/London"
  },
  "geometry": {
    "type": "Point",
    "coordinates": [
      -1.724,
      52.76268
    ]
  }
}