{
  "type": "Feature",
  "properties": {
    "name": "Basildon",
    "country": "GB",
    "subdivision": "ENG",
    "timezone": "Europe/London"
  },
  "geometry": {
    "type": "Point",
    "coordinates": [
      0.45782,
      51.56844
    ]
  }
}