{
  "type": "Feature",
  "properties": {
    "name": "Bembridge",
    "country": "GB",
    "subdivision": "ENG",
    "timezone": "Europe/London"
  },
  "geometry": {
    "type": "Point",
    "coordinates": [
      -1.08275,
      50.68634
    ]
  }
}