{
  "type": "Feature",
  "properties": {
    "name": "Benson",
    "country": "GB",
    "subdivision": "ENG",
    "timezone": "Europe/London"
  },
  "geometry": {
    "type": "Point",
    "coordinates": [
      -1.10979,
      51.62073
    ]
  }
}