{
  "type": "Feature",
  "properties": {
    "name": "Bexhill-on-Sea",
    "country": "GB",
    "subdivision": "ENG",
    "timezone": "Europe/London"
  },
  "geometry": {
    "type": "Point",
    "coordinates": [
      0.47095,
      50.85023
    ]
  }
}