{
  "type": "Feature",
  "properties": {
    "name": "Bilsthorpe",
    "country": "GB",
    "subdivision": "ENG",
    "timezone": "Europe/London"
  },
  "geometry": {
    "type": "Point",
    "coordinates": [
      -1.03392,
      53.14024
    ]
  }
}