{
  "type": "Feature",
  "properties": {
    "name": "Birchington-on-Sea",
    "country": "GB",
    "subdivision": "ENG",
    "timezone": "Europe/London"
  },
  "geometry": {
    "type": "Point",
    "coordinates": [
      1.3048,
      51.37575
    ]
  }
}