{
  "type": "Feature",
  "properties": {
    "name": "Blackmoorfoot",
    "country": "GB",
    "subdivision": "ENG",
    "timezone": "Europe/London"
  },
  "geometry": {
    "type": "Point",
    "coordinates": [
      -1.85588,
      53.61423
    ]
  }
}