{
  "type": "Feature",
  "properties": {
    "name": "Blacon",
    "country": "GB",
    "subdivision": "ENG",
    "timezone": "Europe/London"
  },
  "geometry": {
    "type": "Point",
    "coordinates": [
      -2.9253,
      53.20832
    ]
  }
}