{
  "type": "Feature",
  "properties": {
    "name": "Blindley Heath",
    "country": "GB",
    "subdivision": "ENG",
    "timezone": "Europe/London"
  },
  "geometry": {
    "type": "Point",
    "coordinates": [
      -0.05116,
      51.19344
    ]
  }
}