{
  "type": "Feature",
  "properties": {
    "name": "Blisworth",
    "country": "GB",
    "subdivision": "ENG",
    "timezone": "Europe/London"
  },
  "geometry": {
    "type": "Point",
    "coordinates": [
      -0.94131,
      52.17498
    ]
  }
}