{
  "type": "Feature",
  "properties": {
    "name": "Blockley",
    "country": "GB",
    "subdivision": "ENG",
    "timezone": "Europe/London"
  },
  "geometry": {
    "type": "Point",
    "coordinates": [
      -1.76268,
      52.0122
    ]
  }
}