{
  "type": "Feature",
  "properties": {
    "name": "Bluntisham",
    "country": "GB",
    "subdivision": "ENG",
    "timezone": "Europe/London"
  },
  "geometry": {
    "type": "Point",
    "coordinates": [
      0.00854,
      52.35479
    ]
  }
}