{
  "type": "Feature",
  "properties": {
    "name": "Blyth",
    "country": "GB",
    "subdivision": "ENG",
    "timezone": "Europe/London"
  },
  "geometry": {
    "type": "Point",
    "coordinates": [
      -1.50856,
      55.12708
    ]
  }
}