{
  "type": "Feature",
  "properties": {
    "name": "Bollington",
    "country": "GB",
    "subdivision": "ENG",
    "timezone": "Europe/London"
  },
  "geometry": {
    "type": "Point",
    "coordinates": [
      -2.10963,
      53.29446
    ]
  }
}