{
  "type": "Feature",
  "properties": {
    "name": "Bowdon",
    "country": "GB",
    "subdivision": "ENG",
    "timezone": "Europe/London"
  },
  "geometry": {
    "type": "Point",
    "coordinates": [
      -2.36532,
      53.37644
    ]
  }
}