{
  "type": "Feature",
  "properties": {
    "name": "Braintree",
    "country": "GB",
    "subdivision": "ENG",
    "timezone": "Europe/London"
  },
  "geometry": {
    "type": "Point",
    "coordinates": [
      0.55292,
      51.87819
    ]
  }
}