{
  "type": "Feature",
  "properties": {
    "name": "Brampton",
    "country": "GB",
    "subdivision": "ENG",
    "timezone": "Europe/London"
  },
  "geometry": {
    "type": "Point",
    "coordinates": [
      -2.73333,
      54.95
    ]
  }
}