{
  "type": "Feature",
  "properties": {
    "name": "Branston",
    "country": "GB",
    "subdivision": "ENG",
    "timezone": "Europe/London"
  },
  "geometry": {
    "type": "Point",
    "coordinates": [
      -0.47482,
      53.19544
    ]
  }
}