{
  "type": "Feature",
  "properties": {
    "name": "Bratton",
    "country": "GB",
    "subdivision": "ENG",
    "timezone": "Europe/London"
  },
  "geometry": {
    "type": "Point",
    "coordinates": [
      -2.12444,
      51.27056
    ]
  }
}