{
  "type": "Feature",
  "properties": {
    "name": "Bream",
    "country": "GB",
    "subdivision": "ENG",
    "timezone": "Europe/London"
  },
  "geometry": {
    "type": "Point",
    "coordinates": [
      -2.57747,
      51.74822
    ]
  }
}