{
  "type": "Feature",
  "properties": {
    "name": "Brentford",
    "country": "GB",
    "subdivision": "ENG",
    "timezone": "Europe/London"
  },
  "geometry": {
    "type": "Point",
    "coordinates": [
      -0.3083,
      51.48619
    ]
  }
}