{
  "type": "Feature",
  "properties": {
    "name": "Bridgnorth",
    "country": "GB",
    "subdivision": "ENG",
    "timezone": "Europe/London"
  },
  "geometry": {
    "type": "Point",
    "coordinates": [
      -2.42033,
      52.53661
    ]
  }
}