{
  "type": "Feature",
  "properties": {
    "name": "Brierley Hill",
    "country": "GB",
    "subdivision": "ENG",
    "timezone": "Europe/London"
  },
  "geometry": {
    "type": "Point",
    "coordinates": [
      -2.12139,
      52.48173
    ]
  }
}