{
  "type": "Feature",
  "properties": {
    "name": "Brill",
    "country": "GB",
    "subdivision": "ENG",
    "timezone": "Europe/London"
  },
  "geometry": {
    "type": "Point",
    "coordinates": [
      -1.05,
      51.81667
    ]
  }
}