{
  "type": "Feature",
  "properties": {
    "name": "Brotton",
    "country": "GB",
    "subdivision": "ENG",
    "timezone": "Europe/London"
  },
  "geometry": {
    "type": "Point",
    "coordinates": [
      -0.93929,
      54.56661
    ]
  }
}