{
  "type": "Feature",
  "properties": {
    "name": "Broughton Astley",
    "country": "GB",
    "subdivision": "ENG",
    "timezone": "Europe/London"
  },
  "geometry": {
    "type": "Point",
    "coordinates": [
      -1.21768,
      52.52787
    ]
  }
}