{
  "type": "Feature",
  "properties": {
    "name": "Broxbourne",
    "country": "GB",
    "subdivision": "ENG",
    "timezone": "Europe/London"
  },
  "geometry": {
    "type": "Point",
    "coordinates": [
      -0.01923,
      51.74712
    ]
  }
}