{
  "type": "Feature",
  "properties": {
    "name": "Burley",
    "country": "GB",
    "subdivision": "ENG",
    "timezone": "Europe/London"
  },
  "geometry": {
    "type": "Point",
    "coordinates": [
      -1.69977,
      50.828
    ]
  }
}