{
  "type": "Feature",
  "properties": {
    "name": "Burnham-on-Sea",
    "country": "GB",
    "subdivision": "ENG",
    "timezone": "Europe/London"
  },
  "geometry": {
    "type": "Point",
    "coordinates": [
      -2.9978,
      51.23862
    ]
  }
}