{
  "type": "Feature",
  "properties": {
    "name": "Butterwick",
    "country": "GB",
    "subdivision": "ENG",
    "timezone": "Europe/London"
  },
  "geometry": {
    "type": "Point",
    "coordinates": [
      0.06667,
      52.98333
    ]
  }
}