{
  "type": "Feature",
  "properties": {
    "name": "Canewdon",
    "country": "GB",
    "subdivision": "ENG",
    "timezone": "Europe/London"
  },
  "geometry": {
    "type": "Point",
    "coordinates": [
      0.74458,
      51.61759
    ]
  }
}