{
  "type": "Feature",
  "properties": {
    "name": "Canford Heath",
    "country": "GB",
    "subdivision": "ENG",
    "timezone": "Europe/London"
  },
  "geometry": {
    "type": "Point",
    "coordinates": [
      -1.96862,
      50.751
    ]
  }
}