{
  "type": "Feature",
  "properties": {
    "name": "Castle Vale",
    "country": "GB",
    "subdivision": "ENG",
    "timezone": "Europe/London"
  },
  "geometry": {
    "type": "Point",
    "coordinates": [
      -1.79683,
      52.51879
    ]
  }
}