{
  "type": "Feature",
  "properties": {
    "name": "Castle Hedingham",
    "country": "GB",
    "subdivision": "ENG",
    "timezone": "Europe/London"
  },
  "geometry": {
    "type": "Point",
    "coordinates": [
      0.59882,
      51.99015
    ]
  }
}