{
  "type": "Feature",
  "properties": {
    "name": "Catcliffe",
    "country": "GB",
    "subdivision": "ENG",
    "timezone": "Europe/London"
  },
  "geometry": {
    "type": "Point",
    "coordinates": [
      -1.36207,
      53.39316
    ]
  }
}