{
  "type": "Feature",
  "properties": {
    "name": "Catterall",
    "country": "GB",
    "subdivision": "ENG",
    "timezone": "Europe/London"
  },
  "geometry": {
    "type": "Point",
    "coordinates": [
      -2.76478,
      53.87965
    ]
  }
}