{
  "type": "Feature",
  "properties": {
    "name": "Chapeltown",
    "country": "GB",
    "subdivision": "ENG",
    "timezone": "Europe/London"
  },
  "geometry": {
    "type": "Point",
    "coordinates": [
      -1.47217,
      53.46506
    ]
  }
}