{
  "type": "Feature",
  "properties": {
    "name": "Chapel Allerton",
    "country": "GB",
    "subdivision": "ENG",
    "timezone": "Europe/London"
  },
  "geometry": {
    "type": "Point",
    "coordinates": [
      -1.53834,
      53.82901
    ]
  }
}