{
  "type": "Feature",
  "properties": {
    "name": "Chard",
    "country": "GB",
    "subdivision": "ENG",
    "timezone": "Europe/London"
  },
  "geometry": {
    "type": "Point",
    "coordinates": [
      -2.96597,
      50.8727
    ]
  }
}