{
  "type": "Feature",
  "properties": {
    "name": "Charlbury",
    "country": "GB",
    "subdivision": "ENG",
    "timezone": "Europe/London"
  },
  "geometry": {
    "type": "Point",
    "coordinates": [
      -1.48247,
      51.8727
    ]
  }
}