{
  "type": "Feature",
  "properties": {
    "name": "Chelmsford",
    "country": "GB",
    "subdivision": "ENG",
    "timezone": "Europe/London"
  },
  "geometry": {
    "type": "Point",
    "coordinates": [
      0.46958,
      51.73575
    ]
  }
}