{
  "type": "Feature",
  "properties": {
    "name": "Chelmsley Wood",
    "country": "GB",
    "subdivision": "ENG",
    "timezone": "Europe/London"
  },
  "geometry": {
    "type": "Point",
    "coordinates": [
      -1.73813,
      52.4781
    ]
  }
}