{
  "type": "Feature",
  "properties": {
    "name": "Chesterfield",
    "country": "GB",
    "subdivision": "ENG",
    "timezone": "Europe/London"
  },
  "geometry": {
    "type": "Point",
    "coordinates": [
      -1.41667,
      53.25
    ]
  }
}