{
  "type": "Feature",
  "properties": {
    "name": "Chickerell",
    "country": "GB",
    "subdivision": "ENG",
    "timezone": "Europe/London"
  },
  "geometry": {
    "type": "Point",
    "coordinates": [
      -2.5028,
      50.62429
    ]
  }
}