{
  "type": "Feature",
  "properties": {
    "name": "Chinnor",
    "country": "GB",
    "subdivision": "ENG",
    "timezone": "Europe/London"
  },
  "geometry": {
    "type": "Point",
    "coordinates": [
      -0.91161,
      51.70177
    ]
  }
}