{
  "type": "Feature",
  "properties": {
    "name": "Chipping Campden",
    "country": "GB",
    "subdivision": "ENG",
    "timezone": "Europe/London"
  },
  "geometry": {
    "type": "Point",
    "coordinates": [
      -1.7767,
      52.04964
    ]
  }
}