{
  "type": "Feature",
  "properties": {
    "name": "Chorlton cum Hardy",
    "country": "GB",
    "subdivision": "ENG",
    "timezone": "Europe/London"
  },
  "geometry": {
    "type": "Point",
    "coordinates": [
      -2.2631,
      53.43505
    ]
  }
}