{
  "type": "Feature",
  "properties": {
    "name": "Churchdown",
    "country": "GB",
    "subdivision": "ENG",
    "timezone": "Europe/London"
  },
  "geometry": {
    "type": "Point",
    "coordinates": [
      -2.17087,
      51.87739
    ]
  }
}