{
  "type": "Feature",
  "properties": {
    "name": "Clarborough",
    "country": "GB",
    "subdivision": "ENG",
    "timezone": "Europe/London"
  },
  "geometry": {
    "type": "Point",
    "coordinates": [
      -0.90382,
      53.34549
    ]
  }
}