{
  "type": "Feature",
  "properties": {
    "name": "Clerkenwell",
    "country": "GB",
    "subdivision": "ENG",
    "timezone": "Europe/London"
  },
  "geometry": {
    "type": "Point",
    "coordinates": [
      -0.11022,
      51.52438
    ]
  }
}