{
  "type": "Feature",
  "properties": {
    "name": "Cliffe",
    "country": "GB",
    "subdivision": "ENG",
    "timezone": "Europe/London"
  },
  "geometry": {
    "type": "Point",
    "coordinates": [
      0.49833,
      51.46224
    ]
  }
}