{
  "type": "Feature",
  "properties": {
    "name": "Clowne",
    "country": "GB",
    "subdivision": "ENG",
    "timezone": "Europe/London"
  },
  "geometry": {
    "type": "Point",
    "coordinates": [
      -1.26406,
      53.27449
    ]
  }
}