{
  "type": "Feature",
  "properties": {
    "name": "Coalville",
    "country": "GB",
    "subdivision": "ENG",
    "timezone": "Europe/London"
  },
  "geometry": {
    "type": "Point",
    "coordinates": [
      -1.3702,
      52.72247
    ]
  }
}