{
  "type": "Feature",
  "properties": {
    "name": "Cockermouth",
    "country": "GB",
    "subdivision": "ENG",
    "timezone": "Europe/London"
  },
  "geometry": {
    "type": "Point",
    "coordinates": [
      -3.36086,
      54.66209
    ]
  }
}