{
  "type": "Feature",
  "properties": {
    "name": "Collier Row",
    "country": "GB",
    "subdivision": "ENG",
    "timezone": "Europe/London"
  },
  "geometry": {
    "type": "Point",
    "coordinates": [
      0.166,
      51.59893
    ]
  }
}