{
  "type": "Feature",
  "properties": {
    "name": "Colyton",
    "country": "GB",
    "subdivision": "ENG",
    "timezone": "Europe/London"
  },
  "geometry": {
    "type": "Point",
    "coordinates": [
      -3.07021,
      50.74006
    ]
  }
}