{
  "type": "Feature",
  "properties": {
    "name": "Congleton",
    "country": "GB",
    "subdivision": "ENG",
    "timezone": "Europe/London"
  },
  "geometry": {
    "type": "Point",
    "coordinates": [
      -2.21253,
      53.16314
    ]
  }
}