{
  "type": "Feature",
  "properties": {
    "name": "Corfe Castle",
    "country": "GB",
    "subdivision": "ENG",
    "timezone": "Europe/London"
  },
  "geometry": {
    "type": "Point",
    "coordinates": [
      -2.05672,
      50.63947
    ]
  }
}