{
  "type": "Feature",
  "properties": {
    "name": "Cosby",
    "country": "GB",
    "subdivision": "ENG",
    "timezone": "Europe/London"
  },
  "geometry": {
    "type": "Point",
    "coordinates": [
      -1.19395,
      52.55127
    ]
  }
}