{
  "type": "Feature",
  "properties": {
    "name": "Costessey",
    "country": "GB",
    "subdivision": "ENG",
    "timezone": "Europe/London"
  },
  "geometry": {
    "type": "Point",
    "coordinates": [
      1.2097,
      52.65914
    ]
  }
}