{
  "type": "Feature",
  "properties": {
    "name": "Cotgrave",
    "country": "GB",
    "subdivision": "ENG",
    "timezone": "Europe/London"
  },
  "geometry": {
    "type": "Point",
    "coordinates": [
      -1.03752,
      52.90859
    ]
  }
}