{
  "type": "Feature",
  "properties": {
    "name": "Coundon",
    "country": "GB",
    "subdivision": "ENG",
    "timezone": "Europe/London"
  },
  "geometry": {
    "type": "Point",
    "coordinates": [
      -1.62688,
      54.6628
    ]
  }
}