{
  "type": "Feature",
  "properties": {
    "name": "Cowes",
    "country": "GB",
    "subdivision": "ENG",
    "timezone": "Europe/London"
  },
  "geometry": {
    "type": "Point",
    "coordinates": [
      -1.29772,
      50.76306
    ]
  }
}