{
  "type": "Feature",
  "properties": {
    "name": "Cranbrook",
    "country": "GB",
    "subdivision": "ENG",
    "timezone": "Europe/London"
  },
  "geometry": {
    "type": "Point",
    "coordinates": [
      0.53567,
      51.09662
    ]
  }
}