{
  "type": "Feature",
  "properties": {
    "name": "Cropwell Bishop",
    "country": "GB",
    "subdivision": "ENG",
    "timezone": "Europe/London"
  },
  "geometry": {
    "type": "Point",
    "coordinates": [
      -0.98482,
      52.9148
    ]
  }
}