{
  "type": "Feature",
  "properties": {
    "name": "Darenth",
    "country": "GB",
    "subdivision": "ENG",
    "timezone": "Europe/London"
  },
  "geometry": {
    "type": "Point",
    "coordinates": [
      0.25784,
      51.42137
    ]
  }
}