{
  "type": "Feature",
  "properties": {
    "name": "Darlington",
    "country": "GB",
    "subdivision": "ENG",
    "timezone": "Europe/London"
  },
  "geometry": {
    "type": "Point",
    "coordinates": [
      -1.55039,
      54.52429
    ]
  }
}