{
  "type": "Feature",
  "properties": {
    "name": "Debenham",
    "country": "GB",
    "subdivision": "ENG",
    "timezone": "Europe/London"
  },
  "geometry": {
    "type": "Point",
    "coordinates": [
      1.18172,
      52.22422
    ]
  }
}