{
  "type": "Feature",
  "properties": {
    "name": "Dickleburgh",
    "country": "GB",
    "subdivision": "ENG",
    "timezone": "Europe/London"
  },
  "geometry": {
    "type": "Point",
    "coordinates": [
      1.18498,
      52.3965
    ]
  }
}