{
  "type": "Feature",
  "properties": {
    "name": "Didcot",
    "country": "GB",
    "subdivision": "ENG",
    "timezone": "Europe/London"
  },
  "geometry": {
    "type": "Point",
    "coordinates": [
      -1.24214,
      51.60928
    ]
  }
}