{
  "type": "Feature",
  "properties": {
    "name": "Drybrook",
    "country": "GB",
    "subdivision": "ENG",
    "timezone": "Europe/London"
  },
  "geometry": {
    "type": "Point",
    "coordinates": [
      -2.51681,
      51.8555
    ]
  }
}