{
  "type": "Feature",
  "properties": {
    "name": "Dunswell",
    "country": "GB",
    "subdivision": "ENG",
    "timezone": "Europe/London"
  },
  "geometry": {
    "type": "Point",
    "coordinates": [
      -0.37139,
      53.80106
    ]
  }
}