{
  "type": "Feature",
  "properties": {
    "name": "Dymchurch",
    "country": "GB",
    "subdivision": "ENG",
    "timezone": "Europe/London"
  },
  "geometry": {
    "type": "Point",
    "coordinates": [
      0.99392,
      51.02544
    ]
  }
}