{
  "type": "Feature",
  "properties": {
    "name": "Easingwold",
    "country": "GB",
    "subdivision": "ENG",
    "timezone": "Europe/London"
  },
  "geometry": {
    "type": "Point",
    "coordinates": [
      -1.1939,
      54.1201
    ]
  }
}