{
  "type": "Feature",
  "properties": {
    "name": "Easington",
    "country": "GB",
    "subdivision": "ENG",
    "timezone": "Europe/London"
  },
  "geometry": {
    "type": "Point",
    "coordinates": [
      -1.35917,
      54.78528
    ]
  }
}