{
  "type": "Feature",
  "properties": {
    "name": "East Tilbury",
    "country": "GB",
    "subdivision": "ENG",
    "timezone": "Europe/London"
  },
  "geometry": {
    "type": "Point",
    "coordinates": [
      0.41714,
      51.48053
    ]
  }
}