{
  "type": "Feature",
  "properties": {
    "name": "East Leake",
    "country": "GB",
    "subdivision": "ENG",
    "timezone": "Europe/London"
  },
  "geometry": {
    "type": "Point",
    "coordinates": [
      -1.18103,
      52.83015
    ]
  }
}