{
  "type": "Feature",
  "properties": {
    "name": "East Keswick",
    "country": "GB",
    "subdivision": "ENG",
    "timezone": "Europe/London"
  },
  "geometry": {
    "type": "Point",
    "coordinates": [
      -1.45221,
      53.8943
    ]
  }
}