{
  "type": "Feature",
  "properties": {
    "name": "East Molesey",
    "country": "GB",
    "subdivision": "ENG",
    "timezone": "Europe/London"
  },
  "geometry": {
    "type": "Point",
    "coordinates": [
      -0.34916,
      51.39872
    ]
  }
}