{
  "type": "Feature",
  "properties": {
    "name": "Edwinstowe",
    "country": "GB",
    "subdivision": "ENG",
    "timezone": "Europe/London"
  },
  "geometry": {
    "type": "Point",
    "coordinates": [
      -1.06439,
      53.19454
    ]
  }
}