{
  "type": "Feature",
  "properties": {
    "name": "Exeter",
    "country": "GB",
    "subdivision": "ENG",
    "timezone": "Europe/London"
  },
  "geometry": {
    "type": "Point",
    "coordinates": [
      -3.52751,
      50.7236
    ]
  }
}