{
  "type": "Feature",
  "properties": {
    "name": "Exmouth",
    "country": "GB",
    "subdivision": "ENG",
    "timezone": "Europe/London"
  },
  "geometry": {
    "type": "Point",
    "coordinates": [
      -3.40233,
      50.61723
    ]
  }
}