{
  "type": "Feature",
  "properties": {
    "name": "Eynsham",
    "country": "GB",
    "subdivision": "ENG",
    "timezone": "Europe/London"
  },
  "geometry": {
    "type": "Point",
    "coordinates": [
      -1.37454,
      51.78077
    ]
  }
}