{
  "type": "Feature",
  "properties": {
    "name": "Failsworth",
    "country": "GB",
    "subdivision": "ENG",
    "timezone": "Europe/London"
  },
  "geometry": {
    "type": "Point",
    "coordinates": [
      -2.16568,
      53.50484
    ]
  }
}