{
  "type": "Feature",
  "properties": {
    "name": "Fairlight",
    "country": "GB",
    "subdivision": "ENG",
    "timezone": "Europe/London"
  },
  "geometry": {
    "type": "Point",
    "coordinates": [
      0.65669,
      50.87802
    ]
  }
}