{
  "type": "Feature",
  "properties": {
    "name": "Fallowfield",
    "country": "GB",
    "subdivision": "ENG",
    "timezone": "Europe/London"
  },
  "geometry": {
    "type": "Point",
    "coordinates": [
      -2.21572,
      53.43981
    ]
  }
}