{
  "type": "Feature",
  "properties": {
    "name": "Farnham Royal",
    "country": "GB",
    "subdivision": "ENG",
    "timezone": "Europe/London"
  },
  "geometry": {
    "type": "Point",
    "coordinates": [
      -0.61584,
      51.54208
    ]
  }
}