{
  "type": "Feature",
  "properties": {
    "name": "Farnborough",
    "country": "GB",
    "subdivision": "ENG",
    "timezone": "Europe/London"
  },
  "geometry": {
    "type": "Point",
    "coordinates": [
      -1.36926,
      52.14289
    ]
  }
}