{
  "type": "Feature",
  "properties": {
    "name": "Felling",
    "country": "GB",
    "subdivision": "ENG",
    "timezone": "Europe/London"
  },
  "geometry": {
    "type": "Point",
    "coordinates": [
      -1.57152,
      54.95297
    ]
  }
}