{
  "type": "Feature",
  "properties": {
    "name": "Felton",
    "country": "GB",
    "subdivision": "ENG",
    "timezone": "Europe/London"
  },
  "geometry": {
    "type": "Point",
    "coordinates": [
      -1.71143,
      55.29768
    ]
  }
}