{
  "type": "Feature",
  "properties": {
    "name": "Fernhurst",
    "country": "GB",
    "subdivision": "ENG",
    "timezone": "Europe/London"
  },
  "geometry": {
    "type": "Point",
    "coordinates": [
      -0.71789,
      51.04873
    ]
  }
}