{
  "type": "Feature",
  "properties": {
    "name": "Fernhill Heath",
    "country": "GB",
    "subdivision": "ENG",
    "timezone": "Europe/London"
  },
  "geometry": {
    "type": "Point",
    "coordinates": [
      -2.19659,
      52.23002
    ]
  }
}