{
  "type": "Feature",
  "properties": {
    "name": "Fishtoft",
    "country": "GB",
    "subdivision": "ENG",
    "timezone": "Europe/London"
  },
  "geometry": {
    "type": "Point",
    "coordinates": [
      0.02702,
      52.96095
    ]
  }
}