{
  "type": "Feature",
  "properties": {
    "name": "Fitzwilliam",
    "country": "GB",
    "subdivision": "ENG",
    "timezone": "Europe/London"
  },
  "geometry": {
    "type": "Point",
    "coordinates": [
      -1.3769,
      53.63288
    ]
  }
}