{
  "type": "Feature",
  "properties": {
    "name": "Fleetwood",
    "country": "GB",
    "subdivision": "ENG",
    "timezone": "Europe/London"
  },
  "geometry": {
    "type": "Point",
    "coordinates": [
      -3.01085,
      53.92527
    ]
  }
}