{
  "type": "Feature",
  "properties": {
    "name": "Flimwell",
    "country": "GB",
    "subdivision": "ENG",
    "timezone": "Europe/London"
  },
  "geometry": {
    "type": "Point",
    "coordinates": [
      0.44531,
      51.05502
    ]
  }
}