{
  "type": "Feature",
  "properties": {
    "name": "Friston",
    "country": "GB",
    "subdivision": "ENG",
    "timezone": "Europe/London"
  },
  "geometry": {
    "type": "Point",
    "coordinates": [
      0.1993,
      50.76402
    ]
  }
}