{
  "type": "Feature",
  "properties": {
    "name": "Frodsham",
    "country": "GB",
    "subdivision": "ENG",
    "timezone": "Europe/London"
  },
  "geometry": {
    "type": "Point",
    "coordinates": [
      -2.72745,
      53.29485
    ]
  }
}