{
  "type": "Feature",
  "properties": {
    "name": "Glenfield",
    "country": "GB",
    "subdivision": "ENG",
    "timezone": "Europe/London"
  },
  "geometry": {
    "type": "Point",
    "coordinates": [
      -1.19493,
      52.6466
    ]
  }
}