{
  "type": "Feature",
  "properties": {
    "name": "Gnosall",
    "country": "GB",
    "subdivision": "ENG",
    "timezone": "Europe/London"
  },
  "geometry": {
    "type": "Point",
    "coordinates": [
      -2.25483,
      52.78558
    ]
  }
}