{
  "type": "Feature",
  "properties": {
    "name": "Golborne",
    "country": "GB",
    "subdivision": "ENG",
    "timezone": "Europe/London"
  },
  "geometry": {
    "type": "Point",
    "coordinates": [
      -2.59651,
      53.47693
    ]
  }
}