{
  "type": "Feature",
  "properties": {
    "name": "Gossops Green",
    "country": "GB",
    "subdivision": "ENG",
    "timezone": "Europe/London"
  },
  "geometry": {
    "type": "Point",
    "coordinates": [
      -0.21728,
      51.11105
    ]
  }
}