{
  "type": "Feature",
  "properties": {
    "name": "Great Amwell",
    "country": "GB",
    "subdivision": "ENG",
    "timezone": "Europe/London"
  },
  "geometry": {
    "type": "Point",
    "coordinates": [
      -0.01669,
      51.79014
    ]
  }
}