{
  "type": "Feature",
  "properties": {
    "name": "Great Bedwyn",
    "country": "GB",
    "subdivision": "ENG",
    "timezone": "Europe/London"
  },
  "geometry": {
    "type": "Point",
    "coordinates": [
      -1.60151,
      51.3795
    ]
  }
}