{
  "type": "Feature",
  "properties": {
    "name": "Great Marton",
    "country": "GB",
    "subdivision": "ENG",
    "timezone": "Europe/London"
  },
  "geometry": {
    "type": "Point",
    "coordinates": [
      -3.02261,
      53.81185
    ]
  }
}