{
  "type": "Feature",
  "properties": {
    "name": "Great Horwood",
    "country": "GB",
    "subdivision": "ENG",
    "timezone": "Europe/London"
  },
  "geometry": {
    "type": "Point",
    "coordinates": [
      -0.88088,
      51.97351
    ]
  }
}