{
  "type": "Feature",
  "properties": {
    "name": "Great Bookham",
    "country": "GB",
    "subdivision": "ENG",
    "timezone": "Europe/London"
  },
  "geometry": {
    "type": "Point",
    "coordinates": [
      -0.37423,
      51.27916
    ]
  }
}