{
  "type": "Feature",
  "properties": {
    "name": "Greenhithe",
    "country": "GB",
    "subdivision": "ENG",
    "timezone": "Europe/London"
  },
  "geometry": {
    "type": "Point",
    "coordinates": [
      0.28539,
      51.45026
    ]
  }
}