{
  "type": "Feature",
  "properties": {
    "name": "Groombridge",
    "country": "GB",
    "subdivision": "ENG",
    "timezone": "Europe/London"
  },
  "geometry": {
    "type": "Point",
    "coordinates": [
      0.18295,
      51.11543
    ]
  }
}