{
  "type": "Feature",
  "properties": {
    "name": "Gunnislake",
    "country": "GB",
    "subdivision": "ENG",
    "timezone": "Europe/London"
  },
  "geometry": {
    "type": "Point",
    "coordinates": [
      -4.21333,
      50.52441
    ]
  }
}