{
  "type": "Feature",
  "properties": {
    "name": "Hagley",
    "country": "GB",
    "subdivision": "ENG",
    "timezone": "Europe/London"
  },
  "geometry": {
    "type": "Point",
    "coordinates": [
      -2.12819,
      52.4262
    ]
  }
}