{
  "type": "Feature",
  "properties": {
    "name": "Haltwhistle",
    "country": "GB",
    "subdivision": "ENG",
    "timezone": "Europe/London"
  },
  "geometry": {
    "type": "Point",
    "coordinates": [
      -2.45682,
      54.97101
    ]
  }
}