{
  "type": "Feature",
  "properties": {
    "name": "Hameldon Hill",
    "country": "GB",
    "subdivision": "ENG",
    "timezone": "Europe/London"
  },
  "geometry": {
    "type": "Point",
    "coordinates": [
      -2.2919,
      53.7557
    ]
  }
}