{
  "type": "Feature",
  "properties": {
    "name": "Harbury",
    "country": "GB",
    "subdivision": "ENG",
    "timezone": "Europe/London"
  },
  "geometry": {
    "type": "Point",
    "coordinates": [
      -1.45706,
      52.23537
    ]
  }
}