{
  "type": "Feature",
  "properties": {
    "name": "Harrow on the Hill",
    "country": "GB",
    "subdivision": "ENG",
    "timezone": "Europe/London"
  },
  "geometry": {
    "type": "Point",
    "coordinates": [
      -0.33371,
      51.57142
    ]
  }
}