{
  "type": "Feature",
  "properties": {
    "name": "Harthill",
    "country": "GB",
    "subdivision": "ENG",
    "timezone": "Europe/London"
  },
  "geometry": {
    "type": "Point",
    "coordinates": [
      -1.26667,
      53.31667
    ]
  }
}