{
  "type": "Feature",
  "properties": {
    "name": "Haworth",
    "country": "GB",
    "subdivision": "ENG",
    "timezone": "Europe/London"
  },
  "geometry": {
    "type": "Point",
    "coordinates": [
      -1.94827,
      53.82905
    ]
  }
}