{
  "type": "Feature",
  "properties": {
    "name": "Haydon Bridge",
    "country": "GB",
    "subdivision": "ENG",
    "timezone": "Europe/London"
  },
  "geometry": {
    "type": "Point",
    "coordinates": [
      -2.2468,
      54.97486
    ]
  }
}