{
  "type": "Feature",
  "properties": {
    "name": "Hazel Grove",
    "country": "GB",
    "subdivision": "ENG",
    "timezone": "Europe/London"
  },
  "geometry": {
    "type": "Point",
    "coordinates": [
      -2.11667,
      53.38333
    ]
  }
}