{
  "type": "Feature",
  "properties": {
    "name": "Hazlerigg",
    "country": "GB",
    "subdivision": "ENG",
    "timezone": "Europe/London"
  },
  "geometry": {
    "type": "Point",
    "coordinates": [
      -1.63912,
      55.04135
    ]
  }
}