{
  "type": "Feature",
  "properties": {
    "name": "Heage",
    "country": "GB",
    "subdivision": "ENG",
    "timezone": "Europe/London"
  },
  "geometry": {
    "type": "Point",
    "coordinates": [
      -1.44688,
      53.0505
    ]
  }
}