{
  "type": "Feature",
  "properties": {
    "name": "Heaton Chapel",
    "country": "GB",
    "subdivision": "ENG",
    "timezone": "Europe/London"
  },
  "geometry": {
    "type": "Point",
    "coordinates": [
      -2.17538,
      53.43015
    ]
  }
}