{
  "type": "Feature",
  "properties": {
    "name": "Heckmondwike",
    "country": "GB",
    "subdivision": "ENG",
    "timezone": "Europe/London"
  },
  "geometry": {
    "type": "Point",
    "coordinates": [
      -1.67747,
      53.70646
    ]
  }
}