{
  "type": "Feature",
  "properties": {
    "name": "Hedon",
    "country": "GB",
    "subdivision": "ENG",
    "timezone": "Europe/London"
  },
  "geometry": {
    "type": "Point",
    "coordinates": [
      -0.19655,
      53.73962
    ]
  }
}