{
  "type": "Feature",
  "properties": {
    "name": "Hetton-Le-Hole",
    "country": "GB",
    "subdivision": "ENG",
    "timezone": "Europe/London"
  },
  "geometry": {
    "type": "Point",
    "coordinates": [
      -1.45,
      54.81667
    ]
  }
}