{
  "type": "Feature",
  "properties": {
    "name": "Highworth",
    "country": "GB",
    "subdivision": "ENG",
    "timezone": "Europe/London"
  },
  "geometry": {
    "type": "Point",
    "coordinates": [
      -1.711,
      51.63051
    ]
  }
}