{
  "type": "Feature",
  "properties": {
    "name": "Hitchin",
    "country": "GB",
    "subdivision": "ENG",
    "timezone": "Europe/London"
  },
  "geometry": {
    "type": "Point",
    "coordinates": [
      -0.28496,
      51.94924
    ]
  }
}