{
  "type": "Feature",
  "properties": {
    "name": "Holbrook",
    "country": "GB",
    "subdivision": "ENG",
    "timezone": "Europe/London"
  },
  "geometry": {
    "type": "Point",
    "coordinates": [
      1.15854,
      51.9834
    ]
  }
}