{
  "type": "Feature",
  "properties": {
    "name": "Holmfirth",
    "country": "GB",
    "subdivision": "ENG",
    "timezone": "Europe/London"
  },
  "geometry": {
    "type": "Point",
    "coordinates": [
      -1.78777,
      53.56968
    ]
  }
}