{
  "type": "Feature",
  "properties": {
    "name": "Holmwood",
    "country": "GB",
    "subdivision": "ENG",
    "timezone": "Europe/London"
  },
  "geometry": {
    "type": "Point",
    "coordinates": [
      -0.32176,
      51.18049
    ]
  }
}