{
  "type": "Feature",
  "properties": {
    "name": "Holton le Clay",
    "country": "GB",
    "subdivision": "ENG",
    "timezone": "Europe/London"
  },
  "geometry": {
    "type": "Point",
    "coordinates": [
      -0.063,
      53.5052
    ]
  }
}