{
  "type": "Feature",
  "properties": {
    "name": "Horndon on the Hill",
    "country": "GB",
    "subdivision": "ENG",
    "timezone": "Europe/London"
  },
  "geometry": {
    "type": "Point",
    "coordinates": [
      0.40491,
      51.52358
    ]
  }
}