{
  "type": "Feature",
  "properties": {
    "name": "Horsford",
    "country": "GB",
    "subdivision": "ENG",
    "timezone": "Europe/London"
  },
  "geometry": {
    "type": "Point",
    "coordinates": [
      1.24015,
      52.70153
    ]
  }
}