{
  "type": "Feature",
  "properties": {
    "name": "Houghton on the Hill",
    "country": "GB",
    "subdivision": "ENG",
    "timezone": "Europe/London"
  },
  "geometry": {
    "type": "Point",
    "coordinates": [
      -0.99546,
      52.62663
    ]
  }
}