{
  "type": "Feature",
  "properties": {
    "name": "Houghton-Le-Spring",
    "country": "GB",
    "subdivision": "ENG",
    "timezone": "Europe/London"
  },
  "geometry": {
    "type": "Point",
    "coordinates": [
      -1.46427,
      54.84034
    ]
  }
}