{
  "type": "Feature",
  "properties": {
    "name": "Howden",
    "country": "GB",
    "subdivision": "ENG",
    "timezone": "Europe/London"
  },
  "geometry": {
    "type": "Point",
    "coordinates": [
      -0.86994,
      53.7463
    ]
  }
}