{
  "type": "Feature",
  "properties": {
    "name": "Huntley",
    "country": "GB",
    "subdivision": "ENG",
    "timezone": "Europe/London"
  },
  "geometry": {
    "type": "Point",
    "coordinates": [
      -2.40137,
      51.87172
    ]
  }
}