{
  "type": "Feature",
  "properties": {
    "name": "Husbands Bosworth",
    "country": "GB",
    "subdivision": "ENG",
    "timezone": "Europe/London"
  },
  "geometry": {
    "type": "Point",
    "coordinates": [
      -1.05557,
      52.45232
    ]
  }
}