{
  "type": "Feature",
  "properties": {
    "name": "Ilchester",
    "country": "GB",
    "subdivision": "ENG",
    "timezone": "Europe/London"
  },
  "geometry": {
    "type": "Point",
    "coordinates": [
      -2.67981,
      51.00587
    ]
  }
}