{
  "type": "Feature",
  "properties": {
    "name": "Kedington",
    "country": "GB",
    "subdivision": "ENG",
    "timezone": "Europe/London"
  },
  "geometry": {
    "type": "Point",
    "coordinates": [
      0.48675,
      52.09282
    ]
  }
}