{
  "type": "Feature",
  "properties": {
    "name": "Keresley",
    "country": "GB",
    "subdivision": "ENG",
    "timezone": "Europe/London"
  },
  "geometry": {
    "type": "Point",
    "coordinates": [
      -1.53319,
      52.45156
    ]
  }
}