{
  "type": "Feature",
  "properties": {
    "name": "Keswick",
    "country": "GB",
    "subdivision": "ENG",
    "timezone": "Europe/London"
  },
  "geometry": {
    "type": "Point",
    "coordinates": [
      -3.13256,
      54.59947
    ]
  }
}