{
  "type": "Feature",
  "properties": {
    "name": "Kilburn",
    "country": "GB",
    "subdivision": "ENG",
    "timezone": "Europe/London"
  },
  "geometry": {
    "type": "Point",
    "coordinates": [
      -1.43869,
      53.0058
    ]
  }
}