{
  "type": "Feature",
  "properties": {
    "name": "Kimpton",
    "country": "GB",
    "subdivision": "ENG",
    "timezone": "Europe/London"
  },
  "geometry": {
    "type": "Point",
    "coordinates": [
      -0.2998,
      51.85089
    ]
  }
}