{
  "type": "Feature",
  "properties": {
    "name": "Kingswood",
    "country": "GB",
    "subdivision": "ENG",
    "timezone": "Europe/London"
  },
  "geometry": {
    "type": "Point",
    "coordinates": [
      -2.36722,
      51.62583
    ]
  }
}