{
  "type": "Feature",
  "properties": {
    "name": "King's Lynn",
    "country": "GB",
    "subdivision": "ENG",
    "timezone": "Europe/London"
  },
  "geometry": {
    "type": "Point",
    "coordinates": [
      0.39516,
      52.75172
    ]
  }
}