{
  "type": "Feature",
  "properties": {
    "name": "Kirby Muxloe",
    "country": "GB",
    "subdivision": "ENG",
    "timezone": "Europe/London"
  },
  "geometry": {
    "type": "Point",
    "coordinates": [
      -1.22755,
      52.63025
    ]
  }
}