{
  "type": "Feature",
  "properties": {
    "name": "Kirkby",
    "country": "GB",
    "subdivision": "ENG",
    "timezone": "Europe/London"
  },
  "geometry": {
    "type": "Point",
    "coordinates": [
      -2.89215,
      53.48138
    ]
  }
}