{
  "type": "Feature",
  "properties": {
    "name": "Lambeth",
    "country": "GB",
    "subdivision": "ENG",
    "timezone": "Europe/London"
  },
  "geometry": {
    "type": "Point",
    "coordinates": [
      -0.11152,
      51.49635
    ]
  }
}