{
  "type": "Feature",
  "properties": {
    "name": "Lamesley",
    "country": "GB",
    "subdivision": "ENG",
    "timezone": "Europe/London"
  },
  "geometry": {
    "type": "Point",
    "coordinates": [
      -1.60945,
      54.91567
    ]
  }
}