{
  "type": "Feature",
  "properties": {
    "name": "Landrake",
    "country": "GB",
    "subdivision": "ENG",
    "timezone": "Europe/London"
  },
  "geometry": {
    "type": "Point",
    "coordinates": [
      -4.29023,
      50.42265
    ]
  }
}