{
  "type": "Feature",
  "properties": {
    "name": "Langport",
    "country": "GB",
    "subdivision": "ENG",
    "timezone": "Europe/London"
  },
  "geometry": {
    "type": "Point",
    "coordinates": [
      -2.82806,
      51.03778
    ]
  }
}