{
  "type": "Feature",
  "properties": {
    "name": "Langley Park",
    "country": "GB",
    "subdivision": "ENG",
    "timezone": "Europe/London"
  },
  "geometry": {
    "type": "Point",
    "coordinates": [
      -1.67005,
      54.79979
    ]
  }
}