{
  "type": "Feature",
  "properties": {
    "name": "Leconfield",
    "country": "GB",
    "subdivision": "ENG",
    "timezone": "Europe/London"
  },
  "geometry": {
    "type": "Point",
    "coordinates": [
      -0.45729,
      53.8773
    ]
  }
}