{
  "type": "Feature",
  "properties": {
    "name": "Leigh",
    "country": "GB",
    "subdivision": "ENG",
    "timezone": "Europe/London"
  },
  "geometry": {
    "type": "Point",
    "coordinates": [
      -2.51973,
      53.49642
    ]
  }
}