{
  "type": "Feature",
  "properties": {
    "name": "Lenham",
    "country": "GB",
    "subdivision": "ENG",
    "timezone": "Europe/London"
  },
  "geometry": {
    "type": "Point",
    "coordinates": [
      0.71892,
      51.23705
    ]
  }
}