{
  "type": "Feature",
  "properties": {
    "name": "Lidlington",
    "country": "GB",
    "subdivision": "ENG",
    "timezone": "Europe/London"
  },
  "geometry": {
    "type": "Point",
    "coordinates": [
      -0.55914,
      52.04154
    ]
  }
}