{
  "type": "Feature",
  "properties": {
    "name": "Lingwood",
    "country": "GB",
    "subdivision": "ENG",
    "timezone": "Europe/London"
  },
  "geometry": {
    "type": "Point",
    "coordinates": [
      1.48616,
      52.62104
    ]
  }
}