{
  "type": "Feature",
  "properties": {
    "name": "Liskeard",
    "country": "GB",
    "subdivision": "ENG",
    "timezone": "Europe/London"
  },
  "geometry": {
    "type": "Point",
    "coordinates": [
      -4.46517,
      50.4545
    ]
  }
}