{
  "type": "Feature",
  "properties": {
    "name": "Little Chalfont",
    "country": "GB",
    "subdivision": "ENG",
    "timezone": "Europe/London"
  },
  "geometry": {
    "type": "Point",
    "coordinates": [
      -0.57038,
      51.66829
    ]
  }
}