{
  "type": "Feature",
  "properties": {
    "name": "Liversedge",
    "country": "GB",
    "subdivision": "ENG",
    "timezone": "Europe/London"
  },
  "geometry": {
    "type": "Point",
    "coordinates": [
      -1.69327,
      53.70514
    ]
  }
}