{
  "type": "Feature",
  "properties": {
    "name": "Long Sutton",
    "country": "GB",
    "subdivision": "ENG",
    "timezone": "Europe/London"
  },
  "geometry": {
    "type": "Point",
    "coordinates": [
      -0.94293,
      51.21978
    ]
  }
}