{
  "type": "Feature",
  "properties": {
    "name": "Low Bradley",
    "country": "GB",
    "subdivision": "ENG",
    "timezone": "Europe/London"
  },
  "geometry": {
    "type": "Point",
    "coordinates": [
      -1.99646,
      53.93217
    ]
  }
}