{
  "type": "Feature",
  "properties": {
    "name": "Low Etherley",
    "country": "GB",
    "subdivision": "ENG",
    "timezone": "Europe/London"
  },
  "geometry": {
    "type": "Point",
    "coordinates": [
      -1.74315,
      54.65349
    ]
  }
}