{
  "type": "Feature",
  "properties": {
    "name": "Lower Earley",
    "country": "GB",
    "subdivision": "ENG",
    "timezone": "Europe/London"
  },
  "geometry": {
    "type": "Point",
    "coordinates": [
      -0.91979,
      51.42708
    ]
  }
}