{
  "type": "Feature",
  "properties": {
    "name": "Lynemouth",
    "country": "GB",
    "subdivision": "ENG",
    "timezone": "Europe/London"
  },
  "geometry": {
    "type": "Point",
    "coordinates": [
      -1.5425,
      55.21306
    ]
  }
}