{
  "type": "Feature",
  "properties": {
    "name": "Maldon",
    "country": "GB",
    "subdivision": "ENG",
    "timezone": "Europe/London"
  },
  "geometry": {
    "type": "Point",
    "coordinates": [
      0.67463,
      51.7311
    ]
  }
}