{
  "type": "Feature",
  "properties": {
    "name": "Malpas",
    "country": "GB",
    "subdivision": "ENG",
    "timezone": "Europe/London"
  },
  "geometry": {
    "type": "Point",
    "coordinates": [
      -2.76667,
      53.01667
    ]
  }
}