{
  "type": "Feature",
  "properties": {
    "name": "Marcham",
    "country": "GB",
    "subdivision": "ENG",
    "timezone": "Europe/London"
  },
  "geometry": {
    "type": "Point",
    "coordinates": [
      -1.34295,
      51.66755
    ]
  }
}