{
  "type": "Feature",
  "properties": {
    "name": "Market Lavington",
    "country": "GB",
    "subdivision": "ENG",
    "timezone": "Europe/London"
  },
  "geometry": {
    "type": "Point",
    "coordinates": [
      -1.97729,
      51.28756
    ]
  }
}