{
  "type": "Feature",
  "properties": {
    "name": "Maryport",
    "country": "GB",
    "subdivision": "ENG",
    "timezone": "Europe/London"
  },
  "geometry": {
    "type": "Point",
    "coordinates": [
      -3.49509,
      54.71434
    ]
  }
}