{
  "type": "Feature",
  "properties": {
    "name": "Melksham",
    "country": "GB",
    "subdivision": "ENG",
    "timezone": "Europe/London"
  },
  "geometry": {
    "type": "Point",
    "coordinates": [
      -2.14002,
      51.37281
    ]
  }
}