{
  "type": "Feature",
  "properties": {
    "name": "Mildenhall",
    "country": "GB",
    "subdivision": "ENG",
    "timezone": "Europe/London"
  },
  "geometry": {
    "type": "Point",
    "coordinates": [
      0.51086,
      52.34446
    ]
  }
}