{
  "type": "Feature",
  "properties": {
    "name": "Mirfield",
    "country": "GB",
    "subdivision": "ENG",
    "timezone": "Europe/London"
  },
  "geometry": {
    "type": "Point",
    "coordinates": [
      -1.69636,
      53.67343
    ]
  }
}