{
  "type": "Feature",
  "properties": {
    "name": "Moreton in Marsh",
    "country": "GB",
    "subdivision": "ENG",
    "timezone": "Europe/London"
  },
  "geometry": {
    "type": "Point",
    "coordinates": [
      -1.70297,
      51.98964
    ]
  }
}