{
  "type": "Feature",
  "properties": {
    "name": "Mount Hawke",
    "country": "GB",
    "subdivision": "ENG",
    "timezone": "Europe/London"
  },
  "geometry": {
    "type": "Point",
    "coordinates": [
      -5.20855,
      50.28229
    ]
  }
}