{
  "type": "Feature",
  "properties": {
    "name": "Mountsorrel",
    "country": "GB",
    "subdivision": "ENG",
    "timezone": "Europe/London"
  },
  "geometry": {
    "type": "Point",
    "coordinates": [
      -1.15,
      52.71667
    ]
  }
}