{
  "type": "Feature",
  "properties": {
    "name": "Mylor Bridge",
    "country": "GB",
    "subdivision": "ENG",
    "timezone": "Europe/London"
  },
  "geometry": {
    "type": "Point",
    "coordinates": [
      -5.07963,
      50.18506
    ]
  }
}