{
  "type": "Feature",
  "properties": {
    "name": "Mytholmroyd",
    "country": "GB",
    "subdivision": "ENG",
    "timezone": "Europe/London"
  },
  "geometry": {
    "type": "Point",
    "coordinates": [
      -1.98258,
      53.73065
    ]
  }
}