{
  "type": "Feature",
  "properties": {
    "name": "Nailsea",
    "country": "GB",
    "subdivision": "ENG",
    "timezone": "Europe/London"
  },
  "geometry": {
    "type": "Point",
    "coordinates": [
      -2.75847,
      51.43239
    ]
  }
}