{
  "type": "Feature",
  "properties": {
    "name": "Narborough",
    "country": "GB",
    "subdivision": "ENG",
    "timezone": "Europe/London"
  },
  "geometry": {
    "type": "Point",
    "coordinates": [
      0.58333,
      52.68333
    ]
  }
}