{
  "type": "Feature",
  "properties": {
    "name": "Necton",
    "country": "GB",
    "subdivision": "ENG",
    "timezone": "Europe/London"
  },
  "geometry": {
    "type": "Point",
    "coordinates": [
      0.77539,
      52.64994
    ]
  }
}