{
  "type": "Feature",
  "properties": {
    "name": "Netley",
    "country": "GB",
    "subdivision": "ENG",
    "timezone": "Europe/London"
  },
  "geometry": {
    "type": "Point",
    "coordinates": [
      -1.35398,
      50.87634
    ]
  }
}