{
  "type": "Feature",
  "properties": {
    "name": "Northiam",
    "country": "GB",
    "subdivision": "ENG",
    "timezone": "Europe/London"
  },
  "geometry": {
    "type": "Point",
    "coordinates": [
      0.60026,
      50.99439
    ]
  }
}