{
  "type": "Feature",
  "properties": {
    "name": "North Somercotes",
    "country": "GB",
    "subdivision": "ENG",
    "timezone": "Europe/London"
  },
  "geometry": {
    "type": "Point",
    "coordinates": [
      0.14103,
      53.44573
    ]
  }
}