{
  "type": "Feature",
  "properties": {
    "name": "Northborough",
    "country": "GB",
    "subdivision": "ENG",
    "timezone": "Europe/London"
  },
  "geometry": {
    "type": "Point",
    "coordinates": [
      -0.29818,
      52.65868
    ]
  }
}