{
  "type": "Feature",
  "properties": {
    "name": "North Thoresby",
    "country": "GB",
    "subdivision": "ENG",
    "timezone": "Europe/London"
  },
  "geometry": {
    "type": "Point",
    "coordinates": [
      -0.05575,
      53.46651
    ]
  }
}