{
  "type": "Feature",
  "properties": {
    "name": "Nuneaton",
    "country": "GB",
    "subdivision": "ENG",
    "timezone": "Europe/London"
  },
  "geometry": {
    "type": "Point",
    "coordinates": [
      -1.46523,
      52.52323
    ]
  }
}