{
  "type": "Feature",
  "properties": {
    "name": "Oakham",
    "country": "GB",
    "subdivision": "ENG",
    "timezone": "Europe/London"
  },
  "geometry": {
    "type": "Point",
    "coordinates": [
      -0.73333,
      52.66667
    ]
  }
}