{
  "type": "Feature",
  "properties": {
    "name": "Old Windsor",
    "country": "GB",
    "subdivision": "ENG",
    "timezone": "Europe/London"
  },
  "geometry": {
    "type": "Point",
    "coordinates": [
      -0.58674,
      51.45807
    ]
  }
}