{
  "type": "Feature",
  "properties": {
    "name": "Otley",
    "country": "GB",
    "subdivision": "ENG",
    "timezone": "Europe/London"
  },
  "geometry": {
    "type": "Point",
    "coordinates": [
      -1.69383,
      53.90553
    ]
  }
}