{
  "type": "Feature",
  "properties": {
    "name": "Oughtibridge",
    "country": "GB",
    "subdivision": "ENG",
    "timezone": "Europe/London"
  },
  "geometry": {
    "type": "Point",
    "coordinates": [
      -1.53902,
      53.43612
    ]
  }
}