{
  "type": "Feature",
  "properties": {
    "name": "Over",
    "country": "GB",
    "subdivision": "ENG",
    "timezone": "Europe/London"
  },
  "geometry": {
    "type": "Point",
    "coordinates": [
      -2.55,
      53.18333
    ]
  }
}