{
  "type": "Feature",
  "properties": {
    "name": "Parkstone",
    "country": "GB",
    "subdivision": "ENG",
    "timezone": "Europe/London"
  },
  "geometry": {
    "type": "Point",
    "coordinates": [
      -1.94492,
      50.72994
    ]
  }
}