{
  "type": "Feature",
  "properties": {
    "name": "Pegswood",
    "country": "GB",
    "subdivision": "ENG",
    "timezone": "Europe/London"
  },
  "geometry": {
    "type": "Point",
    "coordinates": [
      -1.64525,
      55.1793
    ]
  }
}