{
  "type": "Feature",
  "properties": {
    "name": "Penkridge",
    "country": "GB",
    "subdivision": "ENG",
    "timezone": "Europe/London"
  },
  "geometry": {
    "type": "Point",
    "coordinates": [
      -2.1156,
      52.72556
    ]
  }
}