{
  "type": "Feature",
  "properties": {
    "name": "Penryn",
    "country": "GB",
    "subdivision": "ENG",
    "timezone": "Europe/London"
  },
  "geometry": {
    "type": "Point",
    "coordinates": [
      -5.10416,
      50.16812
    ]
  }
}