{
  "type": "Feature",
  "properties": {
    "name": "Petersfield",
    "country": "GB",
    "subdivision": "ENG",
    "timezone": "Europe/London"
  },
  "geometry": {
    "type": "Point",
    "coordinates": [
      -0.93375,
      51.00495
    ]
  }
}