{
  "type": "Feature",
  "properties": {
    "name": "Pevensey",
    "country": "GB",
    "subdivision": "ENG",
    "timezone": "Europe/London"
  },
  "geometry": {
    "type": "Point",
    "coordinates": [
      0.33963,
      50.81966
    ]
  }
}