{
  "type": "Feature",
  "properties": {
    "name": "Pickering",
    "country": "GB",
    "subdivision": "ENG",
    "timezone": "Europe/London"
  },
  "geometry": {
    "type": "Point",
    "coordinates": [
      -0.76667,
      54.25
    ]
  }
}