{
  "type": "Feature",
  "properties": {
    "name": "Pimperne",
    "country": "GB",
    "subdivision": "ENG",
    "timezone": "Europe/London"
  },
  "geometry": {
    "type": "Point",
    "coordinates": [
      -2.1362,
      50.88374
    ]
  }
}