{
  "type": "Feature",
  "properties": {
    "name": "Ponteland",
    "country": "GB",
    "subdivision": "ENG",
    "timezone": "Europe/London"
  },
  "geometry": {
    "type": "Point",
    "coordinates": [
      -1.74532,
      55.05024
    ]
  }
}