{
  "type": "Feature",
  "properties": {
    "name": "Pontesbury",
    "country": "GB",
    "subdivision": "ENG",
    "timezone": "Europe/London"
  },
  "geometry": {
    "type": "Point",
    "coordinates": [
      -2.89035,
      52.64826
    ]
  }
}