{
  "type": "Feature",
  "properties": {
    "name": "Porthleven",
    "country": "GB",
    "subdivision": "ENG",
    "timezone": "Europe/London"
  },
  "geometry": {
    "type": "Point",
    "coordinates": [
      -5.31501,
      50.08618
    ]
  }
}