{
  "type": "Feature",
  "properties": {
    "name": "Queensbury",
    "country": "GB",
    "subdivision": "ENG",
    "timezone": "Europe/London"
  },
  "geometry": {
    "type": "Point",
    "coordinates": [
      -1.84912,
      53.76657
    ]
  }
}