{
  "type": "Feature",
  "properties": {
    "name": "Rastrick",
    "country": "GB",
    "subdivision": "ENG",
    "timezone": "Europe/London"
  },
  "geometry": {
    "type": "Point",
    "coordinates": [
      -1.7883,
      53.6921
    ]
  }
}