{
  "type": "Feature",
  "properties": {
    "name": "Ravenstone",
    "country": "GB",
    "subdivision": "ENG",
    "timezone": "Europe/London"
  },
  "geometry": {
    "type": "Point",
    "coordinates": [
      -1.40582,
      52.72111
    ]
  }
}