{
  "type": "Feature",
  "properties": {
    "name": "Riccall",
    "country": "GB",
    "subdivision": "ENG",
    "timezone": "Europe/London"
  },
  "geometry": {
    "type": "Point",
    "coordinates": [
      -1.0573,
      53.83331
    ]
  }
}