{
  "type": "Feature",
  "properties": {
    "name": "Rickinghall",
    "country": "GB",
    "subdivision": "ENG",
    "timezone": "Europe/London"
  },
  "geometry": {
    "type": "Point",
    "coordinates": [
      0.99272,
      52.33649
    ]
  }
}