{
  "type": "Feature",
  "properties": {
    "name": "Ringstead",
    "country": "GB",
    "subdivision": "ENG",
    "timezone": "Europe/London"
  },
  "geometry": {
    "type": "Point",
    "coordinates": [
      -0.5549,
      52.36528
    ]
  }
}