{
  "type": "Feature",
  "properties": {
    "name": "Roade",
    "country": "GB",
    "subdivision": "ENG",
    "timezone": "Europe/London"
  },
  "geometry": {
    "type": "Point",
    "coordinates": [
      -0.89745,
      52.15824
    ]
  }
}