{
  "type": "Feature",
  "properties": {
    "name": "Romsey",
    "country": "GB",
    "subdivision": "ENG",
    "timezone": "Europe/London"
  },
  "geometry": {
    "type": "Point",
    "coordinates": [
      -1.49989,
      50.98906
    ]
  }
}