{
  "type": "Feature",
  "properties": {
    "name": "Rotherfield Peppard",
    "country": "GB",
    "subdivision": "ENG",
    "timezone": "Europe/London"
  },
  "geometry": {
    "type": "Point",
    "coordinates": [
      -0.97847,
      51.53064
    ]
  }
}