{
  "type": "Feature",
  "properties": {
    "name": "Rothley",
    "country": "GB",
    "subdivision": "ENG",
    "timezone": "Europe/London"
  },
  "geometry": {
    "type": "Point",
    "coordinates": [
      -1.13739,
      52.70916
    ]
  }
}