{
  "type": "Feature",
  "properties": {
    "name": "Rowley Regis",
    "country": "GB",
    "subdivision": "ENG",
    "timezone": "Europe/London"
  },
  "geometry": {
    "type": "Point",
    "coordinates": [
      -2.04376,
      52.48292
    ]
  }
}