{
  "type": "Feature",
  "properties": {
    "name": "Rustington",
    "country": "GB",
    "subdivision": "ENG",
    "timezone": "Europe/London"
  },
  "geometry": {
    "type": "Point",
    "coordinates": [
      -0.50674,
      50.81027
    ]
  }
}