{
  "type": "Feature",
  "properties": {
    "name": "Ryhill",
    "country": "GB",
    "subdivision": "ENG",
    "timezone": "Europe/London"
  },
  "geometry": {
    "type": "Point",
    "coordinates": [
      -1.41071,
      53.62204
    ]
  }
}