{
  "type": "Feature",
  "properties": {
    "name": "Sabden",
    "country": "GB",
    "subdivision": "ENG",
    "timezone": "Europe/London"
  },
  "geometry": {
    "type": "Point",
    "coordinates": [
      -2.33728,
      53.83355
    ]
  }
}