{
  "type": "Feature",
  "properties": {
    "name": "Saint Peters",
    "country": "GB",
    "subdivision": "ENG",
    "timezone": "Europe/London"
  },
  "geometry": {
    "type": "Point",
    "coordinates": [
      1.41667,
      51.36667
    ]
  }
}