{
  "type": "Feature",
  "properties": {
    "name": "Saltburn-by-the-Sea",
    "country": "GB",
    "subdivision": "ENG",
    "timezone": "Europe/London"
  },
  "geometry": {
    "type": "Point",
    "coordinates": [
      -0.97367,
      54.58237
    ]
  }
}