{
  "type": "Feature",
  "properties": {
    "name": "Scole",
    "country": "GB",
    "subdivision": "ENG",
    "timezone": "Europe/London"
  },
  "geometry": {
    "type": "Point",
    "coordinates": [
      1.15674,
      52.36706
    ]
  }
}