{
  "type": "Feature",
  "properties": {
    "name": "Shanklin",
    "country": "GB",
    "subdivision": "ENG",
    "timezone": "Europe/London"
  },
  "geometry": {
    "type": "Point",
    "coordinates": [
      -1.1785,
      50.62613
    ]
  }
}