{
  "type": "Feature",
  "properties": {
    "name": "Shepherdswell",
    "country": "GB",
    "subdivision": "ENG",
    "timezone": "Europe/London"
  },
  "geometry": {
    "type": "Point",
    "coordinates": [
      1.23049,
      51.18713
    ]
  }
}