{
  "type": "Feature",
  "properties": {
    "name": "Sherburn Hill",
    "country": "GB",
    "subdivision": "ENG",
    "timezone": "Europe/London"
  },
  "geometry": {
    "type": "Point",
    "coordinates": [
      -1.47985,
      54.7727
    ]
  }
}