{
  "type": "Feature",
  "properties": {
    "name": "Shevington",
    "country": "GB",
    "subdivision": "ENG",
    "timezone": "Europe/London"
  },
  "geometry": {
    "type": "Point",
    "coordinates": [
      -2.69316,
      53.57236
    ]
  }
}