{
  "type": "Feature",
  "properties": {
    "name": "Shillingstone",
    "country": "GB",
    "subdivision": "ENG",
    "timezone": "Europe/London"
  },
  "geometry": {
    "type": "Point",
    "coordinates": [
      -2.24495,
      50.89567
    ]
  }
}