{
  "type": "Feature",
  "properties": {
    "name": "Shirley",
    "country": "GB",
    "subdivision": "ENG",
    "timezone": "Europe/London"
  },
  "geometry": {
    "type": "Point",
    "coordinates": [
      -1.81952,
      52.41074
    ]
  }
}