{
  "type": "Feature",
  "properties": {
    "name": "Shrivenham",
    "country": "GB",
    "subdivision": "ENG",
    "timezone": "Europe/London"
  },
  "geometry": {
    "type": "Point",
    "coordinates": [
      -1.65461,
      51.59853
    ]
  }
}