{
  "type": "Feature",
  "properties": {
    "name": "Sible Hedingham",
    "country": "GB",
    "subdivision": "ENG",
    "timezone": "Europe/London"
  },
  "geometry": {
    "type": "Point",
    "coordinates": [
      0.59262,
      51.97772
    ]
  }
}