{
  "type": "Feature",
  "properties": {
    "name": "Silsden",
    "country": "GB",
    "subdivision": "ENG",
    "timezone": "Europe/London"
  },
  "geometry": {
    "type": "Point",
    "coordinates": [
      -1.93802,
      53.91443
    ]
  }
}