{
  "type": "Feature",
  "properties": {
    "name": "Sissinghurst",
    "country": "GB",
    "subdivision": "ENG",
    "timezone": "Europe/London"
  },
  "geometry": {
    "type": "Point",
    "coordinates": [
      0.56,
      51.10905
    ]
  }
}