{
  "type": "Feature",
  "properties": {
    "name": "Sonning Common",
    "country": "GB",
    "subdivision": "ENG",
    "timezone": "Europe/London"
  },
  "geometry": {
    "type": "Point",
    "coordinates": [
      -0.97753,
      51.51873
    ]
  }
}