{
  "type": "Feature",
  "properties": {
    "name": "Southsea",
    "country": "GB",
    "subdivision": "ENG",
    "timezone": "Europe/London"
  },
  "geometry": {
    "type": "Point",
    "coordinates": [
      -1.09071,
      50.78351
    ]
  }
}