{
  "type": "Feature",
  "properties": {
    "name": "Southery",
    "country": "GB",
    "subdivision": "ENG",
    "timezone": "Europe/London"
  },
  "geometry": {
    "type": "Point",
    "coordinates": [
      0.38783,
      52.52714
    ]
  }
}