{
  "type": "Feature",
  "properties": {
    "name": "Spalding",
    "country": "GB",
    "subdivision": "ENG",
    "timezone": "Europe/London"
  },
  "geometry": {
    "type": "Point",
    "coordinates": [
      -0.15141,
      52.78709
    ]
  }
}