{
  "type": "Feature",
  "properties": {
    "name": "Stainburn",
    "country": "GB",
    "subdivision": "ENG",
    "timezone": "Europe/London"
  },
  "geometry": {
    "type": "Point",
    "coordinates": [
      -1.61667,
      53.93333
    ]
  }
}