{
  "type": "Feature",
  "properties": {
    "name": "Stanford-le-Hope",
    "country": "GB",
    "subdivision": "ENG",
    "timezone": "Europe/London"
  },
  "geometry": {
    "type": "Point",
    "coordinates": [
      0.43422,
      51.52274
    ]
  }
}