{
  "type": "Feature",
  "properties": {
    "name": "Stoke Gifford",
    "country": "GB",
    "subdivision": "ENG",
    "timezone": "Europe/London"
  },
  "geometry": {
    "type": "Point",
    "coordinates": [
      -2.54053,
      51.51686
    ]
  }
}