{
  "type": "Feature",
  "properties": {
    "name": "Stoke-on-Trent",
    "country": "GB",
    "subdivision": "ENG",
    "timezone": "Europe/London"
  },
  "geometry": {
    "type": "Point",
    "coordinates": [
      -2.18538,
      53.00415
    ]
  }
}