{
  "type": "Feature",
  "properties": {
    "name": "Streetly",
    "country": "GB",
    "subdivision": "ENG",
    "timezone": "Europe/London"
  },
  "geometry": {
    "type": "Point",
    "coordinates": [
      -1.88333,
      52.58333
    ]
  }
}