{
  "type": "Feature",
  "properties": {
    "name": "Sutton Benger",
    "country": "GB",
    "subdivision": "ENG",
    "timezone": "Europe/London"
  },
  "geometry": {
    "type": "Point",
    "coordinates": [
      -2.08015,
      51.50685
    ]
  }
}