{
  "type": "Feature",
  "properties": {
    "name": "Sutton Coldfield",
    "country": "GB",
    "subdivision": "ENG",
    "timezone": "Europe/London"
  },
  "geometry": {
    "type": "Point",
    "coordinates": [
      -1.81667,
      52.56667
    ]
  }
}