{
  "type": "Feature",
  "properties": {
    "name": "Swadlincote",
    "country": "GB",
    "subdivision": "ENG",
    "timezone": "Europe/London"
  },
  "geometry": {
    "type": "Point",
    "coordinates": [
      -1.55744,
      52.774
    ]
  }
}