{
  "type": "Feature",
  "properties": {
    "name": "Swanley",
    "country": "GB",
    "subdivision": "ENG",
    "timezone": "Europe/London"
  },
  "geometry": {
    "type": "Point",
    "coordinates": [
      0.17321,
      51.39717
    ]
  }
}