{
  "type": "Feature",
  "properties": {
    "name": "Tamworth",
    "country": "GB",
    "subdivision": "ENG",
    "timezone": "Europe/London"
  },
  "geometry": {
    "type": "Point",
    "coordinates": [
      -1.69587,
      52.63399
    ]
  }
}