{
  "type": "Feature",
  "properties": {
    "name": "Tarporley",
    "country": "GB",
    "subdivision": "ENG",
    "timezone": "Europe/London"
  },
  "geometry": {
    "type": "Point",
    "coordinates": [
      -2.66867,
      53.15918
    ]
  }
}