{
  "type": "Feature",
  "properties": {
    "name": "Tattenhall",
    "country": "GB",
    "subdivision": "ENG",
    "timezone": "Europe/London"
  },
  "geometry": {
    "type": "Point",
    "coordinates": [
      -2.76746,
      53.12188
    ]
  }
}