{
  "type": "Feature",
  "properties": {
    "name": "Thirsk",
    "country": "GB",
    "subdivision": "ENG",
    "timezone": "Europe/London"
  },
  "geometry": {
    "type": "Point",
    "coordinates": [
      -1.34411,
      54.23298
    ]
  }
}