{
  "type": "Feature",
  "properties": {
    "name": "Thornbury",
    "country": "GB",
    "subdivision": "ENG",
    "timezone": "Europe/London"
  },
  "geometry": {
    "type": "Point",
    "coordinates": [
      -2.52028,
      51.60889
    ]
  }
}