{
  "type": "Feature",
  "properties": {
    "name": "Thurlby",
    "country": "GB",
    "subdivision": "ENG",
    "timezone": "Europe/London"
  },
  "geometry": {
    "type": "Point",
    "coordinates": [
      -0.37868,
      52.73879
    ]
  }
}