{
  "type": "Feature",
  "properties": {
    "name": "Tottington",
    "country": "GB",
    "subdivision": "ENG",
    "timezone": "Europe/London"
  },
  "geometry": {
    "type": "Point",
    "coordinates": [
      -2.34071,
      53.61326
    ]
  }
}