{
  "type": "Feature",
  "properties": {
    "name": "Town Row",
    "country": "GB",
    "subdivision": "ENG",
    "timezone": "Europe/London"
  },
  "geometry": {
    "type": "Point",
    "coordinates": [
      0.23217,
      51.05302
    ]
  }
}