{
  "type": "Feature",
  "properties": {
    "name": "Tring",
    "country": "GB",
    "subdivision": "ENG",
    "timezone": "Europe/London"
  },
  "geometry": {
    "type": "Point",
    "coordinates": [
      -0.65824,
      51.79471
    ]
  }
}