{
  "type": "Feature",
  "properties": {
    "name": "Tyldesley",
    "country": "GB",
    "subdivision": "ENG",
    "timezone": "Europe/London"
  },
  "geometry": {
    "type": "Point",
    "coordinates": [
      -2.46754,
      53.51393
    ]
  }
}