{
  "type": "Feature",
  "properties": {
    "name": "Uckfield",
    "country": "GB",
    "subdivision": "ENG",
    "timezone": "Europe/London"
  },
  "geometry": {
    "type": "Point",
    "coordinates": [
      0.09589,
      50.96948
    ]
  }
}