{
  "type": "Feature",
  "properties": {
    "name": "Upper Basildon",
    "country": "GB",
    "subdivision": "ENG",
    "timezone": "Europe/London"
  },
  "geometry": {
    "type": "Point",
    "coordinates": [
      -1.14075,
      51.48165
    ]
  }
}