{
  "type": "Feature",
  "properties": {
    "name": "Uppingham",
    "country": "GB",
    "subdivision": "ENG",
    "timezone": "Europe/London"
  },
  "geometry": {
    "type": "Point",
    "coordinates": [
      -0.72272,
      52.58803
    ]
  }
}