{
  "type": "Feature",
  "properties": {
    "name": "Upwell",
    "country": "GB",
    "subdivision": "ENG",
    "timezone": "Europe/London"
  },
  "geometry": {
    "type": "Point",
    "coordinates": [
      0.2219,
      52.60249
    ]
  }
}