{
  "type": "Feature",
  "properties": {
    "name": "Virginia Water",
    "country": "GB",
    "subdivision": "ENG",
    "timezone": "Europe/London"
  },
  "geometry": {
    "type": "Point",
    "coordinates": [
      -0.56651,
      51.40343
    ]
  }
}