{
  "type": "Feature",
  "properties": {
    "name": "Wadebridge",
    "country": "GB",
    "subdivision": "ENG",
    "timezone": "Europe/London"
  },
  "geometry": {
    "type": "Point",
    "coordinates": [
      -4.83633,
      50.51734
    ]
  }
}