{
  "type": "Feature",
  "properties": {
    "name": "Walsall",
    "country": "GB",
    "subdivision": "ENG",
    "timezone": "Europe/London"
  },
  "geometry": {
    "type": "Point",
    "coordinates": [
      -1.98396,
      52.58528
    ]
  }
}