{
  "type": "Feature",
  "properties": {
    "name": "Walton",
    "country": "GB",
    "subdivision": "ENG",
    "timezone": "Europe/London"
  },
  "geometry": {
    "type": "Point",
    "coordinates": [
      -1.46084,
      53.22284
    ]
  }
}