{
  "type": "Feature",
  "properties": {
    "name": "Waltham Abbey",
    "country": "GB",
    "subdivision": "ENG",
    "timezone": "Europe/London"
  },
  "geometry": {
    "type": "Point",
    "coordinates": [
      -0.00421,
      51.687
    ]
  }
}