{
  "type": "Feature",
  "properties": {
    "name": "Warlingham",
    "country": "GB",
    "subdivision": "ENG",
    "timezone": "Europe/London"
  },
  "geometry": {
    "type": "Point",
    "coordinates": [
      -0.05794,
      51.30953
    ]
  }
}