{
  "type": "Feature",
  "properties": {
    "name": "Watton at Stone",
    "country": "GB",
    "subdivision": "ENG",
    "timezone": "Europe/London"
  },
  "geometry": {
    "type": "Point",
    "coordinates": [
      -0.11381,
      51.85842
    ]
  }
}