{
  "type": "Feature",
  "properties": {
    "name": "Wellesbourne Mountford",
    "country": "GB",
    "subdivision": "ENG",
    "timezone": "Europe/London"
  },
  "geometry": {
    "type": "Point",
    "coordinates": [
      -1.60967,
      52.19246
    ]
  }
}