{
  "type": "Feature",
  "properties": {
    "name": "Westonzoyland",
    "country": "GB",
    "subdivision": "ENG",
    "timezone": "Europe/London"
  },
  "geometry": {
    "type": "Point",
    "coordinates": [
      -2.92843,
      51.10854
    ]
  }
}