{
  "type": "Feature",
  "properties": {
    "name": "West End",
    "country": "GB",
    "subdivision": "ENG",
    "timezone": "Europe/London"
  },
  "geometry": {
    "type": "Point",
    "coordinates": [
      -1.33282,
      50.92741
    ]
  }
}