{
  "type": "Feature",
  "properties": {
    "name": "West Kingsdown",
    "country": "GB",
    "subdivision": "ENG",
    "timezone": "Europe/London"
  },
  "geometry": {
    "type": "Point",
    "coordinates": [
      0.26127,
      51.34281
    ]
  }
}