{
  "type": "Feature",
  "properties": {
    "name": "Westfield",
    "country": "GB",
    "subdivision": "ENG",
    "timezone": "Europe/London"
  },
  "geometry": {
    "type": "Point",
    "coordinates": [
      -1.87471,
      51.89291
    ]
  }
}