{
  "type": "Feature",
  "properties": {
    "name": "Westcott",
    "country": "GB",
    "subdivision": "ENG",
    "timezone": "Europe/London"
  },
  "geometry": {
    "type": "Point",
    "coordinates": [
      -0.37195,
      51.22438
    ]
  }
}