{
  "type": "Feature",
  "properties": {
    "name": "Weymouth",
    "country": "GB",
    "subdivision": "ENG",
    "timezone": "Europe/London"
  },
  "geometry": {
    "type": "Point",
    "coordinates": [
      -2.45991,
      50.61448
    ]
  }
}