{
  "type": "Feature",
  "properties": {
    "name": "Whalley",
    "country": "GB",
    "subdivision": "ENG",
    "timezone": "Europe/London"
  },
  "geometry": {
    "type": "Point",
    "coordinates": [
      -2.40712,
      53.82209
    ]
  }
}