{
  "type": "Feature",
  "properties": {
    "name": "Wickham",
    "country": "GB",
    "subdivision": "ENG",
    "timezone": "Europe/London"
  },
  "geometry": {
    "type": "Point",
    "coordinates": [
      -1.432,
      51.44342
    ]
  }
}