{
  "type": "Feature",
  "properties": {
    "name": "Wigton",
    "country": "GB",
    "subdivision": "ENG",
    "timezone": "Europe/London"
  },
  "geometry": {
    "type": "Point",
    "coordinates": [
      -3.16114,
      54.82482
    ]
  }
}