{
  "type": "Feature",
  "properties": {
    "name": "Wilsden",
    "country": "GB",
    "subdivision": "ENG",
    "timezone": "Europe/London"
  },
  "geometry": {
    "type": "Point",
    "coordinates": [
      -1.85959,
      53.82084
    ]
  }
}