{
  "type": "Feature",
  "properties": {
    "name": "Wirksworth",
    "country": "GB",
    "subdivision": "ENG",
    "timezone": "Europe/London"
  },
  "geometry": {
    "type": "Point",
    "coordinates": [
      -1.57391,
      53.08232
    ]
  }
}