{
  "type": "Feature",
  "properties": {
    "name": "Wisbech",
    "country": "GB",
    "subdivision": "ENG",
    "timezone": "Europe/London"
  },
  "geometry": {
    "type": "Point",
    "coordinates": [
      0.15938,
      52.66622
    ]
  }
}