{
  "type": "Feature",
  "properties": {
    "name": "Wombourn",
    "country": "GB",
    "subdivision": "ENG",
    "timezone": "Europe/London"
  },
  "geometry": {
    "type": "Point",
    "coordinates": [
      -2.18333,
      52.53333
    ]
  }
}