{
  "type": "Feature",
  "properties": {
    "name": "Woodbridge",
    "country": "GB",
    "subdivision": "ENG",
    "timezone": "Europe/London"
  },
  "geometry": {
    "type": "Point",
    "coordinates": [
      1.32042,
      52.09332
    ]
  }
}