{
  "type": "Feature",
  "properties": {
    "name": "Wool",
    "country": "GB",
    "subdivision": "ENG",
    "timezone": "Europe/London"
  },
  "geometry": {
    "type": "Point",
    "coordinates": [
      -2.2189,
      50.67966
    ]
  }
}