{
  "type": "Feature",
  "properties": {
    "name": "Wootton",
    "country": "GB",
    "subdivision": "ENG",
    "timezone": "Europe/London"
  },
  "geometry": {
    "type": "Point",
    "coordinates": [
      -0.53494,
      52.09525
    ]
  }
}