{
  "type": "Feature",
  "properties": {
    "name": "Wormley",
    "country": "GB",
    "subdivision": "ENG",
    "timezone": "Europe/London"
  },
  "geometry": {
    "type": "Point",
    "coordinates": [
      -0.64673,
      51.13622
    ]
  }
}