{
  "type": "Feature",
  "properties": {
    "name": "Wotton-under-Edge",
    "country": "GB",
    "subdivision": "ENG",
    "timezone": "Europe/London"
  },
  "geometry": {
    "type": "Point",
    "coordinates": [
      -2.34512,
      51.63242
    ]
  }
}