{
  "type": "Feature",
  "properties": {
    "name": "Wroxall",
    "country": "GB",
    "subdivision": "ENG",
    "timezone": "Europe/London"
  },
  "geometry": {
    "type": "Point",
    "coordinates": [
      -1.66898,
      52.33791
    ]
  }
}