{
  "type": "Feature",
  "properties": {
    "name": "Wylam",
    "country": "GB",
    "subdivision": "ENG",
    "timezone": "Europe/London"
  },
  "geometry": {
    "type": "Point",
    "coordinates": [
      -1.82187,
      54.97654
    ]
  }
}