{
  "type": "Feature",
  "properties": {
    "name": "Mankono",
    "country": "CI",
    "subdivision": "97",
    "timezone": "Africa/Abidjan"
  },
  "geometry": {
    "type": "Point",
    "coordinates": [
      -6.18972,
      8.05861
    ]
  }
}