{
  "type": "Feature",
  "properties": {
    "name": "Neiafu",
    "country": "TO",
    "subdivision": "03",
    "timezone": "Pacific/Tongatapu"
  },
  "geometry": {
    "type": "Point",
    "coordinates": [
      -173.98404,
      -18.6506
    ]
  }
}