{
  "type": "Feature",
  "properties": {
    "name": "Brandvlei",
    "country": "ZA",
    "subdivision": "08",
    "timezone": "Africa/Johannesburg"
  },
  "geometry": {
    "type": "Point",
    "coordinates": [
      20.48659,
      -30.46532
    ]
  }
}