{
  "type": "Feature",
  "properties": {
    "name": "De Aar",
    "country": "ZA",
    "subdivision": "08",
    "timezone": "Africa/Johannesburg"
  },
  "geometry": {
    "type": "Point",
    "coordinates": [
      24.0123,
      -30.64966
    ]
  }
}