{
  "type": "Feature",
  "properties": {
    "name": "Pampierstad",
    "country": "ZA",
    "subdivision": "08",
    "timezone": "Africa/Johannesburg"
  },
  "geometry": {
    "type": "Point",
    "coordinates": [
      24.68768,
      -27.78324
    ]
  }
}