{
  "type": "Feature",
  "properties": {
    "name": "Springbok",
    "country": "ZA",
    "subdivision": "08",
    "timezone": "Africa/Johannesburg"
  },
  "geometry": {
    "type": "Point",
    "coordinates": [
      17.8865,
      -29.66434
    ]
  }
}