{
  "type": "Feature",
  "properties": {
    "name": "Aínsa",
    "country": "ES",
    "subdivision": "52",
    "timezone": "Europe/Madrid"
  },
  "geometry": {
    "type": "Point",
    "coordinates": [
      0.14008,
      42.41547
    ]
  }
}