{
  "type": "Feature",
  "properties": {
    "name": "Albarracín",
    "country": "ES",
    "subdivision": "52",
    "timezone": "Europe/Madrid"
  },
  "geometry": {
    "type": "Point",
    "coordinates": [
      -1.44375,
      40.40818
    ]
  }
}