{
  "type": "Feature",
  "properties": {
    "name": "Biota",
    "country": "ES",
    "subdivision": "52",
    "timezone": "Europe/Madrid"
  },
  "geometry": {
    "type": "Point",
    "coordinates": [
      -1.18735,
      42.26214
    ]
  }
}