{
  "type": "Feature",
  "properties": {
    "name": "Calaceite",
    "country": "ES",
    "subdivision": "52",
    "timezone": "Europe/Madrid"
  },
  "geometry": {
    "type": "Point",
    "coordinates": [
      0.18876,
      41.01625
    ]
  }
}