{
  "type": "Feature",
  "properties": {
    "name": "Ejea de los Caballeros",
    "country": "ES",
    "subdivision": "52",
    "timezone": "Europe/Madrid"
  },
  "geometry": {
    "type": "Point",
    "coordinates": [
      -1.13716,
      42.12632
    ]
  }
}