{
  "type": "Feature",
  "properties": {
    "name": "El Burgo de Ebro",
    "country": "ES",
    "subdivision": "52",
    "timezone": "Europe/Madrid"
  },
  "geometry": {
    "type": "Point",
    "coordinates": [
      -0.74128,
      41.57157
    ]
  }
}