{
  "type": "Feature",
  "properties": {
    "name": "Fraga",
    "country": "ES",
    "subdivision": "52",
    "timezone": "Europe/Madrid"
  },
  "geometry": {
    "type": "Point",
    "coordinates": [
      0.34894,
      41.52294
    ]
  }
}