{
  "type": "Feature",
  "properties": {
    "name": "Mallén",
    "country": "ES",
    "subdivision": "52",
    "timezone": "Europe/Madrid"
  },
  "geometry": {
    "type": "Point",
    "coordinates": [
      -1.41994,
      41.90064
    ]
  }
}