{
  "type": "Feature",
  "properties": {
    "name": "Monreal del Campo",
    "country": "ES",
    "subdivision": "52",
    "timezone": "Europe/Madrid"
  },
  "geometry": {
    "type": "Point",
    "coordinates": [
      -1.35541,
      40.788
    ]
  }
}