{
  "type": "Feature",
  "properties": {
    "name": "Montecanal",
    "country": "ES",
    "subdivision": "52",
    "timezone": "Europe/Madrid"
  },
  "geometry": {
    "type": "Point",
    "coordinates": [
      -0.93873,
      41.62965
    ]
  }
}