{
  "type": "Feature",
  "properties": {
    "name": "Montalbán",
    "country": "ES",
    "subdivision": "52",
    "timezone": "Europe/Madrid"
  },
  "geometry": {
    "type": "Point",
    "coordinates": [
      -0.80178,
      40.83278
    ]
  }
}