{
  "type": "Feature",
  "properties": {
    "name": "Nonaspe",
    "country": "ES",
    "subdivision": "52",
    "timezone": "Europe/Madrid"
  },
  "geometry": {
    "type": "Point",
    "coordinates": [
      0.24775,
      41.20881
    ]
  }
}