{
  "type": "Feature",
  "properties": {
    "name": "Oliver-Valdefierro",
    "country": "ES",
    "subdivision": "52",
    "timezone": "Europe/Madrid"
  },
  "geometry": {
    "type": "Point",
    "coordinates": [
      -0.93349,
      41.64454
    ]
  }
}