{
  "type": "Feature",
  "properties": {
    "name": "Sádaba",
    "country": "ES",
    "subdivision": "52",
    "timezone": "Europe/Madrid"
  },
  "geometry": {
    "type": "Point",
    "coordinates": [
      -1.26951,
      42.2818
    ]
  }
}