{
  "type": "Feature",
  "properties": {
    "name": "Tarazona",
    "country": "ES",
    "subdivision": "52",
    "timezone": "Europe/Madrid"
  },
  "geometry": {
    "type": "Point",
    "coordinates": [
      -1.72678,
      41.90475
    ]
  }
}