{
  "type": "Feature",
  "properties": {
    "name": "Tardienta",
    "country": "ES",
    "subdivision": "52",
    "timezone": "Europe/Madrid"
  },
  "geometry": {
    "type": "Point",
    "coordinates": [
      -0.53731,
      41.97781
    ]
  }
}