{
  "type": "Feature",
  "properties": {
    "name": "Zuera",
    "country": "ES",
    "subdivision": "52",
    "timezone": "Europe/Madrid"
  },
  "geometry": {
    "type": "Point",
    "coordinates": [
      -0.78984,
      41.86775
    ]
  }
}