{
  "type": "Feature",
  "properties": {
    "name": "Arraial do Cabo",
    "country": "BR",
    "subdivision": "21",
    "timezone": "America/Sao_Paulo"
  },
  "geometry": {
    "type": "Point",
    "coordinates": [
      -42.02778,
      -22.96611
    ]
  }
}