{
  "type": "Feature",
  "properties": {
    "name": "Itaguaí",
    "country": "BR",
    "subdivision": "21",
    "timezone": "America/Sao_Paulo"
  },
  "geometry": {
    "type": "Point",
    "coordinates": [
      -43.77528,
      -22.85222
    ]
  }
}