{
  "type": "Feature",
  "properties": {
    "name": "Volta Redonda",
    "country": "BR",
    "subdivision": "21",
    "timezone": "America/Sao_Paulo"
  },
  "geometry": {
    "type": "Point",
    "coordinates": [
      -44.10417,
      -22.52306
    ]
  }
}