{
  "type": "Feature",
  "properties": {
    "name": "Fontana",
    "country": "AR",
    "subdivision": "03",
    "timezone": "America/Argentina/Cordoba"
  },
  "geometry": {
    "type": "Point",
    "coordinates": [
      -59.02392,
      -27.41813
    ]
  }
}