{
  "type": "Feature",
  "properties": {
    "name": "General Vedia",
    "country": "AR",
    "subdivision": "03",
    "timezone": "America/Argentina/Cordoba"
  },
  "geometry": {
    "type": "Point",
    "coordinates": [
      -58.6604,
      -26.93382
    ]
  }
}