{
  "type": "Feature",
  "properties": {
    "name": "La Verde",
    "country": "AR",
    "subdivision": "03",
    "timezone": "America/Argentina/Cordoba"
  },
  "geometry": {
    "type": "Point",
    "coordinates": [
      -59.37352,
      -27.12634
    ]
  }
}