{
  "type": "Feature",
  "properties": {
    "name": "Machagai",
    "country": "AR",
    "subdivision": "03",
    "timezone": "America/Argentina/Cordoba"
  },
  "geometry": {
    "type": "Point",
    "coordinates": [
      -60.04955,
      -26.92614
    ]
  }
}