{
  "type": "Feature",
  "properties": {
    "name": "Margarita Belén",
    "country": "AR",
    "subdivision": "03",
    "timezone": "America/Argentina/Cordoba"
  },
  "geometry": {
    "type": "Point",
    "coordinates": [
      -58.97219,
      -27.2616
    ]
  }
}