{
  "type": "Feature",
  "properties": {
    "name": "Argayash",
    "country": "RU",
    "subdivision": "13",
    "timezone": "Asia/Yekaterinburg"
  },
  "geometry": {
    "type": "Point",
    "coordinates": [
      60.8767,
      55.4888
    ]
  }
}