{
  "type": "Feature",
  "properties": {
    "name": "Kopeysk",
    "country": "RU",
    "subdivision": "13",
    "timezone": "Asia/Yekaterinburg"
  },
  "geometry": {
    "type": "Point",
    "coordinates": [
      61.62823,
      55.11722
    ]
  }
}