{
  "type": "Feature",
  "properties": {
    "name": "Kropachëvo",
    "country": "RU",
    "subdivision": "13",
    "timezone": "Asia/Yekaterinburg"
  },
  "geometry": {
    "type": "Point",
    "coordinates": [
      57.9896,
      55.0112
    ]
  }
}