{
  "type": "Feature",
  "properties": {
    "name": "Kyshtym",
    "country": "RU",
    "subdivision": "13",
    "timezone": "Asia/Yekaterinburg"
  },
  "geometry": {
    "type": "Point",
    "coordinates": [
      60.5528,
      55.714
    ]
  }
}