{
  "type": "Feature",
  "properties": {
    "name": "Mezhevoy",
    "country": "RU",
    "subdivision": "13",
    "timezone": "Asia/Yekaterinburg"
  },
  "geometry": {
    "type": "Point",
    "coordinates": [
      58.78139,
      55.17111
    ]
  }
}