{
  "type": "Feature",
  "properties": {
    "name": "Miasskoye",
    "country": "RU",
    "subdivision": "13",
    "timezone": "Asia/Yekaterinburg"
  },
  "geometry": {
    "type": "Point",
    "coordinates": [
      61.8905,
      55.2784
    ]
  }
}