{
  "type": "Feature",
  "properties": {
    "name": "Selezyan",
    "country": "RU",
    "subdivision": "13",
    "timezone": "Asia/Yekaterinburg"
  },
  "geometry": {
    "type": "Point",
    "coordinates": [
      61.82444,
      54.90583
    ]
  }
}