{
  "type": "Feature",
  "properties": {
    "name": "Tayginka",
    "country": "RU",
    "subdivision": "13",
    "timezone": "Asia/Yekaterinburg"
  },
  "geometry": {
    "type": "Point",
    "coordinates": [
      60.5076,
      55.6244
    ]
  }
}