{
  "type": "Feature",
  "properties": {
    "name": "Tyubuk",
    "country": "RU",
    "subdivision": "13",
    "timezone": "Asia/Yekaterinburg"
  },
  "geometry": {
    "type": "Point",
    "coordinates": [
      60.9405,
      56.05521
    ]
  }
}