{
  "type": "Feature",
  "properties": {
    "name": "Albion Park",
    "country": "AU",
    "subdivision": "02",
    "timezone": "Australia/Sydney"
  },
  "geometry": {
    "type": "Point",
    "coordinates": [
      150.77568,
      -34.57132
    ]
  }
}