{
  "type": "Feature",
  "properties": {
    "name": "Aldavilla",
    "country": "AU",
    "subdivision": "02",
    "timezone": "Australia/Sydney"
  },
  "geometry": {
    "type": "Point",
    "coordinates": [
      152.7679,
      -31.0818
    ]
  }
}