{
  "type": "Feature",
  "properties": {
    "name": "Annandale",
    "country": "AU",
    "subdivision": "02",
    "timezone": "Australia/Sydney"
  },
  "geometry": {
    "type": "Point",
    "coordinates": [
      151.16667,
      -33.88333
    ]
  }
}