{
  "type": "Feature",
  "properties": {
    "name": "Artarmon",
    "country": "AU",
    "subdivision": "02",
    "timezone": "Australia/Sydney"
  },
  "geometry": {
    "type": "Point",
    "coordinates": [
      151.18333,
      -33.81667
    ]
  }
}