{
  "type": "Feature",
  "properties": {
    "name": "Austinmer",
    "country": "AU",
    "subdivision": "02",
    "timezone": "Australia/Sydney"
  },
  "geometry": {
    "type": "Point",
    "coordinates": [
      150.93335,
      -34.30516
    ]
  }
}