{
  "type": "Feature",
  "properties": {
    "name": "Bardia",
    "country": "AU",
    "subdivision": "02",
    "timezone": "Australia/Sydney"
  },
  "geometry": {
    "type": "Point",
    "coordinates": [
      150.86306,
      -33.97789
    ]
  }
}