{
  "type": "Feature",
  "properties": {
    "name": "Barraba",
    "country": "AU",
    "subdivision": "02",
    "timezone": "Australia/Sydney"
  },
  "geometry": {
    "type": "Point",
    "coordinates": [
      150.60901,
      -30.38547
    ]
  }
}