{
  "type": "Feature",
  "properties": {
    "name": "Bateau Bay",
    "country": "AU",
    "subdivision": "02",
    "timezone": "Australia/Sydney"
  },
  "geometry": {
    "type": "Point",
    "coordinates": [
      151.46671,
      -33.38334
    ]
  }
}