{
  "type": "Feature",
  "properties": {
    "name": "Batlow",
    "country": "AU",
    "subdivision": "02",
    "timezone": "Australia/Sydney"
  },
  "geometry": {
    "type": "Point",
    "coordinates": [
      148.14727,
      -35.51987
    ]
  }
}