{
  "type": "Feature",
  "properties": {
    "name": "Bellevue Hill",
    "country": "AU",
    "subdivision": "02",
    "timezone": "Australia/Sydney"
  },
  "geometry": {
    "type": "Point",
    "coordinates": [
      151.25101,
      -33.87899
    ]
  }
}