{
  "type": "Feature",
  "properties": {
    "name": "Belmont South",
    "country": "AU",
    "subdivision": "02",
    "timezone": "Australia/Sydney"
  },
  "geometry": {
    "type": "Point",
    "coordinates": [
      151.65695,
      -33.04934
    ]
  }
}