{
  "type": "Feature",
  "properties": {
    "name": "Belrose",
    "country": "AU",
    "subdivision": "02",
    "timezone": "Australia/Sydney"
  },
  "geometry": {
    "type": "Point",
    "coordinates": [
      151.21033,
      -33.73954
    ]
  }
}