{
  "type": "Feature",
  "properties": {
    "name": "Berowra",
    "country": "AU",
    "subdivision": "02",
    "timezone": "Australia/Sydney"
  },
  "geometry": {
    "type": "Point",
    "coordinates": [
      151.15091,
      -33.62078
    ]
  }
}