{
  "type": "Feature",
  "properties": {
    "name": "Berowra Heights",
    "country": "AU",
    "subdivision": "02",
    "timezone": "Australia/Sydney"
  },
  "geometry": {
    "type": "Point",
    "coordinates": [
      151.13754,
      -33.61211
    ]
  }
}