{
  "type": "Feature",
  "properties": {
    "name": "Bilambil Heights",
    "country": "AU",
    "subdivision": "02",
    "timezone": "Australia/Sydney"
  },
  "geometry": {
    "type": "Point",
    "coordinates": [
      153.48415,
      -28.2161
    ]
  }
}