{
  "type": "Feature",
  "properties": {
    "name": "Bilgola Plateau",
    "country": "AU",
    "subdivision": "02",
    "timezone": "Australia/Sydney"
  },
  "geometry": {
    "type": "Point",
    "coordinates": [
      151.31212,
      -33.64781
    ]
  }
}