{
  "type": "Feature",
  "properties": {
    "name": "Blackbutt",
    "country": "AU",
    "subdivision": "02",
    "timezone": "Australia/Sydney"
  },
  "geometry": {
    "type": "Point",
    "coordinates": [
      150.83804,
      -34.57164
    ]
  }
}