{
  "type": "Feature",
  "properties": {
    "name": "Bomaderry",
    "country": "AU",
    "subdivision": "02",
    "timezone": "Australia/Sydney"
  },
  "geometry": {
    "type": "Point",
    "coordinates": [
      150.61093,
      -34.84967
    ]
  }
}