{
  "type": "Feature",
  "properties": {
    "name": "Bondi Beach",
    "country": "AU",
    "subdivision": "02",
    "timezone": "Australia/Sydney"
  },
  "geometry": {
    "type": "Point",
    "coordinates": [
      151.27852,
      -33.89079
    ]
  }
}