{
  "type": "Feature",
  "properties": {
    "name": "Bonville",
    "country": "AU",
    "subdivision": "02",
    "timezone": "Australia/Sydney"
  },
  "geometry": {
    "type": "Point",
    "coordinates": [
      153.05959,
      -30.38284
    ]
  }
}