{
  "type": "Feature",
  "properties": {
    "name": "Booker Bay",
    "country": "AU",
    "subdivision": "02",
    "timezone": "Australia/Sydney"
  },
  "geometry": {
    "type": "Point",
    "coordinates": [
      151.3459,
      -33.5125
    ]
  }
}