{
  "type": "Feature",
  "properties": {
    "name": "Botany",
    "country": "AU",
    "subdivision": "02",
    "timezone": "Australia/Sydney"
  },
  "geometry": {
    "type": "Point",
    "coordinates": [
      151.19591,
      -33.94599
    ]
  }
}