{
  "type": "Feature",
  "properties": {
    "name": "Bourkelands",
    "country": "AU",
    "subdivision": "02",
    "timezone": "Australia/Sydney"
  },
  "geometry": {
    "type": "Point",
    "coordinates": [
      147.34704,
      -35.15593
    ]
  }
}