{
  "type": "Feature",
  "properties": {
    "name": "Cabarita",
    "country": "AU",
    "subdivision": "02",
    "timezone": "Australia/Sydney"
  },
  "geometry": {
    "type": "Point",
    "coordinates": [
      151.11638,
      -33.84721
    ]
  }
}