{
  "type": "Feature",
  "properties": {
    "name": "Calala",
    "country": "AU",
    "subdivision": "02",
    "timezone": "Australia/Sydney"
  },
  "geometry": {
    "type": "Point",
    "coordinates": [
      150.98059,
      -31.17356
    ]
  }
}