{
  "type": "Feature",
  "properties": {
    "name": "Callala Bay",
    "country": "AU",
    "subdivision": "02",
    "timezone": "Australia/Sydney"
  },
  "geometry": {
    "type": "Point",
    "coordinates": [
      150.72281,
      -34.99668
    ]
  }
}