{
  "type": "Feature",
  "properties": {
    "name": "Camden",
    "country": "AU",
    "subdivision": "02",
    "timezone": "Australia/Sydney"
  },
  "geometry": {
    "type": "Point",
    "coordinates": [
      150.69624,
      -34.05405
    ]
  }
}