{
  "type": "Feature",
  "properties": {
    "name": "Catherine Field",
    "country": "AU",
    "subdivision": "02",
    "timezone": "Australia/Sydney"
  },
  "geometry": {
    "type": "Point",
    "coordinates": [
      150.77253,
      -34.00439
    ]
  }
}