{
  "type": "Feature",
  "properties": {
    "name": "Caves Beach",
    "country": "AU",
    "subdivision": "02",
    "timezone": "Australia/Sydney"
  },
  "geometry": {
    "type": "Point",
    "coordinates": [
      151.64402,
      -33.10637
    ]
  }
}