{
  "type": "Feature",
  "properties": {
    "name": "Cecil Hills",
    "country": "AU",
    "subdivision": "02",
    "timezone": "Australia/Sydney"
  },
  "geometry": {
    "type": "Point",
    "coordinates": [
      150.85137,
      -33.88917
    ]
  }
}