{
  "type": "Feature",
  "properties": {
    "name": "Charlestown",
    "country": "AU",
    "subdivision": "02",
    "timezone": "Australia/Sydney"
  },
  "geometry": {
    "type": "Point",
    "coordinates": [
      151.69318,
      -32.96828
    ]
  }
}