{
  "type": "Feature",
  "properties": {
    "name": "Charmhaven",
    "country": "AU",
    "subdivision": "02",
    "timezone": "Australia/Sydney"
  },
  "geometry": {
    "type": "Point",
    "coordinates": [
      151.50284,
      -33.22671
    ]
  }
}