{
  "type": "Feature",
  "properties": {
    "name": "Cherrybrook",
    "country": "AU",
    "subdivision": "02",
    "timezone": "Australia/Sydney"
  },
  "geometry": {
    "type": "Point",
    "coordinates": [
      151.04607,
      -33.72197
    ]
  }
}