{
  "type": "Feature",
  "properties": {
    "name": "Chester Hill",
    "country": "AU",
    "subdivision": "02",
    "timezone": "Australia/Sydney"
  },
  "geometry": {
    "type": "Point",
    "coordinates": [
      150.99945,
      -33.87896
    ]
  }
}