{
  "type": "Feature",
  "properties": {
    "name": "Clarence Town",
    "country": "AU",
    "subdivision": "02",
    "timezone": "Australia/Sydney"
  },
  "geometry": {
    "type": "Point",
    "coordinates": [
      151.77757,
      -32.58395
    ]
  }
}