{
  "type": "Feature",
  "properties": {
    "name": "Clontarf",
    "country": "AU",
    "subdivision": "02",
    "timezone": "Australia/Sydney"
  },
  "geometry": {
    "type": "Point",
    "coordinates": [
      151.25367,
      -33.80554
    ]
  }
}