{
  "type": "Feature",
  "properties": {
    "name": "Coffs Harbour",
    "country": "AU",
    "subdivision": "02",
    "timezone": "Australia/Sydney"
  },
  "geometry": {
    "type": "Point",
    "coordinates": [
      153.11351,
      -30.29626
    ]
  }
}