{
  "type": "Feature",
  "properties": {
    "name": "Colebee",
    "country": "AU",
    "subdivision": "02",
    "timezone": "Australia/Sydney"
  },
  "geometry": {
    "type": "Point",
    "coordinates": [
      150.84743,
      -33.72769
    ]
  }
}