{
  "type": "Feature",
  "properties": {
    "name": "Coleambally",
    "country": "AU",
    "subdivision": "02",
    "timezone": "Australia/Sydney"
  },
  "geometry": {
    "type": "Point",
    "coordinates": [
      145.88036,
      -34.80388
    ]
  }
}