{
  "type": "Feature",
  "properties": {
    "name": "Cremorne",
    "country": "AU",
    "subdivision": "02",
    "timezone": "Australia/Sydney"
  },
  "geometry": {
    "type": "Point",
    "coordinates": [
      151.22633,
      -33.82679
    ]
  }
}