{
  "type": "Feature",
  "properties": {
    "name": "Cronulla",
    "country": "AU",
    "subdivision": "02",
    "timezone": "Australia/Sydney"
  },
  "geometry": {
    "type": "Point",
    "coordinates": [
      151.14961,
      -34.06251
    ]
  }
}