{
  "type": "Feature",
  "properties": {
    "name": "Culburra Beach",
    "country": "AU",
    "subdivision": "02",
    "timezone": "Australia/Sydney"
  },
  "geometry": {
    "type": "Point",
    "coordinates": [
      150.75766,
      -34.92788
    ]
  }
}