{
  "type": "Feature",
  "properties": {
    "name": "Darlington Point",
    "country": "AU",
    "subdivision": "02",
    "timezone": "Australia/Sydney"
  },
  "geometry": {
    "type": "Point",
    "coordinates": [
      145.9987,
      -34.56942
    ]
  }
}