{
  "type": "Feature",
  "properties": {
    "name": "Davistown",
    "country": "AU",
    "subdivision": "02",
    "timezone": "Australia/Sydney"
  },
  "geometry": {
    "type": "Point",
    "coordinates": [
      151.36151,
      -33.48559
    ]
  }
}