{
  "type": "Feature",
  "properties": {
    "name": "Davidson",
    "country": "AU",
    "subdivision": "02",
    "timezone": "Australia/Sydney"
  },
  "geometry": {
    "type": "Point",
    "coordinates": [
      151.2008,
      -33.74297
    ]
  }
}