{
  "type": "Feature",
  "properties": {
    "name": "Dharruk",
    "country": "AU",
    "subdivision": "02",
    "timezone": "Australia/Sydney"
  },
  "geometry": {
    "type": "Point",
    "coordinates": [
      150.81561,
      -33.74814
    ]
  }
}