{
  "type": "Feature",
  "properties": {
    "name": "Dubbo",
    "country": "AU",
    "subdivision": "02",
    "timezone": "Australia/Sydney"
  },
  "geometry": {
    "type": "Point",
    "coordinates": [
      148.60484,
      -32.24295
    ]
  }
}