{
  "type": "Feature",
  "properties": {
    "name": "Eastlakes",
    "country": "AU",
    "subdivision": "02",
    "timezone": "Australia/Sydney"
  },
  "geometry": {
    "type": "Point",
    "coordinates": [
      151.21214,
      -33.93196
    ]
  }
}