{
  "type": "Feature",
  "properties": {
    "name": "East Lindfield",
    "country": "AU",
    "subdivision": "02",
    "timezone": "Australia/Sydney"
  },
  "geometry": {
    "type": "Point",
    "coordinates": [
      151.18685,
      -33.76664
    ]
  }
}