{
  "type": "Feature",
  "properties": {
    "name": "Edensor Park",
    "country": "AU",
    "subdivision": "02",
    "timezone": "Australia/Sydney"
  },
  "geometry": {
    "type": "Point",
    "coordinates": [
      150.87778,
      -33.87971
    ]
  }
}