{
  "type": "Feature",
  "properties": {
    "name": "Edgeworth",
    "country": "AU",
    "subdivision": "02",
    "timezone": "Australia/Sydney"
  },
  "geometry": {
    "type": "Point",
    "coordinates": [
      151.61612,
      -32.92508
    ]
  }
}