{
  "type": "Feature",
  "properties": {
    "name": "Ettalong",
    "country": "AU",
    "subdivision": "02",
    "timezone": "Australia/Sydney"
  },
  "geometry": {
    "type": "Point",
    "coordinates": [
      151.3383,
      -33.51301
    ]
  }
}