{
  "type": "Feature",
  "properties": {
    "name": "Fairfield",
    "country": "AU",
    "subdivision": "02",
    "timezone": "Australia/Sydney"
  },
  "geometry": {
    "type": "Point",
    "coordinates": [
      150.95,
      -33.86667
    ]
  }
}