{
  "type": "Feature",
  "properties": {
    "name": "Farmborough Heights",
    "country": "AU",
    "subdivision": "02",
    "timezone": "Australia/Sydney"
  },
  "geometry": {
    "type": "Point",
    "coordinates": [
      150.81308,
      -34.45499
    ]
  }
}