{
  "type": "Feature",
  "properties": {
    "name": "Floraville",
    "country": "AU",
    "subdivision": "02",
    "timezone": "Australia/Sydney"
  },
  "geometry": {
    "type": "Point",
    "coordinates": [
      151.6648,
      -33.01116
    ]
  }
}