{
  "type": "Feature",
  "properties": {
    "name": "Forbes",
    "country": "AU",
    "subdivision": "02",
    "timezone": "Australia/Sydney"
  },
  "geometry": {
    "type": "Point",
    "coordinates": [
      148.0076,
      -33.38436
    ]
  }
}