{
  "type": "Feature",
  "properties": {
    "name": "Forresters Beach",
    "country": "AU",
    "subdivision": "02",
    "timezone": "Australia/Sydney"
  },
  "geometry": {
    "type": "Point",
    "coordinates": [
      151.476,
      -33.407
    ]
  }
}