{
  "type": "Feature",
  "properties": {
    "name": "Freemans Reach",
    "country": "AU",
    "subdivision": "02",
    "timezone": "Australia/Sydney"
  },
  "geometry": {
    "type": "Point",
    "coordinates": [
      150.79553,
      -33.55794
    ]
  }
}