{
  "type": "Feature",
  "properties": {
    "name": "Granville",
    "country": "AU",
    "subdivision": "02",
    "timezone": "Australia/Sydney"
  },
  "geometry": {
    "type": "Point",
    "coordinates": [
      151.00748,
      -33.8406
    ]
  }
}