{
  "type": "Feature",
  "properties": {
    "name": "Grenfell",
    "country": "AU",
    "subdivision": "02",
    "timezone": "Australia/Sydney"
  },
  "geometry": {
    "type": "Point",
    "coordinates": [
      148.16438,
      -33.89549
    ]
  }
}