{
  "type": "Feature",
  "properties": {
    "name": "Hanwood",
    "country": "AU",
    "subdivision": "02",
    "timezone": "Australia/Sydney"
  },
  "geometry": {
    "type": "Point",
    "coordinates": [
      146.04137,
      -34.33095
    ]
  }
}