{
  "type": "Feature",
  "properties": {
    "name": "Hillvue",
    "country": "AU",
    "subdivision": "02",
    "timezone": "Australia/Sydney"
  },
  "geometry": {
    "type": "Point",
    "coordinates": [
      150.90711,
      -31.12756
    ]
  }
}