{
  "type": "Feature",
  "properties": {
    "name": "Hillsdale",
    "country": "AU",
    "subdivision": "02",
    "timezone": "Australia/Sydney"
  },
  "geometry": {
    "type": "Point",
    "coordinates": [
      151.22784,
      -33.95151
    ]
  }
}