{
  "type": "Feature",
  "properties": {
    "name": "Horningsea Park",
    "country": "AU",
    "subdivision": "02",
    "timezone": "Australia/Sydney"
  },
  "geometry": {
    "type": "Point",
    "coordinates": [
      150.84528,
      -33.94341
    ]
  }
}