{
  "type": "Feature",
  "properties": {
    "name": "Inverell",
    "country": "AU",
    "subdivision": "02",
    "timezone": "Australia/Sydney"
  },
  "geometry": {
    "type": "Point",
    "coordinates": [
      151.11166,
      -29.77403
    ]
  }
}