{
  "type": "Feature",
  "properties": {
    "name": "Kahibah",
    "country": "AU",
    "subdivision": "02",
    "timezone": "Australia/Sydney"
  },
  "geometry": {
    "type": "Point",
    "coordinates": [
      151.71251,
      -32.96175
    ]
  }
}