{
  "type": "Feature",
  "properties": {
    "name": "Kapooka",
    "country": "AU",
    "subdivision": "02",
    "timezone": "Australia/Sydney"
  },
  "geometry": {
    "type": "Point",
    "coordinates": [
      147.28439,
      -35.15693
    ]
  }
}