{
  "type": "Feature",
  "properties": {
    "name": "Kiama",
    "country": "AU",
    "subdivision": "02",
    "timezone": "Australia/Sydney"
  },
  "geometry": {
    "type": "Point",
    "coordinates": [
      150.85219,
      -34.66828
    ]
  }
}