{
  "type": "Feature",
  "properties": {
    "name": "Killarney Heights",
    "country": "AU",
    "subdivision": "02",
    "timezone": "Australia/Sydney"
  },
  "geometry": {
    "type": "Point",
    "coordinates": [
      151.22028,
      -33.77451
    ]
  }
}