{
  "type": "Feature",
  "properties": {
    "name": "Kings Park",
    "country": "AU",
    "subdivision": "02",
    "timezone": "Australia/Sydney"
  },
  "geometry": {
    "type": "Point",
    "coordinates": [
      150.90761,
      -33.7432
    ]
  }
}