{
  "type": "Feature",
  "properties": {
    "name": "Kooringal",
    "country": "AU",
    "subdivision": "02",
    "timezone": "Australia/Sydney"
  },
  "geometry": {
    "type": "Point",
    "coordinates": [
      147.3768,
      -35.14069
    ]
  }
}