{
  "type": "Feature",
  "properties": {
    "name": "Lakelands",
    "country": "AU",
    "subdivision": "02",
    "timezone": "Australia/Sydney"
  },
  "geometry": {
    "type": "Point",
    "coordinates": [
      151.64972,
      -32.96185
    ]
  }
}