{
  "type": "Feature",
  "properties": {
    "name": "Lane Cove",
    "country": "AU",
    "subdivision": "02",
    "timezone": "Australia/Sydney"
  },
  "geometry": {
    "type": "Point",
    "coordinates": [
      151.16679,
      -33.8157
    ]
  }
}