{
  "type": "Feature",
  "properties": {
    "name": "Lansvale",
    "country": "AU",
    "subdivision": "02",
    "timezone": "Australia/Sydney"
  },
  "geometry": {
    "type": "Point",
    "coordinates": [
      150.95078,
      -33.90073
    ]
  }
}