{
  "type": "Feature",
  "properties": {
    "name": "Leeton",
    "country": "AU",
    "subdivision": "02",
    "timezone": "Australia/Sydney"
  },
  "geometry": {
    "type": "Point",
    "coordinates": [
      146.40483,
      -34.55105
    ]
  }
}