{
  "type": "Feature",
  "properties": {
    "name": "Lilyfield",
    "country": "AU",
    "subdivision": "02",
    "timezone": "Australia/Sydney"
  },
  "geometry": {
    "type": "Point",
    "coordinates": [
      151.1653,
      -33.87499
    ]
  }
}