{
  "type": "Feature",
  "properties": {
    "name": "Lithgow",
    "country": "AU",
    "subdivision": "02",
    "timezone": "Australia/Sydney"
  },
  "geometry": {
    "type": "Point",
    "coordinates": [
      150.14903,
      -33.4845
    ]
  }
}