{
  "type": "Feature",
  "properties": {
    "name": "Lockhart",
    "country": "AU",
    "subdivision": "02",
    "timezone": "Australia/Sydney"
  },
  "geometry": {
    "type": "Point",
    "coordinates": [
      146.71816,
      -35.22333
    ]
  }
}