{
  "type": "Feature",
  "properties": {
    "name": "Lugarno",
    "country": "AU",
    "subdivision": "02",
    "timezone": "Australia/Sydney"
  },
  "geometry": {
    "type": "Point",
    "coordinates": [
      151.04184,
      -33.98267
    ]
  }
}