{
  "type": "Feature",
  "properties": {
    "name": "Maclean",
    "country": "AU",
    "subdivision": "02",
    "timezone": "Australia/Sydney"
  },
  "geometry": {
    "type": "Point",
    "coordinates": [
      153.19753,
      -29.4581
    ]
  }
}