{
  "type": "Feature",
  "properties": {
    "name": "Maitland",
    "country": "AU",
    "subdivision": "02",
    "timezone": "Australia/Sydney"
  },
  "geometry": {
    "type": "Point",
    "coordinates": [
      151.5574,
      -32.73308
    ]
  }
}