{
  "type": "Feature",
  "properties": {
    "name": "Malua Bay",
    "country": "AU",
    "subdivision": "02",
    "timezone": "Australia/Sydney"
  },
  "geometry": {
    "type": "Point",
    "coordinates": [
      150.22833,
      -35.79382
    ]
  }
}