{
  "type": "Feature",
  "properties": {
    "name": "Manilla",
    "country": "AU",
    "subdivision": "02",
    "timezone": "Australia/Sydney"
  },
  "geometry": {
    "type": "Point",
    "coordinates": [
      150.71974,
      -30.74748
    ]
  }
}