{
  "type": "Feature",
  "properties": {
    "name": "Marayong",
    "country": "AU",
    "subdivision": "02",
    "timezone": "Australia/Sydney"
  },
  "geometry": {
    "type": "Point",
    "coordinates": [
      150.89272,
      -33.74824
    ]
  }
}