{
  "type": "Feature",
  "properties": {
    "name": "Marulan",
    "country": "AU",
    "subdivision": "02",
    "timezone": "Australia/Sydney"
  },
  "geometry": {
    "type": "Point",
    "coordinates": [
      150.00966,
      -34.70836
    ]
  }
}