{
  "type": "Feature",
  "properties": {
    "name": "Menangle",
    "country": "AU",
    "subdivision": "02",
    "timezone": "Australia/Sydney"
  },
  "geometry": {
    "type": "Point",
    "coordinates": [
      150.73868,
      -34.12675
    ]
  }
}