{
  "type": "Feature",
  "properties": {
    "name": "Merewether Heights",
    "country": "AU",
    "subdivision": "02",
    "timezone": "Australia/Sydney"
  },
  "geometry": {
    "type": "Point",
    "coordinates": [
      151.73565,
      -32.94733
    ]
  }
}