{
  "type": "Feature",
  "properties": {
    "name": "Merrylands West",
    "country": "AU",
    "subdivision": "02",
    "timezone": "Australia/Sydney"
  },
  "geometry": {
    "type": "Point",
    "coordinates": [
      150.96906,
      -33.83269
    ]
  }
}