{
  "type": "Feature",
  "properties": {
    "name": "Miller",
    "country": "AU",
    "subdivision": "02",
    "timezone": "Australia/Sydney"
  },
  "geometry": {
    "type": "Point",
    "coordinates": [
      150.88469,
      -33.92089
    ]
  }
}