{
  "type": "Feature",
  "properties": {
    "name": "Mitchell",
    "country": "AU",
    "subdivision": "02",
    "timezone": "Australia/Sydney"
  },
  "geometry": {
    "type": "Point",
    "coordinates": [
      149.55674,
      -33.42732
    ]
  }
}