{
  "type": "Feature",
  "properties": {
    "name": "Mollymook Beach",
    "country": "AU",
    "subdivision": "02",
    "timezone": "Australia/Sydney"
  },
  "geometry": {
    "type": "Point",
    "coordinates": [
      150.47173,
      -35.32966
    ]
  }
}