{
  "type": "Feature",
  "properties": {
    "name": "Moss Vale",
    "country": "AU",
    "subdivision": "02",
    "timezone": "Australia/Sydney"
  },
  "geometry": {
    "type": "Point",
    "coordinates": [
      150.37115,
      -34.55374
    ]
  }
}