{
  "type": "Feature",
  "properties": {
    "name": "Mount Druitt",
    "country": "AU",
    "subdivision": "02",
    "timezone": "Australia/Sydney"
  },
  "geometry": {
    "type": "Point",
    "coordinates": [
      150.81667,
      -33.76667
    ]
  }
}