{
  "type": "Feature",
  "properties": {
    "name": "Mount Riverview",
    "country": "AU",
    "subdivision": "02",
    "timezone": "Australia/Sydney"
  },
  "geometry": {
    "type": "Point",
    "coordinates": [
      150.63532,
      -33.73074
    ]
  }
}