{
  "type": "Feature",
  "properties": {
    "name": "Mulwala",
    "country": "AU",
    "subdivision": "02",
    "timezone": "Australia/Sydney"
  },
  "geometry": {
    "type": "Point",
    "coordinates": [
      146.00534,
      -35.98536
    ]
  }
}