{
  "type": "Feature",
  "properties": {
    "name": "Murrurundi",
    "country": "AU",
    "subdivision": "02",
    "timezone": "Australia/Sydney"
  },
  "geometry": {
    "type": "Point",
    "coordinates": [
      150.83575,
      -31.76422
    ]
  }
}