{
  "type": "Feature",
  "properties": {
    "name": "Murwillumbah",
    "country": "AU",
    "subdivision": "02",
    "timezone": "Australia/Sydney"
  },
  "geometry": {
    "type": "Point",
    "coordinates": [
      153.39339,
      -28.32732
    ]
  }
}