{
  "type": "Feature",
  "properties": {
    "name": "Nambucca Heads",
    "country": "AU",
    "subdivision": "02",
    "timezone": "Australia/Sydney"
  },
  "geometry": {
    "type": "Point",
    "coordinates": [
      153.00884,
      -30.64318
    ]
  }
}