{
  "type": "Feature",
  "properties": {
    "name": "Narrandera",
    "country": "AU",
    "subdivision": "02",
    "timezone": "Australia/Sydney"
  },
  "geometry": {
    "type": "Point",
    "coordinates": [
      146.55096,
      -34.74752
    ]
  }
}