{
  "type": "Feature",
  "properties": {
    "name": "Narromine",
    "country": "AU",
    "subdivision": "02",
    "timezone": "Australia/Sydney"
  },
  "geometry": {
    "type": "Point",
    "coordinates": [
      148.24052,
      -32.23121
    ]
  }
}