{
  "type": "Feature",
  "properties": {
    "name": "Neutral Bay",
    "country": "AU",
    "subdivision": "02",
    "timezone": "Australia/Sydney"
  },
  "geometry": {
    "type": "Point",
    "coordinates": [
      151.2175,
      -33.83784
    ]
  }
}