{
  "type": "Feature",
  "properties": {
    "name": "Newcastle",
    "country": "AU",
    "subdivision": "02",
    "timezone": "Australia/Sydney"
  },
  "geometry": {
    "type": "Point",
    "coordinates": [
      151.7801,
      -32.92953
    ]
  }
}