{
  "type": "Feature",
  "properties": {
    "name": "North Willoughby",
    "country": "AU",
    "subdivision": "02",
    "timezone": "Australia/Sydney"
  },
  "geometry": {
    "type": "Point",
    "coordinates": [
      151.20067,
      -33.79563
    ]
  }
}