{
  "type": "Feature",
  "properties": {
    "name": "North Strathfield",
    "country": "AU",
    "subdivision": "02",
    "timezone": "Australia/Sydney"
  },
  "geometry": {
    "type": "Point",
    "coordinates": [
      151.09124,
      -33.85693
    ]
  }
}