{
  "type": "Feature",
  "properties": {
    "name": "North Curl Curl",
    "country": "AU",
    "subdivision": "02",
    "timezone": "Australia/Sydney"
  },
  "geometry": {
    "type": "Point",
    "coordinates": [
      151.29727,
      -33.76434
    ]
  }
}