{
  "type": "Feature",
  "properties": {
    "name": "Oatley",
    "country": "AU",
    "subdivision": "02",
    "timezone": "Australia/Sydney"
  },
  "geometry": {
    "type": "Point",
    "coordinates": [
      151.07201,
      -33.98004
    ]
  }
}