{
  "type": "Feature",
  "properties": {
    "name": "Ocean Shores",
    "country": "AU",
    "subdivision": "02",
    "timezone": "Australia/Sydney"
  },
  "geometry": {
    "type": "Point",
    "coordinates": [
      153.5376,
      -28.5093
    ]
  }
}