{
  "type": "Feature",
  "properties": {
    "name": "Picnic Point",
    "country": "AU",
    "subdivision": "02",
    "timezone": "Australia/Sydney"
  },
  "geometry": {
    "type": "Point",
    "coordinates": [
      150.99661,
      -33.98062
    ]
  }
}