{
  "type": "Feature",
  "properties": {
    "name": "Pitt Town",
    "country": "AU",
    "subdivision": "02",
    "timezone": "Australia/Sydney"
  },
  "geometry": {
    "type": "Point",
    "coordinates": [
      150.85857,
      -33.58718
    ]
  }
}