{
  "type": "Feature",
  "properties": {
    "name": "Portland",
    "country": "AU",
    "subdivision": "02",
    "timezone": "Australia/Sydney"
  },
  "geometry": {
    "type": "Point",
    "coordinates": [
      149.98148,
      -33.35709
    ]
  }
}