{
  "type": "Feature",
  "properties": {
    "name": "Pottsville Beach",
    "country": "AU",
    "subdivision": "02",
    "timezone": "Australia/Sydney"
  },
  "geometry": {
    "type": "Point",
    "coordinates": [
      153.56564,
      -28.38853
    ]
  }
}