{
  "type": "Feature",
  "properties": {
    "name": "Primbee",
    "country": "AU",
    "subdivision": "02",
    "timezone": "Australia/Sydney"
  },
  "geometry": {
    "type": "Point",
    "coordinates": [
      150.8795,
      -34.50358
    ]
  }
}