{
  "type": "Feature",
  "properties": {
    "name": "Razorback",
    "country": "AU",
    "subdivision": "02",
    "timezone": "Australia/Sydney"
  },
  "geometry": {
    "type": "Point",
    "coordinates": [
      150.65308,
      -34.15237
    ]
  }
}