{
  "type": "Feature",
  "properties": {
    "name": "Ruse",
    "country": "AU",
    "subdivision": "02",
    "timezone": "Australia/Sydney"
  },
  "geometry": {
    "type": "Point",
    "coordinates": [
      150.84168,
      -34.06976
    ]
  }
}