{
  "type": "Feature",
  "properties": {
    "name": "Salamander Bay",
    "country": "AU",
    "subdivision": "02",
    "timezone": "Australia/Sydney"
  },
  "geometry": {
    "type": "Point",
    "coordinates": [
      152.07945,
      -32.72253
    ]
  }
}