{
  "type": "Feature",
  "properties": {
    "name": "Shellharbour",
    "country": "AU",
    "subdivision": "02",
    "timezone": "Australia/Sydney"
  },
  "geometry": {
    "type": "Point",
    "coordinates": [
      150.86667,
      -34.58333
    ]
  }
}