{
  "type": "Feature",
  "properties": {
    "name": "Silverdale",
    "country": "AU",
    "subdivision": "02",
    "timezone": "Australia/Sydney"
  },
  "geometry": {
    "type": "Point",
    "coordinates": [
      150.6096,
      -33.9152
    ]
  }
}