{
  "type": "Feature",
  "properties": {
    "name": "Skennars Head",
    "country": "AU",
    "subdivision": "02",
    "timezone": "Australia/Sydney"
  },
  "geometry": {
    "type": "Point",
    "coordinates": [
      153.60209,
      -28.82888
    ]
  }
}