{
  "type": "Feature",
  "properties": {
    "name": "Smithfield",
    "country": "AU",
    "subdivision": "02",
    "timezone": "Australia/Sydney"
  },
  "geometry": {
    "type": "Point",
    "coordinates": [
      150.93333,
      -33.85
    ]
  }
}