{
  "type": "Feature",
  "properties": {
    "name": "South Hurstville",
    "country": "AU",
    "subdivision": "02",
    "timezone": "Australia/Sydney"
  },
  "geometry": {
    "type": "Point",
    "coordinates": [
      151.1055,
      -33.97756
    ]
  }
}