{
  "type": "Feature",
  "properties": {
    "name": "South Penrith",
    "country": "AU",
    "subdivision": "02",
    "timezone": "Australia/Sydney"
  },
  "geometry": {
    "type": "Point",
    "coordinates": [
      150.69466,
      -33.77349
    ]
  }
}