{
  "type": "Feature",
  "properties": {
    "name": "Spring Farm",
    "country": "AU",
    "subdivision": "02",
    "timezone": "Australia/Sydney"
  },
  "geometry": {
    "type": "Point",
    "coordinates": [
      150.71182,
      -34.06851
    ]
  }
}