{
  "type": "Feature",
  "properties": {
    "name": "Springvale",
    "country": "AU",
    "subdivision": "02",
    "timezone": "Australia/Sydney"
  },
  "geometry": {
    "type": "Point",
    "coordinates": [
      147.33058,
      -35.16687
    ]
  }
}