{
  "type": "Feature",
  "properties": {
    "name": "St Andrews",
    "country": "AU",
    "subdivision": "02",
    "timezone": "Australia/Sydney"
  },
  "geometry": {
    "type": "Point",
    "coordinates": [
      150.82958,
      -34.02243
    ]
  }
}