{
  "type": "Feature",
  "properties": {
    "name": "Swansea",
    "country": "AU",
    "subdivision": "02",
    "timezone": "Australia/Sydney"
  },
  "geometry": {
    "type": "Point",
    "coordinates": [
      151.63745,
      -33.08765
    ]
  }
}