{
  "type": "Feature",
  "properties": {
    "name": "Terranora",
    "country": "AU",
    "subdivision": "02",
    "timezone": "Australia/Sydney"
  },
  "geometry": {
    "type": "Point",
    "coordinates": [
      153.50078,
      -28.23832
    ]
  }
}