{
  "type": "Feature",
  "properties": {
    "name": "Thirroul",
    "country": "AU",
    "subdivision": "02",
    "timezone": "Australia/Sydney"
  },
  "geometry": {
    "type": "Point",
    "coordinates": [
      150.92142,
      -34.31604
    ]
  }
}