{
  "type": "Feature",
  "properties": {
    "name": "Tomakin",
    "country": "AU",
    "subdivision": "02",
    "timezone": "Australia/Sydney"
  },
  "geometry": {
    "type": "Point",
    "coordinates": [
      150.18794,
      -35.82335
    ]
  }
}