{
  "type": "Feature",
  "properties": {
    "name": "Towradgi",
    "country": "AU",
    "subdivision": "02",
    "timezone": "Australia/Sydney"
  },
  "geometry": {
    "type": "Point",
    "coordinates": [
      150.90278,
      -34.38667
    ]
  }
}