{
  "type": "Feature",
  "properties": {
    "name": "Tura Beach",
    "country": "AU",
    "subdivision": "02",
    "timezone": "Australia/Sydney"
  },
  "geometry": {
    "type": "Point",
    "coordinates": [
      149.93027,
      -36.86358
    ]
  }
}