{
  "type": "Feature",
  "properties": {
    "name": "Turramurra",
    "country": "AU",
    "subdivision": "02",
    "timezone": "Australia/Sydney"
  },
  "geometry": {
    "type": "Point",
    "coordinates": [
      151.12849,
      -33.73342
    ]
  }
}