{
  "type": "Feature",
  "properties": {
    "name": "Tweed Heads South",
    "country": "AU",
    "subdivision": "02",
    "timezone": "Australia/Sydney"
  },
  "geometry": {
    "type": "Point",
    "coordinates": [
      153.53964,
      -28.19517
    ]
  }
}