{
  "type": "Feature",
  "properties": {
    "name": "Warrawee",
    "country": "AU",
    "subdivision": "02",
    "timezone": "Australia/Sydney"
  },
  "geometry": {
    "type": "Point",
    "coordinates": [
      151.12051,
      -33.72884
    ]
  }
}