{
  "type": "Feature",
  "properties": {
    "name": "Wellington",
    "country": "AU",
    "subdivision": "02",
    "timezone": "Australia/Sydney"
  },
  "geometry": {
    "type": "Point",
    "coordinates": [
      148.94508,
      -32.55588
    ]
  }
}