{
  "type": "Feature",
  "properties": {
    "name": "Werris Creek",
    "country": "AU",
    "subdivision": "02",
    "timezone": "Australia/Sydney"
  },
  "geometry": {
    "type": "Point",
    "coordinates": [
      150.6487,
      -31.34908
    ]
  }
}