{
  "type": "Feature",
  "properties": {
    "name": "West Ryde",
    "country": "AU",
    "subdivision": "02",
    "timezone": "Australia/Sydney"
  },
  "geometry": {
    "type": "Point",
    "coordinates": [
      151.07386,
      -33.80543
    ]
  }
}