{
  "type": "Feature",
  "properties": {
    "name": "West Kempsey",
    "country": "AU",
    "subdivision": "02",
    "timezone": "Australia/Sydney"
  },
  "geometry": {
    "type": "Point",
    "coordinates": [
      152.82794,
      -31.05757
    ]
  }
}