{
  "type": "Feature",
  "properties": {
    "name": "Woodberry",
    "country": "AU",
    "subdivision": "02",
    "timezone": "Australia/Sydney"
  },
  "geometry": {
    "type": "Point",
    "coordinates": [
      151.67687,
      -32.79311
    ]
  }
}