{
  "type": "Feature",
  "properties": {
    "name": "Woodrising",
    "country": "AU",
    "subdivision": "02",
    "timezone": "Australia/Sydney"
  },
  "geometry": {
    "type": "Point",
    "coordinates": [
      151.60657,
      -32.98595
    ]
  }
}