{
  "type": "Feature",
  "properties": {
    "name": "Woolloomooloo",
    "country": "AU",
    "subdivision": "02",
    "timezone": "Australia/Sydney"
  },
  "geometry": {
    "type": "Point",
    "coordinates": [
      151.21968,
      -33.87042
    ]
  }
}