{
  "type": "Feature",
  "properties": {
    "name": "Woongarrah",
    "country": "AU",
    "subdivision": "02",
    "timezone": "Australia/Sydney"
  },
  "geometry": {
    "type": "Point",
    "coordinates": [
      151.47563,
      -33.24134
    ]
  }
}