{
  "type": "Feature",
  "properties": {
    "name": "Yowie Bay",
    "country": "AU",
    "subdivision": "02",
    "timezone": "Australia/Sydney"
  },
  "geometry": {
    "type": "Point",
    "coordinates": [
      151.10228,
      -34.05116
    ]
  }
}