{
  "type": "Feature",
  "properties": {
    "name": "Arpaçay",
    "country": "TR",
    "subdivision": "84",
    "timezone": "Europe/Istanbul"
  },
  "geometry": {
    "type": "Point",
    "coordinates": [
      43.32747,
      40.84522
    ]
  }
}