{
  "type": "Feature",
  "properties": {
    "name": "Aseri",
    "country": "EE",
    "subdivision": "08",
    "timezone": "Europe/Tallinn"
  },
  "geometry": {
    "type": "Point",
    "coordinates": [
      26.87163,
      59.45256
    ]
  }
}