{
  "type": "Feature",
  "properties": {
    "name": "Champerico",
    "country": "GT",
    "subdivision": "15",
    "timezone": "America/Guatemala"
  },
  "geometry": {
    "type": "Point",
    "coordinates": [
      -91.91214,
      14.29337
    ]
  }
}