{
  "type": "Feature",
  "properties": {
    "name": "El Asintal",
    "country": "GT",
    "subdivision": "15",
    "timezone": "America/Guatemala"
  },
  "geometry": {
    "type": "Point",
    "coordinates": [
      -91.72744,
      14.59626
    ]
  }
}