{
  "type": "Feature",
  "properties": {
    "name": "Retalhuleu",
    "country": "GT",
    "subdivision": "15",
    "timezone": "America/Guatemala"
  },
  "geometry": {
    "type": "Point",
    "coordinates": [
      -91.67778,
      14.53611
    ]
  }
}