{
  "type": "Feature",
  "properties": {
    "name": "Santa Cruz Muluá",
    "country": "GT",
    "subdivision": "15",
    "timezone": "America/Guatemala"
  },
  "geometry": {
    "type": "Point",
    "coordinates": [
      -91.62441,
      14.58153
    ]
  }
}