{
  "type": "Feature",
  "properties": {
    "name": "Anacleto Canabal 3ra. Sección",
    "country": "MX",
    "subdivision": "27",
    "timezone": "America/Mexico_City"
  },
  "geometry": {
    "type": "Point",
    "coordinates": [
      -92.98992,
      18.0183
    ]
  }
}