{
  "type": "Feature",
  "properties": {
    "name": "Aquiles Serdán",
    "country": "MX",
    "subdivision": "27",
    "timezone": "America/Mexico_City"
  },
  "geometry": {
    "type": "Point",
    "coordinates": [
      -92.28333,
      17.78333
    ]
  }
}