{
  "type": "Feature",
  "properties": {
    "name": "Barrancas y Amate 3ra. Sección",
    "country": "MX",
    "subdivision": "27",
    "timezone": "America/Mexico_City"
  },
  "geometry": {
    "type": "Point",
    "coordinates": [
      -92.76173,
      17.971
    ]
  }
}