{
  "type": "Feature",
  "properties": {
    "name": "Benito Juárez (La Playita)",
    "country": "MX",
    "subdivision": "27",
    "timezone": "America/Mexico_City"
  },
  "geometry": {
    "type": "Point",
    "coordinates": [
      -93.36472,
      17.93231
    ]
  }
}