{
  "type": "Feature",
  "properties": {
    "name": "C-32 (Licenciado Francisco Trujillo Gurría)",
    "country": "MX",
    "subdivision": "27",
    "timezone": "America/Mexico_City"
  },
  "geometry": {
    "type": "Point",
    "coordinates": [
      -93.50139,
      17.96833
    ]
  }
}