{
  "type": "Feature",
  "properties": {
    "name": "Cunduacán",
    "country": "MX",
    "subdivision": "27",
    "timezone": "America/Mexico_City"
  },
  "geometry": {
    "type": "Point",
    "coordinates": [
      -93.17302,
      18.06557
    ]
  }
}