{
  "type": "Feature",
  "properties": {
    "name": "General Luis Felipe Domínguez Suárez",
    "country": "MX",
    "subdivision": "27",
    "timezone": "America/Mexico_City"
  },
  "geometry": {
    "type": "Point",
    "coordinates": [
      -91.53667,
      17.65639
    ]
  }
}