{
  "type": "Feature",
  "properties": {
    "name": "Gregorio Méndez",
    "country": "MX",
    "subdivision": "27",
    "timezone": "America/Mexico_City"
  },
  "geometry": {
    "type": "Point",
    "coordinates": [
      -93.08472,
      18.04694
    ]
  }
}