{
  "type": "Feature",
  "properties": {
    "name": "Guatacalca",
    "country": "MX",
    "subdivision": "27",
    "timezone": "America/Mexico_City"
  },
  "geometry": {
    "type": "Point",
    "coordinates": [
      -92.97871,
      18.16599
    ]
  }
}