{
  "type": "Feature",
  "properties": {
    "name": "Jiménez",
    "country": "MX",
    "subdivision": "27",
    "timezone": "America/Mexico_City"
  },
  "geometry": {
    "type": "Point",
    "coordinates": [
      -92.93336,
      18.16043
    ]
  }
}