{
  "type": "Feature",
  "properties": {
    "name": "La Península",
    "country": "MX",
    "subdivision": "27",
    "timezone": "America/Mexico_City"
  },
  "geometry": {
    "type": "Point",
    "coordinates": [
      -93.36148,
      17.94347
    ]
  }
}