{
  "type": "Feature",
  "properties": {
    "name": "Los Cenotes",
    "country": "MX",
    "subdivision": "27",
    "timezone": "America/Mexico_City"
  },
  "geometry": {
    "type": "Point",
    "coordinates": [
      -91.03759,
      17.63461
    ]
  }
}