{
  "type": "Feature",
  "properties": {
    "name": "Macuspana",
    "country": "MX",
    "subdivision": "27",
    "timezone": "America/Mexico_City"
  },
  "geometry": {
    "type": "Point",
    "coordinates": [
      -92.59539,
      17.76052
    ]
  }
}