{
  "type": "Feature",
  "properties": {
    "name": "Occidente (San Francisco)",
    "country": "MX",
    "subdivision": "27",
    "timezone": "America/Mexico_City"
  },
  "geometry": {
    "type": "Point",
    "coordinates": [
      -93.25238,
      18.3313
    ]
  }
}