{
  "type": "Feature",
  "properties": {
    "name": "Rancho Nuevo",
    "country": "MX",
    "subdivision": "27",
    "timezone": "America/Mexico_City"
  },
  "geometry": {
    "type": "Point",
    "coordinates": [
      -93.07252,
      18.07201
    ]
  }
}