{
  "type": "Feature",
  "properties": {
    "name": "San Carlos",
    "country": "MX",
    "subdivision": "27",
    "timezone": "America/Mexico_City"
  },
  "geometry": {
    "type": "Point",
    "coordinates": [
      -91.15408,
      17.55221
    ]
  }
}