{
  "type": "Feature",
  "properties": {
    "name": "Taxco",
    "country": "MX",
    "subdivision": "27",
    "timezone": "America/Mexico_City"
  },
  "geometry": {
    "type": "Point",
    "coordinates": [
      -93.00528,
      18.13917
    ]
  }
}