{
  "type": "Feature",
  "properties": {
    "name": "Tucta",
    "country": "MX",
    "subdivision": "27",
    "timezone": "America/Mexico_City"
  },
  "geometry": {
    "type": "Point",
    "coordinates": [
      -92.99535,
      18.19346
    ]
  }
}