{
  "type": "Feature",
  "properties": {
    "name": "Villa Vicente Guerrero",
    "country": "MX",
    "subdivision": "27",
    "timezone": "America/Mexico_City"
  },
  "geometry": {
    "type": "Point",
    "coordinates": [
      -92.89607,
      18.39007
    ]
  }
}