{
  "type": "Feature",
  "properties": {
    "name": "Villa Tecolutilla",
    "country": "MX",
    "subdivision": "27",
    "timezone": "America/Mexico_City"
  },
  "geometry": {
    "type": "Point",
    "coordinates": [
      -93.33398,
      18.28338
    ]
  }
}