{
  "type": "Feature",
  "properties": {
    "name": "Golyshmanovo",
    "country": "RU",
    "subdivision": "78",
    "timezone": "Asia/Yekaterinburg"
  },
  "geometry": {
    "type": "Point",
    "coordinates": [
      68.37279,
      56.3979
    ]
  }
}