{
  "type": "Feature",
  "properties": {
    "name": "Novoseleznëvo",
    "country": "RU",
    "subdivision": "78",
    "timezone": "Asia/Yekaterinburg"
  },
  "geometry": {
    "type": "Point",
    "coordinates": [
      69.20562,
      55.68207
    ]
  }
}