{
  "type": "Feature",
  "properties": {
    "name": "Vagay",
    "country": "RU",
    "subdivision": "78",
    "timezone": "Asia/Yekaterinburg"
  },
  "geometry": {
    "type": "Point",
    "coordinates": [
      69.01953,
      57.93566
    ]
  }
}