{
  "type": "Feature",
  "properties": {
    "name": "Yalutorovsk",
    "country": "RU",
    "subdivision": "78",
    "timezone": "Asia/Yekaterinburg"
  },
  "geometry": {
    "type": "Point",
    "coordinates": [
      66.30057,
      56.65358
    ]
  }
}