{
  "type": "Feature",
  "properties": {
    "name": "Chaiya",
    "country": "TH",
    "subdivision": "60",
    "timezone": "Asia/Bangkok"
  },
  "geometry": {
    "type": "Point",
    "coordinates": [
      99.19861,
      9.38625
    ]
  }
}