{
  "type": "Feature",
  "properties": {
    "name": "Ko Samui",
    "country": "TH",
    "subdivision": "60",
    "timezone": "Asia/Bangkok"
  },
  "geometry": {
    "type": "Point",
    "coordinates": [
      99.93567,
      9.53567
    ]
  }
}