{
  "type": "Feature",
  "properties": {
    "name": "Angren",
    "country": "UZ",
    "subdivision": "14",
    "timezone": "Asia/Tashkent"
  },
  "geometry": {
    "type": "Point",
    "coordinates": [
      70.14361,
      41.01667
    ]
  }
}