{
  "type": "Feature",
  "properties": {
    "name": "Qibray",
    "country": "UZ",
    "subdivision": "14",
    "timezone": "Asia/Tashkent"
  },
  "geometry": {
    "type": "Point",
    "coordinates": [
      69.465,
      41.38972
    ]
  }
}