{
  "type": "Feature",
  "properties": {
    "name": "Yangiobod",
    "country": "UZ",
    "subdivision": "14",
    "timezone": "Asia/Tashkent"
  },
  "geometry": {
    "type": "Point",
    "coordinates": [
      70.09406,
      41.11919
    ]
  }
}