{
  "type": "Feature",
  "properties": {
    "name": "Koani",
    "country": "TZ",
    "subdivision": "21",
    "timezone": "Africa/Dar_es_Salaam"
  },
  "geometry": {
    "type": "Point",
    "coordinates": [
      39.28333,
      -6.13333
    ]
  }
}