{
  "type": "Feature",
  "properties": {
    "name": "Bucovăţ",
    "country": "MD",
    "subdivision": "89",
    "timezone": "Europe/Chisinau"
  },
  "geometry": {
    "type": "Point",
    "coordinates": [
      28.45802,
      47.19064
    ]
  }
}