{
  "type": "Feature",
  "properties": {
    "name": "Tosu",
    "country": "JP",
    "subdivision": "33",
    "timezone": "Asia/Tokyo"
  },
  "geometry": {
    "type": "Point",
    "coordinates": [
      130.51667,
      33.36667
    ]
  }
}