{
  "type": "Feature",
  "properties": {
    "name": "Anūch",
    "country": "IR",
    "subdivision": "09",
    "timezone": "Asia/Tehran"
  },
  "geometry": {
    "type": "Point",
    "coordinates": [
      48.57375,
      34.10829
    ]
  }
}