{
  "type": "Feature",
  "properties": {
    "name": "Asadābād",
    "country": "IR",
    "subdivision": "09",
    "timezone": "Asia/Tehran"
  },
  "geometry": {
    "type": "Point",
    "coordinates": [
      48.12012,
      34.78241
    ]
  }
}