{
  "type": "Feature",
  "properties": {
    "name": "BahÄr",
    "country": "IR",
    "subdivision": "09",
    "timezone": "Asia/Tehran"
  },
  "geometry": {
    "type": "Point",
    "coordinates": [
      48.4414,
      34.9072
    ]
  }
}