{
  "type": "Feature",
  "properties": {
    "name": "Famast",
    "country": "IR",
    "subdivision": "09",
    "timezone": "Asia/Tehran"
  },
  "geometry": {
    "type": "Point",
    "coordinates": [
      48.4626,
      34.03897
    ]
  }
}