{
  "type": "Feature",
  "properties": {
    "name": "HamadÄn",
    "country": "IR",
    "subdivision": "09",
    "timezone": "Asia/Tehran"
  },
  "geometry": {
    "type": "Point",
    "coordinates": [
      48.51456,
      34.79922
    ]
  }
}