{
  "type": "Feature",
  "properties": {
    "name": "pamas",
    "country": "IR",
    "subdivision": "09",
    "timezone": "Asia/Tehran"
  },
  "geometry": {
    "type": "Point",
    "coordinates": [
      48.462,
      34.03791
    ]
  }
}