{
  "type": "Feature",
  "properties": {
    "name": "Mumford",
    "country": "GH",
    "subdivision": "04",
    "timezone": "Africa/Accra"
  },
  "geometry": {
    "type": "Point",
    "coordinates": [
      -0.75897,
      5.26176
    ]
  }
}