{
  "type": "Feature",
  "properties": {
    "name": "Swedru",
    "country": "GH",
    "subdivision": "04",
    "timezone": "Africa/Accra"
  },
  "geometry": {
    "type": "Point",
    "coordinates": [
      -0.69984,
      5.53711
    ]
  }
}