{
  "type": "Feature",
  "properties": {
    "name": "Chełmża",
    "country": "PL",
    "subdivision": "73",
    "timezone": "Europe/Warsaw"
  },
  "geometry": {
    "type": "Point",
    "coordinates": [
      18.60466,
      53.18463
    ]
  }
}