{
  "type": "Feature",
  "properties": {
    "name": "Dąbrowa",
    "country": "PL",
    "subdivision": "73",
    "timezone": "Europe/Warsaw"
  },
  "geometry": {
    "type": "Point",
    "coordinates": [
      17.94342,
      52.74668
    ]
  }
}