{
  "type": "Feature",
  "properties": {
    "name": "Fordon",
    "country": "PL",
    "subdivision": "73",
    "timezone": "Europe/Warsaw"
  },
  "geometry": {
    "type": "Point",
    "coordinates": [
      18.17036,
      53.14821
    ]
  }
}