{
  "type": "Feature",
  "properties": {
    "name": "Kikół",
    "country": "PL",
    "subdivision": "73",
    "timezone": "Europe/Warsaw"
  },
  "geometry": {
    "type": "Point",
    "coordinates": [
      19.12016,
      52.90994
    ]
  }
}