{
  "type": "Feature",
  "properties": {
    "name": "Nakło nad Notecią",
    "country": "PL",
    "subdivision": "73",
    "timezone": "Europe/Warsaw"
  },
  "geometry": {
    "type": "Point",
    "coordinates": [
      17.60181,
      53.14214
    ]
  }
}