{
  "type": "Feature",
  "properties": {
    "name": "Solec Kujawski",
    "country": "PL",
    "subdivision": "73",
    "timezone": "Europe/Warsaw"
  },
  "geometry": {
    "type": "Point",
    "coordinates": [
      18.22572,
      53.08371
    ]
  }
}