{
  "type": "Feature",
  "properties": {
    "name": "Tuchola",
    "country": "PL",
    "subdivision": "73",
    "timezone": "Europe/Warsaw"
  },
  "geometry": {
    "type": "Point",
    "coordinates": [
      17.85905,
      53.58792
    ]
  }
}