{
  "type": "Feature",
  "properties": {
    "name": "Tłuchowo",
    "country": "PL",
    "subdivision": "73",
    "timezone": "Europe/Warsaw"
  },
  "geometry": {
    "type": "Point",
    "coordinates": [
      19.46563,
      52.74715
    ]
  }
}