{
  "type": "Feature",
  "properties": {
    "name": "Unisław",
    "country": "PL",
    "subdivision": "73",
    "timezone": "Europe/Warsaw"
  },
  "geometry": {
    "type": "Point",
    "coordinates": [
      18.38622,
      53.21241
    ]
  }
}