{
  "type": "Feature",
  "properties": {
    "name": "Warlubie",
    "country": "PL",
    "subdivision": "73",
    "timezone": "Europe/Warsaw"
  },
  "geometry": {
    "type": "Point",
    "coordinates": [
      18.63444,
      53.58751
    ]
  }
}