{
  "type": "Feature",
  "properties": {
    "name": "Łabiszyn",
    "country": "PL",
    "subdivision": "73",
    "timezone": "Europe/Warsaw"
  },
  "geometry": {
    "type": "Point",
    "coordinates": [
      17.91971,
      52.9521
    ]
  }
}