{
  "type": "Feature",
  "properties": {
    "name": "Çaycuma",
    "country": "TR",
    "subdivision": "85",
    "timezone": "Europe/Istanbul"
  },
  "geometry": {
    "type": "Point",
    "coordinates": [
      32.07556,
      41.42639
    ]
  }
}