{
  "type": "Feature",
  "properties": {
    "name": "Caldas das Taipas",
    "country": "PT",
    "subdivision": "04",
    "timezone": "Europe/Lisbon"
  },
  "geometry": {
    "type": "Point",
    "coordinates": [
      -8.3485,
      41.48465
    ]
  }
}