{
  "type": "Feature",
  "properties": {
    "name": "Cristelo",
    "country": "PT",
    "subdivision": "04",
    "timezone": "Europe/Lisbon"
  },
  "geometry": {
    "type": "Point",
    "coordinates": [
      -8.69785,
      41.47964
    ]
  }
}