{
  "type": "Feature",
  "properties": {
    "name": "Fafe",
    "country": "PT",
    "subdivision": "04",
    "timezone": "Europe/Lisbon"
  },
  "geometry": {
    "type": "Point",
    "coordinates": [
      -8.17258,
      41.45083
    ]
  }
}