{
  "type": "Feature",
  "properties": {
    "name": "Gandra",
    "country": "PT",
    "subdivision": "04",
    "timezone": "Europe/Lisbon"
  },
  "geometry": {
    "type": "Point",
    "coordinates": [
      -8.76185,
      41.52185
    ]
  }
}