{
  "type": "Feature",
  "properties": {
    "name": "Real",
    "country": "PT",
    "subdivision": "04",
    "timezone": "Europe/Lisbon"
  },
  "geometry": {
    "type": "Point",
    "coordinates": [
      -8.4433,
      41.55841
    ]
  }
}