{
  "type": "Feature",
  "properties": {
    "name": "Ribeirão",
    "country": "PT",
    "subdivision": "04",
    "timezone": "Europe/Lisbon"
  },
  "geometry": {
    "type": "Point",
    "coordinates": [
      -8.56774,
      41.36081
    ]
  }
}