{
  "type": "Feature",
  "properties": {
    "name": "Vilaça",
    "country": "PT",
    "subdivision": "04",
    "timezone": "Europe/Lisbon"
  },
  "geometry": {
    "type": "Point",
    "coordinates": [
      -8.48357,
      41.51787
    ]
  }
}