{
  "type": "Feature",
  "properties": {
    "name": "Vila Cova",
    "country": "PT",
    "subdivision": "04",
    "timezone": "Europe/Lisbon"
  },
  "geometry": {
    "type": "Point",
    "coordinates": [
      -8.71645,
      41.55107
    ]
  }
}