{
  "type": "Feature",
  "properties": {
    "name": "Juankoski",
    "country": "FI",
    "subdivision": "11",
    "timezone": "Europe/Helsinki"
  },
  "geometry": {
    "type": "Point",
    "coordinates": [
      28.35,
      63.06667
    ]
  }
}