{
  "type": "Feature",
  "properties": {
    "name": "Tervo",
    "country": "FI",
    "subdivision": "11",
    "timezone": "Europe/Helsinki"
  },
  "geometry": {
    "type": "Point",
    "coordinates": [
      26.75,
      62.95
    ]
  }
}