{
  "type": "Feature",
  "properties": {
    "name": "PehÄevo",
    "country": "MK",
    "subdivision": "78",
    "timezone": "Europe/Skopje"
  },
  "geometry": {
    "type": "Point",
    "coordinates": [
      22.88921,
      41.76226
    ]
  }
}