{
  "type": "Feature",
  "properties": {
    "name": "Argoños",
    "country": "ES",
    "subdivision": "39",
    "timezone": "Europe/Madrid"
  },
  "geometry": {
    "type": "Point",
    "coordinates": [
      -3.49013,
      43.4574
    ]
  }
}