{
  "type": "Feature",
  "properties": {
    "name": "Hazas de Cesto",
    "country": "ES",
    "subdivision": "39",
    "timezone": "Europe/Madrid"
  },
  "geometry": {
    "type": "Point",
    "coordinates": [
      -3.58916,
      43.39653
    ]
  }
}