{
  "type": "Feature",
  "properties": {
    "name": "Molledo",
    "country": "ES",
    "subdivision": "39",
    "timezone": "Europe/Madrid"
  },
  "geometry": {
    "type": "Point",
    "coordinates": [
      -4.04239,
      43.14974
    ]
  }
}