{
  "type": "Feature",
  "properties": {
    "name": "Reocín",
    "country": "ES",
    "subdivision": "39",
    "timezone": "Europe/Madrid"
  },
  "geometry": {
    "type": "Point",
    "coordinates": [
      -4.09403,
      43.33915
    ]
  }
}