{
  "type": "Feature",
  "properties": {
    "name": "Selaya",
    "country": "ES",
    "subdivision": "39",
    "timezone": "Europe/Madrid"
  },
  "geometry": {
    "type": "Point",
    "coordinates": [
      -3.80563,
      43.21376
    ]
  }
}