{
  "type": "Feature",
  "properties": {
    "name": "Lumphat",
    "country": "KH",
    "subdivision": "23",
    "timezone": "Asia/Phnom_Penh"
  },
  "geometry": {
    "type": "Point",
    "coordinates": [
      106.98022,
      13.49146
    ]
  }
}