{
  "type": "Feature",
  "properties": {
    "name": "Barativka",
    "country": "UA",
    "subdivision": "16",
    "timezone": "Europe/Kiev"
  },
  "geometry": {
    "type": "Point",
    "coordinates": [
      32.77938,
      46.94606
    ]
  }
}