{
  "type": "Feature",
  "properties": {
    "name": "Bilousivka",
    "country": "UA",
    "subdivision": "16",
    "timezone": "Europe/Kiev"
  },
  "geometry": {
    "type": "Point",
    "coordinates": [
      31.53289,
      47.42161
    ]
  }
}