{
  "type": "Feature",
  "properties": {
    "name": "Kalynivka",
    "country": "UA",
    "subdivision": "16",
    "timezone": "Europe/Kiev"
  },
  "geometry": {
    "type": "Point",
    "coordinates": [
      32.18071,
      47.04732
    ]
  }
}