{
  "type": "Feature",
  "properties": {
    "name": "Kamyanyy Mist",
    "country": "UA",
    "subdivision": "16",
    "timezone": "Europe/Kiev"
  },
  "geometry": {
    "type": "Point",
    "coordinates": [
      30.78891,
      47.90786
    ]
  }
}