{
  "type": "Feature",
  "properties": {
    "name": "Kryve Ozero",
    "country": "UA",
    "subdivision": "16",
    "timezone": "Europe/Kiev"
  },
  "geometry": {
    "type": "Point",
    "coordinates": [
      30.34701,
      47.94763
    ]
  }
}