{
  "type": "Feature",
  "properties": {
    "name": "Lysa Hora",
    "country": "UA",
    "subdivision": "16",
    "timezone": "Europe/Kiev"
  },
  "geometry": {
    "type": "Point",
    "coordinates": [
      31.10994,
      48.17059
    ]
  }
}