{
  "type": "Feature",
  "properties": {
    "name": "Stantsiyne",
    "country": "UA",
    "subdivision": "16",
    "timezone": "Europe/Kiev"
  },
  "geometry": {
    "type": "Point",
    "coordinates": [
      32.57261,
      47.68615
    ]
  }
}