{
  "type": "Feature",
  "properties": {
    "name": "Tryduby",
    "country": "UA",
    "subdivision": "16",
    "timezone": "Europe/Kiev"
  },
  "geometry": {
    "type": "Point",
    "coordinates": [
      30.41274,
      48.07558
    ]
  }
}