{
  "type": "Feature",
  "properties": {
    "name": "Yuzhnoukrayinsk",
    "country": "UA",
    "subdivision": "16",
    "timezone": "Europe/Kiev"
  },
  "geometry": {
    "type": "Point",
    "coordinates": [
      31.17513,
      47.82879
    ]
  }
}