{
  "type": "Feature",
  "properties": {
    "name": "Midoun",
    "country": "TN",
    "subdivision": "28",
    "timezone": "Africa/Tunis"
  },
  "geometry": {
    "type": "Point",
    "coordinates": [
      10.99228,
      33.80813
    ]
  }
}