{
  "type": "Feature",
  "properties": {
    "name": "Zarzis",
    "country": "TN",
    "subdivision": "28",
    "timezone": "Africa/Tunis"
  },
  "geometry": {
    "type": "Point",
    "coordinates": [
      11.11215,
      33.50398
    ]
  }
}