{
  "type": "Feature",
  "properties": {
    "name": "Amaury",
    "country": "MU",
    "subdivision": "19",
    "timezone": "Indian/Mauritius"
  },
  "geometry": {
    "type": "Point",
    "coordinates": [
      57.65917,
      -20.13083
    ]
  }
}