{
  "type": "Feature",
  "properties": {
    "name": "Dornava",
    "country": "SI",
    "subdivision": "24",
    "timezone": "Europe/Ljubljana"
  },
  "geometry": {
    "type": "Point",
    "coordinates": [
      15.95361,
      46.43667
    ]
  }
}