{
  "type": "Feature",
  "properties": {
    "name": "Alitagtag",
    "country": "PH",
    "subdivision": "40",
    "timezone": "Asia/Manila"
  },
  "geometry": {
    "type": "Point",
    "coordinates": [
      121.0041,
      13.8645
    ]
  }
}