{
  "type": "Feature",
  "properties": {
    "name": "Alupay",
    "country": "PH",
    "subdivision": "40",
    "timezone": "Asia/Manila"
  },
  "geometry": {
    "type": "Point",
    "coordinates": [
      121.30719,
      13.84696
    ]
  }
}