{
  "type": "Feature",
  "properties": {
    "name": "Amadeo",
    "country": "PH",
    "subdivision": "40",
    "timezone": "Asia/Manila"
  },
  "geometry": {
    "type": "Point",
    "coordinates": [
      120.92361,
      14.17056
    ]
  }
}