{
  "type": "Feature",
  "properties": {
    "name": "Anuling",
    "country": "PH",
    "subdivision": "40",
    "timezone": "Asia/Manila"
  },
  "geometry": {
    "type": "Point",
    "coordinates": [
      120.8922,
      14.12388
    ]
  }
}