{
  "type": "Feature",
  "properties": {
    "name": "Bacoor",
    "country": "PH",
    "subdivision": "40",
    "timezone": "Asia/Manila"
  },
  "geometry": {
    "type": "Point",
    "coordinates": [
      120.93851,
      14.45896
    ]
  }
}