{
  "type": "Feature",
  "properties": {
    "name": "Balagtasin",
    "country": "PH",
    "subdivision": "40",
    "timezone": "Asia/Manila"
  },
  "geometry": {
    "type": "Point",
    "coordinates": [
      121.0889,
      13.9018
    ]
  }
}