{
  "type": "Feature",
  "properties": {
    "name": "Banalo",
    "country": "PH",
    "subdivision": "40",
    "timezone": "Asia/Manila"
  },
  "geometry": {
    "type": "Point",
    "coordinates": [
      121.1817,
      13.6464
    ]
  }
}