{
  "type": "Feature",
  "properties": {
    "name": "Bautista",
    "country": "PH",
    "subdivision": "40",
    "timezone": "Asia/Manila"
  },
  "geometry": {
    "type": "Point",
    "coordinates": [
      121.27778,
      13.99444
    ]
  }
}