{
  "type": "Feature",
  "properties": {
    "name": "Binulasan",
    "country": "PH",
    "subdivision": "40",
    "timezone": "Asia/Manila"
  },
  "geometry": {
    "type": "Point",
    "coordinates": [
      121.69781,
      14.73159
    ]
  }
}