{
  "type": "Feature",
  "properties": {
    "name": "Bitin",
    "country": "PH",
    "subdivision": "40",
    "timezone": "Asia/Manila"
  },
  "geometry": {
    "type": "Point",
    "coordinates": [
      121.22194,
      14.11647
    ]
  }
}