{
  "type": "Feature",
  "properties": {
    "name": "Bugaan",
    "country": "PH",
    "subdivision": "40",
    "timezone": "Asia/Manila"
  },
  "geometry": {
    "type": "Point",
    "coordinates": [
      120.93609,
      14.03987
    ]
  }
}