{
  "type": "Feature",
  "properties": {
    "name": "Cabay",
    "country": "PH",
    "subdivision": "40",
    "timezone": "Asia/Manila"
  },
  "geometry": {
    "type": "Point",
    "coordinates": [
      121.37992,
      13.8708
    ]
  }
}