{
  "type": "Feature",
  "properties": {
    "name": "Cainta",
    "country": "PH",
    "subdivision": "40",
    "timezone": "Asia/Manila"
  },
  "geometry": {
    "type": "Point",
    "coordinates": [
      121.1222,
      14.5786
    ]
  }
}