{
  "type": "Feature",
  "properties": {
    "name": "Calubcub Dos",
    "country": "PH",
    "subdivision": "40",
    "timezone": "Asia/Manila"
  },
  "geometry": {
    "type": "Point",
    "coordinates": [
      121.42193,
      13.7393
    ]
  }
}