{
  "type": "Feature",
  "properties": {
    "name": "Calumpang",
    "country": "PH",
    "subdivision": "40",
    "timezone": "Asia/Manila"
  },
  "geometry": {
    "type": "Point",
    "coordinates": [
      121.402,
      14.1966
    ]
  }
}