{
  "type": "Feature",
  "properties": {
    "name": "Camp Flora",
    "country": "PH",
    "subdivision": "40",
    "timezone": "Asia/Manila"
  },
  "geometry": {
    "type": "Point",
    "coordinates": [
      122.6641,
      13.3508
    ]
  }
}