{
  "type": "Feature",
  "properties": {
    "name": "Dasmariñas",
    "country": "PH",
    "subdivision": "40",
    "timezone": "Asia/Manila"
  },
  "geometry": {
    "type": "Point",
    "coordinates": [
      120.93667,
      14.32944
    ]
  }
}