{
  "type": "Feature",
  "properties": {
    "name": "Dayapan",
    "country": "PH",
    "subdivision": "40",
    "timezone": "Asia/Manila"
  },
  "geometry": {
    "type": "Point",
    "coordinates": [
      120.9162,
      13.93723
    ]
  }
}