{
  "type": "Feature",
  "properties": {
    "name": "Halayhayin",
    "country": "PH",
    "subdivision": "40",
    "timezone": "Asia/Manila"
  },
  "geometry": {
    "type": "Point",
    "coordinates": [
      121.4075,
      14.1891
    ]
  }
}