{
  "type": "Feature",
  "properties": {
    "name": "Hukay",
    "country": "PH",
    "subdivision": "40",
    "timezone": "Asia/Manila"
  },
  "geometry": {
    "type": "Point",
    "coordinates": [
      120.70287,
      13.84519
    ]
  }
}