{
  "type": "Feature",
  "properties": {
    "name": "Ilihan",
    "country": "PH",
    "subdivision": "40",
    "timezone": "Asia/Manila"
  },
  "geometry": {
    "type": "Point",
    "coordinates": [
      121.0709,
      13.631
    ]
  }
}