{
  "type": "Feature",
  "properties": {
    "name": "Infanta",
    "country": "PH",
    "subdivision": "40",
    "timezone": "Asia/Manila"
  },
  "geometry": {
    "type": "Point",
    "coordinates": [
      121.64953,
      14.74495
    ]
  }
}