{
  "type": "Feature",
  "properties": {
    "name": "Inicbulan",
    "country": "PH",
    "subdivision": "40",
    "timezone": "Asia/Manila"
  },
  "geometry": {
    "type": "Point",
    "coordinates": [
      120.98345,
      13.82043
    ]
  }
}