{
  "type": "Feature",
  "properties": {
    "name": "Janopol",
    "country": "PH",
    "subdivision": "40",
    "timezone": "Asia/Manila"
  },
  "geometry": {
    "type": "Point",
    "coordinates": [
      121.09489,
      14.08586
    ]
  }
}