{
  "type": "Feature",
  "properties": {
    "name": "Kanluran",
    "country": "PH",
    "subdivision": "40",
    "timezone": "Asia/Manila"
  },
  "geometry": {
    "type": "Point",
    "coordinates": [
      120.85,
      14.41667
    ]
  }
}