{
  "type": "Feature",
  "properties": {
    "name": "Lapolapo",
    "country": "PH",
    "subdivision": "40",
    "timezone": "Asia/Manila"
  },
  "geometry": {
    "type": "Point",
    "coordinates": [
      121.1379,
      13.8341
    ]
  }
}