{
  "type": "Feature",
  "properties": {
    "name": "Madulao",
    "country": "PH",
    "subdivision": "40",
    "timezone": "Asia/Manila"
  },
  "geometry": {
    "type": "Point",
    "coordinates": [
      122.3413,
      13.5684
    ]
  }
}