{
  "type": "Feature",
  "properties": {
    "name": "Malabanban Norte",
    "country": "PH",
    "subdivision": "40",
    "timezone": "Asia/Manila"
  },
  "geometry": {
    "type": "Point",
    "coordinates": [
      121.43065,
      13.94521
    ]
  }
}