{
  "type": "Feature",
  "properties": {
    "name": "Malinao Ilaya",
    "country": "PH",
    "subdivision": "40",
    "timezone": "Asia/Manila"
  },
  "geometry": {
    "type": "Point",
    "coordinates": [
      121.83577,
      13.99611
    ]
  }
}