{
  "type": "Feature",
  "properties": {
    "name": "Mapulo",
    "country": "PH",
    "subdivision": "40",
    "timezone": "Asia/Manila"
  },
  "geometry": {
    "type": "Point",
    "coordinates": [
      121.1842,
      13.7317
    ]
  }
}