{
  "type": "Feature",
  "properties": {
    "name": "Paiisa",
    "country": "PH",
    "subdivision": "40",
    "timezone": "Asia/Manila"
  },
  "geometry": {
    "type": "Point",
    "coordinates": [
      121.35415,
      13.92629
    ]
  }
}