{
  "type": "Feature",
  "properties": {
    "name": "Panikihan",
    "country": "PH",
    "subdivision": "40",
    "timezone": "Asia/Manila"
  },
  "geometry": {
    "type": "Point",
    "coordinates": [
      122.131,
      13.9083
    ]
  }
}