{
  "type": "Feature",
  "properties": {
    "name": "Panukulan",
    "country": "PH",
    "subdivision": "40",
    "timezone": "Asia/Manila"
  },
  "geometry": {
    "type": "Point",
    "coordinates": [
      121.81685,
      14.93371
    ]
  }
}