{
  "type": "Feature",
  "properties": {
    "name": "Pasong Kawayan Primero",
    "country": "PH",
    "subdivision": "40",
    "timezone": "Asia/Manila"
  },
  "geometry": {
    "type": "Point",
    "coordinates": [
      120.88157,
      14.34317
    ]
  }
}