{
  "type": "Feature",
  "properties": {
    "name": "Pila",
    "country": "PH",
    "subdivision": "40",
    "timezone": "Asia/Manila"
  },
  "geometry": {
    "type": "Point",
    "coordinates": [
      121.3648,
      14.2325
    ]
  }
}