{
  "type": "Feature",
  "properties": {
    "name": "Pinugay",
    "country": "PH",
    "subdivision": "40",
    "timezone": "Asia/Manila"
  },
  "geometry": {
    "type": "Point",
    "coordinates": [
      121.2623,
      14.5967
    ]
  }
}