{
  "type": "Feature",
  "properties": {
    "name": "Quipot",
    "country": "PH",
    "subdivision": "40",
    "timezone": "Asia/Manila"
  },
  "geometry": {
    "type": "Point",
    "coordinates": [
      121.31903,
      13.9556
    ]
  }
}