{
  "type": "Feature",
  "properties": {
    "name": "San Juan",
    "country": "PH",
    "subdivision": "40",
    "timezone": "Asia/Manila"
  },
  "geometry": {
    "type": "Point",
    "coordinates": [
      121.22931,
      14.05715
    ]
  }
}