{
  "type": "Feature",
  "properties": {
    "name": "San Jose",
    "country": "PH",
    "subdivision": "40",
    "timezone": "Asia/Manila"
  },
  "geometry": {
    "type": "Point",
    "coordinates": [
      120.94951,
      13.85209
    ]
  }
}