{
  "type": "Feature",
  "properties": {
    "name": "San Carlos",
    "country": "PH",
    "subdivision": "40",
    "timezone": "Asia/Manila"
  },
  "geometry": {
    "type": "Point",
    "coordinates": [
      121.2416,
      13.8422
    ]
  }
}