{
  "type": "Feature",
  "properties": {
    "name": "San Miguel",
    "country": "PH",
    "subdivision": "40",
    "timezone": "Asia/Manila"
  },
  "geometry": {
    "type": "Point",
    "coordinates": [
      121.3732,
      14.2013
    ]
  }
}