{
  "type": "Feature",
  "properties": {
    "name": "Santa Rosa",
    "country": "PH",
    "subdivision": "40",
    "timezone": "Asia/Manila"
  },
  "geometry": {
    "type": "Point",
    "coordinates": [
      120.87931,
      14.42612
    ]
  }
}