{
  "type": "Feature",
  "properties": {
    "name": "Sibulan",
    "country": "PH",
    "subdivision": "40",
    "timezone": "Asia/Manila"
  },
  "geometry": {
    "type": "Point",
    "coordinates": [
      121.93333,
      14.75
    ]
  }
}