{
  "type": "Feature",
  "properties": {
    "name": "Tayabas",
    "country": "PH",
    "subdivision": "40",
    "timezone": "Asia/Manila"
  },
  "geometry": {
    "type": "Point",
    "coordinates": [
      121.5929,
      14.0259
    ]
  }
}