{
  "type": "Feature",
  "properties": {
    "name": "Tignoan",
    "country": "PH",
    "subdivision": "40",
    "timezone": "Asia/Manila"
  },
  "geometry": {
    "type": "Point",
    "coordinates": [
      121.61786,
      14.56522
    ]
  }
}