{
  "type": "Feature",
  "properties": {
    "name": "Yuni",
    "country": "PH",
    "subdivision": "40",
    "timezone": "Asia/Manila"
  },
  "geometry": {
    "type": "Point",
    "coordinates": [
      122.4846,
      13.4124
    ]
  }
}