{
  "type": "Feature",
  "properties": {
    "name": "Crosby",
    "country": "US",
    "subdivision": "ND",
    "timezone": "America/Chicago"
  },
  "geometry": {
    "type": "Point",
    "coordinates": [
      -103.29491,
      48.9142
    ]
  }
}