{
  "type": "Feature",
  "properties": {
    "name": "Harvey",
    "country": "US",
    "subdivision": "ND",
    "timezone": "America/Chicago"
  },
  "geometry": {
    "type": "Point",
    "coordinates": [
      -99.9354,
      47.76972
    ]
  }
}