{
  "type": "Feature",
  "properties": {
    "name": "Hillsboro",
    "country": "US",
    "subdivision": "ND",
    "timezone": "America/Chicago"
  },
  "geometry": {
    "type": "Point",
    "coordinates": [
      -97.06203,
      47.40387
    ]
  }
}