{
  "type": "Feature",
  "properties": {
    "name": "Linton",
    "country": "US",
    "subdivision": "ND",
    "timezone": "America/Chicago"
  },
  "geometry": {
    "type": "Point",
    "coordinates": [
      -100.23289,
      46.26666
    ]
  }
}