{
  "type": "Feature",
  "properties": {
    "name": "New Rockford",
    "country": "US",
    "subdivision": "ND",
    "timezone": "America/Chicago"
  },
  "geometry": {
    "type": "Point",
    "coordinates": [
      -99.1379,
      47.68
    ]
  }
}