{
  "type": "Feature",
  "properties": {
    "name": "Rugby",
    "country": "US",
    "subdivision": "ND",
    "timezone": "America/Chicago"
  },
  "geometry": {
    "type": "Point",
    "coordinates": [
      -99.99625,
      48.36889
    ]
  }
}