{
  "type": "Feature",
  "properties": {
    "name": "Shell Valley",
    "country": "US",
    "subdivision": "ND",
    "timezone": "America/Chicago"
  },
  "geometry": {
    "type": "Point",
    "coordinates": [
      -99.86486,
      48.79806
    ]
  }
}