{
  "type": "Feature",
  "properties": {
    "name": "Surrey",
    "country": "US",
    "subdivision": "ND",
    "timezone": "America/Chicago"
  },
  "geometry": {
    "type": "Point",
    "coordinates": [
      -101.13349,
      48.2364
    ]
  }
}