{
  "type": "Feature",
  "properties": {
    "name": "Valley City",
    "country": "US",
    "subdivision": "ND",
    "timezone": "America/Chicago"
  },
  "geometry": {
    "type": "Point",
    "coordinates": [
      -98.00315,
      46.92331
    ]
  }
}