{
  "type": "Feature",
  "properties": {
    "name": "Kiomboi",
    "country": "TZ",
    "subdivision": "16",
    "timezone": "Africa/Dar_es_Salaam"
  },
  "geometry": {
    "type": "Point",
    "coordinates": [
      34.36667,
      -4.26667
    ]
  }
}