{
  "type": "Feature",
  "properties": {
    "name": "Aarau",
    "country": "CH",
    "subdivision": "AG",
    "timezone": "Europe/Zurich"
  },
  "geometry": {
    "type": "Point",
    "coordinates": [
      8.04422,
      47.39254
    ]
  }
}