{
  "type": "Feature",
  "properties": {
    "name": "Birr",
    "country": "CH",
    "subdivision": "AG",
    "timezone": "Europe/Zurich"
  },
  "geometry": {
    "type": "Point",
    "coordinates": [
      8.20891,
      47.43432
    ]
  }
}