{
  "type": "Feature",
  "properties": {
    "name": "Bremgarten",
    "country": "CH",
    "subdivision": "AG",
    "timezone": "Europe/Zurich"
  },
  "geometry": {
    "type": "Point",
    "coordinates": [
      8.34214,
      47.35109
    ]
  }
}