{
  "type": "Feature",
  "properties": {
    "name": "Ehrendingen",
    "country": "CH",
    "subdivision": "AG",
    "timezone": "Europe/Zurich"
  },
  "geometry": {
    "type": "Point",
    "coordinates": [
      8.34729,
      47.5025
    ]
  }
}