{
  "type": "Feature",
  "properties": {
    "name": "Kaiseraugst",
    "country": "CH",
    "subdivision": "AG",
    "timezone": "Europe/Zurich"
  },
  "geometry": {
    "type": "Point",
    "coordinates": [
      7.72605,
      47.53966
    ]
  }
}