{
  "type": "Feature",
  "properties": {
    "name": "Lauffohr (Brugg)",
    "country": "CH",
    "subdivision": "AG",
    "timezone": "Europe/Zurich"
  },
  "geometry": {
    "type": "Point",
    "coordinates": [
      8.23122,
      47.50154
    ]
  }
}