{
  "type": "Feature",
  "properties": {
    "name": "Muhen",
    "country": "CH",
    "subdivision": "AG",
    "timezone": "Europe/Zurich"
  },
  "geometry": {
    "type": "Point",
    "coordinates": [
      8.05536,
      47.33578
    ]
  }
}