{
  "type": "Feature",
  "properties": {
    "name": "Niederlenz",
    "country": "CH",
    "subdivision": "AG",
    "timezone": "Europe/Zurich"
  },
  "geometry": {
    "type": "Point",
    "coordinates": [
      8.1764,
      47.40079
    ]
  }
}