{
  "type": "Feature",
  "properties": {
    "name": "Schinznach Bad",
    "country": "CH",
    "subdivision": "AG",
    "timezone": "Europe/Zurich"
  },
  "geometry": {
    "type": "Point",
    "coordinates": [
      8.16833,
      47.44992
    ]
  }
}