{
  "type": "Feature",
  "properties": {
    "name": "Uerkheim",
    "country": "CH",
    "subdivision": "AG",
    "timezone": "Europe/Zurich"
  },
  "geometry": {
    "type": "Point",
    "coordinates": [
      8.0232,
      47.30353
    ]
  }
}