{
  "type": "Feature",
  "properties": {
    "name": "Novo Aripuanã",
    "country": "BR",
    "subdivision": "04",
    "timezone": "America/Manaus"
  },
  "geometry": {
    "type": "Point",
    "coordinates": [
      -60.37972,
      -5.12056
    ]
  }
}