{
  "type": "Feature",
  "properties": {
    "name": "Santo Antônio do Içá",
    "country": "BR",
    "subdivision": "04",
    "timezone": "America/Manaus"
  },
  "geometry": {
    "type": "Point",
    "coordinates": [
      -67.93972,
      -3.10222
    ]
  }
}