{
  "type": "Feature",
  "properties": {
    "name": "Andouillé",
    "country": "FR",
    "subdivision": "52",
    "timezone": "Europe/Paris"
  },
  "geometry": {
    "type": "Point",
    "coordinates": [
      -0.78434,
      48.17686
    ]
  }
}