{
  "type": "Feature",
  "properties": {
    "name": "Auvers-le-Hamon",
    "country": "FR",
    "subdivision": "52",
    "timezone": "Europe/Paris"
  },
  "geometry": {
    "type": "Point",
    "coordinates": [
      -0.35195,
      47.90181
    ]
  }
}