{
  "type": "Feature",
  "properties": {
    "name": "Basse-Goulaine",
    "country": "FR",
    "subdivision": "52",
    "timezone": "Europe/Paris"
  },
  "geometry": {
    "type": "Point",
    "coordinates": [
      -1.46598,
      47.2151
    ]
  }
}