{
  "type": "Feature",
  "properties": {
    "name": "Beaufay",
    "country": "FR",
    "subdivision": "52",
    "timezone": "Europe/Paris"
  },
  "geometry": {
    "type": "Point",
    "coordinates": [
      0.36192,
      48.14715
    ]
  }
}