{
  "type": "Feature",
  "properties": {
    "name": "Bonchamp-lès-Laval",
    "country": "FR",
    "subdivision": "52",
    "timezone": "Europe/Paris"
  },
  "geometry": {
    "type": "Point",
    "coordinates": [
      -0.70195,
      48.07379
    ]
  }
}