{
  "type": "Feature",
  "properties": {
    "name": "Bouvron",
    "country": "FR",
    "subdivision": "52",
    "timezone": "Europe/Paris"
  },
  "geometry": {
    "type": "Point",
    "coordinates": [
      -1.84938,
      47.41774
    ]
  }
}