{
  "type": "Feature",
  "properties": {
    "name": "Brion",
    "country": "FR",
    "subdivision": "52",
    "timezone": "Europe/Paris"
  },
  "geometry": {
    "type": "Point",
    "coordinates": [
      -0.15616,
      47.44121
    ]
  }
}