{
  "type": "Feature",
  "properties": {
    "name": "Chambretaud",
    "country": "FR",
    "subdivision": "52",
    "timezone": "Europe/Paris"
  },
  "geometry": {
    "type": "Point",
    "coordinates": [
      -0.96559,
      46.92178
    ]
  }
}