{
  "type": "Feature",
  "properties": {
    "name": "Château-du-Loir",
    "country": "FR",
    "subdivision": "52",
    "timezone": "Europe/Paris"
  },
  "geometry": {
    "type": "Point",
    "coordinates": [
      0.41829,
      47.69409
    ]
  }
}