{
  "type": "Feature",
  "properties": {
    "name": "Clermont-Créans",
    "country": "FR",
    "subdivision": "52",
    "timezone": "Europe/Paris"
  },
  "geometry": {
    "type": "Point",
    "coordinates": [
      -0.01459,
      47.71831
    ]
  }
}