{
  "type": "Feature",
  "properties": {
    "name": "Coëx",
    "country": "FR",
    "subdivision": "52",
    "timezone": "Europe/Paris"
  },
  "geometry": {
    "type": "Point",
    "coordinates": [
      -1.7602,
      46.69748
    ]
  }
}