{
  "type": "Feature",
  "properties": {
    "name": "Commequiers",
    "country": "FR",
    "subdivision": "52",
    "timezone": "Europe/Paris"
  },
  "geometry": {
    "type": "Point",
    "coordinates": [
      -1.83815,
      46.76264
    ]
  }
}