{
  "type": "Feature",
  "properties": {
    "name": "Congrier",
    "country": "FR",
    "subdivision": "52",
    "timezone": "Europe/Paris"
  },
  "geometry": {
    "type": "Point",
    "coordinates": [
      -1.1167,
      47.81033
    ]
  }
}