{
  "type": "Feature",
  "properties": {
    "name": "Corzé",
    "country": "FR",
    "subdivision": "52",
    "timezone": "Europe/Paris"
  },
  "geometry": {
    "type": "Point",
    "coordinates": [
      -0.39062,
      47.55956
    ]
  }
}