{
  "type": "Feature",
  "properties": {
    "name": "Couëron",
    "country": "FR",
    "subdivision": "52",
    "timezone": "Europe/Paris"
  },
  "geometry": {
    "type": "Point",
    "coordinates": [
      -1.72452,
      47.21473
    ]
  }
}