{
  "type": "Feature",
  "properties": {
    "name": "Coulaines",
    "country": "FR",
    "subdivision": "52",
    "timezone": "Europe/Paris"
  },
  "geometry": {
    "type": "Point",
    "coordinates": [
      0.20411,
      48.02409
    ]
  }
}