{
  "type": "Feature",
  "properties": {
    "name": "Cugand",
    "country": "FR",
    "subdivision": "52",
    "timezone": "Europe/Paris"
  },
  "geometry": {
    "type": "Point",
    "coordinates": [
      -1.25463,
      47.06353
    ]
  }
}