{
  "type": "Feature",
  "properties": {
    "name": "Drain",
    "country": "FR",
    "subdivision": "52",
    "timezone": "Europe/Paris"
  },
  "geometry": {
    "type": "Point",
    "coordinates": [
      -1.20773,
      47.33655
    ]
  }
}