{
  "type": "Feature",
  "properties": {
    "name": "Durtal",
    "country": "FR",
    "subdivision": "52",
    "timezone": "Europe/Paris"
  },
  "geometry": {
    "type": "Point",
    "coordinates": [
      -0.23393,
      47.67247
    ]
  }
}