{
  "type": "Feature",
  "properties": {
    "name": "Écouflant",
    "country": "FR",
    "subdivision": "52",
    "timezone": "Europe/Paris"
  },
  "geometry": {
    "type": "Point",
    "coordinates": [
      -0.52829,
      47.5308
    ]
  }
}