{
  "type": "Feature",
  "properties": {
    "name": "Ernée",
    "country": "FR",
    "subdivision": "52",
    "timezone": "Europe/Paris"
  },
  "geometry": {
    "type": "Point",
    "coordinates": [
      -0.93263,
      48.29722
    ]
  }
}