{
  "type": "Feature",
  "properties": {
    "name": "Étriché",
    "country": "FR",
    "subdivision": "52",
    "timezone": "Europe/Paris"
  },
  "geometry": {
    "type": "Point",
    "coordinates": [
      -0.44423,
      47.65127
    ]
  }
}