{
  "type": "Feature",
  "properties": {
    "name": "Falleron",
    "country": "FR",
    "subdivision": "52",
    "timezone": "Europe/Paris"
  },
  "geometry": {
    "type": "Point",
    "coordinates": [
      -1.70263,
      46.88186
    ]
  }
}