{
  "type": "Feature",
  "properties": {
    "name": "Gorron",
    "country": "FR",
    "subdivision": "52",
    "timezone": "Europe/Paris"
  },
  "geometry": {
    "type": "Point",
    "coordinates": [
      -0.81287,
      48.41161
    ]
  }
}