{
  "type": "Feature",
  "properties": {
    "name": "Jallais",
    "country": "FR",
    "subdivision": "52",
    "timezone": "Europe/Paris"
  },
  "geometry": {
    "type": "Point",
    "coordinates": [
      -0.86738,
      47.19691
    ]
  }
}