{
  "type": "Feature",
  "properties": {
    "name": "Jard-sur-Mer",
    "country": "FR",
    "subdivision": "52",
    "timezone": "Europe/Paris"
  },
  "geometry": {
    "type": "Point",
    "coordinates": [
      -1.57678,
      46.41638
    ]
  }
}