{
  "type": "Feature",
  "properties": {
    "name": "Juigné-sur-Sarthe",
    "country": "FR",
    "subdivision": "52",
    "timezone": "Europe/Paris"
  },
  "geometry": {
    "type": "Point",
    "coordinates": [
      -0.28667,
      47.86388
    ]
  }
}