{
  "type": "Feature",
  "properties": {
    "name": "La Barre-de-Monts",
    "country": "FR",
    "subdivision": "52",
    "timezone": "Europe/Paris"
  },
  "geometry": {
    "type": "Point",
    "coordinates": [
      -2.11862,
      46.88421
    ]
  }
}