{
  "type": "Feature",
  "properties": {
    "name": "La Bernardière",
    "country": "FR",
    "subdivision": "52",
    "timezone": "Europe/Paris"
  },
  "geometry": {
    "type": "Point",
    "coordinates": [
      -1.26648,
      47.04937
    ]
  }
}