{
  "type": "Feature",
  "properties": {
    "name": "La Chapelle-Launay",
    "country": "FR",
    "subdivision": "52",
    "timezone": "Europe/Paris"
  },
  "geometry": {
    "type": "Point",
    "coordinates": [
      -1.9715,
      47.37195
    ]
  }
}