{
  "type": "Feature",
  "properties": {
    "name": "La Chapelle-Achard",
    "country": "FR",
    "subdivision": "52",
    "timezone": "Europe/Paris"
  },
  "geometry": {
    "type": "Point",
    "coordinates": [
      -1.64731,
      46.58876
    ]
  }
}