{
  "type": "Feature",
  "properties": {
    "name": "La Guérinière",
    "country": "FR",
    "subdivision": "52",
    "timezone": "Europe/Paris"
  },
  "geometry": {
    "type": "Point",
    "coordinates": [
      -2.23333,
      46.96667
    ]
  }
}