{
  "type": "Feature",
  "properties": {
    "name": "La Ménitré",
    "country": "FR",
    "subdivision": "52",
    "timezone": "Europe/Paris"
  },
  "geometry": {
    "type": "Point",
    "coordinates": [
      -0.26857,
      47.40254
    ]
  }
}