{
  "type": "Feature",
  "properties": {
    "name": "La Pouëze",
    "country": "FR",
    "subdivision": "52",
    "timezone": "Europe/Paris"
  },
  "geometry": {
    "type": "Point",
    "coordinates": [
      -0.80928,
      47.55357
    ]
  }
}