{
  "type": "Feature",
  "properties": {
    "name": "La Roche-sur-Yon",
    "country": "FR",
    "subdivision": "52",
    "timezone": "Europe/Paris"
  },
  "geometry": {
    "type": "Point",
    "coordinates": [
      -1.42757,
      46.66974
    ]
  }
}