{
  "type": "Feature",
  "properties": {
    "name": "La Séguinière",
    "country": "FR",
    "subdivision": "52",
    "timezone": "Europe/Paris"
  },
  "geometry": {
    "type": "Point",
    "coordinates": [
      -0.93996,
      47.06343
    ]
  }
}