{
  "type": "Feature",
  "properties": {
    "name": "Landeronde",
    "country": "FR",
    "subdivision": "52",
    "timezone": "Europe/Paris"
  },
  "geometry": {
    "type": "Point",
    "coordinates": [
      -1.57117,
      46.65794
    ]
  }
}