{
  "type": "Feature",
  "properties": {
    "name": "Lassay-les-Châteaux",
    "country": "FR",
    "subdivision": "52",
    "timezone": "Europe/Paris"
  },
  "geometry": {
    "type": "Point",
    "coordinates": [
      -0.49758,
      48.43835
    ]
  }
}