{
  "type": "Feature",
  "properties": {
    "name": "Laval",
    "country": "FR",
    "subdivision": "52",
    "timezone": "Europe/Paris"
  },
  "geometry": {
    "type": "Point",
    "coordinates": [
      -0.77019,
      48.07247
    ]
  }
}