{
  "type": "Feature",
  "properties": {
    "name": "Le Louroux Béconnais",
    "country": "FR",
    "subdivision": "52",
    "timezone": "Europe/Paris"
  },
  "geometry": {
    "type": "Point",
    "coordinates": [
      -0.88559,
      47.52148
    ]
  }
}