{
  "type": "Feature",
  "properties": {
    "name": "Les Herbiers",
    "country": "FR",
    "subdivision": "52",
    "timezone": "Europe/Paris"
  },
  "geometry": {
    "type": "Point",
    "coordinates": [
      -1.0156,
      46.87095
    ]
  }
}