{
  "type": "Feature",
  "properties": {
    "name": "Ligné",
    "country": "FR",
    "subdivision": "52",
    "timezone": "Europe/Paris"
  },
  "geometry": {
    "type": "Point",
    "coordinates": [
      -1.37796,
      47.41148
    ]
  }
}