{
  "type": "Feature",
  "properties": {
    "name": "Louplande",
    "country": "FR",
    "subdivision": "52",
    "timezone": "Europe/Paris"
  },
  "geometry": {
    "type": "Point",
    "coordinates": [
      -0.05,
      47.95
    ]
  }
}