{
  "type": "Feature",
  "properties": {
    "name": "Luçon",
    "country": "FR",
    "subdivision": "52",
    "timezone": "Europe/Paris"
  },
  "geometry": {
    "type": "Point",
    "coordinates": [
      -1.16629,
      46.45493
    ]
  }
}