{
  "type": "Feature",
  "properties": {
    "name": "Maulévrier",
    "country": "FR",
    "subdivision": "52",
    "timezone": "Europe/Paris"
  },
  "geometry": {
    "type": "Point",
    "coordinates": [
      -0.745,
      47.00966
    ]
  }
}