{
  "type": "Feature",
  "properties": {
    "name": "Montsûrs",
    "country": "FR",
    "subdivision": "52",
    "timezone": "Europe/Paris"
  },
  "geometry": {
    "type": "Point",
    "coordinates": [
      -0.55381,
      48.13475
    ]
  }
}