{
  "type": "Feature",
  "properties": {
    "name": "Montbizot",
    "country": "FR",
    "subdivision": "52",
    "timezone": "Europe/Paris"
  },
  "geometry": {
    "type": "Point",
    "coordinates": [
      0.18213,
      48.14767
    ]
  }
}