{
  "type": "Feature",
  "properties": {
    "name": "Montbert",
    "country": "FR",
    "subdivision": "52",
    "timezone": "Europe/Paris"
  },
  "geometry": {
    "type": "Point",
    "coordinates": [
      -1.48873,
      47.05778
    ]
  }
}