{
  "type": "Feature",
  "properties": {
    "name": "Montrevault",
    "country": "FR",
    "subdivision": "52",
    "timezone": "Europe/Paris"
  },
  "geometry": {
    "type": "Point",
    "coordinates": [
      -1.04579,
      47.26145
    ]
  }
}