{
  "type": "Feature",
  "properties": {
    "name": "Mouilleron-en-Pareds",
    "country": "FR",
    "subdivision": "52",
    "timezone": "Europe/Paris"
  },
  "geometry": {
    "type": "Point",
    "coordinates": [
      -0.84915,
      46.67617
    ]
  }
}