{
  "type": "Feature",
  "properties": {
    "name": "Moulay",
    "country": "FR",
    "subdivision": "52",
    "timezone": "Europe/Paris"
  },
  "geometry": {
    "type": "Point",
    "coordinates": [
      -0.6283,
      48.27269
    ]
  }
}