{
  "type": "Feature",
  "properties": {
    "name": "Moutiers-les-Mauxfaits",
    "country": "FR",
    "subdivision": "52",
    "timezone": "Europe/Paris"
  },
  "geometry": {
    "type": "Point",
    "coordinates": [
      -1.42662,
      46.49358
    ]
  }
}