{
  "type": "Feature",
  "properties": {
    "name": "Notre-Dame-de-Riez",
    "country": "FR",
    "subdivision": "52",
    "timezone": "Europe/Paris"
  },
  "geometry": {
    "type": "Point",
    "coordinates": [
      -1.90791,
      46.74518
    ]
  }
}