{
  "type": "Feature",
  "properties": {
    "name": "Nozay",
    "country": "FR",
    "subdivision": "52",
    "timezone": "Europe/Paris"
  },
  "geometry": {
    "type": "Point",
    "coordinates": [
      -1.62559,
      47.56473
    ]
  }
}