{
  "type": "Feature",
  "properties": {
    "name": "Pontchâteau",
    "country": "FR",
    "subdivision": "52",
    "timezone": "Europe/Paris"
  },
  "geometry": {
    "type": "Point",
    "coordinates": [
      -2.09422,
      47.43868
    ]
  }
}