{
  "type": "Feature",
  "properties": {
    "name": "Roézé-sur-Sarthe",
    "country": "FR",
    "subdivision": "52",
    "timezone": "Europe/Paris"
  },
  "geometry": {
    "type": "Point",
    "coordinates": [
      0.06662,
      47.89578
    ]
  }
}