{
  "type": "Feature",
  "properties": {
    "name": "Ruaudin",
    "country": "FR",
    "subdivision": "52",
    "timezone": "Europe/Paris"
  },
  "geometry": {
    "type": "Point",
    "coordinates": [
      0.26632,
      47.94499
    ]
  }
}