{
  "type": "Feature",
  "properties": {
    "name": "Saint-Léger-sous-Cholet",
    "country": "FR",
    "subdivision": "52",
    "timezone": "Europe/Paris"
  },
  "geometry": {
    "type": "Point",
    "coordinates": [
      -0.91031,
      47.09339
    ]
  }
}