{
  "type": "Feature",
  "properties": {
    "name": "Saint-Hilaire-de-Loulay",
    "country": "FR",
    "subdivision": "52",
    "timezone": "Europe/Paris"
  },
  "geometry": {
    "type": "Point",
    "coordinates": [
      -1.33079,
      47.0019
    ]
  }
}