{
  "type": "Feature",
  "properties": {
    "name": "Saint-Fulgent",
    "country": "FR",
    "subdivision": "52",
    "timezone": "Europe/Paris"
  },
  "geometry": {
    "type": "Point",
    "coordinates": [
      -1.17774,
      46.85323
    ]
  }
}