{
  "type": "Feature",
  "properties": {
    "name": "Saint-Malô-du-Bois",
    "country": "FR",
    "subdivision": "52",
    "timezone": "Europe/Paris"
  },
  "geometry": {
    "type": "Point",
    "coordinates": [
      -0.90004,
      46.92891
    ]
  }
}