{
  "type": "Feature",
  "properties": {
    "name": "Saint-Léger-les-Vignes",
    "country": "FR",
    "subdivision": "52",
    "timezone": "Europe/Paris"
  },
  "geometry": {
    "type": "Point",
    "coordinates": [
      -1.73166,
      47.13576
    ]
  }
}