{
  "type": "Feature",
  "properties": {
    "name": "Saint-Martin sous Mouzeuil",
    "country": "FR",
    "subdivision": "52",
    "timezone": "Europe/Paris"
  },
  "geometry": {
    "type": "Point",
    "coordinates": [
      -0.98822,
      46.45978
    ]
  }
}