{
  "type": "Feature",
  "properties": {
    "name": "Saint-Ouën-des-Toits",
    "country": "FR",
    "subdivision": "52",
    "timezone": "Europe/Paris"
  },
  "geometry": {
    "type": "Point",
    "coordinates": [
      -0.90396,
      48.138
    ]
  }
}