{
  "type": "Feature",
  "properties": {
    "name": "Saint-Jean",
    "country": "FR",
    "subdivision": "52",
    "timezone": "Europe/Paris"
  },
  "geometry": {
    "type": "Point",
    "coordinates": [
      -0.38413,
      47.24553
    ]
  }
}