{
  "type": "Feature",
  "properties": {
    "name": "Sainte-Gemmes-sur-Loire",
    "country": "FR",
    "subdivision": "52",
    "timezone": "Europe/Paris"
  },
  "geometry": {
    "type": "Point",
    "coordinates": [
      -0.55684,
      47.4229
    ]
  }
}