{
  "type": "Feature",
  "properties": {
    "name": "Saint-Clément-de-la-Place",
    "country": "FR",
    "subdivision": "52",
    "timezone": "Europe/Paris"
  },
  "geometry": {
    "type": "Point",
    "coordinates": [
      -0.74668,
      47.52623
    ]
  }
}