{
  "type": "Feature",
  "properties": {
    "name": "Saint-Nicolas-de-Redon",
    "country": "FR",
    "subdivision": "52",
    "timezone": "Europe/Paris"
  },
  "geometry": {
    "type": "Point",
    "coordinates": [
      -2.06637,
      47.64408
    ]
  }
}