{
  "type": "Feature",
  "properties": {
    "name": "Saint-Lumine-de-Coutais",
    "country": "FR",
    "subdivision": "52",
    "timezone": "Europe/Paris"
  },
  "geometry": {
    "type": "Point",
    "coordinates": [
      -1.7269,
      47.05471
    ]
  }
}