{
  "type": "Feature",
  "properties": {
    "name": "Saint-Michel-le-Cloucq",
    "country": "FR",
    "subdivision": "52",
    "timezone": "Europe/Paris"
  },
  "geometry": {
    "type": "Point",
    "coordinates": [
      -0.75344,
      46.48482
    ]
  }
}