{
  "type": "Feature",
  "properties": {
    "name": "Seiches-sur-le-Loir",
    "country": "FR",
    "subdivision": "52",
    "timezone": "Europe/Paris"
  },
  "geometry": {
    "type": "Point",
    "coordinates": [
      -0.35628,
      47.57351
    ]
  }
}