{
  "type": "Feature",
  "properties": {
    "name": "Teillé",
    "country": "FR",
    "subdivision": "52",
    "timezone": "Europe/Paris"
  },
  "geometry": {
    "type": "Point",
    "coordinates": [
      -1.2781,
      47.4617
    ]
  }
}