{
  "type": "Feature",
  "properties": {
    "name": "Teloché",
    "country": "FR",
    "subdivision": "52",
    "timezone": "Europe/Paris"
  },
  "geometry": {
    "type": "Point",
    "coordinates": [
      0.27112,
      47.888
    ]
  }
}