{
  "type": "Feature",
  "properties": {
    "name": "Tillières",
    "country": "FR",
    "subdivision": "52",
    "timezone": "Europe/Paris"
  },
  "geometry": {
    "type": "Point",
    "coordinates": [
      -1.16334,
      47.14397
    ]
  }
}