{
  "type": "Feature",
  "properties": {
    "name": "Triaize",
    "country": "FR",
    "subdivision": "52",
    "timezone": "Europe/Paris"
  },
  "geometry": {
    "type": "Point",
    "coordinates": [
      -1.19785,
      46.39265
    ]
  }
}