{
  "type": "Feature",
  "properties": {
    "name": "Vaas",
    "country": "FR",
    "subdivision": "52",
    "timezone": "Europe/Paris"
  },
  "geometry": {
    "type": "Point",
    "coordinates": [
      0.31168,
      47.66895
    ]
  }
}