{
  "type": "Feature",
  "properties": {
    "name": "Vernantes",
    "country": "FR",
    "subdivision": "52",
    "timezone": "Europe/Paris"
  },
  "geometry": {
    "type": "Point",
    "coordinates": [
      0.05155,
      47.39323
    ]
  }
}