{
  "type": "Feature",
  "properties": {
    "name": "Vieillevigne",
    "country": "FR",
    "subdivision": "52",
    "timezone": "Europe/Paris"
  },
  "geometry": {
    "type": "Point",
    "coordinates": [
      -1.43446,
      46.97152
    ]
  }
}