{
  "type": "Feature",
  "properties": {
    "name": "Villedieu-la-Blouère",
    "country": "FR",
    "subdivision": "52",
    "timezone": "Europe/Paris"
  },
  "geometry": {
    "type": "Point",
    "coordinates": [
      -1.06286,
      47.14738
    ]
  }
}