{
  "type": "Feature",
  "properties": {
    "name": "Vix",
    "country": "FR",
    "subdivision": "52",
    "timezone": "Europe/Paris"
  },
  "geometry": {
    "type": "Point",
    "coordinates": [
      -0.85959,
      46.36431
    ]
  }
}