{
  "type": "Feature",
  "properties": {
    "name": "Cham",
    "country": "CH",
    "subdivision": "ZG",
    "timezone": "Europe/Zurich"
  },
  "geometry": {
    "type": "Point",
    "coordinates": [
      8.46358,
      47.18213
    ]
  }
}