{
  "type": "Feature",
  "properties": {
    "name": "Novyy Karanlug",
    "country": "AZ",
    "subdivision": "65",
    "timezone": "Asia/Baku"
  },
  "geometry": {
    "type": "Point",
    "coordinates": [
      47.1117,
      39.79496
    ]
  }
}