{
  "type": "Feature",
  "properties": {
    "name": "Imeni Vladimira Il’icha Lenina",
    "country": "RU",
    "subdivision": "81",
    "timezone": "Europe/Ulyanovsk"
  },
  "geometry": {
    "type": "Point",
    "coordinates": [
      46.9801,
      53.56422
    ]
  }
}