{
  "type": "Feature",
  "properties": {
    "name": "El Rosario",
    "country": "SV",
    "subdivision": "06",
    "timezone": "America/El_Salvador"
  },
  "geometry": {
    "type": "Point",
    "coordinates": [
      -89.02972,
      13.49778
    ]
  }
}