{
  "type": "Feature",
  "properties": {
    "name": "Chamouny",
    "country": "MU",
    "subdivision": "20",
    "timezone": "Indian/Mauritius"
  },
  "geometry": {
    "type": "Point",
    "coordinates": [
      57.46611,
      -20.48222
    ]
  }
}