{
  "type": "Feature",
  "properties": {
    "name": "Saint Aubin",
    "country": "MU",
    "subdivision": "20",
    "timezone": "Indian/Mauritius"
  },
  "geometry": {
    "type": "Point",
    "coordinates": [
      57.55,
      -20.496
    ]
  }
}