{
  "type": "Feature",
  "properties": {
    "name": "Érsekvadkert",
    "country": "HU",
    "subdivision": "14",
    "timezone": "Europe/Budapest"
  },
  "geometry": {
    "type": "Point",
    "coordinates": [
      19.20231,
      47.99619
    ]
  }
}