{
  "type": "Feature",
  "properties": {
    "name": "Pásztó",
    "country": "HU",
    "subdivision": "14",
    "timezone": "Europe/Budapest"
  },
  "geometry": {
    "type": "Point",
    "coordinates": [
      19.69829,
      47.92019
    ]
  }
}