{
  "type": "Feature",
  "properties": {
    "name": "Somoskőújfalu",
    "country": "HU",
    "subdivision": "14",
    "timezone": "Europe/Budapest"
  },
  "geometry": {
    "type": "Point",
    "coordinates": [
      19.82303,
      48.16374
    ]
  }
}