{
  "type": "Feature",
  "properties": {
    "name": "Clodomira",
    "country": "AR",
    "subdivision": "22",
    "timezone": "America/Argentina/Cordoba"
  },
  "geometry": {
    "type": "Point",
    "coordinates": [
      -64.13108,
      -27.5744
    ]
  }
}