{
  "type": "Feature",
  "properties": {
    "name": "Termas de Río Hondo",
    "country": "AR",
    "subdivision": "22",
    "timezone": "America/Argentina/Cordoba"
  },
  "geometry": {
    "type": "Point",
    "coordinates": [
      -64.85972,
      -27.49362
    ]
  }
}