{
  "type": "Feature",
  "properties": {
    "name": "Villa General Mitre",
    "country": "AR",
    "subdivision": "22",
    "timezone": "America/Argentina/Cordoba"
  },
  "geometry": {
    "type": "Point",
    "coordinates": [
      -62.65248,
      -29.1431
    ]
  }
}