{
  "type": "Feature",
  "properties": {
    "name": "Villa Atamisqui",
    "country": "AR",
    "subdivision": "22",
    "timezone": "America/Argentina/Cordoba"
  },
  "geometry": {
    "type": "Point",
    "coordinates": [
      -63.81609,
      -28.49609
    ]
  }
}