{
  "type": "Feature",
  "properties": {
    "name": "Villa Ojo de Agua",
    "country": "AR",
    "subdivision": "22",
    "timezone": "America/Argentina/Cordoba"
  },
  "geometry": {
    "type": "Point",
    "coordinates": [
      -63.69377,
      -29.50003
    ]
  }
}