{
  "type": "Feature",
  "properties": {
    "name": "Choristí",
    "country": "GR",
    "subdivision": "ESYE11",
    "timezone": "Europe/Athens"
  },
  "geometry": {
    "type": "Point",
    "coordinates": [
      24.20843,
      41.13056
    ]
  }
}