{
  "type": "Feature",
  "properties": {
    "name": "Kalampáki",
    "country": "GR",
    "subdivision": "ESYE11",
    "timezone": "Europe/Athens"
  },
  "geometry": {
    "type": "Point",
    "coordinates": [
      24.18333,
      41.05
    ]
  }
}