{
  "type": "Feature",
  "properties": {
    "name": "Kalí Vrýsi",
    "country": "GR",
    "subdivision": "ESYE11",
    "timezone": "Europe/Athens"
  },
  "geometry": {
    "type": "Point",
    "coordinates": [
      23.90667,
      41.14653
    ]
  }
}