{
  "type": "Feature",
  "properties": {
    "name": "Komotiní",
    "country": "GR",
    "subdivision": "ESYE11",
    "timezone": "Europe/Athens"
  },
  "geometry": {
    "type": "Point",
    "coordinates": [
      25.40535,
      41.11917
    ]
  }
}