{
  "type": "Feature",
  "properties": {
    "name": "Limenária",
    "country": "GR",
    "subdivision": "ESYE11",
    "timezone": "Europe/Athens"
  },
  "geometry": {
    "type": "Point",
    "coordinates": [
      24.5765,
      40.62741
    ]
  }
}