{
  "type": "Feature",
  "properties": {
    "name": "Lýkeio",
    "country": "GR",
    "subdivision": "ESYE11",
    "timezone": "Europe/Athens"
  },
  "geometry": {
    "type": "Point",
    "coordinates": [
      25.6857,
      41.06413
    ]
  }
}