{
  "type": "Feature",
  "properties": {
    "name": "Néa Péramos",
    "country": "GR",
    "subdivision": "ESYE11",
    "timezone": "Europe/Athens"
  },
  "geometry": {
    "type": "Point",
    "coordinates": [
      24.3013,
      40.83854
    ]
  }
}