{
  "type": "Feature",
  "properties": {
    "name": "Néa Výssa",
    "country": "GR",
    "subdivision": "ESYE11",
    "timezone": "Europe/Athens"
  },
  "geometry": {
    "type": "Point",
    "coordinates": [
      26.54318,
      41.58449
    ]
  }
}