{
  "type": "Feature",
  "properties": {
    "name": "Paralía Ofryníou",
    "country": "GR",
    "subdivision": "ESYE11",
    "timezone": "Europe/Athens"
  },
  "geometry": {
    "type": "Point",
    "coordinates": [
      23.90039,
      40.76663
    ]
  }
}