{
  "type": "Feature",
  "properties": {
    "name": "Petroússa",
    "country": "GR",
    "subdivision": "ESYE11",
    "timezone": "Europe/Athens"
  },
  "geometry": {
    "type": "Point",
    "coordinates": [
      24.01731,
      41.1947
    ]
  }
}