{
  "type": "Feature",
  "properties": {
    "name": "Souflí",
    "country": "GR",
    "subdivision": "ESYE11",
    "timezone": "Europe/Athens"
  },
  "geometry": {
    "type": "Point",
    "coordinates": [
      26.29944,
      41.19194
    ]
  }
}