{
  "type": "Feature",
  "properties": {
    "name": "Vólakas",
    "country": "GR",
    "subdivision": "ESYE11",
    "timezone": "Europe/Athens"
  },
  "geometry": {
    "type": "Point",
    "coordinates": [
      24.00215,
      41.31661
    ]
  }
}