{
  "type": "Feature",
  "properties": {
    "name": "Dorogobuzh",
    "country": "RU",
    "subdivision": "69",
    "timezone": "Europe/Moscow"
  },
  "geometry": {
    "type": "Point",
    "coordinates": [
      33.29722,
      54.915
    ]
  }
}