{
  "type": "Feature",
  "properties": {
    "name": "Dukhovshchina",
    "country": "RU",
    "subdivision": "69",
    "timezone": "Europe/Moscow"
  },
  "geometry": {
    "type": "Point",
    "coordinates": [
      32.4111,
      55.1919
    ]
  }
}