{
  "type": "Feature",
  "properties": {
    "name": "Yel’nya",
    "country": "RU",
    "subdivision": "69",
    "timezone": "Europe/Moscow"
  },
  "geometry": {
    "type": "Point",
    "coordinates": [
      33.18373,
      54.57864
    ]
  }
}