{
  "type": "Feature",
  "properties": {
    "name": "Yershichi",
    "country": "RU",
    "subdivision": "69",
    "timezone": "Europe/Moscow"
  },
  "geometry": {
    "type": "Point",
    "coordinates": [
      32.75417,
      53.6725
    ]
  }
}