{
  "type": "Feature",
  "properties": {
    "name": "Aianí",
    "country": "GR",
    "subdivision": "ESYE13",
    "timezone": "Europe/Athens"
  },
  "geometry": {
    "type": "Point",
    "coordinates": [
      21.81945,
      40.16381
    ]
  }
}