{
  "type": "Feature",
  "properties": {
    "name": "Ammochóri",
    "country": "GR",
    "subdivision": "ESYE13",
    "timezone": "Europe/Athens"
  },
  "geometry": {
    "type": "Point",
    "coordinates": [
      21.48458,
      40.78203
    ]
  }
}