{
  "type": "Feature",
  "properties": {
    "name": "Galatiní",
    "country": "GR",
    "subdivision": "ESYE13",
    "timezone": "Europe/Athens"
  },
  "geometry": {
    "type": "Point",
    "coordinates": [
      21.55148,
      40.31966
    ]
  }
}