{
  "type": "Feature",
  "properties": {
    "name": "Acámbaro",
    "country": "MX",
    "subdivision": "11",
    "timezone": "America/Mexico_City"
  },
  "geometry": {
    "type": "Point",
    "coordinates": [
      -100.72194,
      20.03085
    ]
  }
}