{
  "type": "Feature",
  "properties": {
    "name": "Ameche",
    "country": "MX",
    "subdivision": "11",
    "timezone": "America/Mexico_City"
  },
  "geometry": {
    "type": "Point",
    "coordinates": [
      -100.58367,
      20.55261
    ]
  }
}