{
  "type": "Feature",
  "properties": {
    "name": "Barrón",
    "country": "MX",
    "subdivision": "11",
    "timezone": "America/Mexico_City"
  },
  "geometry": {
    "type": "Point",
    "coordinates": [
      -101.08423,
      20.67667
    ]
  }
}