{
  "type": "Feature",
  "properties": {
    "name": "Cerano",
    "country": "MX",
    "subdivision": "11",
    "timezone": "America/Mexico_City"
  },
  "geometry": {
    "type": "Point",
    "coordinates": [
      -101.3871,
      20.10877
    ]
  }
}