{
  "type": "Feature",
  "properties": {
    "name": "Charco de Pantoja",
    "country": "MX",
    "subdivision": "11",
    "timezone": "America/Mexico_City"
  },
  "geometry": {
    "type": "Point",
    "coordinates": [
      -101.35436,
      20.38949
    ]
  }
}