{
  "type": "Feature",
  "properties": {
    "name": "Cieneguilla",
    "country": "MX",
    "subdivision": "11",
    "timezone": "America/Mexico_City"
  },
  "geometry": {
    "type": "Point",
    "coordinates": [
      -100.27389,
      21.24833
    ]
  }
}