{
  "type": "Feature",
  "properties": {
    "name": "Coachiti",
    "country": "MX",
    "subdivision": "11",
    "timezone": "America/Mexico_City"
  },
  "geometry": {
    "type": "Point",
    "coordinates": [
      -100.58944,
      20.55944
    ]
  }
}