{
  "type": "Feature",
  "properties": {
    "name": "Colonia Nuevo México",
    "country": "MX",
    "subdivision": "11",
    "timezone": "America/Mexico_City"
  },
  "geometry": {
    "type": "Point",
    "coordinates": [
      -101.48502,
      20.98475
    ]
  }
}