{
  "type": "Feature",
  "properties": {
    "name": "Ejido Jesús María",
    "country": "MX",
    "subdivision": "11",
    "timezone": "America/Mexico_City"
  },
  "geometry": {
    "type": "Point",
    "coordinates": [
      -100.91167,
      21.14194
    ]
  }
}