{
  "type": "Feature",
  "properties": {
    "name": "El Castillo",
    "country": "MX",
    "subdivision": "11",
    "timezone": "America/Mexico_City"
  },
  "geometry": {
    "type": "Point",
    "coordinates": [
      -100.49297,
      20.58072
    ]
  }
}