{
  "type": "Feature",
  "properties": {
    "name": "El Capulín",
    "country": "MX",
    "subdivision": "11",
    "timezone": "America/Mexico_City"
  },
  "geometry": {
    "type": "Point",
    "coordinates": [
      -100.98532,
      20.27536
    ]
  }
}