{
  "type": "Feature",
  "properties": {
    "name": "El Chinaco (El Pujido)",
    "country": "MX",
    "subdivision": "11",
    "timezone": "America/Mexico_City"
  },
  "geometry": {
    "type": "Point",
    "coordinates": [
      -100.91972,
      20.52222
    ]
  }
}