{
  "type": "Feature",
  "properties": {
    "name": "El Salvador (Ranchito San José del Carmen)",
    "country": "MX",
    "subdivision": "11",
    "timezone": "America/Mexico_City"
  },
  "geometry": {
    "type": "Point",
    "coordinates": [
      -100.87722,
      20.2875
    ]
  }
}