{
  "type": "Feature",
  "properties": {
    "name": "El Zapote",
    "country": "MX",
    "subdivision": "11",
    "timezone": "America/Mexico_City"
  },
  "geometry": {
    "type": "Point",
    "coordinates": [
      -101.04905,
      21.73563
    ]
  }
}