{
  "type": "Feature",
  "properties": {
    "name": "Estación de San Francisco",
    "country": "MX",
    "subdivision": "11",
    "timezone": "America/Mexico_City"
  },
  "geometry": {
    "type": "Point",
    "coordinates": [
      -101.82472,
      21.03722
    ]
  }
}