{
  "type": "Feature",
  "properties": {
    "name": "Estación Pénjamo",
    "country": "MX",
    "subdivision": "11",
    "timezone": "America/Mexico_City"
  },
  "geometry": {
    "type": "Point",
    "coordinates": [
      -101.69188,
      20.3947
    ]
  }
}