{
  "type": "Feature",
  "properties": {
    "name": "Ex-Hacienda del Copal",
    "country": "MX",
    "subdivision": "11",
    "timezone": "America/Mexico_City"
  },
  "geometry": {
    "type": "Point",
    "coordinates": [
      -101.33528,
      20.74083
    ]
  }
}