{
  "type": "Feature",
  "properties": {
    "name": "Fraccionamiento Villa Jardín",
    "country": "MX",
    "subdivision": "11",
    "timezone": "America/Mexico_City"
  },
  "geometry": {
    "type": "Point",
    "coordinates": [
      -101.85194,
      20.99167
    ]
  }
}