{
  "type": "Feature",
  "properties": {
    "name": "Guadalupe",
    "country": "MX",
    "subdivision": "11",
    "timezone": "America/Mexico_City"
  },
  "geometry": {
    "type": "Point",
    "coordinates": [
      -100.97645,
      21.71644
    ]
  }
}