{
  "type": "Feature",
  "properties": {
    "name": "Juan Martín",
    "country": "MX",
    "subdivision": "11",
    "timezone": "America/Mexico_City"
  },
  "geometry": {
    "type": "Point",
    "coordinates": [
      -100.74691,
      20.47301
    ]
  }
}