{
  "type": "Feature",
  "properties": {
    "name": "La Cruz del Palmar",
    "country": "MX",
    "subdivision": "11",
    "timezone": "America/Mexico_City"
  },
  "geometry": {
    "type": "Point",
    "coordinates": [
      -100.84354,
      20.96973
    ]
  }
}