{
  "type": "Feature",
  "properties": {
    "name": "La Ciénega",
    "country": "MX",
    "subdivision": "11",
    "timezone": "America/Mexico_City"
  },
  "geometry": {
    "type": "Point",
    "coordinates": [
      -100.48027,
      21.3005
    ]
  }
}