{
  "type": "Feature",
  "properties": {
    "name": "La Escondida",
    "country": "MX",
    "subdivision": "11",
    "timezone": "America/Mexico_City"
  },
  "geometry": {
    "type": "Point",
    "coordinates": [
      -101.53446,
      21.68723
    ]
  }
}