{
  "type": "Feature",
  "properties": {
    "name": "La Estrella",
    "country": "MX",
    "subdivision": "11",
    "timezone": "America/Mexico_City"
  },
  "geometry": {
    "type": "Point",
    "coordinates": [
      -101.92109,
      20.3905
    ]
  }
}