{
  "type": "Feature",
  "properties": {
    "name": "La Luz",
    "country": "MX",
    "subdivision": "11",
    "timezone": "America/Mexico_City"
  },
  "geometry": {
    "type": "Point",
    "coordinates": [
      -100.91742,
      20.28897
    ]
  }
}