{
  "type": "Feature",
  "properties": {
    "name": "La Moncada",
    "country": "MX",
    "subdivision": "11",
    "timezone": "America/Mexico_City"
  },
  "geometry": {
    "type": "Point",
    "coordinates": [
      -100.80502,
      20.28348
    ]
  }
}