{
  "type": "Feature",
  "properties": {
    "name": "La Palma",
    "country": "MX",
    "subdivision": "11",
    "timezone": "America/Mexico_City"
  },
  "geometry": {
    "type": "Point",
    "coordinates": [
      -100.69787,
      20.5156
    ]
  }
}