{
  "type": "Feature",
  "properties": {
    "name": "Laguna Larga de Cortés",
    "country": "MX",
    "subdivision": "11",
    "timezone": "America/Mexico_City"
  },
  "geometry": {
    "type": "Point",
    "coordinates": [
      -101.94062,
      20.3927
    ]
  }
}