{
  "type": "Feature",
  "properties": {
    "name": "Laguna Larga",
    "country": "MX",
    "subdivision": "11",
    "timezone": "America/Mexico_City"
  },
  "geometry": {
    "type": "Point",
    "coordinates": [
      -101.48451,
      20.54131
    ]
  }
}