{
  "type": "Feature",
  "properties": {
    "name": "Loma de Zempoala",
    "country": "MX",
    "subdivision": "11",
    "timezone": "America/Mexico_City"
  },
  "geometry": {
    "type": "Point",
    "coordinates": [
      -101.08023,
      20.29182
    ]
  }
}