{
  "type": "Feature",
  "properties": {
    "name": "Los Mancera",
    "country": "MX",
    "subdivision": "11",
    "timezone": "America/Mexico_City"
  },
  "geometry": {
    "type": "Point",
    "coordinates": [
      -100.80389,
      20.47028
    ]
  }
}