{
  "type": "Feature",
  "properties": {
    "name": "Los Lorenzos",
    "country": "MX",
    "subdivision": "11",
    "timezone": "America/Mexico_City"
  },
  "geometry": {
    "type": "Point",
    "coordinates": [
      -101.3758,
      21.07229
    ]
  }
}