{
  "type": "Feature",
  "properties": {
    "name": "Lucio Blanco (Los Gavilanes)",
    "country": "MX",
    "subdivision": "11",
    "timezone": "America/Mexico_City"
  },
  "geometry": {
    "type": "Point",
    "coordinates": [
      -101.55111,
      21.11528
    ]
  }
}