{
  "type": "Feature",
  "properties": {
    "name": "Maravatío del Encinal",
    "country": "MX",
    "subdivision": "11",
    "timezone": "America/Mexico_City"
  },
  "geometry": {
    "type": "Point",
    "coordinates": [
      -100.96211,
      20.20513
    ]
  }
}