{
  "type": "Feature",
  "properties": {
    "name": "Medio Sitio",
    "country": "MX",
    "subdivision": "11",
    "timezone": "America/Mexico_City"
  },
  "geometry": {
    "type": "Point",
    "coordinates": [
      -101.35689,
      20.86948
    ]
  }
}