{
  "type": "Feature",
  "properties": {
    "name": "Mezquite Gordo",
    "country": "MX",
    "subdivision": "11",
    "timezone": "America/Mexico_City"
  },
  "geometry": {
    "type": "Point",
    "coordinates": [
      -101.49277,
      20.81463
    ]
  }
}