{
  "type": "Feature",
  "properties": {
    "name": "Morales",
    "country": "MX",
    "subdivision": "11",
    "timezone": "America/Mexico_City"
  },
  "geometry": {
    "type": "Point",
    "coordinates": [
      -100.80932,
      20.77821
    ]
  }
}