{
  "type": "Feature",
  "properties": {
    "name": "Ocampo",
    "country": "MX",
    "subdivision": "11",
    "timezone": "America/Mexico_City"
  },
  "geometry": {
    "type": "Point",
    "coordinates": [
      -101.48012,
      21.64653
    ]
  }
}