{
  "type": "Feature",
  "properties": {
    "name": "Peñuelas",
    "country": "MX",
    "subdivision": "11",
    "timezone": "America/Mexico_City"
  },
  "geometry": {
    "type": "Point",
    "coordinates": [
      -101.85285,
      20.88039
    ]
  }
}