{
  "type": "Feature",
  "properties": {
    "name": "Presa Blanca",
    "country": "MX",
    "subdivision": "11",
    "timezone": "America/Mexico_City"
  },
  "geometry": {
    "type": "Point",
    "coordinates": [
      -100.79241,
      20.64146
    ]
  }
}