{
  "type": "Feature",
  "properties": {
    "name": "Rancho Nuevo de la Luz",
    "country": "MX",
    "subdivision": "11",
    "timezone": "America/Mexico_City"
  },
  "geometry": {
    "type": "Point",
    "coordinates": [
      -101.64573,
      20.96246
    ]
  }
}