{
  "type": "Feature",
  "properties": {
    "name": "Roque",
    "country": "MX",
    "subdivision": "11",
    "timezone": "America/Mexico_City"
  },
  "geometry": {
    "type": "Point",
    "coordinates": [
      -100.83727,
      20.58228
    ]
  }
}