{
  "type": "Feature",
  "properties": {
    "name": "Salamanca",
    "country": "MX",
    "subdivision": "11",
    "timezone": "America/Mexico_City"
  },
  "geometry": {
    "type": "Point",
    "coordinates": [
      -101.19154,
      20.57196
    ]
  }
}