{
  "type": "Feature",
  "properties": {
    "name": "San Juan Bautista Cacalote",
    "country": "MX",
    "subdivision": "11",
    "timezone": "America/Mexico_City"
  },
  "geometry": {
    "type": "Point",
    "coordinates": [
      -100.78833,
      20.34806
    ]
  }
}