{
  "type": "Feature",
  "properties": {
    "name": "San Pedro Tenango",
    "country": "MX",
    "subdivision": "11",
    "timezone": "America/Mexico_City"
  },
  "geometry": {
    "type": "Point",
    "coordinates": [
      -100.63247,
      20.50769
    ]
  }
}