{
  "type": "Feature",
  "properties": {
    "name": "San Agustín de las Flores",
    "country": "MX",
    "subdivision": "11",
    "timezone": "America/Mexico_City"
  },
  "geometry": {
    "type": "Point",
    "coordinates": [
      -101.4371,
      21.00727
    ]
  }
}