{
  "type": "Feature",
  "properties": {
    "name": "San Miguel del Arenal",
    "country": "MX",
    "subdivision": "11",
    "timezone": "America/Mexico_City"
  },
  "geometry": {
    "type": "Point",
    "coordinates": [
      -101.48556,
      20.99083
    ]
  }
}