{
  "type": "Feature",
  "properties": {
    "name": "San José Temascatío",
    "country": "MX",
    "subdivision": "11",
    "timezone": "America/Mexico_City"
  },
  "geometry": {
    "type": "Point",
    "coordinates": [
      -101.26028,
      20.69183
    ]
  }
}