{
  "type": "Feature",
  "properties": {
    "name": "San José de Cervera",
    "country": "MX",
    "subdivision": "11",
    "timezone": "America/Mexico_City"
  },
  "geometry": {
    "type": "Point",
    "coordinates": [
      -101.3025,
      20.96778
    ]
  }
}