{
  "type": "Feature",
  "properties": {
    "name": "San José el Nuevo",
    "country": "MX",
    "subdivision": "11",
    "timezone": "America/Mexico_City"
  },
  "geometry": {
    "type": "Point",
    "coordinates": [
      -100.77194,
      20.44389
    ]
  }
}