{
  "type": "Feature",
  "properties": {
    "name": "San Isidro de Gamboa",
    "country": "MX",
    "subdivision": "11",
    "timezone": "America/Mexico_City"
  },
  "geometry": {
    "type": "Point",
    "coordinates": [
      -100.52705,
      20.39501
    ]
  }
}