{
  "type": "Feature",
  "properties": {
    "name": "San Antonio Texas",
    "country": "MX",
    "subdivision": "11",
    "timezone": "America/Mexico_City"
  },
  "geometry": {
    "type": "Point",
    "coordinates": [
      -101.49,
      20.98556
    ]
  }
}