{
  "type": "Feature",
  "properties": {
    "name": "San Juan de Abajo",
    "country": "MX",
    "subdivision": "11",
    "timezone": "America/Mexico_City"
  },
  "geometry": {
    "type": "Point",
    "coordinates": [
      -101.63544,
      21.05623
    ]
  }
}