{
  "type": "Feature",
  "properties": {
    "name": "San Antonio Eménguaro",
    "country": "MX",
    "subdivision": "11",
    "timezone": "America/Mexico_City"
  },
  "geometry": {
    "type": "Point",
    "coordinates": [
      -100.87874,
      20.13997
    ]
  }
}