{
  "type": "Feature",
  "properties": {
    "name": "San Ignacio de Rivera (Ojo de Agua)",
    "country": "MX",
    "subdivision": "11",
    "timezone": "America/Mexico_City"
  },
  "geometry": {
    "type": "Point",
    "coordinates": [
      -101.46127,
      20.55926
    ]
  }
}