{
  "type": "Feature",
  "properties": {
    "name": "San Bartolo de Berrios",
    "country": "MX",
    "subdivision": "11",
    "timezone": "America/Mexico_City"
  },
  "geometry": {
    "type": "Point",
    "coordinates": [
      -101.06845,
      21.6124
    ]
  }
}