{
  "type": "Feature",
  "properties": {
    "name": "San Antonio Primero",
    "country": "MX",
    "subdivision": "11",
    "timezone": "America/Mexico_City"
  },
  "geometry": {
    "type": "Point",
    "coordinates": [
      -100.52844,
      21.09417
    ]
  }
}