{
  "type": "Feature",
  "properties": {
    "name": "San José de Guanajuato",
    "country": "MX",
    "subdivision": "11",
    "timezone": "America/Mexico_City"
  },
  "geometry": {
    "type": "Point",
    "coordinates": [
      -100.89277,
      20.55601
    ]
  }
}