{
  "type": "Feature",
  "properties": {
    "name": "San José Viborillas",
    "country": "MX",
    "subdivision": "11",
    "timezone": "America/Mexico_City"
  },
  "geometry": {
    "type": "Point",
    "coordinates": [
      -100.63361,
      20.56778
    ]
  }
}