{
  "type": "Feature",
  "properties": {
    "name": "Santiago Capitiro",
    "country": "MX",
    "subdivision": "11",
    "timezone": "America/Mexico_City"
  },
  "geometry": {
    "type": "Point",
    "coordinates": [
      -101.01767,
      20.30427
    ]
  }
}