{
  "type": "Feature",
  "properties": {
    "name": "Santa Rosa los Angeles",
    "country": "MX",
    "subdivision": "11",
    "timezone": "America/Mexico_City"
  },
  "geometry": {
    "type": "Point",
    "coordinates": [
      -100.92356,
      20.56585
    ]
  }
}