{
  "type": "Feature",
  "properties": {
    "name": "Santa Fe de la Purísima",
    "country": "MX",
    "subdivision": "11",
    "timezone": "America/Mexico_City"
  },
  "geometry": {
    "type": "Point",
    "coordinates": [
      -100.89278,
      20.49556
    ]
  }
}