{
  "type": "Feature",
  "properties": {
    "name": "Santa Rosa de Lima",
    "country": "MX",
    "subdivision": "11",
    "timezone": "America/Mexico_City"
  },
  "geometry": {
    "type": "Point",
    "coordinates": [
      -101.19723,
      21.07179
    ]
  }
}