{
  "type": "Feature",
  "properties": {
    "name": "Tamazula",
    "country": "MX",
    "subdivision": "11",
    "timezone": "America/Mexico_City"
  },
  "geometry": {
    "type": "Point",
    "coordinates": [
      -101.5533,
      20.44228
    ]
  }
}