{
  "type": "Feature",
  "properties": {
    "name": "Valencia de Cerro Gordo",
    "country": "MX",
    "subdivision": "11",
    "timezone": "America/Mexico_City"
  },
  "geometry": {
    "type": "Point",
    "coordinates": [
      -101.08173,
      20.60133
    ]
  }
}