{
  "type": "Feature",
  "properties": {
    "name": "Valencianita",
    "country": "MX",
    "subdivision": "11",
    "timezone": "America/Mexico_City"
  },
  "geometry": {
    "type": "Point",
    "coordinates": [
      -101.30223,
      20.74701
    ]
  }
}