{
  "type": "Feature",
  "properties": {
    "name": "Yerbabuena",
    "country": "MX",
    "subdivision": "11",
    "timezone": "America/Mexico_City"
  },
  "geometry": {
    "type": "Point",
    "coordinates": [
      -101.27448,
      20.96319
    ]
  }
}