{
  "type": "Feature",
  "properties": {
    "name": "Zapote de Palomas",
    "country": "MX",
    "subdivision": "11",
    "timezone": "America/Mexico_City"
  },
  "geometry": {
    "type": "Point",
    "coordinates": [
      -101.115,
      20.58444
    ]
  }
}