{
  "type": "Feature",
  "properties": {
    "name": "Färlöv",
    "country": "SE",
    "subdivision": "27",
    "timezone": "Europe/Stockholm"
  },
  "geometry": {
    "type": "Point",
    "coordinates": [
      14.08333,
      56.06667
    ]
  }
}