{
  "type": "Feature",
  "properties": {
    "name": "Hjärnarp",
    "country": "SE",
    "subdivision": "27",
    "timezone": "Europe/Stockholm"
  },
  "geometry": {
    "type": "Point",
    "coordinates": [
      12.91667,
      56.31667
    ]
  }
}