{
  "type": "Feature",
  "properties": {
    "name": "Hjärup",
    "country": "SE",
    "subdivision": "27",
    "timezone": "Europe/Stockholm"
  },
  "geometry": {
    "type": "Point",
    "coordinates": [
      13.13931,
      55.6688
    ]
  }
}