{
  "type": "Feature",
  "properties": {
    "name": "Höllviken",
    "country": "SE",
    "subdivision": "27",
    "timezone": "Europe/Stockholm"
  },
  "geometry": {
    "type": "Point",
    "coordinates": [
      12.9558,
      55.40982
    ]
  }
}