{
  "type": "Feature",
  "properties": {
    "name": "Köpingebro",
    "country": "SE",
    "subdivision": "27",
    "timezone": "Europe/Stockholm"
  },
  "geometry": {
    "type": "Point",
    "coordinates": [
      13.93453,
      55.45526
    ]
  }
}