{
  "type": "Feature",
  "properties": {
    "name": "Ödåkra",
    "country": "SE",
    "subdivision": "27",
    "timezone": "Europe/Stockholm"
  },
  "geometry": {
    "type": "Point",
    "coordinates": [
      12.7477,
      56.10412
    ]
  }
}