{
  "type": "Feature",
  "properties": {
    "name": "Påarp",
    "country": "SE",
    "subdivision": "27",
    "timezone": "Europe/Stockholm"
  },
  "geometry": {
    "type": "Point",
    "coordinates": [
      12.81667,
      56.03333
    ]
  }
}