{
  "type": "Feature",
  "properties": {
    "name": "Skivarp",
    "country": "SE",
    "subdivision": "27",
    "timezone": "Europe/Stockholm"
  },
  "geometry": {
    "type": "Point",
    "coordinates": [
      13.56667,
      55.41667
    ]
  }
}