{
  "type": "Feature",
  "properties": {
    "name": "Stångby",
    "country": "SE",
    "subdivision": "27",
    "timezone": "Europe/Stockholm"
  },
  "geometry": {
    "type": "Point",
    "coordinates": [
      13.19797,
      55.7503
    ]
  }
}