{
  "type": "Feature",
  "properties": {
    "name": "Stehag",
    "country": "SE",
    "subdivision": "27",
    "timezone": "Europe/Stockholm"
  },
  "geometry": {
    "type": "Point",
    "coordinates": [
      13.39577,
      55.90188
    ]
  }
}