{
  "type": "Feature",
  "properties": {
    "name": "Ystad",
    "country": "SE",
    "subdivision": "27",
    "timezone": "Europe/Stockholm"
  },
  "geometry": {
    "type": "Point",
    "coordinates": [
      13.82041,
      55.42966
    ]
  }
}