{
  "type": "Feature",
  "properties": {
    "name": "Tezu",
    "country": "IN",
    "subdivision": "30",
    "timezone": "Asia/Kolkata"
  },
  "geometry": {
    "type": "Point",
    "coordinates": [
      96.12882,
      27.91256
    ]
  }
}