{
  "type": "Feature",
  "properties": {
    "name": "De-Kastri",
    "country": "RU",
    "subdivision": "30",
    "timezone": "Asia/Vladivostok"
  },
  "geometry": {
    "type": "Point",
    "coordinates": [
      140.76986,
      51.47543
    ]
  }
}