{
  "type": "Feature",
  "properties": {
    "name": "Khabarovsk Vtoroy",
    "country": "RU",
    "subdivision": "30",
    "timezone": "Asia/Vladivostok"
  },
  "geometry": {
    "type": "Point",
    "coordinates": [
      135.13329,
      48.43776
    ]
  }
}