{
  "type": "Feature",
  "properties": {
    "name": "Komsomolsk-on-Amur",
    "country": "RU",
    "subdivision": "30",
    "timezone": "Asia/Vladivostok"
  },
  "geometry": {
    "type": "Point",
    "coordinates": [
      137.00995,
      50.55034
    ]
  }
}