{
  "type": "Feature",
  "properties": {
    "name": "Litovko",
    "country": "RU",
    "subdivision": "30",
    "timezone": "Asia/Vladivostok"
  },
  "geometry": {
    "type": "Point",
    "coordinates": [
      135.17401,
      49.23754
    ]
  }
}