{
  "type": "Feature",
  "properties": {
    "name": "Tyrma",
    "country": "RU",
    "subdivision": "30",
    "timezone": "Asia/Vladivostok"
  },
  "geometry": {
    "type": "Point",
    "coordinates": [
      132.15011,
      50.0477
    ]
  }
}