{
  "type": "Feature",
  "properties": {
    "name": "Danshui",
    "country": "CN",
    "subdivision": "30",
    "timezone": "Asia/Shanghai"
  },
  "geometry": {
    "type": "Point",
    "coordinates": [
      114.46716,
      22.7984
    ]
  }
}