{
  "type": "Feature",
  "properties": {
    "name": "Huizhou",
    "country": "CN",
    "subdivision": "30",
    "timezone": "Asia/Shanghai"
  },
  "geometry": {
    "type": "Point",
    "coordinates": [
      114.41523,
      23.11147
    ]
  }
}