{
  "type": "Feature",
  "properties": {
    "name": "Shilong",
    "country": "CN",
    "subdivision": "30",
    "timezone": "Asia/Shanghai"
  },
  "geometry": {
    "type": "Point",
    "coordinates": [
      113.84722,
      23.11444
    ]
  }
}