{
  "type": "Feature",
  "properties": {
    "name": "Shiqiao",
    "country": "CN",
    "subdivision": "30",
    "timezone": "Asia/Shanghai"
  },
  "geometry": {
    "type": "Point",
    "coordinates": [
      113.35769,
      22.9464
    ]
  }
}