{
  "type": "Feature",
  "properties": {
    "name": "Shixing",
    "country": "CN",
    "subdivision": "30",
    "timezone": "Asia/Shanghai"
  },
  "geometry": {
    "type": "Point",
    "coordinates": [
      114.06572,
      24.94824
    ]
  }
}