{
  "type": "Feature",
  "properties": {
    "name": "Xinhui",
    "country": "CN",
    "subdivision": "30",
    "timezone": "Asia/Shanghai"
  },
  "geometry": {
    "type": "Point",
    "coordinates": [
      113.0482,
      22.456
    ]
  }
}