{
  "type": "Feature",
  "properties": {
    "name": "Kaffrine",
    "country": "SN",
    "subdivision": "16",
    "timezone": "Africa/Dakar"
  },
  "geometry": {
    "type": "Point",
    "coordinates": [
      -15.5508,
      14.10594
    ]
  }
}