{
  "type": "Feature",
  "properties": {
    "name": "Brod",
    "country": "BA",
    "subdivision": "02",
    "timezone": "Europe/Sarajevo"
  },
  "geometry": {
    "type": "Point",
    "coordinates": [
      17.98722,
      45.13747
    ]
  }
}