{
  "type": "Feature",
  "properties": {
    "name": "Dvorovi",
    "country": "BA",
    "subdivision": "02",
    "timezone": "Europe/Sarajevo"
  },
  "geometry": {
    "type": "Point",
    "coordinates": [
      19.25999,
      44.80753
    ]
  }
}