{
  "type": "Feature",
  "properties": {
    "name": "Gradiška",
    "country": "BA",
    "subdivision": "02",
    "timezone": "Europe/Sarajevo"
  },
  "geometry": {
    "type": "Point",
    "coordinates": [
      17.25453,
      45.14484
    ]
  }
}