{
  "type": "Feature",
  "properties": {
    "name": "Ljubinje",
    "country": "BA",
    "subdivision": "02",
    "timezone": "Europe/Sarajevo"
  },
  "geometry": {
    "type": "Point",
    "coordinates": [
      18.08702,
      42.9512
    ]
  }
}