{
  "type": "Feature",
  "properties": {
    "name": "Marićka",
    "country": "BA",
    "subdivision": "02",
    "timezone": "Europe/Sarajevo"
  },
  "geometry": {
    "type": "Point",
    "coordinates": [
      16.8551,
      44.86801
    ]
  }
}