{
  "type": "Feature",
  "properties": {
    "name": "Rudo",
    "country": "BA",
    "subdivision": "02",
    "timezone": "Europe/Sarajevo"
  },
  "geometry": {
    "type": "Point",
    "coordinates": [
      19.36719,
      43.61781
    ]
  }
}