{
  "type": "Feature",
  "properties": {
    "name": "Višegrad",
    "country": "BA",
    "subdivision": "02",
    "timezone": "Europe/Sarajevo"
  },
  "geometry": {
    "type": "Point",
    "coordinates": [
      19.29256,
      43.7826
    ]
  }
}