{
  "type": "Feature",
  "properties": {
    "name": "Živinice",
    "country": "BA",
    "subdivision": "02",
    "timezone": "Europe/Sarajevo"
  },
  "geometry": {
    "type": "Point",
    "coordinates": [
      17.37357,
      44.54765
    ]
  }
}