{
  "type": "Feature",
  "properties": {
    "name": "Arauquita",
    "country": "CO",
    "subdivision": "03",
    "timezone": "America/Bogota"
  },
  "geometry": {
    "type": "Point",
    "coordinates": [
      -71.42806,
      7.02917
    ]
  }
}