{
  "type": "Feature",
  "properties": {
    "name": "Tame",
    "country": "CO",
    "subdivision": "03",
    "timezone": "America/Bogota"
  },
  "geometry": {
    "type": "Point",
    "coordinates": [
      -71.73618,
      6.46065
    ]
  }
}