{
  "type": "Feature",
  "properties": {
    "name": "Parbatipur",
    "country": "BD",
    "subdivision": "87",
    "timezone": "Asia/Dhaka"
  },
  "geometry": {
    "type": "Point",
    "coordinates": [
      88.93093,
      25.66369
    ]
  }
}