{
  "type": "Feature",
  "properties": {
    "name": "Rangpur",
    "country": "BD",
    "subdivision": "87",
    "timezone": "Asia/Dhaka"
  },
  "geometry": {
    "type": "Point",
    "coordinates": [
      89.25166,
      25.74664
    ]
  }
}