{
  "type": "Feature",
  "properties": {
    "name": "Funadhoo",
    "country": "MV",
    "subdivision": "45",
    "timezone": "Indian/Maldives"
  },
  "geometry": {
    "type": "Point",
    "coordinates": [
      73.29013,
      6.15091
    ]
  }
}