{
  "type": "Feature",
  "properties": {
    "name": "Wanju",
    "country": "KR",
    "subdivision": "03",
    "timezone": "Asia/Seoul"
  },
  "geometry": {
    "type": "Point",
    "coordinates": [
      127.14752,
      35.84509
    ]
  }
}