{
  "type": "Feature",
  "properties": {
    "name": "Quthing",
    "country": "LS",
    "subdivision": "18",
    "timezone": "Africa/Maseru"
  },
  "geometry": {
    "type": "Point",
    "coordinates": [
      27.70027,
      -30.40001
    ]
  }
}