{
  "type": "Feature",
  "properties": {
    "name": "Innoshima",
    "country": "JP",
    "subdivision": "11",
    "timezone": "Asia/Tokyo"
  },
  "geometry": {
    "type": "Point",
    "coordinates": [
      133.18333,
      34.28333
    ]
  }
}