{
  "type": "Feature",
  "properties": {
    "name": "Kerema",
    "country": "PG",
    "subdivision": "02",
    "timezone": "Pacific/Port_Moresby"
  },
  "geometry": {
    "type": "Point",
    "coordinates": [
      145.77278,
      -7.96028
    ]
  }
}