{
  "type": "Feature",
  "properties": {
    "name": "Bjelovar",
    "country": "HR",
    "subdivision": "01",
    "timezone": "Europe/Zagreb"
  },
  "geometry": {
    "type": "Point",
    "coordinates": [
      16.84889,
      45.89861
    ]
  }
}