{
  "type": "Feature",
  "properties": {
    "name": "Dežanovac",
    "country": "HR",
    "subdivision": "01",
    "timezone": "Europe/Zagreb"
  },
  "geometry": {
    "type": "Point",
    "coordinates": [
      17.08667,
      45.57056
    ]
  }
}