{
  "type": "Feature",
  "properties": {
    "name": "Rovišće",
    "country": "HR",
    "subdivision": "01",
    "timezone": "Europe/Zagreb"
  },
  "geometry": {
    "type": "Point",
    "coordinates": [
      16.735,
      45.94472
    ]
  }
}