{
  "type": "Feature",
  "properties": {
    "name": "Guinguinéo",
    "country": "SN",
    "subdivision": "09",
    "timezone": "Africa/Dakar"
  },
  "geometry": {
    "type": "Point",
    "coordinates": [
      -15.95,
      14.26667
    ]
  }
}