{
  "type": "Feature",
  "properties": {
    "name": "Penacova",
    "country": "PT",
    "subdivision": "07",
    "timezone": "Europe/Lisbon"
  },
  "geometry": {
    "type": "Point",
    "coordinates": [
      -8.28237,
      40.26884
    ]
  }
}