{
  "type": "Feature",
  "properties": {
    "name": "Soure",
    "country": "PT",
    "subdivision": "07",
    "timezone": "Europe/Lisbon"
  },
  "geometry": {
    "type": "Point",
    "coordinates": [
      -8.62605,
      40.05989
    ]
  }
}