{
  "type": "Feature",
  "properties": {
    "name": "Moïssala",
    "country": "TD",
    "subdivision": "19",
    "timezone": "Africa/Ndjamena"
  },
  "geometry": {
    "type": "Point",
    "coordinates": [
      17.7663,
      8.3404
    ]
  }
}