{
  "type": "Feature",
  "properties": {
    "name": "Palmarejo",
    "country": "PR",
    "subdivision": "043",
    "timezone": "America/Puerto_Rico"
  },
  "geometry": {
    "type": "Point",
    "coordinates": [
      -66.32545,
      18.06802
    ]
  }
}