{
  "type": "Feature",
  "properties": {
    "name": "Arês",
    "country": "BR",
    "subdivision": "22",
    "timezone": "America/Fortaleza"
  },
  "geometry": {
    "type": "Point",
    "coordinates": [
      -35.16028,
      -6.19444
    ]
  }
}