{
  "type": "Feature",
  "properties": {
    "name": "Jucurutu",
    "country": "BR",
    "subdivision": "22",
    "timezone": "America/Fortaleza"
  },
  "geometry": {
    "type": "Point",
    "coordinates": [
      -37.02028,
      -6.03389
    ]
  }
}