{
  "type": "Feature",
  "properties": {
    "name": "Parelhas",
    "country": "BR",
    "subdivision": "22",
    "timezone": "America/Fortaleza"
  },
  "geometry": {
    "type": "Point",
    "coordinates": [
      -36.6575,
      -6.68778
    ]
  }
}