{
  "type": "Feature",
  "properties": {
    "name": "Pedro Velho",
    "country": "BR",
    "subdivision": "22",
    "timezone": "America/Fortaleza"
  },
  "geometry": {
    "type": "Point",
    "coordinates": [
      -35.22139,
      -6.43917
    ]
  }
}