{
  "type": "Feature",
  "properties": {
    "name": "Santa Cruz",
    "country": "BR",
    "subdivision": "22",
    "timezone": "America/Fortaleza"
  },
  "geometry": {
    "type": "Point",
    "coordinates": [
      -36.02278,
      -6.22944
    ]
  }
}