{
  "type": "Feature",
  "properties": {
    "name": "São José de Mipibu",
    "country": "BR",
    "subdivision": "22",
    "timezone": "America/Fortaleza"
  },
  "geometry": {
    "type": "Point",
    "coordinates": [
      -35.23778,
      -6.07472
    ]
  }
}