{
  "type": "Feature",
  "properties": {
    "name": "São Gonçalo do Amarante",
    "country": "BR",
    "subdivision": "22",
    "timezone": "America/Fortaleza"
  },
  "geometry": {
    "type": "Point",
    "coordinates": [
      -35.32944,
      -5.79333
    ]
  }
}