{
  "type": "Feature",
  "properties": {
    "name": "São Paulo do Potengi",
    "country": "BR",
    "subdivision": "22",
    "timezone": "America/Fortaleza"
  },
  "geometry": {
    "type": "Point",
    "coordinates": [
      -35.76278,
      -5.895
    ]
  }
}