{
  "type": "Feature",
  "properties": {
    "name": "Severiano Melo",
    "country": "BR",
    "subdivision": "22",
    "timezone": "America/Fortaleza"
  },
  "geometry": {
    "type": "Point",
    "coordinates": [
      -37.95778,
      -5.77722
    ]
  }
}