{
  "type": "Feature",
  "properties": {
    "name": "Upanema",
    "country": "BR",
    "subdivision": "22",
    "timezone": "America/Fortaleza"
  },
  "geometry": {
    "type": "Point",
    "coordinates": [
      -37.25778,
      -5.64194
    ]
  }
}