{
  "type": "Feature",
  "properties": {
    "name": "Clement Town",
    "country": "IN",
    "subdivision": "39",
    "timezone": "Asia/Kolkata"
  },
  "geometry": {
    "type": "Point",
    "coordinates": [
      78.00862,
      30.26361
    ]
  }
}