{
  "type": "Feature",
  "properties": {
    "name": "Doiwāla",
    "country": "IN",
    "subdivision": "39",
    "timezone": "Asia/Kolkata"
  },
  "geometry": {
    "type": "Point",
    "coordinates": [
      78.11659,
      30.17667
    ]
  }
}