{
  "type": "Feature",
  "properties": {
    "name": "Kashipur",
    "country": "IN",
    "subdivision": "39",
    "timezone": "Asia/Kolkata"
  },
  "geometry": {
    "type": "Point",
    "coordinates": [
      78.95693,
      29.21399
    ]
  }
}