{
  "type": "Feature",
  "properties": {
    "name": "RÄnikhet",
    "country": "IN",
    "subdivision": "39",
    "timezone": "Asia/Kolkata"
  },
  "geometry": {
    "type": "Point",
    "coordinates": [
      79.43229,
      29.64082
    ]
  }
}