{
  "type": "Feature",
  "properties": {
    "name": "SitÄrganj",
    "country": "IN",
    "subdivision": "39",
    "timezone": "Asia/Kolkata"
  },
  "geometry": {
    "type": "Point",
    "coordinates": [
      79.70436,
      28.9293
    ]
  }
}