{
  "type": "Feature",
  "properties": {
    "name": "Jaru",
    "country": "BR",
    "subdivision": "24",
    "timezone": "America/Porto_Velho"
  },
  "geometry": {
    "type": "Point",
    "coordinates": [
      -62.46639,
      -10.43889
    ]
  }
}