{
  "type": "Feature",
  "properties": {
    "name": "Ramsey",
    "country": "IM",
    "subdivision": "9782191",
    "timezone": "Europe/Isle_of_Man"
  },
  "geometry": {
    "type": "Point",
    "coordinates": [
      -4.38526,
      54.32273
    ]
  }
}