{
  "type": "Feature",
  "properties": {
    "name": "Vana-Antsla",
    "country": "EE",
    "subdivision": "21",
    "timezone": "Europe/Tallinn"
  },
  "geometry": {
    "type": "Point",
    "coordinates": [
      26.53222,
      57.86611
    ]
  }
}