{
  "type": "Feature",
  "properties": {
    "name": "Totogalpa",
    "country": "NI",
    "subdivision": "09",
    "timezone": "America/Managua"
  },
  "geometry": {
    "type": "Point",
    "coordinates": [
      -86.49254,
      13.56284
    ]
  }
}