{
  "type": "Feature",
  "properties": {
    "name": "Gamboula",
    "country": "CF",
    "subdivision": "04",
    "timezone": "Africa/Bangui"
  },
  "geometry": {
    "type": "Point",
    "coordinates": [
      15.13926,
      4.11775
    ]
  }
}