{
  "type": "Feature",
  "properties": {
    "name": "Weno",
    "country": "FM",
    "subdivision": "03",
    "timezone": "Pacific/Chuuk"
  },
  "geometry": {
    "type": "Point",
    "coordinates": [
      151.84135,
      7.44648
    ]
  }
}