{
  "type": "Feature",
  "properties": {
    "name": "Chāībāsa",
    "country": "IN",
    "subdivision": "38",
    "timezone": "Asia/Kolkata"
  },
  "geometry": {
    "type": "Point",
    "coordinates": [
      85.80249,
      22.55038
    ]
  }
}