{
  "type": "Feature",
  "properties": {
    "name": "Chākuliā",
    "country": "IN",
    "subdivision": "38",
    "timezone": "Asia/Kolkata"
  },
  "geometry": {
    "type": "Point",
    "coordinates": [
      86.71793,
      22.48301
    ]
  }
}