{
  "type": "Feature",
  "properties": {
    "name": "Chakradharpur",
    "country": "IN",
    "subdivision": "38",
    "timezone": "Asia/Kolkata"
  },
  "geometry": {
    "type": "Point",
    "coordinates": [
      85.62892,
      22.67611
    ]
  }
}