{
  "type": "Feature",
  "properties": {
    "name": "Gumia",
    "country": "IN",
    "subdivision": "38",
    "timezone": "Asia/Kolkata"
  },
  "geometry": {
    "type": "Point",
    "coordinates": [
      85.82523,
      23.7975
    ]
  }
}