{
  "type": "Feature",
  "properties": {
    "name": "Madhupur",
    "country": "IN",
    "subdivision": "38",
    "timezone": "Asia/Kolkata"
  },
  "geometry": {
    "type": "Point",
    "coordinates": [
      86.63929,
      24.27419
    ]
  }
}