{
  "type": "Feature",
  "properties": {
    "name": "SÄhibganj",
    "country": "IN",
    "subdivision": "38",
    "timezone": "Asia/Kolkata"
  },
  "geometry": {
    "type": "Point",
    "coordinates": [
      87.63481,
      25.24425
    ]
  }
}