{
  "type": "Feature",
  "properties": {
    "name": "Sāruberā",
    "country": "IN",
    "subdivision": "38",
    "timezone": "Asia/Kolkata"
  },
  "geometry": {
    "type": "Point",
    "coordinates": [
      85.99628,
      23.81813
    ]
  }
}