{
  "type": "Feature",
  "properties": {
    "name": "Sini",
    "country": "IN",
    "subdivision": "38",
    "timezone": "Asia/Kolkata"
  },
  "geometry": {
    "type": "Point",
    "coordinates": [
      85.94543,
      22.79325
    ]
  }
}