{
  "type": "Feature",
  "properties": {
    "name": "Amasra",
    "country": "TR",
    "subdivision": "87",
    "timezone": "Europe/Istanbul"
  },
  "geometry": {
    "type": "Point",
    "coordinates": [
      32.38633,
      41.74633
    ]
  }
}