{
  "type": "Feature",
  "properties": {
    "name": "Tutong",
    "country": "BN",
    "subdivision": "04",
    "timezone": "Asia/Brunei"
  },
  "geometry": {
    "type": "Point",
    "coordinates": [
      114.64917,
      4.80278
    ]
  }
}