{
  "type": "Feature",
  "properties": {
    "name": "Markovac Našički",
    "country": "HR",
    "subdivision": "10",
    "timezone": "Europe/Zagreb"
  },
  "geometry": {
    "type": "Point",
    "coordinates": [
      18.12556,
      45.49389
    ]
  }
}