{
  "type": "Feature",
  "properties": {
    "name": "Osijek",
    "country": "HR",
    "subdivision": "10",
    "timezone": "Europe/Zagreb"
  },
  "geometry": {
    "type": "Point",
    "coordinates": [
      18.69389,
      45.55111
    ]
  }
}