{
  "type": "Feature",
  "properties": {
    "name": "Sarvaš",
    "country": "HR",
    "subdivision": "10",
    "timezone": "Europe/Zagreb"
  },
  "geometry": {
    "type": "Point",
    "coordinates": [
      18.8375,
      45.52722
    ]
  }
}