{
  "type": "Feature",
  "properties": {
    "name": "Široko Polje",
    "country": "HR",
    "subdivision": "10",
    "timezone": "Europe/Zagreb"
  },
  "geometry": {
    "type": "Point",
    "coordinates": [
      18.4725,
      45.40528
    ]
  }
}