{
  "type": "Feature",
  "properties": {
    "name": "Viljevo",
    "country": "HR",
    "subdivision": "10",
    "timezone": "Europe/Zagreb"
  },
  "geometry": {
    "type": "Point",
    "coordinates": [
      18.06306,
      45.75139
    ]
  }
}