{
  "type": "Feature",
  "properties": {
    "name": "Arzon",
    "country": "FR",
    "subdivision": "53",
    "timezone": "Europe/Paris"
  },
  "geometry": {
    "type": "Point",
    "coordinates": [
      -2.89588,
      47.54943
    ]
  }
}