{
  "type": "Feature",
  "properties": {
    "name": "Bains-sur-Oust",
    "country": "FR",
    "subdivision": "53",
    "timezone": "Europe/Paris"
  },
  "geometry": {
    "type": "Point",
    "coordinates": [
      -2.07199,
      47.70335
    ]
  }
}