{
  "type": "Feature",
  "properties": {
    "name": "Belle-Isle-en-Terre",
    "country": "FR",
    "subdivision": "53",
    "timezone": "Europe/Paris"
  },
  "geometry": {
    "type": "Point",
    "coordinates": [
      -3.39583,
      48.54477
    ]
  }
}