{
  "type": "Feature",
  "properties": {
    "name": "Berrien",
    "country": "FR",
    "subdivision": "53",
    "timezone": "Europe/Paris"
  },
  "geometry": {
    "type": "Point",
    "coordinates": [
      -3.7518,
      48.40342
    ]
  }
}