{
  "type": "Feature",
  "properties": {
    "name": "Betton",
    "country": "FR",
    "subdivision": "53",
    "timezone": "Europe/Paris"
  },
  "geometry": {
    "type": "Point",
    "coordinates": [
      -1.6448,
      48.1827
    ]
  }
}