{
  "type": "Feature",
  "properties": {
    "name": "Beuzec-Cap-Sizun",
    "country": "FR",
    "subdivision": "53",
    "timezone": "Europe/Paris"
  },
  "geometry": {
    "type": "Point",
    "coordinates": [
      -4.51189,
      48.07556
    ]
  }
}