{
  "type": "Feature",
  "properties": {
    "name": "Binic",
    "country": "FR",
    "subdivision": "53",
    "timezone": "Europe/Paris"
  },
  "geometry": {
    "type": "Point",
    "coordinates": [
      -2.82602,
      48.60074
    ]
  }
}