{
  "type": "Feature",
  "properties": {
    "name": "Campénéac",
    "country": "FR",
    "subdivision": "53",
    "timezone": "Europe/Paris"
  },
  "geometry": {
    "type": "Point",
    "coordinates": [
      -2.29479,
      47.95808
    ]
  }
}