{
  "type": "Feature",
  "properties": {
    "name": "Caudan",
    "country": "FR",
    "subdivision": "53",
    "timezone": "Europe/Paris"
  },
  "geometry": {
    "type": "Point",
    "coordinates": [
      -3.34255,
      47.80995
    ]
  }
}