{
  "type": "Feature",
  "properties": {
    "name": "Caulnes",
    "country": "FR",
    "subdivision": "53",
    "timezone": "Europe/Paris"
  },
  "geometry": {
    "type": "Point",
    "coordinates": [
      -2.15444,
      48.28893
    ]
  }
}