{
  "type": "Feature",
  "properties": {
    "name": "Châtillon-sur-Seiche",
    "country": "FR",
    "subdivision": "53",
    "timezone": "Europe/Paris"
  },
  "geometry": {
    "type": "Point",
    "coordinates": [
      -1.67114,
      48.03448
    ]
  }
}