{
  "type": "Feature",
  "properties": {
    "name": "Cintré",
    "country": "FR",
    "subdivision": "53",
    "timezone": "Europe/Paris"
  },
  "geometry": {
    "type": "Point",
    "coordinates": [
      -1.87153,
      48.10569
    ]
  }
}