{
  "type": "Feature",
  "properties": {
    "name": "Cléden-Poher",
    "country": "FR",
    "subdivision": "53",
    "timezone": "Europe/Paris"
  },
  "geometry": {
    "type": "Point",
    "coordinates": [
      -3.66925,
      48.23575
    ]
  }
}