{
  "type": "Feature",
  "properties": {
    "name": "Clohars-Fouesnant",
    "country": "FR",
    "subdivision": "53",
    "timezone": "Europe/Paris"
  },
  "geometry": {
    "type": "Point",
    "coordinates": [
      -4.06814,
      47.89756
    ]
  }
}