{
  "type": "Feature",
  "properties": {
    "name": "Combrit",
    "country": "FR",
    "subdivision": "53",
    "timezone": "Europe/Paris"
  },
  "geometry": {
    "type": "Point",
    "coordinates": [
      -4.16051,
      47.88719
    ]
  }
}