{
  "type": "Feature",
  "properties": {
    "name": "Corlay",
    "country": "FR",
    "subdivision": "53",
    "timezone": "Europe/Paris"
  },
  "geometry": {
    "type": "Point",
    "coordinates": [
      -3.05737,
      48.31649
    ]
  }
}