{
  "type": "Feature",
  "properties": {
    "name": "Epiniac",
    "country": "FR",
    "subdivision": "53",
    "timezone": "Europe/Paris"
  },
  "geometry": {
    "type": "Point",
    "coordinates": [
      -1.69751,
      48.51023
    ]
  }
}