{
  "type": "Feature",
  "properties": {
    "name": "Ergué-Gabéric",
    "country": "FR",
    "subdivision": "53",
    "timezone": "Europe/Paris"
  },
  "geometry": {
    "type": "Point",
    "coordinates": [
      -4.02438,
      47.99657
    ]
  }
}