{
  "type": "Feature",
  "properties": {
    "name": "Gosné",
    "country": "FR",
    "subdivision": "53",
    "timezone": "Europe/Paris"
  },
  "geometry": {
    "type": "Point",
    "coordinates": [
      -1.46534,
      48.24666
    ]
  }
}