{
  "type": "Feature",
  "properties": {
    "name": "Guémené-sur-Scorff",
    "country": "FR",
    "subdivision": "53",
    "timezone": "Europe/Paris"
  },
  "geometry": {
    "type": "Point",
    "coordinates": [
      -3.20456,
      48.06791
    ]
  }
}