{
  "type": "Feature",
  "properties": {
    "name": "Guidel-Plage",
    "country": "FR",
    "subdivision": "53",
    "timezone": "Europe/Paris"
  },
  "geometry": {
    "type": "Point",
    "coordinates": [
      -3.5218,
      47.76768
    ]
  }
}