{
  "type": "Feature",
  "properties": {
    "name": "Guignen",
    "country": "FR",
    "subdivision": "53",
    "timezone": "Europe/Paris"
  },
  "geometry": {
    "type": "Point",
    "coordinates": [
      -1.86298,
      47.92092
    ]
  }
}