{
  "type": "Feature",
  "properties": {
    "name": "Guingamp",
    "country": "FR",
    "subdivision": "53",
    "timezone": "Europe/Paris"
  },
  "geometry": {
    "type": "Point",
    "coordinates": [
      -3.15289,
      48.56259
    ]
  }
}