{
  "type": "Feature",
  "properties": {
    "name": "La Gouesnière",
    "country": "FR",
    "subdivision": "53",
    "timezone": "Europe/Paris"
  },
  "geometry": {
    "type": "Point",
    "coordinates": [
      -1.89516,
      48.60445
    ]
  }
}