{
  "type": "Feature",
  "properties": {
    "name": "Landerneau",
    "country": "FR",
    "subdivision": "53",
    "timezone": "Europe/Paris"
  },
  "geometry": {
    "type": "Point",
    "coordinates": [
      -4.25175,
      48.4515
    ]
  }
}