{
  "type": "Feature",
  "properties": {
    "name": "Lanvollon",
    "country": "FR",
    "subdivision": "53",
    "timezone": "Europe/Paris"
  },
  "geometry": {
    "type": "Point",
    "coordinates": [
      -2.98597,
      48.63116
    ]
  }
}