{
  "type": "Feature",
  "properties": {
    "name": "Larmor-Baden",
    "country": "FR",
    "subdivision": "53",
    "timezone": "Europe/Paris"
  },
  "geometry": {
    "type": "Point",
    "coordinates": [
      -2.89723,
      47.58724
    ]
  }
}