{
  "type": "Feature",
  "properties": {
    "name": "Le Faou",
    "country": "FR",
    "subdivision": "53",
    "timezone": "Europe/Paris"
  },
  "geometry": {
    "type": "Point",
    "coordinates": [
      -4.17927,
      48.29456
    ]
  }
}