{
  "type": "Feature",
  "properties": {
    "name": "Le Pertre",
    "country": "FR",
    "subdivision": "53",
    "timezone": "Europe/Paris"
  },
  "geometry": {
    "type": "Point",
    "coordinates": [
      -1.03735,
      48.03373
    ]
  }
}