{
  "type": "Feature",
  "properties": {
    "name": "Locquémeau",
    "country": "FR",
    "subdivision": "53",
    "timezone": "Europe/Paris"
  },
  "geometry": {
    "type": "Point",
    "coordinates": [
      -3.56374,
      48.72409
    ]
  }
}