{
  "type": "Feature",
  "properties": {
    "name": "Malansac",
    "country": "FR",
    "subdivision": "53",
    "timezone": "Europe/Paris"
  },
  "geometry": {
    "type": "Point",
    "coordinates": [
      -2.29674,
      47.67739
    ]
  }
}