{
  "type": "Feature",
  "properties": {
    "name": "Melgven",
    "country": "FR",
    "subdivision": "53",
    "timezone": "Europe/Paris"
  },
  "geometry": {
    "type": "Point",
    "coordinates": [
      -3.83501,
      47.90648
    ]
  }
}