{
  "type": "Feature",
  "properties": {
    "name": "Messac",
    "country": "FR",
    "subdivision": "53",
    "timezone": "Europe/Paris"
  },
  "geometry": {
    "type": "Point",
    "coordinates": [
      -1.80892,
      47.8245
    ]
  }
}