{
  "type": "Feature",
  "properties": {
    "name": "Miniac-Morvan",
    "country": "FR",
    "subdivision": "53",
    "timezone": "Europe/Paris"
  },
  "geometry": {
    "type": "Point",
    "coordinates": [
      -1.89976,
      48.51425
    ]
  }
}