{
  "type": "Feature",
  "properties": {
    "name": "Minihy-Tréguier",
    "country": "FR",
    "subdivision": "53",
    "timezone": "Europe/Paris"
  },
  "geometry": {
    "type": "Point",
    "coordinates": [
      -3.22877,
      48.77543
    ]
  }
}