{
  "type": "Feature",
  "properties": {
    "name": "Montfort-sur-Meu",
    "country": "FR",
    "subdivision": "53",
    "timezone": "Europe/Paris"
  },
  "geometry": {
    "type": "Point",
    "coordinates": [
      -1.95585,
      48.13762
    ]
  }
}