{
  "type": "Feature",
  "properties": {
    "name": "Montreuil-le-Gast",
    "country": "FR",
    "subdivision": "53",
    "timezone": "Europe/Paris"
  },
  "geometry": {
    "type": "Point",
    "coordinates": [
      -1.72682,
      48.24685
    ]
  }
}