{
  "type": "Feature",
  "properties": {
    "name": "Nouvoitou",
    "country": "FR",
    "subdivision": "53",
    "timezone": "Europe/Paris"
  },
  "geometry": {
    "type": "Point",
    "coordinates": [
      -1.54671,
      48.04081
    ]
  }
}