{
  "type": "Feature",
  "properties": {
    "name": "Noyal-Pontivy",
    "country": "FR",
    "subdivision": "53",
    "timezone": "Europe/Paris"
  },
  "geometry": {
    "type": "Point",
    "coordinates": [
      -2.88251,
      48.06729
    ]
  }
}