{
  "type": "Feature",
  "properties": {
    "name": "Ossé",
    "country": "FR",
    "subdivision": "53",
    "timezone": "Europe/Paris"
  },
  "geometry": {
    "type": "Point",
    "coordinates": [
      -1.45029,
      48.05542
    ]
  }
}