{
  "type": "Feature",
  "properties": {
    "name": "Pacé",
    "country": "FR",
    "subdivision": "53",
    "timezone": "Europe/Paris"
  },
  "geometry": {
    "type": "Point",
    "coordinates": [
      -1.77435,
      48.14854
    ]
  }
}