{
  "type": "Feature",
  "properties": {
    "name": "Pancé",
    "country": "FR",
    "subdivision": "53",
    "timezone": "Europe/Paris"
  },
  "geometry": {
    "type": "Point",
    "coordinates": [
      -1.65911,
      47.8812
    ]
  }
}