{
  "type": "Feature",
  "properties": {
    "name": "Peillac",
    "country": "FR",
    "subdivision": "53",
    "timezone": "Europe/Paris"
  },
  "geometry": {
    "type": "Point",
    "coordinates": [
      -2.21954,
      47.71346
    ]
  }
}