{
  "type": "Feature",
  "properties": {
    "name": "Plaintel",
    "country": "FR",
    "subdivision": "53",
    "timezone": "Europe/Paris"
  },
  "geometry": {
    "type": "Point",
    "coordinates": [
      -2.8179,
      48.40754
    ]
  }
}