{
  "type": "Feature",
  "properties": {
    "name": "Plédran",
    "country": "FR",
    "subdivision": "53",
    "timezone": "Europe/Paris"
  },
  "geometry": {
    "type": "Point",
    "coordinates": [
      -2.7461,
      48.44561
    ]
  }
}