{
  "type": "Feature",
  "properties": {
    "name": "Plérin",
    "country": "FR",
    "subdivision": "53",
    "timezone": "Europe/Paris"
  },
  "geometry": {
    "type": "Point",
    "coordinates": [
      -2.76975,
      48.53451
    ]
  }
}