{
  "type": "Feature",
  "properties": {
    "name": "Plestin-les-Grèves",
    "country": "FR",
    "subdivision": "53",
    "timezone": "Europe/Paris"
  },
  "geometry": {
    "type": "Point",
    "coordinates": [
      -3.63071,
      48.65783
    ]
  }
}