{
  "type": "Feature",
  "properties": {
    "name": "Pleumeleuc",
    "country": "FR",
    "subdivision": "53",
    "timezone": "Europe/Paris"
  },
  "geometry": {
    "type": "Point",
    "coordinates": [
      -1.91922,
      48.18449
    ]
  }
}