{
  "type": "Feature",
  "properties": {
    "name": "Plobannalec-Lesconil",
    "country": "FR",
    "subdivision": "53",
    "timezone": "Europe/Paris"
  },
  "geometry": {
    "type": "Point",
    "coordinates": [
      -4.21667,
      47.81667
    ]
  }
}