{
  "type": "Feature",
  "properties": {
    "name": "Ploërdut",
    "country": "FR",
    "subdivision": "53",
    "timezone": "Europe/Paris"
  },
  "geometry": {
    "type": "Point",
    "coordinates": [
      -3.28713,
      48.08732
    ]
  }
}