{
  "type": "Feature",
  "properties": {
    "name": "Ploeren",
    "country": "FR",
    "subdivision": "53",
    "timezone": "Europe/Paris"
  },
  "geometry": {
    "type": "Point",
    "coordinates": [
      -2.86592,
      47.65619
    ]
  }
}