{
  "type": "Feature",
  "properties": {
    "name": "Plogonnec",
    "country": "FR",
    "subdivision": "53",
    "timezone": "Europe/Paris"
  },
  "geometry": {
    "type": "Point",
    "coordinates": [
      -4.19488,
      48.078
    ]
  }
}