{
  "type": "Feature",
  "properties": {
    "name": "Plogoff",
    "country": "FR",
    "subdivision": "53",
    "timezone": "Europe/Paris"
  },
  "geometry": {
    "type": "Point",
    "coordinates": [
      -4.66606,
      48.037
    ]
  }
}