{
  "type": "Feature",
  "properties": {
    "name": "Plouezoc'h",
    "country": "FR",
    "subdivision": "53",
    "timezone": "Europe/Paris"
  },
  "geometry": {
    "type": "Point",
    "coordinates": [
      -3.82308,
      48.63944
    ]
  }
}