{
  "type": "Feature",
  "properties": {
    "name": "Ploudaniel",
    "country": "FR",
    "subdivision": "53",
    "timezone": "Europe/Paris"
  },
  "geometry": {
    "type": "Point",
    "coordinates": [
      -4.31146,
      48.53693
    ]
  }
}