{
  "type": "Feature",
  "properties": {
    "name": "Plougasnou",
    "country": "FR",
    "subdivision": "53",
    "timezone": "Europe/Paris"
  },
  "geometry": {
    "type": "Point",
    "coordinates": [
      -3.79179,
      48.69597
    ]
  }
}