{
  "type": "Feature",
  "properties": {
    "name": "Plouézec",
    "country": "FR",
    "subdivision": "53",
    "timezone": "Europe/Paris"
  },
  "geometry": {
    "type": "Point",
    "coordinates": [
      -2.98466,
      48.74894
    ]
  }
}