{
  "type": "Feature",
  "properties": {
    "name": "Plouay",
    "country": "FR",
    "subdivision": "53",
    "timezone": "Europe/Paris"
  },
  "geometry": {
    "type": "Point",
    "coordinates": [
      -3.33482,
      47.91466
    ]
  }
}