{
  "type": "Feature",
  "properties": {
    "name": "Plouénan",
    "country": "FR",
    "subdivision": "53",
    "timezone": "Europe/Paris"
  },
  "geometry": {
    "type": "Point",
    "coordinates": [
      -3.9877,
      48.62844
    ]
  }
}