{
  "type": "Feature",
  "properties": {
    "name": "Plougoulm",
    "country": "FR",
    "subdivision": "53",
    "timezone": "Europe/Paris"
  },
  "geometry": {
    "type": "Point",
    "coordinates": [
      -4.04539,
      48.66401
    ]
  }
}