{
  "type": "Feature",
  "properties": {
    "name": "Plougastel-Daoulas",
    "country": "FR",
    "subdivision": "53",
    "timezone": "Europe/Paris"
  },
  "geometry": {
    "type": "Point",
    "coordinates": [
      -4.36978,
      48.37368
    ]
  }
}