{
  "type": "Feature",
  "properties": {
    "name": "Plozévet",
    "country": "FR",
    "subdivision": "53",
    "timezone": "Europe/Paris"
  },
  "geometry": {
    "type": "Point",
    "coordinates": [
      -4.4261,
      47.98546
    ]
  }
}