{
  "type": "Feature",
  "properties": {
    "name": "Pont-Scorff",
    "country": "FR",
    "subdivision": "53",
    "timezone": "Europe/Paris"
  },
  "geometry": {
    "type": "Point",
    "coordinates": [
      -3.40338,
      47.83425
    ]
  }
}