{
  "type": "Feature",
  "properties": {
    "name": "Pont-Croix",
    "country": "FR",
    "subdivision": "53",
    "timezone": "Europe/Paris"
  },
  "geometry": {
    "type": "Point",
    "coordinates": [
      -4.48714,
      48.04088
    ]
  }
}