{
  "type": "Feature",
  "properties": {
    "name": "Poullaouen",
    "country": "FR",
    "subdivision": "53",
    "timezone": "Europe/Paris"
  },
  "geometry": {
    "type": "Point",
    "coordinates": [
      -3.64237,
      48.34013
    ]
  }
}