{
  "type": "Feature",
  "properties": {
    "name": "Rohan",
    "country": "FR",
    "subdivision": "53",
    "timezone": "Europe/Paris"
  },
  "geometry": {
    "type": "Point",
    "coordinates": [
      -2.75307,
      48.06885
    ]
  }
}