{
  "type": "Feature",
  "properties": {
    "name": "Saint-Aubin-du-Cormier",
    "country": "FR",
    "subdivision": "53",
    "timezone": "Europe/Paris"
  },
  "geometry": {
    "type": "Point",
    "coordinates": [
      -1.39983,
      48.25967
    ]
  }
}