{
  "type": "Feature",
  "properties": {
    "name": "Saint-Hélen",
    "country": "FR",
    "subdivision": "53",
    "timezone": "Europe/Paris"
  },
  "geometry": {
    "type": "Point",
    "coordinates": [
      -1.95943,
      48.47084
    ]
  }
}