{
  "type": "Feature",
  "properties": {
    "name": "Saint-Perreux",
    "country": "FR",
    "subdivision": "53",
    "timezone": "Europe/Paris"
  },
  "geometry": {
    "type": "Point",
    "coordinates": [
      -2.10783,
      47.66875
    ]
  }
}