{
  "type": "Feature",
  "properties": {
    "name": "Saint-Armel",
    "country": "FR",
    "subdivision": "53",
    "timezone": "Europe/Paris"
  },
  "geometry": {
    "type": "Point",
    "coordinates": [
      -1.59146,
      48.01247
    ]
  }
}