{
  "type": "Feature",
  "properties": {
    "name": "Sainte-Hélène",
    "country": "FR",
    "subdivision": "53",
    "timezone": "Europe/Paris"
  },
  "geometry": {
    "type": "Point",
    "coordinates": [
      -3.20463,
      47.71958
    ]
  }
}