{
  "type": "Feature",
  "properties": {
    "name": "Saint-Jean-Brévelay",
    "country": "FR",
    "subdivision": "53",
    "timezone": "Europe/Paris"
  },
  "geometry": {
    "type": "Point",
    "coordinates": [
      -2.72293,
      47.84507
    ]
  }
}