{
  "type": "Feature",
  "properties": {
    "name": "Saint-Sauveur-des-Landes",
    "country": "FR",
    "subdivision": "53",
    "timezone": "Europe/Paris"
  },
  "geometry": {
    "type": "Point",
    "coordinates": [
      -1.31308,
      48.34241
    ]
  }
}