{
  "type": "Feature",
  "properties": {
    "name": "Saint-Senoux",
    "country": "FR",
    "subdivision": "53",
    "timezone": "Europe/Paris"
  },
  "geometry": {
    "type": "Point",
    "coordinates": [
      -1.78847,
      47.90485
    ]
  }
}