{
  "type": "Feature",
  "properties": {
    "name": "Saint-Étienne-en-Coglès",
    "country": "FR",
    "subdivision": "53",
    "timezone": "Europe/Paris"
  },
  "geometry": {
    "type": "Point",
    "coordinates": [
      -1.32812,
      48.40172
    ]
  }
}