{
  "type": "Feature",
  "properties": {
    "name": "Saint-Avé",
    "country": "FR",
    "subdivision": "53",
    "timezone": "Europe/Paris"
  },
  "geometry": {
    "type": "Point",
    "coordinates": [
      -2.7349,
      47.6865
    ]
  }
}