{
  "type": "Feature",
  "properties": {
    "name": "Saint-Thuriau",
    "country": "FR",
    "subdivision": "53",
    "timezone": "Europe/Paris"
  },
  "geometry": {
    "type": "Point",
    "coordinates": [
      -2.95048,
      48.01698
    ]
  }
}