{
  "type": "Feature",
  "properties": {
    "name": "Saint-Nolff",
    "country": "FR",
    "subdivision": "53",
    "timezone": "Europe/Paris"
  },
  "geometry": {
    "type": "Point",
    "coordinates": [
      -2.65182,
      47.70393
    ]
  }
}