{
  "type": "Feature",
  "properties": {
    "name": "Sixt-sur-Aff",
    "country": "FR",
    "subdivision": "53",
    "timezone": "Europe/Paris"
  },
  "geometry": {
    "type": "Point",
    "coordinates": [
      -2.07987,
      47.77606
    ]
  }
}