{
  "type": "Feature",
  "properties": {
    "name": "Trévou-Tréguignec",
    "country": "FR",
    "subdivision": "53",
    "timezone": "Europe/Paris"
  },
  "geometry": {
    "type": "Point",
    "coordinates": [
      -3.35876,
      48.81398
    ]
  }
}