{
  "type": "Feature",
  "properties": {
    "name": "Yvignac-la-Tour",
    "country": "FR",
    "subdivision": "53",
    "timezone": "Europe/Paris"
  },
  "geometry": {
    "type": "Point",
    "coordinates": [
      -2.18333,
      48.35
    ]
  }
}