{
  "type": "Feature",
  "properties": {
    "name": "Bad Lobenstein",
    "country": "DE",
    "subdivision": "15",
    "timezone": "Europe/Berlin"
  },
  "geometry": {
    "type": "Point",
    "coordinates": [
      11.6393,
      50.45223
    ]
  }
}