{
  "type": "Feature",
  "properties": {
    "name": "Bad Blankenburg",
    "country": "DE",
    "subdivision": "15",
    "timezone": "Europe/Berlin"
  },
  "geometry": {
    "type": "Point",
    "coordinates": [
      11.27369,
      50.68189
    ]
  }
}