{
  "type": "Feature",
  "properties": {
    "name": "Dachwig",
    "country": "DE",
    "subdivision": "15",
    "timezone": "Europe/Berlin"
  },
  "geometry": {
    "type": "Point",
    "coordinates": [
      10.85479,
      51.0777
    ]
  }
}