{
  "type": "Feature",
  "properties": {
    "name": "Deuna",
    "country": "DE",
    "subdivision": "15",
    "timezone": "Europe/Berlin"
  },
  "geometry": {
    "type": "Point",
    "coordinates": [
      10.47439,
      51.3545
    ]
  }
}