{
  "type": "Feature",
  "properties": {
    "name": "Ebeleben",
    "country": "DE",
    "subdivision": "15",
    "timezone": "Europe/Berlin"
  },
  "geometry": {
    "type": "Point",
    "coordinates": [
      10.72999,
      51.28283
    ]
  }
}