{
  "type": "Feature",
  "properties": {
    "name": "Finsterbergen",
    "country": "DE",
    "subdivision": "15",
    "timezone": "Europe/Berlin"
  },
  "geometry": {
    "type": "Point",
    "coordinates": [
      10.58916,
      50.83464
    ]
  }
}