{
  "type": "Feature",
  "properties": {
    "name": "Gangloffsömmern",
    "country": "DE",
    "subdivision": "15",
    "timezone": "Europe/Berlin"
  },
  "geometry": {
    "type": "Point",
    "coordinates": [
      10.94332,
      51.1894
    ]
  }
}