{
  "type": "Feature",
  "properties": {
    "name": "Geraberg",
    "country": "DE",
    "subdivision": "15",
    "timezone": "Europe/Berlin"
  },
  "geometry": {
    "type": "Point",
    "coordinates": [
      10.83737,
      50.71594
    ]
  }
}