{
  "type": "Feature",
  "properties": {
    "name": "Gera",
    "country": "DE",
    "subdivision": "15",
    "timezone": "Europe/Berlin"
  },
  "geometry": {
    "type": "Point",
    "coordinates": [
      12.08187,
      50.88029
    ]
  }
}