{
  "type": "Feature",
  "properties": {
    "name": "Großenehrich",
    "country": "DE",
    "subdivision": "15",
    "timezone": "Europe/Berlin"
  },
  "geometry": {
    "type": "Point",
    "coordinates": [
      10.83458,
      51.24838
    ]
  }
}