{
  "type": "Feature",
  "properties": {
    "name": "Großrudestedt",
    "country": "DE",
    "subdivision": "15",
    "timezone": "Europe/Berlin"
  },
  "geometry": {
    "type": "Point",
    "coordinates": [
      11.09977,
      51.09305
    ]
  }
}