{
  "type": "Feature",
  "properties": {
    "name": "Großbreitenbach",
    "country": "DE",
    "subdivision": "15",
    "timezone": "Europe/Berlin"
  },
  "geometry": {
    "type": "Point",
    "coordinates": [
      11.00955,
      50.58335
    ]
  }
}