{
  "type": "Feature",
  "properties": {
    "name": "Kannawurf",
    "country": "DE",
    "subdivision": "15",
    "timezone": "Europe/Berlin"
  },
  "geometry": {
    "type": "Point",
    "coordinates": [
      11.13333,
      51.26667
    ]
  }
}