{
  "type": "Feature",
  "properties": {
    "name": "Katzhütte",
    "country": "DE",
    "subdivision": "15",
    "timezone": "Europe/Berlin"
  },
  "geometry": {
    "type": "Point",
    "coordinates": [
      11.05293,
      50.55191
    ]
  }
}