{
  "type": "Feature",
  "properties": {
    "name": "Kirchworbis",
    "country": "DE",
    "subdivision": "15",
    "timezone": "Europe/Berlin"
  },
  "geometry": {
    "type": "Point",
    "coordinates": [
      10.39625,
      51.41122
    ]
  }
}