{
  "type": "Feature",
  "properties": {
    "name": "Kleinfurra",
    "country": "DE",
    "subdivision": "15",
    "timezone": "Europe/Berlin"
  },
  "geometry": {
    "type": "Point",
    "coordinates": [
      10.76454,
      51.41556
    ]
  }
}