{
  "type": "Feature",
  "properties": {
    "name": "Kraftsdorf",
    "country": "DE",
    "subdivision": "15",
    "timezone": "Europe/Berlin"
  },
  "geometry": {
    "type": "Point",
    "coordinates": [
      11.92944,
      50.87574
    ]
  }
}