{
  "type": "Feature",
  "properties": {
    "name": "Kühndorf",
    "country": "DE",
    "subdivision": "15",
    "timezone": "Europe/Berlin"
  },
  "geometry": {
    "type": "Point",
    "coordinates": [
      10.4894,
      50.6086
    ]
  }
}