{
  "type": "Feature",
  "properties": {
    "name": "Lauchröden",
    "country": "DE",
    "subdivision": "15",
    "timezone": "Europe/Berlin"
  },
  "geometry": {
    "type": "Point",
    "coordinates": [
      10.15694,
      50.99371
    ]
  }
}