{
  "type": "Feature",
  "properties": {
    "name": "Lehesten",
    "country": "DE",
    "subdivision": "15",
    "timezone": "Europe/Berlin"
  },
  "geometry": {
    "type": "Point",
    "coordinates": [
      11.58333,
      50.98333
    ]
  }
}