{
  "type": "Feature",
  "properties": {
    "name": "Leutenberg",
    "country": "DE",
    "subdivision": "15",
    "timezone": "Europe/Berlin"
  },
  "geometry": {
    "type": "Point",
    "coordinates": [
      11.45619,
      50.56354
    ]
  }
}