{
  "type": "Feature",
  "properties": {
    "name": "Magdala",
    "country": "DE",
    "subdivision": "15",
    "timezone": "Europe/Berlin"
  },
  "geometry": {
    "type": "Point",
    "coordinates": [
      11.44801,
      50.90698
    ]
  }
}