{
  "type": "Feature",
  "properties": {
    "name": "Meiningen",
    "country": "DE",
    "subdivision": "15",
    "timezone": "Europe/Berlin"
  },
  "geometry": {
    "type": "Point",
    "coordinates": [
      10.41521,
      50.56787
    ]
  }
}