{
  "type": "Feature",
  "properties": {
    "name": "Milz",
    "country": "DE",
    "subdivision": "15",
    "timezone": "Europe/Berlin"
  },
  "geometry": {
    "type": "Point",
    "coordinates": [
      10.53757,
      50.3776
    ]
  }
}