{
  "type": "Feature",
  "properties": {
    "name": "Niedersachswerfen",
    "country": "DE",
    "subdivision": "15",
    "timezone": "Europe/Berlin"
  },
  "geometry": {
    "type": "Point",
    "coordinates": [
      10.76594,
      51.55062
    ]
  }
}