{
  "type": "Feature",
  "properties": {
    "name": "Nöbdenitz",
    "country": "DE",
    "subdivision": "15",
    "timezone": "Europe/Berlin"
  },
  "geometry": {
    "type": "Point",
    "coordinates": [
      12.28333,
      50.86667
    ]
  }
}