{
  "type": "Feature",
  "properties": {
    "name": "Oberhof",
    "country": "DE",
    "subdivision": "15",
    "timezone": "Europe/Berlin"
  },
  "geometry": {
    "type": "Point",
    "coordinates": [
      10.72716,
      50.70435
    ]
  }
}