{
  "type": "Feature",
  "properties": {
    "name": "Oppurg",
    "country": "DE",
    "subdivision": "15",
    "timezone": "Europe/Berlin"
  },
  "geometry": {
    "type": "Point",
    "coordinates": [
      11.65289,
      50.71065
    ]
  }
}