{
  "type": "Feature",
  "properties": {
    "name": "Plaue",
    "country": "DE",
    "subdivision": "15",
    "timezone": "Europe/Berlin"
  },
  "geometry": {
    "type": "Point",
    "coordinates": [
      10.89969,
      50.77835
    ]
  }
}