{
  "type": "Feature",
  "properties": {
    "name": "Ranis",
    "country": "DE",
    "subdivision": "15",
    "timezone": "Europe/Berlin"
  },
  "geometry": {
    "type": "Point",
    "coordinates": [
      11.56912,
      50.66132
    ]
  }
}