{
  "type": "Feature",
  "properties": {
    "name": "Ronneburg",
    "country": "DE",
    "subdivision": "15",
    "timezone": "Europe/Berlin"
  },
  "geometry": {
    "type": "Point",
    "coordinates": [
      12.18666,
      50.8634
    ]
  }
}