{
  "type": "Feature",
  "properties": {
    "name": "Schkölen",
    "country": "DE",
    "subdivision": "15",
    "timezone": "Europe/Berlin"
  },
  "geometry": {
    "type": "Point",
    "coordinates": [
      11.82141,
      51.04166
    ]
  }
}