{
  "type": "Feature",
  "properties": {
    "name": "Schleusingen",
    "country": "DE",
    "subdivision": "15",
    "timezone": "Europe/Berlin"
  },
  "geometry": {
    "type": "Point",
    "coordinates": [
      10.75658,
      50.51076
    ]
  }
}