{
  "type": "Feature",
  "properties": {
    "name": "Schmiedefeld am Rennsteig",
    "country": "DE",
    "subdivision": "15",
    "timezone": "Europe/Berlin"
  },
  "geometry": {
    "type": "Point",
    "coordinates": [
      10.81284,
      50.60863
    ]
  }
}