{
  "type": "Feature",
  "properties": {
    "name": "Sonneborn",
    "country": "DE",
    "subdivision": "15",
    "timezone": "Europe/Berlin"
  },
  "geometry": {
    "type": "Point",
    "coordinates": [
      10.59173,
      50.9927
    ]
  }
}