{
  "type": "Feature",
  "properties": {
    "name": "Stadtilm",
    "country": "DE",
    "subdivision": "15",
    "timezone": "Europe/Berlin"
  },
  "geometry": {
    "type": "Point",
    "coordinates": [
      11.08262,
      50.77596
    ]
  }
}