{
  "type": "Feature",
  "properties": {
    "name": "Steinbach-Hallenberg",
    "country": "DE",
    "subdivision": "15",
    "timezone": "Europe/Berlin"
  },
  "geometry": {
    "type": "Point",
    "coordinates": [
      10.56541,
      50.69624
    ]
  }
}