{
  "type": "Feature",
  "properties": {
    "name": "Steinbach",
    "country": "DE",
    "subdivision": "15",
    "timezone": "Europe/Berlin"
  },
  "geometry": {
    "type": "Point",
    "coordinates": [
      10.36393,
      50.83321
    ]
  }
}