{
  "type": "Feature",
  "properties": {
    "name": "Thal",
    "country": "DE",
    "subdivision": "15",
    "timezone": "Europe/Berlin"
  },
  "geometry": {
    "type": "Point",
    "coordinates": [
      10.39209,
      50.91684
    ]
  }
}