{
  "type": "Feature",
  "properties": {
    "name": "Themar",
    "country": "DE",
    "subdivision": "15",
    "timezone": "Europe/Berlin"
  },
  "geometry": {
    "type": "Point",
    "coordinates": [
      10.61536,
      50.50465
    ]
  }
}