{
  "type": "Feature",
  "properties": {
    "name": "Triebes",
    "country": "DE",
    "subdivision": "15",
    "timezone": "Europe/Berlin"
  },
  "geometry": {
    "type": "Point",
    "coordinates": [
      12.02042,
      50.68489
    ]
  }
}