{
  "type": "Feature",
  "properties": {
    "name": "Wandersleben",
    "country": "DE",
    "subdivision": "15",
    "timezone": "Europe/Berlin"
  },
  "geometry": {
    "type": "Point",
    "coordinates": [
      10.84959,
      50.89946
    ]
  }
}