{
  "type": "Feature",
  "properties": {
    "name": "Wiehe",
    "country": "DE",
    "subdivision": "15",
    "timezone": "Europe/Berlin"
  },
  "geometry": {
    "type": "Point",
    "coordinates": [
      11.41282,
      51.26586
    ]
  }
}