{
  "type": "Feature",
  "properties": {
    "name": "Wingerode",
    "country": "DE",
    "subdivision": "15",
    "timezone": "Europe/Berlin"
  },
  "geometry": {
    "type": "Point",
    "coordinates": [
      10.23954,
      51.39032
    ]
  }
}