{
  "type": "Feature",
  "properties": {
    "name": "Alabushevo",
    "country": "RU",
    "subdivision": "47",
    "timezone": "Europe/Moscow"
  },
  "geometry": {
    "type": "Point",
    "coordinates": [
      37.15,
      56.01667
    ]
  }
}