{
  "type": "Feature",
  "properties": {
    "name": "Bol'shiye Vyazëmy",
    "country": "RU",
    "subdivision": "47",
    "timezone": "Europe/Moscow"
  },
  "geometry": {
    "type": "Point",
    "coordinates": [
      36.9762,
      55.62058
    ]
  }
}