{
  "type": "Feature",
  "properties": {
    "name": "Bratovshchina",
    "country": "RU",
    "subdivision": "47",
    "timezone": "Europe/Moscow"
  },
  "geometry": {
    "type": "Point",
    "coordinates": [
      37.88333,
      56.05
    ]
  }
}