{
  "type": "Feature",
  "properties": {
    "name": "Fryazino",
    "country": "RU",
    "subdivision": "47",
    "timezone": "Europe/Moscow"
  },
  "geometry": {
    "type": "Point",
    "coordinates": [
      38.04556,
      55.96056
    ]
  }
}