{
  "type": "Feature",
  "properties": {
    "name": "Gorki Vtoryye",
    "country": "RU",
    "subdivision": "47",
    "timezone": "Europe/Moscow"
  },
  "geometry": {
    "type": "Point",
    "coordinates": [
      37.1635,
      55.72565
    ]
  }
}