{
  "type": "Feature",
  "properties": {
    "name": "Gorshkovo",
    "country": "RU",
    "subdivision": "47",
    "timezone": "Europe/Moscow"
  },
  "geometry": {
    "type": "Point",
    "coordinates": [
      37.4124,
      56.37561
    ]
  }
}