{
  "type": "Feature",
  "properties": {
    "name": "Khimki",
    "country": "RU",
    "subdivision": "47",
    "timezone": "Europe/Moscow"
  },
  "geometry": {
    "type": "Point",
    "coordinates": [
      37.42969,
      55.89704
    ]
  }
}