{
  "type": "Feature",
  "properties": {
    "name": "Kommunarka",
    "country": "RU",
    "subdivision": "47",
    "timezone": "Europe/Moscow"
  },
  "geometry": {
    "type": "Point",
    "coordinates": [
      37.48932,
      55.56952
    ]
  }
}