{
  "type": "Feature",
  "properties": {
    "name": "Korenëvo",
    "country": "RU",
    "subdivision": "47",
    "timezone": "Europe/Moscow"
  },
  "geometry": {
    "type": "Point",
    "coordinates": [
      38.00778,
      55.67194
    ]
  }
}