{
  "type": "Feature",
  "properties": {
    "name": "Kurilovo",
    "country": "RU",
    "subdivision": "47",
    "timezone": "Europe/Moscow"
  },
  "geometry": {
    "type": "Point",
    "coordinates": [
      37.37703,
      55.37271
    ]
  }
}