{
  "type": "Feature",
  "properties": {
    "name": "Lesnyye Polyany",
    "country": "RU",
    "subdivision": "47",
    "timezone": "Europe/Moscow"
  },
  "geometry": {
    "type": "Point",
    "coordinates": [
      37.86667,
      55.96667
    ]
  }
}