{
  "type": "Feature",
  "properties": {
    "name": "Loza",
    "country": "RU",
    "subdivision": "47",
    "timezone": "Europe/Moscow"
  },
  "geometry": {
    "type": "Point",
    "coordinates": [
      38.21375,
      56.25922
    ]
  }
}