{
  "type": "Feature",
  "properties": {
    "name": "Malakhovka",
    "country": "RU",
    "subdivision": "47",
    "timezone": "Europe/Moscow"
  },
  "geometry": {
    "type": "Point",
    "coordinates": [
      38.02486,
      55.64776
    ]
  }
}