{
  "type": "Feature",
  "properties": {
    "name": "Noginsk-9",
    "country": "RU",
    "subdivision": "47",
    "timezone": "Europe/Moscow"
  },
  "geometry": {
    "type": "Point",
    "coordinates": [
      38.50013,
      56.06681
    ]
  }
}