{
  "type": "Feature",
  "properties": {
    "name": "Novosin’kovo",
    "country": "RU",
    "subdivision": "47",
    "timezone": "Europe/Moscow"
  },
  "geometry": {
    "type": "Point",
    "coordinates": [
      37.32871,
      56.37737
    ]
  }
}