{
  "type": "Feature",
  "properties": {
    "name": "Novoivanovskoye",
    "country": "RU",
    "subdivision": "47",
    "timezone": "Europe/Moscow"
  },
  "geometry": {
    "type": "Point",
    "coordinates": [
      37.3651,
      55.70381
    ]
  }
}