{
  "type": "Feature",
  "properties": {
    "name": "Novo-Nikol’skoye",
    "country": "RU",
    "subdivision": "47",
    "timezone": "Europe/Moscow"
  },
  "geometry": {
    "type": "Point",
    "coordinates": [
      37.53333,
      56.56667
    ]
  }
}