{
  "type": "Feature",
  "properties": {
    "name": "Ostrovtsy",
    "country": "RU",
    "subdivision": "47",
    "timezone": "Europe/Moscow"
  },
  "geometry": {
    "type": "Point",
    "coordinates": [
      38.00556,
      55.5875
    ]
  }
}