{
  "type": "Feature",
  "properties": {
    "name": "Rakhmanovo",
    "country": "RU",
    "subdivision": "47",
    "timezone": "Europe/Moscow"
  },
  "geometry": {
    "type": "Point",
    "coordinates": [
      38.61124,
      55.74401
    ]
  }
}