{
  "type": "Feature",
  "properties": {
    "name": "Rogachëvo",
    "country": "RU",
    "subdivision": "47",
    "timezone": "Europe/Moscow"
  },
  "geometry": {
    "type": "Point",
    "coordinates": [
      37.16667,
      56.43333
    ]
  }
}