{
  "type": "Feature",
  "properties": {
    "name": "Semënovskoye",
    "country": "RU",
    "subdivision": "47",
    "timezone": "Europe/Moscow"
  },
  "geometry": {
    "type": "Point",
    "coordinates": [
      37.55,
      55.68333
    ]
  }
}