{
  "type": "Feature",
  "properties": {
    "name": "Semkhoz",
    "country": "RU",
    "subdivision": "47",
    "timezone": "Europe/Moscow"
  },
  "geometry": {
    "type": "Point",
    "coordinates": [
      38.06667,
      56.28333
    ]
  }
}