{
  "type": "Feature",
  "properties": {
    "name": "Serpukhov",
    "country": "RU",
    "subdivision": "47",
    "timezone": "Europe/Moscow"
  },
  "geometry": {
    "type": "Point",
    "coordinates": [
      37.41114,
      54.91578
    ]
  }
}