{
  "type": "Feature",
  "properties": {
    "name": "Shchelkovo",
    "country": "RU",
    "subdivision": "47",
    "timezone": "Europe/Moscow"
  },
  "geometry": {
    "type": "Point",
    "coordinates": [
      37.97218,
      55.92497
    ]
  }
}