{
  "type": "Feature",
  "properties": {
    "name": "Snegiri",
    "country": "RU",
    "subdivision": "47",
    "timezone": "Europe/Moscow"
  },
  "geometry": {
    "type": "Point",
    "coordinates": [
      37.02421,
      55.88867
    ]
  }
}