{
  "type": "Feature",
  "properties": {
    "name": "Stupino",
    "country": "RU",
    "subdivision": "47",
    "timezone": "Europe/Moscow"
  },
  "geometry": {
    "type": "Point",
    "coordinates": [
      38.07083,
      54.90083
    ]
  }
}