{
  "type": "Feature",
  "properties": {
    "name": "Sychëvo",
    "country": "RU",
    "subdivision": "47",
    "timezone": "Europe/Moscow"
  },
  "geometry": {
    "type": "Point",
    "coordinates": [
      36.22785,
      55.95771
    ]
  }
}