{
  "type": "Feature",
  "properties": {
    "name": "Teryayevo",
    "country": "RU",
    "subdivision": "47",
    "timezone": "Europe/Moscow"
  },
  "geometry": {
    "type": "Point",
    "coordinates": [
      36.12545,
      56.16974
    ]
  }
}