{
  "type": "Feature",
  "properties": {
    "name": "Vniissok",
    "country": "RU",
    "subdivision": "47",
    "timezone": "Europe/Moscow"
  },
  "geometry": {
    "type": "Point",
    "coordinates": [
      37.21194,
      55.65639
    ]
  }
}