{
  "type": "Feature",
  "properties": {
    "name": "Zarya",
    "country": "RU",
    "subdivision": "47",
    "timezone": "Europe/Moscow"
  },
  "geometry": {
    "type": "Point",
    "coordinates": [
      38.09578,
      55.75533
    ]
  }
}