{
  "type": "Feature",
  "properties": {
    "name": "Zheleznodorozhnyy",
    "country": "RU",
    "subdivision": "47",
    "timezone": "Europe/Moscow"
  },
  "geometry": {
    "type": "Point",
    "coordinates": [
      38.01684,
      55.744
    ]
  }
}