{
  "type": "Feature",
  "properties": {
    "name": "Same",
    "country": "TL",
    "subdivision": "MF",
    "timezone": "Asia/Dili"
  },
  "geometry": {
    "type": "Point",
    "coordinates": [
      125.64861,
      -9.00417
    ]
  }
}