{
  "type": "Feature",
  "properties": {
    "name": "Acevedo",
    "country": "CO",
    "subdivision": "16",
    "timezone": "America/Bogota"
  },
  "geometry": {
    "type": "Point",
    "coordinates": [
      -75.89036,
      1.80464
    ]
  }
}