{
  "type": "Feature",
  "properties": {
    "name": "Isnos",
    "country": "CO",
    "subdivision": "16",
    "timezone": "America/Bogota"
  },
  "geometry": {
    "type": "Point",
    "coordinates": [
      -76.24056,
      1.93556
    ]
  }
}