{
  "type": "Feature",
  "properties": {
    "name": "Oporapa",
    "country": "CO",
    "subdivision": "16",
    "timezone": "America/Bogota"
  },
  "geometry": {
    "type": "Point",
    "coordinates": [
      -75.99588,
      2.02378
    ]
  }
}