{
  "type": "Feature",
  "properties": {
    "name": "Palermo",
    "country": "CO",
    "subdivision": "16",
    "timezone": "America/Bogota"
  },
  "geometry": {
    "type": "Point",
    "coordinates": [
      -75.4375,
      2.89167
    ]
  }
}