{
  "type": "Feature",
  "properties": {
    "name": "Ati",
    "country": "TD",
    "subdivision": "01",
    "timezone": "Africa/Ndjamena"
  },
  "geometry": {
    "type": "Point",
    "coordinates": [
      18.3393,
      13.2138
    ]
  }
}