{
  "type": "Feature",
  "properties": {
    "name": "Chela",
    "country": "AO",
    "subdivision": "08",
    "timezone": "Africa/Luanda"
  },
  "geometry": {
    "type": "Point",
    "coordinates": [
      15.43358,
      -12.30261
    ]
  }
}