{
  "type": "Feature",
  "properties": {
    "name": "Longonjo",
    "country": "AO",
    "subdivision": "08",
    "timezone": "Africa/Luanda"
  },
  "geometry": {
    "type": "Point",
    "coordinates": [
      15.24845,
      -12.90795
    ]
  }
}