{
  "type": "Feature",
  "properties": {
    "name": "Crângu",
    "country": "RO",
    "subdivision": "35",
    "timezone": "Europe/Bucharest"
  },
  "geometry": {
    "type": "Point",
    "coordinates": [
      25.0735,
      43.84611
    ]
  }
}