{
  "type": "Feature",
  "properties": {
    "name": "Dracea",
    "country": "RO",
    "subdivision": "35",
    "timezone": "Europe/Bucharest"
  },
  "geometry": {
    "type": "Point",
    "coordinates": [
      25.05194,
      43.84914
    ]
  }
}