{
  "type": "Feature",
  "properties": {
    "name": "Drăgăneşti de Vede",
    "country": "RO",
    "subdivision": "35",
    "timezone": "Europe/Bucharest"
  },
  "geometry": {
    "type": "Point",
    "coordinates": [
      25.05,
      44.13333
    ]
  }
}