{
  "type": "Feature",
  "properties": {
    "name": "Merenii de Jos",
    "country": "RO",
    "subdivision": "35",
    "timezone": "Europe/Bucharest"
  },
  "geometry": {
    "type": "Point",
    "coordinates": [
      25.64346,
      44.23214
    ]
  }
}