{
  "type": "Feature",
  "properties": {
    "name": "Năsturelu",
    "country": "RO",
    "subdivision": "35",
    "timezone": "Europe/Bucharest"
  },
  "geometry": {
    "type": "Point",
    "coordinates": [
      25.46667,
      43.66667
    ]
  }
}