{
  "type": "Feature",
  "properties": {
    "name": "Nenciulești",
    "country": "RO",
    "subdivision": "35",
    "timezone": "Europe/Bucharest"
  },
  "geometry": {
    "type": "Point",
    "coordinates": [
      25.20061,
      44.03486
    ]
  }
}