{
  "type": "Feature",
  "properties": {
    "name": "Purani",
    "country": "RO",
    "subdivision": "35",
    "timezone": "Europe/Bucharest"
  },
  "geometry": {
    "type": "Point",
    "coordinates": [
      25.43656,
      43.97989
    ]
  }
}