{
  "type": "Feature",
  "properties": {
    "name": "Scrioaştea",
    "country": "RO",
    "subdivision": "35",
    "timezone": "Europe/Bucharest"
  },
  "geometry": {
    "type": "Point",
    "coordinates": [
      24.95,
      44.15
    ]
  }
}