{
  "type": "Feature",
  "properties": {
    "name": "Trivalea-Moşteni",
    "country": "RO",
    "subdivision": "35",
    "timezone": "Europe/Bucharest"
  },
  "geometry": {
    "type": "Point",
    "coordinates": [
      25.23333,
      44.26667
    ]
  }
}