{
  "type": "Feature",
  "properties": {
    "name": "Turnu Măgurele",
    "country": "RO",
    "subdivision": "35",
    "timezone": "Europe/Bucharest"
  },
  "geometry": {
    "type": "Point",
    "coordinates": [
      24.86846,
      43.7469
    ]
  }
}