{
  "type": "Feature",
  "properties": {
    "name": "Uda-Paciurea",
    "country": "RO",
    "subdivision": "35",
    "timezone": "Europe/Bucharest"
  },
  "geometry": {
    "type": "Point",
    "coordinates": [
      24.72379,
      43.87979
    ]
  }
}