{
  "type": "Feature",
  "properties": {
    "name": "Zâmbreasca",
    "country": "RO",
    "subdivision": "35",
    "timezone": "Europe/Bucharest"
  },
  "geometry": {
    "type": "Point",
    "coordinates": [
      24.98333,
      44.31667
    ]
  }
}