{
  "type": "Feature",
  "properties": {
    "name": "Gwanda",
    "country": "ZW",
    "subdivision": "07",
    "timezone": "Africa/Harare"
  },
  "geometry": {
    "type": "Point",
    "coordinates": [
      29.00698,
      -20.93622
    ]
  }
}