{
  "type": "Feature",
  "properties": {
    "name": "Tambopata",
    "country": "PE",
    "subdivision": "17",
    "timezone": "America/Lima"
  },
  "geometry": {
    "type": "Point",
    "coordinates": [
      -69.35547,
      -12.67191
    ]
  }
}