{
  "type": "Feature",
  "properties": {
    "name": "Dvor",
    "country": "HR",
    "subdivision": "14",
    "timezone": "Europe/Zagreb"
  },
  "geometry": {
    "type": "Point",
    "coordinates": [
      16.37753,
      45.07032
    ]
  }
}