{
  "type": "Feature",
  "properties": {
    "name": "Kutina",
    "country": "HR",
    "subdivision": "14",
    "timezone": "Europe/Zagreb"
  },
  "geometry": {
    "type": "Point",
    "coordinates": [
      16.78194,
      45.475
    ]
  }
}