{
  "type": "Feature",
  "properties": {
    "name": "Novska",
    "country": "HR",
    "subdivision": "14",
    "timezone": "Europe/Zagreb"
  },
  "geometry": {
    "type": "Point",
    "coordinates": [
      16.97694,
      45.34056
    ]
  }
}