{
  "type": "Feature",
  "properties": {
    "name": "Repušnica",
    "country": "HR",
    "subdivision": "14",
    "timezone": "Europe/Zagreb"
  },
  "geometry": {
    "type": "Point",
    "coordinates": [
      16.73083,
      45.49278
    ]
  }
}