{
  "type": "Feature",
  "properties": {
    "name": "Acerno",
    "country": "IT",
    "subdivision": "04",
    "timezone": "Europe/Rome"
  },
  "geometry": {
    "type": "Point",
    "coordinates": [
      15.05695,
      40.73771
    ]
  }
}