{
  "type": "Feature",
  "properties": {
    "name": "Agerola",
    "country": "IT",
    "subdivision": "04",
    "timezone": "Europe/Rome"
  },
  "geometry": {
    "type": "Point",
    "coordinates": [
      14.53884,
      40.63771
    ]
  }
}