{
  "type": "Feature",
  "properties": {
    "name": "Alvignano",
    "country": "IT",
    "subdivision": "04",
    "timezone": "Europe/Rome"
  },
  "geometry": {
    "type": "Point",
    "coordinates": [
      14.33671,
      41.24427
    ]
  }
}