{
  "type": "Feature",
  "properties": {
    "name": "Amalfi",
    "country": "IT",
    "subdivision": "04",
    "timezone": "Europe/Rome"
  },
  "geometry": {
    "type": "Point",
    "coordinates": [
      14.60238,
      40.6349
    ]
  }
}