{
  "type": "Feature",
  "properties": {
    "name": "Anacapri",
    "country": "IT",
    "subdivision": "04",
    "timezone": "Europe/Rome"
  },
  "geometry": {
    "type": "Point",
    "coordinates": [
      14.21225,
      40.5517
    ]
  }
}