{
  "type": "Feature",
  "properties": {
    "name": "Apollosa",
    "country": "IT",
    "subdivision": "04",
    "timezone": "Europe/Rome"
  },
  "geometry": {
    "type": "Point",
    "coordinates": [
      14.69625,
      41.09156
    ]
  }
}