{
  "type": "Feature",
  "properties": {
    "name": "Benevento",
    "country": "IT",
    "subdivision": "04",
    "timezone": "Europe/Rome"
  },
  "geometry": {
    "type": "Point",
    "coordinates": [
      14.77816,
      41.1307
    ]
  }
}