{
  "type": "Feature",
  "properties": {
    "name": "Borgo",
    "country": "IT",
    "subdivision": "04",
    "timezone": "Europe/Rome"
  },
  "geometry": {
    "type": "Point",
    "coordinates": [
      14.78364,
      40.84022
    ]
  }
}