{
  "type": "Feature",
  "properties": {
    "name": "Calvizzano",
    "country": "IT",
    "subdivision": "04",
    "timezone": "Europe/Rome"
  },
  "geometry": {
    "type": "Point",
    "coordinates": [
      14.18581,
      40.90782
    ]
  }
}