{
  "type": "Feature",
  "properties": {
    "name": "Campanarello",
    "country": "IT",
    "subdivision": "04",
    "timezone": "Europe/Rome"
  },
  "geometry": {
    "type": "Point",
    "coordinates": [
      14.91418,
      41.04717
    ]
  }
}