{
  "type": "Feature",
  "properties": {
    "name": "Camposano",
    "country": "IT",
    "subdivision": "04",
    "timezone": "Europe/Rome"
  },
  "geometry": {
    "type": "Point",
    "coordinates": [
      14.52991,
      40.95242
    ]
  }
}