{
  "type": "Feature",
  "properties": {
    "name": "Capriglia",
    "country": "IT",
    "subdivision": "04",
    "timezone": "Europe/Rome"
  },
  "geometry": {
    "type": "Point",
    "coordinates": [
      14.76035,
      40.73216
    ]
  }
}