{
  "type": "Feature",
  "properties": {
    "name": "Cardito",
    "country": "IT",
    "subdivision": "04",
    "timezone": "Europe/Rome"
  },
  "geometry": {
    "type": "Point",
    "coordinates": [
      14.29952,
      40.9459
    ]
  }
}