{
  "type": "Feature",
  "properties": {
    "name": "Carife",
    "country": "IT",
    "subdivision": "04",
    "timezone": "Europe/Rome"
  },
  "geometry": {
    "type": "Point",
    "coordinates": [
      15.21044,
      41.02667
    ]
  }
}