{
  "type": "Feature",
  "properties": {
    "name": "Casalnuovo di Napoli",
    "country": "IT",
    "subdivision": "04",
    "timezone": "Europe/Rome"
  },
  "geometry": {
    "type": "Point",
    "coordinates": [
      14.34205,
      40.90969
    ]
  }
}