{
  "type": "Feature",
  "properties": {
    "name": "Casale",
    "country": "IT",
    "subdivision": "04",
    "timezone": "Europe/Rome"
  },
  "geometry": {
    "type": "Point",
    "coordinates": [
      14.00231,
      41.21972
    ]
  }
}