{
  "type": "Feature",
  "properties": {
    "name": "Casanova",
    "country": "IT",
    "subdivision": "04",
    "timezone": "Europe/Rome"
  },
  "geometry": {
    "type": "Point",
    "coordinates": [
      13.96344,
      41.19254
    ]
  }
}