{
  "type": "Feature",
  "properties": {
    "name": "Castiglione del Genovesi",
    "country": "IT",
    "subdivision": "04",
    "timezone": "Europe/Rome"
  },
  "geometry": {
    "type": "Point",
    "coordinates": [
      14.84796,
      40.72367
    ]
  }
}