{
  "type": "Feature",
  "properties": {
    "name": "Castel Morrone",
    "country": "IT",
    "subdivision": "04",
    "timezone": "Europe/Rome"
  },
  "geometry": {
    "type": "Point",
    "coordinates": [
      14.35473,
      41.12102
    ]
  }
}