{
  "type": "Feature",
  "properties": {
    "name": "Castelvetere sul Calore",
    "country": "IT",
    "subdivision": "04",
    "timezone": "Europe/Rome"
  },
  "geometry": {
    "type": "Point",
    "coordinates": [
      14.9864,
      40.9298
    ]
  }
}