{
  "type": "Feature",
  "properties": {
    "name": "Cautano",
    "country": "IT",
    "subdivision": "04",
    "timezone": "Europe/Rome"
  },
  "geometry": {
    "type": "Point",
    "coordinates": [
      14.64425,
      41.15009
    ]
  }
}