{
  "type": "Feature",
  "properties": {
    "name": "Cercola",
    "country": "IT",
    "subdivision": "04",
    "timezone": "Europe/Rome"
  },
  "geometry": {
    "type": "Point",
    "coordinates": [
      14.35733,
      40.86043
    ]
  }
}