{
  "type": "Feature",
  "properties": {
    "name": "Cimitile",
    "country": "IT",
    "subdivision": "04",
    "timezone": "Europe/Rome"
  },
  "geometry": {
    "type": "Point",
    "coordinates": [
      14.52558,
      40.94231
    ]
  }
}