{
  "type": "Feature",
  "properties": {
    "name": "Corbara",
    "country": "IT",
    "subdivision": "04",
    "timezone": "Europe/Rome"
  },
  "geometry": {
    "type": "Point",
    "coordinates": [
      14.59187,
      40.72278
    ]
  }
}