{
  "type": "Feature",
  "properties": {
    "name": "Crispano",
    "country": "IT",
    "subdivision": "04",
    "timezone": "Europe/Rome"
  },
  "geometry": {
    "type": "Point",
    "coordinates": [
      14.28993,
      40.95251
    ]
  }
}