{
  "type": "Feature",
  "properties": {
    "name": "Flumeri",
    "country": "IT",
    "subdivision": "04",
    "timezone": "Europe/Rome"
  },
  "geometry": {
    "type": "Point",
    "coordinates": [
      15.15072,
      41.07623
    ]
  }
}