{
  "type": "Feature",
  "properties": {
    "name": "Fontanarosa",
    "country": "IT",
    "subdivision": "04",
    "timezone": "Europe/Rome"
  },
  "geometry": {
    "type": "Point",
    "coordinates": [
      15.02055,
      41.01812
    ]
  }
}