{
  "type": "Feature",
  "properties": {
    "name": "Formicola",
    "country": "IT",
    "subdivision": "04",
    "timezone": "Europe/Rome"
  },
  "geometry": {
    "type": "Point",
    "coordinates": [
      14.23462,
      41.21084
    ]
  }
}