{
  "type": "Feature",
  "properties": {
    "name": "Lacco Ameno",
    "country": "IT",
    "subdivision": "04",
    "timezone": "Europe/Rome"
  },
  "geometry": {
    "type": "Point",
    "coordinates": [
      13.88718,
      40.74901
    ]
  }
}