{
  "type": "Feature",
  "properties": {
    "name": "Limatola",
    "country": "IT",
    "subdivision": "04",
    "timezone": "Europe/Rome"
  },
  "geometry": {
    "type": "Point",
    "coordinates": [
      14.39437,
      41.14012
    ]
  }
}