{
  "type": "Feature",
  "properties": {
    "name": "Maccoli-Perrillo",
    "country": "IT",
    "subdivision": "04",
    "timezone": "Europe/Rome"
  },
  "geometry": {
    "type": "Point",
    "coordinates": [
      14.80585,
      41.08762
    ]
  }
}