{
  "type": "Feature",
  "properties": {
    "name": "Macchia",
    "country": "IT",
    "subdivision": "04",
    "timezone": "Europe/Rome"
  },
  "geometry": {
    "type": "Point",
    "coordinates": [
      14.97879,
      40.65353
    ]
  }
}