{
  "type": "Feature",
  "properties": {
    "name": "Molinara",
    "country": "IT",
    "subdivision": "04",
    "timezone": "Europe/Rome"
  },
  "geometry": {
    "type": "Point",
    "coordinates": [
      14.90867,
      41.29728
    ]
  }
}