{
  "type": "Feature",
  "properties": {
    "name": "Mondragone",
    "country": "IT",
    "subdivision": "04",
    "timezone": "Europe/Rome"
  },
  "geometry": {
    "type": "Point",
    "coordinates": [
      13.89157,
      41.11399
    ]
  }
}