{
  "type": "Feature",
  "properties": {
    "name": "Montecorvino Pugliano",
    "country": "IT",
    "subdivision": "04",
    "timezone": "Europe/Rome"
  },
  "geometry": {
    "type": "Point",
    "coordinates": [
      14.94475,
      40.67921
    ]
  }
}