{
  "type": "Feature",
  "properties": {
    "name": "Monticelli",
    "country": "IT",
    "subdivision": "04",
    "timezone": "Europe/Rome"
  },
  "geometry": {
    "type": "Point",
    "coordinates": [
      15.01667,
      40.65
    ]
  }
}