{
  "type": "Feature",
  "properties": {
    "name": "Montefalcione",
    "country": "IT",
    "subdivision": "04",
    "timezone": "Europe/Rome"
  },
  "geometry": {
    "type": "Point",
    "coordinates": [
      14.88312,
      40.96173
    ]
  }
}