{
  "type": "Feature",
  "properties": {
    "name": "Montoro Superiore",
    "country": "IT",
    "subdivision": "04",
    "timezone": "Europe/Rome"
  },
  "geometry": {
    "type": "Point",
    "coordinates": [
      14.79841,
      40.81699
    ]
  }
}