{
  "type": "Feature",
  "properties": {
    "name": "Pannarano",
    "country": "IT",
    "subdivision": "04",
    "timezone": "Europe/Rome"
  },
  "geometry": {
    "type": "Point",
    "coordinates": [
      14.70293,
      41.01082
    ]
  }
}