{
  "type": "Feature",
  "properties": {
    "name": "Passo di Mirabella-Pianopantano",
    "country": "IT",
    "subdivision": "04",
    "timezone": "Europe/Rome"
  },
  "geometry": {
    "type": "Point",
    "coordinates": [
      15.01649,
      41.05468
    ]
  }
}