{
  "type": "Feature",
  "properties": {
    "name": "Pezzano-Filetta",
    "country": "IT",
    "subdivision": "04",
    "timezone": "Europe/Rome"
  },
  "geometry": {
    "type": "Point",
    "coordinates": [
      14.86971,
      40.69773
    ]
  }
}