{
  "type": "Feature",
  "properties": {
    "name": "Pianillo",
    "country": "IT",
    "subdivision": "04",
    "timezone": "Europe/Rome"
  },
  "geometry": {
    "type": "Point",
    "coordinates": [
      14.54922,
      40.63416
    ]
  }
}