{
  "type": "Feature",
  "properties": {
    "name": "Policastro Bussentino",
    "country": "IT",
    "subdivision": "04",
    "timezone": "Europe/Rome"
  },
  "geometry": {
    "type": "Point",
    "coordinates": [
      15.52165,
      40.07511
    ]
  }
}