{
  "type": "Feature",
  "properties": {
    "name": "Pozzuoli",
    "country": "IT",
    "subdivision": "04",
    "timezone": "Europe/Rome"
  },
  "geometry": {
    "type": "Point",
    "coordinates": [
      14.0952,
      40.84394
    ]
  }
}