{
  "type": "Feature",
  "properties": {
    "name": "Pratole",
    "country": "IT",
    "subdivision": "04",
    "timezone": "Europe/Rome"
  },
  "geometry": {
    "type": "Point",
    "coordinates": [
      14.92565,
      40.6258
    ]
  }
}