{
  "type": "Feature",
  "properties": {
    "name": "Quadrivio",
    "country": "IT",
    "subdivision": "04",
    "timezone": "Europe/Rome"
  },
  "geometry": {
    "type": "Point",
    "coordinates": [
      15.10353,
      40.62494
    ]
  }
}