{
  "type": "Feature",
  "properties": {
    "name": "Roccarainola",
    "country": "IT",
    "subdivision": "04",
    "timezone": "Europe/Rome"
  },
  "geometry": {
    "type": "Point",
    "coordinates": [
      14.54283,
      40.9725
    ]
  }
}