{
  "type": "Feature",
  "properties": {
    "name": "San Potito Sannitico",
    "country": "IT",
    "subdivision": "04",
    "timezone": "Europe/Rome"
  },
  "geometry": {
    "type": "Point",
    "coordinates": [
      14.39185,
      41.33698
    ]
  }
}