{
  "type": "Feature",
  "properties": {
    "name": "San Marzano sul Sarno",
    "country": "IT",
    "subdivision": "04",
    "timezone": "Europe/Rome"
  },
  "geometry": {
    "type": "Point",
    "coordinates": [
      14.58006,
      40.77801
    ]
  }
}