{
  "type": "Feature",
  "properties": {
    "name": "Santa Tecla-Castelpagano",
    "country": "IT",
    "subdivision": "04",
    "timezone": "Europe/Rome"
  },
  "geometry": {
    "type": "Point",
    "coordinates": [
      14.91806,
      40.67353
    ]
  }
}