{
  "type": "Feature",
  "properties": {
    "name": "Santa Maria",
    "country": "IT",
    "subdivision": "04",
    "timezone": "Europe/Rome"
  },
  "geometry": {
    "type": "Point",
    "coordinates": [
      14.95214,
      40.29782
    ]
  }
}