{
  "type": "Feature",
  "properties": {
    "name": "Sapri",
    "country": "IT",
    "subdivision": "04",
    "timezone": "Europe/Rome"
  },
  "geometry": {
    "type": "Point",
    "coordinates": [
      15.63212,
      40.07464
    ]
  }
}