{
  "type": "Feature",
  "properties": {
    "name": "Serino",
    "country": "IT",
    "subdivision": "04",
    "timezone": "Europe/Rome"
  },
  "geometry": {
    "type": "Point",
    "coordinates": [
      14.87224,
      40.85481
    ]
  }
}