{
  "type": "Feature",
  "properties": {
    "name": "Sperone",
    "country": "IT",
    "subdivision": "04",
    "timezone": "Europe/Rome"
  },
  "geometry": {
    "type": "Point",
    "coordinates": [
      14.60524,
      40.95251
    ]
  }
}