{
  "type": "Feature",
  "properties": {
    "name": "Striano",
    "country": "IT",
    "subdivision": "04",
    "timezone": "Europe/Rome"
  },
  "geometry": {
    "type": "Point",
    "coordinates": [
      14.57534,
      40.81543
    ]
  }
}