{
  "type": "Feature",
  "properties": {
    "name": "Tufino",
    "country": "IT",
    "subdivision": "04",
    "timezone": "Europe/Rome"
  },
  "geometry": {
    "type": "Point",
    "coordinates": [
      14.56568,
      40.95586
    ]
  }
}