{
  "type": "Feature",
  "properties": {
    "name": "Valle di Maddaloni",
    "country": "IT",
    "subdivision": "04",
    "timezone": "Europe/Rome"
  },
  "geometry": {
    "type": "Point",
    "coordinates": [
      14.41788,
      41.07946
    ]
  }
}