{
  "type": "Feature",
  "properties": {
    "name": "Vietri sul Mare",
    "country": "IT",
    "subdivision": "04",
    "timezone": "Europe/Rome"
  },
  "geometry": {
    "type": "Point",
    "coordinates": [
      14.72661,
      40.6702
    ]
  }
}