{
  "type": "Feature",
  "properties": {
    "name": "Villaricca",
    "country": "IT",
    "subdivision": "04",
    "timezone": "Europe/Rome"
  },
  "geometry": {
    "type": "Point",
    "coordinates": [
      14.19339,
      40.92006
    ]
  }
}