{
  "type": "Feature",
  "properties": {
    "name": "Volturara Irpina",
    "country": "IT",
    "subdivision": "04",
    "timezone": "Europe/Rome"
  },
  "geometry": {
    "type": "Point",
    "coordinates": [
      14.91801,
      40.88293
    ]
  }
}