{
  "type": "Feature",
  "properties": {
    "name": "Zuni",
    "country": "IT",
    "subdivision": "04",
    "timezone": "Europe/Rome"
  },
  "geometry": {
    "type": "Point",
    "coordinates": [
      14.13082,
      41.21722
    ]
  }
}