{
  "type": "Feature",
  "properties": {
    "name": "Hoeryŏng",
    "country": "KP",
    "subdivision": "17",
    "timezone": "Asia/Pyongyang"
  },
  "geometry": {
    "type": "Point",
    "coordinates": [
      129.74601,
      42.44113
    ]
  }
}