{
  "type": "Feature",
  "properties": {
    "name": "Aquiraz",
    "country": "BR",
    "subdivision": "06",
    "timezone": "America/Fortaleza"
  },
  "geometry": {
    "type": "Point",
    "coordinates": [
      -38.39111,
      -3.90139
    ]
  }
}