{
  "type": "Feature",
  "properties": {
    "name": "Araripe",
    "country": "BR",
    "subdivision": "06",
    "timezone": "America/Fortaleza"
  },
  "geometry": {
    "type": "Point",
    "coordinates": [
      -40.137,
      -7.21337
    ]
  }
}