{
  "type": "Feature",
  "properties": {
    "name": "Camocim",
    "country": "BR",
    "subdivision": "06",
    "timezone": "America/Fortaleza"
  },
  "geometry": {
    "type": "Point",
    "coordinates": [
      -40.84111,
      -2.90222
    ]
  }
}