{
  "type": "Feature",
  "properties": {
    "name": "Caririaçu",
    "country": "BR",
    "subdivision": "06",
    "timezone": "America/Fortaleza"
  },
  "geometry": {
    "type": "Point",
    "coordinates": [
      -39.28361,
      -7.04222
    ]
  }
}