{
  "type": "Feature",
  "properties": {
    "name": "Forquilha",
    "country": "BR",
    "subdivision": "06",
    "timezone": "America/Fortaleza"
  },
  "geometry": {
    "type": "Point",
    "coordinates": [
      -40.26056,
      -3.79833
    ]
  }
}