{
  "type": "Feature",
  "properties": {
    "name": "Granja",
    "country": "BR",
    "subdivision": "06",
    "timezone": "America/Fortaleza"
  },
  "geometry": {
    "type": "Point",
    "coordinates": [
      -40.82611,
      -3.12028
    ]
  }
}