{
  "type": "Feature",
  "properties": {
    "name": "Guaraciaba do Norte",
    "country": "BR",
    "subdivision": "06",
    "timezone": "America/Fortaleza"
  },
  "geometry": {
    "type": "Point",
    "coordinates": [
      -40.7475,
      -4.16694
    ]
  }
}