{
  "type": "Feature",
  "properties": {
    "name": "Mombaça",
    "country": "BR",
    "subdivision": "06",
    "timezone": "America/Fortaleza"
  },
  "geometry": {
    "type": "Point",
    "coordinates": [
      -39.6275,
      -5.74306
    ]
  }
}