{
  "type": "Feature",
  "properties": {
    "name": "Senador Pompeu",
    "country": "BR",
    "subdivision": "06",
    "timezone": "America/Fortaleza"
  },
  "geometry": {
    "type": "Point",
    "coordinates": [
      -39.37167,
      -5.58806
    ]
  }
}