{
  "type": "Feature",
  "properties": {
    "name": "Tianguá",
    "country": "BR",
    "subdivision": "06",
    "timezone": "America/Fortaleza"
  },
  "geometry": {
    "type": "Point",
    "coordinates": [
      -40.99167,
      -3.73222
    ]
  }
}