{
  "type": "Feature",
  "properties": {
    "name": "Várzea Alegre",
    "country": "BR",
    "subdivision": "06",
    "timezone": "America/Fortaleza"
  },
  "geometry": {
    "type": "Point",
    "coordinates": [
      -40.38333,
      -5.35
    ]
  }
}