{
  "type": "Feature",
  "properties": {
    "name": "Guichón",
    "country": "UY",
    "subdivision": "11",
    "timezone": "America/Montevideo"
  },
  "geometry": {
    "type": "Point",
    "coordinates": [
      -57.19778,
      -32.35846
    ]
  }
}