{
  "type": "Feature",
  "properties": {
    "name": "Uzunköprü",
    "country": "TR",
    "subdivision": "22",
    "timezone": "Europe/Istanbul"
  },
  "geometry": {
    "type": "Point",
    "coordinates": [
      26.6885,
      41.26597
    ]
  }
}