{
  "type": "Feature",
  "properties": {
    "name": "Murgul",
    "country": "TR",
    "subdivision": "08",
    "timezone": "Europe/Istanbul"
  },
  "geometry": {
    "type": "Point",
    "coordinates": [
      41.56438,
      41.28049
    ]
  }
}