{
  "type": "Feature",
  "properties": {
    "name": "Şavşat",
    "country": "TR",
    "subdivision": "08",
    "timezone": "Europe/Istanbul"
  },
  "geometry": {
    "type": "Point",
    "coordinates": [
      42.35531,
      41.25336
    ]
  }
}