{
  "type": "Feature",
  "properties": {
    "name": "Naftalan",
    "country": "AZ",
    "subdivision": "34",
    "timezone": "Asia/Baku"
  },
  "geometry": {
    "type": "Point",
    "coordinates": [
      46.8203,
      40.50821
    ]
  }
}