{
  "type": "Feature",
  "properties": {
    "name": "Attinghausen",
    "country": "CH",
    "subdivision": "UR",
    "timezone": "Europe/Zurich"
  },
  "geometry": {
    "type": "Point",
    "coordinates": [
      8.63036,
      46.86255
    ]
  }
}