{
  "type": "Feature",
  "properties": {
    "name": "Banjol",
    "country": "HR",
    "subdivision": "12",
    "timezone": "Europe/Zagreb"
  },
  "geometry": {
    "type": "Point",
    "coordinates": [
      14.78333,
      44.75
    ]
  }
}