{
  "type": "Feature",
  "properties": {
    "name": "Bribir",
    "country": "HR",
    "subdivision": "12",
    "timezone": "Europe/Zagreb"
  },
  "geometry": {
    "type": "Point",
    "coordinates": [
      14.76472,
      45.16111
    ]
  }
}