{
  "type": "Feature",
  "properties": {
    "name": "Dražice",
    "country": "HR",
    "subdivision": "12",
    "timezone": "Europe/Zagreb"
  },
  "geometry": {
    "type": "Point",
    "coordinates": [
      14.47028,
      45.39083
    ]
  }
}