{
  "type": "Feature",
  "properties": {
    "name": "Marinići",
    "country": "HR",
    "subdivision": "12",
    "timezone": "Europe/Zagreb"
  },
  "geometry": {
    "type": "Point",
    "coordinates": [
      14.39389,
      45.365
    ]
  }
}