{
  "type": "Feature",
  "properties": {
    "name": "Opatija",
    "country": "HR",
    "subdivision": "12",
    "timezone": "Europe/Zagreb"
  },
  "geometry": {
    "type": "Point",
    "coordinates": [
      14.30782,
      45.33658
    ]
  }
}