{
  "type": "Feature",
  "properties": {
    "name": "Rubeši",
    "country": "HR",
    "subdivision": "12",
    "timezone": "Europe/Zagreb"
  },
  "geometry": {
    "type": "Point",
    "coordinates": [
      14.34806,
      45.36694
    ]
  }
}