{
  "type": "Feature",
  "properties": {
    "name": "Akbou",
    "country": "DZ",
    "subdivision": "18",
    "timezone": "Africa/Algiers"
  },
  "geometry": {
    "type": "Point",
    "coordinates": [
      4.53494,
      36.4575
    ]
  }
}