{
  "type": "Feature",
  "properties": {
    "name": "Dabas",
    "country": "HU",
    "subdivision": "16",
    "timezone": "Europe/Budapest"
  },
  "geometry": {
    "type": "Point",
    "coordinates": [
      19.31091,
      47.18594
    ]
  }
}