{
  "type": "Feature",
  "properties": {
    "name": "Délegyháza",
    "country": "HU",
    "subdivision": "16",
    "timezone": "Europe/Budapest"
  },
  "geometry": {
    "type": "Point",
    "coordinates": [
      19.09019,
      47.24135
    ]
  }
}