{
  "type": "Feature",
  "properties": {
    "name": "Gödöllő",
    "country": "HU",
    "subdivision": "16",
    "timezone": "Europe/Budapest"
  },
  "geometry": {
    "type": "Point",
    "coordinates": [
      19.35515,
      47.59657
    ]
  }
}