{
  "type": "Feature",
  "properties": {
    "name": "Kakucs",
    "country": "HU",
    "subdivision": "16",
    "timezone": "Europe/Budapest"
  },
  "geometry": {
    "type": "Point",
    "coordinates": [
      19.36467,
      47.242
    ]
  }
}