{
  "type": "Feature",
  "properties": {
    "name": "Kismaros",
    "country": "HU",
    "subdivision": "16",
    "timezone": "Europe/Budapest"
  },
  "geometry": {
    "type": "Point",
    "coordinates": [
      19.00463,
      47.83742
    ]
  }
}