{
  "type": "Feature",
  "properties": {
    "name": "Leányfalu",
    "country": "HU",
    "subdivision": "16",
    "timezone": "Europe/Budapest"
  },
  "geometry": {
    "type": "Point",
    "coordinates": [
      19.08585,
      47.71778
    ]
  }
}