{
  "type": "Feature",
  "properties": {
    "name": "Maglód",
    "country": "HU",
    "subdivision": "16",
    "timezone": "Europe/Budapest"
  },
  "geometry": {
    "type": "Point",
    "coordinates": [
      19.36438,
      47.44258
    ]
  }
}