{
  "type": "Feature",
  "properties": {
    "name": "Mende",
    "country": "HU",
    "subdivision": "16",
    "timezone": "Europe/Budapest"
  },
  "geometry": {
    "type": "Point",
    "coordinates": [
      19.45628,
      47.43133
    ]
  }
}