{
  "type": "Feature",
  "properties": {
    "name": "Nagytarcsa",
    "country": "HU",
    "subdivision": "16",
    "timezone": "Europe/Budapest"
  },
  "geometry": {
    "type": "Point",
    "coordinates": [
      19.28343,
      47.53128
    ]
  }
}