{
  "type": "Feature",
  "properties": {
    "name": "Nagymaros",
    "country": "HU",
    "subdivision": "16",
    "timezone": "Europe/Budapest"
  },
  "geometry": {
    "type": "Point",
    "coordinates": [
      18.95984,
      47.7928
    ]
  }
}