{
  "type": "Feature",
  "properties": {
    "name": "Perbál",
    "country": "HU",
    "subdivision": "16",
    "timezone": "Europe/Budapest"
  },
  "geometry": {
    "type": "Point",
    "coordinates": [
      18.76099,
      47.58957
    ]
  }
}