{
  "type": "Feature",
  "properties": {
    "name": "Pomáz",
    "country": "HU",
    "subdivision": "16",
    "timezone": "Europe/Budapest"
  },
  "geometry": {
    "type": "Point",
    "coordinates": [
      19.02784,
      47.64227
    ]
  }
}