{
  "type": "Feature",
  "properties": {
    "name": "Szigethalom",
    "country": "HU",
    "subdivision": "16",
    "timezone": "Europe/Budapest"
  },
  "geometry": {
    "type": "Point",
    "coordinates": [
      19.00262,
      47.32228
    ]
  }
}