{
  "type": "Feature",
  "properties": {
    "name": "Tápiógyörgye",
    "country": "HU",
    "subdivision": "16",
    "timezone": "Europe/Budapest"
  },
  "geometry": {
    "type": "Point",
    "coordinates": [
      19.95276,
      47.33505
    ]
  }
}