{
  "type": "Feature",
  "properties": {
    "name": "Újszilvás",
    "country": "HU",
    "subdivision": "16",
    "timezone": "Europe/Budapest"
  },
  "geometry": {
    "type": "Point",
    "coordinates": [
      19.92477,
      47.27477
    ]
  }
}