{
  "type": "Feature",
  "properties": {
    "name": "Úri",
    "country": "HU",
    "subdivision": "16",
    "timezone": "Europe/Budapest"
  },
  "geometry": {
    "type": "Point",
    "coordinates": [
      19.52762,
      47.41429
    ]
  }
}