{
  "type": "Feature",
  "properties": {
    "name": "Üröm",
    "country": "HU",
    "subdivision": "16",
    "timezone": "Europe/Budapest"
  },
  "geometry": {
    "type": "Point",
    "coordinates": [
      19.01583,
      47.59674
    ]
  }
}