{
  "type": "Feature",
  "properties": {
    "name": "Zsámbok",
    "country": "HU",
    "subdivision": "16",
    "timezone": "Europe/Budapest"
  },
  "geometry": {
    "type": "Point",
    "coordinates": [
      19.61048,
      47.54381
    ]
  }
}