{
  "type": "Feature",
  "properties": {
    "name": "Češinovo",
    "country": "MK",
    "subdivision": "19",
    "timezone": "Europe/Skopje"
  },
  "geometry": {
    "type": "Point",
    "coordinates": [
      22.28961,
      41.87148
    ]
  }
}