{
  "type": "Feature",
  "properties": {
    "name": "Bonabéri",
    "country": "CM",
    "subdivision": "05",
    "timezone": "Africa/Douala"
  },
  "geometry": {
    "type": "Point",
    "coordinates": [
      9.68177,
      4.07142
    ]
  }
}