{
  "type": "Feature",
  "properties": {
    "name": "Dibombari",
    "country": "CM",
    "subdivision": "05",
    "timezone": "Africa/Douala"
  },
  "geometry": {
    "type": "Point",
    "coordinates": [
      9.6561,
      4.1787
    ]
  }
}