{
  "type": "Feature",
  "properties": {
    "name": "Bezhetsk",
    "country": "RU",
    "subdivision": "77",
    "timezone": "Europe/Moscow"
  },
  "geometry": {
    "type": "Point",
    "coordinates": [
      36.69651,
      57.78506
    ]
  }
}