{
  "type": "Feature",
  "properties": {
    "name": "Emmaus",
    "country": "RU",
    "subdivision": "77",
    "timezone": "Europe/Moscow"
  },
  "geometry": {
    "type": "Point",
    "coordinates": [
      36.115,
      56.78055
    ]
  }
}