{
  "type": "Feature",
  "properties": {
    "name": "Izoplit",
    "country": "RU",
    "subdivision": "77",
    "timezone": "Europe/Moscow"
  },
  "geometry": {
    "type": "Point",
    "coordinates": [
      36.22198,
      56.62558
    ]
  }
}