{
  "type": "Feature",
  "properties": {
    "name": "Kalyazin",
    "country": "RU",
    "subdivision": "77",
    "timezone": "Europe/Moscow"
  },
  "geometry": {
    "type": "Point",
    "coordinates": [
      37.84333,
      57.24028
    ]
  }
}