{
  "type": "Feature",
  "properties": {
    "name": "Kesova Gora",
    "country": "RU",
    "subdivision": "77",
    "timezone": "Europe/Moscow"
  },
  "geometry": {
    "type": "Point",
    "coordinates": [
      37.29222,
      57.58361
    ]
  }
}