{
  "type": "Feature",
  "properties": {
    "name": "Krasnomayskiy",
    "country": "RU",
    "subdivision": "77",
    "timezone": "Europe/Moscow"
  },
  "geometry": {
    "type": "Point",
    "coordinates": [
      34.40987,
      57.61941
    ]
  }
}