{
  "type": "Feature",
  "properties": {
    "name": "Kuzhenkino",
    "country": "RU",
    "subdivision": "77",
    "timezone": "Europe/Moscow"
  },
  "geometry": {
    "type": "Point",
    "coordinates": [
      33.95083,
      57.76111
    ]
  }
}