{
  "type": "Feature",
  "properties": {
    "name": "Selizharovo",
    "country": "RU",
    "subdivision": "77",
    "timezone": "Europe/Moscow"
  },
  "geometry": {
    "type": "Point",
    "coordinates": [
      33.44869,
      56.85188
    ]
  }
}