{
  "type": "Feature",
  "properties": {
    "name": "Toropets",
    "country": "RU",
    "subdivision": "77",
    "timezone": "Europe/Moscow"
  },
  "geometry": {
    "type": "Point",
    "coordinates": [
      31.63528,
      56.49779
    ]
  }
}