{
  "type": "Feature",
  "properties": {
    "name": "Udomlya",
    "country": "RU",
    "subdivision": "77",
    "timezone": "Europe/Moscow"
  },
  "geometry": {
    "type": "Point",
    "coordinates": [
      34.9925,
      57.87944
    ]
  }
}