{
  "type": "Feature",
  "properties": {
    "name": "Vypolzovo",
    "country": "RU",
    "subdivision": "77",
    "timezone": "Europe/Moscow"
  },
  "geometry": {
    "type": "Point",
    "coordinates": [
      33.69861,
      57.87667
    ]
  }
}