{
  "type": "Feature",
  "properties": {
    "name": "Bela Vista",
    "country": "BR",
    "subdivision": "11",
    "timezone": "America/Campo_Grande"
  },
  "geometry": {
    "type": "Point",
    "coordinates": [
      -56.52111,
      -22.10889
    ]
  }
}