{
  "type": "Feature",
  "properties": {
    "name": "Bonito",
    "country": "BR",
    "subdivision": "11",
    "timezone": "America/Campo_Grande"
  },
  "geometry": {
    "type": "Point",
    "coordinates": [
      -56.48194,
      -21.12111
    ]
  }
}