{
  "type": "Feature",
  "properties": {
    "name": "Naviraí",
    "country": "BR",
    "subdivision": "11",
    "timezone": "America/Campo_Grande"
  },
  "geometry": {
    "type": "Point",
    "coordinates": [
      -54.19056,
      -23.065
    ]
  }
}