{
  "type": "Feature",
  "properties": {
    "name": "Paraíso das Águas",
    "country": "BR",
    "subdivision": "11",
    "timezone": "America/Campo_Grande"
  },
  "geometry": {
    "type": "Point",
    "coordinates": [
      -53.01222,
      -19.0175
    ]
  }
}