{
  "type": "Feature",
  "properties": {
    "name": "Sidrolândia",
    "country": "BR",
    "subdivision": "11",
    "timezone": "America/Campo_Grande"
  },
  "geometry": {
    "type": "Point",
    "coordinates": [
      -54.96139,
      -20.93194
    ]
  }
}