{
  "type": "Feature",
  "properties": {
    "name": "Terenos",
    "country": "BR",
    "subdivision": "11",
    "timezone": "America/Campo_Grande"
  },
  "geometry": {
    "type": "Point",
    "coordinates": [
      -54.86028,
      -20.44222
    ]
  }
}