{
  "type": "Feature",
  "properties": {
    "name": "Băcani",
    "country": "RO",
    "subdivision": "38",
    "timezone": "Europe/Bucharest"
  },
  "geometry": {
    "type": "Point",
    "coordinates": [
      27.66667,
      46.33333
    ]
  }
}