{
  "type": "Feature",
  "properties": {
    "name": "Măluşteni",
    "country": "RO",
    "subdivision": "38",
    "timezone": "Europe/Bucharest"
  },
  "geometry": {
    "type": "Point",
    "coordinates": [
      27.91667,
      46.18333
    ]
  }
}