{
  "type": "Feature",
  "properties": {
    "name": "Murgeni",
    "country": "RO",
    "subdivision": "38",
    "timezone": "Europe/Bucharest"
  },
  "geometry": {
    "type": "Point",
    "coordinates": [
      28.01972,
      46.20444
    ]
  }
}