{
  "type": "Feature",
  "properties": {
    "name": "Negreşti",
    "country": "RO",
    "subdivision": "38",
    "timezone": "Europe/Bucharest"
  },
  "geometry": {
    "type": "Point",
    "coordinates": [
      27.43333,
      46.83333
    ]
  }
}