{
  "type": "Feature",
  "properties": {
    "name": "Pogănești",
    "country": "RO",
    "subdivision": "38",
    "timezone": "Europe/Bucharest"
  },
  "geometry": {
    "type": "Point",
    "coordinates": [
      28.16779,
      46.69237
    ]
  }
}