{
  "type": "Feature",
  "properties": {
    "name": "Rafaila",
    "country": "RO",
    "subdivision": "38",
    "timezone": "Europe/Bucharest"
  },
  "geometry": {
    "type": "Point",
    "coordinates": [
      27.36236,
      46.80064
    ]
  }
}