{
  "type": "Feature",
  "properties": {
    "name": "Râșești",
    "country": "RO",
    "subdivision": "38",
    "timezone": "Europe/Bucharest"
  },
  "geometry": {
    "type": "Point",
    "coordinates": [
      28.14273,
      46.77219
    ]
  }
}