{
  "type": "Feature",
  "properties": {
    "name": "Roşieşti",
    "country": "RO",
    "subdivision": "38",
    "timezone": "Europe/Bucharest"
  },
  "geometry": {
    "type": "Point",
    "coordinates": [
      27.88333,
      46.43333
    ]
  }
}