{
  "type": "Feature",
  "properties": {
    "name": "Åmål",
    "country": "SE",
    "subdivision": "28",
    "timezone": "Europe/Stockholm"
  },
  "geometry": {
    "type": "Point",
    "coordinates": [
      12.70492,
      59.051
    ]
  }
}