{
  "type": "Feature",
  "properties": {
    "name": "Axvall",
    "country": "SE",
    "subdivision": "28",
    "timezone": "Europe/Stockholm"
  },
  "geometry": {
    "type": "Point",
    "coordinates": [
      13.56667,
      58.38333
    ]
  }
}