{
  "type": "Feature",
  "properties": {
    "name": "Eriksbo",
    "country": "SE",
    "subdivision": "28",
    "timezone": "Europe/Stockholm"
  },
  "geometry": {
    "type": "Point",
    "coordinates": [
      12.04183,
      57.77141
    ]
  }
}