{
  "type": "Feature",
  "properties": {
    "name": "Färgelanda",
    "country": "SE",
    "subdivision": "28",
    "timezone": "Europe/Stockholm"
  },
  "geometry": {
    "type": "Point",
    "coordinates": [
      11.99235,
      58.56816
    ]
  }
}