{
  "type": "Feature",
  "properties": {
    "name": "Floby",
    "country": "SE",
    "subdivision": "28",
    "timezone": "Europe/Stockholm"
  },
  "geometry": {
    "type": "Point",
    "coordinates": [
      13.33333,
      58.13333
    ]
  }
}