{
  "type": "Feature",
  "properties": {
    "name": "Höviksnäs",
    "country": "SE",
    "subdivision": "28",
    "timezone": "Europe/Stockholm"
  },
  "geometry": {
    "type": "Point",
    "coordinates": [
      11.76667,
      58.03333
    ]
  }
}