{
  "type": "Feature",
  "properties": {
    "name": "Nolvik",
    "country": "SE",
    "subdivision": "28",
    "timezone": "Europe/Stockholm"
  },
  "geometry": {
    "type": "Point",
    "coordinates": [
      11.83333,
      57.775
    ]
  }
}