{
  "type": "Feature",
  "properties": {
    "name": "Öckerö",
    "country": "SE",
    "subdivision": "28",
    "timezone": "Europe/Stockholm"
  },
  "geometry": {
    "type": "Point",
    "coordinates": [
      11.65585,
      57.70814
    ]
  }
}