{
  "type": "Feature",
  "properties": {
    "name": "Olstorp",
    "country": "SE",
    "subdivision": "28",
    "timezone": "Europe/Stockholm"
  },
  "geometry": {
    "type": "Point",
    "coordinates": [
      12.27696,
      57.82277
    ]
  }
}