{
  "type": "Feature",
  "properties": {
    "name": "Rannebergen",
    "country": "SE",
    "subdivision": "28",
    "timezone": "Europe/Stockholm"
  },
  "geometry": {
    "type": "Point",
    "coordinates": [
      12.07131,
      57.80236
    ]
  }
}