{
  "type": "Feature",
  "properties": {
    "name": "Rävlanda",
    "country": "SE",
    "subdivision": "28",
    "timezone": "Europe/Stockholm"
  },
  "geometry": {
    "type": "Point",
    "coordinates": [
      12.49791,
      57.65338
    ]
  }
}