{
  "type": "Feature",
  "properties": {
    "name": "Rönnäng",
    "country": "SE",
    "subdivision": "28",
    "timezone": "Europe/Stockholm"
  },
  "geometry": {
    "type": "Point",
    "coordinates": [
      11.58333,
      57.93333
    ]
  }
}