{
  "type": "Feature",
  "properties": {
    "name": "Stenungsund",
    "country": "SE",
    "subdivision": "28",
    "timezone": "Europe/Stockholm"
  },
  "geometry": {
    "type": "Point",
    "coordinates": [
      11.8181,
      58.07046
    ]
  }
}