{
  "type": "Feature",
  "properties": {
    "name": "Vänersborg",
    "country": "SE",
    "subdivision": "28",
    "timezone": "Europe/Stockholm"
  },
  "geometry": {
    "type": "Point",
    "coordinates": [
      12.3234,
      58.38075
    ]
  }
}