{
  "type": "Feature",
  "properties": {
    "name": "Vargön",
    "country": "SE",
    "subdivision": "28",
    "timezone": "Europe/Stockholm"
  },
  "geometry": {
    "type": "Point",
    "coordinates": [
      12.3906,
      58.35599
    ]
  }
}