{
  "type": "Feature",
  "properties": {
    "name": "Viskafors",
    "country": "SE",
    "subdivision": "28",
    "timezone": "Europe/Stockholm"
  },
  "geometry": {
    "type": "Point",
    "coordinates": [
      12.8489,
      57.62941
    ]
  }
}