{
  "type": "Feature",
  "properties": {
    "name": "Aldeia Nova de São Bento",
    "country": "PT",
    "subdivision": "03",
    "timezone": "Europe/Lisbon"
  },
  "geometry": {
    "type": "Point",
    "coordinates": [
      -7.40804,
      37.92603
    ]
  }
}