{
  "type": "Feature",
  "properties": {
    "name": "Almodôvar",
    "country": "PT",
    "subdivision": "03",
    "timezone": "Europe/Lisbon"
  },
  "geometry": {
    "type": "Point",
    "coordinates": [
      -8.06008,
      37.51279
    ]
  }
}