{
  "type": "Feature",
  "properties": {
    "name": "Boavista dos Pinheiros",
    "country": "PT",
    "subdivision": "03",
    "timezone": "Europe/Lisbon"
  },
  "geometry": {
    "type": "Point",
    "coordinates": [
      -8.66441,
      37.58058
    ]
  }
}