{
  "type": "Feature",
  "properties": {
    "name": "Minas de São Domingos",
    "country": "PT",
    "subdivision": "03",
    "timezone": "Europe/Lisbon"
  },
  "geometry": {
    "type": "Point",
    "coordinates": [
      -7.49765,
      37.67322
    ]
  }
}