{
  "type": "Feature",
  "properties": {
    "name": "Serpa",
    "country": "PT",
    "subdivision": "03",
    "timezone": "Europe/Lisbon"
  },
  "geometry": {
    "type": "Point",
    "coordinates": [
      -7.59754,
      37.94581
    ]
  }
}