{
  "type": "Feature",
  "properties": {
    "name": "Druzhnaya Gorka",
    "country": "RU",
    "subdivision": "42",
    "timezone": "Europe/Moscow"
  },
  "geometry": {
    "type": "Point",
    "coordinates": [
      30.12709,
      59.28018
    ]
  }
}