{
  "type": "Feature",
  "properties": {
    "name": "Garbolovo",
    "country": "RU",
    "subdivision": "42",
    "timezone": "Europe/Moscow"
  },
  "geometry": {
    "type": "Point",
    "coordinates": [
      30.49551,
      60.34127
    ]
  }
}