{
  "type": "Feature",
  "properties": {
    "name": "Khvalovo",
    "country": "RU",
    "subdivision": "42",
    "timezone": "Europe/Moscow"
  },
  "geometry": {
    "type": "Point",
    "coordinates": [
      32.73723,
      59.94774
    ]
  }
}