{
  "type": "Feature",
  "properties": {
    "name": "Kingisepp",
    "country": "RU",
    "subdivision": "42",
    "timezone": "Europe/Moscow"
  },
  "geometry": {
    "type": "Point",
    "coordinates": [
      28.61343,
      59.37331
    ]
  }
}