{
  "type": "Feature",
  "properties": {
    "name": "Kopor’ye",
    "country": "RU",
    "subdivision": "42",
    "timezone": "Europe/Moscow"
  },
  "geometry": {
    "type": "Point",
    "coordinates": [
      29.042,
      59.70633
    ]
  }
}