{
  "type": "Feature",
  "properties": {
    "name": "Luppolovo",
    "country": "RU",
    "subdivision": "42",
    "timezone": "Europe/Moscow"
  },
  "geometry": {
    "type": "Point",
    "coordinates": [
      30.28034,
      60.15402
    ]
  }
}