{
  "type": "Feature",
  "properties": {
    "name": "Osel’ki",
    "country": "RU",
    "subdivision": "42",
    "timezone": "Europe/Moscow"
  },
  "geometry": {
    "type": "Point",
    "coordinates": [
      30.49667,
      60.20503
    ]
  }
}