{
  "type": "Feature",
  "properties": {
    "name": "Podporozh’ye",
    "country": "RU",
    "subdivision": "42",
    "timezone": "Europe/Moscow"
  },
  "geometry": {
    "type": "Point",
    "coordinates": [
      34.17064,
      60.91124
    ]
  }
}