{
  "type": "Feature",
  "properties": {
    "name": "Shcheglovo",
    "country": "RU",
    "subdivision": "42",
    "timezone": "Europe/Moscow"
  },
  "geometry": {
    "type": "Point",
    "coordinates": [
      30.75289,
      60.02839
    ]
  }
}