{
  "type": "Feature",
  "properties": {
    "name": "Staraya Ladoga",
    "country": "RU",
    "subdivision": "42",
    "timezone": "Europe/Moscow"
  },
  "geometry": {
    "type": "Point",
    "coordinates": [
      32.29413,
      59.99872
    ]
  }
}