{
  "type": "Feature",
  "properties": {
    "name": "Taytsy",
    "country": "RU",
    "subdivision": "42",
    "timezone": "Europe/Moscow"
  },
  "geometry": {
    "type": "Point",
    "coordinates": [
      30.11472,
      59.66444
    ]
  }
}