{
  "type": "Feature",
  "properties": {
    "name": "Tolmachevo",
    "country": "RU",
    "subdivision": "42",
    "timezone": "Europe/Moscow"
  },
  "geometry": {
    "type": "Point",
    "coordinates": [
      29.91091,
      58.85973
    ]
  }
}