{
  "type": "Feature",
  "properties": {
    "name": "Veshchevo",
    "country": "RU",
    "subdivision": "42",
    "timezone": "Europe/Moscow"
  },
  "geometry": {
    "type": "Point",
    "coordinates": [
      29.18305,
      60.73107
    ]
  }
}