{
  "type": "Feature",
  "properties": {
    "name": "Vinnitsy",
    "country": "RU",
    "subdivision": "42",
    "timezone": "Europe/Moscow"
  },
  "geometry": {
    "type": "Point",
    "coordinates": [
      34.77302,
      60.62867
    ]
  }
}