{
  "type": "Feature",
  "properties": {
    "name": "Voznesen’ye",
    "country": "RU",
    "subdivision": "42",
    "timezone": "Europe/Moscow"
  },
  "geometry": {
    "type": "Point",
    "coordinates": [
      35.47813,
      61.0106
    ]
  }
}