{
  "type": "Feature",
  "properties": {
    "name": "Vsevolozhsk",
    "country": "RU",
    "subdivision": "42",
    "timezone": "Europe/Moscow"
  },
  "geometry": {
    "type": "Point",
    "coordinates": [
      30.67314,
      60.01512
    ]
  }
}