{
  "type": "Feature",
  "properties": {
    "name": "Basotu",
    "country": "TZ",
    "subdivision": "27",
    "timezone": "Africa/Dar_es_Salaam"
  },
  "geometry": {
    "type": "Point",
    "coordinates": [
      35.08333,
      -4.36667
    ]
  }
}