{
  "type": "Feature",
  "properties": {
    "name": "Kirya",
    "country": "TZ",
    "subdivision": "27",
    "timezone": "Africa/Dar_es_Salaam"
  },
  "geometry": {
    "type": "Point",
    "coordinates": [
      37.48333,
      -3.91667
    ]
  }
}