{
  "type": "Feature",
  "properties": {
    "name": "Magugu",
    "country": "TZ",
    "subdivision": "27",
    "timezone": "Africa/Dar_es_Salaam"
  },
  "geometry": {
    "type": "Point",
    "coordinates": [
      35.76667,
      -4.01667
    ]
  }
}