{
  "type": "Feature",
  "properties": {
    "name": "Aracaju",
    "country": "BR",
    "subdivision": "28",
    "timezone": "America/Maceio"
  },
  "geometry": {
    "type": "Point",
    "coordinates": [
      -37.07167,
      -10.91111
    ]
  }
}