{
  "type": "Feature",
  "properties": {
    "name": "Areia Branca",
    "country": "BR",
    "subdivision": "28",
    "timezone": "America/Maceio"
  },
  "geometry": {
    "type": "Point",
    "coordinates": [
      -37.31528,
      -10.75778
    ]
  }
}