{
  "type": "Feature",
  "properties": {
    "name": "Cristinápolis",
    "country": "BR",
    "subdivision": "28",
    "timezone": "America/Maceio"
  },
  "geometry": {
    "type": "Point",
    "coordinates": [
      -37.75528,
      -11.47556
    ]
  }
}