{
  "type": "Feature",
  "properties": {
    "name": "Estância",
    "country": "BR",
    "subdivision": "28",
    "timezone": "America/Maceio"
  },
  "geometry": {
    "type": "Point",
    "coordinates": [
      -37.43833,
      -11.26833
    ]
  }
}