{
  "type": "Feature",
  "properties": {
    "name": "Japoatã",
    "country": "BR",
    "subdivision": "28",
    "timezone": "America/Maceio"
  },
  "geometry": {
    "type": "Point",
    "coordinates": [
      -36.80111,
      -10.34667
    ]
  }
}