{
  "type": "Feature",
  "properties": {
    "name": "Tobias Barreto",
    "country": "BR",
    "subdivision": "28",
    "timezone": "America/Maceio"
  },
  "geometry": {
    "type": "Point",
    "coordinates": [
      -37.99833,
      -11.18389
    ]
  }
}