{
  "type": "Feature",
  "properties": {
    "name": "Khanu Woralaksaburi",
    "country": "TH",
    "subdivision": "11",
    "timezone": "Asia/Bangkok"
  },
  "geometry": {
    "type": "Point",
    "coordinates": [
      99.86058,
      16.0617
    ]
  }
}