{
  "type": "Feature",
  "properties": {
    "name": "Diyadin",
    "country": "TR",
    "subdivision": "04",
    "timezone": "Europe/Istanbul"
  },
  "geometry": {
    "type": "Point",
    "coordinates": [
      43.67135,
      39.54056
    ]
  }
}