{
  "type": "Feature",
  "properties": {
    "name": "Geiro",
    "country": "TZ",
    "subdivision": "10",
    "timezone": "Africa/Dar_es_Salaam"
  },
  "geometry": {
    "type": "Point",
    "coordinates": [
      36.86667,
      -6.15
    ]
  }
}