{
  "type": "Feature",
  "properties": {
    "name": "Kidatu",
    "country": "TZ",
    "subdivision": "10",
    "timezone": "Africa/Dar_es_Salaam"
  },
  "geometry": {
    "type": "Point",
    "coordinates": [
      36.95722,
      -7.69916
    ]
  }
}