{
  "type": "Feature",
  "properties": {
    "name": "Lupiro",
    "country": "TZ",
    "subdivision": "10",
    "timezone": "Africa/Dar_es_Salaam"
  },
  "geometry": {
    "type": "Point",
    "coordinates": [
      36.66667,
      -8.38333
    ]
  }
}