{
  "type": "Feature",
  "properties": {
    "name": "Morogoro",
    "country": "TZ",
    "subdivision": "10",
    "timezone": "Africa/Dar_es_Salaam"
  },
  "geometry": {
    "type": "Point",
    "coordinates": [
      37.66122,
      -6.82102
    ]
  }
}