{
  "type": "Feature",
  "properties": {
    "name": "Abeokuta",
    "country": "NG",
    "subdivision": "16",
    "timezone": "Africa/Lagos"
  },
  "geometry": {
    "type": "Point",
    "coordinates": [
      3.34509,
      7.15571
    ]
  }
}