{
  "type": "Feature",
  "properties": {
    "name": "Ado-Odo",
    "country": "NG",
    "subdivision": "16",
    "timezone": "Africa/Lagos"
  },
  "geometry": {
    "type": "Point",
    "coordinates": [
      2.94176,
      6.59546
    ]
  }
}