{
  "type": "Feature",
  "properties": {
    "name": "Ijebu-Ife",
    "country": "NG",
    "subdivision": "16",
    "timezone": "Africa/Lagos"
  },
  "geometry": {
    "type": "Point",
    "coordinates": [
      4.03386,
      6.77837
    ]
  }
}