{
  "type": "Feature",
  "properties": {
    "name": "Keban",
    "country": "TR",
    "subdivision": "23",
    "timezone": "Europe/Istanbul"
  },
  "geometry": {
    "type": "Point",
    "coordinates": [
      38.73517,
      38.7938
    ]
  }
}