{
  "type": "Feature",
  "properties": {
    "name": "Sivrice",
    "country": "TR",
    "subdivision": "23",
    "timezone": "Europe/Istanbul"
  },
  "geometry": {
    "type": "Point",
    "coordinates": [
      39.30938,
      38.44223
    ]
  }
}