{
  "type": "Feature",
  "properties": {
    "name": "Diphu",
    "country": "IN",
    "subdivision": "03",
    "timezone": "Asia/Kolkata"
  },
  "geometry": {
    "type": "Point",
    "coordinates": [
      93.43116,
      25.84341
    ]
  }
}