{
  "type": "Feature",
  "properties": {
    "name": "Howli",
    "country": "IN",
    "subdivision": "03",
    "timezone": "Asia/Kolkata"
  },
  "geometry": {
    "type": "Point",
    "coordinates": [
      90.98004,
      26.42237
    ]
  }
}