{
  "type": "Feature",
  "properties": {
    "name": "NÄmrup",
    "country": "IN",
    "subdivision": "03",
    "timezone": "Asia/Kolkata"
  },
  "geometry": {
    "type": "Point",
    "coordinates": [
      95.31929,
      27.19395
    ]
  }
}