{
  "type": "Feature",
  "properties": {
    "name": "Palāsbāri",
    "country": "IN",
    "subdivision": "03",
    "timezone": "Asia/Kolkata"
  },
  "geometry": {
    "type": "Point",
    "coordinates": [
      91.53974,
      26.12388
    ]
  }
}