{
  "type": "Feature",
  "properties": {
    "name": "Soalkuchi",
    "country": "IN",
    "subdivision": "03",
    "timezone": "Asia/Kolkata"
  },
  "geometry": {
    "type": "Point",
    "coordinates": [
      91.57111,
      26.16806
    ]
  }
}