{
  "type": "Feature",
  "properties": {
    "name": "Aleksandrovo",
    "country": "RS",
    "subdivision": "VO",
    "timezone": "Europe/Belgrade"
  },
  "geometry": {
    "type": "Point",
    "coordinates": [
      20.59288,
      45.63755
    ]
  }
}