{
  "type": "Feature",
  "properties": {
    "name": "Bačka Topola",
    "country": "RS",
    "subdivision": "VO",
    "timezone": "Europe/Belgrade"
  },
  "geometry": {
    "type": "Point",
    "coordinates": [
      19.6318,
      45.81516
    ]
  }
}