{
  "type": "Feature",
  "properties": {
    "name": "Belegiš",
    "country": "RS",
    "subdivision": "VO",
    "timezone": "Europe/Belgrade"
  },
  "geometry": {
    "type": "Point",
    "coordinates": [
      20.33323,
      45.0192
    ]
  }
}