{
  "type": "Feature",
  "properties": {
    "name": "Bogojevo",
    "country": "RS",
    "subdivision": "VO",
    "timezone": "Europe/Belgrade"
  },
  "geometry": {
    "type": "Point",
    "coordinates": [
      19.13022,
      45.53015
    ]
  }
}