{
  "type": "Feature",
  "properties": {
    "name": "Bosut",
    "country": "RS",
    "subdivision": "VO",
    "timezone": "Europe/Belgrade"
  },
  "geometry": {
    "type": "Point",
    "coordinates": [
      19.36086,
      44.92977
    ]
  }
}