{
  "type": "Feature",
  "properties": {
    "name": "Dobrica",
    "country": "RS",
    "subdivision": "VO",
    "timezone": "Europe/Belgrade"
  },
  "geometry": {
    "type": "Point",
    "coordinates": [
      20.84995,
      45.21339
    ]
  }
}