{
  "type": "Feature",
  "properties": {
    "name": "Gakovo",
    "country": "RS",
    "subdivision": "VO",
    "timezone": "Europe/Belgrade"
  },
  "geometry": {
    "type": "Point",
    "coordinates": [
      19.06138,
      45.90078
    ]
  }
}