{
  "type": "Feature",
  "properties": {
    "name": "Inđija",
    "country": "RS",
    "subdivision": "VO",
    "timezone": "Europe/Belgrade"
  },
  "geometry": {
    "type": "Point",
    "coordinates": [
      20.08165,
      45.04816
    ]
  }
}