{
  "type": "Feature",
  "properties": {
    "name": "Iđoš",
    "country": "RS",
    "subdivision": "VO",
    "timezone": "Europe/Belgrade"
  },
  "geometry": {
    "type": "Point",
    "coordinates": [
      20.31791,
      45.82648
    ]
  }
}