{
  "type": "Feature",
  "properties": {
    "name": "Konak",
    "country": "RS",
    "subdivision": "VO",
    "timezone": "Europe/Belgrade"
  },
  "geometry": {
    "type": "Point",
    "coordinates": [
      20.91468,
      45.31575
    ]
  }
}