{
  "type": "Feature",
  "properties": {
    "name": "Kulpin",
    "country": "RS",
    "subdivision": "VO",
    "timezone": "Europe/Belgrade"
  },
  "geometry": {
    "type": "Point",
    "coordinates": [
      19.58814,
      45.4024
    ]
  }
}