{
  "type": "Feature",
  "properties": {
    "name": "Lazarevo",
    "country": "RS",
    "subdivision": "VO",
    "timezone": "Europe/Belgrade"
  },
  "geometry": {
    "type": "Point",
    "coordinates": [
      20.53999,
      45.38893
    ]
  }
}