{
  "type": "Feature",
  "properties": {
    "name": "Lokve",
    "country": "RS",
    "subdivision": "VO",
    "timezone": "Europe/Belgrade"
  },
  "geometry": {
    "type": "Point",
    "coordinates": [
      21.03073,
      45.15198
    ]
  }
}