{
  "type": "Feature",
  "properties": {
    "name": "Međa",
    "country": "RS",
    "subdivision": "VO",
    "timezone": "Europe/Belgrade"
  },
  "geometry": {
    "type": "Point",
    "coordinates": [
      20.80677,
      45.53815
    ]
  }
}