{
  "type": "Feature",
  "properties": {
    "name": "Petrovaradin",
    "country": "RS",
    "subdivision": "VO",
    "timezone": "Europe/Belgrade"
  },
  "geometry": {
    "type": "Point",
    "coordinates": [
      19.87944,
      45.24667
    ]
  }
}