{
  "type": "Feature",
  "properties": {
    "name": "Radojevo",
    "country": "RS",
    "subdivision": "VO",
    "timezone": "Europe/Belgrade"
  },
  "geometry": {
    "type": "Point",
    "coordinates": [
      20.78917,
      45.74617
    ]
  }
}