{
  "type": "Feature",
  "properties": {
    "name": "Šašinci",
    "country": "RS",
    "subdivision": "VO",
    "timezone": "Europe/Belgrade"
  },
  "geometry": {
    "type": "Point",
    "coordinates": [
      19.74151,
      44.96514
    ]
  }
}