{
  "type": "Feature",
  "properties": {
    "name": "Seleuš",
    "country": "RS",
    "subdivision": "VO",
    "timezone": "Europe/Belgrade"
  },
  "geometry": {
    "type": "Point",
    "coordinates": [
      20.91461,
      45.1277
    ]
  }
}