{
  "type": "Feature",
  "properties": {
    "name": "Sombor",
    "country": "RS",
    "subdivision": "VO",
    "timezone": "Europe/Belgrade"
  },
  "geometry": {
    "type": "Point",
    "coordinates": [
      19.11222,
      45.77417
    ]
  }
}