{
  "type": "Feature",
  "properties": {
    "name": "Sremska Mitrovica",
    "country": "RS",
    "subdivision": "VO",
    "timezone": "Europe/Belgrade"
  },
  "geometry": {
    "type": "Point",
    "coordinates": [
      19.61222,
      44.97639
    ]
  }
}