{
  "type": "Feature",
  "properties": {
    "name": "Uljma",
    "country": "RS",
    "subdivision": "VO",
    "timezone": "Europe/Belgrade"
  },
  "geometry": {
    "type": "Point",
    "coordinates": [
      21.15393,
      45.04213
    ]
  }
}