{
  "type": "Feature",
  "properties": {
    "name": "Uzdin",
    "country": "RS",
    "subdivision": "VO",
    "timezone": "Europe/Belgrade"
  },
  "geometry": {
    "type": "Point",
    "coordinates": [
      20.62342,
      45.20512
    ]
  }
}