{
  "type": "Feature",
  "properties": {
    "name": "Veliko Središte",
    "country": "RS",
    "subdivision": "VO",
    "timezone": "Europe/Belgrade"
  },
  "geometry": {
    "type": "Point",
    "coordinates": [
      21.40353,
      45.17919
    ]
  }
}