{
  "type": "Feature",
  "properties": {
    "name": "Zrenjanin",
    "country": "RS",
    "subdivision": "VO",
    "timezone": "Europe/Belgrade"
  },
  "geometry": {
    "type": "Point",
    "coordinates": [
      20.38194,
      45.38361
    ]
  }
}