{
  "type": "Feature",
  "properties": {
    "name": "Ðurđevo",
    "country": "RS",
    "subdivision": "VO",
    "timezone": "Europe/Belgrade"
  },
  "geometry": {
    "type": "Point",
    "coordinates": [
      20.06532,
      45.32591
    ]
  }
}