{
  "type": "Feature",
  "properties": {
    "name": "Banie",
    "country": "PL",
    "subdivision": "87",
    "timezone": "Europe/Warsaw"
  },
  "geometry": {
    "type": "Point",
    "coordinates": [
      14.66228,
      53.10031
    ]
  }
}