{
  "type": "Feature",
  "properties": {
    "name": "Barwice",
    "country": "PL",
    "subdivision": "87",
    "timezone": "Europe/Warsaw"
  },
  "geometry": {
    "type": "Point",
    "coordinates": [
      16.3553,
      53.7449
    ]
  }
}