{
  "type": "Feature",
  "properties": {
    "name": "Biały Bór",
    "country": "PL",
    "subdivision": "87",
    "timezone": "Europe/Warsaw"
  },
  "geometry": {
    "type": "Point",
    "coordinates": [
      16.83543,
      53.8967
    ]
  }
}