{
  "type": "Feature",
  "properties": {
    "name": "Bobolice",
    "country": "PL",
    "subdivision": "87",
    "timezone": "Europe/Warsaw"
  },
  "geometry": {
    "type": "Point",
    "coordinates": [
      16.58893,
      53.95508
    ]
  }
}