{
  "type": "Feature",
  "properties": {
    "name": "Dobrzany",
    "country": "PL",
    "subdivision": "87",
    "timezone": "Europe/Warsaw"
  },
  "geometry": {
    "type": "Point",
    "coordinates": [
      15.42886,
      53.35914
    ]
  }
}