{
  "type": "Feature",
  "properties": {
    "name": "Gryfino",
    "country": "PL",
    "subdivision": "87",
    "timezone": "Europe/Warsaw"
  },
  "geometry": {
    "type": "Point",
    "coordinates": [
      14.48831,
      53.25243
    ]
  }
}