{
  "type": "Feature",
  "properties": {
    "name": "Mrzeżyno",
    "country": "PL",
    "subdivision": "87",
    "timezone": "Europe/Warsaw"
  },
  "geometry": {
    "type": "Point",
    "coordinates": [
      15.29142,
      54.14384
    ]
  }
}