{
  "type": "Feature",
  "properties": {
    "name": "Nowogard",
    "country": "PL",
    "subdivision": "87",
    "timezone": "Europe/Warsaw"
  },
  "geometry": {
    "type": "Point",
    "coordinates": [
      15.1163,
      53.67437
    ]
  }
}