{
  "type": "Feature",
  "properties": {
    "name": "Stepnica",
    "country": "PL",
    "subdivision": "87",
    "timezone": "Europe/Warsaw"
  },
  "geometry": {
    "type": "Point",
    "coordinates": [
      14.62555,
      53.65187
    ]
  }
}