{
  "type": "Feature",
  "properties": {
    "name": "Szczecinek",
    "country": "PL",
    "subdivision": "87",
    "timezone": "Europe/Warsaw"
  },
  "geometry": {
    "type": "Point",
    "coordinates": [
      16.69937,
      53.70791
    ]
  }
}