{
  "type": "Feature",
  "properties": {
    "name": "Widuchowa",
    "country": "PL",
    "subdivision": "87",
    "timezone": "Europe/Warsaw"
  },
  "geometry": {
    "type": "Point",
    "coordinates": [
      14.39074,
      53.12693
    ]
  }
}