{
  "type": "Feature",
  "properties": {
    "name": "Łubowo",
    "country": "PL",
    "subdivision": "87",
    "timezone": "Europe/Warsaw"
  },
  "geometry": {
    "type": "Point",
    "coordinates": [
      16.39177,
      53.58634
    ]
  }
}