{
  "type": "Feature",
  "properties": {
    "name": "Apastepeque",
    "country": "SV",
    "subdivision": "12",
    "timezone": "America/El_Salvador"
  },
  "geometry": {
    "type": "Point",
    "coordinates": [
      -88.78333,
      13.66667
    ]
  }
}