{
  "type": "Feature",
  "properties": {
    "name": "Awantipur",
    "country": "IN",
    "subdivision": "12",
    "timezone": "Asia/Kolkata"
  },
  "geometry": {
    "type": "Point",
    "coordinates": [
      75.01515,
      33.91978
    ]
  }
}