{
  "type": "Feature",
  "properties": {
    "name": "Bāramūla",
    "country": "IN",
    "subdivision": "12",
    "timezone": "Asia/Kolkata"
  },
  "geometry": {
    "type": "Point",
    "coordinates": [
      74.34285,
      34.209
    ]
  }
}