{
  "type": "Feature",
  "properties": {
    "name": "HÄjan",
    "country": "IN",
    "subdivision": "12",
    "timezone": "Asia/Kolkata"
  },
  "geometry": {
    "type": "Point",
    "coordinates": [
      74.61681,
      34.29895
    ]
  }
}