{
  "type": "Feature",
  "properties": {
    "name": "KupwÄra",
    "country": "IN",
    "subdivision": "12",
    "timezone": "Asia/Kolkata"
  },
  "geometry": {
    "type": "Point",
    "coordinates": [
      74.26417,
      34.03056
    ]
  }
}