{
  "type": "Feature",
  "properties": {
    "name": "Uri",
    "country": "IN",
    "subdivision": "12",
    "timezone": "Asia/Kolkata"
  },
  "geometry": {
    "type": "Point",
    "coordinates": [
      74.05088,
      34.08064
    ]
  }
}