{
  "type": "Feature",
  "properties": {
    "name": "Jorethang",
    "country": "IN",
    "subdivision": "29",
    "timezone": "Asia/Kolkata"
  },
  "geometry": {
    "type": "Point",
    "coordinates": [
      88.32332,
      27.10696
    ]
  }
}