{
  "type": "Feature",
  "properties": {
    "name": "Kabanga",
    "country": "TZ",
    "subdivision": "19",
    "timezone": "Africa/Dar_es_Salaam"
  },
  "geometry": {
    "type": "Point",
    "coordinates": [
      30.46778,
      -2.63861
    ]
  }
}