{
  "type": "Feature",
  "properties": {
    "name": "Nsunga",
    "country": "TZ",
    "subdivision": "19",
    "timezone": "Africa/Dar_es_Salaam"
  },
  "geometry": {
    "type": "Point",
    "coordinates": [
      31.39472,
      -1.14389
    ]
  }
}