{
  "type": "Feature",
  "properties": {
    "name": "Ino",
    "country": "JP",
    "subdivision": "20",
    "timezone": "Asia/Tokyo"
  },
  "geometry": {
    "type": "Point",
    "coordinates": [
      133.43333,
      33.55
    ]
  }
}