{
  "type": "Feature",
  "properties": {
    "name": "Vezirhan",
    "country": "TR",
    "subdivision": "11",
    "timezone": "Europe/Istanbul"
  },
  "geometry": {
    "type": "Point",
    "coordinates": [
      30.02,
      40.24472
    ]
  }
}