{
  "type": "Feature",
  "properties": {
    "name": "Rongai",
    "country": "KE",
    "subdivision": "39",
    "timezone": "Africa/Nairobi"
  },
  "geometry": {
    "type": "Point",
    "coordinates": [
      35.86313,
      -0.17344
    ]
  }
}