{
  "type": "Feature",
  "properties": {
    "name": "Ardglass",
    "country": "GB",
    "subdivision": "NIR",
    "timezone": "Europe/London"
  },
  "geometry": {
    "type": "Point",
    "coordinates": [
      -5.60981,
      54.26312
    ]
  }
}