{
  "type": "Feature",
  "properties": {
    "name": "Ballyclare",
    "country": "GB",
    "subdivision": "NIR",
    "timezone": "Europe/London"
  },
  "geometry": {
    "type": "Point",
    "coordinates": [
      -5.99944,
      54.75089
    ]
  }
}