{
  "type": "Feature",
  "properties": {
    "name": "Broughshane",
    "country": "GB",
    "subdivision": "NIR",
    "timezone": "Europe/London"
  },
  "geometry": {
    "type": "Point",
    "coordinates": [
      -6.20899,
      54.8926
    ]
  }
}