{
  "type": "Feature",
  "properties": {
    "name": "Bushmills",
    "country": "GB",
    "subdivision": "NIR",
    "timezone": "Europe/London"
  },
  "geometry": {
    "type": "Point",
    "coordinates": [
      -6.51918,
      55.20493
    ]
  }
}