{
  "type": "Feature",
  "properties": {
    "name": "Carnmoney",
    "country": "GB",
    "subdivision": "NIR",
    "timezone": "Europe/London"
  },
  "geometry": {
    "type": "Point",
    "coordinates": [
      -5.95,
      54.68333
    ]
  }
}