{
  "type": "Feature",
  "properties": {
    "name": "Carryduff",
    "country": "GB",
    "subdivision": "NIR",
    "timezone": "Europe/London"
  },
  "geometry": {
    "type": "Point",
    "coordinates": [
      -5.88713,
      54.51799
    ]
  }
}