{
  "type": "Feature",
  "properties": {
    "name": "Dundrum",
    "country": "GB",
    "subdivision": "NIR",
    "timezone": "Europe/London"
  },
  "geometry": {
    "type": "Point",
    "coordinates": [
      -5.84455,
      54.2575
    ]
  }
}