{
  "type": "Feature",
  "properties": {
    "name": "Gilford",
    "country": "GB",
    "subdivision": "NIR",
    "timezone": "Europe/London"
  },
  "geometry": {
    "type": "Point",
    "coordinates": [
      -6.36126,
      54.37256
    ]
  }
}