{
  "type": "Feature",
  "properties": {
    "name": "Hillsborough",
    "country": "GB",
    "subdivision": "NIR",
    "timezone": "Europe/London"
  },
  "geometry": {
    "type": "Point",
    "coordinates": [
      -6.07664,
      54.46345
    ]
  }
}