{
  "type": "Feature",
  "properties": {
    "name": "Magherafelt",
    "country": "GB",
    "subdivision": "NIR",
    "timezone": "Europe/London"
  },
  "geometry": {
    "type": "Point",
    "coordinates": [
      -6.60656,
      54.75356
    ]
  }
}