{
  "type": "Feature",
  "properties": {
    "name": "Kefar Shemaryahu",
    "country": "IL",
    "subdivision": "05",
    "timezone": "Asia/Jerusalem"
  },
  "geometry": {
    "type": "Point",
    "coordinates": [
      34.82082,
      32.18529
    ]
  }
}