{
  "type": "Feature",
  "properties": {
    "name": "Chalán",
    "country": "CO",
    "subdivision": "27",
    "timezone": "America/Bogota"
  },
  "geometry": {
    "type": "Point",
    "coordinates": [
      -75.31128,
      9.54765
    ]
  }
}