{
  "type": "Feature",
  "properties": {
    "name": "San Juan de Betulia",
    "country": "CO",
    "subdivision": "27",
    "timezone": "America/Bogota"
  },
  "geometry": {
    "type": "Point",
    "coordinates": [
      -75.24103,
      9.27345
    ]
  }
}