{
  "type": "Feature",
  "properties": {
    "name": "Sincelejo",
    "country": "CO",
    "subdivision": "27",
    "timezone": "America/Bogota"
  },
  "geometry": {
    "type": "Point",
    "coordinates": [
      -75.39778,
      9.30472
    ]
  }
}