{
  "type": "Feature",
  "properties": {
    "name": "Makary",
    "country": "CM",
    "subdivision": "12",
    "timezone": "Africa/Douala"
  },
  "geometry": {
    "type": "Point",
    "coordinates": [
      14.45483,
      12.57535
    ]
  }
}