{
  "type": "Feature",
  "properties": {
    "name": "Maroua",
    "country": "CM",
    "subdivision": "12",
    "timezone": "Africa/Douala"
  },
  "geometry": {
    "type": "Point",
    "coordinates": [
      14.31593,
      10.59095
    ]
  }
}