{
  "type": "Feature",
  "properties": {
    "name": "Mora",
    "country": "CM",
    "subdivision": "12",
    "timezone": "Africa/Douala"
  },
  "geometry": {
    "type": "Point",
    "coordinates": [
      14.14011,
      11.04611
    ]
  }
}