{
  "type": "Feature",
  "properties": {
    "name": "Barberton",
    "country": "US",
    "subdivision": "WA",
    "timezone": "America/Los_Angeles"
  },
  "geometry": {
    "type": "Point",
    "coordinates": [
      -122.59899,
      45.69317
    ]
  }
}