{
  "type": "Feature",
  "properties": {
    "name": "Bellingham",
    "country": "US",
    "subdivision": "WA",
    "timezone": "America/Los_Angeles"
  },
  "geometry": {
    "type": "Point",
    "coordinates": [
      -122.48822,
      48.75955
    ]
  }
}