{
  "type": "Feature",
  "properties": {
    "name": "Bellevue",
    "country": "US",
    "subdivision": "WA",
    "timezone": "America/Los_Angeles"
  },
  "geometry": {
    "type": "Point",
    "coordinates": [
      -122.20068,
      47.61038
    ]
  }
}