{
  "type": "Feature",
  "properties": {
    "name": "Bothell East",
    "country": "US",
    "subdivision": "WA",
    "timezone": "America/Los_Angeles"
  },
  "geometry": {
    "type": "Point",
    "coordinates": [
      -122.18427,
      47.80631
    ]
  }
}