{
  "type": "Feature",
  "properties": {
    "name": "Browns Point",
    "country": "US",
    "subdivision": "WA",
    "timezone": "America/Los_Angeles"
  },
  "geometry": {
    "type": "Point",
    "coordinates": [
      -122.44124,
      47.30038
    ]
  }
}