{
  "type": "Feature",
  "properties": {
    "name": "Carnation",
    "country": "US",
    "subdivision": "WA",
    "timezone": "America/Los_Angeles"
  },
  "geometry": {
    "type": "Point",
    "coordinates": [
      -121.91401,
      47.64788
    ]
  }
}