{
  "type": "Feature",
  "properties": {
    "name": "City of Sammamish",
    "country": "US",
    "subdivision": "WA",
    "timezone": "America/Los_Angeles"
  },
  "geometry": {
    "type": "Point",
    "coordinates": [
      -122.03768,
      47.60444
    ]
  }
}