{
  "type": "Feature",
  "properties": {
    "name": "Clyde Hill",
    "country": "US",
    "subdivision": "WA",
    "timezone": "America/Los_Angeles"
  },
  "geometry": {
    "type": "Point",
    "coordinates": [
      -122.2179,
      47.63177
    ]
  }
}