{
  "type": "Feature",
  "properties": {
    "name": "Colville",
    "country": "US",
    "subdivision": "WA",
    "timezone": "America/Los_Angeles"
  },
  "geometry": {
    "type": "Point",
    "coordinates": [
      -117.90554,
      48.54657
    ]
  }
}