{
  "type": "Feature",
  "properties": {
    "name": "Des Moines",
    "country": "US",
    "subdivision": "WA",
    "timezone": "America/Los_Angeles"
  },
  "geometry": {
    "type": "Point",
    "coordinates": [
      -122.32429,
      47.40177
    ]
  }
}