{
  "type": "Feature",
  "properties": {
    "name": "Eastgate",
    "country": "US",
    "subdivision": "WA",
    "timezone": "America/Los_Angeles"
  },
  "geometry": {
    "type": "Point",
    "coordinates": [
      -122.14578,
      47.57266
    ]
  }
}