{
  "type": "Feature",
  "properties": {
    "name": "East Hill-Meridian",
    "country": "US",
    "subdivision": "WA",
    "timezone": "America/Los_Angeles"
  },
  "geometry": {
    "type": "Point",
    "coordinates": [
      -122.17369,
      47.41052
    ]
  }
}