{
  "type": "Feature",
  "properties": {
    "name": "Forks",
    "country": "US",
    "subdivision": "WA",
    "timezone": "America/Los_Angeles"
  },
  "geometry": {
    "type": "Point",
    "coordinates": [
      -124.38549,
      47.95036
    ]
  }
}