{
  "type": "Feature",
  "properties": {
    "name": "Gold Bar",
    "country": "US",
    "subdivision": "WA",
    "timezone": "America/Los_Angeles"
  },
  "geometry": {
    "type": "Point",
    "coordinates": [
      -121.69706,
      47.85677
    ]
  }
}