{
  "type": "Feature",
  "properties": {
    "name": "Graham",
    "country": "US",
    "subdivision": "WA",
    "timezone": "America/Los_Angeles"
  },
  "geometry": {
    "type": "Point",
    "coordinates": [
      -122.29428,
      47.05288
    ]
  }
}