{
  "type": "Feature",
  "properties": {
    "name": "Kent",
    "country": "US",
    "subdivision": "WA",
    "timezone": "America/Los_Angeles"
  },
  "geometry": {
    "type": "Point",
    "coordinates": [
      -122.23484,
      47.38093
    ]
  }
}