{
  "type": "Feature",
  "properties": {
    "name": "La Center",
    "country": "US",
    "subdivision": "WA",
    "timezone": "America/Los_Angeles"
  },
  "geometry": {
    "type": "Point",
    "coordinates": [
      -122.67038,
      45.86234
    ]
  }
}