{
  "type": "Feature",
  "properties": {
    "name": "Lake Stickney",
    "country": "US",
    "subdivision": "WA",
    "timezone": "America/Los_Angeles"
  },
  "geometry": {
    "type": "Point",
    "coordinates": [
      -122.26214,
      47.87655
    ]
  }
}