{
  "type": "Feature",
  "properties": {
    "name": "Maltby",
    "country": "US",
    "subdivision": "WA",
    "timezone": "America/Los_Angeles"
  },
  "geometry": {
    "type": "Point",
    "coordinates": [
      -122.11318,
      47.8051
    ]
  }
}