{
  "type": "Feature",
  "properties": {
    "name": "Manson",
    "country": "US",
    "subdivision": "WA",
    "timezone": "America/Los_Angeles"
  },
  "geometry": {
    "type": "Point",
    "coordinates": [
      -120.15841,
      47.88486
    ]
  }
}