{
  "type": "Feature",
  "properties": {
    "name": "Martha Lake",
    "country": "US",
    "subdivision": "WA",
    "timezone": "America/Los_Angeles"
  },
  "geometry": {
    "type": "Point",
    "coordinates": [
      -122.2393,
      47.85093
    ]
  }
}