{
  "type": "Feature",
  "properties": {
    "name": "McChord Air Force Base",
    "country": "US",
    "subdivision": "WA",
    "timezone": "America/Los_Angeles"
  },
  "geometry": {
    "type": "Point",
    "coordinates": [
      -122.49157,
      47.13397
    ]
  }
}