{
  "type": "Feature",
  "properties": {
    "name": "Milton",
    "country": "US",
    "subdivision": "WA",
    "timezone": "America/Los_Angeles"
  },
  "geometry": {
    "type": "Point",
    "coordinates": [
      -122.3129,
      47.24816
    ]
  }
}