{
  "type": "Feature",
  "properties": {
    "name": "Monroe North",
    "country": "US",
    "subdivision": "WA",
    "timezone": "America/Los_Angeles"
  },
  "geometry": {
    "type": "Point",
    "coordinates": [
      -121.98729,
      47.88225
    ]
  }
}