{
  "type": "Feature",
  "properties": {
    "name": "North Fort Lewis",
    "country": "US",
    "subdivision": "WA",
    "timezone": "America/Los_Angeles"
  },
  "geometry": {
    "type": "Point",
    "coordinates": [
      -122.59452,
      47.12131
    ]
  }
}