{
  "type": "Feature",
  "properties": {
    "name": "North Creek",
    "country": "US",
    "subdivision": "WA",
    "timezone": "America/Los_Angeles"
  },
  "geometry": {
    "type": "Point",
    "coordinates": [
      -122.17624,
      47.81954
    ]
  }
}