{
  "type": "Feature",
  "properties": {
    "name": "Omak",
    "country": "US",
    "subdivision": "WA",
    "timezone": "America/Los_Angeles"
  },
  "geometry": {
    "type": "Point",
    "coordinates": [
      -119.52755,
      48.41099
    ]
  }
}