{
  "type": "Feature",
  "properties": {
    "name": "Parkwood",
    "country": "US",
    "subdivision": "WA",
    "timezone": "America/Los_Angeles"
  },
  "geometry": {
    "type": "Point",
    "coordinates": [
      -122.61014,
      47.53315
    ]
  }
}