{
  "type": "Feature",
  "properties": {
    "name": "Picnic Point",
    "country": "US",
    "subdivision": "WA",
    "timezone": "America/Los_Angeles"
  },
  "geometry": {
    "type": "Point",
    "coordinates": [
      -122.3284,
      47.88111
    ]
  }
}