{
  "type": "Feature",
  "properties": {
    "name": "Pullman",
    "country": "US",
    "subdivision": "WA",
    "timezone": "America/Los_Angeles"
  },
  "geometry": {
    "type": "Point",
    "coordinates": [
      -117.17962,
      46.73127
    ]
  }
}