{
  "type": "Feature",
  "properties": {
    "name": "Rocky Point",
    "country": "US",
    "subdivision": "WA",
    "timezone": "America/Los_Angeles"
  },
  "geometry": {
    "type": "Point",
    "coordinates": [
      -122.66848,
      47.59287
    ]
  }
}