{
  "type": "Feature",
  "properties": {
    "name": "Silverdale",
    "country": "US",
    "subdivision": "WA",
    "timezone": "America/Los_Angeles"
  },
  "geometry": {
    "type": "Point",
    "coordinates": [
      -122.69487,
      47.64454
    ]
  }
}