{
  "type": "Feature",
  "properties": {
    "name": "South Wenatchee",
    "country": "US",
    "subdivision": "WA",
    "timezone": "America/Los_Angeles"
  },
  "geometry": {
    "type": "Point",
    "coordinates": [
      -120.28958,
      47.39012
    ]
  }
}