{
  "type": "Feature",
  "properties": {
    "name": "South Bend",
    "country": "US",
    "subdivision": "WA",
    "timezone": "America/Los_Angeles"
  },
  "geometry": {
    "type": "Point",
    "coordinates": [
      -123.80461,
      46.66315
    ]
  }
}