{
  "type": "Feature",
  "properties": {
    "name": "Spanaway",
    "country": "US",
    "subdivision": "WA",
    "timezone": "America/Los_Angeles"
  },
  "geometry": {
    "type": "Point",
    "coordinates": [
      -122.43457,
      47.10399
    ]
  }
}