{
  "type": "Feature",
  "properties": {
    "name": "Sultan",
    "country": "US",
    "subdivision": "WA",
    "timezone": "America/Los_Angeles"
  },
  "geometry": {
    "type": "Point",
    "coordinates": [
      -121.81651,
      47.8626
    ]
  }
}