{
  "type": "Feature",
  "properties": {
    "name": "Sunnyside",
    "country": "US",
    "subdivision": "WA",
    "timezone": "America/Los_Angeles"
  },
  "geometry": {
    "type": "Point",
    "coordinates": [
      -120.00865,
      46.32374
    ]
  }
}