{
  "type": "Feature",
  "properties": {
    "name": "Tacoma",
    "country": "US",
    "subdivision": "WA",
    "timezone": "America/Los_Angeles"
  },
  "geometry": {
    "type": "Point",
    "coordinates": [
      -122.44429,
      47.25288
    ]
  }
}