{
  "type": "Feature",
  "properties": {
    "name": "Tanglewilde-Thompson Place",
    "country": "US",
    "subdivision": "WA",
    "timezone": "America/Los_Angeles"
  },
  "geometry": {
    "type": "Point",
    "coordinates": [
      -122.78081,
      47.05116
    ]
  }
}