{
  "type": "Feature",
  "properties": {
    "name": "Union Hill-Novelty Hill",
    "country": "US",
    "subdivision": "WA",
    "timezone": "America/Los_Angeles"
  },
  "geometry": {
    "type": "Point",
    "coordinates": [
      -122.02833,
      47.67887
    ]
  }
}