{
  "type": "Feature",
  "properties": {
    "name": "Venersborg",
    "country": "US",
    "subdivision": "WA",
    "timezone": "America/Los_Angeles"
  },
  "geometry": {
    "type": "Point",
    "coordinates": [
      -122.42454,
      45.77373
    ]
  }
}