{
  "type": "Feature",
  "properties": {
    "name": "Waterville",
    "country": "US",
    "subdivision": "WA",
    "timezone": "America/Los_Angeles"
  },
  "geometry": {
    "type": "Point",
    "coordinates": [
      -120.07118,
      47.64708
    ]
  }
}