{
  "type": "Feature",
  "properties": {
    "name": "West Lake Stevens",
    "country": "US",
    "subdivision": "WA",
    "timezone": "America/Los_Angeles"
  },
  "geometry": {
    "type": "Point",
    "coordinates": [
      -122.1018,
      47.99343
    ]
  }
}