{
  "type": "Feature",
  "properties": {
    "name": "West Pasco",
    "country": "US",
    "subdivision": "WA",
    "timezone": "America/Los_Angeles"
  },
  "geometry": {
    "type": "Point",
    "coordinates": [
      -119.18279,
      46.24541
    ]
  }
}