{
  "type": "Feature",
  "properties": {
    "name": "Yacolt",
    "country": "US",
    "subdivision": "WA",
    "timezone": "America/Los_Angeles"
  },
  "geometry": {
    "type": "Point",
    "coordinates": [
      -122.40621,
      45.86595
    ]
  }
}