{
  "type": "Feature",
  "properties": {
    "name": "Yakima",
    "country": "US",
    "subdivision": "WA",
    "timezone": "America/Los_Angeles"
  },
  "geometry": {
    "type": "Point",
    "coordinates": [
      -120.5059,
      46.60207
    ]
  }
}