{
  "type": "Feature",
  "properties": {
    "name": "Apia",
    "country": "WS",
    "subdivision": "10",
    "timezone": "Pacific/Apia"
  },
  "geometry": {
    "type": "Point",
    "coordinates": [
      -171.76666,
      -13.83333
    ]
  }
}