{
  "type": "Feature",
  "properties": {
    "name": "Aurisina",
    "country": "IT",
    "subdivision": "06",
    "timezone": "Europe/Rome"
  },
  "geometry": {
    "type": "Point",
    "coordinates": [
      13.67345,
      45.74968
    ]
  }
}