{
  "type": "Feature",
  "properties": {
    "name": "Basiliano-Vissandone",
    "country": "IT",
    "subdivision": "06",
    "timezone": "Europe/Rome"
  },
  "geometry": {
    "type": "Point",
    "coordinates": [
      13.09306,
      46.02278
    ]
  }
}