{
  "type": "Feature",
  "properties": {
    "name": "Buttrio",
    "country": "IT",
    "subdivision": "06",
    "timezone": "Europe/Rome"
  },
  "geometry": {
    "type": "Point",
    "coordinates": [
      13.33354,
      46.01098
    ]
  }
}