{
  "type": "Feature",
  "properties": {
    "name": "Capriva del Friuli",
    "country": "IT",
    "subdivision": "06",
    "timezone": "Europe/Rome"
  },
  "geometry": {
    "type": "Point",
    "coordinates": [
      13.51422,
      45.94093
    ]
  }
}