{
  "type": "Feature",
  "properties": {
    "name": "Cassacco",
    "country": "IT",
    "subdivision": "06",
    "timezone": "Europe/Rome"
  },
  "geometry": {
    "type": "Point",
    "coordinates": [
      13.19236,
      46.17345
    ]
  }
}