{
  "type": "Feature",
  "properties": {
    "name": "Cavasso Nuovo",
    "country": "IT",
    "subdivision": "06",
    "timezone": "Europe/Rome"
  },
  "geometry": {
    "type": "Point",
    "coordinates": [
      12.77193,
      46.19441
    ]
  }
}