{
  "type": "Feature",
  "properties": {
    "name": "Gradisca d'Isonzo",
    "country": "IT",
    "subdivision": "06",
    "timezone": "Europe/Rome"
  },
  "geometry": {
    "type": "Point",
    "coordinates": [
      13.50167,
      45.8925
    ]
  }
}