{
  "type": "Feature",
  "properties": {
    "name": "Marano Lagunare",
    "country": "IT",
    "subdivision": "06",
    "timezone": "Europe/Rome"
  },
  "geometry": {
    "type": "Point",
    "coordinates": [
      13.16733,
      45.76353
    ]
  }
}