{
  "type": "Feature",
  "properties": {
    "name": "Muzzana del Turgnano",
    "country": "IT",
    "subdivision": "06",
    "timezone": "Europe/Rome"
  },
  "geometry": {
    "type": "Point",
    "coordinates": [
      13.12751,
      45.81799
    ]
  }
}