{
  "type": "Feature",
  "properties": {
    "name": "Palmanova",
    "country": "IT",
    "subdivision": "06",
    "timezone": "Europe/Rome"
  },
  "geometry": {
    "type": "Point",
    "coordinates": [
      13.30998,
      45.9054
    ]
  }
}