{
  "type": "Feature",
  "properties": {
    "name": "Paluzza",
    "country": "IT",
    "subdivision": "06",
    "timezone": "Europe/Rome"
  },
  "geometry": {
    "type": "Point",
    "coordinates": [
      13.01586,
      46.53202
    ]
  }
}