{
  "type": "Feature",
  "properties": {
    "name": "Percoto",
    "country": "IT",
    "subdivision": "06",
    "timezone": "Europe/Rome"
  },
  "geometry": {
    "type": "Point",
    "coordinates": [
      13.32304,
      45.97471
    ]
  }
}