{
  "type": "Feature",
  "properties": {
    "name": "Pontebba",
    "country": "IT",
    "subdivision": "06",
    "timezone": "Europe/Rome"
  },
  "geometry": {
    "type": "Point",
    "coordinates": [
      13.30622,
      46.5054
    ]
  }
}