{
  "type": "Feature",
  "properties": {
    "name": "Pordenone",
    "country": "IT",
    "subdivision": "06",
    "timezone": "Europe/Rome"
  },
  "geometry": {
    "type": "Point",
    "coordinates": [
      12.66051,
      45.95689
    ]
  }
}