{
  "type": "Feature",
  "properties": {
    "name": "Pozzuolo del Friuli",
    "country": "IT",
    "subdivision": "06",
    "timezone": "Europe/Rome"
  },
  "geometry": {
    "type": "Point",
    "coordinates": [
      13.19724,
      45.98517
    ]
  }
}