{
  "type": "Feature",
  "properties": {
    "name": "Prato Carnico",
    "country": "IT",
    "subdivision": "06",
    "timezone": "Europe/Rome"
  },
  "geometry": {
    "type": "Point",
    "coordinates": [
      12.80886,
      46.52049
    ]
  }
}