{
  "type": "Feature",
  "properties": {
    "name": "Prosecco-Contovello",
    "country": "IT",
    "subdivision": "06",
    "timezone": "Europe/Rome"
  },
  "geometry": {
    "type": "Point",
    "coordinates": [
      13.73376,
      45.70807
    ]
  }
}