{
  "type": "Feature",
  "properties": {
    "name": "Reana del Rojale",
    "country": "IT",
    "subdivision": "06",
    "timezone": "Europe/Rome"
  },
  "geometry": {
    "type": "Point",
    "coordinates": [
      13.24653,
      46.14322
    ]
  }
}