{
  "type": "Feature",
  "properties": {
    "name": "Rodeano",
    "country": "IT",
    "subdivision": "06",
    "timezone": "Europe/Rome"
  },
  "geometry": {
    "type": "Point",
    "coordinates": [
      13.0111,
      46.11085
    ]
  }
}