{
  "type": "Feature",
  "properties": {
    "name": "Ronchis",
    "country": "IT",
    "subdivision": "06",
    "timezone": "Europe/Rome"
  },
  "geometry": {
    "type": "Point",
    "coordinates": [
      12.99545,
      45.80792
    ]
  }
}