{
  "type": "Feature",
  "properties": {
    "name": "Sagrado",
    "country": "IT",
    "subdivision": "06",
    "timezone": "Europe/Rome"
  },
  "geometry": {
    "type": "Point",
    "coordinates": [
      13.48418,
      45.87393
    ]
  }
}