{
  "type": "Feature",
  "properties": {
    "name": "Santa Croce",
    "country": "IT",
    "subdivision": "06",
    "timezone": "Europe/Rome"
  },
  "geometry": {
    "type": "Point",
    "coordinates": [
      13.69278,
      45.73472
    ]
  }
}