{
  "type": "Feature",
  "properties": {
    "name": "Sedegliano",
    "country": "IT",
    "subdivision": "06",
    "timezone": "Europe/Rome"
  },
  "geometry": {
    "type": "Point",
    "coordinates": [
      12.97734,
      46.01396
    ]
  }
}