{
  "type": "Feature",
  "properties": {
    "name": "Tarvisio",
    "country": "IT",
    "subdivision": "06",
    "timezone": "Europe/Rome"
  },
  "geometry": {
    "type": "Point",
    "coordinates": [
      13.58689,
      46.50567
    ]
  }
}