{
  "type": "Feature",
  "properties": {
    "name": "Villesse",
    "country": "IT",
    "subdivision": "06",
    "timezone": "Europe/Rome"
  },
  "geometry": {
    "type": "Point",
    "coordinates": [
      13.4438,
      45.86526
    ]
  }
}