{
  "type": "Feature",
  "properties": {
    "name": "Chadiza",
    "country": "ZM",
    "subdivision": "03",
    "timezone": "Africa/Lusaka"
  },
  "geometry": {
    "type": "Point",
    "coordinates": [
      32.43917,
      -14.06779
    ]
  }
}