{
  "type": "Feature",
  "properties": {
    "name": "Abnūb",
    "country": "EG",
    "subdivision": "17",
    "timezone": "Africa/Cairo"
  },
  "geometry": {
    "type": "Point",
    "coordinates": [
      31.15232,
      27.26881
    ]
  }
}