{
  "type": "Feature",
  "properties": {
    "name": "Abū Tīj",
    "country": "EG",
    "subdivision": "17",
    "timezone": "Africa/Cairo"
  },
  "geometry": {
    "type": "Point",
    "coordinates": [
      31.31845,
      27.04514
    ]
  }
}