{
  "type": "Feature",
  "properties": {
    "name": "Al Badārī",
    "country": "EG",
    "subdivision": "17",
    "timezone": "Africa/Cairo"
  },
  "geometry": {
    "type": "Point",
    "coordinates": [
      31.41605,
      26.99306
    ]
  }
}