{
  "type": "Feature",
  "properties": {
    "name": "Nzega",
    "country": "RW",
    "subdivision": "15",
    "timezone": "Africa/Kigali"
  },
  "geometry": {
    "type": "Point",
    "coordinates": [
      29.5564,
      -2.479
    ]
  }
}