{
  "type": "Feature",
  "properties": {
    "name": "Pitampura",
    "country": "IN",
    "subdivision": "07",
    "timezone": "Asia/Kolkata"
  },
  "geometry": {
    "type": "Point",
    "coordinates": [
      77.13126,
      28.68964
    ]
  }
}