{
  "type": "Feature",
  "properties": {
    "name": "Labé",
    "country": "GN",
    "subdivision": "L",
    "timezone": "Africa/Conakry"
  },
  "geometry": {
    "type": "Point",
    "coordinates": [
      -12.28332,
      11.31823
    ]
  }
}