{
  "type": "Feature",
  "properties": {
    "name": "Zhabei",
    "country": "CN",
    "subdivision": "23",
    "timezone": "Asia/Shanghai"
  },
  "geometry": {
    "type": "Point",
    "coordinates": [
      121.45972,
      31.25861
    ]
  }
}