{
  "type": "Feature",
  "properties": {
    "name": "Zhujiajiao",
    "country": "CN",
    "subdivision": "23",
    "timezone": "Asia/Shanghai"
  },
  "geometry": {
    "type": "Point",
    "coordinates": [
      121.05696,
      31.10757
    ]
  }
}