{
  "type": "Feature",
  "properties": {
    "name": "Jalingo",
    "country": "NG",
    "subdivision": "43",
    "timezone": "Africa/Lagos"
  },
  "geometry": {
    "type": "Point",
    "coordinates": [
      11.3596,
      8.89367
    ]
  }
}