{
  "type": "Feature",
  "properties": {
    "name": "Priyutnoye",
    "country": "RU",
    "subdivision": "24",
    "timezone": "Europe/Moscow"
  },
  "geometry": {
    "type": "Point",
    "coordinates": [
      43.50722,
      46.10111
    ]
  }
}