{
  "type": "Feature",
  "properties": {
    "name": "Yashkul’",
    "country": "RU",
    "subdivision": "24",
    "timezone": "Europe/Moscow"
  },
  "geometry": {
    "type": "Point",
    "coordinates": [
      45.3435,
      46.1711
    ]
  }
}