{
  "type": "Feature",
  "properties": {
    "name": "’Aïn el Melh",
    "country": "DZ",
    "subdivision": "27",
    "timezone": "Africa/Algiers"
  },
  "geometry": {
    "type": "Point",
    "coordinates": [
      4.16383,
      34.84146
    ]
  }
}