{
  "type": "Feature",
  "properties": {
    "name": "Mboursou Léré",
    "country": "TD",
    "subdivision": "20",
    "timezone": "Africa/Ndjamena"
  },
  "geometry": {
    "type": "Point",
    "coordinates": [
      14.1539,
      9.7639
    ]
  }
}