{
  "type": "Feature",
  "properties": {
    "name": "Planaltina",
    "country": "BR",
    "subdivision": "07",
    "timezone": "America/Sao_Paulo"
  },
  "geometry": {
    "type": "Point",
    "coordinates": [
      -47.64874,
      -15.61791
    ]
  }
}