{
  "type": "Feature",
  "properties": {
    "name": "General José Eduvigis Díaz",
    "country": "PY",
    "subdivision": "13",
    "timezone": "America/Asuncion"
  },
  "geometry": {
    "type": "Point",
    "coordinates": [
      -58.3691,
      -27.20153
    ]
  }
}