{
  "type": "Feature",
  "properties": {
    "name": "Admiralteisky",
    "country": "RU",
    "subdivision": "66",
    "timezone": "Europe/Moscow"
  },
  "geometry": {
    "type": "Point",
    "coordinates": [
      30.28484,
      59.90839
    ]
  }
}