{
  "type": "Feature",
  "properties": {
    "name": "Obukhovo",
    "country": "RU",
    "subdivision": "66",
    "timezone": "Europe/Moscow"
  },
  "geometry": {
    "type": "Point",
    "coordinates": [
      30.45111,
      59.84389
    ]
  }
}