{
  "type": "Feature",
  "properties": {
    "name": "Repino",
    "country": "RU",
    "subdivision": "66",
    "timezone": "Europe/Moscow"
  },
  "geometry": {
    "type": "Point",
    "coordinates": [
      29.86908,
      60.17217
    ]
  }
}