{
  "type": "Feature",
  "properties": {
    "name": "Condoto",
    "country": "CO",
    "subdivision": "11",
    "timezone": "America/Bogota"
  },
  "geometry": {
    "type": "Point",
    "coordinates": [
      -76.64973,
      5.09351
    ]
  }
}