{
  "type": "Feature",
  "properties": {
    "name": "Quibdó",
    "country": "CO",
    "subdivision": "11",
    "timezone": "America/Bogota"
  },
  "geometry": {
    "type": "Point",
    "coordinates": [
      -76.65835,
      5.69188
    ]
  }
}