{
  "type": "Feature",
  "properties": {
    "name": "Šmartno pri Slovenj Gradcu",
    "country": "SI",
    "subdivision": "C2",
    "timezone": "Europe/Ljubljana"
  },
  "geometry": {
    "type": "Point",
    "coordinates": [
      15.10667,
      46.48944
    ]
  }
}