{
  "type": "Feature",
  "properties": {
    "name": "Madaoua",
    "country": "NE",
    "subdivision": "06",
    "timezone": "Africa/Niamey"
  },
  "geometry": {
    "type": "Point",
    "coordinates": [
      5.96,
      14.073
    ]
  }
}