{
  "type": "Feature",
  "properties": {
    "name": "Magaria",
    "country": "NE",
    "subdivision": "07",
    "timezone": "Africa/Niamey"
  },
  "geometry": {
    "type": "Point",
    "coordinates": [
      8.90991,
      12.99826
    ]
  }
}