{
  "type": "Feature",
  "properties": {
    "name": "Zinder",
    "country": "NE",
    "subdivision": "07",
    "timezone": "Africa/Niamey"
  },
  "geometry": {
    "type": "Point",
    "coordinates": [
      8.9881,
      13.80716
    ]
  }
}