{
  "type": "Feature",
  "properties": {
    "name": "Betio Village",
    "country": "KI",
    "subdivision": "01",
    "timezone": "Pacific/Tarawa"
  },
  "geometry": {
    "type": "Point",
    "coordinates": [
      172.92105,
      1.35797
    ]
  }
}