{
  "type": "Feature",
  "properties": {
    "name": "Eita Village",
    "country": "KI",
    "subdivision": "01",
    "timezone": "Pacific/Tarawa"
  },
  "geometry": {
    "type": "Point",
    "coordinates": [
      173.08113,
      1.36154
    ]
  }
}