{
  "type": "Feature",
  "properties": {
    "name": "Cherkasskoye",
    "country": "RU",
    "subdivision": "67",
    "timezone": "Europe/Saratov"
  },
  "geometry": {
    "type": "Point",
    "coordinates": [
      47.21048,
      52.42895
    ]
  }
}