{
  "type": "Feature",
  "properties": {
    "name": "Dukhovnitskoye",
    "country": "RU",
    "subdivision": "67",
    "timezone": "Europe/Saratov"
  },
  "geometry": {
    "type": "Point",
    "coordinates": [
      48.2137,
      52.4828
    ]
  }
}