{
  "type": "Feature",
  "properties": {
    "name": "Lysyye Gory",
    "country": "RU",
    "subdivision": "67",
    "timezone": "Europe/Saratov"
  },
  "geometry": {
    "type": "Point",
    "coordinates": [
      44.84144,
      51.55063
    ]
  }
}