{
  "type": "Feature",
  "properties": {
    "name": "Piterka",
    "country": "RU",
    "subdivision": "67",
    "timezone": "Europe/Saratov"
  },
  "geometry": {
    "type": "Point",
    "coordinates": [
      47.44539,
      50.6803
    ]
  }
}