{
  "type": "Feature",
  "properties": {
    "name": "Privolzhskiy",
    "country": "RU",
    "subdivision": "67",
    "timezone": "Europe/Saratov"
  },
  "geometry": {
    "type": "Point",
    "coordinates": [
      46.04833,
      51.40944
    ]
  }
}