{
  "type": "Feature",
  "properties": {
    "name": "Sennoy",
    "country": "RU",
    "subdivision": "67",
    "timezone": "Europe/Saratov"
  },
  "geometry": {
    "type": "Point",
    "coordinates": [
      46.96309,
      52.1509
    ]
  }
}