{
  "type": "Feature",
  "properties": {
    "name": "Sokolovyy",
    "country": "RU",
    "subdivision": "67",
    "timezone": "Europe/Saratov"
  },
  "geometry": {
    "type": "Point",
    "coordinates": [
      45.83312,
      51.56857
    ]
  }
}