{
  "type": "Feature",
  "properties": {
    "name": "Staryye Ozinki",
    "country": "RU",
    "subdivision": "67",
    "timezone": "Europe/Saratov"
  },
  "geometry": {
    "type": "Point",
    "coordinates": [
      49.6769,
      51.1786
    ]
  }
}