{
  "type": "Feature",
  "properties": {
    "name": "Ahlbeck",
    "country": "DE",
    "subdivision": "12",
    "timezone": "Europe/Berlin"
  },
  "geometry": {
    "type": "Point",
    "coordinates": [
      14.18622,
      53.66972
    ]
  }
}