{
  "type": "Feature",
  "properties": {
    "name": "Biendorf",
    "country": "DE",
    "subdivision": "12",
    "timezone": "Europe/Berlin"
  },
  "geometry": {
    "type": "Point",
    "coordinates": [
      11.70127,
      54.0752
    ]
  }
}