{
  "type": "Feature",
  "properties": {
    "name": "Boizenburg",
    "country": "DE",
    "subdivision": "12",
    "timezone": "Europe/Berlin"
  },
  "geometry": {
    "type": "Point",
    "coordinates": [
      10.72375,
      53.38153
    ]
  }
}