{
  "type": "Feature",
  "properties": {
    "name": "Brunn",
    "country": "DE",
    "subdivision": "12",
    "timezone": "Europe/Berlin"
  },
  "geometry": {
    "type": "Point",
    "coordinates": [
      13.37032,
      53.67076
    ]
  }
}