{
  "type": "Feature",
  "properties": {
    "name": "Dabel",
    "country": "DE",
    "subdivision": "12",
    "timezone": "Europe/Berlin"
  },
  "geometry": {
    "type": "Point",
    "coordinates": [
      11.90025,
      53.66112
    ]
  }
}