{
  "type": "Feature",
  "properties": {
    "name": "Dargun",
    "country": "DE",
    "subdivision": "12",
    "timezone": "Europe/Berlin"
  },
  "geometry": {
    "type": "Point",
    "coordinates": [
      12.85014,
      53.9009
    ]
  }
}