{
  "type": "Feature",
  "properties": {
    "name": "Dobbertin",
    "country": "DE",
    "subdivision": "12",
    "timezone": "Europe/Berlin"
  },
  "geometry": {
    "type": "Point",
    "coordinates": [
      12.07466,
      53.62306
    ]
  }
}