{
  "type": "Feature",
  "properties": {
    "name": "Ducherow",
    "country": "DE",
    "subdivision": "12",
    "timezone": "Europe/Berlin"
  },
  "geometry": {
    "type": "Point",
    "coordinates": [
      13.78216,
      53.76436
    ]
  }
}