{
  "type": "Feature",
  "properties": {
    "name": "Garz",
    "country": "DE",
    "subdivision": "12",
    "timezone": "Europe/Berlin"
  },
  "geometry": {
    "type": "Point",
    "coordinates": [
      13.35125,
      54.31843
    ]
  }
}