{
  "type": "Feature",
  "properties": {
    "name": "Jatznick",
    "country": "DE",
    "subdivision": "12",
    "timezone": "Europe/Berlin"
  },
  "geometry": {
    "type": "Point",
    "coordinates": [
      13.93955,
      53.57951
    ]
  }
}