{
  "type": "Feature",
  "properties": {
    "name": "Klütz",
    "country": "DE",
    "subdivision": "12",
    "timezone": "Europe/Berlin"
  },
  "geometry": {
    "type": "Point",
    "coordinates": [
      11.16367,
      53.9647
    ]
  }
}