{
  "type": "Feature",
  "properties": {
    "name": "Lüdersdorf",
    "country": "DE",
    "subdivision": "12",
    "timezone": "Europe/Berlin"
  },
  "geometry": {
    "type": "Point",
    "coordinates": [
      11.74902,
      53.86835
    ]
  }
}