{
  "type": "Feature",
  "properties": {
    "name": "Ludwigslust",
    "country": "DE",
    "subdivision": "12",
    "timezone": "Europe/Berlin"
  },
  "geometry": {
    "type": "Point",
    "coordinates": [
      11.49714,
      53.32917
    ]
  }
}