{
  "type": "Feature",
  "properties": {
    "name": "Mecklenburg",
    "country": "DE",
    "subdivision": "12",
    "timezone": "Europe/Berlin"
  },
  "geometry": {
    "type": "Point",
    "coordinates": [
      11.4633,
      53.8427
    ]
  }
}