{
  "type": "Feature",
  "properties": {
    "name": "Mühl Rosin",
    "country": "DE",
    "subdivision": "12",
    "timezone": "Europe/Berlin"
  },
  "geometry": {
    "type": "Point",
    "coordinates": [
      12.21388,
      53.76383
    ]
  }
}