{
  "type": "Feature",
  "properties": {
    "name": "Ostseebad Binz",
    "country": "DE",
    "subdivision": "12",
    "timezone": "Europe/Berlin"
  },
  "geometry": {
    "type": "Point",
    "coordinates": [
      13.61052,
      54.39995
    ]
  }
}