{
  "type": "Feature",
  "properties": {
    "name": "Raben Steinfeld",
    "country": "DE",
    "subdivision": "12",
    "timezone": "Europe/Berlin"
  },
  "geometry": {
    "type": "Point",
    "coordinates": [
      11.50487,
      53.60141
    ]
  }
}