{
  "type": "Feature",
  "properties": {
    "name": "Ribnitz-Damgarten",
    "country": "DE",
    "subdivision": "12",
    "timezone": "Europe/Berlin"
  },
  "geometry": {
    "type": "Point",
    "coordinates": [
      12.45666,
      54.2422
    ]
  }
}