{
  "type": "Feature",
  "properties": {
    "name": "Spornitz",
    "country": "DE",
    "subdivision": "12",
    "timezone": "Europe/Berlin"
  },
  "geometry": {
    "type": "Point",
    "coordinates": [
      11.71864,
      53.40749
    ]
  }
}