{
  "type": "Feature",
  "properties": {
    "name": "Strasburg",
    "country": "DE",
    "subdivision": "12",
    "timezone": "Europe/Berlin"
  },
  "geometry": {
    "type": "Point",
    "coordinates": [
      13.74513,
      53.5103
    ]
  }
}