{
  "type": "Feature",
  "properties": {
    "name": "Tarnow",
    "country": "DE",
    "subdivision": "12",
    "timezone": "Europe/Berlin"
  },
  "geometry": {
    "type": "Point",
    "coordinates": [
      12.01785,
      53.77941
    ]
  }
}