{
  "type": "Feature",
  "properties": {
    "name": "Teterow",
    "country": "DE",
    "subdivision": "12",
    "timezone": "Europe/Berlin"
  },
  "geometry": {
    "type": "Point",
    "coordinates": [
      12.57487,
      53.77545
    ]
  }
}