{
  "type": "Feature",
  "properties": {
    "name": "Wackerow",
    "country": "DE",
    "subdivision": "12",
    "timezone": "Europe/Berlin"
  },
  "geometry": {
    "type": "Point",
    "coordinates": [
      12.98164,
      53.67683
    ]
  }
}