{
  "type": "Feature",
  "properties": {
    "name": "Weststadt",
    "country": "DE",
    "subdivision": "12",
    "timezone": "Europe/Berlin"
  },
  "geometry": {
    "type": "Point",
    "coordinates": [
      11.39565,
      53.63472
    ]
  }
}