{
  "type": "Feature",
  "properties": {
    "name": "Wismar",
    "country": "DE",
    "subdivision": "12",
    "timezone": "Europe/Berlin"
  },
  "geometry": {
    "type": "Point",
    "coordinates": [
      11.45286,
      53.89314
    ]
  }
}