{
  "type": "Feature",
  "properties": {
    "name": "Ventanas",
    "country": "EC",
    "subdivision": "13",
    "timezone": "America/Guayaquil"
  },
  "geometry": {
    "type": "Point",
    "coordinates": [
      -79.45943,
      -1.44158
    ]
  }
}