{
  "type": "Feature",
  "properties": {
    "name": "Belén",
    "country": "CO",
    "subdivision": "20",
    "timezone": "America/Bogota"
  },
  "geometry": {
    "type": "Point",
    "coordinates": [
      -77.05408,
      1.59477
    ]
  }
}