{
  "type": "Feature",
  "properties": {
    "name": "Córdoba",
    "country": "CO",
    "subdivision": "20",
    "timezone": "America/Bogota"
  },
  "geometry": {
    "type": "Point",
    "coordinates": [
      -77.51817,
      0.85362
    ]
  }
}