{
  "type": "Feature",
  "properties": {
    "name": "Policarpa",
    "country": "CO",
    "subdivision": "20",
    "timezone": "America/Bogota"
  },
  "geometry": {
    "type": "Point",
    "coordinates": [
      -77.45956,
      1.62843
    ]
  }
}