{
  "type": "Feature",
  "properties": {
    "name": "Potosí",
    "country": "CO",
    "subdivision": "20",
    "timezone": "America/Bogota"
  },
  "geometry": {
    "type": "Point",
    "coordinates": [
      -77.57216,
      0.80739
    ]
  }
}