{
  "type": "Feature",
  "properties": {
    "name": "Puerres",
    "country": "CO",
    "subdivision": "20",
    "timezone": "America/Bogota"
  },
  "geometry": {
    "type": "Point",
    "coordinates": [
      -77.26661,
      1.19374
    ]
  }
}