{
  "type": "Feature",
  "properties": {
    "name": "Ricaurte",
    "country": "CO",
    "subdivision": "20",
    "timezone": "America/Bogota"
  },
  "geometry": {
    "type": "Point",
    "coordinates": [
      -77.99801,
      1.21474
    ]
  }
}