{
  "type": "Feature",
  "properties": {
    "name": "Salahonda",
    "country": "CO",
    "subdivision": "20",
    "timezone": "America/Bogota"
  },
  "geometry": {
    "type": "Point",
    "coordinates": [
      -78.65877,
      2.0406
    ]
  }
}