{
  "type": "Feature",
  "properties": {
    "name": "Sandoná",
    "country": "CO",
    "subdivision": "20",
    "timezone": "America/Bogota"
  },
  "geometry": {
    "type": "Point",
    "coordinates": [
      -77.46921,
      1.28626
    ]
  }
}