{
  "type": "Feature",
  "properties": {
    "name": "Batabanó",
    "country": "CU",
    "subdivision": "MA",
    "timezone": "America/Havana"
  },
  "geometry": {
    "type": "Point",
    "coordinates": [
      -82.28965,
      22.71794
    ]
  }
}