{
  "type": "Feature",
  "properties": {
    "name": "Algrange",
    "country": "FR",
    "subdivision": "44",
    "timezone": "Europe/Paris"
  },
  "geometry": {
    "type": "Point",
    "coordinates": [
      6.05094,
      49.36276
    ]
  }
}