{
  "type": "Feature",
  "properties": {
    "name": "Altkirch",
    "country": "FR",
    "subdivision": "44",
    "timezone": "Europe/Paris"
  },
  "geometry": {
    "type": "Point",
    "coordinates": [
      7.23954,
      47.62417
    ]
  }
}