{
  "type": "Feature",
  "properties": {
    "name": "Amanvillers",
    "country": "FR",
    "subdivision": "44",
    "timezone": "Europe/Paris"
  },
  "geometry": {
    "type": "Point",
    "coordinates": [
      6.04367,
      49.16784
    ]
  }
}