{
  "type": "Feature",
  "properties": {
    "name": "Amnéville",
    "country": "FR",
    "subdivision": "44",
    "timezone": "Europe/Paris"
  },
  "geometry": {
    "type": "Point",
    "coordinates": [
      6.13414,
      49.25671
    ]
  }
}