{
  "type": "Feature",
  "properties": {
    "name": "Argancy",
    "country": "FR",
    "subdivision": "44",
    "timezone": "Europe/Paris"
  },
  "geometry": {
    "type": "Point",
    "coordinates": [
      6.20157,
      49.19543
    ]
  }
}