{
  "type": "Feature",
  "properties": {
    "name": "Aspach-le-Bas",
    "country": "FR",
    "subdivision": "44",
    "timezone": "Europe/Paris"
  },
  "geometry": {
    "type": "Point",
    "coordinates": [
      7.15104,
      47.76135
    ]
  }
}