{
  "type": "Feature",
  "properties": {
    "name": "Avize",
    "country": "FR",
    "subdivision": "44",
    "timezone": "Europe/Paris"
  },
  "geometry": {
    "type": "Point",
    "coordinates": [
      4.01438,
      48.97352
    ]
  }
}