{
  "type": "Feature",
  "properties": {
    "name": "Aydoilles",
    "country": "FR",
    "subdivision": "44",
    "timezone": "Europe/Paris"
  },
  "geometry": {
    "type": "Point",
    "coordinates": [
      6.57389,
      48.21026
    ]
  }
}