{
  "type": "Feature",
  "properties": {
    "name": "Barr",
    "country": "FR",
    "subdivision": "44",
    "timezone": "Europe/Paris"
  },
  "geometry": {
    "type": "Point",
    "coordinates": [
      7.44873,
      48.40755
    ]
  }
}