{
  "type": "Feature",
  "properties": {
    "name": "Basse-Ham",
    "country": "FR",
    "subdivision": "44",
    "timezone": "Europe/Paris"
  },
  "geometry": {
    "type": "Point",
    "coordinates": [
      6.2418,
      49.38626
    ]
  }
}