{
  "type": "Feature",
  "properties": {
    "name": "Bazeilles",
    "country": "FR",
    "subdivision": "44",
    "timezone": "Europe/Paris"
  },
  "geometry": {
    "type": "Point",
    "coordinates": [
      4.97752,
      49.6765
    ]
  }
}