{
  "type": "Feature",
  "properties": {
    "name": "Belleville",
    "country": "FR",
    "subdivision": "44",
    "timezone": "Europe/Paris"
  },
  "geometry": {
    "type": "Point",
    "coordinates": [
      6.10294,
      48.81817
    ]
  }
}