{
  "type": "Feature",
  "properties": {
    "name": "Béning-lès-Saint-Avold",
    "country": "FR",
    "subdivision": "44",
    "timezone": "Europe/Paris"
  },
  "geometry": {
    "type": "Point",
    "coordinates": [
      6.83902,
      49.13504
    ]
  }
}