{
  "type": "Feature",
  "properties": {
    "name": "Berrwiller",
    "country": "FR",
    "subdivision": "44",
    "timezone": "Europe/Paris"
  },
  "geometry": {
    "type": "Point",
    "coordinates": [
      7.21922,
      47.84984
    ]
  }
}