{
  "type": "Feature",
  "properties": {
    "name": "Bitche",
    "country": "FR",
    "subdivision": "44",
    "timezone": "Europe/Paris"
  },
  "geometry": {
    "type": "Point",
    "coordinates": [
      7.42992,
      49.05232
    ]
  }
}