{
  "type": "Feature",
  "properties": {
    "name": "Bologne",
    "country": "FR",
    "subdivision": "44",
    "timezone": "Europe/Paris"
  },
  "geometry": {
    "type": "Point",
    "coordinates": [
      5.14209,
      48.20005
    ]
  }
}