{
  "type": "Feature",
  "properties": {
    "name": "Boofzheim",
    "country": "FR",
    "subdivision": "44",
    "timezone": "Europe/Paris"
  },
  "geometry": {
    "type": "Point",
    "coordinates": [
      7.68071,
      48.33186
    ]
  }
}