{
  "type": "Feature",
  "properties": {
    "name": "Bruyères",
    "country": "FR",
    "subdivision": "44",
    "timezone": "Europe/Paris"
  },
  "geometry": {
    "type": "Point",
    "coordinates": [
      6.71845,
      48.20709
    ]
  }
}