{
  "type": "Feature",
  "properties": {
    "name": "Buhl",
    "country": "FR",
    "subdivision": "44",
    "timezone": "Europe/Paris"
  },
  "geometry": {
    "type": "Point",
    "coordinates": [
      7.18719,
      47.92806
    ]
  }
}