{
  "type": "Feature",
  "properties": {
    "name": "Chaligny",
    "country": "FR",
    "subdivision": "44",
    "timezone": "Europe/Paris"
  },
  "geometry": {
    "type": "Point",
    "coordinates": [
      6.08262,
      48.62422
    ]
  }
}