{
  "type": "Feature",
  "properties": {
    "name": "Chantraine",
    "country": "FR",
    "subdivision": "44",
    "timezone": "Europe/Paris"
  },
  "geometry": {
    "type": "Point",
    "coordinates": [
      6.43538,
      48.17157
    ]
  }
}