{
  "type": "Feature",
  "properties": {
    "name": "Châtel-sur-Moselle",
    "country": "FR",
    "subdivision": "44",
    "timezone": "Europe/Paris"
  },
  "geometry": {
    "type": "Point",
    "coordinates": [
      6.39403,
      48.3143
    ]
  }
}