{
  "type": "Feature",
  "properties": {
    "name": "Compertrix",
    "country": "FR",
    "subdivision": "44",
    "timezone": "Europe/Paris"
  },
  "geometry": {
    "type": "Point",
    "coordinates": [
      4.34631,
      48.94179
    ]
  }
}