{
  "type": "Feature",
  "properties": {
    "name": "Deyvillers",
    "country": "FR",
    "subdivision": "44",
    "timezone": "Europe/Paris"
  },
  "geometry": {
    "type": "Point",
    "coordinates": [
      6.51533,
      48.20013
    ]
  }
}