{
  "type": "Feature",
  "properties": {
    "name": "Didenheim",
    "country": "FR",
    "subdivision": "44",
    "timezone": "Europe/Paris"
  },
  "geometry": {
    "type": "Point",
    "coordinates": [
      7.30157,
      47.71866
    ]
  }
}