{
  "type": "Feature",
  "properties": {
    "name": "Dieue-sur-Meuse",
    "country": "FR",
    "subdivision": "44",
    "timezone": "Europe/Paris"
  },
  "geometry": {
    "type": "Point",
    "coordinates": [
      5.42248,
      49.072
    ]
  }
}