{
  "type": "Feature",
  "properties": {
    "name": "Dingsheim",
    "country": "FR",
    "subdivision": "44",
    "timezone": "Europe/Paris"
  },
  "geometry": {
    "type": "Point",
    "coordinates": [
      7.66932,
      48.63053
    ]
  }
}