{
  "type": "Feature",
  "properties": {
    "name": "Dinsheim-sur-Bruche",
    "country": "FR",
    "subdivision": "44",
    "timezone": "Europe/Paris"
  },
  "geometry": {
    "type": "Point",
    "coordinates": [
      7.42727,
      48.54258
    ]
  }
}