{
  "type": "Feature",
  "properties": {
    "name": "Doncourt-lès-Conflans",
    "country": "FR",
    "subdivision": "44",
    "timezone": "Europe/Paris"
  },
  "geometry": {
    "type": "Point",
    "coordinates": [
      5.93368,
      49.1425
    ]
  }
}