{
  "type": "Feature",
  "properties": {
    "name": "Ensisheim",
    "country": "FR",
    "subdivision": "44",
    "timezone": "Europe/Paris"
  },
  "geometry": {
    "type": "Point",
    "coordinates": [
      7.35052,
      47.86584
    ]
  }
}