{
  "type": "Feature",
  "properties": {
    "name": "Ervy-le-Châtel",
    "country": "FR",
    "subdivision": "44",
    "timezone": "Europe/Paris"
  },
  "geometry": {
    "type": "Point",
    "coordinates": [
      3.90988,
      48.04116
    ]
  }
}