{
  "type": "Feature",
  "properties": {
    "name": "Eschau",
    "country": "FR",
    "subdivision": "44",
    "timezone": "Europe/Paris"
  },
  "geometry": {
    "type": "Point",
    "coordinates": [
      7.71644,
      48.48897
    ]
  }
}