{
  "type": "Feature",
  "properties": {
    "name": "Etzling",
    "country": "FR",
    "subdivision": "44",
    "timezone": "Europe/Paris"
  },
  "geometry": {
    "type": "Point",
    "coordinates": [
      6.95864,
      49.17943
    ]
  }
}