{
  "type": "Feature",
  "properties": {
    "name": "Eurville-Bienville",
    "country": "FR",
    "subdivision": "44",
    "timezone": "Europe/Paris"
  },
  "geometry": {
    "type": "Point",
    "coordinates": [
      5.03333,
      48.58333
    ]
  }
}