{
  "type": "Feature",
  "properties": {
    "name": "Euville",
    "country": "FR",
    "subdivision": "44",
    "timezone": "Europe/Paris"
  },
  "geometry": {
    "type": "Point",
    "coordinates": [
      5.62603,
      48.7503
    ]
  }
}