{
  "type": "Feature",
  "properties": {
    "name": "Fismes",
    "country": "FR",
    "subdivision": "44",
    "timezone": "Europe/Paris"
  },
  "geometry": {
    "type": "Point",
    "coordinates": [
      3.68607,
      49.30773
    ]
  }
}