{
  "type": "Feature",
  "properties": {
    "name": "Fleury",
    "country": "FR",
    "subdivision": "44",
    "timezone": "Europe/Paris"
  },
  "geometry": {
    "type": "Point",
    "coordinates": [
      6.19329,
      49.04181
    ]
  }
}