{
  "type": "Feature",
  "properties": {
    "name": "Flize",
    "country": "FR",
    "subdivision": "44",
    "timezone": "Europe/Paris"
  },
  "geometry": {
    "type": "Point",
    "coordinates": [
      4.77171,
      49.69875
    ]
  }
}