{
  "type": "Feature",
  "properties": {
    "name": "Fontoy",
    "country": "FR",
    "subdivision": "44",
    "timezone": "Europe/Paris"
  },
  "geometry": {
    "type": "Point",
    "coordinates": [
      5.9925,
      49.35597
    ]
  }
}