{
  "type": "Feature",
  "properties": {
    "name": "Gérardmer",
    "country": "FR",
    "subdivision": "44",
    "timezone": "Europe/Paris"
  },
  "geometry": {
    "type": "Point",
    "coordinates": [
      6.87787,
      48.07346
    ]
  }
}