{
  "type": "Feature",
  "properties": {
    "name": "Gorze",
    "country": "FR",
    "subdivision": "44",
    "timezone": "Europe/Paris"
  },
  "geometry": {
    "type": "Point",
    "coordinates": [
      6.00072,
      49.05236
    ]
  }
}