{
  "type": "Feature",
  "properties": {
    "name": "Gueux",
    "country": "FR",
    "subdivision": "44",
    "timezone": "Europe/Paris"
  },
  "geometry": {
    "type": "Point",
    "coordinates": [
      3.91024,
      49.25048
    ]
  }
}