{
  "type": "Feature",
  "properties": {
    "name": "Hagenthal-le-Bas",
    "country": "FR",
    "subdivision": "44",
    "timezone": "Europe/Paris"
  },
  "geometry": {
    "type": "Point",
    "coordinates": [
      7.47783,
      47.52497
    ]
  }
}