{
  "type": "Feature",
  "properties": {
    "name": "Hindisheim",
    "country": "FR",
    "subdivision": "44",
    "timezone": "Europe/Paris"
  },
  "geometry": {
    "type": "Point",
    "coordinates": [
      7.63859,
      48.46837
    ]
  }
}