{
  "type": "Feature",
  "properties": {
    "name": "Holtzheim",
    "country": "FR",
    "subdivision": "44",
    "timezone": "Europe/Paris"
  },
  "geometry": {
    "type": "Point",
    "coordinates": [
      7.64434,
      48.5582
    ]
  }
}