{
  "type": "Feature",
  "properties": {
    "name": "Kaysersberg",
    "country": "FR",
    "subdivision": "44",
    "timezone": "Europe/Paris"
  },
  "geometry": {
    "type": "Point",
    "coordinates": [
      7.26385,
      48.13803
    ]
  }
}