{
  "type": "Feature",
  "properties": {
    "name": "Kunheim",
    "country": "FR",
    "subdivision": "44",
    "timezone": "Europe/Paris"
  },
  "geometry": {
    "type": "Point",
    "coordinates": [
      7.53489,
      48.07657
    ]
  }
}