{
  "type": "Feature",
  "properties": {
    "name": "Kœnigsmacker",
    "country": "FR",
    "subdivision": "44",
    "timezone": "Europe/Paris"
  },
  "geometry": {
    "type": "Point",
    "coordinates": [
      6.27727,
      49.39386
    ]
  }
}