{
  "type": "Feature",
  "properties": {
    "name": "La Chapelle-Saint-Luc",
    "country": "FR",
    "subdivision": "44",
    "timezone": "Europe/Paris"
  },
  "geometry": {
    "type": "Point",
    "coordinates": [
      4.03988,
      48.31734
    ]
  }
}