{
  "type": "Feature",
  "properties": {
    "name": "Longuyon",
    "country": "FR",
    "subdivision": "44",
    "timezone": "Europe/Paris"
  },
  "geometry": {
    "type": "Point",
    "coordinates": [
      5.60508,
      49.44181
    ]
  }
}