{
  "type": "Feature",
  "properties": {
    "name": "Lorquin",
    "country": "FR",
    "subdivision": "44",
    "timezone": "Europe/Paris"
  },
  "geometry": {
    "type": "Point",
    "coordinates": [
      6.99915,
      48.67102
    ]
  }
}