{
  "type": "Feature",
  "properties": {
    "name": "Mancieulles",
    "country": "FR",
    "subdivision": "44",
    "timezone": "Europe/Paris"
  },
  "geometry": {
    "type": "Point",
    "coordinates": [
      5.89612,
      49.28231
    ]
  }
}