{
  "type": "Feature",
  "properties": {
    "name": "Mardeuil",
    "country": "FR",
    "subdivision": "44",
    "timezone": "Europe/Paris"
  },
  "geometry": {
    "type": "Point",
    "coordinates": [
      3.93,
      49.05393
    ]
  }
}