{
  "type": "Feature",
  "properties": {
    "name": "Matzenheim",
    "country": "FR",
    "subdivision": "44",
    "timezone": "Europe/Paris"
  },
  "geometry": {
    "type": "Point",
    "coordinates": [
      7.62185,
      48.3945
    ]
  }
}