{
  "type": "Feature",
  "properties": {
    "name": "Méréville",
    "country": "FR",
    "subdivision": "44",
    "timezone": "Europe/Paris"
  },
  "geometry": {
    "type": "Point",
    "coordinates": [
      6.15106,
      48.59113
    ]
  }
}