{
  "type": "Feature",
  "properties": {
    "name": "Montigny-lès-Metz",
    "country": "FR",
    "subdivision": "44",
    "timezone": "Europe/Paris"
  },
  "geometry": {
    "type": "Point",
    "coordinates": [
      6.15271,
      49.0956
    ]
  }
}