{
  "type": "Feature",
  "properties": {
    "name": "Montbronn",
    "country": "FR",
    "subdivision": "44",
    "timezone": "Europe/Paris"
  },
  "geometry": {
    "type": "Point",
    "coordinates": [
      7.31075,
      48.99243
    ]
  }
}