{
  "type": "Feature",
  "properties": {
    "name": "Montauville",
    "country": "FR",
    "subdivision": "44",
    "timezone": "Europe/Paris"
  },
  "geometry": {
    "type": "Point",
    "coordinates": [
      6.02359,
      48.90111
    ]
  }
}