{
  "type": "Feature",
  "properties": {
    "name": "Morsbach",
    "country": "FR",
    "subdivision": "44",
    "timezone": "Europe/Paris"
  },
  "geometry": {
    "type": "Point",
    "coordinates": [
      6.8719,
      49.16806
    ]
  }
}