{
  "type": "Feature",
  "properties": {
    "name": "Moutiers",
    "country": "FR",
    "subdivision": "44",
    "timezone": "Europe/Paris"
  },
  "geometry": {
    "type": "Point",
    "coordinates": [
      5.96553,
      49.23302
    ]
  }
}