{
  "type": "Feature",
  "properties": {
    "name": "Mussig",
    "country": "FR",
    "subdivision": "44",
    "timezone": "Europe/Paris"
  },
  "geometry": {
    "type": "Point",
    "coordinates": [
      7.51963,
      48.22993
    ]
  }
}