{
  "type": "Feature",
  "properties": {
    "name": "Muttersholtz",
    "country": "FR",
    "subdivision": "44",
    "timezone": "Europe/Paris"
  },
  "geometry": {
    "type": "Point",
    "coordinates": [
      7.53567,
      48.26761
    ]
  }
}