{
  "type": "Feature",
  "properties": {
    "name": "Neufgrange",
    "country": "FR",
    "subdivision": "44",
    "timezone": "Europe/Paris"
  },
  "geometry": {
    "type": "Point",
    "coordinates": [
      7.06526,
      49.07679
    ]
  }
}