{
  "type": "Feature",
  "properties": {
    "name": "Niederhaslach",
    "country": "FR",
    "subdivision": "44",
    "timezone": "Europe/Paris"
  },
  "geometry": {
    "type": "Point",
    "coordinates": [
      7.34282,
      48.54264
    ]
  }
}