{
  "type": "Feature",
  "properties": {
    "name": "Nilvange",
    "country": "FR",
    "subdivision": "44",
    "timezone": "Europe/Paris"
  },
  "geometry": {
    "type": "Point",
    "coordinates": [
      6.04964,
      49.34224
    ]
  }
}