{
  "type": "Feature",
  "properties": {
    "name": "Nogent-sur-Seine",
    "country": "FR",
    "subdivision": "44",
    "timezone": "Europe/Paris"
  },
  "geometry": {
    "type": "Point",
    "coordinates": [
      3.50262,
      48.49372
    ]
  }
}