{
  "type": "Feature",
  "properties": {
    "name": "Obermodern-Zutzendorf",
    "country": "FR",
    "subdivision": "44",
    "timezone": "Europe/Paris"
  },
  "geometry": {
    "type": "Point",
    "coordinates": [
      7.53333,
      48.85
    ]
  }
}