{
  "type": "Feature",
  "properties": {
    "name": "Offenheim",
    "country": "FR",
    "subdivision": "44",
    "timezone": "Europe/Paris"
  },
  "geometry": {
    "type": "Point",
    "coordinates": [
      7.61668,
      48.63208
    ]
  }
}