{
  "type": "Feature",
  "properties": {
    "name": "Pagny-sur-Moselle",
    "country": "FR",
    "subdivision": "44",
    "timezone": "Europe/Paris"
  },
  "geometry": {
    "type": "Point",
    "coordinates": [
      6.02069,
      48.98365
    ]
  }
}