{
  "type": "Feature",
  "properties": {
    "name": "Piennes",
    "country": "FR",
    "subdivision": "44",
    "timezone": "Europe/Paris"
  },
  "geometry": {
    "type": "Point",
    "coordinates": [
      5.78009,
      49.30964
    ]
  }
}