{
  "type": "Feature",
  "properties": {
    "name": "Pierrevillers",
    "country": "FR",
    "subdivision": "44",
    "timezone": "Europe/Paris"
  },
  "geometry": {
    "type": "Point",
    "coordinates": [
      6.10337,
      49.22468
    ]
  }
}