{
  "type": "Feature",
  "properties": {
    "name": "Pompey",
    "country": "FR",
    "subdivision": "44",
    "timezone": "Europe/Paris"
  },
  "geometry": {
    "type": "Point",
    "coordinates": [
      6.12639,
      48.76876
    ]
  }
}