{
  "type": "Feature",
  "properties": {
    "name": "Port à Binson",
    "country": "FR",
    "subdivision": "44",
    "timezone": "Europe/Paris"
  },
  "geometry": {
    "type": "Point",
    "coordinates": [
      3.75989,
      49.08202
    ]
  }
}