{
  "type": "Feature",
  "properties": {
    "name": "Pouxeux",
    "country": "FR",
    "subdivision": "44",
    "timezone": "Europe/Paris"
  },
  "geometry": {
    "type": "Point",
    "coordinates": [
      6.57299,
      48.10621
    ]
  }
}