{
  "type": "Feature",
  "properties": {
    "name": "Reiningue",
    "country": "FR",
    "subdivision": "44",
    "timezone": "Europe/Paris"
  },
  "geometry": {
    "type": "Point",
    "coordinates": [
      7.23327,
      47.75215
    ]
  }
}