{
  "type": "Feature",
  "properties": {
    "name": "Rémilly",
    "country": "FR",
    "subdivision": "44",
    "timezone": "Europe/Paris"
  },
  "geometry": {
    "type": "Point",
    "coordinates": [
      6.39219,
      49.01359
    ]
  }
}