{
  "type": "Feature",
  "properties": {
    "name": "Retonfey",
    "country": "FR",
    "subdivision": "44",
    "timezone": "Europe/Paris"
  },
  "geometry": {
    "type": "Point",
    "coordinates": [
      6.30634,
      49.13648
    ]
  }
}