{
  "type": "Feature",
  "properties": {
    "name": "Richemont",
    "country": "FR",
    "subdivision": "44",
    "timezone": "Europe/Paris"
  },
  "geometry": {
    "type": "Point",
    "coordinates": [
      6.16372,
      49.27723
    ]
  }
}