{
  "type": "Feature",
  "properties": {
    "name": "Rosenau",
    "country": "FR",
    "subdivision": "44",
    "timezone": "Europe/Paris"
  },
  "geometry": {
    "type": "Point",
    "coordinates": [
      7.53598,
      47.63688
    ]
  }
}