{
  "type": "Feature",
  "properties": {
    "name": "Rozérieulles",
    "country": "FR",
    "subdivision": "44",
    "timezone": "Europe/Paris"
  },
  "geometry": {
    "type": "Point",
    "coordinates": [
      6.08198,
      49.10668
    ]
  }
}