{
  "type": "Feature",
  "properties": {
    "name": "Rurange-lès-Thionville",
    "country": "FR",
    "subdivision": "44",
    "timezone": "Europe/Paris"
  },
  "geometry": {
    "type": "Point",
    "coordinates": [
      6.23184,
      49.27599
    ]
  }
}