{
  "type": "Feature",
  "properties": {
    "name": "Sainte-Maure",
    "country": "FR",
    "subdivision": "44",
    "timezone": "Europe/Paris"
  },
  "geometry": {
    "type": "Point",
    "coordinates": [
      4.05962,
      48.34729
    ]
  }
}