{
  "type": "Feature",
  "properties": {
    "name": "Saint-Julien-lès-Metz",
    "country": "FR",
    "subdivision": "44",
    "timezone": "Europe/Paris"
  },
  "geometry": {
    "type": "Point",
    "coordinates": [
      6.2024,
      49.13288
    ]
  }
}