{
  "type": "Feature",
  "properties": {
    "name": "Saint-Privat-la-Montagne",
    "country": "FR",
    "subdivision": "44",
    "timezone": "Europe/Paris"
  },
  "geometry": {
    "type": "Point",
    "coordinates": [
      6.03874,
      49.18768
    ]
  }
}