{
  "type": "Feature",
  "properties": {
    "name": "Sainte-Marguerite",
    "country": "FR",
    "subdivision": "44",
    "timezone": "Europe/Paris"
  },
  "geometry": {
    "type": "Point",
    "coordinates": [
      6.98439,
      48.26735
    ]
  }
}