{
  "type": "Feature",
  "properties": {
    "name": "Saulny",
    "country": "FR",
    "subdivision": "44",
    "timezone": "Europe/Paris"
  },
  "geometry": {
    "type": "Point",
    "coordinates": [
      6.10929,
      49.1577
    ]
  }
}