{
  "type": "Feature",
  "properties": {
    "name": "Sélestat",
    "country": "FR",
    "subdivision": "44",
    "timezone": "Europe/Paris"
  },
  "geometry": {
    "type": "Point",
    "coordinates": [
      7.4489,
      48.26195
    ]
  }
}