{
  "type": "Feature",
  "properties": {
    "name": "Sentheim",
    "country": "FR",
    "subdivision": "44",
    "timezone": "Europe/Paris"
  },
  "geometry": {
    "type": "Point",
    "coordinates": [
      7.05305,
      47.7556
    ]
  }
}