{
  "type": "Feature",
  "properties": {
    "name": "Serémange-Erzange",
    "country": "FR",
    "subdivision": "44",
    "timezone": "Europe/Paris"
  },
  "geometry": {
    "type": "Point",
    "coordinates": [
      6.09092,
      49.32062
    ]
  }
}