{
  "type": "Feature",
  "properties": {
    "name": "Sierck-les-Bains",
    "country": "FR",
    "subdivision": "44",
    "timezone": "Europe/Paris"
  },
  "geometry": {
    "type": "Point",
    "coordinates": [
      6.35816,
      49.43942
    ]
  }
}