{
  "type": "Feature",
  "properties": {
    "name": "Solgne",
    "country": "FR",
    "subdivision": "44",
    "timezone": "Europe/Paris"
  },
  "geometry": {
    "type": "Point",
    "coordinates": [
      6.29429,
      48.96543
    ]
  }
}