{
  "type": "Feature",
  "properties": {
    "name": "Soultzeren",
    "country": "FR",
    "subdivision": "44",
    "timezone": "Europe/Paris"
  },
  "geometry": {
    "type": "Point",
    "coordinates": [
      7.10233,
      48.06394
    ]
  }
}