{
  "type": "Feature",
  "properties": {
    "name": "Soultzmatt",
    "country": "FR",
    "subdivision": "44",
    "timezone": "Europe/Paris"
  },
  "geometry": {
    "type": "Point",
    "coordinates": [
      7.23759,
      47.96188
    ]
  }
}