{
  "type": "Feature",
  "properties": {
    "name": "Stenay",
    "country": "FR",
    "subdivision": "44",
    "timezone": "Europe/Paris"
  },
  "geometry": {
    "type": "Point",
    "coordinates": [
      5.18606,
      49.49489
    ]
  }
}