{
  "type": "Feature",
  "properties": {
    "name": "Sundhouse",
    "country": "FR",
    "subdivision": "44",
    "timezone": "Europe/Paris"
  },
  "geometry": {
    "type": "Point",
    "coordinates": [
      7.60427,
      48.2511
    ]
  }
}