{
  "type": "Feature",
  "properties": {
    "name": "Tenteling",
    "country": "FR",
    "subdivision": "44",
    "timezone": "Europe/Paris"
  },
  "geometry": {
    "type": "Point",
    "coordinates": [
      6.93751,
      49.12544
    ]
  }
}