{
  "type": "Feature",
  "properties": {
    "name": "Thann",
    "country": "FR",
    "subdivision": "44",
    "timezone": "Europe/Paris"
  },
  "geometry": {
    "type": "Point",
    "coordinates": [
      7.10301,
      47.80789
    ]
  }
}