{
  "type": "Feature",
  "properties": {
    "name": "Tournes",
    "country": "FR",
    "subdivision": "44",
    "timezone": "Europe/Paris"
  },
  "geometry": {
    "type": "Point",
    "coordinates": [
      4.63856,
      49.797
    ]
  }
}