{
  "type": "Feature",
  "properties": {
    "name": "Tronville-en-Barrois",
    "country": "FR",
    "subdivision": "44",
    "timezone": "Europe/Paris"
  },
  "geometry": {
    "type": "Point",
    "coordinates": [
      5.27808,
      48.71977
    ]
  }
}