{
  "type": "Feature",
  "properties": {
    "name": "Troyes",
    "country": "FR",
    "subdivision": "44",
    "timezone": "Europe/Paris"
  },
  "geometry": {
    "type": "Point",
    "coordinates": [
      4.08524,
      48.30073
    ]
  }
}