{
  "type": "Feature",
  "properties": {
    "name": "Uckange",
    "country": "FR",
    "subdivision": "44",
    "timezone": "Europe/Paris"
  },
  "geometry": {
    "type": "Point",
    "coordinates": [
      6.1492,
      49.30304
    ]
  }
}