{
  "type": "Feature",
  "properties": {
    "name": "Uriménil",
    "country": "FR",
    "subdivision": "44",
    "timezone": "Europe/Paris"
  },
  "geometry": {
    "type": "Point",
    "coordinates": [
      6.40046,
      48.10079
    ]
  }
}