{
  "type": "Feature",
  "properties": {
    "name": "Urmatt",
    "country": "FR",
    "subdivision": "44",
    "timezone": "Europe/Paris"
  },
  "geometry": {
    "type": "Point",
    "coordinates": [
      7.32565,
      48.52752
    ]
  }
}