{
  "type": "Feature",
  "properties": {
    "name": "Vendeuvre-sur-Barse",
    "country": "FR",
    "subdivision": "44",
    "timezone": "Europe/Paris"
  },
  "geometry": {
    "type": "Point",
    "coordinates": [
      4.46905,
      48.23786
    ]
  }
}