{
  "type": "Feature",
  "properties": {
    "name": "Verdun",
    "country": "FR",
    "subdivision": "44",
    "timezone": "Europe/Paris"
  },
  "geometry": {
    "type": "Point",
    "coordinates": [
      5.3829,
      49.15964
    ]
  }
}