{
  "type": "Feature",
  "properties": {
    "name": "Verrières",
    "country": "FR",
    "subdivision": "44",
    "timezone": "Europe/Paris"
  },
  "geometry": {
    "type": "Point",
    "coordinates": [
      4.14893,
      48.23334
    ]
  }
}