{
  "type": "Feature",
  "properties": {
    "name": "Verzy",
    "country": "FR",
    "subdivision": "44",
    "timezone": "Europe/Paris"
  },
  "geometry": {
    "type": "Point",
    "coordinates": [
      4.16409,
      49.14576
    ]
  }
}