{
  "type": "Feature",
  "properties": {
    "name": "Villerupt",
    "country": "FR",
    "subdivision": "44",
    "timezone": "Europe/Paris"
  },
  "geometry": {
    "type": "Point",
    "coordinates": [
      5.93202,
      49.46715
    ]
  }
}