{
  "type": "Feature",
  "properties": {
    "name": "Villey-Saint-Étienne",
    "country": "FR",
    "subdivision": "44",
    "timezone": "Europe/Paris"
  },
  "geometry": {
    "type": "Point",
    "coordinates": [
      5.97851,
      48.73254
    ]
  }
}