{
  "type": "Feature",
  "properties": {
    "name": "Villers-lès-Nancy",
    "country": "FR",
    "subdivision": "44",
    "timezone": "Europe/Paris"
  },
  "geometry": {
    "type": "Point",
    "coordinates": [
      6.15283,
      48.67333
    ]
  }
}