{
  "type": "Feature",
  "properties": {
    "name": "Village-Neuf",
    "country": "FR",
    "subdivision": "44",
    "timezone": "Europe/Paris"
  },
  "geometry": {
    "type": "Point",
    "coordinates": [
      7.56964,
      47.60682
    ]
  }
}