{
  "type": "Feature",
  "properties": {
    "name": "Waldighofen",
    "country": "FR",
    "subdivision": "44",
    "timezone": "Europe/Paris"
  },
  "geometry": {
    "type": "Point",
    "coordinates": [
      7.31512,
      47.55045
    ]
  }
}