{
  "type": "Feature",
  "properties": {
    "name": "Walscheid",
    "country": "FR",
    "subdivision": "44",
    "timezone": "Europe/Paris"
  },
  "geometry": {
    "type": "Point",
    "coordinates": [
      7.14998,
      48.65308
    ]
  }
}