{
  "type": "Feature",
  "properties": {
    "name": "Warmeriville",
    "country": "FR",
    "subdivision": "44",
    "timezone": "Europe/Paris"
  },
  "geometry": {
    "type": "Point",
    "coordinates": [
      4.21882,
      49.35227
    ]
  }
}