{
  "type": "Feature",
  "properties": {
    "name": "Wettolsheim",
    "country": "FR",
    "subdivision": "44",
    "timezone": "Europe/Paris"
  },
  "geometry": {
    "type": "Point",
    "coordinates": [
      7.29844,
      48.05755
    ]
  }
}