{
  "type": "Feature",
  "properties": {
    "name": "Wisches",
    "country": "FR",
    "subdivision": "44",
    "timezone": "Europe/Paris"
  },
  "geometry": {
    "type": "Point",
    "coordinates": [
      7.26814,
      48.50881
    ]
  }
}