{
  "type": "Feature",
  "properties": {
    "name": "Woippy",
    "country": "FR",
    "subdivision": "44",
    "timezone": "Europe/Paris"
  },
  "geometry": {
    "type": "Point",
    "coordinates": [
      6.15132,
      49.15111
    ]
  }
}