{
  "type": "Feature",
  "properties": {
    "name": "Wolfisheim",
    "country": "FR",
    "subdivision": "44",
    "timezone": "Europe/Paris"
  },
  "geometry": {
    "type": "Point",
    "coordinates": [
      7.66708,
      48.58723
    ]
  }
}