{
  "type": "Feature",
  "properties": {
    "name": "Xertigny",
    "country": "FR",
    "subdivision": "44",
    "timezone": "Europe/Paris"
  },
  "geometry": {
    "type": "Point",
    "coordinates": [
      6.40836,
      48.04394
    ]
  }
}