{
  "type": "Feature",
  "properties": {
    "name": "Ksamil",
    "country": "AL",
    "subdivision": "51",
    "timezone": "Europe/Tirane"
  },
  "geometry": {
    "type": "Point",
    "coordinates": [
      19.99972,
      39.76889
    ]
  }
}