{
  "type": "Feature",
  "properties": {
    "name": "Sabaneta",
    "country": "DO",
    "subdivision": "26",
    "timezone": "America/Santo_Domingo"
  },
  "geometry": {
    "type": "Point",
    "coordinates": [
      -71.34125,
      19.47793
    ]
  }
}