{
  "type": "Feature",
  "properties": {
    "name": "Chmielowice",
    "country": "PL",
    "subdivision": "79",
    "timezone": "Europe/Warsaw"
  },
  "geometry": {
    "type": "Point",
    "coordinates": [
      17.86669,
      50.64957
    ]
  }
}