{
  "type": "Feature",
  "properties": {
    "name": "Dalachów",
    "country": "PL",
    "subdivision": "79",
    "timezone": "Europe/Warsaw"
  },
  "geometry": {
    "type": "Point",
    "coordinates": [
      18.5784,
      51.07732
    ]
  }
}