{
  "type": "Feature",
  "properties": {
    "name": "Dobrzeń Wielki",
    "country": "PL",
    "subdivision": "79",
    "timezone": "Europe/Warsaw"
  },
  "geometry": {
    "type": "Point",
    "coordinates": [
      17.84652,
      50.76844
    ]
  }
}