{
  "type": "Feature",
  "properties": {
    "name": "Gorzów Śląski",
    "country": "PL",
    "subdivision": "79",
    "timezone": "Europe/Warsaw"
  },
  "geometry": {
    "type": "Point",
    "coordinates": [
      18.42304,
      51.02871
    ]
  }
}