{
  "type": "Feature",
  "properties": {
    "name": "Głuchołazy",
    "country": "PL",
    "subdivision": "79",
    "timezone": "Europe/Warsaw"
  },
  "geometry": {
    "type": "Point",
    "coordinates": [
      17.38355,
      50.31505
    ]
  }
}