{
  "type": "Feature",
  "properties": {
    "name": "Kup",
    "country": "PL",
    "subdivision": "79",
    "timezone": "Europe/Warsaw"
  },
  "geometry": {
    "type": "Point",
    "coordinates": [
      17.88351,
      50.80659
    ]
  }
}