{
  "type": "Feature",
  "properties": {
    "name": "Otmuchów",
    "country": "PL",
    "subdivision": "79",
    "timezone": "Europe/Warsaw"
  },
  "geometry": {
    "type": "Point",
    "coordinates": [
      17.17348,
      50.46627
    ]
  }
}