{
  "type": "Feature",
  "properties": {
    "name": "Paczków",
    "country": "PL",
    "subdivision": "79",
    "timezone": "Europe/Warsaw"
  },
  "geometry": {
    "type": "Point",
    "coordinates": [
      17.00658,
      50.46395
    ]
  }
}