{
  "type": "Feature",
  "properties": {
    "name": "Pawłowiczki",
    "country": "PL",
    "subdivision": "79",
    "timezone": "Europe/Warsaw"
  },
  "geometry": {
    "type": "Point",
    "coordinates": [
      18.04865,
      50.2466
    ]
  }
}