{
  "type": "Feature",
  "properties": {
    "name": "Reńska Wieś",
    "country": "PL",
    "subdivision": "79",
    "timezone": "Europe/Warsaw"
  },
  "geometry": {
    "type": "Point",
    "coordinates": [
      18.12607,
      50.31587
    ]
  }
}