{
  "type": "Feature",
  "properties": {
    "name": "Skorogoszcz",
    "country": "PL",
    "subdivision": "79",
    "timezone": "Europe/Warsaw"
  },
  "geometry": {
    "type": "Point",
    "coordinates": [
      17.68198,
      50.75916
    ]
  }
}