{
  "type": "Feature",
  "properties": {
    "name": "Twardawa",
    "country": "PL",
    "subdivision": "79",
    "timezone": "Europe/Warsaw"
  },
  "geometry": {
    "type": "Point",
    "coordinates": [
      17.99097,
      50.34349
    ]
  }
}