{
  "type": "Feature",
  "properties": {
    "name": "Walce",
    "country": "PL",
    "subdivision": "79",
    "timezone": "Europe/Warsaw"
  },
  "geometry": {
    "type": "Point",
    "coordinates": [
      18.00427,
      50.37322
    ]
  }
}