{
  "type": "Feature",
  "properties": {
    "name": "Węgry",
    "country": "PL",
    "subdivision": "79",
    "timezone": "Europe/Warsaw"
  },
  "geometry": {
    "type": "Point",
    "coordinates": [
      18.01741,
      50.74319
    ]
  }
}