{
  "type": "Feature",
  "properties": {
    "name": "Większyce",
    "country": "PL",
    "subdivision": "79",
    "timezone": "Europe/Warsaw"
  },
  "geometry": {
    "type": "Point",
    "coordinates": [
      18.10221,
      50.33659
    ]
  }
}