{
  "type": "Feature",
  "properties": {
    "name": "Ramos",
    "country": "PR",
    "subdivision": "089",
    "timezone": "America/Puerto_Rico"
  },
  "geometry": {
    "type": "Point",
    "coordinates": [
      -65.71266,
      18.33967
    ]
  }
}