{
  "type": "Feature",
  "properties": {
    "name": "Arroyo Naranjo",
    "country": "CU",
    "subdivision": "02",
    "timezone": "America/Havana"
  },
  "geometry": {
    "type": "Point",
    "coordinates": [
      -82.37703,
      23.03811
    ]
  }
}