{
  "type": "Feature",
  "properties": {
    "name": "Diez de Octubre",
    "country": "CU",
    "subdivision": "02",
    "timezone": "America/Havana"
  },
  "geometry": {
    "type": "Point",
    "coordinates": [
      -82.3597,
      23.0881
    ]
  }
}