{
  "type": "Feature",
  "properties": {
    "name": "Byalynichy",
    "country": "BY",
    "subdivision": "06",
    "timezone": "Europe/Minsk"
  },
  "geometry": {
    "type": "Point",
    "coordinates": [
      29.7141,
      53.9994
    ]
  }
}