{
  "type": "Feature",
  "properties": {
    "name": "Cherykaw",
    "country": "BY",
    "subdivision": "06",
    "timezone": "Europe/Minsk"
  },
  "geometry": {
    "type": "Point",
    "coordinates": [
      31.3831,
      53.5689
    ]
  }
}