{
  "type": "Feature",
  "properties": {
    "name": "Kadino",
    "country": "BY",
    "subdivision": "06",
    "timezone": "Europe/Minsk"
  },
  "geometry": {
    "type": "Point",
    "coordinates": [
      30.52028,
      53.88389
    ]
  }
}