{
  "type": "Feature",
  "properties": {
    "name": "Khodasy",
    "country": "BY",
    "subdivision": "06",
    "timezone": "Europe/Minsk"
  },
  "geometry": {
    "type": "Point",
    "coordinates": [
      31.4779,
      53.9266
    ]
  }
}