{
  "type": "Feature",
  "properties": {
    "name": "Krasnapollye",
    "country": "BY",
    "subdivision": "06",
    "timezone": "Europe/Minsk"
  },
  "geometry": {
    "type": "Point",
    "coordinates": [
      31.3999,
      53.3353
    ]
  }
}