{
  "type": "Feature",
  "properties": {
    "name": "Palykavichy Pyershyya",
    "country": "BY",
    "subdivision": "06",
    "timezone": "Europe/Minsk"
  },
  "geometry": {
    "type": "Point",
    "coordinates": [
      30.36,
      53.9854
    ]
  }
}