{
  "type": "Feature",
  "properties": {
    "name": "Posëlok Voskhod",
    "country": "BY",
    "subdivision": "06",
    "timezone": "Europe/Minsk"
  },
  "geometry": {
    "type": "Point",
    "coordinates": [
      30.3497,
      53.7766
    ]
  }
}