{
  "type": "Feature",
  "properties": {
    "name": "Shklow",
    "country": "BY",
    "subdivision": "06",
    "timezone": "Europe/Minsk"
  },
  "geometry": {
    "type": "Point",
    "coordinates": [
      30.2877,
      54.2131
    ]
  }
}