{
  "type": "Feature",
  "properties": {
    "name": "Yalizava",
    "country": "BY",
    "subdivision": "06",
    "timezone": "Europe/Minsk"
  },
  "geometry": {
    "type": "Point",
    "coordinates": [
      29.0048,
      53.3994
    ]
  }
}