{
  "type": "Feature",
  "properties": {
    "name": "Chuka",
    "country": "KE",
    "subdivision": "49",
    "timezone": "Africa/Nairobi"
  },
  "geometry": {
    "type": "Point",
    "coordinates": [
      37.64587,
      -0.33316
    ]
  }
}