{
  "type": "Feature",
  "properties": {
    "name": "Göynük",
    "country": "TR",
    "subdivision": "07",
    "timezone": "Europe/Istanbul"
  },
  "geometry": {
    "type": "Point",
    "coordinates": [
      30.55,
      36.66
    ]
  }
}