{
  "type": "Feature",
  "properties": {
    "name": "Kalkan",
    "country": "TR",
    "subdivision": "07",
    "timezone": "Europe/Istanbul"
  },
  "geometry": {
    "type": "Point",
    "coordinates": [
      29.41369,
      36.2651
    ]
  }
}