{
  "type": "Feature",
  "properties": {
    "name": "Mahmutlar",
    "country": "TR",
    "subdivision": "07",
    "timezone": "Europe/Istanbul"
  },
  "geometry": {
    "type": "Point",
    "coordinates": [
      32.09085,
      36.49463
    ]
  }
}