{
  "type": "Feature",
  "properties": {
    "name": "Side",
    "country": "TR",
    "subdivision": "07",
    "timezone": "Europe/Istanbul"
  },
  "geometry": {
    "type": "Point",
    "coordinates": [
      31.38889,
      36.76667
    ]
  }
}