{
  "type": "Feature",
  "properties": {
    "name": "Ban Houakhoua",
    "country": "LA",
    "subdivision": "22",
    "timezone": "Asia/Vientiane"
  },
  "geometry": {
    "type": "Point",
    "coordinates": [
      100.45401,
      20.2467
    ]
  }
}