{
  "type": "Feature",
  "properties": {
    "name": "Baykan",
    "country": "TR",
    "subdivision": "74",
    "timezone": "Europe/Istanbul"
  },
  "geometry": {
    "type": "Point",
    "coordinates": [
      41.7733,
      38.15754
    ]
  }
}