{
  "type": "Feature",
  "properties": {
    "name": "Doğanköy",
    "country": "TR",
    "subdivision": "74",
    "timezone": "Europe/Istanbul"
  },
  "geometry": {
    "type": "Point",
    "coordinates": [
      42.78929,
      37.76334
    ]
  }
}