{
  "type": "Feature",
  "properties": {
    "name": "Güleçler",
    "country": "TR",
    "subdivision": "74",
    "timezone": "Europe/Istanbul"
  },
  "geometry": {
    "type": "Point",
    "coordinates": [
      42.53861,
      37.95333
    ]
  }
}