{
  "type": "Feature",
  "properties": {
    "name": "Auas",
    "country": "HN",
    "subdivision": "09",
    "timezone": "America/Tegucigalpa"
  },
  "geometry": {
    "type": "Point",
    "coordinates": [
      -84.33333,
      15.48333
    ]
  }
}