{
  "type": "Feature",
  "properties": {
    "name": "Santa Rita Village",
    "country": "GU",
    "subdivision": "SR",
    "timezone": "Pacific/Guam"
  },
  "geometry": {
    "type": "Point",
    "coordinates": [
      144.67226,
      13.38608
    ]
  }
}