{
  "type": "Feature",
  "properties": {
    "name": "Huai Khot",
    "country": "TH",
    "subdivision": "15",
    "timezone": "Asia/Bangkok"
  },
  "geometry": {
    "type": "Point",
    "coordinates": [
      99.61661,
      15.29095
    ]
  }
}