{
  "type": "Feature",
  "properties": {
    "name": "Rollingen",
    "country": "LU",
    "subdivision": "ME",
    "timezone": "Europe/Luxembourg"
  },
  "geometry": {
    "type": "Point",
    "coordinates": [
      6.11444,
      49.74167
    ]
  }
}