{
  "type": "Feature",
  "properties": {
    "name": "Al Hindīyah",
    "country": "IQ",
    "subdivision": "12",
    "timezone": "Asia/Baghdad"
  },
  "geometry": {
    "type": "Point",
    "coordinates": [
      44.22765,
      32.54671
    ]
  }
}