{
  "type": "Feature",
  "properties": {
    "name": "Chuhuiv",
    "country": "UA",
    "subdivision": "07",
    "timezone": "Europe/Kiev"
  },
  "geometry": {
    "type": "Point",
    "coordinates": [
      36.68803,
      49.83588
    ]
  }
}