{
  "type": "Feature",
  "properties": {
    "name": "Eskhar",
    "country": "UA",
    "subdivision": "07",
    "timezone": "Europe/Kiev"
  },
  "geometry": {
    "type": "Point",
    "coordinates": [
      36.59047,
      49.79614
    ]
  }
}