{
  "type": "Feature",
  "properties": {
    "name": "Kolomak",
    "country": "UA",
    "subdivision": "07",
    "timezone": "Europe/Kiev"
  },
  "geometry": {
    "type": "Point",
    "coordinates": [
      35.30441,
      49.83987
    ]
  }
}