{
  "type": "Feature",
  "properties": {
    "name": "Lyman",
    "country": "UA",
    "subdivision": "07",
    "timezone": "Europe/Kiev"
  },
  "geometry": {
    "type": "Point",
    "coordinates": [
      36.4703,
      49.59769
    ]
  }
}