{
  "type": "Feature",
  "properties": {
    "name": "Slatyne",
    "country": "UA",
    "subdivision": "07",
    "timezone": "Europe/Kiev"
  },
  "geometry": {
    "type": "Point",
    "coordinates": [
      36.15376,
      50.21041
    ]
  }
}