{
  "type": "Feature",
  "properties": {
    "name": "Vasyshcheve",
    "country": "UA",
    "subdivision": "07",
    "timezone": "Europe/Kiev"
  },
  "geometry": {
    "type": "Point",
    "coordinates": [
      36.32691,
      49.82852
    ]
  }
}