{
  "type": "Feature",
  "properties": {
    "name": "Andover",
    "country": "US",
    "subdivision": "MN",
    "timezone": "America/Chicago"
  },
  "geometry": {
    "type": "Point",
    "coordinates": [
      -93.29134,
      45.2333
    ]
  }
}