{
  "type": "Feature",
  "properties": {
    "name": "Bagley",
    "country": "US",
    "subdivision": "MN",
    "timezone": "America/Chicago"
  },
  "geometry": {
    "type": "Point",
    "coordinates": [
      -95.39835,
      47.52162
    ]
  }
}