{
  "type": "Feature",
  "properties": {
    "name": "Baudette",
    "country": "US",
    "subdivision": "MN",
    "timezone": "America/Chicago"
  },
  "geometry": {
    "type": "Point",
    "coordinates": [
      -94.59993,
      48.71247
    ]
  }
}