{
  "type": "Feature",
  "properties": {
    "name": "Becker",
    "country": "US",
    "subdivision": "MN",
    "timezone": "America/Chicago"
  },
  "geometry": {
    "type": "Point",
    "coordinates": [
      -93.87692,
      45.3933
    ]
  }
}