{
  "type": "Feature",
  "properties": {
    "name": "Bloomington",
    "country": "US",
    "subdivision": "MN",
    "timezone": "America/Chicago"
  },
  "geometry": {
    "type": "Point",
    "coordinates": [
      -93.29828,
      44.8408
    ]
  }
}