{
  "type": "Feature",
  "properties": {
    "name": "Braham",
    "country": "US",
    "subdivision": "MN",
    "timezone": "America/Chicago"
  },
  "geometry": {
    "type": "Point",
    "coordinates": [
      -93.17078,
      45.72274
    ]
  }
}