{
  "type": "Feature",
  "properties": {
    "name": "Branch",
    "country": "US",
    "subdivision": "MN",
    "timezone": "America/Chicago"
  },
  "geometry": {
    "type": "Point",
    "coordinates": [
      -92.96188,
      45.48524
    ]
  }
}