{
  "type": "Feature",
  "properties": {
    "name": "Caledonia",
    "country": "US",
    "subdivision": "MN",
    "timezone": "America/Chicago"
  },
  "geometry": {
    "type": "Point",
    "coordinates": [
      -91.49681,
      43.63469
    ]
  }
}