{
  "type": "Feature",
  "properties": {
    "name": "Carlton",
    "country": "US",
    "subdivision": "MN",
    "timezone": "America/Chicago"
  },
  "geometry": {
    "type": "Point",
    "coordinates": [
      -92.42491,
      46.66383
    ]
  }
}