{
  "type": "Feature",
  "properties": {
    "name": "Chisago City",
    "country": "US",
    "subdivision": "MN",
    "timezone": "America/Chicago"
  },
  "geometry": {
    "type": "Point",
    "coordinates": [
      -92.88994,
      45.37358
    ]
  }
}