{
  "type": "Feature",
  "properties": {
    "name": "Dodge Center",
    "country": "US",
    "subdivision": "MN",
    "timezone": "America/Chicago"
  },
  "geometry": {
    "type": "Point",
    "coordinates": [
      -92.85464,
      44.02802
    ]
  }
}