{
  "type": "Feature",
  "properties": {
    "name": "Dundas",
    "country": "US",
    "subdivision": "MN",
    "timezone": "America/Chicago"
  },
  "geometry": {
    "type": "Point",
    "coordinates": [
      -93.20188,
      44.42941
    ]
  }
}