{
  "type": "Feature",
  "properties": {
    "name": "Edgerton",
    "country": "US",
    "subdivision": "MN",
    "timezone": "America/Chicago"
  },
  "geometry": {
    "type": "Point",
    "coordinates": [
      -96.12864,
      43.87247
    ]
  }
}