{
  "type": "Feature",
  "properties": {
    "name": "Edina",
    "country": "US",
    "subdivision": "MN",
    "timezone": "America/Chicago"
  },
  "geometry": {
    "type": "Point",
    "coordinates": [
      -93.34995,
      44.88969
    ]
  }
}