{
  "type": "Feature",
  "properties": {
    "name": "Elbow Lake",
    "country": "US",
    "subdivision": "MN",
    "timezone": "America/Chicago"
  },
  "geometry": {
    "type": "Point",
    "coordinates": [
      -95.97672,
      45.99413
    ]
  }
}