{
  "type": "Feature",
  "properties": {
    "name": "Ely",
    "country": "US",
    "subdivision": "MN",
    "timezone": "America/Chicago"
  },
  "geometry": {
    "type": "Point",
    "coordinates": [
      -91.86709,
      47.90324
    ]
  }
}