{
  "type": "Feature",
  "properties": {
    "name": "Fosston",
    "country": "US",
    "subdivision": "MN",
    "timezone": "America/Chicago"
  },
  "geometry": {
    "type": "Point",
    "coordinates": [
      -95.75141,
      47.57635
    ]
  }
}