{
  "type": "Feature",
  "properties": {
    "name": "Glyndon",
    "country": "US",
    "subdivision": "MN",
    "timezone": "America/Chicago"
  },
  "geometry": {
    "type": "Point",
    "coordinates": [
      -96.57896,
      46.87524
    ]
  }
}