{
  "type": "Feature",
  "properties": {
    "name": "Goodhue",
    "country": "US",
    "subdivision": "MN",
    "timezone": "America/Chicago"
  },
  "geometry": {
    "type": "Point",
    "coordinates": [
      -92.6238,
      44.40052
    ]
  }
}