{
  "type": "Feature",
  "properties": {
    "name": "Grand Meadow",
    "country": "US",
    "subdivision": "MN",
    "timezone": "America/Chicago"
  },
  "geometry": {
    "type": "Point",
    "coordinates": [
      -92.57212,
      43.7058
    ]
  }
}