{
  "type": "Feature",
  "properties": {
    "name": "Hibbing",
    "country": "US",
    "subdivision": "MN",
    "timezone": "America/Chicago"
  },
  "geometry": {
    "type": "Point",
    "coordinates": [
      -92.93769,
      47.42715
    ]
  }
}