{
  "type": "Feature",
  "properties": {
    "name": "Hopkins",
    "country": "US",
    "subdivision": "MN",
    "timezone": "America/Chicago"
  },
  "geometry": {
    "type": "Point",
    "coordinates": [
      -93.46273,
      44.92496
    ]
  }
}