{
  "type": "Feature",
  "properties": {
    "name": "Hoyt Lakes",
    "country": "US",
    "subdivision": "MN",
    "timezone": "America/Chicago"
  },
  "geometry": {
    "type": "Point",
    "coordinates": [
      -92.13851,
      47.51965
    ]
  }
}