{
  "type": "Feature",
  "properties": {
    "name": "Independence",
    "country": "US",
    "subdivision": "MN",
    "timezone": "America/Chicago"
  },
  "geometry": {
    "type": "Point",
    "coordinates": [
      -93.70746,
      45.02524
    ]
  }
}