{
  "type": "Feature",
  "properties": {
    "name": "International Falls",
    "country": "US",
    "subdivision": "MN",
    "timezone": "America/Chicago"
  },
  "geometry": {
    "type": "Point",
    "coordinates": [
      -93.41098,
      48.60105
    ]
  }
}