{
  "type": "Feature",
  "properties": {
    "name": "La Crescent",
    "country": "US",
    "subdivision": "MN",
    "timezone": "America/Chicago"
  },
  "geometry": {
    "type": "Point",
    "coordinates": [
      -91.30403,
      43.82802
    ]
  }
}