{
  "type": "Feature",
  "properties": {
    "name": "Lake Shore",
    "country": "US",
    "subdivision": "MN",
    "timezone": "America/Chicago"
  },
  "geometry": {
    "type": "Point",
    "coordinates": [
      -94.36056,
      46.48552
    ]
  }
}