{
  "type": "Feature",
  "properties": {
    "name": "Lauderdale",
    "country": "US",
    "subdivision": "MN",
    "timezone": "America/Chicago"
  },
  "geometry": {
    "type": "Point",
    "coordinates": [
      -93.20578,
      44.99858
    ]
  }
}