{
  "type": "Feature",
  "properties": {
    "name": "Litchfield",
    "country": "US",
    "subdivision": "MN",
    "timezone": "America/Chicago"
  },
  "geometry": {
    "type": "Point",
    "coordinates": [
      -94.52805,
      45.12718
    ]
  }
}