{
  "type": "Feature",
  "properties": {
    "name": "Long Prairie",
    "country": "US",
    "subdivision": "MN",
    "timezone": "America/Chicago"
  },
  "geometry": {
    "type": "Point",
    "coordinates": [
      -94.86558,
      45.97469
    ]
  }
}