{
  "type": "Feature",
  "properties": {
    "name": "Lonsdale",
    "country": "US",
    "subdivision": "MN",
    "timezone": "America/Chicago"
  },
  "geometry": {
    "type": "Point",
    "coordinates": [
      -93.42856,
      44.48024
    ]
  }
}