{
  "type": "Feature",
  "properties": {
    "name": "Medina",
    "country": "US",
    "subdivision": "MN",
    "timezone": "America/Chicago"
  },
  "geometry": {
    "type": "Point",
    "coordinates": [
      -93.58246,
      45.03524
    ]
  }
}