{
  "type": "Feature",
  "properties": {
    "name": "Melrose",
    "country": "US",
    "subdivision": "MN",
    "timezone": "America/Chicago"
  },
  "geometry": {
    "type": "Point",
    "coordinates": [
      -94.80752,
      45.67469
    ]
  }
}