{
  "type": "Feature",
  "properties": {
    "name": "Minnetonka Mills",
    "country": "US",
    "subdivision": "MN",
    "timezone": "America/Chicago"
  },
  "geometry": {
    "type": "Point",
    "coordinates": [
      -93.4419,
      44.94107
    ]
  }
}