{
  "type": "Feature",
  "properties": {
    "name": "New London",
    "country": "US",
    "subdivision": "MN",
    "timezone": "America/Chicago"
  },
  "geometry": {
    "type": "Point",
    "coordinates": [
      -94.94418,
      45.30108
    ]
  }
}