{
  "type": "Feature",
  "properties": {
    "name": "New Hope",
    "country": "US",
    "subdivision": "MN",
    "timezone": "America/Chicago"
  },
  "geometry": {
    "type": "Point",
    "coordinates": [
      -93.38662,
      45.03802
    ]
  }
}