{
  "type": "Feature",
  "properties": {
    "name": "Nowthen",
    "country": "US",
    "subdivision": "MN",
    "timezone": "America/Chicago"
  },
  "geometry": {
    "type": "Point",
    "coordinates": [
      -93.47023,
      45.32802
    ]
  }
}