{
  "type": "Feature",
  "properties": {
    "name": "Owatonna",
    "country": "US",
    "subdivision": "MN",
    "timezone": "America/Chicago"
  },
  "geometry": {
    "type": "Point",
    "coordinates": [
      -93.22604,
      44.08385
    ]
  }
}