{
  "type": "Feature",
  "properties": {
    "name": "Rock Creek",
    "country": "US",
    "subdivision": "MN",
    "timezone": "America/Chicago"
  },
  "geometry": {
    "type": "Point",
    "coordinates": [
      -92.96243,
      45.75746
    ]
  }
}