{
  "type": "Feature",
  "properties": {
    "name": "Saint Paul Park",
    "country": "US",
    "subdivision": "MN",
    "timezone": "America/Chicago"
  },
  "geometry": {
    "type": "Point",
    "coordinates": [
      -92.99132,
      44.84219
    ]
  }
}