{
  "type": "Feature",
  "properties": {
    "name": "Sleepy Eye",
    "country": "US",
    "subdivision": "MN",
    "timezone": "America/Chicago"
  },
  "geometry": {
    "type": "Point",
    "coordinates": [
      -94.72415,
      44.29718
    ]
  }
}