{
  "type": "Feature",
  "properties": {
    "name": "Spring Park",
    "country": "US",
    "subdivision": "MN",
    "timezone": "America/Chicago"
  },
  "geometry": {
    "type": "Point",
    "coordinates": [
      -93.63218,
      44.93524
    ]
  }
}