{
  "type": "Feature",
  "properties": {
    "name": "Stewartville",
    "country": "US",
    "subdivision": "MN",
    "timezone": "America/Chicago"
  },
  "geometry": {
    "type": "Point",
    "coordinates": [
      -92.48851,
      43.85552
    ]
  }
}