{
  "type": "Feature",
  "properties": {
    "name": "Two Harbors",
    "country": "US",
    "subdivision": "MN",
    "timezone": "America/Chicago"
  },
  "geometry": {
    "type": "Point",
    "coordinates": [
      -91.67073,
      47.02271
    ]
  }
}