{
  "type": "Feature",
  "properties": {
    "name": "Waconia",
    "country": "US",
    "subdivision": "MN",
    "timezone": "America/Chicago"
  },
  "geometry": {
    "type": "Point",
    "coordinates": [
      -93.78691,
      44.8508
    ]
  }
}