{
  "type": "Feature",
  "properties": {
    "name": "Wadena",
    "country": "US",
    "subdivision": "MN",
    "timezone": "America/Chicago"
  },
  "geometry": {
    "type": "Point",
    "coordinates": [
      -95.13614,
      46.44246
    ]
  }
}