{
  "type": "Feature",
  "properties": {
    "name": "Willmar",
    "country": "US",
    "subdivision": "MN",
    "timezone": "America/Chicago"
  },
  "geometry": {
    "type": "Point",
    "coordinates": [
      -95.04334,
      45.12191
    ]
  }
}