{
  "type": "Feature",
  "properties": {
    "name": "Winthrop",
    "country": "US",
    "subdivision": "MN",
    "timezone": "America/Chicago"
  },
  "geometry": {
    "type": "Point",
    "coordinates": [
      -94.36637,
      44.54302
    ]
  }
}