{
  "type": "Feature",
  "properties": {
    "name": "Barinitas",
    "country": "VE",
    "subdivision": "05",
    "timezone": "America/Caracas"
  },
  "geometry": {
    "type": "Point",
    "coordinates": [
      -70.41199,
      8.76171
    ]
  }
}