{
  "type": "Feature",
  "properties": {
    "name": "Huanta",
    "country": "PE",
    "subdivision": "05",
    "timezone": "America/Lima"
  },
  "geometry": {
    "type": "Point",
    "coordinates": [
      -74.25,
      -12.93333
    ]
  }
}