{
  "type": "Feature",
  "properties": {
    "name": "Caucagüito",
    "country": "VE",
    "subdivision": "15",
    "timezone": "America/Caracas"
  },
  "geometry": {
    "type": "Point",
    "coordinates": [
      -66.73799,
      10.48666
    ]
  }
}