{
  "type": "Feature",
  "properties": {
    "name": "Chacao",
    "country": "VE",
    "subdivision": "15",
    "timezone": "America/Caracas"
  },
  "geometry": {
    "type": "Point",
    "coordinates": [
      -66.85367,
      10.49581
    ]
  }
}