{
  "type": "Feature",
  "properties": {
    "name": "El Cafetal",
    "country": "VE",
    "subdivision": "15",
    "timezone": "America/Caracas"
  },
  "geometry": {
    "type": "Point",
    "coordinates": [
      -66.82951,
      10.46541
    ]
  }
}