{
  "type": "Feature",
  "properties": {
    "name": "Ocumare del Tuy",
    "country": "VE",
    "subdivision": "15",
    "timezone": "America/Caracas"
  },
  "geometry": {
    "type": "Point",
    "coordinates": [
      -66.77513,
      10.1182
    ]
  }
}