{
  "type": "Feature",
  "properties": {
    "name": "Matamba",
    "country": "TZ",
    "subdivision": "30",
    "timezone": "Africa/Dar_es_Salaam"
  },
  "geometry": {
    "type": "Point",
    "coordinates": [
      33.96667,
      -8.98333
    ]
  }
}