{
  "type": "Feature",
  "properties": {
    "name": "Chivana",
    "country": "HN",
    "subdivision": "06",
    "timezone": "America/Tegucigalpa"
  },
  "geometry": {
    "type": "Point",
    "coordinates": [
      -87.98333,
      15.75
    ]
  }
}