{
  "type": "Feature",
  "properties": {
    "name": "Choloma",
    "country": "HN",
    "subdivision": "06",
    "timezone": "America/Tegucigalpa"
  },
  "geometry": {
    "type": "Point",
    "coordinates": [
      -87.95302,
      15.61444
    ]
  }
}