{
  "type": "Feature",
  "properties": {
    "name": "El Llano",
    "country": "HN",
    "subdivision": "06",
    "timezone": "America/Tegucigalpa"
  },
  "geometry": {
    "type": "Point",
    "coordinates": [
      -87.88333,
      15.15
    ]
  }
}