{
  "type": "Feature",
  "properties": {
    "name": "El Rancho",
    "country": "HN",
    "subdivision": "06",
    "timezone": "America/Tegucigalpa"
  },
  "geometry": {
    "type": "Point",
    "coordinates": [
      -87.95,
      15.66667
    ]
  }
}