{
  "type": "Feature",
  "properties": {
    "name": "DharÄn",
    "country": "NP",
    "subdivision": "1",
    "timezone": "Asia/Kathmandu"
  },
  "geometry": {
    "type": "Point",
    "coordinates": [
      87.27972,
      26.81436
    ]
  }
}