{
  "type": "Feature",
  "properties": {
    "name": "Triyuga",
    "country": "NP",
    "subdivision": "1",
    "timezone": "Asia/Kathmandu"
  },
  "geometry": {
    "type": "Point",
    "coordinates": [
      86.699,
      26.7919
    ]
  }
}