{
  "type": "Feature",
  "properties": {
    "name": "Paragsha- San Andres - Jose Carlos Mariategui",
    "country": "PE",
    "subdivision": "19",
    "timezone": "America/Lima"
  },
  "geometry": {
    "type": "Point",
    "coordinates": [
      -76.27098,
      -10.67147
    ]
  }
}