{
  "type": "Feature",
  "properties": {
    "name": "Yanahuanca",
    "country": "PE",
    "subdivision": "19",
    "timezone": "America/Lima"
  },
  "geometry": {
    "type": "Point",
    "coordinates": [
      -76.49861,
      -10.51667
    ]
  }
}