{
  "type": "Feature",
  "properties": {
    "name": "Longyearbyen",
    "country": "SJ",
    "subdivision": "21",
    "timezone": "Arctic/Longyearbyen"
  },
  "geometry": {
    "type": "Point",
    "coordinates": [
      15.64689,
      78.22334
    ]
  }
}