{
  "type": "Feature",
  "properties": {
    "name": "Buctzotz",
    "country": "MX",
    "subdivision": "31",
    "timezone": "America/Merida"
  },
  "geometry": {
    "type": "Point",
    "coordinates": [
      -88.79271,
      21.20303
    ]
  }
}