{
  "type": "Feature",
  "properties": {
    "name": "Celestún",
    "country": "MX",
    "subdivision": "31",
    "timezone": "America/Merida"
  },
  "geometry": {
    "type": "Point",
    "coordinates": [
      -90.39902,
      20.85973
    ]
  }
}