{
  "type": "Feature",
  "properties": {
    "name": "Chapab",
    "country": "MX",
    "subdivision": "31",
    "timezone": "America/Merida"
  },
  "geometry": {
    "type": "Point",
    "coordinates": [
      -89.4569,
      20.45911
    ]
  }
}