{
  "type": "Feature",
  "properties": {
    "name": "Chelem",
    "country": "MX",
    "subdivision": "31",
    "timezone": "America/Merida"
  },
  "geometry": {
    "type": "Point",
    "coordinates": [
      -89.74006,
      21.26967
    ]
  }
}