{
  "type": "Feature",
  "properties": {
    "name": "Chichimila",
    "country": "MX",
    "subdivision": "31",
    "timezone": "America/Merida"
  },
  "geometry": {
    "type": "Point",
    "coordinates": [
      -88.21689,
      20.63176
    ]
  }
}