{
  "type": "Feature",
  "properties": {
    "name": "Chochola",
    "country": "MX",
    "subdivision": "31",
    "timezone": "America/Merida"
  },
  "geometry": {
    "type": "Point",
    "coordinates": [
      -89.83041,
      20.75087
    ]
  }
}