{
  "type": "Feature",
  "properties": {
    "name": "Cholul Cantón",
    "country": "MX",
    "subdivision": "31",
    "timezone": "America/Merida"
  },
  "geometry": {
    "type": "Point",
    "coordinates": [
      -89.29147,
      21.01078
    ]
  }
}