{
  "type": "Feature",
  "properties": {
    "name": "Cuch Holoch",
    "country": "MX",
    "subdivision": "31",
    "timezone": "America/Merida"
  },
  "geometry": {
    "type": "Point",
    "coordinates": [
      -90.09694,
      20.4345
    ]
  }
}