{
  "type": "Feature",
  "properties": {
    "name": "Dzidzantun",
    "country": "MX",
    "subdivision": "31",
    "timezone": "America/Merida"
  },
  "geometry": {
    "type": "Point",
    "coordinates": [
      -89.04205,
      21.24898
    ]
  }
}