{
  "type": "Feature",
  "properties": {
    "name": "Dzilam González",
    "country": "MX",
    "subdivision": "31",
    "timezone": "America/Merida"
  },
  "geometry": {
    "type": "Point",
    "coordinates": [
      -88.92957,
      21.28098
    ]
  }
}