{
  "type": "Feature",
  "properties": {
    "name": "Dzoncauich",
    "country": "MX",
    "subdivision": "31",
    "timezone": "America/Merida"
  },
  "geometry": {
    "type": "Point",
    "coordinates": [
      -88.88975,
      21.12938
    ]
  }
}