{
  "type": "Feature",
  "properties": {
    "name": "Huhi",
    "country": "MX",
    "subdivision": "31",
    "timezone": "America/Merida"
  },
  "geometry": {
    "type": "Point",
    "coordinates": [
      -89.16072,
      20.72603
    ]
  }
}