{
  "type": "Feature",
  "properties": {
    "name": "Ixil",
    "country": "MX",
    "subdivision": "31",
    "timezone": "America/Merida"
  },
  "geometry": {
    "type": "Point",
    "coordinates": [
      -89.48182,
      21.15235
    ]
  }
}