{
  "type": "Feature",
  "properties": {
    "name": "Kochol",
    "country": "MX",
    "subdivision": "31",
    "timezone": "America/Merida"
  },
  "geometry": {
    "type": "Point",
    "coordinates": [
      -90.15906,
      20.61867
    ]
  }
}