{
  "type": "Feature",
  "properties": {
    "name": "Pencuyut",
    "country": "MX",
    "subdivision": "31",
    "timezone": "America/Merida"
  },
  "geometry": {
    "type": "Point",
    "coordinates": [
      -89.28947,
      20.29408
    ]
  }
}