{
  "type": "Feature",
  "properties": {
    "name": "Peto",
    "country": "MX",
    "subdivision": "31",
    "timezone": "America/Merida"
  },
  "geometry": {
    "type": "Point",
    "coordinates": [
      -88.92282,
      20.12776
    ]
  }
}