{
  "type": "Feature",
  "properties": {
    "name": "Popolnah",
    "country": "MX",
    "subdivision": "31",
    "timezone": "America/Merida"
  },
  "geometry": {
    "type": "Point",
    "coordinates": [
      -87.56281,
      20.9935
    ]
  }
}