{
  "type": "Feature",
  "properties": {
    "name": "Sierra Papacal",
    "country": "MX",
    "subdivision": "31",
    "timezone": "America/Merida"
  },
  "geometry": {
    "type": "Point",
    "coordinates": [
      -89.73018,
      21.12522
    ]
  }
}