{
  "type": "Feature",
  "properties": {
    "name": "Tekal de Venegas",
    "country": "MX",
    "subdivision": "31",
    "timezone": "America/Merida"
  },
  "geometry": {
    "type": "Point",
    "coordinates": [
      -88.94658,
      21.01487
    ]
  }
}