{
  "type": "Feature",
  "properties": {
    "name": "Tekanto",
    "country": "MX",
    "subdivision": "31",
    "timezone": "America/Merida"
  },
  "geometry": {
    "type": "Point",
    "coordinates": [
      -89.10723,
      21.00968
    ]
  }
}