{
  "type": "Feature",
  "properties": {
    "name": "Telchac Puerto",
    "country": "MX",
    "subdivision": "31",
    "timezone": "America/Merida"
  },
  "geometry": {
    "type": "Point",
    "coordinates": [
      -89.26333,
      21.34121
    ]
  }
}