{
  "type": "Feature",
  "properties": {
    "name": "Tunkas",
    "country": "MX",
    "subdivision": "31",
    "timezone": "America/Merida"
  },
  "geometry": {
    "type": "Point",
    "coordinates": [
      -88.75171,
      20.90294
    ]
  }
}