{
  "type": "Feature",
  "properties": {
    "name": "Tzucacab",
    "country": "MX",
    "subdivision": "31",
    "timezone": "America/Merida"
  },
  "geometry": {
    "type": "Point",
    "coordinates": [
      -89.05022,
      20.07237
    ]
  }
}