{
  "type": "Feature",
  "properties": {
    "name": "Babócsa",
    "country": "HU",
    "subdivision": "17",
    "timezone": "Europe/Budapest"
  },
  "geometry": {
    "type": "Point",
    "coordinates": [
      17.34332,
      46.04155
    ]
  }
}