{
  "type": "Feature",
  "properties": {
    "name": "Böhönye",
    "country": "HU",
    "subdivision": "17",
    "timezone": "Europe/Budapest"
  },
  "geometry": {
    "type": "Point",
    "coordinates": [
      17.38037,
      46.41345
    ]
  }
}