{
  "type": "Feature",
  "properties": {
    "name": "Segesd",
    "country": "HU",
    "subdivision": "17",
    "timezone": "Europe/Budapest"
  },
  "geometry": {
    "type": "Point",
    "coordinates": [
      17.35132,
      46.34142
    ]
  }
}