{
  "type": "Feature",
  "properties": {
    "name": "Jan Kempdorp",
    "country": "ZA",
    "subdivision": "10",
    "timezone": "Africa/Johannesburg"
  },
  "geometry": {
    "type": "Point",
    "coordinates": [
      24.83051,
      -27.92246
    ]
  }
}