{
  "type": "Feature",
  "properties": {
    "name": "Orkney",
    "country": "ZA",
    "subdivision": "10",
    "timezone": "Africa/Johannesburg"
  },
  "geometry": {
    "type": "Point",
    "coordinates": [
      26.67272,
      -26.98023
    ]
  }
}