{
  "type": "Feature",
  "properties": {
    "name": "Schweizer-Reneke",
    "country": "ZA",
    "subdivision": "10",
    "timezone": "Africa/Johannesburg"
  },
  "geometry": {
    "type": "Point",
    "coordinates": [
      25.32931,
      -27.18871
    ]
  }
}