{
  "type": "Feature",
  "properties": {
    "name": "Fernley",
    "country": "US",
    "subdivision": "NV",
    "timezone": "America/Los_Angeles"
  },
  "geometry": {
    "type": "Point",
    "coordinates": [
      -119.25183,
      39.60797
    ]
  }
}