{
  "type": "Feature",
  "properties": {
    "name": "Laughlin",
    "country": "US",
    "subdivision": "NV",
    "timezone": "America/Los_Angeles"
  },
  "geometry": {
    "type": "Point",
    "coordinates": [
      -114.57302,
      35.16778
    ]
  }
}