{
  "type": "Feature",
  "properties": {
    "name": "Minden",
    "country": "US",
    "subdivision": "NV",
    "timezone": "America/Los_Angeles"
  },
  "geometry": {
    "type": "Point",
    "coordinates": [
      -119.76573,
      38.95407
    ]
  }
}