{
  "type": "Feature",
  "properties": {
    "name": "Moapa Valley",
    "country": "US",
    "subdivision": "NV",
    "timezone": "America/Los_Angeles"
  },
  "geometry": {
    "type": "Point",
    "coordinates": [
      -114.47026,
      36.58053
    ]
  }
}