{
  "type": "Feature",
  "properties": {
    "name": "Nellis Air Force Base",
    "country": "US",
    "subdivision": "NV",
    "timezone": "America/Los_Angeles"
  },
  "geometry": {
    "type": "Point",
    "coordinates": [
      -115.05721,
      36.24607
    ]
  }
}