{
  "type": "Feature",
  "properties": {
    "name": "Sun Valley",
    "country": "US",
    "subdivision": "NV",
    "timezone": "America/Los_Angeles"
  },
  "geometry": {
    "type": "Point",
    "coordinates": [
      -119.77602,
      39.5963
    ]
  }
}