{
  "type": "Feature",
  "properties": {
    "name": "Sunrise Manor",
    "country": "US",
    "subdivision": "NV",
    "timezone": "America/Los_Angeles"
  },
  "geometry": {
    "type": "Point",
    "coordinates": [
      -115.07306,
      36.21108
    ]
  }
}