{
  "type": "Feature",
  "properties": {
    "name": "West Wendover",
    "country": "US",
    "subdivision": "NV",
    "timezone": "America/Los_Angeles"
  },
  "geometry": {
    "type": "Point",
    "coordinates": [
      -114.07335,
      40.7391
    ]
  }
}