{
  "type": "Feature",
  "properties": {
    "name": "Kuraymah",
    "country": "SD",
    "subdivision": "43",
    "timezone": "Africa/Khartoum"
  },
  "geometry": {
    "type": "Point",
    "coordinates": [
      31.85,
      18.55
    ]
  }
}