{
  "type": "Feature",
  "properties": {
    "name": "Alotau",
    "country": "PG",
    "subdivision": "03",
    "timezone": "Pacific/Port_Moresby"
  },
  "geometry": {
    "type": "Point",
    "coordinates": [
      150.45742,
      -10.31509
    ]
  }
}