{
  "type": "Feature",
  "properties": {
    "name": "Dabat",
    "country": "ET",
    "subdivision": "46",
    "timezone": "Africa/Addis_Ababa"
  },
  "geometry": {
    "type": "Point",
    "coordinates": [
      37.765,
      12.98417
    ]
  }
}