{
  "type": "Feature",
  "properties": {
    "name": "Desē",
    "country": "ET",
    "subdivision": "46",
    "timezone": "Africa/Addis_Ababa"
  },
  "geometry": {
    "type": "Point",
    "coordinates": [
      39.63333,
      11.13333
    ]
  }
}