{
  "type": "Feature",
  "properties": {
    "name": "Chikwawa",
    "country": "MW",
    "subdivision": "S",
    "timezone": "Africa/Blantyre"
  },
  "geometry": {
    "type": "Point",
    "coordinates": [
      34.80091,
      -16.03352
    ]
  }
}