{
  "type": "Feature",
  "properties": {
    "name": "Luchenza",
    "country": "MW",
    "subdivision": "S",
    "timezone": "Africa/Blantyre"
  },
  "geometry": {
    "type": "Point",
    "coordinates": [
      35.30947,
      -16.00693
    ]
  }
}