{
  "type": "Feature",
  "properties": {
    "name": "Nsanje",
    "country": "MW",
    "subdivision": "S",
    "timezone": "Africa/Blantyre"
  },
  "geometry": {
    "type": "Point",
    "coordinates": [
      35.26199,
      -16.91995
    ]
  }
}