{
  "type": "Feature",
  "properties": {
    "name": "Jermuk",
    "country": "AM",
    "subdivision": "10",
    "timezone": "Asia/Yerevan"
  },
  "geometry": {
    "type": "Point",
    "coordinates": [
      45.66949,
      39.84168
    ]
  }
}