{
  "type": "Feature",
  "properties": {
    "name": "Korsakovo",
    "country": "RU",
    "subdivision": "56",
    "timezone": "Europe/Moscow"
  },
  "geometry": {
    "type": "Point",
    "coordinates": [
      37.35689,
      53.26767
    ]
  }
}