{
  "type": "Feature",
  "properties": {
    "name": "Naryshkino",
    "country": "RU",
    "subdivision": "56",
    "timezone": "Europe/Moscow"
  },
  "geometry": {
    "type": "Point",
    "coordinates": [
      35.72677,
      52.96778
    ]
  }
}