{
  "type": "Feature",
  "properties": {
    "name": "Zalegoshch’",
    "country": "RU",
    "subdivision": "56",
    "timezone": "Europe/Moscow"
  },
  "geometry": {
    "type": "Point",
    "coordinates": [
      36.89093,
      52.8989
    ]
  }
}