{
  "type": "Feature",
  "properties": {
    "name": "Mahdia",
    "country": "GY",
    "subdivision": "17",
    "timezone": "America/Guyana"
  },
  "geometry": {
    "type": "Point",
    "coordinates": [
      -59.15,
      5.26667
    ]
  }
}