{
  "type": "Feature",
  "properties": {
    "name": "Avarua",
    "country": "CK",
    "subdivision": "11695425",
    "timezone": "Pacific/Rarotonga"
  },
  "geometry": {
    "type": "Point",
    "coordinates": [
      -159.77545,
      -21.2075
    ]
  }
}