{
  "type": "Feature",
  "properties": {
    "name": "Büyük Kardeş",
    "country": "TR",
    "subdivision": "72",
    "timezone": "Europe/Istanbul"
  },
  "geometry": {
    "type": "Point",
    "coordinates": [
      41.03364,
      37.27304
    ]
  }
}