{
  "type": "Feature",
  "properties": {
    "name": "Karalar",
    "country": "TR",
    "subdivision": "72",
    "timezone": "Europe/Istanbul"
  },
  "geometry": {
    "type": "Point",
    "coordinates": [
      41.67582,
      37.30073
    ]
  }
}