{
  "type": "Feature",
  "properties": {
    "name": "Nusaybin",
    "country": "TR",
    "subdivision": "72",
    "timezone": "Europe/Istanbul"
  },
  "geometry": {
    "type": "Point",
    "coordinates": [
      41.21465,
      37.07028
    ]
  }
}