{
  "type": "Feature",
  "properties": {
    "name": "Mafraq",
    "country": "JO",
    "subdivision": "15",
    "timezone": "Asia/Amman"
  },
  "geometry": {
    "type": "Point",
    "coordinates": [
      36.20804,
      32.34289
    ]
  }
}