{
  "type": "Feature",
  "properties": {
    "name": "Crnilište",
    "country": "MK",
    "subdivision": "28",
    "timezone": "Europe/Skopje"
  },
  "geometry": {
    "type": "Point",
    "coordinates": [
      21.41416,
      41.53025
    ]
  }
}