{
  "type": "Feature",
  "properties": {
    "name": "Sing Buri",
    "country": "TH",
    "subdivision": "33",
    "timezone": "Asia/Bangkok"
  },
  "geometry": {
    "type": "Point",
    "coordinates": [
      100.40464,
      14.88786
    ]
  }
}