{
  "type": "Feature",
  "properties": {
    "name": "Isahaya",
    "country": "JP",
    "subdivision": "27",
    "timezone": "Asia/Tokyo"
  },
  "geometry": {
    "type": "Point",
    "coordinates": [
      130.04306,
      32.84111
    ]
  }
}