{
  "type": "Feature",
  "properties": {
    "name": "Togitsu",
    "country": "JP",
    "subdivision": "27",
    "timezone": "Asia/Tokyo"
  },
  "geometry": {
    "type": "Point",
    "coordinates": [
      129.85,
      32.83333
    ]
  }
}