{
  "type": "Feature",
  "properties": {
    "name": "Chuchkovo",
    "country": "RU",
    "subdivision": "62",
    "timezone": "Europe/Moscow"
  },
  "geometry": {
    "type": "Point",
    "coordinates": [
      41.44648,
      54.26931
    ]
  }
}