{
  "type": "Feature",
  "properties": {
    "name": "Kiritsy",
    "country": "RU",
    "subdivision": "62",
    "timezone": "Europe/Moscow"
  },
  "geometry": {
    "type": "Point",
    "coordinates": [
      40.3572,
      54.2862
    ]
  }
}