{
  "type": "Feature",
  "properties": {
    "name": "Lesnoy",
    "country": "RU",
    "subdivision": "62",
    "timezone": "Europe/Moscow"
  },
  "geometry": {
    "type": "Point",
    "coordinates": [
      40.4713,
      54.2125
    ]
  }
}