{
  "type": "Feature",
  "properties": {
    "name": "Miloslavskoye",
    "country": "RU",
    "subdivision": "62",
    "timezone": "Europe/Moscow"
  },
  "geometry": {
    "type": "Point",
    "coordinates": [
      39.43992,
      53.58152
    ]
  }
}