{
  "type": "Feature",
  "properties": {
    "name": "Novomichurinsk",
    "country": "RU",
    "subdivision": "62",
    "timezone": "Europe/Moscow"
  },
  "geometry": {
    "type": "Point",
    "coordinates": [
      39.7479,
      54.0384
    ]
  }
}