{
  "type": "Feature",
  "properties": {
    "name": "Putyatino",
    "country": "RU",
    "subdivision": "62",
    "timezone": "Europe/Moscow"
  },
  "geometry": {
    "type": "Point",
    "coordinates": [
      41.1169,
      54.15998
    ]
  }
}