{
  "type": "Feature",
  "properties": {
    "name": "Sapozhok",
    "country": "RU",
    "subdivision": "62",
    "timezone": "Europe/Moscow"
  },
  "geometry": {
    "type": "Point",
    "coordinates": [
      40.68056,
      53.94194
    ]
  }
}