{
  "type": "Feature",
  "properties": {
    "name": "Sasovo",
    "country": "RU",
    "subdivision": "62",
    "timezone": "Europe/Moscow"
  },
  "geometry": {
    "type": "Point",
    "coordinates": [
      41.91986,
      54.35369
    ]
  }
}