{
  "type": "Feature",
  "properties": {
    "name": "Skopin",
    "country": "RU",
    "subdivision": "62",
    "timezone": "Europe/Moscow"
  },
  "geometry": {
    "type": "Point",
    "coordinates": [
      39.55053,
      53.82486
    ]
  }
}