{
  "type": "Feature",
  "properties": {
    "name": "Spas-Klepiki",
    "country": "RU",
    "subdivision": "62",
    "timezone": "Europe/Moscow"
  },
  "geometry": {
    "type": "Point",
    "coordinates": [
      40.17673,
      55.13472
    ]
  }
}