{
  "type": "Feature",
  "properties": {
    "name": "Yambirno",
    "country": "RU",
    "subdivision": "62",
    "timezone": "Europe/Moscow"
  },
  "geometry": {
    "type": "Point",
    "coordinates": [
      42.0911,
      54.1231
    ]
  }
}