{
  "type": "Feature",
  "properties": {
    "name": "Yermish’",
    "country": "RU",
    "subdivision": "62",
    "timezone": "Europe/Moscow"
  },
  "geometry": {
    "type": "Point",
    "coordinates": [
      42.27111,
      54.76778
    ]
  }
}