{
  "type": "Feature",
  "properties": {
    "name": "Zarechnyy",
    "country": "RU",
    "subdivision": "62",
    "timezone": "Europe/Moscow"
  },
  "geometry": {
    "type": "Point",
    "coordinates": [
      39.59437,
      53.7306
    ]
  }
}