{
  "type": "Feature",
  "properties": {
    "name": "Dombås",
    "country": "NO",
    "subdivision": "34",
    "timezone": "Europe/Oslo"
  },
  "geometry": {
    "type": "Point",
    "coordinates": [
      9.12785,
      62.07554
    ]
  }
}