{
  "type": "Feature",
  "properties": {
    "name": "Skarnes",
    "country": "NO",
    "subdivision": "34",
    "timezone": "Europe/Oslo"
  },
  "geometry": {
    "type": "Point",
    "coordinates": [
      11.68485,
      60.25391
    ]
  }
}