{
  "type": "Feature",
  "properties": {
    "name": "Skotterud",
    "country": "NO",
    "subdivision": "34",
    "timezone": "Europe/Oslo"
  },
  "geometry": {
    "type": "Point",
    "coordinates": [
      12.12825,
      59.98281
    ]
  }
}