{
  "type": "Feature",
  "properties": {
    "name": "Vinstra",
    "country": "NO",
    "subdivision": "34",
    "timezone": "Europe/Oslo"
  },
  "geometry": {
    "type": "Point",
    "coordinates": [
      9.75134,
      61.59496
    ]
  }
}