{
  "type": "Feature",
  "properties": {
    "name": "Koprivshtitsa",
    "country": "BG",
    "subdivision": "58",
    "timezone": "Europe/Sofia"
  },
  "geometry": {
    "type": "Point",
    "coordinates": [
      24.35,
      42.63333
    ]
  }
}