{
  "type": "Feature",
  "properties": {
    "name": "Kostinbrod",
    "country": "BG",
    "subdivision": "58",
    "timezone": "Europe/Sofia"
  },
  "geometry": {
    "type": "Point",
    "coordinates": [
      23.21667,
      42.81667
    ]
  }
}