{
  "type": "Feature",
  "properties": {
    "name": "Slivnitsa",
    "country": "BG",
    "subdivision": "58",
    "timezone": "Europe/Sofia"
  },
  "geometry": {
    "type": "Point",
    "coordinates": [
      23.03792,
      42.85182
    ]
  }
}