{
  "type": "Feature",
  "properties": {
    "name": "Acconia",
    "country": "IT",
    "subdivision": "03",
    "timezone": "Europe/Rome"
  },
  "geometry": {
    "type": "Point",
    "coordinates": [
      16.2653,
      38.83585
    ]
  }
}