{
  "type": "Feature",
  "properties": {
    "name": "Amica",
    "country": "IT",
    "subdivision": "03",
    "timezone": "Europe/Rome"
  },
  "geometry": {
    "type": "Point",
    "coordinates": [
      16.66694,
      39.60085
    ]
  }
}