{
  "type": "Feature",
  "properties": {
    "name": "Bivongi",
    "country": "IT",
    "subdivision": "03",
    "timezone": "Europe/Rome"
  },
  "geometry": {
    "type": "Point",
    "coordinates": [
      16.45251,
      38.48328
    ]
  }
}