{
  "type": "Feature",
  "properties": {
    "name": "Capistrano",
    "country": "IT",
    "subdivision": "03",
    "timezone": "Europe/Rome"
  },
  "geometry": {
    "type": "Point",
    "coordinates": [
      16.28935,
      38.69131
    ]
  }
}