{
  "type": "Feature",
  "properties": {
    "name": "Capo Rizzuto",
    "country": "IT",
    "subdivision": "03",
    "timezone": "Europe/Rome"
  },
  "geometry": {
    "type": "Point",
    "coordinates": [
      17.09872,
      38.90412
    ]
  }
}