{
  "type": "Feature",
  "properties": {
    "name": "Casole Bruzio",
    "country": "IT",
    "subdivision": "03",
    "timezone": "Europe/Rome"
  },
  "geometry": {
    "type": "Point",
    "coordinates": [
      16.33193,
      39.28384
    ]
  }
}