{
  "type": "Feature",
  "properties": {
    "name": "Cinque Frondi",
    "country": "IT",
    "subdivision": "03",
    "timezone": "Europe/Rome"
  },
  "geometry": {
    "type": "Point",
    "coordinates": [
      16.0842,
      38.41618
    ]
  }
}