{
  "type": "Feature",
  "properties": {
    "name": "Cittanova",
    "country": "IT",
    "subdivision": "03",
    "timezone": "Europe/Rome"
  },
  "geometry": {
    "type": "Point",
    "coordinates": [
      16.07898,
      38.35431
    ]
  }
}