{
  "type": "Feature",
  "properties": {
    "name": "Crichi",
    "country": "IT",
    "subdivision": "03",
    "timezone": "Europe/Rome"
  },
  "geometry": {
    "type": "Point",
    "coordinates": [
      16.64178,
      38.95296
    ]
  }
}