{
  "type": "Feature",
  "properties": {
    "name": "Crotone",
    "country": "IT",
    "subdivision": "03",
    "timezone": "Europe/Rome"
  },
  "geometry": {
    "type": "Point",
    "coordinates": [
      17.12764,
      39.08077
    ]
  }
}