{
  "type": "Feature",
  "properties": {
    "name": "Curinga",
    "country": "IT",
    "subdivision": "03",
    "timezone": "Europe/Rome"
  },
  "geometry": {
    "type": "Point",
    "coordinates": [
      16.31344,
      38.82811
    ]
  }
}