{
  "type": "Feature",
  "properties": {
    "name": "Cutro",
    "country": "IT",
    "subdivision": "03",
    "timezone": "Europe/Rome"
  },
  "geometry": {
    "type": "Point",
    "coordinates": [
      16.98658,
      39.03484
    ]
  }
}