{
  "type": "Feature",
  "properties": {
    "name": "Delianuova",
    "country": "IT",
    "subdivision": "03",
    "timezone": "Europe/Rome"
  },
  "geometry": {
    "type": "Point",
    "coordinates": [
      15.91714,
      38.23587
    ]
  }
}