{
  "type": "Feature",
  "properties": {
    "name": "Fagnano Castello",
    "country": "IT",
    "subdivision": "03",
    "timezone": "Europe/Rome"
  },
  "geometry": {
    "type": "Point",
    "coordinates": [
      16.06253,
      39.5716
    ]
  }
}