{
  "type": "Feature",
  "properties": {
    "name": "Foresta",
    "country": "IT",
    "subdivision": "03",
    "timezone": "Europe/Rome"
  },
  "geometry": {
    "type": "Point",
    "coordinates": [
      16.81287,
      39.09939
    ]
  }
}