{
  "type": "Feature",
  "properties": {
    "name": "Grisolia",
    "country": "IT",
    "subdivision": "03",
    "timezone": "Europe/Rome"
  },
  "geometry": {
    "type": "Point",
    "coordinates": [
      15.85605,
      39.72538
    ]
  }
}