{
  "type": "Feature",
  "properties": {
    "name": "Maierato",
    "country": "IT",
    "subdivision": "03",
    "timezone": "Europe/Rome"
  },
  "geometry": {
    "type": "Point",
    "coordinates": [
      16.17532,
      38.71111
    ]
  }
}