{
  "type": "Feature",
  "properties": {
    "name": "Marina",
    "country": "IT",
    "subdivision": "03",
    "timezone": "Europe/Rome"
  },
  "geometry": {
    "type": "Point",
    "coordinates": [
      16.60585,
      39.93857
    ]
  }
}