{
  "type": "Feature",
  "properties": {
    "name": "Nicastro",
    "country": "IT",
    "subdivision": "03",
    "timezone": "Europe/Rome"
  },
  "geometry": {
    "type": "Point",
    "coordinates": [
      16.31285,
      38.97089
    ]
  }
}