{
  "type": "Feature",
  "properties": {
    "name": "Pianopoli",
    "country": "IT",
    "subdivision": "03",
    "timezone": "Europe/Rome"
  },
  "geometry": {
    "type": "Point",
    "coordinates": [
      16.38863,
      38.95246
    ]
  }
}