{
  "type": "Feature",
  "properties": {
    "name": "Roggiano Gravina",
    "country": "IT",
    "subdivision": "03",
    "timezone": "Europe/Rome"
  },
  "geometry": {
    "type": "Point",
    "coordinates": [
      16.16173,
      39.61786
    ]
  }
}