{
  "type": "Feature",
  "properties": {
    "name": "Rosarno",
    "country": "IT",
    "subdivision": "03",
    "timezone": "Europe/Rome"
  },
  "geometry": {
    "type": "Point",
    "coordinates": [
      15.97956,
      38.48717
    ]
  }
}