{
  "type": "Feature",
  "properties": {
    "name": "San Pietro in Guarano",
    "country": "IT",
    "subdivision": "03",
    "timezone": "Europe/Rome"
  },
  "geometry": {
    "type": "Point",
    "coordinates": [
      16.31304,
      39.34164
    ]
  }
}