{
  "type": "Feature",
  "properties": {
    "name": "San Nico",
    "country": "IT",
    "subdivision": "03",
    "timezone": "Europe/Rome"
  },
  "geometry": {
    "type": "Point",
    "coordinates": [
      16.43182,
      39.66906
    ]
  }
}