{
  "type": "Feature",
  "properties": {
    "name": "San Sosti",
    "country": "IT",
    "subdivision": "03",
    "timezone": "Europe/Rome"
  },
  "geometry": {
    "type": "Point",
    "coordinates": [
      16.02958,
      39.65879
    ]
  }
}