{
  "type": "Feature",
  "properties": {
    "name": "Santa Severina",
    "country": "IT",
    "subdivision": "03",
    "timezone": "Europe/Rome"
  },
  "geometry": {
    "type": "Point",
    "coordinates": [
      16.91112,
      39.1477
    ]
  }
}