{
  "type": "Feature",
  "properties": {
    "name": "Siderno",
    "country": "IT",
    "subdivision": "03",
    "timezone": "Europe/Rome"
  },
  "geometry": {
    "type": "Point",
    "coordinates": [
      16.29607,
      38.26993
    ]
  }
}