{
  "type": "Feature",
  "properties": {
    "name": "Spilinga",
    "country": "IT",
    "subdivision": "03",
    "timezone": "Europe/Rome"
  },
  "geometry": {
    "type": "Point",
    "coordinates": [
      15.90572,
      38.62825
    ]
  }
}