{
  "type": "Feature",
  "properties": {
    "name": "Squillace Lido",
    "country": "IT",
    "subdivision": "03",
    "timezone": "Europe/Rome"
  },
  "geometry": {
    "type": "Point",
    "coordinates": [
      16.57007,
      38.77781
    ]
  }
}