{
  "type": "Feature",
  "properties": {
    "name": "Stazione Montalto-Coretto",
    "country": "IT",
    "subdivision": "03",
    "timezone": "Europe/Rome"
  },
  "geometry": {
    "type": "Point",
    "coordinates": [
      16.24313,
      39.4072
    ]
  }
}