{
  "type": "Feature",
  "properties": {
    "name": "Stefanaconi",
    "country": "IT",
    "subdivision": "03",
    "timezone": "Europe/Rome"
  },
  "geometry": {
    "type": "Point",
    "coordinates": [
      16.1242,
      38.67788
    ]
  }
}