{
  "type": "Feature",
  "properties": {
    "name": "Terranova da Sibari",
    "country": "IT",
    "subdivision": "03",
    "timezone": "Europe/Rome"
  },
  "geometry": {
    "type": "Point",
    "coordinates": [
      16.33979,
      39.65548
    ]
  }
}