{
  "type": "Feature",
  "properties": {
    "name": "Tropea",
    "country": "IT",
    "subdivision": "03",
    "timezone": "Europe/Rome"
  },
  "geometry": {
    "type": "Point",
    "coordinates": [
      15.89505,
      38.67449
    ]
  }
}