{
  "type": "Feature",
  "properties": {
    "name": "Vazzano",
    "country": "IT",
    "subdivision": "03",
    "timezone": "Europe/Rome"
  },
  "geometry": {
    "type": "Point",
    "coordinates": [
      16.248,
      38.63288
    ]
  }
}