{
  "type": "Feature",
  "properties": {
    "name": "Zagarise",
    "country": "IT",
    "subdivision": "03",
    "timezone": "Europe/Rome"
  },
  "geometry": {
    "type": "Point",
    "coordinates": [
      16.6642,
      38.99985
    ]
  }
}