{
  "type": "Feature",
  "properties": {
    "name": "Saharna",
    "country": "MD",
    "subdivision": "83",
    "timezone": "Europe/Chisinau"
  },
  "geometry": {
    "type": "Point",
    "coordinates": [
      28.97458,
      47.69107
    ]
  }
}