{
  "type": "Feature",
  "properties": {
    "name": "Plateliai",
    "country": "LT",
    "subdivision": "63",
    "timezone": "Europe/Vilnius"
  },
  "geometry": {
    "type": "Point",
    "coordinates": [
      21.81615,
      56.04657
    ]
  }
}