{
  "type": "Feature",
  "properties": {
    "name": "Abbeville",
    "country": "US",
    "subdivision": "LA",
    "timezone": "America/Chicago"
  },
  "geometry": {
    "type": "Point",
    "coordinates": [
      -92.13429,
      29.97465
    ]
  }
}