{
  "type": "Feature",
  "properties": {
    "name": "Albany",
    "country": "US",
    "subdivision": "LA",
    "timezone": "America/Chicago"
  },
  "geometry": {
    "type": "Point",
    "coordinates": [
      -90.58231,
      30.50436
    ]
  }
}