{
  "type": "Feature",
  "properties": {
    "name": "Amite",
    "country": "US",
    "subdivision": "LA",
    "timezone": "America/Chicago"
  },
  "geometry": {
    "type": "Point",
    "coordinates": [
      -90.50898,
      30.72657
    ]
  }
}