{
  "type": "Feature",
  "properties": {
    "name": "Basile",
    "country": "US",
    "subdivision": "LA",
    "timezone": "America/Chicago"
  },
  "geometry": {
    "type": "Point",
    "coordinates": [
      -92.59597,
      30.4852
    ]
  }
}