{
  "type": "Feature",
  "properties": {
    "name": "Batchelor",
    "country": "US",
    "subdivision": "LA",
    "timezone": "America/Chicago"
  },
  "geometry": {
    "type": "Point",
    "coordinates": [
      -91.66151,
      30.84046
    ]
  }
}