{
  "type": "Feature",
  "properties": {
    "name": "Bourg",
    "country": "US",
    "subdivision": "LA",
    "timezone": "America/Chicago"
  },
  "geometry": {
    "type": "Point",
    "coordinates": [
      -90.60231,
      29.55355
    ]
  }
}