{
  "type": "Feature",
  "properties": {
    "name": "Breaux Bridge",
    "country": "US",
    "subdivision": "LA",
    "timezone": "America/Chicago"
  },
  "geometry": {
    "type": "Point",
    "coordinates": [
      -91.89928,
      30.27353
    ]
  }
}