{
  "type": "Feature",
  "properties": {
    "name": "Bridge City",
    "country": "US",
    "subdivision": "LA",
    "timezone": "America/Chicago"
  },
  "geometry": {
    "type": "Point",
    "coordinates": [
      -90.17007,
      29.93326
    ]
  }
}