{
  "type": "Feature",
  "properties": {
    "name": "Broussard",
    "country": "US",
    "subdivision": "LA",
    "timezone": "America/Chicago"
  },
  "geometry": {
    "type": "Point",
    "coordinates": [
      -91.96123,
      30.14715
    ]
  }
}