{
  "type": "Feature",
  "properties": {
    "name": "Catahoula",
    "country": "US",
    "subdivision": "LA",
    "timezone": "America/Chicago"
  },
  "geometry": {
    "type": "Point",
    "coordinates": [
      -91.709,
      30.21464
    ]
  }
}