{
  "type": "Feature",
  "properties": {
    "name": "Chauvin",
    "country": "US",
    "subdivision": "LA",
    "timezone": "America/Chicago"
  },
  "geometry": {
    "type": "Point",
    "coordinates": [
      -90.59537,
      29.43855
    ]
  }
}