{
  "type": "Feature",
  "properties": {
    "name": "Cottonport",
    "country": "US",
    "subdivision": "LA",
    "timezone": "America/Chicago"
  },
  "geometry": {
    "type": "Point",
    "coordinates": [
      -92.05346,
      30.98408
    ]
  }
}