{
  "type": "Feature",
  "properties": {
    "name": "DeQuincy",
    "country": "US",
    "subdivision": "LA",
    "timezone": "America/Chicago"
  },
  "geometry": {
    "type": "Point",
    "coordinates": [
      -93.43322,
      30.45048
    ]
  }
}