{
  "type": "Feature",
  "properties": {
    "name": "Donaldsonville",
    "country": "US",
    "subdivision": "LA",
    "timezone": "America/Chicago"
  },
  "geometry": {
    "type": "Point",
    "coordinates": [
      -90.99412,
      30.10114
    ]
  }
}