{
  "type": "Feature",
  "properties": {
    "name": "Estelle",
    "country": "US",
    "subdivision": "LA",
    "timezone": "America/Chicago"
  },
  "geometry": {
    "type": "Point",
    "coordinates": [
      -90.10674,
      29.84576
    ]
  }
}