{
  "type": "Feature",
  "properties": {
    "name": "Golden Meadow",
    "country": "US",
    "subdivision": "LA",
    "timezone": "America/Chicago"
  },
  "geometry": {
    "type": "Point",
    "coordinates": [
      -90.26008,
      29.37911
    ]
  }
}