{
  "type": "Feature",
  "properties": {
    "name": "Haughton",
    "country": "US",
    "subdivision": "LA",
    "timezone": "America/Chicago"
  },
  "geometry": {
    "type": "Point",
    "coordinates": [
      -93.50406,
      32.53265
    ]
  }
}