{
  "type": "Feature",
  "properties": {
    "name": "Homer",
    "country": "US",
    "subdivision": "LA",
    "timezone": "America/Chicago"
  },
  "geometry": {
    "type": "Point",
    "coordinates": [
      -93.05503,
      32.79192
    ]
  }
}