{
  "type": "Feature",
  "properties": {
    "name": "Kenner",
    "country": "US",
    "subdivision": "LA",
    "timezone": "America/Chicago"
  },
  "geometry": {
    "type": "Point",
    "coordinates": [
      -90.24174,
      29.99409
    ]
  }
}