{
  "type": "Feature",
  "properties": {
    "name": "Lake Arthur",
    "country": "US",
    "subdivision": "LA",
    "timezone": "America/Chicago"
  },
  "geometry": {
    "type": "Point",
    "coordinates": [
      -92.67153,
      30.08076
    ]
  }
}