{
  "type": "Feature",
  "properties": {
    "name": "Leonville",
    "country": "US",
    "subdivision": "LA",
    "timezone": "America/Chicago"
  },
  "geometry": {
    "type": "Point",
    "coordinates": [
      -91.97845,
      30.47047
    ]
  }
}