{
  "type": "Feature",
  "properties": {
    "name": "Livingston",
    "country": "US",
    "subdivision": "LA",
    "timezone": "America/Chicago"
  },
  "geometry": {
    "type": "Point",
    "coordinates": [
      -90.74787,
      30.50213
    ]
  }
}