{
  "type": "Feature",
  "properties": {
    "name": "Patterson",
    "country": "US",
    "subdivision": "LA",
    "timezone": "America/Chicago"
  },
  "geometry": {
    "type": "Point",
    "coordinates": [
      -91.30205,
      29.69326
    ]
  }
}