{
  "type": "Feature",
  "properties": {
    "name": "Port Allen",
    "country": "US",
    "subdivision": "LA",
    "timezone": "America/Chicago"
  },
  "geometry": {
    "type": "Point",
    "coordinates": [
      -91.21011,
      30.45214
    ]
  }
}