{
  "type": "Feature",
  "properties": {
    "name": "Poydras",
    "country": "US",
    "subdivision": "LA",
    "timezone": "America/Chicago"
  },
  "geometry": {
    "type": "Point",
    "coordinates": [
      -89.88895,
      29.86937
    ]
  }
}