{
  "type": "Feature",
  "properties": {
    "name": "Prairieville",
    "country": "US",
    "subdivision": "LA",
    "timezone": "America/Chicago"
  },
  "geometry": {
    "type": "Point",
    "coordinates": [
      -90.97205,
      30.30297
    ]
  }
}