{
  "type": "Feature",
  "properties": {
    "name": "Prien",
    "country": "US",
    "subdivision": "LA",
    "timezone": "America/Chicago"
  },
  "geometry": {
    "type": "Point",
    "coordinates": [
      -93.27377,
      30.18187
    ]
  }
}