{
  "type": "Feature",
  "properties": {
    "name": "Ringgold",
    "country": "US",
    "subdivision": "LA",
    "timezone": "America/Chicago"
  },
  "geometry": {
    "type": "Point",
    "coordinates": [
      -93.27989,
      32.32849
    ]
  }
}