{
  "type": "Feature",
  "properties": {
    "name": "Simmesport",
    "country": "US",
    "subdivision": "LA",
    "timezone": "America/Chicago"
  },
  "geometry": {
    "type": "Point",
    "coordinates": [
      -91.80012,
      30.98352
    ]
  }
}