{
  "type": "Feature",
  "properties": {
    "name": "South Vacherie",
    "country": "US",
    "subdivision": "LA",
    "timezone": "America/Chicago"
  },
  "geometry": {
    "type": "Point",
    "coordinates": [
      -90.69981,
      29.92743
    ]
  }
}