{
  "type": "Feature",
  "properties": {
    "name": "Sterlington",
    "country": "US",
    "subdivision": "LA",
    "timezone": "America/Chicago"
  },
  "geometry": {
    "type": "Point",
    "coordinates": [
      -92.08597,
      32.69625
    ]
  }
}