{
  "type": "Feature",
  "properties": {
    "name": "Stonewall",
    "country": "US",
    "subdivision": "LA",
    "timezone": "America/Chicago"
  },
  "geometry": {
    "type": "Point",
    "coordinates": [
      -93.82407,
      32.28183
    ]
  }
}