{
  "type": "Feature",
  "properties": {
    "name": "Sulphur",
    "country": "US",
    "subdivision": "LA",
    "timezone": "America/Chicago"
  },
  "geometry": {
    "type": "Point",
    "coordinates": [
      -93.37738,
      30.23659
    ]
  }
}