{
  "type": "Feature",
  "properties": {
    "name": "Vienna Bend",
    "country": "US",
    "subdivision": "LA",
    "timezone": "America/Chicago"
  },
  "geometry": {
    "type": "Point",
    "coordinates": [
      -93.041,
      31.73239
    ]
  }
}