{
  "type": "Feature",
  "properties": {
    "name": "Vinton",
    "country": "US",
    "subdivision": "LA",
    "timezone": "America/Chicago"
  },
  "geometry": {
    "type": "Point",
    "coordinates": [
      -93.58127,
      30.19076
    ]
  }
}