{
  "type": "Feature",
  "properties": {
    "name": "Waggaman",
    "country": "US",
    "subdivision": "LA",
    "timezone": "America/Chicago"
  },
  "geometry": {
    "type": "Point",
    "coordinates": [
      -90.21091,
      29.91854
    ]
  }
}