{
  "type": "Feature",
  "properties": {
    "name": "Westlake",
    "country": "US",
    "subdivision": "LA",
    "timezone": "America/Chicago"
  },
  "geometry": {
    "type": "Point",
    "coordinates": [
      -93.25071,
      30.24215
    ]
  }
}