{
  "type": "Feature",
  "properties": {
    "name": "Siliana",
    "country": "TN",
    "subdivision": "22",
    "timezone": "Africa/Tunis"
  },
  "geometry": {
    "type": "Point",
    "coordinates": [
      9.37082,
      36.08497
    ]
  }
}