{
  "type": "Feature",
  "properties": {
    "name": "Al Faḩāḩīl",
    "country": "KW",
    "subdivision": "04",
    "timezone": "Asia/Kuwait"
  },
  "geometry": {
    "type": "Point",
    "coordinates": [
      48.13028,
      29.0825
    ]
  }
}