{
  "type": "Feature",
  "properties": {
    "name": "Avenue B and C",
    "country": "US",
    "subdivision": "AZ",
    "timezone": "America/Phoenix"
  },
  "geometry": {
    "type": "Point",
    "coordinates": [
      -114.66005,
      32.71904
    ]
  }
}