{
  "type": "Feature",
  "properties": {
    "name": "Avra Valley",
    "country": "US",
    "subdivision": "AZ",
    "timezone": "America/Phoenix"
  },
  "geometry": {
    "type": "Point",
    "coordinates": [
      -111.31539,
      32.43785
    ]
  }
}