{
  "type": "Feature",
  "properties": {
    "name": "Bagdad",
    "country": "US",
    "subdivision": "AZ",
    "timezone": "America/Phoenix"
  },
  "geometry": {
    "type": "Point",
    "coordinates": [
      -113.20464,
      34.58113
    ]
  }
}