{
  "type": "Feature",
  "properties": {
    "name": "Buckeye",
    "country": "US",
    "subdivision": "AZ",
    "timezone": "America/Phoenix"
  },
  "geometry": {
    "type": "Point",
    "coordinates": [
      -112.58378,
      33.37032
    ]
  }
}