{
  "type": "Feature",
  "properties": {
    "name": "Casa Grande",
    "country": "US",
    "subdivision": "AZ",
    "timezone": "America/Phoenix"
  },
  "geometry": {
    "type": "Point",
    "coordinates": [
      -111.75735,
      32.8795
    ]
  }
}