{
  "type": "Feature",
  "properties": {
    "name": "Cave Creek",
    "country": "US",
    "subdivision": "AZ",
    "timezone": "America/Phoenix"
  },
  "geometry": {
    "type": "Point",
    "coordinates": [
      -111.95083,
      33.83333
    ]
  }
}