{
  "type": "Feature",
  "properties": {
    "name": "Dolan Springs",
    "country": "US",
    "subdivision": "AZ",
    "timezone": "America/Phoenix"
  },
  "geometry": {
    "type": "Point",
    "coordinates": [
      -114.27329,
      35.59194
    ]
  }
}