{
  "type": "Feature",
  "properties": {
    "name": "East Sahuarita",
    "country": "US",
    "subdivision": "AZ",
    "timezone": "America/Phoenix"
  },
  "geometry": {
    "type": "Point",
    "coordinates": [
      -110.92842,
      31.94286
    ]
  }
}