{
  "type": "Feature",
  "properties": {
    "name": "Flowing Wells",
    "country": "US",
    "subdivision": "AZ",
    "timezone": "America/Phoenix"
  },
  "geometry": {
    "type": "Point",
    "coordinates": [
      -111.00982,
      32.29396
    ]
  }
}