{
  "type": "Feature",
  "properties": {
    "name": "Glendale",
    "country": "US",
    "subdivision": "AZ",
    "timezone": "America/Phoenix"
  },
  "geometry": {
    "type": "Point",
    "coordinates": [
      -112.18599,
      33.53865
    ]
  }
}