{
  "type": "Feature",
  "properties": {
    "name": "Lake of the Woods",
    "country": "US",
    "subdivision": "AZ",
    "timezone": "America/Phoenix"
  },
  "geometry": {
    "type": "Point",
    "coordinates": [
      -109.98955,
      34.16393
    ]
  }
}