{
  "type": "Feature",
  "properties": {
    "name": "Litchfield Park",
    "country": "US",
    "subdivision": "AZ",
    "timezone": "America/Phoenix"
  },
  "geometry": {
    "type": "Point",
    "coordinates": [
      -112.35794,
      33.49337
    ]
  }
}