{
  "type": "Feature",
  "properties": {
    "name": "Marana",
    "country": "US",
    "subdivision": "AZ",
    "timezone": "America/Phoenix"
  },
  "geometry": {
    "type": "Point",
    "coordinates": [
      -111.22538,
      32.43674
    ]
  }
}