{
  "type": "Feature",
  "properties": {
    "name": "New Kingman-Butler",
    "country": "US",
    "subdivision": "AZ",
    "timezone": "America/Phoenix"
  },
  "geometry": {
    "type": "Point",
    "coordinates": [
      -114.03226,
      35.26504
    ]
  }
}