{
  "type": "Feature",
  "properties": {
    "name": "Page",
    "country": "US",
    "subdivision": "AZ",
    "timezone": "America/Phoenix"
  },
  "geometry": {
    "type": "Point",
    "coordinates": [
      -111.45583,
      36.91472
    ]
  }
}