{
  "type": "Feature",
  "properties": {
    "name": "Rio Rico",
    "country": "US",
    "subdivision": "AZ",
    "timezone": "America/Phoenix"
  },
  "geometry": {
    "type": "Point",
    "coordinates": [
      -110.97648,
      31.47148
    ]
  }
}