{
  "type": "Feature",
  "properties": {
    "name": "Saint Johns",
    "country": "US",
    "subdivision": "AZ",
    "timezone": "America/Phoenix"
  },
  "geometry": {
    "type": "Point",
    "coordinates": [
      -109.36093,
      34.50587
    ]
  }
}