{
  "type": "Feature",
  "properties": {
    "name": "Salome",
    "country": "US",
    "subdivision": "AZ",
    "timezone": "America/Phoenix"
  },
  "geometry": {
    "type": "Point",
    "coordinates": [
      -113.61465,
      33.78114
    ]
  }
}