{
  "type": "Feature",
  "properties": {
    "name": "San Tan Valley",
    "country": "US",
    "subdivision": "AZ",
    "timezone": "America/Phoenix"
  },
  "geometry": {
    "type": "Point",
    "coordinates": [
      -111.528,
      33.1911
    ]
  }
}