{
  "type": "Feature",
  "properties": {
    "name": "Sierra Vista",
    "country": "US",
    "subdivision": "AZ",
    "timezone": "America/Phoenix"
  },
  "geometry": {
    "type": "Point",
    "coordinates": [
      -110.30369,
      31.55454
    ]
  }
}