{
  "type": "Feature",
  "properties": {
    "name": "South Tucson",
    "country": "US",
    "subdivision": "AZ",
    "timezone": "America/Phoenix"
  },
  "geometry": {
    "type": "Point",
    "coordinates": [
      -110.96842,
      32.19952
    ]
  }
}