{
  "type": "Feature",
  "properties": {
    "name": "Sun City",
    "country": "US",
    "subdivision": "AZ",
    "timezone": "America/Phoenix"
  },
  "geometry": {
    "type": "Point",
    "coordinates": [
      -112.27182,
      33.59754
    ]
  }
}