{
  "type": "Feature",
  "properties": {
    "name": "Sun Valley",
    "country": "US",
    "subdivision": "AZ",
    "timezone": "America/Phoenix"
  },
  "geometry": {
    "type": "Point",
    "coordinates": [
      -111.26125,
      34.2542
    ]
  }
}