{
  "type": "Feature",
  "properties": {
    "name": "Swift Trail Junction",
    "country": "US",
    "subdivision": "AZ",
    "timezone": "America/Phoenix"
  },
  "geometry": {
    "type": "Point",
    "coordinates": [
      -109.71397,
      32.72979
    ]
  }
}