{
  "type": "Feature",
  "properties": {
    "name": "Vail",
    "country": "US",
    "subdivision": "AZ",
    "timezone": "America/Phoenix"
  },
  "geometry": {
    "type": "Point",
    "coordinates": [
      -110.71203,
      32.04786
    ]
  }
}