{
  "type": "Feature",
  "properties": {
    "name": "Verde Village",
    "country": "US",
    "subdivision": "AZ",
    "timezone": "America/Phoenix"
  },
  "geometry": {
    "type": "Point",
    "coordinates": [
      -112.01152,
      34.7105
    ]
  }
}