{
  "type": "Feature",
  "properties": {
    "name": "Wellton",
    "country": "US",
    "subdivision": "AZ",
    "timezone": "America/Phoenix"
  },
  "geometry": {
    "type": "Point",
    "coordinates": [
      -114.14688,
      32.67283
    ]
  }
}