{
  "type": "Feature",
  "properties": {
    "name": "White Mountain Lake",
    "country": "US",
    "subdivision": "AZ",
    "timezone": "America/Phoenix"
  },
  "geometry": {
    "type": "Point",
    "coordinates": [
      -109.99789,
      34.34865
    ]
  }
}