{
  "type": "Feature",
  "properties": {
    "name": "Malazgirt",
    "country": "TR",
    "subdivision": "49",
    "timezone": "Europe/Istanbul"
  },
  "geometry": {
    "type": "Point",
    "coordinates": [
      42.53536,
      39.1465
    ]
  }
}