{
  "type": "Feature",
  "properties": {
    "name": "Manismata",
    "country": "ID",
    "subdivision": "11",
    "timezone": "Asia/Pontianak"
  },
  "geometry": {
    "type": "Point",
    "coordinates": [
      111.03333,
      -2.46667
    ]
  }
}