{
  "type": "Feature",
  "properties": {
    "name": "Hamanoichi",
    "country": "JP",
    "subdivision": "18",
    "timezone": "Asia/Tokyo"
  },
  "geometry": {
    "type": "Point",
    "coordinates": [
      130.73333,
      31.71667
    ]
  }
}