{
  "type": "Feature",
  "properties": {
    "name": "Kaseda-shirakame",
    "country": "JP",
    "subdivision": "18",
    "timezone": "Asia/Tokyo"
  },
  "geometry": {
    "type": "Point",
    "coordinates": [
      130.31667,
      31.41667
    ]
  }
}