{
  "type": "Feature",
  "properties": {
    "name": "Naze",
    "country": "JP",
    "subdivision": "18",
    "timezone": "Asia/Tokyo"
  },
  "geometry": {
    "type": "Point",
    "coordinates": [
      129.48333,
      28.36667
    ]
  }
}