{
  "type": "Feature",
  "properties": {
    "name": "Chiroqchi",
    "country": "UZ",
    "subdivision": "08",
    "timezone": "Asia/Samarkand"
  },
  "geometry": {
    "type": "Point",
    "coordinates": [
      66.57222,
      39.03361
    ]
  }
}