{
  "type": "Feature",
  "properties": {
    "name": "Alagoa Grande",
    "country": "BR",
    "subdivision": "17",
    "timezone": "America/Fortaleza"
  },
  "geometry": {
    "type": "Point",
    "coordinates": [
      -35.63,
      -7.15833
    ]
  }
}