{
  "type": "Feature",
  "properties": {
    "name": "Conde",
    "country": "BR",
    "subdivision": "17",
    "timezone": "America/Fortaleza"
  },
  "geometry": {
    "type": "Point",
    "coordinates": [
      -34.9075,
      -7.25972
    ]
  }
}