{
  "type": "Feature",
  "properties": {
    "name": "Cuité",
    "country": "BR",
    "subdivision": "17",
    "timezone": "America/Fortaleza"
  },
  "geometry": {
    "type": "Point",
    "coordinates": [
      -36.15361,
      -6.48361
    ]
  }
}