{
  "type": "Feature",
  "properties": {
    "name": "Natuba",
    "country": "BR",
    "subdivision": "17",
    "timezone": "America/Fortaleza"
  },
  "geometry": {
    "type": "Point",
    "coordinates": [
      -35.55,
      -7.64139
    ]
  }
}