{
  "type": "Feature",
  "properties": {
    "name": "Princesa Isabel",
    "country": "BR",
    "subdivision": "17",
    "timezone": "America/Fortaleza"
  },
  "geometry": {
    "type": "Point",
    "coordinates": [
      -37.99333,
      -7.73667
    ]
  }
}