{
  "type": "Feature",
  "properties": {
    "name": "Tavares",
    "country": "BR",
    "subdivision": "17",
    "timezone": "America/Fortaleza"
  },
  "geometry": {
    "type": "Point",
    "coordinates": [
      -37.87833,
      -7.63583
    ]
  }
}