{
  "type": "Feature",
  "properties": {
    "name": "Teixeira",
    "country": "BR",
    "subdivision": "17",
    "timezone": "America/Fortaleza"
  },
  "geometry": {
    "type": "Point",
    "coordinates": [
      -37.25417,
      -7.22278
    ]
  }
}