{
  "type": "Feature",
  "properties": {
    "name": "Andzhiyevskiy",
    "country": "RU",
    "subdivision": "70",
    "timezone": "Europe/Moscow"
  },
  "geometry": {
    "type": "Point",
    "coordinates": [
      43.08556,
      44.23889
    ]
  }
}