{
  "type": "Feature",
  "properties": {
    "name": "Borgustanskaya",
    "country": "RU",
    "subdivision": "70",
    "timezone": "Europe/Moscow"
  },
  "geometry": {
    "type": "Point",
    "coordinates": [
      42.5288,
      44.0547
    ]
  }
}