{
  "type": "Feature",
  "properties": {
    "name": "Burlatskoye",
    "country": "RU",
    "subdivision": "70",
    "timezone": "Europe/Moscow"
  },
  "geometry": {
    "type": "Point",
    "coordinates": [
      43.635,
      45.05639
    ]
  }
}