{
  "type": "Feature",
  "properties": {
    "name": "Edissiya",
    "country": "RU",
    "subdivision": "70",
    "timezone": "Europe/Moscow"
  },
  "geometry": {
    "type": "Point",
    "coordinates": [
      44.54083,
      44.05111
    ]
  }
}