{
  "type": "Feature",
  "properties": {
    "name": "Inozemtsevo",
    "country": "RU",
    "subdivision": "70",
    "timezone": "Europe/Moscow"
  },
  "geometry": {
    "type": "Point",
    "coordinates": [
      43.09113,
      44.09264
    ]
  }
}