{
  "type": "Feature",
  "properties": {
    "name": "Kangly",
    "country": "RU",
    "subdivision": "70",
    "timezone": "Europe/Moscow"
  },
  "geometry": {
    "type": "Point",
    "coordinates": [
      43.03083,
      44.25444
    ]
  }
}