{
  "type": "Feature",
  "properties": {
    "name": "Kruglolesskoye",
    "country": "RU",
    "subdivision": "70",
    "timezone": "Europe/Moscow"
  },
  "geometry": {
    "type": "Point",
    "coordinates": [
      42.81417,
      44.65889
    ]
  }
}