{
  "type": "Feature",
  "properties": {
    "name": "Kursavka",
    "country": "RU",
    "subdivision": "70",
    "timezone": "Europe/Moscow"
  },
  "geometry": {
    "type": "Point",
    "coordinates": [
      42.5093,
      44.4564
    ]
  }
}