{
  "type": "Feature",
  "properties": {
    "name": "Neftekumsk",
    "country": "RU",
    "subdivision": "70",
    "timezone": "Europe/Moscow"
  },
  "geometry": {
    "type": "Point",
    "coordinates": [
      44.9925,
      44.75583
    ]
  }
}