{
  "type": "Feature",
  "properties": {
    "name": "Novoaleksandrovsk",
    "country": "RU",
    "subdivision": "70",
    "timezone": "Europe/Moscow"
  },
  "geometry": {
    "type": "Point",
    "coordinates": [
      41.22075,
      45.4948
    ]
  }
}