{
  "type": "Feature",
  "properties": {
    "name": "Pokoynoye",
    "country": "RU",
    "subdivision": "70",
    "timezone": "Europe/Moscow"
  },
  "geometry": {
    "type": "Point",
    "coordinates": [
      44.25167,
      44.80972
    ]
  }
}