{
  "type": "Feature",
  "properties": {
    "name": "Staropavlovskaya",
    "country": "RU",
    "subdivision": "70",
    "timezone": "Europe/Moscow"
  },
  "geometry": {
    "type": "Point",
    "coordinates": [
      43.63278,
      43.84889
    ]
  }
}