{
  "type": "Feature",
  "properties": {
    "name": "Stavropol’",
    "country": "RU",
    "subdivision": "70",
    "timezone": "Europe/Moscow"
  },
  "geometry": {
    "type": "Point",
    "coordinates": [
      41.9734,
      45.0428
    ]
  }
}