{
  "type": "Feature",
  "properties": {
    "name": "Svetlograd",
    "country": "RU",
    "subdivision": "70",
    "timezone": "Europe/Moscow"
  },
  "geometry": {
    "type": "Point",
    "coordinates": [
      42.85472,
      45.33528
    ]
  }
}