{
  "type": "Feature",
  "properties": {
    "name": "Vostochny",
    "country": "RU",
    "subdivision": "70",
    "timezone": "Europe/Moscow"
  },
  "geometry": {
    "type": "Point",
    "coordinates": [
      44.19637,
      44.31494
    ]
  }
}