{
  "type": "Feature",
  "properties": {
    "name": "Zmeyka",
    "country": "RU",
    "subdivision": "70",
    "timezone": "Europe/Moscow"
  },
  "geometry": {
    "type": "Point",
    "coordinates": [
      43.12083,
      44.14278
    ]
  }
}