{
  "type": "Feature",
  "properties": {
    "name": "Escuintla",
    "country": "GT",
    "subdivision": "06",
    "timezone": "America/Guatemala"
  },
  "geometry": {
    "type": "Point",
    "coordinates": [
      -90.78581,
      14.3009
    ]
  }
}