{
  "type": "Feature",
  "properties": {
    "name": "Iztapa",
    "country": "GT",
    "subdivision": "06",
    "timezone": "America/Guatemala"
  },
  "geometry": {
    "type": "Point",
    "coordinates": [
      -90.7075,
      13.93333
    ]
  }
}