{
  "type": "Feature",
  "properties": {
    "name": "Centenario",
    "country": "AR",
    "subdivision": "15",
    "timezone": "America/Argentina/Salta"
  },
  "geometry": {
    "type": "Point",
    "coordinates": [
      -68.1318,
      -38.82955
    ]
  }
}