{
  "type": "Feature",
  "properties": {
    "name": "Plottier",
    "country": "AR",
    "subdivision": "15",
    "timezone": "America/Argentina/Salta"
  },
  "geometry": {
    "type": "Point",
    "coordinates": [
      -68.23333,
      -38.96667
    ]
  }
}