{
  "type": "Feature",
  "properties": {
    "name": "San Martín de los Andes",
    "country": "AR",
    "subdivision": "15",
    "timezone": "America/Argentina/Salta"
  },
  "geometry": {
    "type": "Point",
    "coordinates": [
      -71.35337,
      -40.15789
    ]
  }
}