{
  "type": "Feature",
  "properties": {
    "name": "Vista Alegre",
    "country": "AR",
    "subdivision": "15",
    "timezone": "America/Argentina/Salta"
  },
  "geometry": {
    "type": "Point",
    "coordinates": [
      -68.18333,
      -38.75
    ]
  }
}