{
  "type": "Feature",
  "properties": {
    "name": "Kaset Wisai",
    "country": "TH",
    "subdivision": "25",
    "timezone": "Asia/Bangkok"
  },
  "geometry": {
    "type": "Point",
    "coordinates": [
      103.58361,
      15.65558
    ]
  }
}