{
  "type": "Feature",
  "properties": {
    "name": "Dunda",
    "country": "TZ",
    "subdivision": "09",
    "timezone": "Africa/Dar_es_Salaam"
  },
  "geometry": {
    "type": "Point",
    "coordinates": [
      34.25,
      -8.11667
    ]
  }
}