{
  "type": "Feature",
  "properties": {
    "name": "Ulenje",
    "country": "TZ",
    "subdivision": "09",
    "timezone": "Africa/Dar_es_Salaam"
  },
  "geometry": {
    "type": "Point",
    "coordinates": [
      33.68333,
      -8.93333
    ]
  }
}