{
  "type": "Feature",
  "properties": {
    "name": "Durağan",
    "country": "TR",
    "subdivision": "57",
    "timezone": "Europe/Istanbul"
  },
  "geometry": {
    "type": "Point",
    "coordinates": [
      35.05444,
      41.41583
    ]
  }
}