{
  "type": "Feature",
  "properties": {
    "name": "Bojano",
    "country": "PL",
    "subdivision": "82",
    "timezone": "Europe/Warsaw"
  },
  "geometry": {
    "type": "Point",
    "coordinates": [
      18.38408,
      54.47123
    ]
  }
}