{
  "type": "Feature",
  "properties": {
    "name": "Cedry Wielkie",
    "country": "PL",
    "subdivision": "82",
    "timezone": "Europe/Warsaw"
  },
  "geometry": {
    "type": "Point",
    "coordinates": [
      18.84567,
      54.24707
    ]
  }
}