{
  "type": "Feature",
  "properties": {
    "name": "Chwaszczyno",
    "country": "PL",
    "subdivision": "82",
    "timezone": "Europe/Warsaw"
  },
  "geometry": {
    "type": "Point",
    "coordinates": [
      18.41875,
      54.44379
    ]
  }
}