{
  "type": "Feature",
  "properties": {
    "name": "Chłapowo",
    "country": "PL",
    "subdivision": "82",
    "timezone": "Europe/Warsaw"
  },
  "geometry": {
    "type": "Point",
    "coordinates": [
      18.37352,
      54.80365
    ]
  }
}