{
  "type": "Feature",
  "properties": {
    "name": "Czarne",
    "country": "PL",
    "subdivision": "82",
    "timezone": "Europe/Warsaw"
  },
  "geometry": {
    "type": "Point",
    "coordinates": [
      16.93834,
      53.6842
    ]
  }
}