{
  "type": "Feature",
  "properties": {
    "name": "Debrzno",
    "country": "PL",
    "subdivision": "82",
    "timezone": "Europe/Warsaw"
  },
  "geometry": {
    "type": "Point",
    "coordinates": [
      17.23643,
      53.53817
    ]
  }
}