{
  "type": "Feature",
  "properties": {
    "name": "Gdynia",
    "country": "PL",
    "subdivision": "82",
    "timezone": "Europe/Warsaw"
  },
  "geometry": {
    "type": "Point",
    "coordinates": [
      18.53188,
      54.51889
    ]
  }
}