{
  "type": "Feature",
  "properties": {
    "name": "Kępice",
    "country": "PL",
    "subdivision": "82",
    "timezone": "Europe/Warsaw"
  },
  "geometry": {
    "type": "Point",
    "coordinates": [
      16.88968,
      54.24111
    ]
  }
}