{
  "type": "Feature",
  "properties": {
    "name": "Luzino",
    "country": "PL",
    "subdivision": "82",
    "timezone": "Europe/Warsaw"
  },
  "geometry": {
    "type": "Point",
    "coordinates": [
      18.10907,
      54.56604
    ]
  }
}