{
  "type": "Feature",
  "properties": {
    "name": "Miłoradz",
    "country": "PL",
    "subdivision": "82",
    "timezone": "Europe/Warsaw"
  },
  "geometry": {
    "type": "Point",
    "coordinates": [
      18.91846,
      54.01392
    ]
  }
}