{
  "type": "Feature",
  "properties": {
    "name": "Osiek",
    "country": "PL",
    "subdivision": "82",
    "timezone": "Europe/Warsaw"
  },
  "geometry": {
    "type": "Point",
    "coordinates": [
      18.49051,
      53.72226
    ]
  }
}