{
  "type": "Feature",
  "properties": {
    "name": "Puck",
    "country": "PL",
    "subdivision": "82",
    "timezone": "Europe/Warsaw"
  },
  "geometry": {
    "type": "Point",
    "coordinates": [
      18.40841,
      54.7179
    ]
  }
}