{
  "type": "Feature",
  "properties": {
    "name": "Smętowo Graniczne",
    "country": "PL",
    "subdivision": "82",
    "timezone": "Europe/Warsaw"
  },
  "geometry": {
    "type": "Point",
    "coordinates": [
      18.68586,
      53.74638
    ]
  }
}