{
  "type": "Feature",
  "properties": {
    "name": "Stary Targ",
    "country": "PL",
    "subdivision": "82",
    "timezone": "Europe/Warsaw"
  },
  "geometry": {
    "type": "Point",
    "coordinates": [
      19.17003,
      53.92335
    ]
  }
}