{
  "type": "Feature",
  "properties": {
    "name": "Strzelno",
    "country": "PL",
    "subdivision": "82",
    "timezone": "Europe/Warsaw"
  },
  "geometry": {
    "type": "Point",
    "coordinates": [
      18.32515,
      54.78564
    ]
  }
}