{
  "type": "Feature",
  "properties": {
    "name": "Słupsk",
    "country": "PL",
    "subdivision": "82",
    "timezone": "Europe/Warsaw"
  },
  "geometry": {
    "type": "Point",
    "coordinates": [
      17.02872,
      54.46405
    ]
  }
}