{
  "type": "Feature",
  "properties": {
    "name": "Tuchomie",
    "country": "PL",
    "subdivision": "82",
    "timezone": "Europe/Warsaw"
  },
  "geometry": {
    "type": "Point",
    "coordinates": [
      17.33634,
      54.11522
    ]
  }
}