{
  "type": "Feature",
  "properties": {
    "name": "Zblewo",
    "country": "PL",
    "subdivision": "82",
    "timezone": "Europe/Warsaw"
  },
  "geometry": {
    "type": "Point",
    "coordinates": [
      18.32262,
      53.93366
    ]
  }
}