{
  "type": "Feature",
  "properties": {
    "name": "Oke Ila",
    "country": "NG",
    "subdivision": "54",
    "timezone": "Africa/Lagos"
  },
  "geometry": {
    "type": "Point",
    "coordinates": [
      4.98333,
      7.95
    ]
  }
}