{
  "type": "Feature",
  "properties": {
    "name": "Omuo-Ekiti",
    "country": "NG",
    "subdivision": "54",
    "timezone": "Africa/Lagos"
  },
  "geometry": {
    "type": "Point",
    "coordinates": [
      5.72227,
      7.75833
    ]
  }
}