{
  "type": "Feature",
  "properties": {
    "name": "Cruz Bay",
    "country": "VI",
    "subdivision": "020",
    "timezone": "America/St_Thomas"
  },
  "geometry": {
    "type": "Point",
    "coordinates": [
      -64.79375,
      18.33134
    ]
  }
}