{
  "type": "Feature",
  "properties": {
    "name": "Badaogu",
    "country": "CN",
    "subdivision": "28",
    "timezone": "Asia/Shanghai"
  },
  "geometry": {
    "type": "Point",
    "coordinates": [
      117.32972,
      39.47333
    ]
  }
}