{
  "type": "Feature",
  "properties": {
    "name": "Bangjun",
    "country": "CN",
    "subdivision": "28",
    "timezone": "Asia/Shanghai"
  },
  "geometry": {
    "type": "Point",
    "coordinates": [
      117.26278,
      39.99111
    ]
  }
}