{
  "type": "Feature",
  "properties": {
    "name": "Beilizigu",
    "country": "CN",
    "subdivision": "28",
    "timezone": "Asia/Shanghai"
  },
  "geometry": {
    "type": "Point",
    "coordinates": [
      117.465,
      39.49139
    ]
  }
}