{
  "type": "Feature",
  "properties": {
    "name": "Chengtougu",
    "country": "CN",
    "subdivision": "28",
    "timezone": "Asia/Shanghai"
  },
  "geometry": {
    "type": "Point",
    "coordinates": [
      117.77889,
      39.14
    ]
  }
}