{
  "type": "Feature",
  "properties": {
    "name": "Dabaizhuang",
    "country": "CN",
    "subdivision": "28",
    "timezone": "Asia/Shanghai"
  },
  "geometry": {
    "type": "Point",
    "coordinates": [
      117.38028,
      39.44472
    ]
  }
}