{
  "type": "Feature",
  "properties": {
    "name": "Darenzhuang",
    "country": "CN",
    "subdivision": "28",
    "timezone": "Asia/Shanghai"
  },
  "geometry": {
    "type": "Point",
    "coordinates": [
      117.25194,
      39.03889
    ]
  }
}