{
  "type": "Feature",
  "properties": {
    "name": "Dawangtai",
    "country": "CN",
    "subdivision": "28",
    "timezone": "Asia/Shanghai"
  },
  "geometry": {
    "type": "Point",
    "coordinates": [
      117.48502,
      39.27504
    ]
  }
}