{
  "type": "Feature",
  "properties": {
    "name": "Dongnigu",
    "country": "CN",
    "subdivision": "28",
    "timezone": "Asia/Shanghai"
  },
  "geometry": {
    "type": "Point",
    "coordinates": [
      117.44396,
      39.01655
    ]
  }
}