{
  "type": "Feature",
  "properties": {
    "name": "Houxiang",
    "country": "CN",
    "subdivision": "28",
    "timezone": "Asia/Shanghai"
  },
  "geometry": {
    "type": "Point",
    "coordinates": [
      117.11583,
      39.51278
    ]
  }
}