{
  "type": "Feature",
  "properties": {
    "name": "Liukuaizhuang",
    "country": "CN",
    "subdivision": "28",
    "timezone": "Asia/Shanghai"
  },
  "geometry": {
    "type": "Point",
    "coordinates": [
      117.33941,
      39.24789
    ]
  }
}