{
  "type": "Feature",
  "properties": {
    "name": "Lizhuangzi",
    "country": "CN",
    "subdivision": "28",
    "timezone": "Asia/Shanghai"
  },
  "geometry": {
    "type": "Point",
    "coordinates": [
      117.52556,
      39.00417
    ]
  }
}