{
  "type": "Feature",
  "properties": {
    "name": "Niujiapai",
    "country": "CN",
    "subdivision": "28",
    "timezone": "Asia/Shanghai"
  },
  "geometry": {
    "type": "Point",
    "coordinates": [
      117.28944,
      39.52222
    ]
  }
}