{
  "type": "Feature",
  "properties": {
    "name": "Qiaogu",
    "country": "CN",
    "subdivision": "28",
    "timezone": "Asia/Shanghai"
  },
  "geometry": {
    "type": "Point",
    "coordinates": [
      117.72472,
      39.3125
    ]
  }
}