{
  "type": "Feature",
  "properties": {
    "name": "Sanchakou",
    "country": "CN",
    "subdivision": "28",
    "timezone": "Asia/Shanghai"
  },
  "geometry": {
    "type": "Point",
    "coordinates": [
      117.31861,
      39.78444
    ]
  }
}