{
  "type": "Feature",
  "properties": {
    "name": "Tanggu",
    "country": "CN",
    "subdivision": "28",
    "timezone": "Asia/Shanghai"
  },
  "geometry": {
    "type": "Point",
    "coordinates": [
      117.64694,
      39.02111
    ]
  }
}