{
  "type": "Feature",
  "properties": {
    "name": "Yonghe",
    "country": "CN",
    "subdivision": "28",
    "timezone": "Asia/Shanghai"
  },
  "geometry": {
    "type": "Point",
    "coordinates": [
      117.47556,
      39.07528
    ]
  }
}