{
  "type": "Feature",
  "properties": {
    "name": "Zhongxinqiao",
    "country": "CN",
    "subdivision": "28",
    "timezone": "Asia/Shanghai"
  },
  "geometry": {
    "type": "Point",
    "coordinates": [
      117.56062,
      39.03794
    ]
  }
}