{
  "type": "Feature",
  "properties": {
    "name": "Donji Vinjani",
    "country": "HR",
    "subdivision": "15",
    "timezone": "Europe/Zagreb"
  },
  "geometry": {
    "type": "Point",
    "coordinates": [
      17.24064,
      43.44613
    ]
  }
}