{
  "type": "Feature",
  "properties": {
    "name": "Imotski",
    "country": "HR",
    "subdivision": "15",
    "timezone": "Europe/Zagreb"
  },
  "geometry": {
    "type": "Point",
    "coordinates": [
      17.21667,
      43.44667
    ]
  }
}