{
  "type": "Feature",
  "properties": {
    "name": "Sinj",
    "country": "HR",
    "subdivision": "15",
    "timezone": "Europe/Zagreb"
  },
  "geometry": {
    "type": "Point",
    "coordinates": [
      16.63944,
      43.70361
    ]
  }
}