{
  "type": "Feature",
  "properties": {
    "name": "Slatine",
    "country": "HR",
    "subdivision": "15",
    "timezone": "Europe/Zagreb"
  },
  "geometry": {
    "type": "Point",
    "coordinates": [
      16.33333,
      43.49944
    ]
  }
}