{
  "type": "Feature",
  "properties": {
    "name": "TuÄepi",
    "country": "HR",
    "subdivision": "15",
    "timezone": "Europe/Zagreb"
  },
  "geometry": {
    "type": "Point",
    "coordinates": [
      17.05444,
      43.27222
    ]
  }
}