{
  "type": "Feature",
  "properties": {
    "name": "Ferreñafe",
    "country": "PE",
    "subdivision": "14",
    "timezone": "America/Lima"
  },
  "geometry": {
    "type": "Point",
    "coordinates": [
      -79.78889,
      -6.63889
    ]
  }
}