{
  "type": "Feature",
  "properties": {
    "name": "Pueblo Nuevo",
    "country": "PE",
    "subdivision": "14",
    "timezone": "America/Lima"
  },
  "geometry": {
    "type": "Point",
    "coordinates": [
      -79.88333,
      -5.71667
    ]
  }
}