{
  "type": "Feature",
  "properties": {
    "name": "Kashimnagar",
    "country": "BD",
    "subdivision": "81",
    "timezone": "Asia/Dhaka"
  },
  "geometry": {
    "type": "Point",
    "coordinates": [
      90.11595,
      23.81773
    ]
  }
}