{
  "type": "Feature",
  "properties": {
    "name": "Ramnagar",
    "country": "BD",
    "subdivision": "81",
    "timezone": "Asia/Dhaka"
  },
  "geometry": {
    "type": "Point",
    "coordinates": [
      90.17604,
      23.7772
    ]
  }
}