{
  "type": "Feature",
  "properties": {
    "name": "Banhā",
    "country": "EG",
    "subdivision": "12",
    "timezone": "Africa/Cairo"
  },
  "geometry": {
    "type": "Point",
    "coordinates": [
      31.1842,
      30.45977
    ]
  }
}