{
  "type": "Feature",
  "properties": {
    "name": "Shibīn al Qanāṭir",
    "country": "EG",
    "subdivision": "12",
    "timezone": "Africa/Cairo"
  },
  "geometry": {
    "type": "Point",
    "coordinates": [
      31.32018,
      30.31269
    ]
  }
}