{
  "type": "Feature",
  "properties": {
    "name": "Ţūkh",
    "country": "EG",
    "subdivision": "12",
    "timezone": "Africa/Cairo"
  },
  "geometry": {
    "type": "Point",
    "coordinates": [
      31.20105,
      30.35487
    ]
  }
}