{
  "type": "Feature",
  "properties": {
    "name": "Bang Saphan",
    "country": "TH",
    "subdivision": "57",
    "timezone": "Asia/Bangkok"
  },
  "geometry": {
    "type": "Point",
    "coordinates": [
      99.51167,
      11.21259
    ]
  }
}