{
  "type": "Feature",
  "properties": {
    "name": "San Pedro Sacatepéquez",
    "country": "GT",
    "subdivision": "07",
    "timezone": "America/Guatemala"
  },
  "geometry": {
    "type": "Point",
    "coordinates": [
      -90.64253,
      14.68612
    ]
  }
}