{
  "type": "Feature",
  "properties": {
    "name": "San José del Golfo",
    "country": "GT",
    "subdivision": "07",
    "timezone": "America/Guatemala"
  },
  "geometry": {
    "type": "Point",
    "coordinates": [
      -90.37228,
      14.76414
    ]
  }
}