{
  "type": "Feature",
  "properties": {
    "name": "Bon Accueil",
    "country": "MU",
    "subdivision": "13",
    "timezone": "Indian/Mauritius"
  },
  "geometry": {
    "type": "Point",
    "coordinates": [
      57.65639,
      -20.17083
    ]
  }
}