{
  "type": "Feature",
  "properties": {
    "name": "Olivia",
    "country": "MU",
    "subdivision": "13",
    "timezone": "Indian/Mauritius"
  },
  "geometry": {
    "type": "Point",
    "coordinates": [
      57.73097,
      -20.28778
    ]
  }
}