{
  "type": "Feature",
  "properties": {
    "name": "Saint Julien",
    "country": "MU",
    "subdivision": "13",
    "timezone": "Indian/Mauritius"
  },
  "geometry": {
    "type": "Point",
    "coordinates": [
      57.63639,
      -20.22639
    ]
  }
}