{
  "type": "Feature",
  "properties": {
    "name": "Abut",
    "country": "PH",
    "subdivision": "02",
    "timezone": "Asia/Manila"
  },
  "geometry": {
    "type": "Point",
    "coordinates": [
      121.60138,
      17.35423
    ]
  }
}