{
  "type": "Feature",
  "properties": {
    "name": "Afusing Centro",
    "country": "PH",
    "subdivision": "02",
    "timezone": "Asia/Manila"
  },
  "geometry": {
    "type": "Point",
    "coordinates": [
      121.6269,
      17.8526
    ]
  }
}