{
  "type": "Feature",
  "properties": {
    "name": "Aggugaddah",
    "country": "PH",
    "subdivision": "02",
    "timezone": "Asia/Manila"
  },
  "geometry": {
    "type": "Point",
    "coordinates": [
      121.8025,
      17.70016
    ]
  }
}