{
  "type": "Feature",
  "properties": {
    "name": "Bacnor East",
    "country": "PH",
    "subdivision": "02",
    "timezone": "Asia/Manila"
  },
  "geometry": {
    "type": "Point",
    "coordinates": [
      121.70375,
      17.03449
    ]
  }
}