{
  "type": "Feature",
  "properties": {
    "name": "Banganan",
    "country": "PH",
    "subdivision": "02",
    "timezone": "Asia/Manila"
  },
  "geometry": {
    "type": "Point",
    "coordinates": [
      121.0544,
      16.3144
    ]
  }
}