{
  "type": "Feature",
  "properties": {
    "name": "Buliwao",
    "country": "PH",
    "subdivision": "02",
    "timezone": "Asia/Manila"
  },
  "geometry": {
    "type": "Point",
    "coordinates": [
      121.23333,
      16.48333
    ]
  }
}