{
  "type": "Feature",
  "properties": {
    "name": "Cabagan",
    "country": "PH",
    "subdivision": "02",
    "timezone": "Asia/Manila"
  },
  "geometry": {
    "type": "Point",
    "coordinates": [
      121.76955,
      17.42782
    ]
  }
}