{
  "type": "Feature",
  "properties": {
    "name": "Cabannungan Second",
    "country": "PH",
    "subdivision": "02",
    "timezone": "Asia/Manila"
  },
  "geometry": {
    "type": "Point",
    "coordinates": [
      121.8506,
      17.1249
    ]
  }
}