{
  "type": "Feature",
  "properties": {
    "name": "Guiddam",
    "country": "PH",
    "subdivision": "02",
    "timezone": "Asia/Manila"
  },
  "geometry": {
    "type": "Point",
    "coordinates": [
      121.46617,
      18.33493
    ]
  }
}