{
  "type": "Feature",
  "properties": {
    "name": "Larion Alto",
    "country": "PH",
    "subdivision": "02",
    "timezone": "Asia/Manila"
  },
  "geometry": {
    "type": "Point",
    "coordinates": [
      121.76062,
      17.63082
    ]
  }
}