{
  "type": "Feature",
  "properties": {
    "name": "Masaya Sur",
    "country": "PH",
    "subdivision": "02",
    "timezone": "Asia/Manila"
  },
  "geometry": {
    "type": "Point",
    "coordinates": [
      121.74743,
      16.50017
    ]
  }
}