{
  "type": "Feature",
  "properties": {
    "name": "Minante Segundo",
    "country": "PH",
    "subdivision": "02",
    "timezone": "Asia/Manila"
  },
  "geometry": {
    "type": "Point",
    "coordinates": [
      121.76191,
      16.9022
    ]
  }
}