{
  "type": "Feature",
  "properties": {
    "name": "Naguilian",
    "country": "PH",
    "subdivision": "02",
    "timezone": "Asia/Manila"
  },
  "geometry": {
    "type": "Point",
    "coordinates": [
      121.83704,
      17.02315
    ]
  }
}