{
  "type": "Feature",
  "properties": {
    "name": "San Mateo",
    "country": "PH",
    "subdivision": "02",
    "timezone": "Asia/Manila"
  },
  "geometry": {
    "type": "Point",
    "coordinates": [
      121.74534,
      17.13754
    ]
  }
}