{
  "type": "Feature",
  "properties": {
    "name": "Santiago",
    "country": "PH",
    "subdivision": "02",
    "timezone": "Asia/Manila"
  },
  "geometry": {
    "type": "Point",
    "coordinates": [
      121.5487,
      16.68808
    ]
  }
}