{
  "type": "Feature",
  "properties": {
    "name": "Uddiawan",
    "country": "PH",
    "subdivision": "02",
    "timezone": "Asia/Manila"
  },
  "geometry": {
    "type": "Point",
    "coordinates": [
      121.15124,
      16.55888
    ]
  }
}