{
  "type": "Feature",
  "properties": {
    "name": "Upi",
    "country": "PH",
    "subdivision": "02",
    "timezone": "Asia/Manila"
  },
  "geometry": {
    "type": "Point",
    "coordinates": [
      121.83453,
      17.08262
    ]
  }
}