{
  "type": "Feature",
  "properties": {
    "name": "Berber",
    "country": "SD",
    "subdivision": "53",
    "timezone": "Africa/Khartoum"
  },
  "geometry": {
    "type": "Point",
    "coordinates": [
      33.98299,
      18.02158
    ]
  }
}