{
  "type": "Feature",
  "properties": {
    "name": "Nizwá",
    "country": "OM",
    "subdivision": "01",
    "timezone": "Asia/Muscat"
  },
  "geometry": {
    "type": "Point",
    "coordinates": [
      57.53333,
      22.93333
    ]
  }
}