{
  "type": "Feature",
  "properties": {
    "name": "Cenicero",
    "country": "ES",
    "subdivision": "27",
    "timezone": "Europe/Madrid"
  },
  "geometry": {
    "type": "Point",
    "coordinates": [
      -2.64412,
      42.4813
    ]
  }
}