{
  "type": "Feature",
  "properties": {
    "name": "Rincón de Soto",
    "country": "ES",
    "subdivision": "27",
    "timezone": "Europe/Madrid"
  },
  "geometry": {
    "type": "Point",
    "coordinates": [
      -1.85214,
      42.23475
    ]
  }
}