{
  "type": "Feature",
  "properties": {
    "name": "Bình Long",
    "country": "VN",
    "subdivision": "76",
    "timezone": "Asia/Ho_Chi_Minh"
  },
  "geometry": {
    "type": "Point",
    "coordinates": [
      106.60586,
      11.64711
    ]
  }
}