{
  "type": "Feature",
  "properties": {
    "name": "Luthern",
    "country": "CH",
    "subdivision": "LU",
    "timezone": "Europe/Zurich"
  },
  "geometry": {
    "type": "Point",
    "coordinates": [
      7.91692,
      47.05753
    ]
  }
}