{
  "type": "Feature",
  "properties": {
    "name": "Menznau",
    "country": "CH",
    "subdivision": "LU",
    "timezone": "Europe/Zurich"
  },
  "geometry": {
    "type": "Point",
    "coordinates": [
      8.03971,
      47.08364
    ]
  }
}