{
  "type": "Feature",
  "properties": {
    "name": "Nebikon",
    "country": "CH",
    "subdivision": "LU",
    "timezone": "Europe/Zurich"
  },
  "geometry": {
    "type": "Point",
    "coordinates": [
      7.97769,
      47.19185
    ]
  }
}