{
  "type": "Feature",
  "properties": {
    "name": "Römerswil",
    "country": "CH",
    "subdivision": "LU",
    "timezone": "Europe/Zurich"
  },
  "geometry": {
    "type": "Point",
    "coordinates": [
      8.24528,
      47.16881
    ]
  }
}