{
  "type": "Feature",
  "properties": {
    "name": "Berat",
    "country": "AL",
    "subdivision": "40",
    "timezone": "Europe/Tirane"
  },
  "geometry": {
    "type": "Point",
    "coordinates": [
      19.95222,
      40.70583
    ]
  }
}