{
  "type": "Feature",
  "properties": {
    "name": "1ra. Sección de Izapa",
    "country": "MX",
    "subdivision": "05",
    "timezone": "America/Mexico_City"
  },
  "geometry": {
    "type": "Point",
    "coordinates": [
      -92.17083,
      14.92083
    ]
  }
}