{
  "type": "Feature",
  "properties": {
    "name": "Alfonso Moguel",
    "country": "MX",
    "subdivision": "05",
    "timezone": "America/Mexico_City"
  },
  "geometry": {
    "type": "Point",
    "coordinates": [
      -93.50639,
      16.6675
    ]
  }
}