{
  "type": "Feature",
  "properties": {
    "name": "Álvaro Obregón",
    "country": "MX",
    "subdivision": "05",
    "timezone": "America/Mexico_City"
  },
  "geometry": {
    "type": "Point",
    "coordinates": [
      -92.37813,
      14.92231
    ]
  }
}