{
  "type": "Feature",
  "properties": {
    "name": "Amado Nervo",
    "country": "MX",
    "subdivision": "05",
    "timezone": "America/Mexico_City"
  },
  "geometry": {
    "type": "Point",
    "coordinates": [
      -92.24581,
      17.23107
    ]
  }
}