{
  "type": "Feature",
  "properties": {
    "name": "América Libre",
    "country": "MX",
    "subdivision": "05",
    "timezone": "America/Mexico_City"
  },
  "geometry": {
    "type": "Point",
    "coordinates": [
      -92.99185,
      16.61462
    ]
  }
}