{
  "type": "Feature",
  "properties": {
    "name": "Belisario Domínguez",
    "country": "MX",
    "subdivision": "05",
    "timezone": "America/Mexico_City"
  },
  "geometry": {
    "type": "Point",
    "coordinates": [
      -92.66053,
      16.89186
    ]
  }
}