{
  "type": "Feature",
  "properties": {
    "name": "Buenavista (Matasanos)",
    "country": "MX",
    "subdivision": "05",
    "timezone": "America/Mexico_City"
  },
  "geometry": {
    "type": "Point",
    "coordinates": [
      -93.06694,
      17.10778
    ]
  }
}