{
  "type": "Feature",
  "properties": {
    "name": "Cabeza de Toro",
    "country": "MX",
    "subdivision": "05",
    "timezone": "America/Mexico_City"
  },
  "geometry": {
    "type": "Point",
    "coordinates": [
      -93.78256,
      15.93698
    ]
  }
}