{
  "type": "Feature",
  "properties": {
    "name": "Cacahoatán",
    "country": "MX",
    "subdivision": "05",
    "timezone": "America/Mexico_City"
  },
  "geometry": {
    "type": "Point",
    "coordinates": [
      -92.16376,
      14.99201
    ]
  }
}