{
  "type": "Feature",
  "properties": {
    "name": "Cenobio Aguilar (La Trinidad)",
    "country": "MX",
    "subdivision": "05",
    "timezone": "America/Mexico_City"
  },
  "geometry": {
    "type": "Point",
    "coordinates": [
      -92.31944,
      17.40472
    ]
  }
}