{
  "type": "Feature",
  "properties": {
    "name": "Chalam",
    "country": "MX",
    "subdivision": "05",
    "timezone": "America/Mexico_City"
  },
  "geometry": {
    "type": "Point",
    "coordinates": [
      -92.55009,
      16.88771
    ]
  }
}