{
  "type": "Feature",
  "properties": {
    "name": "Chicumtantic",
    "country": "MX",
    "subdivision": "05",
    "timezone": "America/Mexico_City"
  },
  "geometry": {
    "type": "Point",
    "coordinates": [
      -92.60528,
      16.86556
    ]
  }
}