{
  "type": "Feature",
  "properties": {
    "name": "Chulum Cárdenas",
    "country": "MX",
    "subdivision": "05",
    "timezone": "America/Mexico_City"
  },
  "geometry": {
    "type": "Point",
    "coordinates": [
      -92.57389,
      17.38417
    ]
  }
}