{
  "type": "Feature",
  "properties": {
    "name": "Ciudad Hidalgo",
    "country": "MX",
    "subdivision": "05",
    "timezone": "America/Mexico_City"
  },
  "geometry": {
    "type": "Point",
    "coordinates": [
      -92.15217,
      14.68148
    ]
  }
}