{
  "type": "Feature",
  "properties": {
    "name": "Colonia Obrera",
    "country": "MX",
    "subdivision": "05",
    "timezone": "America/Mexico_City"
  },
  "geometry": {
    "type": "Point",
    "coordinates": [
      -92.49806,
      15.09806
    ]
  }
}