{
  "type": "Feature",
  "properties": {
    "name": "Comitán",
    "country": "MX",
    "subdivision": "05",
    "timezone": "America/Mexico_City"
  },
  "geometry": {
    "type": "Point",
    "coordinates": [
      -92.13515,
      16.2471
    ]
  }
}