{
  "type": "Feature",
  "properties": {
    "name": "Copainalá",
    "country": "MX",
    "subdivision": "05",
    "timezone": "America/Mexico_City"
  },
  "geometry": {
    "type": "Point",
    "coordinates": [
      -93.21059,
      17.09366
    ]
  }
}