{
  "type": "Feature",
  "properties": {
    "name": "Cruztón",
    "country": "MX",
    "subdivision": "05",
    "timezone": "America/Mexico_City"
  },
  "geometry": {
    "type": "Point",
    "coordinates": [
      -92.57917,
      16.76167
    ]
  }
}