{
  "type": "Feature",
  "properties": {
    "name": "El Copal",
    "country": "MX",
    "subdivision": "05",
    "timezone": "America/Mexico_City"
  },
  "geometry": {
    "type": "Point",
    "coordinates": [
      -92.92625,
      16.96729
    ]
  }
}