{
  "type": "Feature",
  "properties": {
    "name": "El Palmar Grande",
    "country": "MX",
    "subdivision": "05",
    "timezone": "America/Mexico_City"
  },
  "geometry": {
    "type": "Point",
    "coordinates": [
      -92.25518,
      15.49858
    ]
  }
}