{
  "type": "Feature",
  "properties": {
    "name": "El Parral",
    "country": "MX",
    "subdivision": "05",
    "timezone": "America/Mexico_City"
  },
  "geometry": {
    "type": "Point",
    "coordinates": [
      -93.00567,
      16.37035
    ]
  }
}