{
  "type": "Feature",
  "properties": {
    "name": "El Palmarcito",
    "country": "MX",
    "subdivision": "05",
    "timezone": "America/Mexico_City"
  },
  "geometry": {
    "type": "Point",
    "coordinates": [
      -93.21387,
      15.49728
    ]
  }
}