{
  "type": "Feature",
  "properties": {
    "name": "El Triunfo 1ra. Sección (Cardona)",
    "country": "MX",
    "subdivision": "05",
    "timezone": "America/Mexico_City"
  },
  "geometry": {
    "type": "Point",
    "coordinates": [
      -93.23306,
      17.60778
    ]
  }
}