{
  "type": "Feature",
  "properties": {
    "name": "Francisco Sarabia",
    "country": "MX",
    "subdivision": "05",
    "timezone": "America/Mexico_City"
  },
  "geometry": {
    "type": "Point",
    "coordinates": [
      -92.10465,
      16.15879
    ]
  }
}