{
  "type": "Feature",
  "properties": {
    "name": "Hidalgo",
    "country": "MX",
    "subdivision": "05",
    "timezone": "America/Mexico_City"
  },
  "geometry": {
    "type": "Point",
    "coordinates": [
      -92.74189,
      15.34984
    ]
  }
}