{
  "type": "Feature",
  "properties": {
    "name": "Huehuetán",
    "country": "MX",
    "subdivision": "05",
    "timezone": "America/Mexico_City"
  },
  "geometry": {
    "type": "Point",
    "coordinates": [
      -92.38249,
      15.01981
    ]
  }
}