{
  "type": "Feature",
  "properties": {
    "name": "Huizachal",
    "country": "MX",
    "subdivision": "05",
    "timezone": "America/Mexico_City"
  },
  "geometry": {
    "type": "Point",
    "coordinates": [
      -93.80011,
      16.05184
    ]
  }
}