{
  "type": "Feature",
  "properties": {
    "name": "Jesús María Garza",
    "country": "MX",
    "subdivision": "05",
    "timezone": "America/Mexico_City"
  },
  "geometry": {
    "type": "Point",
    "coordinates": [
      -93.29368,
      16.39669
    ]
  }
}