{
  "type": "Feature",
  "properties": {
    "name": "Jiquilpan (Estación Bonanza)",
    "country": "MX",
    "subdivision": "05",
    "timezone": "America/Mexico_City"
  },
  "geometry": {
    "type": "Point",
    "coordinates": [
      -92.7475,
      15.34194
    ]
  }
}