{
  "type": "Feature",
  "properties": {
    "name": "La Concordia",
    "country": "MX",
    "subdivision": "05",
    "timezone": "America/Mexico_City"
  },
  "geometry": {
    "type": "Point",
    "coordinates": [
      -92.69018,
      16.11774
    ]
  }
}