{
  "type": "Feature",
  "properties": {
    "name": "La Esperanza (El Zapotal)",
    "country": "MX",
    "subdivision": "05",
    "timezone": "America/Mexico_City"
  },
  "geometry": {
    "type": "Point",
    "coordinates": [
      -93.16417,
      15.44917
    ]
  }
}