{
  "type": "Feature",
  "properties": {
    "name": "La Esperanza",
    "country": "MX",
    "subdivision": "05",
    "timezone": "America/Mexico_City"
  },
  "geometry": {
    "type": "Point",
    "coordinates": [
      -91.86874,
      16.15191
    ]
  }
}