{
  "type": "Feature",
  "properties": {
    "name": "Maravillas",
    "country": "MX",
    "subdivision": "05",
    "timezone": "America/Mexico_City"
  },
  "geometry": {
    "type": "Point",
    "coordinates": [
      -92.55774,
      17.13674
    ]
  }
}