{
  "type": "Feature",
  "properties": {
    "name": "Mazapa",
    "country": "MX",
    "subdivision": "05",
    "timezone": "America/Mexico_City"
  },
  "geometry": {
    "type": "Point",
    "coordinates": [
      -92.1878,
      15.38773
    ]
  }
}