{
  "type": "Feature",
  "properties": {
    "name": "Miguel Utrilla (Los Chorros)",
    "country": "MX",
    "subdivision": "05",
    "timezone": "America/Mexico_City"
  },
  "geometry": {
    "type": "Point",
    "coordinates": [
      -92.47972,
      16.94278
    ]
  }
}