{
  "type": "Feature",
  "properties": {
    "name": "Navenchauc",
    "country": "MX",
    "subdivision": "05",
    "timezone": "America/Mexico_City"
  },
  "geometry": {
    "type": "Point",
    "coordinates": [
      -92.779,
      16.73501
    ]
  }
}