{
  "type": "Feature",
  "properties": {
    "name": "Nueva Tenochtitlán (Rizo de Oro)",
    "country": "MX",
    "subdivision": "05",
    "timezone": "America/Mexico_City"
  },
  "geometry": {
    "type": "Point",
    "coordinates": [
      -94.08056,
      16.47639
    ]
  }
}