{
  "type": "Feature",
  "properties": {
    "name": "Nuevo Pacayal",
    "country": "MX",
    "subdivision": "05",
    "timezone": "America/Mexico_City"
  },
  "geometry": {
    "type": "Point",
    "coordinates": [
      -92.31538,
      15.6601
    ]
  }
}