{
  "type": "Feature",
  "properties": {
    "name": "Ojo de Agua",
    "country": "MX",
    "subdivision": "05",
    "timezone": "America/Mexico_City"
  },
  "geometry": {
    "type": "Point",
    "coordinates": [
      -91.75794,
      16.15773
    ]
  }
}