{
  "type": "Feature",
  "properties": {
    "name": "Oxchuc",
    "country": "MX",
    "subdivision": "05",
    "timezone": "America/Mexico_City"
  },
  "geometry": {
    "type": "Point",
    "coordinates": [
      -92.34455,
      16.78588
    ]
  }
}