{
  "type": "Feature",
  "properties": {
    "name": "Oxinam",
    "country": "MX",
    "subdivision": "05",
    "timezone": "America/Mexico_City"
  },
  "geometry": {
    "type": "Point",
    "coordinates": [
      -92.54917,
      16.86306
    ]
  }
}