{
  "type": "Feature",
  "properties": {
    "name": "Palenque",
    "country": "MX",
    "subdivision": "05",
    "timezone": "America/Mexico_City"
  },
  "geometry": {
    "type": "Point",
    "coordinates": [
      -91.98248,
      17.50953
    ]
  }
}