{
  "type": "Feature",
  "properties": {
    "name": "Potrerillo",
    "country": "MX",
    "subdivision": "05",
    "timezone": "America/Mexico_City"
  },
  "geometry": {
    "type": "Point",
    "coordinates": [
      -92.02059,
      15.63096
    ]
  }
}