{
  "type": "Feature",
  "properties": {
    "name": "Primer Cantón",
    "country": "MX",
    "subdivision": "05",
    "timezone": "America/Mexico_City"
  },
  "geometry": {
    "type": "Point",
    "coordinates": [
      -92.44,
      15.12056
    ]
  }
}