{
  "type": "Feature",
  "properties": {
    "name": "Reforma",
    "country": "MX",
    "subdivision": "05",
    "timezone": "America/Mexico_City"
  },
  "geometry": {
    "type": "Point",
    "coordinates": [
      -93.14897,
      17.86519
    ]
  }
}