{
  "type": "Feature",
  "properties": {
    "name": "Rincón Chamula",
    "country": "MX",
    "subdivision": "05",
    "timezone": "America/Mexico_City"
  },
  "geometry": {
    "type": "Point",
    "coordinates": [
      -92.93912,
      17.20718
    ]
  }
}