{
  "type": "Feature",
  "properties": {
    "name": "Saltillo",
    "country": "MX",
    "subdivision": "05",
    "timezone": "America/Mexico_City"
  },
  "geometry": {
    "type": "Point",
    "coordinates": [
      -91.9489,
      16.39359
    ]
  }
}