{
  "type": "Feature",
  "properties": {
    "name": "San Cayetano",
    "country": "MX",
    "subdivision": "05",
    "timezone": "America/Mexico_City"
  },
  "geometry": {
    "type": "Point",
    "coordinates": [
      -92.76016,
      16.96119
    ]
  }
}