{
  "type": "Feature",
  "properties": {
    "name": "San Francisco (El Calvito)",
    "country": "MX",
    "subdivision": "05",
    "timezone": "America/Mexico_City"
  },
  "geometry": {
    "type": "Point",
    "coordinates": [
      -92.56194,
      16.32167
    ]
  }
}