{
  "type": "Feature",
  "properties": {
    "name": "San José Chapayal",
    "country": "MX",
    "subdivision": "05",
    "timezone": "America/Mexico_City"
  },
  "geometry": {
    "type": "Point",
    "coordinates": [
      -92.89028,
      17.30056
    ]
  }
}