{
  "type": "Feature",
  "properties": {
    "name": "San Francisco Jaconá",
    "country": "MX",
    "subdivision": "05",
    "timezone": "America/Mexico_City"
  },
  "geometry": {
    "type": "Point",
    "coordinates": [
      -93.0325,
      17.26278
    ]
  }
}