{
  "type": "Feature",
  "properties": {
    "name": "San Miguel",
    "country": "MX",
    "subdivision": "05",
    "timezone": "America/Mexico_City"
  },
  "geometry": {
    "type": "Point",
    "coordinates": [
      -92.00762,
      17.36324
    ]
  }
}