{
  "type": "Feature",
  "properties": {
    "name": "San Miguel la Sardina",
    "country": "MX",
    "subdivision": "05",
    "timezone": "America/Mexico_City"
  },
  "geometry": {
    "type": "Point",
    "coordinates": [
      -93.3525,
      17.29417
    ]
  }
}