{
  "type": "Feature",
  "properties": {
    "name": "San Isidro las Banderas",
    "country": "MX",
    "subdivision": "05",
    "timezone": "America/Mexico_City"
  },
  "geometry": {
    "type": "Point",
    "coordinates": [
      -93.06028,
      17.23028
    ]
  }
}