{
  "type": "Feature",
  "properties": {
    "name": "Santa Rita",
    "country": "MX",
    "subdivision": "05",
    "timezone": "America/Mexico_City"
  },
  "geometry": {
    "type": "Point",
    "coordinates": [
      -91.975,
      16.13167
    ]
  }
}