{
  "type": "Feature",
  "properties": {
    "name": "Sibacá",
    "country": "MX",
    "subdivision": "05",
    "timezone": "America/Mexico_City"
  },
  "geometry": {
    "type": "Point",
    "coordinates": [
      -92.14006,
      16.93093
    ]
  }
}