{
  "type": "Feature",
  "properties": {
    "name": "Tiltepec",
    "country": "MX",
    "subdivision": "05",
    "timezone": "America/Mexico_City"
  },
  "geometry": {
    "type": "Point",
    "coordinates": [
      -93.86972,
      16.39389
    ]
  }
}