{
  "type": "Feature",
  "properties": {
    "name": "Tocob Leglemal",
    "country": "MX",
    "subdivision": "05",
    "timezone": "America/Mexico_City"
  },
  "geometry": {
    "type": "Point",
    "coordinates": [
      -92.37833,
      17.23389
    ]
  }
}