{
  "type": "Feature",
  "properties": {
    "name": "Tzinil",
    "country": "MX",
    "subdivision": "05",
    "timezone": "America/Mexico_City"
  },
  "geometry": {
    "type": "Point",
    "coordinates": [
      -92.32222,
      16.25778
    ]
  }
}