{
  "type": "Feature",
  "properties": {
    "name": "Tziscao",
    "country": "MX",
    "subdivision": "05",
    "timezone": "America/Mexico_City"
  },
  "geometry": {
    "type": "Point",
    "coordinates": [
      -91.66641,
      16.08155
    ]
  }
}