{
  "type": "Feature",
  "properties": {
    "name": "Tzoeptic",
    "country": "MX",
    "subdivision": "05",
    "timezone": "America/Mexico_City"
  },
  "geometry": {
    "type": "Point",
    "coordinates": [
      -92.56806,
      16.88278
    ]
  }
}