{
  "type": "Feature",
  "properties": {
    "name": "Verapaz",
    "country": "MX",
    "subdivision": "05",
    "timezone": "America/Mexico_City"
  },
  "geometry": {
    "type": "Point",
    "coordinates": [
      -92.06199,
      15.71166
    ]
  }
}