{
  "type": "Feature",
  "properties": {
    "name": "Villaflores",
    "country": "MX",
    "subdivision": "05",
    "timezone": "America/Mexico_City"
  },
  "geometry": {
    "type": "Point",
    "coordinates": [
      -93.27037,
      16.2341
    ]
  }
}