{
  "type": "Feature",
  "properties": {
    "name": "Zacatonal de Juárez",
    "country": "MX",
    "subdivision": "05",
    "timezone": "America/Mexico_City"
  },
  "geometry": {
    "type": "Point",
    "coordinates": [
      -92.79936,
      17.27097
    ]
  }
}