{
  "type": "Feature",
  "properties": {
    "name": "Zacualpa",
    "country": "MX",
    "subdivision": "05",
    "timezone": "America/Mexico_City"
  },
  "geometry": {
    "type": "Point",
    "coordinates": [
      -92.62705,
      15.1682
    ]
  }
}