{
  "type": "Feature",
  "properties": {
    "name": "Beau Bassin-Rose Hill",
    "country": "MU",
    "subdivision": "17",
    "timezone": "Indian/Mauritius"
  },
  "geometry": {
    "type": "Point",
    "coordinates": [
      57.46609,
      -20.23325
    ]
  }
}