{
  "type": "Feature",
  "properties": {
    "name": "Ebene",
    "country": "MU",
    "subdivision": "17",
    "timezone": "Indian/Mauritius"
  },
  "geometry": {
    "type": "Point",
    "coordinates": [
      57.49163,
      -20.24494
    ]
  }
}