{
  "type": "Feature",
  "properties": {
    "name": "Budapest XV. kerület",
    "country": "HU",
    "subdivision": "05",
    "timezone": "Europe/Budapest"
  },
  "geometry": {
    "type": "Point",
    "coordinates": [
      19.11681,
      47.56263
    ]
  }
}