{
  "type": "Feature",
  "properties": {
    "name": "Budapest I. kerület",
    "country": "HU",
    "subdivision": "05",
    "timezone": "Europe/Budapest"
  },
  "geometry": {
    "type": "Point",
    "coordinates": [
      19.03961,
      47.49705
    ]
  }
}