{
  "type": "Feature",
  "properties": {
    "name": "Bilky",
    "country": "UA",
    "subdivision": "25",
    "timezone": "Europe/Uzhgorod"
  },
  "geometry": {
    "type": "Point",
    "coordinates": [
      23.13811,
      48.32629
    ]
  }
}