{
  "type": "Feature",
  "properties": {
    "name": "Drahovo",
    "country": "UA",
    "subdivision": "25",
    "timezone": "Europe/Uzhgorod"
  },
  "geometry": {
    "type": "Point",
    "coordinates": [
      23.54868,
      48.23789
    ]
  }
}