{
  "type": "Feature",
  "properties": {
    "name": "Koson",
    "country": "UA",
    "subdivision": "25",
    "timezone": "Europe/Uzhgorod"
  },
  "geometry": {
    "type": "Point",
    "coordinates": [
      22.45896,
      48.25482
    ]
  }
}