{
  "type": "Feature",
  "properties": {
    "name": "Nove Davydkovo",
    "country": "UA",
    "subdivision": "25",
    "timezone": "Europe/Uzhgorod"
  },
  "geometry": {
    "type": "Point",
    "coordinates": [
      22.6229,
      48.44079
    ]
  }
}