{
  "type": "Feature",
  "properties": {
    "name": "Perechyn",
    "country": "UA",
    "subdivision": "25",
    "timezone": "Europe/Uzhgorod"
  },
  "geometry": {
    "type": "Point",
    "coordinates": [
      22.47718,
      48.73494
    ]
  }
}