{
  "type": "Feature",
  "properties": {
    "name": "Rokosovo",
    "country": "UA",
    "subdivision": "25",
    "timezone": "Europe/Uzhgorod"
  },
  "geometry": {
    "type": "Point",
    "coordinates": [
      23.17849,
      48.20829
    ]
  }
}