{
  "type": "Feature",
  "properties": {
    "name": "Velyki Berehy",
    "country": "UA",
    "subdivision": "25",
    "timezone": "Europe/Uzhgorod"
  },
  "geometry": {
    "type": "Point",
    "coordinates": [
      22.74985,
      48.23161
    ]
  }
}