{
  "type": "Feature",
  "properties": {
    "name": "Velykyy Bychkiv",
    "country": "UA",
    "subdivision": "25",
    "timezone": "Europe/Uzhgorod"
  },
  "geometry": {
    "type": "Point",
    "coordinates": [
      24.01061,
      47.96821
    ]
  }
}