{
  "type": "Feature",
  "properties": {
    "name": "Volovets",
    "country": "UA",
    "subdivision": "25",
    "timezone": "Europe/Uzhgorod"
  },
  "geometry": {
    "type": "Point",
    "coordinates": [
      23.1851,
      48.7109
    ]
  }
}