{
  "type": "Feature",
  "properties": {
    "name": "Karlovac",
    "country": "HR",
    "subdivision": "05",
    "timezone": "Europe/Zagreb"
  },
  "geometry": {
    "type": "Point",
    "coordinates": [
      15.55,
      45.49167
    ]
  }
}