{
  "type": "Feature",
  "properties": {
    "name": "Plaški",
    "country": "HR",
    "subdivision": "05",
    "timezone": "Europe/Zagreb"
  },
  "geometry": {
    "type": "Point",
    "coordinates": [
      15.36806,
      45.07639
    ]
  }
}