{
  "type": "Feature",
  "properties": {
    "name": "Djambala",
    "country": "CG",
    "subdivision": "08",
    "timezone": "Africa/Brazzaville"
  },
  "geometry": {
    "type": "Point",
    "coordinates": [
      14.75333,
      -2.54472
    ]
  }
}