{
  "type": "Feature",
  "properties": {
    "name": "Gamboma",
    "country": "CG",
    "subdivision": "08",
    "timezone": "Africa/Brazzaville"
  },
  "geometry": {
    "type": "Point",
    "coordinates": [
      15.86444,
      -1.87639
    ]
  }
}