{
  "type": "Feature",
  "properties": {
    "name": "Acriș",
    "country": "RO",
    "subdivision": "09",
    "timezone": "Europe/Bucharest"
  },
  "geometry": {
    "type": "Point",
    "coordinates": [
      25.99247,
      45.63673
    ]
  }
}