{
  "type": "Feature",
  "properties": {
    "name": "Apaţa",
    "country": "RO",
    "subdivision": "09",
    "timezone": "Europe/Bucharest"
  },
  "geometry": {
    "type": "Point",
    "coordinates": [
      25.51667,
      45.95
    ]
  }
}