{
  "type": "Feature",
  "properties": {
    "name": "Augustin",
    "country": "RO",
    "subdivision": "09",
    "timezone": "Europe/Bucharest"
  },
  "geometry": {
    "type": "Point",
    "coordinates": [
      25.55333,
      46.04613
    ]
  }
}