{
  "type": "Feature",
  "properties": {
    "name": "Bod",
    "country": "RO",
    "subdivision": "09",
    "timezone": "Europe/Bucharest"
  },
  "geometry": {
    "type": "Point",
    "coordinates": [
      25.65,
      45.76667
    ]
  }
}