{
  "type": "Feature",
  "properties": {
    "name": "Colonia Bod",
    "country": "RO",
    "subdivision": "09",
    "timezone": "Europe/Bucharest"
  },
  "geometry": {
    "type": "Point",
    "coordinates": [
      25.5996,
      45.75588
    ]
  }
}