{
  "type": "Feature",
  "properties": {
    "name": "Hărman",
    "country": "RO",
    "subdivision": "09",
    "timezone": "Europe/Bucharest"
  },
  "geometry": {
    "type": "Point",
    "coordinates": [
      25.68333,
      45.71667
    ]
  }
}