{
  "type": "Feature",
  "properties": {
    "name": "Perșani",
    "country": "RO",
    "subdivision": "09",
    "timezone": "Europe/Bucharest"
  },
  "geometry": {
    "type": "Point",
    "coordinates": [
      25.21285,
      45.7816
    ]
  }
}