{
  "type": "Feature",
  "properties": {
    "name": "Şoarş",
    "country": "RO",
    "subdivision": "09",
    "timezone": "Europe/Bucharest"
  },
  "geometry": {
    "type": "Point",
    "coordinates": [
      24.92867,
      45.92859
    ]
  }
}