{
  "type": "Feature",
  "properties": {
    "name": "Voila",
    "country": "RO",
    "subdivision": "09",
    "timezone": "Europe/Bucharest"
  },
  "geometry": {
    "type": "Point",
    "coordinates": [
      24.84215,
      45.81839
    ]
  }
}