{
  "type": "Feature",
  "properties": {
    "name": "Madagali",
    "country": "NG",
    "subdivision": "35",
    "timezone": "Africa/Lagos"
  },
  "geometry": {
    "type": "Point",
    "coordinates": [
      13.62832,
      10.88942
    ]
  }
}