{
  "type": "Feature",
  "properties": {
    "name": "Ngurore",
    "country": "NG",
    "subdivision": "35",
    "timezone": "Africa/Lagos"
  },
  "geometry": {
    "type": "Point",
    "coordinates": [
      12.24026,
      9.28871
    ]
  }
}