{
  "type": "Feature",
  "properties": {
    "name": "Numan",
    "country": "NG",
    "subdivision": "35",
    "timezone": "Africa/Lagos"
  },
  "geometry": {
    "type": "Point",
    "coordinates": [
      12.03062,
      9.46374
    ]
  }
}