{
  "type": "Feature",
  "properties": {
    "name": "Toungo",
    "country": "NG",
    "subdivision": "35",
    "timezone": "Africa/Lagos"
  },
  "geometry": {
    "type": "Point",
    "coordinates": [
      12.04611,
      8.11733
    ]
  }
}