{
  "type": "Feature",
  "properties": {
    "name": "Hanko",
    "country": "FI",
    "subdivision": "01",
    "timezone": "Europe/Helsinki"
  },
  "geometry": {
    "type": "Point",
    "coordinates": [
      22.95,
      59.83333
    ]
  }
}