{
  "type": "Feature",
  "properties": {
    "name": "Karkkila",
    "country": "FI",
    "subdivision": "01",
    "timezone": "Europe/Helsinki"
  },
  "geometry": {
    "type": "Point",
    "coordinates": [
      24.20977,
      60.53418
    ]
  }
}