{
  "type": "Feature",
  "properties": {
    "name": "Sibbo",
    "country": "FI",
    "subdivision": "01",
    "timezone": "Europe/Helsinki"
  },
  "geometry": {
    "type": "Point",
    "coordinates": [
      25.26906,
      60.37752
    ]
  }
}