{
  "type": "Feature",
  "properties": {
    "name": "Okayama",
    "country": "JP",
    "subdivision": "31",
    "timezone": "Asia/Tokyo"
  },
  "geometry": {
    "type": "Point",
    "coordinates": [
      133.93333,
      34.65
    ]
  }
}