{
  "type": "Feature",
  "properties": {
    "name": "Tsuyama",
    "country": "JP",
    "subdivision": "31",
    "timezone": "Asia/Tokyo"
  },
  "geometry": {
    "type": "Point",
    "coordinates": [
      133.99885,
      35.05215
    ]
  }
}