{
  "type": "Feature",
  "properties": {
    "name": "İhsaniye",
    "country": "TR",
    "subdivision": "41",
    "timezone": "Europe/Istanbul"
  },
  "geometry": {
    "type": "Point",
    "coordinates": [
      29.83472,
      40.69087
    ]
  }
}