{
  "type": "Feature",
  "properties": {
    "name": "Yalakdere",
    "country": "TR",
    "subdivision": "41",
    "timezone": "Europe/Istanbul"
  },
  "geometry": {
    "type": "Point",
    "coordinates": [
      29.56225,
      40.60636
    ]
  }
}