{
  "type": "Feature",
  "properties": {
    "name": "Buldan",
    "country": "TR",
    "subdivision": "20",
    "timezone": "Europe/Istanbul"
  },
  "geometry": {
    "type": "Point",
    "coordinates": [
      28.83056,
      38.045
    ]
  }
}