{
  "type": "Feature",
  "properties": {
    "name": "Sarayköy",
    "country": "TR",
    "subdivision": "20",
    "timezone": "Europe/Istanbul"
  },
  "geometry": {
    "type": "Point",
    "coordinates": [
      28.92516,
      37.92448
    ]
  }
}