{
  "type": "Feature",
  "properties": {
    "name": "Kampung Tanjung Karang",
    "country": "MY",
    "subdivision": "12",
    "timezone": "Asia/Kuala_Lumpur"
  },
  "geometry": {
    "type": "Point",
    "coordinates": [
      101.1849,
      3.4242
    ]
  }
}