{
  "type": "Feature",
  "properties": {
    "name": "Ladang Seri Kundang",
    "country": "MY",
    "subdivision": "12",
    "timezone": "Asia/Kuala_Lumpur"
  },
  "geometry": {
    "type": "Point",
    "coordinates": [
      101.519,
      3.2856
    ]
  }
}