{
  "type": "Feature",
  "properties": {
    "name": "Azuaga",
    "country": "ES",
    "subdivision": "57",
    "timezone": "Europe/Madrid"
  },
  "geometry": {
    "type": "Point",
    "coordinates": [
      -5.68333,
      38.26667
    ]
  }
}