{
  "type": "Feature",
  "properties": {
    "name": "Badajoz",
    "country": "ES",
    "subdivision": "57",
    "timezone": "Europe/Madrid"
  },
  "geometry": {
    "type": "Point",
    "coordinates": [
      -6.97061,
      38.87789
    ]
  }
}