{
  "type": "Feature",
  "properties": {
    "name": "Burguillos del Cerro",
    "country": "ES",
    "subdivision": "57",
    "timezone": "Europe/Madrid"
  },
  "geometry": {
    "type": "Point",
    "coordinates": [
      -6.59037,
      38.38008
    ]
  }
}