{
  "type": "Feature",
  "properties": {
    "name": "Cabeza del Buey",
    "country": "ES",
    "subdivision": "57",
    "timezone": "Europe/Madrid"
  },
  "geometry": {
    "type": "Point",
    "coordinates": [
      -5.21946,
      38.72227
    ]
  }
}