{
  "type": "Feature",
  "properties": {
    "name": "Esparragosa de Lares",
    "country": "ES",
    "subdivision": "57",
    "timezone": "Europe/Madrid"
  },
  "geometry": {
    "type": "Point",
    "coordinates": [
      -5.26968,
      38.97517
    ]
  }
}