{
  "type": "Feature",
  "properties": {
    "name": "Jarandilla de la Vera",
    "country": "ES",
    "subdivision": "57",
    "timezone": "Europe/Madrid"
  },
  "geometry": {
    "type": "Point",
    "coordinates": [
      -5.66079,
      40.12915
    ]
  }
}