{
  "type": "Feature",
  "properties": {
    "name": "La Roca de la Sierra",
    "country": "ES",
    "subdivision": "57",
    "timezone": "Europe/Madrid"
  },
  "geometry": {
    "type": "Point",
    "coordinates": [
      -6.68916,
      39.10966
    ]
  }
}