{
  "type": "Feature",
  "properties": {
    "name": "Santa Marta",
    "country": "ES",
    "subdivision": "57",
    "timezone": "Europe/Madrid"
  },
  "geometry": {
    "type": "Point",
    "coordinates": [
      -6.62799,
      38.61421
    ]
  }
}