{
  "type": "Feature",
  "properties": {
    "name": "Torrejoncillo",
    "country": "ES",
    "subdivision": "57",
    "timezone": "Europe/Madrid"
  },
  "geometry": {
    "type": "Point",
    "coordinates": [
      -6.46712,
      39.89675
    ]
  }
}