{
  "type": "Feature",
  "properties": {
    "name": "Torreorgaz",
    "country": "ES",
    "subdivision": "57",
    "timezone": "Europe/Madrid"
  },
  "geometry": {
    "type": "Point",
    "coordinates": [
      -6.24941,
      39.3831
    ]
  }
}