{
  "type": "Feature",
  "properties": {
    "name": "Torrecillas de la Tiesa",
    "country": "ES",
    "subdivision": "57",
    "timezone": "Europe/Madrid"
  },
  "geometry": {
    "type": "Point",
    "coordinates": [
      -5.74238,
      39.56837
    ]
  }
}