{
  "type": "Feature",
  "properties": {
    "name": "Valle de la Serena",
    "country": "ES",
    "subdivision": "57",
    "timezone": "Europe/Madrid"
  },
  "geometry": {
    "type": "Point",
    "coordinates": [
      -5.79847,
      38.7101
    ]
  }
}