{
  "type": "Feature",
  "properties": {
    "name": "Valverde de Mérida",
    "country": "ES",
    "subdivision": "57",
    "timezone": "Europe/Madrid"
  },
  "geometry": {
    "type": "Point",
    "coordinates": [
      -6.21999,
      38.91122
    ]
  }
}