{
  "type": "Feature",
  "properties": {
    "name": "Villanueva del Fresno",
    "country": "ES",
    "subdivision": "57",
    "timezone": "Europe/Madrid"
  },
  "geometry": {
    "type": "Point",
    "coordinates": [
      -7.16753,
      38.376
    ]
  }
}