{
  "type": "Feature",
  "properties": {
    "name": "Rupite",
    "country": "BG",
    "subdivision": "38",
    "timezone": "Europe/Sofia"
  },
  "geometry": {
    "type": "Point",
    "coordinates": [
      23.24168,
      41.44245
    ]
  }
}