{
  "type": "Feature",
  "properties": {
    "name": "Simitli",
    "country": "BG",
    "subdivision": "38",
    "timezone": "Europe/Sofia"
  },
  "geometry": {
    "type": "Point",
    "coordinates": [
      23.11667,
      41.88333
    ]
  }
}