{
  "type": "Feature",
  "properties": {
    "name": "Band",
    "country": "RO",
    "subdivision": "27",
    "timezone": "Europe/Bucharest"
  },
  "geometry": {
    "type": "Point",
    "coordinates": [
      24.38333,
      46.58333
    ]
  }
}