{
  "type": "Feature",
  "properties": {
    "name": "Breaza",
    "country": "RO",
    "subdivision": "27",
    "timezone": "Europe/Bucharest"
  },
  "geometry": {
    "type": "Point",
    "coordinates": [
      24.63333,
      46.76667
    ]
  }
}