{
  "type": "Feature",
  "properties": {
    "name": "Chibed",
    "country": "RO",
    "subdivision": "27",
    "timezone": "Europe/Bucharest"
  },
  "geometry": {
    "type": "Point",
    "coordinates": [
      24.96215,
      46.53328
    ]
  }
}