{
  "type": "Feature",
  "properties": {
    "name": "Dedrad",
    "country": "RO",
    "subdivision": "27",
    "timezone": "Europe/Bucharest"
  },
  "geometry": {
    "type": "Point",
    "coordinates": [
      24.65799,
      46.82632
    ]
  }
}