{
  "type": "Feature",
  "properties": {
    "name": "Eremitu",
    "country": "RO",
    "subdivision": "27",
    "timezone": "Europe/Bucharest"
  },
  "geometry": {
    "type": "Point",
    "coordinates": [
      24.93333,
      46.66667
    ]
  }
}