{
  "type": "Feature",
  "properties": {
    "name": "Găneşti",
    "country": "RO",
    "subdivision": "27",
    "timezone": "Europe/Bucharest"
  },
  "geometry": {
    "type": "Point",
    "coordinates": [
      24.35,
      46.33333
    ]
  }
}