{
  "type": "Feature",
  "properties": {
    "name": "Hodac",
    "country": "RO",
    "subdivision": "27",
    "timezone": "Europe/Bucharest"
  },
  "geometry": {
    "type": "Point",
    "coordinates": [
      24.91667,
      46.76667
    ]
  }
}