{
  "type": "Feature",
  "properties": {
    "name": "Sărățeni",
    "country": "RO",
    "subdivision": "27",
    "timezone": "Europe/Bucharest"
  },
  "geometry": {
    "type": "Point",
    "coordinates": [
      25.01331,
      46.56247
    ]
  }
}