{
  "type": "Feature",
  "properties": {
    "name": "Saschiz",
    "country": "RO",
    "subdivision": "27",
    "timezone": "Europe/Bucharest"
  },
  "geometry": {
    "type": "Point",
    "coordinates": [
      24.96667,
      46.18333
    ]
  }
}