{
  "type": "Feature",
  "properties": {
    "name": "Vătava",
    "country": "RO",
    "subdivision": "27",
    "timezone": "Europe/Bucharest"
  },
  "geometry": {
    "type": "Point",
    "coordinates": [
      24.76667,
      46.96667
    ]
  }
}