{
  "type": "Feature",
  "properties": {
    "name": "Kalamare",
    "country": "BW",
    "subdivision": "01",
    "timezone": "Africa/Gaborone"
  },
  "geometry": {
    "type": "Point",
    "coordinates": [
      26.57032,
      -22.93369
    ]
  }
}