{
  "type": "Feature",
  "properties": {
    "name": "Mosetse",
    "country": "BW",
    "subdivision": "01",
    "timezone": "Africa/Gaborone"
  },
  "geometry": {
    "type": "Point",
    "coordinates": [
      26.65,
      -20.75
    ]
  }
}