{
  "type": "Feature",
  "properties": {
    "name": "Ramokgonami",
    "country": "BW",
    "subdivision": "01",
    "timezone": "Africa/Gaborone"
  },
  "geometry": {
    "type": "Point",
    "coordinates": [
      27.42391,
      -22.8645
    ]
  }
}