{
  "type": "Feature",
  "properties": {
    "name": "Ban Bueng",
    "country": "TH",
    "subdivision": "46",
    "timezone": "Asia/Bangkok"
  },
  "geometry": {
    "type": "Point",
    "coordinates": [
      101.11214,
      13.311
    ]
  }
}