{
  "type": "Feature",
  "properties": {
    "name": "Ban Ko Lan",
    "country": "TH",
    "subdivision": "46",
    "timezone": "Asia/Bangkok"
  },
  "geometry": {
    "type": "Point",
    "coordinates": [
      100.78794,
      12.92419
    ]
  }
}