{
  "type": "Feature",
  "properties": {
    "name": "Ilava",
    "country": "SK",
    "subdivision": "06",
    "timezone": "Europe/Bratislava"
  },
  "geometry": {
    "type": "Point",
    "coordinates": [
      18.2353,
      48.99769
    ]
  }
}