{
  "type": "Feature",
  "properties": {
    "name": "Považská Bystrica",
    "country": "SK",
    "subdivision": "06",
    "timezone": "Europe/Bratislava"
  },
  "geometry": {
    "type": "Point",
    "coordinates": [
      18.42169,
      49.12153
    ]
  }
}