{
  "type": "Feature",
  "properties": {
    "name": "TrenÄianske Teplice",
    "country": "SK",
    "subdivision": "06",
    "timezone": "Europe/Bratislava"
  },
  "geometry": {
    "type": "Point",
    "coordinates": [
      18.16691,
      48.91063
    ]
  }
}