{
  "type": "Feature",
  "properties": {
    "name": "Senica",
    "country": "SK",
    "subdivision": "07",
    "timezone": "Europe/Bratislava"
  },
  "geometry": {
    "type": "Point",
    "coordinates": [
      17.36697,
      48.67922
    ]
  }
}