{
  "type": "Feature",
  "properties": {
    "name": "Skalica",
    "country": "SK",
    "subdivision": "07",
    "timezone": "Europe/Bratislava"
  },
  "geometry": {
    "type": "Point",
    "coordinates": [
      17.22635,
      48.8449
    ]
  }
}