{
  "type": "Feature",
  "properties": {
    "name": "Aberdeen",
    "country": "US",
    "subdivision": "OH",
    "timezone": "America/New_York"
  },
  "geometry": {
    "type": "Point",
    "coordinates": [
      -83.76103,
      38.65563
    ]
  }
}