{
  "type": "Feature",
  "properties": {
    "name": "Ada",
    "country": "US",
    "subdivision": "OH",
    "timezone": "America/New_York"
  },
  "geometry": {
    "type": "Point",
    "coordinates": [
      -83.82271,
      40.7695
    ]
  }
}