{
  "type": "Feature",
  "properties": {
    "name": "Alliance",
    "country": "US",
    "subdivision": "OH",
    "timezone": "America/New_York"
  },
  "geometry": {
    "type": "Point",
    "coordinates": [
      -81.10593,
      40.91534
    ]
  }
}