{
  "type": "Feature",
  "properties": {
    "name": "Ansonia",
    "country": "US",
    "subdivision": "OH",
    "timezone": "America/New_York"
  },
  "geometry": {
    "type": "Point",
    "coordinates": [
      -84.6369,
      40.21449
    ]
  }
}