{
  "type": "Feature",
  "properties": {
    "name": "Apple Creek",
    "country": "US",
    "subdivision": "OH",
    "timezone": "America/New_York"
  },
  "geometry": {
    "type": "Point",
    "coordinates": [
      -81.8393,
      40.75172
    ]
  }
}