{
  "type": "Feature",
  "properties": {
    "name": "Aurora",
    "country": "US",
    "subdivision": "OH",
    "timezone": "America/New_York"
  },
  "geometry": {
    "type": "Point",
    "coordinates": [
      -81.34539,
      41.31755
    ]
  }
}