{
  "type": "Feature",
  "properties": {
    "name": "Avon Lake",
    "country": "US",
    "subdivision": "OH",
    "timezone": "America/New_York"
  },
  "geometry": {
    "type": "Point",
    "coordinates": [
      -82.0282,
      41.50532
    ]
  }
}