{
  "type": "Feature",
  "properties": {
    "name": "Bellville",
    "country": "US",
    "subdivision": "OH",
    "timezone": "America/New_York"
  },
  "geometry": {
    "type": "Point",
    "coordinates": [
      -82.51072,
      40.62006
    ]
  }
}