{
  "type": "Feature",
  "properties": {
    "name": "Belpre",
    "country": "US",
    "subdivision": "OH",
    "timezone": "America/New_York"
  },
  "geometry": {
    "type": "Point",
    "coordinates": [
      -81.5729,
      39.27396
    ]
  }
}