{
  "type": "Feature",
  "properties": {
    "name": "Bethel",
    "country": "US",
    "subdivision": "OH",
    "timezone": "America/New_York"
  },
  "geometry": {
    "type": "Point",
    "coordinates": [
      -84.08077,
      38.96368
    ]
  }
}