{
  "type": "Feature",
  "properties": {
    "name": "Blacklick Estates",
    "country": "US",
    "subdivision": "OH",
    "timezone": "America/New_York"
  },
  "geometry": {
    "type": "Point",
    "coordinates": [
      -82.86434,
      39.90506
    ]
  }
}