{
  "type": "Feature",
  "properties": {
    "name": "Blanchester",
    "country": "US",
    "subdivision": "OH",
    "timezone": "America/New_York"
  },
  "geometry": {
    "type": "Point",
    "coordinates": [
      -83.98882,
      39.29312
    ]
  }
}