{
  "type": "Feature",
  "properties": {
    "name": "Bowling Green",
    "country": "US",
    "subdivision": "OH",
    "timezone": "America/New_York"
  },
  "geometry": {
    "type": "Point",
    "coordinates": [
      -83.65132,
      41.37477
    ]
  }
}