{
  "type": "Feature",
  "properties": {
    "name": "Bradner",
    "country": "US",
    "subdivision": "OH",
    "timezone": "America/New_York"
  },
  "geometry": {
    "type": "Point",
    "coordinates": [
      -83.43854,
      41.32422
    ]
  }
}