{
  "type": "Feature",
  "properties": {
    "name": "Bratenahl",
    "country": "US",
    "subdivision": "OH",
    "timezone": "America/New_York"
  },
  "geometry": {
    "type": "Point",
    "coordinates": [
      -81.62624,
      41.54255
    ]
  }
}