{
  "type": "Feature",
  "properties": {
    "name": "Bridgeport",
    "country": "US",
    "subdivision": "OH",
    "timezone": "America/New_York"
  },
  "geometry": {
    "type": "Point",
    "coordinates": [
      -80.74008,
      40.06979
    ]
  }
}