{
  "type": "Feature",
  "properties": {
    "name": "Brilliant",
    "country": "US",
    "subdivision": "OH",
    "timezone": "America/New_York"
  },
  "geometry": {
    "type": "Point",
    "coordinates": [
      -80.62619,
      40.26479
    ]
  }
}