{
  "type": "Feature",
  "properties": {
    "name": "Brooklyn Heights",
    "country": "US",
    "subdivision": "OH",
    "timezone": "America/New_York"
  },
  "geometry": {
    "type": "Point",
    "coordinates": [
      -81.68818,
      41.42533
    ]
  }
}