{
  "type": "Feature",
  "properties": {
    "name": "Brook Park",
    "country": "US",
    "subdivision": "OH",
    "timezone": "America/New_York"
  },
  "geometry": {
    "type": "Point",
    "coordinates": [
      -81.80458,
      41.39838
    ]
  }
}