{
  "type": "Feature",
  "properties": {
    "name": "Caldwell",
    "country": "US",
    "subdivision": "OH",
    "timezone": "America/New_York"
  },
  "geometry": {
    "type": "Point",
    "coordinates": [
      -81.51651,
      39.74785
    ]
  }
}