{
  "type": "Feature",
  "properties": {
    "name": "Centerburg",
    "country": "US",
    "subdivision": "OH",
    "timezone": "America/New_York"
  },
  "geometry": {
    "type": "Point",
    "coordinates": [
      -82.69628,
      40.30451
    ]
  }
}