{
  "type": "Feature",
  "properties": {
    "name": "Chillicothe",
    "country": "US",
    "subdivision": "OH",
    "timezone": "America/New_York"
  },
  "geometry": {
    "type": "Point",
    "coordinates": [
      -82.9824,
      39.33312
    ]
  }
}