{
  "type": "Feature",
  "properties": {
    "name": "Collinwood",
    "country": "US",
    "subdivision": "OH",
    "timezone": "America/New_York"
  },
  "geometry": {
    "type": "Point",
    "coordinates": [
      -81.56929,
      41.55838
    ]
  }
}