{
  "type": "Feature",
  "properties": {
    "name": "Columbus",
    "country": "US",
    "subdivision": "OH",
    "timezone": "America/New_York"
  },
  "geometry": {
    "type": "Point",
    "coordinates": [
      -82.99879,
      39.96118
    ]
  }
}