{
  "type": "Feature",
  "properties": {
    "name": "Continental",
    "country": "US",
    "subdivision": "OH",
    "timezone": "America/New_York"
  },
  "geometry": {
    "type": "Point",
    "coordinates": [
      -84.26634,
      41.10033
    ]
  }
}