{
  "type": "Feature",
  "properties": {
    "name": "Copley",
    "country": "US",
    "subdivision": "OH",
    "timezone": "America/New_York"
  },
  "geometry": {
    "type": "Point",
    "coordinates": [
      -81.64457,
      41.09894
    ]
  }
}