{
  "type": "Feature",
  "properties": {
    "name": "Cortland",
    "country": "US",
    "subdivision": "OH",
    "timezone": "America/New_York"
  },
  "geometry": {
    "type": "Point",
    "coordinates": [
      -80.72536,
      41.33033
    ]
  }
}