{
  "type": "Feature",
  "properties": {
    "name": "Deer Park",
    "country": "US",
    "subdivision": "OH",
    "timezone": "America/New_York"
  },
  "geometry": {
    "type": "Point",
    "coordinates": [
      -84.39466,
      39.20534
    ]
  }
}