{
  "type": "Feature",
  "properties": {
    "name": "Detroit-Shoreway",
    "country": "US",
    "subdivision": "OH",
    "timezone": "America/New_York"
  },
  "geometry": {
    "type": "Point",
    "coordinates": [
      -81.72991,
      41.47772
    ]
  }
}