{
  "type": "Feature",
  "properties": {
    "name": "Dunlap",
    "country": "US",
    "subdivision": "OH",
    "timezone": "America/New_York"
  },
  "geometry": {
    "type": "Point",
    "coordinates": [
      -84.618,
      39.29228
    ]
  }
}