{
  "type": "Feature",
  "properties": {
    "name": "East Palestine",
    "country": "US",
    "subdivision": "OH",
    "timezone": "America/New_York"
  },
  "geometry": {
    "type": "Point",
    "coordinates": [
      -80.54035,
      40.83395
    ]
  }
}