{
  "type": "Feature",
  "properties": {
    "name": "Elida",
    "country": "US",
    "subdivision": "OH",
    "timezone": "America/New_York"
  },
  "geometry": {
    "type": "Point",
    "coordinates": [
      -84.20384,
      40.78866
    ]
  }
}