{
  "type": "Feature",
  "properties": {
    "name": "Elmore",
    "country": "US",
    "subdivision": "OH",
    "timezone": "America/New_York"
  },
  "geometry": {
    "type": "Point",
    "coordinates": [
      -83.29576,
      41.47616
    ]
  }
}