{
  "type": "Feature",
  "properties": {
    "name": "Enon",
    "country": "US",
    "subdivision": "OH",
    "timezone": "America/New_York"
  },
  "geometry": {
    "type": "Point",
    "coordinates": [
      -83.93688,
      39.87812
    ]
  }
}