{
  "type": "Feature",
  "properties": {
    "name": "Fairfield Beach",
    "country": "US",
    "subdivision": "OH",
    "timezone": "America/New_York"
  },
  "geometry": {
    "type": "Point",
    "coordinates": [
      -82.47516,
      39.9159
    ]
  }
}