{
  "type": "Feature",
  "properties": {
    "name": "Gahanna",
    "country": "US",
    "subdivision": "OH",
    "timezone": "America/New_York"
  },
  "geometry": {
    "type": "Point",
    "coordinates": [
      -82.87934,
      40.01923
    ]
  }
}