{
  "type": "Feature",
  "properties": {
    "name": "Garrettsville",
    "country": "US",
    "subdivision": "OH",
    "timezone": "America/New_York"
  },
  "geometry": {
    "type": "Point",
    "coordinates": [
      -81.09649,
      41.28422
    ]
  }
}