{
  "type": "Feature",
  "properties": {
    "name": "Glendale",
    "country": "US",
    "subdivision": "OH",
    "timezone": "America/New_York"
  },
  "geometry": {
    "type": "Point",
    "coordinates": [
      -84.45939,
      39.27061
    ]
  }
}