{
  "type": "Feature",
  "properties": {
    "name": "Greenville",
    "country": "US",
    "subdivision": "OH",
    "timezone": "America/New_York"
  },
  "geometry": {
    "type": "Point",
    "coordinates": [
      -84.63301,
      40.10283
    ]
  }
}