{
  "type": "Feature",
  "properties": {
    "name": "Hanover",
    "country": "US",
    "subdivision": "OH",
    "timezone": "America/New_York"
  },
  "geometry": {
    "type": "Point",
    "coordinates": [
      -82.26098,
      40.07979
    ]
  }
}