{
  "type": "Feature",
  "properties": {
    "name": "Huron",
    "country": "US",
    "subdivision": "OH",
    "timezone": "America/New_York"
  },
  "geometry": {
    "type": "Point",
    "coordinates": [
      -82.55517,
      41.39505
    ]
  }
}