{
  "type": "Feature",
  "properties": {
    "name": "Johnstown",
    "country": "US",
    "subdivision": "OH",
    "timezone": "America/New_York"
  },
  "geometry": {
    "type": "Point",
    "coordinates": [
      -82.68517,
      40.15367
    ]
  }
}