{
  "type": "Feature",
  "properties": {
    "name": "Lakeview",
    "country": "US",
    "subdivision": "OH",
    "timezone": "America/New_York"
  },
  "geometry": {
    "type": "Point",
    "coordinates": [
      -83.923,
      40.48477
    ]
  }
}