{
  "type": "Feature",
  "properties": {
    "name": "Lake Lakengren",
    "country": "US",
    "subdivision": "OH",
    "timezone": "America/New_York"
  },
  "geometry": {
    "type": "Point",
    "coordinates": [
      -84.69347,
      39.68843
    ]
  }
}