{
  "type": "Feature",
  "properties": {
    "name": "Lancaster",
    "country": "US",
    "subdivision": "OH",
    "timezone": "America/New_York"
  },
  "geometry": {
    "type": "Point",
    "coordinates": [
      -82.59933,
      39.71368
    ]
  }
}