{
  "type": "Feature",
  "properties": {
    "name": "Landen",
    "country": "US",
    "subdivision": "OH",
    "timezone": "America/New_York"
  },
  "geometry": {
    "type": "Point",
    "coordinates": [
      -84.28299,
      39.312
    ]
  }
}