{
  "type": "Feature",
  "properties": {
    "name": "Leesburg",
    "country": "US",
    "subdivision": "OH",
    "timezone": "America/New_York"
  },
  "geometry": {
    "type": "Point",
    "coordinates": [
      -83.55297,
      39.34506
    ]
  }
}