{
  "type": "Feature",
  "properties": {
    "name": "Liberty Center",
    "country": "US",
    "subdivision": "OH",
    "timezone": "America/New_York"
  },
  "geometry": {
    "type": "Point",
    "coordinates": [
      -84.00883,
      41.44338
    ]
  }
}