{
  "type": "Feature",
  "properties": {
    "name": "Lincoln Heights",
    "country": "US",
    "subdivision": "OH",
    "timezone": "America/New_York"
  },
  "geometry": {
    "type": "Point",
    "coordinates": [
      -84.4555,
      39.23895
    ]
  }
}