{
  "type": "Feature",
  "properties": {
    "name": "Lorain",
    "country": "US",
    "subdivision": "OH",
    "timezone": "America/New_York"
  },
  "geometry": {
    "type": "Point",
    "coordinates": [
      -82.18237,
      41.45282
    ]
  }
}