{
  "type": "Feature",
  "properties": {
    "name": "Marion",
    "country": "US",
    "subdivision": "OH",
    "timezone": "America/New_York"
  },
  "geometry": {
    "type": "Point",
    "coordinates": [
      -83.12852,
      40.58867
    ]
  }
}