{
  "type": "Feature",
  "properties": {
    "name": "Marysville",
    "country": "US",
    "subdivision": "OH",
    "timezone": "America/New_York"
  },
  "geometry": {
    "type": "Point",
    "coordinates": [
      -83.36714,
      40.23645
    ]
  }
}