{
  "type": "Feature",
  "properties": {
    "name": "Maumee",
    "country": "US",
    "subdivision": "OH",
    "timezone": "America/New_York"
  },
  "geometry": {
    "type": "Point",
    "coordinates": [
      -83.65382,
      41.56283
    ]
  }
}