{
  "type": "Feature",
  "properties": {
    "name": "McComb",
    "country": "US",
    "subdivision": "OH",
    "timezone": "America/New_York"
  },
  "geometry": {
    "type": "Point",
    "coordinates": [
      -83.79271,
      41.10755
    ]
  }
}