{
  "type": "Feature",
  "properties": {
    "name": "Middletown",
    "country": "US",
    "subdivision": "OH",
    "timezone": "America/New_York"
  },
  "geometry": {
    "type": "Point",
    "coordinates": [
      -84.39828,
      39.51506
    ]
  }
}