{
  "type": "Feature",
  "properties": {
    "name": "Middleport",
    "country": "US",
    "subdivision": "OH",
    "timezone": "America/New_York"
  },
  "geometry": {
    "type": "Point",
    "coordinates": [
      -82.04875,
      39.00175
    ]
  }
}