{
  "type": "Feature",
  "properties": {
    "name": "Milford",
    "country": "US",
    "subdivision": "OH",
    "timezone": "America/New_York"
  },
  "geometry": {
    "type": "Point",
    "coordinates": [
      -84.29438,
      39.17534
    ]
  }
}