{
  "type": "Feature",
  "properties": {
    "name": "Mineral Ridge",
    "country": "US",
    "subdivision": "OH",
    "timezone": "America/New_York"
  },
  "geometry": {
    "type": "Point",
    "coordinates": [
      -80.76897,
      41.14006
    ]
  }
}