{
  "type": "Feature",
  "properties": {
    "name": "Moraine",
    "country": "US",
    "subdivision": "OH",
    "timezone": "America/New_York"
  },
  "geometry": {
    "type": "Point",
    "coordinates": [
      -84.21938,
      39.70617
    ]
  }
}