{
  "type": "Feature",
  "properties": {
    "name": "Mount Carmel",
    "country": "US",
    "subdivision": "OH",
    "timezone": "America/New_York"
  },
  "geometry": {
    "type": "Point",
    "coordinates": [
      -84.3041,
      39.10589
    ]
  }
}