{
  "type": "Feature",
  "properties": {
    "name": "Munroe Falls",
    "country": "US",
    "subdivision": "OH",
    "timezone": "America/New_York"
  },
  "geometry": {
    "type": "Point",
    "coordinates": [
      -81.43983,
      41.1445
    ]
  }
}