{
  "type": "Feature",
  "properties": {
    "name": "New Burlington",
    "country": "US",
    "subdivision": "OH",
    "timezone": "America/New_York"
  },
  "geometry": {
    "type": "Point",
    "coordinates": [
      -84.55717,
      39.2595
    ]
  }
}