{
  "type": "Feature",
  "properties": {
    "name": "New Bremen",
    "country": "US",
    "subdivision": "OH",
    "timezone": "America/New_York"
  },
  "geometry": {
    "type": "Point",
    "coordinates": [
      -84.37967,
      40.43699
    ]
  }
}