{
  "type": "Feature",
  "properties": {
    "name": "New Paris",
    "country": "US",
    "subdivision": "OH",
    "timezone": "America/New_York"
  },
  "geometry": {
    "type": "Point",
    "coordinates": [
      -84.79329,
      39.85699
    ]
  }
}