{
  "type": "Feature",
  "properties": {
    "name": "Newcomerstown",
    "country": "US",
    "subdivision": "OH",
    "timezone": "America/New_York"
  },
  "geometry": {
    "type": "Point",
    "coordinates": [
      -81.60595,
      40.27229
    ]
  }
}