{
  "type": "Feature",
  "properties": {
    "name": "North Canton",
    "country": "US",
    "subdivision": "OH",
    "timezone": "America/New_York"
  },
  "geometry": {
    "type": "Point",
    "coordinates": [
      -81.40234,
      40.87589
    ]
  }
}