{
  "type": "Feature",
  "properties": {
    "name": "North College Hill",
    "country": "US",
    "subdivision": "OH",
    "timezone": "America/New_York"
  },
  "geometry": {
    "type": "Point",
    "coordinates": [
      -84.55078,
      39.21839
    ]
  }
}