{
  "type": "Feature",
  "properties": {
    "name": "Oxford",
    "country": "US",
    "subdivision": "OH",
    "timezone": "America/New_York"
  },
  "geometry": {
    "type": "Point",
    "coordinates": [
      -84.74523,
      39.507
    ]
  }
}