{
  "type": "Feature",
  "properties": {
    "name": "Parma",
    "country": "US",
    "subdivision": "OH",
    "timezone": "America/New_York"
  },
  "geometry": {
    "type": "Point",
    "coordinates": [
      -81.72291,
      41.40477
    ]
  }
}