{
  "type": "Feature",
  "properties": {
    "name": "Pataskala",
    "country": "US",
    "subdivision": "OH",
    "timezone": "America/New_York"
  },
  "geometry": {
    "type": "Point",
    "coordinates": [
      -82.67433,
      39.99562
    ]
  }
}