{
  "type": "Feature",
  "properties": {
    "name": "Pemberville",
    "country": "US",
    "subdivision": "OH",
    "timezone": "America/New_York"
  },
  "geometry": {
    "type": "Point",
    "coordinates": [
      -83.46104,
      41.41089
    ]
  }
}