{
  "type": "Feature",
  "properties": {
    "name": "Piketon",
    "country": "US",
    "subdivision": "OH",
    "timezone": "America/New_York"
  },
  "geometry": {
    "type": "Point",
    "coordinates": [
      -83.01434,
      39.06813
    ]
  }
}