{
  "type": "Feature",
  "properties": {
    "name": "Pioneer",
    "country": "US",
    "subdivision": "OH",
    "timezone": "America/New_York"
  },
  "geometry": {
    "type": "Point",
    "coordinates": [
      -84.55301,
      41.68005
    ]
  }
}