{
  "type": "Feature",
  "properties": {
    "name": "Pleasant Run Farm",
    "country": "US",
    "subdivision": "OH",
    "timezone": "America/New_York"
  },
  "geometry": {
    "type": "Point",
    "coordinates": [
      -84.548,
      39.30311
    ]
  }
}