{
  "type": "Feature",
  "properties": {
    "name": "Riverside",
    "country": "US",
    "subdivision": "OH",
    "timezone": "America/New_York"
  },
  "geometry": {
    "type": "Point",
    "coordinates": [
      -84.1241,
      39.77978
    ]
  }
}