{
  "type": "Feature",
  "properties": {
    "name": "Roseville",
    "country": "US",
    "subdivision": "OH",
    "timezone": "America/New_York"
  },
  "geometry": {
    "type": "Point",
    "coordinates": [
      -82.07125,
      39.80729
    ]
  }
}