{
  "type": "Feature",
  "properties": {
    "name": "Saint Paris",
    "country": "US",
    "subdivision": "OH",
    "timezone": "America/New_York"
  },
  "geometry": {
    "type": "Point",
    "coordinates": [
      -83.95966,
      40.12839
    ]
  }
}