{
  "type": "Feature",
  "properties": {
    "name": "Salineville",
    "country": "US",
    "subdivision": "OH",
    "timezone": "America/New_York"
  },
  "geometry": {
    "type": "Point",
    "coordinates": [
      -80.83786,
      40.62256
    ]
  }
}