{
  "type": "Feature",
  "properties": {
    "name": "Seven Hills",
    "country": "US",
    "subdivision": "OH",
    "timezone": "America/New_York"
  },
  "geometry": {
    "type": "Point",
    "coordinates": [
      -81.67624,
      41.39533
    ]
  }
}