{
  "type": "Feature",
  "properties": {
    "name": "South Zanesville",
    "country": "US",
    "subdivision": "OH",
    "timezone": "America/New_York"
  },
  "geometry": {
    "type": "Point",
    "coordinates": [
      -82.00625,
      39.89923
    ]
  }
}