{
  "type": "Feature",
  "properties": {
    "name": "Stow",
    "country": "US",
    "subdivision": "OH",
    "timezone": "America/New_York"
  },
  "geometry": {
    "type": "Point",
    "coordinates": [
      -81.44039,
      41.1595
    ]
  }
}