{
  "type": "Feature",
  "properties": {
    "name": "Vandalia",
    "country": "US",
    "subdivision": "OH",
    "timezone": "America/New_York"
  },
  "geometry": {
    "type": "Point",
    "coordinates": [
      -84.19883,
      39.89061
    ]
  }
}