{
  "type": "Feature",
  "properties": {
    "name": "Waterville",
    "country": "US",
    "subdivision": "OH",
    "timezone": "America/New_York"
  },
  "geometry": {
    "type": "Point",
    "coordinates": [
      -83.71827,
      41.50089
    ]
  }
}