{
  "type": "Feature",
  "properties": {
    "name": "Wauseon",
    "country": "US",
    "subdivision": "OH",
    "timezone": "America/New_York"
  },
  "geometry": {
    "type": "Point",
    "coordinates": [
      -84.14161,
      41.54922
    ]
  }
}