{
  "type": "Feature",
  "properties": {
    "name": "White Oak",
    "country": "US",
    "subdivision": "OH",
    "timezone": "America/New_York"
  },
  "geometry": {
    "type": "Point",
    "coordinates": [
      -84.59939,
      39.21311
    ]
  }
}