{
  "type": "Feature",
  "properties": {
    "name": "Willoughby",
    "country": "US",
    "subdivision": "OH",
    "timezone": "America/New_York"
  },
  "geometry": {
    "type": "Point",
    "coordinates": [
      -81.4065,
      41.63977
    ]
  }
}