{
  "type": "Feature",
  "properties": {
    "name": "Willoughby Hills",
    "country": "US",
    "subdivision": "OH",
    "timezone": "America/New_York"
  },
  "geometry": {
    "type": "Point",
    "coordinates": [
      -81.41845,
      41.59838
    ]
  }
}