{
  "type": "Feature",
  "properties": {
    "name": "Wilmington",
    "country": "US",
    "subdivision": "OH",
    "timezone": "America/New_York"
  },
  "geometry": {
    "type": "Point",
    "coordinates": [
      -83.82854,
      39.44534
    ]
  }
}