{
  "type": "Feature",
  "properties": {
    "name": "Woodsfield",
    "country": "US",
    "subdivision": "OH",
    "timezone": "America/New_York"
  },
  "geometry": {
    "type": "Point",
    "coordinates": [
      -81.11538,
      39.76257
    ]
  }
}