{
  "type": "Feature",
  "properties": {
    "name": "Woodlawn",
    "country": "US",
    "subdivision": "OH",
    "timezone": "America/New_York"
  },
  "geometry": {
    "type": "Point",
    "coordinates": [
      -84.47022,
      39.252
    ]
  }
}