{
  "type": "Feature",
  "properties": {
    "name": "Wright-Patterson AFB",
    "country": "US",
    "subdivision": "OH",
    "timezone": "America/New_York"
  },
  "geometry": {
    "type": "Point",
    "coordinates": [
      -84.05731,
      39.81113
    ]
  }
}