{
  "type": "Feature",
  "properties": {
    "name": "Youngstown",
    "country": "US",
    "subdivision": "OH",
    "timezone": "America/New_York"
  },
  "geometry": {
    "type": "Point",
    "coordinates": [
      -80.64952,
      41.09978
    ]
  }
}