{
  "type": "Feature",
  "properties": {
    "name": "Pushkinskiye Gory",
    "country": "RU",
    "subdivision": "60",
    "timezone": "Europe/Moscow"
  },
  "geometry": {
    "type": "Point",
    "coordinates": [
      28.9103,
      57.02085
    ]
  }
}