{
  "type": "Feature",
  "properties": {
    "name": "Pytalovo",
    "country": "RU",
    "subdivision": "60",
    "timezone": "Europe/Moscow"
  },
  "geometry": {
    "type": "Point",
    "coordinates": [
      27.91384,
      57.06791
    ]
  }
}