{
  "type": "Feature",
  "properties": {
    "name": "Altheim",
    "country": "AT",
    "subdivision": "04",
    "timezone": "Europe/Vienna"
  },
  "geometry": {
    "type": "Point",
    "coordinates": [
      13.23406,
      48.25154
    ]
  }
}