{
  "type": "Feature",
  "properties": {
    "name": "Andorf",
    "country": "AT",
    "subdivision": "04",
    "timezone": "Europe/Vienna"
  },
  "geometry": {
    "type": "Point",
    "coordinates": [
      13.57412,
      48.3713
    ]
  }
}