{
  "type": "Feature",
  "properties": {
    "name": "Diesseits",
    "country": "AT",
    "subdivision": "04",
    "timezone": "Europe/Vienna"
  },
  "geometry": {
    "type": "Point",
    "coordinates": [
      13.43546,
      48.29216
    ]
  }
}