{
  "type": "Feature",
  "properties": {
    "name": "Dörfl",
    "country": "AT",
    "subdivision": "04",
    "timezone": "Europe/Vienna"
  },
  "geometry": {
    "type": "Point",
    "coordinates": [
      13.65472,
      48.01245
    ]
  }
}