{
  "type": "Feature",
  "properties": {
    "name": "Dürnau",
    "country": "AT",
    "subdivision": "04",
    "timezone": "Europe/Vienna"
  },
  "geometry": {
    "type": "Point",
    "coordinates": [
      13.64459,
      47.9971
    ]
  }
}