{
  "type": "Feature",
  "properties": {
    "name": "Eberstalzell",
    "country": "AT",
    "subdivision": "04",
    "timezone": "Europe/Vienna"
  },
  "geometry": {
    "type": "Point",
    "coordinates": [
      13.98319,
      48.04392
    ]
  }
}