{
  "type": "Feature",
  "properties": {
    "name": "Gallspach",
    "country": "AT",
    "subdivision": "04",
    "timezone": "Europe/Vienna"
  },
  "geometry": {
    "type": "Point",
    "coordinates": [
      13.80981,
      48.20992
    ]
  }
}