{
  "type": "Feature",
  "properties": {
    "name": "Garsten",
    "country": "AT",
    "subdivision": "04",
    "timezone": "Europe/Vienna"
  },
  "geometry": {
    "type": "Point",
    "coordinates": [
      14.40747,
      48.0224
    ]
  }
}