{
  "type": "Feature",
  "properties": {
    "name": "Hartkirchen",
    "country": "AT",
    "subdivision": "04",
    "timezone": "Europe/Vienna"
  },
  "geometry": {
    "type": "Point",
    "coordinates": [
      14.00422,
      48.36349
    ]
  }
}