{
  "type": "Feature",
  "properties": {
    "name": "Hartheim",
    "country": "AT",
    "subdivision": "04",
    "timezone": "Europe/Vienna"
  },
  "geometry": {
    "type": "Point",
    "coordinates": [
      14.11426,
      48.28079
    ]
  }
}