{
  "type": "Feature",
  "properties": {
    "name": "Haslach an der Mühl",
    "country": "AT",
    "subdivision": "04",
    "timezone": "Europe/Vienna"
  },
  "geometry": {
    "type": "Point",
    "coordinates": [
      14.03984,
      48.5757
    ]
  }
}