{
  "type": "Feature",
  "properties": {
    "name": "Inzersdorf im Kremstal",
    "country": "AT",
    "subdivision": "04",
    "timezone": "Europe/Vienna"
  },
  "geometry": {
    "type": "Point",
    "coordinates": [
      14.08104,
      47.92808
    ]
  }
}