{
  "type": "Feature",
  "properties": {
    "name": "Laussa",
    "country": "AT",
    "subdivision": "04",
    "timezone": "Europe/Vienna"
  },
  "geometry": {
    "type": "Point",
    "coordinates": [
      14.45,
      47.95
    ]
  }
}