{
  "type": "Feature",
  "properties": {
    "name": "Lembach im Mühlkreis",
    "country": "AT",
    "subdivision": "04",
    "timezone": "Europe/Vienna"
  },
  "geometry": {
    "type": "Point",
    "coordinates": [
      13.89513,
      48.49517
    ]
  }
}