{
  "type": "Feature",
  "properties": {
    "name": "Losenstein",
    "country": "AT",
    "subdivision": "04",
    "timezone": "Europe/Vienna"
  },
  "geometry": {
    "type": "Point",
    "coordinates": [
      14.43672,
      47.92428
    ]
  }
}