{
  "type": "Feature",
  "properties": {
    "name": "Micheldorf in Oberösterreich",
    "country": "AT",
    "subdivision": "04",
    "timezone": "Europe/Vienna"
  },
  "geometry": {
    "type": "Point",
    "coordinates": [
      14.13357,
      47.87764
    ]
  }
}