{
  "type": "Feature",
  "properties": {
    "name": "Natternbach",
    "country": "AT",
    "subdivision": "04",
    "timezone": "Europe/Vienna"
  },
  "geometry": {
    "type": "Point",
    "coordinates": [
      13.74965,
      48.3973
    ]
  }
}