{
  "type": "Feature",
  "properties": {
    "name": "Neumarkt im Hausruckkreis",
    "country": "AT",
    "subdivision": "04",
    "timezone": "Europe/Vienna"
  },
  "geometry": {
    "type": "Point",
    "coordinates": [
      13.72836,
      48.2728
    ]
  }
}