{
  "type": "Feature",
  "properties": {
    "name": "Pettenbach",
    "country": "AT",
    "subdivision": "04",
    "timezone": "Europe/Vienna"
  },
  "geometry": {
    "type": "Point",
    "coordinates": [
      14.01692,
      47.96016
    ]
  }
}