{
  "type": "Feature",
  "properties": {
    "name": "Plesching",
    "country": "AT",
    "subdivision": "04",
    "timezone": "Europe/Vienna"
  },
  "geometry": {
    "type": "Point",
    "coordinates": [
      14.33802,
      48.32099
    ]
  }
}