{
  "type": "Feature",
  "properties": {
    "name": "Pregarten",
    "country": "AT",
    "subdivision": "04",
    "timezone": "Europe/Vienna"
  },
  "geometry": {
    "type": "Point",
    "coordinates": [
      14.53217,
      48.35488
    ]
  }
}