{
  "type": "Feature",
  "properties": {
    "name": "Rohrbach in Oberösterreich",
    "country": "AT",
    "subdivision": "04",
    "timezone": "Europe/Vienna"
  },
  "geometry": {
    "type": "Point",
    "coordinates": [
      13.98834,
      48.57275
    ]
  }
}