{
  "type": "Feature",
  "properties": {
    "name": "Sankt Georgen an der Gusen",
    "country": "AT",
    "subdivision": "04",
    "timezone": "Europe/Vienna"
  },
  "geometry": {
    "type": "Point",
    "coordinates": [
      14.44951,
      48.27183
    ]
  }
}