{
  "type": "Feature",
  "properties": {
    "name": "Sankt Martin im Mühlkreis",
    "country": "AT",
    "subdivision": "04",
    "timezone": "Europe/Vienna"
  },
  "geometry": {
    "type": "Point",
    "coordinates": [
      14.03821,
      48.41553
    ]
  }
}