{
  "type": "Feature",
  "properties": {
    "name": "Sankt Lorenz",
    "country": "AT",
    "subdivision": "04",
    "timezone": "Europe/Vienna"
  },
  "geometry": {
    "type": "Point",
    "coordinates": [
      13.34839,
      47.8324
    ]
  }
}