{
  "type": "Feature",
  "properties": {
    "name": "Sarleinsbach",
    "country": "AT",
    "subdivision": "04",
    "timezone": "Europe/Vienna"
  },
  "geometry": {
    "type": "Point",
    "coordinates": [
      13.90491,
      48.54525
    ]
  }
}