{
  "type": "Feature",
  "properties": {
    "name": "Schafwiesen",
    "country": "AT",
    "subdivision": "04",
    "timezone": "Europe/Vienna"
  },
  "geometry": {
    "type": "Point",
    "coordinates": [
      14.07067,
      48.17194
    ]
  }
}