{
  "type": "Feature",
  "properties": {
    "name": "Schwertberg",
    "country": "AT",
    "subdivision": "04",
    "timezone": "Europe/Vienna"
  },
  "geometry": {
    "type": "Point",
    "coordinates": [
      14.58474,
      48.2734
    ]
  }
}