{
  "type": "Feature",
  "properties": {
    "name": "Stadl-Hausruck",
    "country": "AT",
    "subdivision": "04",
    "timezone": "Europe/Vienna"
  },
  "geometry": {
    "type": "Point",
    "coordinates": [
      13.85213,
      48.08255
    ]
  }
}