{
  "type": "Feature",
  "properties": {
    "name": "Strassham",
    "country": "AT",
    "subdivision": "04",
    "timezone": "Europe/Vienna"
  },
  "geometry": {
    "type": "Point",
    "coordinates": [
      14.14524,
      48.28348
    ]
  }
}