{
  "type": "Feature",
  "properties": {
    "name": "Tiefgraben",
    "country": "AT",
    "subdivision": "04",
    "timezone": "Europe/Vienna"
  },
  "geometry": {
    "type": "Point",
    "coordinates": [
      13.30591,
      47.87385
    ]
  }
}