{
  "type": "Feature",
  "properties": {
    "name": "Traun",
    "country": "AT",
    "subdivision": "04",
    "timezone": "Europe/Vienna"
  },
  "geometry": {
    "type": "Point",
    "coordinates": [
      14.23833,
      48.22086
    ]
  }
}