{
  "type": "Feature",
  "properties": {
    "name": "Vorchdorf",
    "country": "AT",
    "subdivision": "04",
    "timezone": "Europe/Vienna"
  },
  "geometry": {
    "type": "Point",
    "coordinates": [
      13.92122,
      48.00388
    ]
  }
}