{
  "type": "Feature",
  "properties": {
    "name": "Wagram",
    "country": "AT",
    "subdivision": "04",
    "timezone": "Europe/Vienna"
  },
  "geometry": {
    "type": "Point",
    "coordinates": [
      14.22996,
      48.23828
    ]
  }
}