{
  "type": "Feature",
  "properties": {
    "name": "Wagrain",
    "country": "AT",
    "subdivision": "04",
    "timezone": "Europe/Vienna"
  },
  "geometry": {
    "type": "Point",
    "coordinates": [
      13.67163,
      48.00503
    ]
  }
}