{
  "type": "Feature",
  "properties": {
    "name": "Weisskirchen an der Traun",
    "country": "AT",
    "subdivision": "04",
    "timezone": "Europe/Vienna"
  },
  "geometry": {
    "type": "Point",
    "coordinates": [
      14.12395,
      48.16202
    ]
  }
}