{
  "type": "Feature",
  "properties": {
    "name": "Balbasava",
    "country": "BY",
    "subdivision": "07",
    "timezone": "Europe/Minsk"
  },
  "geometry": {
    "type": "Point",
    "coordinates": [
      30.2909,
      54.4207
    ]
  }
}