{
  "type": "Feature",
  "properties": {
    "name": "Baran’",
    "country": "BY",
    "subdivision": "07",
    "timezone": "Europe/Minsk"
  },
  "geometry": {
    "type": "Point",
    "coordinates": [
      30.3159,
      54.4784
    ]
  }
}