{
  "type": "Feature",
  "properties": {
    "name": "Braslaw",
    "country": "BY",
    "subdivision": "07",
    "timezone": "Europe/Minsk"
  },
  "geometry": {
    "type": "Point",
    "coordinates": [
      27.0418,
      55.6413
    ]
  }
}