{
  "type": "Feature",
  "properties": {
    "name": "Chashniki",
    "country": "BY",
    "subdivision": "07",
    "timezone": "Europe/Minsk"
  },
  "geometry": {
    "type": "Point",
    "coordinates": [
      29.1608,
      54.8584
    ]
  }
}