{
  "type": "Feature",
  "properties": {
    "name": "Lyozna",
    "country": "BY",
    "subdivision": "07",
    "timezone": "Europe/Minsk"
  },
  "geometry": {
    "type": "Point",
    "coordinates": [
      30.797,
      55.0247
    ]
  }
}