{
  "type": "Feature",
  "properties": {
    "name": "Pastavy",
    "country": "BY",
    "subdivision": "07",
    "timezone": "Europe/Minsk"
  },
  "geometry": {
    "type": "Point",
    "coordinates": [
      26.83263,
      55.11676
    ]
  }
}