{
  "type": "Feature",
  "properties": {
    "name": "Asahikawa",
    "country": "JP",
    "subdivision": "12",
    "timezone": "Asia/Tokyo"
  },
  "geometry": {
    "type": "Point",
    "coordinates": [
      142.36489,
      43.77063
    ]
  }
}