{
  "type": "Feature",
  "properties": {
    "name": "Fukagawa",
    "country": "JP",
    "subdivision": "12",
    "timezone": "Asia/Tokyo"
  },
  "geometry": {
    "type": "Point",
    "coordinates": [
      142.03917,
      43.70806
    ]
  }
}