{
  "type": "Feature",
  "properties": {
    "name": "Honchō",
    "country": "JP",
    "subdivision": "12",
    "timezone": "Asia/Tokyo"
  },
  "geometry": {
    "type": "Point",
    "coordinates": [
      140.69386,
      41.8944
    ]
  }
}