{
  "type": "Feature",
  "properties": {
    "name": "Ishikari",
    "country": "JP",
    "subdivision": "12",
    "timezone": "Asia/Tokyo"
  },
  "geometry": {
    "type": "Point",
    "coordinates": [
      141.35389,
      43.23972
    ]
  }
}