{
  "type": "Feature",
  "properties": {
    "name": "Makubetsu",
    "country": "JP",
    "subdivision": "12",
    "timezone": "Asia/Tokyo"
  },
  "geometry": {
    "type": "Point",
    "coordinates": [
      141.82111,
      45.37139
    ]
  }
}