{
  "type": "Feature",
  "properties": {
    "name": "Shibetsu",
    "country": "JP",
    "subdivision": "12",
    "timezone": "Asia/Tokyo"
  },
  "geometry": {
    "type": "Point",
    "coordinates": [
      145.13197,
      43.65899
    ]
  }
}