{
  "type": "Feature",
  "properties": {
    "name": "Bongor",
    "country": "TD",
    "subdivision": "16",
    "timezone": "Africa/Ndjamena"
  },
  "geometry": {
    "type": "Point",
    "coordinates": [
      15.37425,
      10.28088
    ]
  }
}