{
  "type": "Feature",
  "properties": {
    "name": "Andaç",
    "country": "TR",
    "subdivision": "80",
    "timezone": "Europe/Istanbul"
  },
  "geometry": {
    "type": "Point",
    "coordinates": [
      43.26395,
      37.355
    ]
  }
}