{
  "type": "Feature",
  "properties": {
    "name": "Çardaklı",
    "country": "TR",
    "subdivision": "80",
    "timezone": "Europe/Istanbul"
  },
  "geometry": {
    "type": "Point",
    "coordinates": [
      42.58409,
      37.23098
    ]
  }
}