{
  "type": "Feature",
  "properties": {
    "name": "Kızılsu",
    "country": "TR",
    "subdivision": "80",
    "timezone": "Europe/Istanbul"
  },
  "geometry": {
    "type": "Point",
    "coordinates": [
      42.19639,
      37.45402
    ]
  }
}