{
  "type": "Feature",
  "properties": {
    "name": "Pınarbaşı",
    "country": "TR",
    "subdivision": "80",
    "timezone": "Europe/Istanbul"
  },
  "geometry": {
    "type": "Point",
    "coordinates": [
      41.88689,
      37.21368
    ]
  }
}