{
  "type": "Feature",
  "properties": {
    "name": "Altınözü",
    "country": "TR",
    "subdivision": "31",
    "timezone": "Europe/Istanbul"
  },
  "geometry": {
    "type": "Point",
    "coordinates": [
      36.24827,
      36.11554
    ]
  }
}