{
  "type": "Feature",
  "properties": {
    "name": "Gümüşgöze",
    "country": "TR",
    "subdivision": "31",
    "timezone": "Europe/Istanbul"
  },
  "geometry": {
    "type": "Point",
    "coordinates": [
      36.13284,
      36.14785
    ]
  }
}