{
  "type": "Feature",
  "properties": {
    "name": "Karasüleymanlı",
    "country": "TR",
    "subdivision": "31",
    "timezone": "Europe/Istanbul"
  },
  "geometry": {
    "type": "Point",
    "coordinates": [
      36.41431,
      36.34191
    ]
  }
}