{
  "type": "Feature",
  "properties": {
    "name": "Kastal",
    "country": "TR",
    "subdivision": "31",
    "timezone": "Europe/Istanbul"
  },
  "geometry": {
    "type": "Point",
    "coordinates": [
      36.2409,
      36.2476
    ]
  }
}