{
  "type": "Feature",
  "properties": {
    "name": "Mahmutlar",
    "country": "TR",
    "subdivision": "31",
    "timezone": "Europe/Istanbul"
  },
  "geometry": {
    "type": "Point",
    "coordinates": [
      36.19231,
      36.949
    ]
  }
}