{
  "type": "Feature",
  "properties": {
    "name": "Reyhanlı",
    "country": "TR",
    "subdivision": "31",
    "timezone": "Europe/Istanbul"
  },
  "geometry": {
    "type": "Point",
    "coordinates": [
      36.56747,
      36.26791
    ]
  }
}