{
  "type": "Feature",
  "properties": {
    "name": "Uzunbağ",
    "country": "TR",
    "subdivision": "31",
    "timezone": "Europe/Istanbul"
  },
  "geometry": {
    "type": "Point",
    "coordinates": [
      36.03603,
      36.14023
    ]
  }
}