{
  "type": "Feature",
  "properties": {
    "name": "Marka",
    "country": "SO",
    "subdivision": "14",
    "timezone": "Africa/Mogadishu"
  },
  "geometry": {
    "type": "Point",
    "coordinates": [
      44.77166,
      1.71594
    ]
  }
}