{
  "type": "Feature",
  "properties": {
    "name": "Mongmong-Toto-Maite Village",
    "country": "GU",
    "subdivision": "MT",
    "timezone": "Pacific/Guam"
  },
  "geometry": {
    "type": "Point",
    "coordinates": [
      144.78214,
      13.46857
    ]
  }
}