{
  "type": "Feature",
  "properties": {
    "name": "Cuca",
    "country": "RO",
    "subdivision": "18",
    "timezone": "Europe/Bucharest"
  },
  "geometry": {
    "type": "Point",
    "coordinates": [
      27.88333,
      45.73333
    ]
  }
}