{
  "type": "Feature",
  "properties": {
    "name": "Drăguşeni",
    "country": "RO",
    "subdivision": "18",
    "timezone": "Europe/Bucharest"
  },
  "geometry": {
    "type": "Point",
    "coordinates": [
      27.75,
      45.96667
    ]
  }
}