{
  "type": "Feature",
  "properties": {
    "name": "Folteşti",
    "country": "RO",
    "subdivision": "18",
    "timezone": "Europe/Bucharest"
  },
  "geometry": {
    "type": "Point",
    "coordinates": [
      28.05,
      45.75
    ]
  }
}