{
  "type": "Feature",
  "properties": {
    "name": "Ungureni",
    "country": "RO",
    "subdivision": "18",
    "timezone": "Europe/Bucharest"
  },
  "geometry": {
    "type": "Point",
    "coordinates": [
      27.47,
      45.91307
    ]
  }
}