{
  "type": "Feature",
  "properties": {
    "name": "Vânători",
    "country": "RO",
    "subdivision": "18",
    "timezone": "Europe/Bucharest"
  },
  "geometry": {
    "type": "Point",
    "coordinates": [
      28.01667,
      45.53333
    ]
  }
}