{
  "type": "Feature",
  "properties": {
    "name": "Elhovo",
    "country": "BG",
    "subdivision": "65",
    "timezone": "Europe/Sofia"
  },
  "geometry": {
    "type": "Point",
    "coordinates": [
      26.56667,
      42.16667
    ]
  }
}