{
  "type": "Feature",
  "properties": {
    "name": "Ciego de Ávila",
    "country": "CU",
    "subdivision": "07",
    "timezone": "America/Havana"
  },
  "geometry": {
    "type": "Point",
    "coordinates": [
      -78.76194,
      21.84
    ]
  }
}