{
  "type": "Feature",
  "properties": {
    "name": "Almodóvar del Campo",
    "country": "ES",
    "subdivision": "54",
    "timezone": "Europe/Madrid"
  },
  "geometry": {
    "type": "Point",
    "coordinates": [
      -4.17908,
      38.70936
    ]
  }
}