{
  "type": "Feature",
  "properties": {
    "name": "Alovera",
    "country": "ES",
    "subdivision": "54",
    "timezone": "Europe/Madrid"
  },
  "geometry": {
    "type": "Point",
    "coordinates": [
      -3.24529,
      40.59368
    ]
  }
}