{
  "type": "Feature",
  "properties": {
    "name": "Azuqueca de Henares",
    "country": "ES",
    "subdivision": "54",
    "timezone": "Europe/Madrid"
  },
  "geometry": {
    "type": "Point",
    "coordinates": [
      -3.26753,
      40.56566
    ]
  }
}