{
  "type": "Feature",
  "properties": {
    "name": "Borox",
    "country": "ES",
    "subdivision": "54",
    "timezone": "Europe/Madrid"
  },
  "geometry": {
    "type": "Point",
    "coordinates": [
      -3.73804,
      40.06795
    ]
  }
}