{
  "type": "Feature",
  "properties": {
    "name": "Calera y Chozas",
    "country": "ES",
    "subdivision": "54",
    "timezone": "Europe/Madrid"
  },
  "geometry": {
    "type": "Point",
    "coordinates": [
      -4.98213,
      39.88278
    ]
  }
}