{
  "type": "Feature",
  "properties": {
    "name": "Casas Ibáñez",
    "country": "ES",
    "subdivision": "54",
    "timezone": "Europe/Madrid"
  },
  "geometry": {
    "type": "Point",
    "coordinates": [
      -1.46667,
      39.28333
    ]
  }
}