{
  "type": "Feature",
  "properties": {
    "name": "Casas de Fernando Alonso",
    "country": "ES",
    "subdivision": "54",
    "timezone": "Europe/Madrid"
  },
  "geometry": {
    "type": "Point",
    "coordinates": [
      -2.32402,
      39.35065
    ]
  }
}