{
  "type": "Feature",
  "properties": {
    "name": "Cedillo del Condado",
    "country": "ES",
    "subdivision": "54",
    "timezone": "Europe/Madrid"
  },
  "geometry": {
    "type": "Point",
    "coordinates": [
      -3.92127,
      40.1126
    ]
  }
}