{
  "type": "Feature",
  "properties": {
    "name": "Chiloeches",
    "country": "ES",
    "subdivision": "54",
    "timezone": "Europe/Madrid"
  },
  "geometry": {
    "type": "Point",
    "coordinates": [
      -3.16003,
      40.57038
    ]
  }
}