{
  "type": "Feature",
  "properties": {
    "name": "Chozas de Canales",
    "country": "ES",
    "subdivision": "54",
    "timezone": "Europe/Madrid"
  },
  "geometry": {
    "type": "Point",
    "coordinates": [
      -4.04333,
      40.10014
    ]
  }
}