{
  "type": "Feature",
  "properties": {
    "name": "Daimiel",
    "country": "ES",
    "subdivision": "54",
    "timezone": "Europe/Madrid"
  },
  "geometry": {
    "type": "Point",
    "coordinates": [
      -3.61498,
      39.07004
    ]
  }
}