{
  "type": "Feature",
  "properties": {
    "name": "El Toboso",
    "country": "ES",
    "subdivision": "54",
    "timezone": "Europe/Madrid"
  },
  "geometry": {
    "type": "Point",
    "coordinates": [
      -2.99726,
      39.51333
    ]
  }
}