{
  "type": "Feature",
  "properties": {
    "name": "Fuencaliente",
    "country": "ES",
    "subdivision": "54",
    "timezone": "Europe/Madrid"
  },
  "geometry": {
    "type": "Point",
    "coordinates": [
      -4.02576,
      39.18624
    ]
  }
}