{
  "type": "Feature",
  "properties": {
    "name": "Huerta de Valdecarábanos",
    "country": "ES",
    "subdivision": "54",
    "timezone": "Europe/Madrid"
  },
  "geometry": {
    "type": "Point",
    "coordinates": [
      -3.61275,
      39.86319
    ]
  }
}