{
  "type": "Feature",
  "properties": {
    "name": "La Pueblanueva",
    "country": "ES",
    "subdivision": "54",
    "timezone": "Europe/Madrid"
  },
  "geometry": {
    "type": "Point",
    "coordinates": [
      -4.67933,
      39.91208
    ]
  }
}