{
  "type": "Feature",
  "properties": {
    "name": "Las Ventas de Retamosa",
    "country": "ES",
    "subdivision": "54",
    "timezone": "Europe/Madrid"
  },
  "geometry": {
    "type": "Point",
    "coordinates": [
      -4.11455,
      40.15526
    ]
  }
}