{
  "type": "Feature",
  "properties": {
    "name": "Lominchar",
    "country": "ES",
    "subdivision": "54",
    "timezone": "Europe/Madrid"
  },
  "geometry": {
    "type": "Point",
    "coordinates": [
      -3.96713,
      40.09061
    ]
  }
}