{
  "type": "Feature",
  "properties": {
    "name": "Menasalbas",
    "country": "ES",
    "subdivision": "54",
    "timezone": "Europe/Madrid"
  },
  "geometry": {
    "type": "Point",
    "coordinates": [
      -4.28418,
      39.63954
    ]
  }
}