{
  "type": "Feature",
  "properties": {
    "name": "Numancia de la Sagra",
    "country": "ES",
    "subdivision": "54",
    "timezone": "Europe/Madrid"
  },
  "geometry": {
    "type": "Point",
    "coordinates": [
      -3.85118,
      40.07395
    ]
  }
}