{
  "type": "Feature",
  "properties": {
    "name": "Olías del Rey",
    "country": "ES",
    "subdivision": "54",
    "timezone": "Europe/Madrid"
  },
  "geometry": {
    "type": "Point",
    "coordinates": [
      -3.98684,
      39.94436
    ]
  }
}