{
  "type": "Feature",
  "properties": {
    "name": "Ontígola",
    "country": "ES",
    "subdivision": "54",
    "timezone": "Europe/Madrid"
  },
  "geometry": {
    "type": "Point",
    "coordinates": [
      -3.57227,
      40.00421
    ]
  }
}