{
  "type": "Feature",
  "properties": {
    "name": "Ontur",
    "country": "ES",
    "subdivision": "54",
    "timezone": "Europe/Madrid"
  },
  "geometry": {
    "type": "Point",
    "coordinates": [
      -1.49724,
      38.61509
    ]
  }
}