{
  "type": "Feature",
  "properties": {
    "name": "Pedro Muñoz",
    "country": "ES",
    "subdivision": "54",
    "timezone": "Europe/Madrid"
  },
  "geometry": {
    "type": "Point",
    "coordinates": [
      -2.94664,
      39.40285
    ]
  }
}