{
  "type": "Feature",
  "properties": {
    "name": "Polán",
    "country": "ES",
    "subdivision": "54",
    "timezone": "Europe/Madrid"
  },
  "geometry": {
    "type": "Point",
    "coordinates": [
      -4.16792,
      39.78765
    ]
  }
}