{
  "type": "Feature",
  "properties": {
    "name": "Pozuelo de Calatrava",
    "country": "ES",
    "subdivision": "54",
    "timezone": "Europe/Madrid"
  },
  "geometry": {
    "type": "Point",
    "coordinates": [
      -3.83333,
      38.58333
    ]
  }
}