{
  "type": "Feature",
  "properties": {
    "name": "Pulgar",
    "country": "ES",
    "subdivision": "54",
    "timezone": "Europe/Madrid"
  },
  "geometry": {
    "type": "Point",
    "coordinates": [
      -4.15233,
      39.69383
    ]
  }
}