{
  "type": "Feature",
  "properties": {
    "name": "Quintanar del Rey",
    "country": "ES",
    "subdivision": "54",
    "timezone": "Europe/Madrid"
  },
  "geometry": {
    "type": "Point",
    "coordinates": [
      -1.93333,
      39.33333
    ]
  }
}