{
  "type": "Feature",
  "properties": {
    "name": "Quismondo",
    "country": "ES",
    "subdivision": "54",
    "timezone": "Europe/Madrid"
  },
  "geometry": {
    "type": "Point",
    "coordinates": [
      -4.32394,
      40.10533
    ]
  }
}