{
  "type": "Feature",
  "properties": {
    "name": "Santa Olalla",
    "country": "ES",
    "subdivision": "54",
    "timezone": "Europe/Madrid"
  },
  "geometry": {
    "type": "Point",
    "coordinates": [
      -4.43025,
      40.02348
    ]
  }
}