{
  "type": "Feature",
  "properties": {
    "name": "Sigüenza",
    "country": "ES",
    "subdivision": "54",
    "timezone": "Europe/Madrid"
  },
  "geometry": {
    "type": "Point",
    "coordinates": [
      -2.64308,
      41.06892
    ]
  }
}