{
  "type": "Feature",
  "properties": {
    "name": "Socovos",
    "country": "ES",
    "subdivision": "54",
    "timezone": "Europe/Madrid"
  },
  "geometry": {
    "type": "Point",
    "coordinates": [
      -1.98485,
      38.33232
    ]
  }
}