{
  "type": "Feature",
  "properties": {
    "name": "Sonseca",
    "country": "ES",
    "subdivision": "54",
    "timezone": "Europe/Madrid"
  },
  "geometry": {
    "type": "Point",
    "coordinates": [
      -3.97448,
      39.67747
    ]
  }
}