{
  "type": "Feature",
  "properties": {
    "name": "Terrinches",
    "country": "ES",
    "subdivision": "54",
    "timezone": "Europe/Madrid"
  },
  "geometry": {
    "type": "Point",
    "coordinates": [
      -2.84215,
      38.61057
    ]
  }
}