{
  "type": "Feature",
  "properties": {
    "name": "Velada",
    "country": "ES",
    "subdivision": "54",
    "timezone": "Europe/Madrid"
  },
  "geometry": {
    "type": "Point",
    "coordinates": [
      -4.97641,
      39.97687
    ]
  }
}