{
  "type": "Feature",
  "properties": {
    "name": "Villanueva de la Torre",
    "country": "ES",
    "subdivision": "54",
    "timezone": "Europe/Madrid"
  },
  "geometry": {
    "type": "Point",
    "coordinates": [
      -3.29764,
      40.58216
    ]
  }
}