{
  "type": "Feature",
  "properties": {
    "name": "Villar de Olalla",
    "country": "ES",
    "subdivision": "54",
    "timezone": "Europe/Madrid"
  },
  "geometry": {
    "type": "Point",
    "coordinates": [
      -2.19561,
      40.01496
    ]
  }
}