{
  "type": "Feature",
  "properties": {
    "name": "Villaseca de la Sagra",
    "country": "ES",
    "subdivision": "54",
    "timezone": "Europe/Madrid"
  },
  "geometry": {
    "type": "Point",
    "coordinates": [
      -3.88291,
      39.96185
    ]
  }
}