{
  "type": "Feature",
  "properties": {
    "name": "Villasequilla de Yepes",
    "country": "ES",
    "subdivision": "54",
    "timezone": "Europe/Madrid"
  },
  "geometry": {
    "type": "Point",
    "coordinates": [
      -3.7311,
      39.87582
    ]
  }
}