{
  "type": "Feature",
  "properties": {
    "name": "Villanueva de la Fuente",
    "country": "ES",
    "subdivision": "54",
    "timezone": "Europe/Madrid"
  },
  "geometry": {
    "type": "Point",
    "coordinates": [
      -2.69637,
      38.69463
    ]
  }
}