{
  "type": "Feature",
  "properties": {
    "name": "Yunquera de Henares",
    "country": "ES",
    "subdivision": "54",
    "timezone": "Europe/Madrid"
  },
  "geometry": {
    "type": "Point",
    "coordinates": [
      -3.1626,
      40.75139
    ]
  }
}