{
  "type": "Feature",
  "properties": {
    "name": "Ashdown",
    "country": "US",
    "subdivision": "AR",
    "timezone": "America/Chicago"
  },
  "geometry": {
    "type": "Point",
    "coordinates": [
      -94.13131,
      33.67429
    ]
  }
}