{
  "type": "Feature",
  "properties": {
    "name": "Augusta",
    "country": "US",
    "subdivision": "AR",
    "timezone": "America/Chicago"
  },
  "geometry": {
    "type": "Point",
    "coordinates": [
      -91.36541,
      35.28231
    ]
  }
}