{
  "type": "Feature",
  "properties": {
    "name": "Bald Knob",
    "country": "US",
    "subdivision": "AR",
    "timezone": "America/Chicago"
  },
  "geometry": {
    "type": "Point",
    "coordinates": [
      -91.56791,
      35.30981
    ]
  }
}