{
  "type": "Feature",
  "properties": {
    "name": "Bay",
    "country": "US",
    "subdivision": "AR",
    "timezone": "America/Chicago"
  },
  "geometry": {
    "type": "Point",
    "coordinates": [
      -90.56233,
      35.7423
    ]
  }
}