{
  "type": "Feature",
  "properties": {
    "name": "Bentonville",
    "country": "US",
    "subdivision": "AR",
    "timezone": "America/Chicago"
  },
  "geometry": {
    "type": "Point",
    "coordinates": [
      -94.20882,
      36.37285
    ]
  }
}