{
  "type": "Feature",
  "properties": {
    "name": "Calico Rock",
    "country": "US",
    "subdivision": "AR",
    "timezone": "America/Chicago"
  },
  "geometry": {
    "type": "Point",
    "coordinates": [
      -92.13599,
      36.11951
    ]
  }
}