{
  "type": "Feature",
  "properties": {
    "name": "Cave City",
    "country": "US",
    "subdivision": "AR",
    "timezone": "America/Chicago"
  },
  "geometry": {
    "type": "Point",
    "coordinates": [
      -91.54847,
      35.94174
    ]
  }
}