{
  "type": "Feature",
  "properties": {
    "name": "Cherokee Village",
    "country": "US",
    "subdivision": "AR",
    "timezone": "America/Chicago"
  },
  "geometry": {
    "type": "Point",
    "coordinates": [
      -91.51597,
      36.29784
    ]
  }
}