{
  "type": "Feature",
  "properties": {
    "name": "Conway",
    "country": "US",
    "subdivision": "AR",
    "timezone": "America/Chicago"
  },
  "geometry": {
    "type": "Point",
    "coordinates": [
      -92.4421,
      35.0887
    ]
  }
}