{
  "type": "Feature",
  "properties": {
    "name": "Dover",
    "country": "US",
    "subdivision": "AR",
    "timezone": "America/Chicago"
  },
  "geometry": {
    "type": "Point",
    "coordinates": [
      -93.11434,
      35.40147
    ]
  }
}