{
  "type": "Feature",
  "properties": {
    "name": "El Dorado",
    "country": "US",
    "subdivision": "AR",
    "timezone": "America/Chicago"
  },
  "geometry": {
    "type": "Point",
    "coordinates": [
      -92.66627,
      33.20763
    ]
  }
}