{
  "type": "Feature",
  "properties": {
    "name": "Elkins",
    "country": "US",
    "subdivision": "AR",
    "timezone": "America/Chicago"
  },
  "geometry": {
    "type": "Point",
    "coordinates": [
      -94.00825,
      36.00147
    ]
  }
}