{
  "type": "Feature",
  "properties": {
    "name": "Gentry",
    "country": "US",
    "subdivision": "AR",
    "timezone": "America/Chicago"
  },
  "geometry": {
    "type": "Point",
    "coordinates": [
      -94.48466,
      36.26758
    ]
  }
}