{
  "type": "Feature",
  "properties": {
    "name": "Greenbrier",
    "country": "US",
    "subdivision": "AR",
    "timezone": "America/Chicago"
  },
  "geometry": {
    "type": "Point",
    "coordinates": [
      -92.38765,
      35.23397
    ]
  }
}