{
  "type": "Feature",
  "properties": {
    "name": "Hope",
    "country": "US",
    "subdivision": "AR",
    "timezone": "America/Chicago"
  },
  "geometry": {
    "type": "Point",
    "coordinates": [
      -93.59157,
      33.66706
    ]
  }
}