{
  "type": "Feature",
  "properties": {
    "name": "Horatio",
    "country": "US",
    "subdivision": "AR",
    "timezone": "America/Chicago"
  },
  "geometry": {
    "type": "Point",
    "coordinates": [
      -94.35715,
      33.93845
    ]
  }
}