{
  "type": "Feature",
  "properties": {
    "name": "Jonesboro",
    "country": "US",
    "subdivision": "AR",
    "timezone": "America/Chicago"
  },
  "geometry": {
    "type": "Point",
    "coordinates": [
      -90.70428,
      35.8423
    ]
  }
}