{
  "type": "Feature",
  "properties": {
    "name": "Mansfield",
    "country": "US",
    "subdivision": "AR",
    "timezone": "America/Chicago"
  },
  "geometry": {
    "type": "Point",
    "coordinates": [
      -94.25271,
      35.05954
    ]
  }
}