{
  "type": "Feature",
  "properties": {
    "name": "Mena",
    "country": "US",
    "subdivision": "AR",
    "timezone": "America/Chicago"
  },
  "geometry": {
    "type": "Point",
    "coordinates": [
      -94.23966,
      34.58622
    ]
  }
}