{
  "type": "Feature",
  "properties": {
    "name": "Mountain Home",
    "country": "US",
    "subdivision": "AR",
    "timezone": "America/Chicago"
  },
  "geometry": {
    "type": "Point",
    "coordinates": [
      -92.38516,
      36.33534
    ]
  }
}