{
  "type": "Feature",
  "properties": {
    "name": "Nashville",
    "country": "US",
    "subdivision": "AR",
    "timezone": "America/Chicago"
  },
  "geometry": {
    "type": "Point",
    "coordinates": [
      -93.84713,
      33.94567
    ]
  }
}