{
  "type": "Feature",
  "properties": {
    "name": "Southside",
    "country": "US",
    "subdivision": "AR",
    "timezone": "America/Chicago"
  },
  "geometry": {
    "type": "Point",
    "coordinates": [
      -91.62347,
      35.69841
    ]
  }
}