{
  "type": "Feature",
  "properties": {
    "name": "Stuttgart",
    "country": "US",
    "subdivision": "AR",
    "timezone": "America/Chicago"
  },
  "geometry": {
    "type": "Point",
    "coordinates": [
      -91.55263,
      34.50037
    ]
  }
}