{
  "type": "Feature",
  "properties": {
    "name": "West Memphis",
    "country": "US",
    "subdivision": "AR",
    "timezone": "America/Chicago"
  },
  "geometry": {
    "type": "Point",
    "coordinates": [
      -90.18454,
      35.14648
    ]
  }
}