{
  "type": "Feature",
  "properties": {
    "name": "Orashac",
    "country": "MK",
    "subdivision": "75",
    "timezone": "Europe/Skopje"
  },
  "geometry": {
    "type": "Point",
    "coordinates": [
      21.79972,
      42.0625
    ]
  }
}