{
  "type": "Feature",
  "properties": {
    "name": "Булачани",
    "country": "MK",
    "subdivision": "00",
    "timezone": "Europe/Skopje"
  },
  "geometry": {
    "type": "Point",
    "coordinates": [
      21.50278,
      42.07056
    ]
  }
}