{
  "type": "Feature",
  "properties": {
    "name": "Goulouré",
    "country": "BF",
    "subdivision": "06",
    "timezone": "Africa/Ouagadougou"
  },
  "geometry": {
    "type": "Point",
    "coordinates": [
      -1.93394,
      12.23484
    ]
  }
}