{
  "type": "Feature",
  "properties": {
    "name": "Ayvacık",
    "country": "TR",
    "subdivision": "17",
    "timezone": "Europe/Istanbul"
  },
  "geometry": {
    "type": "Point",
    "coordinates": [
      26.40472,
      39.60111
    ]
  }
}