{
  "type": "Feature",
  "properties": {
    "name": "Camayenne",
    "country": "GN",
    "subdivision": "04",
    "timezone": "Africa/Conakry"
  },
  "geometry": {
    "type": "Point",
    "coordinates": [
      -13.68778,
      9.535
    ]
  }
}