{
  "type": "Feature",
  "properties": {
    "name": "Mişrātah",
    "country": "LY",
    "subdivision": "72",
    "timezone": "Africa/Tripoli"
  },
  "geometry": {
    "type": "Point",
    "coordinates": [
      15.09254,
      32.37535
    ]
  }
}