{
  "type": "Feature",
  "properties": {
    "name": "Abancay",
    "country": "PE",
    "subdivision": "03",
    "timezone": "America/Lima"
  },
  "geometry": {
    "type": "Point",
    "coordinates": [
      -72.88139,
      -13.63389
    ]
  }
}