{
  "type": "Feature",
  "properties": {
    "name": "Alice",
    "country": "US",
    "subdivision": "TX",
    "timezone": "America/Chicago"
  },
  "geometry": {
    "type": "Point",
    "coordinates": [
      -98.06972,
      27.75225
    ]
  }
}