{
  "type": "Feature",
  "properties": {
    "name": "Alton",
    "country": "US",
    "subdivision": "TX",
    "timezone": "America/Chicago"
  },
  "geometry": {
    "type": "Point",
    "coordinates": [
      -98.31335,
      26.28729
    ]
  }
}