{
  "type": "Feature",
  "properties": {
    "name": "Alvord",
    "country": "US",
    "subdivision": "TX",
    "timezone": "America/Chicago"
  },
  "geometry": {
    "type": "Point",
    "coordinates": [
      -97.69475,
      33.35845
    ]
  }
}