{
  "type": "Feature",
  "properties": {
    "name": "Aubrey",
    "country": "US",
    "subdivision": "TX",
    "timezone": "America/Chicago"
  },
  "geometry": {
    "type": "Point",
    "coordinates": [
      -96.98612,
      33.30428
    ]
  }
}