{
  "type": "Feature",
  "properties": {
    "name": "Bangs",
    "country": "US",
    "subdivision": "TX",
    "timezone": "America/Chicago"
  },
  "geometry": {
    "type": "Point",
    "coordinates": [
      -99.13255,
      31.7171
    ]
  }
}