{
  "type": "Feature",
  "properties": {
    "name": "Bartlett",
    "country": "US",
    "subdivision": "TX",
    "timezone": "America/Chicago"
  },
  "geometry": {
    "type": "Point",
    "coordinates": [
      -97.42556,
      30.79491
    ]
  }
}