{
  "type": "Feature",
  "properties": {
    "name": "Bells",
    "country": "US",
    "subdivision": "TX",
    "timezone": "America/Chicago"
  },
  "geometry": {
    "type": "Point",
    "coordinates": [
      -96.41082,
      33.61038
    ]
  }
}