{
  "type": "Feature",
  "properties": {
    "name": "Beverly Hills",
    "country": "US",
    "subdivision": "TX",
    "timezone": "America/Chicago"
  },
  "geometry": {
    "type": "Point",
    "coordinates": [
      -97.15389,
      31.52156
    ]
  }
}