{
  "type": "Feature",
  "properties": {
    "name": "Boyd",
    "country": "US",
    "subdivision": "TX",
    "timezone": "America/Chicago"
  },
  "geometry": {
    "type": "Point",
    "coordinates": [
      -97.5653,
      33.07873
    ]
  }
}