{
  "type": "Feature",
  "properties": {
    "name": "Breckenridge",
    "country": "US",
    "subdivision": "TX",
    "timezone": "America/Chicago"
  },
  "geometry": {
    "type": "Point",
    "coordinates": [
      -98.90229,
      32.75568
    ]
  }
}