{
  "type": "Feature",
  "properties": {
    "name": "Cameron Park",
    "country": "US",
    "subdivision": "TX",
    "timezone": "America/Chicago"
  },
  "geometry": {
    "type": "Point",
    "coordinates": [
      -97.47665,
      25.96452
    ]
  }
}