{
  "type": "Feature",
  "properties": {
    "name": "Canton",
    "country": "US",
    "subdivision": "TX",
    "timezone": "America/Chicago"
  },
  "geometry": {
    "type": "Point",
    "coordinates": [
      -95.8633,
      32.55652
    ]
  }
}