{
  "type": "Feature",
  "properties": {
    "name": "Cedar Hill",
    "country": "US",
    "subdivision": "TX",
    "timezone": "America/Chicago"
  },
  "geometry": {
    "type": "Point",
    "coordinates": [
      -96.95612,
      32.58847
    ]
  }
}