{
  "type": "Feature",
  "properties": {
    "name": "Claude",
    "country": "US",
    "subdivision": "TX",
    "timezone": "America/Chicago"
  },
  "geometry": {
    "type": "Point",
    "coordinates": [
      -101.36322,
      35.11172
    ]
  }
}