{
  "type": "Feature",
  "properties": {
    "name": "Cleburne",
    "country": "US",
    "subdivision": "TX",
    "timezone": "America/Chicago"
  },
  "geometry": {
    "type": "Point",
    "coordinates": [
      -97.38668,
      32.34764
    ]
  }
}