{
  "type": "Feature",
  "properties": {
    "name": "Corinth",
    "country": "US",
    "subdivision": "TX",
    "timezone": "America/Chicago"
  },
  "geometry": {
    "type": "Point",
    "coordinates": [
      -97.06473,
      33.15401
    ]
  }
}