{
  "type": "Feature",
  "properties": {
    "name": "De Leon",
    "country": "US",
    "subdivision": "TX",
    "timezone": "America/Chicago"
  },
  "geometry": {
    "type": "Point",
    "coordinates": [
      -98.53588,
      32.11097
    ]
  }
}