{
  "type": "Feature",
  "properties": {
    "name": "Denton",
    "country": "US",
    "subdivision": "TX",
    "timezone": "America/Chicago"
  },
  "geometry": {
    "type": "Point",
    "coordinates": [
      -97.13307,
      33.21484
    ]
  }
}