{
  "type": "Feature",
  "properties": {
    "name": "Denver City",
    "country": "US",
    "subdivision": "TX",
    "timezone": "America/Chicago"
  },
  "geometry": {
    "type": "Point",
    "coordinates": [
      -102.8291,
      32.96455
    ]
  }
}