{
  "type": "Feature",
  "properties": {
    "name": "Dickinson",
    "country": "US",
    "subdivision": "TX",
    "timezone": "America/Chicago"
  },
  "geometry": {
    "type": "Point",
    "coordinates": [
      -95.05132,
      29.46079
    ]
  }
}