{
  "type": "Feature",
  "properties": {
    "name": "Dripping Springs",
    "country": "US",
    "subdivision": "TX",
    "timezone": "America/Chicago"
  },
  "geometry": {
    "type": "Point",
    "coordinates": [
      -98.08668,
      30.19021
    ]
  }
}