{
  "type": "Feature",
  "properties": {
    "name": "Duncanville",
    "country": "US",
    "subdivision": "TX",
    "timezone": "America/Chicago"
  },
  "geometry": {
    "type": "Point",
    "coordinates": [
      -96.90834,
      32.6518
    ]
  }
}