{
  "type": "Feature",
  "properties": {
    "name": "Early",
    "country": "US",
    "subdivision": "TX",
    "timezone": "America/Chicago"
  },
  "geometry": {
    "type": "Point",
    "coordinates": [
      -98.94561,
      31.7421
    ]
  }
}