{
  "type": "Feature",
  "properties": {
    "name": "Eastland",
    "country": "US",
    "subdivision": "TX",
    "timezone": "America/Chicago"
  },
  "geometry": {
    "type": "Point",
    "coordinates": [
      -98.81756,
      32.40152
    ]
  }
}