{
  "type": "Feature",
  "properties": {
    "name": "Edgecliff Village",
    "country": "US",
    "subdivision": "TX",
    "timezone": "America/Chicago"
  },
  "geometry": {
    "type": "Point",
    "coordinates": [
      -97.34279,
      32.65763
    ]
  }
}