{
  "type": "Feature",
  "properties": {
    "name": "Eidson Road",
    "country": "US",
    "subdivision": "TX",
    "timezone": "America/Chicago"
  },
  "geometry": {
    "type": "Point",
    "coordinates": [
      -100.48702,
      28.6772
    ]
  }
}