{
  "type": "Feature",
  "properties": {
    "name": "El Campo",
    "country": "US",
    "subdivision": "TX",
    "timezone": "America/Chicago"
  },
  "geometry": {
    "type": "Point",
    "coordinates": [
      -96.26969,
      29.19664
    ]
  }
}