{
  "type": "Feature",
  "properties": {
    "name": "Evadale",
    "country": "US",
    "subdivision": "TX",
    "timezone": "America/Chicago"
  },
  "geometry": {
    "type": "Point",
    "coordinates": [
      -94.07268,
      30.35493
    ]
  }
}