{
  "type": "Feature",
  "properties": {
    "name": "Fair Oaks Ranch",
    "country": "US",
    "subdivision": "TX",
    "timezone": "America/Chicago"
  },
  "geometry": {
    "type": "Point",
    "coordinates": [
      -98.64336,
      29.74578
    ]
  }
}