{
  "type": "Feature",
  "properties": {
    "name": "Falcon Lake Estates",
    "country": "US",
    "subdivision": "TX",
    "timezone": "America/Chicago"
  },
  "geometry": {
    "type": "Point",
    "coordinates": [
      -99.25531,
      26.87282
    ]
  }
}