{
  "type": "Feature",
  "properties": {
    "name": "Fort Clark Springs",
    "country": "US",
    "subdivision": "TX",
    "timezone": "America/Chicago"
  },
  "geometry": {
    "type": "Point",
    "coordinates": [
      -100.42202,
      29.30607
    ]
  }
}