{
  "type": "Feature",
  "properties": {
    "name": "Fort Hancock",
    "country": "US",
    "subdivision": "TX",
    "timezone": "America/Denver"
  },
  "geometry": {
    "type": "Point",
    "coordinates": [
      -105.84525,
      31.29846
    ]
  }
}