{
  "type": "Feature",
  "properties": {
    "name": "Fulton",
    "country": "US",
    "subdivision": "TX",
    "timezone": "America/Chicago"
  },
  "geometry": {
    "type": "Point",
    "coordinates": [
      -97.0411,
      28.0614
    ]
  }
}