{
  "type": "Feature",
  "properties": {
    "name": "Gainesville",
    "country": "US",
    "subdivision": "TX",
    "timezone": "America/Chicago"
  },
  "geometry": {
    "type": "Point",
    "coordinates": [
      -97.13335,
      33.62594
    ]
  }
}