{
  "type": "Feature",
  "properties": {
    "name": "Galveston",
    "country": "US",
    "subdivision": "TX",
    "timezone": "America/Chicago"
  },
  "geometry": {
    "type": "Point",
    "coordinates": [
      -94.7977,
      29.30135
    ]
  }
}