{
  "type": "Feature",
  "properties": {
    "name": "Ganado",
    "country": "US",
    "subdivision": "TX",
    "timezone": "America/Chicago"
  },
  "geometry": {
    "type": "Point",
    "coordinates": [
      -96.51358,
      29.04054
    ]
  }
}