{
  "type": "Feature",
  "properties": {
    "name": "Gardendale",
    "country": "US",
    "subdivision": "TX",
    "timezone": "America/Chicago"
  },
  "geometry": {
    "type": "Point",
    "coordinates": [
      -99.21614,
      28.51693
    ]
  }
}