{
  "type": "Feature",
  "properties": {
    "name": "Gilmer",
    "country": "US",
    "subdivision": "TX",
    "timezone": "America/Chicago"
  },
  "geometry": {
    "type": "Point",
    "coordinates": [
      -94.94244,
      32.72875
    ]
  }
}