{
  "type": "Feature",
  "properties": {
    "name": "Glen Rose",
    "country": "US",
    "subdivision": "TX",
    "timezone": "America/Chicago"
  },
  "geometry": {
    "type": "Point",
    "coordinates": [
      -97.75531,
      32.23459
    ]
  }
}