{
  "type": "Feature",
  "properties": {
    "name": "Godley",
    "country": "US",
    "subdivision": "TX",
    "timezone": "America/Chicago"
  },
  "geometry": {
    "type": "Point",
    "coordinates": [
      -97.52669,
      32.44903
    ]
  }
}