{
  "type": "Feature",
  "properties": {
    "name": "Gregory",
    "country": "US",
    "subdivision": "TX",
    "timezone": "America/Chicago"
  },
  "geometry": {
    "type": "Point",
    "coordinates": [
      -97.28999,
      27.92224
    ]
  }
}