{
  "type": "Feature",
  "properties": {
    "name": "Gun Barrel City",
    "country": "US",
    "subdivision": "TX",
    "timezone": "America/Chicago"
  },
  "geometry": {
    "type": "Point",
    "coordinates": [
      -96.15136,
      32.33459
    ]
  }
}