{
  "type": "Feature",
  "properties": {
    "name": "Henrietta",
    "country": "US",
    "subdivision": "TX",
    "timezone": "America/Chicago"
  },
  "geometry": {
    "type": "Point",
    "coordinates": [
      -98.19532,
      33.81732
    ]
  }
}