{
  "type": "Feature",
  "properties": {
    "name": "Hillsboro",
    "country": "US",
    "subdivision": "TX",
    "timezone": "America/Chicago"
  },
  "geometry": {
    "type": "Point",
    "coordinates": [
      -97.13001,
      32.01099
    ]
  }
}