{
  "type": "Feature",
  "properties": {
    "name": "Humble",
    "country": "US",
    "subdivision": "TX",
    "timezone": "America/Chicago"
  },
  "geometry": {
    "type": "Point",
    "coordinates": [
      -95.26216,
      29.99883
    ]
  }
}