{
  "type": "Feature",
  "properties": {
    "name": "Huntsville",
    "country": "US",
    "subdivision": "TX",
    "timezone": "America/Chicago"
  },
  "geometry": {
    "type": "Point",
    "coordinates": [
      -95.55078,
      30.72353
    ]
  }
}