{
  "type": "Feature",
  "properties": {
    "name": "Iraan",
    "country": "US",
    "subdivision": "TX",
    "timezone": "America/Chicago"
  },
  "geometry": {
    "type": "Point",
    "coordinates": [
      -101.89791,
      30.91405
    ]
  }
}