{
  "type": "Feature",
  "properties": {
    "name": "Irving",
    "country": "US",
    "subdivision": "TX",
    "timezone": "America/Chicago"
  },
  "geometry": {
    "type": "Point",
    "coordinates": [
      -96.94889,
      32.81402
    ]
  }
}