{
  "type": "Feature",
  "properties": {
    "name": "Jacksonville",
    "country": "US",
    "subdivision": "TX",
    "timezone": "America/Chicago"
  },
  "geometry": {
    "type": "Point",
    "coordinates": [
      -95.2705,
      31.96378
    ]
  }
}