{
  "type": "Feature",
  "properties": {
    "name": "Jersey Village",
    "country": "US",
    "subdivision": "TX",
    "timezone": "America/Chicago"
  },
  "geometry": {
    "type": "Point",
    "coordinates": [
      -95.563,
      29.88772
    ]
  }
}