{
  "type": "Feature",
  "properties": {
    "name": "Jewett",
    "country": "US",
    "subdivision": "TX",
    "timezone": "America/Chicago"
  },
  "geometry": {
    "type": "Point",
    "coordinates": [
      -96.14413,
      31.36157
    ]
  }
}