{
  "type": "Feature",
  "properties": {
    "name": "Katy",
    "country": "US",
    "subdivision": "TX",
    "timezone": "America/Chicago"
  },
  "geometry": {
    "type": "Point",
    "coordinates": [
      -95.8244,
      29.78579
    ]
  }
}