{
  "type": "Feature",
  "properties": {
    "name": "Kemah",
    "country": "US",
    "subdivision": "TX",
    "timezone": "America/Chicago"
  },
  "geometry": {
    "type": "Point",
    "coordinates": [
      -95.02048,
      29.54273
    ]
  }
}