{
  "type": "Feature",
  "properties": {
    "name": "Kenedy",
    "country": "US",
    "subdivision": "TX",
    "timezone": "America/Chicago"
  },
  "geometry": {
    "type": "Point",
    "coordinates": [
      -97.84861,
      28.81915
    ]
  }
}