{
  "type": "Feature",
  "properties": {
    "name": "Kennedale",
    "country": "US",
    "subdivision": "TX",
    "timezone": "America/Chicago"
  },
  "geometry": {
    "type": "Point",
    "coordinates": [
      -97.22585,
      32.6468
    ]
  }
}