{
  "type": "Feature",
  "properties": {
    "name": "Knox City",
    "country": "US",
    "subdivision": "TX",
    "timezone": "America/Chicago"
  },
  "geometry": {
    "type": "Point",
    "coordinates": [
      -99.81898,
      33.41815
    ]
  }
}