{
  "type": "Feature",
  "properties": {
    "name": "La Blanca",
    "country": "US",
    "subdivision": "TX",
    "timezone": "America/Chicago"
  },
  "geometry": {
    "type": "Point",
    "coordinates": [
      -98.03778,
      26.29285
    ]
  }
}