{
  "type": "Feature",
  "properties": {
    "name": "La Coste",
    "country": "US",
    "subdivision": "TX",
    "timezone": "America/Chicago"
  },
  "geometry": {
    "type": "Point",
    "coordinates": [
      -98.81003,
      29.31079
    ]
  }
}