{
  "type": "Feature",
  "properties": {
    "name": "Lago Vista",
    "country": "US",
    "subdivision": "TX",
    "timezone": "America/Chicago"
  },
  "geometry": {
    "type": "Point",
    "coordinates": [
      -97.98835,
      30.4602
    ]
  }
}