{
  "type": "Feature",
  "properties": {
    "name": "Laguna Heights",
    "country": "US",
    "subdivision": "TX",
    "timezone": "America/Chicago"
  },
  "geometry": {
    "type": "Point",
    "coordinates": [
      -97.25386,
      26.08008
    ]
  }
}