{
  "type": "Feature",
  "properties": {
    "name": "Lake Worth",
    "country": "US",
    "subdivision": "TX",
    "timezone": "America/Chicago"
  },
  "geometry": {
    "type": "Point",
    "coordinates": [
      -97.44502,
      32.80485
    ]
  }
}