{
  "type": "Feature",
  "properties": {
    "name": "Lampasas",
    "country": "US",
    "subdivision": "TX",
    "timezone": "America/Chicago"
  },
  "geometry": {
    "type": "Point",
    "coordinates": [
      -98.1817,
      31.06378
    ]
  }
}