{
  "type": "Feature",
  "properties": {
    "name": "Las Quintas Fronterizas",
    "country": "US",
    "subdivision": "TX",
    "timezone": "America/Chicago"
  },
  "geometry": {
    "type": "Point",
    "coordinates": [
      -100.46869,
      28.69053
    ]
  }
}