{
  "type": "Feature",
  "properties": {
    "name": "Lindsay",
    "country": "US",
    "subdivision": "TX",
    "timezone": "America/Chicago"
  },
  "geometry": {
    "type": "Point",
    "coordinates": [
      -97.22279,
      33.63594
    ]
  }
}