{
  "type": "Feature",
  "properties": {
    "name": "Little Elm",
    "country": "US",
    "subdivision": "TX",
    "timezone": "America/Chicago"
  },
  "geometry": {
    "type": "Point",
    "coordinates": [
      -96.93751,
      33.16262
    ]
  }
}