{
  "type": "Feature",
  "properties": {
    "name": "Littlefield",
    "country": "US",
    "subdivision": "TX",
    "timezone": "America/Chicago"
  },
  "geometry": {
    "type": "Point",
    "coordinates": [
      -102.3249,
      33.91731
    ]
  }
}