{
  "type": "Feature",
  "properties": {
    "name": "Llano Grande",
    "country": "US",
    "subdivision": "TX",
    "timezone": "America/Chicago"
  },
  "geometry": {
    "type": "Point",
    "coordinates": [
      -97.96806,
      26.1298
    ]
  }
}