{
  "type": "Feature",
  "properties": {
    "name": "Lubbock",
    "country": "US",
    "subdivision": "TX",
    "timezone": "America/Chicago"
  },
  "geometry": {
    "type": "Point",
    "coordinates": [
      -101.85517,
      33.57786
    ]
  }
}