{
  "type": "Feature",
  "properties": {
    "name": "Marion",
    "country": "US",
    "subdivision": "TX",
    "timezone": "America/Chicago"
  },
  "geometry": {
    "type": "Point",
    "coordinates": [
      -98.14029,
      29.57134
    ]
  }
}