{
  "type": "Feature",
  "properties": {
    "name": "McLendon-Chisholm",
    "country": "US",
    "subdivision": "TX",
    "timezone": "America/Chicago"
  },
  "geometry": {
    "type": "Point",
    "coordinates": [
      -96.38054,
      32.84235
    ]
  }
}