{
  "type": "Feature",
  "properties": {
    "name": "Meridian",
    "country": "US",
    "subdivision": "TX",
    "timezone": "America/Chicago"
  },
  "geometry": {
    "type": "Point",
    "coordinates": [
      -97.65669,
      31.92321
    ]
  }
}