{
  "type": "Feature",
  "properties": {
    "name": "Mesquite",
    "country": "US",
    "subdivision": "TX",
    "timezone": "America/Chicago"
  },
  "geometry": {
    "type": "Point",
    "coordinates": [
      -96.59916,
      32.7668
    ]
  }
}