{
  "type": "Feature",
  "properties": {
    "name": "Mexia",
    "country": "US",
    "subdivision": "TX",
    "timezone": "America/Chicago"
  },
  "geometry": {
    "type": "Point",
    "coordinates": [
      -96.4822,
      31.67989
    ]
  }
}