{
  "type": "Feature",
  "properties": {
    "name": "Midway North",
    "country": "US",
    "subdivision": "TX",
    "timezone": "America/Chicago"
  },
  "geometry": {
    "type": "Point",
    "coordinates": [
      -98.01708,
      26.18776
    ]
  }
}