{
  "type": "Feature",
  "properties": {
    "name": "Mila Doce",
    "country": "US",
    "subdivision": "TX",
    "timezone": "America/Chicago"
  },
  "geometry": {
    "type": "Point",
    "coordinates": [
      -97.95889,
      26.22618
    ]
  }
}