{
  "type": "Feature",
  "properties": {
    "name": "Morgans Point Resort",
    "country": "US",
    "subdivision": "TX",
    "timezone": "America/Chicago"
  },
  "geometry": {
    "type": "Point",
    "coordinates": [
      -97.46334,
      31.14823
    ]
  }
}