{
  "type": "Feature",
  "properties": {
    "name": "Mount Vernon",
    "country": "US",
    "subdivision": "TX",
    "timezone": "America/Chicago"
  },
  "geometry": {
    "type": "Point",
    "coordinates": [
      -95.22133,
      33.18873
    ]
  }
}