{
  "type": "Feature",
  "properties": {
    "name": "Muenster",
    "country": "US",
    "subdivision": "TX",
    "timezone": "America/Chicago"
  },
  "geometry": {
    "type": "Point",
    "coordinates": [
      -97.37641,
      33.65177
    ]
  }
}