{
  "type": "Feature",
  "properties": {
    "name": "Munday",
    "country": "US",
    "subdivision": "TX",
    "timezone": "America/Chicago"
  },
  "geometry": {
    "type": "Point",
    "coordinates": [
      -99.62286,
      33.44926
    ]
  }
}