{
  "type": "Feature",
  "properties": {
    "name": "Nevada",
    "country": "US",
    "subdivision": "TX",
    "timezone": "America/Chicago"
  },
  "geometry": {
    "type": "Point",
    "coordinates": [
      -96.37387,
      33.04234
    ]
  }
}