{
  "type": "Feature",
  "properties": {
    "name": "New Territory",
    "country": "US",
    "subdivision": "TX",
    "timezone": "America/Chicago"
  },
  "geometry": {
    "type": "Point",
    "coordinates": [
      -95.68078,
      29.59412
    ]
  }
}