{
  "type": "Feature",
  "properties": {
    "name": "New Boston",
    "country": "US",
    "subdivision": "TX",
    "timezone": "America/Chicago"
  },
  "geometry": {
    "type": "Point",
    "coordinates": [
      -94.41548,
      33.45984
    ]
  }
}