{
  "type": "Feature",
  "properties": {
    "name": "Newark",
    "country": "US",
    "subdivision": "TX",
    "timezone": "America/Chicago"
  },
  "geometry": {
    "type": "Point",
    "coordinates": [
      -97.48447,
      33.00124
    ]
  }
}