{
  "type": "Feature",
  "properties": {
    "name": "Olmito",
    "country": "US",
    "subdivision": "TX",
    "timezone": "America/Chicago"
  },
  "geometry": {
    "type": "Point",
    "coordinates": [
      -97.53415,
      26.02174
    ]
  }
}