{
  "type": "Feature",
  "properties": {
    "name": "Olton",
    "country": "US",
    "subdivision": "TX",
    "timezone": "America/Chicago"
  },
  "geometry": {
    "type": "Point",
    "coordinates": [
      -102.13463,
      34.18341
    ]
  }
}