{
  "type": "Feature",
  "properties": {
    "name": "Onion Creek",
    "country": "US",
    "subdivision": "TX",
    "timezone": "America/Chicago"
  },
  "geometry": {
    "type": "Point",
    "coordinates": [
      -97.78417,
      30.1366
    ]
  }
}