{
  "type": "Feature",
  "properties": {
    "name": "Palestine",
    "country": "US",
    "subdivision": "TX",
    "timezone": "America/Chicago"
  },
  "geometry": {
    "type": "Point",
    "coordinates": [
      -95.63079,
      31.76212
    ]
  }
}