{
  "type": "Feature",
  "properties": {
    "name": "Patton Village",
    "country": "US",
    "subdivision": "TX",
    "timezone": "America/Chicago"
  },
  "geometry": {
    "type": "Point",
    "coordinates": [
      -95.16882,
      30.19299
    ]
  }
}