{
  "type": "Feature",
  "properties": {
    "name": "Pecos",
    "country": "US",
    "subdivision": "TX",
    "timezone": "America/Chicago"
  },
  "geometry": {
    "type": "Point",
    "coordinates": [
      -103.49323,
      31.42291
    ]
  }
}