{
  "type": "Feature",
  "properties": {
    "name": "Pelican Bay",
    "country": "US",
    "subdivision": "TX",
    "timezone": "America/Chicago"
  },
  "geometry": {
    "type": "Point",
    "coordinates": [
      -97.51836,
      32.92096
    ]
  }
}