{
  "type": "Feature",
  "properties": {
    "name": "Perezville",
    "country": "US",
    "subdivision": "TX",
    "timezone": "America/Chicago"
  },
  "geometry": {
    "type": "Point",
    "coordinates": [
      -98.40057,
      26.22452
    ]
  }
}