{
  "type": "Feature",
  "properties": {
    "name": "Pflugerville",
    "country": "US",
    "subdivision": "TX",
    "timezone": "America/Chicago"
  },
  "geometry": {
    "type": "Point",
    "coordinates": [
      -97.62,
      30.43937
    ]
  }
}