{
  "type": "Feature",
  "properties": {
    "name": "Port Isabel",
    "country": "US",
    "subdivision": "TX",
    "timezone": "America/Chicago"
  },
  "geometry": {
    "type": "Point",
    "coordinates": [
      -97.20858,
      26.07341
    ]
  }
}