{
  "type": "Feature",
  "properties": {
    "name": "Poth",
    "country": "US",
    "subdivision": "TX",
    "timezone": "America/Chicago"
  },
  "geometry": {
    "type": "Point",
    "coordinates": [
      -98.08195,
      29.06969
    ]
  }
}