{
  "type": "Feature",
  "properties": {
    "name": "Potosi",
    "country": "US",
    "subdivision": "TX",
    "timezone": "America/Chicago"
  },
  "geometry": {
    "type": "Point",
    "coordinates": [
      -99.65647,
      32.3293
    ]
  }
}