{
  "type": "Feature",
  "properties": {
    "name": "Prosper",
    "country": "US",
    "subdivision": "TX",
    "timezone": "America/Chicago"
  },
  "geometry": {
    "type": "Point",
    "coordinates": [
      -96.80111,
      33.23623
    ]
  }
}