{
  "type": "Feature",
  "properties": {
    "name": "Ralls",
    "country": "US",
    "subdivision": "TX",
    "timezone": "America/Chicago"
  },
  "geometry": {
    "type": "Point",
    "coordinates": [
      -101.38766,
      33.67425
    ]
  }
}