{
  "type": "Feature",
  "properties": {
    "name": "Raymondville",
    "country": "US",
    "subdivision": "TX",
    "timezone": "America/Chicago"
  },
  "geometry": {
    "type": "Point",
    "coordinates": [
      -97.78305,
      26.48146
    ]
  }
}