{
  "type": "Feature",
  "properties": {
    "name": "Reno",
    "country": "US",
    "subdivision": "TX",
    "timezone": "America/Chicago"
  },
  "geometry": {
    "type": "Point",
    "coordinates": [
      -95.46245,
      33.66316
    ]
  }
}