{
  "type": "Feature",
  "properties": {
    "name": "Riesel",
    "country": "US",
    "subdivision": "TX",
    "timezone": "America/Chicago"
  },
  "geometry": {
    "type": "Point",
    "coordinates": [
      -96.92333,
      31.47489
    ]
  }
}