{
  "type": "Feature",
  "properties": {
    "name": "Robert Lee",
    "country": "US",
    "subdivision": "TX",
    "timezone": "America/Chicago"
  },
  "geometry": {
    "type": "Point",
    "coordinates": [
      -100.48482,
      31.89237
    ]
  }
}