{
  "type": "Feature",
  "properties": {
    "name": "Rockwall",
    "country": "US",
    "subdivision": "TX",
    "timezone": "America/Chicago"
  },
  "geometry": {
    "type": "Point",
    "coordinates": [
      -96.45971,
      32.93123
    ]
  }
}