{
  "type": "Feature",
  "properties": {
    "name": "Rockport",
    "country": "US",
    "subdivision": "TX",
    "timezone": "America/Chicago"
  },
  "geometry": {
    "type": "Point",
    "coordinates": [
      -97.05601,
      28.02077
    ]
  }
}