{
  "type": "Feature",
  "properties": {
    "name": "Rowlett",
    "country": "US",
    "subdivision": "TX",
    "timezone": "America/Chicago"
  },
  "geometry": {
    "type": "Point",
    "coordinates": [
      -96.56388,
      32.9029
    ]
  }
}