{
  "type": "Feature",
  "properties": {
    "name": "Saint Jo",
    "country": "US",
    "subdivision": "TX",
    "timezone": "America/Chicago"
  },
  "geometry": {
    "type": "Point",
    "coordinates": [
      -97.52252,
      33.69483
    ]
  }
}