{
  "type": "Feature",
  "properties": {
    "name": "Salado",
    "country": "US",
    "subdivision": "TX",
    "timezone": "America/Chicago"
  },
  "geometry": {
    "type": "Point",
    "coordinates": [
      -97.53862,
      30.94713
    ]
  }
}