{
  "type": "Feature",
  "properties": {
    "name": "San Antonio",
    "country": "US",
    "subdivision": "TX",
    "timezone": "America/Chicago"
  },
  "geometry": {
    "type": "Point",
    "coordinates": [
      -98.49363,
      29.42412
    ]
  }
}