{
  "type": "Feature",
  "properties": {
    "name": "San Saba",
    "country": "US",
    "subdivision": "TX",
    "timezone": "America/Chicago"
  },
  "geometry": {
    "type": "Point",
    "coordinates": [
      -98.7181,
      31.19572
    ]
  }
}