{
  "type": "Feature",
  "properties": {
    "name": "San Carlos",
    "country": "US",
    "subdivision": "TX",
    "timezone": "America/Chicago"
  },
  "geometry": {
    "type": "Point",
    "coordinates": [
      -98.07195,
      26.29563
    ]
  }
}