{
  "type": "Feature",
  "properties": {
    "name": "Santa Fe",
    "country": "US",
    "subdivision": "TX",
    "timezone": "America/Chicago"
  },
  "geometry": {
    "type": "Point",
    "coordinates": [
      -95.10576,
      29.37801
    ]
  }
}