{
  "type": "Feature",
  "properties": {
    "name": "Seadrift",
    "country": "US",
    "subdivision": "TX",
    "timezone": "America/Chicago"
  },
  "geometry": {
    "type": "Point",
    "coordinates": [
      -96.71359,
      28.41528
    ]
  }
}