{
  "type": "Feature",
  "properties": {
    "name": "Seymour",
    "country": "US",
    "subdivision": "TX",
    "timezone": "America/Chicago"
  },
  "geometry": {
    "type": "Point",
    "coordinates": [
      -99.26035,
      33.59426
    ]
  }
}