{
  "type": "Feature",
  "properties": {
    "name": "Shenandoah",
    "country": "US",
    "subdivision": "TX",
    "timezone": "America/Chicago"
  },
  "geometry": {
    "type": "Point",
    "coordinates": [
      -95.45577,
      30.18022
    ]
  }
}