{
  "type": "Feature",
  "properties": {
    "name": "Somerville",
    "country": "US",
    "subdivision": "TX",
    "timezone": "America/Chicago"
  },
  "geometry": {
    "type": "Point",
    "coordinates": [
      -96.5283,
      30.34604
    ]
  }
}