{
  "type": "Feature",
  "properties": {
    "name": "South Padre Island",
    "country": "US",
    "subdivision": "TX",
    "timezone": "America/Chicago"
  },
  "geometry": {
    "type": "Point",
    "coordinates": [
      -97.16469,
      26.10369
    ]
  }
}