{
  "type": "Feature",
  "properties": {
    "name": "Spring",
    "country": "US",
    "subdivision": "TX",
    "timezone": "America/Chicago"
  },
  "geometry": {
    "type": "Point",
    "coordinates": [
      -95.41716,
      30.07994
    ]
  }
}