{
  "type": "Feature",
  "properties": {
    "name": "Spur",
    "country": "US",
    "subdivision": "TX",
    "timezone": "America/Chicago"
  },
  "geometry": {
    "type": "Point",
    "coordinates": [
      -100.85569,
      33.47648
    ]
  }
}