{
  "type": "Feature",
  "properties": {
    "name": "Sullivan City",
    "country": "US",
    "subdivision": "TX",
    "timezone": "America/Chicago"
  },
  "geometry": {
    "type": "Point",
    "coordinates": [
      -98.56363,
      26.27757
    ]
  }
}