{
  "type": "Feature",
  "properties": {
    "name": "Terrell Hills",
    "country": "US",
    "subdivision": "TX",
    "timezone": "America/Chicago"
  },
  "geometry": {
    "type": "Point",
    "coordinates": [
      -98.45085,
      29.47495
    ]
  }
}