{
  "type": "Feature",
  "properties": {
    "name": "Troup",
    "country": "US",
    "subdivision": "TX",
    "timezone": "America/Chicago"
  },
  "geometry": {
    "type": "Point",
    "coordinates": [
      -95.1205,
      32.1446
    ]
  }
}