{
  "type": "Feature",
  "properties": {
    "name": "Troy",
    "country": "US",
    "subdivision": "TX",
    "timezone": "America/Chicago"
  },
  "geometry": {
    "type": "Point",
    "coordinates": [
      -97.30278,
      31.20684
    ]
  }
}