{
  "type": "Feature",
  "properties": {
    "name": "University Park",
    "country": "US",
    "subdivision": "TX",
    "timezone": "America/Chicago"
  },
  "geometry": {
    "type": "Point",
    "coordinates": [
      -96.80028,
      32.85013
    ]
  }
}