{
  "type": "Feature",
  "properties": {
    "name": "Van Vleck",
    "country": "US",
    "subdivision": "TX",
    "timezone": "America/Chicago"
  },
  "geometry": {
    "type": "Point",
    "coordinates": [
      -95.8894,
      29.01775
    ]
  }
}