{
  "type": "Feature",
  "properties": {
    "name": "Webster",
    "country": "US",
    "subdivision": "TX",
    "timezone": "America/Chicago"
  },
  "geometry": {
    "type": "Point",
    "coordinates": [
      -95.11826,
      29.53773
    ]
  }
}