{
  "type": "Feature",
  "properties": {
    "name": "West Livingston",
    "country": "US",
    "subdivision": "TX",
    "timezone": "America/Chicago"
  },
  "geometry": {
    "type": "Point",
    "coordinates": [
      -95.00188,
      30.69825
    ]
  }
}