{
  "type": "Feature",
  "properties": {
    "name": "Weston Lakes",
    "country": "US",
    "subdivision": "TX",
    "timezone": "America/Chicago"
  },
  "geometry": {
    "type": "Point",
    "coordinates": [
      -95.93571,
      29.68324
    ]
  }
}