{
  "type": "Feature",
  "properties": {
    "name": "Whitney",
    "country": "US",
    "subdivision": "TX",
    "timezone": "America/Chicago"
  },
  "geometry": {
    "type": "Point",
    "coordinates": [
      -97.3214,
      31.95182
    ]
  }
}