{
  "type": "Feature",
  "properties": {
    "name": "Windcrest",
    "country": "US",
    "subdivision": "TX",
    "timezone": "America/Chicago"
  },
  "geometry": {
    "type": "Point",
    "coordinates": [
      -98.38029,
      29.51551
    ]
  }
}