{
  "type": "Feature",
  "properties": {
    "name": "Winters",
    "country": "US",
    "subdivision": "TX",
    "timezone": "America/Chicago"
  },
  "geometry": {
    "type": "Point",
    "coordinates": [
      -99.96231,
      31.95653
    ]
  }
}