{
  "type": "Feature",
  "properties": {
    "name": "Woodbranch",
    "country": "US",
    "subdivision": "TX",
    "timezone": "America/Chicago"
  },
  "geometry": {
    "type": "Point",
    "coordinates": [
      -95.18882,
      30.18105
    ]
  }
}