{
  "type": "Feature",
  "properties": {
    "name": "Štrba",
    "country": "SK",
    "subdivision": "05",
    "timezone": "Europe/Bratislava"
  },
  "geometry": {
    "type": "Point",
    "coordinates": [
      20.07975,
      49.05913
    ]
  }
}