{
  "type": "Feature",
  "properties": {
    "name": "Vranov nad Topľou",
    "country": "SK",
    "subdivision": "05",
    "timezone": "Europe/Bratislava"
  },
  "geometry": {
    "type": "Point",
    "coordinates": [
      21.68479,
      48.88836
    ]
  }
}