{
  "type": "Feature",
  "properties": {
    "name": "Allahābād",
    "country": "IN",
    "subdivision": "36",
    "timezone": "Asia/Kolkata"
  },
  "geometry": {
    "type": "Point",
    "coordinates": [
      81.84322,
      25.44478
    ]
  }
}