{
  "type": "Feature",
  "properties": {
    "name": "AmÄnpur",
    "country": "IN",
    "subdivision": "36",
    "timezone": "Asia/Kolkata"
  },
  "geometry": {
    "type": "Point",
    "coordinates": [
      78.73788,
      27.71222
    ]
  }
}