{
  "type": "Feature",
  "properties": {
    "name": "Anūpshahr",
    "country": "IN",
    "subdivision": "36",
    "timezone": "Asia/Kolkata"
  },
  "geometry": {
    "type": "Point",
    "coordinates": [
      78.26914,
      28.35748
    ]
  }
}