{
  "type": "Feature",
  "properties": {
    "name": "Atraulia",
    "country": "IN",
    "subdivision": "36",
    "timezone": "Asia/Kolkata"
  },
  "geometry": {
    "type": "Point",
    "coordinates": [
      82.94727,
      26.3333
    ]
  }
}