{
  "type": "Feature",
  "properties": {
    "name": "Atraulī",
    "country": "IN",
    "subdivision": "36",
    "timezone": "Asia/Kolkata"
  },
  "geometry": {
    "type": "Point",
    "coordinates": [
      78.28571,
      28.02964
    ]
  }
}