{
  "type": "Feature",
  "properties": {
    "name": "Babīna",
    "country": "IN",
    "subdivision": "36",
    "timezone": "Asia/Kolkata"
  },
  "geometry": {
    "type": "Point",
    "coordinates": [
      78.47028,
      25.23947
    ]
  }
}