{
  "type": "Feature",
  "properties": {
    "name": "BabrÄla",
    "country": "IN",
    "subdivision": "36",
    "timezone": "Asia/Kolkata"
  },
  "geometry": {
    "type": "Point",
    "coordinates": [
      78.4056,
      28.26419
    ]
  }
}