{
  "type": "Feature",
  "properties": {
    "name": "Baldev",
    "country": "IN",
    "subdivision": "36",
    "timezone": "Asia/Kolkata"
  },
  "geometry": {
    "type": "Point",
    "coordinates": [
      77.82214,
      27.40684
    ]
  }
}