{
  "type": "Feature",
  "properties": {
    "name": "Bānsdīh",
    "country": "IN",
    "subdivision": "36",
    "timezone": "Asia/Kolkata"
  },
  "geometry": {
    "type": "Point",
    "coordinates": [
      84.21827,
      25.88377
    ]
  }
}