{
  "type": "Feature",
  "properties": {
    "name": "BilariÄganj",
    "country": "IN",
    "subdivision": "36",
    "timezone": "Asia/Kolkata"
  },
  "geometry": {
    "type": "Point",
    "coordinates": [
      83.2269,
      26.19593
    ]
  }
}