{
  "type": "Feature",
  "properties": {
    "name": "BilÄri",
    "country": "IN",
    "subdivision": "36",
    "timezone": "Asia/Kolkata"
  },
  "geometry": {
    "type": "Point",
    "coordinates": [
      78.80361,
      28.62146
    ]
  }
}