{
  "type": "Feature",
  "properties": {
    "name": "Bilthra",
    "country": "IN",
    "subdivision": "36",
    "timezone": "Asia/Kolkata"
  },
  "geometry": {
    "type": "Point",
    "coordinates": [
      83.89148,
      26.12705
    ]
  }
}