{
  "type": "Feature",
  "properties": {
    "name": "Captainganj",
    "country": "IN",
    "subdivision": "36",
    "timezone": "Asia/Kolkata"
  },
  "geometry": {
    "type": "Point",
    "coordinates": [
      83.71334,
      26.9264
    ]
  }
}