{
  "type": "Feature",
  "properties": {
    "name": "Chakia",
    "country": "IN",
    "subdivision": "36",
    "timezone": "Asia/Kolkata"
  },
  "geometry": {
    "type": "Point",
    "coordinates": [
      83.22155,
      25.04891
    ]
  }
}