{
  "type": "Feature",
  "properties": {
    "name": "Chandauli",
    "country": "IN",
    "subdivision": "36",
    "timezone": "Asia/Kolkata"
  },
  "geometry": {
    "type": "Point",
    "coordinates": [
      83.26825,
      25.25803
    ]
  }
}