{
  "type": "Feature",
  "properties": {
    "name": "ChÄndpur",
    "country": "IN",
    "subdivision": "36",
    "timezone": "Asia/Kolkata"
  },
  "geometry": {
    "type": "Point",
    "coordinates": [
      78.27187,
      29.13489
    ]
  }
}