{
  "type": "Feature",
  "properties": {
    "name": "Dalmau",
    "country": "IN",
    "subdivision": "36",
    "timezone": "Asia/Kolkata"
  },
  "geometry": {
    "type": "Point",
    "coordinates": [
      81.0298,
      26.06477
    ]
  }
}