{
  "type": "Feature",
  "properties": {
    "name": "Dostpur",
    "country": "IN",
    "subdivision": "36",
    "timezone": "Asia/Kolkata"
  },
  "geometry": {
    "type": "Point",
    "coordinates": [
      82.47091,
      26.27486
    ]
  }
}