{
  "type": "Feature",
  "properties": {
    "name": "Farah",
    "country": "IN",
    "subdivision": "36",
    "timezone": "Asia/Kolkata"
  },
  "geometry": {
    "type": "Point",
    "coordinates": [
      77.76185,
      27.32081
    ]
  }
}