{
  "type": "Feature",
  "properties": {
    "name": "Farrukhābād",
    "country": "IN",
    "subdivision": "36",
    "timezone": "Asia/Kolkata"
  },
  "geometry": {
    "type": "Point",
    "coordinates": [
      79.5793,
      27.39134
    ]
  }
}