{
  "type": "Feature",
  "properties": {
    "name": "Gajraula",
    "country": "IN",
    "subdivision": "36",
    "timezone": "Asia/Kolkata"
  },
  "geometry": {
    "type": "Point",
    "coordinates": [
      78.2396,
      28.8457
    ]
  }
}