{
  "type": "Feature",
  "properties": {
    "name": "GawÄn",
    "country": "IN",
    "subdivision": "36",
    "timezone": "Asia/Kolkata"
  },
  "geometry": {
    "type": "Point",
    "coordinates": [
      78.35186,
      28.41969
    ]
  }
}