{
  "type": "Feature",
  "properties": {
    "name": "Goshāīnganj",
    "country": "IN",
    "subdivision": "36",
    "timezone": "Asia/Kolkata"
  },
  "geometry": {
    "type": "Point",
    "coordinates": [
      81.10752,
      26.76793
    ]
  }
}