{
  "type": "Feature",
  "properties": {
    "name": "Hamīrpur",
    "country": "IN",
    "subdivision": "36",
    "timezone": "Asia/Kolkata"
  },
  "geometry": {
    "type": "Point",
    "coordinates": [
      80.14842,
      25.9553
    ]
  }
}