{
  "type": "Feature",
  "properties": {
    "name": "HÄthras",
    "country": "IN",
    "subdivision": "36",
    "timezone": "Asia/Kolkata"
  },
  "geometry": {
    "type": "Point",
    "coordinates": [
      78.05201,
      27.59551
    ]
  }
}