{
  "type": "Feature",
  "properties": {
    "name": "Jagdīshpur",
    "country": "IN",
    "subdivision": "36",
    "timezone": "Asia/Kolkata"
  },
  "geometry": {
    "type": "Point",
    "coordinates": [
      80.5451,
      26.74967
    ]
  }
}