{
  "type": "Feature",
  "properties": {
    "name": "Jaswantnagar",
    "country": "IN",
    "subdivision": "36",
    "timezone": "Asia/Kolkata"
  },
  "geometry": {
    "type": "Point",
    "coordinates": [
      78.90256,
      26.88271
    ]
  }
}