{
  "type": "Feature",
  "properties": {
    "name": "JhÄnsi",
    "country": "IN",
    "subdivision": "36",
    "timezone": "Asia/Kolkata"
  },
  "geometry": {
    "type": "Point",
    "coordinates": [
      78.57994,
      25.45887
    ]
  }
}