{
  "type": "Feature",
  "properties": {
    "name": "Jhūsi",
    "country": "IN",
    "subdivision": "36",
    "timezone": "Asia/Kolkata"
  },
  "geometry": {
    "type": "Point",
    "coordinates": [
      81.9055,
      25.43745
    ]
  }
}