{
  "type": "Feature",
  "properties": {
    "name": "Kaimganj",
    "country": "IN",
    "subdivision": "36",
    "timezone": "Asia/Kolkata"
  },
  "geometry": {
    "type": "Point",
    "coordinates": [
      79.33525,
      27.55441
    ]
  }
}