{
  "type": "Feature",
  "properties": {
    "name": "Kālīnagar",
    "country": "IN",
    "subdivision": "36",
    "timezone": "Asia/Kolkata"
  },
  "geometry": {
    "type": "Point",
    "coordinates": [
      80.08152,
      28.62019
    ]
  }
}