{
  "type": "Feature",
  "properties": {
    "name": "Kampil",
    "country": "IN",
    "subdivision": "36",
    "timezone": "Asia/Kolkata"
  },
  "geometry": {
    "type": "Point",
    "coordinates": [
      79.27687,
      27.61268
    ]
  }
}