{
  "type": "Feature",
  "properties": {
    "name": "Khekra",
    "country": "IN",
    "subdivision": "36",
    "timezone": "Asia/Kolkata"
  },
  "geometry": {
    "type": "Point",
    "coordinates": [
      77.2841,
      28.86586
    ]
  }
}