{
  "type": "Feature",
  "properties": {
    "name": "Khūtār",
    "country": "IN",
    "subdivision": "36",
    "timezone": "Asia/Kolkata"
  },
  "geometry": {
    "type": "Point",
    "coordinates": [
      80.27046,
      28.20307
    ]
  }
}