{
  "type": "Feature",
  "properties": {
    "name": "Kotra",
    "country": "IN",
    "subdivision": "36",
    "timezone": "Asia/Kolkata"
  },
  "geometry": {
    "type": "Point",
    "coordinates": [
      79.30909,
      25.8077
    ]
  }
}