{
  "type": "Feature",
  "properties": {
    "name": "KulpahÄr",
    "country": "IN",
    "subdivision": "36",
    "timezone": "Asia/Kolkata"
  },
  "geometry": {
    "type": "Point",
    "coordinates": [
      79.63931,
      25.32007
    ]
  }
}