{
  "type": "Feature",
  "properties": {
    "name": "Lāwar Khās",
    "country": "IN",
    "subdivision": "36",
    "timezone": "Asia/Kolkata"
  },
  "geometry": {
    "type": "Point",
    "coordinates": [
      77.77767,
      29.11091
    ]
  }
}