{
  "type": "Feature",
  "properties": {
    "name": "Machhlīshahr",
    "country": "IN",
    "subdivision": "36",
    "timezone": "Asia/Kolkata"
  },
  "geometry": {
    "type": "Point",
    "coordinates": [
      82.41106,
      25.68564
    ]
  }
}