{
  "type": "Feature",
  "properties": {
    "name": "MahobÄ",
    "country": "IN",
    "subdivision": "36",
    "timezone": "Asia/Kolkata"
  },
  "geometry": {
    "type": "Point",
    "coordinates": [
      79.87533,
      25.2905
    ]
  }
}