{
  "type": "Feature",
  "properties": {
    "name": "Mataundh",
    "country": "IN",
    "subdivision": "36",
    "timezone": "Asia/Kolkata"
  },
  "geometry": {
    "type": "Point",
    "coordinates": [
      80.15653,
      25.43594
    ]
  }
}