{
  "type": "Feature",
  "properties": {
    "name": "Mehnagar",
    "country": "IN",
    "subdivision": "36",
    "timezone": "Asia/Kolkata"
  },
  "geometry": {
    "type": "Point",
    "coordinates": [
      83.11611,
      25.87889
    ]
  }
}