{
  "type": "Feature",
  "properties": {
    "name": "Mīrānpur Katra",
    "country": "IN",
    "subdivision": "36",
    "timezone": "Asia/Kolkata"
  },
  "geometry": {
    "type": "Point",
    "coordinates": [
      79.66778,
      28.02963
    ]
  }
}