{
  "type": "Feature",
  "properties": {
    "name": "Musāfir-Khāna",
    "country": "IN",
    "subdivision": "36",
    "timezone": "Asia/Kolkata"
  },
  "geometry": {
    "type": "Point",
    "coordinates": [
      81.79607,
      26.37837
    ]
  }
}