{
  "type": "Feature",
  "properties": {
    "name": "Nagīna",
    "country": "IN",
    "subdivision": "36",
    "timezone": "Asia/Kolkata"
  },
  "geometry": {
    "type": "Point",
    "coordinates": [
      78.43646,
      29.44433
    ]
  }
}