{
  "type": "Feature",
  "properties": {
    "name": "Nanauta",
    "country": "IN",
    "subdivision": "36",
    "timezone": "Asia/Kolkata"
  },
  "geometry": {
    "type": "Point",
    "coordinates": [
      77.41728,
      29.71215
    ]
  }
}