{
  "type": "Feature",
  "properties": {
    "name": "Nichlaul",
    "country": "IN",
    "subdivision": "36",
    "timezone": "Asia/Kolkata"
  },
  "geometry": {
    "type": "Point",
    "coordinates": [
      83.7253,
      27.31247
    ]
  }
}