{
  "type": "Feature",
  "properties": {
    "name": "Nūrpur",
    "country": "IN",
    "subdivision": "36",
    "timezone": "Asia/Kolkata"
  },
  "geometry": {
    "type": "Point",
    "coordinates": [
      78.4084,
      29.14956
    ]
  }
}