{
  "type": "Feature",
  "properties": {
    "name": "RasrÄ",
    "country": "IN",
    "subdivision": "36",
    "timezone": "Asia/Kolkata"
  },
  "geometry": {
    "type": "Point",
    "coordinates": [
      83.85487,
      25.8576
    ]
  }
}