{
  "type": "Feature",
  "properties": {
    "name": "Rasūlābād",
    "country": "IN",
    "subdivision": "36",
    "timezone": "Asia/Kolkata"
  },
  "geometry": {
    "type": "Point",
    "coordinates": [
      80.49012,
      26.74491
    ]
  }
}