{
  "type": "Feature",
  "properties": {
    "name": "RÄth",
    "country": "IN",
    "subdivision": "36",
    "timezone": "Asia/Kolkata"
  },
  "geometry": {
    "type": "Point",
    "coordinates": [
      79.5666,
      25.59474
    ]
  }
}