{
  "type": "Feature",
  "properties": {
    "name": "Renukūt",
    "country": "IN",
    "subdivision": "36",
    "timezone": "Asia/Kolkata"
  },
  "geometry": {
    "type": "Point",
    "coordinates": [
      83.0358,
      24.21641
    ]
  }
}