{
  "type": "Feature",
  "properties": {
    "name": "Rura",
    "country": "IN",
    "subdivision": "36",
    "timezone": "Asia/Kolkata"
  },
  "geometry": {
    "type": "Point",
    "coordinates": [
      79.90108,
      26.49001
    ]
  }
}