{
  "type": "Feature",
  "properties": {
    "name": "Sarauli",
    "country": "IN",
    "subdivision": "36",
    "timezone": "Asia/Kolkata"
  },
  "geometry": {
    "type": "Point",
    "coordinates": [
      79.09177,
      28.49404
    ]
  }
}