{
  "type": "Feature",
  "properties": {
    "name": "Thakurdwara",
    "country": "IN",
    "subdivision": "36",
    "timezone": "Asia/Kolkata"
  },
  "geometry": {
    "type": "Point",
    "coordinates": [
      78.86145,
      29.19203
    ]
  }
}