{
  "type": "Feature",
  "properties": {
    "name": "Tikaitnagar",
    "country": "IN",
    "subdivision": "36",
    "timezone": "Asia/Kolkata"
  },
  "geometry": {
    "type": "Point",
    "coordinates": [
      81.56583,
      26.94612
    ]
  }
}