{
  "type": "Feature",
  "properties": {
    "name": "Tilhar",
    "country": "IN",
    "subdivision": "36",
    "timezone": "Asia/Kolkata"
  },
  "geometry": {
    "type": "Point",
    "coordinates": [
      79.73827,
      27.96282
    ]
  }
}