{
  "type": "Feature",
  "properties": {
    "name": "Utraula",
    "country": "IN",
    "subdivision": "36",
    "timezone": "Asia/Kolkata"
  },
  "geometry": {
    "type": "Point",
    "coordinates": [
      82.41872,
      27.31933
    ]
  }
}