{
  "type": "Feature",
  "properties": {
    "name": "Zaidpur",
    "country": "IN",
    "subdivision": "36",
    "timezone": "Asia/Kolkata"
  },
  "geometry": {
    "type": "Point",
    "coordinates": [
      81.32929,
      26.83093
    ]
  }
}