{
  "type": "Feature",
  "properties": {
    "name": "Anicuns",
    "country": "BR",
    "subdivision": "29",
    "timezone": "America/Sao_Paulo"
  },
  "geometry": {
    "type": "Point",
    "coordinates": [
      -49.96167,
      -16.46111
    ]
  }
}