{
  "type": "Feature",
  "properties": {
    "name": "Iaciara",
    "country": "BR",
    "subdivision": "29",
    "timezone": "America/Sao_Paulo"
  },
  "geometry": {
    "type": "Point",
    "coordinates": [
      -46.63167,
      -14.09583
    ]
  }
}