{
  "type": "Feature",
  "properties": {
    "name": "Iporá",
    "country": "BR",
    "subdivision": "29",
    "timezone": "America/Sao_Paulo"
  },
  "geometry": {
    "type": "Point",
    "coordinates": [
      -51.11778,
      -16.44194
    ]
  }
}