{
  "type": "Feature",
  "properties": {
    "name": "Paraúna",
    "country": "BR",
    "subdivision": "29",
    "timezone": "America/Sao_Paulo"
  },
  "geometry": {
    "type": "Point",
    "coordinates": [
      -50.44861,
      -16.94778
    ]
  }
}