{
  "type": "Feature",
  "properties": {
    "name": "Piranhas",
    "country": "BR",
    "subdivision": "29",
    "timezone": "America/Sao_Paulo"
  },
  "geometry": {
    "type": "Point",
    "coordinates": [
      -51.82222,
      -16.42694
    ]
  }
}