{
  "type": "Feature",
  "properties": {
    "name": "Uruaçu",
    "country": "BR",
    "subdivision": "29",
    "timezone": "America/Sao_Paulo"
  },
  "geometry": {
    "type": "Point",
    "coordinates": [
      -49.14083,
      -14.52472
    ]
  }
}