{
  "type": "Feature",
  "properties": {
    "name": "Bohuslav",
    "country": "UA",
    "subdivision": "13",
    "timezone": "Europe/Kiev"
  },
  "geometry": {
    "type": "Point",
    "coordinates": [
      30.87407,
      49.54637
    ]
  }
}