{
  "type": "Feature",
  "properties": {
    "name": "Brovary",
    "country": "UA",
    "subdivision": "13",
    "timezone": "Europe/Kiev"
  },
  "geometry": {
    "type": "Point",
    "coordinates": [
      30.80671,
      50.51809
    ]
  }
}