{
  "type": "Feature",
  "properties": {
    "name": "Chabany",
    "country": "UA",
    "subdivision": "13",
    "timezone": "Europe/Kiev"
  },
  "geometry": {
    "type": "Point",
    "coordinates": [
      30.42356,
      50.34071
    ]
  }
}