{
  "type": "Feature",
  "properties": {
    "name": "Horenka",
    "country": "UA",
    "subdivision": "13",
    "timezone": "Europe/Kiev"
  },
  "geometry": {
    "type": "Point",
    "coordinates": [
      30.33217,
      50.55731
    ]
  }
}