{
  "type": "Feature",
  "properties": {
    "name": "Pereiaslav-Khmelnytskyi",
    "country": "UA",
    "subdivision": "13",
    "timezone": "Europe/Kiev"
  },
  "geometry": {
    "type": "Point",
    "coordinates": [
      31.44969,
      50.06739
    ]
  }
}