{
  "type": "Feature",
  "properties": {
    "name": "Ukrainka",
    "country": "UA",
    "subdivision": "13",
    "timezone": "Europe/Kiev"
  },
  "geometry": {
    "type": "Point",
    "coordinates": [
      30.74612,
      50.14317
    ]
  }
}