{
  "type": "Feature",
  "properties": {
    "name": "Voronkov",
    "country": "UA",
    "subdivision": "13",
    "timezone": "Europe/Kiev"
  },
  "geometry": {
    "type": "Point",
    "coordinates": [
      30.89967,
      50.22235
    ]
  }
}