{
  "type": "Feature",
  "properties": {
    "name": "El Aguilar",
    "country": "AR",
    "subdivision": "10",
    "timezone": "America/Argentina/Jujuy"
  },
  "geometry": {
    "type": "Point",
    "coordinates": [
      -65.68005,
      -23.21572
    ]
  }
}