{
  "type": "Feature",
  "properties": {
    "name": "Santa Clara",
    "country": "AR",
    "subdivision": "10",
    "timezone": "America/Argentina/Jujuy"
  },
  "geometry": {
    "type": "Point",
    "coordinates": [
      -64.66253,
      -24.30921
    ]
  }
}