{
  "type": "Feature",
  "properties": {
    "name": "Atarrabia",
    "country": "ES",
    "subdivision": "32",
    "timezone": "Europe/Madrid"
  },
  "geometry": {
    "type": "Point",
    "coordinates": [
      -1.60735,
      42.8323
    ]
  }
}