{
  "type": "Feature",
  "properties": {
    "name": "Caparroso",
    "country": "ES",
    "subdivision": "32",
    "timezone": "Europe/Madrid"
  },
  "geometry": {
    "type": "Point",
    "coordinates": [
      -1.64962,
      42.34129
    ]
  }
}