{
  "type": "Feature",
  "properties": {
    "name": "Cáseda",
    "country": "ES",
    "subdivision": "32",
    "timezone": "Europe/Madrid"
  },
  "geometry": {
    "type": "Point",
    "coordinates": [
      -1.36636,
      42.52255
    ]
  }
}