{
  "type": "Feature",
  "properties": {
    "name": "Tudela",
    "country": "ES",
    "subdivision": "32",
    "timezone": "Europe/Madrid"
  },
  "geometry": {
    "type": "Point",
    "coordinates": [
      -1.60452,
      42.06166
    ]
  }
}