{
  "type": "Feature",
  "properties": {
    "name": "Csepreg",
    "country": "HU",
    "subdivision": "22",
    "timezone": "Europe/Budapest"
  },
  "geometry": {
    "type": "Point",
    "coordinates": [
      16.70881,
      47.40098
    ]
  }
}