{
  "type": "Feature",
  "properties": {
    "name": "Sárvár",
    "country": "HU",
    "subdivision": "22",
    "timezone": "Europe/Budapest"
  },
  "geometry": {
    "type": "Point",
    "coordinates": [
      16.93525,
      47.25395
    ]
  }
}