{
  "type": "Feature",
  "properties": {
    "name": "Táplánszentkereszt",
    "country": "HU",
    "subdivision": "22",
    "timezone": "Europe/Budapest"
  },
  "geometry": {
    "type": "Point",
    "coordinates": [
      16.69613,
      47.19496
    ]
  }
}