{
  "type": "Feature",
  "properties": {
    "name": "Vasvár",
    "country": "HU",
    "subdivision": "22",
    "timezone": "Europe/Budapest"
  },
  "geometry": {
    "type": "Point",
    "coordinates": [
      16.79954,
      47.04928
    ]
  }
}