{
  "type": "Feature",
  "properties": {
    "name": "Ekpoma",
    "country": "NG",
    "subdivision": "37",
    "timezone": "Africa/Lagos"
  },
  "geometry": {
    "type": "Point",
    "coordinates": [
      6.14029,
      6.743
    ]
  }
}