{
  "type": "Feature",
  "properties": {
    "name": "Igarra",
    "country": "NG",
    "subdivision": "37",
    "timezone": "Africa/Lagos"
  },
  "geometry": {
    "type": "Point",
    "coordinates": [
      6.10432,
      7.29366
    ]
  }
}