{
  "type": "Feature",
  "properties": {
    "name": "Ubiaja",
    "country": "NG",
    "subdivision": "37",
    "timezone": "Africa/Lagos"
  },
  "geometry": {
    "type": "Point",
    "coordinates": [
      6.38494,
      6.65581
    ]
  }
}