{
  "type": "Feature",
  "properties": {
    "name": "Qrendi",
    "country": "MT",
    "subdivision": "44",
    "timezone": "Europe/Malta"
  },
  "geometry": {
    "type": "Point",
    "coordinates": [
      14.45833,
      35.83472
    ]
  }
}