{
  "type": "Feature",
  "properties": {
    "name": "Apc",
    "country": "HU",
    "subdivision": "11",
    "timezone": "Europe/Budapest"
  },
  "geometry": {
    "type": "Point",
    "coordinates": [
      19.69429,
      47.79419
    ]
  }
}