{
  "type": "Feature",
  "properties": {
    "name": "Felsőtárkány",
    "country": "HU",
    "subdivision": "11",
    "timezone": "Europe/Budapest"
  },
  "geometry": {
    "type": "Point",
    "coordinates": [
      20.41667,
      47.96667
    ]
  }
}