{
  "type": "Feature",
  "properties": {
    "name": "Gyöngyös",
    "country": "HU",
    "subdivision": "11",
    "timezone": "Europe/Budapest"
  },
  "geometry": {
    "type": "Point",
    "coordinates": [
      19.928,
      47.78257
    ]
  }
}