{
  "type": "Feature",
  "properties": {
    "name": "Hort",
    "country": "HU",
    "subdivision": "11",
    "timezone": "Europe/Budapest"
  },
  "geometry": {
    "type": "Point",
    "coordinates": [
      19.7893,
      47.69081
    ]
  }
}