{
  "type": "Feature",
  "properties": {
    "name": "Poroszló",
    "country": "HU",
    "subdivision": "11",
    "timezone": "Europe/Budapest"
  },
  "geometry": {
    "type": "Point",
    "coordinates": [
      20.66667,
      47.65
    ]
  }
}