{
  "type": "Feature",
  "properties": {
    "name": "Tarnalelesz",
    "country": "HU",
    "subdivision": "11",
    "timezone": "Europe/Budapest"
  },
  "geometry": {
    "type": "Point",
    "coordinates": [
      20.18333,
      48.05
    ]
  }
}