{
  "type": "Feature",
  "properties": {
    "name": "Mwinilunga",
    "country": "ZM",
    "subdivision": "06",
    "timezone": "Africa/Lusaka"
  },
  "geometry": {
    "type": "Point",
    "coordinates": [
      24.42926,
      -11.73584
    ]
  }
}