{
  "type": "Feature",
  "properties": {
    "name": "Solwezi",
    "country": "ZM",
    "subdivision": "06",
    "timezone": "Africa/Lusaka"
  },
  "geometry": {
    "type": "Point",
    "coordinates": [
      26.38938,
      -12.1688
    ]
  }
}