{
  "type": "Feature",
  "properties": {
    "name": "Rong Kwang",
    "country": "TH",
    "subdivision": "07",
    "timezone": "Asia/Bangkok"
  },
  "geometry": {
    "type": "Point",
    "coordinates": [
      100.31736,
      18.33903
    ]
  }
}