{
  "type": "Feature",
  "properties": {
    "name": "Alakurtti",
    "country": "RU",
    "subdivision": "49",
    "timezone": "Europe/Moscow"
  },
  "geometry": {
    "type": "Point",
    "coordinates": [
      30.34905,
      66.9672
    ]
  }
}