{
  "type": "Feature",
  "properties": {
    "name": "Kandalaksha",
    "country": "RU",
    "subdivision": "49",
    "timezone": "Europe/Moscow"
  },
  "geometry": {
    "type": "Point",
    "coordinates": [
      32.41284,
      67.15123
    ]
  }
}