{
  "type": "Feature",
  "properties": {
    "name": "Kovdor",
    "country": "RU",
    "subdivision": "49",
    "timezone": "Europe/Moscow"
  },
  "geometry": {
    "type": "Point",
    "coordinates": [
      30.47576,
      67.56616
    ]
  }
}