{
  "type": "Feature",
  "properties": {
    "name": "Molochnyy",
    "country": "RU",
    "subdivision": "49",
    "timezone": "Europe/Moscow"
  },
  "geometry": {
    "type": "Point",
    "coordinates": [
      33.02046,
      68.85389
    ]
  }
}