{
  "type": "Feature",
  "properties": {
    "name": "Roslyakovo",
    "country": "RU",
    "subdivision": "49",
    "timezone": "Europe/Moscow"
  },
  "geometry": {
    "type": "Point",
    "coordinates": [
      33.19906,
      69.04303
    ]
  }
}