{
  "type": "Feature",
  "properties": {
    "name": "Bwizibwera",
    "country": "UG",
    "subdivision": "W",
    "timezone": "Africa/Kampala"
  },
  "geometry": {
    "type": "Point",
    "coordinates": [
      30.62861,
      -0.59167
    ]
  }
}