{
  "type": "Feature",
  "properties": {
    "name": "Muhororo",
    "country": "UG",
    "subdivision": "W",
    "timezone": "Africa/Kampala"
  },
  "geometry": {
    "type": "Point",
    "coordinates": [
      30.75944,
      0.93806
    ]
  }
}