{
  "type": "Feature",
  "properties": {
    "name": "Eielson Air Force Base",
    "country": "US",
    "subdivision": "AK",
    "timezone": "America/Anchorage"
  },
  "geometry": {
    "type": "Point",
    "coordinates": [
      -147.05442,
      64.66327
    ]
  }
}