{
  "type": "Feature",
  "properties": {
    "name": "Fishhook",
    "country": "US",
    "subdivision": "AK",
    "timezone": "America/Anchorage"
  },
  "geometry": {
    "type": "Point",
    "coordinates": [
      -149.23613,
      61.74402
    ]
  }
}