{
  "type": "Feature",
  "properties": {
    "name": "Kotzebue",
    "country": "US",
    "subdivision": "AK",
    "timezone": "America/Nome"
  },
  "geometry": {
    "type": "Point",
    "coordinates": [
      -162.59809,
      66.89846
    ]
  }
}