{
  "type": "Feature",
  "properties": {
    "name": "Prudhoe Bay",
    "country": "US",
    "subdivision": "AK",
    "timezone": "America/Anchorage"
  },
  "geometry": {
    "type": "Point",
    "coordinates": [
      -148.33722,
      70.25528
    ]
  }
}