{
  "type": "Feature",
  "properties": {
    "name": "Valdez",
    "country": "US",
    "subdivision": "AK",
    "timezone": "America/Anchorage"
  },
  "geometry": {
    "type": "Point",
    "coordinates": [
      -146.34833,
      61.13083
    ]
  }
}