{
  "type": "Feature",
  "properties": {
    "name": "Wasilla",
    "country": "US",
    "subdivision": "AK",
    "timezone": "America/Anchorage"
  },
  "geometry": {
    "type": "Point",
    "coordinates": [
      -149.4415,
      61.5809
    ]
  }
}