{
  "type": "Feature",
  "properties": {
    "name": "Kućan Marof",
    "country": "HR",
    "subdivision": "16",
    "timezone": "Europe/Zagreb"
  },
  "geometry": {
    "type": "Point",
    "coordinates": [
      16.37222,
      46.28944
    ]
  }
}