{
  "type": "Feature",
  "properties": {
    "name": "Lepoglava",
    "country": "HR",
    "subdivision": "16",
    "timezone": "Europe/Zagreb"
  },
  "geometry": {
    "type": "Point",
    "coordinates": [
      16.03556,
      46.21056
    ]
  }
}