{
  "type": "Feature",
  "properties": {
    "name": "Gua Musang",
    "country": "MY",
    "subdivision": "03",
    "timezone": "Asia/Kuala_Lumpur"
  },
  "geometry": {
    "type": "Point",
    "coordinates": [
      101.96857,
      4.88441
    ]
  }
}