{
  "type": "Feature",
  "properties": {
    "name": "Abriola",
    "country": "IT",
    "subdivision": "02",
    "timezone": "Europe/Rome"
  },
  "geometry": {
    "type": "Point",
    "coordinates": [
      15.8131,
      40.50748
    ]
  }
}