{
  "type": "Feature",
  "properties": {
    "name": "Brienza",
    "country": "IT",
    "subdivision": "02",
    "timezone": "Europe/Rome"
  },
  "geometry": {
    "type": "Point",
    "coordinates": [
      15.62927,
      40.47751
    ]
  }
}