{
  "type": "Feature",
  "properties": {
    "name": "Chiaromonte",
    "country": "IT",
    "subdivision": "02",
    "timezone": "Europe/Rome"
  },
  "geometry": {
    "type": "Point",
    "coordinates": [
      16.2144,
      40.12323
    ]
  }
}