{
  "type": "Feature",
  "properties": {
    "name": "Marsico Nuovo",
    "country": "IT",
    "subdivision": "02",
    "timezone": "Europe/Rome"
  },
  "geometry": {
    "type": "Point",
    "coordinates": [
      15.73462,
      40.42359
    ]
  }
}