{
  "type": "Feature",
  "properties": {
    "name": "Maschito",
    "country": "IT",
    "subdivision": "02",
    "timezone": "Europe/Rome"
  },
  "geometry": {
    "type": "Point",
    "coordinates": [
      15.82946,
      40.90892
    ]
  }
}