{
  "type": "Feature",
  "properties": {
    "name": "Palazzo San Gervasio",
    "country": "IT",
    "subdivision": "02",
    "timezone": "Europe/Rome"
  },
  "geometry": {
    "type": "Point",
    "coordinates": [
      15.98149,
      40.93156
    ]
  }
}