{
  "type": "Feature",
  "properties": {
    "name": "Rapolla",
    "country": "IT",
    "subdivision": "02",
    "timezone": "Europe/Rome"
  },
  "geometry": {
    "type": "Point",
    "coordinates": [
      15.67201,
      40.97499
    ]
  }
}