{
  "type": "Feature",
  "properties": {
    "name": "Ripacandida",
    "country": "IT",
    "subdivision": "02",
    "timezone": "Europe/Rome"
  },
  "geometry": {
    "type": "Point",
    "coordinates": [
      15.72597,
      40.91256
    ]
  }
}