{
  "type": "Feature",
  "properties": {
    "name": "Satriano di Lucania",
    "country": "IT",
    "subdivision": "02",
    "timezone": "Europe/Rome"
  },
  "geometry": {
    "type": "Point",
    "coordinates": [
      15.64024,
      40.54296
    ]
  }
}