{
  "type": "Feature",
  "properties": {
    "name": "Chalchuapa",
    "country": "SV",
    "subdivision": "11",
    "timezone": "America/El_Salvador"
  },
  "geometry": {
    "type": "Point",
    "coordinates": [
      -89.68111,
      13.98667
    ]
  }
}