{
  "type": "Feature",
  "properties": {
    "name": "Panamá",
    "country": "PA",
    "subdivision": "08",
    "timezone": "America/Panama"
  },
  "geometry": {
    "type": "Point",
    "coordinates": [
      -79.51973,
      8.9936
    ]
  }
}