{
  "type": "Feature",
  "properties": {
    "name": "Acatlán",
    "country": "MX",
    "subdivision": "30",
    "timezone": "America/Mexico_City"
  },
  "geometry": {
    "type": "Point",
    "coordinates": [
      -96.84216,
      19.69677
    ]
  }
}