{
  "type": "Feature",
  "properties": {
    "name": "Actopan",
    "country": "MX",
    "subdivision": "30",
    "timezone": "America/Mexico_City"
  },
  "geometry": {
    "type": "Point",
    "coordinates": [
      -96.61668,
      19.50427
    ]
  }
}