{
  "type": "Feature",
  "properties": {
    "name": "Alpatláhuac",
    "country": "MX",
    "subdivision": "30",
    "timezone": "America/Mexico_City"
  },
  "geometry": {
    "type": "Point",
    "coordinates": [
      -97.09367,
      19.12015
    ]
  }
}