{
  "type": "Feature",
  "properties": {
    "name": "Altotonga",
    "country": "MX",
    "subdivision": "30",
    "timezone": "America/Mexico_City"
  },
  "geometry": {
    "type": "Point",
    "coordinates": [
      -97.24514,
      19.76613
    ]
  }
}