{
  "type": "Feature",
  "properties": {
    "name": "Alto Lucero",
    "country": "MX",
    "subdivision": "30",
    "timezone": "America/Mexico_City"
  },
  "geometry": {
    "type": "Point",
    "coordinates": [
      -96.73409,
      19.62442
    ]
  }
}