{
  "type": "Feature",
  "properties": {
    "name": "Arenal Santa Ana",
    "country": "MX",
    "subdivision": "30",
    "timezone": "America/Mexico_City"
  },
  "geometry": {
    "type": "Point",
    "coordinates": [
      -95.7697,
      17.78951
    ]
  }
}