{
  "type": "Feature",
  "properties": {
    "name": "Arroyo Hondo",
    "country": "MX",
    "subdivision": "30",
    "timezone": "America/Mexico_City"
  },
  "geometry": {
    "type": "Point",
    "coordinates": [
      -96.87372,
      20.02317
    ]
  }
}