{
  "type": "Feature",
  "properties": {
    "name": "Arroyo del Maíz Uno",
    "country": "MX",
    "subdivision": "30",
    "timezone": "America/Mexico_City"
  },
  "geometry": {
    "type": "Point",
    "coordinates": [
      -97.41528,
      20.53667
    ]
  }
}