{
  "type": "Feature",
  "properties": {
    "name": "Arroyo del Potrero",
    "country": "MX",
    "subdivision": "30",
    "timezone": "America/Mexico_City"
  },
  "geometry": {
    "type": "Point",
    "coordinates": [
      -97.0652,
      20.14554
    ]
  }
}