{
  "type": "Feature",
  "properties": {
    "name": "Axochío",
    "country": "MX",
    "subdivision": "30",
    "timezone": "America/Mexico_City"
  },
  "geometry": {
    "type": "Point",
    "coordinates": [
      -95.29985,
      18.37175
    ]
  }
}