{
  "type": "Feature",
  "properties": {
    "name": "Benito Juárez",
    "country": "MX",
    "subdivision": "30",
    "timezone": "America/Mexico_City"
  },
  "geometry": {
    "type": "Point",
    "coordinates": [
      -98.20594,
      20.88635
    ]
  }
}