{
  "type": "Feature",
  "properties": {
    "name": "Buenos Aires",
    "country": "MX",
    "subdivision": "30",
    "timezone": "America/Mexico_City"
  },
  "geometry": {
    "type": "Point",
    "coordinates": [
      -95.24879,
      18.46463
    ]
  }
}