{
  "type": "Feature",
  "properties": {
    "name": "Cabezas",
    "country": "MX",
    "subdivision": "30",
    "timezone": "America/Mexico_City"
  },
  "geometry": {
    "type": "Point",
    "coordinates": [
      -96.38278,
      19.37167
    ]
  }
}