{
  "type": "Feature",
  "properties": {
    "name": "Campo Chico",
    "country": "MX",
    "subdivision": "30",
    "timezone": "America/Mexico_City"
  },
  "geometry": {
    "type": "Point",
    "coordinates": [
      -97.02802,
      18.83639
    ]
  }
}