{
  "type": "Feature",
  "properties": {
    "name": "Castillo de Teayo",
    "country": "MX",
    "subdivision": "30",
    "timezone": "America/Mexico_City"
  },
  "geometry": {
    "type": "Point",
    "coordinates": [
      -97.6303,
      20.74927
    ]
  }
}