{
  "type": "Feature",
  "properties": {
    "name": "Chiconquiaco",
    "country": "MX",
    "subdivision": "30",
    "timezone": "America/Mexico_City"
  },
  "geometry": {
    "type": "Point",
    "coordinates": [
      -96.81851,
      19.74208
    ]
  }
}