{
  "type": "Feature",
  "properties": {
    "name": "Chontla",
    "country": "MX",
    "subdivision": "30",
    "timezone": "America/Mexico_City"
  },
  "geometry": {
    "type": "Point",
    "coordinates": [
      -97.92419,
      21.2958
    ]
  }
}