{
  "type": "Feature",
  "properties": {
    "name": "Chumatlán",
    "country": "MX",
    "subdivision": "30",
    "timezone": "America/Mexico_City"
  },
  "geometry": {
    "type": "Point",
    "coordinates": [
      -97.59402,
      20.20574
    ]
  }
}