{
  "type": "Feature",
  "properties": {
    "name": "Corozal",
    "country": "MX",
    "subdivision": "30",
    "timezone": "America/Mexico_City"
  },
  "geometry": {
    "type": "Point",
    "coordinates": [
      -98.55444,
      21.54627
    ]
  }
}