{
  "type": "Feature",
  "properties": {
    "name": "Cosoleacaque",
    "country": "MX",
    "subdivision": "30",
    "timezone": "America/Mexico_City"
  },
  "geometry": {
    "type": "Point",
    "coordinates": [
      -94.6359,
      17.99913
    ]
  }
}