{
  "type": "Feature",
  "properties": {
    "name": "Cuautlapán",
    "country": "MX",
    "subdivision": "30",
    "timezone": "America/Mexico_City"
  },
  "geometry": {
    "type": "Point",
    "coordinates": [
      -97.02291,
      18.87747
    ]
  }
}