{
  "type": "Feature",
  "properties": {
    "name": "El Escobillo",
    "country": "MX",
    "subdivision": "30",
    "timezone": "America/Mexico_City"
  },
  "geometry": {
    "type": "Point",
    "coordinates": [
      -97.19791,
      19.5145
    ]
  }
}