{
  "type": "Feature",
  "properties": {
    "name": "El Juile",
    "country": "MX",
    "subdivision": "30",
    "timezone": "America/Mexico_City"
  },
  "geometry": {
    "type": "Point",
    "coordinates": [
      -94.98946,
      17.74412
    ]
  }
}