{
  "type": "Feature",
  "properties": {
    "name": "El Mollejon",
    "country": "MX",
    "subdivision": "30",
    "timezone": "America/Mexico_City"
  },
  "geometry": {
    "type": "Point",
    "coordinates": [
      -97.41111,
      20.54222
    ]
  }
}