{
  "type": "Feature",
  "properties": {
    "name": "El Maguey",
    "country": "MX",
    "subdivision": "30",
    "timezone": "America/Mexico_City"
  },
  "geometry": {
    "type": "Point",
    "coordinates": [
      -96.73434,
      18.83295
    ]
  }
}