{
  "type": "Feature",
  "properties": {
    "name": "El Pueblito (Garbanzal)",
    "country": "MX",
    "subdivision": "30",
    "timezone": "America/Mexico_City"
  },
  "geometry": {
    "type": "Point",
    "coordinates": [
      -96.92417,
      19.59389
    ]
  }
}