{
  "type": "Feature",
  "properties": {
    "name": "El Remolino",
    "country": "MX",
    "subdivision": "30",
    "timezone": "America/Mexico_City"
  },
  "geometry": {
    "type": "Point",
    "coordinates": [
      -97.21213,
      20.38921
    ]
  }
}