{
  "type": "Feature",
  "properties": {
    "name": "El Terrero",
    "country": "MX",
    "subdivision": "30",
    "timezone": "America/Mexico_City"
  },
  "geometry": {
    "type": "Point",
    "coordinates": [
      -96.79907,
      19.53709
    ]
  }
}