{
  "type": "Feature",
  "properties": {
    "name": "Fraccionamiento Ciudad Olmeca",
    "country": "MX",
    "subdivision": "30",
    "timezone": "America/Mexico_City"
  },
  "geometry": {
    "type": "Point",
    "coordinates": [
      -94.5525,
      18.15056
    ]
  }
}