{
  "type": "Feature",
  "properties": {
    "name": "Fraccionamiento Villas de la Llave",
    "country": "MX",
    "subdivision": "30",
    "timezone": "America/Mexico_City"
  },
  "geometry": {
    "type": "Point",
    "coordinates": [
      -96.99111,
      18.91583
    ]
  }
}