{
  "type": "Feature",
  "properties": {
    "name": "General Alatriste (San Joaquín)",
    "country": "MX",
    "subdivision": "30",
    "timezone": "America/Mexico_City"
  },
  "geometry": {
    "type": "Point",
    "coordinates": [
      -96.79361,
      18.84028
    ]
  }
}