{
  "type": "Feature",
  "properties": {
    "name": "Guillermo Prieto",
    "country": "MX",
    "subdivision": "30",
    "timezone": "America/Mexico_City"
  },
  "geometry": {
    "type": "Point",
    "coordinates": [
      -94.27658,
      18.16077
    ]
  }
}