{
  "type": "Feature",
  "properties": {
    "name": "Hueyapan de Ocampo",
    "country": "MX",
    "subdivision": "30",
    "timezone": "America/Mexico_City"
  },
  "geometry": {
    "type": "Point",
    "coordinates": [
      -95.14873,
      18.14479
    ]
  }
}