{
  "type": "Feature",
  "properties": {
    "name": "Huiloapan de Cuauhtémoc",
    "country": "MX",
    "subdivision": "30",
    "timezone": "America/Mexico_City"
  },
  "geometry": {
    "type": "Point",
    "coordinates": [
      -97.15444,
      18.81722
    ]
  }
}