{
  "type": "Feature",
  "properties": {
    "name": "Ixcatla",
    "country": "MX",
    "subdivision": "30",
    "timezone": "America/Mexico_City"
  },
  "geometry": {
    "type": "Point",
    "coordinates": [
      -96.91889,
      19.07528
    ]
  }
}