{
  "type": "Feature",
  "properties": {
    "name": "Jáltipan de Morelos",
    "country": "MX",
    "subdivision": "30",
    "timezone": "America/Mexico_City"
  },
  "geometry": {
    "type": "Point",
    "coordinates": [
      -94.71396,
      17.96542
    ]
  }
}