{
  "type": "Feature",
  "properties": {
    "name": "Jesús Carranza",
    "country": "MX",
    "subdivision": "30",
    "timezone": "America/Mexico_City"
  },
  "geometry": {
    "type": "Point",
    "coordinates": [
      -95.02637,
      17.43526
    ]
  }
}