{
  "type": "Feature",
  "properties": {
    "name": "Juan Marcos (San José Buenavista)",
    "country": "MX",
    "subdivision": "30",
    "timezone": "America/Mexico_City"
  },
  "geometry": {
    "type": "Point",
    "coordinates": [
      -97.19667,
      19.72917
    ]
  }
}