{
  "type": "Feature",
  "properties": {
    "name": "La Gloria",
    "country": "MX",
    "subdivision": "30",
    "timezone": "America/Mexico_City"
  },
  "geometry": {
    "type": "Point",
    "coordinates": [
      -96.40211,
      19.42631
    ]
  }
}