{
  "type": "Feature",
  "properties": {
    "name": "La Nueva Victoria",
    "country": "MX",
    "subdivision": "30",
    "timezone": "America/Mexico_City"
  },
  "geometry": {
    "type": "Point",
    "coordinates": [
      -95.25806,
      18.65639
    ]
  }
}