{
  "type": "Feature",
  "properties": {
    "name": "La Toma",
    "country": "MX",
    "subdivision": "30",
    "timezone": "America/Mexico_City"
  },
  "geometry": {
    "type": "Point",
    "coordinates": [
      -97.19361,
      19.45278
    ]
  }
}