{
  "type": "Feature",
  "properties": {
    "name": "La Unión Paso Largo",
    "country": "MX",
    "subdivision": "30",
    "timezone": "America/Mexico_City"
  },
  "geometry": {
    "type": "Point",
    "coordinates": [
      -96.99995,
      20.14224
    ]
  }
}