{
  "type": "Feature",
  "properties": {
    "name": "Las Vigas de Ramírez",
    "country": "MX",
    "subdivision": "30",
    "timezone": "America/Mexico_City"
  },
  "geometry": {
    "type": "Point",
    "coordinates": [
      -97.09821,
      19.63722
    ]
  }
}