{
  "type": "Feature",
  "properties": {
    "name": "Llano Grande",
    "country": "MX",
    "subdivision": "30",
    "timezone": "America/Mexico_City"
  },
  "geometry": {
    "type": "Point",
    "coordinates": [
      -96.88002,
      19.37035
    ]
  }
}