{
  "type": "Feature",
  "properties": {
    "name": "Loma de los Carmona",
    "country": "MX",
    "subdivision": "30",
    "timezone": "America/Mexico_City"
  },
  "geometry": {
    "type": "Point",
    "coordinates": [
      -96.39369,
      19.10556
    ]
  }
}