{
  "type": "Feature",
  "properties": {
    "name": "Los Mangos",
    "country": "MX",
    "subdivision": "30",
    "timezone": "America/Mexico_City"
  },
  "geometry": {
    "type": "Point",
    "coordinates": [
      -95.12222,
      18.24361
    ]
  }
}