{
  "type": "Feature",
  "properties": {
    "name": "Los Torrentes",
    "country": "MX",
    "subdivision": "30",
    "timezone": "America/Mexico_City"
  },
  "geometry": {
    "type": "Point",
    "coordinates": [
      -96.21139,
      19.20194
    ]
  }
}