{
  "type": "Feature",
  "properties": {
    "name": "Mata Naranjo",
    "country": "MX",
    "subdivision": "30",
    "timezone": "America/Mexico_City"
  },
  "geometry": {
    "type": "Point",
    "coordinates": [
      -96.71333,
      18.77746
    ]
  }
}