{
  "type": "Feature",
  "properties": {
    "name": "Medias Aguas",
    "country": "MX",
    "subdivision": "30",
    "timezone": "America/Mexico_City"
  },
  "geometry": {
    "type": "Point",
    "coordinates": [
      -95.02857,
      17.66776
    ]
  }
}