{
  "type": "Feature",
  "properties": {
    "name": "Mequetla",
    "country": "MX",
    "subdivision": "30",
    "timezone": "America/Mexico_City"
  },
  "geometry": {
    "type": "Point",
    "coordinates": [
      -97.68855,
      20.79468
    ]
  }
}