{
  "type": "Feature",
  "properties": {
    "name": "Mesa de Guadalupe",
    "country": "MX",
    "subdivision": "30",
    "timezone": "America/Mexico_City"
  },
  "geometry": {
    "type": "Point",
    "coordinates": [
      -96.69948,
      19.56403
    ]
  }
}