{
  "type": "Feature",
  "properties": {
    "name": "Miguel Hidalgo",
    "country": "MX",
    "subdivision": "30",
    "timezone": "America/Mexico_City"
  },
  "geometry": {
    "type": "Point",
    "coordinates": [
      -97.502,
      20.55316
    ]
  }
}