{
  "type": "Feature",
  "properties": {
    "name": "Minatitlán",
    "country": "MX",
    "subdivision": "30",
    "timezone": "America/Mexico_City"
  },
  "geometry": {
    "type": "Point",
    "coordinates": [
      -94.5569,
      18.00011
    ]
  }
}