{
  "type": "Feature",
  "properties": {
    "name": "Mozomboa",
    "country": "MX",
    "subdivision": "30",
    "timezone": "America/Mexico_City"
  },
  "geometry": {
    "type": "Point",
    "coordinates": [
      -96.47738,
      19.50437
    ]
  }
}