{
  "type": "Feature",
  "properties": {
    "name": "Naranjal",
    "country": "MX",
    "subdivision": "30",
    "timezone": "America/Mexico_City"
  },
  "geometry": {
    "type": "Point",
    "coordinates": [
      -96.96282,
      18.81074
    ]
  }
}