{
  "type": "Feature",
  "properties": {
    "name": "Nuevo Progreso",
    "country": "MX",
    "subdivision": "30",
    "timezone": "America/Mexico_City"
  },
  "geometry": {
    "type": "Point",
    "coordinates": [
      -97.50756,
      20.6182
    ]
  }
}