{
  "type": "Feature",
  "properties": {
    "name": "Paso del Macho",
    "country": "MX",
    "subdivision": "30",
    "timezone": "America/Mexico_City"
  },
  "geometry": {
    "type": "Point",
    "coordinates": [
      -96.72419,
      18.97098
    ]
  }
}