{
  "type": "Feature",
  "properties": {
    "name": "Peñuela",
    "country": "MX",
    "subdivision": "30",
    "timezone": "America/Mexico_City"
  },
  "geometry": {
    "type": "Point",
    "coordinates": [
      -96.89327,
      18.86432
    ]
  }
}