{
  "type": "Feature",
  "properties": {
    "name": "Piedra Pinta",
    "country": "MX",
    "subdivision": "30",
    "timezone": "America/Mexico_City"
  },
  "geometry": {
    "type": "Point",
    "coordinates": [
      -97.19538,
      19.99115
    ]
  }
}