{
  "type": "Feature",
  "properties": {
    "name": "Polutla",
    "country": "MX",
    "subdivision": "30",
    "timezone": "America/Mexico_City"
  },
  "geometry": {
    "type": "Point",
    "coordinates": [
      -97.25884,
      20.52799
    ]
  }
}