{
  "type": "Feature",
  "properties": {
    "name": "San Rafael Río Seco",
    "country": "MX",
    "subdivision": "30",
    "timezone": "America/Mexico_City"
  },
  "geometry": {
    "type": "Point",
    "coordinates": [
      -96.88127,
      18.87608
    ]
  }
}