{
  "type": "Feature",
  "properties": {
    "name": "San Pedro Mártir",
    "country": "MX",
    "subdivision": "30",
    "timezone": "America/Mexico_City"
  },
  "geometry": {
    "type": "Point",
    "coordinates": [
      -94.61033,
      17.9787
    ]
  }
}