{
  "type": "Feature",
  "properties": {
    "name": "San José Neria",
    "country": "MX",
    "subdivision": "30",
    "timezone": "America/Mexico_City"
  },
  "geometry": {
    "type": "Point",
    "coordinates": [
      -96.99917,
      18.99333
    ]
  }
}