{
  "type": "Feature",
  "properties": {
    "name": "San Miguel Tlalpoalán",
    "country": "MX",
    "subdivision": "30",
    "timezone": "America/Mexico_City"
  },
  "geometry": {
    "type": "Point",
    "coordinates": [
      -97.22662,
      19.73981
    ]
  }
}