{
  "type": "Feature",
  "properties": {
    "name": "San Pedro Tlanixco",
    "country": "MX",
    "subdivision": "30",
    "timezone": "America/Mexico_City"
  },
  "geometry": {
    "type": "Point",
    "coordinates": [
      -99.65237,
      19.06259
    ]
  }
}