{
  "type": "Feature",
  "properties": {
    "name": "San José Súchil",
    "country": "MX",
    "subdivision": "30",
    "timezone": "America/Mexico_City"
  },
  "geometry": {
    "type": "Point",
    "coordinates": [
      -97.23722,
      18.88778
    ]
  }
}