{
  "type": "Feature",
  "properties": {
    "name": "San Julián",
    "country": "MX",
    "subdivision": "30",
    "timezone": "America/Mexico_City"
  },
  "geometry": {
    "type": "Point",
    "coordinates": [
      -96.26717,
      19.2568
    ]
  }
}