{
  "type": "Feature",
  "properties": {
    "name": "San Cristóbal",
    "country": "MX",
    "subdivision": "30",
    "timezone": "America/Mexico_City"
  },
  "geometry": {
    "type": "Point",
    "coordinates": [
      -97.12392,
      18.82979
    ]
  }
}