{
  "type": "Feature",
  "properties": {
    "name": "Santa Catalina",
    "country": "MX",
    "subdivision": "30",
    "timezone": "America/Mexico_City"
  },
  "geometry": {
    "type": "Point",
    "coordinates": [
      -95.20779,
      18.16353
    ]
  }
}