{
  "type": "Feature",
  "properties": {
    "name": "Santa Rita",
    "country": "MX",
    "subdivision": "30",
    "timezone": "America/Mexico_City"
  },
  "geometry": {
    "type": "Point",
    "coordinates": [
      -96.26,
      19.16736
    ]
  }
}