{
  "type": "Feature",
  "properties": {
    "name": "Sonora",
    "country": "MX",
    "subdivision": "30",
    "timezone": "America/Mexico_City"
  },
  "geometry": {
    "type": "Point",
    "coordinates": [
      -96.63531,
      19.11219
    ]
  }
}