{
  "type": "Feature",
  "properties": {
    "name": "Tamalín",
    "country": "MX",
    "subdivision": "30",
    "timezone": "America/Mexico_City"
  },
  "geometry": {
    "type": "Point",
    "coordinates": [
      -97.81188,
      21.33936
    ]
  }
}