{
  "type": "Feature",
  "properties": {
    "name": "Tapalapan",
    "country": "MX",
    "subdivision": "30",
    "timezone": "America/Mexico_City"
  },
  "geometry": {
    "type": "Point",
    "coordinates": [
      -95.30631,
      18.5325
    ]
  }
}