{
  "type": "Feature",
  "properties": {
    "name": "Tecolutla",
    "country": "MX",
    "subdivision": "30",
    "timezone": "America/Mexico_City"
  },
  "geometry": {
    "type": "Point",
    "coordinates": [
      -97.01309,
      20.48049
    ]
  }
}