{
  "type": "Feature",
  "properties": {
    "name": "Tehuipango",
    "country": "MX",
    "subdivision": "30",
    "timezone": "America/Mexico_City"
  },
  "geometry": {
    "type": "Point",
    "coordinates": [
      -97.05438,
      18.51964
    ]
  }
}