{
  "type": "Feature",
  "properties": {
    "name": "Tepetlán",
    "country": "MX",
    "subdivision": "30",
    "timezone": "America/Mexico_City"
  },
  "geometry": {
    "type": "Point",
    "coordinates": [
      -96.79734,
      19.67318
    ]
  }
}