{
  "type": "Feature",
  "properties": {
    "name": "Teteltzingo",
    "country": "MX",
    "subdivision": "30",
    "timezone": "America/Mexico_City"
  },
  "geometry": {
    "type": "Point",
    "coordinates": [
      -97.14465,
      19.05141
    ]
  }
}