{
  "type": "Feature",
  "properties": {
    "name": "Texcatepec",
    "country": "MX",
    "subdivision": "30",
    "timezone": "America/Mexico_City"
  },
  "geometry": {
    "type": "Point",
    "coordinates": [
      -98.36538,
      20.58505
    ]
  }
}