{
  "type": "Feature",
  "properties": {
    "name": "Tezonapa",
    "country": "MX",
    "subdivision": "30",
    "timezone": "America/Mexico_City"
  },
  "geometry": {
    "type": "Point",
    "coordinates": [
      -96.68417,
      18.60706
    ]
  }
}