{
  "type": "Feature",
  "properties": {
    "name": "Tilapan",
    "country": "MX",
    "subdivision": "30",
    "timezone": "America/Mexico_City"
  },
  "geometry": {
    "type": "Point",
    "coordinates": [
      -95.32806,
      18.34917
    ]
  }
}