{
  "type": "Feature",
  "properties": {
    "name": "Tinajitas",
    "country": "MX",
    "subdivision": "30",
    "timezone": "America/Mexico_City"
  },
  "geometry": {
    "type": "Point",
    "coordinates": [
      -96.4425,
      19.61806
    ]
  }
}