{
  "type": "Feature",
  "properties": {
    "name": "Tlacolula",
    "country": "MX",
    "subdivision": "30",
    "timezone": "America/Mexico_City"
  },
  "geometry": {
    "type": "Point",
    "coordinates": [
      -97.9596,
      21.09177
    ]
  }
}