{
  "type": "Feature",
  "properties": {
    "name": "Tlilapan",
    "country": "MX",
    "subdivision": "30",
    "timezone": "America/Mexico_City"
  },
  "geometry": {
    "type": "Point",
    "coordinates": [
      -97.09867,
      18.8056
    ]
  }
}