{
  "type": "Feature",
  "properties": {
    "name": "Tocuila",
    "country": "MX",
    "subdivision": "30",
    "timezone": "America/Mexico_City"
  },
  "geometry": {
    "type": "Point",
    "coordinates": [
      -97.01667,
      18.95
    ]
  }
}