{
  "type": "Feature",
  "properties": {
    "name": "Tonalixco",
    "country": "MX",
    "subdivision": "30",
    "timezone": "America/Mexico_City"
  },
  "geometry": {
    "type": "Point",
    "coordinates": [
      -97.05972,
      18.78194
    ]
  }
}