{
  "type": "Feature",
  "properties": {
    "name": "Tonalapan",
    "country": "MX",
    "subdivision": "30",
    "timezone": "America/Mexico_City"
  },
  "geometry": {
    "type": "Point",
    "coordinates": [
      -95.22,
      18.46833
    ]
  }
}