{
  "type": "Feature",
  "properties": {
    "name": "Tula",
    "country": "MX",
    "subdivision": "30",
    "timezone": "America/Mexico_City"
  },
  "geometry": {
    "type": "Point",
    "coordinates": [
      -95.37679,
      18.58672
    ]
  }
}