{
  "type": "Feature",
  "properties": {
    "name": "Tuzamapan",
    "country": "MX",
    "subdivision": "30",
    "timezone": "America/Mexico_City"
  },
  "geometry": {
    "type": "Point",
    "coordinates": [
      -96.8636,
      19.40253
    ]
  }
}