{
  "type": "Feature",
  "properties": {
    "name": "Venustiano Carranza (Peña Blanca)",
    "country": "MX",
    "subdivision": "30",
    "timezone": "America/Mexico_City"
  },
  "geometry": {
    "type": "Point",
    "coordinates": [
      -94.75417,
      17.64194
    ]
  }
}