{
  "type": "Feature",
  "properties": {
    "name": "Vicente Herrera",
    "country": "MX",
    "subdivision": "30",
    "timezone": "America/Mexico_City"
  },
  "geometry": {
    "type": "Point",
    "coordinates": [
      -97.34973,
      20.57695
    ]
  }
}