{
  "type": "Feature",
  "properties": {
    "name": "Xoampolco",
    "country": "MX",
    "subdivision": "30",
    "timezone": "America/Mexico_City"
  },
  "geometry": {
    "type": "Point",
    "coordinates": [
      -97.22965,
      19.76055
    ]
  }
}