{
  "type": "Feature",
  "properties": {
    "name": "Yanga",
    "country": "MX",
    "subdivision": "30",
    "timezone": "America/Mexico_City"
  },
  "geometry": {
    "type": "Point",
    "coordinates": [
      -96.79837,
      18.83288
    ]
  }
}