{
  "type": "Feature",
  "properties": {
    "name": "Zacate Colorado Segundo (Fraternidad)",
    "country": "MX",
    "subdivision": "30",
    "timezone": "America/Mexico_City"
  },
  "geometry": {
    "type": "Point",
    "coordinates": [
      -95.97111,
      18.68333
    ]
  }
}