{
  "type": "Feature",
  "properties": {
    "name": "Dubá",
    "country": "CZ",
    "subdivision": "83",
    "timezone": "Europe/Prague"
  },
  "geometry": {
    "type": "Point",
    "coordinates": [
      14.54023,
      50.54034
    ]
  }
}