{
  "type": "Feature",
  "properties": {
    "name": "Jablonec nad Nisou",
    "country": "CZ",
    "subdivision": "83",
    "timezone": "Europe/Prague"
  },
  "geometry": {
    "type": "Point",
    "coordinates": [
      15.17108,
      50.72431
    ]
  }
}