{
  "type": "Feature",
  "properties": {
    "name": "Janov nad Nisou",
    "country": "CZ",
    "subdivision": "83",
    "timezone": "Europe/Prague"
  },
  "geometry": {
    "type": "Point",
    "coordinates": [
      15.16913,
      50.77204
    ]
  }
}