{
  "type": "Feature",
  "properties": {
    "name": "Lomnice nad Popelkou",
    "country": "CZ",
    "subdivision": "83",
    "timezone": "Europe/Prague"
  },
  "geometry": {
    "type": "Point",
    "coordinates": [
      15.37341,
      50.53062
    ]
  }
}