{
  "type": "Feature",
  "properties": {
    "name": "Nové Město pod Smrkem",
    "country": "CZ",
    "subdivision": "83",
    "timezone": "Europe/Prague"
  },
  "geometry": {
    "type": "Point",
    "coordinates": [
      15.22943,
      50.92491
    ]
  }
}