{
  "type": "Feature",
  "properties": {
    "name": "Ohrazenice",
    "country": "CZ",
    "subdivision": "83",
    "timezone": "Europe/Prague"
  },
  "geometry": {
    "type": "Point",
    "coordinates": [
      15.12596,
      50.59765
    ]
  }
}