{
  "type": "Feature",
  "properties": {
    "name": "Osečná",
    "country": "CZ",
    "subdivision": "83",
    "timezone": "Europe/Prague"
  },
  "geometry": {
    "type": "Point",
    "coordinates": [
      14.92138,
      50.69489
    ]
  }
}