{
  "type": "Feature",
  "properties": {
    "name": "Zákupy",
    "country": "CZ",
    "subdivision": "83",
    "timezone": "Europe/Prague"
  },
  "geometry": {
    "type": "Point",
    "coordinates": [
      14.64522,
      50.68475
    ]
  }
}