{
  "type": "Feature",
  "properties": {
    "name": "Delmas",
    "country": "ZA",
    "subdivision": "07",
    "timezone": "Africa/Johannesburg"
  },
  "geometry": {
    "type": "Point",
    "coordinates": [
      28.68322,
      -26.1466
    ]
  }
}