{
  "type": "Feature",
  "properties": {
    "name": "eMbalenhle",
    "country": "ZA",
    "subdivision": "07",
    "timezone": "Africa/Johannesburg"
  },
  "geometry": {
    "type": "Point",
    "coordinates": [
      29.06667,
      -26.53333
    ]
  }
}