{
  "type": "Feature",
  "properties": {
    "name": "Lydenburg",
    "country": "ZA",
    "subdivision": "07",
    "timezone": "Africa/Johannesburg"
  },
  "geometry": {
    "type": "Point",
    "coordinates": [
      30.44393,
      -25.09598
    ]
  }
}