{
  "type": "Feature",
  "properties": {
    "name": "Middelburg",
    "country": "ZA",
    "subdivision": "07",
    "timezone": "Africa/Johannesburg"
  },
  "geometry": {
    "type": "Point",
    "coordinates": [
      29.46482,
      -25.77507
    ]
  }
}