{
  "type": "Feature",
  "properties": {
    "name": "Siyabuswa",
    "country": "ZA",
    "subdivision": "07",
    "timezone": "Africa/Johannesburg"
  },
  "geometry": {
    "type": "Point",
    "coordinates": [
      29.04454,
      -25.11319
    ]
  }
}