{
  "type": "Feature",
  "properties": {
    "name": "Pulumer",
    "country": "TR",
    "subdivision": "62",
    "timezone": "Europe/Istanbul"
  },
  "geometry": {
    "type": "Point",
    "coordinates": [
      39.89532,
      39.48449
    ]
  }
}