{
  "type": "Feature",
  "properties": {
    "name": "Sibut",
    "country": "CF",
    "subdivision": "06",
    "timezone": "Africa/Bangui"
  },
  "geometry": {
    "type": "Point",
    "coordinates": [
      19.07389,
      5.71801
    ]
  }
}