{
  "type": "Feature",
  "properties": {
    "name": "Saqqez",
    "country": "IR",
    "subdivision": "16",
    "timezone": "Asia/Tehran"
  },
  "geometry": {
    "type": "Point",
    "coordinates": [
      46.2735,
      36.24992
    ]
  }
}