{
  "type": "Feature",
  "properties": {
    "name": "Manzini",
    "country": "SZ",
    "subdivision": "03",
    "timezone": "Africa/Mbabane"
  },
  "geometry": {
    "type": "Point",
    "coordinates": [
      31.38004,
      -26.49884
    ]
  }
}