{
  "type": "Feature",
  "properties": {
    "name": "Almendricos",
    "country": "ES",
    "subdivision": "31",
    "timezone": "Europe/Madrid"
  },
  "geometry": {
    "type": "Point",
    "coordinates": [
      -1.77468,
      37.47256
    ]
  }
}