{
  "type": "Feature",
  "properties": {
    "name": "Archena",
    "country": "ES",
    "subdivision": "31",
    "timezone": "Europe/Madrid"
  },
  "geometry": {
    "type": "Point",
    "coordinates": [
      -1.30043,
      38.11631
    ]
  }
}