{
  "type": "Feature",
  "properties": {
    "name": "Calasparra",
    "country": "ES",
    "subdivision": "31",
    "timezone": "Europe/Madrid"
  },
  "geometry": {
    "type": "Point",
    "coordinates": [
      -1.69986,
      38.22997
    ]
  }
}