{
  "type": "Feature",
  "properties": {
    "name": "La Torrecilla",
    "country": "ES",
    "subdivision": "31",
    "timezone": "Europe/Madrid"
  },
  "geometry": {
    "type": "Point",
    "coordinates": [
      -1.72785,
      37.62363
    ]
  }
}