{
  "type": "Feature",
  "properties": {
    "name": "Ricote",
    "country": "ES",
    "subdivision": "31",
    "timezone": "Europe/Madrid"
  },
  "geometry": {
    "type": "Point",
    "coordinates": [
      -1.36557,
      38.15338
    ]
  }
}