{
  "type": "Feature",
  "properties": {
    "name": "San Pedro del Pinatar",
    "country": "ES",
    "subdivision": "31",
    "timezone": "Europe/Madrid"
  },
  "geometry": {
    "type": "Point",
    "coordinates": [
      -0.79102,
      37.83568
    ]
  }
}