{
  "type": "Feature",
  "properties": {
    "name": "Gavrilov-Yam",
    "country": "RU",
    "subdivision": "88",
    "timezone": "Europe/Moscow"
  },
  "geometry": {
    "type": "Point",
    "coordinates": [
      39.85331,
      57.30185
    ]
  }
}