{
  "type": "Feature",
  "properties": {
    "name": "Nekrasovskoye",
    "country": "RU",
    "subdivision": "88",
    "timezone": "Europe/Moscow"
  },
  "geometry": {
    "type": "Point",
    "coordinates": [
      40.36567,
      57.67663
    ]
  }
}