{
  "type": "Feature",
  "properties": {
    "name": "Rostov",
    "country": "RU",
    "subdivision": "88",
    "timezone": "Europe/Moscow"
  },
  "geometry": {
    "type": "Point",
    "coordinates": [
      39.41394,
      57.1914
    ]
  }
}