{
  "type": "Feature",
  "properties": {
    "name": "Sudoverf’",
    "country": "RU",
    "subdivision": "88",
    "timezone": "Europe/Moscow"
  },
  "geometry": {
    "type": "Point",
    "coordinates": [
      38.64175,
      58.11696
    ]
  }
}