{
  "type": "Feature",
  "properties": {
    "name": "Sredno Konjari",
    "country": "MK",
    "subdivision": "79",
    "timezone": "Europe/Skopje"
  },
  "geometry": {
    "type": "Point",
    "coordinates": [
      21.71494,
      41.95743
    ]
  }
}