{
  "type": "Feature",
  "properties": {
    "name": "Reguiba",
    "country": "DZ",
    "subdivision": "43",
    "timezone": "Africa/Algiers"
  },
  "geometry": {
    "type": "Point",
    "coordinates": [
      6.70326,
      33.56391
    ]
  }
}