{
  "type": "Feature",
  "properties": {
    "name": "Shahr-e Kord",
    "country": "IR",
    "subdivision": "03",
    "timezone": "Asia/Tehran"
  },
  "geometry": {
    "type": "Point",
    "coordinates": [
      50.8572,
      32.32612
    ]
  }
}