{
  "type": "Feature",
  "properties": {
    "name": "Johnston",
    "country": "US",
    "subdivision": "RI",
    "timezone": "America/New_York"
  },
  "geometry": {
    "type": "Point",
    "coordinates": [
      -71.50675,
      41.82186
    ]
  }
}