{
  "type": "Feature",
  "properties": {
    "name": "Narragansett",
    "country": "US",
    "subdivision": "RI",
    "timezone": "America/New_York"
  },
  "geometry": {
    "type": "Point",
    "coordinates": [
      -71.4495,
      41.4501
    ]
  }
}