{
  "type": "Feature",
  "properties": {
    "name": "Portsmouth",
    "country": "US",
    "subdivision": "RI",
    "timezone": "America/New_York"
  },
  "geometry": {
    "type": "Point",
    "coordinates": [
      -71.25033,
      41.60232
    ]
  }
}