{
  "type": "Feature",
  "properties": {
    "name": "South Kingstown",
    "country": "US",
    "subdivision": "RI",
    "timezone": "America/New_York"
  },
  "geometry": {
    "type": "Point",
    "coordinates": [
      -71.52494,
      41.44718
    ]
  }
}