{
  "type": "Feature",
  "properties": {
    "name": "Warren",
    "country": "US",
    "subdivision": "RI",
    "timezone": "America/New_York"
  },
  "geometry": {
    "type": "Point",
    "coordinates": [
      -71.28255,
      41.73038
    ]
  }
}