{
  "type": "Feature",
  "properties": {
    "name": "West Warwick",
    "country": "US",
    "subdivision": "RI",
    "timezone": "America/New_York"
  },
  "geometry": {
    "type": "Point",
    "coordinates": [
      -71.52194,
      41.69689
    ]
  }
}