{
  "type": "Feature",
  "properties": {
    "name": "Boffa",
    "country": "GN",
    "subdivision": "B",
    "timezone": "Africa/Conakry"
  },
  "geometry": {
    "type": "Point",
    "coordinates": [
      -14.03333,
      10.16667
    ]
  }
}