{
  "type": "Feature",
  "properties": {
    "name": "Beit Horon",
    "country": "IL",
    "subdivision": "",
    "timezone": "Asia/Jerusalem"
  },
  "geometry": {
    "type": "Point",
    "coordinates": [
      35.12999,
      31.87581
    ]
  }
}