{
  "type": "Feature",
  "properties": {
    "name": "Dorowa Mining Lease",
    "country": "ZW",
    "subdivision": "01",
    "timezone": "Africa/Harare"
  },
  "geometry": {
    "type": "Point",
    "coordinates": [
      31.75,
      -19.06667
    ]
  }
}