{
  "type": "Feature",
  "properties": {
    "name": "Ibrā’",
    "country": "OM",
    "subdivision": "12",
    "timezone": "Asia/Muscat"
  },
  "geometry": {
    "type": "Point",
    "coordinates": [
      58.53337,
      22.69057
    ]
  }
}