{
  "type": "Feature",
  "properties": {
    "name": "Aguçadoura",
    "country": "PT",
    "subdivision": "17",
    "timezone": "Europe/Lisbon"
  },
  "geometry": {
    "type": "Point",
    "coordinates": [
      -8.77844,
      41.43116
    ]
  }
}