{
  "type": "Feature",
  "properties": {
    "name": "Amorim",
    "country": "PT",
    "subdivision": "17",
    "timezone": "Europe/Lisbon"
  },
  "geometry": {
    "type": "Point",
    "coordinates": [
      -8.75046,
      41.40503
    ]
  }
}