{
  "type": "Feature",
  "properties": {
    "name": "Arcozelo",
    "country": "PT",
    "subdivision": "17",
    "timezone": "Europe/Lisbon"
  },
  "geometry": {
    "type": "Point",
    "coordinates": [
      -8.63192,
      41.06187
    ]
  }
}