{
  "type": "Feature",
  "properties": {
    "name": "Aves",
    "country": "PT",
    "subdivision": "17",
    "timezone": "Europe/Lisbon"
  },
  "geometry": {
    "type": "Point",
    "coordinates": [
      -8.4101,
      41.37034
    ]
  }
}