{
  "type": "Feature",
  "properties": {
    "name": "Baltar",
    "country": "PT",
    "subdivision": "17",
    "timezone": "Europe/Lisbon"
  },
  "geometry": {
    "type": "Point",
    "coordinates": [
      -8.38768,
      41.19272
    ]
  }
}