{
  "type": "Feature",
  "properties": {
    "name": "Barrosas",
    "country": "PT",
    "subdivision": "17",
    "timezone": "Europe/Lisbon"
  },
  "geometry": {
    "type": "Point",
    "coordinates": [
      -8.29943,
      41.35534
    ]
  }
}