{
  "type": "Feature",
  "properties": {
    "name": "Beiriz de Baixo",
    "country": "PT",
    "subdivision": "17",
    "timezone": "Europe/Lisbon"
  },
  "geometry": {
    "type": "Point",
    "coordinates": [
      -8.72385,
      41.39727
    ]
  }
}