{
  "type": "Feature",
  "properties": {
    "name": "Estela",
    "country": "PT",
    "subdivision": "17",
    "timezone": "Europe/Lisbon"
  },
  "geometry": {
    "type": "Point",
    "coordinates": [
      -8.75166,
      41.44944
    ]
  }
}