{
  "type": "Feature",
  "properties": {
    "name": "Foz do Sousa",
    "country": "PT",
    "subdivision": "17",
    "timezone": "Europe/Lisbon"
  },
  "geometry": {
    "type": "Point",
    "coordinates": [
      -8.50184,
      41.09668
    ]
  }
}