{
  "type": "Feature",
  "properties": {
    "name": "Frazão",
    "country": "PT",
    "subdivision": "17",
    "timezone": "Europe/Lisbon"
  },
  "geometry": {
    "type": "Point",
    "coordinates": [
      -8.40014,
      41.25866
    ]
  }
}