{
  "type": "Feature",
  "properties": {
    "name": "Lordelo",
    "country": "PT",
    "subdivision": "17",
    "timezone": "Europe/Lisbon"
  },
  "geometry": {
    "type": "Point",
    "coordinates": [
      -8.40297,
      41.23451
    ]
  }
}