{
  "type": "Feature",
  "properties": {
    "name": "Negrelos",
    "country": "PT",
    "subdivision": "17",
    "timezone": "Europe/Lisbon"
  },
  "geometry": {
    "type": "Point",
    "coordinates": [
      -8.40145,
      41.34946
    ]
  }
}