{
  "type": "Feature",
  "properties": {
    "name": "Penafiel",
    "country": "PT",
    "subdivision": "17",
    "timezone": "Europe/Lisbon"
  },
  "geometry": {
    "type": "Point",
    "coordinates": [
      -8.28285,
      41.20835
    ]
  }
}