{
  "type": "Feature",
  "properties": {
    "name": "São Félix da Marinha",
    "country": "PT",
    "subdivision": "17",
    "timezone": "Europe/Lisbon"
  },
  "geometry": {
    "type": "Point",
    "coordinates": [
      -8.62259,
      41.03555
    ]
  }
}