{
  "type": "Feature",
  "properties": {
    "name": "São Pedro da Cova",
    "country": "PT",
    "subdivision": "17",
    "timezone": "Europe/Lisbon"
  },
  "geometry": {
    "type": "Point",
    "coordinates": [
      -8.50033,
      41.14331
    ]
  }
}