{
  "type": "Feature",
  "properties": {
    "name": "Valadares",
    "country": "PT",
    "subdivision": "17",
    "timezone": "Europe/Lisbon"
  },
  "geometry": {
    "type": "Point",
    "coordinates": [
      -7.9812,
      41.14737
    ]
  }
}