{
  "type": "Feature",
  "properties": {
    "name": "Valongo",
    "country": "PT",
    "subdivision": "17",
    "timezone": "Europe/Lisbon"
  },
  "geometry": {
    "type": "Point",
    "coordinates": [
      -8.49857,
      41.18883
    ]
  }
}