{
  "type": "Feature",
  "properties": {
    "name": "Vilar do Paraíso",
    "country": "PT",
    "subdivision": "17",
    "timezone": "Europe/Lisbon"
  },
  "geometry": {
    "type": "Point",
    "coordinates": [
      -8.6211,
      41.08974
    ]
  }
}