{
  "type": "Feature",
  "properties": {
    "name": "Sollefteå",
    "country": "SE",
    "subdivision": "24",
    "timezone": "Europe/Stockholm"
  },
  "geometry": {
    "type": "Point",
    "coordinates": [
      17.26667,
      63.16667
    ]
  }
}