{
  "type": "Feature",
  "properties": {
    "name": "Aígio",
    "country": "GR",
    "subdivision": "ESYE23",
    "timezone": "Europe/Athens"
  },
  "geometry": {
    "type": "Point",
    "coordinates": [
      22.08194,
      38.24861
    ]
  }
}