{
  "type": "Feature",
  "properties": {
    "name": "Amfilochía",
    "country": "GR",
    "subdivision": "ESYE23",
    "timezone": "Europe/Athens"
  },
  "geometry": {
    "type": "Point",
    "coordinates": [
      21.16639,
      38.85944
    ]
  }
}