{
  "type": "Feature",
  "properties": {
    "name": "Dhokímion",
    "country": "GR",
    "subdivision": "ESYE23",
    "timezone": "Europe/Athens"
  },
  "geometry": {
    "type": "Point",
    "coordinates": [
      21.38072,
      38.61352
    ]
  }
}