{
  "type": "Feature",
  "properties": {
    "name": "Fyteíes",
    "country": "GR",
    "subdivision": "ESYE23",
    "timezone": "Europe/Athens"
  },
  "geometry": {
    "type": "Point",
    "coordinates": [
      21.18467,
      38.69524
    ]
  }
}