{
  "type": "Feature",
  "properties": {
    "name": "Kamárai",
    "country": "GR",
    "subdivision": "ESYE23",
    "timezone": "Europe/Athens"
  },
  "geometry": {
    "type": "Point",
    "coordinates": [
      21.99892,
      38.29881
    ]
  }
}