{
  "type": "Feature",
  "properties": {
    "name": "Kandíla",
    "country": "GR",
    "subdivision": "ESYE23",
    "timezone": "Europe/Athens"
  },
  "geometry": {
    "type": "Point",
    "coordinates": [
      20.94749,
      38.70564
    ]
  }
}