{
  "type": "Feature",
  "properties": {
    "name": "Katochí",
    "country": "GR",
    "subdivision": "ESYE23",
    "timezone": "Europe/Athens"
  },
  "geometry": {
    "type": "Point",
    "coordinates": [
      21.25258,
      38.41237
    ]
  }
}