{
  "type": "Feature",
  "properties": {
    "name": "Kavásila",
    "country": "GR",
    "subdivision": "ESYE23",
    "timezone": "Europe/Athens"
  },
  "geometry": {
    "type": "Point",
    "coordinates": [
      21.26422,
      37.87581
    ]
  }
}