{
  "type": "Feature",
  "properties": {
    "name": "Kyllíni",
    "country": "GR",
    "subdivision": "ESYE23",
    "timezone": "Europe/Athens"
  },
  "geometry": {
    "type": "Point",
    "coordinates": [
      21.14503,
      37.93542
    ]
  }
}