{
  "type": "Feature",
  "properties": {
    "name": "Lechainá",
    "country": "GR",
    "subdivision": "ESYE23",
    "timezone": "Europe/Athens"
  },
  "geometry": {
    "type": "Point",
    "coordinates": [
      21.26667,
      37.93333
    ]
  }
}