{
  "type": "Feature",
  "properties": {
    "name": "Lepenoú",
    "country": "GR",
    "subdivision": "ESYE23",
    "timezone": "Europe/Athens"
  },
  "geometry": {
    "type": "Point",
    "coordinates": [
      21.2897,
      38.70839
    ]
  }
}