{
  "type": "Feature",
  "properties": {
    "name": "Manoláda",
    "country": "GR",
    "subdivision": "ESYE23",
    "timezone": "Europe/Athens"
  },
  "geometry": {
    "type": "Point",
    "coordinates": [
      21.34814,
      38.04708
    ]
  }
}