{
  "type": "Feature",
  "properties": {
    "name": "Mesolóngi",
    "country": "GR",
    "subdivision": "ESYE23",
    "timezone": "Europe/Athens"
  },
  "geometry": {
    "type": "Point",
    "coordinates": [
      21.43151,
      38.37138
    ]
  }
}