{
  "type": "Feature",
  "properties": {
    "name": "Paravóla",
    "country": "GR",
    "subdivision": "ESYE23",
    "timezone": "Europe/Athens"
  },
  "geometry": {
    "type": "Point",
    "coordinates": [
      21.52046,
      38.61472
    ]
  }
}