{
  "type": "Feature",
  "properties": {
    "name": "Valle de La Pascua",
    "country": "VE",
    "subdivision": "12",
    "timezone": "America/Caracas"
  },
  "geometry": {
    "type": "Point",
    "coordinates": [
      -66.00734,
      9.21554
    ]
  }
}