{
  "type": "Feature",
  "properties": {
    "name": "FarasÄn",
    "country": "SA",
    "subdivision": "17",
    "timezone": "Asia/Riyadh"
  },
  "geometry": {
    "type": "Point",
    "coordinates": [
      42.11833,
      16.70222
    ]
  }
}