{
  "type": "Feature",
  "properties": {
    "name": "Şāmitah",
    "country": "SA",
    "subdivision": "17",
    "timezone": "Asia/Riyadh"
  },
  "geometry": {
    "type": "Point",
    "coordinates": [
      42.94435,
      16.59601
    ]
  }
}