{
  "type": "Feature",
  "properties": {
    "name": "Iggesund",
    "country": "SE",
    "subdivision": "03",
    "timezone": "Europe/Stockholm"
  },
  "geometry": {
    "type": "Point",
    "coordinates": [
      17.07477,
      61.64219
    ]
  }
}