{
  "type": "Feature",
  "properties": {
    "name": "Järvsö",
    "country": "SE",
    "subdivision": "03",
    "timezone": "Europe/Stockholm"
  },
  "geometry": {
    "type": "Point",
    "coordinates": [
      16.16667,
      61.71667
    ]
  }
}