{
  "type": "Feature",
  "properties": {
    "name": "Nyūzen",
    "country": "JP",
    "subdivision": "42",
    "timezone": "Asia/Tokyo"
  },
  "geometry": {
    "type": "Point",
    "coordinates": [
      137.50059,
      36.93744
    ]
  }
}