{
  "type": "Feature",
  "properties": {
    "name": "Yatsuomachi-higashikumisaka",
    "country": "JP",
    "subdivision": "42",
    "timezone": "Asia/Tokyo"
  },
  "geometry": {
    "type": "Point",
    "coordinates": [
      137.13333,
      36.56667
    ]
  }
}