{
  "type": "Feature",
  "properties": {
    "name": "Dame-Marie",
    "country": "HT",
    "subdivision": "14",
    "timezone": "America/Port-au-Prince"
  },
  "geometry": {
    "type": "Point",
    "coordinates": [
      -74.42167,
      18.56107
    ]
  }
}