{
  "type": "Feature",
  "properties": {
    "name": "Petite Rivière de Nippes",
    "country": "HT",
    "subdivision": "14",
    "timezone": "America/Port-au-Prince"
  },
  "geometry": {
    "type": "Point",
    "coordinates": [
      -73.23495,
      18.47611
    ]
  }
}