{
  "type": "Feature",
  "properties": {
    "name": "Bardaskan",
    "country": "IR",
    "subdivision": "42",
    "timezone": "Asia/Tehran"
  },
  "geometry": {
    "type": "Point",
    "coordinates": [
      57.97075,
      35.26218
    ]
  }
}