{
  "type": "Feature",
  "properties": {
    "name": "Capira",
    "country": "PA",
    "subdivision": "13",
    "timezone": "America/Panama"
  },
  "geometry": {
    "type": "Point",
    "coordinates": [
      -79.87996,
      8.75636
    ]
  }
}