{
  "type": "Feature",
  "properties": {
    "name": "Cerro Cama",
    "country": "PA",
    "subdivision": "13",
    "timezone": "America/Panama"
  },
  "geometry": {
    "type": "Point",
    "coordinates": [
      -79.90744,
      9.02802
    ]
  }
}