{
  "type": "Feature",
  "properties": {
    "name": "El Espino",
    "country": "PA",
    "subdivision": "13",
    "timezone": "America/Panama"
  },
  "geometry": {
    "type": "Point",
    "coordinates": [
      -79.84515,
      8.84843
    ]
  }
}