{
  "type": "Feature",
  "properties": {
    "name": "Guadalupe",
    "country": "PA",
    "subdivision": "13",
    "timezone": "America/Panama"
  },
  "geometry": {
    "type": "Point",
    "coordinates": [
      -79.81184,
      8.86064
    ]
  }
}