{
  "type": "Feature",
  "properties": {
    "name": "La Chorrera",
    "country": "PA",
    "subdivision": "13",
    "timezone": "America/Panama"
  },
  "geometry": {
    "type": "Point",
    "coordinates": [
      -79.78333,
      8.88028
    ]
  }
}