{
  "type": "Feature",
  "properties": {
    "name": "Potrero Grande",
    "country": "PA",
    "subdivision": "13",
    "timezone": "America/Panama"
  },
  "geometry": {
    "type": "Point",
    "coordinates": [
      -79.83006,
      8.88305
    ]
  }
}