{
  "type": "Feature",
  "properties": {
    "name": "San Vicente de Bique",
    "country": "PA",
    "subdivision": "13",
    "timezone": "America/Panama"
  },
  "geometry": {
    "type": "Point",
    "coordinates": [
      -79.67227,
      8.91605
    ]
  }
}