{
  "type": "Feature",
  "properties": {
    "name": "Adamów",
    "country": "PL",
    "subdivision": "75",
    "timezone": "Europe/Warsaw"
  },
  "geometry": {
    "type": "Point",
    "coordinates": [
      22.26414,
      51.74335
    ]
  }
}