{
  "type": "Feature",
  "properties": {
    "name": "Annopol",
    "country": "PL",
    "subdivision": "75",
    "timezone": "Europe/Warsaw"
  },
  "geometry": {
    "type": "Point",
    "coordinates": [
      21.85678,
      50.88551
    ]
  }
}