{
  "type": "Feature",
  "properties": {
    "name": "Bełżec",
    "country": "PL",
    "subdivision": "75",
    "timezone": "Europe/Warsaw"
  },
  "geometry": {
    "type": "Point",
    "coordinates": [
      23.43839,
      50.38453
    ]
  }
}