{
  "type": "Feature",
  "properties": {
    "name": "Chrzanów",
    "country": "PL",
    "subdivision": "75",
    "timezone": "Europe/Warsaw"
  },
  "geometry": {
    "type": "Point",
    "coordinates": [
      22.60351,
      50.77256
    ]
  }
}