{
  "type": "Feature",
  "properties": {
    "name": "Frampol",
    "country": "PL",
    "subdivision": "75",
    "timezone": "Europe/Warsaw"
  },
  "geometry": {
    "type": "Point",
    "coordinates": [
      22.67061,
      50.67159
    ]
  }
}