{
  "type": "Feature",
  "properties": {
    "name": "Godziszów Pierwszy",
    "country": "PL",
    "subdivision": "75",
    "timezone": "Europe/Warsaw"
  },
  "geometry": {
    "type": "Point",
    "coordinates": [
      22.48386,
      50.75753
    ]
  }
}