{
  "type": "Feature",
  "properties": {
    "name": "Godziszów",
    "country": "PL",
    "subdivision": "75",
    "timezone": "Europe/Warsaw"
  },
  "geometry": {
    "type": "Point",
    "coordinates": [
      22.49794,
      50.74889
    ]
  }
}