{
  "type": "Feature",
  "properties": {
    "name": "Janów Podlaski",
    "country": "PL",
    "subdivision": "75",
    "timezone": "Europe/Warsaw"
  },
  "geometry": {
    "type": "Point",
    "coordinates": [
      23.21218,
      52.19398
    ]
  }
}