{
  "type": "Feature",
  "properties": {
    "name": "Kazimierz Dolny",
    "country": "PL",
    "subdivision": "75",
    "timezone": "Europe/Warsaw"
  },
  "geometry": {
    "type": "Point",
    "coordinates": [
      21.95502,
      51.31911
    ]
  }
}