{
  "type": "Feature",
  "properties": {
    "name": "Modliborzyce",
    "country": "PL",
    "subdivision": "75",
    "timezone": "Europe/Warsaw"
  },
  "geometry": {
    "type": "Point",
    "coordinates": [
      22.32945,
      50.75416
    ]
  }
}