{
  "type": "Feature",
  "properties": {
    "name": "Piaski",
    "country": "PL",
    "subdivision": "75",
    "timezone": "Europe/Warsaw"
  },
  "geometry": {
    "type": "Point",
    "coordinates": [
      22.84856,
      51.13892
    ]
  }
}