{
  "type": "Feature",
  "properties": {
    "name": "Rejowiec Fabryczny",
    "country": "PL",
    "subdivision": "75",
    "timezone": "Europe/Warsaw"
  },
  "geometry": {
    "type": "Point",
    "coordinates": [
      23.24724,
      51.11414
    ]
  }
}