{
  "type": "Feature",
  "properties": {
    "name": "Rogóźno",
    "country": "PL",
    "subdivision": "75",
    "timezone": "Europe/Warsaw"
  },
  "geometry": {
    "type": "Point",
    "coordinates": [
      23.39041,
      50.46417
    ]
  }
}