{
  "type": "Feature",
  "properties": {
    "name": "Ruda-Huta",
    "country": "PL",
    "subdivision": "75",
    "timezone": "Europe/Warsaw"
  },
  "geometry": {
    "type": "Point",
    "coordinates": [
      23.59486,
      51.23666
    ]
  }
}