{
  "type": "Feature",
  "properties": {
    "name": "Ryki",
    "country": "PL",
    "subdivision": "75",
    "timezone": "Europe/Warsaw"
  },
  "geometry": {
    "type": "Point",
    "coordinates": [
      21.93274,
      51.62574
    ]
  }
}