{
  "type": "Feature",
  "properties": {
    "name": "Sawin",
    "country": "PL",
    "subdivision": "75",
    "timezone": "Europe/Warsaw"
  },
  "geometry": {
    "type": "Point",
    "coordinates": [
      23.43375,
      51.27443
    ]
  }
}