{
  "type": "Feature",
  "properties": {
    "name": "Serokomla",
    "country": "PL",
    "subdivision": "75",
    "timezone": "Europe/Warsaw"
  },
  "geometry": {
    "type": "Point",
    "coordinates": [
      22.33237,
      51.7007
    ]
  }
}