{
  "type": "Feature",
  "properties": {
    "name": "Wisznice",
    "country": "PL",
    "subdivision": "75",
    "timezone": "Europe/Warsaw"
  },
  "geometry": {
    "type": "Point",
    "coordinates": [
      23.20836,
      51.78924
    ]
  }
}