{
  "type": "Feature",
  "properties": {
    "name": "Fengxiang",
    "country": "CN",
    "subdivision": "08",
    "timezone": "Asia/Shanghai"
  },
  "geometry": {
    "type": "Point",
    "coordinates": [
      130.82306,
      47.57549
    ]
  }
}