{
  "type": "Feature",
  "properties": {
    "name": "Langxiang",
    "country": "CN",
    "subdivision": "08",
    "timezone": "Asia/Shanghai"
  },
  "geometry": {
    "type": "Point",
    "coordinates": [
      128.86849,
      46.94985
    ]
  }
}