{
  "type": "Feature",
  "properties": {
    "name": "Nianzishan",
    "country": "CN",
    "subdivision": "08",
    "timezone": "Asia/Shanghai"
  },
  "geometry": {
    "type": "Point",
    "coordinates": [
      122.88333,
      47.51667
    ]
  }
}