{
  "type": "Feature",
  "properties": {
    "name": "Shuangcheng",
    "country": "CN",
    "subdivision": "08",
    "timezone": "Asia/Shanghai"
  },
  "geometry": {
    "type": "Point",
    "coordinates": [
      126.28333,
      45.35
    ]
  }
}