{
  "type": "Feature",
  "properties": {
    "name": "Suifenhe",
    "country": "CN",
    "subdivision": "08",
    "timezone": "Asia/Shanghai"
  },
  "geometry": {
    "type": "Point",
    "coordinates": [
      131.14775,
      44.39982
    ]
  }
}