{
  "type": "Feature",
  "properties": {
    "name": "Wangkui",
    "country": "CN",
    "subdivision": "08",
    "timezone": "Asia/Shanghai"
  },
  "geometry": {
    "type": "Point",
    "coordinates": [
      126.47768,
      46.83283
    ]
  }
}