{
  "type": "Feature",
  "properties": {
    "name": "Xinqing",
    "country": "CN",
    "subdivision": "08",
    "timezone": "Asia/Shanghai"
  },
  "geometry": {
    "type": "Point",
    "coordinates": [
      129.52337,
      48.28701
    ]
  }
}