{
  "type": "Feature",
  "properties": {
    "name": "Nha Trang",
    "country": "VN",
    "subdivision": "54",
    "timezone": "Asia/Ho_Chi_Minh"
  },
  "geometry": {
    "type": "Point",
    "coordinates": [
      109.19432,
      12.24507
    ]
  }
}