{
  "type": "Feature",
  "properties": {
    "name": "Ninh Hòa",
    "country": "VN",
    "subdivision": "54",
    "timezone": "Asia/Ho_Chi_Minh"
  },
  "geometry": {
    "type": "Point",
    "coordinates": [
      109.12495,
      12.49187
    ]
  }
}