{
  "type": "Feature",
  "properties": {
    "name": "Garoowe",
    "country": "SO",
    "subdivision": "18",
    "timezone": "Africa/Mogadishu"
  },
  "geometry": {
    "type": "Point",
    "coordinates": [
      48.48284,
      8.40207
    ]
  }
}