{
  "type": "Feature",
  "properties": {
    "name": "Ágioi Theódoroi",
    "country": "GR",
    "subdivision": "ESYE25",
    "timezone": "Europe/Athens"
  },
  "geometry": {
    "type": "Point",
    "coordinates": [
      23.14221,
      37.92736
    ]
  }
}