{
  "type": "Feature",
  "properties": {
    "name": "Dídyma",
    "country": "GR",
    "subdivision": "ESYE25",
    "timezone": "Europe/Athens"
  },
  "geometry": {
    "type": "Point",
    "coordinates": [
      23.17183,
      37.4625
    ]
  }
}