{
  "type": "Feature",
  "properties": {
    "name": "Ermióni",
    "country": "GR",
    "subdivision": "ESYE25",
    "timezone": "Europe/Athens"
  },
  "geometry": {
    "type": "Point",
    "coordinates": [
      23.24686,
      37.38492
    ]
  }
}