{
  "type": "Feature",
  "properties": {
    "name": "Kopanáki",
    "country": "GR",
    "subdivision": "ESYE25",
    "timezone": "Europe/Athens"
  },
  "geometry": {
    "type": "Point",
    "coordinates": [
      21.81854,
      37.28913
    ]
  }
}