{
  "type": "Feature",
  "properties": {
    "name": "Loutrá Oraías Elénis",
    "country": "GR",
    "subdivision": "ESYE25",
    "timezone": "Europe/Athens"
  },
  "geometry": {
    "type": "Point",
    "coordinates": [
      22.99614,
      37.86466
    ]
  }
}