{
  "type": "Feature",
  "properties": {
    "name": "Megalópoli",
    "country": "GR",
    "subdivision": "ESYE25",
    "timezone": "Europe/Athens"
  },
  "geometry": {
    "type": "Point",
    "coordinates": [
      22.14222,
      37.40111
    ]
  }
}