{
  "type": "Feature",
  "properties": {
    "name": "Messíni",
    "country": "GR",
    "subdivision": "ESYE25",
    "timezone": "Europe/Athens"
  },
  "geometry": {
    "type": "Point",
    "coordinates": [
      22.00778,
      37.05111
    ]
  }
}