{
  "type": "Feature",
  "properties": {
    "name": "Néa Tírins",
    "country": "GR",
    "subdivision": "ESYE25",
    "timezone": "Europe/Athens"
  },
  "geometry": {
    "type": "Point",
    "coordinates": [
      22.81996,
      37.60793
    ]
  }
}