{
  "type": "Feature",
  "properties": {
    "name": "Sperchógeia",
    "country": "GR",
    "subdivision": "ESYE25",
    "timezone": "Europe/Athens"
  },
  "geometry": {
    "type": "Point",
    "coordinates": [
      22.06248,
      37.07405
    ]
  }
}