{
  "type": "Feature",
  "properties": {
    "name": "Carouge",
    "country": "CH",
    "subdivision": "GE",
    "timezone": "Europe/Zurich"
  },
  "geometry": {
    "type": "Point",
    "coordinates": [
      6.13921,
      46.18096
    ]
  }
}