{
  "type": "Feature",
  "properties": {
    "name": "Lancy",
    "country": "CH",
    "subdivision": "GE",
    "timezone": "Europe/Zurich"
  },
  "geometry": {
    "type": "Point",
    "coordinates": [
      6.11441,
      46.18981
    ]
  }
}