{
  "type": "Feature",
  "properties": {
    "name": "Vandœuvres",
    "country": "CH",
    "subdivision": "GE",
    "timezone": "Europe/Zurich"
  },
  "geometry": {
    "type": "Point",
    "coordinates": [
      6.20285,
      46.22179
    ]
  }
}