{
  "type": "Feature",
  "properties": {
    "name": "Ilo",
    "country": "PE",
    "subdivision": "18",
    "timezone": "America/Lima"
  },
  "geometry": {
    "type": "Point",
    "coordinates": [
      -71.34108,
      -17.63185
    ]
  }
}