{
  "type": "Feature",
  "properties": {
    "name": "Arroyo",
    "country": "PR",
    "subdivision": "015",
    "timezone": "America/Puerto_Rico"
  },
  "geometry": {
    "type": "Point",
    "coordinates": [
      -66.06128,
      17.9658
    ]
  }
}