{
  "type": "Feature",
  "properties": {
    "name": "Virbalis",
    "country": "LT",
    "subdivision": "59",
    "timezone": "Europe/Vilnius"
  },
  "geometry": {
    "type": "Point",
    "coordinates": [
      22.82272,
      54.62858
    ]
  }
}