{
  "type": "Feature",
  "properties": {
    "name": "Avşar",
    "country": "AZ",
    "subdivision": "02",
    "timezone": "Asia/Baku"
  },
  "geometry": {
    "type": "Point",
    "coordinates": [
      47.42389,
      39.97389
    ]
  }
}