{
  "type": "Feature",
  "properties": {
    "name": "Damaturu",
    "country": "NG",
    "subdivision": "44",
    "timezone": "Africa/Lagos"
  },
  "geometry": {
    "type": "Point",
    "coordinates": [
      11.96083,
      11.74697
    ]
  }
}