{
  "type": "Feature",
  "properties": {
    "name": "Machina",
    "country": "NG",
    "subdivision": "44",
    "timezone": "Africa/Lagos"
  },
  "geometry": {
    "type": "Point",
    "coordinates": [
      10.04924,
      13.13639
    ]
  }
}