{
  "type": "Feature",
  "properties": {
    "name": "Potiskum",
    "country": "NG",
    "subdivision": "44",
    "timezone": "Africa/Lagos"
  },
  "geometry": {
    "type": "Point",
    "coordinates": [
      11.08108,
      11.71391
    ]
  }
}