{
  "type": "Feature",
  "properties": {
    "name": "Binagadi",
    "country": "AZ",
    "subdivision": "09",
    "timezone": "Asia/Baku"
  },
  "geometry": {
    "type": "Point",
    "coordinates": [
      49.82783,
      40.46602
    ]
  }
}