{
  "type": "Feature",
  "properties": {
    "name": "Maştağa",
    "country": "AZ",
    "subdivision": "09",
    "timezone": "Asia/Baku"
  },
  "geometry": {
    "type": "Point",
    "coordinates": [
      50.00616,
      40.52983
    ]
  }
}