{
  "type": "Feature",
  "properties": {
    "name": "Pirallahı",
    "country": "AZ",
    "subdivision": "09",
    "timezone": "Asia/Baku"
  },
  "geometry": {
    "type": "Point",
    "coordinates": [
      50.32476,
      40.47013
    ]
  }
}