{
  "type": "Feature",
  "properties": {
    "name": "Qala",
    "country": "AZ",
    "subdivision": "09",
    "timezone": "Asia/Baku"
  },
  "geometry": {
    "type": "Point",
    "coordinates": [
      50.16759,
      40.44256
    ]
  }
}