{
  "type": "Feature",
  "properties": {
    "name": "Blizne",
    "country": "PL",
    "subdivision": "80",
    "timezone": "Europe/Warsaw"
  },
  "geometry": {
    "type": "Point",
    "coordinates": [
      21.97351,
      49.75332
    ]
  }
}