{
  "type": "Feature",
  "properties": {
    "name": "Brzyska",
    "country": "PL",
    "subdivision": "80",
    "timezone": "Europe/Warsaw"
  },
  "geometry": {
    "type": "Point",
    "coordinates": [
      21.39004,
      49.82226
    ]
  }
}