{
  "type": "Feature",
  "properties": {
    "name": "Chmielnik",
    "country": "PL",
    "subdivision": "80",
    "timezone": "Europe/Warsaw"
  },
  "geometry": {
    "type": "Point",
    "coordinates": [
      22.14535,
      49.97386
    ]
  }
}