{
  "type": "Feature",
  "properties": {
    "name": "Chwałowice",
    "country": "PL",
    "subdivision": "80",
    "timezone": "Europe/Warsaw"
  },
  "geometry": {
    "type": "Point",
    "coordinates": [
      21.88683,
      50.76665
    ]
  }
}