{
  "type": "Feature",
  "properties": {
    "name": "Czaszyn",
    "country": "PL",
    "subdivision": "80",
    "timezone": "Europe/Warsaw"
  },
  "geometry": {
    "type": "Point",
    "coordinates": [
      22.2165,
      49.44854
    ]
  }
}