{
  "type": "Feature",
  "properties": {
    "name": "Dubiecko",
    "country": "PL",
    "subdivision": "80",
    "timezone": "Europe/Warsaw"
  },
  "geometry": {
    "type": "Point",
    "coordinates": [
      22.39117,
      49.82608
    ]
  }
}