{
  "type": "Feature",
  "properties": {
    "name": "Dukla",
    "country": "PL",
    "subdivision": "80",
    "timezone": "Europe/Warsaw"
  },
  "geometry": {
    "type": "Point",
    "coordinates": [
      21.68317,
      49.55554
    ]
  }
}