{
  "type": "Feature",
  "properties": {
    "name": "Głogów Małopolski",
    "country": "PL",
    "subdivision": "80",
    "timezone": "Europe/Warsaw"
  },
  "geometry": {
    "type": "Point",
    "coordinates": [
      21.96287,
      50.15122
    ]
  }
}