{
  "type": "Feature",
  "properties": {
    "name": "Głuchów",
    "country": "PL",
    "subdivision": "80",
    "timezone": "Europe/Warsaw"
  },
  "geometry": {
    "type": "Point",
    "coordinates": [
      22.27135,
      50.08171
    ]
  }
}