{
  "type": "Feature",
  "properties": {
    "name": "Handzlówka",
    "country": "PL",
    "subdivision": "80",
    "timezone": "Europe/Warsaw"
  },
  "geometry": {
    "type": "Point",
    "coordinates": [
      22.22311,
      49.99527
    ]
  }
}