{
  "type": "Feature",
  "properties": {
    "name": "Horyniec-Zdrój",
    "country": "PL",
    "subdivision": "80",
    "timezone": "Europe/Warsaw"
  },
  "geometry": {
    "type": "Point",
    "coordinates": [
      23.36277,
      50.19152
    ]
  }
}