{
  "type": "Feature",
  "properties": {
    "name": "Husów",
    "country": "PL",
    "subdivision": "80",
    "timezone": "Europe/Warsaw"
  },
  "geometry": {
    "type": "Point",
    "coordinates": [
      22.28645,
      49.97971
    ]
  }
}