{
  "type": "Feature",
  "properties": {
    "name": "Jabłonka",
    "country": "PL",
    "subdivision": "80",
    "timezone": "Europe/Warsaw"
  },
  "geometry": {
    "type": "Point",
    "coordinates": [
      22.11565,
      49.69417
    ]
  }
}