{
  "type": "Feature",
  "properties": {
    "name": "Jabłonica Polska",
    "country": "PL",
    "subdivision": "80",
    "timezone": "Europe/Warsaw"
  },
  "geometry": {
    "type": "Point",
    "coordinates": [
      21.89961,
      49.69784
    ]
  }
}