{
  "type": "Feature",
  "properties": {
    "name": "Jarosław",
    "country": "PL",
    "subdivision": "80",
    "timezone": "Europe/Warsaw"
  },
  "geometry": {
    "type": "Point",
    "coordinates": [
      22.67776,
      50.01623
    ]
  }
}