{
  "type": "Feature",
  "properties": {
    "name": "Jodłowa",
    "country": "PL",
    "subdivision": "80",
    "timezone": "Europe/Warsaw"
  },
  "geometry": {
    "type": "Point",
    "coordinates": [
      21.27897,
      49.87229
    ]
  }
}