{
  "type": "Feature",
  "properties": {
    "name": "Kołaczyce",
    "country": "PL",
    "subdivision": "80",
    "timezone": "Europe/Warsaw"
  },
  "geometry": {
    "type": "Point",
    "coordinates": [
      21.43407,
      49.80743
    ]
  }
}