{
  "type": "Feature",
  "properties": {
    "name": "Kraczkowa",
    "country": "PL",
    "subdivision": "80",
    "timezone": "Europe/Warsaw"
  },
  "geometry": {
    "type": "Point",
    "coordinates": [
      22.16801,
      50.03796
    ]
  }
}