{
  "type": "Feature",
  "properties": {
    "name": "Lesko",
    "country": "PL",
    "subdivision": "80",
    "timezone": "Europe/Warsaw"
  },
  "geometry": {
    "type": "Point",
    "coordinates": [
      22.33042,
      49.4701
    ]
  }
}