{
  "type": "Feature",
  "properties": {
    "name": "Lubaczów",
    "country": "PL",
    "subdivision": "80",
    "timezone": "Europe/Warsaw"
  },
  "geometry": {
    "type": "Point",
    "coordinates": [
      23.12339,
      50.157
    ]
  }
}