{
  "type": "Feature",
  "properties": {
    "name": "Lubenia",
    "country": "PL",
    "subdivision": "80",
    "timezone": "Europe/Warsaw"
  },
  "geometry": {
    "type": "Point",
    "coordinates": [
      21.92665,
      49.93078
    ]
  }
}