{
  "type": "Feature",
  "properties": {
    "name": "Miejsce Piastowe",
    "country": "PL",
    "subdivision": "80",
    "timezone": "Europe/Warsaw"
  },
  "geometry": {
    "type": "Point",
    "coordinates": [
      21.78735,
      49.6344
    ]
  }
}