{
  "type": "Feature",
  "properties": {
    "name": "Nisko",
    "country": "PL",
    "subdivision": "80",
    "timezone": "Europe/Warsaw"
  },
  "geometry": {
    "type": "Point",
    "coordinates": [
      22.13968,
      50.51987
    ]
  }
}