{
  "type": "Feature",
  "properties": {
    "name": "Nowa Dęba",
    "country": "PL",
    "subdivision": "80",
    "timezone": "Europe/Warsaw"
  },
  "geometry": {
    "type": "Point",
    "coordinates": [
      21.75078,
      50.42974
    ]
  }
}