{
  "type": "Feature",
  "properties": {
    "name": "Olszanica",
    "country": "PL",
    "subdivision": "80",
    "timezone": "Europe/Warsaw"
  },
  "geometry": {
    "type": "Point",
    "coordinates": [
      22.44382,
      49.47741
    ]
  }
}