{
  "type": "Feature",
  "properties": {
    "name": "Orzechówka",
    "country": "PL",
    "subdivision": "80",
    "timezone": "Europe/Warsaw"
  },
  "geometry": {
    "type": "Point",
    "coordinates": [
      21.94519,
      49.7308
    ]
  }
}