{
  "type": "Feature",
  "properties": {
    "name": "Sokolniki",
    "country": "PL",
    "subdivision": "80",
    "timezone": "Europe/Warsaw"
  },
  "geometry": {
    "type": "Point",
    "coordinates": [
      21.80649,
      50.63803
    ]
  }
}