{
  "type": "Feature",
  "properties": {
    "name": "Stare Miasto",
    "country": "PL",
    "subdivision": "80",
    "timezone": "Europe/Warsaw"
  },
  "geometry": {
    "type": "Point",
    "coordinates": [
      22.42928,
      50.28879
    ]
  }
}