{
  "type": "Feature",
  "properties": {
    "name": "Straszydle",
    "country": "PL",
    "subdivision": "80",
    "timezone": "Europe/Warsaw"
  },
  "geometry": {
    "type": "Point",
    "coordinates": [
      21.98124,
      49.90038
    ]
  }
}