{
  "type": "Feature",
  "properties": {
    "name": "Tarnobrzeg",
    "country": "PL",
    "subdivision": "80",
    "timezone": "Europe/Warsaw"
  },
  "geometry": {
    "type": "Point",
    "coordinates": [
      21.67937,
      50.57304
    ]
  }
}