{
  "type": "Feature",
  "properties": {
    "name": "Ustrzyki Dolne",
    "country": "PL",
    "subdivision": "80",
    "timezone": "Europe/Warsaw"
  },
  "geometry": {
    "type": "Point",
    "coordinates": [
      22.59381,
      49.4304
    ]
  }
}