{
  "type": "Feature",
  "properties": {
    "name": "Wola Żarczycka",
    "country": "PL",
    "subdivision": "80",
    "timezone": "Europe/Warsaw"
  },
  "geometry": {
    "type": "Point",
    "coordinates": [
      22.25023,
      50.2912
    ]
  }
}