{
  "type": "Feature",
  "properties": {
    "name": "Wólka Podleśna",
    "country": "PL",
    "subdivision": "80",
    "timezone": "Europe/Warsaw"
  },
  "geometry": {
    "type": "Point",
    "coordinates": [
      22.11213,
      50.11785
    ]
  }
}