{
  "type": "Feature",
  "properties": {
    "name": "Zarzecze",
    "country": "PL",
    "subdivision": "80",
    "timezone": "Europe/Warsaw"
  },
  "geometry": {
    "type": "Point",
    "coordinates": [
      22.19522,
      50.52767
    ]
  }
}