{
  "type": "Feature",
  "properties": {
    "name": "Paya",
    "country": "DO",
    "subdivision": "35",
    "timezone": "America/Santo_Domingo"
  },
  "geometry": {
    "type": "Point",
    "coordinates": [
      -70.2956,
      18.26196
    ]
  }
}