{
  "type": "Feature",
  "properties": {
    "name": "Tuzi",
    "country": "ME",
    "subdivision": "24",
    "timezone": "Europe/Podgorica"
  },
  "geometry": {
    "type": "Point",
    "coordinates": [
      19.33139,
      42.36556
    ]
  }
}