{
  "type": "Feature",
  "properties": {
    "name": "Arques-la-Bataille",
    "country": "FR",
    "subdivision": "28",
    "timezone": "Europe/Paris"
  },
  "geometry": {
    "type": "Point",
    "coordinates": [
      1.12875,
      49.88122
    ]
  }
}