{
  "type": "Feature",
  "properties": {
    "name": "Auffay",
    "country": "FR",
    "subdivision": "28",
    "timezone": "Europe/Paris"
  },
  "geometry": {
    "type": "Point",
    "coordinates": [
      1.09911,
      49.71881
    ]
  }
}