{
  "type": "Feature",
  "properties": {
    "name": "Aunay-sur-Odon",
    "country": "FR",
    "subdivision": "28",
    "timezone": "Europe/Paris"
  },
  "geometry": {
    "type": "Point",
    "coordinates": [
      -0.63238,
      49.02012
    ]
  }
}