{
  "type": "Feature",
  "properties": {
    "name": "Aviron",
    "country": "FR",
    "subdivision": "28",
    "timezone": "Europe/Paris"
  },
  "geometry": {
    "type": "Point",
    "coordinates": [
      1.11667,
      49.05
    ]
  }
}