{
  "type": "Feature",
  "properties": {
    "name": "Avranches",
    "country": "FR",
    "subdivision": "28",
    "timezone": "Europe/Paris"
  },
  "geometry": {
    "type": "Point",
    "coordinates": [
      -1.35686,
      48.68436
    ]
  }
}