{
  "type": "Feature",
  "properties": {
    "name": "Belbeuf",
    "country": "FR",
    "subdivision": "28",
    "timezone": "Europe/Paris"
  },
  "geometry": {
    "type": "Point",
    "coordinates": [
      1.14245,
      49.38766
    ]
  }
}