{
  "type": "Feature",
  "properties": {
    "name": "Bellengreville",
    "country": "FR",
    "subdivision": "28",
    "timezone": "Europe/Paris"
  },
  "geometry": {
    "type": "Point",
    "coordinates": [
      -0.20961,
      49.12425
    ]
  }
}