{
  "type": "Feature",
  "properties": {
    "name": "Blangy-sur-Bresle",
    "country": "FR",
    "subdivision": "28",
    "timezone": "Europe/Paris"
  },
  "geometry": {
    "type": "Point",
    "coordinates": [
      1.62514,
      49.93211
    ]
  }
}