{
  "type": "Feature",
  "properties": {
    "name": "Boos",
    "country": "FR",
    "subdivision": "28",
    "timezone": "Europe/Paris"
  },
  "geometry": {
    "type": "Point",
    "coordinates": [
      1.20348,
      49.38849
    ]
  }
}