{
  "type": "Feature",
  "properties": {
    "name": "Bourth",
    "country": "FR",
    "subdivision": "28",
    "timezone": "Europe/Paris"
  },
  "geometry": {
    "type": "Point",
    "coordinates": [
      0.80911,
      48.76846
    ]
  }
}