{
  "type": "Feature",
  "properties": {
    "name": "Bretteville",
    "country": "FR",
    "subdivision": "28",
    "timezone": "Europe/Paris"
  },
  "geometry": {
    "type": "Point",
    "coordinates": [
      -1.52884,
      49.6544
    ]
  }
}