{
  "type": "Feature",
  "properties": {
    "name": "Buchy",
    "country": "FR",
    "subdivision": "28",
    "timezone": "Europe/Paris"
  },
  "geometry": {
    "type": "Point",
    "coordinates": [
      1.35852,
      49.58513
    ]
  }
}