{
  "type": "Feature",
  "properties": {
    "name": "Canon",
    "country": "FR",
    "subdivision": "28",
    "timezone": "Europe/Paris"
  },
  "geometry": {
    "type": "Point",
    "coordinates": [
      -0.09219,
      49.0738
    ]
  }
}