{
  "type": "Feature",
  "properties": {
    "name": "Canteleu",
    "country": "FR",
    "subdivision": "28",
    "timezone": "Europe/Paris"
  },
  "geometry": {
    "type": "Point",
    "coordinates": [
      1.02459,
      49.44065
    ]
  }
}