{
  "type": "Feature",
  "properties": {
    "name": "Cérences",
    "country": "FR",
    "subdivision": "28",
    "timezone": "Europe/Paris"
  },
  "geometry": {
    "type": "Point",
    "coordinates": [
      -1.4347,
      48.91667
    ]
  }
}