{
  "type": "Feature",
  "properties": {
    "name": "Champsecret",
    "country": "FR",
    "subdivision": "28",
    "timezone": "Europe/Paris"
  },
  "geometry": {
    "type": "Point",
    "coordinates": [
      -0.55058,
      48.60925
    ]
  }
}