{
  "type": "Feature",
  "properties": {
    "name": "Cormeilles",
    "country": "FR",
    "subdivision": "28",
    "timezone": "Europe/Paris"
  },
  "geometry": {
    "type": "Point",
    "coordinates": [
      0.37654,
      49.24803
    ]
  }
}