{
  "type": "Feature",
  "properties": {
    "name": "Coutances",
    "country": "FR",
    "subdivision": "28",
    "timezone": "Europe/Paris"
  },
  "geometry": {
    "type": "Point",
    "coordinates": [
      -1.44518,
      49.04541
    ]
  }
}