{
  "type": "Feature",
  "properties": {
    "name": "Déville-lès-Rouen",
    "country": "FR",
    "subdivision": "28",
    "timezone": "Europe/Paris"
  },
  "geometry": {
    "type": "Point",
    "coordinates": [
      1.05214,
      49.46942
    ]
  }
}