{
  "type": "Feature",
  "properties": {
    "name": "Donville-les-Bains",
    "country": "FR",
    "subdivision": "28",
    "timezone": "Europe/Paris"
  },
  "geometry": {
    "type": "Point",
    "coordinates": [
      -1.58315,
      48.84608
    ]
  }
}