{
  "type": "Feature",
  "properties": {
    "name": "Dozulé",
    "country": "FR",
    "subdivision": "28",
    "timezone": "Europe/Paris"
  },
  "geometry": {
    "type": "Point",
    "coordinates": [
      -0.04454,
      49.23132
    ]
  }
}