{
  "type": "Feature",
  "properties": {
    "name": "Eslettes",
    "country": "FR",
    "subdivision": "28",
    "timezone": "Europe/Paris"
  },
  "geometry": {
    "type": "Point",
    "coordinates": [
      1.05515,
      49.5482
    ]
  }
}