{
  "type": "Feature",
  "properties": {
    "name": "Falaise",
    "country": "FR",
    "subdivision": "28",
    "timezone": "Europe/Paris"
  },
  "geometry": {
    "type": "Point",
    "coordinates": [
      -0.19527,
      48.89217
    ]
  }
}