{
  "type": "Feature",
  "properties": {
    "name": "Fauville-en-Caux",
    "country": "FR",
    "subdivision": "28",
    "timezone": "Europe/Paris"
  },
  "geometry": {
    "type": "Point",
    "coordinates": [
      0.59197,
      49.65257
    ]
  }
}