{
  "type": "Feature",
  "properties": {
    "name": "Fontenay-le-Marmion",
    "country": "FR",
    "subdivision": "28",
    "timezone": "Europe/Paris"
  },
  "geometry": {
    "type": "Point",
    "coordinates": [
      -0.35294,
      49.09346
    ]
  }
}