{
  "type": "Feature",
  "properties": {
    "name": "Fontaine-le-Dun",
    "country": "FR",
    "subdivision": "28",
    "timezone": "Europe/Paris"
  },
  "geometry": {
    "type": "Point",
    "coordinates": [
      0.85095,
      49.81182
    ]
  }
}