{
  "type": "Feature",
  "properties": {
    "name": "Foucarmont",
    "country": "FR",
    "subdivision": "28",
    "timezone": "Europe/Paris"
  },
  "geometry": {
    "type": "Point",
    "coordinates": [
      1.56899,
      49.84682
    ]
  }
}