{
  "type": "Feature",
  "properties": {
    "name": "Gainneville",
    "country": "FR",
    "subdivision": "28",
    "timezone": "Europe/Paris"
  },
  "geometry": {
    "type": "Point",
    "coordinates": [
      0.26164,
      49.51845
    ]
  }
}