{
  "type": "Feature",
  "properties": {
    "name": "Gisors",
    "country": "FR",
    "subdivision": "28",
    "timezone": "Europe/Paris"
  },
  "geometry": {
    "type": "Point",
    "coordinates": [
      1.7801,
      49.28178
    ]
  }
}