{
  "type": "Feature",
  "properties": {
    "name": "Gournay-en-Bray",
    "country": "FR",
    "subdivision": "28",
    "timezone": "Europe/Paris"
  },
  "geometry": {
    "type": "Point",
    "coordinates": [
      1.72471,
      49.48285
    ]
  }
}