{
  "type": "Feature",
  "properties": {
    "name": "Jumièges",
    "country": "FR",
    "subdivision": "28",
    "timezone": "Europe/Paris"
  },
  "geometry": {
    "type": "Point",
    "coordinates": [
      0.81918,
      49.43324
    ]
  }
}