{
  "type": "Feature",
  "properties": {
    "name": "La Haye-du-Puits",
    "country": "FR",
    "subdivision": "28",
    "timezone": "Europe/Paris"
  },
  "geometry": {
    "type": "Point",
    "coordinates": [
      -1.54324,
      49.28973
    ]
  }
}