{
  "type": "Feature",
  "properties": {
    "name": "La Selle-la-Forge",
    "country": "FR",
    "subdivision": "28",
    "timezone": "Europe/Paris"
  },
  "geometry": {
    "type": "Point",
    "coordinates": [
      -0.54103,
      48.73295
    ]
  }
}