{
  "type": "Feature",
  "properties": {
    "name": "Le Molay-Littry",
    "country": "FR",
    "subdivision": "28",
    "timezone": "Europe/Paris"
  },
  "geometry": {
    "type": "Point",
    "coordinates": [
      -0.87238,
      49.24265
    ]
  }
}