{
  "type": "Feature",
  "properties": {
    "name": "Les Loges",
    "country": "FR",
    "subdivision": "28",
    "timezone": "Europe/Paris"
  },
  "geometry": {
    "type": "Point",
    "coordinates": [
      0.28403,
      49.6986
    ]
  }
}