{
  "type": "Feature",
  "properties": {
    "name": "Les Authieux-sur-le-Port-Saint-Ouen",
    "country": "FR",
    "subdivision": "28",
    "timezone": "Europe/Paris"
  },
  "geometry": {
    "type": "Point",
    "coordinates": [
      1.13465,
      49.341
    ]
  }
}