{
  "type": "Feature",
  "properties": {
    "name": "Lessay",
    "country": "FR",
    "subdivision": "28",
    "timezone": "Europe/Paris"
  },
  "geometry": {
    "type": "Point",
    "coordinates": [
      -1.53089,
      49.21703
    ]
  }
}