{
  "type": "Feature",
  "properties": {
    "name": "Marcey-les-Grèves",
    "country": "FR",
    "subdivision": "28",
    "timezone": "Europe/Paris"
  },
  "geometry": {
    "type": "Point",
    "coordinates": [
      -1.39156,
      48.69673
    ]
  }
}