{
  "type": "Feature",
  "properties": {
    "name": "Martinvast",
    "country": "FR",
    "subdivision": "28",
    "timezone": "Europe/Paris"
  },
  "geometry": {
    "type": "Point",
    "coordinates": [
      -1.66434,
      49.59608
    ]
  }
}