{
  "type": "Feature",
  "properties": {
    "name": "Mesnières-en-Bray",
    "country": "FR",
    "subdivision": "28",
    "timezone": "Europe/Paris"
  },
  "geometry": {
    "type": "Point",
    "coordinates": [
      1.38187,
      49.76172
    ]
  }
}