{
  "type": "Feature",
  "properties": {
    "name": "Mondeville",
    "country": "FR",
    "subdivision": "28",
    "timezone": "Europe/Paris"
  },
  "geometry": {
    "type": "Point",
    "coordinates": [
      -0.32238,
      49.17497
    ]
  }
}