{
  "type": "Feature",
  "properties": {
    "name": "Montigny",
    "country": "FR",
    "subdivision": "28",
    "timezone": "Europe/Paris"
  },
  "geometry": {
    "type": "Point",
    "coordinates": [
      1.00168,
      49.4596
    ]
  }
}