{
  "type": "Feature",
  "properties": {
    "name": "Montaure",
    "country": "FR",
    "subdivision": "28",
    "timezone": "Europe/Paris"
  },
  "geometry": {
    "type": "Point",
    "coordinates": [
      1.08837,
      49.23417
    ]
  }
}