{
  "type": "Feature",
  "properties": {
    "name": "Montmain",
    "country": "FR",
    "subdivision": "28",
    "timezone": "Europe/Paris"
  },
  "geometry": {
    "type": "Point",
    "coordinates": [
      1.23742,
      49.40996
    ]
  }
}