{
  "type": "Feature",
  "properties": {
    "name": "Mont-Saint-Aignan",
    "country": "FR",
    "subdivision": "28",
    "timezone": "Europe/Paris"
  },
  "geometry": {
    "type": "Point",
    "coordinates": [
      1.09364,
      49.46307
    ]
  }
}