{
  "type": "Feature",
  "properties": {
    "name": "Mortagne-au-Perche",
    "country": "FR",
    "subdivision": "28",
    "timezone": "Europe/Paris"
  },
  "geometry": {
    "type": "Point",
    "coordinates": [
      0.54734,
      48.52018
    ]
  }
}