{
  "type": "Feature",
  "properties": {
    "name": "Nassandres",
    "country": "FR",
    "subdivision": "28",
    "timezone": "Europe/Paris"
  },
  "geometry": {
    "type": "Point",
    "coordinates": [
      0.73597,
      49.12632
    ]
  }
}