{
  "type": "Feature",
  "properties": {
    "name": "Pont-l'Évêque",
    "country": "FR",
    "subdivision": "28",
    "timezone": "Europe/Paris"
  },
  "geometry": {
    "type": "Point",
    "coordinates": [
      0.19161,
      49.28912
    ]
  }
}