{
  "type": "Feature",
  "properties": {
    "name": "Pont-Audemer",
    "country": "FR",
    "subdivision": "28",
    "timezone": "Europe/Paris"
  },
  "geometry": {
    "type": "Point",
    "coordinates": [
      0.51667,
      49.35
    ]
  }
}