{
  "type": "Feature",
  "properties": {
    "name": "Portbail",
    "country": "FR",
    "subdivision": "28",
    "timezone": "Europe/Paris"
  },
  "geometry": {
    "type": "Point",
    "coordinates": [
      -1.6956,
      49.33571
    ]
  }
}