{
  "type": "Feature",
  "properties": {
    "name": "Potigny",
    "country": "FR",
    "subdivision": "28",
    "timezone": "Europe/Paris"
  },
  "geometry": {
    "type": "Point",
    "coordinates": [
      -0.24166,
      48.96925
    ]
  }
}