{
  "type": "Feature",
  "properties": {
    "name": "Querqueville",
    "country": "FR",
    "subdivision": "28",
    "timezone": "Europe/Paris"
  },
  "geometry": {
    "type": "Point",
    "coordinates": [
      -1.69119,
      49.66251
    ]
  }
}