{
  "type": "Feature",
  "properties": {
    "name": "Quettehou",
    "country": "FR",
    "subdivision": "28",
    "timezone": "Europe/Paris"
  },
  "geometry": {
    "type": "Point",
    "coordinates": [
      -1.30352,
      49.59308
    ]
  }
}