{
  "type": "Feature",
  "properties": {
    "name": "Saint-Martin-des-Champs",
    "country": "FR",
    "subdivision": "28",
    "timezone": "Europe/Paris"
  },
  "geometry": {
    "type": "Point",
    "coordinates": [
      -1.33393,
      48.66841
    ]
  }
}