{
  "type": "Feature",
  "properties": {
    "name": "Saint-Martin-du-Vivier",
    "country": "FR",
    "subdivision": "28",
    "timezone": "Europe/Paris"
  },
  "geometry": {
    "type": "Point",
    "coordinates": [
      1.16667,
      49.46667
    ]
  }
}