{
  "type": "Feature",
  "properties": {
    "name": "Saint-James",
    "country": "FR",
    "subdivision": "28",
    "timezone": "Europe/Paris"
  },
  "geometry": {
    "type": "Point",
    "coordinates": [
      -1.32629,
      48.5218
    ]
  }
}