{
  "type": "Feature",
  "properties": {
    "name": "Serqueux",
    "country": "FR",
    "subdivision": "28",
    "timezone": "Europe/Paris"
  },
  "geometry": {
    "type": "Point",
    "coordinates": [
      1.54005,
      49.63202
    ]
  }
}