{
  "type": "Feature",
  "properties": {
    "name": "Urville-Nacqueville",
    "country": "FR",
    "subdivision": "28",
    "timezone": "Europe/Paris"
  },
  "geometry": {
    "type": "Point",
    "coordinates": [
      -1.73664,
      49.67444
    ]
  }
}