{
  "type": "Feature",
  "properties": {
    "name": "Vernon",
    "country": "FR",
    "subdivision": "28",
    "timezone": "Europe/Paris"
  },
  "geometry": {
    "type": "Point",
    "coordinates": [
      1.46332,
      49.09292
    ]
  }
}