{
  "type": "Feature",
  "properties": {
    "name": "Villers-sur-Mer",
    "country": "FR",
    "subdivision": "28",
    "timezone": "Europe/Paris"
  },
  "geometry": {
    "type": "Point",
    "coordinates": [
      0.00027,
      49.32264
    ]
  }
}