{
  "type": "Feature",
  "properties": {
    "name": "Villers-Bocage",
    "country": "FR",
    "subdivision": "28",
    "timezone": "Europe/Paris"
  },
  "geometry": {
    "type": "Point",
    "coordinates": [
      -0.65412,
      49.0796
    ]
  }
}