{
  "type": "Feature",
  "properties": {
    "name": "Vire",
    "country": "FR",
    "subdivision": "28",
    "timezone": "Europe/Paris"
  },
  "geometry": {
    "type": "Point",
    "coordinates": [
      -0.88929,
      48.83849
    ]
  }
}