{
  "type": "Feature",
  "properties": {
    "name": "Yerville",
    "country": "FR",
    "subdivision": "28",
    "timezone": "Europe/Paris"
  },
  "geometry": {
    "type": "Point",
    "coordinates": [
      0.89594,
      49.6672
    ]
  }
}