{
  "type": "Feature",
  "properties": {
    "name": "Yport",
    "country": "FR",
    "subdivision": "28",
    "timezone": "Europe/Paris"
  },
  "geometry": {
    "type": "Point",
    "coordinates": [
      0.31537,
      49.73716
    ]
  }
}