{
  "type": "Feature",
  "properties": {
    "name": "Haikou",
    "country": "CN",
    "subdivision": "29",
    "timezone": "Asia/Shanghai"
  },
  "geometry": {
    "type": "Point",
    "coordinates": [
      102.57548,
      24.77985
    ]
  }
}