{
  "type": "Feature",
  "properties": {
    "name": "Jianshui",
    "country": "CN",
    "subdivision": "29",
    "timezone": "Asia/Shanghai"
  },
  "geometry": {
    "type": "Point",
    "coordinates": [
      101.224,
      24.2774
    ]
  }
}