{
  "type": "Feature",
  "properties": {
    "name": "Lianran",
    "country": "CN",
    "subdivision": "29",
    "timezone": "Asia/Shanghai"
  },
  "geometry": {
    "type": "Point",
    "coordinates": [
      102.48496,
      24.92271
    ]
  }
}