{
  "type": "Feature",
  "properties": {
    "name": "Yuxi",
    "country": "CN",
    "subdivision": "29",
    "timezone": "Asia/Shanghai"
  },
  "geometry": {
    "type": "Point",
    "coordinates": [
      102.54222,
      24.355
    ]
  }
}