{
  "type": "Feature",
  "properties": {
    "name": "Başçiftlik",
    "country": "TR",
    "subdivision": "60",
    "timezone": "Europe/Istanbul"
  },
  "geometry": {
    "type": "Point",
    "coordinates": [
      37.16917,
      40.54694
    ]
  }
}