{
  "type": "Feature",
  "properties": {
    "name": "Turhal",
    "country": "TR",
    "subdivision": "60",
    "timezone": "Europe/Istanbul"
  },
  "geometry": {
    "type": "Point",
    "coordinates": [
      36.08111,
      40.3875
    ]
  }
}