{
  "type": "Feature",
  "properties": {
    "name": "Zile",
    "country": "TR",
    "subdivision": "60",
    "timezone": "Europe/Istanbul"
  },
  "geometry": {
    "type": "Point",
    "coordinates": [
      35.88639,
      40.30306
    ]
  }
}