{
  "type": "Feature",
  "properties": {
    "name": "Isanlu-Itedoijowa",
    "country": "NG",
    "subdivision": "41",
    "timezone": "Africa/Lagos"
  },
  "geometry": {
    "type": "Point",
    "coordinates": [
      5.83528,
      8.27445
    ]
  }
}