{
  "type": "Feature",
  "properties": {
    "name": "Lokoja",
    "country": "NG",
    "subdivision": "41",
    "timezone": "Africa/Lagos"
  },
  "geometry": {
    "type": "Point",
    "coordinates": [
      6.74048,
      7.79688
    ]
  }
}