{
  "type": "Feature",
  "properties": {
    "name": "Liptovský Mikuláš",
    "country": "SK",
    "subdivision": "08",
    "timezone": "Europe/Bratislava"
  },
  "geometry": {
    "type": "Point",
    "coordinates": [
      19.62218,
      49.08061
    ]
  }
}