{
  "type": "Feature",
  "properties": {
    "name": "Nižná",
    "country": "SK",
    "subdivision": "08",
    "timezone": "Europe/Bratislava"
  },
  "geometry": {
    "type": "Point",
    "coordinates": [
      19.52428,
      49.31046
    ]
  }
}