{
  "type": "Feature",
  "properties": {
    "name": "Ružomberok",
    "country": "SK",
    "subdivision": "08",
    "timezone": "Europe/Bratislava"
  },
  "geometry": {
    "type": "Point",
    "coordinates": [
      19.30751,
      49.0748
    ]
  }
}