{
  "type": "Feature",
  "properties": {
    "name": "Atikokan",
    "country": "CA",
    "subdivision": "08",
    "timezone": "America/Atikokan"
  },
  "geometry": {
    "type": "Point",
    "coordinates": [
      -91.62409,
      48.75667
    ]
  }
}