{
  "type": "Feature",
  "properties": {
    "name": "Banbury-Don Mills",
    "country": "CA",
    "subdivision": "08",
    "timezone": "America/Toronto"
  },
  "geometry": {
    "type": "Point",
    "coordinates": [
      -79.34972,
      43.73766
    ]
  }
}