{
  "type": "Feature",
  "properties": {
    "name": "Barrie",
    "country": "CA",
    "subdivision": "08",
    "timezone": "America/Toronto"
  },
  "geometry": {
    "type": "Point",
    "coordinates": [
      -79.66634,
      44.40011
    ]
  }
}