{
  "type": "Feature",
  "properties": {
    "name": "Beechborough-Greenbrook",
    "country": "CA",
    "subdivision": "08",
    "timezone": "America/Toronto"
  },
  "geometry": {
    "type": "Point",
    "coordinates": [
      -79.47947,
      43.69322
    ]
  }
}