{
  "type": "Feature",
  "properties": {
    "name": "Bendale",
    "country": "CA",
    "subdivision": "08",
    "timezone": "America/Toronto"
  },
  "geometry": {
    "type": "Point",
    "coordinates": [
      -79.25326,
      43.76681
    ]
  }
}