{
  "type": "Feature",
  "properties": {
    "name": "Broadview North",
    "country": "CA",
    "subdivision": "08",
    "timezone": "America/Toronto"
  },
  "geometry": {
    "type": "Point",
    "coordinates": [
      -79.35563,
      43.68883
    ]
  }
}