{
  "type": "Feature",
  "properties": {
    "name": "Collingwood",
    "country": "CA",
    "subdivision": "08",
    "timezone": "America/Toronto"
  },
  "geometry": {
    "type": "Point",
    "coordinates": [
      -80.21638,
      44.4834
    ]
  }
}