{
  "type": "Feature",
  "properties": {
    "name": "Dorchester",
    "country": "CA",
    "subdivision": "08",
    "timezone": "America/Toronto"
  },
  "geometry": {
    "type": "Point",
    "coordinates": [
      -81.06643,
      42.98339
    ]
  }
}