{
  "type": "Feature",
  "properties": {
    "name": "Dovercourt-Wallace Emerson-Junction",
    "country": "CA",
    "subdivision": "08",
    "timezone": "America/Toronto"
  },
  "geometry": {
    "type": "Point",
    "coordinates": [
      -79.43854,
      43.66568
    ]
  }
}