{
  "type": "Feature",
  "properties": {
    "name": "Dufferin Grove",
    "country": "CA",
    "subdivision": "08",
    "timezone": "America/Toronto"
  },
  "geometry": {
    "type": "Point",
    "coordinates": [
      -79.42793,
      43.65766
    ]
  }
}