{
  "type": "Feature",
  "properties": {
    "name": "Elliot Lake",
    "country": "CA",
    "subdivision": "08",
    "timezone": "America/Toronto"
  },
  "geometry": {
    "type": "Point",
    "coordinates": [
      -82.63315,
      46.38336
    ]
  }
}