{
  "type": "Feature",
  "properties": {
    "name": "Elmvale",
    "country": "CA",
    "subdivision": "08",
    "timezone": "America/Toronto"
  },
  "geometry": {
    "type": "Point",
    "coordinates": [
      -79.86636,
      44.5834
    ]
  }
}