{
  "type": "Feature",
  "properties": {
    "name": "Englehart",
    "country": "CA",
    "subdivision": "08",
    "timezone": "America/Toronto"
  },
  "geometry": {
    "type": "Point",
    "coordinates": [
      -79.87386,
      47.82397
    ]
  }
}