{
  "type": "Feature",
  "properties": {
    "name": "Essex",
    "country": "CA",
    "subdivision": "08",
    "timezone": "America/Toronto"
  },
  "geometry": {
    "type": "Point",
    "coordinates": [
      -82.82483,
      42.17509
    ]
  }
}