{
  "type": "Feature",
  "properties": {
    "name": "Gananoque",
    "country": "CA",
    "subdivision": "08",
    "timezone": "America/Toronto"
  },
  "geometry": {
    "type": "Point",
    "coordinates": [
      -76.16607,
      44.33342
    ]
  }
}