{
  "type": "Feature",
  "properties": {
    "name": "Islington-City Centre West",
    "country": "CA",
    "subdivision": "08",
    "timezone": "America/Toronto"
  },
  "geometry": {
    "type": "Point",
    "coordinates": [
      -79.54332,
      43.63347
    ]
  }
}