{
  "type": "Feature",
  "properties": {
    "name": "Limoges",
    "country": "CA",
    "subdivision": "08",
    "timezone": "America/Toronto"
  },
  "geometry": {
    "type": "Point",
    "coordinates": [
      -75.24931,
      45.3334
    ]
  }
}