{
  "type": "Feature",
  "properties": {
    "name": "Little Portugal",
    "country": "CA",
    "subdivision": "08",
    "timezone": "America/Toronto"
  },
  "geometry": {
    "type": "Point",
    "coordinates": [
      -79.42956,
      43.64663
    ]
  }
}