{
  "type": "Feature",
  "properties": {
    "name": "Maple Leaf",
    "country": "CA",
    "subdivision": "08",
    "timezone": "America/Toronto"
  },
  "geometry": {
    "type": "Point",
    "coordinates": [
      -79.48076,
      43.71557
    ]
  }
}