{
  "type": "Feature",
  "properties": {
    "name": "Markdale",
    "country": "CA",
    "subdivision": "08",
    "timezone": "America/Toronto"
  },
  "geometry": {
    "type": "Point",
    "coordinates": [
      -80.64971,
      44.3168
    ]
  }
}