{
  "type": "Feature",
  "properties": {
    "name": "Moose Factory",
    "country": "CA",
    "subdivision": "08",
    "timezone": "America/Toronto"
  },
  "geometry": {
    "type": "Point",
    "coordinates": [
      -80.61624,
      51.26689
    ]
  }
}