{
  "type": "Feature",
  "properties": {
    "name": "Mount Dennis",
    "country": "CA",
    "subdivision": "08",
    "timezone": "America/Toronto"
  },
  "geometry": {
    "type": "Point",
    "coordinates": [
      -79.48917,
      43.68694
    ]
  }
}