{
  "type": "Feature",
  "properties": {
    "name": "Picton",
    "country": "CA",
    "subdivision": "08",
    "timezone": "America/Toronto"
  },
  "geometry": {
    "type": "Point",
    "coordinates": [
      -77.14637,
      44.00176
    ]
  }
}