{
  "type": "Feature",
  "properties": {
    "name": "Port Colborne",
    "country": "CA",
    "subdivision": "08",
    "timezone": "America/Toronto"
  },
  "geometry": {
    "type": "Point",
    "coordinates": [
      -79.23288,
      42.90012
    ]
  }
}