{
  "type": "Feature",
  "properties": {
    "name": "Prince Edward",
    "country": "CA",
    "subdivision": "08",
    "timezone": "America/Toronto"
  },
  "geometry": {
    "type": "Point",
    "coordinates": [
      -77.24946,
      44.00012
    ]
  }
}