{
  "type": "Feature",
  "properties": {
    "name": "Roncesvalles",
    "country": "CA",
    "subdivision": "08",
    "timezone": "America/Toronto"
  },
  "geometry": {
    "type": "Point",
    "coordinates": [
      -79.45016,
      43.64887
    ]
  }
}