{
  "type": "Feature",
  "properties": {
    "name": "Shelburne",
    "country": "CA",
    "subdivision": "08",
    "timezone": "America/Toronto"
  },
  "geometry": {
    "type": "Point",
    "coordinates": [
      -80.20408,
      44.0787
    ]
  }
}