{
  "type": "Feature",
  "properties": {
    "name": "Simcoe",
    "country": "CA",
    "subdivision": "08",
    "timezone": "America/Toronto"
  },
  "geometry": {
    "type": "Point",
    "coordinates": [
      -80.29967,
      42.8334
    ]
  }
}