{
  "type": "Feature",
  "properties": {
    "name": "Skatepark",
    "country": "CA",
    "subdivision": "08",
    "timezone": "America/Toronto"
  },
  "geometry": {
    "type": "Point",
    "coordinates": [
      -76.94424,
      44.25122
    ]
  }
}