{
  "type": "Feature",
  "properties": {
    "name": "St. Catharines",
    "country": "CA",
    "subdivision": "08",
    "timezone": "America/Toronto"
  },
  "geometry": {
    "type": "Point",
    "coordinates": [
      -79.24267,
      43.17126
    ]
  }
}