{
  "type": "Feature",
  "properties": {
    "name": "Stirling",
    "country": "CA",
    "subdivision": "08",
    "timezone": "America/Toronto"
  },
  "geometry": {
    "type": "Point",
    "coordinates": [
      -77.54948,
      44.30012
    ]
  }
}