{
  "type": "Feature",
  "properties": {
    "name": "Taylor-Massey",
    "country": "CA",
    "subdivision": "08",
    "timezone": "America/Toronto"
  },
  "geometry": {
    "type": "Point",
    "coordinates": [
      -79.2959,
      43.695
    ]
  }
}