{
  "type": "Feature",
  "properties": {
    "name": "Tobermory",
    "country": "CA",
    "subdivision": "08",
    "timezone": "America/Toronto"
  },
  "geometry": {
    "type": "Point",
    "coordinates": [
      -81.66647,
      45.25007
    ]
  }
}