{
  "type": "Feature",
  "properties": {
    "name": "University",
    "country": "CA",
    "subdivision": "08",
    "timezone": "America/Toronto"
  },
  "geometry": {
    "type": "Point",
    "coordinates": [
      -79.40118,
      43.66251
    ]
  }
}