{
  "type": "Feature",
  "properties": {
    "name": "Vanier",
    "country": "CA",
    "subdivision": "08",
    "timezone": "America/Toronto"
  },
  "geometry": {
    "type": "Point",
    "coordinates": [
      -75.66498,
      45.4399
    ]
  }
}