{
  "type": "Feature",
  "properties": {
    "name": "Virgil",
    "country": "CA",
    "subdivision": "08",
    "timezone": "America/Toronto"
  },
  "geometry": {
    "type": "Point",
    "coordinates": [
      -79.13288,
      43.21682
    ]
  }
}