{
  "type": "Feature",
  "properties": {
    "name": "Wasaga Beach",
    "country": "CA",
    "subdivision": "08",
    "timezone": "America/Toronto"
  },
  "geometry": {
    "type": "Point",
    "coordinates": [
      -80.01637,
      44.5168
    ]
  }
}