{
  "type": "Feature",
  "properties": {
    "name": "Welland",
    "country": "CA",
    "subdivision": "08",
    "timezone": "America/Toronto"
  },
  "geometry": {
    "type": "Point",
    "coordinates": [
      -79.24958,
      42.98342
    ]
  }
}