{
  "type": "Feature",
  "properties": {
    "name": "West Humber-Clairville",
    "country": "CA",
    "subdivision": "08",
    "timezone": "America/Toronto"
  },
  "geometry": {
    "type": "Point",
    "coordinates": [
      -79.59636,
      43.71619
    ]
  }
}