{
  "type": "Feature",
  "properties": {
    "name": "Willowridge-Martingrove-Richview",
    "country": "CA",
    "subdivision": "08",
    "timezone": "America/Toronto"
  },
  "geometry": {
    "type": "Point",
    "coordinates": [
      -79.55422,
      43.68364
    ]
  }
}