{
  "type": "Feature",
  "properties": {
    "name": "Yorkdale-Glen Park",
    "country": "CA",
    "subdivision": "08",
    "timezone": "America/Toronto"
  },
  "geometry": {
    "type": "Point",
    "coordinates": [
      -79.45711,
      43.71467
    ]
  }
}