{
  "type": "Feature",
  "properties": {
    "name": "Água Preta",
    "country": "BR",
    "subdivision": "30",
    "timezone": "America/Recife"
  },
  "geometry": {
    "type": "Point",
    "coordinates": [
      -35.53056,
      -8.7075
    ]
  }
}