{
  "type": "Feature",
  "properties": {
    "name": "Capoeiras",
    "country": "BR",
    "subdivision": "30",
    "timezone": "America/Recife"
  },
  "geometry": {
    "type": "Point",
    "coordinates": [
      -36.62667,
      -8.73472
    ]
  }
}