{
  "type": "Feature",
  "properties": {
    "name": "Colônia Leopoldina",
    "country": "BR",
    "subdivision": "30",
    "timezone": "America/Recife"
  },
  "geometry": {
    "type": "Point",
    "coordinates": [
      -35.725,
      -8.90889
    ]
  }
}