{
  "type": "Feature",
  "properties": {
    "name": "Custódia",
    "country": "BR",
    "subdivision": "30",
    "timezone": "America/Recife"
  },
  "geometry": {
    "type": "Point",
    "coordinates": [
      -37.64306,
      -8.0875
    ]
  }
}