{
  "type": "Feature",
  "properties": {
    "name": "Escada",
    "country": "BR",
    "subdivision": "30",
    "timezone": "America/Recife"
  },
  "geometry": {
    "type": "Point",
    "coordinates": [
      -35.22361,
      -8.35917
    ]
  }
}