{
  "type": "Feature",
  "properties": {
    "name": "Exu",
    "country": "BR",
    "subdivision": "30",
    "timezone": "America/Recife"
  },
  "geometry": {
    "type": "Point",
    "coordinates": [
      -39.72417,
      -7.51194
    ]
  }
}