{
  "type": "Feature",
  "properties": {
    "name": "Jaboatão",
    "country": "BR",
    "subdivision": "30",
    "timezone": "America/Recife"
  },
  "geometry": {
    "type": "Point",
    "coordinates": [
      -35.00139,
      -8.18028
    ]
  }
}