{
  "type": "Feature",
  "properties": {
    "name": "Jaboatão dos Guararapes",
    "country": "BR",
    "subdivision": "30",
    "timezone": "America/Recife"
  },
  "geometry": {
    "type": "Point",
    "coordinates": [
      -35.01472,
      -8.11278
    ]
  }
}