{
  "type": "Feature",
  "properties": {
    "name": "Jatobá",
    "country": "BR",
    "subdivision": "30",
    "timezone": "America/Recife"
  },
  "geometry": {
    "type": "Point",
    "coordinates": [
      -38.26889,
      -9.18306
    ]
  }
}