{
  "type": "Feature",
  "properties": {
    "name": "Pedra",
    "country": "BR",
    "subdivision": "30",
    "timezone": "America/Recife"
  },
  "geometry": {
    "type": "Point",
    "coordinates": [
      -36.94083,
      -8.49694
    ]
  }
}