{
  "type": "Feature",
  "properties": {
    "name": "Quipapá",
    "country": "BR",
    "subdivision": "30",
    "timezone": "America/Recife"
  },
  "geometry": {
    "type": "Point",
    "coordinates": [
      -36.01167,
      -8.82778
    ]
  }
}