{
  "type": "Feature",
  "properties": {
    "name": "Salgueiro",
    "country": "BR",
    "subdivision": "30",
    "timezone": "America/Recife"
  },
  "geometry": {
    "type": "Point",
    "coordinates": [
      -39.11917,
      -8.07417
    ]
  }
}