{
  "type": "Feature",
  "properties": {
    "name": "São José da Coroa Grande",
    "country": "BR",
    "subdivision": "30",
    "timezone": "America/Recife"
  },
  "geometry": {
    "type": "Point",
    "coordinates": [
      -35.14778,
      -8.89778
    ]
  }
}