{
  "type": "Feature",
  "properties": {
    "name": "Tabira",
    "country": "BR",
    "subdivision": "30",
    "timezone": "America/Recife"
  },
  "geometry": {
    "type": "Point",
    "coordinates": [
      -37.53944,
      -7.59083
    ]
  }
}