{
  "type": "Feature",
  "properties": {
    "name": "Douane",
    "country": "TN",
    "subdivision": "19",
    "timezone": "Africa/Tunis"
  },
  "geometry": {
    "type": "Point",
    "coordinates": [
      10.7557,
      36.44766
    ]
  }
}