{
  "type": "Feature",
  "properties": {
    "name": "Menzel Heurr",
    "country": "TN",
    "subdivision": "19",
    "timezone": "Africa/Tunis"
  },
  "geometry": {
    "type": "Point",
    "coordinates": [
      10.95757,
      36.72818
    ]
  }
}