{
  "type": "Feature",
  "properties": {
    "name": "Mqabba",
    "country": "MT",
    "subdivision": "22",
    "timezone": "Europe/Malta"
  },
  "geometry": {
    "type": "Point",
    "coordinates": [
      14.46824,
      35.84763
    ]
  }
}