{
  "type": "Feature",
  "properties": {
    "name": "Goričani",
    "country": "ME",
    "subdivision": "16",
    "timezone": "Europe/Podgorica"
  },
  "geometry": {
    "type": "Point",
    "coordinates": [
      19.21194,
      42.33222
    ]
  }
}