{
  "type": "Feature",
  "properties": {
    "name": "Beloyarsk",
    "country": "RU",
    "subdivision": "04",
    "timezone": "Asia/Barnaul"
  },
  "geometry": {
    "type": "Point",
    "coordinates": [
      83.9048,
      53.4461
    ]
  }
}