{
  "type": "Feature",
  "properties": {
    "name": "Charyshskoye",
    "country": "RU",
    "subdivision": "04",
    "timezone": "Asia/Barnaul"
  },
  "geometry": {
    "type": "Point",
    "coordinates": [
      83.5598,
      51.3978
    ]
  }
}