{
  "type": "Feature",
  "properties": {
    "name": "Cheremnoye",
    "country": "RU",
    "subdivision": "04",
    "timezone": "Asia/Barnaul"
  },
  "geometry": {
    "type": "Point",
    "coordinates": [
      83.21333,
      53.16972
    ]
  }
}