{
  "type": "Feature",
  "properties": {
    "name": "Gon’ba",
    "country": "RU",
    "subdivision": "04",
    "timezone": "Asia/Barnaul"
  },
  "geometry": {
    "type": "Point",
    "coordinates": [
      83.5747,
      53.4172
    ]
  }
}