{
  "type": "Feature",
  "properties": {
    "name": "Kalmanka",
    "country": "RU",
    "subdivision": "04",
    "timezone": "Asia/Barnaul"
  },
  "geometry": {
    "type": "Point",
    "coordinates": [
      83.54333,
      52.89917
    ]
  }
}