{
  "type": "Feature",
  "properties": {
    "name": "Krasnyy Yar",
    "country": "RU",
    "subdivision": "04",
    "timezone": "Asia/Barnaul"
  },
  "geometry": {
    "type": "Point",
    "coordinates": [
      85.33806,
      52.3575
    ]
  }
}