{
  "type": "Feature",
  "properties": {
    "name": "Pospelikha",
    "country": "RU",
    "subdivision": "04",
    "timezone": "Asia/Barnaul"
  },
  "geometry": {
    "type": "Point",
    "coordinates": [
      81.76667,
      51.95
    ]
  }
}