{
  "type": "Feature",
  "properties": {
    "name": "Romanovo",
    "country": "RU",
    "subdivision": "04",
    "timezone": "Asia/Barnaul"
  },
  "geometry": {
    "type": "Point",
    "coordinates": [
      81.2271,
      52.6182
    ]
  }
}