{
  "type": "Feature",
  "properties": {
    "name": "Severka",
    "country": "RU",
    "subdivision": "04",
    "timezone": "Asia/Barnaul"
  },
  "geometry": {
    "type": "Point",
    "coordinates": [
      79.28333,
      52.13333
    ]
  }
}