{
  "type": "Feature",
  "properties": {
    "name": "Sokolovo",
    "country": "RU",
    "subdivision": "04",
    "timezone": "Asia/Barnaul"
  },
  "geometry": {
    "type": "Point",
    "coordinates": [
      84.7896,
      52.5318
    ]
  }
}