{
  "type": "Feature",
  "properties": {
    "name": "Solton",
    "country": "RU",
    "subdivision": "04",
    "timezone": "Asia/Barnaul"
  },
  "geometry": {
    "type": "Point",
    "coordinates": [
      86.4787,
      52.8429
    ]
  }
}