{
  "type": "Feature",
  "properties": {
    "name": "Starobelokurikha",
    "country": "RU",
    "subdivision": "04",
    "timezone": "Asia/Barnaul"
  },
  "geometry": {
    "type": "Point",
    "coordinates": [
      85.08765,
      52.05206
    ]
  }
}