{
  "type": "Feature",
  "properties": {
    "name": "Tabuny",
    "country": "RU",
    "subdivision": "04",
    "timezone": "Asia/Barnaul"
  },
  "geometry": {
    "type": "Point",
    "coordinates": [
      78.7896,
      52.7773
    ]
  }
}