{
  "type": "Feature",
  "properties": {
    "name": "Ust’-Kalmanka",
    "country": "RU",
    "subdivision": "04",
    "timezone": "Asia/Barnaul"
  },
  "geometry": {
    "type": "Point",
    "coordinates": [
      83.305,
      52.1207
    ]
  }
}