{
  "type": "Feature",
  "properties": {
    "name": "Verkh-Suetka",
    "country": "RU",
    "subdivision": "04",
    "timezone": "Asia/Barnaul"
  },
  "geometry": {
    "type": "Point",
    "coordinates": [
      80.04675,
      53.30401
    ]
  }
}