{
  "type": "Feature",
  "properties": {
    "name": "Veseloyarsk",
    "country": "RU",
    "subdivision": "04",
    "timezone": "Asia/Barnaul"
  },
  "geometry": {
    "type": "Point",
    "coordinates": [
      81.10703,
      51.28737
    ]
  }
}