{
  "type": "Feature",
  "properties": {
    "name": "Yarovoye",
    "country": "RU",
    "subdivision": "04",
    "timezone": "Asia/Barnaul"
  },
  "geometry": {
    "type": "Point",
    "coordinates": [
      78.58,
      52.9273
    ]
  }
}