{
  "type": "Feature",
  "properties": {
    "name": "Zalesovo",
    "country": "RU",
    "subdivision": "04",
    "timezone": "Asia/Barnaul"
  },
  "geometry": {
    "type": "Point",
    "coordinates": [
      84.74306,
      53.99389
    ]
  }
}