{
  "type": "Feature",
  "properties": {
    "name": "Mount Darwin",
    "country": "ZW",
    "subdivision": "03",
    "timezone": "Africa/Harare"
  },
  "geometry": {
    "type": "Point",
    "coordinates": [
      31.58381,
      -16.77251
    ]
  }
}