{
  "type": "Feature",
  "properties": {
    "name": "Manta",
    "country": "EC",
    "subdivision": "14",
    "timezone": "America/Guayaquil"
  },
  "geometry": {
    "type": "Point",
    "coordinates": [
      -80.71271,
      -0.96212
    ]
  }
}