{
  "type": "Feature",
  "properties": {
    "name": "Amherst Center",
    "country": "US",
    "subdivision": "MA",
    "timezone": "America/New_York"
  },
  "geometry": {
    "type": "Point",
    "coordinates": [
      -72.51925,
      42.37537
    ]
  }
}