{
  "type": "Feature",
  "properties": {
    "name": "Ashfield",
    "country": "US",
    "subdivision": "MA",
    "timezone": "America/New_York"
  },
  "geometry": {
    "type": "Point",
    "coordinates": [
      -72.78843,
      42.52647
    ]
  }
}