{
  "type": "Feature",
  "properties": {
    "name": "Boxborough",
    "country": "US",
    "subdivision": "MA",
    "timezone": "America/New_York"
  },
  "geometry": {
    "type": "Point",
    "coordinates": [
      -71.52851,
      42.49084
    ]
  }
}