{
  "type": "Feature",
  "properties": {
    "name": "Buckland",
    "country": "US",
    "subdivision": "MA",
    "timezone": "America/New_York"
  },
  "geometry": {
    "type": "Point",
    "coordinates": [
      -72.79176,
      42.59231
    ]
  }
}