{
  "type": "Feature",
  "properties": {
    "name": "Dedham",
    "country": "US",
    "subdivision": "MA",
    "timezone": "America/New_York"
  },
  "geometry": {
    "type": "Point",
    "coordinates": [
      -71.16616,
      42.24177
    ]
  }
}