{
  "type": "Feature",
  "properties": {
    "name": "Duxbury",
    "country": "US",
    "subdivision": "MA",
    "timezone": "America/New_York"
  },
  "geometry": {
    "type": "Point",
    "coordinates": [
      -70.67226,
      42.04177
    ]
  }
}