{
  "type": "Feature",
  "properties": {
    "name": "Easthampton",
    "country": "US",
    "subdivision": "MA",
    "timezone": "America/New_York"
  },
  "geometry": {
    "type": "Point",
    "coordinates": [
      -72.66898,
      42.26676
    ]
  }
}