{
  "type": "Feature",
  "properties": {
    "name": "Essex",
    "country": "US",
    "subdivision": "MA",
    "timezone": "America/New_York"
  },
  "geometry": {
    "type": "Point",
    "coordinates": [
      -70.78283,
      42.63204
    ]
  }
}