{
  "type": "Feature",
  "properties": {
    "name": "Green Harbor-Cedar Crest",
    "country": "US",
    "subdivision": "MA",
    "timezone": "America/New_York"
  },
  "geometry": {
    "type": "Point",
    "coordinates": [
      -70.65843,
      42.07495
    ]
  }
}