{
  "type": "Feature",
  "properties": {
    "name": "Hadley",
    "country": "US",
    "subdivision": "MA",
    "timezone": "America/New_York"
  },
  "geometry": {
    "type": "Point",
    "coordinates": [
      -72.58842,
      42.34176
    ]
  }
}