{
  "type": "Feature",
  "properties": {
    "name": "Hamilton Worcester",
    "country": "US",
    "subdivision": "MA",
    "timezone": "America/New_York"
  },
  "geometry": {
    "type": "Point",
    "coordinates": [
      -71.76757,
      42.2562
    ]
  }
}