{
  "type": "Feature",
  "properties": {
    "name": "Harvard",
    "country": "US",
    "subdivision": "MA",
    "timezone": "America/New_York"
  },
  "geometry": {
    "type": "Point",
    "coordinates": [
      -71.58284,
      42.50009
    ]
  }
}