{
  "type": "Feature",
  "properties": {
    "name": "Hinsdale",
    "country": "US",
    "subdivision": "MA",
    "timezone": "America/New_York"
  },
  "geometry": {
    "type": "Point",
    "coordinates": [
      -73.12538,
      42.4387
    ]
  }
}