{
  "type": "Feature",
  "properties": {
    "name": "North Reading",
    "country": "US",
    "subdivision": "MA",
    "timezone": "America/New_York"
  },
  "geometry": {
    "type": "Point",
    "coordinates": [
      -71.07867,
      42.57509
    ]
  }
}