{
  "type": "Feature",
  "properties": {
    "name": "Northfield",
    "country": "US",
    "subdivision": "MA",
    "timezone": "America/New_York"
  },
  "geometry": {
    "type": "Point",
    "coordinates": [
      -72.45287,
      42.69592
    ]
  }
}