{
  "type": "Feature",
  "properties": {
    "name": "Northwest Harwich",
    "country": "US",
    "subdivision": "MA",
    "timezone": "America/New_York"
  },
  "geometry": {
    "type": "Point",
    "coordinates": [
      -70.1025,
      41.69029
    ]
  }
}