{
  "type": "Feature",
  "properties": {
    "name": "Osterville",
    "country": "US",
    "subdivision": "MA",
    "timezone": "America/New_York"
  },
  "geometry": {
    "type": "Point",
    "coordinates": [
      -70.38697,
      41.62844
    ]
  }
}