{
  "type": "Feature",
  "properties": {
    "name": "Oxford",
    "country": "US",
    "subdivision": "MA",
    "timezone": "America/New_York"
  },
  "geometry": {
    "type": "Point",
    "coordinates": [
      -71.86479,
      42.11676
    ]
  }
}