{
  "type": "Feature",
  "properties": {
    "name": "Palmer",
    "country": "US",
    "subdivision": "MA",
    "timezone": "America/New_York"
  },
  "geometry": {
    "type": "Point",
    "coordinates": [
      -72.32869,
      42.15843
    ]
  }
}