{
  "type": "Feature",
  "properties": {
    "name": "Plympton",
    "country": "US",
    "subdivision": "MA",
    "timezone": "America/New_York"
  },
  "geometry": {
    "type": "Point",
    "coordinates": [
      -70.81448,
      41.95288
    ]
  }
}