{
  "type": "Feature",
  "properties": {
    "name": "Raynham",
    "country": "US",
    "subdivision": "MA",
    "timezone": "America/New_York"
  },
  "geometry": {
    "type": "Point",
    "coordinates": [
      -71.0731,
      41.94871
    ]
  }
}