{
  "type": "Feature",
  "properties": {
    "name": "Reading",
    "country": "US",
    "subdivision": "MA",
    "timezone": "America/New_York"
  },
  "geometry": {
    "type": "Point",
    "coordinates": [
      -71.09533,
      42.52565
    ]
  }
}