{
  "type": "Feature",
  "properties": {
    "name": "Rehoboth",
    "country": "US",
    "subdivision": "MA",
    "timezone": "America/New_York"
  },
  "geometry": {
    "type": "Point",
    "coordinates": [
      -71.24949,
      41.84038
    ]
  }
}