{
  "type": "Feature",
  "properties": {
    "name": "Rockland",
    "country": "US",
    "subdivision": "MA",
    "timezone": "America/New_York"
  },
  "geometry": {
    "type": "Point",
    "coordinates": [
      -70.91616,
      42.13066
    ]
  }
}