{
  "type": "Feature",
  "properties": {
    "name": "Rockport",
    "country": "US",
    "subdivision": "MA",
    "timezone": "America/New_York"
  },
  "geometry": {
    "type": "Point",
    "coordinates": [
      -70.62032,
      42.65565
    ]
  }
}