{
  "type": "Feature",
  "properties": {
    "name": "Rutland",
    "country": "US",
    "subdivision": "MA",
    "timezone": "America/New_York"
  },
  "geometry": {
    "type": "Point",
    "coordinates": [
      -71.94813,
      42.36954
    ]
  }
}