{
  "type": "Feature",
  "properties": {
    "name": "Sharon",
    "country": "US",
    "subdivision": "MA",
    "timezone": "America/New_York"
  },
  "geometry": {
    "type": "Point",
    "coordinates": [
      -71.17866,
      42.12371
    ]
  }
}