{
  "type": "Feature",
  "properties": {
    "name": "Shirley",
    "country": "US",
    "subdivision": "MA",
    "timezone": "America/New_York"
  },
  "geometry": {
    "type": "Point",
    "coordinates": [
      -71.64951,
      42.5437
    ]
  }
}