{
  "type": "Feature",
  "properties": {
    "name": "Smith Mills",
    "country": "US",
    "subdivision": "MA",
    "timezone": "America/New_York"
  },
  "geometry": {
    "type": "Point",
    "coordinates": [
      -70.99115,
      41.63899
    ]
  }
}