{
  "type": "Feature",
  "properties": {
    "name": "South Duxbury",
    "country": "US",
    "subdivision": "MA",
    "timezone": "America/New_York"
  },
  "geometry": {
    "type": "Point",
    "coordinates": [
      -70.68281,
      42.02316
    ]
  }
}