{
  "type": "Feature",
  "properties": {
    "name": "Southwick",
    "country": "US",
    "subdivision": "MA",
    "timezone": "America/New_York"
  },
  "geometry": {
    "type": "Point",
    "coordinates": [
      -72.77037,
      42.05482
    ]
  }
}