{
  "type": "Feature",
  "properties": {
    "name": "South Dennis",
    "country": "US",
    "subdivision": "MA",
    "timezone": "America/New_York"
  },
  "geometry": {
    "type": "Point",
    "coordinates": [
      -70.15641,
      41.68956
    ]
  }
}