{
  "type": "Feature",
  "properties": {
    "name": "Spencer",
    "country": "US",
    "subdivision": "MA",
    "timezone": "America/New_York"
  },
  "geometry": {
    "type": "Point",
    "coordinates": [
      -71.9923,
      42.24398
    ]
  }
}