{
  "type": "Feature",
  "properties": {
    "name": "Sterling",
    "country": "US",
    "subdivision": "MA",
    "timezone": "America/New_York"
  },
  "geometry": {
    "type": "Point",
    "coordinates": [
      -71.76063,
      42.43759
    ]
  }
}