{
  "type": "Feature",
  "properties": {
    "name": "Upton",
    "country": "US",
    "subdivision": "MA",
    "timezone": "America/New_York"
  },
  "geometry": {
    "type": "Point",
    "coordinates": [
      -71.60229,
      42.17454
    ]
  }
}