{
  "type": "Feature",
  "properties": {
    "name": "Wareham Center",
    "country": "US",
    "subdivision": "MA",
    "timezone": "America/New_York"
  },
  "geometry": {
    "type": "Point",
    "coordinates": [
      -70.72615,
      41.76677
    ]
  }
}