{
  "type": "Feature",
  "properties": {
    "name": "Westhampton",
    "country": "US",
    "subdivision": "MA",
    "timezone": "America/New_York"
  },
  "geometry": {
    "type": "Point",
    "coordinates": [
      -72.77454,
      42.30287
    ]
  }
}