{
  "type": "Feature",
  "properties": {
    "name": "West Yarmouth",
    "country": "US",
    "subdivision": "MA",
    "timezone": "America/New_York"
  },
  "geometry": {
    "type": "Point",
    "coordinates": [
      -70.24113,
      41.65011
    ]
  }
}