{
  "type": "Feature",
  "properties": {
    "name": "Yarmouth Port",
    "country": "US",
    "subdivision": "MA",
    "timezone": "America/New_York"
  },
  "geometry": {
    "type": "Point",
    "coordinates": [
      -70.24947,
      41.70205
    ]
  }
}