{
  "type": "Feature",
  "properties": {
    "name": "San José de Guanipa",
    "country": "VE",
    "subdivision": "02",
    "timezone": "America/Caracas"
  },
  "geometry": {
    "type": "Point",
    "coordinates": [
      -64.16512,
      8.88724
    ]
  }
}