{
  "type": "Feature",
  "properties": {
    "name": "Bacău",
    "country": "RO",
    "subdivision": "04",
    "timezone": "Europe/Bucharest"
  },
  "geometry": {
    "type": "Point",
    "coordinates": [
      26.91384,
      46.56718
    ]
  }
}