{
  "type": "Feature",
  "properties": {
    "name": "Bolătău",
    "country": "RO",
    "subdivision": "04",
    "timezone": "Europe/Bucharest"
  },
  "geometry": {
    "type": "Point",
    "coordinates": [
      26.40149,
      46.63345
    ]
  }
}