{
  "type": "Feature",
  "properties": {
    "name": "Caraclău",
    "country": "RO",
    "subdivision": "04",
    "timezone": "Europe/Bucharest"
  },
  "geometry": {
    "type": "Point",
    "coordinates": [
      26.71641,
      46.30696
    ]
  }
}