{
  "type": "Feature",
  "properties": {
    "name": "Cerdac",
    "country": "RO",
    "subdivision": "04",
    "timezone": "Europe/Bucharest"
  },
  "geometry": {
    "type": "Point",
    "coordinates": [
      26.51638,
      46.23794
    ]
  }
}