{
  "type": "Feature",
  "properties": {
    "name": "Frumușelu",
    "country": "RO",
    "subdivision": "04",
    "timezone": "Europe/Bucharest"
  },
  "geometry": {
    "type": "Point",
    "coordinates": [
      27.35203,
      46.27796
    ]
  }
}