{
  "type": "Feature",
  "properties": {
    "name": "Gheorghe Doja",
    "country": "RO",
    "subdivision": "04",
    "timezone": "Europe/Bucharest"
  },
  "geometry": {
    "type": "Point",
    "coordinates": [
      26.96248,
      46.37831
    ]
  }
}