{
  "type": "Feature",
  "properties": {
    "name": "Gioseni",
    "country": "RO",
    "subdivision": "04",
    "timezone": "Europe/Bucharest"
  },
  "geometry": {
    "type": "Point",
    "coordinates": [
      26.99239,
      46.42925
    ]
  }
}