{
  "type": "Feature",
  "properties": {
    "name": "Helegiu",
    "country": "RO",
    "subdivision": "04",
    "timezone": "Europe/Bucharest"
  },
  "geometry": {
    "type": "Point",
    "coordinates": [
      26.75,
      46.35
    ]
  }
}