{
  "type": "Feature",
  "properties": {
    "name": "Lăpoș",
    "country": "RO",
    "subdivision": "04",
    "timezone": "Europe/Bucharest"
  },
  "geometry": {
    "type": "Point",
    "coordinates": [
      26.46245,
      46.39363
    ]
  }
}