{
  "type": "Feature",
  "properties": {
    "name": "Măgireşti",
    "country": "RO",
    "subdivision": "04",
    "timezone": "Europe/Bucharest"
  },
  "geometry": {
    "type": "Point",
    "coordinates": [
      26.55,
      46.51667
    ]
  }
}