{
  "type": "Feature",
  "properties": {
    "name": "Plopu",
    "country": "RO",
    "subdivision": "04",
    "timezone": "Europe/Bucharest"
  },
  "geometry": {
    "type": "Point",
    "coordinates": [
      26.50268,
      46.39256
    ]
  }
}