{
  "type": "Feature",
  "properties": {
    "name": "Poduri",
    "country": "RO",
    "subdivision": "04",
    "timezone": "Europe/Bucharest"
  },
  "geometry": {
    "type": "Point",
    "coordinates": [
      26.53333,
      46.46667
    ]
  }
}