{
  "type": "Feature",
  "properties": {
    "name": "Răchitoasa",
    "country": "RO",
    "subdivision": "04",
    "timezone": "Europe/Bucharest"
  },
  "geometry": {
    "type": "Point",
    "coordinates": [
      27.36667,
      46.43333
    ]
  }
}