{
  "type": "Feature",
  "properties": {
    "name": "Schitu Frumoasa",
    "country": "RO",
    "subdivision": "04",
    "timezone": "Europe/Bucharest"
  },
  "geometry": {
    "type": "Point",
    "coordinates": [
      26.48761,
      46.63541
    ]
  }
}