{
  "type": "Feature",
  "properties": {
    "name": "Tuta",
    "country": "RO",
    "subdivision": "04",
    "timezone": "Europe/Bucharest"
  },
  "geometry": {
    "type": "Point",
    "coordinates": [
      26.69103,
      46.25643
    ]
  }
}