{
  "type": "Feature",
  "properties": {
    "name": "Verșești",
    "country": "RO",
    "subdivision": "04",
    "timezone": "Europe/Bucharest"
  },
  "geometry": {
    "type": "Point",
    "coordinates": [
      26.70183,
      46.44904
    ]
  }
}