{
  "type": "Feature",
  "properties": {
    "name": "Tsiroanomandidy",
    "country": "MG",
    "subdivision": "14",
    "timezone": "Indian/Antananarivo"
  },
  "geometry": {
    "type": "Point",
    "coordinates": [
      46.04653,
      -18.76969
    ]
  }
}