{
  "type": "Feature",
  "properties": {
    "name": "Nuevo Imperial",
    "country": "PE",
    "subdivision": "15",
    "timezone": "America/Lima"
  },
  "geometry": {
    "type": "Point",
    "coordinates": [
      -76.31719,
      -13.07541
    ]
  }
}