{
  "type": "Feature",
  "properties": {
    "name": "San Francisco De Borja",
    "country": "PE",
    "subdivision": "15",
    "timezone": "America/Lima"
  },
  "geometry": {
    "type": "Point",
    "coordinates": [
      -76.99876,
      -12.08911
    ]
  }
}