{
  "type": "Feature",
  "properties": {
    "name": "Sayán",
    "country": "PE",
    "subdivision": "15",
    "timezone": "America/Lima"
  },
  "geometry": {
    "type": "Point",
    "coordinates": [
      -77.1946,
      -11.13333
    ]
  }
}