{
  "type": "Feature",
  "properties": {
    "name": "Végueta",
    "country": "PE",
    "subdivision": "15",
    "timezone": "America/Lima"
  },
  "geometry": {
    "type": "Point",
    "coordinates": [
      -77.64378,
      -11.02253
    ]
  }
}