{
  "type": "Feature",
  "properties": {
    "name": "Hanamaki",
    "country": "JP",
    "subdivision": "16",
    "timezone": "Asia/Tokyo"
  },
  "geometry": {
    "type": "Point",
    "coordinates": [
      141.11667,
      39.38333
    ]
  }
}