{
  "type": "Feature",
  "properties": {
    "name": "Albanvale",
    "country": "AU",
    "subdivision": "07",
    "timezone": "Australia/Melbourne"
  },
  "geometry": {
    "type": "Point",
    "coordinates": [
      144.76856,
      -37.74609
    ]
  }
}