{
  "type": "Feature",
  "properties": {
    "name": "Ashwood",
    "country": "AU",
    "subdivision": "07",
    "timezone": "Australia/Melbourne"
  },
  "geometry": {
    "type": "Point",
    "coordinates": [
      145.10553,
      -37.86659
    ]
  }
}