{
  "type": "Feature",
  "properties": {
    "name": "Aspendale Gardens",
    "country": "AU",
    "subdivision": "07",
    "timezone": "Australia/Melbourne"
  },
  "geometry": {
    "type": "Point",
    "coordinates": [
      145.11798,
      -38.02277
    ]
  }
}