{
  "type": "Feature",
  "properties": {
    "name": "Ballarat North",
    "country": "AU",
    "subdivision": "07",
    "timezone": "Australia/Melbourne"
  },
  "geometry": {
    "type": "Point",
    "coordinates": [
      143.86648,
      -37.54087
    ]
  }
}