{
  "type": "Feature",
  "properties": {
    "name": "Belgrave South",
    "country": "AU",
    "subdivision": "07",
    "timezone": "Australia/Melbourne"
  },
  "geometry": {
    "type": "Point",
    "coordinates": [
      145.33333,
      -37.93333
    ]
  }
}