{
  "type": "Feature",
  "properties": {
    "name": "Belgrave Heights",
    "country": "AU",
    "subdivision": "07",
    "timezone": "Australia/Melbourne"
  },
  "geometry": {
    "type": "Point",
    "coordinates": [
      145.34367,
      -37.92624
    ]
  }
}