{
  "type": "Feature",
  "properties": {
    "name": "Bellfield",
    "country": "AU",
    "subdivision": "07",
    "timezone": "Australia/Melbourne"
  },
  "geometry": {
    "type": "Point",
    "coordinates": [
      145.03848,
      -37.75309
    ]
  }
}