{
  "type": "Feature",
  "properties": {
    "name": "Blackburn",
    "country": "AU",
    "subdivision": "07",
    "timezone": "Australia/Melbourne"
  },
  "geometry": {
    "type": "Point",
    "coordinates": [
      145.15326,
      -37.81901
    ]
  }
}