{
  "type": "Feature",
  "properties": {
    "name": "Bonbeach",
    "country": "AU",
    "subdivision": "07",
    "timezone": "Australia/Melbourne"
  },
  "geometry": {
    "type": "Point",
    "coordinates": [
      145.12278,
      -38.06528
    ]
  }
}