{
  "type": "Feature",
  "properties": {
    "name": "Botanic Ridge",
    "country": "AU",
    "subdivision": "07",
    "timezone": "Australia/Melbourne"
  },
  "geometry": {
    "type": "Point",
    "coordinates": [
      145.26841,
      -38.13922
    ]
  }
}