{
  "type": "Feature",
  "properties": {
    "name": "Camperdown",
    "country": "AU",
    "subdivision": "07",
    "timezone": "Australia/Melbourne"
  },
  "geometry": {
    "type": "Point",
    "coordinates": [
      143.14983,
      -38.23392
    ]
  }
}