{
  "type": "Feature",
  "properties": {
    "name": "Caulfield",
    "country": "AU",
    "subdivision": "07",
    "timezone": "Australia/Melbourne"
  },
  "geometry": {
    "type": "Point",
    "coordinates": [
      145.02288,
      -37.88251
    ]
  }
}