{
  "type": "Feature",
  "properties": {
    "name": "Clunes",
    "country": "AU",
    "subdivision": "07",
    "timezone": "Australia/Melbourne"
  },
  "geometry": {
    "type": "Point",
    "coordinates": [
      143.78636,
      -37.29473
    ]
  }
}