{
  "type": "Feature",
  "properties": {
    "name": "Cobden",
    "country": "AU",
    "subdivision": "07",
    "timezone": "Australia/Melbourne"
  },
  "geometry": {
    "type": "Point",
    "coordinates": [
      143.07484,
      -38.3286
    ]
  }
}