{
  "type": "Feature",
  "properties": {
    "name": "Corio",
    "country": "AU",
    "subdivision": "07",
    "timezone": "Australia/Melbourne"
  },
  "geometry": {
    "type": "Point",
    "coordinates": [
      144.38333,
      -38.08333
    ]
  }
}