{
  "type": "Feature",
  "properties": {
    "name": "Corryong",
    "country": "AU",
    "subdivision": "07",
    "timezone": "Australia/Melbourne"
  },
  "geometry": {
    "type": "Point",
    "coordinates": [
      147.90256,
      -36.19705
    ]
  }
}