{
  "type": "Feature",
  "properties": {
    "name": "Cowes",
    "country": "AU",
    "subdivision": "07",
    "timezone": "Australia/Melbourne"
  },
  "geometry": {
    "type": "Point",
    "coordinates": [
      145.23865,
      -38.45231
    ]
  }
}