{
  "type": "Feature",
  "properties": {
    "name": "Delahey",
    "country": "AU",
    "subdivision": "07",
    "timezone": "Australia/Melbourne"
  },
  "geometry": {
    "type": "Point",
    "coordinates": [
      144.77732,
      -37.7198
    ]
  }
}