{
  "type": "Feature",
  "properties": {
    "name": "Donvale",
    "country": "AU",
    "subdivision": "07",
    "timezone": "Australia/Melbourne"
  },
  "geometry": {
    "type": "Point",
    "coordinates": [
      145.17488,
      -37.7891
    ]
  }
}