{
  "type": "Feature",
  "properties": {
    "name": "Emerald",
    "country": "AU",
    "subdivision": "07",
    "timezone": "Australia/Melbourne"
  },
  "geometry": {
    "type": "Point",
    "coordinates": [
      145.44093,
      -37.93167
    ]
  }
}