{
  "type": "Feature",
  "properties": {
    "name": "Eynesbury",
    "country": "AU",
    "subdivision": "07",
    "timezone": "Australia/Melbourne"
  },
  "geometry": {
    "type": "Point",
    "coordinates": [
      144.57458,
      -37.80043
    ]
  }
}