{
  "type": "Feature",
  "properties": {
    "name": "Geelong city centre",
    "country": "AU",
    "subdivision": "07",
    "timezone": "Australia/Melbourne"
  },
  "geometry": {
    "type": "Point",
    "coordinates": [
      144.36176,
      -38.14996
    ]
  }
}