{
  "type": "Feature",
  "properties": {
    "name": "Greenvale",
    "country": "AU",
    "subdivision": "07",
    "timezone": "Australia/Melbourne"
  },
  "geometry": {
    "type": "Point",
    "coordinates": [
      144.86667,
      -37.63333
    ]
  }
}