{
  "type": "Feature",
  "properties": {
    "name": "Hawthorn South",
    "country": "AU",
    "subdivision": "07",
    "timezone": "Australia/Melbourne"
  },
  "geometry": {
    "type": "Point",
    "coordinates": [
      145.0367,
      -37.8329
    ]
  }
}