{
  "type": "Feature",
  "properties": {
    "name": "Hillside",
    "country": "AU",
    "subdivision": "07",
    "timezone": "Australia/Melbourne"
  },
  "geometry": {
    "type": "Point",
    "coordinates": [
      144.74172,
      -37.69047
    ]
  }
}