{
  "type": "Feature",
  "properties": {
    "name": "Horsham",
    "country": "AU",
    "subdivision": "07",
    "timezone": "Australia/Melbourne"
  },
  "geometry": {
    "type": "Point",
    "coordinates": [
      142.19981,
      -36.71131
    ]
  }
}