{
  "type": "Feature",
  "properties": {
    "name": "Jan Juc",
    "country": "AU",
    "subdivision": "07",
    "timezone": "Australia/Melbourne"
  },
  "geometry": {
    "type": "Point",
    "coordinates": [
      144.29518,
      -38.34455
    ]
  }
}