{
  "type": "Feature",
  "properties": {
    "name": "Keilor Lodge",
    "country": "AU",
    "subdivision": "07",
    "timezone": "Australia/Melbourne"
  },
  "geometry": {
    "type": "Point",
    "coordinates": [
      144.80332,
      -37.69997
    ]
  }
}