{
  "type": "Feature",
  "properties": {
    "name": "Kialla",
    "country": "AU",
    "subdivision": "07",
    "timezone": "Australia/Melbourne"
  },
  "geometry": {
    "type": "Point",
    "coordinates": [
      145.41422,
      -36.44729
    ]
  }
}