{
  "type": "Feature",
  "properties": {
    "name": "Kingsville",
    "country": "AU",
    "subdivision": "07",
    "timezone": "Australia/Melbourne"
  },
  "geometry": {
    "type": "Point",
    "coordinates": [
      144.87911,
      -37.80819
    ]
  }
}