{
  "type": "Feature",
  "properties": {
    "name": "Kings Park",
    "country": "AU",
    "subdivision": "07",
    "timezone": "Australia/Melbourne"
  },
  "geometry": {
    "type": "Point",
    "coordinates": [
      144.77766,
      -37.73397
    ]
  }
}