{
  "type": "Feature",
  "properties": {
    "name": "Long Gully",
    "country": "AU",
    "subdivision": "07",
    "timezone": "Australia/Melbourne"
  },
  "geometry": {
    "type": "Point",
    "coordinates": [
      144.25788,
      -36.74305
    ]
  }
}