{
  "type": "Feature",
  "properties": {
    "name": "Lower Plenty",
    "country": "AU",
    "subdivision": "07",
    "timezone": "Australia/Melbourne"
  },
  "geometry": {
    "type": "Point",
    "coordinates": [
      145.11667,
      -37.73333
    ]
  }
}