{
  "type": "Feature",
  "properties": {
    "name": "Middle Park",
    "country": "AU",
    "subdivision": "07",
    "timezone": "Australia/Melbourne"
  },
  "geometry": {
    "type": "Point",
    "coordinates": [
      144.96201,
      -37.85116
    ]
  }
}