{
  "type": "Feature",
  "properties": {
    "name": "Millgrove",
    "country": "AU",
    "subdivision": "07",
    "timezone": "Australia/Melbourne"
  },
  "geometry": {
    "type": "Point",
    "coordinates": [
      145.65347,
      -37.75527
    ]
  }
}