{
  "type": "Feature",
  "properties": {
    "name": "Moe",
    "country": "AU",
    "subdivision": "07",
    "timezone": "Australia/Melbourne"
  },
  "geometry": {
    "type": "Point",
    "coordinates": [
      146.26099,
      -38.17828
    ]
  }
}