{
  "type": "Feature",
  "properties": {
    "name": "Mornington",
    "country": "AU",
    "subdivision": "07",
    "timezone": "Australia/Melbourne"
  },
  "geometry": {
    "type": "Point",
    "coordinates": [
      145.03876,
      -38.21792
    ]
  }
}