{
  "type": "Feature",
  "properties": {
    "name": "Mulgrave",
    "country": "AU",
    "subdivision": "07",
    "timezone": "Australia/Melbourne"
  },
  "geometry": {
    "type": "Point",
    "coordinates": [
      145.17708,
      -37.92845
    ]
  }
}