{
  "type": "Feature",
  "properties": {
    "name": "Nathalia",
    "country": "AU",
    "subdivision": "07",
    "timezone": "Australia/Melbourne"
  },
  "geometry": {
    "type": "Point",
    "coordinates": [
      145.20406,
      -36.05772
    ]
  }
}