{
  "type": "Feature",
  "properties": {
    "name": "North Warrandyte",
    "country": "AU",
    "subdivision": "07",
    "timezone": "Australia/Melbourne"
  },
  "geometry": {
    "type": "Point",
    "coordinates": [
      145.21574,
      -37.72924
    ]
  }
}