{
  "type": "Feature",
  "properties": {
    "name": "Olinda",
    "country": "AU",
    "subdivision": "07",
    "timezone": "Australia/Melbourne"
  },
  "geometry": {
    "type": "Point",
    "coordinates": [
      145.36667,
      -37.85
    ]
  }
}