{
  "type": "Feature",
  "properties": {
    "name": "Panton Hill",
    "country": "AU",
    "subdivision": "07",
    "timezone": "Australia/Melbourne"
  },
  "geometry": {
    "type": "Point",
    "coordinates": [
      145.23991,
      -37.64082
    ]
  }
}