{
  "type": "Feature",
  "properties": {
    "name": "Pascoe Vale South",
    "country": "AU",
    "subdivision": "07",
    "timezone": "Australia/Melbourne"
  },
  "geometry": {
    "type": "Point",
    "coordinates": [
      144.94615,
      -37.73973
    ]
  }
}