{
  "type": "Feature",
  "properties": {
    "name": "Prahran",
    "country": "AU",
    "subdivision": "07",
    "timezone": "Australia/Melbourne"
  },
  "geometry": {
    "type": "Point",
    "coordinates": [
      144.99318,
      -37.85114
    ]
  }
}