{
  "type": "Feature",
  "properties": {
    "name": "Princes Hill",
    "country": "AU",
    "subdivision": "07",
    "timezone": "Australia/Melbourne"
  },
  "geometry": {
    "type": "Point",
    "coordinates": [
      144.96656,
      -37.78185
    ]
  }
}