{
  "type": "Feature",
  "properties": {
    "name": "Red Cliffs",
    "country": "AU",
    "subdivision": "07",
    "timezone": "Australia/Melbourne"
  },
  "geometry": {
    "type": "Point",
    "coordinates": [
      142.18971,
      -34.30942
    ]
  }
}