{
  "type": "Feature",
  "properties": {
    "name": "Ringwood",
    "country": "AU",
    "subdivision": "07",
    "timezone": "Australia/Melbourne"
  },
  "geometry": {
    "type": "Point",
    "coordinates": [
      145.23333,
      -37.81667
    ]
  }
}