{
  "type": "Feature",
  "properties": {
    "name": "Ross Creek",
    "country": "AU",
    "subdivision": "07",
    "timezone": "Australia/Melbourne"
  },
  "geometry": {
    "type": "Point",
    "coordinates": [
      143.75,
      -37.65
    ]
  }
}