{
  "type": "Feature",
  "properties": {
    "name": "Rye",
    "country": "AU",
    "subdivision": "07",
    "timezone": "Australia/Melbourne"
  },
  "geometry": {
    "type": "Point",
    "coordinates": [
      144.81221,
      -38.38528
    ]
  }
}