{
  "type": "Feature",
  "properties": {
    "name": "Springvale South",
    "country": "AU",
    "subdivision": "07",
    "timezone": "Australia/Melbourne"
  },
  "geometry": {
    "type": "Point",
    "coordinates": [
      145.15,
      -37.96667
    ]
  }
}