{
  "type": "Feature",
  "properties": {
    "name": "St Kilda East",
    "country": "AU",
    "subdivision": "07",
    "timezone": "Australia/Melbourne"
  },
  "geometry": {
    "type": "Point",
    "coordinates": [
      145.00018,
      -37.86594
    ]
  }
}