{
  "type": "Feature",
  "properties": {
    "name": "Sunshine West",
    "country": "AU",
    "subdivision": "07",
    "timezone": "Australia/Melbourne"
  },
  "geometry": {
    "type": "Point",
    "coordinates": [
      144.81637,
      -37.79117
    ]
  }
}