{
  "type": "Feature",
  "properties": {
    "name": "Thornbury",
    "country": "AU",
    "subdivision": "07",
    "timezone": "Australia/Melbourne"
  },
  "geometry": {
    "type": "Point",
    "coordinates": [
      145.00583,
      -37.75819
    ]
  }
}