{
  "type": "Feature",
  "properties": {
    "name": "Trafalgar",
    "country": "AU",
    "subdivision": "07",
    "timezone": "Australia/Melbourne"
  },
  "geometry": {
    "type": "Point",
    "coordinates": [
      146.15347,
      -38.20906
    ]
  }
}