{
  "type": "Feature",
  "properties": {
    "name": "Traralgon",
    "country": "AU",
    "subdivision": "07",
    "timezone": "Australia/Melbourne"
  },
  "geometry": {
    "type": "Point",
    "coordinates": [
      146.5415,
      -38.19528
    ]
  }
}