{
  "type": "Feature",
  "properties": {
    "name": "Vermont South",
    "country": "AU",
    "subdivision": "07",
    "timezone": "Australia/Melbourne"
  },
  "geometry": {
    "type": "Point",
    "coordinates": [
      145.1827,
      -37.85747
    ]
  }
}