{
  "type": "Feature",
  "properties": {
    "name": "Vermont",
    "country": "AU",
    "subdivision": "07",
    "timezone": "Australia/Melbourne"
  },
  "geometry": {
    "type": "Point",
    "coordinates": [
      145.19428,
      -37.83616
    ]
  }
}