{
  "type": "Feature",
  "properties": {
    "name": "Waurn Ponds",
    "country": "AU",
    "subdivision": "07",
    "timezone": "Australia/Melbourne"
  },
  "geometry": {
    "type": "Point",
    "coordinates": [
      144.28333,
      -38.21667
    ]
  }
}