{
  "type": "Feature",
  "properties": {
    "name": "Whittington",
    "country": "AU",
    "subdivision": "07",
    "timezone": "Australia/Melbourne"
  },
  "geometry": {
    "type": "Point",
    "coordinates": [
      144.39322,
      -38.1808
    ]
  }
}