{
  "type": "Feature",
  "properties": {
    "name": "Woodend",
    "country": "AU",
    "subdivision": "07",
    "timezone": "Australia/Melbourne"
  },
  "geometry": {
    "type": "Point",
    "coordinates": [
      144.52902,
      -37.35469
    ]
  }
}