{
  "type": "Feature",
  "properties": {
    "name": "Archis",
    "country": "AM",
    "subdivision": "09",
    "timezone": "Asia/Yerevan"
  },
  "geometry": {
    "type": "Point",
    "coordinates": [
      44.87631,
      41.16351
    ]
  }
}