{
  "type": "Feature",
  "properties": {
    "name": "Ijevan",
    "country": "AM",
    "subdivision": "09",
    "timezone": "Asia/Yerevan"
  },
  "geometry": {
    "type": "Point",
    "coordinates": [
      45.14851,
      40.87877
    ]
  }
}