{
  "type": "Feature",
  "properties": {
    "name": "Dindima",
    "country": "NG",
    "subdivision": "46",
    "timezone": "Africa/Lagos"
  },
  "geometry": {
    "type": "Point",
    "coordinates": [
      10.15132,
      10.22629
    ]
  }
}