{
  "type": "Feature",
  "properties": {
    "name": "Misau",
    "country": "NG",
    "subdivision": "46",
    "timezone": "Africa/Lagos"
  },
  "geometry": {
    "type": "Point",
    "coordinates": [
      10.46664,
      11.3137
    ]
  }
}