{
  "type": "Feature",
  "properties": {
    "name": "Yamrat",
    "country": "NG",
    "subdivision": "46",
    "timezone": "Africa/Lagos"
  },
  "geometry": {
    "type": "Point",
    "coordinates": [
      9.82604,
      10.11161
    ]
  }
}