{
  "type": "Feature",
  "properties": {
    "name": "Yuli",
    "country": "NG",
    "subdivision": "46",
    "timezone": "Africa/Lagos"
  },
  "geometry": {
    "type": "Point",
    "coordinates": [
      10.2735,
      9.69707
    ]
  }
}