{
  "type": "Feature",
  "properties": {
    "name": "Jõhvi",
    "country": "EE",
    "subdivision": "03",
    "timezone": "Europe/Tallinn"
  },
  "geometry": {
    "type": "Point",
    "coordinates": [
      27.42111,
      59.35917
    ]
  }
}