{
  "type": "Feature",
  "properties": {
    "name": "Voka",
    "country": "EE",
    "subdivision": "03",
    "timezone": "Europe/Tallinn"
  },
  "geometry": {
    "type": "Point",
    "coordinates": [
      27.58263,
      59.40776
    ]
  }
}