{
  "type": "Feature",
  "properties": {
    "name": "Akron",
    "country": "US",
    "subdivision": "IN",
    "timezone": "America/Indiana/Indianapolis"
  },
  "geometry": {
    "type": "Point",
    "coordinates": [
      -86.02805,
      41.03838
    ]
  }
}