{
  "type": "Feature",
  "properties": {
    "name": "Andrews",
    "country": "US",
    "subdivision": "IN",
    "timezone": "America/Indiana/Indianapolis"
  },
  "geometry": {
    "type": "Point",
    "coordinates": [
      -85.60165,
      40.86254
    ]
  }
}