{
  "type": "Feature",
  "properties": {
    "name": "Attica",
    "country": "US",
    "subdivision": "IN",
    "timezone": "America/Indiana/Indianapolis"
  },
  "geometry": {
    "type": "Point",
    "coordinates": [
      -87.2489,
      40.2942
    ]
  }
}