{
  "type": "Feature",
  "properties": {
    "name": "Austin",
    "country": "US",
    "subdivision": "IN",
    "timezone": "America/Indiana/Indianapolis"
  },
  "geometry": {
    "type": "Point",
    "coordinates": [
      -85.80803,
      38.75839
    ]
  }
}