{
  "type": "Feature",
  "properties": {
    "name": "Bourbon",
    "country": "US",
    "subdivision": "IN",
    "timezone": "America/Indiana/Indianapolis"
  },
  "geometry": {
    "type": "Point",
    "coordinates": [
      -86.11639,
      41.2956
    ]
  }
}