{
  "type": "Feature",
  "properties": {
    "name": "Brooklyn",
    "country": "US",
    "subdivision": "IN",
    "timezone": "America/Indiana/Indianapolis"
  },
  "geometry": {
    "type": "Point",
    "coordinates": [
      -86.36916,
      39.53921
    ]
  }
}