{
  "type": "Feature",
  "properties": {
    "name": "Cayuga",
    "country": "US",
    "subdivision": "IN",
    "timezone": "America/Indiana/Indianapolis"
  },
  "geometry": {
    "type": "Point",
    "coordinates": [
      -87.45974,
      39.94865
    ]
  }
}