{
  "type": "Feature",
  "properties": {
    "name": "Cedar Lake",
    "country": "US",
    "subdivision": "IN",
    "timezone": "America/Chicago"
  },
  "geometry": {
    "type": "Point",
    "coordinates": [
      -87.44115,
      41.36476
    ]
  }
}