{
  "type": "Feature",
  "properties": {
    "name": "Columbia City",
    "country": "US",
    "subdivision": "IN",
    "timezone": "America/Indiana/Indianapolis"
  },
  "geometry": {
    "type": "Point",
    "coordinates": [
      -85.48831,
      41.15727
    ]
  }
}