{
  "type": "Feature",
  "properties": {
    "name": "Covington",
    "country": "US",
    "subdivision": "IN",
    "timezone": "America/Indiana/Indianapolis"
  },
  "geometry": {
    "type": "Point",
    "coordinates": [
      -87.39474,
      40.1417
    ]
  }
}