{
  "type": "Feature",
  "properties": {
    "name": "Culver",
    "country": "US",
    "subdivision": "IN",
    "timezone": "America/Indiana/Indianapolis"
  },
  "geometry": {
    "type": "Point",
    "coordinates": [
      -86.42306,
      41.21893
    ]
  }
}