{
  "type": "Feature",
  "properties": {
    "name": "Eaton",
    "country": "US",
    "subdivision": "IN",
    "timezone": "America/Indiana/Indianapolis"
  },
  "geometry": {
    "type": "Point",
    "coordinates": [
      -85.3508,
      40.34032
    ]
  }
}