{
  "type": "Feature",
  "properties": {
    "name": "Edinburgh",
    "country": "US",
    "subdivision": "IN",
    "timezone": "America/Indiana/Indianapolis"
  },
  "geometry": {
    "type": "Point",
    "coordinates": [
      -85.96666,
      39.35422
    ]
  }
}