{
  "type": "Feature",
  "properties": {
    "name": "Fish Lake",
    "country": "US",
    "subdivision": "IN",
    "timezone": "America/Chicago"
  },
  "geometry": {
    "type": "Point",
    "coordinates": [
      -86.55196,
      41.56671
    ]
  }
}