{
  "type": "Feature",
  "properties": {
    "name": "Fortville",
    "country": "US",
    "subdivision": "IN",
    "timezone": "America/Indiana/Indianapolis"
  },
  "geometry": {
    "type": "Point",
    "coordinates": [
      -85.84804,
      39.93226
    ]
  }
}