{
  "type": "Feature",
  "properties": {
    "name": "Frankfort",
    "country": "US",
    "subdivision": "IN",
    "timezone": "America/Indiana/Indianapolis"
  },
  "geometry": {
    "type": "Point",
    "coordinates": [
      -86.51084,
      40.27948
    ]
  }
}