{
  "type": "Feature",
  "properties": {
    "name": "Gary",
    "country": "US",
    "subdivision": "IN",
    "timezone": "America/Chicago"
  },
  "geometry": {
    "type": "Point",
    "coordinates": [
      -87.34643,
      41.59337
    ]
  }
}