{
  "type": "Feature",
  "properties": {
    "name": "Greensburg",
    "country": "US",
    "subdivision": "IN",
    "timezone": "America/Indiana/Indianapolis"
  },
  "geometry": {
    "type": "Point",
    "coordinates": [
      -85.48358,
      39.33727
    ]
  }
}