{
  "type": "Feature",
  "properties": {
    "name": "Harlan",
    "country": "US",
    "subdivision": "IN",
    "timezone": "America/Indiana/Indianapolis"
  },
  "geometry": {
    "type": "Point",
    "coordinates": [
      -84.91969,
      41.19616
    ]
  }
}