{
  "type": "Feature",
  "properties": {
    "name": "Indianapolis",
    "country": "US",
    "subdivision": "IN",
    "timezone": "America/Indiana/Indianapolis"
  },
  "geometry": {
    "type": "Point",
    "coordinates": [
      -86.15804,
      39.76838
    ]
  }
}