{
  "type": "Feature",
  "properties": {
    "name": "Ingalls",
    "country": "US",
    "subdivision": "IN",
    "timezone": "America/Indiana/Indianapolis"
  },
  "geometry": {
    "type": "Point",
    "coordinates": [
      -85.80526,
      39.95699
    ]
  }
}