{
  "type": "Feature",
  "properties": {
    "name": "Kokomo",
    "country": "US",
    "subdivision": "IN",
    "timezone": "America/Indiana/Indianapolis"
  },
  "geometry": {
    "type": "Point",
    "coordinates": [
      -86.1336,
      40.48643
    ]
  }
}