{
  "type": "Feature",
  "properties": {
    "name": "Lakes of the Four Seasons",
    "country": "US",
    "subdivision": "IN",
    "timezone": "America/Chicago"
  },
  "geometry": {
    "type": "Point",
    "coordinates": [
      -87.21309,
      41.41032
    ]
  }
}