{
  "type": "Feature",
  "properties": {
    "name": "Lebanon",
    "country": "US",
    "subdivision": "IN",
    "timezone": "America/Indiana/Indianapolis"
  },
  "geometry": {
    "type": "Point",
    "coordinates": [
      -86.46917,
      40.04837
    ]
  }
}