{
  "type": "Feature",
  "properties": {
    "name": "Linton",
    "country": "US",
    "subdivision": "IN",
    "timezone": "America/Indiana/Indianapolis"
  },
  "geometry": {
    "type": "Point",
    "coordinates": [
      -87.16585,
      39.03477
    ]
  }
}