{
  "type": "Feature",
  "properties": {
    "name": "Melody Hill",
    "country": "US",
    "subdivision": "IN",
    "timezone": "America/Chicago"
  },
  "geometry": {
    "type": "Point",
    "coordinates": [
      -87.51585,
      38.02615
    ]
  }
}