{
  "type": "Feature",
  "properties": {
    "name": "Middletown",
    "country": "US",
    "subdivision": "IN",
    "timezone": "America/Indiana/Indianapolis"
  },
  "geometry": {
    "type": "Point",
    "coordinates": [
      -85.5372,
      40.05727
    ]
  }
}