{
  "type": "Feature",
  "properties": {
    "name": "Mount Vernon",
    "country": "US",
    "subdivision": "IN",
    "timezone": "America/Chicago"
  },
  "geometry": {
    "type": "Point",
    "coordinates": [
      -87.89503,
      37.93227
    ]
  }
}