{
  "type": "Feature",
  "properties": {
    "name": "Nashville",
    "country": "US",
    "subdivision": "IN",
    "timezone": "America/Indiana/Indianapolis"
  },
  "geometry": {
    "type": "Point",
    "coordinates": [
      -86.2511,
      39.20727
    ]
  }
}