{
  "type": "Feature",
  "properties": {
    "name": "Pittsboro",
    "country": "US",
    "subdivision": "IN",
    "timezone": "America/Indiana/Indianapolis"
  },
  "geometry": {
    "type": "Point",
    "coordinates": [
      -86.46694,
      39.86393
    ]
  }
}