{
  "type": "Feature",
  "properties": {
    "name": "Princeton",
    "country": "US",
    "subdivision": "IN",
    "timezone": "America/Chicago"
  },
  "geometry": {
    "type": "Point",
    "coordinates": [
      -87.56752,
      38.35532
    ]
  }
}