{
  "type": "Feature",
  "properties": {
    "name": "Russiaville",
    "country": "US",
    "subdivision": "IN",
    "timezone": "America/Indiana/Indianapolis"
  },
  "geometry": {
    "type": "Point",
    "coordinates": [
      -86.27138,
      40.41754
    ]
  }
}