{
  "type": "Feature",
  "properties": {
    "name": "Seymour",
    "country": "US",
    "subdivision": "IN",
    "timezone": "America/Indiana/Indianapolis"
  },
  "geometry": {
    "type": "Point",
    "coordinates": [
      -85.89025,
      38.95922
    ]
  }
}