{
  "type": "Feature",
  "properties": {
    "name": "Smithville-Sanders",
    "country": "US",
    "subdivision": "IN",
    "timezone": "America/Indiana/Indianapolis"
  },
  "geometry": {
    "type": "Point",
    "coordinates": [
      -86.51077,
      39.05969
    ]
  }
}