{
  "type": "Feature",
  "properties": {
    "name": "South Whitley",
    "country": "US",
    "subdivision": "IN",
    "timezone": "America/Indiana/Indianapolis"
  },
  "geometry": {
    "type": "Point",
    "coordinates": [
      -85.62804,
      41.08477
    ]
  }
}