{
  "type": "Feature",
  "properties": {
    "name": "Spencer",
    "country": "US",
    "subdivision": "IN",
    "timezone": "America/Indiana/Indianapolis"
  },
  "geometry": {
    "type": "Point",
    "coordinates": [
      -86.76251,
      39.28671
    ]
  }
}