{
  "type": "Feature",
  "properties": {
    "name": "Sweetser",
    "country": "US",
    "subdivision": "IN",
    "timezone": "America/Indiana/Indianapolis"
  },
  "geometry": {
    "type": "Point",
    "coordinates": [
      -85.76915,
      40.57198
    ]
  }
}