{
  "type": "Feature",
  "properties": {
    "name": "Thorntown",
    "country": "US",
    "subdivision": "IN",
    "timezone": "America/Indiana/Indianapolis"
  },
  "geometry": {
    "type": "Point",
    "coordinates": [
      -86.60667,
      40.12948
    ]
  }
}