{
  "type": "Feature",
  "properties": {
    "name": "Vincennes",
    "country": "US",
    "subdivision": "IN",
    "timezone": "America/Indiana/Vincennes"
  },
  "geometry": {
    "type": "Point",
    "coordinates": [
      -87.52863,
      38.67727
    ]
  }
}