{
  "type": "Feature",
  "properties": {
    "name": "Winona Lake",
    "country": "US",
    "subdivision": "IN",
    "timezone": "America/Indiana/Indianapolis"
  },
  "geometry": {
    "type": "Point",
    "coordinates": [
      -85.82193,
      41.22727
    ]
  }
}