{
  "type": "Feature",
  "properties": {
    "name": "Goričan",
    "country": "HR",
    "subdivision": "09",
    "timezone": "Europe/Zagreb"
  },
  "geometry": {
    "type": "Point",
    "coordinates": [
      16.68083,
      46.38417
    ]
  }
}