{
  "type": "Feature",
  "properties": {
    "name": "Mala Subotica",
    "country": "HR",
    "subdivision": "09",
    "timezone": "Europe/Zagreb"
  },
  "geometry": {
    "type": "Point",
    "coordinates": [
      16.52893,
      46.37616
    ]
  }
}