{
  "type": "Feature",
  "properties": {
    "name": "Mihovljan",
    "country": "HR",
    "subdivision": "09",
    "timezone": "Europe/Zagreb"
  },
  "geometry": {
    "type": "Point",
    "coordinates": [
      16.44627,
      46.40586
    ]
  }
}