{
  "type": "Feature",
  "properties": {
    "name": "Pribislavec",
    "country": "HR",
    "subdivision": "09",
    "timezone": "Europe/Zagreb"
  },
  "geometry": {
    "type": "Point",
    "coordinates": [
      16.4825,
      46.3925
    ]
  }
}