{
  "type": "Feature",
  "properties": {
    "name": "kankrabari Dovan",
    "country": "NP",
    "subdivision": "3",
    "timezone": "Asia/Kathmandu"
  },
  "geometry": {
    "type": "Point",
    "coordinates": [
      85.45934,
      27.62881
    ]
  }
}