{
  "type": "Feature",
  "properties": {
    "name": "Tyuratam",
    "country": "KZ",
    "subdivision": "08",
    "timezone": "Asia/Qostanay"
  },
  "geometry": {
    "type": "Point",
    "coordinates": [
      63.31163,
      45.65005
    ]
  }
}