{
  "type": "Feature",
  "properties": {
    "name": "Mayna",
    "country": "RU",
    "subdivision": "31",
    "timezone": "Asia/Krasnoyarsk"
  },
  "geometry": {
    "type": "Point",
    "coordinates": [
      91.48361,
      53.00639
    ]
  }
}