{
  "type": "Feature",
  "properties": {
    "name": "Abadzekhskaya",
    "country": "RU",
    "subdivision": "01",
    "timezone": "Europe/Moscow"
  },
  "geometry": {
    "type": "Point",
    "coordinates": [
      40.22139,
      44.39389
    ]
  }
}