{
  "type": "Feature",
  "properties": {
    "name": "Natyrbovo",
    "country": "RU",
    "subdivision": "01",
    "timezone": "Europe/Moscow"
  },
  "geometry": {
    "type": "Point",
    "coordinates": [
      40.62639,
      44.73
    ]
  }
}