{
  "type": "Feature",
  "properties": {
    "name": "Beneditinos",
    "country": "BR",
    "subdivision": "20",
    "timezone": "America/Fortaleza"
  },
  "geometry": {
    "type": "Point",
    "coordinates": [
      -42.36667,
      -5.45
    ]
  }
}