{
  "type": "Feature",
  "properties": {
    "name": "Elesbão Veloso",
    "country": "BR",
    "subdivision": "20",
    "timezone": "America/Fortaleza"
  },
  "geometry": {
    "type": "Point",
    "coordinates": [
      -42.14028,
      -6.20194
    ]
  }
}