{
  "type": "Feature",
  "properties": {
    "name": "Esperantina",
    "country": "BR",
    "subdivision": "20",
    "timezone": "America/Fortaleza"
  },
  "geometry": {
    "type": "Point",
    "coordinates": [
      -42.23361,
      -3.90167
    ]
  }
}