{
  "type": "Feature",
  "properties": {
    "name": "Inhuma",
    "country": "BR",
    "subdivision": "20",
    "timezone": "America/Fortaleza"
  },
  "geometry": {
    "type": "Point",
    "coordinates": [
      -41.70778,
      -6.66833
    ]
  }
}