{
  "type": "Feature",
  "properties": {
    "name": "Matias Olímpio",
    "country": "BR",
    "subdivision": "20",
    "timezone": "America/Fortaleza"
  },
  "geometry": {
    "type": "Point",
    "coordinates": [
      -42.55556,
      -3.71583
    ]
  }
}