{
  "type": "Feature",
  "properties": {
    "name": "São Raimundo Nonato",
    "country": "BR",
    "subdivision": "20",
    "timezone": "America/Fortaleza"
  },
  "geometry": {
    "type": "Point",
    "coordinates": [
      -42.69944,
      -9.01528
    ]
  }
}