{
  "type": "Feature",
  "properties": {
    "name": "Vorë",
    "country": "AL",
    "subdivision": "50",
    "timezone": "Europe/Tirane"
  },
  "geometry": {
    "type": "Point",
    "coordinates": [
      19.655,
      41.39083
    ]
  }
}