{
  "type": "Feature",
  "properties": {
    "name": "Shahre Jadide Andisheh",
    "country": "IR",
    "subdivision": "26",
    "timezone": "Asia/Tehran"
  },
  "geometry": {
    "type": "Point",
    "coordinates": [
      51.0193,
      35.6803
    ]
  }
}