{
  "type": "Feature",
  "properties": {
    "name": "Soleh Bon",
    "country": "IR",
    "subdivision": "26",
    "timezone": "Asia/Tehran"
  },
  "geometry": {
    "type": "Point",
    "coordinates": [
      52.56091,
      35.76841
    ]
  }
}