{
  "type": "Feature",
  "properties": {
    "name": "Tehran",
    "country": "IR",
    "subdivision": "26",
    "timezone": "Asia/Tehran"
  },
  "geometry": {
    "type": "Point",
    "coordinates": [
      51.42151,
      35.69439
    ]
  }
}