{
  "type": "Feature",
  "properties": {
    "name": "Ake-Eze",
    "country": "NG",
    "subdivision": "47",
    "timezone": "Africa/Lagos"
  },
  "geometry": {
    "type": "Point",
    "coordinates": [
      7.67615,
      5.91677
    ]
  }
}