{
  "type": "Feature",
  "properties": {
    "name": "Ete",
    "country": "NG",
    "subdivision": "47",
    "timezone": "Africa/Lagos"
  },
  "geometry": {
    "type": "Point",
    "coordinates": [
      7.45341,
      7.08956
    ]
  }
}