{
  "type": "Feature",
  "properties": {
    "name": "Opi",
    "country": "NG",
    "subdivision": "47",
    "timezone": "Africa/Lagos"
  },
  "geometry": {
    "type": "Point",
    "coordinates": [
      7.43319,
      6.78223
    ]
  }
}