{
  "type": "Feature",
  "properties": {
    "name": "Udi",
    "country": "NG",
    "subdivision": "47",
    "timezone": "Africa/Lagos"
  },
  "geometry": {
    "type": "Point",
    "coordinates": [
      7.42086,
      6.31592
    ]
  }
}