{
  "type": "Feature",
  "properties": {
    "name": "Gárdony",
    "country": "HU",
    "subdivision": "08",
    "timezone": "Europe/Budapest"
  },
  "geometry": {
    "type": "Point",
    "coordinates": [
      18.63607,
      47.20942
    ]
  }
}