{
  "type": "Feature",
  "properties": {
    "name": "Bozdar Wada",
    "country": "PK",
    "subdivision": "05",
    "timezone": "Asia/Karachi"
  },
  "geometry": {
    "type": "Point",
    "coordinates": [
      68.6358,
      27.183
    ]
  }
}