{
  "type": "Feature",
  "properties": {
    "name": "Dadu",
    "country": "PK",
    "subdivision": "05",
    "timezone": "Asia/Karachi"
  },
  "geometry": {
    "type": "Point",
    "coordinates": [
      67.7769,
      26.73033
    ]
  }
}