{
  "type": "Feature",
  "properties": {
    "name": "Diplo",
    "country": "PK",
    "subdivision": "05",
    "timezone": "Asia/Karachi"
  },
  "geometry": {
    "type": "Point",
    "coordinates": [
      69.58114,
      24.46688
    ]
  }
}