{
  "type": "Feature",
  "properties": {
    "name": "Gambat",
    "country": "PK",
    "subdivision": "05",
    "timezone": "Asia/Karachi"
  },
  "geometry": {
    "type": "Point",
    "coordinates": [
      68.5215,
      27.3517
    ]
  }
}