{
  "type": "Feature",
  "properties": {
    "name": "Goth Radhan",
    "country": "PK",
    "subdivision": "05",
    "timezone": "Asia/Karachi"
  },
  "geometry": {
    "type": "Point",
    "coordinates": [
      67.95348,
      27.19846
    ]
  }
}