{
  "type": "Feature",
  "properties": {
    "name": "Hala",
    "country": "PK",
    "subdivision": "05",
    "timezone": "Asia/Karachi"
  },
  "geometry": {
    "type": "Point",
    "coordinates": [
      68.42198,
      25.81459
    ]
  }
}