{
  "type": "Feature",
  "properties": {
    "name": "Khairpur Nathan Shah",
    "country": "PK",
    "subdivision": "05",
    "timezone": "Asia/Karachi"
  },
  "geometry": {
    "type": "Point",
    "coordinates": [
      67.73489,
      27.09064
    ]
  }
}