{
  "type": "Feature",
  "properties": {
    "name": "Madeji",
    "country": "PK",
    "subdivision": "05",
    "timezone": "Asia/Karachi"
  },
  "geometry": {
    "type": "Point",
    "coordinates": [
      68.45166,
      27.75314
    ]
  }
}