{
  "type": "Feature",
  "properties": {
    "name": "Miro Khan",
    "country": "PK",
    "subdivision": "05",
    "timezone": "Asia/Karachi"
  },
  "geometry": {
    "type": "Point",
    "coordinates": [
      68.09195,
      27.75985
    ]
  }
}