{
  "type": "Feature",
  "properties": {
    "name": "Nasirabad",
    "country": "PK",
    "subdivision": "05",
    "timezone": "Asia/Karachi"
  },
  "geometry": {
    "type": "Point",
    "coordinates": [
      67.91644,
      27.38137
    ]
  }
}