{
  "type": "Feature",
  "properties": {
    "name": "Setharja Old",
    "country": "PK",
    "subdivision": "05",
    "timezone": "Asia/Karachi"
  },
  "geometry": {
    "type": "Point",
    "coordinates": [
      68.46883,
      27.2127
    ]
  }
}