{
  "type": "Feature",
  "properties": {
    "name": "Shahdadpur",
    "country": "PK",
    "subdivision": "05",
    "timezone": "Asia/Karachi"
  },
  "geometry": {
    "type": "Point",
    "coordinates": [
      68.6228,
      25.92539
    ]
  }
}