{
  "type": "Feature",
  "properties": {
    "name": "Tangwani",
    "country": "PK",
    "subdivision": "05",
    "timezone": "Asia/Karachi"
  },
  "geometry": {
    "type": "Point",
    "coordinates": [
      68.9976,
      28.27886
    ]
  }
}