{
  "type": "Feature",
  "properties": {
    "name": "Thul",
    "country": "PK",
    "subdivision": "05",
    "timezone": "Asia/Karachi"
  },
  "geometry": {
    "type": "Point",
    "coordinates": [
      68.7755,
      28.2403
    ]
  }
}