{
  "type": "Feature",
  "properties": {
    "name": "Güinope",
    "country": "HN",
    "subdivision": "07",
    "timezone": "America/Tegucigalpa"
  },
  "geometry": {
    "type": "Point",
    "coordinates": [
      -86.93333,
      13.88333
    ]
  }
}