{
  "type": "Feature",
  "properties": {
    "name": "Morocelí",
    "country": "HN",
    "subdivision": "07",
    "timezone": "America/Tegucigalpa"
  },
  "geometry": {
    "type": "Point",
    "coordinates": [
      -86.86667,
      14.11667
    ]
  }
}