{
  "type": "Feature",
  "properties": {
    "name": "San Diego",
    "country": "HN",
    "subdivision": "07",
    "timezone": "America/Tegucigalpa"
  },
  "geometry": {
    "type": "Point",
    "coordinates": [
      -86.46667,
      14.05
    ]
  }
}