{
  "type": "Feature",
  "properties": {
    "name": "Alcantarilha",
    "country": "PT",
    "subdivision": "09",
    "timezone": "Europe/Lisbon"
  },
  "geometry": {
    "type": "Point",
    "coordinates": [
      -8.34623,
      37.13044
    ]
  }
}