{
  "type": "Feature",
  "properties": {
    "name": "Estômbar",
    "country": "PT",
    "subdivision": "09",
    "timezone": "Europe/Lisbon"
  },
  "geometry": {
    "type": "Point",
    "coordinates": [
      -8.48505,
      37.14629
    ]
  }
}