{
  "type": "Feature",
  "properties": {
    "name": "Marmelete",
    "country": "PT",
    "subdivision": "09",
    "timezone": "Europe/Lisbon"
  },
  "geometry": {
    "type": "Point",
    "coordinates": [
      -8.66813,
      37.31014
    ]
  }
}