{
  "type": "Feature",
  "properties": {
    "name": "Pêra",
    "country": "PT",
    "subdivision": "09",
    "timezone": "Europe/Lisbon"
  },
  "geometry": {
    "type": "Point",
    "coordinates": [
      -8.34115,
      37.12296
    ]
  }
}