{
  "type": "Feature",
  "properties": {
    "name": "São Marcos da Serra",
    "country": "PT",
    "subdivision": "09",
    "timezone": "Europe/Lisbon"
  },
  "geometry": {
    "type": "Point",
    "coordinates": [
      -8.37764,
      37.361
    ]
  }
}