{
  "type": "Feature",
  "properties": {
    "name": "Silves",
    "country": "PT",
    "subdivision": "09",
    "timezone": "Europe/Lisbon"
  },
  "geometry": {
    "type": "Point",
    "coordinates": [
      -8.43822,
      37.18921
    ]
  }
}