{
  "type": "Feature",
  "properties": {
    "name": "Tunes",
    "country": "PT",
    "subdivision": "09",
    "timezone": "Europe/Lisbon"
  },
  "geometry": {
    "type": "Point",
    "coordinates": [
      -8.25919,
      37.16592
    ]
  }
}