{
  "type": "Feature",
  "properties": {
    "name": "Burlin",
    "country": "KZ",
    "subdivision": "07",
    "timezone": "Asia/Oral"
  },
  "geometry": {
    "type": "Point",
    "coordinates": [
      52.71392,
      51.42724
    ]
  }
}