{
  "type": "Feature",
  "properties": {
    "name": "Chingirlau",
    "country": "KZ",
    "subdivision": "07",
    "timezone": "Asia/Oral"
  },
  "geometry": {
    "type": "Point",
    "coordinates": [
      54.08426,
      51.09878
    ]
  }
}