{
  "type": "Feature",
  "properties": {
    "name": "Krūgloozernoe",
    "country": "KZ",
    "subdivision": "07",
    "timezone": "Asia/Oral"
  },
  "geometry": {
    "type": "Point",
    "coordinates": [
      51.28992,
      51.07854
    ]
  }
}