{
  "type": "Feature",
  "properties": {
    "name": "Gualán",
    "country": "GT",
    "subdivision": "22",
    "timezone": "America/Guatemala"
  },
  "geometry": {
    "type": "Point",
    "coordinates": [
      -89.35721,
      15.11952
    ]
  }
}