{
  "type": "Feature",
  "properties": {
    "name": "Diu",
    "country": "IN",
    "subdivision": "52",
    "timezone": "Asia/Kolkata"
  },
  "geometry": {
    "type": "Point",
    "coordinates": [
      70.98224,
      20.71405
    ]
  }
}