{
  "type": "Feature",
  "properties": {
    "name": "Mafinga",
    "country": "TZ",
    "subdivision": "04",
    "timezone": "Africa/Dar_es_Salaam"
  },
  "geometry": {
    "type": "Point",
    "coordinates": [
      35.06667,
      -7.25
    ]
  }
}