{
  "type": "Feature",
  "properties": {
    "name": "Ban Dung",
    "country": "TH",
    "subdivision": "76",
    "timezone": "Asia/Bangkok"
  },
  "geometry": {
    "type": "Point",
    "coordinates": [
      103.25957,
      17.699
    ]
  }
}