{
  "type": "Feature",
  "properties": {
    "name": "Log pri Brezovici",
    "country": "SI",
    "subdivision": "O4",
    "timezone": "Europe/Ljubljana"
  },
  "geometry": {
    "type": "Point",
    "coordinates": [
      14.36667,
      46.01667
    ]
  }
}