{
  "type": "Feature",
  "properties": {
    "name": "Hazorasp",
    "country": "UZ",
    "subdivision": "05",
    "timezone": "Asia/Samarkand"
  },
  "geometry": {
    "type": "Point",
    "coordinates": [
      61.07417,
      41.31944
    ]
  }
}