{
  "type": "Feature",
  "properties": {
    "name": "Urganch",
    "country": "UZ",
    "subdivision": "05",
    "timezone": "Asia/Samarkand"
  },
  "geometry": {
    "type": "Point",
    "coordinates": [
      60.62057,
      41.55339
    ]
  }
}