{
  "type": "Feature",
  "properties": {
    "name": "Ban Ratsada",
    "country": "TH",
    "subdivision": "62",
    "timezone": "Asia/Bangkok"
  },
  "geometry": {
    "type": "Point",
    "coordinates": [
      98.40248,
      7.90963
    ]
  }
}