{
  "type": "Feature",
  "properties": {
    "name": "Nai Harn",
    "country": "TH",
    "subdivision": "62",
    "timezone": "Asia/Bangkok"
  },
  "geometry": {
    "type": "Point",
    "coordinates": [
      98.30661,
      7.77859
    ]
  }
}