{
  "type": "Feature",
  "properties": {
    "name": "El Obeid",
    "country": "SD",
    "subdivision": "56",
    "timezone": "Africa/Khartoum"
  },
  "geometry": {
    "type": "Point",
    "coordinates": [
      30.21669,
      13.18421
    ]
  }
}