{
  "type": "Feature",
  "properties": {
    "name": "Umm Ruwaba",
    "country": "SD",
    "subdivision": "56",
    "timezone": "Africa/Khartoum"
  },
  "geometry": {
    "type": "Point",
    "coordinates": [
      31.2158,
      12.9061
    ]
  }
}