{
  "type": "Feature",
  "properties": {
    "name": "Qaraçala",
    "country": "AZ",
    "subdivision": "49",
    "timezone": "Asia/Baku"
  },
  "geometry": {
    "type": "Point",
    "coordinates": [
      48.93792,
      39.81614
    ]
  }
}