{
  "type": "Feature",
  "properties": {
    "name": "Coatepeque",
    "country": "GT",
    "subdivision": "13",
    "timezone": "America/Guatemala"
  },
  "geometry": {
    "type": "Point",
    "coordinates": [
      -91.86426,
      14.70413
    ]
  }
}