{
  "type": "Feature",
  "properties": {
    "name": "Concepción Chiquirichapa",
    "country": "GT",
    "subdivision": "13",
    "timezone": "America/Guatemala"
  },
  "geometry": {
    "type": "Point",
    "coordinates": [
      -91.6236,
      14.8551
    ]
  }
}