{
  "type": "Feature",
  "properties": {
    "name": "La Esperanza",
    "country": "GT",
    "subdivision": "13",
    "timezone": "America/Guatemala"
  },
  "geometry": {
    "type": "Point",
    "coordinates": [
      -91.5614,
      14.87169
    ]
  }
}