{
  "type": "Feature",
  "properties": {
    "name": "San Francisco la Unión",
    "country": "GT",
    "subdivision": "13",
    "timezone": "America/Guatemala"
  },
  "geometry": {
    "type": "Point",
    "coordinates": [
      -91.54157,
      14.9235
    ]
  }
}