{
  "type": "Feature",
  "properties": {
    "name": "Ippy",
    "country": "CF",
    "subdivision": "11",
    "timezone": "Africa/Bangui"
  },
  "geometry": {
    "type": "Point",
    "coordinates": [
      21.22468,
      6.26793
    ]
  }
}