{
  "type": "Feature",
  "properties": {
    "name": "Bunker Hill",
    "country": "US",
    "subdivision": "OR",
    "timezone": "America/Los_Angeles"
  },
  "geometry": {
    "type": "Point",
    "coordinates": [
      -124.20483,
      43.35595
    ]
  }
}