{
  "type": "Feature",
  "properties": {
    "name": "Dallas",
    "country": "US",
    "subdivision": "OR",
    "timezone": "America/Los_Angeles"
  },
  "geometry": {
    "type": "Point",
    "coordinates": [
      -123.31705,
      44.91928
    ]
  }
}