{
  "type": "Feature",
  "properties": {
    "name": "Dayton",
    "country": "US",
    "subdivision": "OR",
    "timezone": "America/Los_Angeles"
  },
  "geometry": {
    "type": "Point",
    "coordinates": [
      -123.07621,
      45.22067
    ]
  }
}