{
  "type": "Feature",
  "properties": {
    "name": "Dundee",
    "country": "US",
    "subdivision": "OR",
    "timezone": "America/Los_Angeles"
  },
  "geometry": {
    "type": "Point",
    "coordinates": [
      -123.01094,
      45.27817
    ]
  }
}