{
  "type": "Feature",
  "properties": {
    "name": "Eugene",
    "country": "US",
    "subdivision": "OR",
    "timezone": "America/Los_Angeles"
  },
  "geometry": {
    "type": "Point",
    "coordinates": [
      -123.08675,
      44.05207
    ]
  }
}