{
  "type": "Feature",
  "properties": {
    "name": "Jennings Lodge",
    "country": "US",
    "subdivision": "OR",
    "timezone": "America/Los_Angeles"
  },
  "geometry": {
    "type": "Point",
    "coordinates": [
      -122.61259,
      45.39123
    ]
  }
}