{
  "type": "Feature",
  "properties": {
    "name": "John Day",
    "country": "US",
    "subdivision": "OR",
    "timezone": "America/Los_Angeles"
  },
  "geometry": {
    "type": "Point",
    "coordinates": [
      -118.95301,
      44.41599
    ]
  }
}