{
  "type": "Feature",
  "properties": {
    "name": "Keizer",
    "country": "US",
    "subdivision": "OR",
    "timezone": "America/Los_Angeles"
  },
  "geometry": {
    "type": "Point",
    "coordinates": [
      -123.02621,
      44.99012
    ]
  }
}