{
  "type": "Feature",
  "properties": {
    "name": "Lafayette",
    "country": "US",
    "subdivision": "OR",
    "timezone": "America/Los_Angeles"
  },
  "geometry": {
    "type": "Point",
    "coordinates": [
      -123.11483,
      45.24428
    ]
  }
}