{
  "type": "Feature",
  "properties": {
    "name": "Lincoln City",
    "country": "US",
    "subdivision": "OR",
    "timezone": "America/Los_Angeles"
  },
  "geometry": {
    "type": "Point",
    "coordinates": [
      -124.01789,
      44.95816
    ]
  }
}