{
  "type": "Feature",
  "properties": {
    "name": "Lyons",
    "country": "US",
    "subdivision": "OR",
    "timezone": "America/Los_Angeles"
  },
  "geometry": {
    "type": "Point",
    "coordinates": [
      -122.61509,
      44.77457
    ]
  }
}