{
  "type": "Feature",
  "properties": {
    "name": "Mill City",
    "country": "US",
    "subdivision": "OR",
    "timezone": "America/Los_Angeles"
  },
  "geometry": {
    "type": "Point",
    "coordinates": [
      -122.47814,
      44.75401
    ]
  }
}