{
  "type": "Feature",
  "properties": {
    "name": "Mulino",
    "country": "US",
    "subdivision": "OR",
    "timezone": "America/Los_Angeles"
  },
  "geometry": {
    "type": "Point",
    "coordinates": [
      -122.58203,
      45.22151
    ]
  }
}