{
  "type": "Feature",
  "properties": {
    "name": "North Plains",
    "country": "US",
    "subdivision": "OR",
    "timezone": "America/Los_Angeles"
  },
  "geometry": {
    "type": "Point",
    "coordinates": [
      -122.99344,
      45.59706
    ]
  }
}