{
  "type": "Feature",
  "properties": {
    "name": "Oakridge",
    "country": "US",
    "subdivision": "OR",
    "timezone": "America/Los_Angeles"
  },
  "geometry": {
    "type": "Point",
    "coordinates": [
      -122.46172,
      43.74651
    ]
  }
}