{
  "type": "Feature",
  "properties": {
    "name": "Oatfield",
    "country": "US",
    "subdivision": "OR",
    "timezone": "America/Los_Angeles"
  },
  "geometry": {
    "type": "Point",
    "coordinates": [
      -122.60007,
      45.41418
    ]
  }
}