{
  "type": "Feature",
  "properties": {
    "name": "Pilot Rock",
    "country": "US",
    "subdivision": "OR",
    "timezone": "America/Los_Angeles"
  },
  "geometry": {
    "type": "Point",
    "coordinates": [
      -118.82998,
      45.48318
    ]
  }
}