{
  "type": "Feature",
  "properties": {
    "name": "Reedsport",
    "country": "US",
    "subdivision": "OR",
    "timezone": "America/Los_Angeles"
  },
  "geometry": {
    "type": "Point",
    "coordinates": [
      -124.09678,
      43.70234
    ]
  }
}