{
  "type": "Feature",
  "properties": {
    "name": "Salem",
    "country": "US",
    "subdivision": "OR",
    "timezone": "America/Los_Angeles"
  },
  "geometry": {
    "type": "Point",
    "coordinates": [
      -123.0351,
      44.9429
    ]
  }
}