{
  "type": "Feature",
  "properties": {
    "name": "Sherwood",
    "country": "US",
    "subdivision": "OR",
    "timezone": "America/Los_Angeles"
  },
  "geometry": {
    "type": "Point",
    "coordinates": [
      -122.8401,
      45.35651
    ]
  }
}