{
  "type": "Feature",
  "properties": {
    "name": "Stanfield",
    "country": "US",
    "subdivision": "OR",
    "timezone": "America/Los_Angeles"
  },
  "geometry": {
    "type": "Point",
    "coordinates": [
      -119.21724,
      45.78041
    ]
  }
}