{
  "type": "Feature",
  "properties": {
    "name": "Sublimity",
    "country": "US",
    "subdivision": "OR",
    "timezone": "America/Los_Angeles"
  },
  "geometry": {
    "type": "Point",
    "coordinates": [
      -122.79453,
      44.82957
    ]
  }
}