{
  "type": "Feature",
  "properties": {
    "name": "Terrebonne",
    "country": "US",
    "subdivision": "OR",
    "timezone": "America/Los_Angeles"
  },
  "geometry": {
    "type": "Point",
    "coordinates": [
      -121.17781,
      44.3529
    ]
  }
}