{
  "type": "Feature",
  "properties": {
    "name": "Tri-City",
    "country": "US",
    "subdivision": "OR",
    "timezone": "America/Los_Angeles"
  },
  "geometry": {
    "type": "Point",
    "coordinates": [
      -123.31173,
      42.98456
    ]
  }
}