{
  "type": "Feature",
  "properties": {
    "name": "Veneta",
    "country": "US",
    "subdivision": "OR",
    "timezone": "America/Los_Angeles"
  },
  "geometry": {
    "type": "Point",
    "coordinates": [
      -123.35093,
      44.04873
    ]
  }
}