{
  "type": "Feature",
  "properties": {
    "name": "Woodburn",
    "country": "US",
    "subdivision": "OR",
    "timezone": "America/Los_Angeles"
  },
  "geometry": {
    "type": "Point",
    "coordinates": [
      -122.85537,
      45.14373
    ]
  }
}