{
  "type": "Feature",
  "properties": {
    "name": "Cheboksary",
    "country": "RU",
    "subdivision": "16",
    "timezone": "Europe/Moscow"
  },
  "geometry": {
    "type": "Point",
    "coordinates": [
      47.25194,
      56.13222
    ]
  }
}