{
  "type": "Feature",
  "properties": {
    "name": "Ibresi",
    "country": "RU",
    "subdivision": "16",
    "timezone": "Europe/Moscow"
  },
  "geometry": {
    "type": "Point",
    "coordinates": [
      47.038,
      55.3011
    ]
  }
}