{
  "type": "Feature",
  "properties": {
    "name": "Kirya",
    "country": "RU",
    "subdivision": "16",
    "timezone": "Europe/Moscow"
  },
  "geometry": {
    "type": "Point",
    "coordinates": [
      46.86091,
      55.08102
    ]
  }
}