{
  "type": "Feature",
  "properties": {
    "name": "Berrahal",
    "country": "DZ",
    "subdivision": "37",
    "timezone": "Africa/Algiers"
  },
  "geometry": {
    "type": "Point",
    "coordinates": [
      7.45333,
      36.83528
    ]
  }
}