{
  "type": "Feature",
  "properties": {
    "name": "Marinhais",
    "country": "PT",
    "subdivision": "18",
    "timezone": "Europe/Lisbon"
  },
  "geometry": {
    "type": "Point",
    "coordinates": [
      -8.70236,
      39.0473
    ]
  }
}