{
  "type": "Feature",
  "properties": {
    "name": "Minde",
    "country": "PT",
    "subdivision": "18",
    "timezone": "Europe/Lisbon"
  },
  "geometry": {
    "type": "Point",
    "coordinates": [
      -8.68799,
      39.51631
    ]
  }
}