{
  "type": "Feature",
  "properties": {
    "name": "Vale de Figueira",
    "country": "PT",
    "subdivision": "18",
    "timezone": "Europe/Lisbon"
  },
  "geometry": {
    "type": "Point",
    "coordinates": [
      -8.62876,
      39.30569
    ]
  }
}