{
  "type": "Feature",
  "properties": {
    "name": "Vale de Santarém",
    "country": "PT",
    "subdivision": "18",
    "timezone": "Europe/Lisbon"
  },
  "geometry": {
    "type": "Point",
    "coordinates": [
      -8.72735,
      39.19052
    ]
  }
}