{
  "type": "Feature",
  "properties": {
    "name": "Achslach",
    "country": "DE",
    "subdivision": "02",
    "timezone": "Europe/Berlin"
  },
  "geometry": {
    "type": "Point",
    "coordinates": [
      12.93511,
      48.97171
    ]
  }
}