{
  "type": "Feature",
  "properties": {
    "name": "Adelshofen",
    "country": "DE",
    "subdivision": "02",
    "timezone": "Europe/Berlin"
  },
  "geometry": {
    "type": "Point",
    "coordinates": [
      11.11667,
      48.18333
    ]
  }
}