{
  "type": "Feature",
  "properties": {
    "name": "Aislingen",
    "country": "DE",
    "subdivision": "02",
    "timezone": "Europe/Berlin"
  },
  "geometry": {
    "type": "Point",
    "coordinates": [
      10.45778,
      48.50648
    ]
  }
}