{
  "type": "Feature",
  "properties": {
    "name": "Albertshofen",
    "country": "DE",
    "subdivision": "02",
    "timezone": "Europe/Berlin"
  },
  "geometry": {
    "type": "Point",
    "coordinates": [
      10.16667,
      49.76667
    ]
  }
}