{
  "type": "Feature",
  "properties": {
    "name": "Alling",
    "country": "DE",
    "subdivision": "02",
    "timezone": "Europe/Berlin"
  },
  "geometry": {
    "type": "Point",
    "coordinates": [
      11.30144,
      48.14034
    ]
  }
}