{
  "type": "Feature",
  "properties": {
    "name": "Altenkunstadt",
    "country": "DE",
    "subdivision": "02",
    "timezone": "Europe/Berlin"
  },
  "geometry": {
    "type": "Point",
    "coordinates": [
      11.2503,
      50.12504
    ]
  }
}