{
  "type": "Feature",
  "properties": {
    "name": "Altenmünster",
    "country": "DE",
    "subdivision": "02",
    "timezone": "Europe/Berlin"
  },
  "geometry": {
    "type": "Point",
    "coordinates": [
      10.59065,
      48.46495
    ]
  }
}