{
  "type": "Feature",
  "properties": {
    "name": "Alzenau in Unterfranken",
    "country": "DE",
    "subdivision": "02",
    "timezone": "Europe/Berlin"
  },
  "geometry": {
    "type": "Point",
    "coordinates": [
      9.06455,
      50.0888
    ]
  }
}