{
  "type": "Feature",
  "properties": {
    "name": "Arnstein",
    "country": "DE",
    "subdivision": "02",
    "timezone": "Europe/Berlin"
  },
  "geometry": {
    "type": "Point",
    "coordinates": [
      9.96983,
      49.97767
    ]
  }
}