{
  "type": "Feature",
  "properties": {
    "name": "Babenhausen",
    "country": "DE",
    "subdivision": "02",
    "timezone": "Europe/Berlin"
  },
  "geometry": {
    "type": "Point",
    "coordinates": [
      10.25325,
      48.14497
    ]
  }
}