{
  "type": "Feature",
  "properties": {
    "name": "Bad Staffelstein",
    "country": "DE",
    "subdivision": "02",
    "timezone": "Europe/Berlin"
  },
  "geometry": {
    "type": "Point",
    "coordinates": [
      11.00128,
      50.10199
    ]
  }
}