{
  "type": "Feature",
  "properties": {
    "name": "Bernau am Chiemsee",
    "country": "DE",
    "subdivision": "02",
    "timezone": "Europe/Berlin"
  },
  "geometry": {
    "type": "Point",
    "coordinates": [
      12.37566,
      47.81167
    ]
  }
}