{
  "type": "Feature",
  "properties": {
    "name": "Böbing",
    "country": "DE",
    "subdivision": "02",
    "timezone": "Europe/Berlin"
  },
  "geometry": {
    "type": "Point",
    "coordinates": [
      10.98877,
      47.75562
    ]
  }
}