{
  "type": "Feature",
  "properties": {
    "name": "Bobingen",
    "country": "DE",
    "subdivision": "02",
    "timezone": "Europe/Berlin"
  },
  "geometry": {
    "type": "Point",
    "coordinates": [
      10.8339,
      48.27091
    ]
  }
}