{
  "type": "Feature",
  "properties": {
    "name": "Bogenhausen",
    "country": "DE",
    "subdivision": "02",
    "timezone": "Europe/Berlin"
  },
  "geometry": {
    "type": "Point",
    "coordinates": [
      11.61585,
      48.15221
    ]
  }
}