{
  "type": "Feature",
  "properties": {
    "name": "Bruckberg",
    "country": "DE",
    "subdivision": "02",
    "timezone": "Europe/Berlin"
  },
  "geometry": {
    "type": "Point",
    "coordinates": [
      10.69924,
      49.35991
    ]
  }
}