{
  "type": "Feature",
  "properties": {
    "name": "Brunnen",
    "country": "DE",
    "subdivision": "02",
    "timezone": "Europe/Berlin"
  },
  "geometry": {
    "type": "Point",
    "coordinates": [
      10.97332,
      48.22956
    ]
  }
}