{
  "type": "Feature",
  "properties": {
    "name": "Buch",
    "country": "DE",
    "subdivision": "02",
    "timezone": "Europe/Berlin"
  },
  "geometry": {
    "type": "Point",
    "coordinates": [
      12.16311,
      48.65234
    ]
  }
}