{
  "type": "Feature",
  "properties": {
    "name": "Burgheim",
    "country": "DE",
    "subdivision": "02",
    "timezone": "Europe/Berlin"
  },
  "geometry": {
    "type": "Point",
    "coordinates": [
      11.01599,
      48.70035
    ]
  }
}