{
  "type": "Feature",
  "properties": {
    "name": "Burgkunstadt",
    "country": "DE",
    "subdivision": "02",
    "timezone": "Europe/Berlin"
  },
  "geometry": {
    "type": "Point",
    "coordinates": [
      11.25205,
      50.14093
    ]
  }
}