{
  "type": "Feature",
  "properties": {
    "name": "Coburg",
    "country": "DE",
    "subdivision": "02",
    "timezone": "Europe/Berlin"
  },
  "geometry": {
    "type": "Point",
    "coordinates": [
      10.96384,
      50.25937
    ]
  }
}