{
  "type": "Feature",
  "properties": {
    "name": "Creußen",
    "country": "DE",
    "subdivision": "02",
    "timezone": "Europe/Berlin"
  },
  "geometry": {
    "type": "Point",
    "coordinates": [
      11.62683,
      49.84495
    ]
  }
}