{
  "type": "Feature",
  "properties": {
    "name": "Dachau",
    "country": "DE",
    "subdivision": "02",
    "timezone": "Europe/Berlin"
  },
  "geometry": {
    "type": "Point",
    "coordinates": [
      11.43402,
      48.26
    ]
  }
}