{
  "type": "Feature",
  "properties": {
    "name": "Dorfprozelten",
    "country": "DE",
    "subdivision": "02",
    "timezone": "Europe/Berlin"
  },
  "geometry": {
    "type": "Point",
    "coordinates": [
      9.38028,
      49.78056
    ]
  }
}