{
  "type": "Feature",
  "properties": {
    "name": "Ederheim",
    "country": "DE",
    "subdivision": "02",
    "timezone": "Europe/Berlin"
  },
  "geometry": {
    "type": "Point",
    "coordinates": [
      10.46609,
      48.80827
    ]
  }
}