{
  "type": "Feature",
  "properties": {
    "name": "Egg an der Günz",
    "country": "DE",
    "subdivision": "02",
    "timezone": "Europe/Berlin"
  },
  "geometry": {
    "type": "Point",
    "coordinates": [
      10.28495,
      48.08714
    ]
  }
}