{
  "type": "Feature",
  "properties": {
    "name": "Egglham",
    "country": "DE",
    "subdivision": "02",
    "timezone": "Europe/Berlin"
  },
  "geometry": {
    "type": "Point",
    "coordinates": [
      13.05402,
      48.52902
    ]
  }
}