{
  "type": "Feature",
  "properties": {
    "name": "Eggstätt",
    "country": "DE",
    "subdivision": "02",
    "timezone": "Europe/Berlin"
  },
  "geometry": {
    "type": "Point",
    "coordinates": [
      12.37919,
      47.92698
    ]
  }
}