{
  "type": "Feature",
  "properties": {
    "name": "Emersacker",
    "country": "DE",
    "subdivision": "02",
    "timezone": "Europe/Berlin"
  },
  "geometry": {
    "type": "Point",
    "coordinates": [
      10.6738,
      48.48965
    ]
  }
}