{
  "type": "Feature",
  "properties": {
    "name": "Eurasburg",
    "country": "DE",
    "subdivision": "02",
    "timezone": "Europe/Berlin"
  },
  "geometry": {
    "type": "Point",
    "coordinates": [
      11.08333,
      48.33333
    ]
  }
}