{
  "type": "Feature",
  "properties": {
    "name": "Flossenbürg",
    "country": "DE",
    "subdivision": "02",
    "timezone": "Europe/Berlin"
  },
  "geometry": {
    "type": "Point",
    "coordinates": [
      12.35,
      49.73333
    ]
  }
}