{
  "type": "Feature",
  "properties": {
    "name": "Friedberg",
    "country": "DE",
    "subdivision": "02",
    "timezone": "Europe/Berlin"
  },
  "geometry": {
    "type": "Point",
    "coordinates": [
      10.98461,
      48.35693
    ]
  }
}