{
  "type": "Feature",
  "properties": {
    "name": "Fuchsmühl",
    "country": "DE",
    "subdivision": "02",
    "timezone": "Europe/Berlin"
  },
  "geometry": {
    "type": "Point",
    "coordinates": [
      12.14582,
      49.92265
    ]
  }
}