{
  "type": "Feature",
  "properties": {
    "name": "Fuchsstadt",
    "country": "DE",
    "subdivision": "02",
    "timezone": "Europe/Berlin"
  },
  "geometry": {
    "type": "Point",
    "coordinates": [
      9.9337,
      50.10825
    ]
  }
}