{
  "type": "Feature",
  "properties": {
    "name": "Geltendorf",
    "country": "DE",
    "subdivision": "02",
    "timezone": "Europe/Berlin"
  },
  "geometry": {
    "type": "Point",
    "coordinates": [
      11.03216,
      48.11737
    ]
  }
}