{
  "type": "Feature",
  "properties": {
    "name": "Geslau",
    "country": "DE",
    "subdivision": "02",
    "timezone": "Europe/Berlin"
  },
  "geometry": {
    "type": "Point",
    "coordinates": [
      10.31528,
      49.36643
    ]
  }
}