{
  "type": "Feature",
  "properties": {
    "name": "Glattbach",
    "country": "DE",
    "subdivision": "02",
    "timezone": "Europe/Berlin"
  },
  "geometry": {
    "type": "Point",
    "coordinates": [
      9.1499,
      50.0076
    ]
  }
}