{
  "type": "Feature",
  "properties": {
    "name": "Grafrath",
    "country": "DE",
    "subdivision": "02",
    "timezone": "Europe/Berlin"
  },
  "geometry": {
    "type": "Point",
    "coordinates": [
      11.16667,
      48.11667
    ]
  }
}