{
  "type": "Feature",
  "properties": {
    "name": "Grafengehaig",
    "country": "DE",
    "subdivision": "02",
    "timezone": "Europe/Berlin"
  },
  "geometry": {
    "type": "Point",
    "coordinates": [
      11.59358,
      50.2031
    ]
  }
}