{
  "type": "Feature",
  "properties": {
    "name": "Grasbrunn",
    "country": "DE",
    "subdivision": "02",
    "timezone": "Europe/Berlin"
  },
  "geometry": {
    "type": "Point",
    "coordinates": [
      11.74361,
      48.07905
    ]
  }
}