{
  "type": "Feature",
  "properties": {
    "name": "Grünenbach",
    "country": "DE",
    "subdivision": "02",
    "timezone": "Europe/Berlin"
  },
  "geometry": {
    "type": "Point",
    "coordinates": [
      10.00843,
      47.62864
    ]
  }
}