{
  "type": "Feature",
  "properties": {
    "name": "Güntersleben",
    "country": "DE",
    "subdivision": "02",
    "timezone": "Europe/Berlin"
  },
  "geometry": {
    "type": "Point",
    "coordinates": [
      9.905,
      49.86972
    ]
  }
}