{
  "type": "Feature",
  "properties": {
    "name": "Günzburg",
    "country": "DE",
    "subdivision": "02",
    "timezone": "Europe/Berlin"
  },
  "geometry": {
    "type": "Point",
    "coordinates": [
      10.27695,
      48.45599
    ]
  }
}