{
  "type": "Feature",
  "properties": {
    "name": "Hagenbüchach",
    "country": "DE",
    "subdivision": "02",
    "timezone": "Europe/Berlin"
  },
  "geometry": {
    "type": "Point",
    "coordinates": [
      10.76667,
      49.53333
    ]
  }
}