{
  "type": "Feature",
  "properties": {
    "name": "Halfing",
    "country": "DE",
    "subdivision": "02",
    "timezone": "Europe/Berlin"
  },
  "geometry": {
    "type": "Point",
    "coordinates": [
      12.27525,
      47.95197
    ]
  }
}