{
  "type": "Feature",
  "properties": {
    "name": "Hallbergmoos",
    "country": "DE",
    "subdivision": "02",
    "timezone": "Europe/Berlin"
  },
  "geometry": {
    "type": "Point",
    "coordinates": [
      11.75142,
      48.32747
    ]
  }
}