{
  "type": "Feature",
  "properties": {
    "name": "Heimenkirch",
    "country": "DE",
    "subdivision": "02",
    "timezone": "Europe/Berlin"
  },
  "geometry": {
    "type": "Point",
    "coordinates": [
      9.90304,
      47.62959
    ]
  }
}