{
  "type": "Feature",
  "properties": {
    "name": "Hengersberg",
    "country": "DE",
    "subdivision": "02",
    "timezone": "Europe/Berlin"
  },
  "geometry": {
    "type": "Point",
    "coordinates": [
      13.05485,
      48.77255
    ]
  }
}