{
  "type": "Feature",
  "properties": {
    "name": "Hergensweiler",
    "country": "DE",
    "subdivision": "02",
    "timezone": "Europe/Berlin"
  },
  "geometry": {
    "type": "Point",
    "coordinates": [
      9.78333,
      47.61667
    ]
  }
}