{
  "type": "Feature",
  "properties": {
    "name": "Hofkirchen",
    "country": "DE",
    "subdivision": "02",
    "timezone": "Europe/Berlin"
  },
  "geometry": {
    "type": "Point",
    "coordinates": [
      13.11917,
      48.67805
    ]
  }
}