{
  "type": "Feature",
  "properties": {
    "name": "Hollfeld",
    "country": "DE",
    "subdivision": "02",
    "timezone": "Europe/Berlin"
  },
  "geometry": {
    "type": "Point",
    "coordinates": [
      11.29153,
      49.93793
    ]
  }
}