{
  "type": "Feature",
  "properties": {
    "name": "Huisheim",
    "country": "DE",
    "subdivision": "02",
    "timezone": "Europe/Berlin"
  },
  "geometry": {
    "type": "Point",
    "coordinates": [
      10.70331,
      48.8251
    ]
  }
}