{
  "type": "Feature",
  "properties": {
    "name": "Ichenhausen",
    "country": "DE",
    "subdivision": "02",
    "timezone": "Europe/Berlin"
  },
  "geometry": {
    "type": "Point",
    "coordinates": [
      10.30706,
      48.37119
    ]
  }
}