{
  "type": "Feature",
  "properties": {
    "name": "Irchenrieth",
    "country": "DE",
    "subdivision": "02",
    "timezone": "Europe/Berlin"
  },
  "geometry": {
    "type": "Point",
    "coordinates": [
      12.22495,
      49.62286
    ]
  }
}