{
  "type": "Feature",
  "properties": {
    "name": "Jesenwang",
    "country": "DE",
    "subdivision": "02",
    "timezone": "Europe/Berlin"
  },
  "geometry": {
    "type": "Point",
    "coordinates": [
      11.13333,
      48.16667
    ]
  }
}