{
  "type": "Feature",
  "properties": {
    "name": "Jettingen-Scheppach",
    "country": "DE",
    "subdivision": "02",
    "timezone": "Europe/Berlin"
  },
  "geometry": {
    "type": "Point",
    "coordinates": [
      10.4381,
      48.3896
    ]
  }
}