{
  "type": "Feature",
  "properties": {
    "name": "Karlstadt",
    "country": "DE",
    "subdivision": "02",
    "timezone": "Europe/Berlin"
  },
  "geometry": {
    "type": "Point",
    "coordinates": [
      9.77239,
      49.96034
    ]
  }
}