{
  "type": "Feature",
  "properties": {
    "name": "Kaufering",
    "country": "DE",
    "subdivision": "02",
    "timezone": "Europe/Berlin"
  },
  "geometry": {
    "type": "Point",
    "coordinates": [
      10.87913,
      48.09121
    ]
  }
}