{
  "type": "Feature",
  "properties": {
    "name": "Kirchdorf",
    "country": "DE",
    "subdivision": "02",
    "timezone": "Europe/Berlin"
  },
  "geometry": {
    "type": "Point",
    "coordinates": [
      11.65438,
      48.45942
    ]
  }
}