{
  "type": "Feature",
  "properties": {
    "name": "Kirchheim bei München",
    "country": "DE",
    "subdivision": "02",
    "timezone": "Europe/Berlin"
  },
  "geometry": {
    "type": "Point",
    "coordinates": [
      11.75563,
      48.17656
    ]
  }
}