{
  "type": "Feature",
  "properties": {
    "name": "Kissing",
    "country": "DE",
    "subdivision": "02",
    "timezone": "Europe/Berlin"
  },
  "geometry": {
    "type": "Point",
    "coordinates": [
      10.97088,
      48.30375
    ]
  }
}