{
  "type": "Feature",
  "properties": {
    "name": "Klosterlechfeld",
    "country": "DE",
    "subdivision": "02",
    "timezone": "Europe/Berlin"
  },
  "geometry": {
    "type": "Point",
    "coordinates": [
      10.82986,
      48.15586
    ]
  }
}