{
  "type": "Feature",
  "properties": {
    "name": "Kumhausen",
    "country": "DE",
    "subdivision": "02",
    "timezone": "Europe/Berlin"
  },
  "geometry": {
    "type": "Point",
    "coordinates": [
      12.15637,
      48.50938
    ]
  }
}