{
  "type": "Feature",
  "properties": {
    "name": "Lam",
    "country": "DE",
    "subdivision": "02",
    "timezone": "Europe/Berlin"
  },
  "geometry": {
    "type": "Point",
    "coordinates": [
      13.05051,
      49.19665
    ]
  }
}