{
  "type": "Feature",
  "properties": {
    "name": "Lauben",
    "country": "DE",
    "subdivision": "02",
    "timezone": "Europe/Berlin"
  },
  "geometry": {
    "type": "Point",
    "coordinates": [
      10.29014,
      48.05928
    ]
  }
}