{
  "type": "Feature",
  "properties": {
    "name": "Lichtenau",
    "country": "DE",
    "subdivision": "02",
    "timezone": "Europe/Berlin"
  },
  "geometry": {
    "type": "Point",
    "coordinates": [
      10.37935,
      49.15979
    ]
  }
}