{
  "type": "Feature",
  "properties": {
    "name": "Luhe-Wildenau",
    "country": "DE",
    "subdivision": "02",
    "timezone": "Europe/Berlin"
  },
  "geometry": {
    "type": "Point",
    "coordinates": [
      12.14921,
      49.58367
    ]
  }
}