{
  "type": "Feature",
  "properties": {
    "name": "Malching",
    "country": "DE",
    "subdivision": "02",
    "timezone": "Europe/Berlin"
  },
  "geometry": {
    "type": "Point",
    "coordinates": [
      13.18746,
      48.31226
    ]
  }
}