{
  "type": "Feature",
  "properties": {
    "name": "Mallersdorf-Pfaffenberg",
    "country": "DE",
    "subdivision": "02",
    "timezone": "Europe/Berlin"
  },
  "geometry": {
    "type": "Point",
    "coordinates": [
      12.23096,
      48.76637
    ]
  }
}