{
  "type": "Feature",
  "properties": {
    "name": "Marktheidenfeld",
    "country": "DE",
    "subdivision": "02",
    "timezone": "Europe/Berlin"
  },
  "geometry": {
    "type": "Point",
    "coordinates": [
      9.60359,
      49.8454
    ]
  }
}