{
  "type": "Feature",
  "properties": {
    "name": "Markt Indersdorf",
    "country": "DE",
    "subdivision": "02",
    "timezone": "Europe/Berlin"
  },
  "geometry": {
    "type": "Point",
    "coordinates": [
      11.37789,
      48.36058
    ]
  }
}