{
  "type": "Feature",
  "properties": {
    "name": "Markt Berolzheim",
    "country": "DE",
    "subdivision": "02",
    "timezone": "Europe/Berlin"
  },
  "geometry": {
    "type": "Point",
    "coordinates": [
      10.84473,
      49.00955
    ]
  }
}