{
  "type": "Feature",
  "properties": {
    "name": "Marktl",
    "country": "DE",
    "subdivision": "02",
    "timezone": "Europe/Berlin"
  },
  "geometry": {
    "type": "Point",
    "coordinates": [
      12.8447,
      48.25516
    ]
  }
}