{
  "type": "Feature",
  "properties": {
    "name": "Marktoffingen",
    "country": "DE",
    "subdivision": "02",
    "timezone": "Europe/Berlin"
  },
  "geometry": {
    "type": "Point",
    "coordinates": [
      10.47078,
      48.92566
    ]
  }
}