{
  "type": "Feature",
  "properties": {
    "name": "Maxhütte-Haidhof",
    "country": "DE",
    "subdivision": "02",
    "timezone": "Europe/Berlin"
  },
  "geometry": {
    "type": "Point",
    "coordinates": [
      12.09229,
      49.19963
    ]
  }
}