{
  "type": "Feature",
  "properties": {
    "name": "Mehlmeisel",
    "country": "DE",
    "subdivision": "02",
    "timezone": "Europe/Berlin"
  },
  "geometry": {
    "type": "Point",
    "coordinates": [
      11.862,
      49.97421
    ]
  }
}