{
  "type": "Feature",
  "properties": {
    "name": "Mengkofen",
    "country": "DE",
    "subdivision": "02",
    "timezone": "Europe/Berlin"
  },
  "geometry": {
    "type": "Point",
    "coordinates": [
      12.44047,
      48.71894
    ]
  }
}