{
  "type": "Feature",
  "properties": {
    "name": "Miesbach",
    "country": "DE",
    "subdivision": "02",
    "timezone": "Europe/Berlin"
  },
  "geometry": {
    "type": "Point",
    "coordinates": [
      11.83382,
      47.78903
    ]
  }
}