{
  "type": "Feature",
  "properties": {
    "name": "Mintraching",
    "country": "DE",
    "subdivision": "02",
    "timezone": "Europe/Berlin"
  },
  "geometry": {
    "type": "Point",
    "coordinates": [
      12.24209,
      48.95357
    ]
  }
}