{
  "type": "Feature",
  "properties": {
    "name": "Monheim",
    "country": "DE",
    "subdivision": "02",
    "timezone": "Europe/Berlin"
  },
  "geometry": {
    "type": "Point",
    "coordinates": [
      10.85834,
      48.84389
    ]
  }
}