{
  "type": "Feature",
  "properties": {
    "name": "Moorenweis",
    "country": "DE",
    "subdivision": "02",
    "timezone": "Europe/Berlin"
  },
  "geometry": {
    "type": "Point",
    "coordinates": [
      11.07851,
      48.15561
    ]
  }
}