{
  "type": "Feature",
  "properties": {
    "name": "Möttingen",
    "country": "DE",
    "subdivision": "02",
    "timezone": "Europe/Berlin"
  },
  "geometry": {
    "type": "Point",
    "coordinates": [
      10.59022,
      48.80924
    ]
  }
}