{
  "type": "Feature",
  "properties": {
    "name": "Mötzing",
    "country": "DE",
    "subdivision": "02",
    "timezone": "Europe/Berlin"
  },
  "geometry": {
    "type": "Point",
    "coordinates": [
      12.37361,
      48.8935
    ]
  }
}