{
  "type": "Feature",
  "properties": {
    "name": "Münchsteinach",
    "country": "DE",
    "subdivision": "02",
    "timezone": "Europe/Berlin"
  },
  "geometry": {
    "type": "Point",
    "coordinates": [
      10.59502,
      49.63937
    ]
  }
}