{
  "type": "Feature",
  "properties": {
    "name": "Neuendettelsau",
    "country": "DE",
    "subdivision": "02",
    "timezone": "Europe/Berlin"
  },
  "geometry": {
    "type": "Point",
    "coordinates": [
      10.78333,
      49.28333
    ]
  }
}