{
  "type": "Feature",
  "properties": {
    "name": "Neuhaus am Inn",
    "country": "DE",
    "subdivision": "02",
    "timezone": "Europe/Berlin"
  },
  "geometry": {
    "type": "Point",
    "coordinates": [
      13.42083,
      48.46086
    ]
  }
}