{
  "type": "Feature",
  "properties": {
    "name": "Neunkirchen am Main",
    "country": "DE",
    "subdivision": "02",
    "timezone": "Europe/Berlin"
  },
  "geometry": {
    "type": "Point",
    "coordinates": [
      11.64793,
      49.923
    ]
  }
}