{
  "type": "Feature",
  "properties": {
    "name": "Niedernberg",
    "country": "DE",
    "subdivision": "02",
    "timezone": "Europe/Berlin"
  },
  "geometry": {
    "type": "Point",
    "coordinates": [
      9.13694,
      49.91222
    ]
  }
}