{
  "type": "Feature",
  "properties": {
    "name": "Niedermurach",
    "country": "DE",
    "subdivision": "02",
    "timezone": "Europe/Berlin"
  },
  "geometry": {
    "type": "Point",
    "coordinates": [
      12.3761,
      49.44999
    ]
  }
}