{
  "type": "Feature",
  "properties": {
    "name": "Nußdorf",
    "country": "DE",
    "subdivision": "02",
    "timezone": "Europe/Berlin"
  },
  "geometry": {
    "type": "Point",
    "coordinates": [
      12.59608,
      47.90564
    ]
  }
}