{
  "type": "Feature",
  "properties": {
    "name": "Oberelsbach",
    "country": "DE",
    "subdivision": "02",
    "timezone": "Europe/Berlin"
  },
  "geometry": {
    "type": "Point",
    "coordinates": [
      10.11692,
      50.44118
    ]
  }
}