{
  "type": "Feature",
  "properties": {
    "name": "Oberschwarzach",
    "country": "DE",
    "subdivision": "02",
    "timezone": "Europe/Berlin"
  },
  "geometry": {
    "type": "Point",
    "coordinates": [
      10.40999,
      49.86051
    ]
  }
}