{
  "type": "Feature",
  "properties": {
    "name": "Obersüßbach",
    "country": "DE",
    "subdivision": "02",
    "timezone": "Europe/Berlin"
  },
  "geometry": {
    "type": "Point",
    "coordinates": [
      11.95,
      48.61667
    ]
  }
}