{
  "type": "Feature",
  "properties": {
    "name": "Obersinn",
    "country": "DE",
    "subdivision": "02",
    "timezone": "Europe/Berlin"
  },
  "geometry": {
    "type": "Point",
    "coordinates": [
      9.61545,
      50.20875
    ]
  }
}