{
  "type": "Feature",
  "properties": {
    "name": "Obergriesbach",
    "country": "DE",
    "subdivision": "02",
    "timezone": "Europe/Berlin"
  },
  "geometry": {
    "type": "Point",
    "coordinates": [
      11.0685,
      48.42305
    ]
  }
}