{
  "type": "Feature",
  "properties": {
    "name": "Oberreichenbach",
    "country": "DE",
    "subdivision": "02",
    "timezone": "Europe/Berlin"
  },
  "geometry": {
    "type": "Point",
    "coordinates": [
      10.76892,
      49.58946
    ]
  }
}