{
  "type": "Feature",
  "properties": {
    "name": "Oberthulba",
    "country": "DE",
    "subdivision": "02",
    "timezone": "Europe/Berlin"
  },
  "geometry": {
    "type": "Point",
    "coordinates": [
      9.95882,
      50.19904
    ]
  }
}