{
  "type": "Feature",
  "properties": {
    "name": "Oberasbach",
    "country": "DE",
    "subdivision": "02",
    "timezone": "Europe/Berlin"
  },
  "geometry": {
    "type": "Point",
    "coordinates": [
      10.95766,
      49.42275
    ]
  }
}