{
  "type": "Feature",
  "properties": {
    "name": "Obermeitingen",
    "country": "DE",
    "subdivision": "02",
    "timezone": "Europe/Berlin"
  },
  "geometry": {
    "type": "Point",
    "coordinates": [
      10.80626,
      48.14685
    ]
  }
}