{
  "type": "Feature",
  "properties": {
    "name": "Oberostendorf",
    "country": "DE",
    "subdivision": "02",
    "timezone": "Europe/Berlin"
  },
  "geometry": {
    "type": "Point",
    "coordinates": [
      10.7427,
      47.9436
    ]
  }
}