{
  "type": "Feature",
  "properties": {
    "name": "Obermichelbach",
    "country": "DE",
    "subdivision": "02",
    "timezone": "Europe/Berlin"
  },
  "geometry": {
    "type": "Point",
    "coordinates": [
      10.90891,
      49.53117
    ]
  }
}