{
  "type": "Feature",
  "properties": {
    "name": "Oberschleißheim",
    "country": "DE",
    "subdivision": "02",
    "timezone": "Europe/Berlin"
  },
  "geometry": {
    "type": "Point",
    "coordinates": [
      11.56667,
      48.25
    ]
  }
}