{
  "type": "Feature",
  "properties": {
    "name": "Oberndorf",
    "country": "DE",
    "subdivision": "02",
    "timezone": "Europe/Berlin"
  },
  "geometry": {
    "type": "Point",
    "coordinates": [
      10.86749,
      48.66918
    ]
  }
}