{
  "type": "Feature",
  "properties": {
    "name": "Oberschneiding",
    "country": "DE",
    "subdivision": "02",
    "timezone": "Europe/Berlin"
  },
  "geometry": {
    "type": "Point",
    "coordinates": [
      12.642,
      48.79573
    ]
  }
}