{
  "type": "Feature",
  "properties": {
    "name": "Offenberg",
    "country": "DE",
    "subdivision": "02",
    "timezone": "Europe/Berlin"
  },
  "geometry": {
    "type": "Point",
    "coordinates": [
      12.86293,
      48.86195
    ]
  }
}