{
  "type": "Feature",
  "properties": {
    "name": "Ottensoos",
    "country": "DE",
    "subdivision": "02",
    "timezone": "Europe/Berlin"
  },
  "geometry": {
    "type": "Point",
    "coordinates": [
      11.34158,
      49.50949
    ]
  }
}