{
  "type": "Feature",
  "properties": {
    "name": "Pechbrunn",
    "country": "DE",
    "subdivision": "02",
    "timezone": "Europe/Berlin"
  },
  "geometry": {
    "type": "Point",
    "coordinates": [
      12.16667,
      49.96667
    ]
  }
}