{
  "type": "Feature",
  "properties": {
    "name": "Pentling",
    "country": "DE",
    "subdivision": "02",
    "timezone": "Europe/Berlin"
  },
  "geometry": {
    "type": "Point",
    "coordinates": [
      12.0587,
      48.98343
    ]
  }
}