{
  "type": "Feature",
  "properties": {
    "name": "Pettstadt",
    "country": "DE",
    "subdivision": "02",
    "timezone": "Europe/Berlin"
  },
  "geometry": {
    "type": "Point",
    "coordinates": [
      10.92839,
      49.82996
    ]
  }
}