{
  "type": "Feature",
  "properties": {
    "name": "Planegg",
    "country": "DE",
    "subdivision": "02",
    "timezone": "Europe/Berlin"
  },
  "geometry": {
    "type": "Point",
    "coordinates": [
      11.42483,
      48.10672
    ]
  }
}