{
  "type": "Feature",
  "properties": {
    "name": "Pommersfelden",
    "country": "DE",
    "subdivision": "02",
    "timezone": "Europe/Berlin"
  },
  "geometry": {
    "type": "Point",
    "coordinates": [
      10.81667,
      49.76667
    ]
  }
}