{
  "type": "Feature",
  "properties": {
    "name": "Poppenhausen",
    "country": "DE",
    "subdivision": "02",
    "timezone": "Europe/Berlin"
  },
  "geometry": {
    "type": "Point",
    "coordinates": [
      10.14244,
      50.09999
    ]
  }
}