{
  "type": "Feature",
  "properties": {
    "name": "Postbauer-Heng",
    "country": "DE",
    "subdivision": "02",
    "timezone": "Europe/Berlin"
  },
  "geometry": {
    "type": "Point",
    "coordinates": [
      11.35722,
      49.30528
    ]
  }
}