{
  "type": "Feature",
  "properties": {
    "name": "Pressath",
    "country": "DE",
    "subdivision": "02",
    "timezone": "Europe/Berlin"
  },
  "geometry": {
    "type": "Point",
    "coordinates": [
      11.93972,
      49.76859
    ]
  }
}