{
  "type": "Feature",
  "properties": {
    "name": "Putzbrunn",
    "country": "DE",
    "subdivision": "02",
    "timezone": "Europe/Berlin"
  },
  "geometry": {
    "type": "Point",
    "coordinates": [
      11.71572,
      48.07579
    ]
  }
}