{
  "type": "Feature",
  "properties": {
    "name": "Ramerberg",
    "country": "DE",
    "subdivision": "02",
    "timezone": "Europe/Berlin"
  },
  "geometry": {
    "type": "Point",
    "coordinates": [
      12.14513,
      48.01806
    ]
  }
}