{
  "type": "Feature",
  "properties": {
    "name": "Raubling",
    "country": "DE",
    "subdivision": "02",
    "timezone": "Europe/Berlin"
  },
  "geometry": {
    "type": "Point",
    "coordinates": [
      12.11088,
      47.7905
    ]
  }
}