{
  "type": "Feature",
  "properties": {
    "name": "Regensburg",
    "country": "DE",
    "subdivision": "02",
    "timezone": "Europe/Berlin"
  },
  "geometry": {
    "type": "Point",
    "coordinates": [
      12.10161,
      49.01513
    ]
  }
}