{
  "type": "Feature",
  "properties": {
    "name": "Reichersbeuern",
    "country": "DE",
    "subdivision": "02",
    "timezone": "Europe/Berlin"
  },
  "geometry": {
    "type": "Point",
    "coordinates": [
      11.63333,
      47.76667
    ]
  }
}