{
  "type": "Feature",
  "properties": {
    "name": "Rettenberg",
    "country": "DE",
    "subdivision": "02",
    "timezone": "Europe/Berlin"
  },
  "geometry": {
    "type": "Point",
    "coordinates": [
      10.29173,
      47.57428
    ]
  }
}