{
  "type": "Feature",
  "properties": {
    "name": "Rieden an der Kötz",
    "country": "DE",
    "subdivision": "02",
    "timezone": "Europe/Berlin"
  },
  "geometry": {
    "type": "Point",
    "coordinates": [
      10.25711,
      48.38499
    ]
  }
}