{
  "type": "Feature",
  "properties": {
    "name": "Riedenberg",
    "country": "DE",
    "subdivision": "02",
    "timezone": "Europe/Berlin"
  },
  "geometry": {
    "type": "Point",
    "coordinates": [
      9.861,
      50.31993
    ]
  }
}