{
  "type": "Feature",
  "properties": {
    "name": "Rinchnach",
    "country": "DE",
    "subdivision": "02",
    "timezone": "Europe/Berlin"
  },
  "geometry": {
    "type": "Point",
    "coordinates": [
      13.20102,
      48.94956
    ]
  }
}