{
  "type": "Feature",
  "properties": {
    "name": "Rödelsee",
    "country": "DE",
    "subdivision": "02",
    "timezone": "Europe/Berlin"
  },
  "geometry": {
    "type": "Point",
    "coordinates": [
      10.2436,
      49.7284
    ]
  }
}