{
  "type": "Feature",
  "properties": {
    "name": "Rödental",
    "country": "DE",
    "subdivision": "02",
    "timezone": "Europe/Berlin"
  },
  "geometry": {
    "type": "Point",
    "coordinates": [
      11.04122,
      50.29516
    ]
  }
}