{
  "type": "Feature",
  "properties": {
    "name": "Roding",
    "country": "DE",
    "subdivision": "02",
    "timezone": "Europe/Berlin"
  },
  "geometry": {
    "type": "Point",
    "coordinates": [
      12.51956,
      49.19426
    ]
  }
}