{
  "type": "Feature",
  "properties": {
    "name": "Rottenburg an der Laaber",
    "country": "DE",
    "subdivision": "02",
    "timezone": "Europe/Berlin"
  },
  "geometry": {
    "type": "Point",
    "coordinates": [
      12.02717,
      48.70233
    ]
  }
}