{
  "type": "Feature",
  "properties": {
    "name": "Saldenburg",
    "country": "DE",
    "subdivision": "02",
    "timezone": "Europe/Berlin"
  },
  "geometry": {
    "type": "Point",
    "coordinates": [
      13.35586,
      48.7731
    ]
  }
}