{
  "type": "Feature",
  "properties": {
    "name": "Salzweg",
    "country": "DE",
    "subdivision": "02",
    "timezone": "Europe/Berlin"
  },
  "geometry": {
    "type": "Point",
    "coordinates": [
      13.48333,
      48.61667
    ]
  }
}