{
  "type": "Feature",
  "properties": {
    "name": "Scherstetten",
    "country": "DE",
    "subdivision": "02",
    "timezone": "Europe/Berlin"
  },
  "geometry": {
    "type": "Point",
    "coordinates": [
      10.64005,
      48.18032
    ]
  }
}