{
  "type": "Feature",
  "properties": {
    "name": "Schmiechen",
    "country": "DE",
    "subdivision": "02",
    "timezone": "Europe/Berlin"
  },
  "geometry": {
    "type": "Point",
    "coordinates": [
      10.96667,
      48.21667
    ]
  }
}