{
  "type": "Feature",
  "properties": {
    "name": "Schnaittenbach",
    "country": "DE",
    "subdivision": "02",
    "timezone": "Europe/Berlin"
  },
  "geometry": {
    "type": "Point",
    "coordinates": [
      12.00184,
      49.54692
    ]
  }
}