{
  "type": "Feature",
  "properties": {
    "name": "Schöngeising",
    "country": "DE",
    "subdivision": "02",
    "timezone": "Europe/Berlin"
  },
  "geometry": {
    "type": "Point",
    "coordinates": [
      11.20399,
      48.14135
    ]
  }
}