{
  "type": "Feature",
  "properties": {
    "name": "Schopfloch",
    "country": "DE",
    "subdivision": "02",
    "timezone": "Europe/Berlin"
  },
  "geometry": {
    "type": "Point",
    "coordinates": [
      10.30774,
      49.11917
    ]
  }
}