{
  "type": "Feature",
  "properties": {
    "name": "Schönwald",
    "country": "DE",
    "subdivision": "02",
    "timezone": "Europe/Berlin"
  },
  "geometry": {
    "type": "Point",
    "coordinates": [
      12.08503,
      50.1997
    ]
  }
}