{
  "type": "Feature",
  "properties": {
    "name": "Schönau",
    "country": "DE",
    "subdivision": "02",
    "timezone": "Europe/Berlin"
  },
  "geometry": {
    "type": "Point",
    "coordinates": [
      9.72169,
      50.07571
    ]
  }
}