{
  "type": "Feature",
  "properties": {
    "name": "Schwarzhofen",
    "country": "DE",
    "subdivision": "02",
    "timezone": "Europe/Berlin"
  },
  "geometry": {
    "type": "Point",
    "coordinates": [
      12.3449,
      49.37749
    ]
  }
}