{
  "type": "Feature",
  "properties": {
    "name": "Schwarzenbruck",
    "country": "DE",
    "subdivision": "02",
    "timezone": "Europe/Berlin"
  },
  "geometry": {
    "type": "Point",
    "coordinates": [
      11.24333,
      49.35778
    ]
  }
}