{
  "type": "Feature",
  "properties": {
    "name": "Seefeld",
    "country": "DE",
    "subdivision": "02",
    "timezone": "Europe/Berlin"
  },
  "geometry": {
    "type": "Point",
    "coordinates": [
      11.21395,
      48.03505
    ]
  }
}