{
  "type": "Feature",
  "properties": {
    "name": "Seeshaupt",
    "country": "DE",
    "subdivision": "02",
    "timezone": "Europe/Berlin"
  },
  "geometry": {
    "type": "Point",
    "coordinates": [
      11.30219,
      47.82468
    ]
  }
}