{
  "type": "Feature",
  "properties": {
    "name": "Sengenthal",
    "country": "DE",
    "subdivision": "02",
    "timezone": "Europe/Berlin"
  },
  "geometry": {
    "type": "Point",
    "coordinates": [
      11.46667,
      49.23333
    ]
  }
}