{
  "type": "Feature",
  "properties": {
    "name": "Sennfeld",
    "country": "DE",
    "subdivision": "02",
    "timezone": "Europe/Berlin"
  },
  "geometry": {
    "type": "Point",
    "coordinates": [
      10.25986,
      50.03895
    ]
  }
}