{
  "type": "Feature",
  "properties": {
    "name": "Simbach",
    "country": "DE",
    "subdivision": "02",
    "timezone": "Europe/Berlin"
  },
  "geometry": {
    "type": "Point",
    "coordinates": [
      12.73888,
      48.56606
    ]
  }
}