{
  "type": "Feature",
  "properties": {
    "name": "Söchtenau",
    "country": "DE",
    "subdivision": "02",
    "timezone": "Europe/Berlin"
  },
  "geometry": {
    "type": "Point",
    "coordinates": [
      12.22959,
      47.93118
    ]
  }
}