{
  "type": "Feature",
  "properties": {
    "name": "Solnhofen",
    "country": "DE",
    "subdivision": "02",
    "timezone": "Europe/Berlin"
  },
  "geometry": {
    "type": "Point",
    "coordinates": [
      10.9956,
      48.89582
    ]
  }
}