{
  "type": "Feature",
  "properties": {
    "name": "Sondheim vor der Rhön",
    "country": "DE",
    "subdivision": "02",
    "timezone": "Europe/Berlin"
  },
  "geometry": {
    "type": "Point",
    "coordinates": [
      10.15675,
      50.4651
    ]
  }
}