{
  "type": "Feature",
  "properties": {
    "name": "Steinfeld",
    "country": "DE",
    "subdivision": "02",
    "timezone": "Europe/Berlin"
  },
  "geometry": {
    "type": "Point",
    "coordinates": [
      9.66944,
      49.95278
    ]
  }
}