{
  "type": "Feature",
  "properties": {
    "name": "Stephanskirchen",
    "country": "DE",
    "subdivision": "02",
    "timezone": "Europe/Berlin"
  },
  "geometry": {
    "type": "Point",
    "coordinates": [
      12.1856,
      47.85389
    ]
  }
}