{
  "type": "Feature",
  "properties": {
    "name": "Stettfeld",
    "country": "DE",
    "subdivision": "02",
    "timezone": "Europe/Berlin"
  },
  "geometry": {
    "type": "Point",
    "coordinates": [
      10.7217,
      49.9709
    ]
  }
}