{
  "type": "Feature",
  "properties": {
    "name": "Taufkirchen",
    "country": "DE",
    "subdivision": "02",
    "timezone": "Europe/Berlin"
  },
  "geometry": {
    "type": "Point",
    "coordinates": [
      12.13202,
      48.34987
    ]
  }
}