{
  "type": "Feature",
  "properties": {
    "name": "Teising",
    "country": "DE",
    "subdivision": "02",
    "timezone": "Europe/Berlin"
  },
  "geometry": {
    "type": "Point",
    "coordinates": [
      12.61137,
      48.22721
    ]
  }
}