{
  "type": "Feature",
  "properties": {
    "name": "Teisnach",
    "country": "DE",
    "subdivision": "02",
    "timezone": "Europe/Berlin"
  },
  "geometry": {
    "type": "Point",
    "coordinates": [
      12.98784,
      49.04114
    ]
  }
}