{
  "type": "Feature",
  "properties": {
    "name": "Teugn",
    "country": "DE",
    "subdivision": "02",
    "timezone": "Europe/Berlin"
  },
  "geometry": {
    "type": "Point",
    "coordinates": [
      12.01175,
      48.89299
    ]
  }
}