{
  "type": "Feature",
  "properties": {
    "name": "Teuschnitz",
    "country": "DE",
    "subdivision": "02",
    "timezone": "Europe/Berlin"
  },
  "geometry": {
    "type": "Point",
    "coordinates": [
      11.38235,
      50.39839
    ]
  }
}