{
  "type": "Feature",
  "properties": {
    "name": "Thanstein",
    "country": "DE",
    "subdivision": "02",
    "timezone": "Europe/Berlin"
  },
  "geometry": {
    "type": "Point",
    "coordinates": [
      12.46667,
      49.38333
    ]
  }
}