{
  "type": "Feature",
  "properties": {
    "name": "Theisseil",
    "country": "DE",
    "subdivision": "02",
    "timezone": "Europe/Berlin"
  },
  "geometry": {
    "type": "Point",
    "coordinates": [
      12.22744,
      49.69034
    ]
  }
}