{
  "type": "Feature",
  "properties": {
    "name": "Theilheim",
    "country": "DE",
    "subdivision": "02",
    "timezone": "Europe/Berlin"
  },
  "geometry": {
    "type": "Point",
    "coordinates": [
      10.03056,
      49.75403
    ]
  }
}