{
  "type": "Feature",
  "properties": {
    "name": "Thüngen",
    "country": "DE",
    "subdivision": "02",
    "timezone": "Europe/Berlin"
  },
  "geometry": {
    "type": "Point",
    "coordinates": [
      9.8586,
      49.9414
    ]
  }
}