{
  "type": "Feature",
  "properties": {
    "name": "Traunstein",
    "country": "DE",
    "subdivision": "02",
    "timezone": "Europe/Berlin"
  },
  "geometry": {
    "type": "Point",
    "coordinates": [
      12.64335,
      47.86825
    ]
  }
}