{
  "type": "Feature",
  "properties": {
    "name": "Tyrlaching",
    "country": "DE",
    "subdivision": "02",
    "timezone": "Europe/Berlin"
  },
  "geometry": {
    "type": "Point",
    "coordinates": [
      12.66667,
      48.06667
    ]
  }
}