{
  "type": "Feature",
  "properties": {
    "name": "Übersee",
    "country": "DE",
    "subdivision": "02",
    "timezone": "Europe/Berlin"
  },
  "geometry": {
    "type": "Point",
    "coordinates": [
      12.48333,
      47.81667
    ]
  }
}