{
  "type": "Feature",
  "properties": {
    "name": "Uffing",
    "country": "DE",
    "subdivision": "02",
    "timezone": "Europe/Berlin"
  },
  "geometry": {
    "type": "Point",
    "coordinates": [
      11.15034,
      47.71378
    ]
  }
}