{
  "type": "Feature",
  "properties": {
    "name": "Ungerhausen",
    "country": "DE",
    "subdivision": "02",
    "timezone": "Europe/Berlin"
  },
  "geometry": {
    "type": "Point",
    "coordinates": [
      10.26672,
      48.00566
    ]
  }
}