{
  "type": "Feature",
  "properties": {
    "name": "Unterdießen",
    "country": "DE",
    "subdivision": "02",
    "timezone": "Europe/Berlin"
  },
  "geometry": {
    "type": "Point",
    "coordinates": [
      10.83333,
      47.98333
    ]
  }
}