{
  "type": "Feature",
  "properties": {
    "name": "Untrasried",
    "country": "DE",
    "subdivision": "02",
    "timezone": "Europe/Berlin"
  },
  "geometry": {
    "type": "Point",
    "coordinates": [
      10.38333,
      47.83333
    ]
  }
}