{
  "type": "Feature",
  "properties": {
    "name": "Urspringen",
    "country": "DE",
    "subdivision": "02",
    "timezone": "Europe/Berlin"
  },
  "geometry": {
    "type": "Point",
    "coordinates": [
      9.67123,
      49.90166
    ]
  }
}