{
  "type": "Feature",
  "properties": {
    "name": "Vaterstetten",
    "country": "DE",
    "subdivision": "02",
    "timezone": "Europe/Berlin"
  },
  "geometry": {
    "type": "Point",
    "coordinates": [
      11.76825,
      48.10537
    ]
  }
}