{
  "type": "Feature",
  "properties": {
    "name": "Velburg",
    "country": "DE",
    "subdivision": "02",
    "timezone": "Europe/Berlin"
  },
  "geometry": {
    "type": "Point",
    "coordinates": [
      11.6716,
      49.23212
    ]
  }
}