{
  "type": "Feature",
  "properties": {
    "name": "Viechtach",
    "country": "DE",
    "subdivision": "02",
    "timezone": "Europe/Berlin"
  },
  "geometry": {
    "type": "Point",
    "coordinates": [
      12.88566,
      49.08001
    ]
  }
}