{
  "type": "Feature",
  "properties": {
    "name": "Villenbach",
    "country": "DE",
    "subdivision": "02",
    "timezone": "Europe/Berlin"
  },
  "geometry": {
    "type": "Point",
    "coordinates": [
      10.61468,
      48.50887
    ]
  }
}