{
  "type": "Feature",
  "properties": {
    "name": "Waal",
    "country": "DE",
    "subdivision": "02",
    "timezone": "Europe/Berlin"
  },
  "geometry": {
    "type": "Point",
    "coordinates": [
      10.77786,
      47.99679
    ]
  }
}