{
  "type": "Feature",
  "properties": {
    "name": "Walpertskirchen",
    "country": "DE",
    "subdivision": "02",
    "timezone": "Europe/Berlin"
  },
  "geometry": {
    "type": "Point",
    "coordinates": [
      11.97527,
      48.2584
    ]
  }
}