{
  "type": "Feature",
  "properties": {
    "name": "Wegscheid",
    "country": "DE",
    "subdivision": "02",
    "timezone": "Europe/Berlin"
  },
  "geometry": {
    "type": "Point",
    "coordinates": [
      13.78733,
      48.60136
    ]
  }
}