{
  "type": "Feature",
  "properties": {
    "name": "Weidenbach",
    "country": "DE",
    "subdivision": "02",
    "timezone": "Europe/Berlin"
  },
  "geometry": {
    "type": "Point",
    "coordinates": [
      10.64489,
      49.19817
    ]
  }
}