{
  "type": "Feature",
  "properties": {
    "name": "Weiden",
    "country": "DE",
    "subdivision": "02",
    "timezone": "Europe/Berlin"
  },
  "geometry": {
    "type": "Point",
    "coordinates": [
      12.15613,
      49.67682
    ]
  }
}