{
  "type": "Feature",
  "properties": {
    "name": "Weilbach",
    "country": "DE",
    "subdivision": "02",
    "timezone": "Europe/Berlin"
  },
  "geometry": {
    "type": "Point",
    "coordinates": [
      9.21639,
      49.66812
    ]
  }
}