{
  "type": "Feature",
  "properties": {
    "name": "Weilheim",
    "country": "DE",
    "subdivision": "02",
    "timezone": "Europe/Berlin"
  },
  "geometry": {
    "type": "Point",
    "coordinates": [
      11.15484,
      47.84147
    ]
  }
}