{
  "type": "Feature",
  "properties": {
    "name": "Weitnau",
    "country": "DE",
    "subdivision": "02",
    "timezone": "Europe/Berlin"
  },
  "geometry": {
    "type": "Point",
    "coordinates": [
      10.12732,
      47.64171
    ]
  }
}