{
  "type": "Feature",
  "properties": {
    "name": "Weißenohe",
    "country": "DE",
    "subdivision": "02",
    "timezone": "Europe/Berlin"
  },
  "geometry": {
    "type": "Point",
    "coordinates": [
      11.25369,
      49.63089
    ]
  }
}