{
  "type": "Feature",
  "properties": {
    "name": "Wemding",
    "country": "DE",
    "subdivision": "02",
    "timezone": "Europe/Berlin"
  },
  "geometry": {
    "type": "Point",
    "coordinates": [
      10.72452,
      48.87461
    ]
  }
}