{
  "type": "Feature",
  "properties": {
    "name": "Wiesen",
    "country": "DE",
    "subdivision": "02",
    "timezone": "Europe/Berlin"
  },
  "geometry": {
    "type": "Point",
    "coordinates": [
      9.36667,
      50.11667
    ]
  }
}