{
  "type": "Feature",
  "properties": {
    "name": "Wiesenfelden",
    "country": "DE",
    "subdivision": "02",
    "timezone": "Europe/Berlin"
  },
  "geometry": {
    "type": "Point",
    "coordinates": [
      12.54008,
      49.04066
    ]
  }
}