{
  "type": "Feature",
  "properties": {
    "name": "Wilburgstetten",
    "country": "DE",
    "subdivision": "02",
    "timezone": "Europe/Berlin"
  },
  "geometry": {
    "type": "Point",
    "coordinates": [
      10.39505,
      49.02427
    ]
  }
}