{
  "type": "Feature",
  "properties": {
    "name": "Wilhermsdorf",
    "country": "DE",
    "subdivision": "02",
    "timezone": "Europe/Berlin"
  },
  "geometry": {
    "type": "Point",
    "coordinates": [
      10.71555,
      49.48308
    ]
  }
}