{
  "type": "Feature",
  "properties": {
    "name": "Winkelhaid",
    "country": "DE",
    "subdivision": "02",
    "timezone": "Europe/Berlin"
  },
  "geometry": {
    "type": "Point",
    "coordinates": [
      11.29888,
      49.38963
    ]
  }
}