{
  "type": "Feature",
  "properties": {
    "name": "Winterhausen",
    "country": "DE",
    "subdivision": "02",
    "timezone": "Europe/Berlin"
  },
  "geometry": {
    "type": "Point",
    "coordinates": [
      10.01661,
      49.70683
    ]
  }
}