{
  "type": "Feature",
  "properties": {
    "name": "Wolferstadt",
    "country": "DE",
    "subdivision": "02",
    "timezone": "Europe/Berlin"
  },
  "geometry": {
    "type": "Point",
    "coordinates": [
      10.78129,
      48.90352
    ]
  }
}