{
  "type": "Feature",
  "properties": {
    "name": "Wörth an der Isar",
    "country": "DE",
    "subdivision": "02",
    "timezone": "Europe/Berlin"
  },
  "geometry": {
    "type": "Point",
    "coordinates": [
      12.33944,
      48.623
    ]
  }
}