{
  "type": "Feature",
  "properties": {
    "name": "Wörthsee",
    "country": "DE",
    "subdivision": "02",
    "timezone": "Europe/Berlin"
  },
  "geometry": {
    "type": "Point",
    "coordinates": [
      11.20175,
      48.0725
    ]
  }
}