{
  "type": "Feature",
  "properties": {
    "name": "Zeitlarn",
    "country": "DE",
    "subdivision": "02",
    "timezone": "Europe/Berlin"
  },
  "geometry": {
    "type": "Point",
    "coordinates": [
      12.11174,
      49.07848
    ]
  }
}