{
  "type": "Feature",
  "properties": {
    "name": "Zirndorf",
    "country": "DE",
    "subdivision": "02",
    "timezone": "Europe/Berlin"
  },
  "geometry": {
    "type": "Point",
    "coordinates": [
      10.95414,
      49.4424
    ]
  }
}