{
  "type": "Feature",
  "properties": {
    "name": "Bernasconi",
    "country": "AR",
    "subdivision": "11",
    "timezone": "America/Argentina/Salta"
  },
  "geometry": {
    "type": "Point",
    "coordinates": [
      -63.7424,
      -37.90459
    ]
  }
}