{
  "type": "Feature",
  "properties": {
    "name": "Eduardo Castex",
    "country": "AR",
    "subdivision": "11",
    "timezone": "America/Argentina/Salta"
  },
  "geometry": {
    "type": "Point",
    "coordinates": [
      -64.29448,
      -35.91501
    ]
  }
}