{
  "type": "Feature",
  "properties": {
    "name": "La Adela",
    "country": "AR",
    "subdivision": "11",
    "timezone": "America/Argentina/Salta"
  },
  "geometry": {
    "type": "Point",
    "coordinates": [
      -64.08333,
      -38.98333
    ]
  }
}