{
  "type": "Feature",
  "properties": {
    "name": "Winifreda",
    "country": "AR",
    "subdivision": "11",
    "timezone": "America/Argentina/Salta"
  },
  "geometry": {
    "type": "Point",
    "coordinates": [
      -64.23388,
      -36.22643
    ]
  }
}