{
  "type": "Feature",
  "properties": {
    "name": "Ahar",
    "country": "IR",
    "subdivision": "33",
    "timezone": "Asia/Tehran"
  },
  "geometry": {
    "type": "Point",
    "coordinates": [
      47.0699,
      38.4774
    ]
  }
}