{
  "type": "Feature",
  "properties": {
    "name": "‘Ajab Shīr",
    "country": "IR",
    "subdivision": "33",
    "timezone": "Asia/Tehran"
  },
  "geometry": {
    "type": "Point",
    "coordinates": [
      45.8943,
      37.4776
    ]
  }
}