{
  "type": "Feature",
  "properties": {
    "name": "Kardonikskaya",
    "country": "RU",
    "subdivision": "27",
    "timezone": "Europe/Moscow"
  },
  "geometry": {
    "type": "Point",
    "coordinates": [
      41.71432,
      43.86577
    ]
  }
}