{
  "type": "Feature",
  "properties": {
    "name": "Kavkazskiy",
    "country": "RU",
    "subdivision": "27",
    "timezone": "Europe/Moscow"
  },
  "geometry": {
    "type": "Point",
    "coordinates": [
      42.2347,
      44.2672
    ]
  }
}