{
  "type": "Feature",
  "properties": {
    "name": "Nizhniy Arkhyz",
    "country": "RU",
    "subdivision": "27",
    "timezone": "Europe/Moscow"
  },
  "geometry": {
    "type": "Point",
    "coordinates": [
      41.45977,
      43.67817
    ]
  }
}