{
  "type": "Feature",
  "properties": {
    "name": "Pervomayskoye",
    "country": "RU",
    "subdivision": "27",
    "timezone": "Europe/Moscow"
  },
  "geometry": {
    "type": "Point",
    "coordinates": [
      42.476,
      43.93847
    ]
  }
}