{
  "type": "Feature",
  "properties": {
    "name": "Psyzh",
    "country": "RU",
    "subdivision": "27",
    "timezone": "Europe/Moscow"
  },
  "geometry": {
    "type": "Point",
    "coordinates": [
      42.01833,
      44.23306
    ]
  }
}