{
  "type": "Feature",
  "properties": {
    "name": "Čačinci",
    "country": "HR",
    "subdivision": "17",
    "timezone": "Europe/Zagreb"
  },
  "geometry": {
    "type": "Point",
    "coordinates": [
      17.87028,
      45.60389
    ]
  }
}