{
  "type": "Feature",
  "properties": {
    "name": "Pitomača",
    "country": "HR",
    "subdivision": "17",
    "timezone": "Europe/Zagreb"
  },
  "geometry": {
    "type": "Point",
    "coordinates": [
      17.22944,
      45.95056
    ]
  }
}