{
  "type": "Feature",
  "properties": {
    "name": "Acaponeta",
    "country": "MX",
    "subdivision": "18",
    "timezone": "America/Mazatlan"
  },
  "geometry": {
    "type": "Point",
    "coordinates": [
      -105.36369,
      22.49396
    ]
  }
}