{
  "type": "Feature",
  "properties": {
    "name": "Chilapa",
    "country": "MX",
    "subdivision": "18",
    "timezone": "America/Mazatlan"
  },
  "geometry": {
    "type": "Point",
    "coordinates": [
      -105.23057,
      22.03138
    ]
  }
}