{
  "type": "Feature",
  "properties": {
    "name": "El Llano",
    "country": "MX",
    "subdivision": "18",
    "timezone": "America/Mazatlan"
  },
  "geometry": {
    "type": "Point",
    "coordinates": [
      -105.17963,
      21.41854
    ]
  }
}