{
  "type": "Feature",
  "properties": {
    "name": "El Tizate",
    "country": "MX",
    "subdivision": "18",
    "timezone": "America/Mazatlan"
  },
  "geometry": {
    "type": "Point",
    "coordinates": [
      -105.1167,
      21.80179
    ]
  }
}