{
  "type": "Feature",
  "properties": {
    "name": "Emiliano Zapata",
    "country": "MX",
    "subdivision": "18",
    "timezone": "America/Mazatlan"
  },
  "geometry": {
    "type": "Point",
    "coordinates": [
      -104.91283,
      21.36477
    ]
  }
}