{
  "type": "Feature",
  "properties": {
    "name": "Huajicori",
    "country": "MX",
    "subdivision": "18",
    "timezone": "America/Mazatlan"
  },
  "geometry": {
    "type": "Point",
    "coordinates": [
      -105.31972,
      22.63667
    ]
  }
}