{
  "type": "Feature",
  "properties": {
    "name": "La Cantera",
    "country": "MX",
    "subdivision": "18",
    "timezone": "America/Mazatlan"
  },
  "geometry": {
    "type": "Point",
    "coordinates": [
      -104.82237,
      21.50308
    ]
  }
}