{
  "type": "Feature",
  "properties": {
    "name": "La Palma",
    "country": "MX",
    "subdivision": "18",
    "timezone": "America/Mazatlan"
  },
  "geometry": {
    "type": "Point",
    "coordinates": [
      -105.17817,
      21.49172
    ]
  }
}