{
  "type": "Feature",
  "properties": {
    "name": "Las Varas",
    "country": "MX",
    "subdivision": "18",
    "timezone": "America/Mazatlan"
  },
  "geometry": {
    "type": "Point",
    "coordinates": [
      -105.13595,
      21.18021
    ]
  }
}