{
  "type": "Feature",
  "properties": {
    "name": "Lo de Marcos",
    "country": "MX",
    "subdivision": "18",
    "timezone": "America/Mazatlan"
  },
  "geometry": {
    "type": "Point",
    "coordinates": [
      -105.35223,
      20.95509
    ]
  }
}