{
  "type": "Feature",
  "properties": {
    "name": "Puerta de Mangos",
    "country": "MX",
    "subdivision": "18",
    "timezone": "America/Mazatlan"
  },
  "geometry": {
    "type": "Point",
    "coordinates": [
      -105.33534,
      21.71853
    ]
  }
}