{
  "type": "Feature",
  "properties": {
    "name": "Rincón de Guayabitos",
    "country": "MX",
    "subdivision": "18",
    "timezone": "America/Mazatlan"
  },
  "geometry": {
    "type": "Point",
    "coordinates": [
      -105.27054,
      21.02315
    ]
  }
}