{
  "type": "Feature",
  "properties": {
    "name": "San Felipe Aztatán",
    "country": "MX",
    "subdivision": "18",
    "timezone": "America/Mazatlan"
  },
  "geometry": {
    "type": "Point",
    "coordinates": [
      -105.4198,
      22.38374
    ]
  }
}