{
  "type": "Feature",
  "properties": {
    "name": "Santiago Ixcuintla",
    "country": "MX",
    "subdivision": "18",
    "timezone": "America/Mazatlan"
  },
  "geometry": {
    "type": "Point",
    "coordinates": [
      -105.20844,
      21.81295
    ]
  }
}