{
  "type": "Feature",
  "properties": {
    "name": "Sayulilla",
    "country": "MX",
    "subdivision": "18",
    "timezone": "America/Mazatlan"
  },
  "geometry": {
    "type": "Point",
    "coordinates": [
      -105.39137,
      22.43822
    ]
  }
}