{
  "type": "Feature",
  "properties": {
    "name": "Bugaba",
    "country": "PA",
    "subdivision": "02",
    "timezone": "America/Panama"
  },
  "geometry": {
    "type": "Point",
    "coordinates": [
      -82.62023,
      8.48606
    ]
  }
}