{
  "type": "Feature",
  "properties": {
    "name": "David",
    "country": "PA",
    "subdivision": "02",
    "timezone": "America/Panama"
  },
  "geometry": {
    "type": "Point",
    "coordinates": [
      -82.43085,
      8.42729
    ]
  }
}