{
  "type": "Feature",
  "properties": {
    "name": "Las Lomas",
    "country": "PA",
    "subdivision": "02",
    "timezone": "America/Panama"
  },
  "geometry": {
    "type": "Point",
    "coordinates": [
      -82.38901,
      8.42897
    ]
  }
}