{
  "type": "Feature",
  "properties": {
    "name": "Santa Clara",
    "country": "PA",
    "subdivision": "02",
    "timezone": "America/Panama"
  },
  "geometry": {
    "type": "Point",
    "coordinates": [
      -82.78189,
      8.8348
    ]
  }
}