{
  "type": "Feature",
  "properties": {
    "name": "Alcabideche",
    "country": "PT",
    "subdivision": "14",
    "timezone": "Europe/Lisbon"
  },
  "geometry": {
    "type": "Point",
    "coordinates": [
      -9.40928,
      38.73366
    ]
  }
}