{
  "type": "Feature",
  "properties": {
    "name": "Alcoentre",
    "country": "PT",
    "subdivision": "14",
    "timezone": "Europe/Lisbon"
  },
  "geometry": {
    "type": "Point",
    "coordinates": [
      -8.95953,
      39.20857
    ]
  }
}