{
  "type": "Feature",
  "properties": {
    "name": "Arranhó",
    "country": "PT",
    "subdivision": "14",
    "timezone": "Europe/Lisbon"
  },
  "geometry": {
    "type": "Point",
    "coordinates": [
      -9.13465,
      38.95378
    ]
  }
}