{
  "type": "Feature",
  "properties": {
    "name": "Aveiras de Cima",
    "country": "PT",
    "subdivision": "14",
    "timezone": "Europe/Lisbon"
  },
  "geometry": {
    "type": "Point",
    "coordinates": [
      -8.89932,
      39.13796
    ]
  }
}