{
  "type": "Feature",
  "properties": {
    "name": "Cacém",
    "country": "PT",
    "subdivision": "14",
    "timezone": "Europe/Lisbon"
  },
  "geometry": {
    "type": "Point",
    "coordinates": [
      -9.29793,
      38.76698
    ]
  }
}