{
  "type": "Feature",
  "properties": {
    "name": "Cadafais",
    "country": "PT",
    "subdivision": "14",
    "timezone": "Europe/Lisbon"
  },
  "geometry": {
    "type": "Point",
    "coordinates": [
      -9.00419,
      39.00461
    ]
  }
}