{
  "type": "Feature",
  "properties": {
    "name": "Cascais",
    "country": "PT",
    "subdivision": "14",
    "timezone": "Europe/Lisbon"
  },
  "geometry": {
    "type": "Point",
    "coordinates": [
      -9.42147,
      38.69681
    ]
  }
}