{
  "type": "Feature",
  "properties": {
    "name": "Moscavide e Portela",
    "country": "PT",
    "subdivision": "14",
    "timezone": "Europe/Lisbon"
  },
  "geometry": {
    "type": "Point",
    "coordinates": [
      -9.10222,
      38.77929
    ]
  }
}