{
  "type": "Feature",
  "properties": {
    "name": "São Bartolomeu",
    "country": "PT",
    "subdivision": "14",
    "timezone": "Europe/Lisbon"
  },
  "geometry": {
    "type": "Point",
    "coordinates": [
      -9.27885,
      39.27511
    ]
  }
}