{
  "type": "Feature",
  "properties": {
    "name": "Sintra",
    "country": "PT",
    "subdivision": "14",
    "timezone": "Europe/Lisbon"
  },
  "geometry": {
    "type": "Point",
    "coordinates": [
      -9.37826,
      38.80097
    ]
  }
}