{
  "type": "Feature",
  "properties": {
    "name": "Terrugem",
    "country": "PT",
    "subdivision": "14",
    "timezone": "Europe/Lisbon"
  },
  "geometry": {
    "type": "Point",
    "coordinates": [
      -9.28693,
      38.70647
    ]
  }
}