{
  "type": "Feature",
  "properties": {
    "name": "Kugluktuk",
    "country": "CA",
    "subdivision": "14",
    "timezone": "America/Cambridge_Bay"
  },
  "geometry": {
    "type": "Point",
    "coordinates": [
      -115.09649,
      67.82743
    ]
  }
}