{
  "type": "Feature",
  "properties": {
    "name": "Giurgiuleşti",
    "country": "MD",
    "subdivision": "64",
    "timezone": "Europe/Chisinau"
  },
  "geometry": {
    "type": "Point",
    "coordinates": [
      28.19722,
      45.48167
    ]
  }
}