{
  "type": "Feature",
  "properties": {
    "name": "Muar",
    "country": "MY",
    "subdivision": "01",
    "timezone": "Asia/Kuala_Lumpur"
  },
  "geometry": {
    "type": "Point",
    "coordinates": [
      102.5689,
      2.0442
    ]
  }
}