{
  "type": "Feature",
  "properties": {
    "name": "Taman Senai",
    "country": "MY",
    "subdivision": "01",
    "timezone": "Asia/Kuala_Lumpur"
  },
  "geometry": {
    "type": "Point",
    "coordinates": [
      103.6419,
      1.6006
    ]
  }
}