{
  "type": "Feature",
  "properties": {
    "name": "Gotovlje",
    "country": "SI",
    "subdivision": "N5",
    "timezone": "Europe/Ljubljana"
  },
  "geometry": {
    "type": "Point",
    "coordinates": [
      15.15186,
      46.27418
    ]
  }
}