{
  "type": "Feature",
  "properties": {
    "name": "GanÄani",
    "country": "SI",
    "subdivision": "02",
    "timezone": "Europe/Ljubljana"
  },
  "geometry": {
    "type": "Point",
    "coordinates": [
      16.25111,
      46.6325
    ]
  }
}