{
  "type": "Feature",
  "properties": {
    "name": "Boende",
    "country": "CD",
    "subdivision": "31",
    "timezone": "Africa/Kinshasa"
  },
  "geometry": {
    "type": "Point",
    "coordinates": [
      20.88053,
      -0.28163
    ]
  }
}