{
  "type": "Feature",
  "properties": {
    "name": "Nordstranda",
    "country": "NO",
    "subdivision": "08",
    "timezone": "Europe/Oslo"
  },
  "geometry": {
    "type": "Point",
    "coordinates": [
      6.13166,
      62.51384
    ]
  }
}