{
  "type": "Feature",
  "properties": {
    "name": "Sunndalsøra",
    "country": "NO",
    "subdivision": "08",
    "timezone": "Europe/Oslo"
  },
  "geometry": {
    "type": "Point",
    "coordinates": [
      8.56327,
      62.67519
    ]
  }
}