{
  "type": "Feature",
  "properties": {
    "name": "Simnas",
    "country": "LT",
    "subdivision": "56",
    "timezone": "Europe/Vilnius"
  },
  "geometry": {
    "type": "Point",
    "coordinates": [
      23.646,
      54.382
    ]
  }
}