{
  "type": "Feature",
  "properties": {
    "name": "Varėna",
    "country": "LT",
    "subdivision": "56",
    "timezone": "Europe/Vilnius"
  },
  "geometry": {
    "type": "Point",
    "coordinates": [
      24.57538,
      54.21546
    ]
  }
}