{
  "type": "Feature",
  "properties": {
    "name": "Ombúes de Lavalle",
    "country": "UY",
    "subdivision": "04",
    "timezone": "America/Montevideo"
  },
  "geometry": {
    "type": "Point",
    "coordinates": [
      -57.80959,
      -33.93783
    ]
  }
}