{
  "type": "Feature",
  "properties": {
    "name": "Karmėlava",
    "country": "LT",
    "subdivision": "57",
    "timezone": "Europe/Vilnius"
  },
  "geometry": {
    "type": "Point",
    "coordinates": [
      24.06182,
      54.97055
    ]
  }
}