{
  "type": "Feature",
  "properties": {
    "name": "Gaoyi",
    "country": "CN",
    "subdivision": "11",
    "timezone": "Asia/Shanghai"
  },
  "geometry": {
    "type": "Point",
    "coordinates": [
      110.01556,
      26.95944
    ]
  }
}