{
  "type": "Feature",
  "properties": {
    "name": "Huangqiao",
    "country": "CN",
    "subdivision": "11",
    "timezone": "Asia/Shanghai"
  },
  "geometry": {
    "type": "Point",
    "coordinates": [
      110.84056,
      27.02194
    ]
  }
}