{
  "type": "Feature",
  "properties": {
    "name": "Jinhe",
    "country": "CN",
    "subdivision": "11",
    "timezone": "Asia/Shanghai"
  },
  "geometry": {
    "type": "Point",
    "coordinates": [
      109.60472,
      27.71694
    ]
  }
}