{
  "type": "Feature",
  "properties": {
    "name": "Lengshuijiang",
    "country": "CN",
    "subdivision": "11",
    "timezone": "Asia/Shanghai"
  },
  "geometry": {
    "type": "Point",
    "coordinates": [
      111.42944,
      27.68806
    ]
  }
}