{
  "type": "Feature",
  "properties": {
    "name": "Ruoshui",
    "country": "CN",
    "subdivision": "11",
    "timezone": "Asia/Shanghai"
  },
  "geometry": {
    "type": "Point",
    "coordinates": [
      109.96667,
      27.00194
    ]
  }
}