{
  "type": "Feature",
  "properties": {
    "name": "Shuangxi",
    "country": "CN",
    "subdivision": "11",
    "timezone": "Asia/Shanghai"
  },
  "geometry": {
    "type": "Point",
    "coordinates": [
      109.85583,
      27.22833
    ]
  }
}