{
  "type": "Feature",
  "properties": {
    "name": "Shuangjiang",
    "country": "CN",
    "subdivision": "11",
    "timezone": "Asia/Shanghai"
  },
  "geometry": {
    "type": "Point",
    "coordinates": [
      109.7138,
      26.15467
    ]
  }
}