{
  "type": "Feature",
  "properties": {
    "name": "Shuiche",
    "country": "CN",
    "subdivision": "11",
    "timezone": "Asia/Shanghai"
  },
  "geometry": {
    "type": "Point",
    "coordinates": [
      110.99972,
      27.68694
    ]
  }
}