{
  "type": "Feature",
  "properties": {
    "name": "Wuyang",
    "country": "CN",
    "subdivision": "11",
    "timezone": "Asia/Shanghai"
  },
  "geometry": {
    "type": "Point",
    "coordinates": [
      110.32833,
      26.74278
    ]
  }
}