{
  "type": "Feature",
  "properties": {
    "name": "Yongfeng",
    "country": "CN",
    "subdivision": "11",
    "timezone": "Asia/Shanghai"
  },
  "geometry": {
    "type": "Point",
    "coordinates": [
      112.16943,
      27.45493
    ]
  }
}