{
  "type": "Feature",
  "properties": {
    "name": "Balta",
    "country": "RO",
    "subdivision": "26",
    "timezone": "Europe/Bucharest"
  },
  "geometry": {
    "type": "Point",
    "coordinates": [
      22.63694,
      44.88694
    ]
  }
}