{
  "type": "Feature",
  "properties": {
    "name": "Brezniţa-Motru",
    "country": "RO",
    "subdivision": "26",
    "timezone": "Europe/Bucharest"
  },
  "geometry": {
    "type": "Point",
    "coordinates": [
      23.21667,
      44.56667
    ]
  }
}