{
  "type": "Feature",
  "properties": {
    "name": "Căzăneşti",
    "country": "RO",
    "subdivision": "26",
    "timezone": "Europe/Bucharest"
  },
  "geometry": {
    "type": "Point",
    "coordinates": [
      22.89056,
      44.72333
    ]
  }
}