{
  "type": "Feature",
  "properties": {
    "name": "Cujmir",
    "country": "RO",
    "subdivision": "26",
    "timezone": "Europe/Bucharest"
  },
  "geometry": {
    "type": "Point",
    "coordinates": [
      22.92667,
      44.20667
    ]
  }
}