{
  "type": "Feature",
  "properties": {
    "name": "Gârla-Mare",
    "country": "RO",
    "subdivision": "26",
    "timezone": "Europe/Bucharest"
  },
  "geometry": {
    "type": "Point",
    "coordinates": [
      22.775,
      44.20917
    ]
  }
}