{
  "type": "Feature",
  "properties": {
    "name": "Malovăţ",
    "country": "RO",
    "subdivision": "26",
    "timezone": "Europe/Bucharest"
  },
  "geometry": {
    "type": "Point",
    "coordinates": [
      22.73111,
      44.70444
    ]
  }
}