{
  "type": "Feature",
  "properties": {
    "name": "Vrata",
    "country": "RO",
    "subdivision": "26",
    "timezone": "Europe/Bucharest"
  },
  "geometry": {
    "type": "Point",
    "coordinates": [
      22.84928,
      44.19197
    ]
  }
}