{
  "type": "Feature",
  "properties": {
    "name": "Cestos City",
    "country": "LR",
    "subdivision": "18",
    "timezone": "Africa/Monrovia"
  },
  "geometry": {
    "type": "Point",
    "coordinates": [
      -9.58167,
      5.45683
    ]
  }
}