{
  "type": "Feature",
  "properties": {
    "name": "Bessonovka",
    "country": "RU",
    "subdivision": "09",
    "timezone": "Europe/Moscow"
  },
  "geometry": {
    "type": "Point",
    "coordinates": [
      36.30107,
      50.52644
    ]
  }
}