{
  "type": "Feature",
  "properties": {
    "name": "Grayvoron",
    "country": "RU",
    "subdivision": "09",
    "timezone": "Europe/Moscow"
  },
  "geometry": {
    "type": "Point",
    "coordinates": [
      35.6773,
      50.4767
    ]
  }
}