{
  "type": "Feature",
  "properties": {
    "name": "Novyy Oskol",
    "country": "RU",
    "subdivision": "09",
    "timezone": "Europe/Moscow"
  },
  "geometry": {
    "type": "Point",
    "coordinates": [
      37.86415,
      50.76331
    ]
  }
}