{
  "type": "Feature",
  "properties": {
    "name": "Rakitnoye",
    "country": "RU",
    "subdivision": "09",
    "timezone": "Europe/Moscow"
  },
  "geometry": {
    "type": "Point",
    "coordinates": [
      35.8515,
      50.8389
    ]
  }
}