{
  "type": "Feature",
  "properties": {
    "name": "Stroitel’",
    "country": "RU",
    "subdivision": "09",
    "timezone": "Europe/Moscow"
  },
  "geometry": {
    "type": "Point",
    "coordinates": [
      36.4831,
      50.78543
    ]
  }
}