{
  "type": "Feature",
  "properties": {
    "name": "Nongstoin",
    "country": "IN",
    "subdivision": "18",
    "timezone": "Asia/Kolkata"
  },
  "geometry": {
    "type": "Point",
    "coordinates": [
      91.26484,
      25.51704
    ]
  }
}