{
  "type": "Feature",
  "properties": {
    "name": "Al Baţţālīyah",
    "country": "SA",
    "subdivision": "06",
    "timezone": "Asia/Riyadh"
  },
  "geometry": {
    "type": "Point",
    "coordinates": [
      49.63333,
      25.43333
    ]
  }
}