{
  "type": "Feature",
  "properties": {
    "name": "Al Hufūf",
    "country": "SA",
    "subdivision": "06",
    "timezone": "Asia/Riyadh"
  },
  "geometry": {
    "type": "Point",
    "coordinates": [
      49.58764,
      25.36467
    ]
  }
}