{
  "type": "Feature",
  "properties": {
    "name": "Dhahran",
    "country": "SA",
    "subdivision": "06",
    "timezone": "Asia/Riyadh"
  },
  "geometry": {
    "type": "Point",
    "coordinates": [
      50.11396,
      26.28864
    ]
  }
}