{
  "type": "Feature",
  "properties": {
    "name": "Hafar Al-Batin",
    "country": "SA",
    "subdivision": "06",
    "timezone": "Asia/Riyadh"
  },
  "geometry": {
    "type": "Point",
    "coordinates": [
      45.97077,
      28.43279
    ]
  }
}