{
  "type": "Feature",
  "properties": {
    "name": "Raḩīmah",
    "country": "SA",
    "subdivision": "06",
    "timezone": "Asia/Riyadh"
  },
  "geometry": {
    "type": "Point",
    "coordinates": [
      50.06194,
      26.70791
    ]
  }
}