{
  "type": "Feature",
  "properties": {
    "name": "SayhÄt",
    "country": "SA",
    "subdivision": "06",
    "timezone": "Asia/Riyadh"
  },
  "geometry": {
    "type": "Point",
    "coordinates": [
      50.04849,
      26.48345
    ]
  }
}