{
  "type": "Feature",
  "properties": {
    "name": "Umm as SÄhik",
    "country": "SA",
    "subdivision": "06",
    "timezone": "Asia/Riyadh"
  },
  "geometry": {
    "type": "Point",
    "coordinates": [
      49.91639,
      26.65361
    ]
  }
}