{
  "type": "Feature",
  "properties": {
    "name": "Býšť",
    "country": "CZ",
    "subdivision": "86",
    "timezone": "Europe/Prague"
  },
  "geometry": {
    "type": "Point",
    "coordinates": [
      15.91116,
      50.13243
    ]
  }
}