{
  "type": "Feature",
  "properties": {
    "name": "Červená Voda",
    "country": "CZ",
    "subdivision": "86",
    "timezone": "Europe/Prague"
  },
  "geometry": {
    "type": "Point",
    "coordinates": [
      16.74268,
      50.04029
    ]
  }
}