{
  "type": "Feature",
  "properties": {
    "name": "Chrudim",
    "country": "CZ",
    "subdivision": "86",
    "timezone": "Europe/Prague"
  },
  "geometry": {
    "type": "Point",
    "coordinates": [
      15.79558,
      49.95109
    ]
  }
}