{
  "type": "Feature",
  "properties": {
    "name": "Dašice",
    "country": "CZ",
    "subdivision": "86",
    "timezone": "Europe/Prague"
  },
  "geometry": {
    "type": "Point",
    "coordinates": [
      15.91244,
      50.02844
    ]
  }
}