{
  "type": "Feature",
  "properties": {
    "name": "Dolní Újezd",
    "country": "CZ",
    "subdivision": "86",
    "timezone": "Europe/Prague"
  },
  "geometry": {
    "type": "Point",
    "coordinates": [
      16.25461,
      49.82562
    ]
  }
}