{
  "type": "Feature",
  "properties": {
    "name": "Jevíčko",
    "country": "CZ",
    "subdivision": "86",
    "timezone": "Europe/Prague"
  },
  "geometry": {
    "type": "Point",
    "coordinates": [
      16.71125,
      49.6322
    ]
  }
}