{
  "type": "Feature",
  "properties": {
    "name": "Králíky",
    "country": "CZ",
    "subdivision": "86",
    "timezone": "Europe/Prague"
  },
  "geometry": {
    "type": "Point",
    "coordinates": [
      16.76054,
      50.08384
    ]
  }
}