{
  "type": "Feature",
  "properties": {
    "name": "Moravská Třebová",
    "country": "CZ",
    "subdivision": "86",
    "timezone": "Europe/Prague"
  },
  "geometry": {
    "type": "Point",
    "coordinates": [
      16.66426,
      49.75793
    ]
  }
}