{
  "type": "Feature",
  "properties": {
    "name": "Opatov",
    "country": "CZ",
    "subdivision": "86",
    "timezone": "Europe/Prague"
  },
  "geometry": {
    "type": "Point",
    "coordinates": [
      16.50458,
      49.825
    ]
  }
}