{
  "type": "Feature",
  "properties": {
    "name": "Opatovice nad Labem",
    "country": "CZ",
    "subdivision": "86",
    "timezone": "Europe/Prague"
  },
  "geometry": {
    "type": "Point",
    "coordinates": [
      15.79045,
      50.14541
    ]
  }
}