{
  "type": "Feature",
  "properties": {
    "name": "Staré Hradiště",
    "country": "CZ",
    "subdivision": "86",
    "timezone": "Europe/Prague"
  },
  "geometry": {
    "type": "Point",
    "coordinates": [
      15.77885,
      50.0654
    ]
  }
}