{
  "type": "Feature",
  "properties": {
    "name": "Argáka",
    "country": "CY",
    "subdivision": "06",
    "timezone": "Asia/Nicosia"
  },
  "geometry": {
    "type": "Point",
    "coordinates": [
      32.49226,
      35.06586
    ]
  }
}