{
  "type": "Feature",
  "properties": {
    "name": "Aalst",
    "country": "NL",
    "subdivision": "06",
    "timezone": "Europe/Amsterdam"
  },
  "geometry": {
    "type": "Point",
    "coordinates": [
      5.47778,
      51.39667
    ]
  }
}