{
  "type": "Feature",
  "properties": {
    "name": "Baarle-Nassau",
    "country": "NL",
    "subdivision": "06",
    "timezone": "Europe/Amsterdam"
  },
  "geometry": {
    "type": "Point",
    "coordinates": [
      4.92917,
      51.4475
    ]
  }
}