{
  "type": "Feature",
  "properties": {
    "name": "Besterd",
    "country": "NL",
    "subdivision": "06",
    "timezone": "Europe/Amsterdam"
  },
  "geometry": {
    "type": "Point",
    "coordinates": [
      5.08658,
      51.5638
    ]
  }
}