{
  "type": "Feature",
  "properties": {
    "name": "Biesdonk",
    "country": "NL",
    "subdivision": "06",
    "timezone": "Europe/Amsterdam"
  },
  "geometry": {
    "type": "Point",
    "coordinates": [
      4.78515,
      51.60613
    ]
  }
}