{
  "type": "Feature",
  "properties": {
    "name": "Budel",
    "country": "NL",
    "subdivision": "06",
    "timezone": "Europe/Amsterdam"
  },
  "geometry": {
    "type": "Point",
    "coordinates": [
      5.575,
      51.27167
    ]
  }
}