{
  "type": "Feature",
  "properties": {
    "name": "Cuijk",
    "country": "NL",
    "subdivision": "06",
    "timezone": "Europe/Amsterdam"
  },
  "geometry": {
    "type": "Point",
    "coordinates": [
      5.87917,
      51.73083
    ]
  }
}