{
  "type": "Feature",
  "properties": {
    "name": "Deuteren",
    "country": "NL",
    "subdivision": "06",
    "timezone": "Europe/Amsterdam"
  },
  "geometry": {
    "type": "Point",
    "coordinates": [
      5.26667,
      51.68667
    ]
  }
}