{
  "type": "Feature",
  "properties": {
    "name": "Elshout",
    "country": "NL",
    "subdivision": "06",
    "timezone": "Europe/Amsterdam"
  },
  "geometry": {
    "type": "Point",
    "coordinates": [
      5.14167,
      51.70083
    ]
  }
}