{
  "type": "Feature",
  "properties": {
    "name": "Geertruidenberg",
    "country": "NL",
    "subdivision": "06",
    "timezone": "Europe/Amsterdam"
  },
  "geometry": {
    "type": "Point",
    "coordinates": [
      4.85694,
      51.70167
    ]
  }
}