{
  "type": "Feature",
  "properties": {
    "name": "Ginneken",
    "country": "NL",
    "subdivision": "06",
    "timezone": "Europe/Amsterdam"
  },
  "geometry": {
    "type": "Point",
    "coordinates": [
      4.7931,
      51.56593
    ]
  }
}