{
  "type": "Feature",
  "properties": {
    "name": "Heusden",
    "country": "NL",
    "subdivision": "06",
    "timezone": "Europe/Amsterdam"
  },
  "geometry": {
    "type": "Point",
    "coordinates": [
      5.13889,
      51.73417
    ]
  }
}