{
  "type": "Feature",
  "properties": {
    "name": "Lierop",
    "country": "NL",
    "subdivision": "06",
    "timezone": "Europe/Amsterdam"
  },
  "geometry": {
    "type": "Point",
    "coordinates": [
      5.67917,
      51.41917
    ]
  }
}