{
  "type": "Feature",
  "properties": {
    "name": "Megen",
    "country": "NL",
    "subdivision": "06",
    "timezone": "Europe/Amsterdam"
  },
  "geometry": {
    "type": "Point",
    "coordinates": [
      5.5625,
      51.82167
    ]
  }
}