{
  "type": "Feature",
  "properties": {
    "name": "Mierlo",
    "country": "NL",
    "subdivision": "06",
    "timezone": "Europe/Amsterdam"
  },
  "geometry": {
    "type": "Point",
    "coordinates": [
      5.61944,
      51.44
    ]
  }
}