{
  "type": "Feature",
  "properties": {
    "name": "Naastenbest",
    "country": "NL",
    "subdivision": "06",
    "timezone": "Europe/Amsterdam"
  },
  "geometry": {
    "type": "Point",
    "coordinates": [
      5.38579,
      51.50484
    ]
  }
}