{
  "type": "Feature",
  "properties": {
    "name": "Neerkant",
    "country": "NL",
    "subdivision": "06",
    "timezone": "Europe/Amsterdam"
  },
  "geometry": {
    "type": "Point",
    "coordinates": [
      5.86667,
      51.36833
    ]
  }
}