{
  "type": "Feature",
  "properties": {
    "name": "Oerle",
    "country": "NL",
    "subdivision": "06",
    "timezone": "Europe/Amsterdam"
  },
  "geometry": {
    "type": "Point",
    "coordinates": [
      5.37163,
      51.42255
    ]
  }
}