{
  "type": "Feature",
  "properties": {
    "name": "Overloon",
    "country": "NL",
    "subdivision": "06",
    "timezone": "Europe/Amsterdam"
  },
  "geometry": {
    "type": "Point",
    "coordinates": [
      5.94722,
      51.57167
    ]
  }
}