{
  "type": "Feature",
  "properties": {
    "name": "Raam",
    "country": "NL",
    "subdivision": "06",
    "timezone": "Europe/Amsterdam"
  },
  "geometry": {
    "type": "Point",
    "coordinates": [
      5.63637,
      51.65967
    ]
  }
}