{
  "type": "Feature",
  "properties": {
    "name": "Riethoven",
    "country": "NL",
    "subdivision": "06",
    "timezone": "Europe/Amsterdam"
  },
  "geometry": {
    "type": "Point",
    "coordinates": [
      5.3875,
      51.35417
    ]
  }
}