{
  "type": "Feature",
  "properties": {
    "name": "Roosendaal",
    "country": "NL",
    "subdivision": "06",
    "timezone": "Europe/Amsterdam"
  },
  "geometry": {
    "type": "Point",
    "coordinates": [
      4.46528,
      51.53083
    ]
  }
}