{
  "type": "Feature",
  "properties": {
    "name": "Rucphen",
    "country": "NL",
    "subdivision": "06",
    "timezone": "Europe/Amsterdam"
  },
  "geometry": {
    "type": "Point",
    "coordinates": [
      4.55833,
      51.53167
    ]
  }
}