{
  "type": "Feature",
  "properties": {
    "name": "Someren-Eind",
    "country": "NL",
    "subdivision": "06",
    "timezone": "Europe/Amsterdam"
  },
  "geometry": {
    "type": "Point",
    "coordinates": [
      5.73333,
      51.3575
    ]
  }
}