{
  "type": "Feature",
  "properties": {
    "name": "Steenbergen",
    "country": "NL",
    "subdivision": "06",
    "timezone": "Europe/Amsterdam"
  },
  "geometry": {
    "type": "Point",
    "coordinates": [
      4.31944,
      51.58417
    ]
  }
}