{
  "type": "Feature",
  "properties": {
    "name": "Terheijden",
    "country": "NL",
    "subdivision": "06",
    "timezone": "Europe/Amsterdam"
  },
  "geometry": {
    "type": "Point",
    "coordinates": [
      4.75417,
      51.64333
    ]
  }
}