{
  "type": "Feature",
  "properties": {
    "name": "Vlierden",
    "country": "NL",
    "subdivision": "06",
    "timezone": "Europe/Amsterdam"
  },
  "geometry": {
    "type": "Point",
    "coordinates": [
      5.75833,
      51.445
    ]
  }
}