{
  "type": "Feature",
  "properties": {
    "name": "Voldijn",
    "country": "NL",
    "subdivision": "06",
    "timezone": "Europe/Amsterdam"
  },
  "geometry": {
    "type": "Point",
    "coordinates": [
      5.47196,
      51.40052
    ]
  }
}