{
  "type": "Feature",
  "properties": {
    "name": "Wagenberg",
    "country": "NL",
    "subdivision": "06",
    "timezone": "Europe/Amsterdam"
  },
  "geometry": {
    "type": "Point",
    "coordinates": [
      4.74861,
      51.665
    ]
  }
}