{
  "type": "Feature",
  "properties": {
    "name": "Izumi",
    "country": "JP",
    "subdivision": "32",
    "timezone": "Asia/Tokyo"
  },
  "geometry": {
    "type": "Point",
    "coordinates": [
      135.43333,
      34.48333
    ]
  }
}