{
  "type": "Feature",
  "properties": {
    "name": "Moriguchi",
    "country": "JP",
    "subdivision": "32",
    "timezone": "Asia/Tokyo"
  },
  "geometry": {
    "type": "Point",
    "coordinates": [
      135.56667,
      34.73333
    ]
  }
}