{
  "type": "Feature",
  "properties": {
    "name": "Neyagawa",
    "country": "JP",
    "subdivision": "32",
    "timezone": "Asia/Tokyo"
  },
  "geometry": {
    "type": "Point",
    "coordinates": [
      135.62759,
      34.76615
    ]
  }
}