{
  "type": "Feature",
  "properties": {
    "name": "Tondabayashichō",
    "country": "JP",
    "subdivision": "32",
    "timezone": "Asia/Tokyo"
  },
  "geometry": {
    "type": "Point",
    "coordinates": [
      135.60211,
      34.50065
    ]
  }
}