{
  "type": "Feature",
  "properties": {
    "name": "Austins Ferry",
    "country": "AU",
    "subdivision": "06",
    "timezone": "Australia/Hobart"
  },
  "geometry": {
    "type": "Point",
    "coordinates": [
      147.25,
      -42.76667
    ]
  }
}