{
  "type": "Feature",
  "properties": {
    "name": "Battery Point",
    "country": "AU",
    "subdivision": "06",
    "timezone": "Australia/Hobart"
  },
  "geometry": {
    "type": "Point",
    "coordinates": [
      147.33324,
      -42.88995
    ]
  }
}