{
  "type": "Feature",
  "properties": {
    "name": "Bridport",
    "country": "AU",
    "subdivision": "06",
    "timezone": "Australia/Hobart"
  },
  "geometry": {
    "type": "Point",
    "coordinates": [
      147.39175,
      -41.00046
    ]
  }
}