{
  "type": "Feature",
  "properties": {
    "name": "Bridgewater",
    "country": "AU",
    "subdivision": "06",
    "timezone": "Australia/Hobart"
  },
  "geometry": {
    "type": "Point",
    "coordinates": [
      147.22784,
      -42.73719
    ]
  }
}