{
  "type": "Feature",
  "properties": {
    "name": "Cygnet",
    "country": "AU",
    "subdivision": "06",
    "timezone": "Australia/Hobart"
  },
  "geometry": {
    "type": "Point",
    "coordinates": [
      147.07253,
      -43.15333
    ]
  }
}