{
  "type": "Feature",
  "properties": {
    "name": "Dynnyrne",
    "country": "AU",
    "subdivision": "06",
    "timezone": "Australia/Hobart"
  },
  "geometry": {
    "type": "Point",
    "coordinates": [
      147.31576,
      -42.90541
    ]
  }
}