{
  "type": "Feature",
  "properties": {
    "name": "East Launceston",
    "country": "AU",
    "subdivision": "06",
    "timezone": "Australia/Hobart"
  },
  "geometry": {
    "type": "Point",
    "coordinates": [
      147.15101,
      -41.43843
    ]
  }
}