{
  "type": "Feature",
  "properties": {
    "name": "Franklin",
    "country": "AU",
    "subdivision": "06",
    "timezone": "Australia/Hobart"
  },
  "geometry": {
    "type": "Point",
    "coordinates": [
      147.00906,
      -43.08884
    ]
  }
}