{
  "type": "Feature",
  "properties": {
    "name": "Howrah",
    "country": "AU",
    "subdivision": "06",
    "timezone": "Australia/Hobart"
  },
  "geometry": {
    "type": "Point",
    "coordinates": [
      147.40554,
      -42.88728
    ]
  }
}