{
  "type": "Feature",
  "properties": {
    "name": "Mount Stuart",
    "country": "AU",
    "subdivision": "06",
    "timezone": "Australia/Hobart"
  },
  "geometry": {
    "type": "Point",
    "coordinates": [
      147.30164,
      -42.87157
    ]
  }
}