{
  "type": "Feature",
  "properties": {
    "name": "Mowbray",
    "country": "AU",
    "subdivision": "06",
    "timezone": "Australia/Hobart"
  },
  "geometry": {
    "type": "Point",
    "coordinates": [
      147.15059,
      -41.40243
    ]
  }
}