{
  "type": "Feature",
  "properties": {
    "name": "Saint Leonards",
    "country": "AU",
    "subdivision": "06",
    "timezone": "Australia/Hobart"
  },
  "geometry": {
    "type": "Point",
    "coordinates": [
      147.19952,
      -41.45672
    ]
  }
}