{
  "type": "Feature",
  "properties": {
    "name": "Snug",
    "country": "AU",
    "subdivision": "06",
    "timezone": "Australia/Hobart"
  },
  "geometry": {
    "type": "Point",
    "coordinates": [
      147.25468,
      -43.06669
    ]
  }
}