{
  "type": "Feature",
  "properties": {
    "name": "Sorell",
    "country": "AU",
    "subdivision": "06",
    "timezone": "Australia/Hobart"
  },
  "geometry": {
    "type": "Point",
    "coordinates": [
      147.56267,
      -42.78161
    ]
  }
}