{
  "type": "Feature",
  "properties": {
    "name": "Fenoarivo Atsinanana",
    "country": "MG",
    "subdivision": "32",
    "timezone": "Indian/Antananarivo"
  },
  "geometry": {
    "type": "Point",
    "coordinates": [
      49.40826,
      -17.38095
    ]
  }
}