{
  "type": "Feature",
  "properties": {
    "name": "Dobrinka",
    "country": "RU",
    "subdivision": "43",
    "timezone": "Europe/Moscow"
  },
  "geometry": {
    "type": "Point",
    "coordinates": [
      40.47306,
      52.16528
    ]
  }
}