{
  "type": "Feature",
  "properties": {
    "name": "Khlevnoye",
    "country": "RU",
    "subdivision": "43",
    "timezone": "Europe/Moscow"
  },
  "geometry": {
    "type": "Point",
    "coordinates": [
      39.09316,
      52.19512
    ]
  }
}