{
  "type": "Feature",
  "properties": {
    "name": "Volovo",
    "country": "RU",
    "subdivision": "43",
    "timezone": "Europe/Moscow"
  },
  "geometry": {
    "type": "Point",
    "coordinates": [
      37.8854,
      52.02659
    ]
  }
}