{
  "type": "Feature",
  "properties": {
    "name": "Lyaskovets",
    "country": "BG",
    "subdivision": "62",
    "timezone": "Europe/Sofia"
  },
  "geometry": {
    "type": "Point",
    "coordinates": [
      25.72833,
      43.11111
    ]
  }
}