{
  "type": "Feature",
  "properties": {
    "name": "Polski Trambesh",
    "country": "BG",
    "subdivision": "62",
    "timezone": "Europe/Sofia"
  },
  "geometry": {
    "type": "Point",
    "coordinates": [
      25.63525,
      43.37233
    ]
  }
}