{
  "type": "Feature",
  "properties": {
    "name": "Breves",
    "country": "BR",
    "subdivision": "16",
    "timezone": "America/Belem"
  },
  "geometry": {
    "type": "Point",
    "coordinates": [
      -50.48028,
      -1.68222
    ]
  }
}