{
  "type": "Feature",
  "properties": {
    "name": "Marapanim",
    "country": "BR",
    "subdivision": "16",
    "timezone": "America/Belem"
  },
  "geometry": {
    "type": "Point",
    "coordinates": [
      -47.69972,
      -0.7175
    ]
  }
}