{
  "type": "Feature",
  "properties": {
    "name": "Muaná",
    "country": "BR",
    "subdivision": "16",
    "timezone": "America/Belem"
  },
  "geometry": {
    "type": "Point",
    "coordinates": [
      -49.21667,
      -1.52833
    ]
  }
}