{
  "type": "Feature",
  "properties": {
    "name": "Oeiras do Pará",
    "country": "BR",
    "subdivision": "16",
    "timezone": "America/Belem"
  },
  "geometry": {
    "type": "Point",
    "coordinates": [
      -49.85444,
      -2.00306
    ]
  }
}