{
  "type": "Feature",
  "properties": {
    "name": "São Félix do Xingu",
    "country": "BR",
    "subdivision": "16",
    "timezone": "America/Belem"
  },
  "geometry": {
    "type": "Point",
    "coordinates": [
      -51.995,
      -6.64472
    ]
  }
}