{
  "type": "Feature",
  "properties": {
    "name": "Terra Santa",
    "country": "BR",
    "subdivision": "16",
    "timezone": "America/Santarem"
  },
  "geometry": {
    "type": "Point",
    "coordinates": [
      -56.48694,
      -2.10417
    ]
  }
}