{
  "type": "Feature",
  "properties": {
    "name": "Xankandi",
    "country": "AZ",
    "subdivision": "61",
    "timezone": "Asia/Baku"
  },
  "geometry": {
    "type": "Point",
    "coordinates": [
      46.7528,
      39.8177
    ]
  }
}