{
  "type": "Feature",
  "properties": {
    "name": "Córdoba",
    "country": "CO",
    "subdivision": "35",
    "timezone": "America/Bogota"
  },
  "geometry": {
    "type": "Point",
    "coordinates": [
      -74.82705,
      9.58612
    ]
  }
}