{
  "type": "Feature",
  "properties": {
    "name": "Regidor",
    "country": "CO",
    "subdivision": "35",
    "timezone": "America/Bogota"
  },
  "geometry": {
    "type": "Point",
    "coordinates": [
      -73.82151,
      8.66565
    ]
  }
}