{
  "type": "Feature",
  "properties": {
    "name": "Santa Cruz del Islote",
    "country": "CO",
    "subdivision": "35",
    "timezone": "America/Bogota"
  },
  "geometry": {
    "type": "Point",
    "coordinates": [
      -75.85899,
      9.78594
    ]
  }
}