{
  "type": "Feature",
  "properties": {
    "name": "Simití",
    "country": "CO",
    "subdivision": "35",
    "timezone": "America/Bogota"
  },
  "geometry": {
    "type": "Point",
    "coordinates": [
      -73.9436,
      7.9579
    ]
  }
}