{
  "type": "Feature",
  "properties": {
    "name": "Villanueva",
    "country": "CO",
    "subdivision": "35",
    "timezone": "America/Bogota"
  },
  "geometry": {
    "type": "Point",
    "coordinates": [
      -75.27306,
      10.44361
    ]
  }
}