{
  "type": "Feature",
  "properties": {
    "name": "Zambrano",
    "country": "CO",
    "subdivision": "35",
    "timezone": "America/Bogota"
  },
  "geometry": {
    "type": "Point",
    "coordinates": [
      -74.81572,
      9.7474
    ]
  }
}