{
  "type": "Feature",
  "properties": {
    "name": "Eshowe",
    "country": "ZA",
    "subdivision": "02",
    "timezone": "Africa/Johannesburg"
  },
  "geometry": {
    "type": "Point",
    "coordinates": [
      31.4699,
      -28.88649
    ]
  }
}