{
  "type": "Feature",
  "properties": {
    "name": "Howick",
    "country": "ZA",
    "subdivision": "02",
    "timezone": "Africa/Johannesburg"
  },
  "geometry": {
    "type": "Point",
    "coordinates": [
      30.23057,
      -29.47795
    ]
  }
}