{
  "type": "Feature",
  "properties": {
    "name": "Mondlo",
    "country": "ZA",
    "subdivision": "02",
    "timezone": "Africa/Johannesburg"
  },
  "geometry": {
    "type": "Point",
    "coordinates": [
      30.71769,
      -27.98299
    ]
  }
}