{
  "type": "Feature",
  "properties": {
    "name": "Port Shepstone",
    "country": "ZA",
    "subdivision": "02",
    "timezone": "Africa/Johannesburg"
  },
  "geometry": {
    "type": "Point",
    "coordinates": [
      30.45499,
      -30.74137
    ]
  }
}