{
  "type": "Feature",
  "properties": {
    "name": "Khon Buri",
    "country": "TH",
    "subdivision": "27",
    "timezone": "Asia/Bangkok"
  },
  "geometry": {
    "type": "Point",
    "coordinates": [
      102.24591,
      14.52541
    ]
  }
}