{
  "type": "Feature",
  "properties": {
    "name": "Nakhon Ratchasima",
    "country": "TH",
    "subdivision": "27",
    "timezone": "Asia/Bangkok"
  },
  "geometry": {
    "type": "Point",
    "coordinates": [
      102.10196,
      14.97066
    ]
  }
}