{
  "type": "Feature",
  "properties": {
    "name": "Phimai",
    "country": "TH",
    "subdivision": "27",
    "timezone": "Asia/Bangkok"
  },
  "geometry": {
    "type": "Point",
    "coordinates": [
      102.49473,
      15.22324
    ]
  }
}