{
  "type": "Feature",
  "properties": {
    "name": "Amayuca",
    "country": "MX",
    "subdivision": "17",
    "timezone": "America/Mexico_City"
  },
  "geometry": {
    "type": "Point",
    "coordinates": [
      -98.79812,
      18.72408
    ]
  }
}