{
  "type": "Feature",
  "properties": {
    "name": "Anenecuilco",
    "country": "MX",
    "subdivision": "17",
    "timezone": "America/Mexico_City"
  },
  "geometry": {
    "type": "Point",
    "coordinates": [
      -98.98907,
      18.77738
    ]
  }
}