{
  "type": "Feature",
  "properties": {
    "name": "Calle Real",
    "country": "MX",
    "subdivision": "17",
    "timezone": "America/Mexico_City"
  },
  "geometry": {
    "type": "Point",
    "coordinates": [
      -99.61332,
      19.48858
    ]
  }
}