{
  "type": "Feature",
  "properties": {
    "name": "El Salitre",
    "country": "MX",
    "subdivision": "17",
    "timezone": "America/Mexico_City"
  },
  "geometry": {
    "type": "Point",
    "coordinates": [
      -98.95806,
      18.67583
    ]
  }
}