{
  "type": "Feature",
  "properties": {
    "name": "Higuerón",
    "country": "MX",
    "subdivision": "17",
    "timezone": "America/Mexico_City"
  },
  "geometry": {
    "type": "Point",
    "coordinates": [
      -99.18056,
      18.5775
    ]
  }
}