{
  "type": "Feature",
  "properties": {
    "name": "Huecahuasco",
    "country": "MX",
    "subdivision": "17",
    "timezone": "America/Mexico_City"
  },
  "geometry": {
    "type": "Point",
    "coordinates": [
      -98.7825,
      18.93694
    ]
  }
}