{
  "type": "Feature",
  "properties": {
    "name": "Hueyapan",
    "country": "MX",
    "subdivision": "17",
    "timezone": "America/Mexico_City"
  },
  "geometry": {
    "type": "Point",
    "coordinates": [
      -98.682,
      18.8897
    ]
  }
}