{
  "type": "Feature",
  "properties": {
    "name": "Independencia",
    "country": "MX",
    "subdivision": "17",
    "timezone": "America/Mexico_City"
  },
  "geometry": {
    "type": "Point",
    "coordinates": [
      -99.12237,
      18.87716
    ]
  }
}