{
  "type": "Feature",
  "properties": {
    "name": "Itzamatitlán",
    "country": "MX",
    "subdivision": "17",
    "timezone": "America/Mexico_City"
  },
  "geometry": {
    "type": "Point",
    "coordinates": [
      -99.02236,
      18.90942
    ]
  }
}