{
  "type": "Feature",
  "properties": {
    "name": "Jantetelco",
    "country": "MX",
    "subdivision": "17",
    "timezone": "America/Mexico_City"
  },
  "geometry": {
    "type": "Point",
    "coordinates": [
      -98.7776,
      18.71828
    ]
  }
}