{
  "type": "Feature",
  "properties": {
    "name": "Jiutepec",
    "country": "MX",
    "subdivision": "17",
    "timezone": "America/Mexico_City"
  },
  "geometry": {
    "type": "Point",
    "coordinates": [
      -99.17778,
      18.88139
    ]
  }
}