{
  "type": "Feature",
  "properties": {
    "name": "Jonacatepec",
    "country": "MX",
    "subdivision": "17",
    "timezone": "America/Mexico_City"
  },
  "geometry": {
    "type": "Point",
    "coordinates": [
      -98.80336,
      18.68081
    ]
  }
}