{
  "type": "Feature",
  "properties": {
    "name": "La Huanica",
    "country": "MX",
    "subdivision": "17",
    "timezone": "America/Mexico_City"
  },
  "geometry": {
    "type": "Point",
    "coordinates": [
      -99.50079,
      19.45956
    ]
  }
}