{
  "type": "Feature",
  "properties": {
    "name": "Mazatepec",
    "country": "MX",
    "subdivision": "17",
    "timezone": "America/Mexico_City"
  },
  "geometry": {
    "type": "Point",
    "coordinates": [
      -99.36339,
      18.72795
    ]
  }
}