{
  "type": "Feature",
  "properties": {
    "name": "Pedro Amaro",
    "country": "MX",
    "subdivision": "17",
    "timezone": "America/Mexico_City"
  },
  "geometry": {
    "type": "Point",
    "coordinates": [
      -99.17306,
      18.59639
    ]
  }
}