{
  "type": "Feature",
  "properties": {
    "name": "Peña Flores (Palo Verde)",
    "country": "MX",
    "subdivision": "17",
    "timezone": "America/Mexico_City"
  },
  "geometry": {
    "type": "Point",
    "coordinates": [
      -98.96833,
      18.86722
    ]
  }
}