{
  "type": "Feature",
  "properties": {
    "name": "San Gabriel las Palmas",
    "country": "MX",
    "subdivision": "17",
    "timezone": "America/Mexico_City"
  },
  "geometry": {
    "type": "Point",
    "coordinates": [
      -99.34694,
      18.61417
    ]
  }
}