{
  "type": "Feature",
  "properties": {
    "name": "San Miguel de La Victoria",
    "country": "MX",
    "subdivision": "17",
    "timezone": "America/Mexico_City"
  },
  "geometry": {
    "type": "Point",
    "coordinates": [
      -99.59109,
      20.05611
    ]
  }
}