{
  "type": "Feature",
  "properties": {
    "name": "San Jerónimo",
    "country": "MX",
    "subdivision": "17",
    "timezone": "America/Mexico_City"
  },
  "geometry": {
    "type": "Point",
    "coordinates": [
      -99.5929,
      19.28279
    ]
  }
}