{
  "type": "Feature",
  "properties": {
    "name": "San Miguel Ameyalco",
    "country": "MX",
    "subdivision": "17",
    "timezone": "America/Mexico_City"
  },
  "geometry": {
    "type": "Point",
    "coordinates": [
      -99.4588,
      19.30681
    ]
  }
}