{
  "type": "Feature",
  "properties": {
    "name": "San Juan la Isla",
    "country": "MX",
    "subdivision": "17",
    "timezone": "America/Mexico_City"
  },
  "geometry": {
    "type": "Point",
    "coordinates": [
      -99.57076,
      19.13027
    ]
  }
}