{
  "type": "Feature",
  "properties": {
    "name": "Tianguistongo",
    "country": "MX",
    "subdivision": "17",
    "timezone": "America/Mexico_City"
  },
  "geometry": {
    "type": "Point",
    "coordinates": [
      -99.03845,
      20.00612
    ]
  }
}