{
  "type": "Feature",
  "properties": {
    "name": "Ticumán",
    "country": "MX",
    "subdivision": "17",
    "timezone": "America/Mexico_City"
  },
  "geometry": {
    "type": "Point",
    "coordinates": [
      -99.11991,
      18.75671
    ]
  }
}