{
  "type": "Feature",
  "properties": {
    "name": "Tlaltizapán",
    "country": "MX",
    "subdivision": "17",
    "timezone": "America/Mexico_City"
  },
  "geometry": {
    "type": "Point",
    "coordinates": [
      -99.11868,
      18.6863
    ]
  }
}