{
  "type": "Feature",
  "properties": {
    "name": "Tlalnepantla",
    "country": "MX",
    "subdivision": "17",
    "timezone": "America/Mexico_City"
  },
  "geometry": {
    "type": "Point",
    "coordinates": [
      -98.99613,
      19.00885
    ]
  }
}