{
  "type": "Feature",
  "properties": {
    "name": "Baranovichi",
    "country": "BY",
    "subdivision": "01",
    "timezone": "Europe/Minsk"
  },
  "geometry": {
    "type": "Point",
    "coordinates": [
      26.0139,
      53.1327
    ]
  }
}