{
  "type": "Feature",
  "properties": {
    "name": "Drahichyn",
    "country": "BY",
    "subdivision": "01",
    "timezone": "Europe/Minsk"
  },
  "geometry": {
    "type": "Point",
    "coordinates": [
      25.1597,
      52.1874
    ]
  }
}