{
  "type": "Feature",
  "properties": {
    "name": "Ivatsevichy",
    "country": "BY",
    "subdivision": "01",
    "timezone": "Europe/Minsk"
  },
  "geometry": {
    "type": "Point",
    "coordinates": [
      25.3401,
      52.709
    ]
  }
}