{
  "type": "Feature",
  "properties": {
    "name": "Kobryn",
    "country": "BY",
    "subdivision": "01",
    "timezone": "Europe/Minsk"
  },
  "geometry": {
    "type": "Point",
    "coordinates": [
      24.3564,
      52.2138
    ]
  }
}