{
  "type": "Feature",
  "properties": {
    "name": "Zhabinka",
    "country": "BY",
    "subdivision": "01",
    "timezone": "Europe/Minsk"
  },
  "geometry": {
    "type": "Point",
    "coordinates": [
      24.0115,
      52.1984
    ]
  }
}