{
  "type": "Feature",
  "properties": {
    "name": "Gümüşhane",
    "country": "TR",
    "subdivision": "69",
    "timezone": "Europe/Istanbul"
  },
  "geometry": {
    "type": "Point",
    "coordinates": [
      39.47176,
      40.46001
    ]
  }
}