{
  "type": "Feature",
  "properties": {
    "name": "Yağlıdere",
    "country": "TR",
    "subdivision": "69",
    "timezone": "Europe/Istanbul"
  },
  "geometry": {
    "type": "Point",
    "coordinates": [
      39.52762,
      40.54432
    ]
  }
}