{
  "type": "Feature",
  "properties": {
    "name": "Császár",
    "country": "HU",
    "subdivision": "12",
    "timezone": "Europe/Budapest"
  },
  "geometry": {
    "type": "Point",
    "coordinates": [
      18.14272,
      47.498
    ]
  }
}