{
  "type": "Feature",
  "properties": {
    "name": "Komárom",
    "country": "HU",
    "subdivision": "12",
    "timezone": "Europe/Budapest"
  },
  "geometry": {
    "type": "Point",
    "coordinates": [
      18.11913,
      47.74318
    ]
  }
}