{
  "type": "Feature",
  "properties": {
    "name": "Környe",
    "country": "HU",
    "subdivision": "12",
    "timezone": "Europe/Budapest"
  },
  "geometry": {
    "type": "Point",
    "coordinates": [
      18.32081,
      47.54668
    ]
  }
}