{
  "type": "Feature",
  "properties": {
    "name": "Pilismarót",
    "country": "HU",
    "subdivision": "12",
    "timezone": "Europe/Budapest"
  },
  "geometry": {
    "type": "Point",
    "coordinates": [
      18.87539,
      47.78464
    ]
  }
}