{
  "type": "Feature",
  "properties": {
    "name": "Fern Acres",
    "country": "US",
    "subdivision": "HI",
    "timezone": "Pacific/Honolulu"
  },
  "geometry": {
    "type": "Point",
    "coordinates": [
      -155.08028,
      19.51222
    ]
  }
}