{
  "type": "Feature",
  "properties": {
    "name": "Hanapēpē",
    "country": "US",
    "subdivision": "HI",
    "timezone": "Pacific/Honolulu"
  },
  "geometry": {
    "type": "Point",
    "coordinates": [
      -159.5944,
      21.90733
    ]
  }
}