{
  "type": "Feature",
  "properties": {
    "name": "Hawaiian Paradise Park",
    "country": "US",
    "subdivision": "HI",
    "timezone": "Pacific/Honolulu"
  },
  "geometry": {
    "type": "Point",
    "coordinates": [
      -154.97306,
      19.59333
    ]
  }
}