{
  "type": "Feature",
  "properties": {
    "name": "Hawaiian Beaches",
    "country": "US",
    "subdivision": "HI",
    "timezone": "Pacific/Honolulu"
  },
  "geometry": {
    "type": "Point",
    "coordinates": [
      -154.91583,
      19.54306
    ]
  }
}