{
  "type": "Feature",
  "properties": {
    "name": "Hilo",
    "country": "US",
    "subdivision": "HI",
    "timezone": "Pacific/Honolulu"
  },
  "geometry": {
    "type": "Point",
    "coordinates": [
      -155.09073,
      19.72991
    ]
  }
}