{
  "type": "Feature",
  "properties": {
    "name": "Honalo",
    "country": "US",
    "subdivision": "HI",
    "timezone": "Pacific/Honolulu"
  },
  "geometry": {
    "type": "Point",
    "coordinates": [
      -155.93194,
      19.54639
    ]
  }
}