{
  "type": "Feature",
  "properties": {
    "name": "Iroquois Point",
    "country": "US",
    "subdivision": "HI",
    "timezone": "Pacific/Honolulu"
  },
  "geometry": {
    "type": "Point",
    "coordinates": [
      -157.98301,
      21.32776
    ]
  }
}