{
  "type": "Feature",
  "properties": {
    "name": "Ka‘a‘awa",
    "country": "US",
    "subdivision": "HI",
    "timezone": "Pacific/Honolulu"
  },
  "geometry": {
    "type": "Point",
    "coordinates": [
      -157.85103,
      21.55445
    ]
  }
}