{
  "type": "Feature",
  "properties": {
    "name": "Kea‘au",
    "country": "US",
    "subdivision": "HI",
    "timezone": "Pacific/Honolulu"
  },
  "geometry": {
    "type": "Point",
    "coordinates": [
      -155.03744,
      19.62265
    ]
  }
}