{
  "type": "Feature",
  "properties": {
    "name": "Kēōkea",
    "country": "US",
    "subdivision": "HI",
    "timezone": "Pacific/Honolulu"
  },
  "geometry": {
    "type": "Point",
    "coordinates": [
      -156.35446,
      20.70711
    ]
  }
}