{
  "type": "Feature",
  "properties": {
    "name": "Lahaina",
    "country": "US",
    "subdivision": "HI",
    "timezone": "Pacific/Honolulu"
  },
  "geometry": {
    "type": "Point",
    "coordinates": [
      -156.67663,
      20.87429
    ]
  }
}