{
  "type": "Feature",
  "properties": {
    "name": "Mākaha Valley",
    "country": "US",
    "subdivision": "HI",
    "timezone": "Pacific/Honolulu"
  },
  "geometry": {
    "type": "Point",
    "coordinates": [
      -158.19918,
      21.47583
    ]
  }
}