{
  "type": "Feature",
  "properties": {
    "name": "Ocean Pointe",
    "country": "US",
    "subdivision": "HI",
    "timezone": "Pacific/Honolulu"
  },
  "geometry": {
    "type": "Point",
    "coordinates": [
      -158.03638,
      21.31066
    ]
  }
}