{
  "type": "Feature",
  "properties": {
    "name": "Pukalani",
    "country": "US",
    "subdivision": "HI",
    "timezone": "Pacific/Honolulu"
  },
  "geometry": {
    "type": "Point",
    "coordinates": [
      -156.33667,
      20.83667
    ]
  }
}