{
  "type": "Feature",
  "properties": {
    "name": "Punaluu",
    "country": "US",
    "subdivision": "HI",
    "timezone": "Pacific/Honolulu"
  },
  "geometry": {
    "type": "Point",
    "coordinates": [
      -157.87861,
      21.57389
    ]
  }
}