{
  "type": "Feature",
  "properties": {
    "name": "Village Park",
    "country": "US",
    "subdivision": "HI",
    "timezone": "Pacific/Honolulu"
  },
  "geometry": {
    "type": "Point",
    "coordinates": [
      -158.03028,
      21.39806
    ]
  }
}