{
  "type": "Feature",
  "properties": {
    "name": "‘Āhuimanu",
    "country": "US",
    "subdivision": "HI",
    "timezone": "Pacific/Honolulu"
  },
  "geometry": {
    "type": "Point",
    "coordinates": [
      -157.83778,
      21.44472
    ]
  }
}