{
  "type": "Feature",
  "properties": {
    "name": "Agapia",
    "country": "RO",
    "subdivision": "28",
    "timezone": "Europe/Bucharest"
  },
  "geometry": {
    "type": "Point",
    "coordinates": [
      26.28333,
      47.16667
    ]
  }
}