{
  "type": "Feature",
  "properties": {
    "name": "Bahna",
    "country": "RO",
    "subdivision": "28",
    "timezone": "Europe/Bucharest"
  },
  "geometry": {
    "type": "Point",
    "coordinates": [
      26.78333,
      46.78333
    ]
  }
}