{
  "type": "Feature",
  "properties": {
    "name": "Bicaz-Chei",
    "country": "RO",
    "subdivision": "28",
    "timezone": "Europe/Bucharest"
  },
  "geometry": {
    "type": "Point",
    "coordinates": [
      25.88333,
      46.81667
    ]
  }
}