{
  "type": "Feature",
  "properties": {
    "name": "Cracăul Negru",
    "country": "RO",
    "subdivision": "28",
    "timezone": "Europe/Bucharest"
  },
  "geometry": {
    "type": "Point",
    "coordinates": [
      26.24061,
      47.09363
    ]
  }
}