{
  "type": "Feature",
  "properties": {
    "name": "Dodeni",
    "country": "RO",
    "subdivision": "28",
    "timezone": "Europe/Bucharest"
  },
  "geometry": {
    "type": "Point",
    "coordinates": [
      26.09277,
      46.92587
    ]
  }
}