{
  "type": "Feature",
  "properties": {
    "name": "Luminiș",
    "country": "RO",
    "subdivision": "28",
    "timezone": "Europe/Bucharest"
  },
  "geometry": {
    "type": "Point",
    "coordinates": [
      26.45275,
      46.81332
    ]
  }
}