{
  "type": "Feature",
  "properties": {
    "name": "Negrești",
    "country": "RO",
    "subdivision": "28",
    "timezone": "Europe/Bucharest"
  },
  "geometry": {
    "type": "Point",
    "coordinates": [
      26.37958,
      47.02938
    ]
  }
}