{
  "type": "Feature",
  "properties": {
    "name": "Piatra Şoimului",
    "country": "RO",
    "subdivision": "28",
    "timezone": "Europe/Bucharest"
  },
  "geometry": {
    "type": "Point",
    "coordinates": [
      26.43333,
      46.83333
    ]
  }
}