{
  "type": "Feature",
  "properties": {
    "name": "Poiana Crăcăoani",
    "country": "RO",
    "subdivision": "28",
    "timezone": "Europe/Bucharest"
  },
  "geometry": {
    "type": "Point",
    "coordinates": [
      26.31667,
      47.06667
    ]
  }
}