{
  "type": "Feature",
  "properties": {
    "name": "Roman",
    "country": "RO",
    "subdivision": "28",
    "timezone": "Europe/Bucharest"
  },
  "geometry": {
    "type": "Point",
    "coordinates": [
      26.92646,
      46.92119
    ]
  }
}