{
  "type": "Feature",
  "properties": {
    "name": "Rotunda",
    "country": "RO",
    "subdivision": "28",
    "timezone": "Europe/Bucharest"
  },
  "geometry": {
    "type": "Point",
    "coordinates": [
      26.96266,
      47.0221
    ]
  }
}