{
  "type": "Feature",
  "properties": {
    "name": "Slobozia",
    "country": "RO",
    "subdivision": "28",
    "timezone": "Europe/Bucharest"
  },
  "geometry": {
    "type": "Point",
    "coordinates": [
      26.53344,
      46.84892
    ]
  }
}