{
  "type": "Feature",
  "properties": {
    "name": "Tarcău",
    "country": "RO",
    "subdivision": "28",
    "timezone": "Europe/Bucharest"
  },
  "geometry": {
    "type": "Point",
    "coordinates": [
      26.13333,
      46.86667
    ]
  }
}