{
  "type": "Feature",
  "properties": {
    "name": "Vădurele",
    "country": "RO",
    "subdivision": "28",
    "timezone": "Europe/Bucharest"
  },
  "geometry": {
    "type": "Point",
    "coordinates": [
      26.25074,
      46.93319
    ]
  }
}