{
  "type": "Feature",
  "properties": {
    "name": "Valea Seacă",
    "country": "RO",
    "subdivision": "28",
    "timezone": "Europe/Bucharest"
  },
  "geometry": {
    "type": "Point",
    "coordinates": [
      26.29956,
      47.13944
    ]
  }
}