{
  "type": "Feature",
  "properties": {
    "name": "BÄfq",
    "country": "IR",
    "subdivision": "40",
    "timezone": "Asia/Tehran"
  },
  "geometry": {
    "type": "Point",
    "coordinates": [
      55.40249,
      31.6035
    ]
  }
}