{
  "type": "Feature",
  "properties": {
    "name": "Taft",
    "country": "IR",
    "subdivision": "40",
    "timezone": "Asia/Tehran"
  },
  "geometry": {
    "type": "Point",
    "coordinates": [
      54.20278,
      31.74384
    ]
  }
}