{
  "type": "Feature",
  "properties": {
    "name": "Fort-de-France",
    "country": "MQ",
    "subdivision": "MQ",
    "timezone": "America/Martinique"
  },
  "geometry": {
    "type": "Point",
    "coordinates": [
      -61.07418,
      14.60365
    ]
  }
}