{
  "type": "Feature",
  "properties": {
    "name": "Le Lamentin",
    "country": "MQ",
    "subdivision": "MQ",
    "timezone": "America/Martinique"
  },
  "geometry": {
    "type": "Point",
    "coordinates": [
      -60.99964,
      14.61341
    ]
  }
}