{
  "type": "Feature",
  "properties": {
    "name": "Le Lorrain",
    "country": "MQ",
    "subdivision": "MQ",
    "timezone": "America/Martinique"
  },
  "geometry": {
    "type": "Point",
    "coordinates": [
      -61.05553,
      14.83257
    ]
  }
}