{
  "type": "Feature",
  "properties": {
    "name": "Le Vauclin",
    "country": "MQ",
    "subdivision": "MQ",
    "timezone": "America/Martinique"
  },
  "geometry": {
    "type": "Point",
    "coordinates": [
      -60.83831,
      14.5454
    ]
  }
}