{
  "type": "Feature",
  "properties": {
    "name": "Ascó",
    "country": "ES",
    "subdivision": "56",
    "timezone": "Europe/Madrid"
  },
  "geometry": {
    "type": "Point",
    "coordinates": [
      0.56667,
      41.18333
    ]
  }
}