{
  "type": "Feature",
  "properties": {
    "name": "Barberà del Vallès",
    "country": "ES",
    "subdivision": "56",
    "timezone": "Europe/Madrid"
  },
  "geometry": {
    "type": "Point",
    "coordinates": [
      2.12457,
      41.5159
    ]
  }
}