{
  "type": "Feature",
  "properties": {
    "name": "Bellcaire d'Urgell",
    "country": "ES",
    "subdivision": "56",
    "timezone": "Europe/Madrid"
  },
  "geometry": {
    "type": "Point",
    "coordinates": [
      0.91667,
      41.75
    ]
  }
}