{
  "type": "Feature",
  "properties": {
    "name": "Bescanó",
    "country": "ES",
    "subdivision": "56",
    "timezone": "Europe/Madrid"
  },
  "geometry": {
    "type": "Point",
    "coordinates": [
      2.73922,
      41.96603
    ]
  }
}