{
  "type": "Feature",
  "properties": {
    "name": "Blanes",
    "country": "ES",
    "subdivision": "56",
    "timezone": "Europe/Madrid"
  },
  "geometry": {
    "type": "Point",
    "coordinates": [
      2.79036,
      41.67419
    ]
  }
}