{
  "type": "Feature",
  "properties": {
    "name": "Calella",
    "country": "ES",
    "subdivision": "56",
    "timezone": "Europe/Madrid"
  },
  "geometry": {
    "type": "Point",
    "coordinates": [
      2.65423,
      41.61381
    ]
  }
}