{
  "type": "Feature",
  "properties": {
    "name": "Campdevànol",
    "country": "ES",
    "subdivision": "56",
    "timezone": "Europe/Madrid"
  },
  "geometry": {
    "type": "Point",
    "coordinates": [
      2.1686,
      42.22445
    ]
  }
}