{
  "type": "Feature",
  "properties": {
    "name": "Can Peguera",
    "country": "ES",
    "subdivision": "56",
    "timezone": "Europe/Madrid"
  },
  "geometry": {
    "type": "Point",
    "coordinates": [
      2.16646,
      41.43487
    ]
  }
}