{
  "type": "Feature",
  "properties": {
    "name": "Canet de Mar",
    "country": "ES",
    "subdivision": "56",
    "timezone": "Europe/Madrid"
  },
  "geometry": {
    "type": "Point",
    "coordinates": [
      2.58116,
      41.59054
    ]
  }
}