{
  "type": "Feature",
  "properties": {
    "name": "Canovelles",
    "country": "ES",
    "subdivision": "56",
    "timezone": "Europe/Madrid"
  },
  "geometry": {
    "type": "Point",
    "coordinates": [
      2.28333,
      41.61667
    ]
  }
}