{
  "type": "Feature",
  "properties": {
    "name": "Cervera",
    "country": "ES",
    "subdivision": "56",
    "timezone": "Europe/Madrid"
  },
  "geometry": {
    "type": "Point",
    "coordinates": [
      1.2721,
      41.67003
    ]
  }
}