{
  "type": "Feature",
  "properties": {
    "name": "Corbera de Llobregat",
    "country": "ES",
    "subdivision": "56",
    "timezone": "Europe/Madrid"
  },
  "geometry": {
    "type": "Point",
    "coordinates": [
      1.9197,
      41.41702
    ]
  }
}