{
  "type": "Feature",
  "properties": {
    "name": "Diagonal Mar",
    "country": "ES",
    "subdivision": "56",
    "timezone": "Europe/Madrid"
  },
  "geometry": {
    "type": "Point",
    "coordinates": [
      2.21615,
      41.40897
    ]
  }
}