{
  "type": "Feature",
  "properties": {
    "name": "el Coll",
    "country": "ES",
    "subdivision": "56",
    "timezone": "Europe/Madrid"
  },
  "geometry": {
    "type": "Point",
    "coordinates": [
      2.14723,
      41.41721
    ]
  }
}