{
  "type": "Feature",
  "properties": {
    "name": "el Guinardó",
    "country": "ES",
    "subdivision": "56",
    "timezone": "Europe/Madrid"
  },
  "geometry": {
    "type": "Point",
    "coordinates": [
      2.17364,
      41.41885
    ]
  }
}