{
  "type": "Feature",
  "properties": {
    "name": "el Putxet i el Farró",
    "country": "ES",
    "subdivision": "56",
    "timezone": "Europe/Madrid"
  },
  "geometry": {
    "type": "Point",
    "coordinates": [
      2.14392,
      41.40693
    ]
  }
}