{
  "type": "Feature",
  "properties": {
    "name": "el Parc i la Llacuna del Poblenou",
    "country": "ES",
    "subdivision": "56",
    "timezone": "Europe/Madrid"
  },
  "geometry": {
    "type": "Point",
    "coordinates": [
      2.1903,
      41.3986
    ]
  }
}