{
  "type": "Feature",
  "properties": {
    "name": "El Vendrell",
    "country": "ES",
    "subdivision": "56",
    "timezone": "Europe/Madrid"
  },
  "geometry": {
    "type": "Point",
    "coordinates": [
      1.53333,
      41.21667
    ]
  }
}