{
  "type": "Feature",
  "properties": {
    "name": "Flix",
    "country": "ES",
    "subdivision": "56",
    "timezone": "Europe/Madrid"
  },
  "geometry": {
    "type": "Point",
    "coordinates": [
      0.55008,
      41.23074
    ]
  }
}