{
  "type": "Feature",
  "properties": {
    "name": "Fort Pienc",
    "country": "ES",
    "subdivision": "56",
    "timezone": "Europe/Madrid"
  },
  "geometry": {
    "type": "Point",
    "coordinates": [
      2.17946,
      41.39458
    ]
  }
}