{
  "type": "Feature",
  "properties": {
    "name": "Gavà",
    "country": "ES",
    "subdivision": "56",
    "timezone": "Europe/Madrid"
  },
  "geometry": {
    "type": "Point",
    "coordinates": [
      2.00123,
      41.30605
    ]
  }
}