{
  "type": "Feature",
  "properties": {
    "name": "la Maternitat i Sant Ramon",
    "country": "ES",
    "subdivision": "56",
    "timezone": "Europe/Madrid"
  },
  "geometry": {
    "type": "Point",
    "coordinates": [
      2.11744,
      41.38125
    ]
  }
}