{
  "type": "Feature",
  "properties": {
    "name": "la Prosperitat",
    "country": "ES",
    "subdivision": "56",
    "timezone": "Europe/Madrid"
  },
  "geometry": {
    "type": "Point",
    "coordinates": [
      2.182,
      41.44269
    ]
  }
}