{
  "type": "Feature",
  "properties": {
    "name": "Lleida",
    "country": "ES",
    "subdivision": "56",
    "timezone": "Europe/Madrid"
  },
  "geometry": {
    "type": "Point",
    "coordinates": [
      0.62218,
      41.61674
    ]
  }
}