{
  "type": "Feature",
  "properties": {
    "name": "Masquefa",
    "country": "ES",
    "subdivision": "56",
    "timezone": "Europe/Madrid"
  },
  "geometry": {
    "type": "Point",
    "coordinates": [
      1.81136,
      41.50353
    ]
  }
}