{
  "type": "Feature",
  "properties": {
    "name": "Mediona",
    "country": "ES",
    "subdivision": "56",
    "timezone": "Europe/Madrid"
  },
  "geometry": {
    "type": "Point",
    "coordinates": [
      1.61222,
      41.47798
    ]
  }
}