{
  "type": "Feature",
  "properties": {
    "name": "Navarcles",
    "country": "ES",
    "subdivision": "56",
    "timezone": "Europe/Madrid"
  },
  "geometry": {
    "type": "Point",
    "coordinates": [
      1.90357,
      41.75171
    ]
  }
}