{
  "type": "Feature",
  "properties": {
    "name": "Nou Barris",
    "country": "ES",
    "subdivision": "56",
    "timezone": "Europe/Madrid"
  },
  "geometry": {
    "type": "Point",
    "coordinates": [
      2.17727,
      41.44163
    ]
  }
}