{
  "type": "Feature",
  "properties": {
    "name": "Poble Sec",
    "country": "ES",
    "subdivision": "56",
    "timezone": "Europe/Madrid"
  },
  "geometry": {
    "type": "Point",
    "coordinates": [
      2.16326,
      41.37452
    ]
  }
}