{
  "type": "Feature",
  "properties": {
    "name": "Polinyà",
    "country": "ES",
    "subdivision": "56",
    "timezone": "Europe/Madrid"
  },
  "geometry": {
    "type": "Point",
    "coordinates": [
      2.15,
      41.55
    ]
  }
}