{
  "type": "Feature",
  "properties": {
    "name": "Ripoll",
    "country": "ES",
    "subdivision": "56",
    "timezone": "Europe/Madrid"
  },
  "geometry": {
    "type": "Point",
    "coordinates": [
      2.19033,
      42.20064
    ]
  }
}