{
  "type": "Feature",
  "properties": {
    "name": "Rubí",
    "country": "ES",
    "subdivision": "56",
    "timezone": "Europe/Madrid"
  },
  "geometry": {
    "type": "Point",
    "coordinates": [
      2.03305,
      41.49226
    ]
  }
}