{
  "type": "Feature",
  "properties": {
    "name": "Santa Eulàlia de Ronçana",
    "country": "ES",
    "subdivision": "56",
    "timezone": "Europe/Madrid"
  },
  "geometry": {
    "type": "Point",
    "coordinates": [
      2.23333,
      41.65
    ]
  }
}