{
  "type": "Feature",
  "properties": {
    "name": "Sant Feliu de Llobregat",
    "country": "ES",
    "subdivision": "56",
    "timezone": "Europe/Madrid"
  },
  "geometry": {
    "type": "Point",
    "coordinates": [
      2.05,
      41.38333
    ]
  }
}