{
  "type": "Feature",
  "properties": {
    "name": "Sant Antoni",
    "country": "ES",
    "subdivision": "56",
    "timezone": "Europe/Madrid"
  },
  "geometry": {
    "type": "Point",
    "coordinates": [
      2.15937,
      41.37857
    ]
  }
}