{
  "type": "Feature",
  "properties": {
    "name": "Sant Quirze del Vallès",
    "country": "ES",
    "subdivision": "56",
    "timezone": "Europe/Madrid"
  },
  "geometry": {
    "type": "Point",
    "coordinates": [
      2.08333,
      41.53333
    ]
  }
}