{
  "type": "Feature",
  "properties": {
    "name": "Santa Coloma de Cervelló",
    "country": "ES",
    "subdivision": "56",
    "timezone": "Europe/Madrid"
  },
  "geometry": {
    "type": "Point",
    "coordinates": [
      2.01426,
      41.36736
    ]
  }
}