{
  "type": "Feature",
  "properties": {
    "name": "Sants - Badal",
    "country": "ES",
    "subdivision": "56",
    "timezone": "Europe/Madrid"
  },
  "geometry": {
    "type": "Point",
    "coordinates": [
      2.12775,
      41.37471
    ]
  }
}