{
  "type": "Feature",
  "properties": {
    "name": "Sentmenat",
    "country": "ES",
    "subdivision": "56",
    "timezone": "Europe/Madrid"
  },
  "geometry": {
    "type": "Point",
    "coordinates": [
      2.13532,
      41.60862
    ]
  }
}