{
  "type": "Feature",
  "properties": {
    "name": "Torelló",
    "country": "ES",
    "subdivision": "56",
    "timezone": "Europe/Madrid"
  },
  "geometry": {
    "type": "Point",
    "coordinates": [
      2.26679,
      42.04627
    ]
  }
}