{
  "type": "Feature",
  "properties": {
    "name": "Torroella de Montgrí",
    "country": "ES",
    "subdivision": "56",
    "timezone": "Europe/Madrid"
  },
  "geometry": {
    "type": "Point",
    "coordinates": [
      3.12703,
      42.04254
    ]
  }
}