{
  "type": "Feature",
  "properties": {
    "name": "Brandýs nad Labem-Stará Boleslav",
    "country": "CZ",
    "subdivision": "88",
    "timezone": "Europe/Prague"
  },
  "geometry": {
    "type": "Point",
    "coordinates": [
      14.66326,
      50.18709
    ]
  }
}