{
  "type": "Feature",
  "properties": {
    "name": "NaÄeradec",
    "country": "CZ",
    "subdivision": "88",
    "timezone": "Europe/Prague"
  },
  "geometry": {
    "type": "Point",
    "coordinates": [
      14.90633,
      49.61018
    ]
  }
}