{
  "type": "Feature",
  "properties": {
    "name": "Neveklov",
    "country": "CZ",
    "subdivision": "88",
    "timezone": "Europe/Prague"
  },
  "geometry": {
    "type": "Point",
    "coordinates": [
      14.53291,
      49.75373
    ]
  }
}