{
  "type": "Feature",
  "properties": {
    "name": "Obecnice",
    "country": "CZ",
    "subdivision": "88",
    "timezone": "Europe/Prague"
  },
  "geometry": {
    "type": "Point",
    "coordinates": [
      13.94731,
      49.71615
    ]
  }
}