{
  "type": "Feature",
  "properties": {
    "name": "Rakovník",
    "country": "CZ",
    "subdivision": "88",
    "timezone": "Europe/Prague"
  },
  "geometry": {
    "type": "Point",
    "coordinates": [
      13.7334,
      50.1037
    ]
  }
}