{
  "type": "Feature",
  "properties": {
    "name": "Roztoky",
    "country": "CZ",
    "subdivision": "88",
    "timezone": "Europe/Prague"
  },
  "geometry": {
    "type": "Point",
    "coordinates": [
      14.3976,
      50.15841
    ]
  }
}