{
  "type": "Feature",
  "properties": {
    "name": "Slaný",
    "country": "CZ",
    "subdivision": "88",
    "timezone": "Europe/Prague"
  },
  "geometry": {
    "type": "Point",
    "coordinates": [
      14.08693,
      50.23046
    ]
  }
}