{
  "type": "Feature",
  "properties": {
    "name": "Týnec nad Labem",
    "country": "CZ",
    "subdivision": "88",
    "timezone": "Europe/Prague"
  },
  "geometry": {
    "type": "Point",
    "coordinates": [
      15.35836,
      50.04202
    ]
  }
}