{
  "type": "Feature",
  "properties": {
    "name": "Velim",
    "country": "CZ",
    "subdivision": "88",
    "timezone": "Europe/Prague"
  },
  "geometry": {
    "type": "Point",
    "coordinates": [
      15.10711,
      50.05965
    ]
  }
}