{
  "type": "Feature",
  "properties": {
    "name": "Všetaty",
    "country": "CZ",
    "subdivision": "88",
    "timezone": "Europe/Prague"
  },
  "geometry": {
    "type": "Point",
    "coordinates": [
      14.59297,
      50.28187
    ]
  }
}