{
  "type": "Feature",
  "properties": {
    "name": "ZajeÄov",
    "country": "CZ",
    "subdivision": "88",
    "timezone": "Europe/Prague"
  },
  "geometry": {
    "type": "Point",
    "coordinates": [
      13.84072,
      49.77435
    ]
  }
}