{
  "type": "Feature",
  "properties": {
    "name": "Luang Prabang",
    "country": "LA",
    "subdivision": "17",
    "timezone": "Asia/Vientiane"
  },
  "geometry": {
    "type": "Point",
    "coordinates": [
      102.13503,
      19.88601
    ]
  }
}