{
  "type": "Feature",
  "properties": {
    "name": "Wichian Buri",
    "country": "TH",
    "subdivision": "14",
    "timezone": "Asia/Bangkok"
  },
  "geometry": {
    "type": "Point",
    "coordinates": [
      101.10603,
      15.65778
    ]
  }
}