{
  "type": "Feature",
  "properties": {
    "name": "Aische-en-Refail",
    "country": "BE",
    "subdivision": "WAL",
    "timezone": "Europe/Brussels"
  },
  "geometry": {
    "type": "Point",
    "coordinates": [
      4.83775,
      50.60009
    ]
  }
}