{
  "type": "Feature",
  "properties": {
    "name": "Amblève",
    "country": "BE",
    "subdivision": "WAL",
    "timezone": "Europe/Brussels"
  },
  "geometry": {
    "type": "Point",
    "coordinates": [
      6.17002,
      50.35357
    ]
  }
}