{
  "type": "Feature",
  "properties": {
    "name": "Arville",
    "country": "BE",
    "subdivision": "WAL",
    "timezone": "Europe/Brussels"
  },
  "geometry": {
    "type": "Point",
    "coordinates": [
      5.31665,
      50.03203
    ]
  }
}