{
  "type": "Feature",
  "properties": {
    "name": "Autelbas",
    "country": "BE",
    "subdivision": "WAL",
    "timezone": "Europe/Brussels"
  },
  "geometry": {
    "type": "Point",
    "coordinates": [
      5.86799,
      49.64813
    ]
  }
}