{
  "type": "Feature",
  "properties": {
    "name": "Baileux",
    "country": "BE",
    "subdivision": "WAL",
    "timezone": "Europe/Brussels"
  },
  "geometry": {
    "type": "Point",
    "coordinates": [
      4.37533,
      50.02877
    ]
  }
}