{
  "type": "Feature",
  "properties": {
    "name": "Bellaire",
    "country": "BE",
    "subdivision": "WAL",
    "timezone": "Europe/Brussels"
  },
  "geometry": {
    "type": "Point",
    "coordinates": [
      5.66585,
      50.64453
    ]
  }
}