{
  "type": "Feature",
  "properties": {
    "name": "Beyne-Heusay",
    "country": "BE",
    "subdivision": "WAL",
    "timezone": "Europe/Brussels"
  },
  "geometry": {
    "type": "Point",
    "coordinates": [
      5.66508,
      50.62251
    ]
  }
}