{
  "type": "Feature",
  "properties": {
    "name": "Bierghes",
    "country": "BE",
    "subdivision": "WAL",
    "timezone": "Europe/Brussels"
  },
  "geometry": {
    "type": "Point",
    "coordinates": [
      4.1192,
      50.69578
    ]
  }
}