{
  "type": "Feature",
  "properties": {
    "name": "Bierset",
    "country": "BE",
    "subdivision": "WAL",
    "timezone": "Europe/Brussels"
  },
  "geometry": {
    "type": "Point",
    "coordinates": [
      5.45102,
      50.65496
    ]
  }
}