{
  "type": "Feature",
  "properties": {
    "name": "Bièvre",
    "country": "BE",
    "subdivision": "WAL",
    "timezone": "Europe/Brussels"
  },
  "geometry": {
    "type": "Point",
    "coordinates": [
      5.01591,
      49.94085
    ]
  }
}