{
  "type": "Feature",
  "properties": {
    "name": "Bois-de-Lessines",
    "country": "BE",
    "subdivision": "WAL",
    "timezone": "Europe/Brussels"
  },
  "geometry": {
    "type": "Point",
    "coordinates": [
      3.89613,
      50.69662
    ]
  }
}