{
  "type": "Feature",
  "properties": {
    "name": "Bois-d'Haine",
    "country": "BE",
    "subdivision": "WAL",
    "timezone": "Europe/Brussels"
  },
  "geometry": {
    "type": "Point",
    "coordinates": [
      4.21555,
      50.5018
    ]
  }
}