{
  "type": "Feature",
  "properties": {
    "name": "Bouffioulx",
    "country": "BE",
    "subdivision": "WAL",
    "timezone": "Europe/Brussels"
  },
  "geometry": {
    "type": "Point",
    "coordinates": [
      4.5155,
      50.39116
    ]
  }
}