{
  "type": "Feature",
  "properties": {
    "name": "Bouillon",
    "country": "BE",
    "subdivision": "WAL",
    "timezone": "Europe/Brussels"
  },
  "geometry": {
    "type": "Point",
    "coordinates": [
      5.06703,
      49.79324
    ]
  }
}