{
  "type": "Feature",
  "properties": {
    "name": "Bovigny",
    "country": "BE",
    "subdivision": "WAL",
    "timezone": "Europe/Brussels"
  },
  "geometry": {
    "type": "Point",
    "coordinates": [
      5.91694,
      50.22417
    ]
  }
}