{
  "type": "Feature",
  "properties": {
    "name": "Carnières",
    "country": "BE",
    "subdivision": "WAL",
    "timezone": "Europe/Brussels"
  },
  "geometry": {
    "type": "Point",
    "coordinates": [
      4.25509,
      50.44428
    ]
  }
}