{
  "type": "Feature",
  "properties": {
    "name": "Casteau",
    "country": "BE",
    "subdivision": "WAL",
    "timezone": "Europe/Brussels"
  },
  "geometry": {
    "type": "Point",
    "coordinates": [
      4.01121,
      50.51233
    ]
  }
}