{
  "type": "Feature",
  "properties": {
    "name": "Chimay",
    "country": "BE",
    "subdivision": "WAL",
    "timezone": "Europe/Brussels"
  },
  "geometry": {
    "type": "Point",
    "coordinates": [
      4.31712,
      50.04856
    ]
  }
}