{
  "type": "Feature",
  "properties": {
    "name": "Chiny",
    "country": "BE",
    "subdivision": "WAL",
    "timezone": "Europe/Brussels"
  },
  "geometry": {
    "type": "Point",
    "coordinates": [
      5.34104,
      49.73833
    ]
  }
}