{
  "type": "Feature",
  "properties": {
    "name": "Daverdisse",
    "country": "BE",
    "subdivision": "WAL",
    "timezone": "Europe/Brussels"
  },
  "geometry": {
    "type": "Point",
    "coordinates": [
      5.11811,
      50.02161
    ]
  }
}