{
  "type": "Feature",
  "properties": {
    "name": "Dave",
    "country": "BE",
    "subdivision": "WAL",
    "timezone": "Europe/Brussels"
  },
  "geometry": {
    "type": "Point",
    "coordinates": [
      4.88789,
      50.4147
    ]
  }
}