{
  "type": "Feature",
  "properties": {
    "name": "Dergneau",
    "country": "BE",
    "subdivision": "WAL",
    "timezone": "Europe/Brussels"
  },
  "geometry": {
    "type": "Point",
    "coordinates": [
      3.58004,
      50.71399
    ]
  }
}