{
  "type": "Feature",
  "properties": {
    "name": "Durnal",
    "country": "BE",
    "subdivision": "WAL",
    "timezone": "Europe/Brussels"
  },
  "geometry": {
    "type": "Point",
    "coordinates": [
      4.98616,
      50.33653
    ]
  }
}