{
  "type": "Feature",
  "properties": {
    "name": "Embourg",
    "country": "BE",
    "subdivision": "WAL",
    "timezone": "Europe/Brussels"
  },
  "geometry": {
    "type": "Point",
    "coordinates": [
      5.6068,
      50.59043
    ]
  }
}