{
  "type": "Feature",
  "properties": {
    "name": "Ensival",
    "country": "BE",
    "subdivision": "WAL",
    "timezone": "Europe/Brussels"
  },
  "geometry": {
    "type": "Point",
    "coordinates": [
      5.84927,
      50.58053
    ]
  }
}