{
  "type": "Feature",
  "properties": {
    "name": "Épinois",
    "country": "BE",
    "subdivision": "WAL",
    "timezone": "Europe/Brussels"
  },
  "geometry": {
    "type": "Point",
    "coordinates": [
      4.20666,
      50.406
    ]
  }
}