{
  "type": "Feature",
  "properties": {
    "name": "Éthe",
    "country": "BE",
    "subdivision": "WAL",
    "timezone": "Europe/Brussels"
  },
  "geometry": {
    "type": "Point",
    "coordinates": [
      5.58208,
      49.58
    ]
  }
}