{
  "type": "Feature",
  "properties": {
    "name": "Fosses-la-Ville",
    "country": "BE",
    "subdivision": "WAL",
    "timezone": "Europe/Brussels"
  },
  "geometry": {
    "type": "Point",
    "coordinates": [
      4.69623,
      50.39517
    ]
  }
}