{
  "type": "Feature",
  "properties": {
    "name": "Gelbressée",
    "country": "BE",
    "subdivision": "WAL",
    "timezone": "Europe/Brussels"
  },
  "geometry": {
    "type": "Point",
    "coordinates": [
      4.95552,
      50.50611
    ]
  }
}