{
  "type": "Feature",
  "properties": {
    "name": "Gembloux",
    "country": "BE",
    "subdivision": "WAL",
    "timezone": "Europe/Brussels"
  },
  "geometry": {
    "type": "Point",
    "coordinates": [
      4.69889,
      50.56149
    ]
  }
}