{
  "type": "Feature",
  "properties": {
    "name": "Genappe",
    "country": "BE",
    "subdivision": "WAL",
    "timezone": "Europe/Brussels"
  },
  "geometry": {
    "type": "Point",
    "coordinates": [
      4.45152,
      50.61173
    ]
  }
}