{
  "type": "Feature",
  "properties": {
    "name": "Givry",
    "country": "BE",
    "subdivision": "WAL",
    "timezone": "Europe/Brussels"
  },
  "geometry": {
    "type": "Point",
    "coordinates": [
      4.02932,
      50.37826
    ]
  }
}