{
  "type": "Feature",
  "properties": {
    "name": "Gosselies",
    "country": "BE",
    "subdivision": "WAL",
    "timezone": "Europe/Brussels"
  },
  "geometry": {
    "type": "Point",
    "coordinates": [
      4.43324,
      50.46936
    ]
  }
}