{
  "type": "Feature",
  "properties": {
    "name": "Gozée",
    "country": "BE",
    "subdivision": "WAL",
    "timezone": "Europe/Brussels"
  },
  "geometry": {
    "type": "Point",
    "coordinates": [
      4.35273,
      50.33461
    ]
  }
}