{
  "type": "Feature",
  "properties": {
    "name": "Grandhan",
    "country": "BE",
    "subdivision": "WAL",
    "timezone": "Europe/Brussels"
  },
  "geometry": {
    "type": "Point",
    "coordinates": [
      5.40996,
      50.32944
    ]
  }
}