{
  "type": "Feature",
  "properties": {
    "name": "Grez-Doiceau",
    "country": "BE",
    "subdivision": "WAL",
    "timezone": "Europe/Brussels"
  },
  "geometry": {
    "type": "Point",
    "coordinates": [
      4.69829,
      50.73901
    ]
  }
}