{
  "type": "Feature",
  "properties": {
    "name": "Haltinne",
    "country": "BE",
    "subdivision": "WAL",
    "timezone": "Europe/Brussels"
  },
  "geometry": {
    "type": "Point",
    "coordinates": [
      5.07731,
      50.45119
    ]
  }
}