{
  "type": "Feature",
  "properties": {
    "name": "Havré",
    "country": "BE",
    "subdivision": "WAL",
    "timezone": "Europe/Brussels"
  },
  "geometry": {
    "type": "Point",
    "coordinates": [
      4.04675,
      50.46401
    ]
  }
}