{
  "type": "Feature",
  "properties": {
    "name": "Henri-Chapelle",
    "country": "BE",
    "subdivision": "WAL",
    "timezone": "Europe/Brussels"
  },
  "geometry": {
    "type": "Point",
    "coordinates": [
      5.93009,
      50.67688
    ]
  }
}