{
  "type": "Feature",
  "properties": {
    "name": "Herseaux",
    "country": "BE",
    "subdivision": "WAL",
    "timezone": "Europe/Brussels"
  },
  "geometry": {
    "type": "Point",
    "coordinates": [
      3.21667,
      50.71667
    ]
  }
}