{
  "type": "Feature",
  "properties": {
    "name": "Houdeng-Goegnies",
    "country": "BE",
    "subdivision": "WAL",
    "timezone": "Europe/Brussels"
  },
  "geometry": {
    "type": "Point",
    "coordinates": [
      4.17513,
      50.49032
    ]
  }
}