{
  "type": "Feature",
  "properties": {
    "name": "Houffalize",
    "country": "BE",
    "subdivision": "WAL",
    "timezone": "Europe/Brussels"
  },
  "geometry": {
    "type": "Point",
    "coordinates": [
      5.78962,
      50.13235
    ]
  }
}