{
  "type": "Feature",
  "properties": {
    "name": "Izel",
    "country": "BE",
    "subdivision": "WAL",
    "timezone": "Europe/Brussels"
  },
  "geometry": {
    "type": "Point",
    "coordinates": [
      5.37382,
      49.69371
    ]
  }
}