{
  "type": "Feature",
  "properties": {
    "name": "Jamoigne",
    "country": "BE",
    "subdivision": "WAL",
    "timezone": "Europe/Brussels"
  },
  "geometry": {
    "type": "Point",
    "coordinates": [
      5.40906,
      49.69328
    ]
  }
}