{
  "type": "Feature",
  "properties": {
    "name": "Jemappes",
    "country": "BE",
    "subdivision": "WAL",
    "timezone": "Europe/Brussels"
  },
  "geometry": {
    "type": "Point",
    "coordinates": [
      3.89096,
      50.44914
    ]
  }
}