{
  "type": "Feature",
  "properties": {
    "name": "Kain",
    "country": "BE",
    "subdivision": "WAL",
    "timezone": "Europe/Brussels"
  },
  "geometry": {
    "type": "Point",
    "coordinates": [
      3.39688,
      50.63869
    ]
  }
}