{
  "type": "Feature",
  "properties": {
    "name": "La Hulpe",
    "country": "BE",
    "subdivision": "WAL",
    "timezone": "Europe/Brussels"
  },
  "geometry": {
    "type": "Point",
    "coordinates": [
      4.48577,
      50.73091
    ]
  }
}