{
  "type": "Feature",
  "properties": {
    "name": "Léglise",
    "country": "BE",
    "subdivision": "WAL",
    "timezone": "Europe/Brussels"
  },
  "geometry": {
    "type": "Point",
    "coordinates": [
      5.53652,
      49.79985
    ]
  }
}