{
  "type": "Feature",
  "properties": {
    "name": "Limelette",
    "country": "BE",
    "subdivision": "WAL",
    "timezone": "Europe/Brussels"
  },
  "geometry": {
    "type": "Point",
    "coordinates": [
      4.57186,
      50.68428
    ]
  }
}