{
  "type": "Feature",
  "properties": {
    "name": "Loyers",
    "country": "BE",
    "subdivision": "WAL",
    "timezone": "Europe/Brussels"
  },
  "geometry": {
    "type": "Point",
    "coordinates": [
      4.95136,
      50.46324
    ]
  }
}