{
  "type": "Feature",
  "properties": {
    "name": "Malmédy",
    "country": "BE",
    "subdivision": "WAL",
    "timezone": "Europe/Brussels"
  },
  "geometry": {
    "type": "Point",
    "coordinates": [
      6.02794,
      50.42686
    ]
  }
}