{
  "type": "Feature",
  "properties": {
    "name": "Malonne",
    "country": "BE",
    "subdivision": "WAL",
    "timezone": "Europe/Brussels"
  },
  "geometry": {
    "type": "Point",
    "coordinates": [
      4.79562,
      50.43969
    ]
  }
}