{
  "type": "Feature",
  "properties": {
    "name": "Marbais",
    "country": "BE",
    "subdivision": "WAL",
    "timezone": "Europe/Brussels"
  },
  "geometry": {
    "type": "Point",
    "coordinates": [
      4.53499,
      50.54652
    ]
  }
}