{
  "type": "Feature",
  "properties": {
    "name": "Membach",
    "country": "BE",
    "subdivision": "WAL",
    "timezone": "Europe/Brussels"
  },
  "geometry": {
    "type": "Point",
    "coordinates": [
      5.99506,
      50.61908
    ]
  }
}