{
  "type": "Feature",
  "properties": {
    "name": "Mettet",
    "country": "BE",
    "subdivision": "WAL",
    "timezone": "Europe/Brussels"
  },
  "geometry": {
    "type": "Point",
    "coordinates": [
      4.66232,
      50.32119
    ]
  }
}