{
  "type": "Feature",
  "properties": {
    "name": "Meyerode",
    "country": "BE",
    "subdivision": "WAL",
    "timezone": "Europe/Brussels"
  },
  "geometry": {
    "type": "Point",
    "coordinates": [
      6.18776,
      50.32818
    ]
  }
}