{
  "type": "Feature",
  "properties": {
    "name": "Morlanwelz-Mariemont",
    "country": "BE",
    "subdivision": "WAL",
    "timezone": "Europe/Brussels"
  },
  "geometry": {
    "type": "Point",
    "coordinates": [
      4.24519,
      50.45502
    ]
  }
}