{
  "type": "Feature",
  "properties": {
    "name": "Mussy-la-Ville",
    "country": "BE",
    "subdivision": "WAL",
    "timezone": "Europe/Brussels"
  },
  "geometry": {
    "type": "Point",
    "coordinates": [
      5.66191,
      49.57009
    ]
  }
}