{
  "type": "Feature",
  "properties": {
    "name": "Neu-Moresnet",
    "country": "BE",
    "subdivision": "WAL",
    "timezone": "Europe/Brussels"
  },
  "geometry": {
    "type": "Point",
    "coordinates": [
      6.02119,
      50.71575
    ]
  }
}