{
  "type": "Feature",
  "properties": {
    "name": "Neufchâteau",
    "country": "BE",
    "subdivision": "WAL",
    "timezone": "Europe/Brussels"
  },
  "geometry": {
    "type": "Point",
    "coordinates": [
      5.43535,
      49.84074
    ]
  }
}