{
  "type": "Feature",
  "properties": {
    "name": "Noiseux",
    "country": "BE",
    "subdivision": "WAL",
    "timezone": "Europe/Brussels"
  },
  "geometry": {
    "type": "Point",
    "coordinates": [
      5.37506,
      50.29976
    ]
  }
}