{
  "type": "Feature",
  "properties": {
    "name": "Odeur",
    "country": "BE",
    "subdivision": "WAL",
    "timezone": "Europe/Brussels"
  },
  "geometry": {
    "type": "Point",
    "coordinates": [
      5.41578,
      50.70642
    ]
  }
}