{
  "type": "Feature",
  "properties": {
    "name": "Ohey",
    "country": "BE",
    "subdivision": "WAL",
    "timezone": "Europe/Brussels"
  },
  "geometry": {
    "type": "Point",
    "coordinates": [
      5.12375,
      50.4357
    ]
  }
}