{
  "type": "Feature",
  "properties": {
    "name": "Ophain-Bois-Seigneur-Isaac",
    "country": "BE",
    "subdivision": "WAL",
    "timezone": "Europe/Brussels"
  },
  "geometry": {
    "type": "Point",
    "coordinates": [
      4.34865,
      50.66646
    ]
  }
}