{
  "type": "Feature",
  "properties": {
    "name": "Pepinster",
    "country": "BE",
    "subdivision": "WAL",
    "timezone": "Europe/Brussels"
  },
  "geometry": {
    "type": "Point",
    "coordinates": [
      5.80386,
      50.56568
    ]
  }
}