{
  "type": "Feature",
  "properties": {
    "name": "Péronnes",
    "country": "BE",
    "subdivision": "WAL",
    "timezone": "Europe/Brussels"
  },
  "geometry": {
    "type": "Point",
    "coordinates": [
      3.45374,
      50.55156
    ]
  }
}