{
  "type": "Feature",
  "properties": {
    "name": "Perwez",
    "country": "BE",
    "subdivision": "WAL",
    "timezone": "Europe/Brussels"
  },
  "geometry": {
    "type": "Point",
    "coordinates": [
      4.81354,
      50.62426
    ]
  }
}