{
  "type": "Feature",
  "properties": {
    "name": "Pipaix",
    "country": "BE",
    "subdivision": "WAL",
    "timezone": "Europe/Brussels"
  },
  "geometry": {
    "type": "Point",
    "coordinates": [
      3.57956,
      50.58297
    ]
  }
}