{
  "type": "Feature",
  "properties": {
    "name": "Pottes",
    "country": "BE",
    "subdivision": "WAL",
    "timezone": "Europe/Brussels"
  },
  "geometry": {
    "type": "Point",
    "coordinates": [
      3.40703,
      50.73294
    ]
  }
}