{
  "type": "Feature",
  "properties": {
    "name": "Presles",
    "country": "BE",
    "subdivision": "WAL",
    "timezone": "Europe/Brussels"
  },
  "geometry": {
    "type": "Point",
    "coordinates": [
      4.57838,
      50.38417
    ]
  }
}