{
  "type": "Feature",
  "properties": {
    "name": "Quevaucamps",
    "country": "BE",
    "subdivision": "WAL",
    "timezone": "Europe/Brussels"
  },
  "geometry": {
    "type": "Point",
    "coordinates": [
      3.68128,
      50.51888
    ]
  }
}