{
  "type": "Feature",
  "properties": {
    "name": "Raeren",
    "country": "BE",
    "subdivision": "WAL",
    "timezone": "Europe/Brussels"
  },
  "geometry": {
    "type": "Point",
    "coordinates": [
      6.11535,
      50.6672
    ]
  }
}