{
  "type": "Feature",
  "properties": {
    "name": "Rance",
    "country": "BE",
    "subdivision": "WAL",
    "timezone": "Europe/Brussels"
  },
  "geometry": {
    "type": "Point",
    "coordinates": [
      4.27917,
      50.14248
    ]
  }
}