{
  "type": "Feature",
  "properties": {
    "name": "Rendeux",
    "country": "BE",
    "subdivision": "WAL",
    "timezone": "Europe/Brussels"
  },
  "geometry": {
    "type": "Point",
    "coordinates": [
      5.50414,
      50.23423
    ]
  }
}