{
  "type": "Feature",
  "properties": {
    "name": "Rhisnes",
    "country": "BE",
    "subdivision": "WAL",
    "timezone": "Europe/Brussels"
  },
  "geometry": {
    "type": "Point",
    "coordinates": [
      4.80592,
      50.50682
    ]
  }
}