{
  "type": "Feature",
  "properties": {
    "name": "Rongy",
    "country": "BE",
    "subdivision": "WAL",
    "timezone": "Europe/Brussels"
  },
  "geometry": {
    "type": "Point",
    "coordinates": [
      3.3895,
      50.50724
    ]
  }
}