{
  "type": "Feature",
  "properties": {
    "name": "Rotheux-Rimière",
    "country": "BE",
    "subdivision": "WAL",
    "timezone": "Europe/Brussels"
  },
  "geometry": {
    "type": "Point",
    "coordinates": [
      5.48063,
      50.53356
    ]
  }
}