{
  "type": "Feature",
  "properties": {
    "name": "Roux",
    "country": "BE",
    "subdivision": "WAL",
    "timezone": "Europe/Brussels"
  },
  "geometry": {
    "type": "Point",
    "coordinates": [
      4.3917,
      50.44111
    ]
  }
}