{
  "type": "Feature",
  "properties": {
    "name": "Rulles",
    "country": "BE",
    "subdivision": "WAL",
    "timezone": "Europe/Brussels"
  },
  "geometry": {
    "type": "Point",
    "coordinates": [
      5.55959,
      49.71805
    ]
  }
}