{
  "type": "Feature",
  "properties": {
    "name": "Saint-Pierre",
    "country": "BE",
    "subdivision": "WAL",
    "timezone": "Europe/Brussels"
  },
  "geometry": {
    "type": "Point",
    "coordinates": [
      5.3875,
      49.90376
    ]
  }
}