{
  "type": "Feature",
  "properties": {
    "name": "Saint-Mard",
    "country": "BE",
    "subdivision": "WAL",
    "timezone": "Europe/Brussels"
  },
  "geometry": {
    "type": "Point",
    "coordinates": [
      5.53427,
      49.55403
    ]
  }
}