{
  "type": "Feature",
  "properties": {
    "name": "Sauvenière",
    "country": "BE",
    "subdivision": "WAL",
    "timezone": "Europe/Brussels"
  },
  "geometry": {
    "type": "Point",
    "coordinates": [
      4.72466,
      50.58157
    ]
  }
}