{
  "type": "Feature",
  "properties": {
    "name": "Schaltin",
    "country": "BE",
    "subdivision": "WAL",
    "timezone": "Europe/Brussels"
  },
  "geometry": {
    "type": "Point",
    "coordinates": [
      5.12535,
      50.35952
    ]
  }
}