{
  "type": "Feature",
  "properties": {
    "name": "Solre-sur-Sambre",
    "country": "BE",
    "subdivision": "WAL",
    "timezone": "Europe/Brussels"
  },
  "geometry": {
    "type": "Point",
    "coordinates": [
      4.15429,
      50.30809
    ]
  }
}