{
  "type": "Feature",
  "properties": {
    "name": "Souvret",
    "country": "BE",
    "subdivision": "WAL",
    "timezone": "Europe/Brussels"
  },
  "geometry": {
    "type": "Point",
    "coordinates": [
      4.34569,
      50.4486
    ]
  }
}