{
  "type": "Feature",
  "properties": {
    "name": "Soye",
    "country": "BE",
    "subdivision": "WAL",
    "timezone": "Europe/Brussels"
  },
  "geometry": {
    "type": "Point",
    "coordinates": [
      4.7303,
      50.44958
    ]
  }
}