{
  "type": "Feature",
  "properties": {
    "name": "Sprimont",
    "country": "BE",
    "subdivision": "WAL",
    "timezone": "Europe/Brussels"
  },
  "geometry": {
    "type": "Point",
    "coordinates": [
      5.6595,
      50.50922
    ]
  }
}