{
  "type": "Feature",
  "properties": {
    "name": "Stavelot",
    "country": "BE",
    "subdivision": "WAL",
    "timezone": "Europe/Brussels"
  },
  "geometry": {
    "type": "Point",
    "coordinates": [
      5.93124,
      50.395
    ]
  }
}