{
  "type": "Feature",
  "properties": {
    "name": "Strépy-Bracquegnies",
    "country": "BE",
    "subdivision": "WAL",
    "timezone": "Europe/Brussels"
  },
  "geometry": {
    "type": "Point",
    "coordinates": [
      4.12022,
      50.4728
    ]
  }
}