{
  "type": "Feature",
  "properties": {
    "name": "Suarlée",
    "country": "BE",
    "subdivision": "WAL",
    "timezone": "Europe/Brussels"
  },
  "geometry": {
    "type": "Point",
    "coordinates": [
      4.7792,
      50.48137
    ]
  }
}