{
  "type": "Feature",
  "properties": {
    "name": "Tamines",
    "country": "BE",
    "subdivision": "WAL",
    "timezone": "Europe/Brussels"
  },
  "geometry": {
    "type": "Point",
    "coordinates": [
      4.60713,
      50.43378
    ]
  }
}