{
  "type": "Feature",
  "properties": {
    "name": "Tavier",
    "country": "BE",
    "subdivision": "WAL",
    "timezone": "Europe/Brussels"
  },
  "geometry": {
    "type": "Point",
    "coordinates": [
      5.47063,
      50.49634
    ]
  }
}