{
  "type": "Feature",
  "properties": {
    "name": "Thisnes",
    "country": "BE",
    "subdivision": "WAL",
    "timezone": "Europe/Brussels"
  },
  "geometry": {
    "type": "Point",
    "coordinates": [
      5.04375,
      50.66578
    ]
  }
}