{
  "type": "Feature",
  "properties": {
    "name": "Tohogne",
    "country": "BE",
    "subdivision": "WAL",
    "timezone": "Europe/Brussels"
  },
  "geometry": {
    "type": "Point",
    "coordinates": [
      5.479,
      50.38006
    ]
  }
}