{
  "type": "Feature",
  "properties": {
    "name": "Vierset-Barse",
    "country": "BE",
    "subdivision": "WAL",
    "timezone": "Europe/Brussels"
  },
  "geometry": {
    "type": "Point",
    "coordinates": [
      5.29816,
      50.48373
    ]
  }
}