{
  "type": "Feature",
  "properties": {
    "name": "Vieux-Genappe",
    "country": "BE",
    "subdivision": "WAL",
    "timezone": "Europe/Brussels"
  },
  "geometry": {
    "type": "Point",
    "coordinates": [
      4.44097,
      50.60846
    ]
  }
}