{
  "type": "Feature",
  "properties": {
    "name": "Virton",
    "country": "BE",
    "subdivision": "WAL",
    "timezone": "Europe/Brussels"
  },
  "geometry": {
    "type": "Point",
    "coordinates": [
      5.53259,
      49.56824
    ]
  }
}