{
  "type": "Feature",
  "properties": {
    "name": "Visé",
    "country": "BE",
    "subdivision": "WAL",
    "timezone": "Europe/Brussels"
  },
  "geometry": {
    "type": "Point",
    "coordinates": [
      5.69907,
      50.7376
    ]
  }
}