{
  "type": "Feature",
  "properties": {
    "name": "Wanze",
    "country": "BE",
    "subdivision": "WAL",
    "timezone": "Europe/Brussels"
  },
  "geometry": {
    "type": "Point",
    "coordinates": [
      5.20846,
      50.53907
    ]
  }
}