{
  "type": "Feature",
  "properties": {
    "name": "Wauthier-Braine",
    "country": "BE",
    "subdivision": "WAL",
    "timezone": "Europe/Brussels"
  },
  "geometry": {
    "type": "Point",
    "coordinates": [
      4.29849,
      50.68183
    ]
  }
}