{
  "type": "Feature",
  "properties": {
    "name": "Wavreille",
    "country": "BE",
    "subdivision": "WAL",
    "timezone": "Europe/Brussels"
  },
  "geometry": {
    "type": "Point",
    "coordinates": [
      5.24831,
      50.12119
    ]
  }
}