{
  "type": "Feature",
  "properties": {
    "name": "Wavre",
    "country": "BE",
    "subdivision": "WAL",
    "timezone": "Europe/Brussels"
  },
  "geometry": {
    "type": "Point",
    "coordinates": [
      4.60138,
      50.71717
    ]
  }
}