{
  "type": "Feature",
  "properties": {
    "name": "Wellin",
    "country": "BE",
    "subdivision": "WAL",
    "timezone": "Europe/Brussels"
  },
  "geometry": {
    "type": "Point",
    "coordinates": [
      5.11413,
      50.08133
    ]
  }
}