{
  "type": "Feature",
  "properties": {
    "name": "Wiers",
    "country": "BE",
    "subdivision": "WAL",
    "timezone": "Europe/Brussels"
  },
  "geometry": {
    "type": "Point",
    "coordinates": [
      3.53468,
      50.50862
    ]
  }
}