{
  "type": "Feature",
  "properties": {
    "name": "Xhoris",
    "country": "BE",
    "subdivision": "WAL",
    "timezone": "Europe/Brussels"
  },
  "geometry": {
    "type": "Point",
    "coordinates": [
      5.60431,
      50.44586
    ]
  }
}