{
  "type": "Feature",
  "properties": {
    "name": "Guáimaro",
    "country": "CU",
    "subdivision": "05",
    "timezone": "America/Havana"
  },
  "geometry": {
    "type": "Point",
    "coordinates": [
      -77.3499,
      21.05222
    ]
  }
}