{
  "type": "Feature",
  "properties": {
    "name": "Santa Cruz del Sur",
    "country": "CU",
    "subdivision": "05",
    "timezone": "America/Havana"
  },
  "geometry": {
    "type": "Point",
    "coordinates": [
      -77.99816,
      20.71633
    ]
  }
}