{
  "type": "Feature",
  "properties": {
    "name": "Benešov nad Černou",
    "country": "CZ",
    "subdivision": "79",
    "timezone": "Europe/Prague"
  },
  "geometry": {
    "type": "Point",
    "coordinates": [
      14.62737,
      48.7294
    ]
  }
}