{
  "type": "Feature",
  "properties": {
    "name": "Dačice",
    "country": "CZ",
    "subdivision": "79",
    "timezone": "Europe/Prague"
  },
  "geometry": {
    "type": "Point",
    "coordinates": [
      15.43727,
      49.08154
    ]
  }
}