{
  "type": "Feature",
  "properties": {
    "name": "Dubné",
    "country": "CZ",
    "subdivision": "79",
    "timezone": "Europe/Prague"
  },
  "geometry": {
    "type": "Point",
    "coordinates": [
      14.36038,
      48.97619
    ]
  }
}