{
  "type": "Feature",
  "properties": {
    "name": "Kardašova Řečice",
    "country": "CZ",
    "subdivision": "79",
    "timezone": "Europe/Prague"
  },
  "geometry": {
    "type": "Point",
    "coordinates": [
      14.85315,
      49.18478
    ]
  }
}