{
  "type": "Feature",
  "properties": {
    "name": "Loučovice",
    "country": "CZ",
    "subdivision": "79",
    "timezone": "Europe/Prague"
  },
  "geometry": {
    "type": "Point",
    "coordinates": [
      14.25747,
      48.62019
    ]
  }
}