{
  "type": "Feature",
  "properties": {
    "name": "Písek",
    "country": "CZ",
    "subdivision": "79",
    "timezone": "Europe/Prague"
  },
  "geometry": {
    "type": "Point",
    "coordinates": [
      14.1475,
      49.3088
    ]
  }
}