{
  "type": "Feature",
  "properties": {
    "name": "Sepekov",
    "country": "CZ",
    "subdivision": "79",
    "timezone": "Europe/Prague"
  },
  "geometry": {
    "type": "Point",
    "coordinates": [
      14.41815,
      49.42865
    ]
  }
}