{
  "type": "Feature",
  "properties": {
    "name": "Ševětín",
    "country": "CZ",
    "subdivision": "79",
    "timezone": "Europe/Prague"
  },
  "geometry": {
    "type": "Point",
    "coordinates": [
      14.5722,
      49.10005
    ]
  }
}