{
  "type": "Feature",
  "properties": {
    "name": "Sezimovo Ústí",
    "country": "CZ",
    "subdivision": "79",
    "timezone": "Europe/Prague"
  },
  "geometry": {
    "type": "Point",
    "coordinates": [
      14.6848,
      49.38519
    ]
  }
}