{
  "type": "Feature",
  "properties": {
    "name": "Tábor",
    "country": "CZ",
    "subdivision": "79",
    "timezone": "Europe/Prague"
  },
  "geometry": {
    "type": "Point",
    "coordinates": [
      14.6578,
      49.41441
    ]
  }
}