{
  "type": "Feature",
  "properties": {
    "name": "Trhové Sviny",
    "country": "CZ",
    "subdivision": "79",
    "timezone": "Europe/Prague"
  },
  "geometry": {
    "type": "Point",
    "coordinates": [
      14.63924,
      48.84231
    ]
  }
}