{
  "type": "Feature",
  "properties": {
    "name": "Včelná",
    "country": "CZ",
    "subdivision": "79",
    "timezone": "Europe/Prague"
  },
  "geometry": {
    "type": "Point",
    "coordinates": [
      14.45383,
      48.92373
    ]
  }
}