{
  "type": "Feature",
  "properties": {
    "name": "Volyně",
    "country": "CZ",
    "subdivision": "79",
    "timezone": "Europe/Prague"
  },
  "geometry": {
    "type": "Point",
    "coordinates": [
      13.88624,
      49.16578
    ]
  }
}