{
  "type": "Feature",
  "properties": {
    "name": "Vyšší Brod",
    "country": "CZ",
    "subdivision": "79",
    "timezone": "Europe/Prague"
  },
  "geometry": {
    "type": "Point",
    "coordinates": [
      14.31183,
      48.61598
    ]
  }
}