{
  "type": "Feature",
  "properties": {
    "name": "Lhokseumawe",
    "country": "ID",
    "subdivision": "01",
    "timezone": "Asia/Jakarta"
  },
  "geometry": {
    "type": "Point",
    "coordinates": [
      97.1507,
      5.1801
    ]
  }
}