{
  "type": "Feature",
  "properties": {
    "name": "Stetten",
    "country": "CH",
    "subdivision": "SH",
    "timezone": "Europe/Zurich"
  },
  "geometry": {
    "type": "Point",
    "coordinates": [
      8.66298,
      47.74025
    ]
  }
}