{
  "type": "Feature",
  "properties": {
    "name": "Damasak",
    "country": "NG",
    "subdivision": "27",
    "timezone": "Africa/Lagos"
  },
  "geometry": {
    "type": "Point",
    "coordinates": [
      12.50854,
      13.10518
    ]
  }
}