{
  "type": "Feature",
  "properties": {
    "name": "Dikwa",
    "country": "NG",
    "subdivision": "27",
    "timezone": "Africa/Lagos"
  },
  "geometry": {
    "type": "Point",
    "coordinates": [
      13.91815,
      12.03609
    ]
  }
}