{
  "type": "Feature",
  "properties": {
    "name": "Maiduguri",
    "country": "NG",
    "subdivision": "27",
    "timezone": "Africa/Lagos"
  },
  "geometry": {
    "type": "Point",
    "coordinates": [
      13.15712,
      11.84692
    ]
  }
}