{
  "type": "Feature",
  "properties": {
    "name": "Ancasti",
    "country": "AR",
    "subdivision": "02",
    "timezone": "America/Argentina/Catamarca"
  },
  "geometry": {
    "type": "Point",
    "coordinates": [
      -65.50145,
      -28.81247
    ]
  }
}