{
  "type": "Feature",
  "properties": {
    "name": "La Puerta de San José",
    "country": "AR",
    "subdivision": "02",
    "timezone": "America/Argentina/Catamarca"
  },
  "geometry": {
    "type": "Point",
    "coordinates": [
      -67.01667,
      -27.55
    ]
  }
}