{
  "type": "Feature",
  "properties": {
    "name": "Puerta de Corral Quemado",
    "country": "AR",
    "subdivision": "02",
    "timezone": "America/Argentina/Catamarca"
  },
  "geometry": {
    "type": "Point",
    "coordinates": [
      -66.93635,
      -27.23
    ]
  }
}