{
  "type": "Feature",
  "properties": {
    "name": "Tinogasta",
    "country": "AR",
    "subdivision": "02",
    "timezone": "America/Argentina/Catamarca"
  },
  "geometry": {
    "type": "Point",
    "coordinates": [
      -67.56488,
      -28.06319
    ]
  }
}