{
  "type": "Feature",
  "properties": {
    "name": "Nachingwea",
    "country": "TZ",
    "subdivision": "07",
    "timezone": "Africa/Dar_es_Salaam"
  },
  "geometry": {
    "type": "Point",
    "coordinates": [
      38.76251,
      -10.3725
    ]
  }
}