{
  "type": "Feature",
  "properties": {
    "name": "Maru",
    "country": "NG",
    "subdivision": "57",
    "timezone": "Africa/Lagos"
  },
  "geometry": {
    "type": "Point",
    "coordinates": [
      6.40372,
      12.3336
    ]
  }
}