{
  "type": "Feature",
  "properties": {
    "name": "Santa María",
    "country": "PY",
    "subdivision": "12",
    "timezone": "America/Asuncion"
  },
  "geometry": {
    "type": "Point",
    "coordinates": [
      -56.94333,
      -26.78371
    ]
  }
}