{
  "type": "Feature",
  "properties": {
    "name": "Faldarlı",
    "country": "AZ",
    "subdivision": "70",
    "timezone": "Asia/Baku"
  },
  "geometry": {
    "type": "Point",
    "coordinates": [
      46.51579,
      41.46868
    ]
  }
}