{
  "type": "Feature",
  "properties": {
    "name": "Clorinda",
    "country": "AR",
    "subdivision": "09",
    "timezone": "America/Argentina/Cordoba"
  },
  "geometry": {
    "type": "Point",
    "coordinates": [
      -57.71851,
      -25.28481
    ]
  }
}