{
  "type": "Feature",
  "properties": {
    "name": "El Colorado",
    "country": "AR",
    "subdivision": "09",
    "timezone": "America/Argentina/Cordoba"
  },
  "geometry": {
    "type": "Point",
    "coordinates": [
      -59.37291,
      -26.30808
    ]
  }
}