{
  "type": "Feature",
  "properties": {
    "name": "Laguna Yema",
    "country": "AR",
    "subdivision": "09",
    "timezone": "America/Argentina/Cordoba"
  },
  "geometry": {
    "type": "Point",
    "coordinates": [
      -61.24466,
      -24.25391
    ]
  }
}