{
  "type": "Feature",
  "properties": {
    "name": "Pirané",
    "country": "AR",
    "subdivision": "09",
    "timezone": "America/Argentina/Cordoba"
  },
  "geometry": {
    "type": "Point",
    "coordinates": [
      -59.10879,
      -25.73239
    ]
  }
}