{
  "type": "Feature",
  "properties": {
    "name": "Minga Porá",
    "country": "PY",
    "subdivision": "01",
    "timezone": "America/Asuncion"
  },
  "geometry": {
    "type": "Point",
    "coordinates": [
      -54.93395,
      -24.87544
    ]
  }
}