{
  "type": "Feature",
  "properties": {
    "name": "Beregsău Mare",
    "country": "RO",
    "subdivision": "36",
    "timezone": "Europe/Bucharest"
  },
  "geometry": {
    "type": "Point",
    "coordinates": [
      21.02666,
      45.75921
    ]
  }
}