{
  "type": "Feature",
  "properties": {
    "name": "Boldur",
    "country": "RO",
    "subdivision": "36",
    "timezone": "Europe/Bucharest"
  },
  "geometry": {
    "type": "Point",
    "coordinates": [
      21.77667,
      45.69417
    ]
  }
}