{
  "type": "Feature",
  "properties": {
    "name": "Buziaş",
    "country": "RO",
    "subdivision": "36",
    "timezone": "Europe/Bucharest"
  },
  "geometry": {
    "type": "Point",
    "coordinates": [
      21.60361,
      45.64917
    ]
  }
}