{
  "type": "Feature",
  "properties": {
    "name": "Făget",
    "country": "RO",
    "subdivision": "36",
    "timezone": "Europe/Bucharest"
  },
  "geometry": {
    "type": "Point",
    "coordinates": [
      22.18333,
      45.85
    ]
  }
}