{
  "type": "Feature",
  "properties": {
    "name": "Gavojdia",
    "country": "RO",
    "subdivision": "36",
    "timezone": "Europe/Bucharest"
  },
  "geometry": {
    "type": "Point",
    "coordinates": [
      22.01667,
      45.61667
    ]
  }
}