{
  "type": "Feature",
  "properties": {
    "name": "Ghilad",
    "country": "RO",
    "subdivision": "36",
    "timezone": "Europe/Bucharest"
  },
  "geometry": {
    "type": "Point",
    "coordinates": [
      21.13824,
      45.46501
    ]
  }
}