{
  "type": "Feature",
  "properties": {
    "name": "Giera",
    "country": "RO",
    "subdivision": "36",
    "timezone": "Europe/Bucharest"
  },
  "geometry": {
    "type": "Point",
    "coordinates": [
      20.99222,
      45.40722
    ]
  }
}