{
  "type": "Feature",
  "properties": {
    "name": "Lugoj",
    "country": "RO",
    "subdivision": "36",
    "timezone": "Europe/Bucharest"
  },
  "geometry": {
    "type": "Point",
    "coordinates": [
      21.90306,
      45.68861
    ]
  }
}