{
  "type": "Feature",
  "properties": {
    "name": "Mănăştiur",
    "country": "RO",
    "subdivision": "36",
    "timezone": "Europe/Bucharest"
  },
  "geometry": {
    "type": "Point",
    "coordinates": [
      22.06667,
      45.81667
    ]
  }
}