{
  "type": "Feature",
  "properties": {
    "name": "Moşniţa Nouă",
    "country": "RO",
    "subdivision": "36",
    "timezone": "Europe/Bucharest"
  },
  "geometry": {
    "type": "Point",
    "coordinates": [
      21.32528,
      45.71722
    ]
  }
}