{
  "type": "Feature",
  "properties": {
    "name": "Nerău",
    "country": "RO",
    "subdivision": "36",
    "timezone": "Europe/Bucharest"
  },
  "geometry": {
    "type": "Point",
    "coordinates": [
      20.5607,
      45.96929
    ]
  }
}