{
  "type": "Feature",
  "properties": {
    "name": "Niţchidorf",
    "country": "RO",
    "subdivision": "36",
    "timezone": "Europe/Bucharest"
  },
  "geometry": {
    "type": "Point",
    "coordinates": [
      21.53333,
      45.58333
    ]
  }
}