{
  "type": "Feature",
  "properties": {
    "name": "Saravale",
    "country": "RO",
    "subdivision": "36",
    "timezone": "Europe/Bucharest"
  },
  "geometry": {
    "type": "Point",
    "coordinates": [
      20.74085,
      46.06929
    ]
  }
}