{
  "type": "Feature",
  "properties": {
    "name": "Urseni",
    "country": "RO",
    "subdivision": "36",
    "timezone": "Europe/Bucharest"
  },
  "geometry": {
    "type": "Point",
    "coordinates": [
      21.30993,
      45.69269
    ]
  }
}