{
  "type": "Feature",
  "properties": {
    "name": "Utvin",
    "country": "RO",
    "subdivision": "36",
    "timezone": "Europe/Bucharest"
  },
  "geometry": {
    "type": "Point",
    "coordinates": [
      21.13011,
      45.71298
    ]
  }
}