{
  "type": "Feature",
  "properties": {
    "name": "Musanze",
    "country": "RW",
    "subdivision": "13",
    "timezone": "Africa/Kigali"
  },
  "geometry": {
    "type": "Point",
    "coordinates": [
      29.63497,
      -1.49984
    ]
  }
}