{
  "type": "Feature",
  "properties": {
    "name": "Umm Kaddadah",
    "country": "SD",
    "subdivision": "55",
    "timezone": "Africa/Khartoum"
  },
  "geometry": {
    "type": "Point",
    "coordinates": [
      26.68759,
      13.60169
    ]
  }
}