{
  "type": "Feature",
  "properties": {
    "name": "Palanga",
    "country": "LT",
    "subdivision": "58",
    "timezone": "Europe/Vilnius"
  },
  "geometry": {
    "type": "Point",
    "coordinates": [
      21.06861,
      55.9175
    ]
  }
}