{
  "type": "Feature",
  "properties": {
    "name": "Borowno",
    "country": "PL",
    "subdivision": "83",
    "timezone": "Europe/Warsaw"
  },
  "geometry": {
    "type": "Point",
    "coordinates": [
      19.2738,
      50.93247
    ]
  }
}