{
  "type": "Feature",
  "properties": {
    "name": "Bujaków",
    "country": "PL",
    "subdivision": "83",
    "timezone": "Europe/Warsaw"
  },
  "geometry": {
    "type": "Point",
    "coordinates": [
      19.19432,
      49.85182
    ]
  }
}