{
  "type": "Feature",
  "properties": {
    "name": "Ciasna",
    "country": "PL",
    "subdivision": "83",
    "timezone": "Europe/Warsaw"
  },
  "geometry": {
    "type": "Point",
    "coordinates": [
      18.60835,
      50.75427
    ]
  }
}