{
  "type": "Feature",
  "properties": {
    "name": "Cielmice",
    "country": "PL",
    "subdivision": "83",
    "timezone": "Europe/Warsaw"
  },
  "geometry": {
    "type": "Point",
    "coordinates": [
      19.01896,
      50.08826
    ]
  }
}