{
  "type": "Feature",
  "properties": {
    "name": "Czechowice-Dziedzice",
    "country": "PL",
    "subdivision": "83",
    "timezone": "Europe/Warsaw"
  },
  "geometry": {
    "type": "Point",
    "coordinates": [
      19.00479,
      49.91342
    ]
  }
}