{
  "type": "Feature",
  "properties": {
    "name": "Dąbrowa Górnicza",
    "country": "PL",
    "subdivision": "83",
    "timezone": "Europe/Warsaw"
  },
  "geometry": {
    "type": "Point",
    "coordinates": [
      19.20479,
      50.33394
    ]
  }
}