{
  "type": "Feature",
  "properties": {
    "name": "Goczałkowice Zdrój",
    "country": "PL",
    "subdivision": "83",
    "timezone": "Europe/Warsaw"
  },
  "geometry": {
    "type": "Point",
    "coordinates": [
      18.96927,
      49.94454
    ]
  }
}