{
  "type": "Feature",
  "properties": {
    "name": "Gorzyczki",
    "country": "PL",
    "subdivision": "83",
    "timezone": "Europe/Warsaw"
  },
  "geometry": {
    "type": "Point",
    "coordinates": [
      18.4033,
      49.94912
    ]
  }
}