{
  "type": "Feature",
  "properties": {
    "name": "Gołkowice",
    "country": "PL",
    "subdivision": "83",
    "timezone": "Europe/Warsaw"
  },
  "geometry": {
    "type": "Point",
    "coordinates": [
      18.51419,
      49.91418
    ]
  }
}