{
  "type": "Feature",
  "properties": {
    "name": "Istebna",
    "country": "PL",
    "subdivision": "83",
    "timezone": "Europe/Warsaw"
  },
  "geometry": {
    "type": "Point",
    "coordinates": [
      18.90567,
      49.56319
    ]
  }
}