{
  "type": "Feature",
  "properties": {
    "name": "Kamyk",
    "country": "PL",
    "subdivision": "83",
    "timezone": "Europe/Warsaw"
  },
  "geometry": {
    "type": "Point",
    "coordinates": [
      19.02875,
      50.90179
    ]
  }
}