{
  "type": "Feature",
  "properties": {
    "name": "Kończyce Wielkie",
    "country": "PL",
    "subdivision": "83",
    "timezone": "Europe/Warsaw"
  },
  "geometry": {
    "type": "Point",
    "coordinates": [
      18.64474,
      49.8351
    ]
  }
}