{
  "type": "Feature",
  "properties": {
    "name": "Ligota",
    "country": "PL",
    "subdivision": "83",
    "timezone": "Europe/Warsaw"
  },
  "geometry": {
    "type": "Point",
    "coordinates": [
      18.9509,
      49.89856
    ]
  }
}