{
  "type": "Feature",
  "properties": {
    "name": "Orzesze",
    "country": "PL",
    "subdivision": "83",
    "timezone": "Europe/Warsaw"
  },
  "geometry": {
    "type": "Point",
    "coordinates": [
      18.77923,
      50.15595
    ]
  }
}