{
  "type": "Feature",
  "properties": {
    "name": "Poraj",
    "country": "PL",
    "subdivision": "83",
    "timezone": "Europe/Warsaw"
  },
  "geometry": {
    "type": "Point",
    "coordinates": [
      19.21509,
      50.67797
    ]
  }
}