{
  "type": "Feature",
  "properties": {
    "name": "Pszczyna",
    "country": "PL",
    "subdivision": "83",
    "timezone": "Europe/Warsaw"
  },
  "geometry": {
    "type": "Point",
    "coordinates": [
      18.95382,
      49.98037
    ]
  }
}