{
  "type": "Feature",
  "properties": {
    "name": "Rajcza",
    "country": "PL",
    "subdivision": "83",
    "timezone": "Europe/Warsaw"
  },
  "geometry": {
    "type": "Point",
    "coordinates": [
      19.11278,
      49.50927
    ]
  }
}