{
  "type": "Feature",
  "properties": {
    "name": "Rędziny",
    "country": "PL",
    "subdivision": "83",
    "timezone": "Europe/Warsaw"
  },
  "geometry": {
    "type": "Point",
    "coordinates": [
      19.2162,
      50.85922
    ]
  }
}