{
  "type": "Feature",
  "properties": {
    "name": "Rogoźnik",
    "country": "PL",
    "subdivision": "83",
    "timezone": "Europe/Warsaw"
  },
  "geometry": {
    "type": "Point",
    "coordinates": [
      19.03776,
      50.39106
    ]
  }
}