{
  "type": "Feature",
  "properties": {
    "name": "Rycerka Dolna",
    "country": "PL",
    "subdivision": "83",
    "timezone": "Europe/Warsaw"
  },
  "geometry": {
    "type": "Point",
    "coordinates": [
      19.06162,
      49.47805
    ]
  }
}