{
  "type": "Feature",
  "properties": {
    "name": "Świętochłowice",
    "country": "PL",
    "subdivision": "83",
    "timezone": "Europe/Warsaw"
  },
  "geometry": {
    "type": "Point",
    "coordinates": [
      18.91726,
      50.29636
    ]
  }
}