{
  "type": "Feature",
  "properties": {
    "name": "Świerklaniec",
    "country": "PL",
    "subdivision": "83",
    "timezone": "Europe/Warsaw"
  },
  "geometry": {
    "type": "Point",
    "coordinates": [
      18.93734,
      50.44237
    ]
  }
}