{
  "type": "Feature",
  "properties": {
    "name": "Truskolasy",
    "country": "PL",
    "subdivision": "83",
    "timezone": "Europe/Warsaw"
  },
  "geometry": {
    "type": "Point",
    "coordinates": [
      18.82705,
      50.86692
    ]
  }
}