{
  "type": "Feature",
  "properties": {
    "name": "Trzebinia",
    "country": "PL",
    "subdivision": "83",
    "timezone": "Europe/Warsaw"
  },
  "geometry": {
    "type": "Point",
    "coordinates": [
      19.22264,
      49.65024
    ]
  }
}