{
  "type": "Feature",
  "properties": {
    "name": "Wilcza",
    "country": "PL",
    "subdivision": "83",
    "timezone": "Europe/Warsaw"
  },
  "geometry": {
    "type": "Point",
    "coordinates": [
      18.59668,
      50.18899
    ]
  }
}