{
  "type": "Feature",
  "properties": {
    "name": "Wilkowice",
    "country": "PL",
    "subdivision": "83",
    "timezone": "Europe/Warsaw"
  },
  "geometry": {
    "type": "Point",
    "coordinates": [
      19.08973,
      49.76282
    ]
  }
}