{
  "type": "Feature",
  "properties": {
    "name": "Wodzisław Śląski",
    "country": "PL",
    "subdivision": "83",
    "timezone": "Europe/Warsaw"
  },
  "geometry": {
    "type": "Point",
    "coordinates": [
      18.47205,
      50.00377
    ]
  }
}