{
  "type": "Feature",
  "properties": {
    "name": "Włodowice",
    "country": "PL",
    "subdivision": "83",
    "timezone": "Europe/Warsaw"
  },
  "geometry": {
    "type": "Point",
    "coordinates": [
      19.45155,
      50.5556
    ]
  }
}