{
  "type": "Feature",
  "properties": {
    "name": "Altena",
    "country": "DE",
    "subdivision": "07",
    "timezone": "Europe/Berlin"
  },
  "geometry": {
    "type": "Point",
    "coordinates": [
      7.67337,
      51.29472
    ]
  }
}