{
  "type": "Feature",
  "properties": {
    "name": "Altstadt Sud",
    "country": "DE",
    "subdivision": "07",
    "timezone": "Europe/Berlin"
  },
  "geometry": {
    "type": "Point",
    "coordinates": [
      6.95954,
      50.93331
    ]
  }
}