{
  "type": "Feature",
  "properties": {
    "name": "Bad Honnef",
    "country": "DE",
    "subdivision": "07",
    "timezone": "Europe/Berlin"
  },
  "geometry": {
    "type": "Point",
    "coordinates": [
      7.2278,
      50.64336
    ]
  }
}