{
  "type": "Feature",
  "properties": {
    "name": "Bochum-Hordel",
    "country": "DE",
    "subdivision": "07",
    "timezone": "Europe/Berlin"
  },
  "geometry": {
    "type": "Point",
    "coordinates": [
      7.1756,
      51.50168
    ]
  }
}