{
  "type": "Feature",
  "properties": {
    "name": "Borken",
    "country": "DE",
    "subdivision": "07",
    "timezone": "Europe/Berlin"
  },
  "geometry": {
    "type": "Point",
    "coordinates": [
      6.85774,
      51.84382
    ]
  }
}