{
  "type": "Feature",
  "properties": {
    "name": "Bornheim",
    "country": "DE",
    "subdivision": "07",
    "timezone": "Europe/Berlin"
  },
  "geometry": {
    "type": "Point",
    "coordinates": [
      6.99089,
      50.76313
    ]
  }
}