{
  "type": "Feature",
  "properties": {
    "name": "Bünde",
    "country": "DE",
    "subdivision": "07",
    "timezone": "Europe/Berlin"
  },
  "geometry": {
    "type": "Point",
    "coordinates": [
      8.58644,
      52.19837
    ]
  }
}