{
  "type": "Feature",
  "properties": {
    "name": "Burbach",
    "country": "DE",
    "subdivision": "07",
    "timezone": "Europe/Berlin"
  },
  "geometry": {
    "type": "Point",
    "coordinates": [
      8.07939,
      50.75105
    ]
  }
}