{
  "type": "Feature",
  "properties": {
    "name": "Drolshagen",
    "country": "DE",
    "subdivision": "07",
    "timezone": "Europe/Berlin"
  },
  "geometry": {
    "type": "Point",
    "coordinates": [
      7.77355,
      51.02358
    ]
  }
}