{
  "type": "Feature",
  "properties": {
    "name": "Dülmen",
    "country": "DE",
    "subdivision": "07",
    "timezone": "Europe/Berlin"
  },
  "geometry": {
    "type": "Point",
    "coordinates": [
      7.28075,
      51.83149
    ]
  }
}