{
  "type": "Feature",
  "properties": {
    "name": "Düren",
    "country": "DE",
    "subdivision": "07",
    "timezone": "Europe/Berlin"
  },
  "geometry": {
    "type": "Point",
    "coordinates": [
      6.49299,
      50.80434
    ]
  }
}