{
  "type": "Feature",
  "properties": {
    "name": "Enger",
    "country": "DE",
    "subdivision": "07",
    "timezone": "Europe/Berlin"
  },
  "geometry": {
    "type": "Point",
    "coordinates": [
      8.55772,
      52.14063
    ]
  }
}