{
  "type": "Feature",
  "properties": {
    "name": "Eschweiler",
    "country": "DE",
    "subdivision": "07",
    "timezone": "Europe/Berlin"
  },
  "geometry": {
    "type": "Point",
    "coordinates": [
      6.27184,
      50.81854
    ]
  }
}