{
  "type": "Feature",
  "properties": {
    "name": "Greven",
    "country": "DE",
    "subdivision": "07",
    "timezone": "Europe/Berlin"
  },
  "geometry": {
    "type": "Point",
    "coordinates": [
      7.59396,
      52.09364
    ]
  }
}