{
  "type": "Feature",
  "properties": {
    "name": "Hemer",
    "country": "DE",
    "subdivision": "07",
    "timezone": "Europe/Berlin"
  },
  "geometry": {
    "type": "Point",
    "coordinates": [
      7.77019,
      51.38707
    ]
  }
}