{
  "type": "Feature",
  "properties": {
    "name": "Herten",
    "country": "DE",
    "subdivision": "07",
    "timezone": "Europe/Berlin"
  },
  "geometry": {
    "type": "Point",
    "coordinates": [
      7.14387,
      51.59638
    ]
  }
}