{
  "type": "Feature",
  "properties": {
    "name": "Hilchenbach",
    "country": "DE",
    "subdivision": "07",
    "timezone": "Europe/Berlin"
  },
  "geometry": {
    "type": "Point",
    "coordinates": [
      8.11062,
      50.99687
    ]
  }
}