{
  "type": "Feature",
  "properties": {
    "name": "Horn",
    "country": "DE",
    "subdivision": "07",
    "timezone": "Europe/Berlin"
  },
  "geometry": {
    "type": "Point",
    "coordinates": [
      8.9451,
      51.87151
    ]
  }
}