{
  "type": "Feature",
  "properties": {
    "name": "Hünxe",
    "country": "DE",
    "subdivision": "07",
    "timezone": "Europe/Berlin"
  },
  "geometry": {
    "type": "Point",
    "coordinates": [
      6.69741,
      51.63405
    ]
  }
}