{
  "type": "Feature",
  "properties": {
    "name": "Ibbenbüren",
    "country": "DE",
    "subdivision": "07",
    "timezone": "Europe/Berlin"
  },
  "geometry": {
    "type": "Point",
    "coordinates": [
      7.71457,
      52.27964
    ]
  }
}