{
  "type": "Feature",
  "properties": {
    "name": "Kierspe",
    "country": "DE",
    "subdivision": "07",
    "timezone": "Europe/Berlin"
  },
  "geometry": {
    "type": "Point",
    "coordinates": [
      7.59075,
      51.13403
    ]
  }
}