{
  "type": "Feature",
  "properties": {
    "name": "Kirchhundem",
    "country": "DE",
    "subdivision": "07",
    "timezone": "Europe/Berlin"
  },
  "geometry": {
    "type": "Point",
    "coordinates": [
      8.08893,
      51.08556
    ]
  }
}