{
  "type": "Feature",
  "properties": {
    "name": "Lage",
    "country": "DE",
    "subdivision": "07",
    "timezone": "Europe/Berlin"
  },
  "geometry": {
    "type": "Point",
    "coordinates": [
      8.79301,
      51.99223
    ]
  }
}