{
  "type": "Feature",
  "properties": {
    "name": "Leichlingen",
    "country": "DE",
    "subdivision": "07",
    "timezone": "Europe/Berlin"
  },
  "geometry": {
    "type": "Point",
    "coordinates": [
      7.01873,
      51.10628
    ]
  }
}