{
  "type": "Feature",
  "properties": {
    "name": "Lippstadt",
    "country": "DE",
    "subdivision": "07",
    "timezone": "Europe/Berlin"
  },
  "geometry": {
    "type": "Point",
    "coordinates": [
      8.34482,
      51.67369
    ]
  }
}