{
  "type": "Feature",
  "properties": {
    "name": "Monheim am Rhein",
    "country": "DE",
    "subdivision": "07",
    "timezone": "Europe/Berlin"
  },
  "geometry": {
    "type": "Point",
    "coordinates": [
      6.89217,
      51.09162
    ]
  }
}