{
  "type": "Feature",
  "properties": {
    "name": "Neuenkirchen",
    "country": "DE",
    "subdivision": "07",
    "timezone": "Europe/Berlin"
  },
  "geometry": {
    "type": "Point",
    "coordinates": [
      7.37183,
      52.24472
    ]
  }
}