{
  "type": "Feature",
  "properties": {
    "name": "Nideggen",
    "country": "DE",
    "subdivision": "07",
    "timezone": "Europe/Berlin"
  },
  "geometry": {
    "type": "Point",
    "coordinates": [
      6.48437,
      50.69268
    ]
  }
}