{
  "type": "Feature",
  "properties": {
    "name": "Niederzier",
    "country": "DE",
    "subdivision": "07",
    "timezone": "Europe/Berlin"
  },
  "geometry": {
    "type": "Point",
    "coordinates": [
      6.46667,
      50.88333
    ]
  }
}