{
  "type": "Feature",
  "properties": {
    "name": "Nordkirchen",
    "country": "DE",
    "subdivision": "07",
    "timezone": "Europe/Berlin"
  },
  "geometry": {
    "type": "Point",
    "coordinates": [
      7.52197,
      51.73827
    ]
  }
}