{
  "type": "Feature",
  "properties": {
    "name": "Nümbrecht",
    "country": "DE",
    "subdivision": "07",
    "timezone": "Europe/Berlin"
  },
  "geometry": {
    "type": "Point",
    "coordinates": [
      7.54063,
      50.90427
    ]
  }
}