{
  "type": "Feature",
  "properties": {
    "name": "Ostbevern",
    "country": "DE",
    "subdivision": "07",
    "timezone": "Europe/Berlin"
  },
  "geometry": {
    "type": "Point",
    "coordinates": [
      7.84229,
      52.04018
    ]
  }
}