{
  "type": "Feature",
  "properties": {
    "name": "Rahden",
    "country": "DE",
    "subdivision": "07",
    "timezone": "Europe/Berlin"
  },
  "geometry": {
    "type": "Point",
    "coordinates": [
      8.61263,
      52.43367
    ]
  }
}