{
  "type": "Feature",
  "properties": {
    "name": "Recklinghausen",
    "country": "DE",
    "subdivision": "07",
    "timezone": "Europe/Berlin"
  },
  "geometry": {
    "type": "Point",
    "coordinates": [
      7.19738,
      51.61379
    ]
  }
}