{
  "type": "Feature",
  "properties": {
    "name": "Salzkotten",
    "country": "DE",
    "subdivision": "07",
    "timezone": "Europe/Berlin"
  },
  "geometry": {
    "type": "Point",
    "coordinates": [
      8.60092,
      51.6717
    ]
  }
}