{
  "type": "Feature",
  "properties": {
    "name": "Sankt Augustin",
    "country": "DE",
    "subdivision": "07",
    "timezone": "Europe/Berlin"
  },
  "geometry": {
    "type": "Point",
    "coordinates": [
      7.197,
      50.77538
    ]
  }
}