{
  "type": "Feature",
  "properties": {
    "name": "Schermbeck",
    "country": "DE",
    "subdivision": "07",
    "timezone": "Europe/Berlin"
  },
  "geometry": {
    "type": "Point",
    "coordinates": [
      6.86667,
      51.68333
    ]
  }
}