{
  "type": "Feature",
  "properties": {
    "name": "Schleiden",
    "country": "DE",
    "subdivision": "07",
    "timezone": "Europe/Berlin"
  },
  "geometry": {
    "type": "Point",
    "coordinates": [
      6.47692,
      50.52896
    ]
  }
}