{
  "type": "Feature",
  "properties": {
    "name": "Steinheim",
    "country": "DE",
    "subdivision": "07",
    "timezone": "Europe/Berlin"
  },
  "geometry": {
    "type": "Point",
    "coordinates": [
      9.09136,
      51.87066
    ]
  }
}