{
  "type": "Feature",
  "properties": {
    "name": "Stolberg",
    "country": "DE",
    "subdivision": "07",
    "timezone": "Europe/Berlin"
  },
  "geometry": {
    "type": "Point",
    "coordinates": [
      6.22595,
      50.77368
    ]
  }
}