{
  "type": "Feature",
  "properties": {
    "name": "Stoßdorf",
    "country": "DE",
    "subdivision": "07",
    "timezone": "Europe/Berlin"
  },
  "geometry": {
    "type": "Point",
    "coordinates": [
      7.25126,
      50.78248
    ]
  }
}