{
  "type": "Feature",
  "properties": {
    "name": "Übach-Palenberg",
    "country": "DE",
    "subdivision": "07",
    "timezone": "Europe/Berlin"
  },
  "geometry": {
    "type": "Point",
    "coordinates": [
      6.12336,
      50.91775
    ]
  }
}