{
  "type": "Feature",
  "properties": {
    "name": "Voerde",
    "country": "DE",
    "subdivision": "07",
    "timezone": "Europe/Berlin"
  },
  "geometry": {
    "type": "Point",
    "coordinates": [
      6.6863,
      51.59703
    ]
  }
}