{
  "type": "Feature",
  "properties": {
    "name": "Warstein",
    "country": "DE",
    "subdivision": "07",
    "timezone": "Europe/Berlin"
  },
  "geometry": {
    "type": "Point",
    "coordinates": [
      8.34851,
      51.44488
    ]
  }
}