{
  "type": "Feature",
  "properties": {
    "name": "Werne",
    "country": "DE",
    "subdivision": "07",
    "timezone": "Europe/Berlin"
  },
  "geometry": {
    "type": "Point",
    "coordinates": [
      7.63421,
      51.66446
    ]
  }
}