{
  "type": "Feature",
  "properties": {
    "name": "Zülpich",
    "country": "DE",
    "subdivision": "07",
    "timezone": "Europe/Berlin"
  },
  "geometry": {
    "type": "Point",
    "coordinates": [
      6.65414,
      50.69447
    ]
  }
}