{
  "type": "Feature",
  "properties": {
    "name": "Bālāpur",
    "country": "IN",
    "subdivision": "40",
    "timezone": "Asia/Kolkata"
  },
  "geometry": {
    "type": "Point",
    "coordinates": [
      78.49969,
      17.31018
    ]
  }
}