{
  "type": "Feature",
  "properties": {
    "name": "Devarkonda",
    "country": "IN",
    "subdivision": "40",
    "timezone": "Asia/Kolkata"
  },
  "geometry": {
    "type": "Point",
    "coordinates": [
      78.92073,
      16.69186
    ]
  }
}