{
  "type": "Feature",
  "properties": {
    "name": "Lakshettipet",
    "country": "IN",
    "subdivision": "40",
    "timezone": "Asia/Kolkata"
  },
  "geometry": {
    "type": "Point",
    "coordinates": [
      79.21667,
      18.86667
    ]
  }
}