{
  "type": "Feature",
  "properties": {
    "name": "Mahbūbnagar",
    "country": "IN",
    "subdivision": "40",
    "timezone": "Asia/Kolkata"
  },
  "geometry": {
    "type": "Point",
    "coordinates": [
      77.98597,
      16.74385
    ]
  }
}