{
  "type": "Feature",
  "properties": {
    "name": "Mulugu",
    "country": "IN",
    "subdivision": "40",
    "timezone": "Asia/Kolkata"
  },
  "geometry": {
    "type": "Point",
    "coordinates": [
      79.943,
      18.191
    ]
  }
}