{
  "type": "Feature",
  "properties": {
    "name": "NÄspur",
    "country": "IN",
    "subdivision": "40",
    "timezone": "Asia/Kolkata"
  },
  "geometry": {
    "type": "Point",
    "coordinates": [
      79.46165,
      18.84577
    ]
  }
}