{
  "type": "Feature",
  "properties": {
    "name": "Nizāmābād",
    "country": "IN",
    "subdivision": "40",
    "timezone": "Asia/Kolkata"
  },
  "geometry": {
    "type": "Point",
    "coordinates": [
      78.0988,
      18.67154
    ]
  }
}