{
  "type": "Feature",
  "properties": {
    "name": "Quthbullapur",
    "country": "IN",
    "subdivision": "40",
    "timezone": "Asia/Kolkata"
  },
  "geometry": {
    "type": "Point",
    "coordinates": [
      78.45818,
      17.50107
    ]
  }
}