{
  "type": "Feature",
  "properties": {
    "name": "Sirpur",
    "country": "IN",
    "subdivision": "40",
    "timezone": "Asia/Kolkata"
  },
  "geometry": {
    "type": "Point",
    "coordinates": [
      79.57558,
      19.47953
    ]
  }
}