{
  "type": "Feature",
  "properties": {
    "name": "Zahirābād",
    "country": "IN",
    "subdivision": "40",
    "timezone": "Asia/Kolkata"
  },
  "geometry": {
    "type": "Point",
    "coordinates": [
      77.60743,
      17.68138
    ]
  }
}