{
  "type": "Feature",
  "properties": {
    "name": "Reshetylivka",
    "country": "UA",
    "subdivision": "18",
    "timezone": "Europe/Kiev"
  },
  "geometry": {
    "type": "Point",
    "coordinates": [
      34.07896,
      49.563
    ]
  }
}