{
  "type": "Feature",
  "properties": {
    "name": "Alegre",
    "country": "BR",
    "subdivision": "08",
    "timezone": "America/Sao_Paulo"
  },
  "geometry": {
    "type": "Point",
    "coordinates": [
      -41.53306,
      -20.76361
    ]
  }
}