{
  "type": "Feature",
  "properties": {
    "name": "Barra de São Francisco",
    "country": "BR",
    "subdivision": "08",
    "timezone": "America/Sao_Paulo"
  },
  "geometry": {
    "type": "Point",
    "coordinates": [
      -40.89083,
      -18.755
    ]
  }
}