{
  "type": "Feature",
  "properties": {
    "name": "Colatina",
    "country": "BR",
    "subdivision": "08",
    "timezone": "America/Sao_Paulo"
  },
  "geometry": {
    "type": "Point",
    "coordinates": [
      -40.63056,
      -19.53944
    ]
  }
}