{
  "type": "Feature",
  "properties": {
    "name": "Conceição do Castelo",
    "country": "BR",
    "subdivision": "08",
    "timezone": "America/Sao_Paulo"
  },
  "geometry": {
    "type": "Point",
    "coordinates": [
      -41.24389,
      -20.36833
    ]
  }
}