{
  "type": "Feature",
  "properties": {
    "name": "Marechal Floriano",
    "country": "BR",
    "subdivision": "08",
    "timezone": "America/Sao_Paulo"
  },
  "geometry": {
    "type": "Point",
    "coordinates": [
      -40.68306,
      -20.41278
    ]
  }
}