{
  "type": "Feature",
  "properties": {
    "name": "Santa Leopoldina",
    "country": "BR",
    "subdivision": "08",
    "timezone": "America/Sao_Paulo"
  },
  "geometry": {
    "type": "Point",
    "coordinates": [
      -40.52972,
      -20.10056
    ]
  }
}