{
  "type": "Feature",
  "properties": {
    "name": "São José do Calçado",
    "country": "BR",
    "subdivision": "08",
    "timezone": "America/Sao_Paulo"
  },
  "geometry": {
    "type": "Point",
    "coordinates": [
      -41.65444,
      -21.02528
    ]
  }
}