{
  "type": "Feature",
  "properties": {
    "name": "Vila Velha",
    "country": "BR",
    "subdivision": "08",
    "timezone": "America/Sao_Paulo"
  },
  "geometry": {
    "type": "Point",
    "coordinates": [
      -40.2925,
      -20.32972
    ]
  }
}