{
  "type": "Feature",
  "properties": {
    "name": "Qasr Abu Hadi",
    "country": "LY",
    "subdivision": "76",
    "timezone": "Africa/Tripoli"
  },
  "geometry": {
    "type": "Point",
    "coordinates": [
      16.65905,
      31.05926
    ]
  }
}