{
  "type": "Feature",
  "properties": {
    "name": "Burhaniye",
    "country": "TR",
    "subdivision": "10",
    "timezone": "Europe/Istanbul"
  },
  "geometry": {
    "type": "Point",
    "coordinates": [
      26.97269,
      39.50041
    ]
  }
}