{
  "type": "Feature",
  "properties": {
    "name": "Gömeç",
    "country": "TR",
    "subdivision": "10",
    "timezone": "Europe/Istanbul"
  },
  "geometry": {
    "type": "Point",
    "coordinates": [
      26.84127,
      39.39016
    ]
  }
}