{
  "type": "Feature",
  "properties": {
    "name": "Savaştepe",
    "country": "TR",
    "subdivision": "10",
    "timezone": "Europe/Istanbul"
  },
  "geometry": {
    "type": "Point",
    "coordinates": [
      27.65612,
      39.38319
    ]
  }
}