{
  "type": "Feature",
  "properties": {
    "name": "Gavarr",
    "country": "AM",
    "subdivision": "04",
    "timezone": "Asia/Yerevan"
  },
  "geometry": {
    "type": "Point",
    "coordinates": [
      45.12386,
      40.35398
    ]
  }
}