{
  "type": "Feature",
  "properties": {
    "name": "Sarukhan",
    "country": "AM",
    "subdivision": "04",
    "timezone": "Asia/Yerevan"
  },
  "geometry": {
    "type": "Point",
    "coordinates": [
      45.13068,
      40.29169
    ]
  }
}