{
  "type": "Feature",
  "properties": {
    "name": "Rwamagana",
    "country": "RW",
    "subdivision": "11",
    "timezone": "Africa/Kigali"
  },
  "geometry": {
    "type": "Point",
    "coordinates": [
      30.4347,
      -1.9487
    ]
  }
}