{
  "type": "Feature",
  "properties": {
    "name": "Pesche",
    "country": "IT",
    "subdivision": "11",
    "timezone": "Europe/Rome"
  },
  "geometry": {
    "type": "Point",
    "coordinates": [
      14.2762,
      41.60552
    ]
  }
}