{
  "type": "Feature",
  "properties": {
    "name": "Rocchetta a Volturno",
    "country": "IT",
    "subdivision": "11",
    "timezone": "Europe/Rome"
  },
  "geometry": {
    "type": "Point",
    "coordinates": [
      14.08902,
      41.62582
    ]
  }
}