{
  "type": "Feature",
  "properties": {
    "name": "Vinchiaturo",
    "country": "IT",
    "subdivision": "11",
    "timezone": "Europe/Rome"
  },
  "geometry": {
    "type": "Point",
    "coordinates": [
      14.592,
      41.49282
    ]
  }
}