{
  "type": "Feature",
  "properties": {
    "name": "Kashihara-shi",
    "country": "JP",
    "subdivision": "28",
    "timezone": "Asia/Tokyo"
  },
  "geometry": {
    "type": "Point",
    "coordinates": [
      135.7929,
      34.50896
    ]
  }
}