{
  "type": "Feature",
  "properties": {
    "name": "Chichica",
    "country": "PA",
    "subdivision": "12",
    "timezone": "America/Panama"
  },
  "geometry": {
    "type": "Point",
    "coordinates": [
      -81.66715,
      8.36446
    ]
  }
}