{
  "type": "Feature",
  "properties": {
    "name": "Holetown",
    "country": "BB",
    "subdivision": "04",
    "timezone": "America/Barbados"
  },
  "geometry": {
    "type": "Point",
    "coordinates": [
      -59.63808,
      13.18672
    ]
  }
}