{
  "type": "Feature",
  "properties": {
    "name": "Astrea",
    "country": "CO",
    "subdivision": "10",
    "timezone": "America/Bogota"
  },
  "geometry": {
    "type": "Point",
    "coordinates": [
      -73.97591,
      9.49828
    ]
  }
}