{
  "type": "Feature",
  "properties": {
    "name": "San Alberto",
    "country": "CO",
    "subdivision": "10",
    "timezone": "America/Bogota"
  },
  "geometry": {
    "type": "Point",
    "coordinates": [
      -73.3922,
      7.76107
    ]
  }
}