{
  "type": "Feature",
  "properties": {
    "name": "Fuwwah",
    "country": "EG",
    "subdivision": "21",
    "timezone": "Africa/Cairo"
  },
  "geometry": {
    "type": "Point",
    "coordinates": [
      30.54908,
      31.20365
    ]
  }
}