{
  "type": "Feature",
  "properties": {
    "name": "Munshāt ‘Alī Āghā",
    "country": "EG",
    "subdivision": "21",
    "timezone": "Africa/Cairo"
  },
  "geometry": {
    "type": "Point",
    "coordinates": [
      30.70177,
      31.15791
    ]
  }
}