{
  "type": "Feature",
  "properties": {
    "name": "Agârbiciu",
    "country": "RO",
    "subdivision": "33",
    "timezone": "Europe/Bucharest"
  },
  "geometry": {
    "type": "Point",
    "coordinates": [
      24.19386,
      46.06764
    ]
  }
}