{
  "type": "Feature",
  "properties": {
    "name": "Alămor",
    "country": "RO",
    "subdivision": "33",
    "timezone": "Europe/Bucharest"
  },
  "geometry": {
    "type": "Point",
    "coordinates": [
      23.9937,
      45.93003
    ]
  }
}