{
  "type": "Feature",
  "properties": {
    "name": "Biertan",
    "country": "RO",
    "subdivision": "33",
    "timezone": "Europe/Bucharest"
  },
  "geometry": {
    "type": "Point",
    "coordinates": [
      24.51667,
      46.13333
    ]
  }
}