{
  "type": "Feature",
  "properties": {
    "name": "Gura Râului",
    "country": "RO",
    "subdivision": "33",
    "timezone": "Europe/Bucharest"
  },
  "geometry": {
    "type": "Point",
    "coordinates": [
      23.98333,
      45.73333
    ]
  }
}