{
  "type": "Feature",
  "properties": {
    "name": "Hoghilag",
    "country": "RO",
    "subdivision": "33",
    "timezone": "Europe/Bucharest"
  },
  "geometry": {
    "type": "Point",
    "coordinates": [
      24.61667,
      46.23333
    ]
  }
}