{
  "type": "Feature",
  "properties": {
    "name": "Mediaş",
    "country": "RO",
    "subdivision": "33",
    "timezone": "Europe/Bucharest"
  },
  "geometry": {
    "type": "Point",
    "coordinates": [
      24.35,
      46.16667
    ]
  }
}