{
  "type": "Feature",
  "properties": {
    "name": "Nou",
    "country": "RO",
    "subdivision": "33",
    "timezone": "Europe/Bucharest"
  },
  "geometry": {
    "type": "Point",
    "coordinates": [
      24.28333,
      45.83333
    ]
  }
}