{
  "type": "Feature",
  "properties": {
    "name": "Orlat",
    "country": "RO",
    "subdivision": "33",
    "timezone": "Europe/Bucharest"
  },
  "geometry": {
    "type": "Point",
    "coordinates": [
      23.96667,
      45.75
    ]
  }
}