{
  "type": "Feature",
  "properties": {
    "name": "Sadu",
    "country": "RO",
    "subdivision": "33",
    "timezone": "Europe/Bucharest"
  },
  "geometry": {
    "type": "Point",
    "coordinates": [
      24.18333,
      45.66667
    ]
  }
}