{
  "type": "Feature",
  "properties": {
    "name": "Sălişte",
    "country": "RO",
    "subdivision": "33",
    "timezone": "Europe/Bucharest"
  },
  "geometry": {
    "type": "Point",
    "coordinates": [
      23.88677,
      45.79633
    ]
  }
}