{
  "type": "Feature",
  "properties": {
    "name": "Şeíca Mare",
    "country": "RO",
    "subdivision": "33",
    "timezone": "Europe/Bucharest"
  },
  "geometry": {
    "type": "Point",
    "coordinates": [
      24.15,
      46.01667
    ]
  }
}