{
  "type": "Feature",
  "properties": {
    "name": "Msaken",
    "country": "TN",
    "subdivision": "23",
    "timezone": "Africa/Tunis"
  },
  "geometry": {
    "type": "Point",
    "coordinates": [
      10.58082,
      35.72917
    ]
  }
}