{
  "type": "Feature",
  "properties": {
    "name": "Sidi Bou Ali",
    "country": "TN",
    "subdivision": "23",
    "timezone": "Africa/Tunis"
  },
  "geometry": {
    "type": "Point",
    "coordinates": [
      10.47306,
      35.95667
    ]
  }
}