{
  "type": "Feature",
  "properties": {
    "name": "Beverwijk",
    "country": "NL",
    "subdivision": "07",
    "timezone": "Europe/Amsterdam"
  },
  "geometry": {
    "type": "Point",
    "coordinates": [
      4.65694,
      52.48333
    ]
  }
}