{
  "type": "Feature",
  "properties": {
    "name": "Blaricum",
    "country": "NL",
    "subdivision": "07",
    "timezone": "Europe/Amsterdam"
  },
  "geometry": {
    "type": "Point",
    "coordinates": [
      5.24167,
      52.2725
    ]
  }
}