{
  "type": "Feature",
  "properties": {
    "name": "Bloemendaal",
    "country": "NL",
    "subdivision": "07",
    "timezone": "Europe/Amsterdam"
  },
  "geometry": {
    "type": "Point",
    "coordinates": [
      4.62222,
      52.4025
    ]
  }
}