{
  "type": "Feature",
  "properties": {
    "name": "De Noord",
    "country": "NL",
    "subdivision": "07",
    "timezone": "Europe/Amsterdam"
  },
  "geometry": {
    "type": "Point",
    "coordinates": [
      4.85139,
      52.7075
    ]
  }
}