{
  "type": "Feature",
  "properties": {
    "name": "Diemen",
    "country": "NL",
    "subdivision": "07",
    "timezone": "Europe/Amsterdam"
  },
  "geometry": {
    "type": "Point",
    "coordinates": [
      4.96256,
      52.33964
    ]
  }
}