{
  "type": "Feature",
  "properties": {
    "name": "Egmond-Binnen",
    "country": "NL",
    "subdivision": "07",
    "timezone": "Europe/Amsterdam"
  },
  "geometry": {
    "type": "Point",
    "coordinates": [
      4.65556,
      52.59583
    ]
  }
}