{
  "type": "Feature",
  "properties": {
    "name": "Enkhuizen",
    "country": "NL",
    "subdivision": "07",
    "timezone": "Europe/Amsterdam"
  },
  "geometry": {
    "type": "Point",
    "coordinates": [
      5.29167,
      52.70333
    ]
  }
}