{
  "type": "Feature",
  "properties": {
    "name": "IJmuiden",
    "country": "NL",
    "subdivision": "07",
    "timezone": "Europe/Amsterdam"
  },
  "geometry": {
    "type": "Point",
    "coordinates": [
      4.61048,
      52.4603
    ]
  }
}