{
  "type": "Feature",
  "properties": {
    "name": "Kudelstaart",
    "country": "NL",
    "subdivision": "07",
    "timezone": "Europe/Amsterdam"
  },
  "geometry": {
    "type": "Point",
    "coordinates": [
      4.75139,
      52.23417
    ]
  }
}