{
  "type": "Feature",
  "properties": {
    "name": "Monnickendam",
    "country": "NL",
    "subdivision": "07",
    "timezone": "Europe/Amsterdam"
  },
  "geometry": {
    "type": "Point",
    "coordinates": [
      5.0375,
      52.45833
    ]
  }
}