{
  "type": "Feature",
  "properties": {
    "name": "Oosteinde",
    "country": "NL",
    "subdivision": "07",
    "timezone": "Europe/Amsterdam"
  },
  "geometry": {
    "type": "Point",
    "coordinates": [
      4.79583,
      52.27917
    ]
  }
}