{
  "type": "Feature",
  "properties": {
    "name": "Opmeer",
    "country": "NL",
    "subdivision": "07",
    "timezone": "Europe/Amsterdam"
  },
  "geometry": {
    "type": "Point",
    "coordinates": [
      4.94444,
      52.70667
    ]
  }
}