{
  "type": "Feature",
  "properties": {
    "name": "Oud-Loosdrecht",
    "country": "NL",
    "subdivision": "07",
    "timezone": "Europe/Amsterdam"
  },
  "geometry": {
    "type": "Point",
    "coordinates": [
      5.08056,
      52.20667
    ]
  }
}