{
  "type": "Feature",
  "properties": {
    "name": "Sint Pancras",
    "country": "NL",
    "subdivision": "07",
    "timezone": "Europe/Amsterdam"
  },
  "geometry": {
    "type": "Point",
    "coordinates": [
      4.78333,
      52.66
    ]
  }
}