{
  "type": "Feature",
  "properties": {
    "name": "Slootdorp",
    "country": "NL",
    "subdivision": "07",
    "timezone": "Europe/Amsterdam"
  },
  "geometry": {
    "type": "Point",
    "coordinates": [
      4.97222,
      52.8425
    ]
  }
}