{
  "type": "Feature",
  "properties": {
    "name": "Spierdijk",
    "country": "NL",
    "subdivision": "07",
    "timezone": "Europe/Amsterdam"
  },
  "geometry": {
    "type": "Point",
    "coordinates": [
      4.94306,
      52.65083
    ]
  }
}