{
  "type": "Feature",
  "properties": {
    "name": "Velsen-Zuid",
    "country": "NL",
    "subdivision": "07",
    "timezone": "Europe/Amsterdam"
  },
  "geometry": {
    "type": "Point",
    "coordinates": [
      4.65,
      52.46
    ]
  }
}