{
  "type": "Feature",
  "properties": {
    "name": "Wijk aan Zee",
    "country": "NL",
    "subdivision": "07",
    "timezone": "Europe/Amsterdam"
  },
  "geometry": {
    "type": "Point",
    "coordinates": [
      4.59409,
      52.4936
    ]
  }
}