{
  "type": "Feature",
  "properties": {
    "name": "Zandvoort",
    "country": "NL",
    "subdivision": "07",
    "timezone": "Europe/Amsterdam"
  },
  "geometry": {
    "type": "Point",
    "coordinates": [
      4.53306,
      52.37125
    ]
  }
}