{
  "type": "Feature",
  "properties": {
    "name": "Zwaanshoek",
    "country": "NL",
    "subdivision": "07",
    "timezone": "Europe/Amsterdam"
  },
  "geometry": {
    "type": "Point",
    "coordinates": [
      4.61667,
      52.3125
    ]
  }
}