{
  "type": "Feature",
  "properties": {
    "name": "Bankim",
    "country": "CM",
    "subdivision": "10",
    "timezone": "Africa/Douala"
  },
  "geometry": {
    "type": "Point",
    "coordinates": [
      11.4905,
      6.08303
    ]
  }
}