{
  "type": "Feature",
  "properties": {
    "name": "Banyo",
    "country": "CM",
    "subdivision": "10",
    "timezone": "Africa/Douala"
  },
  "geometry": {
    "type": "Point",
    "coordinates": [
      11.81667,
      6.75
    ]
  }
}