{
  "type": "Feature",
  "properties": {
    "name": "Tibati",
    "country": "CM",
    "subdivision": "10",
    "timezone": "Africa/Douala"
  },
  "geometry": {
    "type": "Point",
    "coordinates": [
      12.62843,
      6.46504
    ]
  }
}