{
  "type": "Feature",
  "properties": {
    "name": "Chanthaburi",
    "country": "TH",
    "subdivision": "48",
    "timezone": "Asia/Bangkok"
  },
  "geometry": {
    "type": "Point",
    "coordinates": [
      102.10447,
      12.60961
    ]
  }
}