{
  "type": "Feature",
  "properties": {
    "name": "Amlapura",
    "country": "ID",
    "subdivision": "02",
    "timezone": "Asia/Makassar"
  },
  "geometry": {
    "type": "Point",
    "coordinates": [
      115.61667,
      -8.45
    ]
  }
}