{
  "type": "Feature",
  "properties": {
    "name": "Denpasar",
    "country": "ID",
    "subdivision": "02",
    "timezone": "Asia/Makassar"
  },
  "geometry": {
    "type": "Point",
    "coordinates": [
      115.21667,
      -8.65
    ]
  }
}