{
  "type": "Feature",
  "properties": {
    "name": "Jimbaran",
    "country": "ID",
    "subdivision": "02",
    "timezone": "Asia/Makassar"
  },
  "geometry": {
    "type": "Point",
    "coordinates": [
      115.16006,
      -8.79093
    ]
  }
}