{
  "type": "Feature",
  "properties": {
    "name": "Lovina",
    "country": "ID",
    "subdivision": "02",
    "timezone": "Asia/Makassar"
  },
  "geometry": {
    "type": "Point",
    "coordinates": [
      115.03999,
      -8.14927
    ]
  }
}