{
  "type": "Feature",
  "properties": {
    "name": "Nusa Dua",
    "country": "ID",
    "subdivision": "02",
    "timezone": "Asia/Makassar"
  },
  "geometry": {
    "type": "Point",
    "coordinates": [
      115.23341,
      -8.80047
    ]
  }
}