{
  "type": "Feature",
  "properties": {
    "name": "Ozurgeti",
    "country": "GE",
    "subdivision": "65",
    "timezone": "Asia/Tbilisi"
  },
  "geometry": {
    "type": "Point",
    "coordinates": [
      42.00682,
      41.92442
    ]
  }
}