{
  "type": "Feature",
  "properties": {
    "name": "Baharly",
    "country": "TM",
    "subdivision": "01",
    "timezone": "Asia/Ashgabat"
  },
  "geometry": {
    "type": "Point",
    "coordinates": [
      57.43158,
      38.43624
    ]
  }
}