{
  "type": "Feature",
  "properties": {
    "name": "Ghat",
    "country": "LY",
    "subdivision": "71",
    "timezone": "Africa/Tripoli"
  },
  "geometry": {
    "type": "Point",
    "coordinates": [
      10.18003,
      24.96334
    ]
  }
}