{
  "type": "Feature",
  "properties": {
    "name": "Gurupi",
    "country": "BR",
    "subdivision": "31",
    "timezone": "America/Araguaina"
  },
  "geometry": {
    "type": "Point",
    "coordinates": [
      -49.06861,
      -11.72917
    ]
  }
}