{
  "type": "Feature",
  "properties": {
    "name": "Orlinoye",
    "country": "UA",
    "subdivision": "20",
    "timezone": "Europe/Simferopol"
  },
  "geometry": {
    "type": "Point",
    "coordinates": [
      33.77588,
      44.44685
    ]
  }
}