{
  "type": "Feature",
  "properties": {
    "name": "Verkhnesadovoye",
    "country": "UA",
    "subdivision": "20",
    "timezone": "Europe/Simferopol"
  },
  "geometry": {
    "type": "Point",
    "coordinates": [
      33.70207,
      44.68932
    ]
  }
}