{
  "type": "Feature",
  "properties": {
    "name": "Tanga",
    "country": "TZ",
    "subdivision": "18",
    "timezone": "Africa/Dar_es_Salaam"
  },
  "geometry": {
    "type": "Point",
    "coordinates": [
      39.09875,
      -5.06893
    ]
  }
}