{
  "type": "Feature",
  "properties": {
    "name": "Mers el Kebir",
    "country": "DZ",
    "subdivision": "09",
    "timezone": "Africa/Algiers"
  },
  "geometry": {
    "type": "Point",
    "coordinates": [
      -0.7081,
      35.7279
    ]
  }
}