{
  "type": "Feature",
  "properties": {
    "name": "Chodov",
    "country": "CZ",
    "subdivision": "81",
    "timezone": "Europe/Prague"
  },
  "geometry": {
    "type": "Point",
    "coordinates": [
      12.74551,
      50.24018
    ]
  }
}