{
  "type": "Feature",
  "properties": {
    "name": "Hazlov",
    "country": "CZ",
    "subdivision": "81",
    "timezone": "Europe/Prague"
  },
  "geometry": {
    "type": "Point",
    "coordinates": [
      12.27238,
      50.15634
    ]
  }
}