{
  "type": "Feature",
  "properties": {
    "name": "Lázně Kynžvart",
    "country": "CZ",
    "subdivision": "81",
    "timezone": "Europe/Prague"
  },
  "geometry": {
    "type": "Point",
    "coordinates": [
      12.62474,
      50.01058
    ]
  }
}