{
  "type": "Feature",
  "properties": {
    "name": "Mariánské Lázně",
    "country": "CZ",
    "subdivision": "81",
    "timezone": "Europe/Prague"
  },
  "geometry": {
    "type": "Point",
    "coordinates": [
      12.70118,
      49.96459
    ]
  }
}