{
  "type": "Feature",
  "properties": {
    "name": "Skalná",
    "country": "CZ",
    "subdivision": "81",
    "timezone": "Europe/Prague"
  },
  "geometry": {
    "type": "Point",
    "coordinates": [
      12.36144,
      50.1703
    ]
  }
}