{
  "type": "Feature",
  "properties": {
    "name": "Spanish Wells",
    "country": "BS",
    "subdivision": "53",
    "timezone": "America/Nassau"
  },
  "geometry": {
    "type": "Point",
    "coordinates": [
      -76.76405,
      25.54717
    ]
  }
}