{
  "type": "Feature",
  "properties": {
    "name": "LiepÄja",
    "country": "LV",
    "subdivision": "16",
    "timezone": "Europe/Riga"
  },
  "geometry": {
    "type": "Point",
    "coordinates": [
      21.01085,
      56.50474
    ]
  }
}