{
  "type": "Feature",
  "properties": {
    "name": "Kabare",
    "country": "CD",
    "subdivision": "12",
    "timezone": "Africa/Lubumbashi"
  },
  "geometry": {
    "type": "Point",
    "coordinates": [
      28.79081,
      -2.49682
    ]
  }
}