{
  "type": "Feature",
  "properties": {
    "name": "Borisoglebsk",
    "country": "RU",
    "subdivision": "86",
    "timezone": "Europe/Moscow"
  },
  "geometry": {
    "type": "Point",
    "coordinates": [
      42.08494,
      51.36713
    ]
  }
}