{
  "type": "Feature",
  "properties": {
    "name": "Devitsa",
    "country": "RU",
    "subdivision": "86",
    "timezone": "Europe/Moscow"
  },
  "geometry": {
    "type": "Point",
    "coordinates": [
      38.95607,
      51.63505
    ]
  }
}