{
  "type": "Feature",
  "properties": {
    "name": "Drakino",
    "country": "RU",
    "subdivision": "86",
    "timezone": "Europe/Moscow"
  },
  "geometry": {
    "type": "Point",
    "coordinates": [
      39.40215,
      51.13898
    ]
  }
}