{
  "type": "Feature",
  "properties": {
    "name": "Ertil’",
    "country": "RU",
    "subdivision": "86",
    "timezone": "Europe/Moscow"
  },
  "geometry": {
    "type": "Point",
    "coordinates": [
      40.80556,
      51.84056
    ]
  }
}