{
  "type": "Feature",
  "properties": {
    "name": "Gribanovskiy",
    "country": "RU",
    "subdivision": "86",
    "timezone": "Europe/Moscow"
  },
  "geometry": {
    "type": "Point",
    "coordinates": [
      41.97637,
      51.45792
    ]
  }
}