{
  "type": "Feature",
  "properties": {
    "name": "Imeni Pervogo Maya",
    "country": "RU",
    "subdivision": "86",
    "timezone": "Europe/Moscow"
  },
  "geometry": {
    "type": "Point",
    "coordinates": [
      39.5919,
      50.88997
    ]
  }
}