{
  "type": "Feature",
  "properties": {
    "name": "Novovoronezh",
    "country": "RU",
    "subdivision": "86",
    "timezone": "Europe/Moscow"
  },
  "geometry": {
    "type": "Point",
    "coordinates": [
      39.21732,
      51.30719
    ]
  }
}