{
  "type": "Feature",
  "properties": {
    "name": "Novozhivotinnoye",
    "country": "RU",
    "subdivision": "86",
    "timezone": "Europe/Moscow"
  },
  "geometry": {
    "type": "Point",
    "coordinates": [
      39.1753,
      51.8853
    ]
  }
}