{
  "type": "Feature",
  "properties": {
    "name": "Ostrogozhsk",
    "country": "RU",
    "subdivision": "86",
    "timezone": "Europe/Moscow"
  },
  "geometry": {
    "type": "Point",
    "coordinates": [
      39.07561,
      50.8664
    ]
  }
}