{
  "type": "Feature",
  "properties": {
    "name": "Ramon’",
    "country": "RU",
    "subdivision": "86",
    "timezone": "Europe/Moscow"
  },
  "geometry": {
    "type": "Point",
    "coordinates": [
      39.3337,
      51.9051
    ]
  }
}