{
  "type": "Feature",
  "properties": {
    "name": "Volya",
    "country": "RU",
    "subdivision": "86",
    "timezone": "Europe/Moscow"
  },
  "geometry": {
    "type": "Point",
    "coordinates": [
      39.5359,
      51.7696
    ]
  }
}