{
  "type": "Feature",
  "properties": {
    "name": "Zemlyansk",
    "country": "RU",
    "subdivision": "86",
    "timezone": "Europe/Moscow"
  },
  "geometry": {
    "type": "Point",
    "coordinates": [
      38.7334,
      51.9041
    ]
  }
}