{
  "type": "Feature",
  "properties": {
    "name": "Kaya",
    "country": "BF",
    "subdivision": "05",
    "timezone": "Africa/Ouagadougou"
  },
  "geometry": {
    "type": "Point",
    "coordinates": [
      -1.08444,
      13.09167
    ]
  }
}