{
  "type": "Feature",
  "properties": {
    "name": "Saint-Denis",
    "country": "RE",
    "subdivision": "RE",
    "timezone": "Indian/Reunion"
  },
  "geometry": {
    "type": "Point",
    "coordinates": [
      55.4504,
      -20.88231
    ]
  }
}