{
  "type": "Feature",
  "properties": {
    "name": "Saint-Joseph",
    "country": "RE",
    "subdivision": "RE",
    "timezone": "Indian/Reunion"
  },
  "geometry": {
    "type": "Point",
    "coordinates": [
      55.61691,
      -21.3777
    ]
  }
}