{
  "type": "Feature",
  "properties": {
    "name": "Zuwārah",
    "country": "LY",
    "subdivision": "67",
    "timezone": "Africa/Tripoli"
  },
  "geometry": {
    "type": "Point",
    "coordinates": [
      12.08199,
      32.9312
    ]
  }
}