{
  "type": "Feature",
  "properties": {
    "name": "Coihueco",
    "country": "CL",
    "subdivision": "18",
    "timezone": "America/Santiago"
  },
  "geometry": {
    "type": "Point",
    "coordinates": [
      -71.83068,
      -36.62785
    ]
  }
}