{
  "type": "Feature",
  "properties": {
    "name": "Drochia",
    "country": "MD",
    "subdivision": "71",
    "timezone": "Europe/Chisinau"
  },
  "geometry": {
    "type": "Point",
    "coordinates": [
      27.81293,
      48.03555
    ]
  }
}