{
  "type": "Feature",
  "properties": {
    "name": "Anju",
    "country": "KP",
    "subdivision": "15",
    "timezone": "Asia/Pyongyang"
  },
  "geometry": {
    "type": "Point",
    "coordinates": [
      125.66472,
      39.61778
    ]
  }
}