{
  "type": "Feature",
  "properties": {
    "name": "Santa María Chiquimula",
    "country": "GT",
    "subdivision": "21",
    "timezone": "America/Guatemala"
  },
  "geometry": {
    "type": "Point",
    "coordinates": [
      -91.3292,
      15.02992
    ]
  }
}