{
  "type": "Feature",
  "properties": {
    "name": "Santa Lucia La Reforma",
    "country": "GT",
    "subdivision": "21",
    "timezone": "America/Guatemala"
  },
  "geometry": {
    "type": "Point",
    "coordinates": [
      -91.23619,
      15.12819
    ]
  }
}