{
  "type": "Feature",
  "properties": {
    "name": "Alcaraces",
    "country": "MX",
    "subdivision": "08",
    "timezone": "America/Mexico_City"
  },
  "geometry": {
    "type": "Point",
    "coordinates": [
      -103.57676,
      19.36433
    ]
  }
}