{
  "type": "Feature",
  "properties": {
    "name": "Livingstonia",
    "country": "MW",
    "subdivision": "N",
    "timezone": "Africa/Blantyre"
  },
  "geometry": {
    "type": "Point",
    "coordinates": [
      34.10788,
      -10.60603
    ]
  }
}