{
  "type": "Feature",
  "properties": {
    "name": "Habry",
    "country": "CZ",
    "subdivision": "80",
    "timezone": "Europe/Prague"
  },
  "geometry": {
    "type": "Point",
    "coordinates": [
      15.48486,
      49.75603
    ]
  }
}