{
  "type": "Feature",
  "properties": {
    "name": "Horní Cerekev",
    "country": "CZ",
    "subdivision": "80",
    "timezone": "Europe/Prague"
  },
  "geometry": {
    "type": "Point",
    "coordinates": [
      15.32769,
      49.32026
    ]
  }
}