{
  "type": "Feature",
  "properties": {
    "name": "Stařeč",
    "country": "CZ",
    "subdivision": "80",
    "timezone": "Europe/Prague"
  },
  "geometry": {
    "type": "Point",
    "coordinates": [
      15.82791,
      49.19783
    ]
  }
}