{
  "type": "Feature",
  "properties": {
    "name": "Vladislav",
    "country": "CZ",
    "subdivision": "80",
    "timezone": "Europe/Prague"
  },
  "geometry": {
    "type": "Point",
    "coordinates": [
      15.9883,
      49.21017
    ]
  }
}