{
  "type": "Feature",
  "properties": {
    "name": "Želetava",
    "country": "CZ",
    "subdivision": "80",
    "timezone": "Europe/Prague"
  },
  "geometry": {
    "type": "Point",
    "coordinates": [
      15.673,
      49.14187
    ]
  }
}