{
  "type": "Feature",
  "properties": {
    "name": "Benxi",
    "country": "CN",
    "subdivision": "19",
    "timezone": "Asia/Shanghai"
  },
  "geometry": {
    "type": "Point",
    "coordinates": [
      123.765,
      41.28861
    ]
  }
}