{
  "type": "Feature",
  "properties": {
    "name": "Dalianwan",
    "country": "CN",
    "subdivision": "19",
    "timezone": "Asia/Shanghai"
  },
  "geometry": {
    "type": "Point",
    "coordinates": [
      121.695,
      39.02861
    ]
  }
}