{
  "type": "Feature",
  "properties": {
    "name": "Heishan",
    "country": "CN",
    "subdivision": "19",
    "timezone": "Asia/Shanghai"
  },
  "geometry": {
    "type": "Point",
    "coordinates": [
      122.11278,
      41.68917
    ]
  }
}