{
  "type": "Feature",
  "properties": {
    "name": "Huanren",
    "country": "CN",
    "subdivision": "19",
    "timezone": "Asia/Shanghai"
  },
  "geometry": {
    "type": "Point",
    "coordinates": [
      125.36667,
      41.26472
    ]
  }
}