{
  "type": "Feature",
  "properties": {
    "name": "Linghai",
    "country": "CN",
    "subdivision": "19",
    "timezone": "Asia/Shanghai"
  },
  "geometry": {
    "type": "Point",
    "coordinates": [
      121.36667,
      41.16528
    ]
  }
}