{
  "type": "Feature",
  "properties": {
    "name": "Nantai",
    "country": "CN",
    "subdivision": "19",
    "timezone": "Asia/Shanghai"
  },
  "geometry": {
    "type": "Point",
    "coordinates": [
      122.80437,
      40.9241
    ]
  }
}