{
  "type": "Feature",
  "properties": {
    "name": "Yingkou",
    "country": "CN",
    "subdivision": "19",
    "timezone": "Asia/Shanghai"
  },
  "geometry": {
    "type": "Point",
    "coordinates": [
      122.22833,
      40.66482
    ]
  }
}