{
  "type": "Feature",
  "properties": {
    "name": "Qaxbaş",
    "country": "AZ",
    "subdivision": "39",
    "timezone": "Asia/Baku"
  },
  "geometry": {
    "type": "Point",
    "coordinates": [
      46.9646,
      41.43254
    ]
  }
}