{
  "type": "Feature",
  "properties": {
    "name": "Biandrate",
    "country": "IT",
    "subdivision": "12",
    "timezone": "Europe/Rome"
  },
  "geometry": {
    "type": "Point",
    "coordinates": [
      8.46402,
      45.45271
    ]
  }
}