{
  "type": "Feature",
  "properties": {
    "name": "Bibiana",
    "country": "IT",
    "subdivision": "12",
    "timezone": "Europe/Rome"
  },
  "geometry": {
    "type": "Point",
    "coordinates": [
      7.28822,
      44.79894
    ]
  }
}