{
  "type": "Feature",
  "properties": {
    "name": "Borgone Susa",
    "country": "IT",
    "subdivision": "12",
    "timezone": "Europe/Rome"
  },
  "geometry": {
    "type": "Point",
    "coordinates": [
      7.23641,
      45.12334
    ]
  }
}