{
  "type": "Feature",
  "properties": {
    "name": "Borgo San Dalmazzo",
    "country": "IT",
    "subdivision": "12",
    "timezone": "Europe/Rome"
  },
  "geometry": {
    "type": "Point",
    "coordinates": [
      7.4931,
      44.33785
    ]
  }
}