{
  "type": "Feature",
  "properties": {
    "name": "Busca",
    "country": "IT",
    "subdivision": "12",
    "timezone": "Europe/Rome"
  },
  "geometry": {
    "type": "Point",
    "coordinates": [
      7.47662,
      44.51625
    ]
  }
}