{
  "type": "Feature",
  "properties": {
    "name": "Buttigliera Alta",
    "country": "IT",
    "subdivision": "12",
    "timezone": "Europe/Rome"
  },
  "geometry": {
    "type": "Point",
    "coordinates": [
      7.43254,
      45.06836
    ]
  }
}