{
  "type": "Feature",
  "properties": {
    "name": "Canelli",
    "country": "IT",
    "subdivision": "12",
    "timezone": "Europe/Rome"
  },
  "geometry": {
    "type": "Point",
    "coordinates": [
      8.29282,
      44.72084
    ]
  }
}