{
  "type": "Feature",
  "properties": {
    "name": "Caramagna Piemonte",
    "country": "IT",
    "subdivision": "12",
    "timezone": "Europe/Rome"
  },
  "geometry": {
    "type": "Point",
    "coordinates": [
      7.73943,
      44.78224
    ]
  }
}