{
  "type": "Feature",
  "properties": {
    "name": "Carignano",
    "country": "IT",
    "subdivision": "12",
    "timezone": "Europe/Rome"
  },
  "geometry": {
    "type": "Point",
    "coordinates": [
      7.67253,
      44.90599
    ]
  }
}