{
  "type": "Feature",
  "properties": {
    "name": "Carmagnola",
    "country": "IT",
    "subdivision": "12",
    "timezone": "Europe/Rome"
  },
  "geometry": {
    "type": "Point",
    "coordinates": [
      7.72032,
      44.84963
    ]
  }
}