{
  "type": "Feature",
  "properties": {
    "name": "Carpignano Sesia",
    "country": "IT",
    "subdivision": "12",
    "timezone": "Europe/Rome"
  },
  "geometry": {
    "type": "Point",
    "coordinates": [
      8.41734,
      45.53341
    ]
  }
}