{
  "type": "Feature",
  "properties": {
    "name": "Castell'Alfero",
    "country": "IT",
    "subdivision": "12",
    "timezone": "Europe/Rome"
  },
  "geometry": {
    "type": "Point",
    "coordinates": [
      8.22309,
      44.98505
    ]
  }
}