{
  "type": "Feature",
  "properties": {
    "name": "Cavour",
    "country": "IT",
    "subdivision": "12",
    "timezone": "Europe/Rome"
  },
  "geometry": {
    "type": "Point",
    "coordinates": [
      7.37438,
      44.79286
    ]
  }
}