{
  "type": "Feature",
  "properties": {
    "name": "Chiusa di Pesio",
    "country": "IT",
    "subdivision": "12",
    "timezone": "Europe/Rome"
  },
  "geometry": {
    "type": "Point",
    "coordinates": [
      7.67431,
      44.32588
    ]
  }
}