{
  "type": "Feature",
  "properties": {
    "name": "Condove",
    "country": "IT",
    "subdivision": "12",
    "timezone": "Europe/Rome"
  },
  "geometry": {
    "type": "Point",
    "coordinates": [
      7.30859,
      45.11591
    ]
  }
}