{
  "type": "Feature",
  "properties": {
    "name": "Cortemilia",
    "country": "IT",
    "subdivision": "12",
    "timezone": "Europe/Rome"
  },
  "geometry": {
    "type": "Point",
    "coordinates": [
      8.19367,
      44.58044
    ]
  }
}