{
  "type": "Feature",
  "properties": {
    "name": "Crevoladossola",
    "country": "IT",
    "subdivision": "12",
    "timezone": "Europe/Rome"
  },
  "geometry": {
    "type": "Point",
    "coordinates": [
      8.29742,
      46.14858
    ]
  }
}