{
  "type": "Feature",
  "properties": {
    "name": "Cumiana",
    "country": "IT",
    "subdivision": "12",
    "timezone": "Europe/Rome"
  },
  "geometry": {
    "type": "Point",
    "coordinates": [
      7.37761,
      44.97629
    ]
  }
}