{
  "type": "Feature",
  "properties": {
    "name": "Desana",
    "country": "IT",
    "subdivision": "12",
    "timezone": "Europe/Rome"
  },
  "geometry": {
    "type": "Point",
    "coordinates": [
      8.35777,
      45.26915
    ]
  }
}