{
  "type": "Feature",
  "properties": {
    "name": "Dogliani",
    "country": "IT",
    "subdivision": "12",
    "timezone": "Europe/Rome"
  },
  "geometry": {
    "type": "Point",
    "coordinates": [
      7.9451,
      44.53326
    ]
  }
}