{
  "type": "Feature",
  "properties": {
    "name": "Frugarolo",
    "country": "IT",
    "subdivision": "12",
    "timezone": "Europe/Rome"
  },
  "geometry": {
    "type": "Point",
    "coordinates": [
      8.68165,
      44.83924
    ]
  }
}