{
  "type": "Feature",
  "properties": {
    "name": "Gabbio-Cereda-Ramate",
    "country": "IT",
    "subdivision": "12",
    "timezone": "Europe/Rome"
  },
  "geometry": {
    "type": "Point",
    "coordinates": [
      8.42113,
      45.90959
    ]
  }
}