{
  "type": "Feature",
  "properties": {
    "name": "Gargallo",
    "country": "IT",
    "subdivision": "12",
    "timezone": "Europe/Rome"
  },
  "geometry": {
    "type": "Point",
    "coordinates": [
      8.42533,
      45.72877
    ]
  }
}