{
  "type": "Feature",
  "properties": {
    "name": "Garino",
    "country": "IT",
    "subdivision": "12",
    "timezone": "Europe/Rome"
  },
  "geometry": {
    "type": "Point",
    "coordinates": [
      7.61728,
      44.97325
    ]
  }
}