{
  "type": "Feature",
  "properties": {
    "name": "Gassino Torinese",
    "country": "IT",
    "subdivision": "12",
    "timezone": "Europe/Rome"
  },
  "geometry": {
    "type": "Point",
    "coordinates": [
      7.82934,
      45.12907
    ]
  }
}