{
  "type": "Feature",
  "properties": {
    "name": "Genola",
    "country": "IT",
    "subdivision": "12",
    "timezone": "Europe/Rome"
  },
  "geometry": {
    "type": "Point",
    "coordinates": [
      7.66114,
      44.59053
    ]
  }
}