{
  "type": "Feature",
  "properties": {
    "name": "Giaveno",
    "country": "IT",
    "subdivision": "12",
    "timezone": "Europe/Rome"
  },
  "geometry": {
    "type": "Point",
    "coordinates": [
      7.34722,
      45.04435
    ]
  }
}