{
  "type": "Feature",
  "properties": {
    "name": "Lessona",
    "country": "IT",
    "subdivision": "12",
    "timezone": "Europe/Rome"
  },
  "geometry": {
    "type": "Point",
    "coordinates": [
      8.19433,
      45.58693
    ]
  }
}