{
  "type": "Feature",
  "properties": {
    "name": "Livorno Ferraris",
    "country": "IT",
    "subdivision": "12",
    "timezone": "Europe/Rome"
  },
  "geometry": {
    "type": "Point",
    "coordinates": [
      8.0778,
      45.28271
    ]
  }
}