{
  "type": "Feature",
  "properties": {
    "name": "Magliano Alpi",
    "country": "IT",
    "subdivision": "12",
    "timezone": "Europe/Rome"
  },
  "geometry": {
    "type": "Point",
    "coordinates": [
      7.81926,
      44.45808
    ]
  }
}