{
  "type": "Feature",
  "properties": {
    "name": "Mathi",
    "country": "IT",
    "subdivision": "12",
    "timezone": "Europe/Rome"
  },
  "geometry": {
    "type": "Point",
    "coordinates": [
      7.54202,
      45.25515
    ]
  }
}