{
  "type": "Feature",
  "properties": {
    "name": "Montegrosso",
    "country": "IT",
    "subdivision": "12",
    "timezone": "Europe/Rome"
  },
  "geometry": {
    "type": "Point",
    "coordinates": [
      8.23754,
      44.82065
    ]
  }
}