{
  "type": "Feature",
  "properties": {
    "name": "Narzole",
    "country": "IT",
    "subdivision": "12",
    "timezone": "Europe/Rome"
  },
  "geometry": {
    "type": "Point",
    "coordinates": [
      7.86765,
      44.59441
    ]
  }
}