{
  "type": "Feature",
  "properties": {
    "name": "Orbassano",
    "country": "IT",
    "subdivision": "12",
    "timezone": "Europe/Rome"
  },
  "geometry": {
    "type": "Point",
    "coordinates": [
      7.53813,
      45.00547
    ]
  }
}