{
  "type": "Feature",
  "properties": {
    "name": "Ormea",
    "country": "IT",
    "subdivision": "12",
    "timezone": "Europe/Rome"
  },
  "geometry": {
    "type": "Point",
    "coordinates": [
      7.91199,
      44.1487
    ]
  }
}