{
  "type": "Feature",
  "properties": {
    "name": "Oulx",
    "country": "IT",
    "subdivision": "12",
    "timezone": "Europe/Rome"
  },
  "geometry": {
    "type": "Point",
    "coordinates": [
      6.83372,
      45.03641
    ]
  }
}