{
  "type": "Feature",
  "properties": {
    "name": "Pallanzeno",
    "country": "IT",
    "subdivision": "12",
    "timezone": "Europe/Rome"
  },
  "geometry": {
    "type": "Point",
    "coordinates": [
      8.25949,
      46.04202
    ]
  }
}