{
  "type": "Feature",
  "properties": {
    "name": "Paruzzaro",
    "country": "IT",
    "subdivision": "12",
    "timezone": "Europe/Rome"
  },
  "geometry": {
    "type": "Point",
    "coordinates": [
      8.51486,
      45.74818
    ]
  }
}