{
  "type": "Feature",
  "properties": {
    "name": "Pontecurone",
    "country": "IT",
    "subdivision": "12",
    "timezone": "Europe/Rome"
  },
  "geometry": {
    "type": "Point",
    "coordinates": [
      8.93289,
      44.9588
    ]
  }
}