{
  "type": "Feature",
  "properties": {
    "name": "Priocca",
    "country": "IT",
    "subdivision": "12",
    "timezone": "Europe/Rome"
  },
  "geometry": {
    "type": "Point",
    "coordinates": [
      8.06424,
      44.78624
    ]
  }
}