{
  "type": "Feature",
  "properties": {
    "name": "Quargnento",
    "country": "IT",
    "subdivision": "12",
    "timezone": "Europe/Rome"
  },
  "geometry": {
    "type": "Point",
    "coordinates": [
      8.48821,
      44.94566
    ]
  }
}