{
  "type": "Feature",
  "properties": {
    "name": "Racconigi",
    "country": "IT",
    "subdivision": "12",
    "timezone": "Europe/Rome"
  },
  "geometry": {
    "type": "Point",
    "coordinates": [
      7.67893,
      44.76598
    ]
  }
}