{
  "type": "Feature",
  "properties": {
    "name": "Reano",
    "country": "IT",
    "subdivision": "12",
    "timezone": "Europe/Rome"
  },
  "geometry": {
    "type": "Point",
    "coordinates": [
      7.42779,
      45.05217
    ]
  }
}