{
  "type": "Feature",
  "properties": {
    "name": "Revigliasco",
    "country": "IT",
    "subdivision": "12",
    "timezone": "Europe/Rome"
  },
  "geometry": {
    "type": "Point",
    "coordinates": [
      7.73306,
      45.01589
    ]
  }
}