{
  "type": "Feature",
  "properties": {
    "name": "Roata Rossi",
    "country": "IT",
    "subdivision": "12",
    "timezone": "Europe/Rome"
  },
  "geometry": {
    "type": "Point",
    "coordinates": [
      7.52572,
      44.44383
    ]
  }
}