{
  "type": "Feature",
  "properties": {
    "name": "Rondissone",
    "country": "IT",
    "subdivision": "12",
    "timezone": "Europe/Rome"
  },
  "geometry": {
    "type": "Point",
    "coordinates": [
      7.96426,
      45.2463
    ]
  }
}