{
  "type": "Feature",
  "properties": {
    "name": "San Bernardino Verbano",
    "country": "IT",
    "subdivision": "12",
    "timezone": "Europe/Rome"
  },
  "geometry": {
    "type": "Point",
    "coordinates": [
      8.51922,
      45.95638
    ]
  }
}