{
  "type": "Feature",
  "properties": {
    "name": "San Mauro Torinese",
    "country": "IT",
    "subdivision": "12",
    "timezone": "Europe/Rome"
  },
  "geometry": {
    "type": "Point",
    "coordinates": [
      7.76803,
      45.10359
    ]
  }
}