{
  "type": "Feature",
  "properties": {
    "name": "San Giuliano Vecchio",
    "country": "IT",
    "subdivision": "12",
    "timezone": "Europe/Rome"
  },
  "geometry": {
    "type": "Point",
    "coordinates": [
      8.76057,
      44.88902
    ]
  }
}