{
  "type": "Feature",
  "properties": {
    "name": "San Raffaele Cimena",
    "country": "IT",
    "subdivision": "12",
    "timezone": "Europe/Rome"
  },
  "geometry": {
    "type": "Point",
    "coordinates": [
      7.84932,
      45.14665
    ]
  }
}