{
  "type": "Feature",
  "properties": {
    "name": "San Gillio",
    "country": "IT",
    "subdivision": "12",
    "timezone": "Europe/Rome"
  },
  "geometry": {
    "type": "Point",
    "coordinates": [
      7.53285,
      45.1405
    ]
  }
}