{
  "type": "Feature",
  "properties": {
    "name": "Santa Vittoria d'Alba",
    "country": "IT",
    "subdivision": "12",
    "timezone": "Europe/Rome"
  },
  "geometry": {
    "type": "Point",
    "coordinates": [
      7.93733,
      44.69864
    ]
  }
}