{
  "type": "Feature",
  "properties": {
    "name": "Serravalle Sesia",
    "country": "IT",
    "subdivision": "12",
    "timezone": "Europe/Rome"
  },
  "geometry": {
    "type": "Point",
    "coordinates": [
      8.3085,
      45.68485
    ]
  }
}