{
  "type": "Feature",
  "properties": {
    "name": "Sommariva del Bosco",
    "country": "IT",
    "subdivision": "12",
    "timezone": "Europe/Rome"
  },
  "geometry": {
    "type": "Point",
    "coordinates": [
      7.78177,
      44.77257
    ]
  }
}