{
  "type": "Feature",
  "properties": {
    "name": "Torrazza Piemonte",
    "country": "IT",
    "subdivision": "12",
    "timezone": "Europe/Rome"
  },
  "geometry": {
    "type": "Point",
    "coordinates": [
      7.97673,
      45.21535
    ]
  }
}