{
  "type": "Feature",
  "properties": {
    "name": "Trecate",
    "country": "IT",
    "subdivision": "12",
    "timezone": "Europe/Rome"
  },
  "geometry": {
    "type": "Point",
    "coordinates": [
      8.7364,
      45.43399
    ]
  }
}