{
  "type": "Feature",
  "properties": {
    "name": "Vercelli",
    "country": "IT",
    "subdivision": "12",
    "timezone": "Europe/Rome"
  },
  "geometry": {
    "type": "Point",
    "coordinates": [
      8.41989,
      45.32163
    ]
  }
}