{
  "type": "Feature",
  "properties": {
    "name": "Vespolate",
    "country": "IT",
    "subdivision": "12",
    "timezone": "Europe/Rome"
  },
  "geometry": {
    "type": "Point",
    "coordinates": [
      8.66878,
      45.34953
    ]
  }
}