{
  "type": "Feature",
  "properties": {
    "name": "Vezza d'Alba",
    "country": "IT",
    "subdivision": "12",
    "timezone": "Europe/Rome"
  },
  "geometry": {
    "type": "Point",
    "coordinates": [
      8.00793,
      44.76274
    ]
  }
}