{
  "type": "Feature",
  "properties": {
    "name": "Villadossola",
    "country": "IT",
    "subdivision": "12",
    "timezone": "Europe/Rome"
  },
  "geometry": {
    "type": "Point",
    "coordinates": [
      8.26709,
      46.0708
    ]
  }
}