{
  "type": "Feature",
  "properties": {
    "name": "Volvera",
    "country": "IT",
    "subdivision": "12",
    "timezone": "Europe/Rome"
  },
  "geometry": {
    "type": "Point",
    "coordinates": [
      7.51142,
      44.95484
    ]
  }
}