{
  "type": "Feature",
  "properties": {
    "name": "Arevshat",
    "country": "AM",
    "subdivision": "02",
    "timezone": "Asia/Yerevan"
  },
  "geometry": {
    "type": "Point",
    "coordinates": [
      44.54179,
      40.03963
    ]
  }
}