{
  "type": "Feature",
  "properties": {
    "name": "Mrgavet",
    "country": "AM",
    "subdivision": "02",
    "timezone": "Asia/Yerevan"
  },
  "geometry": {
    "type": "Point",
    "coordinates": [
      44.48328,
      40.02789
    ]
  }
}