{
  "type": "Feature",
  "properties": {
    "name": "Nizami",
    "country": "AM",
    "subdivision": "02",
    "timezone": "Asia/Yerevan"
  },
  "geometry": {
    "type": "Point",
    "coordinates": [
      44.4057,
      40.09168
    ]
  }
}