{
  "type": "Feature",
  "properties": {
    "name": "Shahumyan",
    "country": "AM",
    "subdivision": "02",
    "timezone": "Asia/Yerevan"
  },
  "geometry": {
    "type": "Point",
    "coordinates": [
      44.57233,
      39.94171
    ]
  }
}