{
  "type": "Feature",
  "properties": {
    "name": "Sis",
    "country": "AM",
    "subdivision": "02",
    "timezone": "Asia/Yerevan"
  },
  "geometry": {
    "type": "Point",
    "coordinates": [
      44.38892,
      40.05829
    ]
  }
}