{
  "type": "Feature",
  "properties": {
    "name": "Sisavan",
    "country": "AM",
    "subdivision": "02",
    "timezone": "Asia/Yerevan"
  },
  "geometry": {
    "type": "Point",
    "coordinates": [
      44.66721,
      39.90802
    ]
  }
}