{
  "type": "Feature",
  "properties": {
    "name": "Maliq",
    "country": "AL",
    "subdivision": "46",
    "timezone": "Europe/Tirane"
  },
  "geometry": {
    "type": "Point",
    "coordinates": [
      20.69972,
      40.70583
    ]
  }
}