{
  "type": "Feature",
  "properties": {
    "name": "Galaosiyo Shahri",
    "country": "UZ",
    "subdivision": "02",
    "timezone": "Asia/Samarkand"
  },
  "geometry": {
    "type": "Point",
    "coordinates": [
      64.44641,
      39.85721
    ]
  }
}