{
  "type": "Feature",
  "properties": {
    "name": "Romitan Shahri",
    "country": "UZ",
    "subdivision": "02",
    "timezone": "Asia/Samarkand"
  },
  "geometry": {
    "type": "Point",
    "coordinates": [
      64.37944,
      39.92944
    ]
  }
}