{
  "type": "Feature",
  "properties": {
    "name": "Gostivar",
    "country": "MK",
    "subdivision": "D4",
    "timezone": "Europe/Skopje"
  },
  "geometry": {
    "type": "Point",
    "coordinates": [
      20.90819,
      41.79601
    ]
  }
}