{
  "type": "Feature",
  "properties": {
    "name": "Viļāni",
    "country": "LV",
    "subdivision": "E8",
    "timezone": "Europe/Riga"
  },
  "geometry": {
    "type": "Point",
    "coordinates": [
      26.92449,
      56.55253
    ]
  }
}