{
  "type": "Feature",
  "properties": {
    "name": "Dunavtsi",
    "country": "BG",
    "subdivision": "63",
    "timezone": "Europe/Sofia"
  },
  "geometry": {
    "type": "Point",
    "coordinates": [
      22.82111,
      43.92111
    ]
  }
}