{
  "type": "Feature",
  "properties": {
    "name": "Ruzhintsi",
    "country": "BG",
    "subdivision": "63",
    "timezone": "Europe/Sofia"
  },
  "geometry": {
    "type": "Point",
    "coordinates": [
      22.83286,
      43.62179
    ]
  }
}