{
  "type": "Feature",
  "properties": {
    "name": "Vidin",
    "country": "BG",
    "subdivision": "63",
    "timezone": "Europe/Sofia"
  },
  "geometry": {
    "type": "Point",
    "coordinates": [
      22.88236,
      43.99159
    ]
  }
}