{
  "type": "Feature",
  "properties": {
    "name": "Nuevo Sullana",
    "country": "PE",
    "subdivision": "20",
    "timezone": "America/Lima"
  },
  "geometry": {
    "type": "Point",
    "coordinates": [
      -80.72695,
      -4.92108
    ]
  }
}