{
  "type": "Feature",
  "properties": {
    "name": "Sechura",
    "country": "PE",
    "subdivision": "20",
    "timezone": "America/Lima"
  },
  "geometry": {
    "type": "Point",
    "coordinates": [
      -80.82222,
      -5.55694
    ]
  }
}