{
  "type": "Feature",
  "properties": {
    "name": "Vice",
    "country": "PE",
    "subdivision": "20",
    "timezone": "America/Lima"
  },
  "geometry": {
    "type": "Point",
    "coordinates": [
      -80.78333,
      -5.41667
    ]
  }
}