{
  "type": "Feature",
  "properties": {
    "name": "Banī Suhaylā",
    "country": "PS",
    "subdivision": "GZ",
    "timezone": "Asia/Gaza"
  },
  "geometry": {
    "type": "Point",
    "coordinates": [
      34.32337,
      31.34337
    ]
  }
}