{
  "type": "Feature",
  "properties": {
    "name": "Jabālyā",
    "country": "PS",
    "subdivision": "GZ",
    "timezone": "Asia/Gaza"
  },
  "geometry": {
    "type": "Point",
    "coordinates": [
      34.48347,
      31.5272
    ]
  }
}