{
  "type": "Feature",
  "properties": {
    "name": "Mikhmās",
    "country": "PS",
    "subdivision": "GZ",
    "timezone": "Asia/Hebron"
  },
  "geometry": {
    "type": "Point",
    "coordinates": [
      35.27596,
      31.8721
    ]
  }
}