{
  "type": "Feature",
  "properties": {
    "name": "Bereznyaki",
    "country": "RU",
    "subdivision": "20",
    "timezone": "Asia/Irkutsk"
  },
  "geometry": {
    "type": "Point",
    "coordinates": [
      103.5851,
      56.9366
    ]
  }
}