{
  "type": "Feature",
  "properties": {
    "name": "Kachug",
    "country": "RU",
    "subdivision": "20",
    "timezone": "Asia/Irkutsk"
  },
  "geometry": {
    "type": "Point",
    "coordinates": [
      105.88167,
      53.96056
    ]
  }
}