{
  "type": "Feature",
  "properties": {
    "name": "Kotik",
    "country": "RU",
    "subdivision": "20",
    "timezone": "Asia/Irkutsk"
  },
  "geometry": {
    "type": "Point",
    "coordinates": [
      100.45395,
      54.65057
    ]
  }
}