{
  "type": "Feature",
  "properties": {
    "name": "Markovo",
    "country": "RU",
    "subdivision": "20",
    "timezone": "Asia/Irkutsk"
  },
  "geometry": {
    "type": "Point",
    "coordinates": [
      107.08806,
      57.32056
    ]
  }
}