{
  "type": "Feature",
  "properties": {
    "name": "Pad’ Mel’nichnaya",
    "country": "RU",
    "subdivision": "20",
    "timezone": "Asia/Irkutsk"
  },
  "geometry": {
    "type": "Point",
    "coordinates": [
      104.38,
      52.161
    ]
  }
}