{
  "type": "Feature",
  "properties": {
    "name": "Perfilovo",
    "country": "RU",
    "subdivision": "20",
    "timezone": "Asia/Irkutsk"
  },
  "geometry": {
    "type": "Point",
    "coordinates": [
      100.48454,
      54.41083
    ]
  }
}