{
  "type": "Feature",
  "properties": {
    "name": "Pokosnoye",
    "country": "RU",
    "subdivision": "20",
    "timezone": "Asia/Irkutsk"
  },
  "geometry": {
    "type": "Point",
    "coordinates": [
      101.05361,
      55.52583
    ]
  }
}