{
  "type": "Feature",
  "properties": {
    "name": "Sredniy",
    "country": "RU",
    "subdivision": "20",
    "timezone": "Asia/Irkutsk"
  },
  "geometry": {
    "type": "Point",
    "coordinates": [
      103.4904,
      52.8884
    ]
  }
}