{
  "type": "Feature",
  "properties": {
    "name": "Ust’-Ordynskiy",
    "country": "RU",
    "subdivision": "20",
    "timezone": "Asia/Irkutsk"
  },
  "geometry": {
    "type": "Point",
    "coordinates": [
      104.75083,
      52.805
    ]
  }
}