{
  "type": "Feature",
  "properties": {
    "name": "Vikhorevka",
    "country": "RU",
    "subdivision": "20",
    "timezone": "Asia/Irkutsk"
  },
  "geometry": {
    "type": "Point",
    "coordinates": [
      101.17767,
      56.12128
    ]
  }
}