{
  "type": "Feature",
  "properties": {
    "name": "Voznesenskiy",
    "country": "RU",
    "subdivision": "20",
    "timezone": "Asia/Irkutsk"
  },
  "geometry": {
    "type": "Point",
    "coordinates": [
      99.1031,
      54.8968
    ]
  }
}