{
  "type": "Feature",
  "properties": {
    "name": "Yantal’",
    "country": "RU",
    "subdivision": "20",
    "timezone": "Asia/Irkutsk"
  },
  "geometry": {
    "type": "Point",
    "coordinates": [
      105.2542,
      56.8471
    ]
  }
}