{
  "type": "Feature",
  "properties": {
    "name": "Zheleznodorozhnyy",
    "country": "RU",
    "subdivision": "20",
    "timezone": "Asia/Irkutsk"
  },
  "geometry": {
    "type": "Point",
    "coordinates": [
      102.77838,
      57.90525
    ]
  }
}