{
  "type": "Feature",
  "properties": {
    "name": "Zhigalovo",
    "country": "RU",
    "subdivision": "20",
    "timezone": "Asia/Irkutsk"
  },
  "geometry": {
    "type": "Point",
    "coordinates": [
      105.15808,
      54.81061
    ]
  }
}