{
  "type": "Feature",
  "properties": {
    "name": "Mingelchaur",
    "country": "AZ",
    "subdivision": "33",
    "timezone": "Asia/Baku"
  },
  "geometry": {
    "type": "Point",
    "coordinates": [
      47.05953,
      40.76395
    ]
  }
}