{
  "type": "Feature",
  "properties": {
    "name": "Maunabo",
    "country": "PR",
    "subdivision": "095",
    "timezone": "America/Puerto_Rico"
  },
  "geometry": {
    "type": "Point",
    "coordinates": [
      -65.89933,
      18.00719
    ]
  }
}