{
  "type": "Feature",
  "properties": {
    "name": "Alkhazurovo",
    "country": "RU",
    "subdivision": "12",
    "timezone": "Europe/Moscow"
  },
  "geometry": {
    "type": "Point",
    "coordinates": [
      45.65134,
      43.0639
    ]
  }
}