{
  "type": "Feature",
  "properties": {
    "name": "Argun",
    "country": "RU",
    "subdivision": "12",
    "timezone": "Europe/Moscow"
  },
  "geometry": {
    "type": "Point",
    "coordinates": [
      45.87454,
      43.29713
    ]
  }
}