{
  "type": "Feature",
  "properties": {
    "name": "Gekhi",
    "country": "RU",
    "subdivision": "12",
    "timezone": "Europe/Moscow"
  },
  "geometry": {
    "type": "Point",
    "coordinates": [
      45.47238,
      43.16354
    ]
  }
}