{
  "type": "Feature",
  "properties": {
    "name": "Gerzel’-Aul",
    "country": "RU",
    "subdivision": "12",
    "timezone": "Europe/Moscow"
  },
  "geometry": {
    "type": "Point",
    "coordinates": [
      46.40249,
      43.24728
    ]
  }
}