{
  "type": "Feature",
  "properties": {
    "name": "Goyty",
    "country": "RU",
    "subdivision": "12",
    "timezone": "Europe/Moscow"
  },
  "geometry": {
    "type": "Point",
    "coordinates": [
      45.62278,
      43.16417
    ]
  }
}