{
  "type": "Feature",
  "properties": {
    "name": "Ishcherskaya",
    "country": "RU",
    "subdivision": "12",
    "timezone": "Europe/Moscow"
  },
  "geometry": {
    "type": "Point",
    "coordinates": [
      45.13371,
      43.71359
    ]
  }
}