{
  "type": "Feature",
  "properties": {
    "name": "Khambi-Irze",
    "country": "RU",
    "subdivision": "12",
    "timezone": "Europe/Moscow"
  },
  "geometry": {
    "type": "Point",
    "coordinates": [
      45.45302,
      43.23502
    ]
  }
}