{
  "type": "Feature",
  "properties": {
    "name": "Martan-Chu",
    "country": "RU",
    "subdivision": "12",
    "timezone": "Europe/Moscow"
  },
  "geometry": {
    "type": "Point",
    "coordinates": [
      45.56217,
      43.06366
    ]
  }
}