{
  "type": "Feature",
  "properties": {
    "name": "Oyskhara",
    "country": "RU",
    "subdivision": "12",
    "timezone": "Europe/Moscow"
  },
  "geometry": {
    "type": "Point",
    "coordinates": [
      46.24803,
      43.26402
    ]
  }
}