{
  "type": "Feature",
  "properties": {
    "name": "Zakan-Yurt",
    "country": "RU",
    "subdivision": "12",
    "timezone": "Europe/Moscow"
  },
  "geometry": {
    "type": "Point",
    "coordinates": [
      45.42307,
      43.26224
    ]
  }
}