{
  "type": "Feature",
  "properties": {
    "name": "Ebebiyin",
    "country": "GQ",
    "subdivision": "07",
    "timezone": "Africa/Malabo"
  },
  "geometry": {
    "type": "Point",
    "coordinates": [
      11.33528,
      2.15106
    ]
  }
}