{
  "type": "Feature",
  "properties": {
    "name": "Buchanan",
    "country": "LR",
    "subdivision": "11",
    "timezone": "Africa/Monrovia"
  },
  "geometry": {
    "type": "Point",
    "coordinates": [
      -10.04964,
      5.87693
    ]
  }
}