{
  "type": "Feature",
  "properties": {
    "name": "Ankang",
    "country": "CN",
    "subdivision": "26",
    "timezone": "Asia/Shanghai"
  },
  "geometry": {
    "type": "Point",
    "coordinates": [
      109.01722,
      32.68
    ]
  }
}