{
  "type": "Feature",
  "properties": {
    "name": "Tongchuanshi",
    "country": "CN",
    "subdivision": "26",
    "timezone": "Asia/Shanghai"
  },
  "geometry": {
    "type": "Point",
    "coordinates": [
      109.08495,
      35.07474
    ]
  }
}