{
  "type": "Feature",
  "properties": {
    "name": "Yuxia",
    "country": "CN",
    "subdivision": "26",
    "timezone": "Asia/Shanghai"
  },
  "geometry": {
    "type": "Point",
    "coordinates": [
      108.62905,
      34.06153
    ]
  }
}