{
  "type": "Feature",
  "properties": {
    "name": "Páno Polemídia",
    "country": "CY",
    "subdivision": "05",
    "timezone": "Asia/Nicosia"
  },
  "geometry": {
    "type": "Point",
    "coordinates": [
      32.99269,
      34.70559
    ]
  }
}