{
  "type": "Feature",
  "properties": {
    "name": "Pyrgos",
    "country": "CY",
    "subdivision": "05",
    "timezone": "Asia/Nicosia"
  },
  "geometry": {
    "type": "Point",
    "coordinates": [
      33.18333,
      34.74167
    ]
  }
}