{
  "type": "Feature",
  "properties": {
    "name": "Ishurdi",
    "country": "BD",
    "subdivision": "83",
    "timezone": "Asia/Dhaka"
  },
  "geometry": {
    "type": "Point",
    "coordinates": [
      89.06573,
      24.12858
    ]
  }
}