{
  "type": "Feature",
  "properties": {
    "name": "Puthia",
    "country": "BD",
    "subdivision": "83",
    "timezone": "Asia/Dhaka"
  },
  "geometry": {
    "type": "Point",
    "coordinates": [
      88.83431,
      24.36537
    ]
  }
}