{
  "type": "Feature",
  "properties": {
    "name": "Bāsawul",
    "country": "AF",
    "subdivision": "18",
    "timezone": "Asia/Kabul"
  },
  "geometry": {
    "type": "Point",
    "coordinates": [
      70.87218,
      34.24749
    ]
  }
}