{
  "type": "Feature",
  "properties": {
    "name": "Kabwe",
    "country": "ZM",
    "subdivision": "02",
    "timezone": "Africa/Lusaka"
  },
  "geometry": {
    "type": "Point",
    "coordinates": [
      28.44644,
      -14.4469
    ]
  }
}