{
  "type": "Feature",
  "properties": {
    "name": "Leticia",
    "country": "CO",
    "subdivision": "01",
    "timezone": "America/Bogota"
  },
  "geometry": {
    "type": "Point",
    "coordinates": [
      -69.94056,
      -4.21528
    ]
  }
}