{
  "type": "Feature",
  "properties": {
    "name": "Ashland",
    "country": "US",
    "subdivision": "AL",
    "timezone": "America/Chicago"
  },
  "geometry": {
    "type": "Point",
    "coordinates": [
      -85.83607,
      33.27373
    ]
  }
}