{
  "type": "Feature",
  "properties": {
    "name": "Bessemer",
    "country": "US",
    "subdivision": "AL",
    "timezone": "America/Chicago"
  },
  "geometry": {
    "type": "Point",
    "coordinates": [
      -86.95444,
      33.40178
    ]
  }
}