{
  "type": "Feature",
  "properties": {
    "name": "Blue Ridge",
    "country": "US",
    "subdivision": "AL",
    "timezone": "America/Chicago"
  },
  "geometry": {
    "type": "Point",
    "coordinates": [
      -86.19052,
      32.49264
    ]
  }
}