{
  "type": "Feature",
  "properties": {
    "name": "Brookwood",
    "country": "US",
    "subdivision": "AL",
    "timezone": "America/Chicago"
  },
  "geometry": {
    "type": "Point",
    "coordinates": [
      -87.32083,
      33.25567
    ]
  }
}