{
  "type": "Feature",
  "properties": {
    "name": "Brook Highland",
    "country": "US",
    "subdivision": "AL",
    "timezone": "America/Chicago"
  },
  "geometry": {
    "type": "Point",
    "coordinates": [
      -86.67388,
      33.43566
    ]
  }
}