{
  "type": "Feature",
  "properties": {
    "name": "Cahaba Heights",
    "country": "US",
    "subdivision": "AL",
    "timezone": "America/Chicago"
  },
  "geometry": {
    "type": "Point",
    "coordinates": [
      -86.73193,
      33.464
    ]
  }
}