{
  "type": "Feature",
  "properties": {
    "name": "Calera",
    "country": "US",
    "subdivision": "AL",
    "timezone": "America/Chicago"
  },
  "geometry": {
    "type": "Point",
    "coordinates": [
      -86.7536,
      33.1029
    ]
  }
}