{
  "type": "Feature",
  "properties": {
    "name": "Centreville",
    "country": "US",
    "subdivision": "AL",
    "timezone": "America/Chicago"
  },
  "geometry": {
    "type": "Point",
    "coordinates": [
      -87.11669,
      32.9462
    ]
  }
}