{
  "type": "Feature",
  "properties": {
    "name": "Chatom",
    "country": "US",
    "subdivision": "AL",
    "timezone": "America/Chicago"
  },
  "geometry": {
    "type": "Point",
    "coordinates": [
      -88.25446,
      31.46517
    ]
  }
}