{
  "type": "Feature",
  "properties": {
    "name": "Chelsea",
    "country": "US",
    "subdivision": "AL",
    "timezone": "America/Chicago"
  },
  "geometry": {
    "type": "Point",
    "coordinates": [
      -86.63026,
      33.34011
    ]
  }
}