{
  "type": "Feature",
  "properties": {
    "name": "Chickasaw",
    "country": "US",
    "subdivision": "AL",
    "timezone": "America/Chicago"
  },
  "geometry": {
    "type": "Point",
    "coordinates": [
      -88.07472,
      30.7638
    ]
  }
}