{
  "type": "Feature",
  "properties": {
    "name": "Danville",
    "country": "US",
    "subdivision": "AL",
    "timezone": "America/Chicago"
  },
  "geometry": {
    "type": "Point",
    "coordinates": [
      -87.08751,
      34.41454
    ]
  }
}