{
  "type": "Feature",
  "properties": {
    "name": "Dothan",
    "country": "US",
    "subdivision": "AL",
    "timezone": "America/Chicago"
  },
  "geometry": {
    "type": "Point",
    "coordinates": [
      -85.39049,
      31.22323
    ]
  }
}