{
  "type": "Feature",
  "properties": {
    "name": "East Florence",
    "country": "US",
    "subdivision": "AL",
    "timezone": "America/Chicago"
  },
  "geometry": {
    "type": "Point",
    "coordinates": [
      -87.64947,
      34.80953
    ]
  }
}