{
  "type": "Feature",
  "properties": {
    "name": "Flomaton",
    "country": "US",
    "subdivision": "AL",
    "timezone": "America/Chicago"
  },
  "geometry": {
    "type": "Point",
    "coordinates": [
      -87.26081,
      31.00018
    ]
  }
}