{
  "type": "Feature",
  "properties": {
    "name": "Fort Rucker",
    "country": "US",
    "subdivision": "AL",
    "timezone": "America/Chicago"
  },
  "geometry": {
    "type": "Point",
    "coordinates": [
      -85.71538,
      31.34282
    ]
  }
}