{
  "type": "Feature",
  "properties": {
    "name": "Geneva",
    "country": "US",
    "subdivision": "AL",
    "timezone": "America/Chicago"
  },
  "geometry": {
    "type": "Point",
    "coordinates": [
      -85.86382,
      31.03296
    ]
  }
}