{
  "type": "Feature",
  "properties": {
    "name": "Grove Hill",
    "country": "US",
    "subdivision": "AL",
    "timezone": "America/Chicago"
  },
  "geometry": {
    "type": "Point",
    "coordinates": [
      -87.77722,
      31.70877
    ]
  }
}