{
  "type": "Feature",
  "properties": {
    "name": "Harpersville",
    "country": "US",
    "subdivision": "AL",
    "timezone": "America/Chicago"
  },
  "geometry": {
    "type": "Point",
    "coordinates": [
      -86.43804,
      33.344
    ]
  }
}