{
  "type": "Feature",
  "properties": {
    "name": "Holtville",
    "country": "US",
    "subdivision": "AL",
    "timezone": "America/Chicago"
  },
  "geometry": {
    "type": "Point",
    "coordinates": [
      -86.32664,
      32.63624
    ]
  }
}