{
  "type": "Feature",
  "properties": {
    "name": "Kinsey",
    "country": "US",
    "subdivision": "AL",
    "timezone": "America/Chicago"
  },
  "geometry": {
    "type": "Point",
    "coordinates": [
      -85.34438,
      31.29906
    ]
  }
}