{
  "type": "Feature",
  "properties": {
    "name": "Lake View",
    "country": "US",
    "subdivision": "AL",
    "timezone": "America/Chicago"
  },
  "geometry": {
    "type": "Point",
    "coordinates": [
      -87.1375,
      33.28067
    ]
  }
}