{
  "type": "Feature",
  "properties": {
    "name": "Linden",
    "country": "US",
    "subdivision": "AL",
    "timezone": "America/Chicago"
  },
  "geometry": {
    "type": "Point",
    "coordinates": [
      -87.79807,
      32.30625
    ]
  }
}