{
  "type": "Feature",
  "properties": {
    "name": "Lineville",
    "country": "US",
    "subdivision": "AL",
    "timezone": "America/Chicago"
  },
  "geometry": {
    "type": "Point",
    "coordinates": [
      -85.75441,
      33.31067
    ]
  }
}