{
  "type": "Feature",
  "properties": {
    "name": "Malvern",
    "country": "US",
    "subdivision": "AL",
    "timezone": "America/Chicago"
  },
  "geometry": {
    "type": "Point",
    "coordinates": [
      -85.5191,
      31.13934
    ]
  }
}