{
  "type": "Feature",
  "properties": {
    "name": "Marion",
    "country": "US",
    "subdivision": "AL",
    "timezone": "America/Chicago"
  },
  "geometry": {
    "type": "Point",
    "coordinates": [
      -87.31917,
      32.63235
    ]
  }
}