{
  "type": "Feature",
  "properties": {
    "name": "Minor",
    "country": "US",
    "subdivision": "AL",
    "timezone": "America/Chicago"
  },
  "geometry": {
    "type": "Point",
    "coordinates": [
      -86.94055,
      33.53733
    ]
  }
}