{
  "type": "Feature",
  "properties": {
    "name": "Mobile",
    "country": "US",
    "subdivision": "AL",
    "timezone": "America/Chicago"
  },
  "geometry": {
    "type": "Point",
    "coordinates": [
      -88.04305,
      30.69436
    ]
  }
}