{
  "type": "Feature",
  "properties": {
    "name": "Monroeville",
    "country": "US",
    "subdivision": "AL",
    "timezone": "America/Chicago"
  },
  "geometry": {
    "type": "Point",
    "coordinates": [
      -87.32471,
      31.52794
    ]
  }
}