{
  "type": "Feature",
  "properties": {
    "name": "Montevallo",
    "country": "US",
    "subdivision": "AL",
    "timezone": "America/Chicago"
  },
  "geometry": {
    "type": "Point",
    "coordinates": [
      -86.86416,
      33.10067
    ]
  }
}