{
  "type": "Feature",
  "properties": {
    "name": "Oxford",
    "country": "US",
    "subdivision": "AL",
    "timezone": "America/Chicago"
  },
  "geometry": {
    "type": "Point",
    "coordinates": [
      -85.83496,
      33.61427
    ]
  }
}