{
  "type": "Feature",
  "properties": {
    "name": "Pell City",
    "country": "US",
    "subdivision": "AL",
    "timezone": "America/Chicago"
  },
  "geometry": {
    "type": "Point",
    "coordinates": [
      -86.28609,
      33.58621
    ]
  }
}