{
  "type": "Feature",
  "properties": {
    "name": "Point Clear",
    "country": "US",
    "subdivision": "AL",
    "timezone": "America/Chicago"
  },
  "geometry": {
    "type": "Point",
    "coordinates": [
      -87.91916,
      30.47408
    ]
  }
}