{
  "type": "Feature",
  "properties": {
    "name": "Rehobeth",
    "country": "US",
    "subdivision": "AL",
    "timezone": "America/Chicago"
  },
  "geometry": {
    "type": "Point",
    "coordinates": [
      -85.45271,
      31.12296
    ]
  }
}