{
  "type": "Feature",
  "properties": {
    "name": "Satsuma",
    "country": "US",
    "subdivision": "AL",
    "timezone": "America/Chicago"
  },
  "geometry": {
    "type": "Point",
    "coordinates": [
      -88.05611,
      30.85324
    ]
  }
}