{
  "type": "Feature",
  "properties": {
    "name": "Shoal Creek",
    "country": "US",
    "subdivision": "AL",
    "timezone": "America/Chicago"
  },
  "geometry": {
    "type": "Point",
    "coordinates": [
      -86.61092,
      33.43076
    ]
  }
}