{
  "type": "Feature",
  "properties": {
    "name": "Sumiton",
    "country": "US",
    "subdivision": "AL",
    "timezone": "America/Chicago"
  },
  "geometry": {
    "type": "Point",
    "coordinates": [
      -87.05,
      33.75566
    ]
  }
}