{
  "type": "Feature",
  "properties": {
    "name": "Tarrant",
    "country": "US",
    "subdivision": "AL",
    "timezone": "America/Chicago"
  },
  "geometry": {
    "type": "Point",
    "coordinates": [
      -86.77277,
      33.58344
    ]
  }
}