{
  "type": "Feature",
  "properties": {
    "name": "Troy",
    "country": "US",
    "subdivision": "AL",
    "timezone": "America/Chicago"
  },
  "geometry": {
    "type": "Point",
    "coordinates": [
      -85.96995,
      31.80877
    ]
  }
}