{
  "type": "Feature",
  "properties": {
    "name": "Trussville",
    "country": "US",
    "subdivision": "AL",
    "timezone": "America/Chicago"
  },
  "geometry": {
    "type": "Point",
    "coordinates": [
      -86.60888,
      33.61983
    ]
  }
}