{
  "type": "Feature",
  "properties": {
    "name": "Tuscaloosa",
    "country": "US",
    "subdivision": "AL",
    "timezone": "America/Chicago"
  },
  "geometry": {
    "type": "Point",
    "coordinates": [
      -87.56917,
      33.20984
    ]
  }
}