{
  "type": "Feature",
  "properties": {
    "name": "Vestavia Hills",
    "country": "US",
    "subdivision": "AL",
    "timezone": "America/Chicago"
  },
  "geometry": {
    "type": "Point",
    "coordinates": [
      -86.78777,
      33.44872
    ]
  }
}