{
  "type": "Feature",
  "properties": {
    "name": "Westover",
    "country": "US",
    "subdivision": "AL",
    "timezone": "America/Chicago"
  },
  "geometry": {
    "type": "Point",
    "coordinates": [
      -86.53582,
      33.34955
    ]
  }
}