{
  "type": "Feature",
  "properties": {
    "name": "Wilsonville",
    "country": "US",
    "subdivision": "AL",
    "timezone": "America/Chicago"
  },
  "geometry": {
    "type": "Point",
    "coordinates": [
      -86.48359,
      33.23428
    ]
  }
}