{
  "type": "Feature",
  "properties": {
    "name": "Winfield",
    "country": "US",
    "subdivision": "AL",
    "timezone": "America/Chicago"
  },
  "geometry": {
    "type": "Point",
    "coordinates": [
      -87.81725,
      33.92899
    ]
  }
}