{
  "type": "Feature",
  "properties": {
    "name": "York",
    "country": "US",
    "subdivision": "AL",
    "timezone": "America/Chicago"
  },
  "geometry": {
    "type": "Point",
    "coordinates": [
      -88.29642,
      32.48625
    ]
  }
}