{
  "type": "Feature",
  "properties": {
    "name": "Bulung’ur Shahri",
    "country": "UZ",
    "subdivision": "10",
    "timezone": "Asia/Samarkand"
  },
  "geometry": {
    "type": "Point",
    "coordinates": [
      67.27441,
      39.76003
    ]
  }
}