{
  "type": "Feature",
  "properties": {
    "name": "Dahbed",
    "country": "UZ",
    "subdivision": "10",
    "timezone": "Asia/Samarkand"
  },
  "geometry": {
    "type": "Point",
    "coordinates": [
      66.91626,
      39.7644
    ]
  }
}