{
  "type": "Feature",
  "properties": {
    "name": "Belmullet",
    "country": "IE",
    "subdivision": "C",
    "timezone": "Europe/Dublin"
  },
  "geometry": {
    "type": "Point",
    "coordinates": [
      -9.99083,
      54.225
    ]
  }
}