{
  "type": "Feature",
  "properties": {
    "name": "Gaillimh",
    "country": "IE",
    "subdivision": "C",
    "timezone": "Europe/Dublin"
  },
  "geometry": {
    "type": "Point",
    "coordinates": [
      -9.05095,
      53.27245
    ]
  }
}