{
  "type": "Feature",
  "properties": {
    "name": "Tuam",
    "country": "IE",
    "subdivision": "C",
    "timezone": "Europe/Dublin"
  },
  "geometry": {
    "type": "Point",
    "coordinates": [
      -8.85,
      53.51667
    ]
  }
}