{
  "type": "Feature",
  "properties": {
    "name": "Seia",
    "country": "PT",
    "subdivision": "11",
    "timezone": "Europe/Lisbon"
  },
  "geometry": {
    "type": "Point",
    "coordinates": [
      -7.70859,
      40.4151
    ]
  }
}