{
  "type": "Feature",
  "properties": {
    "name": "Sequeira",
    "country": "PT",
    "subdivision": "11",
    "timezone": "Europe/Lisbon"
  },
  "geometry": {
    "type": "Point",
    "coordinates": [
      -7.22594,
      40.55364
    ]
  }
}