{
  "type": "Feature",
  "properties": {
    "name": "Pointe-Noire",
    "country": "GP",
    "subdivision": "GP",
    "timezone": "America/Guadeloupe"
  },
  "geometry": {
    "type": "Point",
    "coordinates": [
      -61.78917,
      16.23218
    ]
  }
}