{
  "type": "Feature",
  "properties": {
    "name": "Adams",
    "country": "US",
    "subdivision": "WI",
    "timezone": "America/Chicago"
  },
  "geometry": {
    "type": "Point",
    "coordinates": [
      -89.81818,
      43.95608
    ]
  }
}