{
  "type": "Feature",
  "properties": {
    "name": "Albany",
    "country": "US",
    "subdivision": "WI",
    "timezone": "America/Chicago"
  },
  "geometry": {
    "type": "Point",
    "coordinates": [
      -89.43706,
      42.70778
    ]
  }
}