{
  "type": "Feature",
  "properties": {
    "name": "Allouez",
    "country": "US",
    "subdivision": "WI",
    "timezone": "America/Chicago"
  },
  "geometry": {
    "type": "Point",
    "coordinates": [
      -88.01621,
      44.47749
    ]
  }
}