{
  "type": "Feature",
  "properties": {
    "name": "Ashford",
    "country": "US",
    "subdivision": "WI",
    "timezone": "America/Chicago"
  },
  "geometry": {
    "type": "Point",
    "coordinates": [
      -88.37066,
      43.58694
    ]
  }
}