{
  "type": "Feature",
  "properties": {
    "name": "Athens",
    "country": "US",
    "subdivision": "WI",
    "timezone": "America/Chicago"
  },
  "geometry": {
    "type": "Point",
    "coordinates": [
      -90.07402,
      45.03302
    ]
  }
}