{
  "type": "Feature",
  "properties": {
    "name": "Aztalan",
    "country": "US",
    "subdivision": "WI",
    "timezone": "America/Chicago"
  },
  "geometry": {
    "type": "Point",
    "coordinates": [
      -88.86233,
      43.07278
    ]
  }
}