{
  "type": "Feature",
  "properties": {
    "name": "Barton",
    "country": "US",
    "subdivision": "WI",
    "timezone": "America/Chicago"
  },
  "geometry": {
    "type": "Point",
    "coordinates": [
      -88.18065,
      43.44361
    ]
  }
}