{
  "type": "Feature",
  "properties": {
    "name": "Berlin",
    "country": "US",
    "subdivision": "WI",
    "timezone": "America/Chicago"
  },
  "geometry": {
    "type": "Point",
    "coordinates": [
      -88.94345,
      43.96804
    ]
  }
}