{
  "type": "Feature",
  "properties": {
    "name": "Brookfield",
    "country": "US",
    "subdivision": "WI",
    "timezone": "America/Chicago"
  },
  "geometry": {
    "type": "Point",
    "coordinates": [
      -88.10648,
      43.06057
    ]
  }
}