{
  "type": "Feature",
  "properties": {
    "name": "Clintonville",
    "country": "US",
    "subdivision": "WI",
    "timezone": "America/Chicago"
  },
  "geometry": {
    "type": "Point",
    "coordinates": [
      -88.76232,
      44.62053
    ]
  }
}