{
  "type": "Feature",
  "properties": {
    "name": "Cornell",
    "country": "US",
    "subdivision": "WI",
    "timezone": "America/Chicago"
  },
  "geometry": {
    "type": "Point",
    "coordinates": [
      -91.14931,
      45.16719
    ]
  }
}