{
  "type": "Feature",
  "properties": {
    "name": "Cross Plains",
    "country": "US",
    "subdivision": "WI",
    "timezone": "America/Chicago"
  },
  "geometry": {
    "type": "Point",
    "coordinates": [
      -89.65568,
      43.11444
    ]
  }
}