{
  "type": "Feature",
  "properties": {
    "name": "Cudahy",
    "country": "US",
    "subdivision": "WI",
    "timezone": "America/Chicago"
  },
  "geometry": {
    "type": "Point",
    "coordinates": [
      -87.86147,
      42.95974
    ]
  }
}