{
  "type": "Feature",
  "properties": {
    "name": "Dodgeville",
    "country": "US",
    "subdivision": "WI",
    "timezone": "America/Chicago"
  },
  "geometry": {
    "type": "Point",
    "coordinates": [
      -90.13012,
      42.96027
    ]
  }
}