{
  "type": "Feature",
  "properties": {
    "name": "Eagle",
    "country": "US",
    "subdivision": "WI",
    "timezone": "America/Chicago"
  },
  "geometry": {
    "type": "Point",
    "coordinates": [
      -88.47427,
      42.87946
    ]
  }
}