{
  "type": "Feature",
  "properties": {
    "name": "East Troy",
    "country": "US",
    "subdivision": "WI",
    "timezone": "America/Chicago"
  },
  "geometry": {
    "type": "Point",
    "coordinates": [
      -88.4051,
      42.78529
    ]
  }
}