{
  "type": "Feature",
  "properties": {
    "name": "Elroy",
    "country": "US",
    "subdivision": "WI",
    "timezone": "America/Chicago"
  },
  "geometry": {
    "type": "Point",
    "coordinates": [
      -90.27235,
      43.7408
    ]
  }
}