{
  "type": "Feature",
  "properties": {
    "name": "Fox Point",
    "country": "US",
    "subdivision": "WI",
    "timezone": "America/Chicago"
  },
  "geometry": {
    "type": "Point",
    "coordinates": [
      -87.90175,
      43.15751
    ]
  }
}