{
  "type": "Feature",
  "properties": {
    "name": "French Island",
    "country": "US",
    "subdivision": "WI",
    "timezone": "America/Chicago"
  },
  "geometry": {
    "type": "Point",
    "coordinates": [
      -91.26042,
      43.8583
    ]
  }
}