{
  "type": "Feature",
  "properties": {
    "name": "Harrison",
    "country": "US",
    "subdivision": "WI",
    "timezone": "America/Chicago"
  },
  "geometry": {
    "type": "Point",
    "coordinates": [
      -88.33591,
      44.22776
    ]
  }
}