{
  "type": "Feature",
  "properties": {
    "name": "Hillsboro",
    "country": "US",
    "subdivision": "WI",
    "timezone": "America/Chicago"
  },
  "geometry": {
    "type": "Point",
    "coordinates": [
      -90.34402,
      43.6522
    ]
  }
}