{
  "type": "Feature",
  "properties": {
    "name": "Independence",
    "country": "US",
    "subdivision": "WI",
    "timezone": "America/Chicago"
  },
  "geometry": {
    "type": "Point",
    "coordinates": [
      -91.42043,
      44.35691
    ]
  }
}