{
  "type": "Feature",
  "properties": {
    "name": "Kenosha",
    "country": "US",
    "subdivision": "WI",
    "timezone": "America/Chicago"
  },
  "geometry": {
    "type": "Point",
    "coordinates": [
      -87.82119,
      42.58474
    ]
  }
}