{
  "type": "Feature",
  "properties": {
    "name": "Kewaunee",
    "country": "US",
    "subdivision": "WI",
    "timezone": "America/Chicago"
  },
  "geometry": {
    "type": "Point",
    "coordinates": [
      -87.50314,
      44.45833
    ]
  }
}