{
  "type": "Feature",
  "properties": {
    "name": "Lake Delton",
    "country": "US",
    "subdivision": "WI",
    "timezone": "America/Chicago"
  },
  "geometry": {
    "type": "Point",
    "coordinates": [
      -89.79374,
      43.60109
    ]
  }
}