{
  "type": "Feature",
  "properties": {
    "name": "Lake Wissota",
    "country": "US",
    "subdivision": "WI",
    "timezone": "America/Chicago"
  },
  "geometry": {
    "type": "Point",
    "coordinates": [
      -91.30099,
      44.92635
    ]
  }
}