{
  "type": "Feature",
  "properties": {
    "name": "Lodi",
    "country": "US",
    "subdivision": "WI",
    "timezone": "America/Chicago"
  },
  "geometry": {
    "type": "Point",
    "coordinates": [
      -89.52651,
      43.31388
    ]
  }
}