{
  "type": "Feature",
  "properties": {
    "name": "Mondovi",
    "country": "US",
    "subdivision": "WI",
    "timezone": "America/Chicago"
  },
  "geometry": {
    "type": "Point",
    "coordinates": [
      -91.67099,
      44.56774
    ]
  }
}