{
  "type": "Feature",
  "properties": {
    "name": "Monona",
    "country": "US",
    "subdivision": "WI",
    "timezone": "America/Chicago"
  },
  "geometry": {
    "type": "Point",
    "coordinates": [
      -89.33401,
      43.06222
    ]
  }
}