{
  "type": "Feature",
  "properties": {
    "name": "Monroe",
    "country": "US",
    "subdivision": "WI",
    "timezone": "America/Chicago"
  },
  "geometry": {
    "type": "Point",
    "coordinates": [
      -89.63845,
      42.60112
    ]
  }
}