{
  "type": "Feature",
  "properties": {
    "name": "Oakfield",
    "country": "US",
    "subdivision": "WI",
    "timezone": "America/Chicago"
  },
  "geometry": {
    "type": "Point",
    "coordinates": [
      -88.5465,
      43.6861
    ]
  }
}