{
  "type": "Feature",
  "properties": {
    "name": "Oconto Falls",
    "country": "US",
    "subdivision": "WI",
    "timezone": "America/Chicago"
  },
  "geometry": {
    "type": "Point",
    "coordinates": [
      -88.14288,
      44.87388
    ]
  }
}