{
  "type": "Feature",
  "properties": {
    "name": "Oconomowoc",
    "country": "US",
    "subdivision": "WI",
    "timezone": "America/Chicago"
  },
  "geometry": {
    "type": "Point",
    "coordinates": [
      -88.49927,
      43.11167
    ]
  }
}