{
  "type": "Feature",
  "properties": {
    "name": "Oconto",
    "country": "US",
    "subdivision": "WI",
    "timezone": "America/Chicago"
  },
  "geometry": {
    "type": "Point",
    "coordinates": [
      -87.86455,
      44.88721
    ]
  }
}