{
  "type": "Feature",
  "properties": {
    "name": "Oregon",
    "country": "US",
    "subdivision": "WI",
    "timezone": "America/Chicago"
  },
  "geometry": {
    "type": "Point",
    "coordinates": [
      -89.38456,
      42.92611
    ]
  }
}