{
  "type": "Feature",
  "properties": {
    "name": "Palmyra",
    "country": "US",
    "subdivision": "WI",
    "timezone": "America/Chicago"
  },
  "geometry": {
    "type": "Point",
    "coordinates": [
      -88.58621,
      42.87779
    ]
  }
}