{
  "type": "Feature",
  "properties": {
    "name": "Peshtigo",
    "country": "US",
    "subdivision": "WI",
    "timezone": "America/Chicago"
  },
  "geometry": {
    "type": "Point",
    "coordinates": [
      -87.74927,
      45.05443
    ]
  }
}