{
  "type": "Feature",
  "properties": {
    "name": "Prairie du Sac",
    "country": "US",
    "subdivision": "WI",
    "timezone": "America/Chicago"
  },
  "geometry": {
    "type": "Point",
    "coordinates": [
      -89.72401,
      43.28693
    ]
  }
}