{
  "type": "Feature",
  "properties": {
    "name": "Pulaski",
    "country": "US",
    "subdivision": "WI",
    "timezone": "America/Chicago"
  },
  "geometry": {
    "type": "Point",
    "coordinates": [
      -88.2426,
      44.67222
    ]
  }
}