{
  "type": "Feature",
  "properties": {
    "name": "Ripon",
    "country": "US",
    "subdivision": "WI",
    "timezone": "America/Chicago"
  },
  "geometry": {
    "type": "Point",
    "coordinates": [
      -88.83594,
      43.8422
    ]
  }
}