{
  "type": "Feature",
  "properties": {
    "name": "Saint Peter",
    "country": "US",
    "subdivision": "WI",
    "timezone": "America/Chicago"
  },
  "geometry": {
    "type": "Point",
    "coordinates": [
      -88.34149,
      43.83638
    ]
  }
}