{
  "type": "Feature",
  "properties": {
    "name": "Shell Lake",
    "country": "US",
    "subdivision": "WI",
    "timezone": "America/Chicago"
  },
  "geometry": {
    "type": "Point",
    "coordinates": [
      -91.92545,
      45.73939
    ]
  }
}