{
  "type": "Feature",
  "properties": {
    "name": "Silver Lake",
    "country": "US",
    "subdivision": "WI",
    "timezone": "America/Chicago"
  },
  "geometry": {
    "type": "Point",
    "coordinates": [
      -88.16564,
      42.54613
    ]
  }
}