{
  "type": "Feature",
  "properties": {
    "name": "Slinger",
    "country": "US",
    "subdivision": "WI",
    "timezone": "America/Chicago"
  },
  "geometry": {
    "type": "Point",
    "coordinates": [
      -88.28621,
      43.33361
    ]
  }
}