{
  "type": "Feature",
  "properties": {
    "name": "Somerset",
    "country": "US",
    "subdivision": "WI",
    "timezone": "America/Chicago"
  },
  "geometry": {
    "type": "Point",
    "coordinates": [
      -92.67354,
      45.12441
    ]
  }
}