{
  "type": "Feature",
  "properties": {
    "name": "Spring Valley",
    "country": "US",
    "subdivision": "WI",
    "timezone": "America/Chicago"
  },
  "geometry": {
    "type": "Point",
    "coordinates": [
      -92.2388,
      44.84524
    ]
  }
}