{
  "type": "Feature",
  "properties": {
    "name": "Stanley",
    "country": "US",
    "subdivision": "WI",
    "timezone": "America/Chicago"
  },
  "geometry": {
    "type": "Point",
    "coordinates": [
      -90.93708,
      44.95997
    ]
  }
}