{
  "type": "Feature",
  "properties": {
    "name": "Stoughton",
    "country": "US",
    "subdivision": "WI",
    "timezone": "America/Chicago"
  },
  "geometry": {
    "type": "Point",
    "coordinates": [
      -89.21789,
      42.91695
    ]
  }
}