{
  "type": "Feature",
  "properties": {
    "name": "Sussex",
    "country": "US",
    "subdivision": "WI",
    "timezone": "America/Chicago"
  },
  "geometry": {
    "type": "Point",
    "coordinates": [
      -88.22204,
      43.1339
    ]
  }
}