{
  "type": "Feature",
  "properties": {
    "name": "Union Grove",
    "country": "US",
    "subdivision": "WI",
    "timezone": "America/Chicago"
  },
  "geometry": {
    "type": "Point",
    "coordinates": [
      -88.05147,
      42.68807
    ]
  }
}