{
  "type": "Feature",
  "properties": {
    "name": "Wauwatosa",
    "country": "US",
    "subdivision": "WI",
    "timezone": "America/Chicago"
  },
  "geometry": {
    "type": "Point",
    "coordinates": [
      -88.00759,
      43.04946
    ]
  }
}