{
  "type": "Feature",
  "properties": {
    "name": "West Baraboo",
    "country": "US",
    "subdivision": "WI",
    "timezone": "America/Chicago"
  },
  "geometry": {
    "type": "Point",
    "coordinates": [
      -89.7704,
      43.47443
    ]
  }
}