{
  "type": "Feature",
  "properties": {
    "name": "Williams Bay",
    "country": "US",
    "subdivision": "WI",
    "timezone": "America/Chicago"
  },
  "geometry": {
    "type": "Point",
    "coordinates": [
      -88.54093,
      42.57807
    ]
  }
}