{
  "type": "Feature",
  "properties": {
    "name": "Wind Lake",
    "country": "US",
    "subdivision": "WI",
    "timezone": "America/Chicago"
  },
  "geometry": {
    "type": "Point",
    "coordinates": [
      -88.1587,
      42.82946
    ]
  }
}