{
  "type": "Feature",
  "properties": {
    "name": "Sarıveliler",
    "country": "TR",
    "subdivision": "78",
    "timezone": "Europe/Istanbul"
  },
  "geometry": {
    "type": "Point",
    "coordinates": [
      32.61203,
      36.69705
    ]
  }
}