{
  "type": "Feature",
  "properties": {
    "name": "Mékhé",
    "country": "SN",
    "subdivision": "07",
    "timezone": "Africa/Dakar"
  },
  "geometry": {
    "type": "Point",
    "coordinates": [
      -16.6218,
      15.1097
    ]
  }
}