{
  "type": "Feature",
  "properties": {
    "name": "Saïda",
    "country": "DZ",
    "subdivision": "10",
    "timezone": "Africa/Algiers"
  },
  "geometry": {
    "type": "Point",
    "coordinates": [
      0.15171,
      34.83033
    ]
  }
}