{
  "type": "Feature",
  "properties": {
    "name": "’Aïn el Hadjar",
    "country": "DZ",
    "subdivision": "10",
    "timezone": "Africa/Algiers"
  },
  "geometry": {
    "type": "Point",
    "coordinates": [
      0.14528,
      34.75846
    ]
  }
}