{
  "type": "Feature",
  "properties": {
    "name": "Ugljan",
    "country": "HR",
    "subdivision": "19",
    "timezone": "Europe/Zagreb"
  },
  "geometry": {
    "type": "Point",
    "coordinates": [
      15.10306,
      44.13083
    ]
  }
}