{
  "type": "Feature",
  "properties": {
    "name": "Kokkári",
    "country": "GR",
    "subdivision": "ESYE41",
    "timezone": "Europe/Athens"
  },
  "geometry": {
    "type": "Point",
    "coordinates": [
      26.89179,
      37.77908
    ]
  }
}