{
  "type": "Feature",
  "properties": {
    "name": "Marathókampos",
    "country": "GR",
    "subdivision": "ESYE41",
    "timezone": "Europe/Athens"
  },
  "geometry": {
    "type": "Point",
    "coordinates": [
      26.68964,
      37.72674
    ]
  }
}