{
  "type": "Feature",
  "properties": {
    "name": "Néon Karlovásion",
    "country": "GR",
    "subdivision": "ESYE41",
    "timezone": "Europe/Athens"
  },
  "geometry": {
    "type": "Point",
    "coordinates": [
      26.7049,
      37.79209
    ]
  }
}