{
  "type": "Feature",
  "properties": {
    "name": "Polichnítos",
    "country": "GR",
    "subdivision": "ESYE41",
    "timezone": "Europe/Athens"
  },
  "geometry": {
    "type": "Point",
    "coordinates": [
      26.18215,
      39.07911
    ]
  }
}