{
  "type": "Feature",
  "properties": {
    "name": "Vrontádos",
    "country": "GR",
    "subdivision": "ESYE41",
    "timezone": "Europe/Athens"
  },
  "geometry": {
    "type": "Point",
    "coordinates": [
      26.12948,
      38.40876
    ]
  }
}