{
  "type": "Feature",
  "properties": {
    "name": "Gyōda",
    "country": "JP",
    "subdivision": "34",
    "timezone": "Asia/Tokyo"
  },
  "geometry": {
    "type": "Point",
    "coordinates": [
      139.46011,
      36.14074
    ]
  }
}