{
  "type": "Feature",
  "properties": {
    "name": "Kukichūō",
    "country": "JP",
    "subdivision": "34",
    "timezone": "Asia/Tokyo"
  },
  "geometry": {
    "type": "Point",
    "coordinates": [
      139.67498,
      36.06739
    ]
  }
}