{
  "type": "Feature",
  "properties": {
    "name": "Sayama",
    "country": "JP",
    "subdivision": "34",
    "timezone": "Asia/Tokyo"
  },
  "geometry": {
    "type": "Point",
    "coordinates": [
      139.41212,
      35.85295
    ]
  }
}