{
  "type": "Feature",
  "properties": {
    "name": "Shiraoka",
    "country": "JP",
    "subdivision": "34",
    "timezone": "Asia/Tokyo"
  },
  "geometry": {
    "type": "Point",
    "coordinates": [
      139.66034,
      36.01839
    ]
  }
}