{
  "type": "Feature",
  "properties": {
    "name": "Ballybunnion",
    "country": "IE",
    "subdivision": "M",
    "timezone": "Europe/Dublin"
  },
  "geometry": {
    "type": "Point",
    "coordinates": [
      -9.67097,
      52.51108
    ]
  }
}