{
  "type": "Feature",
  "properties": {
    "name": "Castleisland",
    "country": "IE",
    "subdivision": "M",
    "timezone": "Europe/Dublin"
  },
  "geometry": {
    "type": "Point",
    "coordinates": [
      -9.46667,
      52.23333
    ]
  }
}