{
  "type": "Feature",
  "properties": {
    "name": "Castlemartyr",
    "country": "IE",
    "subdivision": "M",
    "timezone": "Europe/Dublin"
  },
  "geometry": {
    "type": "Point",
    "coordinates": [
      -8.05389,
      51.91028
    ]
  }
}