{
  "type": "Feature",
  "properties": {
    "name": "Cork",
    "country": "IE",
    "subdivision": "M",
    "timezone": "Europe/Dublin"
  },
  "geometry": {
    "type": "Point",
    "coordinates": [
      -8.47061,
      51.89797
    ]
  }
}