{
  "type": "Feature",
  "properties": {
    "name": "Fermoy",
    "country": "IE",
    "subdivision": "M",
    "timezone": "Europe/Dublin"
  },
  "geometry": {
    "type": "Point",
    "coordinates": [
      -8.27583,
      52.13583
    ]
  }
}