{
  "type": "Feature",
  "properties": {
    "name": "Moroe",
    "country": "IE",
    "subdivision": "M",
    "timezone": "Europe/Dublin"
  },
  "geometry": {
    "type": "Point",
    "coordinates": [
      -8.39611,
      52.65111
    ]
  }
}