{
  "type": "Feature",
  "properties": {
    "name": "Moyross",
    "country": "IE",
    "subdivision": "M",
    "timezone": "Europe/Dublin"
  },
  "geometry": {
    "type": "Point",
    "coordinates": [
      -8.63955,
      52.68198
    ]
  }
}