{
  "type": "Feature",
  "properties": {
    "name": "Palmar de Ocoa",
    "country": "DO",
    "subdivision": "01",
    "timezone": "America/Santo_Domingo"
  },
  "geometry": {
    "type": "Point",
    "coordinates": [
      -70.58635,
      18.29656
    ]
  }
}