{
  "type": "Feature",
  "properties": {
    "name": "Tábara Arriba",
    "country": "DO",
    "subdivision": "01",
    "timezone": "America/Santo_Domingo"
  },
  "geometry": {
    "type": "Point",
    "coordinates": [
      -70.87978,
      18.56999
    ]
  }
}