{
  "type": "Feature",
  "properties": {
    "name": "Aniva",
    "country": "RU",
    "subdivision": "64",
    "timezone": "Asia/Sakhalin"
  },
  "geometry": {
    "type": "Point",
    "coordinates": [
      142.52866,
      46.71492
    ]
  }
}