{
  "type": "Feature",
  "properties": {
    "name": "Okha",
    "country": "RU",
    "subdivision": "64",
    "timezone": "Asia/Sakhalin"
  },
  "geometry": {
    "type": "Point",
    "coordinates": [
      142.95313,
      53.58991
    ]
  }
}