{
  "type": "Feature",
  "properties": {
    "name": "Agay",
    "country": "PH",
    "subdivision": "13",
    "timezone": "Asia/Manila"
  },
  "geometry": {
    "type": "Point",
    "coordinates": [
      125.58667,
      9.05361
    ]
  }
}