{
  "type": "Feature",
  "properties": {
    "name": "Bislig",
    "country": "PH",
    "subdivision": "13",
    "timezone": "Asia/Manila"
  },
  "geometry": {
    "type": "Point",
    "coordinates": [
      126.31639,
      8.21528
    ]
  }
}