{
  "type": "Feature",
  "properties": {
    "name": "Bunawan",
    "country": "PH",
    "subdivision": "13",
    "timezone": "Asia/Manila"
  },
  "geometry": {
    "type": "Point",
    "coordinates": [
      125.99083,
      8.16722
    ]
  }
}