{
  "type": "Feature",
  "properties": {
    "name": "Cantapoy",
    "country": "PH",
    "subdivision": "13",
    "timezone": "Asia/Manila"
  },
  "geometry": {
    "type": "Point",
    "coordinates": [
      125.43639,
      9.49056
    ]
  }
}