{
  "type": "Feature",
  "properties": {
    "name": "Hinatuan",
    "country": "PH",
    "subdivision": "13",
    "timezone": "Asia/Manila"
  },
  "geometry": {
    "type": "Point",
    "coordinates": [
      126.33417,
      8.37222
    ]
  }
}