{
  "type": "Feature",
  "properties": {
    "name": "Libertad",
    "country": "PH",
    "subdivision": "13",
    "timezone": "Asia/Manila"
  },
  "geometry": {
    "type": "Point",
    "coordinates": [
      125.50194,
      8.94417
    ]
  }
}