{
  "type": "Feature",
  "properties": {
    "name": "Pilar",
    "country": "PH",
    "subdivision": "13",
    "timezone": "Asia/Manila"
  },
  "geometry": {
    "type": "Point",
    "coordinates": [
      126.09944,
      9.865
    ]
  }
}