{
  "type": "Feature",
  "properties": {
    "name": "San Francisco",
    "country": "PH",
    "subdivision": "13",
    "timezone": "Asia/Manila"
  },
  "geometry": {
    "type": "Point",
    "coordinates": [
      125.48556,
      9.52806
    ]
  }
}