{
  "type": "Feature",
  "properties": {
    "name": "Surigao",
    "country": "PH",
    "subdivision": "13",
    "timezone": "Asia/Manila"
  },
  "geometry": {
    "type": "Point",
    "coordinates": [
      125.495,
      9.789
    ]
  }
}