{
  "type": "Feature",
  "properties": {
    "name": "Taligaman",
    "country": "PH",
    "subdivision": "13",
    "timezone": "Asia/Manila"
  },
  "geometry": {
    "type": "Point",
    "coordinates": [
      125.65583,
      8.90444
    ]
  }
}