{
  "type": "Feature",
  "properties": {
    "name": "Chadan",
    "country": "RU",
    "subdivision": "79",
    "timezone": "Asia/Krasnoyarsk"
  },
  "geometry": {
    "type": "Point",
    "coordinates": [
      91.58333,
      51.28333
    ]
  }
}