{
  "type": "Feature",
  "properties": {
    "name": "Kaa-Khem",
    "country": "RU",
    "subdivision": "79",
    "timezone": "Asia/Krasnoyarsk"
  },
  "geometry": {
    "type": "Point",
    "coordinates": [
      94.73333,
      51.68333
    ]
  }
}