{
  "type": "Feature",
  "properties": {
    "name": "Khovu-Aksy",
    "country": "RU",
    "subdivision": "79",
    "timezone": "Asia/Krasnoyarsk"
  },
  "geometry": {
    "type": "Point",
    "coordinates": [
      93.71286,
      51.13294
    ]
  }
}