{
  "type": "Feature",
  "properties": {
    "name": "Teeli",
    "country": "RU",
    "subdivision": "79",
    "timezone": "Asia/Krasnoyarsk"
  },
  "geometry": {
    "type": "Point",
    "coordinates": [
      90.20535,
      51.01398
    ]
  }
}