{
  "type": "Feature",
  "properties": {
    "name": "Manggar",
    "country": "ID",
    "subdivision": "35",
    "timezone": "Asia/Jakarta"
  },
  "geometry": {
    "type": "Point",
    "coordinates": [
      108.26667,
      -2.88333
    ]
  }
}