{
  "type": "Feature",
  "properties": {
    "name": "Muntok",
    "country": "ID",
    "subdivision": "35",
    "timezone": "Asia/Jakarta"
  },
  "geometry": {
    "type": "Point",
    "coordinates": [
      105.16228,
      -2.06719
    ]
  }
}