{
  "type": "Feature",
  "properties": {
    "name": "Manghit",
    "country": "UZ",
    "subdivision": "09",
    "timezone": "Asia/Samarkand"
  },
  "geometry": {
    "type": "Point",
    "coordinates": [
      60.05972,
      42.11556
    ]
  }
}