{
  "type": "Feature",
  "properties": {
    "name": "Albaida",
    "country": "ES",
    "subdivision": "60",
    "timezone": "Europe/Madrid"
  },
  "geometry": {
    "type": "Point",
    "coordinates": [
      -0.51721,
      38.83798
    ]
  }
}