{
  "type": "Feature",
  "properties": {
    "name": "Alcocéber",
    "country": "ES",
    "subdivision": "60",
    "timezone": "Europe/Madrid"
  },
  "geometry": {
    "type": "Point",
    "coordinates": [
      0.28433,
      40.25142
    ]
  }
}