{
  "type": "Feature",
  "properties": {
    "name": "Algorfa",
    "country": "ES",
    "subdivision": "60",
    "timezone": "Europe/Madrid"
  },
  "geometry": {
    "type": "Point",
    "coordinates": [
      -0.79646,
      38.08636
    ]
  }
}