{
  "type": "Feature",
  "properties": {
    "name": "Algueña",
    "country": "ES",
    "subdivision": "60",
    "timezone": "Europe/Madrid"
  },
  "geometry": {
    "type": "Point",
    "coordinates": [
      -1.00433,
      38.33905
    ]
  }
}