{
  "type": "Feature",
  "properties": {
    "name": "Almenara",
    "country": "ES",
    "subdivision": "60",
    "timezone": "Europe/Madrid"
  },
  "geometry": {
    "type": "Point",
    "coordinates": [
      -0.21667,
      39.75
    ]
  }
}