{
  "type": "Feature",
  "properties": {
    "name": "Almussafes",
    "country": "ES",
    "subdivision": "60",
    "timezone": "Europe/Madrid"
  },
  "geometry": {
    "type": "Point",
    "coordinates": [
      -0.41667,
      39.28333
    ]
  }
}