{
  "type": "Feature",
  "properties": {
    "name": "Anna",
    "country": "ES",
    "subdivision": "60",
    "timezone": "Europe/Madrid"
  },
  "geometry": {
    "type": "Point",
    "coordinates": [
      -0.64621,
      39.02029
    ]
  }
}