{
  "type": "Feature",
  "properties": {
    "name": "Artana",
    "country": "ES",
    "subdivision": "60",
    "timezone": "Europe/Madrid"
  },
  "geometry": {
    "type": "Point",
    "coordinates": [
      -0.25758,
      39.89104
    ]
  }
}