{
  "type": "Feature",
  "properties": {
    "name": "Benigànim",
    "country": "ES",
    "subdivision": "60",
    "timezone": "Europe/Madrid"
  },
  "geometry": {
    "type": "Point",
    "coordinates": [
      -0.43333,
      38.95
    ]
  }
}