{
  "type": "Feature",
  "properties": {
    "name": "Beniarbeig",
    "country": "ES",
    "subdivision": "60",
    "timezone": "Europe/Madrid"
  },
  "geometry": {
    "type": "Point",
    "coordinates": [
      -0.0021,
      38.82232
    ]
  }
}