{
  "type": "Feature",
  "properties": {
    "name": "Benifaió",
    "country": "ES",
    "subdivision": "60",
    "timezone": "Europe/Madrid"
  },
  "geometry": {
    "type": "Point",
    "coordinates": [
      -0.42598,
      39.28439
    ]
  }
}