{
  "type": "Feature",
  "properties": {
    "name": "Biar",
    "country": "ES",
    "subdivision": "60",
    "timezone": "Europe/Madrid"
  },
  "geometry": {
    "type": "Point",
    "coordinates": [
      -0.76458,
      38.63117
    ]
  }
}