{
  "type": "Feature",
  "properties": {
    "name": "Cabanes",
    "country": "ES",
    "subdivision": "60",
    "timezone": "Europe/Madrid"
  },
  "geometry": {
    "type": "Point",
    "coordinates": [
      0.04325,
      40.156
    ]
  }
}