{
  "type": "Feature",
  "properties": {
    "name": "Càlig",
    "country": "ES",
    "subdivision": "60",
    "timezone": "Europe/Madrid"
  },
  "geometry": {
    "type": "Point",
    "coordinates": [
      0.35521,
      40.46262
    ]
  }
}