{
  "type": "Feature",
  "properties": {
    "name": "Castelló de la Plana",
    "country": "ES",
    "subdivision": "60",
    "timezone": "Europe/Madrid"
  },
  "geometry": {
    "type": "Point",
    "coordinates": [
      -0.04935,
      39.98567
    ]
  }
}