{
  "type": "Feature",
  "properties": {
    "name": "Cuevas de Vinromá",
    "country": "ES",
    "subdivision": "60",
    "timezone": "Europe/Madrid"
  },
  "geometry": {
    "type": "Point",
    "coordinates": [
      0.12084,
      40.30976
    ]
  }
}