{
  "type": "Feature",
  "properties": {
    "name": "Dolores",
    "country": "ES",
    "subdivision": "60",
    "timezone": "Europe/Madrid"
  },
  "geometry": {
    "type": "Point",
    "coordinates": [
      -0.77088,
      38.14002
    ]
  }
}