{
  "type": "Feature",
  "properties": {
    "name": "Estivella",
    "country": "ES",
    "subdivision": "60",
    "timezone": "Europe/Madrid"
  },
  "geometry": {
    "type": "Point",
    "coordinates": [
      -0.35,
      39.71667
    ]
  }
}