{
  "type": "Feature",
  "properties": {
    "name": "Finestrat",
    "country": "ES",
    "subdivision": "60",
    "timezone": "Europe/Madrid"
  },
  "geometry": {
    "type": "Point",
    "coordinates": [
      -0.21235,
      38.56737
    ]
  }
}