{
  "type": "Feature",
  "properties": {
    "name": "Granja de Rocamora",
    "country": "ES",
    "subdivision": "60",
    "timezone": "Europe/Madrid"
  },
  "geometry": {
    "type": "Point",
    "coordinates": [
      -0.8917,
      38.15157
    ]
  }
}