{
  "type": "Feature",
  "properties": {
    "name": "Hondón de las Nieves",
    "country": "ES",
    "subdivision": "60",
    "timezone": "Europe/Madrid"
  },
  "geometry": {
    "type": "Point",
    "coordinates": [
      -0.8533,
      38.30844
    ]
  }
}