{
  "type": "Feature",
  "properties": {
    "name": "Llosa de Ranes",
    "country": "ES",
    "subdivision": "60",
    "timezone": "Europe/Madrid"
  },
  "geometry": {
    "type": "Point",
    "coordinates": [
      -0.53803,
      39.02163
    ]
  }
}