{
  "type": "Feature",
  "properties": {
    "name": "Lucena del Cid",
    "country": "ES",
    "subdivision": "60",
    "timezone": "Europe/Madrid"
  },
  "geometry": {
    "type": "Point",
    "coordinates": [
      -0.28333,
      40.13333
    ]
  }
}