{
  "type": "Feature",
  "properties": {
    "name": "Ondara",
    "country": "ES",
    "subdivision": "60",
    "timezone": "Europe/Madrid"
  },
  "geometry": {
    "type": "Point",
    "coordinates": [
      0.0172,
      38.82817
    ]
  }
}