{
  "type": "Feature",
  "properties": {
    "name": "Quart de les Valls",
    "country": "ES",
    "subdivision": "60",
    "timezone": "Europe/Madrid"
  },
  "geometry": {
    "type": "Point",
    "coordinates": [
      -0.26667,
      39.73333
    ]
  }
}