{
  "type": "Feature",
  "properties": {
    "name": "Ribarroja del Turia",
    "country": "ES",
    "subdivision": "60",
    "timezone": "Europe/Madrid"
  },
  "geometry": {
    "type": "Point",
    "coordinates": [
      -0.57069,
      39.54595
    ]
  }
}