{
  "type": "Feature",
  "properties": {
    "name": "Rotglá y Corbera",
    "country": "ES",
    "subdivision": "60",
    "timezone": "Europe/Madrid"
  },
  "geometry": {
    "type": "Point",
    "coordinates": [
      -0.56482,
      39.00465
    ]
  }
}