{
  "type": "Feature",
  "properties": {
    "name": "Santa Pola",
    "country": "ES",
    "subdivision": "60",
    "timezone": "Europe/Madrid"
  },
  "geometry": {
    "type": "Point",
    "coordinates": [
      -0.5658,
      38.19165
    ]
  }
}