{
  "type": "Feature",
  "properties": {
    "name": "Villavieja",
    "country": "ES",
    "subdivision": "60",
    "timezone": "Europe/Madrid"
  },
  "geometry": {
    "type": "Point",
    "coordinates": [
      -0.18333,
      39.85
    ]
  }
}