{
  "type": "Feature",
  "properties": {
    "name": "Villajoyosa",
    "country": "ES",
    "subdivision": "60",
    "timezone": "Europe/Madrid"
  },
  "geometry": {
    "type": "Point",
    "coordinates": [
      -0.23346,
      38.50754
    ]
  }
}