{
  "type": "Feature",
  "properties": {
    "name": "Xàtiva",
    "country": "ES",
    "subdivision": "60",
    "timezone": "Europe/Madrid"
  },
  "geometry": {
    "type": "Point",
    "coordinates": [
      -0.51852,
      38.99042
    ]
  }
}