{
  "type": "Feature",
  "properties": {
    "name": "Porgera",
    "country": "PG",
    "subdivision": "19",
    "timezone": "Pacific/Port_Moresby"
  },
  "geometry": {
    "type": "Point",
    "coordinates": [
      143.148,
      -5.463
    ]
  }
}