{
  "type": "Feature",
  "properties": {
    "name": "Hajīn",
    "country": "SY",
    "subdivision": "07",
    "timezone": "Asia/Damascus"
  },
  "geometry": {
    "type": "Point",
    "coordinates": [
      40.83138,
      34.69508
    ]
  }
}