{
  "type": "Feature",
  "properties": {
    "name": "Caimito",
    "country": "PA",
    "subdivision": "03",
    "timezone": "America/Panama"
  },
  "geometry": {
    "type": "Point",
    "coordinates": [
      -80.2385,
      8.62454
    ]
  }
}