{
  "type": "Feature",
  "properties": {
    "name": "La Loma",
    "country": "PA",
    "subdivision": "03",
    "timezone": "America/Panama"
  },
  "geometry": {
    "type": "Point",
    "coordinates": [
      -80.63617,
      8.1664
    ]
  }
}