{
  "type": "Feature",
  "properties": {
    "name": "Llano Marín",
    "country": "PA",
    "subdivision": "03",
    "timezone": "America/Panama"
  },
  "geometry": {
    "type": "Point",
    "coordinates": [
      -80.32928,
      8.48847
    ]
  }
}