{
  "type": "Feature",
  "properties": {
    "name": "Ljungbyholm",
    "country": "SE",
    "subdivision": "09",
    "timezone": "Europe/Stockholm"
  },
  "geometry": {
    "type": "Point",
    "coordinates": [
      16.16667,
      56.63333
    ]
  }
}