{
  "type": "Feature",
  "properties": {
    "name": "Oskarshamn",
    "country": "SE",
    "subdivision": "09",
    "timezone": "Europe/Stockholm"
  },
  "geometry": {
    "type": "Point",
    "coordinates": [
      16.44837,
      57.26455
    ]
  }
}