{
  "type": "Feature",
  "properties": {
    "name": "Naranjal",
    "country": "EC",
    "subdivision": "10",
    "timezone": "America/Guayaquil"
  },
  "geometry": {
    "type": "Point",
    "coordinates": [
      -79.6183,
      -2.67364
    ]
  }
}