{
  "type": "Feature",
  "properties": {
    "name": "Ingenbohl",
    "country": "CH",
    "subdivision": "SZ",
    "timezone": "Europe/Zurich"
  },
  "geometry": {
    "type": "Point",
    "coordinates": [
      8.61529,
      46.9988
    ]
  }
}