{
  "type": "Feature",
  "properties": {
    "name": "Kurunegala",
    "country": "LK",
    "subdivision": "32",
    "timezone": "Asia/Colombo"
  },
  "geometry": {
    "type": "Point",
    "coordinates": [
      80.3683,
      7.4839
    ]
  }
}