{
  "type": "Feature",
  "properties": {
    "name": "Radizel",
    "country": "SI",
    "subdivision": "H1",
    "timezone": "Europe/Ljubljana"
  },
  "geometry": {
    "type": "Point",
    "coordinates": [
      15.65583,
      46.47444
    ]
  }
}