{
  "type": "Feature",
  "properties": {
    "name": "Adalan",
    "country": "TR",
    "subdivision": "34",
    "timezone": "Europe/Istanbul"
  },
  "geometry": {
    "type": "Point",
    "coordinates": [
      29.0894,
      40.8759
    ]
  }
}