{
  "type": "Feature",
  "properties": {
    "name": "Büyükçekmece",
    "country": "TR",
    "subdivision": "34",
    "timezone": "Europe/Istanbul"
  },
  "geometry": {
    "type": "Point",
    "coordinates": [
      28.58502,
      41.02072
    ]
  }
}