{
  "type": "Feature",
  "properties": {
    "name": "Şişli",
    "country": "TR",
    "subdivision": "34",
    "timezone": "Europe/Istanbul"
  },
  "geometry": {
    "type": "Point",
    "coordinates": [
      28.98717,
      41.06046
    ]
  }
}