{
  "type": "Feature",
  "properties": {
    "name": "Tepecik",
    "country": "TR",
    "subdivision": "34",
    "timezone": "Europe/Istanbul"
  },
  "geometry": {
    "type": "Point",
    "coordinates": [
      28.54978,
      41.02931
    ]
  }
}