{
  "type": "Feature",
  "properties": {
    "name": "Agía Triáda",
    "country": "GR",
    "subdivision": "ESYE12",
    "timezone": "Europe/Athens"
  },
  "geometry": {
    "type": "Point",
    "coordinates": [
      22.87351,
      40.50003
    ]
  }
}