{
  "type": "Feature",
  "properties": {
    "name": "Ágios Athanásios",
    "country": "GR",
    "subdivision": "ESYE12",
    "timezone": "Europe/Athens"
  },
  "geometry": {
    "type": "Point",
    "coordinates": [
      22.72841,
      40.71598
    ]
  }
}