{
  "type": "Feature",
  "properties": {
    "name": "Agkathiá",
    "country": "GR",
    "subdivision": "ESYE12",
    "timezone": "Europe/Athens"
  },
  "geometry": {
    "type": "Point",
    "coordinates": [
      22.47083,
      40.55535
    ]
  }
}