{
  "type": "Feature",
  "properties": {
    "name": "Árnissa",
    "country": "GR",
    "subdivision": "ESYE12",
    "timezone": "Europe/Athens"
  },
  "geometry": {
    "type": "Point",
    "coordinates": [
      21.83577,
      40.79555
    ]
  }
}