{
  "type": "Feature",
  "properties": {
    "name": "Askós",
    "country": "GR",
    "subdivision": "ESYE12",
    "timezone": "Europe/Athens"
  },
  "geometry": {
    "type": "Point",
    "coordinates": [
      23.38721,
      40.75105
    ]
  }
}