{
  "type": "Feature",
  "properties": {
    "name": "Kalá Déndra",
    "country": "GR",
    "subdivision": "ESYE12",
    "timezone": "Europe/Athens"
  },
  "geometry": {
    "type": "Point",
    "coordinates": [
      23.42396,
      41.09941
    ]
  }
}