{
  "type": "Feature",
  "properties": {
    "name": "Káto Scholári",
    "country": "GR",
    "subdivision": "ESYE12",
    "timezone": "Europe/Athens"
  },
  "geometry": {
    "type": "Point",
    "coordinates": [
      23.02978,
      40.42906
    ]
  }
}