{
  "type": "Feature",
  "properties": {
    "name": "Kopanós",
    "country": "GR",
    "subdivision": "ESYE12",
    "timezone": "Europe/Athens"
  },
  "geometry": {
    "type": "Point",
    "coordinates": [
      22.12893,
      40.63382
    ]
  }
}