{
  "type": "Feature",
  "properties": {
    "name": "Koufália",
    "country": "GR",
    "subdivision": "ESYE12",
    "timezone": "Europe/Athens"
  },
  "geometry": {
    "type": "Point",
    "coordinates": [
      22.57194,
      40.77778
    ]
  }
}