{
  "type": "Feature",
  "properties": {
    "name": "Krithiá",
    "country": "GR",
    "subdivision": "ESYE12",
    "timezone": "Europe/Athens"
  },
  "geometry": {
    "type": "Point",
    "coordinates": [
      22.98292,
      40.84184
    ]
  }
}