{
  "type": "Feature",
  "properties": {
    "name": "Lákkoma",
    "country": "GR",
    "subdivision": "ESYE12",
    "timezone": "Europe/Athens"
  },
  "geometry": {
    "type": "Point",
    "coordinates": [
      23.05578,
      40.39139
    ]
  }
}