{
  "type": "Feature",
  "properties": {
    "name": "Leptokaryá",
    "country": "GR",
    "subdivision": "ESYE12",
    "timezone": "Europe/Athens"
  },
  "geometry": {
    "type": "Point",
    "coordinates": [
      22.5612,
      40.06032
    ]
  }
}