{
  "type": "Feature",
  "properties": {
    "name": "Loutrós",
    "country": "GR",
    "subdivision": "ESYE12",
    "timezone": "Europe/Athens"
  },
  "geometry": {
    "type": "Point",
    "coordinates": [
      22.39976,
      40.58873
    ]
  }
}