{
  "type": "Feature",
  "properties": {
    "name": "Makrýgialos",
    "country": "GR",
    "subdivision": "ESYE12",
    "timezone": "Europe/Athens"
  },
  "geometry": {
    "type": "Point",
    "coordinates": [
      22.60392,
      40.41551
    ]
  }
}