{
  "type": "Feature",
  "properties": {
    "name": "Melissochóri",
    "country": "GR",
    "subdivision": "ESYE12",
    "timezone": "Europe/Athens"
  },
  "geometry": {
    "type": "Point",
    "coordinates": [
      22.92858,
      40.76796
    ]
  }
}