{
  "type": "Feature",
  "properties": {
    "name": "Néa Tríglia",
    "country": "GR",
    "subdivision": "ESYE12",
    "timezone": "Europe/Athens"
  },
  "geometry": {
    "type": "Point",
    "coordinates": [
      23.2066,
      40.30575
    ]
  }
}