{
  "type": "Feature",
  "properties": {
    "name": "Néa Plágia",
    "country": "GR",
    "subdivision": "ESYE12",
    "timezone": "Europe/Athens"
  },
  "geometry": {
    "type": "Point",
    "coordinates": [
      23.20376,
      40.26537
    ]
  }
}