{
  "type": "Feature",
  "properties": {
    "name": "Néa Potídhaia",
    "country": "GR",
    "subdivision": "ESYE12",
    "timezone": "Europe/Athens"
  },
  "geometry": {
    "type": "Point",
    "coordinates": [
      23.32874,
      40.19428
    ]
  }
}