{
  "type": "Feature",
  "properties": {
    "name": "Oraiókastro",
    "country": "GR",
    "subdivision": "ESYE12",
    "timezone": "Europe/Athens"
  },
  "geometry": {
    "type": "Point",
    "coordinates": [
      22.91722,
      40.73083
    ]
  }
}