{
  "type": "Feature",
  "properties": {
    "name": "Ouranoupolis",
    "country": "GR",
    "subdivision": "ESYE12",
    "timezone": "Europe/Athens"
  },
  "geometry": {
    "type": "Point",
    "coordinates": [
      23.98333,
      40.33333
    ]
  }
}