{
  "type": "Feature",
  "properties": {
    "name": "Péfka",
    "country": "GR",
    "subdivision": "ESYE12",
    "timezone": "Europe/Athens"
  },
  "geometry": {
    "type": "Point",
    "coordinates": [
      22.99378,
      40.65806
    ]
  }
}