{
  "type": "Feature",
  "properties": {
    "name": "Políchni",
    "country": "GR",
    "subdivision": "ESYE12",
    "timezone": "Europe/Athens"
  },
  "geometry": {
    "type": "Point",
    "coordinates": [
      22.94881,
      40.66671
    ]
  }
}