{
  "type": "Feature",
  "properties": {
    "name": "Portariá",
    "country": "GR",
    "subdivision": "ESYE12",
    "timezone": "Europe/Athens"
  },
  "geometry": {
    "type": "Point",
    "coordinates": [
      23.29549,
      40.28405
    ]
  }
}