{
  "type": "Feature",
  "properties": {
    "name": "Skoútari",
    "country": "GR",
    "subdivision": "ESYE12",
    "timezone": "Europe/Athens"
  },
  "geometry": {
    "type": "Point",
    "coordinates": [
      23.51971,
      41.01871
    ]
  }
}