{
  "type": "Feature",
  "properties": {
    "name": "Skýdra",
    "country": "GR",
    "subdivision": "ESYE12",
    "timezone": "Europe/Athens"
  },
  "geometry": {
    "type": "Point",
    "coordinates": [
      22.15194,
      40.76722
    ]
  }
}