{
  "type": "Feature",
  "properties": {
    "name": "Sourotí",
    "country": "GR",
    "subdivision": "ESYE12",
    "timezone": "Europe/Athens"
  },
  "geometry": {
    "type": "Point",
    "coordinates": [
      23.09197,
      40.47274
    ]
  }
}