{
  "type": "Feature",
  "properties": {
    "name": "Svorónos",
    "country": "GR",
    "subdivision": "ESYE12",
    "timezone": "Europe/Athens"
  },
  "geometry": {
    "type": "Point",
    "coordinates": [
      22.46366,
      40.26805
    ]
  }
}