{
  "type": "Feature",
  "properties": {
    "name": "Vergína",
    "country": "GR",
    "subdivision": "ESYE12",
    "timezone": "Europe/Athens"
  },
  "geometry": {
    "type": "Point",
    "coordinates": [
      22.31735,
      40.48654
    ]
  }
}