{
  "type": "Feature",
  "properties": {
    "name": "Véroia",
    "country": "GR",
    "subdivision": "ESYE12",
    "timezone": "Europe/Athens"
  },
  "geometry": {
    "type": "Point",
    "coordinates": [
      22.20242,
      40.52437
    ]
  }
}