{
  "type": "Feature",
  "properties": {
    "name": "SayyÄn",
    "country": "YE",
    "subdivision": "16",
    "timezone": "Asia/Aden"
  },
  "geometry": {
    "type": "Point",
    "coordinates": [
      44.32442,
      15.17177
    ]
  }
}