{
  "type": "Feature",
  "properties": {
    "name": "Bukama",
    "country": "CD",
    "subdivision": "15",
    "timezone": "Africa/Lubumbashi"
  },
  "geometry": {
    "type": "Point",
    "coordinates": [
      25.85475,
      -9.20443
    ]
  }
}