{
  "type": "Feature",
  "properties": {
    "name": "Aripuanã",
    "country": "BR",
    "subdivision": "14",
    "timezone": "America/Cuiaba"
  },
  "geometry": {
    "type": "Point",
    "coordinates": [
      -60.63333,
      -9.16667
    ]
  }
}