{
  "type": "Feature",
  "properties": {
    "name": "Nova Olímpia",
    "country": "BR",
    "subdivision": "14",
    "timezone": "America/Cuiaba"
  },
  "geometry": {
    "type": "Point",
    "coordinates": [
      -57.28806,
      -14.79722
    ]
  }
}