{
  "type": "Feature",
  "properties": {
    "name": "Poxoréo",
    "country": "BR",
    "subdivision": "14",
    "timezone": "America/Cuiaba"
  },
  "geometry": {
    "type": "Point",
    "coordinates": [
      -54.38917,
      -15.83722
    ]
  }
}