{
  "type": "Feature",
  "properties": {
    "name": "Rosário Oeste",
    "country": "BR",
    "subdivision": "14",
    "timezone": "America/Cuiaba"
  },
  "geometry": {
    "type": "Point",
    "coordinates": [
      -56.4275,
      -14.83611
    ]
  }
}