{
  "type": "Feature",
  "properties": {
    "name": "Cegłów",
    "country": "PL",
    "subdivision": "78",
    "timezone": "Europe/Warsaw"
  },
  "geometry": {
    "type": "Point",
    "coordinates": [
      21.73739,
      52.14782
    ]
  }
}