{
  "type": "Feature",
  "properties": {
    "name": "Czerwińsk Nad Wisłą",
    "country": "PL",
    "subdivision": "78",
    "timezone": "Europe/Warsaw"
  },
  "geometry": {
    "type": "Point",
    "coordinates": [
      20.3096,
      52.39828
    ]
  }
}