{
  "type": "Feature",
  "properties": {
    "name": "Dębe Wielkie",
    "country": "PL",
    "subdivision": "78",
    "timezone": "Europe/Warsaw"
  },
  "geometry": {
    "type": "Point",
    "coordinates": [
      21.44334,
      52.19961
    ]
  }
}