{
  "type": "Feature",
  "properties": {
    "name": "Dziekanów Leśny",
    "country": "PL",
    "subdivision": "78",
    "timezone": "Europe/Warsaw"
  },
  "geometry": {
    "type": "Point",
    "coordinates": [
      20.85124,
      52.35243
    ]
  }
}