{
  "type": "Feature",
  "properties": {
    "name": "Jadów",
    "country": "PL",
    "subdivision": "78",
    "timezone": "Europe/Warsaw"
  },
  "geometry": {
    "type": "Point",
    "coordinates": [
      21.63199,
      52.47849
    ]
  }
}