{
  "type": "Feature",
  "properties": {
    "name": "Józefów",
    "country": "PL",
    "subdivision": "78",
    "timezone": "Europe/Warsaw"
  },
  "geometry": {
    "type": "Point",
    "coordinates": [
      20.69592,
      52.19446
    ]
  }
}