{
  "type": "Feature",
  "properties": {
    "name": "Kiełpin",
    "country": "PL",
    "subdivision": "78",
    "timezone": "Europe/Warsaw"
  },
  "geometry": {
    "type": "Point",
    "coordinates": [
      20.86214,
      52.35796
    ]
  }
}