{
  "type": "Feature",
  "properties": {
    "name": "Kozienice",
    "country": "PL",
    "subdivision": "78",
    "timezone": "Europe/Warsaw"
  },
  "geometry": {
    "type": "Point",
    "coordinates": [
      21.54779,
      51.58294
    ]
  }
}