{
  "type": "Feature",
  "properties": {
    "name": "Milanówek",
    "country": "PL",
    "subdivision": "78",
    "timezone": "Europe/Warsaw"
  },
  "geometry": {
    "type": "Point",
    "coordinates": [
      20.67155,
      52.11879
    ]
  }
}