{
  "type": "Feature",
  "properties": {
    "name": "Mrozy",
    "country": "PL",
    "subdivision": "78",
    "timezone": "Europe/Warsaw"
  },
  "geometry": {
    "type": "Point",
    "coordinates": [
      21.80263,
      52.16609
    ]
  }
}