{
  "type": "Feature",
  "properties": {
    "name": "Myszyniec",
    "country": "PL",
    "subdivision": "78",
    "timezone": "Europe/Warsaw"
  },
  "geometry": {
    "type": "Point",
    "coordinates": [
      21.34961,
      53.38055
    ]
  }
}