{
  "type": "Feature",
  "properties": {
    "name": "Mława",
    "country": "PL",
    "subdivision": "78",
    "timezone": "Europe/Warsaw"
  },
  "geometry": {
    "type": "Point",
    "coordinates": [
      20.3841,
      53.11278
    ]
  }
}