{
  "type": "Feature",
  "properties": {
    "name": "Nowe Miasto",
    "country": "PL",
    "subdivision": "78",
    "timezone": "Europe/Warsaw"
  },
  "geometry": {
    "type": "Point",
    "coordinates": [
      20.62838,
      52.65691
    ]
  }
}