{
  "type": "Feature",
  "properties": {
    "name": "Nowe Lipiny",
    "country": "PL",
    "subdivision": "78",
    "timezone": "Europe/Warsaw"
  },
  "geometry": {
    "type": "Point",
    "coordinates": [
      21.27125,
      52.35789
    ]
  }
}