{
  "type": "Feature",
  "properties": {
    "name": "Ostrów Mazowiecka",
    "country": "PL",
    "subdivision": "78",
    "timezone": "Europe/Warsaw"
  },
  "geometry": {
    "type": "Point",
    "coordinates": [
      21.89507,
      52.80245
    ]
  }
}