{
  "type": "Feature",
  "properties": {
    "name": "Ostrówek",
    "country": "PL",
    "subdivision": "78",
    "timezone": "Europe/Warsaw"
  },
  "geometry": {
    "type": "Point",
    "coordinates": [
      21.76014,
      52.5535
    ]
  }
}