{
  "type": "Feature",
  "properties": {
    "name": "Otrębusy",
    "country": "PL",
    "subdivision": "78",
    "timezone": "Europe/Warsaw"
  },
  "geometry": {
    "type": "Point",
    "coordinates": [
      20.76073,
      52.12843
    ]
  }
}