{
  "type": "Feature",
  "properties": {
    "name": "Owczarnia",
    "country": "PL",
    "subdivision": "78",
    "timezone": "Europe/Warsaw"
  },
  "geometry": {
    "type": "Point",
    "coordinates": [
      20.70468,
      52.11114
    ]
  }
}