{
  "type": "Feature",
  "properties": {
    "name": "Piaseczno",
    "country": "PL",
    "subdivision": "78",
    "timezone": "Europe/Warsaw"
  },
  "geometry": {
    "type": "Point",
    "coordinates": [
      21.02397,
      52.0814
    ]
  }
}