{
  "type": "Feature",
  "properties": {
    "name": "Policzna",
    "country": "PL",
    "subdivision": "78",
    "timezone": "Europe/Warsaw"
  },
  "geometry": {
    "type": "Point",
    "coordinates": [
      21.62684,
      51.45545
    ]
  }
}