{
  "type": "Feature",
  "properties": {
    "name": "Przasnysz",
    "country": "PL",
    "subdivision": "78",
    "timezone": "Europe/Warsaw"
  },
  "geometry": {
    "type": "Point",
    "coordinates": [
      20.88029,
      53.01907
    ]
  }
}