{
  "type": "Feature",
  "properties": {
    "name": "Raciąż",
    "country": "PL",
    "subdivision": "78",
    "timezone": "Europe/Warsaw"
  },
  "geometry": {
    "type": "Point",
    "coordinates": [
      20.1177,
      52.78152
    ]
  }
}