{
  "type": "Feature",
  "properties": {
    "name": "Rybie",
    "country": "PL",
    "subdivision": "78",
    "timezone": "Europe/Warsaw"
  },
  "geometry": {
    "type": "Point",
    "coordinates": [
      20.93655,
      52.15229
    ]
  }
}