{
  "type": "Feature",
  "properties": {
    "name": "Rzekuń",
    "country": "PL",
    "subdivision": "78",
    "timezone": "Europe/Warsaw"
  },
  "geometry": {
    "type": "Point",
    "coordinates": [
      21.62069,
      53.04756
    ]
  }
}