{
  "type": "Feature",
  "properties": {
    "name": "Sochocin",
    "country": "PL",
    "subdivision": "78",
    "timezone": "Europe/Warsaw"
  },
  "geometry": {
    "type": "Point",
    "coordinates": [
      20.47259,
      52.68715
    ]
  }
}