{
  "type": "Feature",
  "properties": {
    "name": "Strzegowo",
    "country": "PL",
    "subdivision": "78",
    "timezone": "Europe/Warsaw"
  },
  "geometry": {
    "type": "Point",
    "coordinates": [
      20.28548,
      52.89394
    ]
  }
}