{
  "type": "Feature",
  "properties": {
    "name": "Teresin",
    "country": "PL",
    "subdivision": "78",
    "timezone": "Europe/Warsaw"
  },
  "geometry": {
    "type": "Point",
    "coordinates": [
      20.41672,
      52.19887
    ]
  }
}