{
  "type": "Feature",
  "properties": {
    "name": "Zbuczyn",
    "country": "PL",
    "subdivision": "78",
    "timezone": "Europe/Warsaw"
  },
  "geometry": {
    "type": "Point",
    "coordinates": [
      22.43829,
      52.08974
    ]
  }
}