{
  "type": "Feature",
  "properties": {
    "name": "Łajski",
    "country": "PL",
    "subdivision": "78",
    "timezone": "Europe/Warsaw"
  },
  "geometry": {
    "type": "Point",
    "coordinates": [
      20.94946,
      52.42873
    ]
  }
}