{
  "type": "Feature",
  "properties": {
    "name": "Łochów",
    "country": "PL",
    "subdivision": "78",
    "timezone": "Europe/Warsaw"
  },
  "geometry": {
    "type": "Point",
    "coordinates": [
      21.68158,
      52.53076
    ]
  }
}