{
  "type": "Feature",
  "properties": {
    "name": "Alagoinhas",
    "country": "BR",
    "subdivision": "05",
    "timezone": "America/Bahia"
  },
  "geometry": {
    "type": "Point",
    "coordinates": [
      -38.41917,
      -12.13556
    ]
  }
}