{
  "type": "Feature",
  "properties": {
    "name": "Camamu",
    "country": "BR",
    "subdivision": "05",
    "timezone": "America/Bahia"
  },
  "geometry": {
    "type": "Point",
    "coordinates": [
      -39.10389,
      -13.94472
    ]
  }
}