{
  "type": "Feature",
  "properties": {
    "name": "Cipó",
    "country": "BR",
    "subdivision": "05",
    "timezone": "America/Bahia"
  },
  "geometry": {
    "type": "Point",
    "coordinates": [
      -38.51361,
      -11.09972
    ]
  }
}