{
  "type": "Feature",
  "properties": {
    "name": "Conceição do Coité",
    "country": "BR",
    "subdivision": "05",
    "timezone": "America/Bahia"
  },
  "geometry": {
    "type": "Point",
    "coordinates": [
      -39.28278,
      -11.56389
    ]
  }
}