{
  "type": "Feature",
  "properties": {
    "name": "Conde",
    "country": "BR",
    "subdivision": "05",
    "timezone": "America/Bahia"
  },
  "geometry": {
    "type": "Point",
    "coordinates": [
      -37.61056,
      -11.81361
    ]
  }
}