{
  "type": "Feature",
  "properties": {
    "name": "Entre Rios",
    "country": "BR",
    "subdivision": "05",
    "timezone": "America/Bahia"
  },
  "geometry": {
    "type": "Point",
    "coordinates": [
      -38.08444,
      -11.94194
    ]
  }
}