{
  "type": "Feature",
  "properties": {
    "name": "Guaratinga",
    "country": "BR",
    "subdivision": "05",
    "timezone": "America/Bahia"
  },
  "geometry": {
    "type": "Point",
    "coordinates": [
      -39.78189,
      -16.58564
    ]
  }
}