{
  "type": "Feature",
  "properties": {
    "name": "Ibicuí",
    "country": "BR",
    "subdivision": "05",
    "timezone": "America/Bahia"
  },
  "geometry": {
    "type": "Point",
    "coordinates": [
      -39.98667,
      -14.84167
    ]
  }
}