{
  "type": "Feature",
  "properties": {
    "name": "Ibipeba",
    "country": "BR",
    "subdivision": "05",
    "timezone": "America/Bahia"
  },
  "geometry": {
    "type": "Point",
    "coordinates": [
      -42.01111,
      -11.64083
    ]
  }
}