{
  "type": "Feature",
  "properties": {
    "name": "Itacaré",
    "country": "BR",
    "subdivision": "05",
    "timezone": "America/Bahia"
  },
  "geometry": {
    "type": "Point",
    "coordinates": [
      -38.99584,
      -14.2789
    ]
  }
}