{
  "type": "Feature",
  "properties": {
    "name": "Itagi",
    "country": "BR",
    "subdivision": "05",
    "timezone": "America/Bahia"
  },
  "geometry": {
    "type": "Point",
    "coordinates": [
      -40.00611,
      -14.16278
    ]
  }
}