{
  "type": "Feature",
  "properties": {
    "name": "Itajuípe",
    "country": "BR",
    "subdivision": "05",
    "timezone": "America/Bahia"
  },
  "geometry": {
    "type": "Point",
    "coordinates": [
      -39.375,
      -14.67806
    ]
  }
}