{
  "type": "Feature",
  "properties": {
    "name": "Maracás",
    "country": "BR",
    "subdivision": "05",
    "timezone": "America/Bahia"
  },
  "geometry": {
    "type": "Point",
    "coordinates": [
      -40.43083,
      -13.44111
    ]
  }
}