{
  "type": "Feature",
  "properties": {
    "name": "Miguel Calmon",
    "country": "BR",
    "subdivision": "05",
    "timezone": "America/Bahia"
  },
  "geometry": {
    "type": "Point",
    "coordinates": [
      -40.595,
      -11.42889
    ]
  }
}