{
  "type": "Feature",
  "properties": {
    "name": "Muritiba",
    "country": "BR",
    "subdivision": "05",
    "timezone": "America/Bahia"
  },
  "geometry": {
    "type": "Point",
    "coordinates": [
      -39.25,
      -12.91667
    ]
  }
}