{
  "type": "Feature",
  "properties": {
    "name": "Ribeira do Pombal",
    "country": "BR",
    "subdivision": "05",
    "timezone": "America/Bahia"
  },
  "geometry": {
    "type": "Point",
    "coordinates": [
      -38.53583,
      -10.83444
    ]
  }
}