{
  "type": "Feature",
  "properties": {
    "name": "São Felipe",
    "country": "BR",
    "subdivision": "05",
    "timezone": "America/Bahia"
  },
  "geometry": {
    "type": "Point",
    "coordinates": [
      -41.39174,
      -14.8386
    ]
  }
}