{
  "type": "Feature",
  "properties": {
    "name": "Tapiramutá",
    "country": "BR",
    "subdivision": "05",
    "timezone": "America/Bahia"
  },
  "geometry": {
    "type": "Point",
    "coordinates": [
      -40.79139,
      -11.84722
    ]
  }
}