{
  "type": "Feature",
  "properties": {
    "name": "Ubatã",
    "country": "BR",
    "subdivision": "05",
    "timezone": "America/Bahia"
  },
  "geometry": {
    "type": "Point",
    "coordinates": [
      -39.52641,
      -14.20906
    ]
  }
}