{
  "type": "Feature",
  "properties": {
    "name": "Una",
    "country": "BR",
    "subdivision": "05",
    "timezone": "America/Bahia"
  },
  "geometry": {
    "type": "Point",
    "coordinates": [
      -39.07528,
      -15.29333
    ]
  }
}