{
  "type": "Feature",
  "properties": {
    "name": "Valença",
    "country": "BR",
    "subdivision": "05",
    "timezone": "America/Bahia"
  },
  "geometry": {
    "type": "Point",
    "coordinates": [
      -39.07306,
      -13.37028
    ]
  }
}