{
  "type": "Feature",
  "properties": {
    "name": "Petropavl",
    "country": "KZ",
    "subdivision": "16",
    "timezone": "Asia/Almaty"
  },
  "geometry": {
    "type": "Point",
    "coordinates": [
      69.15,
      54.86667
    ]
  }
}