{
  "type": "Feature",
  "properties": {
    "name": "Timiryazevo",
    "country": "KZ",
    "subdivision": "16",
    "timezone": "Asia/Almaty"
  },
  "geometry": {
    "type": "Point",
    "coordinates": [
      66.48852,
      53.74947
    ]
  }
}