{
  "type": "Feature",
  "properties": {
    "name": "Benitez",
    "country": "PR",
    "subdivision": "029",
    "timezone": "America/Puerto_Rico"
  },
  "geometry": {
    "type": "Point",
    "coordinates": [
      -65.87905,
      18.27357
    ]
  }
}