{
  "type": "Feature",
  "properties": {
    "name": "San Kamphaeng",
    "country": "TH",
    "subdivision": "02",
    "timezone": "Asia/Bangkok"
  },
  "geometry": {
    "type": "Point",
    "coordinates": [
      99.11953,
      18.74486
    ]
  }
}