{
  "type": "Feature",
  "properties": {
    "name": "Taungoo",
    "country": "MM",
    "subdivision": "16",
    "timezone": "Asia/Yangon"
  },
  "geometry": {
    "type": "Point",
    "coordinates": [
      96.43408,
      18.94291
    ]
  }
}