{
  "type": "Feature",
  "properties": {
    "name": "Beni Saf",
    "country": "DZ",
    "subdivision": "36",
    "timezone": "Africa/Algiers"
  },
  "geometry": {
    "type": "Point",
    "coordinates": [
      -1.38226,
      35.30099
    ]
  }
}