{
  "type": "Feature",
  "properties": {
    "name": "El Malah",
    "country": "DZ",
    "subdivision": "36",
    "timezone": "Africa/Algiers"
  },
  "geometry": {
    "type": "Point",
    "coordinates": [
      -1.09238,
      35.39137
    ]
  }
}