{
  "type": "Feature",
  "properties": {
    "name": "Ramotswa",
    "country": "BW",
    "subdivision": "09",
    "timezone": "Africa/Gaborone"
  },
  "geometry": {
    "type": "Point",
    "coordinates": [
      25.86989,
      -24.87158
    ]
  }
}