{
  "type": "Feature",
  "properties": {
    "name": "Carhuamayo",
    "country": "PE",
    "subdivision": "12",
    "timezone": "America/Lima"
  },
  "geometry": {
    "type": "Point",
    "coordinates": [
      -76.03333,
      -10.91667
    ]
  }
}