{
  "type": "Feature",
  "properties": {
    "name": "Chupaca",
    "country": "PE",
    "subdivision": "12",
    "timezone": "America/Lima"
  },
  "geometry": {
    "type": "Point",
    "coordinates": [
      -75.28333,
      -12.06667
    ]
  }
}