{
  "type": "Feature",
  "properties": {
    "name": "Huamancaca Chico",
    "country": "PE",
    "subdivision": "12",
    "timezone": "America/Lima"
  },
  "geometry": {
    "type": "Point",
    "coordinates": [
      -75.24523,
      -12.07993
    ]
  }
}