{
  "type": "Feature",
  "properties": {
    "name": "Jauja",
    "country": "PE",
    "subdivision": "12",
    "timezone": "America/Lima"
  },
  "geometry": {
    "type": "Point",
    "coordinates": [
      -75.49656,
      -11.77584
    ]
  }
}