{
  "type": "Feature",
  "properties": {
    "name": "Mazamari",
    "country": "PE",
    "subdivision": "12",
    "timezone": "America/Lima"
  },
  "geometry": {
    "type": "Point",
    "coordinates": [
      -74.53083,
      -11.32583
    ]
  }
}