{
  "type": "Feature",
  "properties": {
    "name": "Satipo",
    "country": "PE",
    "subdivision": "12",
    "timezone": "America/Lima"
  },
  "geometry": {
    "type": "Point",
    "coordinates": [
      -74.63861,
      -11.25222
    ]
  }
}