{
  "type": "Feature",
  "properties": {
    "name": "Beaumont-sur-Oise",
    "country": "FR",
    "subdivision": "11",
    "timezone": "Europe/Paris"
  },
  "geometry": {
    "type": "Point",
    "coordinates": [
      2.28705,
      49.14232
    ]
  }
}