{
  "type": "Feature",
  "properties": {
    "name": "Bois-d'Arcy",
    "country": "FR",
    "subdivision": "11",
    "timezone": "Europe/Paris"
  },
  "geometry": {
    "type": "Point",
    "coordinates": [
      2.02325,
      48.79966
    ]
  }
}