{
  "type": "Feature",
  "properties": {
    "name": "Bougival",
    "country": "FR",
    "subdivision": "11",
    "timezone": "Europe/Paris"
  },
  "geometry": {
    "type": "Point",
    "coordinates": [
      2.14148,
      48.86223
    ]
  }
}