{
  "type": "Feature",
  "properties": {
    "name": "Bouray-sur-Juine",
    "country": "FR",
    "subdivision": "11",
    "timezone": "Europe/Paris"
  },
  "geometry": {
    "type": "Point",
    "coordinates": [
      2.30001,
      48.51981
    ]
  }
}