{
  "type": "Feature",
  "properties": {
    "name": "Bray-sur-Seine",
    "country": "FR",
    "subdivision": "11",
    "timezone": "Europe/Paris"
  },
  "geometry": {
    "type": "Point",
    "coordinates": [
      3.23852,
      48.41371
    ]
  }
}