{
  "type": "Feature",
  "properties": {
    "name": "Brie-Comte-Robert",
    "country": "FR",
    "subdivision": "11",
    "timezone": "Europe/Paris"
  },
  "geometry": {
    "type": "Point",
    "coordinates": [
      2.6109,
      48.69247
    ]
  }
}