{
  "type": "Feature",
  "properties": {
    "name": "Brunoy",
    "country": "FR",
    "subdivision": "11",
    "timezone": "Europe/Paris"
  },
  "geometry": {
    "type": "Point",
    "coordinates": [
      2.49223,
      48.6942
    ]
  }
}