{
  "type": "Feature",
  "properties": {
    "name": "Bullion",
    "country": "FR",
    "subdivision": "11",
    "timezone": "Europe/Paris"
  },
  "geometry": {
    "type": "Point",
    "coordinates": [
      1.99024,
      48.62285
    ]
  }
}