{
  "type": "Feature",
  "properties": {
    "name": "Bures-sur-Yvette",
    "country": "FR",
    "subdivision": "11",
    "timezone": "Europe/Paris"
  },
  "geometry": {
    "type": "Point",
    "coordinates": [
      2.17064,
      48.69981
    ]
  }
}