{
  "type": "Feature",
  "properties": {
    "name": "Chailly-en-Brie",
    "country": "FR",
    "subdivision": "11",
    "timezone": "Europe/Paris"
  },
  "geometry": {
    "type": "Point",
    "coordinates": [
      3.12453,
      48.79006
    ]
  }
}