{
  "type": "Feature",
  "properties": {
    "name": "Champlan",
    "country": "FR",
    "subdivision": "11",
    "timezone": "Europe/Paris"
  },
  "geometry": {
    "type": "Point",
    "coordinates": [
      2.27975,
      48.70823
    ]
  }
}