{
  "type": "Feature",
  "properties": {
    "name": "Chauconin-Neufmontiers",
    "country": "FR",
    "subdivision": "11",
    "timezone": "Europe/Paris"
  },
  "geometry": {
    "type": "Point",
    "coordinates": [
      2.85,
      48.96667
    ]
  }
}