{
  "type": "Feature",
  "properties": {
    "name": "Chaville",
    "country": "FR",
    "subdivision": "11",
    "timezone": "Europe/Paris"
  },
  "geometry": {
    "type": "Point",
    "coordinates": [
      2.18864,
      48.80565
    ]
  }
}