{
  "type": "Feature",
  "properties": {
    "name": "Chevannes",
    "country": "FR",
    "subdivision": "11",
    "timezone": "Europe/Paris"
  },
  "geometry": {
    "type": "Point",
    "coordinates": [
      2.44388,
      48.53259
    ]
  }
}