{
  "type": "Feature",
  "properties": {
    "name": "Chilly-Mazarin",
    "country": "FR",
    "subdivision": "11",
    "timezone": "Europe/Paris"
  },
  "geometry": {
    "type": "Point",
    "coordinates": [
      2.31638,
      48.71489
    ]
  }
}