{
  "type": "Feature",
  "properties": {
    "name": "Clichy-sous-Bois",
    "country": "FR",
    "subdivision": "11",
    "timezone": "Europe/Paris"
  },
  "geometry": {
    "type": "Point",
    "coordinates": [
      2.55323,
      48.9102
    ]
  }
}