{
  "type": "Feature",
  "properties": {
    "name": "Coupvray",
    "country": "FR",
    "subdivision": "11",
    "timezone": "Europe/Paris"
  },
  "geometry": {
    "type": "Point",
    "coordinates": [
      2.7967,
      48.89289
    ]
  }
}