{
  "type": "Feature",
  "properties": {
    "name": "Courdimanche",
    "country": "FR",
    "subdivision": "11",
    "timezone": "Europe/Paris"
  },
  "geometry": {
    "type": "Point",
    "coordinates": [
      2.00096,
      49.03513
    ]
  }
}