{
  "type": "Feature",
  "properties": {
    "name": "Courcouronnes",
    "country": "FR",
    "subdivision": "11",
    "timezone": "Europe/Paris"
  },
  "geometry": {
    "type": "Point",
    "coordinates": [
      2.40762,
      48.61429
    ]
  }
}