{
  "type": "Feature",
  "properties": {
    "name": "Émerainville",
    "country": "FR",
    "subdivision": "11",
    "timezone": "Europe/Paris"
  },
  "geometry": {
    "type": "Point",
    "coordinates": [
      2.62139,
      48.81276
    ]
  }
}