{
  "type": "Feature",
  "properties": {
    "name": "Feucherolles",
    "country": "FR",
    "subdivision": "11",
    "timezone": "Europe/Paris"
  },
  "geometry": {
    "type": "Point",
    "coordinates": [
      1.97402,
      48.87002
    ]
  }
}