{
  "type": "Feature",
  "properties": {
    "name": "Fontenay-le-Fleury",
    "country": "FR",
    "subdivision": "11",
    "timezone": "Europe/Paris"
  },
  "geometry": {
    "type": "Point",
    "coordinates": [
      2.04863,
      48.81253
    ]
  }
}