{
  "type": "Feature",
  "properties": {
    "name": "Forges-les-Bains",
    "country": "FR",
    "subdivision": "11",
    "timezone": "Europe/Paris"
  },
  "geometry": {
    "type": "Point",
    "coordinates": [
      2.10264,
      48.62942
    ]
  }
}