{
  "type": "Feature",
  "properties": {
    "name": "Fourqueux",
    "country": "FR",
    "subdivision": "11",
    "timezone": "Europe/Paris"
  },
  "geometry": {
    "type": "Point",
    "coordinates": [
      2.06367,
      48.88693
    ]
  }
}