{
  "type": "Feature",
  "properties": {
    "name": "Franconville",
    "country": "FR",
    "subdivision": "11",
    "timezone": "Europe/Paris"
  },
  "geometry": {
    "type": "Point",
    "coordinates": [
      2.23333,
      48.98333
    ]
  }
}