{
  "type": "Feature",
  "properties": {
    "name": "Juilly",
    "country": "FR",
    "subdivision": "11",
    "timezone": "Europe/Paris"
  },
  "geometry": {
    "type": "Point",
    "coordinates": [
      2.70563,
      49.01375
    ]
  }
}