{
  "type": "Feature",
  "properties": {
    "name": "Juvisy-sur-Orge",
    "country": "FR",
    "subdivision": "11",
    "timezone": "Europe/Paris"
  },
  "geometry": {
    "type": "Point",
    "coordinates": [
      2.38333,
      48.68333
    ]
  }
}