{
  "type": "Feature",
  "properties": {
    "name": "La Celle-sur-Morin",
    "country": "FR",
    "subdivision": "11",
    "timezone": "Europe/Paris"
  },
  "geometry": {
    "type": "Point",
    "coordinates": [
      2.96921,
      48.81146
    ]
  }
}