{
  "type": "Feature",
  "properties": {
    "name": "La Celle-Saint-Cloud",
    "country": "FR",
    "subdivision": "11",
    "timezone": "Europe/Paris"
  },
  "geometry": {
    "type": "Point",
    "coordinates": [
      2.14523,
      48.85029
    ]
  }
}