{
  "type": "Feature",
  "properties": {
    "name": "La Ville-du-Bois",
    "country": "FR",
    "subdivision": "11",
    "timezone": "Europe/Paris"
  },
  "geometry": {
    "type": "Point",
    "coordinates": [
      2.26833,
      48.65521
    ]
  }
}