{
  "type": "Feature",
  "properties": {
    "name": "Le Blanc-Mesnil",
    "country": "FR",
    "subdivision": "11",
    "timezone": "Europe/Paris"
  },
  "geometry": {
    "type": "Point",
    "coordinates": [
      2.46138,
      48.93872
    ]
  }
}