{
  "type": "Feature",
  "properties": {
    "name": "Le Port-Marly",
    "country": "FR",
    "subdivision": "11",
    "timezone": "Europe/Paris"
  },
  "geometry": {
    "type": "Point",
    "coordinates": [
      2.11139,
      48.89016
    ]
  }
}