{
  "type": "Feature",
  "properties": {
    "name": "Les Mureaux",
    "country": "FR",
    "subdivision": "11",
    "timezone": "Europe/Paris"
  },
  "geometry": {
    "type": "Point",
    "coordinates": [
      1.90972,
      48.99173
    ]
  }
}