{
  "type": "Feature",
  "properties": {
    "name": "Lieusaint",
    "country": "FR",
    "subdivision": "11",
    "timezone": "Europe/Paris"
  },
  "geometry": {
    "type": "Point",
    "coordinates": [
      2.54806,
      48.63476
    ]
  }
}