{
  "type": "Feature",
  "properties": {
    "name": "Longnes",
    "country": "FR",
    "subdivision": "11",
    "timezone": "Europe/Paris"
  },
  "geometry": {
    "type": "Point",
    "coordinates": [
      1.58705,
      48.92002
    ]
  }
}