{
  "type": "Feature",
  "properties": {
    "name": "Magnanville",
    "country": "FR",
    "subdivision": "11",
    "timezone": "Europe/Paris"
  },
  "geometry": {
    "type": "Point",
    "coordinates": [
      1.67842,
      48.96798
    ]
  }
}