{
  "type": "Feature",
  "properties": {
    "name": "Magny-en-Vexin",
    "country": "FR",
    "subdivision": "11",
    "timezone": "Europe/Paris"
  },
  "geometry": {
    "type": "Point",
    "coordinates": [
      1.78669,
      49.15515
    ]
  }
}