{
  "type": "Feature",
  "properties": {
    "name": "Moisenay",
    "country": "FR",
    "subdivision": "11",
    "timezone": "Europe/Paris"
  },
  "geometry": {
    "type": "Point",
    "coordinates": [
      2.73527,
      48.56266
    ]
  }
}