{
  "type": "Feature",
  "properties": {
    "name": "Montsoult",
    "country": "FR",
    "subdivision": "11",
    "timezone": "Europe/Paris"
  },
  "geometry": {
    "type": "Point",
    "coordinates": [
      2.31966,
      49.06942
    ]
  }
}