{
  "type": "Feature",
  "properties": {
    "name": "Montry",
    "country": "FR",
    "subdivision": "11",
    "timezone": "Europe/Paris"
  },
  "geometry": {
    "type": "Point",
    "coordinates": [
      2.82915,
      48.88409
    ]
  }
}