{
  "type": "Feature",
  "properties": {
    "name": "Montereau-Fault-Yonne",
    "country": "FR",
    "subdivision": "11",
    "timezone": "Europe/Paris"
  },
  "geometry": {
    "type": "Point",
    "coordinates": [
      2.95,
      48.38333
    ]
  }
}