{
  "type": "Feature",
  "properties": {
    "name": "Montigny-Lencoup",
    "country": "FR",
    "subdivision": "11",
    "timezone": "Europe/Paris"
  },
  "geometry": {
    "type": "Point",
    "coordinates": [
      3.06503,
      48.45162
    ]
  }
}