{
  "type": "Feature",
  "properties": {
    "name": "Moussy-le-Vieux",
    "country": "FR",
    "subdivision": "11",
    "timezone": "Europe/Paris"
  },
  "geometry": {
    "type": "Point",
    "coordinates": [
      2.62493,
      49.04712
    ]
  }
}