{
  "type": "Feature",
  "properties": {
    "name": "Ormesson-sur-Marne",
    "country": "FR",
    "subdivision": "11",
    "timezone": "Europe/Paris"
  },
  "geometry": {
    "type": "Point",
    "coordinates": [
      2.54471,
      48.7863
    ]
  }
}