{
  "type": "Feature",
  "properties": {
    "name": "Othis",
    "country": "FR",
    "subdivision": "11",
    "timezone": "Europe/Paris"
  },
  "geometry": {
    "type": "Point",
    "coordinates": [
      2.67502,
      49.07387
    ]
  }
}