{
  "type": "Feature",
  "properties": {
    "name": "Ozouer-le-Voulgis",
    "country": "FR",
    "subdivision": "11",
    "timezone": "Europe/Paris"
  },
  "geometry": {
    "type": "Point",
    "coordinates": [
      2.77409,
      48.66012
    ]
  }
}