{
  "type": "Feature",
  "properties": {
    "name": "Parmain",
    "country": "FR",
    "subdivision": "11",
    "timezone": "Europe/Paris"
  },
  "geometry": {
    "type": "Point",
    "coordinates": [
      2.21487,
      49.11247
    ]
  }
}