{
  "type": "Feature",
  "properties": {
    "name": "Poissy",
    "country": "FR",
    "subdivision": "11",
    "timezone": "Europe/Paris"
  },
  "geometry": {
    "type": "Point",
    "coordinates": [
      2.04952,
      48.92902
    ]
  }
}