{
  "type": "Feature",
  "properties": {
    "name": "Quincy-sous-Sénart",
    "country": "FR",
    "subdivision": "11",
    "timezone": "Europe/Paris"
  },
  "geometry": {
    "type": "Point",
    "coordinates": [
      2.53419,
      48.67294
    ]
  }
}