{
  "type": "Feature",
  "properties": {
    "name": "Romainville",
    "country": "FR",
    "subdivision": "11",
    "timezone": "Europe/Paris"
  },
  "geometry": {
    "type": "Point",
    "coordinates": [
      2.43482,
      48.8854
    ]
  }
}