{
  "type": "Feature",
  "properties": {
    "name": "Rozay-en-Brie",
    "country": "FR",
    "subdivision": "11",
    "timezone": "Europe/Paris"
  },
  "geometry": {
    "type": "Point",
    "coordinates": [
      2.95816,
      48.68333
    ]
  }
}