{
  "type": "Feature",
  "properties": {
    "name": "Saint-Cloud",
    "country": "FR",
    "subdivision": "11",
    "timezone": "Europe/Paris"
  },
  "geometry": {
    "type": "Point",
    "coordinates": [
      2.20289,
      48.84598
    ]
  }
}