{
  "type": "Feature",
  "properties": {
    "name": "Saint-Germain-de-la-Grange",
    "country": "FR",
    "subdivision": "11",
    "timezone": "Europe/Paris"
  },
  "geometry": {
    "type": "Point",
    "coordinates": [
      1.89884,
      48.83436
    ]
  }
}