{
  "type": "Feature",
  "properties": {
    "name": "Saint-Maur-des-Fossés",
    "country": "FR",
    "subdivision": "11",
    "timezone": "Europe/Paris"
  },
  "geometry": {
    "type": "Point",
    "coordinates": [
      2.49323,
      48.79395
    ]
  }
}