{
  "type": "Feature",
  "properties": {
    "name": "Saintry-sur-Seine",
    "country": "FR",
    "subdivision": "11",
    "timezone": "Europe/Paris"
  },
  "geometry": {
    "type": "Point",
    "coordinates": [
      2.49515,
      48.5964
    ]
  }
}