{
  "type": "Feature",
  "properties": {
    "name": "Salins",
    "country": "FR",
    "subdivision": "11",
    "timezone": "Europe/Paris"
  },
  "geometry": {
    "type": "Point",
    "coordinates": [
      3.0213,
      48.42156
    ]
  }
}