{
  "type": "Feature",
  "properties": {
    "name": "Samoreau",
    "country": "FR",
    "subdivision": "11",
    "timezone": "Europe/Paris"
  },
  "geometry": {
    "type": "Point",
    "coordinates": [
      2.75587,
      48.42946
    ]
  }
}