{
  "type": "Feature",
  "properties": {
    "name": "Seine-Port",
    "country": "FR",
    "subdivision": "11",
    "timezone": "Europe/Paris"
  },
  "geometry": {
    "type": "Point",
    "coordinates": [
      2.55316,
      48.55743
    ]
  }
}