{
  "type": "Feature",
  "properties": {
    "name": "Soisy-sur-École",
    "country": "FR",
    "subdivision": "11",
    "timezone": "Europe/Paris"
  },
  "geometry": {
    "type": "Point",
    "coordinates": [
      2.49301,
      48.47637
    ]
  }
}