{
  "type": "Feature",
  "properties": {
    "name": "Survilliers",
    "country": "FR",
    "subdivision": "11",
    "timezone": "Europe/Paris"
  },
  "geometry": {
    "type": "Point",
    "coordinates": [
      2.54449,
      49.09712
    ]
  }
}