{
  "type": "Feature",
  "properties": {
    "name": "Thiverval-Grignon",
    "country": "FR",
    "subdivision": "11",
    "timezone": "Europe/Paris"
  },
  "geometry": {
    "type": "Point",
    "coordinates": [
      1.91729,
      48.84964
    ]
  }
}