{
  "type": "Feature",
  "properties": {
    "name": "Vaucresson",
    "country": "FR",
    "subdivision": "11",
    "timezone": "Europe/Paris"
  },
  "geometry": {
    "type": "Point",
    "coordinates": [
      2.15652,
      48.84078
    ]
  }
}