{
  "type": "Feature",
  "properties": {
    "name": "Vauhallan",
    "country": "FR",
    "subdivision": "11",
    "timezone": "Europe/Paris"
  },
  "geometry": {
    "type": "Point",
    "coordinates": [
      2.20277,
      48.73354
    ]
  }
}