{
  "type": "Feature",
  "properties": {
    "name": "Vaux-le-Pénil",
    "country": "FR",
    "subdivision": "11",
    "timezone": "Europe/Paris"
  },
  "geometry": {
    "type": "Point",
    "coordinates": [
      2.69165,
      48.52803
    ]
  }
}