{
  "type": "Feature",
  "properties": {
    "name": "Vert-le-Petit",
    "country": "FR",
    "subdivision": "11",
    "timezone": "Europe/Paris"
  },
  "geometry": {
    "type": "Point",
    "coordinates": [
      2.36526,
      48.55163
    ]
  }
}