{
  "type": "Feature",
  "properties": {
    "name": "Villecresnes",
    "country": "FR",
    "subdivision": "11",
    "timezone": "Europe/Paris"
  },
  "geometry": {
    "type": "Point",
    "coordinates": [
      2.5394,
      48.72002
    ]
  }
}