{
  "type": "Feature",
  "properties": {
    "name": "Villiers-le-Bel",
    "country": "FR",
    "subdivision": "11",
    "timezone": "Europe/Paris"
  },
  "geometry": {
    "type": "Point",
    "coordinates": [
      2.39819,
      49.00875
    ]
  }
}