{
  "type": "Feature",
  "properties": {
    "name": "Villejuif",
    "country": "FR",
    "subdivision": "11",
    "timezone": "Europe/Paris"
  },
  "geometry": {
    "type": "Point",
    "coordinates": [
      2.35992,
      48.7939
    ]
  }
}