{
  "type": "Feature",
  "properties": {
    "name": "Vincennes",
    "country": "FR",
    "subdivision": "11",
    "timezone": "Europe/Paris"
  },
  "geometry": {
    "type": "Point",
    "coordinates": [
      2.43769,
      48.8486
    ]
  }
}