{
  "type": "Feature",
  "properties": {
    "name": "Voisenon",
    "country": "FR",
    "subdivision": "11",
    "timezone": "Europe/Paris"
  },
  "geometry": {
    "type": "Point",
    "coordinates": [
      2.6648,
      48.5717
    ]
  }
}