{
  "type": "Feature",
  "properties": {
    "name": "Voulx",
    "country": "FR",
    "subdivision": "11",
    "timezone": "Europe/Paris"
  },
  "geometry": {
    "type": "Point",
    "coordinates": [
      2.96747,
      48.28204
    ]
  }
}