{
  "type": "Feature",
  "properties": {
    "name": "Voulangis",
    "country": "FR",
    "subdivision": "11",
    "timezone": "Europe/Paris"
  },
  "geometry": {
    "type": "Point",
    "coordinates": [
      2.89558,
      48.85252
    ]
  }
}