{
  "type": "Feature",
  "properties": {
    "name": "Bang Phae",
    "country": "TH",
    "subdivision": "52",
    "timezone": "Asia/Bangkok"
  },
  "geometry": {
    "type": "Point",
    "coordinates": [
      99.92982,
      13.69157
    ]
  }
}