{
  "type": "Feature",
  "properties": {
    "name": "Aghavnatun",
    "country": "AM",
    "subdivision": "03",
    "timezone": "Asia/Yerevan"
  },
  "geometry": {
    "type": "Point",
    "coordinates": [
      44.25295,
      40.2333
    ]
  }
}