{
  "type": "Feature",
  "properties": {
    "name": "Armavir",
    "country": "AM",
    "subdivision": "03",
    "timezone": "Asia/Yerevan"
  },
  "geometry": {
    "type": "Point",
    "coordinates": [
      44.03815,
      40.15446
    ]
  }
}