{
  "type": "Feature",
  "properties": {
    "name": "Aygek",
    "country": "AM",
    "subdivision": "03",
    "timezone": "Asia/Yerevan"
  },
  "geometry": {
    "type": "Point",
    "coordinates": [
      44.38611,
      40.1889
    ]
  }
}