{
  "type": "Feature",
  "properties": {
    "name": "Griboyedov",
    "country": "AM",
    "subdivision": "03",
    "timezone": "Asia/Yerevan"
  },
  "geometry": {
    "type": "Point",
    "coordinates": [
      44.27169,
      40.11307
    ]
  }
}