{
  "type": "Feature",
  "properties": {
    "name": "Merdzavan",
    "country": "AM",
    "subdivision": "03",
    "timezone": "Asia/Yerevan"
  },
  "geometry": {
    "type": "Point",
    "coordinates": [
      44.40033,
      40.1814
    ]
  }
}