{
  "type": "Feature",
  "properties": {
    "name": "Sardarapat",
    "country": "AM",
    "subdivision": "03",
    "timezone": "Asia/Yerevan"
  },
  "geometry": {
    "type": "Point",
    "coordinates": [
      44.00969,
      40.13206
    ]
  }
}