{
  "type": "Feature",
  "properties": {
    "name": "Shenavan",
    "country": "AM",
    "subdivision": "03",
    "timezone": "Asia/Yerevan"
  },
  "geometry": {
    "type": "Point",
    "coordinates": [
      43.93048,
      40.05548
    ]
  }
}