{
  "type": "Feature",
  "properties": {
    "name": "Tsaghkunk’",
    "country": "AM",
    "subdivision": "03",
    "timezone": "Asia/Yerevan"
  },
  "geometry": {
    "type": "Point",
    "coordinates": [
      44.27228,
      40.18048
    ]
  }
}