{
  "type": "Feature",
  "properties": {
    "name": "Vagharshapat",
    "country": "AM",
    "subdivision": "03",
    "timezone": "Asia/Yerevan"
  },
  "geometry": {
    "type": "Point",
    "coordinates": [
      44.29462,
      40.16557
    ]
  }
}