{
  "type": "Feature",
  "properties": {
    "name": "Revúca",
    "country": "SK",
    "subdivision": "01",
    "timezone": "Europe/Bratislava"
  },
  "geometry": {
    "type": "Point",
    "coordinates": [
      20.11734,
      48.68346
    ]
  }
}