{
  "type": "Feature",
  "properties": {
    "name": "Svätý Anton",
    "country": "SK",
    "subdivision": "01",
    "timezone": "Europe/Bratislava"
  },
  "geometry": {
    "type": "Point",
    "coordinates": [
      18.9401,
      48.41923
    ]
  }
}