{
  "type": "Feature",
  "properties": {
    "name": "Forchtenstein",
    "country": "AT",
    "subdivision": "01",
    "timezone": "Europe/Vienna"
  },
  "geometry": {
    "type": "Point",
    "coordinates": [
      16.34525,
      47.71161
    ]
  }
}