{
  "type": "Feature",
  "properties": {
    "name": "Gattendorf",
    "country": "AT",
    "subdivision": "01",
    "timezone": "Europe/Vienna"
  },
  "geometry": {
    "type": "Point",
    "coordinates": [
      16.98333,
      48.01667
    ]
  }
}