{
  "type": "Feature",
  "properties": {
    "name": "Leithaprodersdorf",
    "country": "AT",
    "subdivision": "01",
    "timezone": "Europe/Vienna"
  },
  "geometry": {
    "type": "Point",
    "coordinates": [
      16.47915,
      47.93348
    ]
  }
}