{
  "type": "Feature",
  "properties": {
    "name": "Litzelsdorf",
    "country": "AT",
    "subdivision": "01",
    "timezone": "Europe/Vienna"
  },
  "geometry": {
    "type": "Point",
    "coordinates": [
      16.1717,
      47.20826
    ]
  }
}