{
  "type": "Feature",
  "properties": {
    "name": "Stegersbach",
    "country": "AT",
    "subdivision": "01",
    "timezone": "Europe/Vienna"
  },
  "geometry": {
    "type": "Point",
    "coordinates": [
      16.16667,
      47.16667
    ]
  }
}