{
  "type": "Feature",
  "properties": {
    "name": "Stoob",
    "country": "AT",
    "subdivision": "01",
    "timezone": "Europe/Vienna"
  },
  "geometry": {
    "type": "Point",
    "coordinates": [
      16.4776,
      47.52845
    ]
  }
}