{
  "type": "Feature",
  "properties": {
    "name": "Libertad",
    "country": "UY",
    "subdivision": "16",
    "timezone": "America/Montevideo"
  },
  "geometry": {
    "type": "Point",
    "coordinates": [
      -56.61739,
      -34.63459
    ]
  }
}