{
  "type": "Feature",
  "properties": {
    "name": "Muriti",
    "country": "TZ",
    "subdivision": "08",
    "timezone": "Africa/Dar_es_Salaam"
  },
  "geometry": {
    "type": "Point",
    "coordinates": [
      32.91667,
      -1.98333
    ]
  }
}