{
  "type": "Feature",
  "properties": {
    "name": "Sirari",
    "country": "TZ",
    "subdivision": "08",
    "timezone": "Africa/Dar_es_Salaam"
  },
  "geometry": {
    "type": "Point",
    "coordinates": [
      34.47596,
      -1.25367
    ]
  }
}