{
  "type": "Feature",
  "properties": {
    "name": "Ad Dānā",
    "country": "SY",
    "subdivision": "12",
    "timezone": "Asia/Damascus"
  },
  "geometry": {
    "type": "Point",
    "coordinates": [
      36.76998,
      36.21254
    ]
  }
}