{
  "type": "Feature",
  "properties": {
    "name": "Kafranbel",
    "country": "SY",
    "subdivision": "12",
    "timezone": "Asia/Damascus"
  },
  "geometry": {
    "type": "Point",
    "coordinates": [
      36.56449,
      35.61376
    ]
  }
}