{
  "type": "Feature",
  "properties": {
    "name": "Sarāqib",
    "country": "SY",
    "subdivision": "12",
    "timezone": "Asia/Damascus"
  },
  "geometry": {
    "type": "Point",
    "coordinates": [
      36.80591,
      35.86447
    ]
  }
}