{
  "type": "Feature",
  "properties": {
    "name": "Yaypan",
    "country": "UZ",
    "subdivision": "03",
    "timezone": "Asia/Tashkent"
  },
  "geometry": {
    "type": "Point",
    "coordinates": [
      70.81556,
      40.37583
    ]
  }
}