{
  "type": "Feature",
  "properties": {
    "name": "Puerto Francisco de Orellana",
    "country": "EC",
    "subdivision": "24",
    "timezone": "America/Guayaquil"
  },
  "geometry": {
    "type": "Point",
    "coordinates": [
      -76.98719,
      -0.46645
    ]
  }
}