{
  "type": "Feature",
  "properties": {
    "name": "Grangwav",
    "country": "HT",
    "subdivision": "11",
    "timezone": "America/Port-au-Prince"
  },
  "geometry": {
    "type": "Point",
    "coordinates": [
      -72.76995,
      18.4259
    ]
  }
}