{
  "type": "Feature",
  "properties": {
    "name": "Gressier",
    "country": "HT",
    "subdivision": "11",
    "timezone": "America/Port-au-Prince"
  },
  "geometry": {
    "type": "Point",
    "coordinates": [
      -72.52679,
      18.54091
    ]
  }
}