{
  "type": "Feature",
  "properties": {
    "name": "Charlottenlund",
    "country": "DK",
    "subdivision": "17",
    "timezone": "Europe/Copenhagen"
  },
  "geometry": {
    "type": "Point",
    "coordinates": [
      12.5745,
      55.75238
    ]
  }
}