{
  "type": "Feature",
  "properties": {
    "name": "Hornbæk",
    "country": "DK",
    "subdivision": "17",
    "timezone": "Europe/Copenhagen"
  },
  "geometry": {
    "type": "Point",
    "coordinates": [
      12.45693,
      56.09027
    ]
  }
}