{
  "type": "Feature",
  "properties": {
    "name": "Hundested",
    "country": "DK",
    "subdivision": "17",
    "timezone": "Europe/Copenhagen"
  },
  "geometry": {
    "type": "Point",
    "coordinates": [
      11.85044,
      55.96397
    ]
  }
}