{
  "type": "Feature",
  "properties": {
    "name": "Jægerspris",
    "country": "DK",
    "subdivision": "17",
    "timezone": "Europe/Copenhagen"
  },
  "geometry": {
    "type": "Point",
    "coordinates": [
      11.98565,
      55.85248
    ]
  }
}