{
  "type": "Feature",
  "properties": {
    "name": "Liseleje",
    "country": "DK",
    "subdivision": "17",
    "timezone": "Europe/Copenhagen"
  },
  "geometry": {
    "type": "Point",
    "coordinates": [
      11.96544,
      56.01295
    ]
  }
}