{
  "type": "Feature",
  "properties": {
    "name": "Lynge",
    "country": "DK",
    "subdivision": "17",
    "timezone": "Europe/Copenhagen"
  },
  "geometry": {
    "type": "Point",
    "coordinates": [
      12.27725,
      55.83941
    ]
  }
}