{
  "type": "Feature",
  "properties": {
    "name": "Nivå",
    "country": "DK",
    "subdivision": "17",
    "timezone": "Europe/Copenhagen"
  },
  "geometry": {
    "type": "Point",
    "coordinates": [
      12.50485,
      55.93405
    ]
  }
}