{
  "type": "Feature",
  "properties": {
    "name": "Rønne",
    "country": "DK",
    "subdivision": "17",
    "timezone": "Europe/Copenhagen"
  },
  "geometry": {
    "type": "Point",
    "coordinates": [
      14.70664,
      55.10091
    ]
  }
}