{
  "type": "Feature",
  "properties": {
    "name": "Stenløse",
    "country": "DK",
    "subdivision": "17",
    "timezone": "Europe/Copenhagen"
  },
  "geometry": {
    "type": "Point",
    "coordinates": [
      12.19723,
      55.76828
    ]
  }
}