{
  "type": "Feature",
  "properties": {
    "name": "Hebi",
    "country": "CN",
    "subdivision": "09",
    "timezone": "Asia/Shanghai"
  },
  "geometry": {
    "type": "Point",
    "coordinates": [
      114.1925,
      35.89917
    ]
  }
}