{
  "type": "Feature",
  "properties": {
    "name": "Pingdingshan",
    "country": "CN",
    "subdivision": "09",
    "timezone": "Asia/Shanghai"
  },
  "geometry": {
    "type": "Point",
    "coordinates": [
      113.30119,
      33.73847
    ]
  }
}