{
  "type": "Feature",
  "properties": {
    "name": "Yunyang",
    "country": "CN",
    "subdivision": "09",
    "timezone": "Asia/Shanghai"
  },
  "geometry": {
    "type": "Point",
    "coordinates": [
      112.71422,
      33.44743
    ]
  }
}