{
  "type": "Feature",
  "properties": {
    "name": "Zhumadian",
    "country": "CN",
    "subdivision": "09",
    "timezone": "Asia/Shanghai"
  },
  "geometry": {
    "type": "Point",
    "coordinates": [
      114.02944,
      32.97944
    ]
  }
}