{
  "type": "Feature",
  "properties": {
    "name": "Bratislava - Vajnory",
    "country": "SK",
    "subdivision": "02",
    "timezone": "Europe/Bratislava"
  },
  "geometry": {
    "type": "Point",
    "coordinates": [
      17.20759,
      48.20563
    ]
  }
}