{
  "type": "Feature",
  "properties": {
    "name": "Pezinok",
    "country": "SK",
    "subdivision": "02",
    "timezone": "Europe/Bratislava"
  },
  "geometry": {
    "type": "Point",
    "coordinates": [
      17.26664,
      48.28986
    ]
  }
}