{
  "type": "Feature",
  "properties": {
    "name": "Vinosady",
    "country": "SK",
    "subdivision": "02",
    "timezone": "Europe/Bratislava"
  },
  "geometry": {
    "type": "Point",
    "coordinates": [
      17.29042,
      48.31142
    ]
  }
}