{
  "type": "Feature",
  "properties": {
    "name": "Alvorada",
    "country": "BR",
    "subdivision": "23",
    "timezone": "America/Sao_Paulo"
  },
  "geometry": {
    "type": "Point",
    "coordinates": [
      -51.0781,
      29.9904
    ]
  }
}