{
  "type": "Feature",
  "properties": {
    "name": "Butiá",
    "country": "BR",
    "subdivision": "23",
    "timezone": "America/Sao_Paulo"
  },
  "geometry": {
    "type": "Point",
    "coordinates": [
      -51.96222,
      -30.11972
    ]
  }
}