{
  "type": "Feature",
  "properties": {
    "name": "Camaquã",
    "country": "BR",
    "subdivision": "23",
    "timezone": "America/Sao_Paulo"
  },
  "geometry": {
    "type": "Point",
    "coordinates": [
      -51.81222,
      -30.85111
    ]
  }
}