{
  "type": "Feature",
  "properties": {
    "name": "Cruz Alta",
    "country": "BR",
    "subdivision": "23",
    "timezone": "America/Sao_Paulo"
  },
  "geometry": {
    "type": "Point",
    "coordinates": [
      -53.60633,
      -28.64397
    ]
  }
}