{
  "type": "Feature",
  "properties": {
    "name": "Frederico Westphalen",
    "country": "BR",
    "subdivision": "23",
    "timezone": "America/Sao_Paulo"
  },
  "geometry": {
    "type": "Point",
    "coordinates": [
      -53.39444,
      -27.35917
    ]
  }
}