{
  "type": "Feature",
  "properties": {
    "name": "Igrejinha",
    "country": "BR",
    "subdivision": "23",
    "timezone": "America/Sao_Paulo"
  },
  "geometry": {
    "type": "Point",
    "coordinates": [
      -50.79028,
      -29.57444
    ]
  }
}