{
  "type": "Feature",
  "properties": {
    "name": "Ijuí",
    "country": "BR",
    "subdivision": "23",
    "timezone": "America/Sao_Paulo"
  },
  "geometry": {
    "type": "Point",
    "coordinates": [
      -53.91472,
      -28.38778
    ]
  }
}