{
  "type": "Feature",
  "properties": {
    "name": "Lagoa Vermelha",
    "country": "BR",
    "subdivision": "23",
    "timezone": "America/Sao_Paulo"
  },
  "geometry": {
    "type": "Point",
    "coordinates": [
      -51.52583,
      -28.20861
    ]
  }
}