{
  "type": "Feature",
  "properties": {
    "name": "Portão",
    "country": "BR",
    "subdivision": "23",
    "timezone": "America/Sao_Paulo"
  },
  "geometry": {
    "type": "Point",
    "coordinates": [
      -51.24194,
      -29.70167
    ]
  }
}