{
  "type": "Feature",
  "properties": {
    "name": "Rosário do Sul",
    "country": "BR",
    "subdivision": "23",
    "timezone": "America/Sao_Paulo"
  },
  "geometry": {
    "type": "Point",
    "coordinates": [
      -54.91417,
      -30.25833
    ]
  }
}