{
  "type": "Feature",
  "properties": {
    "name": "Santana do Livramento",
    "country": "BR",
    "subdivision": "23",
    "timezone": "America/Sao_Paulo"
  },
  "geometry": {
    "type": "Point",
    "coordinates": [
      -55.53278,
      -30.89083
    ]
  }
}