{
  "type": "Feature",
  "properties": {
    "name": "Santa Maria",
    "country": "BR",
    "subdivision": "23",
    "timezone": "America/Sao_Paulo"
  },
  "geometry": {
    "type": "Point",
    "coordinates": [
      -53.80694,
      -29.68417
    ]
  }
}