{
  "type": "Feature",
  "properties": {
    "name": "Santo Ângelo",
    "country": "BR",
    "subdivision": "23",
    "timezone": "America/Sao_Paulo"
  },
  "geometry": {
    "type": "Point",
    "coordinates": [
      -54.26306,
      -28.29917
    ]
  }
}