{
  "type": "Feature",
  "properties": {
    "name": "São Luiz Gonzaga",
    "country": "BR",
    "subdivision": "23",
    "timezone": "America/Sao_Paulo"
  },
  "geometry": {
    "type": "Point",
    "coordinates": [
      -54.96083,
      -28.40833
    ]
  }
}