{
  "type": "Feature",
  "properties": {
    "name": "São Francisco de Paula",
    "country": "BR",
    "subdivision": "23",
    "timezone": "America/Sao_Paulo"
  },
  "geometry": {
    "type": "Point",
    "coordinates": [
      -50.58361,
      -29.44806
    ]
  }
}