{
  "type": "Feature",
  "properties": {
    "name": "São Pedro do Sul",
    "country": "BR",
    "subdivision": "23",
    "timezone": "America/Sao_Paulo"
  },
  "geometry": {
    "type": "Point",
    "coordinates": [
      -54.17889,
      -29.62056
    ]
  }
}