{
  "type": "Feature",
  "properties": {
    "name": "Tramandaí",
    "country": "BR",
    "subdivision": "23",
    "timezone": "America/Sao_Paulo"
  },
  "geometry": {
    "type": "Point",
    "coordinates": [
      -50.13361,
      -29.98472
    ]
  }
}