{
  "type": "Feature",
  "properties": {
    "name": "Três Passos",
    "country": "BR",
    "subdivision": "23",
    "timezone": "America/Sao_Paulo"
  },
  "geometry": {
    "type": "Point",
    "coordinates": [
      -53.93194,
      -27.45556
    ]
  }
}