{
  "type": "Feature",
  "properties": {
    "name": "Tupanciretã",
    "country": "BR",
    "subdivision": "23",
    "timezone": "America/Sao_Paulo"
  },
  "geometry": {
    "type": "Point",
    "coordinates": [
      -53.83583,
      -29.08056
    ]
  }
}