{
  "type": "Feature",
  "properties": {
    "name": "Viamão",
    "country": "BR",
    "subdivision": "23",
    "timezone": "America/Sao_Paulo"
  },
  "geometry": {
    "type": "Point",
    "coordinates": [
      -51.02333,
      -30.08111
    ]
  }
}