{
  "type": "Feature",
  "properties": {
    "name": "Boufarik",
    "country": "DZ",
    "subdivision": "20",
    "timezone": "Africa/Algiers"
  },
  "geometry": {
    "type": "Point",
    "coordinates": [
      2.91214,
      36.57413
    ]
  }
}