{
  "type": "Feature",
  "properties": {
    "name": "Chebli",
    "country": "DZ",
    "subdivision": "20",
    "timezone": "Africa/Algiers"
  },
  "geometry": {
    "type": "Point",
    "coordinates": [
      3.00917,
      36.57722
    ]
  }
}