{
  "type": "Feature",
  "properties": {
    "name": "Aïn Touta",
    "country": "DZ",
    "subdivision": "03",
    "timezone": "Africa/Algiers"
  },
  "geometry": {
    "type": "Point",
    "coordinates": [
      5.90001,
      35.37675
    ]
  }
}