{
  "type": "Feature",
  "properties": {
    "name": "Boumagueur",
    "country": "DZ",
    "subdivision": "03",
    "timezone": "Africa/Algiers"
  },
  "geometry": {
    "type": "Point",
    "coordinates": [
      5.5525,
      35.5052
    ]
  }
}