{
  "type": "Feature",
  "properties": {
    "name": "Merouana",
    "country": "DZ",
    "subdivision": "03",
    "timezone": "Africa/Algiers"
  },
  "geometry": {
    "type": "Point",
    "coordinates": [
      5.91186,
      35.63106
    ]
  }
}