{
  "type": "Feature",
  "properties": {
    "name": "BÄbolsar",
    "country": "IR",
    "subdivision": "35",
    "timezone": "Asia/Tehran"
  },
  "geometry": {
    "type": "Point",
    "coordinates": [
      52.65011,
      36.69929
    ]
  }
}