{
  "type": "Feature",
  "properties": {
    "name": "Behshahr",
    "country": "IR",
    "subdivision": "35",
    "timezone": "Asia/Tehran"
  },
  "geometry": {
    "type": "Point",
    "coordinates": [
      53.55262,
      36.69235
    ]
  }
}