{
  "type": "Feature",
  "properties": {
    "name": "Jūybār",
    "country": "IR",
    "subdivision": "35",
    "timezone": "Asia/Tehran"
  },
  "geometry": {
    "type": "Point",
    "coordinates": [
      52.91206,
      36.64088
    ]
  }
}