{
  "type": "Feature",
  "properties": {
    "name": "Nashtārūd",
    "country": "IR",
    "subdivision": "35",
    "timezone": "Asia/Tehran"
  },
  "geometry": {
    "type": "Point",
    "coordinates": [
      51.02362,
      36.7509
    ]
  }
}