{
  "type": "Feature",
  "properties": {
    "name": "Skrunda",
    "country": "LV",
    "subdivision": "C9",
    "timezone": "Europe/Riga"
  },
  "geometry": {
    "type": "Point",
    "coordinates": [
      22.01649,
      56.67749
    ]
  }
}