{
  "type": "Feature",
  "properties": {
    "name": "Pimentel",
    "country": "DO",
    "subdivision": "06",
    "timezone": "America/Santo_Domingo"
  },
  "geometry": {
    "type": "Point",
    "coordinates": [
      -70.10884,
      19.18416
    ]
  }
}