{
  "type": "Feature",
  "properties": {
    "name": "Šoštanj",
    "country": "SI",
    "subdivision": "C7",
    "timezone": "Europe/Ljubljana"
  },
  "geometry": {
    "type": "Point",
    "coordinates": [
      15.04861,
      46.38
    ]
  }
}