{
  "type": "Feature",
  "properties": {
    "name": "Otepää",
    "country": "EE",
    "subdivision": "19",
    "timezone": "Europe/Tallinn"
  },
  "geometry": {
    "type": "Point",
    "coordinates": [
      26.49667,
      58.05833
    ]
  }
}