{
  "type": "Feature",
  "properties": {
    "name": "Tõrva",
    "country": "EE",
    "subdivision": "19",
    "timezone": "Europe/Tallinn"
  },
  "geometry": {
    "type": "Point",
    "coordinates": [
      25.935,
      58.00278
    ]
  }
}