{
  "type": "Feature",
  "properties": {
    "name": "Agazzano",
    "country": "IT",
    "subdivision": "05",
    "timezone": "Europe/Rome"
  },
  "geometry": {
    "type": "Point",
    "coordinates": [
      9.51875,
      44.94726
    ]
  }
}