{
  "type": "Feature",
  "properties": {
    "name": "Baganzola",
    "country": "IT",
    "subdivision": "05",
    "timezone": "Europe/Rome"
  },
  "geometry": {
    "type": "Point",
    "coordinates": [
      10.30706,
      44.85513
    ]
  }
}