{
  "type": "Feature",
  "properties": {
    "name": "Baggiovara",
    "country": "IT",
    "subdivision": "05",
    "timezone": "Europe/Rome"
  },
  "geometry": {
    "type": "Point",
    "coordinates": [
      10.86256,
      44.60416
    ]
  }
}