{
  "type": "Feature",
  "properties": {
    "name": "Bedonia",
    "country": "IT",
    "subdivision": "05",
    "timezone": "Europe/Rome"
  },
  "geometry": {
    "type": "Point",
    "coordinates": [
      9.63489,
      44.504
    ]
  }
}