{
  "type": "Feature",
  "properties": {
    "name": "Bibbiano",
    "country": "IT",
    "subdivision": "05",
    "timezone": "Europe/Rome"
  },
  "geometry": {
    "type": "Point",
    "coordinates": [
      10.47391,
      44.66292
    ]
  }
}