{
  "type": "Feature",
  "properties": {
    "name": "Boretto",
    "country": "IT",
    "subdivision": "05",
    "timezone": "Europe/Rome"
  },
  "geometry": {
    "type": "Point",
    "coordinates": [
      10.55147,
      44.90157
    ]
  }
}