{
  "type": "Feature",
  "properties": {
    "name": "Busseto",
    "country": "IT",
    "subdivision": "05",
    "timezone": "Europe/Rome"
  },
  "geometry": {
    "type": "Point",
    "coordinates": [
      10.04331,
      44.9794
    ]
  }
}