{
  "type": "Feature",
  "properties": {
    "name": "Calerno",
    "country": "IT",
    "subdivision": "05",
    "timezone": "Europe/Rome"
  },
  "geometry": {
    "type": "Point",
    "coordinates": [
      10.48603,
      44.74875
    ]
  }
}