{
  "type": "Feature",
  "properties": {
    "name": "Camposanto",
    "country": "IT",
    "subdivision": "05",
    "timezone": "Europe/Rome"
  },
  "geometry": {
    "type": "Point",
    "coordinates": [
      11.14049,
      44.79009
    ]
  }
}