{
  "type": "Feature",
  "properties": {
    "name": "Casalfiumanese",
    "country": "IT",
    "subdivision": "05",
    "timezone": "Europe/Rome"
  },
  "geometry": {
    "type": "Point",
    "coordinates": [
      11.62402,
      44.29686
    ]
  }
}