{
  "type": "Feature",
  "properties": {
    "name": "Castelvetro di Modena",
    "country": "IT",
    "subdivision": "05",
    "timezone": "Europe/Rome"
  },
  "geometry": {
    "type": "Point",
    "coordinates": [
      10.94666,
      44.50422
    ]
  }
}