{
  "type": "Feature",
  "properties": {
    "name": "Castelnovo di Sotto",
    "country": "IT",
    "subdivision": "05",
    "timezone": "Europe/Rome"
  },
  "geometry": {
    "type": "Point",
    "coordinates": [
      10.56694,
      44.81253
    ]
  }
}