{
  "type": "Feature",
  "properties": {
    "name": "Castrocaro Terme e Terra del Sole",
    "country": "IT",
    "subdivision": "05",
    "timezone": "Europe/Rome"
  },
  "geometry": {
    "type": "Point",
    "coordinates": [
      11.96068,
      44.18676
    ]
  }
}