{
  "type": "Feature",
  "properties": {
    "name": "Castelnuovo Rangone",
    "country": "IT",
    "subdivision": "05",
    "timezone": "Europe/Rome"
  },
  "geometry": {
    "type": "Point",
    "coordinates": [
      10.9335,
      44.54935
    ]
  }
}