{
  "type": "Feature",
  "properties": {
    "name": "Castel Maggiore",
    "country": "IT",
    "subdivision": "05",
    "timezone": "Europe/Rome"
  },
  "geometry": {
    "type": "Point",
    "coordinates": [
      11.36071,
      44.57707
    ]
  }
}