{
  "type": "Feature",
  "properties": {
    "name": "Cona",
    "country": "IT",
    "subdivision": "05",
    "timezone": "Europe/Rome"
  },
  "geometry": {
    "type": "Point",
    "coordinates": [
      11.7069,
      44.80583
    ]
  }
}