{
  "type": "Feature",
  "properties": {
    "name": "Corpolò",
    "country": "IT",
    "subdivision": "05",
    "timezone": "Europe/Rome"
  },
  "geometry": {
    "type": "Point",
    "coordinates": [
      12.45266,
      44.01905
    ]
  }
}