{
  "type": "Feature",
  "properties": {
    "name": "Decima",
    "country": "IT",
    "subdivision": "05",
    "timezone": "Europe/Rome"
  },
  "geometry": {
    "type": "Point",
    "coordinates": [
      11.22978,
      44.71045
    ]
  }
}