{
  "type": "Feature",
  "properties": {
    "name": "Dodici Morelli",
    "country": "IT",
    "subdivision": "05",
    "timezone": "Europe/Rome"
  },
  "geometry": {
    "type": "Point",
    "coordinates": [
      11.29124,
      44.79234
    ]
  }
}