{
  "type": "Feature",
  "properties": {
    "name": "Dosso",
    "country": "IT",
    "subdivision": "05",
    "timezone": "Europe/Rome"
  },
  "geometry": {
    "type": "Point",
    "coordinates": [
      11.33938,
      44.76806
    ]
  }
}