{
  "type": "Feature",
  "properties": {
    "name": "Felino",
    "country": "IT",
    "subdivision": "05",
    "timezone": "Europe/Rome"
  },
  "geometry": {
    "type": "Point",
    "coordinates": [
      10.23828,
      44.69902
    ]
  }
}