{
  "type": "Feature",
  "properties": {
    "name": "Fornovo di Taro",
    "country": "IT",
    "subdivision": "05",
    "timezone": "Europe/Rome"
  },
  "geometry": {
    "type": "Point",
    "coordinates": [
      10.10178,
      44.69465
    ]
  }
}