{
  "type": "Feature",
  "properties": {
    "name": "Gossolengo",
    "country": "IT",
    "subdivision": "05",
    "timezone": "Europe/Rome"
  },
  "geometry": {
    "type": "Point",
    "coordinates": [
      9.61799,
      45.00248
    ]
  }
}