{
  "type": "Feature",
  "properties": {
    "name": "Gualtieri",
    "country": "IT",
    "subdivision": "05",
    "timezone": "Europe/Rome"
  },
  "geometry": {
    "type": "Point",
    "coordinates": [
      10.6286,
      44.89736
    ]
  }
}