{
  "type": "Feature",
  "properties": {
    "name": "Lesignano de'Bagni",
    "country": "IT",
    "subdivision": "05",
    "timezone": "Europe/Rome"
  },
  "geometry": {
    "type": "Point",
    "coordinates": [
      10.30039,
      44.64346
    ]
  }
}