{
  "type": "Feature",
  "properties": {
    "name": "Lido degli Estensi",
    "country": "IT",
    "subdivision": "05",
    "timezone": "Europe/Rome"
  },
  "geometry": {
    "type": "Point",
    "coordinates": [
      12.25,
      44.66639
    ]
  }
}