{
  "type": "Feature",
  "properties": {
    "name": "Lido di Pomposa-Lido degli Scacchi",
    "country": "IT",
    "subdivision": "05",
    "timezone": "Europe/Rome"
  },
  "geometry": {
    "type": "Point",
    "coordinates": [
      12.23611,
      44.70667
    ]
  }
}