{
  "type": "Feature",
  "properties": {
    "name": "Longara",
    "country": "IT",
    "subdivision": "05",
    "timezone": "Europe/Rome"
  },
  "geometry": {
    "type": "Point",
    "coordinates": [
      11.30386,
      44.5711
    ]
  }
}