{
  "type": "Feature",
  "properties": {
    "name": "Massenzatico",
    "country": "IT",
    "subdivision": "05",
    "timezone": "Europe/Rome"
  },
  "geometry": {
    "type": "Point",
    "coordinates": [
      10.69736,
      44.73477
    ]
  }
}