{
  "type": "Feature",
  "properties": {
    "name": "Massa Fiscaglia",
    "country": "IT",
    "subdivision": "05",
    "timezone": "Europe/Rome"
  },
  "geometry": {
    "type": "Point",
    "coordinates": [
      12.00746,
      44.80983
    ]
  }
}