{
  "type": "Feature",
  "properties": {
    "name": "Mezzolara",
    "country": "IT",
    "subdivision": "05",
    "timezone": "Europe/Rome"
  },
  "geometry": {
    "type": "Point",
    "coordinates": [
      11.56492,
      44.58917
    ]
  }
}