{
  "type": "Feature",
  "properties": {
    "name": "Mezzano Inferiore",
    "country": "IT",
    "subdivision": "05",
    "timezone": "Europe/Rome"
  },
  "geometry": {
    "type": "Point",
    "coordinates": [
      10.45838,
      44.91291
    ]
  }
}