{
  "type": "Feature",
  "properties": {
    "name": "Mirabello",
    "country": "IT",
    "subdivision": "05",
    "timezone": "Europe/Rome"
  },
  "geometry": {
    "type": "Point",
    "coordinates": [
      11.45669,
      44.82295
    ]
  }
}