{
  "type": "Feature",
  "properties": {
    "name": "Monghidoro",
    "country": "IT",
    "subdivision": "05",
    "timezone": "Europe/Rome"
  },
  "geometry": {
    "type": "Point",
    "coordinates": [
      11.32331,
      44.22327
    ]
  }
}