{
  "type": "Feature",
  "properties": {
    "name": "Monterenzio",
    "country": "IT",
    "subdivision": "05",
    "timezone": "Europe/Rome"
  },
  "geometry": {
    "type": "Point",
    "coordinates": [
      11.40446,
      44.32632
    ]
  }
}