{
  "type": "Feature",
  "properties": {
    "name": "Montalbano",
    "country": "IT",
    "subdivision": "05",
    "timezone": "Europe/Rome"
  },
  "geometry": {
    "type": "Point",
    "coordinates": [
      12.71646,
      43.95879
    ]
  }
}