{
  "type": "Feature",
  "properties": {
    "name": "Novellara",
    "country": "IT",
    "subdivision": "05",
    "timezone": "Europe/Rome"
  },
  "geometry": {
    "type": "Point",
    "coordinates": [
      10.72745,
      44.84488
    ]
  }
}