{
  "type": "Feature",
  "properties": {
    "name": "Pieve di Cento",
    "country": "IT",
    "subdivision": "05",
    "timezone": "Europe/Rome"
  },
  "geometry": {
    "type": "Point",
    "coordinates": [
      11.30922,
      44.71293
    ]
  }
}