{
  "type": "Feature",
  "properties": {
    "name": "Poggio Renatico",
    "country": "IT",
    "subdivision": "05",
    "timezone": "Europe/Rome"
  },
  "geometry": {
    "type": "Point",
    "coordinates": [
      11.48695,
      44.76581
    ]
  }
}