{
  "type": "Feature",
  "properties": {
    "name": "Pontelangorino",
    "country": "IT",
    "subdivision": "05",
    "timezone": "Europe/Rome"
  },
  "geometry": {
    "type": "Point",
    "coordinates": [
      12.14864,
      44.86087
    ]
  }
}