{
  "type": "Feature",
  "properties": {
    "name": "Ponte Ronca",
    "country": "IT",
    "subdivision": "05",
    "timezone": "Europe/Rome"
  },
  "geometry": {
    "type": "Point",
    "coordinates": [
      11.18973,
      44.50166
    ]
  }
}