{
  "type": "Feature",
  "properties": {
    "name": "Poviglio",
    "country": "IT",
    "subdivision": "05",
    "timezone": "Europe/Rome"
  },
  "geometry": {
    "type": "Point",
    "coordinates": [
      10.53936,
      44.84227
    ]
  }
}