{
  "type": "Feature",
  "properties": {
    "name": "Predappio",
    "country": "IT",
    "subdivision": "05",
    "timezone": "Europe/Rome"
  },
  "geometry": {
    "type": "Point",
    "coordinates": [
      11.98413,
      44.10316
    ]
  }
}