{
  "type": "Feature",
  "properties": {
    "name": "Puianello",
    "country": "IT",
    "subdivision": "05",
    "timezone": "Europe/Rome"
  },
  "geometry": {
    "type": "Point",
    "coordinates": [
      10.5642,
      44.6263
    ]
  }
}