{
  "type": "Feature",
  "properties": {
    "name": "Rastignano-Carteria di Sesto",
    "country": "IT",
    "subdivision": "05",
    "timezone": "Europe/Rome"
  },
  "geometry": {
    "type": "Point",
    "coordinates": [
      11.35695,
      44.43623
    ]
  }
}