{
  "type": "Feature",
  "properties": {
    "name": "Riccò",
    "country": "IT",
    "subdivision": "05",
    "timezone": "Europe/Rome"
  },
  "geometry": {
    "type": "Point",
    "coordinates": [
      10.12095,
      44.7005
    ]
  }
}