{
  "type": "Feature",
  "properties": {
    "name": "Rivergaro",
    "country": "IT",
    "subdivision": "05",
    "timezone": "Europe/Rome"
  },
  "geometry": {
    "type": "Point",
    "coordinates": [
      9.60443,
      44.915
    ]
  }
}