{
  "type": "Feature",
  "properties": {
    "name": "Roncocesi",
    "country": "IT",
    "subdivision": "05",
    "timezone": "Europe/Rome"
  },
  "geometry": {
    "type": "Point",
    "coordinates": [
      10.57816,
      44.73843
    ]
  }
}