{
  "type": "Feature",
  "properties": {
    "name": "San Piero in Bagno",
    "country": "IT",
    "subdivision": "05",
    "timezone": "Europe/Rome"
  },
  "geometry": {
    "type": "Point",
    "coordinates": [
      11.97716,
      43.85793
    ]
  }
}