{
  "type": "Feature",
  "properties": {
    "name": "San Pancrazio",
    "country": "IT",
    "subdivision": "05",
    "timezone": "Europe/Rome"
  },
  "geometry": {
    "type": "Point",
    "coordinates": [
      12.07852,
      44.3581
    ]
  }
}