{
  "type": "Feature",
  "properties": {
    "name": "Santa Croce Scuole",
    "country": "IT",
    "subdivision": "05",
    "timezone": "Europe/Rome"
  },
  "geometry": {
    "type": "Point",
    "coordinates": [
      10.84944,
      44.76281
    ]
  }
}