{
  "type": "Feature",
  "properties": {
    "name": "Santa Monica-Cella",
    "country": "IT",
    "subdivision": "05",
    "timezone": "Europe/Rome"
  },
  "geometry": {
    "type": "Point",
    "coordinates": [
      12.68846,
      43.95765
    ]
  }
}