{
  "type": "Feature",
  "properties": {
    "name": "Sesto Imolese",
    "country": "IT",
    "subdivision": "05",
    "timezone": "Europe/Rome"
  },
  "geometry": {
    "type": "Point",
    "coordinates": [
      11.72919,
      44.45952
    ]
  }
}