{
  "type": "Feature",
  "properties": {
    "name": "Villarotta",
    "country": "IT",
    "subdivision": "05",
    "timezone": "Europe/Rome"
  },
  "geometry": {
    "type": "Point",
    "coordinates": [
      10.74382,
      44.92517
    ]
  }
}