{
  "type": "Feature",
  "properties": {
    "name": "Voltana",
    "country": "IT",
    "subdivision": "05",
    "timezone": "Europe/Rome"
  },
  "geometry": {
    "type": "Point",
    "coordinates": [
      11.93533,
      44.54109
    ]
  }
}