{
  "type": "Feature",
  "properties": {
    "name": "Zocca",
    "country": "IT",
    "subdivision": "05",
    "timezone": "Europe/Rome"
  },
  "geometry": {
    "type": "Point",
    "coordinates": [
      10.99308,
      44.34566
    ]
  }
}