{
  "type": "Feature",
  "properties": {
    "name": "Caparrapí",
    "country": "CO",
    "subdivision": "33",
    "timezone": "America/Bogota"
  },
  "geometry": {
    "type": "Point",
    "coordinates": [
      -74.49147,
      5.34644
    ]
  }
}