{
  "type": "Feature",
  "properties": {
    "name": "Gachancipá",
    "country": "CO",
    "subdivision": "33",
    "timezone": "America/Bogota"
  },
  "geometry": {
    "type": "Point",
    "coordinates": [
      -73.87154,
      4.99111
    ]
  }
}