{
  "type": "Feature",
  "properties": {
    "name": "Granada",
    "country": "CO",
    "subdivision": "33",
    "timezone": "America/Bogota"
  },
  "geometry": {
    "type": "Point",
    "coordinates": [
      -74.56667,
      5.06667
    ]
  }
}