{
  "type": "Feature",
  "properties": {
    "name": "Paratebueno",
    "country": "CO",
    "subdivision": "33",
    "timezone": "America/Bogota"
  },
  "geometry": {
    "type": "Point",
    "coordinates": [
      -73.21547,
      4.37575
    ]
  }
}