{
  "type": "Feature",
  "properties": {
    "name": "Sasaima",
    "country": "CO",
    "subdivision": "33",
    "timezone": "America/Bogota"
  },
  "geometry": {
    "type": "Point",
    "coordinates": [
      -74.43512,
      4.96705
    ]
  }
}