{
  "type": "Feature",
  "properties": {
    "name": "Yacopí",
    "country": "CO",
    "subdivision": "33",
    "timezone": "America/Bogota"
  },
  "geometry": {
    "type": "Point",
    "coordinates": [
      -74.33823,
      5.45948
    ]
  }
}