{
  "type": "Feature",
  "properties": {
    "name": "Ansan-si",
    "country": "KR",
    "subdivision": "13",
    "timezone": "Asia/Seoul"
  },
  "geometry": {
    "type": "Point",
    "coordinates": [
      126.82194,
      37.32361
    ]
  }
}