{
  "type": "Feature",
  "properties": {
    "name": "Hwaseong-si",
    "country": "KR",
    "subdivision": "13",
    "timezone": "Asia/Seoul"
  },
  "geometry": {
    "type": "Point",
    "coordinates": [
      126.8169,
      37.20682
    ]
  }
}