{
  "type": "Feature",
  "properties": {
    "name": "Icheon-si",
    "country": "KR",
    "subdivision": "13",
    "timezone": "Asia/Seoul"
  },
  "geometry": {
    "type": "Point",
    "coordinates": [
      127.4425,
      37.27917
    ]
  }
}