{
  "type": "Feature",
  "properties": {
    "name": "Osan",
    "country": "KR",
    "subdivision": "13",
    "timezone": "Asia/Seoul"
  },
  "geometry": {
    "type": "Point",
    "coordinates": [
      127.07056,
      37.15222
    ]
  }
}