{
  "type": "Feature",
  "properties": {
    "name": "Cazis",
    "country": "CH",
    "subdivision": "GR",
    "timezone": "Europe/Zurich"
  },
  "geometry": {
    "type": "Point",
    "coordinates": [
      9.43271,
      46.7194
    ]
  }
}