{
  "type": "Feature",
  "properties": {
    "name": "Lenzerheide",
    "country": "CH",
    "subdivision": "GR",
    "timezone": "Europe/Zurich"
  },
  "geometry": {
    "type": "Point",
    "coordinates": [
      9.55905,
      46.72215
    ]
  }
}