{
  "type": "Feature",
  "properties": {
    "name": "Luzein",
    "country": "CH",
    "subdivision": "GR",
    "timezone": "Europe/Zurich"
  },
  "geometry": {
    "type": "Point",
    "coordinates": [
      9.7608,
      46.91957
    ]
  }
}