{
  "type": "Feature",
  "properties": {
    "name": "St. Moritz",
    "country": "CH",
    "subdivision": "GR",
    "timezone": "Europe/Zurich"
  },
  "geometry": {
    "type": "Point",
    "coordinates": [
      9.84327,
      46.49937
    ]
  }
}