{
  "type": "Feature",
  "properties": {
    "name": "Untervaz",
    "country": "CH",
    "subdivision": "GR",
    "timezone": "Europe/Zurich"
  },
  "geometry": {
    "type": "Point",
    "coordinates": [
      9.53422,
      46.9275
    ]
  }
}