{
  "type": "Feature",
  "properties": {
    "name": "Birinci Aşıqlı",
    "country": "AZ",
    "subdivision": "12",
    "timezone": "Asia/Baku"
  },
  "geometry": {
    "type": "Point",
    "coordinates": [
      47.67944,
      39.81917
    ]
  }
}