{
  "type": "Feature",
  "properties": {
    "name": "Akdepe",
    "country": "TM",
    "subdivision": "03",
    "timezone": "Asia/Ashgabat"
  },
  "geometry": {
    "type": "Point",
    "coordinates": [
      59.37877,
      42.05513
    ]
  }
}