{
  "type": "Feature",
  "properties": {
    "name": "Fundación",
    "country": "CO",
    "subdivision": "38",
    "timezone": "America/Bogota"
  },
  "geometry": {
    "type": "Point",
    "coordinates": [
      -74.18504,
      10.52066
    ]
  }
}