{
  "type": "Feature",
  "properties": {
    "name": "Pivijay",
    "country": "CO",
    "subdivision": "38",
    "timezone": "America/Bogota"
  },
  "geometry": {
    "type": "Point",
    "coordinates": [
      -74.61621,
      10.46167
    ]
  }
}