{
  "type": "Feature",
  "properties": {
    "name": "Rūdsar",
    "country": "IR",
    "subdivision": "08",
    "timezone": "Asia/Tehran"
  },
  "geometry": {
    "type": "Point",
    "coordinates": [
      50.29174,
      37.13696
    ]
  }
}