{
  "type": "Feature",
  "properties": {
    "name": "Kaolinovo",
    "country": "BG",
    "subdivision": "54",
    "timezone": "Europe/Sofia"
  },
  "geometry": {
    "type": "Point",
    "coordinates": [
      27.11667,
      43.61667
    ]
  }
}