{
  "type": "Feature",
  "properties": {
    "name": "Narathiwat",
    "country": "TH",
    "subdivision": "31",
    "timezone": "Asia/Bangkok"
  },
  "geometry": {
    "type": "Point",
    "coordinates": [
      101.82308,
      6.42639
    ]
  }
}