{
  "type": "Feature",
  "properties": {
    "name": "Banyliv-Pidhirnyy",
    "country": "UA",
    "subdivision": "03",
    "timezone": "Europe/Kiev"
  },
  "geometry": {
    "type": "Point",
    "coordinates": [
      25.48333,
      48.08333
    ]
  }
}