{
  "type": "Feature",
  "properties": {
    "name": "Berehomet",
    "country": "UA",
    "subdivision": "03",
    "timezone": "Europe/Kiev"
  },
  "geometry": {
    "type": "Point",
    "coordinates": [
      25.33032,
      48.17148
    ]
  }
}