{
  "type": "Feature",
  "properties": {
    "name": "Bernove",
    "country": "UA",
    "subdivision": "03",
    "timezone": "Europe/Kiev"
  },
  "geometry": {
    "type": "Point",
    "coordinates": [
      26.63618,
      48.49662
    ]
  }
}