{
  "type": "Feature",
  "properties": {
    "name": "Buzovytsya",
    "country": "UA",
    "subdivision": "03",
    "timezone": "Europe/Kiev"
  },
  "geometry": {
    "type": "Point",
    "coordinates": [
      26.93221,
      48.49859
    ]
  }
}