{
  "type": "Feature",
  "properties": {
    "name": "Cheresh",
    "country": "UA",
    "subdivision": "03",
    "timezone": "Europe/Kiev"
  },
  "geometry": {
    "type": "Point",
    "coordinates": [
      25.61543,
      48.09735
    ]
  }
}