{
  "type": "Feature",
  "properties": {
    "name": "Hlyboka",
    "country": "UA",
    "subdivision": "03",
    "timezone": "Europe/Kiev"
  },
  "geometry": {
    "type": "Point",
    "coordinates": [
      25.9284,
      48.08756
    ]
  }
}