{
  "type": "Feature",
  "properties": {
    "name": "Ivankivtsi",
    "country": "UA",
    "subdivision": "03",
    "timezone": "Europe/Kiev"
  },
  "geometry": {
    "type": "Point",
    "coordinates": [
      25.67275,
      48.45332
    ]
  }
}