{
  "type": "Feature",
  "properties": {
    "name": "Komariv",
    "country": "UA",
    "subdivision": "03",
    "timezone": "Europe/Kiev"
  },
  "geometry": {
    "type": "Point",
    "coordinates": [
      26.9887,
      48.56125
    ]
  }
}