{
  "type": "Feature",
  "properties": {
    "name": "Koteleve",
    "country": "UA",
    "subdivision": "03",
    "timezone": "Europe/Kiev"
  },
  "geometry": {
    "type": "Point",
    "coordinates": [
      26.35822,
      48.2835
    ]
  }
}