{
  "type": "Feature",
  "properties": {
    "name": "Marshyntsi",
    "country": "UA",
    "subdivision": "03",
    "timezone": "Europe/Kiev"
  },
  "geometry": {
    "type": "Point",
    "coordinates": [
      26.29934,
      48.21191
    ]
  }
}