{
  "type": "Feature",
  "properties": {
    "name": "Molnytsya",
    "country": "UA",
    "subdivision": "03",
    "timezone": "Europe/Kiev"
  },
  "geometry": {
    "type": "Point",
    "coordinates": [
      26.22843,
      48.1981
    ]
  }
}