{
  "type": "Feature",
  "properties": {
    "name": "Podviryvka",
    "country": "UA",
    "subdivision": "03",
    "timezone": "Europe/Kiev"
  },
  "geometry": {
    "type": "Point",
    "coordinates": [
      26.78609,
      48.31969
    ]
  }
}