{
  "type": "Feature",
  "properties": {
    "name": "Rynhach",
    "country": "UA",
    "subdivision": "03",
    "timezone": "Europe/Kiev"
  },
  "geometry": {
    "type": "Point",
    "coordinates": [
      26.24408,
      48.30953
    ]
  }
}