{
  "type": "Feature",
  "properties": {
    "name": "Shubranets",
    "country": "UA",
    "subdivision": "03",
    "timezone": "Europe/Kiev"
  },
  "geometry": {
    "type": "Point",
    "coordinates": [
      25.88794,
      48.39552
    ]
  }
}