{
  "type": "Feature",
  "properties": {
    "name": "Shyshkivtsi",
    "country": "UA",
    "subdivision": "03",
    "timezone": "Europe/Kiev"
  },
  "geometry": {
    "type": "Point",
    "coordinates": [
      25.63242,
      48.55048
    ]
  }
}