{
  "type": "Feature",
  "properties": {
    "name": "Sloboda",
    "country": "UA",
    "subdivision": "03",
    "timezone": "Europe/Kiev"
  },
  "geometry": {
    "type": "Point",
    "coordinates": [
      26.19726,
      48.27781
    ]
  }
}