{
  "type": "Feature",
  "properties": {
    "name": "Sokyryany",
    "country": "UA",
    "subdivision": "03",
    "timezone": "Europe/Kiev"
  },
  "geometry": {
    "type": "Point",
    "coordinates": [
      27.41138,
      48.44913
    ]
  }
}