{
  "type": "Feature",
  "properties": {
    "name": "Tarasivtsi",
    "country": "UA",
    "subdivision": "03",
    "timezone": "Europe/Kiev"
  },
  "geometry": {
    "type": "Point",
    "coordinates": [
      26.36444,
      48.20557
    ]
  }
}