{
  "type": "Feature",
  "properties": {
    "name": "Terebleche",
    "country": "UA",
    "subdivision": "03",
    "timezone": "Europe/Kiev"
  },
  "geometry": {
    "type": "Point",
    "coordinates": [
      26.05859,
      48.01592
    ]
  }
}