{
  "type": "Feature",
  "properties": {
    "name": "Turiatka",
    "country": "UA",
    "subdivision": "03",
    "timezone": "Europe/Kiev"
  },
  "geometry": {
    "type": "Point",
    "coordinates": [
      26.14471,
      48.04474
    ]
  }
}