{
  "type": "Feature",
  "properties": {
    "name": "Valyava",
    "country": "UA",
    "subdivision": "03",
    "timezone": "Europe/Kiev"
  },
  "geometry": {
    "type": "Point",
    "coordinates": [
      25.84069,
      48.43491
    ]
  }
}