{
  "type": "Feature",
  "properties": {
    "name": "Voloka",
    "country": "UA",
    "subdivision": "03",
    "timezone": "Europe/Kiev"
  },
  "geometry": {
    "type": "Point",
    "coordinates": [
      25.93554,
      48.19803
    ]
  }
}