{
  "type": "Feature",
  "properties": {
    "name": "Vytylivka",
    "country": "UA",
    "subdivision": "03",
    "timezone": "Europe/Kiev"
  },
  "geometry": {
    "type": "Point",
    "coordinates": [
      25.80456,
      48.40452
    ]
  }
}