{
  "type": "Feature",
  "properties": {
    "name": "Zarozhany",
    "country": "UA",
    "subdivision": "03",
    "timezone": "Europe/Kiev"
  },
  "geometry": {
    "type": "Point",
    "coordinates": [
      26.29894,
      48.41546
    ]
  }
}