{
  "type": "Feature",
  "properties": {
    "name": "Zelenyy Hay",
    "country": "UA",
    "subdivision": "03",
    "timezone": "Europe/Kiev"
  },
  "geometry": {
    "type": "Point",
    "coordinates": [
      26.21241,
      48.2251
    ]
  }
}