{
  "type": "Feature",
  "properties": {
    "name": "Quận Đức Thành",
    "country": "VN",
    "subdivision": "09",
    "timezone": "Asia/Ho_Chi_Minh"
  },
  "geometry": {
    "type": "Point",
    "coordinates": [
      105.646,
      10.25874
    ]
  }
}