{
  "type": "Feature",
  "properties": {
    "name": "Mbocayaty",
    "country": "PY",
    "subdivision": "10",
    "timezone": "America/Asuncion"
  },
  "geometry": {
    "type": "Point",
    "coordinates": [
      -56.42179,
      -25.71938
    ]
  }
}