{
  "type": "Feature",
  "properties": {
    "name": "Aurach",
    "country": "AT",
    "subdivision": "07",
    "timezone": "Europe/Vienna"
  },
  "geometry": {
    "type": "Point",
    "coordinates": [
      12.42734,
      47.41223
    ]
  }
}