{
  "type": "Feature",
  "properties": {
    "name": "Birgitz",
    "country": "AT",
    "subdivision": "07",
    "timezone": "Europe/Vienna"
  },
  "geometry": {
    "type": "Point",
    "coordinates": [
      11.29922,
      47.23536
    ]
  }
}