{
  "type": "Feature",
  "properties": {
    "name": "Breitenwang",
    "country": "AT",
    "subdivision": "07",
    "timezone": "Europe/Vienna"
  },
  "geometry": {
    "type": "Point",
    "coordinates": [
      10.7342,
      47.48713
    ]
  }
}