{
  "type": "Feature",
  "properties": {
    "name": "Brixen im Thale",
    "country": "AT",
    "subdivision": "07",
    "timezone": "Europe/Vienna"
  },
  "geometry": {
    "type": "Point",
    "coordinates": [
      12.25,
      47.45
    ]
  }
}