{
  "type": "Feature",
  "properties": {
    "name": "Hochfilzen",
    "country": "AT",
    "subdivision": "07",
    "timezone": "Europe/Vienna"
  },
  "geometry": {
    "type": "Point",
    "coordinates": [
      12.61667,
      47.46667
    ]
  }
}