{
  "type": "Feature",
  "properties": {
    "name": "Igls",
    "country": "AT",
    "subdivision": "07",
    "timezone": "Europe/Vienna"
  },
  "geometry": {
    "type": "Point",
    "coordinates": [
      11.41018,
      47.23127
    ]
  }
}