{
  "type": "Feature",
  "properties": {
    "name": "Jenbach",
    "country": "AT",
    "subdivision": "07",
    "timezone": "Europe/Vienna"
  },
  "geometry": {
    "type": "Point",
    "coordinates": [
      11.77245,
      47.39173
    ]
  }
}