{
  "type": "Feature",
  "properties": {
    "name": "Kirchdorf in Tirol",
    "country": "AT",
    "subdivision": "07",
    "timezone": "Europe/Vienna"
  },
  "geometry": {
    "type": "Point",
    "coordinates": [
      12.44511,
      47.55626
    ]
  }
}