{
  "type": "Feature",
  "properties": {
    "name": "Kirchberg in Tirol",
    "country": "AT",
    "subdivision": "07",
    "timezone": "Europe/Vienna"
  },
  "geometry": {
    "type": "Point",
    "coordinates": [
      12.31602,
      47.44539
    ]
  }
}