{
  "type": "Feature",
  "properties": {
    "name": "Kirchbichl",
    "country": "AT",
    "subdivision": "07",
    "timezone": "Europe/Vienna"
  },
  "geometry": {
    "type": "Point",
    "coordinates": [
      12.09629,
      47.51743
    ]
  }
}