{
  "type": "Feature",
  "properties": {
    "name": "Mitterndorf",
    "country": "AT",
    "subdivision": "07",
    "timezone": "Europe/Vienna"
  },
  "geometry": {
    "type": "Point",
    "coordinates": [
      12.16968,
      47.57728
    ]
  }
}