{
  "type": "Feature",
  "properties": {
    "name": "Oberperfuss",
    "country": "AT",
    "subdivision": "07",
    "timezone": "Europe/Vienna"
  },
  "geometry": {
    "type": "Point",
    "coordinates": [
      11.24755,
      47.24451
    ]
  }
}