{
  "type": "Feature",
  "properties": {
    "name": "Ötztal-Bahnhof",
    "country": "AT",
    "subdivision": "07",
    "timezone": "Europe/Vienna"
  },
  "geometry": {
    "type": "Point",
    "coordinates": [
      10.85,
      47.23333
    ]
  }
}