{
  "type": "Feature",
  "properties": {
    "name": "Sankt Ulrich am Pillersee",
    "country": "AT",
    "subdivision": "07",
    "timezone": "Europe/Vienna"
  },
  "geometry": {
    "type": "Point",
    "coordinates": [
      12.57239,
      47.5274
    ]
  }
}