{
  "type": "Feature",
  "properties": {
    "name": "Schlitters",
    "country": "AT",
    "subdivision": "07",
    "timezone": "Europe/Vienna"
  },
  "geometry": {
    "type": "Point",
    "coordinates": [
      11.83888,
      47.38045
    ]
  }
}