{
  "type": "Feature",
  "properties": {
    "name": "Stams",
    "country": "AT",
    "subdivision": "07",
    "timezone": "Europe/Vienna"
  },
  "geometry": {
    "type": "Point",
    "coordinates": [
      10.98315,
      47.27603
    ]
  }
}