{
  "type": "Feature",
  "properties": {
    "name": "Steinach am Brenner",
    "country": "AT",
    "subdivision": "07",
    "timezone": "Europe/Vienna"
  },
  "geometry": {
    "type": "Point",
    "coordinates": [
      11.46667,
      47.08333
    ]
  }
}