{
  "type": "Feature",
  "properties": {
    "name": "Strengen",
    "country": "AT",
    "subdivision": "07",
    "timezone": "Europe/Vienna"
  },
  "geometry": {
    "type": "Point",
    "coordinates": [
      10.46199,
      47.12589
    ]
  }
}