{
  "type": "Feature",
  "properties": {
    "name": "Lascano",
    "country": "UY",
    "subdivision": "14",
    "timezone": "America/Montevideo"
  },
  "geometry": {
    "type": "Point",
    "coordinates": [
      -54.2065,
      -33.67235
    ]
  }
}