{
  "type": "Feature",
  "properties": {
    "name": "ArÄria",
    "country": "IN",
    "subdivision": "34",
    "timezone": "Asia/Kolkata"
  },
  "geometry": {
    "type": "Point",
    "coordinates": [
      87.51323,
      26.14934
    ]
  }
}