{
  "type": "Feature",
  "properties": {
    "name": "Barauli",
    "country": "IN",
    "subdivision": "34",
    "timezone": "Asia/Kolkata"
  },
  "geometry": {
    "type": "Point",
    "coordinates": [
      84.58648,
      26.38109
    ]
  }
}