{
  "type": "Feature",
  "properties": {
    "name": "BariÄrpur",
    "country": "IN",
    "subdivision": "34",
    "timezone": "Asia/Kolkata"
  },
  "geometry": {
    "type": "Point",
    "coordinates": [
      86.57643,
      25.28791
    ]
  }
}