{
  "type": "Feature",
  "properties": {
    "name": "Bhabhua",
    "country": "IN",
    "subdivision": "34",
    "timezone": "Asia/Kolkata"
  },
  "geometry": {
    "type": "Point",
    "coordinates": [
      83.60749,
      25.04049
    ]
  }
}