{
  "type": "Feature",
  "properties": {
    "name": "Dalsingh Sarai",
    "country": "IN",
    "subdivision": "34",
    "timezone": "Asia/Kolkata"
  },
  "geometry": {
    "type": "Point",
    "coordinates": [
      85.83636,
      25.66795
    ]
  }
}