{
  "type": "Feature",
  "properties": {
    "name": "Darbhanga",
    "country": "IN",
    "subdivision": "34",
    "timezone": "Asia/Kolkata"
  },
  "geometry": {
    "type": "Point",
    "coordinates": [
      85.89707,
      26.15216
    ]
  }
}