{
  "type": "Feature",
  "properties": {
    "name": "Daudnagar",
    "country": "IN",
    "subdivision": "34",
    "timezone": "Asia/Kolkata"
  },
  "geometry": {
    "type": "Point",
    "coordinates": [
      84.40095,
      25.03473
    ]
  }
}