{
  "type": "Feature",
  "properties": {
    "name": "HisuÄ",
    "country": "IN",
    "subdivision": "34",
    "timezone": "Asia/Kolkata"
  },
  "geometry": {
    "type": "Point",
    "coordinates": [
      85.41729,
      24.8336
    ]
  }
}