{
  "type": "Feature",
  "properties": {
    "name": "Jahānābād",
    "country": "IN",
    "subdivision": "34",
    "timezone": "Asia/Kolkata"
  },
  "geometry": {
    "type": "Point",
    "coordinates": [
      84.9871,
      25.21368
    ]
  }
}