{
  "type": "Feature",
  "properties": {
    "name": "Khagaria",
    "country": "IN",
    "subdivision": "34",
    "timezone": "Asia/Kolkata"
  },
  "geometry": {
    "type": "Point",
    "coordinates": [
      86.46708,
      25.5022
    ]
  }
}