{
  "type": "Feature",
  "properties": {
    "name": "KoelwÄr",
    "country": "IN",
    "subdivision": "34",
    "timezone": "Asia/Kolkata"
  },
  "geometry": {
    "type": "Point",
    "coordinates": [
      84.79751,
      25.58055
    ]
  }
}