{
  "type": "Feature",
  "properties": {
    "name": "Luckeesarai",
    "country": "IN",
    "subdivision": "34",
    "timezone": "Asia/Kolkata"
  },
  "geometry": {
    "type": "Point",
    "coordinates": [
      86.0947,
      25.1765
    ]
  }
}