{
  "type": "Feature",
  "properties": {
    "name": "Mairwa",
    "country": "IN",
    "subdivision": "34",
    "timezone": "Asia/Kolkata"
  },
  "geometry": {
    "type": "Point",
    "coordinates": [
      84.16349,
      26.23218
    ]
  }
}