{
  "type": "Feature",
  "properties": {
    "name": "Monghyr",
    "country": "IN",
    "subdivision": "34",
    "timezone": "Asia/Kolkata"
  },
  "geometry": {
    "type": "Point",
    "coordinates": [
      86.47455,
      25.37459
    ]
  }
}