{
  "type": "Feature",
  "properties": {
    "name": "Mothīhāri",
    "country": "IN",
    "subdivision": "34",
    "timezone": "Asia/Kolkata"
  },
  "geometry": {
    "type": "Point",
    "coordinates": [
      84.91656,
      26.64862
    ]
  }
}