{
  "type": "Feature",
  "properties": {
    "name": "Piro",
    "country": "IN",
    "subdivision": "34",
    "timezone": "Asia/Kolkata"
  },
  "geometry": {
    "type": "Point",
    "coordinates": [
      84.40454,
      25.33218
    ]
  }
}