{
  "type": "Feature",
  "properties": {
    "name": "Rafiganj",
    "country": "IN",
    "subdivision": "34",
    "timezone": "Asia/Kolkata"
  },
  "geometry": {
    "type": "Point",
    "coordinates": [
      84.63445,
      24.81757
    ]
  }
}