{
  "type": "Feature",
  "properties": {
    "name": "Teghra",
    "country": "IN",
    "subdivision": "34",
    "timezone": "Asia/Kolkata"
  },
  "geometry": {
    "type": "Point",
    "coordinates": [
      85.94001,
      25.49043
    ]
  }
}