{
  "type": "Feature",
  "properties": {
    "name": "ThÄkurganj",
    "country": "IN",
    "subdivision": "34",
    "timezone": "Asia/Kolkata"
  },
  "geometry": {
    "type": "Point",
    "coordinates": [
      88.13112,
      26.42742
    ]
  }
}