{
  "type": "Feature",
  "properties": {
    "name": "Gravdal",
    "country": "NO",
    "subdivision": "09",
    "timezone": "Europe/Oslo"
  },
  "geometry": {
    "type": "Point",
    "coordinates": [
      13.55339,
      68.11832
    ]
  }
}