{
  "type": "Feature",
  "properties": {
    "name": "Leknes",
    "country": "NO",
    "subdivision": "09",
    "timezone": "Europe/Oslo"
  },
  "geometry": {
    "type": "Point",
    "coordinates": [
      13.61151,
      68.14746
    ]
  }
}