{
  "type": "Feature",
  "properties": {
    "name": "Løding",
    "country": "NO",
    "subdivision": "09",
    "timezone": "Europe/Oslo"
  },
  "geometry": {
    "type": "Point",
    "coordinates": [
      14.73852,
      67.30055
    ]
  }
}