{
  "type": "Feature",
  "properties": {
    "name": "Løpsmarka",
    "country": "NO",
    "subdivision": "09",
    "timezone": "Europe/Oslo"
  },
  "geometry": {
    "type": "Point",
    "coordinates": [
      14.44934,
      67.31343
    ]
  }
}