{
  "type": "Feature",
  "properties": {
    "name": "Stokmarknes",
    "country": "NO",
    "subdivision": "09",
    "timezone": "Europe/Oslo"
  },
  "geometry": {
    "type": "Point",
    "coordinates": [
      14.91075,
      68.56462
    ]
  }
}