{
  "type": "Feature",
  "properties": {
    "name": "Āsmār",
    "country": "AF",
    "subdivision": "34",
    "timezone": "Asia/Kabul"
  },
  "geometry": {
    "type": "Point",
    "coordinates": [
      71.35809,
      35.03333
    ]
  }
}