{
  "type": "Feature",
  "properties": {
    "name": "Çobansığnaq",
    "country": "AZ",
    "subdivision": "58",
    "timezone": "Asia/Baku"
  },
  "geometry": {
    "type": "Point",
    "coordinates": [
      45.70645,
      40.75244
    ]
  }
}