{
  "type": "Feature",
  "properties": {
    "name": "Alcoa",
    "country": "US",
    "subdivision": "TN",
    "timezone": "America/New_York"
  },
  "geometry": {
    "type": "Point",
    "coordinates": [
      -83.97379,
      35.78953
    ]
  }
}