{
  "type": "Feature",
  "properties": {
    "name": "Caryville",
    "country": "US",
    "subdivision": "TN",
    "timezone": "America/New_York"
  },
  "geometry": {
    "type": "Point",
    "coordinates": [
      -84.22326,
      36.29897
    ]
  }
}