{
  "type": "Feature",
  "properties": {
    "name": "Church Hill",
    "country": "US",
    "subdivision": "TN",
    "timezone": "America/New_York"
  },
  "geometry": {
    "type": "Point",
    "coordinates": [
      -82.71349,
      36.52232
    ]
  }
}