{
  "type": "Feature",
  "properties": {
    "name": "Colonial Heights",
    "country": "US",
    "subdivision": "TN",
    "timezone": "America/New_York"
  },
  "geometry": {
    "type": "Point",
    "coordinates": [
      -82.5032,
      36.4851
    ]
  }
}