{
  "type": "Feature",
  "properties": {
    "name": "Condon",
    "country": "US",
    "subdivision": "TN",
    "timezone": "America/New_York"
  },
  "geometry": {
    "type": "Point",
    "coordinates": [
      -83.7938,
      36.18119
    ]
  }
}