{
  "type": "Feature",
  "properties": {
    "name": "Cross Plains",
    "country": "US",
    "subdivision": "TN",
    "timezone": "America/Chicago"
  },
  "geometry": {
    "type": "Point",
    "coordinates": [
      -86.69611,
      36.54866
    ]
  }
}