{
  "type": "Feature",
  "properties": {
    "name": "Decherd",
    "country": "US",
    "subdivision": "TN",
    "timezone": "America/Chicago"
  },
  "geometry": {
    "type": "Point",
    "coordinates": [
      -86.07943,
      35.2098
    ]
  }
}