{
  "type": "Feature",
  "properties": {
    "name": "Dunlap",
    "country": "US",
    "subdivision": "TN",
    "timezone": "America/Chicago"
  },
  "geometry": {
    "type": "Point",
    "coordinates": [
      -85.39052,
      35.37146
    ]
  }
}