{
  "type": "Feature",
  "properties": {
    "name": "Elizabethton",
    "country": "US",
    "subdivision": "TN",
    "timezone": "America/New_York"
  },
  "geometry": {
    "type": "Point",
    "coordinates": [
      -82.21069,
      36.34872
    ]
  }
}