{
  "type": "Feature",
  "properties": {
    "name": "Fayetteville",
    "country": "US",
    "subdivision": "TN",
    "timezone": "America/Chicago"
  },
  "geometry": {
    "type": "Point",
    "coordinates": [
      -86.57055,
      35.15203
    ]
  }
}