{
  "type": "Feature",
  "properties": {
    "name": "Jackson",
    "country": "US",
    "subdivision": "TN",
    "timezone": "America/Chicago"
  },
  "geometry": {
    "type": "Point",
    "coordinates": [
      -88.81395,
      35.61452
    ]
  }
}