{
  "type": "Feature",
  "properties": {
    "name": "Jellico",
    "country": "US",
    "subdivision": "TN",
    "timezone": "America/New_York"
  },
  "geometry": {
    "type": "Point",
    "coordinates": [
      -84.12687,
      36.58786
    ]
  }
}