{
  "type": "Feature",
  "properties": {
    "name": "Lakeland",
    "country": "US",
    "subdivision": "TN",
    "timezone": "America/Chicago"
  },
  "geometry": {
    "type": "Point",
    "coordinates": [
      -89.74036,
      35.23064
    ]
  }
}