{
  "type": "Feature",
  "properties": {
    "name": "Lenoir City",
    "country": "US",
    "subdivision": "TN",
    "timezone": "America/New_York"
  },
  "geometry": {
    "type": "Point",
    "coordinates": [
      -84.25603,
      35.7973
    ]
  }
}