{
  "type": "Feature",
  "properties": {
    "name": "Lynchburg",
    "country": "US",
    "subdivision": "TN",
    "timezone": "America/Chicago"
  },
  "geometry": {
    "type": "Point",
    "coordinates": [
      -86.37416,
      35.28314
    ]
  }
}