{
  "type": "Feature",
  "properties": {
    "name": "McMinnville",
    "country": "US",
    "subdivision": "TN",
    "timezone": "America/Chicago"
  },
  "geometry": {
    "type": "Point",
    "coordinates": [
      -85.76998,
      35.6834
    ]
  }
}