{
  "type": "Feature",
  "properties": {
    "name": "New Tazewell",
    "country": "US",
    "subdivision": "TN",
    "timezone": "America/New_York"
  },
  "geometry": {
    "type": "Point",
    "coordinates": [
      -83.59963,
      36.44258
    ]
  }
}