{
  "type": "Feature",
  "properties": {
    "name": "New Hope",
    "country": "US",
    "subdivision": "TN",
    "timezone": "America/Chicago"
  },
  "geometry": {
    "type": "Point",
    "coordinates": [
      -85.6583,
      35.00508
    ]
  }
}