{
  "type": "Feature",
  "properties": {
    "name": "Nolensville",
    "country": "US",
    "subdivision": "TN",
    "timezone": "America/Chicago"
  },
  "geometry": {
    "type": "Point",
    "coordinates": [
      -86.66944,
      35.95229
    ]
  }
}