{
  "type": "Feature",
  "properties": {
    "name": "Pleasant View",
    "country": "US",
    "subdivision": "TN",
    "timezone": "America/Chicago"
  },
  "geometry": {
    "type": "Point",
    "coordinates": [
      -87.03667,
      36.39422
    ]
  }
}