{
  "type": "Feature",
  "properties": {
    "name": "Ridgely",
    "country": "US",
    "subdivision": "TN",
    "timezone": "America/Chicago"
  },
  "geometry": {
    "type": "Point",
    "coordinates": [
      -89.48785,
      36.2634
    ]
  }
}