{
  "type": "Feature",
  "properties": {
    "name": "Roan Mountain",
    "country": "US",
    "subdivision": "TN",
    "timezone": "America/New_York"
  },
  "geometry": {
    "type": "Point",
    "coordinates": [
      -82.0704,
      36.19623
    ]
  }
}