{
  "type": "Feature",
  "properties": {
    "name": "South Pittsburg",
    "country": "US",
    "subdivision": "TN",
    "timezone": "America/Chicago"
  },
  "geometry": {
    "type": "Point",
    "coordinates": [
      -85.70441,
      35.0123
    ]
  }
}