{
  "type": "Feature",
  "properties": {
    "name": "Spencer",
    "country": "US",
    "subdivision": "TN",
    "timezone": "America/Chicago"
  },
  "geometry": {
    "type": "Point",
    "coordinates": [
      -85.46664,
      35.74729
    ]
  }
}