{
  "type": "Feature",
  "properties": {
    "name": "Surgoinsville",
    "country": "US",
    "subdivision": "TN",
    "timezone": "America/New_York"
  },
  "geometry": {
    "type": "Point",
    "coordinates": [
      -82.85183,
      36.47093
    ]
  }
}