{
  "type": "Feature",
  "properties": {
    "name": "Sweetwater",
    "country": "US",
    "subdivision": "TN",
    "timezone": "America/New_York"
  },
  "geometry": {
    "type": "Point",
    "coordinates": [
      -84.46104,
      35.60146
    ]
  }
}