{
  "type": "Feature",
  "properties": {
    "name": "Tennessee Ridge",
    "country": "US",
    "subdivision": "TN",
    "timezone": "America/Chicago"
  },
  "geometry": {
    "type": "Point",
    "coordinates": [
      -87.77336,
      36.312
    ]
  }
}