{
  "type": "Feature",
  "properties": {
    "name": "Whitwell",
    "country": "US",
    "subdivision": "TN",
    "timezone": "America/Chicago"
  },
  "geometry": {
    "type": "Point",
    "coordinates": [
      -85.51913,
      35.20146
    ]
  }
}