{
  "type": "Feature",
  "properties": {
    "name": "Årjäng",
    "country": "SE",
    "subdivision": "22",
    "timezone": "Europe/Stockholm"
  },
  "geometry": {
    "type": "Point",
    "coordinates": [
      12.13336,
      59.39217
    ]
  }
}