{
  "type": "Feature",
  "properties": {
    "name": "Munkfors",
    "country": "SE",
    "subdivision": "22",
    "timezone": "Europe/Stockholm"
  },
  "geometry": {
    "type": "Point",
    "coordinates": [
      13.54361,
      59.83856
    ]
  }
}