{
  "type": "Feature",
  "properties": {
    "name": "Pršovce",
    "country": "MK",
    "subdivision": "A5",
    "timezone": "Europe/Skopje"
  },
  "geometry": {
    "type": "Point",
    "coordinates": [
      21.05994,
      42.08336
    ]
  }
}