{
  "type": "Feature",
  "properties": {
    "name": "Viqueque",
    "country": "TL",
    "subdivision": "VI",
    "timezone": "Asia/Dili"
  },
  "geometry": {
    "type": "Point",
    "coordinates": [
      126.36472,
      -8.8575
    ]
  }
}