{
  "type": "Feature",
  "properties": {
    "name": "Alto Paraná",
    "country": "BR",
    "subdivision": "18",
    "timezone": "America/Sao_Paulo"
  },
  "geometry": {
    "type": "Point",
    "coordinates": [
      -52.31889,
      -23.12889
    ]
  }
}