{
  "type": "Feature",
  "properties": {
    "name": "Antonina",
    "country": "BR",
    "subdivision": "18",
    "timezone": "America/Sao_Paulo"
  },
  "geometry": {
    "type": "Point",
    "coordinates": [
      -48.71194,
      -25.42861
    ]
  }
}