{
  "type": "Feature",
  "properties": {
    "name": "Assaí",
    "country": "BR",
    "subdivision": "18",
    "timezone": "America/Sao_Paulo"
  },
  "geometry": {
    "type": "Point",
    "coordinates": [
      -50.84139,
      -23.37333
    ]
  }
}