{
  "type": "Feature",
  "properties": {
    "name": "Borrazópolis",
    "country": "BR",
    "subdivision": "18",
    "timezone": "America/Sao_Paulo"
  },
  "geometry": {
    "type": "Point",
    "coordinates": [
      -51.5875,
      -23.94111
    ]
  }
}