{
  "type": "Feature",
  "properties": {
    "name": "Curitiba",
    "country": "BR",
    "subdivision": "18",
    "timezone": "America/Sao_Paulo"
  },
  "geometry": {
    "type": "Point",
    "coordinates": [
      -49.27306,
      -25.42778
    ]
  }
}