{
  "type": "Feature",
  "properties": {
    "name": "Foz do Iguaçu",
    "country": "BR",
    "subdivision": "18",
    "timezone": "America/Sao_Paulo"
  },
  "geometry": {
    "type": "Point",
    "coordinates": [
      -54.58806,
      -25.54778
    ]
  }
}