{
  "type": "Feature",
  "properties": {
    "name": "Guarapuava",
    "country": "BR",
    "subdivision": "18",
    "timezone": "America/Sao_Paulo"
  },
  "geometry": {
    "type": "Point",
    "coordinates": [
      -51.46541,
      -25.39048
    ]
  }
}