{
  "type": "Feature",
  "properties": {
    "name": "Ibiporã",
    "country": "BR",
    "subdivision": "18",
    "timezone": "America/Sao_Paulo"
  },
  "geometry": {
    "type": "Point",
    "coordinates": [
      -51.04806,
      -23.26917
    ]
  }
}