{
  "type": "Feature",
  "properties": {
    "name": "Jandaia do Sul",
    "country": "BR",
    "subdivision": "18",
    "timezone": "America/Sao_Paulo"
  },
  "geometry": {
    "type": "Point",
    "coordinates": [
      -51.64333,
      -23.60306
    ]
  }
}