{
  "type": "Feature",
  "properties": {
    "name": "Nova Aurora",
    "country": "BR",
    "subdivision": "18",
    "timezone": "America/Sao_Paulo"
  },
  "geometry": {
    "type": "Point",
    "coordinates": [
      -52.56667,
      -22.86667
    ]
  }
}