{
  "type": "Feature",
  "properties": {
    "name": "Ponta Grossa",
    "country": "BR",
    "subdivision": "18",
    "timezone": "America/Sao_Paulo"
  },
  "geometry": {
    "type": "Point",
    "coordinates": [
      -50.16194,
      -25.095
    ]
  }
}