{
  "type": "Feature",
  "properties": {
    "name": "Realeza",
    "country": "BR",
    "subdivision": "18",
    "timezone": "America/Sao_Paulo"
  },
  "geometry": {
    "type": "Point",
    "coordinates": [
      -53.5325,
      -25.76889
    ]
  }
}