{
  "type": "Feature",
  "properties": {
    "name": "Rio Negro",
    "country": "BR",
    "subdivision": "18",
    "timezone": "America/Sao_Paulo"
  },
  "geometry": {
    "type": "Point",
    "coordinates": [
      -49.7975,
      -26.10583
    ]
  }
}