{
  "type": "Feature",
  "properties": {
    "name": "Terra Rica",
    "country": "BR",
    "subdivision": "18",
    "timezone": "America/Sao_Paulo"
  },
  "geometry": {
    "type": "Point",
    "coordinates": [
      -52.61694,
      -22.70944
    ]
  }
}