{
  "type": "Feature",
  "properties": {
    "name": "Ayorou",
    "country": "NE",
    "subdivision": "09",
    "timezone": "Africa/Niamey"
  },
  "geometry": {
    "type": "Point",
    "coordinates": [
      0.91739,
      14.73075
    ]
  }
}