{
  "type": "Feature",
  "properties": {
    "name": "Sanjō",
    "country": "JP",
    "subdivision": "29",
    "timezone": "Asia/Tokyo"
  },
  "geometry": {
    "type": "Point",
    "coordinates": [
      138.95,
      37.61667
    ]
  }
}