{
  "type": "Feature",
  "properties": {
    "name": "Shiozawa",
    "country": "JP",
    "subdivision": "29",
    "timezone": "Asia/Tokyo"
  },
  "geometry": {
    "type": "Point",
    "coordinates": [
      138.84867,
      37.03757
    ]
  }
}