{
  "type": "Feature",
  "properties": {
    "name": "Tochio-honchō",
    "country": "JP",
    "subdivision": "29",
    "timezone": "Asia/Tokyo"
  },
  "geometry": {
    "type": "Point",
    "coordinates": [
      138.99513,
      37.47642
    ]
  }
}