{
  "type": "Feature",
  "properties": {
    "name": "Liminka",
    "country": "FI",
    "subdivision": "17",
    "timezone": "Europe/Helsinki"
  },
  "geometry": {
    "type": "Point",
    "coordinates": [
      25.41545,
      64.80985
    ]
  }
}