{
  "type": "Feature",
  "properties": {
    "name": "Piippola",
    "country": "FI",
    "subdivision": "17",
    "timezone": "Europe/Helsinki"
  },
  "geometry": {
    "type": "Point",
    "coordinates": [
      25.96667,
      64.16667
    ]
  }
}