{
  "type": "Feature",
  "properties": {
    "name": "Ranong",
    "country": "TH",
    "subdivision": "59",
    "timezone": "Asia/Bangkok"
  },
  "geometry": {
    "type": "Point",
    "coordinates": [
      98.63476,
      9.96583
    ]
  }
}