{
  "type": "Feature",
  "properties": {
    "name": "Manatutu",
    "country": "TL",
    "subdivision": "MT",
    "timezone": "Asia/Dili"
  },
  "geometry": {
    "type": "Point",
    "coordinates": [
      126.01306,
      -8.51139
    ]
  }
}