{
  "type": "Feature",
  "properties": {
    "name": "Lagoa da Canoa",
    "country": "BR",
    "subdivision": "02",
    "timezone": "America/Maceio"
  },
  "geometry": {
    "type": "Point",
    "coordinates": [
      -36.73778,
      -9.82972
    ]
  }
}