{
  "type": "Feature",
  "properties": {
    "name": "Maribondo",
    "country": "BR",
    "subdivision": "02",
    "timezone": "America/Maceio"
  },
  "geometry": {
    "type": "Point",
    "coordinates": [
      -36.30528,
      -9.57722
    ]
  }
}