{
  "type": "Feature",
  "properties": {
    "name": "Pão de Açúcar",
    "country": "BR",
    "subdivision": "02",
    "timezone": "America/Maceio"
  },
  "geometry": {
    "type": "Point",
    "coordinates": [
      -37.43667,
      -9.74833
    ]
  }
}