{
  "type": "Feature",
  "properties": {
    "name": "Traipu",
    "country": "BR",
    "subdivision": "02",
    "timezone": "America/Maceio"
  },
  "geometry": {
    "type": "Point",
    "coordinates": [
      -37.00333,
      -9.97056
    ]
  }
}