{
  "type": "Feature",
  "properties": {
    "name": "União dos Palmares",
    "country": "BR",
    "subdivision": "02",
    "timezone": "America/Maceio"
  },
  "geometry": {
    "type": "Point",
    "coordinates": [
      -36.03194,
      -9.16278
    ]
  }
}