{
  "type": "Feature",
  "properties": {
    "name": "Camabatela",
    "country": "AO",
    "subdivision": "05",
    "timezone": "Africa/Luanda"
  },
  "geometry": {
    "type": "Point",
    "coordinates": [
      15.37495,
      -8.18812
    ]
  }
}