{
  "type": "Feature",
  "properties": {
    "name": "Diepsloot",
    "country": "ZA",
    "subdivision": "06",
    "timezone": "Africa/Johannesburg"
  },
  "geometry": {
    "type": "Point",
    "coordinates": [
      28.01213,
      -25.93312
    ]
  }
}