{
  "type": "Feature",
  "properties": {
    "name": "Muldersdriseloop",
    "country": "ZA",
    "subdivision": "06",
    "timezone": "Africa/Johannesburg"
  },
  "geometry": {
    "type": "Point",
    "coordinates": [
      27.83798,
      -26.03673
    ]
  }
}