{
  "type": "Feature",
  "properties": {
    "name": "Randburg",
    "country": "ZA",
    "subdivision": "06",
    "timezone": "Africa/Johannesburg"
  },
  "geometry": {
    "type": "Point",
    "coordinates": [
      28.00123,
      -26.0941
    ]
  }
}