{
  "type": "Feature",
  "properties": {
    "name": "Lyubimets",
    "country": "BG",
    "subdivision": "43",
    "timezone": "Europe/Sofia"
  },
  "geometry": {
    "type": "Point",
    "coordinates": [
      26.08333,
      41.83333
    ]
  }
}