{
  "type": "Feature",
  "properties": {
    "name": "Madzharovo",
    "country": "BG",
    "subdivision": "43",
    "timezone": "Europe/Sofia"
  },
  "geometry": {
    "type": "Point",
    "coordinates": [
      25.86439,
      41.63461
    ]
  }
}