{
  "type": "Feature",
  "properties": {
    "name": "Mineralni Bani",
    "country": "BG",
    "subdivision": "43",
    "timezone": "Europe/Sofia"
  },
  "geometry": {
    "type": "Point",
    "coordinates": [
      25.35,
      41.91667
    ]
  }
}