{
  "type": "Feature",
  "properties": {
    "name": "Göynücek",
    "country": "TR",
    "subdivision": "05",
    "timezone": "Europe/Istanbul"
  },
  "geometry": {
    "type": "Point",
    "coordinates": [
      35.525,
      40.39917
    ]
  }
}