{
  "type": "Feature",
  "properties": {
    "name": "Taşova",
    "country": "TR",
    "subdivision": "05",
    "timezone": "Europe/Istanbul"
  },
  "geometry": {
    "type": "Point",
    "coordinates": [
      36.3225,
      40.75972
    ]
  }
}