{
  "type": "Feature",
  "properties": {
    "name": "Logovardi",
    "country": "MK",
    "subdivision": "06",
    "timezone": "Europe/Skopje"
  },
  "geometry": {
    "type": "Point",
    "coordinates": [
      21.40967,
      41.03096
    ]
  }
}