{
  "type": "Feature",
  "properties": {
    "name": "Andkhōy",
    "country": "AF",
    "subdivision": "07",
    "timezone": "Asia/Kabul"
  },
  "geometry": {
    "type": "Point",
    "coordinates": [
      65.12376,
      36.95293
    ]
  }
}