{
  "type": "Feature",
  "properties": {
    "name": "Baraolt",
    "country": "RO",
    "subdivision": "15",
    "timezone": "Europe/Bucharest"
  },
  "geometry": {
    "type": "Point",
    "coordinates": [
      25.60029,
      46.07514
    ]
  }
}