{
  "type": "Feature",
  "properties": {
    "name": "Brăduţ",
    "country": "RO",
    "subdivision": "15",
    "timezone": "Europe/Bucharest"
  },
  "geometry": {
    "type": "Point",
    "coordinates": [
      25.61667,
      46.13333
    ]
  }
}