{
  "type": "Feature",
  "properties": {
    "name": "Brateş",
    "country": "RO",
    "subdivision": "15",
    "timezone": "Europe/Bucharest"
  },
  "geometry": {
    "type": "Point",
    "coordinates": [
      26.06667,
      45.83333
    ]
  }
}