{
  "type": "Feature",
  "properties": {
    "name": "Dalnic",
    "country": "RO",
    "subdivision": "15",
    "timezone": "Europe/Bucharest"
  },
  "geometry": {
    "type": "Point",
    "coordinates": [
      25.98741,
      45.92242
    ]
  }
}