{
  "type": "Feature",
  "properties": {
    "name": "Dobârlău",
    "country": "RO",
    "subdivision": "15",
    "timezone": "Europe/Bucharest"
  },
  "geometry": {
    "type": "Point",
    "coordinates": [
      25.88333,
      45.73333
    ]
  }
}