{
  "type": "Feature",
  "properties": {
    "name": "Bardo",
    "country": "PL",
    "subdivision": "72",
    "timezone": "Europe/Warsaw"
  },
  "geometry": {
    "type": "Point",
    "coordinates": [
      16.73986,
      50.50589
    ]
  }
}