{
  "type": "Feature",
  "properties": {
    "name": "Bielawa",
    "country": "PL",
    "subdivision": "72",
    "timezone": "Europe/Warsaw"
  },
  "geometry": {
    "type": "Point",
    "coordinates": [
      16.623,
      50.69075
    ]
  }
}