{
  "type": "Feature",
  "properties": {
    "name": "Dąbie",
    "country": "PL",
    "subdivision": "72",
    "timezone": "Europe/Warsaw"
  },
  "geometry": {
    "type": "Point",
    "coordinates": [
      17.08108,
      51.10573
    ]
  }
}