{
  "type": "Feature",
  "properties": {
    "name": "Gądów Mały",
    "country": "PL",
    "subdivision": "72",
    "timezone": "Europe/Warsaw"
  },
  "geometry": {
    "type": "Point",
    "coordinates": [
      16.98596,
      51.11853
    ]
  }
}