{
  "type": "Feature",
  "properties": {
    "name": "Głogów",
    "country": "PL",
    "subdivision": "72",
    "timezone": "Europe/Warsaw"
  },
  "geometry": {
    "type": "Point",
    "coordinates": [
      16.0845,
      51.66361
    ]
  }
}