{
  "type": "Feature",
  "properties": {
    "name": "Karpacz",
    "country": "PL",
    "subdivision": "72",
    "timezone": "Europe/Warsaw"
  },
  "geometry": {
    "type": "Point",
    "coordinates": [
      15.75594,
      50.77669
    ]
  }
}