{
  "type": "Feature",
  "properties": {
    "name": "Kowary",
    "country": "PL",
    "subdivision": "72",
    "timezone": "Europe/Warsaw"
  },
  "geometry": {
    "type": "Point",
    "coordinates": [
      15.83559,
      50.79313
    ]
  }
}