{
  "type": "Feature",
  "properties": {
    "name": "Leśna",
    "country": "PL",
    "subdivision": "72",
    "timezone": "Europe/Warsaw"
  },
  "geometry": {
    "type": "Point",
    "coordinates": [
      15.26413,
      51.02431
    ]
  }
}