{
  "type": "Feature",
  "properties": {
    "name": "Marciszów",
    "country": "PL",
    "subdivision": "72",
    "timezone": "Europe/Warsaw"
  },
  "geometry": {
    "type": "Point",
    "coordinates": [
      16.02116,
      50.8447
    ]
  }
}