{
  "type": "Feature",
  "properties": {
    "name": "Międzybórz",
    "country": "PL",
    "subdivision": "72",
    "timezone": "Europe/Warsaw"
  },
  "geometry": {
    "type": "Point",
    "coordinates": [
      17.6661,
      51.39626
    ]
  }
}