{
  "type": "Feature",
  "properties": {
    "name": "Mirków",
    "country": "PL",
    "subdivision": "72",
    "timezone": "Europe/Warsaw"
  },
  "geometry": {
    "type": "Point",
    "coordinates": [
      17.17026,
      51.16105
    ]
  }
}