{
  "type": "Feature",
  "properties": {
    "name": "Pilczyce",
    "country": "PL",
    "subdivision": "72",
    "timezone": "Europe/Warsaw"
  },
  "geometry": {
    "type": "Point",
    "coordinates": [
      16.95752,
      51.13704
    ]
  }
}