{
  "type": "Feature",
  "properties": {
    "name": "Piława Górna",
    "country": "PL",
    "subdivision": "72",
    "timezone": "Europe/Warsaw"
  },
  "geometry": {
    "type": "Point",
    "coordinates": [
      16.74359,
      50.68357
    ]
  }
}