{
  "type": "Feature",
  "properties": {
    "name": "Powstańców Śląskich Zachód-Centrum Południow",
    "country": "PL",
    "subdivision": "72",
    "timezone": "Europe/Warsaw"
  },
  "geometry": {
    "type": "Point",
    "coordinates": [
      17.0177,
      51.09607
    ]
  }
}