{
  "type": "Feature",
  "properties": {
    "name": "Przeworno",
    "country": "PL",
    "subdivision": "72",
    "timezone": "Europe/Warsaw"
  },
  "geometry": {
    "type": "Point",
    "coordinates": [
      17.16588,
      50.68629
    ]
  }
}