{
  "type": "Feature",
  "properties": {
    "name": "Psary",
    "country": "PL",
    "subdivision": "72",
    "timezone": "Europe/Warsaw"
  },
  "geometry": {
    "type": "Point",
    "coordinates": [
      17.03173,
      51.18712
    ]
  }
}