{
  "type": "Feature",
  "properties": {
    "name": "Rejon placu Grunwaldzkiego",
    "country": "PL",
    "subdivision": "72",
    "timezone": "Europe/Warsaw"
  },
  "geometry": {
    "type": "Point",
    "coordinates": [
      17.06126,
      51.11669
    ]
  }
}