{
  "type": "Feature",
  "properties": {
    "name": "Rudna",
    "country": "PL",
    "subdivision": "72",
    "timezone": "Europe/Warsaw"
  },
  "geometry": {
    "type": "Point",
    "coordinates": [
      16.26363,
      51.50981
    ]
  }
}