{
  "type": "Feature",
  "properties": {
    "name": "Sosnówka",
    "country": "PL",
    "subdivision": "72",
    "timezone": "Europe/Warsaw"
  },
  "geometry": {
    "type": "Point",
    "coordinates": [
      15.72315,
      50.8183
    ]
  }
}