{
  "type": "Feature",
  "properties": {
    "name": "Szczytna",
    "country": "PL",
    "subdivision": "72",
    "timezone": "Europe/Warsaw"
  },
  "geometry": {
    "type": "Point",
    "coordinates": [
      16.44743,
      50.41343
    ]
  }
}