{
  "type": "Feature",
  "properties": {
    "name": "Szklarska Poręba",
    "country": "PL",
    "subdivision": "72",
    "timezone": "Europe/Warsaw"
  },
  "geometry": {
    "type": "Point",
    "coordinates": [
      15.52274,
      50.82567
    ]
  }
}