{
  "type": "Feature",
  "properties": {
    "name": "Twardogóra",
    "country": "PL",
    "subdivision": "72",
    "timezone": "Europe/Warsaw"
  },
  "geometry": {
    "type": "Point",
    "coordinates": [
      17.46878,
      51.36487
    ]
  }
}