{
  "type": "Feature",
  "properties": {
    "name": "Wiązów",
    "country": "PL",
    "subdivision": "72",
    "timezone": "Europe/Warsaw"
  },
  "geometry": {
    "type": "Point",
    "coordinates": [
      17.20214,
      50.81399
    ]
  }
}