{
  "type": "Feature",
  "properties": {
    "name": "Wleń",
    "country": "PL",
    "subdivision": "72",
    "timezone": "Europe/Warsaw"
  },
  "geometry": {
    "type": "Point",
    "coordinates": [
      15.67474,
      51.01635
    ]
  }
}