{
  "type": "Feature",
  "properties": {
    "name": "Wojszyce",
    "country": "PL",
    "subdivision": "72",
    "timezone": "Europe/Warsaw"
  },
  "geometry": {
    "type": "Point",
    "coordinates": [
      17.04513,
      51.05837
    ]
  }
}