{
  "type": "Feature",
  "properties": {
    "name": "Navrongo",
    "country": "GH",
    "subdivision": "10",
    "timezone": "Africa/Accra"
  },
  "geometry": {
    "type": "Point",
    "coordinates": [
      -1.0921,
      10.89557
    ]
  }
}