{
  "type": "Feature",
  "properties": {
    "name": "Miyazaki",
    "country": "JP",
    "subdivision": "25",
    "timezone": "Asia/Tokyo"
  },
  "geometry": {
    "type": "Point",
    "coordinates": [
      131.41667,
      31.91667
    ]
  }
}