{
  "type": "Feature",
  "properties": {
    "name": "Golema Rečica",
    "country": "MK",
    "subdivision": "E8",
    "timezone": "Europe/Skopje"
  },
  "geometry": {
    "type": "Point",
    "coordinates": [
      20.94517,
      41.98803
    ]
  }
}