{
  "type": "Feature",
  "properties": {
    "name": "Šipkovica",
    "country": "MK",
    "subdivision": "E8",
    "timezone": "Europe/Skopje"
  },
  "geometry": {
    "type": "Point",
    "coordinates": [
      20.91556,
      42.035
    ]
  }
}