{
  "type": "Feature",
  "properties": {
    "name": "Tetovo",
    "country": "MK",
    "subdivision": "E8",
    "timezone": "Europe/Skopje"
  },
  "geometry": {
    "type": "Point",
    "coordinates": [
      20.97155,
      42.00973
    ]
  }
}