{
  "type": "Feature",
  "properties": {
    "name": "Blahovishchenske",
    "country": "UA",
    "subdivision": "10",
    "timezone": "Europe/Kiev"
  },
  "geometry": {
    "type": "Point",
    "coordinates": [
      30.23619,
      48.32822
    ]
  }
}