{
  "type": "Feature",
  "properties": {
    "name": "Dobrovelychkivka",
    "country": "UA",
    "subdivision": "10",
    "timezone": "Europe/Kiev"
  },
  "geometry": {
    "type": "Point",
    "coordinates": [
      31.18039,
      48.38939
    ]
  }
}