{
  "type": "Feature",
  "properties": {
    "name": "Holovanivsk",
    "country": "UA",
    "subdivision": "10",
    "timezone": "Europe/Kiev"
  },
  "geometry": {
    "type": "Point",
    "coordinates": [
      30.45947,
      48.3874
    ]
  }
}