{
  "type": "Feature",
  "properties": {
    "name": "Pryyutivka",
    "country": "UA",
    "subdivision": "10",
    "timezone": "Europe/Kiev"
  },
  "geometry": {
    "type": "Point",
    "coordinates": [
      33.06617,
      48.72925
    ]
  }
}