{
  "type": "Feature",
  "properties": {
    "name": "Gudja",
    "country": "MT",
    "subdivision": "16",
    "timezone": "Europe/Malta"
  },
  "geometry": {
    "type": "Point",
    "coordinates": [
      14.50306,
      35.84917
    ]
  }
}