{
  "type": "Feature",
  "properties": {
    "name": "Avio",
    "country": "IT",
    "subdivision": "17",
    "timezone": "Europe/Rome"
  },
  "geometry": {
    "type": "Point",
    "coordinates": [
      10.93938,
      45.73396
    ]
  }
}