{
  "type": "Feature",
  "properties": {
    "name": "Brentonico",
    "country": "IT",
    "subdivision": "17",
    "timezone": "Europe/Rome"
  },
  "geometry": {
    "type": "Point",
    "coordinates": [
      10.95508,
      45.8191
    ]
  }
}