{
  "type": "Feature",
  "properties": {
    "name": "Castelrotto",
    "country": "IT",
    "subdivision": "17",
    "timezone": "Europe/Rome"
  },
  "geometry": {
    "type": "Point",
    "coordinates": [
      11.56098,
      46.56662
    ]
  }
}