{
  "type": "Feature",
  "properties": {
    "name": "Castello Molina di Fiemme",
    "country": "IT",
    "subdivision": "17",
    "timezone": "Europe/Rome"
  },
  "geometry": {
    "type": "Point",
    "coordinates": [
      11.43348,
      46.28241
    ]
  }
}