{
  "type": "Feature",
  "properties": {
    "name": "Cembra",
    "country": "IT",
    "subdivision": "17",
    "timezone": "Europe/Rome"
  },
  "geometry": {
    "type": "Point",
    "coordinates": [
      11.22174,
      46.17489
    ]
  }
}