{
  "type": "Feature",
  "properties": {
    "name": "Cermes",
    "country": "IT",
    "subdivision": "17",
    "timezone": "Europe/Rome"
  },
  "geometry": {
    "type": "Point",
    "coordinates": [
      11.14696,
      46.63277
    ]
  }
}