{
  "type": "Feature",
  "properties": {
    "name": "La Valle - Wengen",
    "country": "IT",
    "subdivision": "17",
    "timezone": "Europe/Rome"
  },
  "geometry": {
    "type": "Point",
    "coordinates": [
      11.92399,
      46.65763
    ]
  }
}