{
  "type": "Feature",
  "properties": {
    "name": "Merano",
    "country": "IT",
    "subdivision": "17",
    "timezone": "Europe/Rome"
  },
  "geometry": {
    "type": "Point",
    "coordinates": [
      11.15953,
      46.66817
    ]
  }
}