{
  "type": "Feature",
  "properties": {
    "name": "Nago-Torbole",
    "country": "IT",
    "subdivision": "17",
    "timezone": "Europe/Rome"
  },
  "geometry": {
    "type": "Point",
    "coordinates": [
      10.89106,
      45.87594
    ]
  }
}