{
  "type": "Feature",
  "properties": {
    "name": "Nalles",
    "country": "IT",
    "subdivision": "17",
    "timezone": "Europe/Rome"
  },
  "geometry": {
    "type": "Point",
    "coordinates": [
      11.20625,
      46.54341
    ]
  }
}