{
  "type": "Feature",
  "properties": {
    "name": "Ora",
    "country": "IT",
    "subdivision": "17",
    "timezone": "Europe/Rome"
  },
  "geometry": {
    "type": "Point",
    "coordinates": [
      11.29747,
      46.34687
    ]
  }
}