{
  "type": "Feature",
  "properties": {
    "name": "Parcines",
    "country": "IT",
    "subdivision": "17",
    "timezone": "Europe/Rome"
  },
  "geometry": {
    "type": "Point",
    "coordinates": [
      11.07337,
      46.68422
    ]
  }
}