{
  "type": "Feature",
  "properties": {
    "name": "Rabbi Fonti",
    "country": "IT",
    "subdivision": "17",
    "timezone": "Europe/Rome"
  },
  "geometry": {
    "type": "Point",
    "coordinates": [
      10.84951,
      46.39886
    ]
  }
}