{
  "type": "Feature",
  "properties": {
    "name": "Racines - Ratschings",
    "country": "IT",
    "subdivision": "17",
    "timezone": "Europe/Rome"
  },
  "geometry": {
    "type": "Point",
    "coordinates": [
      11.37827,
      46.88183
    ]
  }
}