{
  "type": "Feature",
  "properties": {
    "name": "Revò",
    "country": "IT",
    "subdivision": "17",
    "timezone": "Europe/Rome"
  },
  "geometry": {
    "type": "Point",
    "coordinates": [
      11.05808,
      46.39226
    ]
  }
}