{
  "type": "Feature",
  "properties": {
    "name": "Riscone",
    "country": "IT",
    "subdivision": "17",
    "timezone": "Europe/Rome"
  },
  "geometry": {
    "type": "Point",
    "coordinates": [
      11.95149,
      46.77685
    ]
  }
}