{
  "type": "Feature",
  "properties": {
    "name": "San Candido",
    "country": "IT",
    "subdivision": "17",
    "timezone": "Europe/Rome"
  },
  "geometry": {
    "type": "Point",
    "coordinates": [
      12.27855,
      46.7324
    ]
  }
}