{
  "type": "Feature",
  "properties": {
    "name": "Sinigo",
    "country": "IT",
    "subdivision": "17",
    "timezone": "Europe/Rome"
  },
  "geometry": {
    "type": "Point",
    "coordinates": [
      11.17926,
      46.63488
    ]
  }
}