{
  "type": "Feature",
  "properties": {
    "name": "Terento",
    "country": "IT",
    "subdivision": "17",
    "timezone": "Europe/Rome"
  },
  "geometry": {
    "type": "Point",
    "coordinates": [
      11.78288,
      46.82992
    ]
  }
}