{
  "type": "Feature",
  "properties": {
    "name": "Vandoies - Vintl",
    "country": "IT",
    "subdivision": "17",
    "timezone": "Europe/Rome"
  },
  "geometry": {
    "type": "Point",
    "coordinates": [
      11.72068,
      46.81513
    ]
  }
}