{
  "type": "Feature",
  "properties": {
    "name": "Volano",
    "country": "IT",
    "subdivision": "17",
    "timezone": "Europe/Rome"
  },
  "geometry": {
    "type": "Point",
    "coordinates": [
      11.06351,
      45.91718
    ]
  }
}