{
  "type": "Feature",
  "properties": {
    "name": "Chaman",
    "country": "PK",
    "subdivision": "02",
    "timezone": "Asia/Karachi"
  },
  "geometry": {
    "type": "Point",
    "coordinates": [
      66.45259,
      30.91769
    ]
  }
}