{
  "type": "Feature",
  "properties": {
    "name": "Khadan Khak",
    "country": "PK",
    "subdivision": "02",
    "timezone": "Asia/Karachi"
  },
  "geometry": {
    "type": "Point",
    "coordinates": [
      67.71133,
      30.75236
    ]
  }
}