{
  "type": "Feature",
  "properties": {
    "name": "Surab",
    "country": "PK",
    "subdivision": "02",
    "timezone": "Asia/Karachi"
  },
  "geometry": {
    "type": "Point",
    "coordinates": [
      66.25999,
      28.49276
    ]
  }
}