{
  "type": "Feature",
  "properties": {
    "name": "Uthal",
    "country": "PK",
    "subdivision": "02",
    "timezone": "Asia/Karachi"
  },
  "geometry": {
    "type": "Point",
    "coordinates": [
      66.62194,
      25.80722
    ]
  }
}