{
  "type": "Feature",
  "properties": {
    "name": "Constanza",
    "country": "DO",
    "subdivision": "30",
    "timezone": "America/Santo_Domingo"
  },
  "geometry": {
    "type": "Point",
    "coordinates": [
      -70.74499,
      18.90919
    ]
  }
}