{
  "type": "Feature",
  "properties": {
    "name": "Ash ShafÄ",
    "country": "SA",
    "subdivision": "14",
    "timezone": "Asia/Riyadh"
  },
  "geometry": {
    "type": "Point",
    "coordinates": [
      40.31842,
      21.07268
    ]
  }
}