{
  "type": "Feature",
  "properties": {
    "name": "Turabah",
    "country": "SA",
    "subdivision": "14",
    "timezone": "Asia/Riyadh"
  },
  "geometry": {
    "type": "Point",
    "coordinates": [
      41.6331,
      21.21406
    ]
  }
}