{
  "type": "Feature",
  "properties": {
    "name": "Boshkengash",
    "country": "TJ",
    "subdivision": "04",
    "timezone": "Asia/Dushanbe"
  },
  "geometry": {
    "type": "Point",
    "coordinates": [
      68.80533,
      38.46613
    ]
  }
}