{
  "type": "Feature",
  "properties": {
    "name": "Beechwood Village",
    "country": "US",
    "subdivision": "KY",
    "timezone": "America/Kentucky/Louisville"
  },
  "geometry": {
    "type": "Point",
    "coordinates": [
      -85.63135,
      38.25479
    ]
  }
}