{
  "type": "Feature",
  "properties": {
    "name": "Bellevue",
    "country": "US",
    "subdivision": "KY",
    "timezone": "America/New_York"
  },
  "geometry": {
    "type": "Point",
    "coordinates": [
      -84.47883,
      39.10645
    ]
  }
}