{
  "type": "Feature",
  "properties": {
    "name": "Bowling Green",
    "country": "US",
    "subdivision": "KY",
    "timezone": "America/Chicago"
  },
  "geometry": {
    "type": "Point",
    "coordinates": [
      -86.4436,
      36.99032
    ]
  }
}