{
  "type": "Feature",
  "properties": {
    "name": "Burkesville",
    "country": "US",
    "subdivision": "KY",
    "timezone": "America/Chicago"
  },
  "geometry": {
    "type": "Point",
    "coordinates": [
      -85.37052,
      36.79034
    ]
  }
}