{
  "type": "Feature",
  "properties": {
    "name": "Danville",
    "country": "US",
    "subdivision": "KY",
    "timezone": "America/New_York"
  },
  "geometry": {
    "type": "Point",
    "coordinates": [
      -84.77217,
      37.64563
    ]
  }
}