{
  "type": "Feature",
  "properties": {
    "name": "Elkfork",
    "country": "US",
    "subdivision": "KY",
    "timezone": "America/New_York"
  },
  "geometry": {
    "type": "Point",
    "coordinates": [
      -83.13295,
      37.96481
    ]
  }
}