{
  "type": "Feature",
  "properties": {
    "name": "Flatwoods",
    "country": "US",
    "subdivision": "KY",
    "timezone": "America/New_York"
  },
  "geometry": {
    "type": "Point",
    "coordinates": [
      -82.71711,
      38.52258
    ]
  }
}