{
  "type": "Feature",
  "properties": {
    "name": "Fort Campbell North",
    "country": "US",
    "subdivision": "KY",
    "timezone": "America/Chicago"
  },
  "geometry": {
    "type": "Point",
    "coordinates": [
      -87.46056,
      36.65429
    ]
  }
}