{
  "type": "Feature",
  "properties": {
    "name": "Fort Thomas",
    "country": "US",
    "subdivision": "KY",
    "timezone": "America/New_York"
  },
  "geometry": {
    "type": "Point",
    "coordinates": [
      -84.44716,
      39.07506
    ]
  }
}