{
  "type": "Feature",
  "properties": {
    "name": "Greenup",
    "country": "US",
    "subdivision": "KY",
    "timezone": "America/New_York"
  },
  "geometry": {
    "type": "Point",
    "coordinates": [
      -82.83017,
      38.57313
    ]
  }
}