{
  "type": "Feature",
  "properties": {
    "name": "Hendron",
    "country": "US",
    "subdivision": "KY",
    "timezone": "America/Chicago"
  },
  "geometry": {
    "type": "Point",
    "coordinates": [
      -88.62922,
      37.0395
    ]
  }
}