{
  "type": "Feature",
  "properties": {
    "name": "Jeffersontown",
    "country": "US",
    "subdivision": "KY",
    "timezone": "America/Kentucky/Louisville"
  },
  "geometry": {
    "type": "Point",
    "coordinates": [
      -85.5644,
      38.19424
    ]
  }
}