{
  "type": "Feature",
  "properties": {
    "name": "Lancaster",
    "country": "US",
    "subdivision": "KY",
    "timezone": "America/New_York"
  },
  "geometry": {
    "type": "Point",
    "coordinates": [
      -84.578,
      37.61952
    ]
  }
}