{
  "type": "Feature",
  "properties": {
    "name": "Lebanon",
    "country": "US",
    "subdivision": "KY",
    "timezone": "America/New_York"
  },
  "geometry": {
    "type": "Point",
    "coordinates": [
      -85.25274,
      37.56979
    ]
  }
}