{
  "type": "Feature",
  "properties": {
    "name": "Lexington-Fayette",
    "country": "US",
    "subdivision": "KY",
    "timezone": "America/New_York"
  },
  "geometry": {
    "type": "Point",
    "coordinates": [
      -84.45855,
      38.0498
    ]
  }
}