{
  "type": "Feature",
  "properties": {
    "name": "Louisa",
    "country": "US",
    "subdivision": "KY",
    "timezone": "America/New_York"
  },
  "geometry": {
    "type": "Point",
    "coordinates": [
      -82.60321,
      38.11425
    ]
  }
}