{
  "type": "Feature",
  "properties": {
    "name": "Massac",
    "country": "US",
    "subdivision": "KY",
    "timezone": "America/Chicago"
  },
  "geometry": {
    "type": "Point",
    "coordinates": [
      -88.73061,
      37.01672
    ]
  }
}