{
  "type": "Feature",
  "properties": {
    "name": "Murray",
    "country": "US",
    "subdivision": "KY",
    "timezone": "America/Chicago"
  },
  "geometry": {
    "type": "Point",
    "coordinates": [
      -88.31476,
      36.61033
    ]
  }
}