{
  "type": "Feature",
  "properties": {
    "name": "North Corbin",
    "country": "US",
    "subdivision": "KY",
    "timezone": "America/New_York"
  },
  "geometry": {
    "type": "Point",
    "coordinates": [
      -84.09326,
      36.96064
    ]
  }
}