{
  "type": "Feature",
  "properties": {
    "name": "Owingsville",
    "country": "US",
    "subdivision": "KY",
    "timezone": "America/New_York"
  },
  "geometry": {
    "type": "Point",
    "coordinates": [
      -83.76408,
      38.1448
    ]
  }
}