{
  "type": "Feature",
  "properties": {
    "name": "Reidland",
    "country": "US",
    "subdivision": "KY",
    "timezone": "America/Chicago"
  },
  "geometry": {
    "type": "Point",
    "coordinates": [
      -88.53143,
      37.01756
    ]
  }
}