{
  "type": "Feature",
  "properties": {
    "name": "Russell Springs",
    "country": "US",
    "subdivision": "KY",
    "timezone": "America/Chicago"
  },
  "geometry": {
    "type": "Point",
    "coordinates": [
      -85.08857,
      37.05618
    ]
  }
}