{
  "type": "Feature",
  "properties": {
    "name": "Saint Dennis",
    "country": "US",
    "subdivision": "KY",
    "timezone": "America/Kentucky/Louisville"
  },
  "geometry": {
    "type": "Point",
    "coordinates": [
      -85.8458,
      38.1884
    ]
  }
}