{
  "type": "Feature",
  "properties": {
    "name": "Simpsonville",
    "country": "US",
    "subdivision": "KY",
    "timezone": "America/New_York"
  },
  "geometry": {
    "type": "Point",
    "coordinates": [
      -85.35523,
      38.22257
    ]
  }
}