{
  "type": "Feature",
  "properties": {
    "name": "Tompkinsville",
    "country": "US",
    "subdivision": "KY",
    "timezone": "America/Chicago"
  },
  "geometry": {
    "type": "Point",
    "coordinates": [
      -85.69164,
      36.70228
    ]
  }
}