{
  "type": "Feature",
  "properties": {
    "name": "Walton",
    "country": "US",
    "subdivision": "KY",
    "timezone": "America/New_York"
  },
  "geometry": {
    "type": "Point",
    "coordinates": [
      -84.61022,
      38.87562
    ]
  }
}