{
  "type": "Feature",
  "properties": {
    "name": "Warsaw",
    "country": "US",
    "subdivision": "KY",
    "timezone": "America/New_York"
  },
  "geometry": {
    "type": "Point",
    "coordinates": [
      -84.90162,
      38.7834
    ]
  }
}