{
  "type": "Feature",
  "properties": {
    "name": "Pivka",
    "country": "SI",
    "subdivision": "91",
    "timezone": "Europe/Ljubljana"
  },
  "geometry": {
    "type": "Point",
    "coordinates": [
      14.19588,
      45.68292
    ]
  }
}