{
  "type": "Feature",
  "properties": {
    "name": "Tongole",
    "country": "SL",
    "subdivision": "03",
    "timezone": "Africa/Freetown"
  },
  "geometry": {
    "type": "Point",
    "coordinates": [
      -11.90071,
      7.45092
    ]
  }
}