{
  "type": "Feature",
  "properties": {
    "name": "Audubon",
    "country": "US",
    "subdivision": "IA",
    "timezone": "America/Chicago"
  },
  "geometry": {
    "type": "Point",
    "coordinates": [
      -94.93249,
      41.71804
    ]
  }
}