{
  "type": "Feature",
  "properties": {
    "name": "Avoca",
    "country": "US",
    "subdivision": "IA",
    "timezone": "America/Chicago"
  },
  "geometry": {
    "type": "Point",
    "coordinates": [
      -95.33805,
      41.47666
    ]
  }
}