{
  "type": "Feature",
  "properties": {
    "name": "Belle Plaine",
    "country": "US",
    "subdivision": "IA",
    "timezone": "America/Chicago"
  },
  "geometry": {
    "type": "Point",
    "coordinates": [
      -92.27824,
      41.89694
    ]
  }
}