{
  "type": "Feature",
  "properties": {
    "name": "Boone",
    "country": "US",
    "subdivision": "IA",
    "timezone": "America/Chicago"
  },
  "geometry": {
    "type": "Point",
    "coordinates": [
      -93.88023,
      42.0597
    ]
  }
}