{
  "type": "Feature",
  "properties": {
    "name": "Cedar Rapids",
    "country": "US",
    "subdivision": "IA",
    "timezone": "America/Chicago"
  },
  "geometry": {
    "type": "Point",
    "coordinates": [
      -91.64407,
      42.00833
    ]
  }
}