{
  "type": "Feature",
  "properties": {
    "name": "Denison",
    "country": "US",
    "subdivision": "IA",
    "timezone": "America/Chicago"
  },
  "geometry": {
    "type": "Point",
    "coordinates": [
      -95.35528,
      42.01777
    ]
  }
}