{
  "type": "Feature",
  "properties": {
    "name": "Des Moines",
    "country": "US",
    "subdivision": "IA",
    "timezone": "America/Chicago"
  },
  "geometry": {
    "type": "Point",
    "coordinates": [
      -93.60911,
      41.60054
    ]
  }
}