{
  "type": "Feature",
  "properties": {
    "name": "Estherville",
    "country": "US",
    "subdivision": "IA",
    "timezone": "America/Chicago"
  },
  "geometry": {
    "type": "Point",
    "coordinates": [
      -94.83276,
      43.40163
    ]
  }
}