{
  "type": "Feature",
  "properties": {
    "name": "Fort Madison",
    "country": "US",
    "subdivision": "IA",
    "timezone": "America/Chicago"
  },
  "geometry": {
    "type": "Point",
    "coordinates": [
      -91.31515,
      40.62976
    ]
  }
}