{
  "type": "Feature",
  "properties": {
    "name": "Hampton",
    "country": "US",
    "subdivision": "IA",
    "timezone": "America/Chicago"
  },
  "geometry": {
    "type": "Point",
    "coordinates": [
      -93.20242,
      42.74192
    ]
  }
}