{
  "type": "Feature",
  "properties": {
    "name": "Indianola",
    "country": "US",
    "subdivision": "IA",
    "timezone": "America/Chicago"
  },
  "geometry": {
    "type": "Point",
    "coordinates": [
      -93.55744,
      41.35805
    ]
  }
}