{
  "type": "Feature",
  "properties": {
    "name": "Iowa Falls",
    "country": "US",
    "subdivision": "IA",
    "timezone": "America/Chicago"
  },
  "geometry": {
    "type": "Point",
    "coordinates": [
      -93.25131,
      42.52248
    ]
  }
}