{
  "type": "Feature",
  "properties": {
    "name": "Kalona",
    "country": "US",
    "subdivision": "IA",
    "timezone": "America/Chicago"
  },
  "geometry": {
    "type": "Point",
    "coordinates": [
      -91.706,
      41.48307
    ]
  }
}