{
  "type": "Feature",
  "properties": {
    "name": "Lake Park",
    "country": "US",
    "subdivision": "IA",
    "timezone": "America/Chicago"
  },
  "geometry": {
    "type": "Point",
    "coordinates": [
      -95.32083,
      43.45552
    ]
  }
}