{
  "type": "Feature",
  "properties": {
    "name": "Mapleton",
    "country": "US",
    "subdivision": "IA",
    "timezone": "America/Chicago"
  },
  "geometry": {
    "type": "Point",
    "coordinates": [
      -95.79306,
      42.16582
    ]
  }
}