{
  "type": "Feature",
  "properties": {
    "name": "Milford",
    "country": "US",
    "subdivision": "IA",
    "timezone": "America/Chicago"
  },
  "geometry": {
    "type": "Point",
    "coordinates": [
      -95.15,
      43.32469
    ]
  }
}