{
  "type": "Feature",
  "properties": {
    "name": "Missouri Valley",
    "country": "US",
    "subdivision": "IA",
    "timezone": "America/Chicago"
  },
  "geometry": {
    "type": "Point",
    "coordinates": [
      -95.88779,
      41.55638
    ]
  }
}