{
  "type": "Feature",
  "properties": {
    "name": "New London",
    "country": "US",
    "subdivision": "IA",
    "timezone": "America/Chicago"
  },
  "geometry": {
    "type": "Point",
    "coordinates": [
      -91.3996,
      40.92698
    ]
  }
}