{
  "type": "Feature",
  "properties": {
    "name": "Northwood",
    "country": "US",
    "subdivision": "IA",
    "timezone": "America/Chicago"
  },
  "geometry": {
    "type": "Point",
    "coordinates": [
      -93.22104,
      43.44412
    ]
  }
}