{
  "type": "Feature",
  "properties": {
    "name": "Osceola",
    "country": "US",
    "subdivision": "IA",
    "timezone": "America/Chicago"
  },
  "geometry": {
    "type": "Point",
    "coordinates": [
      -93.7655,
      41.03389
    ]
  }
}