{
  "type": "Feature",
  "properties": {
    "name": "Parkersburg",
    "country": "US",
    "subdivision": "IA",
    "timezone": "America/Chicago"
  },
  "geometry": {
    "type": "Point",
    "coordinates": [
      -92.78686,
      42.57748
    ]
  }
}