{
  "type": "Feature",
  "properties": {
    "name": "Perry",
    "country": "US",
    "subdivision": "IA",
    "timezone": "America/Chicago"
  },
  "geometry": {
    "type": "Point",
    "coordinates": [
      -94.10718,
      41.8386
    ]
  }
}