{
  "type": "Feature",
  "properties": {
    "name": "Pocahontas",
    "country": "US",
    "subdivision": "IA",
    "timezone": "America/Chicago"
  },
  "geometry": {
    "type": "Point",
    "coordinates": [
      -94.66915,
      42.73553
    ]
  }
}