{
  "type": "Feature",
  "properties": {
    "name": "Polk City",
    "country": "US",
    "subdivision": "IA",
    "timezone": "America/Chicago"
  },
  "geometry": {
    "type": "Point",
    "coordinates": [
      -93.713,
      41.77138
    ]
  }
}