{
  "type": "Feature",
  "properties": {
    "name": "Red Oak",
    "country": "US",
    "subdivision": "IA",
    "timezone": "America/Chicago"
  },
  "geometry": {
    "type": "Point",
    "coordinates": [
      -95.22555,
      41.00972
    ]
  }
}