{
  "type": "Feature",
  "properties": {
    "name": "Sergeant Bluff",
    "country": "US",
    "subdivision": "IA",
    "timezone": "America/Chicago"
  },
  "geometry": {
    "type": "Point",
    "coordinates": [
      -96.35864,
      42.40388
    ]
  }
}