{
  "type": "Feature",
  "properties": {
    "name": "Sidney",
    "country": "US",
    "subdivision": "IA",
    "timezone": "America/Chicago"
  },
  "geometry": {
    "type": "Point",
    "coordinates": [
      -95.6475,
      40.74833
    ]
  }
}