{
  "type": "Feature",
  "properties": {
    "name": "Strawberry Point",
    "country": "US",
    "subdivision": "IA",
    "timezone": "America/Chicago"
  },
  "geometry": {
    "type": "Point",
    "coordinates": [
      -91.53403,
      42.6836
    ]
  }
}