{
  "type": "Feature",
  "properties": {
    "name": "Tipton",
    "country": "US",
    "subdivision": "IA",
    "timezone": "America/Chicago"
  },
  "geometry": {
    "type": "Point",
    "coordinates": [
      -91.12793,
      41.76974
    ]
  }
}