{
  "type": "Feature",
  "properties": {
    "name": "University Heights",
    "country": "US",
    "subdivision": "IA",
    "timezone": "America/Chicago"
  },
  "geometry": {
    "type": "Point",
    "coordinates": [
      -91.55684,
      41.65502
    ]
  }
}