{
  "type": "Feature",
  "properties": {
    "name": "Urbana",
    "country": "US",
    "subdivision": "IA",
    "timezone": "America/Chicago"
  },
  "geometry": {
    "type": "Point",
    "coordinates": [
      -91.87434,
      42.22416
    ]
  }
}