{
  "type": "Feature",
  "properties": {
    "name": "Waukon",
    "country": "US",
    "subdivision": "IA",
    "timezone": "America/Chicago"
  },
  "geometry": {
    "type": "Point",
    "coordinates": [
      -91.4757,
      43.26942
    ]
  }
}