{
  "type": "Feature",
  "properties": {
    "name": "West Burlington",
    "country": "US",
    "subdivision": "IA",
    "timezone": "America/Chicago"
  },
  "geometry": {
    "type": "Point",
    "coordinates": [
      -91.15654,
      40.82504
    ]
  }
}