{
  "type": "Feature",
  "properties": {
    "name": "Williamsburg",
    "country": "US",
    "subdivision": "IA",
    "timezone": "America/Chicago"
  },
  "geometry": {
    "type": "Point",
    "coordinates": [
      -92.00907,
      41.66112
    ]
  }
}