{
  "type": "Feature",
  "properties": {
    "name": "Winfield",
    "country": "US",
    "subdivision": "IA",
    "timezone": "America/Chicago"
  },
  "geometry": {
    "type": "Point",
    "coordinates": [
      -91.44127,
      41.12308
    ]
  }
}