{
  "type": "Feature",
  "properties": {
    "name": "Winterset",
    "country": "US",
    "subdivision": "IA",
    "timezone": "America/Chicago"
  },
  "geometry": {
    "type": "Point",
    "coordinates": [
      -94.01384,
      41.33082
    ]
  }
}