{
  "type": "Feature",
  "properties": {
    "name": "Senak’i",
    "country": "GE",
    "subdivision": "71",
    "timezone": "Asia/Tbilisi"
  },
  "geometry": {
    "type": "Point",
    "coordinates": [
      42.0675,
      42.27042
    ]
  }
}