{
  "type": "Feature",
  "properties": {
    "name": "Colonia San Lorenzo",
    "country": "PY",
    "subdivision": "11",
    "timezone": "America/Asuncion"
  },
  "geometry": {
    "type": "Point",
    "coordinates": [
      -54.79989,
      -26.49324
    ]
  }
}