{
  "type": "Feature",
  "properties": {
    "name": "Pirapó",
    "country": "PY",
    "subdivision": "11",
    "timezone": "America/Asuncion"
  },
  "geometry": {
    "type": "Point",
    "coordinates": [
      -55.54414,
      -26.85842
    ]
  }
}