{
  "type": "Feature",
  "properties": {
    "name": "San Pedro del Paraná",
    "country": "PY",
    "subdivision": "11",
    "timezone": "America/Asuncion"
  },
  "geometry": {
    "type": "Point",
    "coordinates": [
      -56.20694,
      -26.83387
    ]
  }
}