{
  "type": "Feature",
  "properties": {
    "name": "Nanawa",
    "country": "PY",
    "subdivision": "16",
    "timezone": "America/Asuncion"
  },
  "geometry": {
    "type": "Point",
    "coordinates": [
      -57.70307,
      -25.2793
    ]
  }
}