{
  "type": "Feature",
  "properties": {
    "name": "Bocana de Paiwas",
    "country": "NI",
    "subdivision": "18",
    "timezone": "America/Managua"
  },
  "geometry": {
    "type": "Point",
    "coordinates": [
      -85.12269,
      12.78571
    ]
  }
}