{
  "type": "Feature",
  "properties": {
    "name": "Şebin Karahisar",
    "country": "TR",
    "subdivision": "28",
    "timezone": "Europe/Istanbul"
  },
  "geometry": {
    "type": "Point",
    "coordinates": [
      38.42361,
      40.28833
    ]
  }
}