{
  "type": "Feature",
  "properties": {
    "name": "Balin",
    "country": "PL",
    "subdivision": "77",
    "timezone": "Europe/Warsaw"
  },
  "geometry": {
    "type": "Point",
    "coordinates": [
      19.3834,
      50.16799
    ]
  }
}