{
  "type": "Feature",
  "properties": {
    "name": "Barwałd Średni",
    "country": "PL",
    "subdivision": "77",
    "timezone": "Europe/Warsaw"
  },
  "geometry": {
    "type": "Point",
    "coordinates": [
      19.5936,
      49.86632
    ]
  }
}