{
  "type": "Feature",
  "properties": {
    "name": "Binarowa",
    "country": "PL",
    "subdivision": "77",
    "timezone": "Europe/Warsaw"
  },
  "geometry": {
    "type": "Point",
    "coordinates": [
      21.22816,
      49.75621
    ]
  }
}