{
  "type": "Feature",
  "properties": {
    "name": "Bolechowice",
    "country": "PL",
    "subdivision": "77",
    "timezone": "Europe/Warsaw"
  },
  "geometry": {
    "type": "Point",
    "coordinates": [
      19.79273,
      50.14831
    ]
  }
}