{
  "type": "Feature",
  "properties": {
    "name": "Brzączowice",
    "country": "PL",
    "subdivision": "77",
    "timezone": "Europe/Warsaw"
  },
  "geometry": {
    "type": "Point",
    "coordinates": [
      20.03709,
      49.87478
    ]
  }
}