{
  "type": "Feature",
  "properties": {
    "name": "Brzesko",
    "country": "PL",
    "subdivision": "77",
    "timezone": "Europe/Warsaw"
  },
  "geometry": {
    "type": "Point",
    "coordinates": [
      20.60606,
      49.96911
    ]
  }
}