{
  "type": "Feature",
  "properties": {
    "name": "Brzeźnica",
    "country": "PL",
    "subdivision": "77",
    "timezone": "Europe/Warsaw"
  },
  "geometry": {
    "type": "Point",
    "coordinates": [
      20.49139,
      49.95763
    ]
  }
}