{
  "type": "Feature",
  "properties": {
    "name": "Bystra",
    "country": "PL",
    "subdivision": "77",
    "timezone": "Europe/Warsaw"
  },
  "geometry": {
    "type": "Point",
    "coordinates": [
      21.08628,
      49.66235
    ]
  }
}