{
  "type": "Feature",
  "properties": {
    "name": "Dąbrowa Tarnowska",
    "country": "PL",
    "subdivision": "77",
    "timezone": "Europe/Warsaw"
  },
  "geometry": {
    "type": "Point",
    "coordinates": [
      20.98633,
      50.17462
    ]
  }
}