{
  "type": "Feature",
  "properties": {
    "name": "Dobra",
    "country": "PL",
    "subdivision": "77",
    "timezone": "Europe/Warsaw"
  },
  "geometry": {
    "type": "Point",
    "coordinates": [
      20.25347,
      49.71793
    ]
  }
}