{
  "type": "Feature",
  "properties": {
    "name": "Dziewin",
    "country": "PL",
    "subdivision": "77",
    "timezone": "Europe/Warsaw"
  },
  "geometry": {
    "type": "Point",
    "coordinates": [
      20.45491,
      50.07554
    ]
  }
}