{
  "type": "Feature",
  "properties": {
    "name": "Gierałtowice",
    "country": "PL",
    "subdivision": "77",
    "timezone": "Europe/Warsaw"
  },
  "geometry": {
    "type": "Point",
    "coordinates": [
      19.3907,
      49.94426
    ]
  }
}