{
  "type": "Feature",
  "properties": {
    "name": "Gruszów Wielki",
    "country": "PL",
    "subdivision": "77",
    "timezone": "Europe/Warsaw"
  },
  "geometry": {
    "type": "Point",
    "coordinates": [
      21.03144,
      50.19163
    ]
  }
}