{
  "type": "Feature",
  "properties": {
    "name": "Głogoczów",
    "country": "PL",
    "subdivision": "77",
    "timezone": "Europe/Warsaw"
  },
  "geometry": {
    "type": "Point",
    "coordinates": [
      19.8741,
      49.89452
    ]
  }
}