{
  "type": "Feature",
  "properties": {
    "name": "Kościelisko",
    "country": "PL",
    "subdivision": "77",
    "timezone": "Europe/Warsaw"
  },
  "geometry": {
    "type": "Point",
    "coordinates": [
      19.88929,
      49.29073
    ]
  }
}