{
  "type": "Feature",
  "properties": {
    "name": "Krościenko nad Dunajcem",
    "country": "PL",
    "subdivision": "77",
    "timezone": "Europe/Warsaw"
  },
  "geometry": {
    "type": "Point",
    "coordinates": [
      20.42624,
      49.44081
    ]
  }
}