{
  "type": "Feature",
  "properties": {
    "name": "Kwaczała",
    "country": "PL",
    "subdivision": "77",
    "timezone": "Europe/Warsaw"
  },
  "geometry": {
    "type": "Point",
    "coordinates": [
      19.49215,
      50.06408
    ]
  }
}