{
  "type": "Feature",
  "properties": {
    "name": "Libertów",
    "country": "PL",
    "subdivision": "77",
    "timezone": "Europe/Warsaw"
  },
  "geometry": {
    "type": "Point",
    "coordinates": [
      19.89461,
      49.97242
    ]
  }
}