{
  "type": "Feature",
  "properties": {
    "name": "Lubień",
    "country": "PL",
    "subdivision": "77",
    "timezone": "Europe/Warsaw"
  },
  "geometry": {
    "type": "Point",
    "coordinates": [
      19.97847,
      49.71921
    ]
  }
}