{
  "type": "Feature",
  "properties": {
    "name": "Nawojowa",
    "country": "PL",
    "subdivision": "77",
    "timezone": "Europe/Warsaw"
  },
  "geometry": {
    "type": "Point",
    "coordinates": [
      20.73927,
      49.56686
    ]
  }
}