{
  "type": "Feature",
  "properties": {
    "name": "Niepołomice",
    "country": "PL",
    "subdivision": "77",
    "timezone": "Europe/Warsaw"
  },
  "geometry": {
    "type": "Point",
    "coordinates": [
      20.22257,
      50.04066
    ]
  }
}