{
  "type": "Feature",
  "properties": {
    "name": "Nowe Brzesko",
    "country": "PL",
    "subdivision": "77",
    "timezone": "Europe/Warsaw"
  },
  "geometry": {
    "type": "Point",
    "coordinates": [
      20.37663,
      50.13222
    ]
  }
}