{
  "type": "Feature",
  "properties": {
    "name": "Ochotnica Dolna",
    "country": "PL",
    "subdivision": "77",
    "timezone": "Europe/Warsaw"
  },
  "geometry": {
    "type": "Point",
    "coordinates": [
      20.34265,
      49.52682
    ]
  }
}