{
  "type": "Feature",
  "properties": {
    "name": "Ochojno",
    "country": "PL",
    "subdivision": "77",
    "timezone": "Europe/Warsaw"
  },
  "geometry": {
    "type": "Point",
    "coordinates": [
      19.97452,
      49.95255
    ]
  }
}