{
  "type": "Feature",
  "properties": {
    "name": "Ostrężnica",
    "country": "PL",
    "subdivision": "77",
    "timezone": "Europe/Warsaw"
  },
  "geometry": {
    "type": "Point",
    "coordinates": [
      19.57077,
      50.19262
    ]
  }
}