{
  "type": "Feature",
  "properties": {
    "name": "Piekielnik",
    "country": "PL",
    "subdivision": "77",
    "timezone": "Europe/Warsaw"
  },
  "geometry": {
    "type": "Point",
    "coordinates": [
      19.7681,
      49.47688
    ]
  }
}