{
  "type": "Feature",
  "properties": {
    "name": "Poręba Spytkowska",
    "country": "PL",
    "subdivision": "77",
    "timezone": "Europe/Warsaw"
  },
  "geometry": {
    "type": "Point",
    "coordinates": [
      20.55405,
      49.93995
    ]
  }
}