{
  "type": "Feature",
  "properties": {
    "name": "Proszowice",
    "country": "PL",
    "subdivision": "77",
    "timezone": "Europe/Warsaw"
  },
  "geometry": {
    "type": "Point",
    "coordinates": [
      20.28909,
      50.19275
    ]
  }
}