{
  "type": "Feature",
  "properties": {
    "name": "Rabka-Zdrój",
    "country": "PL",
    "subdivision": "77",
    "timezone": "Europe/Warsaw"
  },
  "geometry": {
    "type": "Point",
    "coordinates": [
      19.96654,
      49.60889
    ]
  }
}