{
  "type": "Feature",
  "properties": {
    "name": "Racławice",
    "country": "PL",
    "subdivision": "77",
    "timezone": "Europe/Warsaw"
  },
  "geometry": {
    "type": "Point",
    "coordinates": [
      19.67686,
      50.19344
    ]
  }
}