{
  "type": "Feature",
  "properties": {
    "name": "Radgoszcz",
    "country": "PL",
    "subdivision": "77",
    "timezone": "Europe/Warsaw"
  },
  "geometry": {
    "type": "Point",
    "coordinates": [
      21.11315,
      50.2058
    ]
  }
}