{
  "type": "Feature",
  "properties": {
    "name": "Sieradza",
    "country": "PL",
    "subdivision": "77",
    "timezone": "Europe/Warsaw"
  },
  "geometry": {
    "type": "Point",
    "coordinates": [
      20.92947,
      50.13499
    ]
  }
}