{
  "type": "Feature",
  "properties": {
    "name": "Skawica",
    "country": "PL",
    "subdivision": "77",
    "timezone": "Europe/Warsaw"
  },
  "geometry": {
    "type": "Point",
    "coordinates": [
      19.62321,
      49.67718
    ]
  }
}