{
  "type": "Feature",
  "properties": {
    "name": "Wawrzeńczyce",
    "country": "PL",
    "subdivision": "77",
    "timezone": "Europe/Warsaw"
  },
  "geometry": {
    "type": "Point",
    "coordinates": [
      20.31612,
      50.11012
    ]
  }
}