{
  "type": "Feature",
  "properties": {
    "name": "Wola Batorska",
    "country": "PL",
    "subdivision": "77",
    "timezone": "Europe/Warsaw"
  },
  "geometry": {
    "type": "Point",
    "coordinates": [
      20.26617,
      50.05262
    ]
  }
}