{
  "type": "Feature",
  "properties": {
    "name": "Wolbrom",
    "country": "PL",
    "subdivision": "77",
    "timezone": "Europe/Warsaw"
  },
  "geometry": {
    "type": "Point",
    "coordinates": [
      19.75831,
      50.37957
    ]
  }
}