{
  "type": "Feature",
  "properties": {
    "name": "Wołowice",
    "country": "PL",
    "subdivision": "77",
    "timezone": "Europe/Warsaw"
  },
  "geometry": {
    "type": "Point",
    "coordinates": [
      19.7263,
      49.98876
    ]
  }
}