{
  "type": "Feature",
  "properties": {
    "name": "Wysoka",
    "country": "PL",
    "subdivision": "77",
    "timezone": "Europe/Warsaw"
  },
  "geometry": {
    "type": "Point",
    "coordinates": [
      19.60356,
      49.90713
    ]
  }
}