{
  "type": "Feature",
  "properties": {
    "name": "Złota",
    "country": "PL",
    "subdivision": "77",
    "timezone": "Europe/Warsaw"
  },
  "geometry": {
    "type": "Point",
    "coordinates": [
      20.69326,
      49.88059
    ]
  }
}