{
  "type": "Feature",
  "properties": {
    "name": "Palmerston North",
    "country": "NZ",
    "subdivision": "F3",
    "timezone": "Pacific/Auckland"
  },
  "geometry": {
    "type": "Point",
    "coordinates": [
      175.61113,
      -40.35636
    ]
  }
}