{
  "type": "Feature",
  "properties": {
    "name": "Baryshevo",
    "country": "RU",
    "subdivision": "53",
    "timezone": "Asia/Novosibirsk"
  },
  "geometry": {
    "type": "Point",
    "coordinates": [
      83.1822,
      54.9564
    ]
  }
}