{
  "type": "Feature",
  "properties": {
    "name": "Kargat",
    "country": "RU",
    "subdivision": "53",
    "timezone": "Asia/Novosibirsk"
  },
  "geometry": {
    "type": "Point",
    "coordinates": [
      80.28111,
      55.19556
    ]
  }
}