{
  "type": "Feature",
  "properties": {
    "name": "Polovinnoye",
    "country": "RU",
    "subdivision": "53",
    "timezone": "Asia/Novosibirsk"
  },
  "geometry": {
    "type": "Point",
    "coordinates": [
      79.24327,
      53.75671
    ]
  }
}