{
  "type": "Feature",
  "properties": {
    "name": "Sadovyy",
    "country": "RU",
    "subdivision": "53",
    "timezone": "Asia/Novosibirsk"
  },
  "geometry": {
    "type": "Point",
    "coordinates": [
      82.9659,
      55.1361
    ]
  }
}