{
  "type": "Feature",
  "properties": {
    "name": "Stantsionno-Oyashinskiy",
    "country": "RU",
    "subdivision": "53",
    "timezone": "Asia/Novosibirsk"
  },
  "geometry": {
    "type": "Point",
    "coordinates": [
      83.8245,
      55.4664
    ]
  }
}