{
  "type": "Feature",
  "properties": {
    "name": "Suzun",
    "country": "RU",
    "subdivision": "53",
    "timezone": "Asia/Novosibirsk"
  },
  "geometry": {
    "type": "Point",
    "coordinates": [
      82.3116,
      53.7841
    ]
  }
}