{
  "type": "Feature",
  "properties": {
    "name": "Toguchin",
    "country": "RU",
    "subdivision": "53",
    "timezone": "Asia/Novosibirsk"
  },
  "geometry": {
    "type": "Point",
    "coordinates": [
      84.38583,
      55.23528
    ]
  }
}