{
  "type": "Feature",
  "properties": {
    "name": "Ganshui",
    "country": "CN",
    "subdivision": "33",
    "timezone": "Asia/Shanghai"
  },
  "geometry": {
    "type": "Point",
    "coordinates": [
      106.71111,
      28.74222
    ]
  }
}