{
  "type": "Feature",
  "properties": {
    "name": "Halmstad",
    "country": "SE",
    "subdivision": "06",
    "timezone": "Europe/Stockholm"
  },
  "geometry": {
    "type": "Point",
    "coordinates": [
      12.85676,
      56.67446
    ]
  }
}