{
  "type": "Feature",
  "properties": {
    "name": "Haverdal",
    "country": "SE",
    "subdivision": "06",
    "timezone": "Europe/Stockholm"
  },
  "geometry": {
    "type": "Point",
    "coordinates": [
      12.67194,
      56.72222
    ]
  }
}