{
  "type": "Feature",
  "properties": {
    "name": "Mellbystrand",
    "country": "SE",
    "subdivision": "06",
    "timezone": "Europe/Stockholm"
  },
  "geometry": {
    "type": "Point",
    "coordinates": [
      12.93958,
      56.48561
    ]
  }
}