{
  "type": "Feature",
  "properties": {
    "name": "Mjällby",
    "country": "SE",
    "subdivision": "06",
    "timezone": "Europe/Stockholm"
  },
  "geometry": {
    "type": "Point",
    "coordinates": [
      12.76667,
      56.68333
    ]
  }
}