{
  "type": "Feature",
  "properties": {
    "name": "Veddige",
    "country": "SE",
    "subdivision": "06",
    "timezone": "Europe/Stockholm"
  },
  "geometry": {
    "type": "Point",
    "coordinates": [
      12.3322,
      57.26591
    ]
  }
}