{
  "type": "Feature",
  "properties": {
    "name": "Papetoai",
    "country": "PF",
    "subdivision": "01",
    "timezone": "Pacific/Tahiti"
  },
  "geometry": {
    "type": "Point",
    "coordinates": [
      -149.87437,
      -17.49538
    ]
  }
}