{
  "type": "Feature",
  "properties": {
    "name": "Teahupoo",
    "country": "PF",
    "subdivision": "01",
    "timezone": "Pacific/Tahiti"
  },
  "geometry": {
    "type": "Point",
    "coordinates": [
      -149.26682,
      -17.84645
    ]
  }
}