{
  "type": "Feature",
  "properties": {
    "name": "Angeghakot’",
    "country": "AM",
    "subdivision": "08",
    "timezone": "Asia/Yerevan"
  },
  "geometry": {
    "type": "Point",
    "coordinates": [
      45.94452,
      39.56952
    ]
  }
}