{
  "type": "Feature",
  "properties": {
    "name": "Peshkopi",
    "country": "AL",
    "subdivision": "41",
    "timezone": "Europe/Tirane"
  },
  "geometry": {
    "type": "Point",
    "coordinates": [
      20.42889,
      41.685
    ]
  }
}