{
  "type": "Feature",
  "properties": {
    "name": "Al Karāmah",
    "country": "JO",
    "subdivision": "02",
    "timezone": "Asia/Amman"
  },
  "geometry": {
    "type": "Point",
    "coordinates": [
      35.58033,
      31.95439
    ]
  }
}