{
  "type": "Feature",
  "properties": {
    "name": "Bogorodskoye",
    "country": "RU",
    "subdivision": "21",
    "timezone": "Europe/Moscow"
  },
  "geometry": {
    "type": "Point",
    "coordinates": [
      41.01354,
      57.04695
    ]
  }
}