{
  "type": "Feature",
  "properties": {
    "name": "Komsomol’sk",
    "country": "RU",
    "subdivision": "21",
    "timezone": "Europe/Moscow"
  },
  "geometry": {
    "type": "Point",
    "coordinates": [
      40.37266,
      57.02913
    ]
  }
}