{
  "type": "Feature",
  "properties": {
    "name": "Puchezh",
    "country": "RU",
    "subdivision": "21",
    "timezone": "Europe/Moscow"
  },
  "geometry": {
    "type": "Point",
    "coordinates": [
      43.16761,
      56.97878
    ]
  }
}