{
  "type": "Feature",
  "properties": {
    "name": "Ḩadīthah",
    "country": "IQ",
    "subdivision": "01",
    "timezone": "Asia/Baghdad"
  },
  "geometry": {
    "type": "Point",
    "coordinates": [
      42.37727,
      34.13661
    ]
  }
}