{
  "type": "Feature",
  "properties": {
    "name": "Ramadi",
    "country": "IQ",
    "subdivision": "01",
    "timezone": "Asia/Baghdad"
  },
  "geometry": {
    "type": "Point",
    "coordinates": [
      43.30778,
      33.42056
    ]
  }
}