{
  "type": "Feature",
  "properties": {
    "name": "RÄwah",
    "country": "IQ",
    "subdivision": "01",
    "timezone": "Asia/Baghdad"
  },
  "geometry": {
    "type": "Point",
    "coordinates": [
      41.91898,
      34.48229
    ]
  }
}