{
  "type": "Feature",
  "properties": {
    "name": "Kūh Sefīd",
    "country": "IR",
    "subdivision": "29",
    "timezone": "Asia/Tehran"
  },
  "geometry": {
    "type": "Point",
    "coordinates": [
      56.8014,
      29.2762
    ]
  }
}