{
  "type": "Feature",
  "properties": {
    "name": "Shahrak-e Pābedānā",
    "country": "IR",
    "subdivision": "29",
    "timezone": "Asia/Tehran"
  },
  "geometry": {
    "type": "Point",
    "coordinates": [
      56.39806,
      31.13444
    ]
  }
}