{
  "type": "Feature",
  "properties": {
    "name": "Alzingen",
    "country": "LU",
    "subdivision": "LU",
    "timezone": "Europe/Luxembourg"
  },
  "geometry": {
    "type": "Point",
    "coordinates": [
      6.16361,
      49.565
    ]
  }
}