{
  "type": "Feature",
  "properties": {
    "name": "Luxembourg",
    "country": "LU",
    "subdivision": "LU",
    "timezone": "Europe/Luxembourg"
  },
  "geometry": {
    "type": "Point",
    "coordinates": [
      6.13,
      49.61167
    ]
  }
}