{
  "type": "Feature",
  "properties": {
    "name": "Belozërskoye",
    "country": "RU",
    "subdivision": "40",
    "timezone": "Asia/Yekaterinburg"
  },
  "geometry": {
    "type": "Point",
    "coordinates": [
      65.58417,
      55.82139
    ]
  }
}