{
  "type": "Feature",
  "properties": {
    "name": "Ketovo",
    "country": "RU",
    "subdivision": "40",
    "timezone": "Asia/Yekaterinburg"
  },
  "geometry": {
    "type": "Point",
    "coordinates": [
      65.32583,
      55.355
    ]
  }
}