{
  "type": "Feature",
  "properties": {
    "name": "Safakulevo",
    "country": "RU",
    "subdivision": "40",
    "timezone": "Asia/Yekaterinburg"
  },
  "geometry": {
    "type": "Point",
    "coordinates": [
      62.5442,
      54.9901
    ]
  }
}