{
  "type": "Feature",
  "properties": {
    "name": "Sovetabad",
    "country": "AZ",
    "subdivision": "36",
    "timezone": "Asia/Baku"
  },
  "geometry": {
    "type": "Point",
    "coordinates": [
      49.21414,
      39.33667
    ]
  }
}