{
  "type": "Feature",
  "properties": {
    "name": "Orhei",
    "country": "MD",
    "subdivision": "82",
    "timezone": "Europe/Chisinau"
  },
  "geometry": {
    "type": "Point",
    "coordinates": [
      28.82446,
      47.38494
    ]
  }
}