{
  "type": "Feature",
  "properties": {
    "name": "Arriba",
    "country": "ES",
    "subdivision": "34",
    "timezone": "Europe/Madrid"
  },
  "geometry": {
    "type": "Point",
    "coordinates": [
      -5.53511,
      43.51615
    ]
  }
}