{
  "type": "Feature",
  "properties": {
    "name": "Bárzana",
    "country": "ES",
    "subdivision": "34",
    "timezone": "Europe/Madrid"
  },
  "geometry": {
    "type": "Point",
    "coordinates": [
      -5.97345,
      43.15742
    ]
  }
}