{
  "type": "Feature",
  "properties": {
    "name": "Campo de Caso",
    "country": "ES",
    "subdivision": "34",
    "timezone": "Europe/Madrid"
  },
  "geometry": {
    "type": "Point",
    "coordinates": [
      -5.34476,
      43.1831
    ]
  }
}