{
  "type": "Feature",
  "properties": {
    "name": "Noreña",
    "country": "ES",
    "subdivision": "34",
    "timezone": "Europe/Madrid"
  },
  "geometry": {
    "type": "Point",
    "coordinates": [
      -5.70662,
      43.39364
    ]
  }
}