{
  "type": "Feature",
  "properties": {
    "name": "San Juan de la Arena",
    "country": "ES",
    "subdivision": "34",
    "timezone": "Europe/Madrid"
  },
  "geometry": {
    "type": "Point",
    "coordinates": [
      -6.07432,
      43.559
    ]
  }
}