{
  "type": "Feature",
  "properties": {
    "name": "Alessano",
    "country": "IT",
    "subdivision": "13",
    "timezone": "Europe/Rome"
  },
  "geometry": {
    "type": "Point",
    "coordinates": [
      18.33221,
      39.89381
    ]
  }
}