{
  "type": "Feature",
  "properties": {
    "name": "Altamura",
    "country": "IT",
    "subdivision": "13",
    "timezone": "Europe/Rome"
  },
  "geometry": {
    "type": "Point",
    "coordinates": [
      16.54952,
      40.82664
    ]
  }
}