{
  "type": "Feature",
  "properties": {
    "name": "Anzano di Puglia",
    "country": "IT",
    "subdivision": "13",
    "timezone": "Europe/Rome"
  },
  "geometry": {
    "type": "Point",
    "coordinates": [
      15.28688,
      41.12162
    ]
  }
}