{
  "type": "Feature",
  "properties": {
    "name": "Bari",
    "country": "IT",
    "subdivision": "13",
    "timezone": "Europe/Rome"
  },
  "geometry": {
    "type": "Point",
    "coordinates": [
      16.86982,
      41.12066
    ]
  }
}