{
  "type": "Feature",
  "properties": {
    "name": "Brindisi",
    "country": "IT",
    "subdivision": "13",
    "timezone": "Europe/Rome"
  },
  "geometry": {
    "type": "Point",
    "coordinates": [
      17.93607,
      40.63215
    ]
  }
}