{
  "type": "Feature",
  "properties": {
    "name": "Capirro",
    "country": "IT",
    "subdivision": "13",
    "timezone": "Europe/Rome"
  },
  "geometry": {
    "type": "Point",
    "coordinates": [
      16.42242,
      41.25403
    ]
  }
}