{
  "type": "Feature",
  "properties": {
    "name": "Castellaneta",
    "country": "IT",
    "subdivision": "13",
    "timezone": "Europe/Rome"
  },
  "geometry": {
    "type": "Point",
    "coordinates": [
      16.9329,
      40.62794
    ]
  }
}