{
  "type": "Feature",
  "properties": {
    "name": "Cerignola",
    "country": "IT",
    "subdivision": "13",
    "timezone": "Europe/Rome"
  },
  "geometry": {
    "type": "Point",
    "coordinates": [
      15.89559,
      41.26523
    ]
  }
}