{
  "type": "Feature",
  "properties": {
    "name": "Chieuti",
    "country": "IT",
    "subdivision": "13",
    "timezone": "Europe/Rome"
  },
  "geometry": {
    "type": "Point",
    "coordinates": [
      15.16681,
      41.84486
    ]
  }
}