{
  "type": "Feature",
  "properties": {
    "name": "Collemeto",
    "country": "IT",
    "subdivision": "13",
    "timezone": "Europe/Rome"
  },
  "geometry": {
    "type": "Point",
    "coordinates": [
      18.10285,
      40.20885
    ]
  }
}