{
  "type": "Feature",
  "properties": {
    "name": "Deliceto",
    "country": "IT",
    "subdivision": "13",
    "timezone": "Europe/Rome"
  },
  "geometry": {
    "type": "Point",
    "coordinates": [
      15.38447,
      41.22289
    ]
  }
}