{
  "type": "Feature",
  "properties": {
    "name": "Diso",
    "country": "IT",
    "subdivision": "13",
    "timezone": "Europe/Rome"
  },
  "geometry": {
    "type": "Point",
    "coordinates": [
      18.39144,
      40.00915
    ]
  }
}