{
  "type": "Feature",
  "properties": {
    "name": "Gallipoli",
    "country": "IT",
    "subdivision": "13",
    "timezone": "Europe/Rome"
  },
  "geometry": {
    "type": "Point",
    "coordinates": [
      17.99088,
      40.05594
    ]
  }
}