{
  "type": "Feature",
  "properties": {
    "name": "Ginosa",
    "country": "IT",
    "subdivision": "13",
    "timezone": "Europe/Rome"
  },
  "geometry": {
    "type": "Point",
    "coordinates": [
      16.75655,
      40.5769
    ]
  }
}