{
  "type": "Feature",
  "properties": {
    "name": "Latiano",
    "country": "IT",
    "subdivision": "13",
    "timezone": "Europe/Rome"
  },
  "geometry": {
    "type": "Point",
    "coordinates": [
      17.71856,
      40.55052
    ]
  }
}