{
  "type": "Feature",
  "properties": {
    "name": "Lesina",
    "country": "IT",
    "subdivision": "13",
    "timezone": "Europe/Rome"
  },
  "geometry": {
    "type": "Point",
    "coordinates": [
      15.35322,
      41.86125
    ]
  }
}