{
  "type": "Feature",
  "properties": {
    "name": "Leverano",
    "country": "IT",
    "subdivision": "13",
    "timezone": "Europe/Rome"
  },
  "geometry": {
    "type": "Point",
    "coordinates": [
      17.9965,
      40.28852
    ]
  }
}