{
  "type": "Feature",
  "properties": {
    "name": "Manfredonia",
    "country": "IT",
    "subdivision": "13",
    "timezone": "Europe/Rome"
  },
  "geometry": {
    "type": "Point",
    "coordinates": [
      15.91876,
      41.63065
    ]
  }
}