{
  "type": "Feature",
  "properties": {
    "name": "Melissano",
    "country": "IT",
    "subdivision": "13",
    "timezone": "Europe/Rome"
  },
  "geometry": {
    "type": "Point",
    "coordinates": [
      18.12113,
      39.97315
    ]
  }
}