{
  "type": "Feature",
  "properties": {
    "name": "Montemesola",
    "country": "IT",
    "subdivision": "13",
    "timezone": "Europe/Rome"
  },
  "geometry": {
    "type": "Point",
    "coordinates": [
      17.33665,
      40.5676
    ]
  }
}