{
  "type": "Feature",
  "properties": {
    "name": "Muro Leccese",
    "country": "IT",
    "subdivision": "13",
    "timezone": "Europe/Rome"
  },
  "geometry": {
    "type": "Point",
    "coordinates": [
      18.33674,
      40.10286
    ]
  }
}