{
  "type": "Feature",
  "properties": {
    "name": "Orta Nova",
    "country": "IT",
    "subdivision": "13",
    "timezone": "Europe/Rome"
  },
  "geometry": {
    "type": "Point",
    "coordinates": [
      15.70994,
      41.32879
    ]
  }
}