{
  "type": "Feature",
  "properties": {
    "name": "Otranto",
    "country": "IT",
    "subdivision": "13",
    "timezone": "Europe/Rome"
  },
  "geometry": {
    "type": "Point",
    "coordinates": [
      18.48682,
      40.14789
    ]
  }
}