{
  "type": "Feature",
  "properties": {
    "name": "Palagianello",
    "country": "IT",
    "subdivision": "13",
    "timezone": "Europe/Rome"
  },
  "geometry": {
    "type": "Point",
    "coordinates": [
      16.97802,
      40.60851
    ]
  }
}