{
  "type": "Feature",
  "properties": {
    "name": "Poggiorsini",
    "country": "IT",
    "subdivision": "13",
    "timezone": "Europe/Rome"
  },
  "geometry": {
    "type": "Point",
    "coordinates": [
      16.25605,
      40.91403
    ]
  }
}