{
  "type": "Feature",
  "properties": {
    "name": "Polignano a Mare",
    "country": "IT",
    "subdivision": "13",
    "timezone": "Europe/Rome"
  },
  "geometry": {
    "type": "Point",
    "coordinates": [
      17.22149,
      40.99221
    ]
  }
}