{
  "type": "Feature",
  "properties": {
    "name": "Presicce",
    "country": "IT",
    "subdivision": "13",
    "timezone": "Europe/Rome"
  },
  "geometry": {
    "type": "Point",
    "coordinates": [
      18.26282,
      39.90055
    ]
  }
}