{
  "type": "Feature",
  "properties": {
    "name": "Rignano Garganico",
    "country": "IT",
    "subdivision": "13",
    "timezone": "Europe/Rome"
  },
  "geometry": {
    "type": "Point",
    "coordinates": [
      15.58835,
      41.67934
    ]
  }
}