{
  "type": "Feature",
  "properties": {
    "name": "San Marzano di San Giuseppe",
    "country": "IT",
    "subdivision": "13",
    "timezone": "Europe/Rome"
  },
  "geometry": {
    "type": "Point",
    "coordinates": [
      17.50351,
      40.45455
    ]
  }
}