{
  "type": "Feature",
  "properties": {
    "name": "San Severo",
    "country": "IT",
    "subdivision": "13",
    "timezone": "Europe/Rome"
  },
  "geometry": {
    "type": "Point",
    "coordinates": [
      15.38148,
      41.68564
    ]
  }
}