{
  "type": "Feature",
  "properties": {
    "name": "San Cassiano",
    "country": "IT",
    "subdivision": "13",
    "timezone": "Europe/Rome"
  },
  "geometry": {
    "type": "Point",
    "coordinates": [
      18.33392,
      40.05631
    ]
  }
}