{
  "type": "Feature",
  "properties": {
    "name": "Santeramo in Colle",
    "country": "IT",
    "subdivision": "13",
    "timezone": "Europe/Rome"
  },
  "geometry": {
    "type": "Point",
    "coordinates": [
      16.75873,
      40.79236
    ]
  }
}