{
  "type": "Feature",
  "properties": {
    "name": "Serrano",
    "country": "IT",
    "subdivision": "13",
    "timezone": "Europe/Rome"
  },
  "geometry": {
    "type": "Point",
    "coordinates": [
      18.35156,
      40.18438
    ]
  }
}