{
  "type": "Feature",
  "properties": {
    "name": "Sternatia",
    "country": "IT",
    "subdivision": "13",
    "timezone": "Europe/Rome"
  },
  "geometry": {
    "type": "Point",
    "coordinates": [
      18.22748,
      40.22022
    ]
  }
}