{
  "type": "Feature",
  "properties": {
    "name": "Strudà",
    "country": "IT",
    "subdivision": "13",
    "timezone": "Europe/Rome"
  },
  "geometry": {
    "type": "Point",
    "coordinates": [
      18.28176,
      40.31991
    ]
  }
}