{
  "type": "Feature",
  "properties": {
    "name": "Taranto",
    "country": "IT",
    "subdivision": "13",
    "timezone": "Europe/Rome"
  },
  "geometry": {
    "type": "Point",
    "coordinates": [
      17.24707,
      40.46438
    ]
  }
}