{
  "type": "Feature",
  "properties": {
    "name": "Trani",
    "country": "IT",
    "subdivision": "13",
    "timezone": "Europe/Rome"
  },
  "geometry": {
    "type": "Point",
    "coordinates": [
      16.41011,
      41.27733
    ]
  }
}