{
  "type": "Feature",
  "properties": {
    "name": "Vieste",
    "country": "IT",
    "subdivision": "13",
    "timezone": "Europe/Rome"
  },
  "geometry": {
    "type": "Point",
    "coordinates": [
      16.17139,
      41.88209
    ]
  }
}