{
  "type": "Feature",
  "properties": {
    "name": "Vignacastrisi",
    "country": "IT",
    "subdivision": "13",
    "timezone": "Europe/Rome"
  },
  "geometry": {
    "type": "Point",
    "coordinates": [
      18.40704,
      40.01604
    ]
  }
}