{
  "type": "Feature",
  "properties": {
    "name": "Argel",
    "country": "RO",
    "subdivision": "34",
    "timezone": "Europe/Bucharest"
  },
  "geometry": {
    "type": "Point",
    "coordinates": [
      25.47049,
      47.76136
    ]
  }
}