{
  "type": "Feature",
  "properties": {
    "name": "Arghira",
    "country": "RO",
    "subdivision": "34",
    "timezone": "Europe/Bucharest"
  },
  "geometry": {
    "type": "Point",
    "coordinates": [
      26.4725,
      47.45412
    ]
  }
}