{
  "type": "Feature",
  "properties": {
    "name": "Bănești",
    "country": "RO",
    "subdivision": "34",
    "timezone": "Europe/Bucharest"
  },
  "geometry": {
    "type": "Point",
    "coordinates": [
      26.52335,
      47.58946
    ]
  }
}