{
  "type": "Feature",
  "properties": {
    "name": "Botoşana",
    "country": "RO",
    "subdivision": "34",
    "timezone": "Europe/Bucharest"
  },
  "geometry": {
    "type": "Point",
    "coordinates": [
      25.95,
      47.68333
    ]
  }
}