{
  "type": "Feature",
  "properties": {
    "name": "Broșteni",
    "country": "RO",
    "subdivision": "34",
    "timezone": "Europe/Bucharest"
  },
  "geometry": {
    "type": "Point",
    "coordinates": [
      26.55625,
      47.30459
    ]
  }
}