{
  "type": "Feature",
  "properties": {
    "name": "Capu Codrului",
    "country": "RO",
    "subdivision": "34",
    "timezone": "Europe/Bucharest"
  },
  "geometry": {
    "type": "Point",
    "coordinates": [
      25.98724,
      47.53117
    ]
  }
}