{
  "type": "Feature",
  "properties": {
    "name": "Colacu",
    "country": "RO",
    "subdivision": "34",
    "timezone": "Europe/Bucharest"
  },
  "geometry": {
    "type": "Point",
    "coordinates": [
      25.37211,
      47.5383
    ]
  }
}