{
  "type": "Feature",
  "properties": {
    "name": "Cornu Luncii",
    "country": "RO",
    "subdivision": "34",
    "timezone": "Europe/Bucharest"
  },
  "geometry": {
    "type": "Point",
    "coordinates": [
      26.15,
      47.46667
    ]
  }
}