{
  "type": "Feature",
  "properties": {
    "name": "Dorna-Arini",
    "country": "RO",
    "subdivision": "34",
    "timezone": "Europe/Bucharest"
  },
  "geometry": {
    "type": "Point",
    "coordinates": [
      25.4074,
      47.33832
    ]
  }
}