{
  "type": "Feature",
  "properties": {
    "name": "Hurjuieni",
    "country": "RO",
    "subdivision": "34",
    "timezone": "Europe/Bucharest"
  },
  "geometry": {
    "type": "Point",
    "coordinates": [
      25.81667,
      47.91667
    ]
  }
}