{
  "type": "Feature",
  "properties": {
    "name": "Măriței",
    "country": "RO",
    "subdivision": "34",
    "timezone": "Europe/Bucharest"
  },
  "geometry": {
    "type": "Point",
    "coordinates": [
      26.14626,
      47.7527
    ]
  }
}