{
  "type": "Feature",
  "properties": {
    "name": "Soloneț",
    "country": "RO",
    "subdivision": "34",
    "timezone": "Europe/Bucharest"
  },
  "geometry": {
    "type": "Point",
    "coordinates": [
      26.03222,
      47.68682
    ]
  }
}