{
  "type": "Feature",
  "properties": {
    "name": "Suceava",
    "country": "RO",
    "subdivision": "34",
    "timezone": "Europe/Bucharest"
  },
  "geometry": {
    "type": "Point",
    "coordinates": [
      26.25,
      47.63333
    ]
  }
}