{
  "type": "Feature",
  "properties": {
    "name": "Țibeni",
    "country": "RO",
    "subdivision": "34",
    "timezone": "Europe/Bucharest"
  },
  "geometry": {
    "type": "Point",
    "coordinates": [
      26.02438,
      47.81618
    ]
  }
}