{
  "type": "Feature",
  "properties": {
    "name": "Vama",
    "country": "RO",
    "subdivision": "34",
    "timezone": "Europe/Bucharest"
  },
  "geometry": {
    "type": "Point",
    "coordinates": [
      25.68333,
      47.56667
    ]
  }
}