{
  "type": "Feature",
  "properties": {
    "name": "Vatra Dornei",
    "country": "RO",
    "subdivision": "34",
    "timezone": "Europe/Bucharest"
  },
  "geometry": {
    "type": "Point",
    "coordinates": [
      25.36667,
      47.35
    ]
  }
}