{
  "type": "Feature",
  "properties": {
    "name": "Chayan",
    "country": "KZ",
    "subdivision": "10",
    "timezone": "Asia/Almaty"
  },
  "geometry": {
    "type": "Point",
    "coordinates": [
      69.38048,
      43.03399
    ]
  }
}