{
  "type": "Feature",
  "properties": {
    "name": "Istok",
    "country": "RU",
    "subdivision": "71",
    "timezone": "Asia/Yekaterinburg"
  },
  "geometry": {
    "type": "Point",
    "coordinates": [
      60.77889,
      56.79086
    ]
  }
}