{
  "type": "Feature",
  "properties": {
    "name": "Kushva",
    "country": "RU",
    "subdivision": "71",
    "timezone": "Asia/Yekaterinburg"
  },
  "geometry": {
    "type": "Point",
    "coordinates": [
      59.75917,
      58.29056
    ]
  }
}