{
  "type": "Feature",
  "properties": {
    "name": "Kuzino",
    "country": "RU",
    "subdivision": "71",
    "timezone": "Asia/Yekaterinburg"
  },
  "geometry": {
    "type": "Point",
    "coordinates": [
      59.4412,
      57.0224
    ]
  }
}