{
  "type": "Feature",
  "properties": {
    "name": "Levikha",
    "country": "RU",
    "subdivision": "71",
    "timezone": "Asia/Yekaterinburg"
  },
  "geometry": {
    "type": "Point",
    "coordinates": [
      59.90028,
      57.58361
    ]
  }
}