{
  "type": "Feature",
  "properties": {
    "name": "Malysheva",
    "country": "RU",
    "subdivision": "71",
    "timezone": "Asia/Yekaterinburg"
  },
  "geometry": {
    "type": "Point",
    "coordinates": [
      61.40345,
      57.11851
    ]
  }
}