{
  "type": "Feature",
  "properties": {
    "name": "Novoasbest",
    "country": "RU",
    "subdivision": "71",
    "timezone": "Asia/Yekaterinburg"
  },
  "geometry": {
    "type": "Point",
    "coordinates": [
      60.28773,
      57.74225
    ]
  }
}