{
  "type": "Feature",
  "properties": {
    "name": "Talitsa",
    "country": "RU",
    "subdivision": "71",
    "timezone": "Asia/Yekaterinburg"
  },
  "geometry": {
    "type": "Point",
    "coordinates": [
      60.0213,
      56.8804
    ]
  }
}