{
  "type": "Feature",
  "properties": {
    "name": "Tsementnyy",
    "country": "RU",
    "subdivision": "71",
    "timezone": "Asia/Yekaterinburg"
  },
  "geometry": {
    "type": "Point",
    "coordinates": [
      60.1536,
      57.4693
    ]
  }
}