{
  "type": "Feature",
  "properties": {
    "name": "Turinsk",
    "country": "RU",
    "subdivision": "71",
    "timezone": "Asia/Yekaterinburg"
  },
  "geometry": {
    "type": "Point",
    "coordinates": [
      63.69605,
      58.04575
    ]
  }
}