{
  "type": "Feature",
  "properties": {
    "name": "Valerianovsk",
    "country": "RU",
    "subdivision": "71",
    "timezone": "Asia/Yekaterinburg"
  },
  "geometry": {
    "type": "Point",
    "coordinates": [
      59.5596,
      58.7608
    ]
  }
}