{
  "type": "Feature",
  "properties": {
    "name": "Verkhnyaya Sysert’",
    "country": "RU",
    "subdivision": "71",
    "timezone": "Asia/Yekaterinburg"
  },
  "geometry": {
    "type": "Point",
    "coordinates": [
      60.75563,
      56.44012
    ]
  }
}