{
  "type": "Feature",
  "properties": {
    "name": "Verkh-Neyvinskiy",
    "country": "RU",
    "subdivision": "71",
    "timezone": "Asia/Yekaterinburg"
  },
  "geometry": {
    "type": "Point",
    "coordinates": [
      60.13762,
      57.27013
    ]
  }
}