{
  "type": "Feature",
  "properties": {
    "name": "Verkhnyaya Salda",
    "country": "RU",
    "subdivision": "71",
    "timezone": "Asia/Yekaterinburg"
  },
  "geometry": {
    "type": "Point",
    "coordinates": [
      60.55949,
      58.04874
    ]
  }
}