{
  "type": "Feature",
  "properties": {
    "name": "Yelanskiy",
    "country": "RU",
    "subdivision": "71",
    "timezone": "Asia/Yekaterinburg"
  },
  "geometry": {
    "type": "Point",
    "coordinates": [
      62.5014,
      56.8419
    ]
  }
}