{
  "type": "Feature",
  "properties": {
    "name": "Allendale",
    "country": "US",
    "subdivision": "SC",
    "timezone": "America/New_York"
  },
  "geometry": {
    "type": "Point",
    "coordinates": [
      -81.30844,
      33.00793
    ]
  }
}