{
  "type": "Feature",
  "properties": {
    "name": "Andrews",
    "country": "US",
    "subdivision": "SC",
    "timezone": "America/New_York"
  },
  "geometry": {
    "type": "Point",
    "coordinates": [
      -79.5609,
      33.45128
    ]
  }
}