{
  "type": "Feature",
  "properties": {
    "name": "Arial",
    "country": "US",
    "subdivision": "SC",
    "timezone": "America/New_York"
  },
  "geometry": {
    "type": "Point",
    "coordinates": [
      -82.64152,
      34.84595
    ]
  }
}