{
  "type": "Feature",
  "properties": {
    "name": "Belton",
    "country": "US",
    "subdivision": "SC",
    "timezone": "America/New_York"
  },
  "geometry": {
    "type": "Point",
    "coordinates": [
      -82.49429,
      34.52289
    ]
  }
}