{
  "type": "Feature",
  "properties": {
    "name": "Blacksburg",
    "country": "US",
    "subdivision": "SC",
    "timezone": "America/New_York"
  },
  "geometry": {
    "type": "Point",
    "coordinates": [
      -81.51592,
      35.12124
    ]
  }
}