{
  "type": "Feature",
  "properties": {
    "name": "Cherryvale",
    "country": "US",
    "subdivision": "SC",
    "timezone": "America/New_York"
  },
  "geometry": {
    "type": "Point",
    "coordinates": [
      -80.45814,
      33.95571
    ]
  }
}