{
  "type": "Feature",
  "properties": {
    "name": "Columbia",
    "country": "US",
    "subdivision": "SC",
    "timezone": "America/New_York"
  },
  "geometry": {
    "type": "Point",
    "coordinates": [
      -81.03481,
      34.00071
    ]
  }
}