{
  "type": "Feature",
  "properties": {
    "name": "Dentsville",
    "country": "US",
    "subdivision": "SC",
    "timezone": "America/New_York"
  },
  "geometry": {
    "type": "Point",
    "coordinates": [
      -80.95815,
      34.06404
    ]
  }
}