{
  "type": "Feature",
  "properties": {
    "name": "Due West",
    "country": "US",
    "subdivision": "SC",
    "timezone": "America/New_York"
  },
  "geometry": {
    "type": "Point",
    "coordinates": [
      -82.3879,
      34.33345
    ]
  }
}