{
  "type": "Feature",
  "properties": {
    "name": "Fairfax",
    "country": "US",
    "subdivision": "SC",
    "timezone": "America/New_York"
  },
  "geometry": {
    "type": "Point",
    "coordinates": [
      -81.2365,
      32.95905
    ]
  }
}