{
  "type": "Feature",
  "properties": {
    "name": "Folly Beach",
    "country": "US",
    "subdivision": "SC",
    "timezone": "America/New_York"
  },
  "geometry": {
    "type": "Point",
    "coordinates": [
      -79.94037,
      32.65518
    ]
  }
}