{
  "type": "Feature",
  "properties": {
    "name": "Forestbrook",
    "country": "US",
    "subdivision": "SC",
    "timezone": "America/New_York"
  },
  "geometry": {
    "type": "Point",
    "coordinates": [
      -78.95809,
      33.72239
    ]
  }
}