{
  "type": "Feature",
  "properties": {
    "name": "Fort Mill",
    "country": "US",
    "subdivision": "SC",
    "timezone": "America/New_York"
  },
  "geometry": {
    "type": "Point",
    "coordinates": [
      -80.94508,
      35.00737
    ]
  }
}