{
  "type": "Feature",
  "properties": {
    "name": "Garden City",
    "country": "US",
    "subdivision": "SC",
    "timezone": "America/New_York"
  },
  "geometry": {
    "type": "Point",
    "coordinates": [
      -79.00865,
      33.59295
    ]
  }
}