{
  "type": "Feature",
  "properties": {
    "name": "Greenville",
    "country": "US",
    "subdivision": "SC",
    "timezone": "America/New_York"
  },
  "geometry": {
    "type": "Point",
    "coordinates": [
      -82.39401,
      34.85262
    ]
  }
}