{
  "type": "Feature",
  "properties": {
    "name": "Hampton",
    "country": "US",
    "subdivision": "SC",
    "timezone": "America/New_York"
  },
  "geometry": {
    "type": "Point",
    "coordinates": [
      -81.12761,
      32.87794
    ]
  }
}