{
  "type": "Feature",
  "properties": {
    "name": "Isle of Palms",
    "country": "US",
    "subdivision": "SC",
    "timezone": "America/New_York"
  },
  "geometry": {
    "type": "Point",
    "coordinates": [
      -79.7948,
      32.78684
    ]
  }
}