{
  "type": "Feature",
  "properties": {
    "name": "Kershaw",
    "country": "US",
    "subdivision": "SC",
    "timezone": "America/New_York"
  },
  "geometry": {
    "type": "Point",
    "coordinates": [
      -80.58368,
      34.55182
    ]
  }
}