{
  "type": "Feature",
  "properties": {
    "name": "Lake Secession",
    "country": "US",
    "subdivision": "SC",
    "timezone": "America/New_York"
  },
  "geometry": {
    "type": "Point",
    "coordinates": [
      -82.59457,
      34.28455
    ]
  }
}