{
  "type": "Feature",
  "properties": {
    "name": "Murrells Inlet",
    "country": "US",
    "subdivision": "SC",
    "timezone": "America/New_York"
  },
  "geometry": {
    "type": "Point",
    "coordinates": [
      -79.04143,
      33.551
    ]
  }
}