{
  "type": "Feature",
  "properties": {
    "name": "Newport",
    "country": "US",
    "subdivision": "SC",
    "timezone": "America/New_York"
  },
  "geometry": {
    "type": "Point",
    "coordinates": [
      -81.10091,
      34.98986
    ]
  }
}