{
  "type": "Feature",
  "properties": {
    "name": "Orangeburg",
    "country": "US",
    "subdivision": "SC",
    "timezone": "America/New_York"
  },
  "geometry": {
    "type": "Point",
    "coordinates": [
      -80.85565,
      33.49182
    ]
  }
}