{
  "type": "Feature",
  "properties": {
    "name": "Port Royal",
    "country": "US",
    "subdivision": "SC",
    "timezone": "America/New_York"
  },
  "geometry": {
    "type": "Point",
    "coordinates": [
      -80.69261,
      32.37908
    ]
  }
}