{
  "type": "Feature",
  "properties": {
    "name": "Ravenel",
    "country": "US",
    "subdivision": "SC",
    "timezone": "America/New_York"
  },
  "geometry": {
    "type": "Point",
    "coordinates": [
      -80.2501,
      32.76323
    ]
  }
}