{
  "type": "Feature",
  "properties": {
    "name": "Sangaree",
    "country": "US",
    "subdivision": "SC",
    "timezone": "America/New_York"
  },
  "geometry": {
    "type": "Point",
    "coordinates": [
      -80.12787,
      33.03545
    ]
  }
}