{
  "type": "Feature",
  "properties": {
    "name": "Saxon",
    "country": "US",
    "subdivision": "SC",
    "timezone": "America/New_York"
  },
  "geometry": {
    "type": "Point",
    "coordinates": [
      -81.96733,
      34.96123
    ]
  }
}