{
  "type": "Feature",
  "properties": {
    "name": "South Congaree",
    "country": "US",
    "subdivision": "SC",
    "timezone": "America/New_York"
  },
  "geometry": {
    "type": "Point",
    "coordinates": [
      -81.13565,
      33.91099
    ]
  }
}