{
  "type": "Feature",
  "properties": {
    "name": "Wedgefield",
    "country": "US",
    "subdivision": "SC",
    "timezone": "America/New_York"
  },
  "geometry": {
    "type": "Point",
    "coordinates": [
      -80.51814,
      33.89266
    ]
  }
}