{
  "type": "Feature",
  "properties": {
    "name": "Punata",
    "country": "BO",
    "subdivision": "02",
    "timezone": "America/La_Paz"
  },
  "geometry": {
    "type": "Point",
    "coordinates": [
      -65.83472,
      -17.54234
    ]
  }
}