{
  "type": "Feature",
  "properties": {
    "name": "Quillacollo",
    "country": "BO",
    "subdivision": "02",
    "timezone": "America/La_Paz"
  },
  "geometry": {
    "type": "Point",
    "coordinates": [
      -66.27838,
      -17.39228
    ]
  }
}