{
  "type": "Feature",
  "properties": {
    "name": "Aslanapa",
    "country": "TR",
    "subdivision": "43",
    "timezone": "Europe/Istanbul"
  },
  "geometry": {
    "type": "Point",
    "coordinates": [
      29.8699,
      39.21581
    ]
  }
}