{
  "type": "Feature",
  "properties": {
    "name": "Pazarlar",
    "country": "TR",
    "subdivision": "43",
    "timezone": "Europe/Istanbul"
  },
  "geometry": {
    "type": "Point",
    "coordinates": [
      29.12583,
      38.995
    ]
  }
}