{
  "type": "Feature",
  "properties": {
    "name": "Junín",
    "country": "CO",
    "subdivision": "28",
    "timezone": "America/Bogota"
  },
  "geometry": {
    "type": "Point",
    "coordinates": [
      -75.01667,
      4.78333
    ]
  }
}