{
  "type": "Feature",
  "properties": {
    "name": "Laureles",
    "country": "CO",
    "subdivision": "28",
    "timezone": "America/Bogota"
  },
  "geometry": {
    "type": "Point",
    "coordinates": [
      -75.3225,
      4.25917
    ]
  }
}