{
  "type": "Feature",
  "properties": {
    "name": "Palocabildo",
    "country": "CO",
    "subdivision": "28",
    "timezone": "America/Bogota"
  },
  "geometry": {
    "type": "Point",
    "coordinates": [
      -75.01732,
      5.11705
    ]
  }
}