{
  "type": "Feature",
  "properties": {
    "name": "Suárez",
    "country": "CO",
    "subdivision": "28",
    "timezone": "America/Bogota"
  },
  "geometry": {
    "type": "Point",
    "coordinates": [
      -74.83198,
      4.04906
    ]
  }
}