{
  "type": "Feature",
  "properties": {
    "name": "Barczewo",
    "country": "PL",
    "subdivision": "85",
    "timezone": "Europe/Warsaw"
  },
  "geometry": {
    "type": "Point",
    "coordinates": [
      20.69112,
      53.83055
    ]
  }
}