{
  "type": "Feature",
  "properties": {
    "name": "Biskupiec",
    "country": "PL",
    "subdivision": "85",
    "timezone": "Europe/Warsaw"
  },
  "geometry": {
    "type": "Point",
    "coordinates": [
      20.95692,
      53.86467
    ]
  }
}