{
  "type": "Feature",
  "properties": {
    "name": "Dywity",
    "country": "PL",
    "subdivision": "85",
    "timezone": "Europe/Warsaw"
  },
  "geometry": {
    "type": "Point",
    "coordinates": [
      20.47817,
      53.83759
    ]
  }
}