{
  "type": "Feature",
  "properties": {
    "name": "Gronowo Górne",
    "country": "PL",
    "subdivision": "85",
    "timezone": "Europe/Warsaw"
  },
  "geometry": {
    "type": "Point",
    "coordinates": [
      19.45988,
      54.13863
    ]
  }
}