{
  "type": "Feature",
  "properties": {
    "name": "Gronowo Elbląskie",
    "country": "PL",
    "subdivision": "85",
    "timezone": "Europe/Warsaw"
  },
  "geometry": {
    "type": "Point",
    "coordinates": [
      19.30598,
      54.08588
    ]
  }
}