{
  "type": "Feature",
  "properties": {
    "name": "Kętrzyn",
    "country": "PL",
    "subdivision": "85",
    "timezone": "Europe/Warsaw"
  },
  "geometry": {
    "type": "Point",
    "coordinates": [
      21.37527,
      54.07676
    ]
  }
}