{
  "type": "Feature",
  "properties": {
    "name": "Lelkowo",
    "country": "PL",
    "subdivision": "85",
    "timezone": "Europe/Warsaw"
  },
  "geometry": {
    "type": "Point",
    "coordinates": [
      20.2248,
      54.32458
    ]
  }
}