{
  "type": "Feature",
  "properties": {
    "name": "Lubawa",
    "country": "PL",
    "subdivision": "85",
    "timezone": "Europe/Warsaw"
  },
  "geometry": {
    "type": "Point",
    "coordinates": [
      19.74966,
      53.50428
    ]
  }
}