{
  "type": "Feature",
  "properties": {
    "name": "Purda",
    "country": "PL",
    "subdivision": "85",
    "timezone": "Europe/Warsaw"
  },
  "geometry": {
    "type": "Point",
    "coordinates": [
      20.70683,
      53.70844
    ]
  }
}