{
  "type": "Feature",
  "properties": {
    "name": "Rybno",
    "country": "PL",
    "subdivision": "85",
    "timezone": "Europe/Warsaw"
  },
  "geometry": {
    "type": "Point",
    "coordinates": [
      19.93229,
      53.38348
    ]
  }
}