{
  "type": "Feature",
  "properties": {
    "name": "Srokowo",
    "country": "PL",
    "subdivision": "85",
    "timezone": "Europe/Warsaw"
  },
  "geometry": {
    "type": "Point",
    "coordinates": [
      21.52282,
      54.21416
    ]
  }
}