{
  "type": "Feature",
  "properties": {
    "name": "Węgorzewo",
    "country": "PL",
    "subdivision": "85",
    "timezone": "Europe/Warsaw"
  },
  "geometry": {
    "type": "Point",
    "coordinates": [
      21.7372,
      54.21567
    ]
  }
}