{
  "type": "Feature",
  "properties": {
    "name": "Zalewo",
    "country": "PL",
    "subdivision": "85",
    "timezone": "Europe/Warsaw"
  },
  "geometry": {
    "type": "Point",
    "coordinates": [
      19.60519,
      53.84534
    ]
  }
}