{
  "type": "Feature",
  "properties": {
    "name": "Degema Hulk",
    "country": "NG",
    "subdivision": "50",
    "timezone": "Africa/Lagos"
  },
  "geometry": {
    "type": "Point",
    "coordinates": [
      6.74957,
      4.76145
    ]
  }
}