{
  "type": "Feature",
  "properties": {
    "name": "Lehtimäki",
    "country": "FI",
    "subdivision": "14",
    "timezone": "Europe/Helsinki"
  },
  "geometry": {
    "type": "Point",
    "coordinates": [
      23.91667,
      62.78333
    ]
  }
}