{
  "type": "Feature",
  "properties": {
    "name": "Töysä",
    "country": "FI",
    "subdivision": "14",
    "timezone": "Europe/Helsinki"
  },
  "geometry": {
    "type": "Point",
    "coordinates": [
      23.81828,
      62.62803
    ]
  }
}