{
  "type": "Feature",
  "properties": {
    "name": "Betlitsa",
    "country": "RU",
    "subdivision": "25",
    "timezone": "Europe/Moscow"
  },
  "geometry": {
    "type": "Point",
    "coordinates": [
      33.95875,
      54.00946
    ]
  }
}