{
  "type": "Feature",
  "properties": {
    "name": "Borovsk",
    "country": "RU",
    "subdivision": "25",
    "timezone": "Europe/Moscow"
  },
  "geometry": {
    "type": "Point",
    "coordinates": [
      36.48611,
      55.20639
    ]
  }
}