{
  "type": "Feature",
  "properties": {
    "name": "Kremenki",
    "country": "RU",
    "subdivision": "25",
    "timezone": "Europe/Moscow"
  },
  "geometry": {
    "type": "Point",
    "coordinates": [
      37.11955,
      54.88626
    ]
  }
}