{
  "type": "Feature",
  "properties": {
    "name": "Maloyaroslavets",
    "country": "RU",
    "subdivision": "25",
    "timezone": "Europe/Moscow"
  },
  "geometry": {
    "type": "Point",
    "coordinates": [
      36.47185,
      55.01457
    ]
  }
}