{
  "type": "Feature",
  "properties": {
    "name": "Nikola-Lenivets",
    "country": "RU",
    "subdivision": "25",
    "timezone": "Europe/Moscow"
  },
  "geometry": {
    "type": "Point",
    "coordinates": [
      35.60133,
      54.74943
    ]
  }
}