{
  "type": "Feature",
  "properties": {
    "name": "Peremyshl’",
    "country": "RU",
    "subdivision": "25",
    "timezone": "Europe/Moscow"
  },
  "geometry": {
    "type": "Point",
    "coordinates": [
      36.16063,
      54.26313
    ]
  }
}