{
  "type": "Feature",
  "properties": {
    "name": "Sosenskiy",
    "country": "RU",
    "subdivision": "25",
    "timezone": "Europe/Moscow"
  },
  "geometry": {
    "type": "Point",
    "coordinates": [
      35.96228,
      54.05899
    ]
  }
}