{
  "type": "Feature",
  "properties": {
    "name": "Tovarkovo",
    "country": "RU",
    "subdivision": "25",
    "timezone": "Europe/Moscow"
  },
  "geometry": {
    "type": "Point",
    "coordinates": [
      35.9386,
      54.67617
    ]
  }
}