{
  "type": "Feature",
  "properties": {
    "name": "Yermolino",
    "country": "RU",
    "subdivision": "25",
    "timezone": "Europe/Moscow"
  },
  "geometry": {
    "type": "Point",
    "coordinates": [
      36.59513,
      55.19489
    ]
  }
}