{
  "type": "Feature",
  "properties": {
    "name": "Bakanas",
    "country": "KZ",
    "subdivision": "01",
    "timezone": "Asia/Almaty"
  },
  "geometry": {
    "type": "Point",
    "coordinates": [
      76.27032,
      44.80622
    ]
  }
}