{
  "type": "Feature",
  "properties": {
    "name": "Druzhba",
    "country": "KZ",
    "subdivision": "01",
    "timezone": "Asia/Almaty"
  },
  "geometry": {
    "type": "Point",
    "coordinates": [
      82.48044,
      45.25332
    ]
  }
}