{
  "type": "Feature",
  "properties": {
    "name": "Bathsheba",
    "country": "BB",
    "subdivision": "06",
    "timezone": "America/Barbados"
  },
  "geometry": {
    "type": "Point",
    "coordinates": [
      -59.52596,
      13.21133
    ]
  }
}