{
  "type": "Feature",
  "properties": {
    "name": "Ogwashi-Uku",
    "country": "NG",
    "subdivision": "36",
    "timezone": "Africa/Lagos"
  },
  "geometry": {
    "type": "Point",
    "coordinates": [
      6.52461,
      6.17811
    ]
  }
}