{
  "type": "Feature",
  "properties": {
    "name": "Jenoi",
    "country": "GM",
    "subdivision": "02",
    "timezone": "Africa/Banjul"
  },
  "geometry": {
    "type": "Point",
    "coordinates": [
      -15.56667,
      13.48333
    ]
  }
}