{
  "type": "Feature",
  "properties": {
    "name": "Nioro",
    "country": "GM",
    "subdivision": "02",
    "timezone": "Africa/Banjul"
  },
  "geometry": {
    "type": "Point",
    "coordinates": [
      -15.75,
      13.35
    ]
  }
}