{
  "type": "Feature",
  "properties": {
    "name": "Illapel",
    "country": "CL",
    "subdivision": "07",
    "timezone": "America/Santiago"
  },
  "geometry": {
    "type": "Point",
    "coordinates": [
      -71.16967,
      -31.63349
    ]
  }
}