{
  "type": "Feature",
  "properties": {
    "name": "Dubréka",
    "country": "GN",
    "subdivision": "D",
    "timezone": "Africa/Conakry"
  },
  "geometry": {
    "type": "Point",
    "coordinates": [
      -13.52333,
      9.79111
    ]
  }
}