{
  "type": "Feature",
  "properties": {
    "name": "Bin Yauri",
    "country": "NG",
    "subdivision": "40",
    "timezone": "Africa/Lagos"
  },
  "geometry": {
    "type": "Point",
    "coordinates": [
      4.81135,
      10.7823
    ]
  }
}