{
  "type": "Feature",
  "properties": {
    "name": "Jordbro",
    "country": "SE",
    "subdivision": "26",
    "timezone": "Europe/Stockholm"
  },
  "geometry": {
    "type": "Point",
    "coordinates": [
      18.11667,
      59.14972
    ]
  }
}