{
  "type": "Feature",
  "properties": {
    "name": "Kungsängen",
    "country": "SE",
    "subdivision": "26",
    "timezone": "Europe/Stockholm"
  },
  "geometry": {
    "type": "Point",
    "coordinates": [
      17.74834,
      59.47857
    ]
  }
}