{
  "type": "Feature",
  "properties": {
    "name": "Kungsholmen",
    "country": "SE",
    "subdivision": "26",
    "timezone": "Europe/Stockholm"
  },
  "geometry": {
    "type": "Point",
    "coordinates": [
      18.04118,
      59.33183
    ]
  }
}