{
  "type": "Feature",
  "properties": {
    "name": "Långvik",
    "country": "SE",
    "subdivision": "26",
    "timezone": "Europe/Stockholm"
  },
  "geometry": {
    "type": "Point",
    "coordinates": [
      18.51667,
      59.24583
    ]
  }
}