{
  "type": "Feature",
  "properties": {
    "name": "Norrtälje",
    "country": "SE",
    "subdivision": "26",
    "timezone": "Europe/Stockholm"
  },
  "geometry": {
    "type": "Point",
    "coordinates": [
      18.70496,
      59.75799
    ]
  }
}