{
  "type": "Feature",
  "properties": {
    "name": "Rimbo",
    "country": "SE",
    "subdivision": "26",
    "timezone": "Europe/Stockholm"
  },
  "geometry": {
    "type": "Point",
    "coordinates": [
      18.36667,
      59.75
    ]
  }
}