{
  "type": "Feature",
  "properties": {
    "name": "Skänninge",
    "country": "SE",
    "subdivision": "26",
    "timezone": "Europe/Stockholm"
  },
  "geometry": {
    "type": "Point",
    "coordinates": [
      18.48333,
      59.93333
    ]
  }
}