{
  "type": "Feature",
  "properties": {
    "name": "Sundbyberg",
    "country": "SE",
    "subdivision": "26",
    "timezone": "Europe/Stockholm"
  },
  "geometry": {
    "type": "Point",
    "coordinates": [
      17.97114,
      59.36128
    ]
  }
}