{
  "type": "Feature",
  "properties": {
    "name": "El Porvenir",
    "country": "HN",
    "subdivision": "04",
    "timezone": "America/Tegucigalpa"
  },
  "geometry": {
    "type": "Point",
    "coordinates": [
      -87.88333,
      14.58333
    ]
  }
}