{
  "type": "Feature",
  "properties": {
    "name": "Victoria",
    "country": "MT",
    "subdivision": "46",
    "timezone": "Europe/Malta"
  },
  "geometry": {
    "type": "Point",
    "coordinates": [
      14.23972,
      36.04444
    ]
  }
}