{
  "type": "Feature",
  "properties": {
    "name": "Batasan",
    "country": "PH",
    "subdivision": "12",
    "timezone": "Asia/Manila"
  },
  "geometry": {
    "type": "Point",
    "coordinates": [
      125.05,
      7.03333
    ]
  }
}