{
  "type": "Feature",
  "properties": {
    "name": "Biwang",
    "country": "PH",
    "subdivision": "12",
    "timezone": "Asia/Manila"
  },
  "geometry": {
    "type": "Point",
    "coordinates": [
      124.54358,
      6.60592
    ]
  }
}