{
  "type": "Feature",
  "properties": {
    "name": "Blingkong",
    "country": "PH",
    "subdivision": "12",
    "timezone": "Asia/Manila"
  },
  "geometry": {
    "type": "Point",
    "coordinates": [
      124.88951,
      6.58808
    ]
  }
}