{
  "type": "Feature",
  "properties": {
    "name": "Bukay Pait",
    "country": "PH",
    "subdivision": "12",
    "timezone": "Asia/Manila"
  },
  "geometry": {
    "type": "Point",
    "coordinates": [
      124.76706,
      6.56161
    ]
  }
}