{
  "type": "Feature",
  "properties": {
    "name": "Bulatukan",
    "country": "PH",
    "subdivision": "12",
    "timezone": "Asia/Manila"
  },
  "geometry": {
    "type": "Point",
    "coordinates": [
      125.16083,
      6.9025
    ]
  }
}