{
  "type": "Feature",
  "properties": {
    "name": "Kalamangog",
    "country": "PH",
    "subdivision": "12",
    "timezone": "Asia/Manila"
  },
  "geometry": {
    "type": "Point",
    "coordinates": [
      124.06889,
      6.72556
    ]
  }
}