{
  "type": "Feature",
  "properties": {
    "name": "Kalamansig",
    "country": "PH",
    "subdivision": "12",
    "timezone": "Asia/Manila"
  },
  "geometry": {
    "type": "Point",
    "coordinates": [
      124.05111,
      6.55187
    ]
  }
}