{
  "type": "Feature",
  "properties": {
    "name": "Kapaya",
    "country": "PH",
    "subdivision": "12",
    "timezone": "Asia/Manila"
  },
  "geometry": {
    "type": "Point",
    "coordinates": [
      124.56314,
      6.54258
    ]
  }
}