{
  "type": "Feature",
  "properties": {
    "name": "Labu-o",
    "country": "PH",
    "subdivision": "12",
    "timezone": "Asia/Manila"
  },
  "geometry": {
    "type": "Point",
    "coordinates": [
      125.04528,
      7.11417
    ]
  }
}