{
  "type": "Feature",
  "properties": {
    "name": "Laguilayan",
    "country": "PH",
    "subdivision": "12",
    "timezone": "Asia/Manila"
  },
  "geometry": {
    "type": "Point",
    "coordinates": [
      124.52491,
      6.67213
    ]
  }
}