{
  "type": "Feature",
  "properties": {
    "name": "Lambontong",
    "country": "PH",
    "subdivision": "12",
    "timezone": "Asia/Manila"
  },
  "geometry": {
    "type": "Point",
    "coordinates": [
      124.81056,
      6.30833
    ]
  }
}