{
  "type": "Feature",
  "properties": {
    "name": "Lampitak",
    "country": "PH",
    "subdivision": "12",
    "timezone": "Asia/Manila"
  },
  "geometry": {
    "type": "Point",
    "coordinates": [
      125.0525,
      6.43222
    ]
  }
}