{
  "type": "Feature",
  "properties": {
    "name": "Lopez Jaena",
    "country": "PH",
    "subdivision": "12",
    "timezone": "Asia/Manila"
  },
  "geometry": {
    "type": "Point",
    "coordinates": [
      124.69828,
      6.47591
    ]
  }
}