{
  "type": "Feature",
  "properties": {
    "name": "Mamali",
    "country": "PH",
    "subdivision": "12",
    "timezone": "Asia/Manila"
  },
  "geometry": {
    "type": "Point",
    "coordinates": [
      124.6477,
      6.7736
    ]
  }
}