{
  "type": "Feature",
  "properties": {
    "name": "Manga",
    "country": "PH",
    "subdivision": "12",
    "timezone": "Asia/Manila"
  },
  "geometry": {
    "type": "Point",
    "coordinates": [
      125.30833,
      6.29083
    ]
  }
}