{
  "type": "Feature",
  "properties": {
    "name": "Manuel Roxas",
    "country": "PH",
    "subdivision": "12",
    "timezone": "Asia/Manila"
  },
  "geometry": {
    "type": "Point",
    "coordinates": [
      124.66605,
      6.44173
    ]
  }
}