{
  "type": "Feature",
  "properties": {
    "name": "Matalam",
    "country": "PH",
    "subdivision": "12",
    "timezone": "Asia/Manila"
  },
  "geometry": {
    "type": "Point",
    "coordinates": [
      124.90056,
      7.08639
    ]
  }
}