{
  "type": "Feature",
  "properties": {
    "name": "Matiompong",
    "country": "PH",
    "subdivision": "12",
    "timezone": "Asia/Manila"
  },
  "geometry": {
    "type": "Point",
    "coordinates": [
      124.56611,
      6.69611
    ]
  }
}