{
  "type": "Feature",
  "properties": {
    "name": "New Iloilo",
    "country": "PH",
    "subdivision": "12",
    "timezone": "Asia/Manila"
  },
  "geometry": {
    "type": "Point",
    "coordinates": [
      124.78951,
      6.54776
    ]
  }
}