{
  "type": "Feature",
  "properties": {
    "name": "Noling",
    "country": "PH",
    "subdivision": "12",
    "timezone": "Asia/Manila"
  },
  "geometry": {
    "type": "Point",
    "coordinates": [
      124.09981,
      6.65984
    ]
  }
}