{
  "type": "Feature",
  "properties": {
    "name": "Pagalungan",
    "country": "PH",
    "subdivision": "12",
    "timezone": "Asia/Manila"
  },
  "geometry": {
    "type": "Point",
    "coordinates": [
      125.01333,
      6.26556
    ]
  }
}