{
  "type": "Feature",
  "properties": {
    "name": "Polonoling",
    "country": "PH",
    "subdivision": "12",
    "timezone": "Asia/Manila"
  },
  "geometry": {
    "type": "Point",
    "coordinates": [
      124.9689,
      6.28496
    ]
  }
}