{
  "type": "Feature",
  "properties": {
    "name": "Sampao",
    "country": "PH",
    "subdivision": "12",
    "timezone": "Asia/Manila"
  },
  "geometry": {
    "type": "Point",
    "coordinates": [
      124.59556,
      6.87667
    ]
  }
}