{
  "type": "Feature",
  "properties": {
    "name": "Santo Niño",
    "country": "PH",
    "subdivision": "12",
    "timezone": "Asia/Manila"
  },
  "geometry": {
    "type": "Point",
    "coordinates": [
      124.6975,
      6.435
    ]
  }
}