{
  "type": "Feature",
  "properties": {
    "name": "Tulunan",
    "country": "PH",
    "subdivision": "12",
    "timezone": "Asia/Manila"
  },
  "geometry": {
    "type": "Point",
    "coordinates": [
      124.87694,
      6.83444
    ]
  }
}