{
  "type": "Feature",
  "properties": {
    "name": "Boju",
    "country": "NG",
    "subdivision": "26",
    "timezone": "Africa/Lagos"
  },
  "geometry": {
    "type": "Point",
    "coordinates": [
      7.89303,
      7.35572
    ]
  }
}