{
  "type": "Feature",
  "properties": {
    "name": "Ochobo",
    "country": "NG",
    "subdivision": "26",
    "timezone": "Africa/Lagos"
  },
  "geometry": {
    "type": "Point",
    "coordinates": [
      7.9824,
      7.18045
    ]
  }
}