{
  "type": "Feature",
  "properties": {
    "name": "Takum",
    "country": "NG",
    "subdivision": "26",
    "timezone": "Africa/Lagos"
  },
  "geometry": {
    "type": "Point",
    "coordinates": [
      9.98333,
      7.26667
    ]
  }
}