{
  "type": "Feature",
  "properties": {
    "name": "Zaki Biam",
    "country": "NG",
    "subdivision": "26",
    "timezone": "Africa/Lagos"
  },
  "geometry": {
    "type": "Point",
    "coordinates": [
      9.6104,
      7.50671
    ]
  }
}