{
  "type": "Feature",
  "properties": {
    "name": "Pak Phanang",
    "country": "TH",
    "subdivision": "64",
    "timezone": "Asia/Bangkok"
  },
  "geometry": {
    "type": "Point",
    "coordinates": [
      100.20195,
      8.35109
    ]
  }
}