{
  "type": "Feature",
  "properties": {
    "name": "Tham Phannara",
    "country": "TH",
    "subdivision": "64",
    "timezone": "Asia/Bangkok"
  },
  "geometry": {
    "type": "Point",
    "coordinates": [
      99.39517,
      8.42045
    ]
  }
}