{
  "type": "Feature",
  "properties": {
    "name": "Jobabo",
    "country": "CU",
    "subdivision": "13",
    "timezone": "America/Havana"
  },
  "geometry": {
    "type": "Point",
    "coordinates": [
      -77.28194,
      20.90748
    ]
  }
}