{
  "type": "Feature",
  "properties": {
    "name": "Romanovci",
    "country": "MK",
    "subdivision": "D7",
    "timezone": "Europe/Skopje"
  },
  "geometry": {
    "type": "Point",
    "coordinates": [
      21.69306,
      42.09472
    ]
  }
}