{
  "type": "Feature",
  "properties": {
    "name": "Badu",
    "country": "CN",
    "subdivision": "07",
    "timezone": "Asia/Shanghai"
  },
  "geometry": {
    "type": "Point",
    "coordinates": [
      119.56417,
      26.81028
    ]
  }
}