{
  "type": "Feature",
  "properties": {
    "name": "Chongru",
    "country": "CN",
    "subdivision": "07",
    "timezone": "Asia/Shanghai"
  },
  "geometry": {
    "type": "Point",
    "coordinates": [
      119.92528,
      26.95111
    ]
  }
}