{
  "type": "Feature",
  "properties": {
    "name": "Dongyuan",
    "country": "CN",
    "subdivision": "07",
    "timezone": "Asia/Shanghai"
  },
  "geometry": {
    "type": "Point",
    "coordinates": [
      118.75236,
      24.91738
    ]
  }
}