{
  "type": "Feature",
  "properties": {
    "name": "Fuqing",
    "country": "CN",
    "subdivision": "07",
    "timezone": "Asia/Shanghai"
  },
  "geometry": {
    "type": "Point",
    "coordinates": [
      119.37469,
      25.7294
    ]
  }
}