{
  "type": "Feature",
  "properties": {
    "name": "Nanping",
    "country": "CN",
    "subdivision": "07",
    "timezone": "Asia/Shanghai"
  },
  "geometry": {
    "type": "Point",
    "coordinates": [
      118.17361,
      26.645
    ]
  }
}