{
  "type": "Feature",
  "properties": {
    "name": "Pandu",
    "country": "CN",
    "subdivision": "07",
    "timezone": "Asia/Shanghai"
  },
  "geometry": {
    "type": "Point",
    "coordinates": [
      119.45026,
      26.23639
    ]
  }
}