{
  "type": "Feature",
  "properties": {
    "name": "Rong’an",
    "country": "CN",
    "subdivision": "07",
    "timezone": "Asia/Shanghai"
  },
  "geometry": {
    "type": "Point",
    "coordinates": [
      119.12666,
      26.12242
    ]
  }
}