{
  "type": "Feature",
  "properties": {
    "name": "Sanming",
    "country": "CN",
    "subdivision": "07",
    "timezone": "Asia/Shanghai"
  },
  "geometry": {
    "type": "Point",
    "coordinates": [
      117.61861,
      26.24861
    ]
  }
}