{
  "type": "Feature",
  "properties": {
    "name": "Zhongfang",
    "country": "CN",
    "subdivision": "07",
    "timezone": "Asia/Shanghai"
  },
  "geometry": {
    "type": "Point",
    "coordinates": [
      119.42583,
      26.60083
    ]
  }
}