{
  "type": "Feature",
  "properties": {
    "name": "Kōfu",
    "country": "JP",
    "subdivision": "46",
    "timezone": "Asia/Tokyo"
  },
  "geometry": {
    "type": "Point",
    "coordinates": [
      138.56667,
      35.66667
    ]
  }
}