{
  "type": "Feature",
  "properties": {
    "name": "Sarishābāri",
    "country": "BD",
    "subdivision": "H",
    "timezone": "Asia/Dhaka"
  },
  "geometry": {
    "type": "Point",
    "coordinates": [
      89.83126,
      24.75127
    ]
  }
}