{
  "type": "Feature",
  "properties": {
    "name": "Avanigadda",
    "country": "IN",
    "subdivision": "02",
    "timezone": "Asia/Kolkata"
  },
  "geometry": {
    "type": "Point",
    "coordinates": [
      80.91808,
      16.02148
    ]
  }
}