{
  "type": "Feature",
  "properties": {
    "name": "Bhīmunipatnam",
    "country": "IN",
    "subdivision": "02",
    "timezone": "Asia/Kolkata"
  },
  "geometry": {
    "type": "Point",
    "coordinates": [
      83.45203,
      17.89017
    ]
  }
}