{
  "type": "Feature",
  "properties": {
    "name": "Cuddapah",
    "country": "IN",
    "subdivision": "02",
    "timezone": "Asia/Kolkata"
  },
  "geometry": {
    "type": "Point",
    "coordinates": [
      78.82346,
      14.47995
    ]
  }
}