{
  "type": "Feature",
  "properties": {
    "name": "Gūdūr",
    "country": "IN",
    "subdivision": "02",
    "timezone": "Asia/Kolkata"
  },
  "geometry": {
    "type": "Point",
    "coordinates": [
      79.8521,
      14.15093
    ]
  }
}