{
  "type": "Feature",
  "properties": {
    "name": "Kurnool",
    "country": "IN",
    "subdivision": "02",
    "timezone": "Asia/Kolkata"
  },
  "geometry": {
    "type": "Point",
    "coordinates": [
      78.03602,
      15.82887
    ]
  }
}