{
  "type": "Feature",
  "properties": {
    "name": "Madanapalle",
    "country": "IN",
    "subdivision": "02",
    "timezone": "Asia/Kolkata"
  },
  "geometry": {
    "type": "Point",
    "coordinates": [
      78.50288,
      13.5503
    ]
  }
}