{
  "type": "Feature",
  "properties": {
    "name": "NandigÄma",
    "country": "IN",
    "subdivision": "02",
    "timezone": "Asia/Kolkata"
  },
  "geometry": {
    "type": "Point",
    "coordinates": [
      80.28596,
      16.7717
    ]
  }
}