{
  "type": "Feature",
  "properties": {
    "name": "NarasingÄpuram",
    "country": "IN",
    "subdivision": "02",
    "timezone": "Asia/Kolkata"
  },
  "geometry": {
    "type": "Point",
    "coordinates": [
      79.31652,
      13.60759
    ]
  }
}