{
  "type": "Feature",
  "properties": {
    "name": "PeddÄpuram",
    "country": "IN",
    "subdivision": "02",
    "timezone": "Asia/Kolkata"
  },
  "geometry": {
    "type": "Point",
    "coordinates": [
      82.13836,
      17.07701
    ]
  }
}