{
  "type": "Feature",
  "properties": {
    "name": "Pippara",
    "country": "IN",
    "subdivision": "02",
    "timezone": "Asia/Kolkata"
  },
  "geometry": {
    "type": "Point",
    "coordinates": [
      81.55,
      16.71667
    ]
  }
}