{
  "type": "Feature",
  "properties": {
    "name": "Sālūr",
    "country": "IN",
    "subdivision": "02",
    "timezone": "Asia/Kolkata"
  },
  "geometry": {
    "type": "Point",
    "coordinates": [
      83.20548,
      18.51716
    ]
  }
}