{
  "type": "Feature",
  "properties": {
    "name": "Srikakulam",
    "country": "IN",
    "subdivision": "02",
    "timezone": "Asia/Kolkata"
  },
  "geometry": {
    "type": "Point",
    "coordinates": [
      83.89751,
      18.2989
    ]
  }
}