{
  "type": "Feature",
  "properties": {
    "name": "Yanamalakuduru",
    "country": "IN",
    "subdivision": "02",
    "timezone": "Asia/Kolkata"
  },
  "geometry": {
    "type": "Point",
    "coordinates": [
      80.66746,
      16.48531
    ]
  }
}