{
  "type": "Feature",
  "properties": {
    "name": "Bangor",
    "country": "US",
    "subdivision": "MI",
    "timezone": "America/Detroit"
  },
  "geometry": {
    "type": "Point",
    "coordinates": [
      -86.11308,
      42.31254
    ]
  }
}