{
  "type": "Feature",
  "properties": {
    "name": "Baraga",
    "country": "US",
    "subdivision": "MI",
    "timezone": "America/Detroit"
  },
  "geometry": {
    "type": "Point",
    "coordinates": [
      -88.48902,
      46.77854
    ]
  }
}