{
  "type": "Feature",
  "properties": {
    "name": "Battle Creek",
    "country": "US",
    "subdivision": "MI",
    "timezone": "America/Detroit"
  },
  "geometry": {
    "type": "Point",
    "coordinates": [
      -85.17816,
      42.3173
    ]
  }
}