{
  "type": "Feature",
  "properties": {
    "name": "Beaverton",
    "country": "US",
    "subdivision": "MI",
    "timezone": "America/Detroit"
  },
  "geometry": {
    "type": "Point",
    "coordinates": [
      -84.48473,
      43.88225
    ]
  }
}