{
  "type": "Feature",
  "properties": {
    "name": "Berrien Springs",
    "country": "US",
    "subdivision": "MI",
    "timezone": "America/Detroit"
  },
  "geometry": {
    "type": "Point",
    "coordinates": [
      -86.3389,
      41.94643
    ]
  }
}