{
  "type": "Feature",
  "properties": {
    "name": "Blissfield",
    "country": "US",
    "subdivision": "MI",
    "timezone": "America/Detroit"
  },
  "geometry": {
    "type": "Point",
    "coordinates": [
      -83.86244,
      41.83255
    ]
  }
}