{
  "type": "Feature",
  "properties": {
    "name": "Bridgman",
    "country": "US",
    "subdivision": "MI",
    "timezone": "America/Detroit"
  },
  "geometry": {
    "type": "Point",
    "coordinates": [
      -86.55697,
      41.9431
    ]
  }
}