{
  "type": "Feature",
  "properties": {
    "name": "Bridgeport",
    "country": "US",
    "subdivision": "MI",
    "timezone": "America/Detroit"
  },
  "geometry": {
    "type": "Point",
    "coordinates": [
      -83.88164,
      43.35947
    ]
  }
}