{
  "type": "Feature",
  "properties": {
    "name": "Brown City",
    "country": "US",
    "subdivision": "MI",
    "timezone": "America/Detroit"
  },
  "geometry": {
    "type": "Point",
    "coordinates": [
      -82.98966,
      43.21225
    ]
  }
}