{
  "type": "Feature",
  "properties": {
    "name": "Center Line",
    "country": "US",
    "subdivision": "MI",
    "timezone": "America/Detroit"
  },
  "geometry": {
    "type": "Point",
    "coordinates": [
      -83.0277,
      42.48504
    ]
  }
}