{
  "type": "Feature",
  "properties": {
    "name": "Colon",
    "country": "US",
    "subdivision": "MI",
    "timezone": "America/Detroit"
  },
  "geometry": {
    "type": "Point",
    "coordinates": [
      -85.32498,
      41.95838
    ]
  }
}