{
  "type": "Feature",
  "properties": {
    "name": "Douglas",
    "country": "US",
    "subdivision": "MI",
    "timezone": "America/Detroit"
  },
  "geometry": {
    "type": "Point",
    "coordinates": [
      -86.20059,
      42.64336
    ]
  }
}