{
  "type": "Feature",
  "properties": {
    "name": "Edwardsburg",
    "country": "US",
    "subdivision": "MI",
    "timezone": "America/Detroit"
  },
  "geometry": {
    "type": "Point",
    "coordinates": [
      -86.08084,
      41.7956
    ]
  }
}