{
  "type": "Feature",
  "properties": {
    "name": "Fennville",
    "country": "US",
    "subdivision": "MI",
    "timezone": "America/Detroit"
  },
  "geometry": {
    "type": "Point",
    "coordinates": [
      -86.1017,
      42.59392
    ]
  }
}