{
  "type": "Feature",
  "properties": {
    "name": "Flushing",
    "country": "US",
    "subdivision": "MI",
    "timezone": "America/Detroit"
  },
  "geometry": {
    "type": "Point",
    "coordinates": [
      -83.85107,
      43.06308
    ]
  }
}