{
  "type": "Feature",
  "properties": {
    "name": "Garden City",
    "country": "US",
    "subdivision": "MI",
    "timezone": "America/Detroit"
  },
  "geometry": {
    "type": "Point",
    "coordinates": [
      -83.33104,
      42.32559
    ]
  }
}