{
  "type": "Feature",
  "properties": {
    "name": "Hancock",
    "country": "US",
    "subdivision": "MI",
    "timezone": "America/Detroit"
  },
  "geometry": {
    "type": "Point",
    "coordinates": [
      -88.58096,
      47.12687
    ]
  }
}