{
  "type": "Feature",
  "properties": {
    "name": "Holt",
    "country": "US",
    "subdivision": "MI",
    "timezone": "America/Detroit"
  },
  "geometry": {
    "type": "Point",
    "coordinates": [
      -84.51525,
      42.64059
    ]
  }
}