{
  "type": "Feature",
  "properties": {
    "name": "Howard City",
    "country": "US",
    "subdivision": "MI",
    "timezone": "America/Detroit"
  },
  "geometry": {
    "type": "Point",
    "coordinates": [
      -85.46782,
      43.39558
    ]
  }
}