{
  "type": "Feature",
  "properties": {
    "name": "Imlay City",
    "country": "US",
    "subdivision": "MI",
    "timezone": "America/Detroit"
  },
  "geometry": {
    "type": "Point",
    "coordinates": [
      -83.07772,
      43.02475
    ]
  }
}