{
  "type": "Feature",
  "properties": {
    "name": "Kalamazoo",
    "country": "US",
    "subdivision": "MI",
    "timezone": "America/Detroit"
  },
  "geometry": {
    "type": "Point",
    "coordinates": [
      -85.58723,
      42.29171
    ]
  }
}