{
  "type": "Feature",
  "properties": {
    "name": "Kentwood",
    "country": "US",
    "subdivision": "MI",
    "timezone": "America/Detroit"
  },
  "geometry": {
    "type": "Point",
    "coordinates": [
      -85.64475,
      42.86947
    ]
  }
}