{
  "type": "Feature",
  "properties": {
    "name": "Laingsburg",
    "country": "US",
    "subdivision": "MI",
    "timezone": "America/Detroit"
  },
  "geometry": {
    "type": "Point",
    "coordinates": [
      -84.35136,
      42.89031
    ]
  }
}