{
  "type": "Feature",
  "properties": {
    "name": "Michigan Center",
    "country": "US",
    "subdivision": "MI",
    "timezone": "America/Detroit"
  },
  "geometry": {
    "type": "Point",
    "coordinates": [
      -84.32718,
      42.23309
    ]
  }
}