{
  "type": "Feature",
  "properties": {
    "name": "Millington",
    "country": "US",
    "subdivision": "MI",
    "timezone": "America/Detroit"
  },
  "geometry": {
    "type": "Point",
    "coordinates": [
      -83.52968,
      43.28141
    ]
  }
}