{
  "type": "Feature",
  "properties": {
    "name": "Morenci",
    "country": "US",
    "subdivision": "MI",
    "timezone": "America/Detroit"
  },
  "geometry": {
    "type": "Point",
    "coordinates": [
      -84.218,
      41.71949
    ]
  }
}