{
  "type": "Feature",
  "properties": {
    "name": "Nashville",
    "country": "US",
    "subdivision": "MI",
    "timezone": "America/Detroit"
  },
  "geometry": {
    "type": "Point",
    "coordinates": [
      -85.09305,
      42.60281
    ]
  }
}