{
  "type": "Feature",
  "properties": {
    "name": "New Buffalo",
    "country": "US",
    "subdivision": "MI",
    "timezone": "America/Detroit"
  },
  "geometry": {
    "type": "Point",
    "coordinates": [
      -86.74392,
      41.79393
    ]
  }
}