{
  "type": "Feature",
  "properties": {
    "name": "Parchment",
    "country": "US",
    "subdivision": "MI",
    "timezone": "America/Detroit"
  },
  "geometry": {
    "type": "Point",
    "coordinates": [
      -85.56973,
      42.3281
    ]
  }
}