{
  "type": "Feature",
  "properties": {
    "name": "Paw Paw Lake",
    "country": "US",
    "subdivision": "MI",
    "timezone": "America/Detroit"
  },
  "geometry": {
    "type": "Point",
    "coordinates": [
      -86.27197,
      42.21226
    ]
  }
}