{
  "type": "Feature",
  "properties": {
    "name": "Plainwell",
    "country": "US",
    "subdivision": "MI",
    "timezone": "America/Detroit"
  },
  "geometry": {
    "type": "Point",
    "coordinates": [
      -85.6489,
      42.44004
    ]
  }
}