{
  "type": "Feature",
  "properties": {
    "name": "Pleasant Ridge",
    "country": "US",
    "subdivision": "MI",
    "timezone": "America/Detroit"
  },
  "geometry": {
    "type": "Point",
    "coordinates": [
      -83.14215,
      42.47115
    ]
  }
}