{
  "type": "Feature",
  "properties": {
    "name": "Prudenville",
    "country": "US",
    "subdivision": "MI",
    "timezone": "America/Detroit"
  },
  "geometry": {
    "type": "Point",
    "coordinates": [
      -84.65197,
      44.29835
    ]
  }
}