{
  "type": "Feature",
  "properties": {
    "name": "Rochester Hills",
    "country": "US",
    "subdivision": "MI",
    "timezone": "America/Detroit"
  },
  "geometry": {
    "type": "Point",
    "coordinates": [
      -83.14993,
      42.65837
    ]
  }
}