{
  "type": "Feature",
  "properties": {
    "name": "Rockford",
    "country": "US",
    "subdivision": "MI",
    "timezone": "America/Detroit"
  },
  "geometry": {
    "type": "Point",
    "coordinates": [
      -85.56003,
      43.12003
    ]
  }
}