{
  "type": "Feature",
  "properties": {
    "name": "Roosevelt Park",
    "country": "US",
    "subdivision": "MI",
    "timezone": "America/Detroit"
  },
  "geometry": {
    "type": "Point",
    "coordinates": [
      -86.27228,
      43.1964
    ]
  }
}