{
  "type": "Feature",
  "properties": {
    "name": "Saint Clair Shores",
    "country": "US",
    "subdivision": "MI",
    "timezone": "America/Detroit"
  },
  "geometry": {
    "type": "Point",
    "coordinates": [
      -82.88881,
      42.49698
    ]
  }
}