{
  "type": "Feature",
  "properties": {
    "name": "Schoolcraft",
    "country": "US",
    "subdivision": "MI",
    "timezone": "America/Detroit"
  },
  "geometry": {
    "type": "Point",
    "coordinates": [
      -85.63778,
      42.11421
    ]
  }
}