{
  "type": "Feature",
  "properties": {
    "name": "Scottville",
    "country": "US",
    "subdivision": "MI",
    "timezone": "America/Detroit"
  },
  "geometry": {
    "type": "Point",
    "coordinates": [
      -86.28008,
      43.95473
    ]
  }
}