{
  "type": "Feature",
  "properties": {
    "name": "Shorewood-Tower Hills-Harbert",
    "country": "US",
    "subdivision": "MI",
    "timezone": "America/Detroit"
  },
  "geometry": {
    "type": "Point",
    "coordinates": [
      -86.61409,
      41.88169
    ]
  }
}