{
  "type": "Feature",
  "properties": {
    "name": "Three Oaks",
    "country": "US",
    "subdivision": "MI",
    "timezone": "America/Detroit"
  },
  "geometry": {
    "type": "Point",
    "coordinates": [
      -86.61058,
      41.79865
    ]
  }
}