{
  "type": "Feature",
  "properties": {
    "name": "Trowbridge Park",
    "country": "US",
    "subdivision": "MI",
    "timezone": "America/Detroit"
  },
  "geometry": {
    "type": "Point",
    "coordinates": [
      -87.43736,
      46.5566
    ]
  }
}