{
  "type": "Feature",
  "properties": {
    "name": "Walker",
    "country": "US",
    "subdivision": "MI",
    "timezone": "America/Detroit"
  },
  "geometry": {
    "type": "Point",
    "coordinates": [
      -85.76809,
      43.00141
    ]
  }
}