{
  "type": "Feature",
  "properties": {
    "name": "Wayland",
    "country": "US",
    "subdivision": "MI",
    "timezone": "America/Detroit"
  },
  "geometry": {
    "type": "Point",
    "coordinates": [
      -85.64474,
      42.67392
    ]
  }
}