{
  "type": "Feature",
  "properties": {
    "name": "Woodland Beach",
    "country": "US",
    "subdivision": "MI",
    "timezone": "America/Detroit"
  },
  "geometry": {
    "type": "Point",
    "coordinates": [
      -83.31326,
      41.94005
    ]
  }
}