{
  "type": "Feature",
  "properties": {
    "name": "Ypsilanti",
    "country": "US",
    "subdivision": "MI",
    "timezone": "America/Detroit"
  },
  "geometry": {
    "type": "Point",
    "coordinates": [
      -83.61299,
      42.24115
    ]
  }
}