{
  "type": "Feature",
  "properties": {
    "name": "Sha Tin",
    "country": "HK",
    "subdivision": "NST",
    "timezone": "Asia/Hong_Kong"
  },
  "geometry": {
    "type": "Point",
    "coordinates": [
      114.18333,
      22.38333
    ]
  }
}