{
  "type": "Feature",
  "properties": {
    "name": "Dhuusamarreeb",
    "country": "SO",
    "subdivision": "05",
    "timezone": "Africa/Mogadishu"
  },
  "geometry": {
    "type": "Point",
    "coordinates": [
      46.38666,
      5.53597
    ]
  }
}