{
  "type": "Feature",
  "properties": {
    "name": "Brójce",
    "country": "PL",
    "subdivision": "76",
    "timezone": "Europe/Warsaw"
  },
  "geometry": {
    "type": "Point",
    "coordinates": [
      15.67414,
      52.31745
    ]
  }
}