{
  "type": "Feature",
  "properties": {
    "name": "Dobiegniew",
    "country": "PL",
    "subdivision": "76",
    "timezone": "Europe/Warsaw"
  },
  "geometry": {
    "type": "Point",
    "coordinates": [
      15.75362,
      52.96947
    ]
  }
}