{
  "type": "Feature",
  "properties": {
    "name": "Stare Kurowo",
    "country": "PL",
    "subdivision": "76",
    "timezone": "Europe/Warsaw"
  },
  "geometry": {
    "type": "Point",
    "coordinates": [
      15.67749,
      52.85669
    ]
  }
}