{
  "type": "Feature",
  "properties": {
    "name": "Świdnica",
    "country": "PL",
    "subdivision": "76",
    "timezone": "Europe/Warsaw"
  },
  "geometry": {
    "type": "Point",
    "coordinates": [
      15.39013,
      51.88836
    ]
  }
}