{
  "type": "Feature",
  "properties": {
    "name": "Świebodzin",
    "country": "PL",
    "subdivision": "76",
    "timezone": "Europe/Warsaw"
  },
  "geometry": {
    "type": "Point",
    "coordinates": [
      15.53355,
      52.24751
    ]
  }
}