{
  "type": "Feature",
  "properties": {
    "name": "Torzym",
    "country": "PL",
    "subdivision": "76",
    "timezone": "Europe/Warsaw"
  },
  "geometry": {
    "type": "Point",
    "coordinates": [
      15.08243,
      52.31331
    ]
  }
}