{
  "type": "Feature",
  "properties": {
    "name": "Żary",
    "country": "PL",
    "subdivision": "76",
    "timezone": "Europe/Warsaw"
  },
  "geometry": {
    "type": "Point",
    "coordinates": [
      15.13727,
      51.64205
    ]
  }
}