{
  "type": "Feature",
  "properties": {
    "name": "Kalinovac",
    "country": "HR",
    "subdivision": "06",
    "timezone": "Europe/Zagreb"
  },
  "geometry": {
    "type": "Point",
    "coordinates": [
      17.11556,
      46.02944
    ]
  }
}