{
  "type": "Feature",
  "properties": {
    "name": "Baraki Barak",
    "country": "AF",
    "subdivision": "17",
    "timezone": "Asia/Kabul"
  },
  "geometry": {
    "type": "Point",
    "coordinates": [
      68.9492,
      33.96744
    ]
  }
}