{
  "type": "Feature",
  "properties": {
    "name": "Aflou",
    "country": "DZ",
    "subdivision": "25",
    "timezone": "Africa/Algiers"
  },
  "geometry": {
    "type": "Point",
    "coordinates": [
      2.10228,
      34.11279
    ]
  }
}