{
  "type": "Feature",
  "properties": {
    "name": "Bettlach",
    "country": "CH",
    "subdivision": "SO",
    "timezone": "Europe/Zurich"
  },
  "geometry": {
    "type": "Point",
    "coordinates": [
      7.42405,
      47.20062
    ]
  }
}