{
  "type": "Feature",
  "properties": {
    "name": "Langendorf",
    "country": "CH",
    "subdivision": "SO",
    "timezone": "Europe/Zurich"
  },
  "geometry": {
    "type": "Point",
    "coordinates": [
      7.51469,
      47.21974
    ]
  }
}