{
  "type": "Feature",
  "properties": {
    "name": "Niedergösgen",
    "country": "CH",
    "subdivision": "SO",
    "timezone": "Europe/Zurich"
  },
  "geometry": {
    "type": "Point",
    "coordinates": [
      7.98837,
      47.37157
    ]
  }
}