{
  "type": "Feature",
  "properties": {
    "name": "Nunningen",
    "country": "CH",
    "subdivision": "SO",
    "timezone": "Europe/Zurich"
  },
  "geometry": {
    "type": "Point",
    "coordinates": [
      7.61951,
      47.3941
    ]
  }
}