{
  "type": "Feature",
  "properties": {
    "name": "Wolfwil",
    "country": "CH",
    "subdivision": "SO",
    "timezone": "Europe/Zurich"
  },
  "geometry": {
    "type": "Point",
    "coordinates": [
      7.79652,
      47.26871
    ]
  }
}