{
  "type": "Feature",
  "properties": {
    "name": "Alpine",
    "country": "US",
    "subdivision": "CA",
    "timezone": "America/Los_Angeles"
  },
  "geometry": {
    "type": "Point",
    "coordinates": [
      -116.76641,
      32.83505
    ]
  }
}