{
  "type": "Feature",
  "properties": {
    "name": "Altadena",
    "country": "US",
    "subdivision": "CA",
    "timezone": "America/Los_Angeles"
  },
  "geometry": {
    "type": "Point",
    "coordinates": [
      -118.13118,
      34.18973
    ]
  }
}