{
  "type": "Feature",
  "properties": {
    "name": "Angels Camp",
    "country": "US",
    "subdivision": "CA",
    "timezone": "America/Los_Angeles"
  },
  "geometry": {
    "type": "Point",
    "coordinates": [
      -120.53965,
      38.06826
    ]
  }
}