{
  "type": "Feature",
  "properties": {
    "name": "Arbuckle",
    "country": "US",
    "subdivision": "CA",
    "timezone": "America/Los_Angeles"
  },
  "geometry": {
    "type": "Point",
    "coordinates": [
      -122.05775,
      39.0174
    ]
  }
}