{
  "type": "Feature",
  "properties": {
    "name": "Arcata",
    "country": "US",
    "subdivision": "CA",
    "timezone": "America/Los_Angeles"
  },
  "geometry": {
    "type": "Point",
    "coordinates": [
      -124.08284,
      40.86652
    ]
  }
}