{
  "type": "Feature",
  "properties": {
    "name": "Arden-Arcade",
    "country": "US",
    "subdivision": "CA",
    "timezone": "America/Los_Angeles"
  },
  "geometry": {
    "type": "Point",
    "coordinates": [
      -121.37854,
      38.6025
    ]
  }
}