{
  "type": "Feature",
  "properties": {
    "name": "Atascadero",
    "country": "US",
    "subdivision": "CA",
    "timezone": "America/Los_Angeles"
  },
  "geometry": {
    "type": "Point",
    "coordinates": [
      -120.67073,
      35.48942
    ]
  }
}