{
  "type": "Feature",
  "properties": {
    "name": "Auburn",
    "country": "US",
    "subdivision": "CA",
    "timezone": "America/Los_Angeles"
  },
  "geometry": {
    "type": "Point",
    "coordinates": [
      -121.07689,
      38.89657
    ]
  }
}