{
  "type": "Feature",
  "properties": {
    "name": "Avila Beach",
    "country": "US",
    "subdivision": "CA",
    "timezone": "America/Los_Angeles"
  },
  "geometry": {
    "type": "Point",
    "coordinates": [
      -120.73184,
      35.17998
    ]
  }
}