{
  "type": "Feature",
  "properties": {
    "name": "Baldwin Park",
    "country": "US",
    "subdivision": "CA",
    "timezone": "America/Los_Angeles"
  },
  "geometry": {
    "type": "Point",
    "coordinates": [
      -117.9609,
      34.08529
    ]
  }
}