{
  "type": "Feature",
  "properties": {
    "name": "Bell",
    "country": "US",
    "subdivision": "CA",
    "timezone": "America/Los_Angeles"
  },
  "geometry": {
    "type": "Point",
    "coordinates": [
      -118.18702,
      33.97751
    ]
  }
}