{
  "type": "Feature",
  "properties": {
    "name": "Berry Creek",
    "country": "US",
    "subdivision": "CA",
    "timezone": "America/Los_Angeles"
  },
  "geometry": {
    "type": "Point",
    "coordinates": [
      -121.4033,
      39.64516
    ]
  }
}