{
  "type": "Feature",
  "properties": {
    "name": "Blythe",
    "country": "US",
    "subdivision": "CA",
    "timezone": "America/Los_Angeles"
  },
  "geometry": {
    "type": "Point",
    "coordinates": [
      -114.59635,
      33.6103
    ]
  }
}