{
  "type": "Feature",
  "properties": {
    "name": "Bonny Doon",
    "country": "US",
    "subdivision": "CA",
    "timezone": "America/Los_Angeles"
  },
  "geometry": {
    "type": "Point",
    "coordinates": [
      -122.15052,
      37.04162
    ]
  }
}