{
  "type": "Feature",
  "properties": {
    "name": "Bret Harte",
    "country": "US",
    "subdivision": "CA",
    "timezone": "America/Los_Angeles"
  },
  "geometry": {
    "type": "Point",
    "coordinates": [
      -121.00519,
      37.60207
    ]
  }
}