{
  "type": "Feature",
  "properties": {
    "name": "Brookdale",
    "country": "US",
    "subdivision": "CA",
    "timezone": "America/Los_Angeles"
  },
  "geometry": {
    "type": "Point",
    "coordinates": [
      -122.10608,
      37.10634
    ]
  }
}