{
  "type": "Feature",
  "properties": {
    "name": "Calipatria",
    "country": "US",
    "subdivision": "CA",
    "timezone": "America/Los_Angeles"
  },
  "geometry": {
    "type": "Point",
    "coordinates": [
      -115.51415,
      33.1256
    ]
  }
}