{
  "type": "Feature",
  "properties": {
    "name": "Campbell",
    "country": "US",
    "subdivision": "CA",
    "timezone": "America/Los_Angeles"
  },
  "geometry": {
    "type": "Point",
    "coordinates": [
      -121.94996,
      37.28717
    ]
  }
}