{
  "type": "Feature",
  "properties": {
    "name": "Castaic",
    "country": "US",
    "subdivision": "CA",
    "timezone": "America/Los_Angeles"
  },
  "geometry": {
    "type": "Point",
    "coordinates": [
      -118.62287,
      34.48888
    ]
  }
}