{
  "type": "Feature",
  "properties": {
    "name": "Castroville",
    "country": "US",
    "subdivision": "CA",
    "timezone": "America/Los_Angeles"
  },
  "geometry": {
    "type": "Point",
    "coordinates": [
      -121.758,
      36.76579
    ]
  }
}