{
  "type": "Feature",
  "properties": {
    "name": "Cayucos",
    "country": "US",
    "subdivision": "CA",
    "timezone": "America/Los_Angeles"
  },
  "geometry": {
    "type": "Point",
    "coordinates": [
      -120.89213,
      35.44275
    ]
  }
}