{
  "type": "Feature",
  "properties": {
    "name": "Chualar",
    "country": "US",
    "subdivision": "CA",
    "timezone": "America/Los_Angeles"
  },
  "geometry": {
    "type": "Point",
    "coordinates": [
      -121.51855,
      36.57052
    ]
  }
}