{
  "type": "Feature",
  "properties": {
    "name": "Chula Vista",
    "country": "US",
    "subdivision": "CA",
    "timezone": "America/Los_Angeles"
  },
  "geometry": {
    "type": "Point",
    "coordinates": [
      -117.0842,
      32.64005
    ]
  }
}