{
  "type": "Feature",
  "properties": {
    "name": "Clayton",
    "country": "US",
    "subdivision": "CA",
    "timezone": "America/Los_Angeles"
  },
  "geometry": {
    "type": "Point",
    "coordinates": [
      -121.93579,
      37.94103
    ]
  }
}