{
  "type": "Feature",
  "properties": {
    "name": "Contra Costa Centre",
    "country": "US",
    "subdivision": "CA",
    "timezone": "America/Los_Angeles"
  },
  "geometry": {
    "type": "Point",
    "coordinates": [
      -122.05786,
      37.92752
    ]
  }
}