{
  "type": "Feature",
  "properties": {
    "name": "Corralitos",
    "country": "US",
    "subdivision": "CA",
    "timezone": "America/Los_Angeles"
  },
  "geometry": {
    "type": "Point",
    "coordinates": [
      -121.80634,
      36.98856
    ]
  }
}