{
  "type": "Feature",
  "properties": {
    "name": "Descanso",
    "country": "US",
    "subdivision": "CA",
    "timezone": "America/Los_Angeles"
  },
  "geometry": {
    "type": "Point",
    "coordinates": [
      -116.61585,
      32.85283
    ]
  }
}