{
  "type": "Feature",
  "properties": {
    "name": "Duarte",
    "country": "US",
    "subdivision": "CA",
    "timezone": "America/Los_Angeles"
  },
  "geometry": {
    "type": "Point",
    "coordinates": [
      -117.97729,
      34.13945
    ]
  }
}