{
  "type": "Feature",
  "properties": {
    "name": "East Los Angeles",
    "country": "US",
    "subdivision": "CA",
    "timezone": "America/Los_Angeles"
  },
  "geometry": {
    "type": "Point",
    "coordinates": [
      -118.17202,
      34.0239
    ]
  }
}