{
  "type": "Feature",
  "properties": {
    "name": "East Hemet",
    "country": "US",
    "subdivision": "CA",
    "timezone": "America/Los_Angeles"
  },
  "geometry": {
    "type": "Point",
    "coordinates": [
      -116.93891,
      33.74002
    ]
  }
}