{
  "type": "Feature",
  "properties": {
    "name": "El Centro",
    "country": "US",
    "subdivision": "CA",
    "timezone": "America/Los_Angeles"
  },
  "geometry": {
    "type": "Point",
    "coordinates": [
      -115.56305,
      32.792
    ]
  }
}