{
  "type": "Feature",
  "properties": {
    "name": "El Cerrito",
    "country": "US",
    "subdivision": "CA",
    "timezone": "America/Los_Angeles"
  },
  "geometry": {
    "type": "Point",
    "coordinates": [
      -122.31164,
      37.91576
    ]
  }
}