{
  "type": "Feature",
  "properties": {
    "name": "Escalon",
    "country": "US",
    "subdivision": "CA",
    "timezone": "America/Los_Angeles"
  },
  "geometry": {
    "type": "Point",
    "coordinates": [
      -120.99792,
      37.79781
    ]
  }
}