{
  "type": "Feature",
  "properties": {
    "name": "Escondido",
    "country": "US",
    "subdivision": "CA",
    "timezone": "America/Los_Angeles"
  },
  "geometry": {
    "type": "Point",
    "coordinates": [
      -117.08642,
      33.11921
    ]
  }
}