{
  "type": "Feature",
  "properties": {
    "name": "Eucalyptus Hills",
    "country": "US",
    "subdivision": "CA",
    "timezone": "America/Los_Angeles"
  },
  "geometry": {
    "type": "Point",
    "coordinates": [
      -116.94669,
      32.87977
    ]
  }
}