{
  "type": "Feature",
  "properties": {
    "name": "Exeter",
    "country": "US",
    "subdivision": "CA",
    "timezone": "America/Los_Angeles"
  },
  "geometry": {
    "type": "Point",
    "coordinates": [
      -119.14205,
      36.29606
    ]
  }
}