{
  "type": "Feature",
  "properties": {
    "name": "Fairview",
    "country": "US",
    "subdivision": "CA",
    "timezone": "America/Los_Angeles"
  },
  "geometry": {
    "type": "Point",
    "coordinates": [
      -122.0458,
      37.67854
    ]
  }
}