{
  "type": "Feature",
  "properties": {
    "name": "Fair Oaks",
    "country": "US",
    "subdivision": "CA",
    "timezone": "America/Los_Angeles"
  },
  "geometry": {
    "type": "Point",
    "coordinates": [
      -121.27217,
      38.64463
    ]
  }
}