{
  "type": "Feature",
  "properties": {
    "name": "Foothill Ranch",
    "country": "US",
    "subdivision": "CA",
    "timezone": "America/Los_Angeles"
  },
  "geometry": {
    "type": "Point",
    "coordinates": [
      -117.66088,
      33.68641
    ]
  }
}