{
  "type": "Feature",
  "properties": {
    "name": "Forest Ranch",
    "country": "US",
    "subdivision": "CA",
    "timezone": "America/Los_Angeles"
  },
  "geometry": {
    "type": "Point",
    "coordinates": [
      -121.67275,
      39.88211
    ]
  }
}