{
  "type": "Feature",
  "properties": {
    "name": "Freedom",
    "country": "US",
    "subdivision": "CA",
    "timezone": "America/Los_Angeles"
  },
  "geometry": {
    "type": "Point",
    "coordinates": [
      -121.77301,
      36.93523
    ]
  }
}