{
  "type": "Feature",
  "properties": {
    "name": "Garnet",
    "country": "US",
    "subdivision": "CA",
    "timezone": "America/Los_Angeles"
  },
  "geometry": {
    "type": "Point",
    "coordinates": [
      -116.54557,
      33.90196
    ]
  }
}