{
  "type": "Feature",
  "properties": {
    "name": "Georgetown",
    "country": "US",
    "subdivision": "CA",
    "timezone": "America/Los_Angeles"
  },
  "geometry": {
    "type": "Point",
    "coordinates": [
      -120.83855,
      38.90684
    ]
  }
}