{
  "type": "Feature",
  "properties": {
    "name": "Glen Avon",
    "country": "US",
    "subdivision": "CA",
    "timezone": "America/Los_Angeles"
  },
  "geometry": {
    "type": "Point",
    "coordinates": [
      -117.48477,
      34.01168
    ]
  }
}