{
  "type": "Feature",
  "properties": {
    "name": "Glendale",
    "country": "US",
    "subdivision": "CA",
    "timezone": "America/Los_Angeles"
  },
  "geometry": {
    "type": "Point",
    "coordinates": [
      -118.25508,
      34.14251
    ]
  }
}