{
  "type": "Feature",
  "properties": {
    "name": "Greenville",
    "country": "US",
    "subdivision": "CA",
    "timezone": "America/Los_Angeles"
  },
  "geometry": {
    "type": "Point",
    "coordinates": [
      -120.95107,
      40.13961
    ]
  }
}