{
  "type": "Feature",
  "properties": {
    "name": "Gustine",
    "country": "US",
    "subdivision": "CA",
    "timezone": "America/Los_Angeles"
  },
  "geometry": {
    "type": "Point",
    "coordinates": [
      -120.99882,
      37.25772
    ]
  }
}