{
  "type": "Feature",
  "properties": {
    "name": "Harbison Canyon",
    "country": "US",
    "subdivision": "CA",
    "timezone": "America/Los_Angeles"
  },
  "geometry": {
    "type": "Point",
    "coordinates": [
      -116.83002,
      32.82033
    ]
  }
}