{
  "type": "Feature",
  "properties": {
    "name": "Herald",
    "country": "US",
    "subdivision": "CA",
    "timezone": "America/Los_Angeles"
  },
  "geometry": {
    "type": "Point",
    "coordinates": [
      -121.24439,
      38.29575
    ]
  }
}