{
  "type": "Feature",
  "properties": {
    "name": "Hesperia",
    "country": "US",
    "subdivision": "CA",
    "timezone": "America/Los_Angeles"
  },
  "geometry": {
    "type": "Point",
    "coordinates": [
      -117.30088,
      34.42639
    ]
  }
}