{
  "type": "Feature",
  "properties": {
    "name": "Humboldt Hill",
    "country": "US",
    "subdivision": "CA",
    "timezone": "America/Los_Angeles"
  },
  "geometry": {
    "type": "Point",
    "coordinates": [
      -124.18978,
      40.72596
    ]
  }
}