{
  "type": "Feature",
  "properties": {
    "name": "Isla Vista",
    "country": "US",
    "subdivision": "CA",
    "timezone": "America/Los_Angeles"
  },
  "geometry": {
    "type": "Point",
    "coordinates": [
      -119.86097,
      34.41333
    ]
  }
}