{
  "type": "Feature",
  "properties": {
    "name": "Jamul",
    "country": "US",
    "subdivision": "CA",
    "timezone": "America/Los_Angeles"
  },
  "geometry": {
    "type": "Point",
    "coordinates": [
      -116.87613,
      32.717
    ]
  }
}