{
  "type": "Feature",
  "properties": {
    "name": "Kenwood",
    "country": "US",
    "subdivision": "CA",
    "timezone": "America/Los_Angeles"
  },
  "geometry": {
    "type": "Point",
    "coordinates": [
      -122.54609,
      38.4138
    ]
  }
}