{
  "type": "Feature",
  "properties": {
    "name": "Knightsen",
    "country": "US",
    "subdivision": "CA",
    "timezone": "America/Los_Angeles"
  },
  "geometry": {
    "type": "Point",
    "coordinates": [
      -121.66801,
      37.96881
    ]
  }
}