{
  "type": "Feature",
  "properties": {
    "name": "Ladera Heights",
    "country": "US",
    "subdivision": "CA",
    "timezone": "America/Los_Angeles"
  },
  "geometry": {
    "type": "Point",
    "coordinates": [
      -118.37535,
      33.99418
    ]
  }
}