{
  "type": "Feature",
  "properties": {
    "name": "Lafayette",
    "country": "US",
    "subdivision": "CA",
    "timezone": "America/Los_Angeles"
  },
  "geometry": {
    "type": "Point",
    "coordinates": [
      -122.11802,
      37.88576
    ]
  }
}