{
  "type": "Feature",
  "properties": {
    "name": "Lake Nacimiento",
    "country": "US",
    "subdivision": "CA",
    "timezone": "America/Los_Angeles"
  },
  "geometry": {
    "type": "Point",
    "coordinates": [
      -120.87963,
      35.7283
    ]
  }
}