{
  "type": "Feature",
  "properties": {
    "name": "Lakeside",
    "country": "US",
    "subdivision": "CA",
    "timezone": "America/Los_Angeles"
  },
  "geometry": {
    "type": "Point",
    "coordinates": [
      -116.92225,
      32.85727
    ]
  }
}