{
  "type": "Feature",
  "properties": {
    "name": "Lodi",
    "country": "US",
    "subdivision": "CA",
    "timezone": "America/Los_Angeles"
  },
  "geometry": {
    "type": "Point",
    "coordinates": [
      -121.27245,
      38.1302
    ]
  }
}