{
  "type": "Feature",
  "properties": {
    "name": "Loma Linda",
    "country": "US",
    "subdivision": "CA",
    "timezone": "America/Los_Angeles"
  },
  "geometry": {
    "type": "Point",
    "coordinates": [
      -117.26115,
      34.04835
    ]
  }
}