{
  "type": "Feature",
  "properties": {
    "name": "Lomita",
    "country": "US",
    "subdivision": "CA",
    "timezone": "America/Los_Angeles"
  },
  "geometry": {
    "type": "Point",
    "coordinates": [
      -118.31507,
      33.79224
    ]
  }
}