{
  "type": "Feature",
  "properties": {
    "name": "Los Gatos",
    "country": "US",
    "subdivision": "CA",
    "timezone": "America/Los_Angeles"
  },
  "geometry": {
    "type": "Point",
    "coordinates": [
      -121.97468,
      37.22661
    ]
  }
}