{
  "type": "Feature",
  "properties": {
    "name": "Los Alamitos",
    "country": "US",
    "subdivision": "CA",
    "timezone": "America/Los_Angeles"
  },
  "geometry": {
    "type": "Point",
    "coordinates": [
      -118.07256,
      33.80307
    ]
  }
}