{
  "type": "Feature",
  "properties": {
    "name": "Lost Hills",
    "country": "US",
    "subdivision": "CA",
    "timezone": "America/Los_Angeles"
  },
  "geometry": {
    "type": "Point",
    "coordinates": [
      -119.69429,
      35.61635
    ]
  }
}