{
  "type": "Feature",
  "properties": {
    "name": "Marysville",
    "country": "US",
    "subdivision": "CA",
    "timezone": "America/Los_Angeles"
  },
  "geometry": {
    "type": "Point",
    "coordinates": [
      -121.59135,
      39.14573
    ]
  }
}