{
  "type": "Feature",
  "properties": {
    "name": "Menifee",
    "country": "US",
    "subdivision": "CA",
    "timezone": "America/Los_Angeles"
  },
  "geometry": {
    "type": "Point",
    "coordinates": [
      -117.14642,
      33.72835
    ]
  }
}