{
  "type": "Feature",
  "properties": {
    "name": "Midway City",
    "country": "US",
    "subdivision": "CA",
    "timezone": "America/Los_Angeles"
  },
  "geometry": {
    "type": "Point",
    "coordinates": [
      -117.98923,
      33.74474
    ]
  }
}