{
  "type": "Feature",
  "properties": {
    "name": "Minkler",
    "country": "US",
    "subdivision": "CA",
    "timezone": "America/Los_Angeles"
  },
  "geometry": {
    "type": "Point",
    "coordinates": [
      -119.45818,
      36.72384
    ]
  }
}