{
  "type": "Feature",
  "properties": {
    "name": "Mono Vista",
    "country": "US",
    "subdivision": "CA",
    "timezone": "America/Los_Angeles"
  },
  "geometry": {
    "type": "Point",
    "coordinates": [
      -120.26991,
      37.9977
    ]
  }
}