{
  "type": "Feature",
  "properties": {
    "name": "Montecito",
    "country": "US",
    "subdivision": "CA",
    "timezone": "America/Los_Angeles"
  },
  "geometry": {
    "type": "Point",
    "coordinates": [
      -119.63208,
      34.43666
    ]
  }
}