{
  "type": "Feature",
  "properties": {
    "name": "Moorpark",
    "country": "US",
    "subdivision": "CA",
    "timezone": "America/Los_Angeles"
  },
  "geometry": {
    "type": "Point",
    "coordinates": [
      -118.88204,
      34.28556
    ]
  }
}