{
  "type": "Feature",
  "properties": {
    "name": "Moraga",
    "country": "US",
    "subdivision": "CA",
    "timezone": "America/Los_Angeles"
  },
  "geometry": {
    "type": "Point",
    "coordinates": [
      -122.12969,
      37.83493
    ]
  }
}