{
  "type": "Feature",
  "properties": {
    "name": "North Hills",
    "country": "US",
    "subdivision": "CA",
    "timezone": "America/Los_Angeles"
  },
  "geometry": {
    "type": "Point",
    "coordinates": [
      -118.48472,
      34.23639
    ]
  }
}