{
  "type": "Feature",
  "properties": {
    "name": "Oakley",
    "country": "US",
    "subdivision": "CA",
    "timezone": "America/Los_Angeles"
  },
  "geometry": {
    "type": "Point",
    "coordinates": [
      -121.71245,
      37.99742
    ]
  }
}