{
  "type": "Feature",
  "properties": {
    "name": "Ontario",
    "country": "US",
    "subdivision": "CA",
    "timezone": "America/Los_Angeles"
  },
  "geometry": {
    "type": "Point",
    "coordinates": [
      -117.65089,
      34.06334
    ]
  }
}