{
  "type": "Feature",
  "properties": {
    "name": "Orosi",
    "country": "US",
    "subdivision": "CA",
    "timezone": "America/Los_Angeles"
  },
  "geometry": {
    "type": "Point",
    "coordinates": [
      -119.28734,
      36.54495
    ]
  }
}