{
  "type": "Feature",
  "properties": {
    "name": "Pacheco",
    "country": "US",
    "subdivision": "CA",
    "timezone": "America/Los_Angeles"
  },
  "geometry": {
    "type": "Point",
    "coordinates": [
      -122.07524,
      37.98353
    ]
  }
}