{
  "type": "Feature",
  "properties": {
    "name": "Palm Desert",
    "country": "US",
    "subdivision": "CA",
    "timezone": "America/Los_Angeles"
  },
  "geometry": {
    "type": "Point",
    "coordinates": [
      -116.37697,
      33.72255
    ]
  }
}