{
  "type": "Feature",
  "properties": {
    "name": "Palmdale",
    "country": "US",
    "subdivision": "CA",
    "timezone": "America/Los_Angeles"
  },
  "geometry": {
    "type": "Point",
    "coordinates": [
      -118.11646,
      34.57943
    ]
  }
}