{
  "type": "Feature",
  "properties": {
    "name": "Paramount",
    "country": "US",
    "subdivision": "CA",
    "timezone": "America/Los_Angeles"
  },
  "geometry": {
    "type": "Point",
    "coordinates": [
      -118.15979,
      33.88946
    ]
  }
}