{
  "type": "Feature",
  "properties": {
    "name": "Patterson Tract",
    "country": "US",
    "subdivision": "CA",
    "timezone": "America/Los_Angeles"
  },
  "geometry": {
    "type": "Point",
    "coordinates": [
      -119.2956,
      36.37952
    ]
  }
}