{
  "type": "Feature",
  "properties": {
    "name": "Pico Rivera",
    "country": "US",
    "subdivision": "CA",
    "timezone": "America/Los_Angeles"
  },
  "geometry": {
    "type": "Point",
    "coordinates": [
      -118.09673,
      33.98307
    ]
  }
}