{
  "type": "Feature",
  "properties": {
    "name": "Pollock Pines",
    "country": "US",
    "subdivision": "CA",
    "timezone": "America/Los_Angeles"
  },
  "geometry": {
    "type": "Point",
    "coordinates": [
      -120.58611,
      38.76158
    ]
  }
}