{
  "type": "Feature",
  "properties": {
    "name": "Prunedale",
    "country": "US",
    "subdivision": "CA",
    "timezone": "America/Los_Angeles"
  },
  "geometry": {
    "type": "Point",
    "coordinates": [
      -121.66967,
      36.77579
    ]
  }
}