{
  "type": "Feature",
  "properties": {
    "name": "Ridgecrest",
    "country": "US",
    "subdivision": "CA",
    "timezone": "America/Los_Angeles"
  },
  "geometry": {
    "type": "Point",
    "coordinates": [
      -117.6709,
      35.62246
    ]
  }
}