{
  "type": "Feature",
  "properties": {
    "name": "Rodeo",
    "country": "US",
    "subdivision": "CA",
    "timezone": "America/Los_Angeles"
  },
  "geometry": {
    "type": "Point",
    "coordinates": [
      -122.26691,
      38.03298
    ]
  }
}