{
  "type": "Feature",
  "properties": {
    "name": "Rolling Hills Estates",
    "country": "US",
    "subdivision": "CA",
    "timezone": "America/Los_Angeles"
  },
  "geometry": {
    "type": "Point",
    "coordinates": [
      -118.35813,
      33.78779
    ]
  }
}