{
  "type": "Feature",
  "properties": {
    "name": "Sacramento",
    "country": "US",
    "subdivision": "CA",
    "timezone": "America/Los_Angeles"
  },
  "geometry": {
    "type": "Point",
    "coordinates": [
      -121.4944,
      38.58157
    ]
  }
}