{
  "type": "Feature",
  "properties": {
    "name": "San Juan Bautista",
    "country": "US",
    "subdivision": "CA",
    "timezone": "America/Los_Angeles"
  },
  "geometry": {
    "type": "Point",
    "coordinates": [
      -121.538,
      36.84551
    ]
  }
}