{
  "type": "Feature",
  "properties": {
    "name": "San Juan Capistrano",
    "country": "US",
    "subdivision": "CA",
    "timezone": "America/Los_Angeles"
  },
  "geometry": {
    "type": "Point",
    "coordinates": [
      -117.66255,
      33.50169
    ]
  }
}