{
  "type": "Feature",
  "properties": {
    "name": "San Andreas",
    "country": "US",
    "subdivision": "CA",
    "timezone": "America/Los_Angeles"
  },
  "geometry": {
    "type": "Point",
    "coordinates": [
      -120.68049,
      38.19603
    ]
  }
}