{
  "type": "Feature",
  "properties": {
    "name": "San Diego",
    "country": "US",
    "subdivision": "CA",
    "timezone": "America/Los_Angeles"
  },
  "geometry": {
    "type": "Point",
    "coordinates": [
      -117.16472,
      32.71571
    ]
  }
}