{
  "type": "Feature",
  "properties": {
    "name": "Searles Valley",
    "country": "US",
    "subdivision": "CA",
    "timezone": "America/Los_Angeles"
  },
  "geometry": {
    "type": "Point",
    "coordinates": [
      -117.40395,
      35.76745
    ]
  }
}