{
  "type": "Feature",
  "properties": {
    "name": "Sherman Oaks",
    "country": "US",
    "subdivision": "CA",
    "timezone": "America/Los_Angeles"
  },
  "geometry": {
    "type": "Point",
    "coordinates": [
      -118.44925,
      34.15112
    ]
  }
}