{
  "type": "Feature",
  "properties": {
    "name": "Sleepy Hollow",
    "country": "US",
    "subdivision": "CA",
    "timezone": "America/Los_Angeles"
  },
  "geometry": {
    "type": "Point",
    "coordinates": [
      -122.58442,
      38.01048
    ]
  }
}