{
  "type": "Feature",
  "properties": {
    "name": "South Taft",
    "country": "US",
    "subdivision": "CA",
    "timezone": "America/Los_Angeles"
  },
  "geometry": {
    "type": "Point",
    "coordinates": [
      -119.45623,
      35.13469
    ]
  }
}