{
  "type": "Feature",
  "properties": {
    "name": "Stevenson Ranch",
    "country": "US",
    "subdivision": "CA",
    "timezone": "America/Los_Angeles"
  },
  "geometry": {
    "type": "Point",
    "coordinates": [
      -118.57372,
      34.39048
    ]
  }
}