{
  "type": "Feature",
  "properties": {
    "name": "Strathmore",
    "country": "US",
    "subdivision": "CA",
    "timezone": "America/Los_Angeles"
  },
  "geometry": {
    "type": "Point",
    "coordinates": [
      -119.06066,
      36.14551
    ]
  }
}