{
  "type": "Feature",
  "properties": {
    "name": "Strawberry",
    "country": "US",
    "subdivision": "CA",
    "timezone": "America/Los_Angeles"
  },
  "geometry": {
    "type": "Point",
    "coordinates": [
      -122.50886,
      37.89687
    ]
  }
}