{
  "type": "Feature",
  "properties": {
    "name": "Talmage",
    "country": "US",
    "subdivision": "CA",
    "timezone": "America/Los_Angeles"
  },
  "geometry": {
    "type": "Point",
    "coordinates": [
      -123.16778,
      39.13323
    ]
  }
}