{
  "type": "Feature",
  "properties": {
    "name": "Tamalpais-Homestead Valley",
    "country": "US",
    "subdivision": "CA",
    "timezone": "America/Los_Angeles"
  },
  "geometry": {
    "type": "Point",
    "coordinates": [
      -122.53625,
      37.87834
    ]
  }
}