{
  "type": "Feature",
  "properties": {
    "name": "Tara Hills",
    "country": "US",
    "subdivision": "CA",
    "timezone": "America/Los_Angeles"
  },
  "geometry": {
    "type": "Point",
    "coordinates": [
      -122.31636,
      37.99353
    ]
  }
}