{
  "type": "Feature",
  "properties": {
    "name": "Tehachapi",
    "country": "US",
    "subdivision": "CA",
    "timezone": "America/Los_Angeles"
  },
  "geometry": {
    "type": "Point",
    "coordinates": [
      -118.44897,
      35.13219
    ]
  }
}