{
  "type": "Feature",
  "properties": {
    "name": "Temple City",
    "country": "US",
    "subdivision": "CA",
    "timezone": "America/Los_Angeles"
  },
  "geometry": {
    "type": "Point",
    "coordinates": [
      -118.05785,
      34.10723
    ]
  }
}