{
  "type": "Feature",
  "properties": {
    "name": "Three Rivers",
    "country": "US",
    "subdivision": "CA",
    "timezone": "America/Los_Angeles"
  },
  "geometry": {
    "type": "Point",
    "coordinates": [
      -118.90454,
      36.43884
    ]
  }
}