{
  "type": "Feature",
  "properties": {
    "name": "Toro Canyon",
    "country": "US",
    "subdivision": "CA",
    "timezone": "America/Los_Angeles"
  },
  "geometry": {
    "type": "Point",
    "coordinates": [
      -119.56707,
      34.42
    ]
  }
}