{
  "type": "Feature",
  "properties": {
    "name": "Twain Harte",
    "country": "US",
    "subdivision": "CA",
    "timezone": "America/Los_Angeles"
  },
  "geometry": {
    "type": "Point",
    "coordinates": [
      -120.23269,
      38.03965
    ]
  }
}