{
  "type": "Feature",
  "properties": {
    "name": "Villa Park",
    "country": "US",
    "subdivision": "CA",
    "timezone": "America/Los_Angeles"
  },
  "geometry": {
    "type": "Point",
    "coordinates": [
      -117.81311,
      33.81446
    ]
  }
}