{
  "type": "Feature",
  "properties": {
    "name": "Vista",
    "country": "US",
    "subdivision": "CA",
    "timezone": "America/Los_Angeles"
  },
  "geometry": {
    "type": "Point",
    "coordinates": [
      -117.24254,
      33.20004
    ]
  }
}