{
  "type": "Feature",
  "properties": {
    "name": "Waterford",
    "country": "US",
    "subdivision": "CA",
    "timezone": "America/Los_Angeles"
  },
  "geometry": {
    "type": "Point",
    "coordinates": [
      -120.76048,
      37.64132
    ]
  }
}