{
  "type": "Feature",
  "properties": {
    "name": "Willowbrook",
    "country": "US",
    "subdivision": "CA",
    "timezone": "America/Los_Angeles"
  },
  "geometry": {
    "type": "Point",
    "coordinates": [
      -118.25507,
      33.91696
    ]
  }
}