{
  "type": "Feature",
  "properties": {
    "name": "Winter Gardens",
    "country": "US",
    "subdivision": "CA",
    "timezone": "America/Los_Angeles"
  },
  "geometry": {
    "type": "Point",
    "coordinates": [
      -116.93336,
      32.83116
    ]
  }
}