{
  "type": "Feature",
  "properties": {
    "name": "Woodbridge",
    "country": "US",
    "subdivision": "CA",
    "timezone": "America/Los_Angeles"
  },
  "geometry": {
    "type": "Point",
    "coordinates": [
      -121.30134,
      38.15408
    ]
  }
}