{
  "type": "Feature",
  "properties": {
    "name": "Woodville",
    "country": "US",
    "subdivision": "CA",
    "timezone": "America/Los_Angeles"
  },
  "geometry": {
    "type": "Point",
    "coordinates": [
      -119.199,
      36.09356
    ]
  }
}