{
  "type": "Feature",
  "properties": {
    "name": "Woodlake",
    "country": "US",
    "subdivision": "CA",
    "timezone": "America/Los_Angeles"
  },
  "geometry": {
    "type": "Point",
    "coordinates": [
      -119.09872,
      36.41356
    ]
  }
}