{
  "type": "Feature",
  "properties": {
    "name": "Svodín",
    "country": "SK",
    "subdivision": "04",
    "timezone": "Europe/Bratislava"
  },
  "geometry": {
    "type": "Point",
    "coordinates": [
      18.49967,
      47.91054
    ]
  }
}