{
  "type": "Feature",
  "properties": {
    "name": "L-Iklin",
    "country": "MT",
    "subdivision": "19",
    "timezone": "Europe/Malta"
  },
  "geometry": {
    "type": "Point",
    "coordinates": [
      14.45415,
      35.90414
    ]
  }
}