{
  "type": "Feature",
  "properties": {
    "name": "Östersund",
    "country": "SE",
    "subdivision": "07",
    "timezone": "Europe/Stockholm"
  },
  "geometry": {
    "type": "Point",
    "coordinates": [
      14.63566,
      63.1792
    ]
  }
}