{
  "type": "Feature",
  "properties": {
    "name": "Sveg",
    "country": "SE",
    "subdivision": "07",
    "timezone": "Europe/Stockholm"
  },
  "geometry": {
    "type": "Point",
    "coordinates": [
      14.36577,
      62.03407
    ]
  }
}