{
  "type": "Feature",
  "properties": {
    "name": "Elvas",
    "country": "PT",
    "subdivision": "16",
    "timezone": "Europe/Lisbon"
  },
  "geometry": {
    "type": "Point",
    "coordinates": [
      -7.16282,
      38.8815
    ]
  }
}