{
  "type": "Feature",
  "properties": {
    "name": "Marvão",
    "country": "PT",
    "subdivision": "16",
    "timezone": "Europe/Lisbon"
  },
  "geometry": {
    "type": "Point",
    "coordinates": [
      -7.37663,
      39.39377
    ]
  }
}