{
  "type": "Feature",
  "properties": {
    "name": "Nisa",
    "country": "PT",
    "subdivision": "16",
    "timezone": "Europe/Lisbon"
  },
  "geometry": {
    "type": "Point",
    "coordinates": [
      -7.64908,
      39.51499
    ]
  }
}