{
  "type": "Feature",
  "properties": {
    "name": "Aubin Grove",
    "country": "AU",
    "subdivision": "08",
    "timezone": "Australia/Perth"
  },
  "geometry": {
    "type": "Point",
    "coordinates": [
      115.86264,
      -32.16714
    ]
  }
}