{
  "type": "Feature",
  "properties": {
    "name": "Beresford",
    "country": "AU",
    "subdivision": "08",
    "timezone": "Australia/Perth"
  },
  "geometry": {
    "type": "Point",
    "coordinates": [
      114.61965,
      -28.75754
    ]
  }
}