{
  "type": "Feature",
  "properties": {
    "name": "Bertram",
    "country": "AU",
    "subdivision": "08",
    "timezone": "Australia/Perth"
  },
  "geometry": {
    "type": "Point",
    "coordinates": [
      115.84572,
      -32.24369
    ]
  }
}