{
  "type": "Feature",
  "properties": {
    "name": "Brunswick",
    "country": "AU",
    "subdivision": "08",
    "timezone": "Australia/Perth"
  },
  "geometry": {
    "type": "Point",
    "coordinates": [
      115.86282,
      -33.2324
    ]
  }
}