{
  "type": "Feature",
  "properties": {
    "name": "Connolly",
    "country": "AU",
    "subdivision": "08",
    "timezone": "Australia/Perth"
  },
  "geometry": {
    "type": "Point",
    "coordinates": [
      115.75053,
      -31.74864
    ]
  }
}