{
  "type": "Feature",
  "properties": {
    "name": "Currambine",
    "country": "AU",
    "subdivision": "08",
    "timezone": "Australia/Perth"
  },
  "geometry": {
    "type": "Point",
    "coordinates": [
      115.74766,
      -31.73306
    ]
  }
}