{
  "type": "Feature",
  "properties": {
    "name": "Eaton",
    "country": "AU",
    "subdivision": "08",
    "timezone": "Australia/Perth"
  },
  "geometry": {
    "type": "Point",
    "coordinates": [
      115.70503,
      -33.31664
    ]
  }
}