{
  "type": "Feature",
  "properties": {
    "name": "Ellenbrook",
    "country": "AU",
    "subdivision": "08",
    "timezone": "Australia/Perth"
  },
  "geometry": {
    "type": "Point",
    "coordinates": [
      115.96936,
      -31.76737
    ]
  }
}