{
  "type": "Feature",
  "properties": {
    "name": "Fitzroy Crossing",
    "country": "AU",
    "subdivision": "08",
    "timezone": "Australia/Perth"
  },
  "geometry": {
    "type": "Point",
    "coordinates": [
      125.56663,
      -18.19714
    ]
  }
}