{
  "type": "Feature",
  "properties": {
    "name": "Forrestdale",
    "country": "AU",
    "subdivision": "08",
    "timezone": "Australia/Perth"
  },
  "geometry": {
    "type": "Point",
    "coordinates": [
      115.93417,
      -32.1552
    ]
  }
}