{
  "type": "Feature",
  "properties": {
    "name": "Glendalough",
    "country": "AU",
    "subdivision": "08",
    "timezone": "Australia/Perth"
  },
  "geometry": {
    "type": "Point",
    "coordinates": [
      115.81945,
      -31.91991
    ]
  }
}