{
  "type": "Feature",
  "properties": {
    "name": "Golden Bay",
    "country": "AU",
    "subdivision": "08",
    "timezone": "Australia/Perth"
  },
  "geometry": {
    "type": "Point",
    "coordinates": [
      115.76099,
      -32.42505
    ]
  }
}