{
  "type": "Feature",
  "properties": {
    "name": "Hamilton Hill",
    "country": "AU",
    "subdivision": "08",
    "timezone": "Australia/Perth"
  },
  "geometry": {
    "type": "Point",
    "coordinates": [
      115.77946,
      -32.08451
    ]
  }
}