{
  "type": "Feature",
  "properties": {
    "name": "Hannans",
    "country": "AU",
    "subdivision": "08",
    "timezone": "Australia/Perth"
  },
  "geometry": {
    "type": "Point",
    "coordinates": [
      121.4548,
      -30.71909
    ]
  }
}