{
  "type": "Feature",
  "properties": {
    "name": "Helena Valley",
    "country": "AU",
    "subdivision": "08",
    "timezone": "Australia/Perth"
  },
  "geometry": {
    "type": "Point",
    "coordinates": [
      116.03982,
      -31.91938
    ]
  }
}