{
  "type": "Feature",
  "properties": {
    "name": "Hilton",
    "country": "AU",
    "subdivision": "08",
    "timezone": "Australia/Perth"
  },
  "geometry": {
    "type": "Point",
    "coordinates": [
      115.78049,
      -32.06208
    ]
  }
}