{
  "type": "Feature",
  "properties": {
    "name": "Joondalup",
    "country": "AU",
    "subdivision": "08",
    "timezone": "Australia/Perth"
  },
  "geometry": {
    "type": "Point",
    "coordinates": [
      115.76835,
      -31.74445
    ]
  }
}