{
  "type": "Feature",
  "properties": {
    "name": "Kambalda East",
    "country": "AU",
    "subdivision": "08",
    "timezone": "Australia/Perth"
  },
  "geometry": {
    "type": "Point",
    "coordinates": [
      121.67011,
      -31.2055
    ]
  }
}