{
  "type": "Feature",
  "properties": {
    "name": "Kinross",
    "country": "AU",
    "subdivision": "08",
    "timezone": "Australia/Perth"
  },
  "geometry": {
    "type": "Point",
    "coordinates": [
      115.73839,
      -31.71868
    ]
  }
}