{
  "type": "Feature",
  "properties": {
    "name": "Lathlain",
    "country": "AU",
    "subdivision": "08",
    "timezone": "Australia/Perth"
  },
  "geometry": {
    "type": "Point",
    "coordinates": [
      115.90631,
      -31.96755
    ]
  }
}