{
  "type": "Feature",
  "properties": {
    "name": "Lesmurdie",
    "country": "AU",
    "subdivision": "08",
    "timezone": "Australia/Perth"
  },
  "geometry": {
    "type": "Point",
    "coordinates": [
      116.04821,
      -32.00199
    ]
  }
}