{
  "type": "Feature",
  "properties": {
    "name": "Merredin",
    "country": "AU",
    "subdivision": "08",
    "timezone": "Australia/Perth"
  },
  "geometry": {
    "type": "Point",
    "coordinates": [
      118.27448,
      -31.48094
    ]
  }
}