{
  "type": "Feature",
  "properties": {
    "name": "Middle Swan",
    "country": "AU",
    "subdivision": "08",
    "timezone": "Australia/Perth"
  },
  "geometry": {
    "type": "Point",
    "coordinates": [
      116.01667,
      -31.85
    ]
  }
}