{
  "type": "Feature",
  "properties": {
    "name": "Mira Mar",
    "country": "AU",
    "subdivision": "08",
    "timezone": "Australia/Perth"
  },
  "geometry": {
    "type": "Point",
    "coordinates": [
      117.90096,
      -35.01517
    ]
  }
}