{
  "type": "Feature",
  "properties": {
    "name": "Moora",
    "country": "AU",
    "subdivision": "08",
    "timezone": "Australia/Perth"
  },
  "geometry": {
    "type": "Point",
    "coordinates": [
      116.00365,
      -30.64003
    ]
  }
}