{
  "type": "Feature",
  "properties": {
    "name": "Mullaloo",
    "country": "AU",
    "subdivision": "08",
    "timezone": "Australia/Perth"
  },
  "geometry": {
    "type": "Point",
    "coordinates": [
      115.73676,
      -31.77896
    ]
  }
}