{
  "type": "Feature",
  "properties": {
    "name": "Munster",
    "country": "AU",
    "subdivision": "08",
    "timezone": "Australia/Perth"
  },
  "geometry": {
    "type": "Point",
    "coordinates": [
      115.78302,
      -32.13647
    ]
  }
}