{
  "type": "Feature",
  "properties": {
    "name": "North Lake",
    "country": "AU",
    "subdivision": "08",
    "timezone": "Australia/Perth"
  },
  "geometry": {
    "type": "Point",
    "coordinates": [
      115.83567,
      -32.0819
    ]
  }
}