{
  "type": "Feature",
  "properties": {
    "name": "Nullagine",
    "country": "AU",
    "subdivision": "08",
    "timezone": "Australia/Perth"
  },
  "geometry": {
    "type": "Point",
    "coordinates": [
      120.1114,
      -21.88972
    ]
  }
}