{
  "type": "Feature",
  "properties": {
    "name": "Piara Waters",
    "country": "AU",
    "subdivision": "08",
    "timezone": "Australia/Perth"
  },
  "geometry": {
    "type": "Point",
    "coordinates": [
      115.91634,
      -32.13344
    ]
  }
}