{
  "type": "Feature",
  "properties": {
    "name": "Roebuck",
    "country": "AU",
    "subdivision": "08",
    "timezone": "Australia/Perth"
  },
  "geometry": {
    "type": "Point",
    "coordinates": [
      122.50116,
      -18.1713
    ]
  }
}