{
  "type": "Feature",
  "properties": {
    "name": "Salter Point",
    "country": "AU",
    "subdivision": "08",
    "timezone": "Australia/Perth"
  },
  "geometry": {
    "type": "Point",
    "coordinates": [
      115.86582,
      -32.02384
    ]
  }
}