{
  "type": "Feature",
  "properties": {
    "name": "Samson",
    "country": "AU",
    "subdivision": "08",
    "timezone": "Australia/Perth"
  },
  "geometry": {
    "type": "Point",
    "coordinates": [
      115.7977,
      -32.06996
    ]
  }
}