{
  "type": "Feature",
  "properties": {
    "name": "Silver Sands",
    "country": "AU",
    "subdivision": "08",
    "timezone": "Australia/Perth"
  },
  "geometry": {
    "type": "Point",
    "coordinates": [
      115.73599,
      -32.50857
    ]
  }
}