{
  "type": "Feature",
  "properties": {
    "name": "South Fremantle",
    "country": "AU",
    "subdivision": "08",
    "timezone": "Australia/Perth"
  },
  "geometry": {
    "type": "Point",
    "coordinates": [
      115.75453,
      -32.06907
    ]
  }
}