{
  "type": "Feature",
  "properties": {
    "name": "South Hedland",
    "country": "AU",
    "subdivision": "08",
    "timezone": "Australia/Perth"
  },
  "geometry": {
    "type": "Point",
    "coordinates": [
      118.60069,
      -20.40655
    ]
  }
}