{
  "type": "Feature",
  "properties": {
    "name": "South Yunderup",
    "country": "AU",
    "subdivision": "08",
    "timezone": "Australia/Perth"
  },
  "geometry": {
    "type": "Point",
    "coordinates": [
      115.78015,
      -32.5851
    ]
  }
}