{
  "type": "Feature",
  "properties": {
    "name": "West Lamington",
    "country": "AU",
    "subdivision": "08",
    "timezone": "Australia/Perth"
  },
  "geometry": {
    "type": "Point",
    "coordinates": [
      121.45248,
      -30.74707
    ]
  }
}