{
  "type": "Feature",
  "properties": {
    "name": "West Busselton",
    "country": "AU",
    "subdivision": "08",
    "timezone": "Australia/Perth"
  },
  "geometry": {
    "type": "Point",
    "coordinates": [
      115.32293,
      -33.65792
    ]
  }
}