{
  "type": "Feature",
  "properties": {
    "name": "Arboledas",
    "country": "CO",
    "subdivision": "21",
    "timezone": "America/Bogota"
  },
  "geometry": {
    "type": "Point",
    "coordinates": [
      -72.79944,
      7.64233
    ]
  }
}