{
  "type": "Feature",
  "properties": {
    "name": "Cúcuta",
    "country": "CO",
    "subdivision": "21",
    "timezone": "America/Bogota"
  },
  "geometry": {
    "type": "Point",
    "coordinates": [
      -72.50782,
      7.89391
    ]
  }
}