{
  "type": "Feature",
  "properties": {
    "name": "Puerto Santander",
    "country": "CO",
    "subdivision": "21",
    "timezone": "America/Bogota"
  },
  "geometry": {
    "type": "Point",
    "coordinates": [
      -72.4063,
      8.36361
    ]
  }
}