{
  "type": "Feature",
  "properties": {
    "name": "La Guata",
    "country": "HN",
    "subdivision": "15",
    "timezone": "America/Tegucigalpa"
  },
  "geometry": {
    "type": "Point",
    "coordinates": [
      -86.38333,
      15.08333
    ]
  }
}