{
  "type": "Feature",
  "properties": {
    "name": "Hadano",
    "country": "JP",
    "subdivision": "19",
    "timezone": "Asia/Tokyo"
  },
  "geometry": {
    "type": "Point",
    "coordinates": [
      139.22361,
      35.37111
    ]
  }
}