{
  "type": "Feature",
  "properties": {
    "name": "Hiratsuka",
    "country": "JP",
    "subdivision": "19",
    "timezone": "Asia/Tokyo"
  },
  "geometry": {
    "type": "Point",
    "coordinates": [
      139.33735,
      35.32785
    ]
  }
}