{
  "type": "Feature",
  "properties": {
    "name": "Zemen",
    "country": "BG",
    "subdivision": "49",
    "timezone": "Europe/Sofia"
  },
  "geometry": {
    "type": "Point",
    "coordinates": [
      22.74917,
      42.47889
    ]
  }
}