{
  "type": "Feature",
  "properties": {
    "name": "Amreli",
    "country": "IN",
    "subdivision": "09",
    "timezone": "Asia/Kolkata"
  },
  "geometry": {
    "type": "Point",
    "coordinates": [
      71.21169,
      21.59983
    ]
  }
}