{
  "type": "Feature",
  "properties": {
    "name": "BÄrdoli",
    "country": "IN",
    "subdivision": "09",
    "timezone": "Asia/Kolkata"
  },
  "geometry": {
    "type": "Point",
    "coordinates": [
      73.11151,
      21.12297
    ]
  }
}