{
  "type": "Feature",
  "properties": {
    "name": "BhachÄu",
    "country": "IN",
    "subdivision": "09",
    "timezone": "Asia/Kolkata"
  },
  "geometry": {
    "type": "Point",
    "coordinates": [
      70.34279,
      23.29858
    ]
  }
}