{
  "type": "Feature",
  "properties": {
    "name": "BhÄnvad",
    "country": "IN",
    "subdivision": "09",
    "timezone": "Asia/Kolkata"
  },
  "geometry": {
    "type": "Point",
    "coordinates": [
      69.78081,
      21.93053
    ]
  }
}