{
  "type": "Feature",
  "properties": {
    "name": "Bharūch",
    "country": "IN",
    "subdivision": "09",
    "timezone": "Asia/Kolkata"
  },
  "geometry": {
    "type": "Point",
    "coordinates": [
      72.9805,
      21.69482
    ]
  }
}