{
  "type": "Feature",
  "properties": {
    "name": "BotÄd",
    "country": "IN",
    "subdivision": "09",
    "timezone": "Asia/Kolkata"
  },
  "geometry": {
    "type": "Point",
    "coordinates": [
      71.66671,
      22.16917
    ]
  }
}