{
  "type": "Feature",
  "properties": {
    "name": "Chotila",
    "country": "IN",
    "subdivision": "09",
    "timezone": "Asia/Kolkata"
  },
  "geometry": {
    "type": "Point",
    "coordinates": [
      71.19641,
      22.42347
    ]
  }
}