{
  "type": "Feature",
  "properties": {
    "name": "Dhanera",
    "country": "IN",
    "subdivision": "09",
    "timezone": "Asia/Kolkata"
  },
  "geometry": {
    "type": "Point",
    "coordinates": [
      72.02343,
      24.50967
    ]
  }
}