{
  "type": "Feature",
  "properties": {
    "name": "Dhrol",
    "country": "IN",
    "subdivision": "09",
    "timezone": "Asia/Kolkata"
  },
  "geometry": {
    "type": "Point",
    "coordinates": [
      70.41769,
      22.567
    ]
  }
}