{
  "type": "Feature",
  "properties": {
    "name": "Gandhinagar",
    "country": "IN",
    "subdivision": "09",
    "timezone": "Asia/Kolkata"
  },
  "geometry": {
    "type": "Point",
    "coordinates": [
      72.68333,
      23.21667
    ]
  }
}