{
  "type": "Feature",
  "properties": {
    "name": "Halvad",
    "country": "IN",
    "subdivision": "09",
    "timezone": "Asia/Kolkata"
  },
  "geometry": {
    "type": "Point",
    "coordinates": [
      71.18029,
      23.01516
    ]
  }
}