{
  "type": "Feature",
  "properties": {
    "name": "Kadod",
    "country": "IN",
    "subdivision": "09",
    "timezone": "Asia/Kolkata"
  },
  "geometry": {
    "type": "Point",
    "coordinates": [
      73.21972,
      21.21717
    ]
  }
}