{
  "type": "Feature",
  "properties": {
    "name": "Keshod",
    "country": "IN",
    "subdivision": "09",
    "timezone": "Asia/Kolkata"
  },
  "geometry": {
    "type": "Point",
    "coordinates": [
      70.24861,
      21.30328
    ]
  }
}