{
  "type": "Feature",
  "properties": {
    "name": "Khedbrahma",
    "country": "IN",
    "subdivision": "09",
    "timezone": "Asia/Kolkata"
  },
  "geometry": {
    "type": "Point",
    "coordinates": [
      73.04632,
      24.0299
    ]
  }
}