{
  "type": "Feature",
  "properties": {
    "name": "Kosamba",
    "country": "IN",
    "subdivision": "09",
    "timezone": "Asia/Kolkata"
  },
  "geometry": {
    "type": "Point",
    "coordinates": [
      72.95842,
      21.46202
    ]
  }
}