{
  "type": "Feature",
  "properties": {
    "name": "Kundla",
    "country": "IN",
    "subdivision": "09",
    "timezone": "Asia/Kolkata"
  },
  "geometry": {
    "type": "Point",
    "coordinates": [
      71.30633,
      21.34222
    ]
  }
}