{
  "type": "Feature",
  "properties": {
    "name": "Mahudha",
    "country": "IN",
    "subdivision": "09",
    "timezone": "Asia/Kolkata"
  },
  "geometry": {
    "type": "Point",
    "coordinates": [
      72.94032,
      22.82082
    ]
  }
}