{
  "type": "Feature",
  "properties": {
    "name": "Mānāvadar",
    "country": "IN",
    "subdivision": "09",
    "timezone": "Asia/Kolkata"
  },
  "geometry": {
    "type": "Point",
    "coordinates": [
      70.13775,
      21.49813
    ]
  }
}