{
  "type": "Feature",
  "properties": {
    "name": "MÄndvi",
    "country": "IN",
    "subdivision": "09",
    "timezone": "Asia/Kolkata"
  },
  "geometry": {
    "type": "Point",
    "coordinates": [
      69.35237,
      22.83282
    ]
  }
}