{
  "type": "Feature",
  "properties": {
    "name": "MÄngrol",
    "country": "IN",
    "subdivision": "09",
    "timezone": "Asia/Kolkata"
  },
  "geometry": {
    "type": "Point",
    "coordinates": [
      70.11484,
      21.12268
    ]
  }
}