{
  "type": "Feature",
  "properties": {
    "name": "Mundra",
    "country": "IN",
    "subdivision": "09",
    "timezone": "Asia/Kolkata"
  },
  "geometry": {
    "type": "Point",
    "coordinates": [
      69.7219,
      22.83918
    ]
  }
}