{
  "type": "Feature",
  "properties": {
    "name": "Naliya",
    "country": "IN",
    "subdivision": "09",
    "timezone": "Asia/Kolkata"
  },
  "geometry": {
    "type": "Point",
    "coordinates": [
      68.82655,
      23.26058
    ]
  }
}