{
  "type": "Feature",
  "properties": {
    "name": "OlpÄd",
    "country": "IN",
    "subdivision": "09",
    "timezone": "Asia/Kolkata"
  },
  "geometry": {
    "type": "Point",
    "coordinates": [
      72.75161,
      21.33649
    ]
  }
}