{
  "type": "Feature",
  "properties": {
    "name": "PÄrdi",
    "country": "IN",
    "subdivision": "09",
    "timezone": "Asia/Kolkata"
  },
  "geometry": {
    "type": "Point",
    "coordinates": [
      72.94569,
      20.5087
    ]
  }
}