{
  "type": "Feature",
  "properties": {
    "name": "Umreth",
    "country": "IN",
    "subdivision": "09",
    "timezone": "Asia/Kolkata"
  },
  "geometry": {
    "type": "Point",
    "coordinates": [
      73.11561,
      22.69881
    ]
  }
}