{
  "type": "Feature",
  "properties": {
    "name": "Upleta",
    "country": "IN",
    "subdivision": "09",
    "timezone": "Asia/Kolkata"
  },
  "geometry": {
    "type": "Point",
    "coordinates": [
      70.28256,
      21.74015
    ]
  }
}