{
  "type": "Feature",
  "properties": {
    "name": "Vadnagar",
    "country": "IN",
    "subdivision": "09",
    "timezone": "Asia/Kolkata"
  },
  "geometry": {
    "type": "Point",
    "coordinates": [
      72.63893,
      23.78593
    ]
  }
}