{
  "type": "Feature",
  "properties": {
    "name": "ValsÄd",
    "country": "IN",
    "subdivision": "09",
    "timezone": "Asia/Kolkata"
  },
  "geometry": {
    "type": "Point",
    "coordinates": [
      72.93428,
      20.61013
    ]
  }
}