{
  "type": "Feature",
  "properties": {
    "name": "VÄnsada",
    "country": "IN",
    "subdivision": "09",
    "timezone": "Asia/Kolkata"
  },
  "geometry": {
    "type": "Point",
    "coordinates": [
      73.36389,
      20.75817
    ]
  }
}