{
  "type": "Feature",
  "properties": {
    "name": "VerÄval",
    "country": "IN",
    "subdivision": "09",
    "timezone": "Asia/Kolkata"
  },
  "geometry": {
    "type": "Point",
    "coordinates": [
      70.36786,
      20.9077
    ]
  }
}