{
  "type": "Feature",
  "properties": {
    "name": "Virpur",
    "country": "IN",
    "subdivision": "09",
    "timezone": "Asia/Kolkata"
  },
  "geometry": {
    "type": "Point",
    "coordinates": [
      73.47987,
      23.1892
    ]
  }
}