{
  "type": "Feature",
  "properties": {
    "name": "Ardatov",
    "country": "RU",
    "subdivision": "51",
    "timezone": "Europe/Moscow"
  },
  "geometry": {
    "type": "Point",
    "coordinates": [
      43.09699,
      55.24205
    ]
  }
}