{
  "type": "Feature",
  "properties": {
    "name": "Ar’ya",
    "country": "RU",
    "subdivision": "51",
    "timezone": "Europe/Moscow"
  },
  "geometry": {
    "type": "Point",
    "coordinates": [
      45.96691,
      57.49146
    ]
  }
}