{
  "type": "Feature",
  "properties": {
    "name": "Bol’shoye Boldino",
    "country": "RU",
    "subdivision": "51",
    "timezone": "Europe/Moscow"
  },
  "geometry": {
    "type": "Point",
    "coordinates": [
      45.31419,
      55.00588
    ]
  }
}