{
  "type": "Feature",
  "properties": {
    "name": "Imeni Stepana Razina",
    "country": "RU",
    "subdivision": "51",
    "timezone": "Europe/Moscow"
  },
  "geometry": {
    "type": "Point",
    "coordinates": [
      44.29627,
      54.8932
    ]
  }
}