{
  "type": "Feature",
  "properties": {
    "name": "Linda",
    "country": "RU",
    "subdivision": "51",
    "timezone": "Europe/Moscow"
  },
  "geometry": {
    "type": "Point",
    "coordinates": [
      44.09544,
      56.61571
    ]
  }
}