{
  "type": "Feature",
  "properties": {
    "name": "Sharanga",
    "country": "RU",
    "subdivision": "51",
    "timezone": "Europe/Moscow"
  },
  "geometry": {
    "type": "Point",
    "coordinates": [
      46.53956,
      57.17749
    ]
  }
}