{
  "type": "Feature",
  "properties": {
    "name": "Shimorskoye",
    "country": "RU",
    "subdivision": "51",
    "timezone": "Europe/Moscow"
  },
  "geometry": {
    "type": "Point",
    "coordinates": [
      42.0256,
      55.3281
    ]
  }
}