{
  "type": "Feature",
  "properties": {
    "name": "Tsentral’nyy",
    "country": "RU",
    "subdivision": "51",
    "timezone": "Europe/Moscow"
  },
  "geometry": {
    "type": "Point",
    "coordinates": [
      42.78869,
      56.297
    ]
  }
}