{
  "type": "Feature",
  "properties": {
    "name": "Vakhtan",
    "country": "RU",
    "subdivision": "51",
    "timezone": "Europe/Moscow"
  },
  "geometry": {
    "type": "Point",
    "coordinates": [
      46.68886,
      57.96592
    ]
  }
}