{
  "type": "Feature",
  "properties": {
    "name": "Vilya",
    "country": "RU",
    "subdivision": "51",
    "timezone": "Europe/Moscow"
  },
  "geometry": {
    "type": "Point",
    "coordinates": [
      42.20889,
      55.24556
    ]
  }
}