{
  "type": "Feature",
  "properties": {
    "name": "Bahani",
    "country": "KM",
    "subdivision": "02",
    "timezone": "Indian/Comoro"
  },
  "geometry": {
    "type": "Point",
    "coordinates": [
      43.28417,
      -11.63972
    ]
  }
}