{
  "type": "Feature",
  "properties": {
    "name": "Itsandra",
    "country": "KM",
    "subdivision": "02",
    "timezone": "Indian/Comoro"
  },
  "geometry": {
    "type": "Point",
    "coordinates": [
      43.26466,
      -11.67638
    ]
  }
}