{
  "type": "Feature",
  "properties": {
    "name": "Mandza",
    "country": "KM",
    "subdivision": "02",
    "timezone": "Indian/Comoro"
  },
  "geometry": {
    "type": "Point",
    "coordinates": [
      43.29528,
      -11.41806
    ]
  }
}