{
  "type": "Feature",
  "properties": {
    "name": "Bweyogerere",
    "country": "UG",
    "subdivision": "C",
    "timezone": "Africa/Kampala"
  },
  "geometry": {
    "type": "Point",
    "coordinates": [
      32.66332,
      0.35773
    ]
  }
}