{
  "type": "Feature",
  "properties": {
    "name": "Santa María",
    "country": "PA",
    "subdivision": "06",
    "timezone": "America/Panama"
  },
  "geometry": {
    "type": "Point",
    "coordinates": [
      -80.66464,
      8.11402
    ]
  }
}