{
  "type": "Feature",
  "properties": {
    "name": "Laikit, Laikit II (Dimembe)",
    "country": "ID",
    "subdivision": "31",
    "timezone": "Asia/Makassar"
  },
  "geometry": {
    "type": "Point",
    "coordinates": [
      124.97444,
      1.48833
    ]
  }
}