{
  "type": "Feature",
  "properties": {
    "name": "Ámfissa",
    "country": "GR",
    "subdivision": "ESYE24",
    "timezone": "Europe/Athens"
  },
  "geometry": {
    "type": "Point",
    "coordinates": [
      22.37713,
      38.52813
    ]
  }
}