{
  "type": "Feature",
  "properties": {
    "name": "Áyios Konstandínos",
    "country": "GR",
    "subdivision": "ESYE24",
    "timezone": "Europe/Athens"
  },
  "geometry": {
    "type": "Point",
    "coordinates": [
      22.85757,
      38.75612
    ]
  }
}