{
  "type": "Feature",
  "properties": {
    "name": "Chalkída",
    "country": "GR",
    "subdivision": "ESYE24",
    "timezone": "Europe/Athens"
  },
  "geometry": {
    "type": "Point",
    "coordinates": [
      23.60284,
      38.46354
    ]
  }
}