{
  "type": "Feature",
  "properties": {
    "name": "Eláteia",
    "country": "GR",
    "subdivision": "ESYE24",
    "timezone": "Europe/Athens"
  },
  "geometry": {
    "type": "Point",
    "coordinates": [
      22.76492,
      38.6277
    ]
  }
}