{
  "type": "Feature",
  "properties": {
    "name": "Istiaía",
    "country": "GR",
    "subdivision": "ESYE24",
    "timezone": "Europe/Athens"
  },
  "geometry": {
    "type": "Point",
    "coordinates": [
      23.1521,
      38.9552
    ]
  }
}