{
  "type": "Feature",
  "properties": {
    "name": "Kainoúryion",
    "country": "GR",
    "subdivision": "ESYE24",
    "timezone": "Europe/Athens"
  },
  "geometry": {
    "type": "Point",
    "coordinates": [
      22.7247,
      38.79283
    ]
  }
}