{
  "type": "Feature",
  "properties": {
    "name": "Karpenísi",
    "country": "GR",
    "subdivision": "ESYE24",
    "timezone": "Europe/Athens"
  },
  "geometry": {
    "type": "Point",
    "coordinates": [
      21.79836,
      38.91218
    ]
  }
}