{
  "type": "Feature",
  "properties": {
    "name": "Kírra",
    "country": "GR",
    "subdivision": "ESYE24",
    "timezone": "Europe/Athens"
  },
  "geometry": {
    "type": "Point",
    "coordinates": [
      22.44443,
      38.42944
    ]
  }
}