{
  "type": "Feature",
  "properties": {
    "name": "Néa Artáki",
    "country": "GR",
    "subdivision": "ESYE24",
    "timezone": "Europe/Athens"
  },
  "geometry": {
    "type": "Point",
    "coordinates": [
      23.63296,
      38.52027
    ]
  }
}