{
  "type": "Feature",
  "properties": {
    "name": "Prokópi",
    "country": "GR",
    "subdivision": "ESYE24",
    "timezone": "Europe/Athens"
  },
  "geometry": {
    "type": "Point",
    "coordinates": [
      23.4906,
      38.73402
    ]
  }
}