{
  "type": "Feature",
  "properties": {
    "name": "Skýros",
    "country": "GR",
    "subdivision": "ESYE24",
    "timezone": "Europe/Athens"
  },
  "geometry": {
    "type": "Point",
    "coordinates": [
      24.56306,
      38.90417
    ]
  }
}