{
  "type": "Feature",
  "properties": {
    "name": "Andilamena",
    "country": "MG",
    "subdivision": "33",
    "timezone": "Indian/Antananarivo"
  },
  "geometry": {
    "type": "Point",
    "coordinates": [
      48.57313,
      -17.01009
    ]
  }
}