{
  "type": "Feature",
  "properties": {
    "name": "Dowa",
    "country": "MW",
    "subdivision": "C",
    "timezone": "Africa/Blantyre"
  },
  "geometry": {
    "type": "Point",
    "coordinates": [
      33.93754,
      -13.65399
    ]
  }
}