{
  "type": "Feature",
  "properties": {
    "name": "Temerluh",
    "country": "MY",
    "subdivision": "06",
    "timezone": "Asia/Kuala_Lumpur"
  },
  "geometry": {
    "type": "Point",
    "coordinates": [
      102.4176,
      3.4506
    ]
  }
}