{
  "type": "Feature",
  "properties": {
    "name": "Atid",
    "country": "RO",
    "subdivision": "20",
    "timezone": "Europe/Bucharest"
  },
  "geometry": {
    "type": "Point",
    "coordinates": [
      25.05,
      46.45
    ]
  }
}