{
  "type": "Feature",
  "properties": {
    "name": "Ciceu",
    "country": "RO",
    "subdivision": "20",
    "timezone": "Europe/Bucharest"
  },
  "geometry": {
    "type": "Point",
    "coordinates": [
      25.78204,
      46.41328
    ]
  }
}