{
  "type": "Feature",
  "properties": {
    "name": "Cristuru Secuiesc",
    "country": "RO",
    "subdivision": "20",
    "timezone": "Europe/Bucharest"
  },
  "geometry": {
    "type": "Point",
    "coordinates": [
      25.03333,
      46.28333
    ]
  }
}