{
  "type": "Feature",
  "properties": {
    "name": "Gheorgheni",
    "country": "RO",
    "subdivision": "20",
    "timezone": "Europe/Bucharest"
  },
  "geometry": {
    "type": "Point",
    "coordinates": [
      25.60055,
      46.72292
    ]
  }
}