{
  "type": "Feature",
  "properties": {
    "name": "Hodoșa",
    "country": "RO",
    "subdivision": "20",
    "timezone": "Europe/Bucharest"
  },
  "geometry": {
    "type": "Point",
    "coordinates": [
      25.4462,
      46.86558
    ]
  }
}