{
  "type": "Feature",
  "properties": {
    "name": "Lăzarea",
    "country": "RO",
    "subdivision": "20",
    "timezone": "Europe/Bucharest"
  },
  "geometry": {
    "type": "Point",
    "coordinates": [
      25.53333,
      46.75
    ]
  }
}