{
  "type": "Feature",
  "properties": {
    "name": "Mereşti",
    "country": "RO",
    "subdivision": "20",
    "timezone": "Europe/Bucharest"
  },
  "geometry": {
    "type": "Point",
    "coordinates": [
      25.45,
      46.23333
    ]
  }
}