{
  "type": "Feature",
  "properties": {
    "name": "Mihăileni",
    "country": "RO",
    "subdivision": "20",
    "timezone": "Europe/Bucharest"
  },
  "geometry": {
    "type": "Point",
    "coordinates": [
      25.81667,
      46.46667
    ]
  }
}