{
  "type": "Feature",
  "properties": {
    "name": "Sândominic",
    "country": "RO",
    "subdivision": "20",
    "timezone": "Europe/Bucharest"
  },
  "geometry": {
    "type": "Point",
    "coordinates": [
      25.78028,
      46.584
    ]
  }
}