{
  "type": "Feature",
  "properties": {
    "name": "Tulgheş",
    "country": "RO",
    "subdivision": "20",
    "timezone": "Europe/Bucharest"
  },
  "geometry": {
    "type": "Point",
    "coordinates": [
      25.76667,
      46.95
    ]
  }
}