{
  "type": "Feature",
  "properties": {
    "name": "Jinjiang",
    "country": "CN",
    "subdivision": "31",
    "timezone": "Asia/Shanghai"
  },
  "geometry": {
    "type": "Point",
    "coordinates": [
      110.00851,
      19.72878
    ]
  }
}