{
  "type": "Feature",
  "properties": {
    "name": "Wanning",
    "country": "CN",
    "subdivision": "31",
    "timezone": "Asia/Shanghai"
  },
  "geometry": {
    "type": "Point",
    "coordinates": [
      110.3841,
      18.79931
    ]
  }
}