{
  "type": "Feature",
  "properties": {
    "name": "Lulindi",
    "country": "TZ",
    "subdivision": "11",
    "timezone": "Africa/Dar_es_Salaam"
  },
  "geometry": {
    "type": "Point",
    "coordinates": [
      39.13333,
      -10.81667
    ]
  }
}