{
  "type": "Feature",
  "properties": {
    "name": "Działoszyce",
    "country": "PL",
    "subdivision": "84",
    "timezone": "Europe/Warsaw"
  },
  "geometry": {
    "type": "Point",
    "coordinates": [
      20.35226,
      50.36534
    ]
  }
}