{
  "type": "Feature",
  "properties": {
    "name": "Krasocin",
    "country": "PL",
    "subdivision": "84",
    "timezone": "Europe/Warsaw"
  },
  "geometry": {
    "type": "Point",
    "coordinates": [
      20.11863,
      50.88874
    ]
  }
}