{
  "type": "Feature",
  "properties": {
    "name": "Małogoszcz",
    "country": "PL",
    "subdivision": "84",
    "timezone": "Europe/Warsaw"
  },
  "geometry": {
    "type": "Point",
    "coordinates": [
      20.26407,
      50.81214
    ]
  }
}