{
  "type": "Feature",
  "properties": {
    "name": "Radoszyce",
    "country": "PL",
    "subdivision": "84",
    "timezone": "Europe/Warsaw"
  },
  "geometry": {
    "type": "Point",
    "coordinates": [
      20.25836,
      51.07392
    ]
  }
}