{
  "type": "Feature",
  "properties": {
    "name": "Rogów",
    "country": "PL",
    "subdivision": "84",
    "timezone": "Europe/Warsaw"
  },
  "geometry": {
    "type": "Point",
    "coordinates": [
      20.43483,
      51.20414
    ]
  }
}