{
  "type": "Feature",
  "properties": {
    "name": "Wąchock",
    "country": "PL",
    "subdivision": "84",
    "timezone": "Europe/Warsaw"
  },
  "geometry": {
    "type": "Point",
    "coordinates": [
      21.01243,
      51.07391
    ]
  }
}