{
  "type": "Feature",
  "properties": {
    "name": "Łopuszno",
    "country": "PL",
    "subdivision": "84",
    "timezone": "Europe/Warsaw"
  },
  "geometry": {
    "type": "Point",
    "coordinates": [
      20.25081,
      50.94864
    ]
  }
}