{
  "type": "Feature",
  "properties": {
    "name": "Alsleben",
    "country": "DE",
    "subdivision": "14",
    "timezone": "Europe/Berlin"
  },
  "geometry": {
    "type": "Point",
    "coordinates": [
      11.67648,
      51.70161
    ]
  }
}