{
  "type": "Feature",
  "properties": {
    "name": "Baalberge",
    "country": "DE",
    "subdivision": "14",
    "timezone": "Europe/Berlin"
  },
  "geometry": {
    "type": "Point",
    "coordinates": [
      11.7988,
      51.76469
    ]
  }
}