{
  "type": "Feature",
  "properties": {
    "name": "Ballenstedt",
    "country": "DE",
    "subdivision": "14",
    "timezone": "Europe/Berlin"
  },
  "geometry": {
    "type": "Point",
    "coordinates": [
      11.23265,
      51.719
    ]
  }
}