{
  "type": "Feature",
  "properties": {
    "name": "Barnstädt",
    "country": "DE",
    "subdivision": "14",
    "timezone": "Europe/Berlin"
  },
  "geometry": {
    "type": "Point",
    "coordinates": [
      11.63735,
      51.34401
    ]
  }
}