{
  "type": "Feature",
  "properties": {
    "name": "Bennungen",
    "country": "DE",
    "subdivision": "14",
    "timezone": "Europe/Berlin"
  },
  "geometry": {
    "type": "Point",
    "coordinates": [
      11.11816,
      51.46085
    ]
  }
}