{
  "type": "Feature",
  "properties": {
    "name": "Blankenheim",
    "country": "DE",
    "subdivision": "14",
    "timezone": "Europe/Berlin"
  },
  "geometry": {
    "type": "Point",
    "coordinates": [
      11.42878,
      51.50717
    ]
  }
}