{
  "type": "Feature",
  "properties": {
    "name": "Calbe",
    "country": "DE",
    "subdivision": "14",
    "timezone": "Europe/Berlin"
  },
  "geometry": {
    "type": "Point",
    "coordinates": [
      11.77478,
      51.90668
    ]
  }
}