{
  "type": "Feature",
  "properties": {
    "name": "Elbingerode",
    "country": "DE",
    "subdivision": "14",
    "timezone": "Europe/Berlin"
  },
  "geometry": {
    "type": "Point",
    "coordinates": [
      10.80557,
      51.77039
    ]
  }
}