{
  "type": "Feature",
  "properties": {
    "name": "Erxleben",
    "country": "DE",
    "subdivision": "14",
    "timezone": "Europe/Berlin"
  },
  "geometry": {
    "type": "Point",
    "coordinates": [
      11.24245,
      52.21812
    ]
  }
}