{
  "type": "Feature",
  "properties": {
    "name": "Gardelegen",
    "country": "DE",
    "subdivision": "14",
    "timezone": "Europe/Berlin"
  },
  "geometry": {
    "type": "Point",
    "coordinates": [
      11.39523,
      52.5252
    ]
  }
}