{
  "type": "Feature",
  "properties": {
    "name": "Giersleben",
    "country": "DE",
    "subdivision": "14",
    "timezone": "Europe/Berlin"
  },
  "geometry": {
    "type": "Point",
    "coordinates": [
      11.56667,
      51.76667
    ]
  }
}