{
  "type": "Feature",
  "properties": {
    "name": "Groß Rosenburg",
    "country": "DE",
    "subdivision": "14",
    "timezone": "Europe/Berlin"
  },
  "geometry": {
    "type": "Point",
    "coordinates": [
      11.89184,
      51.91696
    ]
  }
}