{
  "type": "Feature",
  "properties": {
    "name": "Hadmersleben",
    "country": "DE",
    "subdivision": "14",
    "timezone": "Europe/Berlin"
  },
  "geometry": {
    "type": "Point",
    "coordinates": [
      11.30283,
      51.99275
    ]
  }
}