{
  "type": "Feature",
  "properties": {
    "name": "Hettstedt",
    "country": "DE",
    "subdivision": "14",
    "timezone": "Europe/Berlin"
  },
  "geometry": {
    "type": "Point",
    "coordinates": [
      11.51146,
      51.6503
    ]
  }
}