{
  "type": "Feature",
  "properties": {
    "name": "Hoym",
    "country": "DE",
    "subdivision": "14",
    "timezone": "Europe/Berlin"
  },
  "geometry": {
    "type": "Point",
    "coordinates": [
      11.31244,
      51.78292
    ]
  }
}