{
  "type": "Feature",
  "properties": {
    "name": "Huy-Neinstedt",
    "country": "DE",
    "subdivision": "14",
    "timezone": "Europe/Berlin"
  },
  "geometry": {
    "type": "Point",
    "coordinates": [
      10.91457,
      51.96585
    ]
  }
}