{
  "type": "Feature",
  "properties": {
    "name": "Jessen",
    "country": "DE",
    "subdivision": "14",
    "timezone": "Europe/Berlin"
  },
  "geometry": {
    "type": "Point",
    "coordinates": [
      12.95762,
      51.79337
    ]
  }
}