{
  "type": "Feature",
  "properties": {
    "name": "Kalbe",
    "country": "DE",
    "subdivision": "14",
    "timezone": "Europe/Berlin"
  },
  "geometry": {
    "type": "Point",
    "coordinates": [
      11.38456,
      52.65656
    ]
  }
}