{
  "type": "Feature",
  "properties": {
    "name": "Landsberg",
    "country": "DE",
    "subdivision": "14",
    "timezone": "Europe/Berlin"
  },
  "geometry": {
    "type": "Point",
    "coordinates": [
      12.16076,
      51.52698
    ]
  }
}