{
  "type": "Feature",
  "properties": {
    "name": "Langenstein",
    "country": "DE",
    "subdivision": "14",
    "timezone": "Europe/Berlin"
  },
  "geometry": {
    "type": "Point",
    "coordinates": [
      10.98822,
      51.85551
    ]
  }
}