{
  "type": "Feature",
  "properties": {
    "name": "Lindau",
    "country": "DE",
    "subdivision": "14",
    "timezone": "Europe/Berlin"
  },
  "geometry": {
    "type": "Point",
    "coordinates": [
      12.10788,
      52.03751
    ]
  }
}