{
  "type": "Feature",
  "properties": {
    "name": "Lüderitz",
    "country": "DE",
    "subdivision": "14",
    "timezone": "Europe/Berlin"
  },
  "geometry": {
    "type": "Point",
    "coordinates": [
      11.74301,
      52.50912
    ]
  }
}