{
  "type": "Feature",
  "properties": {
    "name": "Mansfeld",
    "country": "DE",
    "subdivision": "14",
    "timezone": "Europe/Berlin"
  },
  "geometry": {
    "type": "Point",
    "coordinates": [
      11.45223,
      51.59234
    ]
  }
}