{
  "type": "Feature",
  "properties": {
    "name": "Möser",
    "country": "DE",
    "subdivision": "14",
    "timezone": "Europe/Berlin"
  },
  "geometry": {
    "type": "Point",
    "coordinates": [
      11.79279,
      52.21397
    ]
  }
}