{
  "type": "Feature",
  "properties": {
    "name": "Naumburg",
    "country": "DE",
    "subdivision": "14",
    "timezone": "Europe/Berlin"
  },
  "geometry": {
    "type": "Point",
    "coordinates": [
      11.80979,
      51.14987
    ]
  }
}