{
  "type": "Feature",
  "properties": {
    "name": "Plötzkau",
    "country": "DE",
    "subdivision": "14",
    "timezone": "Europe/Berlin"
  },
  "geometry": {
    "type": "Point",
    "coordinates": [
      11.68333,
      51.75
    ]
  }
}