{
  "type": "Feature",
  "properties": {
    "name": "Querfurt",
    "country": "DE",
    "subdivision": "14",
    "timezone": "Europe/Berlin"
  },
  "geometry": {
    "type": "Point",
    "coordinates": [
      11.60047,
      51.38124
    ]
  }
}