{
  "type": "Feature",
  "properties": {
    "name": "Radegast",
    "country": "DE",
    "subdivision": "14",
    "timezone": "Europe/Berlin"
  },
  "geometry": {
    "type": "Point",
    "coordinates": [
      12.09485,
      51.65654
    ]
  }
}