{
  "type": "Feature",
  "properties": {
    "name": "Röblingen am See",
    "country": "DE",
    "subdivision": "14",
    "timezone": "Europe/Berlin"
  },
  "geometry": {
    "type": "Point",
    "coordinates": [
      11.68231,
      51.45944
    ]
  }
}