{
  "type": "Feature",
  "properties": {
    "name": "Tangerhütte",
    "country": "DE",
    "subdivision": "14",
    "timezone": "Europe/Berlin"
  },
  "geometry": {
    "type": "Point",
    "coordinates": [
      11.80724,
      52.4353
    ]
  }
}