{
  "type": "Feature",
  "properties": {
    "name": "Tucheim",
    "country": "DE",
    "subdivision": "14",
    "timezone": "Europe/Berlin"
  },
  "geometry": {
    "type": "Point",
    "coordinates": [
      12.18423,
      52.28923
    ]
  }
}