{
  "type": "Feature",
  "properties": {
    "name": "Uchtspringe",
    "country": "DE",
    "subdivision": "14",
    "timezone": "Europe/Berlin"
  },
  "geometry": {
    "type": "Point",
    "coordinates": [
      11.59959,
      52.54011
    ]
  }
}