{
  "type": "Feature",
  "properties": {
    "name": "Welsleben",
    "country": "DE",
    "subdivision": "14",
    "timezone": "Europe/Berlin"
  },
  "geometry": {
    "type": "Point",
    "coordinates": [
      11.63851,
      52.00304
    ]
  }
}