{
  "type": "Feature",
  "properties": {
    "name": "Zschornewitz",
    "country": "DE",
    "subdivision": "14",
    "timezone": "Europe/Berlin"
  },
  "geometry": {
    "type": "Point",
    "coordinates": [
      12.39998,
      51.71585
    ]
  }
}