{
  "type": "Feature",
  "properties": {
    "name": "Zscherben",
    "country": "DE",
    "subdivision": "14",
    "timezone": "Europe/Berlin"
  },
  "geometry": {
    "type": "Point",
    "coordinates": [
      11.87058,
      51.46709
    ]
  }
}