{
  "type": "Feature",
  "properties": {
    "name": "LahÄn",
    "country": "NP",
    "subdivision": "2",
    "timezone": "Asia/Kathmandu"
  },
  "geometry": {
    "type": "Point",
    "coordinates": [
      86.48258,
      26.72022
    ]
  }
}