{
  "type": "Feature",
  "properties": {
    "name": "Az Zubayr",
    "country": "IQ",
    "subdivision": "02",
    "timezone": "Asia/Baghdad"
  },
  "geometry": {
    "type": "Point",
    "coordinates": [
      47.70175,
      30.39213
    ]
  }
}