{
  "type": "Feature",
  "properties": {
    "name": "Basrah",
    "country": "IQ",
    "subdivision": "02",
    "timezone": "Asia/Baghdad"
  },
  "geometry": {
    "type": "Point",
    "coordinates": [
      47.7804,
      30.50852
    ]
  }
}