{
  "type": "Feature",
  "properties": {
    "name": "Baloteşti",
    "country": "RO",
    "subdivision": "43",
    "timezone": "Europe/Bucharest"
  },
  "geometry": {
    "type": "Point",
    "coordinates": [
      26.11667,
      44.61667
    ]
  }
}