{
  "type": "Feature",
  "properties": {
    "name": "Berceni",
    "country": "RO",
    "subdivision": "43",
    "timezone": "Europe/Bucharest"
  },
  "geometry": {
    "type": "Point",
    "coordinates": [
      26.18556,
      44.31417
    ]
  }
}