{
  "type": "Feature",
  "properties": {
    "name": "Dragomireşti-Vale",
    "country": "RO",
    "subdivision": "43",
    "timezone": "Europe/Bucharest"
  },
  "geometry": {
    "type": "Point",
    "coordinates": [
      25.935,
      44.475
    ]
  }
}