{
  "type": "Feature",
  "properties": {
    "name": "Fundeni",
    "country": "RO",
    "subdivision": "43",
    "timezone": "Europe/Bucharest"
  },
  "geometry": {
    "type": "Point",
    "coordinates": [
      26.16565,
      44.45892
    ]
  }
}