{
  "type": "Feature",
  "properties": {
    "name": "Baitoa",
    "country": "DO",
    "subdivision": "25",
    "timezone": "America/Santo_Domingo"
  },
  "geometry": {
    "type": "Point",
    "coordinates": [
      -70.70357,
      19.32512
    ]
  }
}