{
  "type": "Feature",
  "properties": {
    "name": "La Canela",
    "country": "DO",
    "subdivision": "25",
    "timezone": "America/Santo_Domingo"
  },
  "geometry": {
    "type": "Point",
    "coordinates": [
      -70.81629,
      19.47341
    ]
  }
}