{
  "type": "Feature",
  "properties": {
    "name": "Santiago de los Caballeros",
    "country": "DO",
    "subdivision": "25",
    "timezone": "America/Santo_Domingo"
  },
  "geometry": {
    "type": "Point",
    "coordinates": [
      -70.69703,
      19.4517
    ]
  }
}