{
  "type": "Feature",
  "properties": {
    "name": "Luau",
    "country": "AO",
    "subdivision": "14",
    "timezone": "Africa/Luanda"
  },
  "geometry": {
    "type": "Point",
    "coordinates": [
      22.22466,
      -10.70727
    ]
  }
}