{
  "type": "Feature",
  "properties": {
    "name": "Bílovice",
    "country": "CZ",
    "subdivision": "90",
    "timezone": "Europe/Prague"
  },
  "geometry": {
    "type": "Point",
    "coordinates": [
      17.54961,
      49.09965
    ]
  }
}