{
  "type": "Feature",
  "properties": {
    "name": "Boršice",
    "country": "CZ",
    "subdivision": "90",
    "timezone": "Europe/Prague"
  },
  "geometry": {
    "type": "Point",
    "coordinates": [
      17.35084,
      49.06254
    ]
  }
}