{
  "type": "Feature",
  "properties": {
    "name": "Francova Lhota",
    "country": "CZ",
    "subdivision": "90",
    "timezone": "Europe/Prague"
  },
  "geometry": {
    "type": "Point",
    "coordinates": [
      18.11175,
      49.20174
    ]
  }
}