{
  "type": "Feature",
  "properties": {
    "name": "Karolinka",
    "country": "CZ",
    "subdivision": "90",
    "timezone": "Europe/Prague"
  },
  "geometry": {
    "type": "Point",
    "coordinates": [
      18.24006,
      49.35128
    ]
  }
}