{
  "type": "Feature",
  "properties": {
    "name": "Kvasice",
    "country": "CZ",
    "subdivision": "90",
    "timezone": "Europe/Prague"
  },
  "geometry": {
    "type": "Point",
    "coordinates": [
      17.46974,
      49.24223
    ]
  }
}