{
  "type": "Feature",
  "properties": {
    "name": "Liptál",
    "country": "CZ",
    "subdivision": "90",
    "timezone": "Europe/Prague"
  },
  "geometry": {
    "type": "Point",
    "coordinates": [
      17.92177,
      49.29051
    ]
  }
}