{
  "type": "Feature",
  "properties": {
    "name": "Mistřice",
    "country": "CZ",
    "subdivision": "90",
    "timezone": "Europe/Prague"
  },
  "geometry": {
    "type": "Point",
    "coordinates": [
      17.53597,
      49.08668
    ]
  }
}