{
  "type": "Feature",
  "properties": {
    "name": "Pozlovice",
    "country": "CZ",
    "subdivision": "90",
    "timezone": "Europe/Prague"
  },
  "geometry": {
    "type": "Point",
    "coordinates": [
      17.76925,
      49.12921
    ]
  }
}