{
  "type": "Feature",
  "properties": {
    "name": "Slušovice",
    "country": "CZ",
    "subdivision": "90",
    "timezone": "Europe/Prague"
  },
  "geometry": {
    "type": "Point",
    "coordinates": [
      17.8015,
      49.24782
    ]
  }
}