{
  "type": "Feature",
  "properties": {
    "name": "Tlumačov",
    "country": "CZ",
    "subdivision": "90",
    "timezone": "Europe/Prague"
  },
  "geometry": {
    "type": "Point",
    "coordinates": [
      17.49559,
      49.25351
    ]
  }
}