{
  "type": "Feature",
  "properties": {
    "name": "Traplice",
    "country": "CZ",
    "subdivision": "90",
    "timezone": "Europe/Prague"
  },
  "geometry": {
    "type": "Point",
    "coordinates": [
      17.43622,
      49.13088
    ]
  }
}