{
  "type": "Feature",
  "properties": {
    "name": "Zdounky",
    "country": "CZ",
    "subdivision": "90",
    "timezone": "Europe/Prague"
  },
  "geometry": {
    "type": "Point",
    "coordinates": [
      17.31899,
      49.22771
    ]
  }
}