{
  "type": "Feature",
  "properties": {
    "name": "Žlutava",
    "country": "CZ",
    "subdivision": "90",
    "timezone": "Europe/Prague"
  },
  "geometry": {
    "type": "Point",
    "coordinates": [
      17.49037,
      49.19976
    ]
  }
}