{
  "type": "Feature",
  "properties": {
    "name": "Acuamanala",
    "country": "MX",
    "subdivision": "29",
    "timezone": "America/Mexico_City"
  },
  "geometry": {
    "type": "Point",
    "coordinates": [
      -98.20056,
      19.22361
    ]
  }
}