{
  "type": "Feature",
  "properties": {
    "name": "Acuitlapilco",
    "country": "MX",
    "subdivision": "29",
    "timezone": "America/Mexico_City"
  },
  "geometry": {
    "type": "Point",
    "coordinates": [
      -98.23542,
      19.27333
    ]
  }
}