{
  "type": "Feature",
  "properties": {
    "name": "Colonia Venustiano Carranza",
    "country": "MX",
    "subdivision": "29",
    "timezone": "America/Mexico_City"
  },
  "geometry": {
    "type": "Point",
    "coordinates": [
      -98.05822,
      19.40005
    ]
  }
}