{
  "type": "Feature",
  "properties": {
    "name": "Colonia Ignacio Allende",
    "country": "MX",
    "subdivision": "29",
    "timezone": "America/Mexico_City"
  },
  "geometry": {
    "type": "Point",
    "coordinates": [
      -97.78389,
      19.35667
    ]
  }
}