{
  "type": "Feature",
  "properties": {
    "name": "Concepción Hidalgo",
    "country": "MX",
    "subdivision": "29",
    "timezone": "America/Mexico_City"
  },
  "geometry": {
    "type": "Point",
    "coordinates": [
      -97.81951,
      19.3981
    ]
  }
}