{
  "type": "Feature",
  "properties": {
    "name": "Concepción Chimalpa",
    "country": "MX",
    "subdivision": "29",
    "timezone": "America/Mexico_City"
  },
  "geometry": {
    "type": "Point",
    "coordinates": [
      -98.19806,
      19.21639
    ]
  }
}