{
  "type": "Feature",
  "properties": {
    "name": "Huamantla",
    "country": "MX",
    "subdivision": "29",
    "timezone": "America/Mexico_City"
  },
  "geometry": {
    "type": "Point",
    "coordinates": [
      -97.9252,
      19.31451
    ]
  }
}