{
  "type": "Feature",
  "properties": {
    "name": "José María Morelos",
    "country": "MX",
    "subdivision": "29",
    "timezone": "America/Mexico_City"
  },
  "geometry": {
    "type": "Point",
    "coordinates": [
      -98.1587,
      19.46571
    ]
  }
}