{
  "type": "Feature",
  "properties": {
    "name": "Los Reyes Quiahuixtlan",
    "country": "MX",
    "subdivision": "29",
    "timezone": "America/Mexico_City"
  },
  "geometry": {
    "type": "Point",
    "coordinates": [
      -98.25155,
      19.33955
    ]
  }
}