{
  "type": "Feature",
  "properties": {
    "name": "Mazatecochco",
    "country": "MX",
    "subdivision": "29",
    "timezone": "America/Mexico_City"
  },
  "geometry": {
    "type": "Point",
    "coordinates": [
      -98.18677,
      19.17865
    ]
  }
}