{
  "type": "Feature",
  "properties": {
    "name": "Nicolás Bravo",
    "country": "MX",
    "subdivision": "29",
    "timezone": "America/Mexico_City"
  },
  "geometry": {
    "type": "Point",
    "coordinates": [
      -97.96759,
      19.42213
    ]
  }
}