{
  "type": "Feature",
  "properties": {
    "name": "San Hipólito Chimalpa",
    "country": "MX",
    "subdivision": "29",
    "timezone": "America/Mexico_City"
  },
  "geometry": {
    "type": "Point",
    "coordinates": [
      -98.25004,
      19.31963
    ]
  }
}