{
  "type": "Feature",
  "properties": {
    "name": "San Matías Tepetomatitlán",
    "country": "MX",
    "subdivision": "29",
    "timezone": "America/Mexico_City"
  },
  "geometry": {
    "type": "Point",
    "coordinates": [
      -98.1949,
      19.35389
    ]
  }
}