{
  "type": "Feature",
  "properties": {
    "name": "San Pedro Tlacotepec",
    "country": "MX",
    "subdivision": "29",
    "timezone": "America/Mexico_City"
  },
  "geometry": {
    "type": "Point",
    "coordinates": [
      -98.04589,
      19.39579
    ]
  }
}