{
  "type": "Feature",
  "properties": {
    "name": "San Pedro Xochiteotla",
    "country": "MX",
    "subdivision": "29",
    "timezone": "America/Mexico_City"
  },
  "geometry": {
    "type": "Point",
    "coordinates": [
      -98.13858,
      19.30788
    ]
  }
}