{
  "type": "Feature",
  "properties": {
    "name": "San Pedro Muñoztla",
    "country": "MX",
    "subdivision": "29",
    "timezone": "America/Mexico_City"
  },
  "geometry": {
    "type": "Point",
    "coordinates": [
      -98.16693,
      19.28167
    ]
  }
}