{
  "type": "Feature",
  "properties": {
    "name": "San Bartolomé Tenango",
    "country": "MX",
    "subdivision": "29",
    "timezone": "America/Mexico_City"
  },
  "geometry": {
    "type": "Point",
    "coordinates": [
      -98.29172,
      19.25253
    ]
  }
}