{
  "type": "Feature",
  "properties": {
    "name": "Santiago Tepeticpac",
    "country": "MX",
    "subdivision": "29",
    "timezone": "America/Mexico_City"
  },
  "geometry": {
    "type": "Point",
    "coordinates": [
      -98.22692,
      19.33476
    ]
  }
}