{
  "type": "Feature",
  "properties": {
    "name": "Santa Isabel Xiloxoxtla",
    "country": "MX",
    "subdivision": "29",
    "timezone": "America/Mexico_City"
  },
  "geometry": {
    "type": "Point",
    "coordinates": [
      -98.21399,
      19.26786
    ]
  }
}