{
  "type": "Feature",
  "properties": {
    "name": "Tenancingo",
    "country": "MX",
    "subdivision": "29",
    "timezone": "America/Mexico_City"
  },
  "geometry": {
    "type": "Point",
    "coordinates": [
      -98.20132,
      19.14725
    ]
  }
}