{
  "type": "Feature",
  "properties": {
    "name": "Tetlanohcán",
    "country": "MX",
    "subdivision": "29",
    "timezone": "America/Mexico_City"
  },
  "geometry": {
    "type": "Point",
    "coordinates": [
      -98.16433,
      19.2603
    ]
  }
}