{
  "type": "Feature",
  "properties": {
    "name": "Tetla",
    "country": "MX",
    "subdivision": "29",
    "timezone": "America/Mexico_City"
  },
  "geometry": {
    "type": "Point",
    "coordinates": [
      -98.10325,
      19.44204
    ]
  }
}