{
  "type": "Feature",
  "properties": {
    "name": "Villa de El Carmen Tequexquitla",
    "country": "MX",
    "subdivision": "29",
    "timezone": "America/Mexico_City"
  },
  "geometry": {
    "type": "Point",
    "coordinates": [
      -97.6535,
      19.32426
    ]
  }
}