{
  "type": "Feature",
  "properties": {
    "name": "Zumpango",
    "country": "MX",
    "subdivision": "29",
    "timezone": "America/Mexico_City"
  },
  "geometry": {
    "type": "Point",
    "coordinates": [
      -98.22407,
      19.5577
    ]
  }
}