{
  "type": "Feature",
  "properties": {
    "name": "Besisahar",
    "country": "NP",
    "subdivision": "6",
    "timezone": "Asia/Kathmandu"
  },
  "geometry": {
    "type": "Point",
    "coordinates": [
      82.41278,
      28.23417
    ]
  }
}