{
  "type": "Feature",
  "properties": {
    "name": "Hinvi",
    "country": "BJ",
    "subdivision": "09",
    "timezone": "Africa/Porto-Novo"
  },
  "geometry": {
    "type": "Point",
    "coordinates": [
      2.16667,
      6.76667
    ]
  }
}