{
  "type": "Feature",
  "properties": {
    "name": "Aleksandrov",
    "country": "RU",
    "subdivision": "83",
    "timezone": "Europe/Moscow"
  },
  "geometry": {
    "type": "Point",
    "coordinates": [
      38.71216,
      56.39516
    ]
  }
}