{
  "type": "Feature",
  "properties": {
    "name": "Kovrov",
    "country": "RU",
    "subdivision": "83",
    "timezone": "Europe/Moscow"
  },
  "geometry": {
    "type": "Point",
    "coordinates": [
      41.31917,
      56.35722
    ]
  }
}