{
  "type": "Feature",
  "properties": {
    "name": "Novki",
    "country": "RU",
    "subdivision": "83",
    "timezone": "Europe/Moscow"
  },
  "geometry": {
    "type": "Point",
    "coordinates": [
      41.08655,
      56.36386
    ]
  }
}