{
  "type": "Feature",
  "properties": {
    "name": "Sélibaby",
    "country": "MR",
    "subdivision": "10",
    "timezone": "Africa/Nouakchott"
  },
  "geometry": {
    "type": "Point",
    "coordinates": [
      -12.1843,
      15.15846
    ]
  }
}