{
  "type": "Feature",
  "properties": {
    "name": "Băseşti",
    "country": "RO",
    "subdivision": "25",
    "timezone": "Europe/Bucharest"
  },
  "geometry": {
    "type": "Point",
    "coordinates": [
      23.15,
      47.48333
    ]
  }
}