{
  "type": "Feature",
  "properties": {
    "name": "Cupşeni",
    "country": "RO",
    "subdivision": "25",
    "timezone": "Europe/Bucharest"
  },
  "geometry": {
    "type": "Point",
    "coordinates": [
      23.93333,
      47.55
    ]
  }
}