{
  "type": "Feature",
  "properties": {
    "name": "Dragomireşti",
    "country": "RO",
    "subdivision": "25",
    "timezone": "Europe/Bucharest"
  },
  "geometry": {
    "type": "Point",
    "coordinates": [
      24.29111,
      47.66839
    ]
  }
}