{
  "type": "Feature",
  "properties": {
    "name": "Lăpușel",
    "country": "RO",
    "subdivision": "25",
    "timezone": "Europe/Bucharest"
  },
  "geometry": {
    "type": "Point",
    "coordinates": [
      23.47913,
      47.6183
    ]
  }
}