{
  "type": "Feature",
  "properties": {
    "name": "Tăuții-Măgherăuș",
    "country": "RO",
    "subdivision": "25",
    "timezone": "Europe/Bucharest"
  },
  "geometry": {
    "type": "Point",
    "coordinates": [
      23.48333,
      47.65
    ]
  }
}