{
  "type": "Feature",
  "properties": {
    "name": "Karapürçek",
    "country": "TR",
    "subdivision": "54",
    "timezone": "Europe/Istanbul"
  },
  "geometry": {
    "type": "Point",
    "coordinates": [
      30.53944,
      40.64194
    ]
  }
}