{
  "type": "Feature",
  "properties": {
    "name": "Sapanca",
    "country": "TR",
    "subdivision": "54",
    "timezone": "Europe/Istanbul"
  },
  "geometry": {
    "type": "Point",
    "coordinates": [
      30.26738,
      40.69141
    ]
  }
}