{
  "type": "Feature",
  "properties": {
    "name": "Belousovka",
    "country": "KZ",
    "subdivision": "15",
    "timezone": "Asia/Almaty"
  },
  "geometry": {
    "type": "Point",
    "coordinates": [
      82.52481,
      50.13287
    ]
  }
}