{
  "type": "Feature",
  "properties": {
    "name": "Glubokoye",
    "country": "KZ",
    "subdivision": "15",
    "timezone": "Asia/Almaty"
  },
  "geometry": {
    "type": "Point",
    "coordinates": [
      82.31114,
      50.13887
    ]
  }
}