{
  "type": "Feature",
  "properties": {
    "name": "Suykbulak",
    "country": "KZ",
    "subdivision": "15",
    "timezone": "Asia/Almaty"
  },
  "geometry": {
    "type": "Point",
    "coordinates": [
      81.04854,
      49.70837
    ]
  }
}