{
  "type": "Feature",
  "properties": {
    "name": "Kuala Lumpur",
    "country": "MY",
    "subdivision": "14",
    "timezone": "Asia/Kuala_Lumpur"
  },
  "geometry": {
    "type": "Point",
    "coordinates": [
      101.68653,
      3.1412
    ]
  }
}