{
  "type": "Feature",
  "properties": {
    "name": "Arad",
    "country": "RO",
    "subdivision": "02",
    "timezone": "Europe/Bucharest"
  },
  "geometry": {
    "type": "Point",
    "coordinates": [
      21.31667,
      46.18333
    ]
  }
}