{
  "type": "Feature",
  "properties": {
    "name": "Bârsa",
    "country": "RO",
    "subdivision": "02",
    "timezone": "Europe/Bucharest"
  },
  "geometry": {
    "type": "Point",
    "coordinates": [
      22.06667,
      46.38333
    ]
  }
}