{
  "type": "Feature",
  "properties": {
    "name": "Chier",
    "country": "RO",
    "subdivision": "02",
    "timezone": "Europe/Bucharest"
  },
  "geometry": {
    "type": "Point",
    "coordinates": [
      21.82488,
      46.34199
    ]
  }
}