{
  "type": "Feature",
  "properties": {
    "name": "Dorgoş",
    "country": "RO",
    "subdivision": "02",
    "timezone": "Europe/Bucharest"
  },
  "geometry": {
    "type": "Point",
    "coordinates": [
      21.83333,
      46.05
    ]
  }
}