{
  "type": "Feature",
  "properties": {
    "name": "Gurba",
    "country": "RO",
    "subdivision": "02",
    "timezone": "Europe/Bucharest"
  },
  "geometry": {
    "type": "Point",
    "coordinates": [
      21.78789,
      46.46756
    ]
  }
}