{
  "type": "Feature",
  "properties": {
    "name": "Ineu",
    "country": "RO",
    "subdivision": "02",
    "timezone": "Europe/Bucharest"
  },
  "geometry": {
    "type": "Point",
    "coordinates": [
      21.84048,
      46.43372
    ]
  }
}