{
  "type": "Feature",
  "properties": {
    "name": "Satu Mare",
    "country": "RO",
    "subdivision": "02",
    "timezone": "Europe/Bucharest"
  },
  "geometry": {
    "type": "Point",
    "coordinates": [
      20.95826,
      46.06628
    ]
  }
}