{
  "type": "Feature",
  "properties": {
    "name": "Şiria",
    "country": "RO",
    "subdivision": "02",
    "timezone": "Europe/Bucharest"
  },
  "geometry": {
    "type": "Point",
    "coordinates": [
      21.63333,
      46.26667
    ]
  }
}