{
  "type": "Feature",
  "properties": {
    "name": "Țipar",
    "country": "RO",
    "subdivision": "02",
    "timezone": "Europe/Bucharest"
  },
  "geometry": {
    "type": "Point",
    "coordinates": [
      21.63431,
      46.47563
    ]
  }
}