{
  "type": "Feature",
  "properties": {
    "name": "Boaco",
    "country": "NI",
    "subdivision": "01",
    "timezone": "America/Managua"
  },
  "geometry": {
    "type": "Point",
    "coordinates": [
      -85.6586,
      12.47224
    ]
  }
}