{
  "type": "Feature",
  "properties": {
    "name": "Lærdalsøyri",
    "country": "NO",
    "subdivision": "46",
    "timezone": "Europe/Oslo"
  },
  "geometry": {
    "type": "Point",
    "coordinates": [
      7.47374,
      61.10001
    ]
  }
}