{
  "type": "Feature",
  "properties": {
    "name": "Šibenik",
    "country": "HR",
    "subdivision": "13",
    "timezone": "Europe/Zagreb"
  },
  "geometry": {
    "type": "Point",
    "coordinates": [
      15.8942,
      43.73429
    ]
  }
}