{
  "type": "Feature",
  "properties": {
    "name": "Hikone",
    "country": "JP",
    "subdivision": "35",
    "timezone": "Asia/Tokyo"
  },
  "geometry": {
    "type": "Point",
    "coordinates": [
      136.25,
      35.25
    ]
  }
}