{
  "type": "Feature",
  "properties": {
    "name": "Moriyama",
    "country": "JP",
    "subdivision": "35",
    "timezone": "Asia/Tokyo"
  },
  "geometry": {
    "type": "Point",
    "coordinates": [
      135.98333,
      35.06667
    ]
  }
}