{
  "type": "Feature",
  "properties": {
    "name": "Albshausen",
    "country": "DE",
    "subdivision": "05",
    "timezone": "Europe/Berlin"
  },
  "geometry": {
    "type": "Point",
    "coordinates": [
      8.43784,
      50.54431
    ]
  }
}