{
  "type": "Feature",
  "properties": {
    "name": "Bad König",
    "country": "DE",
    "subdivision": "05",
    "timezone": "Europe/Berlin"
  },
  "geometry": {
    "type": "Point",
    "coordinates": [
      9.0075,
      49.7432
    ]
  }
}