{
  "type": "Feature",
  "properties": {
    "name": "Bad Vilbel",
    "country": "DE",
    "subdivision": "05",
    "timezone": "Europe/Berlin"
  },
  "geometry": {
    "type": "Point",
    "coordinates": [
      8.73756,
      50.17866
    ]
  }
}