{
  "type": "Feature",
  "properties": {
    "name": "Bad Nauheim",
    "country": "DE",
    "subdivision": "05",
    "timezone": "Europe/Berlin"
  },
  "geometry": {
    "type": "Point",
    "coordinates": [
      8.73859,
      50.36463
    ]
  }
}