{
  "type": "Feature",
  "properties": {
    "name": "Bad Soden-Salmünster",
    "country": "DE",
    "subdivision": "05",
    "timezone": "Europe/Berlin"
  },
  "geometry": {
    "type": "Point",
    "coordinates": [
      9.36705,
      50.27574
    ]
  }
}