{
  "type": "Feature",
  "properties": {
    "name": "Bad Schwalbach",
    "country": "DE",
    "subdivision": "05",
    "timezone": "Europe/Berlin"
  },
  "geometry": {
    "type": "Point",
    "coordinates": [
      8.06964,
      50.14196
    ]
  }
}