{
  "type": "Feature",
  "properties": {
    "name": "Bad Homburg vor der Höhe",
    "country": "DE",
    "subdivision": "05",
    "timezone": "Europe/Berlin"
  },
  "geometry": {
    "type": "Point",
    "coordinates": [
      8.61816,
      50.22683
    ]
  }
}