{
  "type": "Feature",
  "properties": {
    "name": "Battenberg",
    "country": "DE",
    "subdivision": "05",
    "timezone": "Europe/Berlin"
  },
  "geometry": {
    "type": "Point",
    "coordinates": [
      8.64603,
      51.01391
    ]
  }
}