{
  "type": "Feature",
  "properties": {
    "name": "Bischofsheim",
    "country": "DE",
    "subdivision": "05",
    "timezone": "Europe/Berlin"
  },
  "geometry": {
    "type": "Point",
    "coordinates": [
      8.36722,
      49.99389
    ]
  }
}