{
  "type": "Feature",
  "properties": {
    "name": "Braunfels",
    "country": "DE",
    "subdivision": "05",
    "timezone": "Europe/Berlin"
  },
  "geometry": {
    "type": "Point",
    "coordinates": [
      8.38918,
      50.51545
    ]
  }
}