{
  "type": "Feature",
  "properties": {
    "name": "Breitenbach",
    "country": "DE",
    "subdivision": "05",
    "timezone": "Europe/Berlin"
  },
  "geometry": {
    "type": "Point",
    "coordinates": [
      9.78285,
      50.95655
    ]
  }
}