{
  "type": "Feature",
  "properties": {
    "name": "Brensbach",
    "country": "DE",
    "subdivision": "05",
    "timezone": "Europe/Berlin"
  },
  "geometry": {
    "type": "Point",
    "coordinates": [
      8.88444,
      49.77389
    ]
  }
}