{
  "type": "Feature",
  "properties": {
    "name": "Burghaun",
    "country": "DE",
    "subdivision": "05",
    "timezone": "Europe/Berlin"
  },
  "geometry": {
    "type": "Point",
    "coordinates": [
      9.72453,
      50.69684
    ]
  }
}