{
  "type": "Feature",
  "properties": {
    "name": "Cornberg",
    "country": "DE",
    "subdivision": "05",
    "timezone": "Europe/Berlin"
  },
  "geometry": {
    "type": "Point",
    "coordinates": [
      9.86051,
      51.0416
    ]
  }
}