{
  "type": "Feature",
  "properties": {
    "name": "Dietzenbach",
    "country": "DE",
    "subdivision": "05",
    "timezone": "Europe/Berlin"
  },
  "geometry": {
    "type": "Point",
    "coordinates": [
      8.77783,
      50.00976
    ]
  }
}