{
  "type": "Feature",
  "properties": {
    "name": "Dillenburg",
    "country": "DE",
    "subdivision": "05",
    "timezone": "Europe/Berlin"
  },
  "geometry": {
    "type": "Point",
    "coordinates": [
      8.28699,
      50.74114
    ]
  }
}