{
  "type": "Feature",
  "properties": {
    "name": "Einhausen",
    "country": "DE",
    "subdivision": "05",
    "timezone": "Europe/Berlin"
  },
  "geometry": {
    "type": "Point",
    "coordinates": [
      8.54833,
      49.67667
    ]
  }
}