{
  "type": "Feature",
  "properties": {
    "name": "Eschborn",
    "country": "DE",
    "subdivision": "05",
    "timezone": "Europe/Berlin"
  },
  "geometry": {
    "type": "Point",
    "coordinates": [
      8.57111,
      50.14328
    ]
  }
}