{
  "type": "Feature",
  "properties": {
    "name": "Flieden",
    "country": "DE",
    "subdivision": "05",
    "timezone": "Europe/Berlin"
  },
  "geometry": {
    "type": "Point",
    "coordinates": [
      9.5666,
      50.42389
    ]
  }
}