{
  "type": "Feature",
  "properties": {
    "name": "Friedewald",
    "country": "DE",
    "subdivision": "05",
    "timezone": "Europe/Berlin"
  },
  "geometry": {
    "type": "Point",
    "coordinates": [
      9.86667,
      50.88333
    ]
  }
}