{
  "type": "Feature",
  "properties": {
    "name": "Fuldatal",
    "country": "DE",
    "subdivision": "05",
    "timezone": "Europe/Berlin"
  },
  "geometry": {
    "type": "Point",
    "coordinates": [
      9.56667,
      51.38333
    ]
  }
}