{
  "type": "Feature",
  "properties": {
    "name": "Helsa",
    "country": "DE",
    "subdivision": "05",
    "timezone": "Europe/Berlin"
  },
  "geometry": {
    "type": "Point",
    "coordinates": [
      9.68872,
      51.25981
    ]
  }
}