{
  "type": "Feature",
  "properties": {
    "name": "Herbstein",
    "country": "DE",
    "subdivision": "05",
    "timezone": "Europe/Berlin"
  },
  "geometry": {
    "type": "Point",
    "coordinates": [
      9.34592,
      50.56105
    ]
  }
}