{
  "type": "Feature",
  "properties": {
    "name": "Hungen",
    "country": "DE",
    "subdivision": "05",
    "timezone": "Europe/Berlin"
  },
  "geometry": {
    "type": "Point",
    "coordinates": [
      8.89326,
      50.47368
    ]
  }
}