{
  "type": "Feature",
  "properties": {
    "name": "Karben",
    "country": "DE",
    "subdivision": "05",
    "timezone": "Europe/Berlin"
  },
  "geometry": {
    "type": "Point",
    "coordinates": [
      8.77155,
      50.23019
    ]
  }
}