{
  "type": "Feature",
  "properties": {
    "name": "Kefenrod",
    "country": "DE",
    "subdivision": "05",
    "timezone": "Europe/Berlin"
  },
  "geometry": {
    "type": "Point",
    "coordinates": [
      9.21141,
      50.34475
    ]
  }
}