{
  "type": "Feature",
  "properties": {
    "name": "Kelkheim (Taunus)",
    "country": "DE",
    "subdivision": "05",
    "timezone": "Europe/Berlin"
  },
  "geometry": {
    "type": "Point",
    "coordinates": [
      8.4502,
      50.13703
    ]
  }
}