{
  "type": "Feature",
  "properties": {
    "name": "Lampertheim",
    "country": "DE",
    "subdivision": "05",
    "timezone": "Europe/Berlin"
  },
  "geometry": {
    "type": "Point",
    "coordinates": [
      8.4725,
      49.59786
    ]
  }
}