{
  "type": "Feature",
  "properties": {
    "name": "Langenselbold",
    "country": "DE",
    "subdivision": "05",
    "timezone": "Europe/Berlin"
  },
  "geometry": {
    "type": "Point",
    "coordinates": [
      9.04003,
      50.17657
    ]
  }
}