{
  "type": "Feature",
  "properties": {
    "name": "Leun",
    "country": "DE",
    "subdivision": "05",
    "timezone": "Europe/Berlin"
  },
  "geometry": {
    "type": "Point",
    "coordinates": [
      8.35836,
      50.55129
    ]
  }
}