{
  "type": "Feature",
  "properties": {
    "name": "Melsungen",
    "country": "DE",
    "subdivision": "05",
    "timezone": "Europe/Berlin"
  },
  "geometry": {
    "type": "Point",
    "coordinates": [
      9.55236,
      51.13029
    ]
  }
}