{
  "type": "Feature",
  "properties": {
    "name": "Mörlenbach",
    "country": "DE",
    "subdivision": "05",
    "timezone": "Europe/Berlin"
  },
  "geometry": {
    "type": "Point",
    "coordinates": [
      8.73472,
      49.59917
    ]
  }
}