{
  "type": "Feature",
  "properties": {
    "name": "Münchhausen",
    "country": "DE",
    "subdivision": "05",
    "timezone": "Europe/Berlin"
  },
  "geometry": {
    "type": "Point",
    "coordinates": [
      8.71837,
      50.96081
    ]
  }
}