{
  "type": "Feature",
  "properties": {
    "name": "Neukirchen",
    "country": "DE",
    "subdivision": "05",
    "timezone": "Europe/Berlin"
  },
  "geometry": {
    "type": "Point",
    "coordinates": [
      9.34655,
      50.86906
    ]
  }
}