{
  "type": "Feature",
  "properties": {
    "name": "Nieder-Florstadt",
    "country": "DE",
    "subdivision": "05",
    "timezone": "Europe/Berlin"
  },
  "geometry": {
    "type": "Point",
    "coordinates": [
      8.86166,
      50.3162
    ]
  }
}