{
  "type": "Feature",
  "properties": {
    "name": "Offenbach",
    "country": "DE",
    "subdivision": "05",
    "timezone": "Europe/Berlin"
  },
  "geometry": {
    "type": "Point",
    "coordinates": [
      8.76647,
      50.10061
    ]
  }
}