{
  "type": "Feature",
  "properties": {
    "name": "Pfungstadt",
    "country": "DE",
    "subdivision": "05",
    "timezone": "Europe/Berlin"
  },
  "geometry": {
    "type": "Point",
    "coordinates": [
      8.60307,
      49.80557
    ]
  }
}