{
  "type": "Feature",
  "properties": {
    "name": "Philippsthal",
    "country": "DE",
    "subdivision": "05",
    "timezone": "Europe/Berlin"
  },
  "geometry": {
    "type": "Point",
    "coordinates": [
      10.00906,
      50.83948
    ]
  }
}