{
  "type": "Feature",
  "properties": {
    "name": "Rockenberg",
    "country": "DE",
    "subdivision": "05",
    "timezone": "Europe/Berlin"
  },
  "geometry": {
    "type": "Point",
    "coordinates": [
      8.73688,
      50.4305
    ]
  }
}