{
  "type": "Feature",
  "properties": {
    "name": "Rosbach vor der Höhe",
    "country": "DE",
    "subdivision": "05",
    "timezone": "Europe/Berlin"
  },
  "geometry": {
    "type": "Point",
    "coordinates": [
      8.68976,
      50.30332
    ]
  }
}