{
  "type": "Feature",
  "properties": {
    "name": "Schlüchtern",
    "country": "DE",
    "subdivision": "05",
    "timezone": "Europe/Berlin"
  },
  "geometry": {
    "type": "Point",
    "coordinates": [
      9.52532,
      50.34891
    ]
  }
}