{
  "type": "Feature",
  "properties": {
    "name": "Schotten",
    "country": "DE",
    "subdivision": "05",
    "timezone": "Europe/Berlin"
  },
  "geometry": {
    "type": "Point",
    "coordinates": [
      9.12516,
      50.50346
    ]
  }
}