{
  "type": "Feature",
  "properties": {
    "name": "Seeheim-Jugenheim",
    "country": "DE",
    "subdivision": "05",
    "timezone": "Europe/Berlin"
  },
  "geometry": {
    "type": "Point",
    "coordinates": [
      8.65194,
      49.765
    ]
  }
}