{
  "type": "Feature",
  "properties": {
    "name": "Staufenberg",
    "country": "DE",
    "subdivision": "05",
    "timezone": "Europe/Berlin"
  },
  "geometry": {
    "type": "Point",
    "coordinates": [
      8.73158,
      50.66197
    ]
  }
}