{
  "type": "Feature",
  "properties": {
    "name": "Steeden",
    "country": "DE",
    "subdivision": "05",
    "timezone": "Europe/Berlin"
  },
  "geometry": {
    "type": "Point",
    "coordinates": [
      8.12748,
      50.41539
    ]
  }
}