{
  "type": "Feature",
  "properties": {
    "name": "Usingen",
    "country": "DE",
    "subdivision": "05",
    "timezone": "Europe/Berlin"
  },
  "geometry": {
    "type": "Point",
    "coordinates": [
      8.53688,
      50.33554
    ]
  }
}