{
  "type": "Feature",
  "properties": {
    "name": "Wächtersbach",
    "country": "DE",
    "subdivision": "05",
    "timezone": "Europe/Berlin"
  },
  "geometry": {
    "type": "Point",
    "coordinates": [
      9.29564,
      50.25511
    ]
  }
}