{
  "type": "Feature",
  "properties": {
    "name": "Waldbrunn",
    "country": "DE",
    "subdivision": "05",
    "timezone": "Europe/Berlin"
  },
  "geometry": {
    "type": "Point",
    "coordinates": [
      8.10812,
      50.51875
    ]
  }
}