{
  "type": "Feature",
  "properties": {
    "name": "Wehrda",
    "country": "DE",
    "subdivision": "05",
    "timezone": "Europe/Berlin"
  },
  "geometry": {
    "type": "Point",
    "coordinates": [
      8.7556,
      50.83814
    ]
  }
}