{
  "type": "Feature",
  "properties": {
    "name": "Weilmünster",
    "country": "DE",
    "subdivision": "05",
    "timezone": "Europe/Berlin"
  },
  "geometry": {
    "type": "Point",
    "coordinates": [
      8.37673,
      50.43143
    ]
  }
}