{
  "type": "Feature",
  "properties": {
    "name": "Linfen",
    "country": "CN",
    "subdivision": "24",
    "timezone": "Asia/Shanghai"
  },
  "geometry": {
    "type": "Point",
    "coordinates": [
      111.51889,
      36.08889
    ]
  }
}