{
  "type": "Feature",
  "properties": {
    "name": "Isfara",
    "country": "TJ",
    "subdivision": "03",
    "timezone": "Asia/Dushanbe"
  },
  "geometry": {
    "type": "Point",
    "coordinates": [
      70.62526,
      40.12649
    ]
  }
}