{
  "type": "Feature",
  "properties": {
    "name": "Konsoy",
    "country": "TJ",
    "subdivision": "03",
    "timezone": "Asia/Dushanbe"
  },
  "geometry": {
    "type": "Point",
    "coordinates": [
      69.70245,
      40.49155
    ]
  }
}