{
  "type": "Feature",
  "properties": {
    "name": "Panjakent",
    "country": "TJ",
    "subdivision": "03",
    "timezone": "Asia/Dushanbe"
  },
  "geometry": {
    "type": "Point",
    "coordinates": [
      67.60931,
      39.49524
    ]
  }
}