{
  "type": "Feature",
  "properties": {
    "name": "Vorukh",
    "country": "TJ",
    "subdivision": "03",
    "timezone": "Asia/Dushanbe"
  },
  "geometry": {
    "type": "Point",
    "coordinates": [
      70.58012,
      39.85125
    ]
  }
}