{
  "type": "Feature",
  "properties": {
    "name": "Aura",
    "country": "FI",
    "subdivision": "02",
    "timezone": "Europe/Helsinki"
  },
  "geometry": {
    "type": "Point",
    "coordinates": [
      22.58755,
      60.6471
    ]
  }
}