{
  "type": "Feature",
  "properties": {
    "name": "Dragsfjärd",
    "country": "FI",
    "subdivision": "02",
    "timezone": "Europe/Helsinki"
  },
  "geometry": {
    "type": "Point",
    "coordinates": [
      22.48333,
      60.06667
    ]
  }
}