{
  "type": "Feature",
  "properties": {
    "name": "Kimito",
    "country": "FI",
    "subdivision": "02",
    "timezone": "Europe/Helsinki"
  },
  "geometry": {
    "type": "Point",
    "coordinates": [
      22.729,
      60.16047
    ]
  }
}