{
  "type": "Feature",
  "properties": {
    "name": "Laitila",
    "country": "FI",
    "subdivision": "02",
    "timezone": "Europe/Helsinki"
  },
  "geometry": {
    "type": "Point",
    "coordinates": [
      21.69765,
      60.87575
    ]
  }
}