{
  "type": "Feature",
  "properties": {
    "name": "Masku",
    "country": "FI",
    "subdivision": "02",
    "timezone": "Europe/Helsinki"
  },
  "geometry": {
    "type": "Point",
    "coordinates": [
      22.09883,
      60.57082
    ]
  }
}