{
  "type": "Feature",
  "properties": {
    "name": "Mellilä",
    "country": "FI",
    "subdivision": "02",
    "timezone": "Europe/Helsinki"
  },
  "geometry": {
    "type": "Point",
    "coordinates": [
      22.95,
      60.76667
    ]
  }
}