{
  "type": "Feature",
  "properties": {
    "name": "Pyhäranta",
    "country": "FI",
    "subdivision": "02",
    "timezone": "Europe/Helsinki"
  },
  "geometry": {
    "type": "Point",
    "coordinates": [
      21.45,
      60.95
    ]
  }
}