{
  "type": "Feature",
  "properties": {
    "name": "Vehmaa",
    "country": "FI",
    "subdivision": "02",
    "timezone": "Europe/Helsinki"
  },
  "geometry": {
    "type": "Point",
    "coordinates": [
      21.66667,
      60.68333
    ]
  }
}