{
  "type": "Feature",
  "properties": {
    "name": "Akbakay",
    "country": "KZ",
    "subdivision": "17",
    "timezone": "Asia/Almaty"
  },
  "geometry": {
    "type": "Point",
    "coordinates": [
      72.67169,
      45.1294
    ]
  }
}