{
  "type": "Feature",
  "properties": {
    "name": "Karatau",
    "country": "KZ",
    "subdivision": "17",
    "timezone": "Asia/Almaty"
  },
  "geometry": {
    "type": "Point",
    "coordinates": [
      70.46768,
      43.17869
    ]
  }
}