{
  "type": "Feature",
  "properties": {
    "name": "Bölcske",
    "country": "HU",
    "subdivision": "21",
    "timezone": "Europe/Budapest"
  },
  "geometry": {
    "type": "Point",
    "coordinates": [
      18.96736,
      46.74102
    ]
  }
}