{
  "type": "Feature",
  "properties": {
    "name": "Őcsény",
    "country": "HU",
    "subdivision": "21",
    "timezone": "Europe/Budapest"
  },
  "geometry": {
    "type": "Point",
    "coordinates": [
      18.75749,
      46.3137
    ]
  }
}