{
  "type": "Feature",
  "properties": {
    "name": "Simontornya",
    "country": "HU",
    "subdivision": "21",
    "timezone": "Europe/Budapest"
  },
  "geometry": {
    "type": "Point",
    "coordinates": [
      18.5549,
      46.75462
    ]
  }
}