{
  "type": "Feature",
  "properties": {
    "name": "Chabahar",
    "country": "IR",
    "subdivision": "04",
    "timezone": "Asia/Tehran"
  },
  "geometry": {
    "type": "Point",
    "coordinates": [
      60.643,
      25.2919
    ]
  }
}