{
  "type": "Feature",
  "properties": {
    "name": "Rajin",
    "country": "KP",
    "subdivision": "18",
    "timezone": "Asia/Pyongyang"
  },
  "geometry": {
    "type": "Point",
    "coordinates": [
      130.28308,
      42.25559
    ]
  }
}