{
  "type": "Feature",
  "properties": {
    "name": "Lawas",
    "country": "MY",
    "subdivision": "11",
    "timezone": "Asia/Kuching"
  },
  "geometry": {
    "type": "Point",
    "coordinates": [
      115.409,
      4.8604
    ]
  }
}