{
  "type": "Feature",
  "properties": {
    "name": "Clemency",
    "country": "LU",
    "subdivision": "CA",
    "timezone": "Europe/Luxembourg"
  },
  "geometry": {
    "type": "Point",
    "coordinates": [
      5.87583,
      49.59667
    ]
  }
}