{
  "type": "Feature",
  "properties": {
    "name": "Torghay",
    "country": "KZ",
    "subdivision": "13",
    "timezone": "Asia/Qostanay"
  },
  "geometry": {
    "type": "Point",
    "coordinates": [
      63.49806,
      49.63389
    ]
  }
}