{
  "type": "Feature",
  "properties": {
    "name": "Afton",
    "country": "US",
    "subdivision": "WY",
    "timezone": "America/Denver"
  },
  "geometry": {
    "type": "Point",
    "coordinates": [
      -110.93187,
      42.72493
    ]
  }
}