{
  "type": "Feature",
  "properties": {
    "name": "Basin",
    "country": "US",
    "subdivision": "WY",
    "timezone": "America/Denver"
  },
  "geometry": {
    "type": "Point",
    "coordinates": [
      -108.03899,
      44.37996
    ]
  }
}