{
  "type": "Feature",
  "properties": {
    "name": "Douglas",
    "country": "US",
    "subdivision": "WY",
    "timezone": "America/Denver"
  },
  "geometry": {
    "type": "Point",
    "coordinates": [
      -105.38221,
      42.75969
    ]
  }
}