{
  "type": "Feature",
  "properties": {
    "name": "Hoback",
    "country": "US",
    "subdivision": "WY",
    "timezone": "America/Denver"
  },
  "geometry": {
    "type": "Point",
    "coordinates": [
      -110.78381,
      43.28187
    ]
  }
}