{
  "type": "Feature",
  "properties": {
    "name": "Marbleton",
    "country": "US",
    "subdivision": "WY",
    "timezone": "America/Denver"
  },
  "geometry": {
    "type": "Point",
    "coordinates": [
      -110.10932,
      42.55355
    ]
  }
}