{
  "type": "Feature",
  "properties": {
    "name": "North Rock Springs",
    "country": "US",
    "subdivision": "WY",
    "timezone": "America/Denver"
  },
  "geometry": {
    "type": "Point",
    "coordinates": [
      -109.26568,
      41.64358
    ]
  }
}