{
  "type": "Feature",
  "properties": {
    "name": "Torrington",
    "country": "US",
    "subdivision": "WY",
    "timezone": "America/Denver"
  },
  "geometry": {
    "type": "Point",
    "coordinates": [
      -104.18439,
      42.06246
    ]
  }
}