{
  "type": "Feature",
  "properties": {
    "name": "Berlevåg",
    "country": "NO",
    "subdivision": "54",
    "timezone": "Europe/Oslo"
  },
  "geometry": {
    "type": "Point",
    "coordinates": [
      29.08636,
      70.85778
    ]
  }
}