{
  "type": "Feature",
  "properties": {
    "name": "Kirkenes",
    "country": "NO",
    "subdivision": "54",
    "timezone": "Europe/Oslo"
  },
  "geometry": {
    "type": "Point",
    "coordinates": [
      30.04578,
      69.72706
    ]
  }
}