{
  "type": "Feature",
  "properties": {
    "name": "Vadsø",
    "country": "NO",
    "subdivision": "54",
    "timezone": "Europe/Oslo"
  },
  "geometry": {
    "type": "Point",
    "coordinates": [
      29.74943,
      70.07348
    ]
  }
}