{
  "type": "Feature",
  "properties": {
    "name": "Aberdour",
    "country": "GB",
    "subdivision": "SCT",
    "timezone": "Europe/London"
  },
  "geometry": {
    "type": "Point",
    "coordinates": [
      -3.30058,
      56.05417
    ]
  }
}