{
  "type": "Feature",
  "properties": {
    "name": "Aberfeldy",
    "country": "GB",
    "subdivision": "SCT",
    "timezone": "Europe/London"
  },
  "geometry": {
    "type": "Point",
    "coordinates": [
      -3.86693,
      56.62196
    ]
  }
}