{
  "type": "Feature",
  "properties": {
    "name": "Aberdeen",
    "country": "GB",
    "subdivision": "SCT",
    "timezone": "Europe/London"
  },
  "geometry": {
    "type": "Point",
    "coordinates": [
      -2.09814,
      57.14369
    ]
  }
}