{
  "type": "Feature",
  "properties": {
    "name": "Alexandria",
    "country": "GB",
    "subdivision": "SCT",
    "timezone": "Europe/London"
  },
  "geometry": {
    "type": "Point",
    "coordinates": [
      -4.5864,
      55.99379
    ]
  }
}