{
  "type": "Feature",
  "properties": {
    "name": "Annan",
    "country": "GB",
    "subdivision": "SCT",
    "timezone": "Europe/London"
  },
  "geometry": {
    "type": "Point",
    "coordinates": [
      -3.25647,
      54.98839
    ]
  }
}