{
  "type": "Feature",
  "properties": {
    "name": "Ardersier",
    "country": "GB",
    "subdivision": "SCT",
    "timezone": "Europe/London"
  },
  "geometry": {
    "type": "Point",
    "coordinates": [
      -4.03784,
      57.56681
    ]
  }
}