{
  "type": "Feature",
  "properties": {
    "name": "Auchterarder",
    "country": "GB",
    "subdivision": "SCT",
    "timezone": "Europe/London"
  },
  "geometry": {
    "type": "Point",
    "coordinates": [
      -3.70692,
      56.29612
    ]
  }
}