{
  "type": "Feature",
  "properties": {
    "name": "Balerno",
    "country": "GB",
    "subdivision": "SCT",
    "timezone": "Europe/London"
  },
  "geometry": {
    "type": "Point",
    "coordinates": [
      -3.33975,
      55.88437
    ]
  }
}