{
  "type": "Feature",
  "properties": {
    "name": "Bankfoot",
    "country": "GB",
    "subdivision": "SCT",
    "timezone": "Europe/London"
  },
  "geometry": {
    "type": "Point",
    "coordinates": [
      -3.51707,
      56.50058
    ]
  }
}