{
  "type": "Feature",
  "properties": {
    "name": "Beauly",
    "country": "GB",
    "subdivision": "SCT",
    "timezone": "Europe/London"
  },
  "geometry": {
    "type": "Point",
    "coordinates": [
      -4.46144,
      57.48345
    ]
  }
}