{
  "type": "Feature",
  "properties": {
    "name": "Beith",
    "country": "GB",
    "subdivision": "SCT",
    "timezone": "Europe/London"
  },
  "geometry": {
    "type": "Point",
    "coordinates": [
      -4.6368,
      55.74923
    ]
  }
}