{
  "type": "Feature",
  "properties": {
    "name": "Bellsbank",
    "country": "GB",
    "subdivision": "SCT",
    "timezone": "Europe/London"
  },
  "geometry": {
    "type": "Point",
    "coordinates": [
      -4.39869,
      55.3131
    ]
  }
}