{
  "type": "Feature",
  "properties": {
    "name": "Biggar",
    "country": "GB",
    "subdivision": "SCT",
    "timezone": "Europe/London"
  },
  "geometry": {
    "type": "Point",
    "coordinates": [
      -3.52455,
      55.62297
    ]
  }
}