{
  "type": "Feature",
  "properties": {
    "name": "Cardross",
    "country": "GB",
    "subdivision": "SCT",
    "timezone": "Europe/London"
  },
  "geometry": {
    "type": "Point",
    "coordinates": [
      -4.65316,
      55.96184
    ]
  }
}