{
  "type": "Feature",
  "properties": {
    "name": "Carfin",
    "country": "GB",
    "subdivision": "SCT",
    "timezone": "Europe/London"
  },
  "geometry": {
    "type": "Point",
    "coordinates": [
      -3.96076,
      55.80502
    ]
  }
}