{
  "type": "Feature",
  "properties": {
    "name": "Carron",
    "country": "GB",
    "subdivision": "SCT",
    "timezone": "Europe/London"
  },
  "geometry": {
    "type": "Point",
    "coordinates": [
      -3.79251,
      56.02611
    ]
  }
}