{
  "type": "Feature",
  "properties": {
    "name": "Coatbridge",
    "country": "GB",
    "subdivision": "SCT",
    "timezone": "Europe/London"
  },
  "geometry": {
    "type": "Point",
    "coordinates": [
      -4.02469,
      55.86216
    ]
  }
}