{
  "type": "Feature",
  "properties": {
    "name": "Cowie",
    "country": "GB",
    "subdivision": "SCT",
    "timezone": "Europe/London"
  },
  "geometry": {
    "type": "Point",
    "coordinates": [
      -3.86753,
      56.07974
    ]
  }
}