{
  "type": "Feature",
  "properties": {
    "name": "Dalkeith",
    "country": "GB",
    "subdivision": "SCT",
    "timezone": "Europe/London"
  },
  "geometry": {
    "type": "Point",
    "coordinates": [
      -3.06806,
      55.89317
    ]
  }
}