{
  "type": "Feature",
  "properties": {
    "name": "Dalserf",
    "country": "GB",
    "subdivision": "SCT",
    "timezone": "Europe/London"
  },
  "geometry": {
    "type": "Point",
    "coordinates": [
      -3.91667,
      55.73333
    ]
  }
}