{
  "type": "Feature",
  "properties": {
    "name": "Denny",
    "country": "GB",
    "subdivision": "SCT",
    "timezone": "Europe/London"
  },
  "geometry": {
    "type": "Point",
    "coordinates": [
      -3.90812,
      56.0235
    ]
  }
}