{
  "type": "Feature",
  "properties": {
    "name": "Dreghorn",
    "country": "GB",
    "subdivision": "SCT",
    "timezone": "Europe/London"
  },
  "geometry": {
    "type": "Point",
    "coordinates": [
      -4.62226,
      55.60807
    ]
  }
}