{
  "type": "Feature",
  "properties": {
    "name": "Drumnadrochit",
    "country": "GB",
    "subdivision": "SCT",
    "timezone": "Europe/London"
  },
  "geometry": {
    "type": "Point",
    "coordinates": [
      -4.47989,
      57.33438
    ]
  }
}