{
  "type": "Feature",
  "properties": {
    "name": "Dunbar",
    "country": "GB",
    "subdivision": "SCT",
    "timezone": "Europe/London"
  },
  "geometry": {
    "type": "Point",
    "coordinates": [
      -2.51418,
      56.00062
    ]
  }
}