{
  "type": "Feature",
  "properties": {
    "name": "Dunlop",
    "country": "GB",
    "subdivision": "SCT",
    "timezone": "Europe/London"
  },
  "geometry": {
    "type": "Point",
    "coordinates": [
      -4.53622,
      55.71198
    ]
  }
}