{
  "type": "Feature",
  "properties": {
    "name": "Dunoon",
    "country": "GB",
    "subdivision": "SCT",
    "timezone": "Europe/London"
  },
  "geometry": {
    "type": "Point",
    "coordinates": [
      -4.92734,
      55.95031
    ]
  }
}