{
  "type": "Feature",
  "properties": {
    "name": "East Linton",
    "country": "GB",
    "subdivision": "SCT",
    "timezone": "Europe/London"
  },
  "geometry": {
    "type": "Point",
    "coordinates": [
      -2.65682,
      55.98737
    ]
  }
}