{
  "type": "Feature",
  "properties": {
    "name": "Edinburgh",
    "country": "GB",
    "subdivision": "SCT",
    "timezone": "Europe/London"
  },
  "geometry": {
    "type": "Point",
    "coordinates": [
      -3.19648,
      55.95206
    ]
  }
}