{
  "type": "Feature",
  "properties": {
    "name": "Eyemouth",
    "country": "GB",
    "subdivision": "SCT",
    "timezone": "Europe/London"
  },
  "geometry": {
    "type": "Point",
    "coordinates": [
      -2.0901,
      55.8713
    ]
  }
}