{
  "type": "Feature",
  "properties": {
    "name": "Fortrose",
    "country": "GB",
    "subdivision": "SCT",
    "timezone": "Europe/London"
  },
  "geometry": {
    "type": "Point",
    "coordinates": [
      -4.13263,
      57.58087
    ]
  }
}