{
  "type": "Feature",
  "properties": {
    "name": "Gartcosh",
    "country": "GB",
    "subdivision": "SCT",
    "timezone": "Europe/London"
  },
  "geometry": {
    "type": "Point",
    "coordinates": [
      -4.0817,
      55.88841
    ]
  }
}