{
  "type": "Feature",
  "properties": {
    "name": "Greenock",
    "country": "GB",
    "subdivision": "SCT",
    "timezone": "Europe/London"
  },
  "geometry": {
    "type": "Point",
    "coordinates": [
      -4.76121,
      55.94838
    ]
  }
}