{
  "type": "Feature",
  "properties": {
    "name": "Haddington",
    "country": "GB",
    "subdivision": "SCT",
    "timezone": "Europe/London"
  },
  "geometry": {
    "type": "Point",
    "coordinates": [
      -2.78332,
      55.95612
    ]
  }
}