{
  "type": "Feature",
  "properties": {
    "name": "Huntly",
    "country": "GB",
    "subdivision": "SCT",
    "timezone": "Europe/London"
  },
  "geometry": {
    "type": "Point",
    "coordinates": [
      -2.78608,
      57.44741
    ]
  }
}