{
  "type": "Feature",
  "properties": {
    "name": "Innerleithen",
    "country": "GB",
    "subdivision": "SCT",
    "timezone": "Europe/London"
  },
  "geometry": {
    "type": "Point",
    "coordinates": [
      -3.06301,
      55.61927
    ]
  }
}