{
  "type": "Feature",
  "properties": {
    "name": "Isle of Islay",
    "country": "GB",
    "subdivision": "SCT",
    "timezone": "Europe/London"
  },
  "geometry": {
    "type": "Point",
    "coordinates": [
      -6.23886,
      55.78526
    ]
  }
}