{
  "type": "Feature",
  "properties": {
    "name": "Keith",
    "country": "GB",
    "subdivision": "SCT",
    "timezone": "Europe/London"
  },
  "geometry": {
    "type": "Point",
    "coordinates": [
      -2.94811,
      57.53633
    ]
  }
}