{
  "type": "Feature",
  "properties": {
    "name": "Kemnay",
    "country": "GB",
    "subdivision": "SCT",
    "timezone": "Europe/London"
  },
  "geometry": {
    "type": "Point",
    "coordinates": [
      -2.44395,
      57.23573
    ]
  }
}