{
  "type": "Feature",
  "properties": {
    "name": "Kilcreggan",
    "country": "GB",
    "subdivision": "SCT",
    "timezone": "Europe/London"
  },
  "geometry": {
    "type": "Point",
    "coordinates": [
      -4.821,
      55.9846
    ]
  }
}