{
  "type": "Feature",
  "properties": {
    "name": "Kingussie",
    "country": "GB",
    "subdivision": "SCT",
    "timezone": "Europe/London"
  },
  "geometry": {
    "type": "Point",
    "coordinates": [
      -4.05231,
      57.07996
    ]
  }
}