{
  "type": "Feature",
  "properties": {
    "name": "Kingskettle",
    "country": "GB",
    "subdivision": "SCT",
    "timezone": "Europe/London"
  },
  "geometry": {
    "type": "Point",
    "coordinates": [
      -3.11693,
      56.26215
    ]
  }
}