{
  "type": "Feature",
  "properties": {
    "name": "Langholm",
    "country": "GB",
    "subdivision": "SCT",
    "timezone": "Europe/London"
  },
  "geometry": {
    "type": "Point",
    "coordinates": [
      -2.99889,
      55.15101
    ]
  }
}