{
  "type": "Feature",
  "properties": {
    "name": "Livingston",
    "country": "GB",
    "subdivision": "SCT",
    "timezone": "Europe/London"
  },
  "geometry": {
    "type": "Point",
    "coordinates": [
      -3.52261,
      55.90288
    ]
  }
}