{
  "type": "Feature",
  "properties": {
    "name": "Lochwinnoch",
    "country": "GB",
    "subdivision": "SCT",
    "timezone": "Europe/London"
  },
  "geometry": {
    "type": "Point",
    "coordinates": [
      -4.63034,
      55.79521
    ]
  }
}