{
  "type": "Feature",
  "properties": {
    "name": "Longniddry",
    "country": "GB",
    "subdivision": "SCT",
    "timezone": "Europe/London"
  },
  "geometry": {
    "type": "Point",
    "coordinates": [
      -2.89593,
      55.97543
    ]
  }
}