{
  "type": "Feature",
  "properties": {
    "name": "Longforgan",
    "country": "GB",
    "subdivision": "SCT",
    "timezone": "Europe/London"
  },
  "geometry": {
    "type": "Point",
    "coordinates": [
      -3.11437,
      56.45732
    ]
  }
}