{
  "type": "Feature",
  "properties": {
    "name": "Maryburgh",
    "country": "GB",
    "subdivision": "SCT",
    "timezone": "Europe/London"
  },
  "geometry": {
    "type": "Point",
    "coordinates": [
      -4.44178,
      57.5742
    ]
  }
}