{
  "type": "Feature",
  "properties": {
    "name": "Methven",
    "country": "GB",
    "subdivision": "SCT",
    "timezone": "Europe/London"
  },
  "geometry": {
    "type": "Point",
    "coordinates": [
      -3.57832,
      56.41737
    ]
  }
}