{
  "type": "Feature",
  "properties": {
    "name": "Mintlaw",
    "country": "GB",
    "subdivision": "SCT",
    "timezone": "Europe/London"
  },
  "geometry": {
    "type": "Point",
    "coordinates": [
      -2.00099,
      57.52414
    ]
  }
}