{
  "type": "Feature",
  "properties": {
    "name": "Montrose",
    "country": "GB",
    "subdivision": "SCT",
    "timezone": "Europe/London"
  },
  "geometry": {
    "type": "Point",
    "coordinates": [
      -2.46695,
      56.71683
    ]
  }
}