{
  "type": "Feature",
  "properties": {
    "name": "Newburgh",
    "country": "GB",
    "subdivision": "SCT",
    "timezone": "Europe/London"
  },
  "geometry": {
    "type": "Point",
    "coordinates": [
      -2.00449,
      57.31711
    ]
  }
}