{
  "type": "Feature",
  "properties": {
    "name": "Newmacher",
    "country": "GB",
    "subdivision": "SCT",
    "timezone": "Europe/London"
  },
  "geometry": {
    "type": "Point",
    "coordinates": [
      -2.18333,
      57.26667
    ]
  }
}