{
  "type": "Feature",
  "properties": {
    "name": "Newton Mearns",
    "country": "GB",
    "subdivision": "SCT",
    "timezone": "Europe/London"
  },
  "geometry": {
    "type": "Point",
    "coordinates": [
      -4.33339,
      55.77334
    ]
  }
}