{
  "type": "Feature",
  "properties": {
    "name": "Ochiltree",
    "country": "GB",
    "subdivision": "SCT",
    "timezone": "Europe/London"
  },
  "geometry": {
    "type": "Point",
    "coordinates": [
      -4.36782,
      55.45981
    ]
  }
}