{
  "type": "Feature",
  "properties": {
    "name": "Old Kilpatrick",
    "country": "GB",
    "subdivision": "SCT",
    "timezone": "Europe/London"
  },
  "geometry": {
    "type": "Point",
    "coordinates": [
      -4.45567,
      55.92241
    ]
  }
}