{
  "type": "Feature",
  "properties": {
    "name": "Ormiston",
    "country": "GB",
    "subdivision": "SCT",
    "timezone": "Europe/London"
  },
  "geometry": {
    "type": "Point",
    "coordinates": [
      -2.93985,
      55.91302
    ]
  }
}