{
  "type": "Feature",
  "properties": {
    "name": "Port Erroll",
    "country": "GB",
    "subdivision": "SCT",
    "timezone": "Europe/London"
  },
  "geometry": {
    "type": "Point",
    "coordinates": [
      -1.84596,
      57.41427
    ]
  }
}