{
  "type": "Feature",
  "properties": {
    "name": "Rosewell",
    "country": "GB",
    "subdivision": "SCT",
    "timezone": "Europe/London"
  },
  "geometry": {
    "type": "Point",
    "coordinates": [
      -3.13625,
      55.85075
    ]
  }
}