{
  "type": "Feature",
  "properties": {
    "name": "Sandbank",
    "country": "GB",
    "subdivision": "SCT",
    "timezone": "Europe/London"
  },
  "geometry": {
    "type": "Point",
    "coordinates": [
      -4.94973,
      55.98203
    ]
  }
}