{
  "type": "Feature",
  "properties": {
    "name": "Stenhousemuir",
    "country": "GB",
    "subdivision": "SCT",
    "timezone": "Europe/London"
  },
  "geometry": {
    "type": "Point",
    "coordinates": [
      -3.81462,
      56.02676
    ]
  }
}