{
  "type": "Feature",
  "properties": {
    "name": "Stonehouse",
    "country": "GB",
    "subdivision": "SCT",
    "timezone": "Europe/London"
  },
  "geometry": {
    "type": "Point",
    "coordinates": [
      -3.9878,
      55.69435
    ]
  }
}