{
  "type": "Feature",
  "properties": {
    "name": "Strathblane",
    "country": "GB",
    "subdivision": "SCT",
    "timezone": "Europe/London"
  },
  "geometry": {
    "type": "Point",
    "coordinates": [
      -4.30658,
      55.98596
    ]
  }
}