{
  "type": "Feature",
  "properties": {
    "name": "Strathpeffer",
    "country": "GB",
    "subdivision": "SCT",
    "timezone": "Europe/London"
  },
  "geometry": {
    "type": "Point",
    "coordinates": [
      -4.54195,
      57.58522
    ]
  }
}