{
  "type": "Feature",
  "properties": {
    "name": "Stromness",
    "country": "GB",
    "subdivision": "SCT",
    "timezone": "Europe/London"
  },
  "geometry": {
    "type": "Point",
    "coordinates": [
      -3.29601,
      58.96498
    ]
  }
}