{
  "type": "Feature",
  "properties": {
    "name": "Tarbolton",
    "country": "GB",
    "subdivision": "SCT",
    "timezone": "Europe/London"
  },
  "geometry": {
    "type": "Point",
    "coordinates": [
      -4.48648,
      55.51292
    ]
  }
}