{
  "type": "Feature",
  "properties": {
    "name": "Thornhill",
    "country": "GB",
    "subdivision": "SCT",
    "timezone": "Europe/London"
  },
  "geometry": {
    "type": "Point",
    "coordinates": [
      -3.76667,
      55.23333
    ]
  }
}