{
  "type": "Feature",
  "properties": {
    "name": "Torrance",
    "country": "GB",
    "subdivision": "SCT",
    "timezone": "Europe/London"
  },
  "geometry": {
    "type": "Point",
    "coordinates": [
      -4.21025,
      55.93995
    ]
  }
}