{
  "type": "Feature",
  "properties": {
    "name": "Troon",
    "country": "GB",
    "subdivision": "SCT",
    "timezone": "Europe/London"
  },
  "geometry": {
    "type": "Point",
    "coordinates": [
      -4.66335,
      55.54359
    ]
  }
}