{
  "type": "Feature",
  "properties": {
    "name": "Uddingston",
    "country": "GB",
    "subdivision": "SCT",
    "timezone": "Europe/London"
  },
  "geometry": {
    "type": "Point",
    "coordinates": [
      -4.08362,
      55.81971
    ]
  }
}