{
  "type": "Feature",
  "properties": {
    "name": "Ullapool",
    "country": "GB",
    "subdivision": "SCT",
    "timezone": "Europe/London"
  },
  "geometry": {
    "type": "Point",
    "coordinates": [
      -5.16039,
      57.89872
    ]
  }
}