{
  "type": "Feature",
  "properties": {
    "name": "Wemyss Bay",
    "country": "GB",
    "subdivision": "SCT",
    "timezone": "Europe/London"
  },
  "geometry": {
    "type": "Point",
    "coordinates": [
      -4.8895,
      55.87614
    ]
  }
}