{
  "type": "Feature",
  "properties": {
    "name": "Whitecraig",
    "country": "GB",
    "subdivision": "SCT",
    "timezone": "Europe/London"
  },
  "geometry": {
    "type": "Point",
    "coordinates": [
      -3.04231,
      55.91937
    ]
  }
}