{
  "type": "Feature",
  "properties": {
    "name": "Batié",
    "country": "BF",
    "subdivision": "13",
    "timezone": "Africa/Ouagadougou"
  },
  "geometry": {
    "type": "Point",
    "coordinates": [
      -2.91667,
      9.88333
    ]
  }
}