{
  "type": "Feature",
  "properties": {
    "name": "Diébougou",
    "country": "BF",
    "subdivision": "13",
    "timezone": "Africa/Ouagadougou"
  },
  "geometry": {
    "type": "Point",
    "coordinates": [
      -3.24967,
      10.96209
    ]
  }
}