{
  "type": "Feature",
  "properties": {
    "name": "Bouloupari",
    "country": "NC",
    "subdivision": "02",
    "timezone": "Pacific/Noumea"
  },
  "geometry": {
    "type": "Point",
    "coordinates": [
      166.05122,
      -21.86226
    ]
  }
}