{
  "type": "Feature",
  "properties": {
    "name": "Asau",
    "country": "WS",
    "subdivision": "11",
    "timezone": "Pacific/Apia"
  },
  "geometry": {
    "type": "Point",
    "coordinates": [
      -172.63784,
      -13.51963
    ]
  }
}