{
  "type": "Feature",
  "properties": {
    "name": "Tsévié",
    "country": "TG",
    "subdivision": "24",
    "timezone": "Africa/Lome"
  },
  "geometry": {
    "type": "Point",
    "coordinates": [
      1.21333,
      6.42611
    ]
  }
}