{
  "type": "Feature",
  "properties": {
    "name": "Bad Liebenwerda",
    "country": "DE",
    "subdivision": "11",
    "timezone": "Europe/Berlin"
  },
  "geometry": {
    "type": "Point",
    "coordinates": [
      13.39459,
      51.51826
    ]
  }
}