{
  "type": "Feature",
  "properties": {
    "name": "Bad Belzig",
    "country": "DE",
    "subdivision": "11",
    "timezone": "Europe/Berlin"
  },
  "geometry": {
    "type": "Point",
    "coordinates": [
      12.59272,
      52.14184
    ]
  }
}