{
  "type": "Feature",
  "properties": {
    "name": "Berkenbrück",
    "country": "DE",
    "subdivision": "11",
    "timezone": "Europe/Berlin"
  },
  "geometry": {
    "type": "Point",
    "coordinates": [
      14.15,
      52.35
    ]
  }
}