{
  "type": "Feature",
  "properties": {
    "name": "Cottbus",
    "country": "DE",
    "subdivision": "11",
    "timezone": "Europe/Berlin"
  },
  "geometry": {
    "type": "Point",
    "coordinates": [
      14.32888,
      51.75769
    ]
  }
}