{
  "type": "Feature",
  "properties": {
    "name": "Dallgow-Döberitz",
    "country": "DE",
    "subdivision": "11",
    "timezone": "Europe/Berlin"
  },
  "geometry": {
    "type": "Point",
    "coordinates": [
      13.05837,
      52.54269
    ]
  }
}