{
  "type": "Feature",
  "properties": {
    "name": "Forst",
    "country": "DE",
    "subdivision": "11",
    "timezone": "Europe/Berlin"
  },
  "geometry": {
    "type": "Point",
    "coordinates": [
      14.63971,
      51.73544
    ]
  }
}