{
  "type": "Feature",
  "properties": {
    "name": "Frankfurt (Oder)",
    "country": "DE",
    "subdivision": "11",
    "timezone": "Europe/Berlin"
  },
  "geometry": {
    "type": "Point",
    "coordinates": [
      14.55062,
      52.34714
    ]
  }
}