{
  "type": "Feature",
  "properties": {
    "name": "Groß Kreutz",
    "country": "DE",
    "subdivision": "11",
    "timezone": "Europe/Berlin"
  },
  "geometry": {
    "type": "Point",
    "coordinates": [
      12.7794,
      52.40281
    ]
  }
}