{
  "type": "Feature",
  "properties": {
    "name": "Groß Lindow",
    "country": "DE",
    "subdivision": "11",
    "timezone": "Europe/Berlin"
  },
  "geometry": {
    "type": "Point",
    "coordinates": [
      14.53333,
      52.23333
    ]
  }
}