{
  "type": "Feature",
  "properties": {
    "name": "Hohen Neuendorf",
    "country": "DE",
    "subdivision": "11",
    "timezone": "Europe/Berlin"
  },
  "geometry": {
    "type": "Point",
    "coordinates": [
      13.27775,
      52.67631
    ]
  }
}