{
  "type": "Feature",
  "properties": {
    "name": "Ketzin",
    "country": "DE",
    "subdivision": "11",
    "timezone": "Europe/Berlin"
  },
  "geometry": {
    "type": "Point",
    "coordinates": [
      12.8453,
      52.47809
    ]
  }
}