{
  "type": "Feature",
  "properties": {
    "name": "Lebus",
    "country": "DE",
    "subdivision": "11",
    "timezone": "Europe/Berlin"
  },
  "geometry": {
    "type": "Point",
    "coordinates": [
      14.53235,
      52.42719
    ]
  }
}