{
  "type": "Feature",
  "properties": {
    "name": "Marienwerder",
    "country": "DE",
    "subdivision": "11",
    "timezone": "Europe/Berlin"
  },
  "geometry": {
    "type": "Point",
    "coordinates": [
      13.59927,
      52.84208
    ]
  }
}