{
  "type": "Feature",
  "properties": {
    "name": "Nauen",
    "country": "DE",
    "subdivision": "11",
    "timezone": "Europe/Berlin"
  },
  "geometry": {
    "type": "Point",
    "coordinates": [
      12.87374,
      52.60701
    ]
  }
}