{
  "type": "Feature",
  "properties": {
    "name": "Neuhardenberg",
    "country": "DE",
    "subdivision": "11",
    "timezone": "Europe/Berlin"
  },
  "geometry": {
    "type": "Point",
    "coordinates": [
      14.23768,
      52.59601
    ]
  }
}