{
  "type": "Feature",
  "properties": {
    "name": "Petershagen",
    "country": "DE",
    "subdivision": "11",
    "timezone": "Europe/Berlin"
  },
  "geometry": {
    "type": "Point",
    "coordinates": [
      13.78748,
      52.52078
    ]
  }
}