{
  "type": "Feature",
  "properties": {
    "name": "Rauen",
    "country": "DE",
    "subdivision": "11",
    "timezone": "Europe/Berlin"
  },
  "geometry": {
    "type": "Point",
    "coordinates": [
      14.02797,
      52.33227
    ]
  }
}