{
  "type": "Feature",
  "properties": {
    "name": "Schenkendöbern",
    "country": "DE",
    "subdivision": "11",
    "timezone": "Europe/Berlin"
  },
  "geometry": {
    "type": "Point",
    "coordinates": [
      14.63541,
      51.95723
    ]
  }
}