{
  "type": "Feature",
  "properties": {
    "name": "Schönefeld",
    "country": "DE",
    "subdivision": "11",
    "timezone": "Europe/Berlin"
  },
  "geometry": {
    "type": "Point",
    "coordinates": [
      13.50374,
      52.38897
    ]
  }
}