{
  "type": "Feature",
  "properties": {
    "name": "Schulzendorf",
    "country": "DE",
    "subdivision": "11",
    "timezone": "Europe/Berlin"
  },
  "geometry": {
    "type": "Point",
    "coordinates": [
      13.59842,
      52.35818
    ]
  }
}