{
  "type": "Feature",
  "properties": {
    "name": "Sonnewalde",
    "country": "DE",
    "subdivision": "11",
    "timezone": "Europe/Berlin"
  },
  "geometry": {
    "type": "Point",
    "coordinates": [
      13.6473,
      51.69223
    ]
  }
}