{
  "type": "Feature",
  "properties": {
    "name": "Sperenberg",
    "country": "DE",
    "subdivision": "11",
    "timezone": "Europe/Berlin"
  },
  "geometry": {
    "type": "Point",
    "coordinates": [
      13.365,
      52.14113
    ]
  }
}