{
  "type": "Feature",
  "properties": {
    "name": "Stahnsdorf",
    "country": "DE",
    "subdivision": "11",
    "timezone": "Europe/Berlin"
  },
  "geometry": {
    "type": "Point",
    "coordinates": [
      13.21667,
      52.38333
    ]
  }
}