{
  "type": "Feature",
  "properties": {
    "name": "Vetschau",
    "country": "DE",
    "subdivision": "11",
    "timezone": "Europe/Berlin"
  },
  "geometry": {
    "type": "Point",
    "coordinates": [
      14.07941,
      51.78638
    ]
  }
}