{
  "type": "Feature",
  "properties": {
    "name": "Wendisch Rietz",
    "country": "DE",
    "subdivision": "11",
    "timezone": "Europe/Berlin"
  },
  "geometry": {
    "type": "Point",
    "coordinates": [
      14.00845,
      52.21613
    ]
  }
}