{
  "type": "Feature",
  "properties": {
    "name": "Wriezen",
    "country": "DE",
    "subdivision": "11",
    "timezone": "Europe/Berlin"
  },
  "geometry": {
    "type": "Point",
    "coordinates": [
      14.13425,
      52.72091
    ]
  }
}