{
  "type": "Feature",
  "properties": {
    "name": "Wusterwitz",
    "country": "DE",
    "subdivision": "11",
    "timezone": "Europe/Berlin"
  },
  "geometry": {
    "type": "Point",
    "coordinates": [
      12.38488,
      52.36666
    ]
  }
}