{
  "type": "Feature",
  "properties": {
    "name": "Zehdenick",
    "country": "DE",
    "subdivision": "11",
    "timezone": "Europe/Berlin"
  },
  "geometry": {
    "type": "Point",
    "coordinates": [
      13.33165,
      52.97852
    ]
  }
}