{
  "type": "Feature",
  "properties": {
    "name": "Valparaíso",
    "country": "CO",
    "subdivision": "08",
    "timezone": "America/Bogota"
  },
  "geometry": {
    "type": "Point",
    "coordinates": [
      -75.70746,
      1.19403
    ]
  }
}