{
  "type": "Feature",
  "properties": {
    "name": "Amos",
    "country": "CA",
    "subdivision": "10",
    "timezone": "America/Toronto"
  },
  "geometry": {
    "type": "Point",
    "coordinates": [
      -78.11624,
      48.56688
    ]
  }
}