{
  "type": "Feature",
  "properties": {
    "name": "Asbestos",
    "country": "CA",
    "subdivision": "10",
    "timezone": "America/Toronto"
  },
  "geometry": {
    "type": "Point",
    "coordinates": [
      -71.9324,
      45.76678
    ]
  }
}