{
  "type": "Feature",
  "properties": {
    "name": "Beaconsfield",
    "country": "CA",
    "subdivision": "10",
    "timezone": "America/Toronto"
  },
  "geometry": {
    "type": "Point",
    "coordinates": [
      -73.86586,
      45.43341
    ]
  }
}