{
  "type": "Feature",
  "properties": {
    "name": "Bécancour",
    "country": "CA",
    "subdivision": "10",
    "timezone": "America/Toronto"
  },
  "geometry": {
    "type": "Point",
    "coordinates": [
      -72.43224,
      46.34106
    ]
  }
}