{
  "type": "Feature",
  "properties": {
    "name": "Beloeil",
    "country": "CA",
    "subdivision": "10",
    "timezone": "America/Toronto"
  },
  "geometry": {
    "type": "Point",
    "coordinates": [
      -73.20568,
      45.56839
    ]
  }
}