{
  "type": "Feature",
  "properties": {
    "name": "Charlemagne",
    "country": "CA",
    "subdivision": "10",
    "timezone": "America/Toronto"
  },
  "geometry": {
    "type": "Point",
    "coordinates": [
      -73.48247,
      45.71678
    ]
  }
}