{
  "type": "Feature",
  "properties": {
    "name": "Chibougamau",
    "country": "CA",
    "subdivision": "10",
    "timezone": "America/Toronto"
  },
  "geometry": {
    "type": "Point",
    "coordinates": [
      -74.36586,
      49.91684
    ]
  }
}