{
  "type": "Feature",
  "properties": {
    "name": "Coaticook",
    "country": "CA",
    "subdivision": "10",
    "timezone": "America/Toronto"
  },
  "geometry": {
    "type": "Point",
    "coordinates": [
      -71.79907,
      45.13339
    ]
  }
}