{
  "type": "Feature",
  "properties": {
    "name": "Crabtree",
    "country": "CA",
    "subdivision": "10",
    "timezone": "America/Toronto"
  },
  "geometry": {
    "type": "Point",
    "coordinates": [
      -73.46586,
      45.96677
    ]
  }
}