{
  "type": "Feature",
  "properties": {
    "name": "Danville",
    "country": "CA",
    "subdivision": "10",
    "timezone": "America/Toronto"
  },
  "geometry": {
    "type": "Point",
    "coordinates": [
      -72.0158,
      45.78337
    ]
  }
}