{
  "type": "Feature",
  "properties": {
    "name": "East Broughton",
    "country": "CA",
    "subdivision": "10",
    "timezone": "America/Toronto"
  },
  "geometry": {
    "type": "Point",
    "coordinates": [
      -71.07674,
      46.21358
    ]
  }
}