{
  "type": "Feature",
  "properties": {
    "name": "Hérouxville",
    "country": "CA",
    "subdivision": "10",
    "timezone": "America/Toronto"
  },
  "geometry": {
    "type": "Point",
    "coordinates": [
      -72.62512,
      46.66617
    ]
  }
}