{
  "type": "Feature",
  "properties": {
    "name": "La Sarre",
    "country": "CA",
    "subdivision": "10",
    "timezone": "America/Toronto"
  },
  "geometry": {
    "type": "Point",
    "coordinates": [
      -79.19964,
      48.80019
    ]
  }
}