{
  "type": "Feature",
  "properties": {
    "name": "Labelle",
    "country": "CA",
    "subdivision": "10",
    "timezone": "America/Toronto"
  },
  "geometry": {
    "type": "Point",
    "coordinates": [
      -74.73255,
      46.28339
    ]
  }
}