{
  "type": "Feature",
  "properties": {
    "name": "Lac-Connelly",
    "country": "CA",
    "subdivision": "10",
    "timezone": "America/Toronto"
  },
  "geometry": {
    "type": "Point",
    "coordinates": [
      -73.9723,
      45.89788
    ]
  }
}