{
  "type": "Feature",
  "properties": {
    "name": "Lac-Alouette",
    "country": "CA",
    "subdivision": "10",
    "timezone": "America/Toronto"
  },
  "geometry": {
    "type": "Point",
    "coordinates": [
      -73.9592,
      45.81698
    ]
  }
}