{
  "type": "Feature",
  "properties": {
    "name": "Leblanc",
    "country": "CA",
    "subdivision": "10",
    "timezone": "America/Toronto"
  },
  "geometry": {
    "type": "Point",
    "coordinates": [
      -74.34914,
      48.26683
    ]
  }
}