{
  "type": "Feature",
  "properties": {
    "name": "Linière",
    "country": "CA",
    "subdivision": "10",
    "timezone": "America/Toronto"
  },
  "geometry": {
    "type": "Point",
    "coordinates": [
      -70.41572,
      46.00007
    ]
  }
}