{
  "type": "Feature",
  "properties": {
    "name": "Louiseville",
    "country": "CA",
    "subdivision": "10",
    "timezone": "America/Toronto"
  },
  "geometry": {
    "type": "Point",
    "coordinates": [
      -72.94145,
      46.25594
    ]
  }
}