{
  "type": "Feature",
  "properties": {
    "name": "Luceville",
    "country": "CA",
    "subdivision": "10",
    "timezone": "America/Toronto"
  },
  "geometry": {
    "type": "Point",
    "coordinates": [
      -68.39658,
      48.54498
    ]
  }
}