{
  "type": "Feature",
  "properties": {
    "name": "Mont-Laurier",
    "country": "CA",
    "subdivision": "10",
    "timezone": "America/Toronto"
  },
  "geometry": {
    "type": "Point",
    "coordinates": [
      -75.4993,
      46.55011
    ]
  }
}