{
  "type": "Feature",
  "properties": {
    "name": "Neuville",
    "country": "CA",
    "subdivision": "10",
    "timezone": "America/Toronto"
  },
  "geometry": {
    "type": "Point",
    "coordinates": [
      -71.58275,
      46.69823
    ]
  }
}