{
  "type": "Feature",
  "properties": {
    "name": "Pierreville",
    "country": "CA",
    "subdivision": "10",
    "timezone": "America/Toronto"
  },
  "geometry": {
    "type": "Point",
    "coordinates": [
      -72.81125,
      46.07034
    ]
  }
}