{
  "type": "Feature",
  "properties": {
    "name": "Port-Cartier",
    "country": "CA",
    "subdivision": "10",
    "timezone": "America/Toronto"
  },
  "geometry": {
    "type": "Point",
    "coordinates": [
      -66.86545,
      50.03339
    ]
  }
}