{
  "type": "Feature",
  "properties": {
    "name": "Saguenay",
    "country": "CA",
    "subdivision": "10",
    "timezone": "America/Toronto"
  },
  "geometry": {
    "type": "Point",
    "coordinates": [
      -71.06573,
      48.41675
    ]
  }
}