{
  "type": "Feature",
  "properties": {
    "name": "Sainte-Anne-de-Bellevue",
    "country": "CA",
    "subdivision": "10",
    "timezone": "America/Toronto"
  },
  "geometry": {
    "type": "Point",
    "coordinates": [
      -73.9456,
      45.40618
    ]
  }
}