{
  "type": "Feature",
  "properties": {
    "name": "Saint-Jacques-le-Mineur",
    "country": "CA",
    "subdivision": "10",
    "timezone": "America/Toronto"
  },
  "geometry": {
    "type": "Point",
    "coordinates": [
      -73.41587,
      45.28338
    ]
  }
}