{
  "type": "Feature",
  "properties": {
    "name": "Sainte-Adèle",
    "country": "CA",
    "subdivision": "10",
    "timezone": "America/Toronto"
  },
  "geometry": {
    "type": "Point",
    "coordinates": [
      -74.13251,
      45.95008
    ]
  }
}