{
  "type": "Feature",
  "properties": {
    "name": "Saint-Damase",
    "country": "CA",
    "subdivision": "10",
    "timezone": "America/Toronto"
  },
  "geometry": {
    "type": "Point",
    "coordinates": [
      -72.99914,
      45.53341
    ]
  }
}