{
  "type": "Feature",
  "properties": {
    "name": "Sainte-Croix",
    "country": "CA",
    "subdivision": "10",
    "timezone": "America/Toronto"
  },
  "geometry": {
    "type": "Point",
    "coordinates": [
      -72.80083,
      45.13368
    ]
  }
}