{
  "type": "Feature",
  "properties": {
    "name": "Saint-Hippolyte",
    "country": "CA",
    "subdivision": "10",
    "timezone": "America/Toronto"
  },
  "geometry": {
    "type": "Point",
    "coordinates": [
      -74.0159,
      45.93338
    ]
  }
}