{
  "type": "Feature",
  "properties": {
    "name": "Sainte-Madeleine",
    "country": "CA",
    "subdivision": "10",
    "timezone": "America/Toronto"
  },
  "geometry": {
    "type": "Point",
    "coordinates": [
      -73.09914,
      45.60008
    ]
  }
}