{
  "type": "Feature",
  "properties": {
    "name": "Saint-Donat-de-Montcalm",
    "country": "CA",
    "subdivision": "10",
    "timezone": "America/Toronto"
  },
  "geometry": {
    "type": "Point",
    "coordinates": [
      -74.22171,
      46.31868
    ]
  }
}