{
  "type": "Feature",
  "properties": {
    "name": "Saint-Honoré",
    "country": "CA",
    "subdivision": "10",
    "timezone": "America/Toronto"
  },
  "geometry": {
    "type": "Point",
    "coordinates": [
      -71.08236,
      48.53338
    ]
  }
}