{
  "type": "Feature",
  "properties": {
    "name": "Saint-Raphaël",
    "country": "CA",
    "subdivision": "10",
    "timezone": "America/Toronto"
  },
  "geometry": {
    "type": "Point",
    "coordinates": [
      -76.01605,
      46.25011
    ]
  }
}