{
  "type": "Feature",
  "properties": {
    "name": "Saint-Jean-Baptiste",
    "country": "CA",
    "subdivision": "10",
    "timezone": "America/Toronto"
  },
  "geometry": {
    "type": "Point",
    "coordinates": [
      -74.0121,
      45.3806
    ]
  }
}