{
  "type": "Feature",
  "properties": {
    "name": "Saint-Norbert",
    "country": "CA",
    "subdivision": "10",
    "timezone": "America/Toronto"
  },
  "geometry": {
    "type": "Point",
    "coordinates": [
      -73.31494,
      46.16949
    ]
  }
}