{
  "type": "Feature",
  "properties": {
    "name": "Senneterre",
    "country": "CA",
    "subdivision": "10",
    "timezone": "America/Toronto"
  },
  "geometry": {
    "type": "Point",
    "coordinates": [
      -77.23951,
      48.39302
    ]
  }
}