{
  "type": "Feature",
  "properties": {
    "name": "Shawville",
    "country": "CA",
    "subdivision": "10",
    "timezone": "America/Toronto"
  },
  "geometry": {
    "type": "Point",
    "coordinates": [
      -76.4827,
      45.60011
    ]
  }
}