{
  "type": "Feature",
  "properties": {
    "name": "St-Jean-Port-Joli",
    "country": "CA",
    "subdivision": "10",
    "timezone": "America/Toronto"
  },
  "geometry": {
    "type": "Point",
    "coordinates": [
      -70.26969,
      47.21418
    ]
  }
}