{
  "type": "Feature",
  "properties": {
    "name": "Vallée-Jonction",
    "country": "CA",
    "subdivision": "10",
    "timezone": "America/Toronto"
  },
  "geometry": {
    "type": "Point",
    "coordinates": [
      -70.91881,
      46.37441
    ]
  }
}