{
  "type": "Feature",
  "properties": {
    "name": "Varennes",
    "country": "CA",
    "subdivision": "10",
    "timezone": "America/Toronto"
  },
  "geometry": {
    "type": "Point",
    "coordinates": [
      -73.43246,
      45.68338
    ]
  }
}