{
  "type": "Feature",
  "properties": {
    "name": "Venise-en-Québec",
    "country": "CA",
    "subdivision": "10",
    "timezone": "America/Toronto"
  },
  "geometry": {
    "type": "Point",
    "coordinates": [
      -73.13245,
      45.08338
    ]
  }
}