{
  "type": "Feature",
  "properties": {
    "name": "Windsor",
    "country": "CA",
    "subdivision": "10",
    "timezone": "America/Toronto"
  },
  "geometry": {
    "type": "Point",
    "coordinates": [
      -71.99909,
      45.56678
    ]
  }
}