{
  "type": "Feature",
  "properties": {
    "name": "Amory",
    "country": "US",
    "subdivision": "MS",
    "timezone": "America/Chicago"
  },
  "geometry": {
    "type": "Point",
    "coordinates": [
      -88.4881,
      33.98428
    ]
  }
}