{
  "type": "Feature",
  "properties": {
    "name": "Bude",
    "country": "US",
    "subdivision": "MS",
    "timezone": "America/Chicago"
  },
  "geometry": {
    "type": "Point",
    "coordinates": [
      -90.8501,
      31.46295
    ]
  }
}