{
  "type": "Feature",
  "properties": {
    "name": "Caledonia",
    "country": "US",
    "subdivision": "MS",
    "timezone": "America/Chicago"
  },
  "geometry": {
    "type": "Point",
    "coordinates": [
      -88.32448,
      33.68289
    ]
  }
}