{
  "type": "Feature",
  "properties": {
    "name": "Collins",
    "country": "US",
    "subdivision": "MS",
    "timezone": "America/Chicago"
  },
  "geometry": {
    "type": "Point",
    "coordinates": [
      -89.55535,
      31.64544
    ]
  }
}