{
  "type": "Feature",
  "properties": {
    "name": "Columbus",
    "country": "US",
    "subdivision": "MS",
    "timezone": "America/Chicago"
  },
  "geometry": {
    "type": "Point",
    "coordinates": [
      -88.42726,
      33.49567
    ]
  }
}