{
  "type": "Feature",
  "properties": {
    "name": "Drew",
    "country": "US",
    "subdivision": "MS",
    "timezone": "America/Chicago"
  },
  "geometry": {
    "type": "Point",
    "coordinates": [
      -90.52648,
      33.80956
    ]
  }
}