{
  "type": "Feature",
  "properties": {
    "name": "Duck Hill",
    "country": "US",
    "subdivision": "MS",
    "timezone": "America/Chicago"
  },
  "geometry": {
    "type": "Point",
    "coordinates": [
      -89.71119,
      33.63318
    ]
  }
}