{
  "type": "Feature",
  "properties": {
    "name": "Glendale",
    "country": "US",
    "subdivision": "MS",
    "timezone": "America/Chicago"
  },
  "geometry": {
    "type": "Point",
    "coordinates": [
      -89.30617,
      31.36462
    ]
  }
}