{
  "type": "Feature",
  "properties": {
    "name": "Hillsboro",
    "country": "US",
    "subdivision": "MS",
    "timezone": "America/Chicago"
  },
  "geometry": {
    "type": "Point",
    "coordinates": [
      -89.51146,
      32.45931
    ]
  }
}