{
  "type": "Feature",
  "properties": {
    "name": "Jonestown",
    "country": "US",
    "subdivision": "MS",
    "timezone": "America/Chicago"
  },
  "geometry": {
    "type": "Point",
    "coordinates": [
      -90.45565,
      34.31955
    ]
  }
}