{
  "type": "Feature",
  "properties": {
    "name": "Kosciusko",
    "country": "US",
    "subdivision": "MS",
    "timezone": "America/Chicago"
  },
  "geometry": {
    "type": "Point",
    "coordinates": [
      -89.58956,
      33.058
    ]
  }
}