{
  "type": "Feature",
  "properties": {
    "name": "Latimer",
    "country": "US",
    "subdivision": "MS",
    "timezone": "America/Chicago"
  },
  "geometry": {
    "type": "Point",
    "coordinates": [
      -88.8667,
      30.53464
    ]
  }
}