{
  "type": "Feature",
  "properties": {
    "name": "Laurel",
    "country": "US",
    "subdivision": "MS",
    "timezone": "America/Chicago"
  },
  "geometry": {
    "type": "Point",
    "coordinates": [
      -89.13061,
      31.69405
    ]
  }
}