{
  "type": "Feature",
  "properties": {
    "name": "Lucedale",
    "country": "US",
    "subdivision": "MS",
    "timezone": "America/Chicago"
  },
  "geometry": {
    "type": "Point",
    "coordinates": [
      -88.59002,
      30.92519
    ]
  }
}