{
  "type": "Feature",
  "properties": {
    "name": "Lynchburg",
    "country": "US",
    "subdivision": "MS",
    "timezone": "America/Chicago"
  },
  "geometry": {
    "type": "Point",
    "coordinates": [
      -90.09593,
      34.96232
    ]
  }
}