{
  "type": "Feature",
  "properties": {
    "name": "Marks",
    "country": "US",
    "subdivision": "MS",
    "timezone": "America/Chicago"
  },
  "geometry": {
    "type": "Point",
    "coordinates": [
      -90.27298,
      34.25683
    ]
  }
}