{
  "type": "Feature",
  "properties": {
    "name": "McComb",
    "country": "US",
    "subdivision": "MS",
    "timezone": "America/Chicago"
  },
  "geometry": {
    "type": "Point",
    "coordinates": [
      -90.45315,
      31.24379
    ]
  }
}