{
  "type": "Feature",
  "properties": {
    "name": "Monticello",
    "country": "US",
    "subdivision": "MS",
    "timezone": "America/Chicago"
  },
  "geometry": {
    "type": "Point",
    "coordinates": [
      -90.10731,
      31.55378
    ]
  }
}