{
  "type": "Feature",
  "properties": {
    "name": "Morgantown",
    "country": "US",
    "subdivision": "MS",
    "timezone": "America/Chicago"
  },
  "geometry": {
    "type": "Point",
    "coordinates": [
      -91.34761,
      31.57267
    ]
  }
}