{
  "type": "Feature",
  "properties": {
    "name": "Newton",
    "country": "US",
    "subdivision": "MS",
    "timezone": "America/Chicago"
  },
  "geometry": {
    "type": "Point",
    "coordinates": [
      -89.16339,
      32.32126
    ]
  }
}