{
  "type": "Feature",
  "properties": {
    "name": "Pass Christian",
    "country": "US",
    "subdivision": "MS",
    "timezone": "America/Chicago"
  },
  "geometry": {
    "type": "Point",
    "coordinates": [
      -89.24754,
      30.31575
    ]
  }
}