{
  "type": "Feature",
  "properties": {
    "name": "Plantersville",
    "country": "US",
    "subdivision": "MS",
    "timezone": "America/Chicago"
  },
  "geometry": {
    "type": "Point",
    "coordinates": [
      -88.6645,
      34.21344
    ]
  }
}