{
  "type": "Feature",
  "properties": {
    "name": "Prentiss",
    "country": "US",
    "subdivision": "MS",
    "timezone": "America/Chicago"
  },
  "geometry": {
    "type": "Point",
    "coordinates": [
      -89.86702,
      31.5985
    ]
  }
}