{
  "type": "Feature",
  "properties": {
    "name": "Sardis",
    "country": "US",
    "subdivision": "MS",
    "timezone": "America/Chicago"
  },
  "geometry": {
    "type": "Point",
    "coordinates": [
      -89.91592,
      34.43705
    ]
  }
}