{
  "type": "Feature",
  "properties": {
    "name": "Southaven",
    "country": "US",
    "subdivision": "MS",
    "timezone": "America/Chicago"
  },
  "geometry": {
    "type": "Point",
    "coordinates": [
      -90.01259,
      34.98898
    ]
  }
}