{
  "type": "Feature",
  "properties": {
    "name": "Tylertown",
    "country": "US",
    "subdivision": "MS",
    "timezone": "America/Chicago"
  },
  "geometry": {
    "type": "Point",
    "coordinates": [
      -90.14203,
      31.11601
    ]
  }
}