{
  "type": "Feature",
  "properties": {
    "name": "Anklaar",
    "country": "NL",
    "subdivision": "03",
    "timezone": "Europe/Amsterdam"
  },
  "geometry": {
    "type": "Point",
    "coordinates": [
      5.98497,
      52.23111
    ]
  }
}