{
  "type": "Feature",
  "properties": {
    "name": "Bakenberg",
    "country": "NL",
    "subdivision": "03",
    "timezone": "Europe/Amsterdam"
  },
  "geometry": {
    "type": "Point",
    "coordinates": [
      5.8771,
      52.00511
    ]
  }
}