{
  "type": "Feature",
  "properties": {
    "name": "Binnenstad",
    "country": "NL",
    "subdivision": "03",
    "timezone": "Europe/Amsterdam"
  },
  "geometry": {
    "type": "Point",
    "coordinates": [
      5.95957,
      52.21304
    ]
  }
}