{
  "type": "Feature",
  "properties": {
    "name": "Brakel",
    "country": "NL",
    "subdivision": "03",
    "timezone": "Europe/Amsterdam"
  },
  "geometry": {
    "type": "Point",
    "coordinates": [
      5.09028,
      51.8175
    ]
  }
}