{
  "type": "Feature",
  "properties": {
    "name": "Deil",
    "country": "NL",
    "subdivision": "03",
    "timezone": "Europe/Amsterdam"
  },
  "geometry": {
    "type": "Point",
    "coordinates": [
      5.24306,
      51.88417
    ]
  }
}