{
  "type": "Feature",
  "properties": {
    "name": "Doornspijk",
    "country": "NL",
    "subdivision": "03",
    "timezone": "Europe/Amsterdam"
  },
  "geometry": {
    "type": "Point",
    "coordinates": [
      5.81806,
      52.41833
    ]
  }
}