{
  "type": "Feature",
  "properties": {
    "name": "Driehuizen",
    "country": "NL",
    "subdivision": "03",
    "timezone": "Europe/Amsterdam"
  },
  "geometry": {
    "type": "Point",
    "coordinates": [
      5.94442,
      52.20879
    ]
  }
}