{
  "type": "Feature",
  "properties": {
    "name": "Duiven",
    "country": "NL",
    "subdivision": "03",
    "timezone": "Europe/Amsterdam"
  },
  "geometry": {
    "type": "Point",
    "coordinates": [
      6.01389,
      51.94667
    ]
  }
}