{
  "type": "Feature",
  "properties": {
    "name": "Eerbeek",
    "country": "NL",
    "subdivision": "03",
    "timezone": "Europe/Amsterdam"
  },
  "geometry": {
    "type": "Point",
    "coordinates": [
      6.05833,
      52.105
    ]
  }
}