{
  "type": "Feature",
  "properties": {
    "name": "Geldermalsen-West",
    "country": "NL",
    "subdivision": "03",
    "timezone": "Europe/Amsterdam"
  },
  "geometry": {
    "type": "Point",
    "coordinates": [
      5.28015,
      51.87968
    ]
  }
}