{
  "type": "Feature",
  "properties": {
    "name": "Giesbeek",
    "country": "NL",
    "subdivision": "03",
    "timezone": "Europe/Amsterdam"
  },
  "geometry": {
    "type": "Point",
    "coordinates": [
      6.06667,
      51.99333
    ]
  }
}