{
  "type": "Feature",
  "properties": {
    "name": "Haaften",
    "country": "NL",
    "subdivision": "03",
    "timezone": "Europe/Amsterdam"
  },
  "geometry": {
    "type": "Point",
    "coordinates": [
      5.21111,
      51.81583
    ]
  }
}