{
  "type": "Feature",
  "properties": {
    "name": "Harderwijk",
    "country": "NL",
    "subdivision": "03",
    "timezone": "Europe/Amsterdam"
  },
  "geometry": {
    "type": "Point",
    "coordinates": [
      5.62083,
      52.34167
    ]
  }
}