{
  "type": "Feature",
  "properties": {
    "name": "Hatert",
    "country": "NL",
    "subdivision": "03",
    "timezone": "Europe/Amsterdam"
  },
  "geometry": {
    "type": "Point",
    "coordinates": [
      5.83057,
      51.80635
    ]
  }
}