{
  "type": "Feature",
  "properties": {
    "name": "Hattem",
    "country": "NL",
    "subdivision": "03",
    "timezone": "Europe/Amsterdam"
  },
  "geometry": {
    "type": "Point",
    "coordinates": [
      6.06389,
      52.475
    ]
  }
}