{
  "type": "Feature",
  "properties": {
    "name": "Herwijnen",
    "country": "NL",
    "subdivision": "03",
    "timezone": "Europe/Amsterdam"
  },
  "geometry": {
    "type": "Point",
    "coordinates": [
      5.12917,
      51.82667
    ]
  }
}