{
  "type": "Feature",
  "properties": {
    "name": "Hummelo",
    "country": "NL",
    "subdivision": "03",
    "timezone": "Europe/Amsterdam"
  },
  "geometry": {
    "type": "Point",
    "coordinates": [
      6.23333,
      52.00417
    ]
  }
}