{
  "type": "Feature",
  "properties": {
    "name": "Nederwoud",
    "country": "NL",
    "subdivision": "03",
    "timezone": "Europe/Amsterdam"
  },
  "geometry": {
    "type": "Point",
    "coordinates": [
      5.57083,
      52.10083
    ]
  }
}