{
  "type": "Feature",
  "properties": {
    "name": "Neede",
    "country": "NL",
    "subdivision": "03",
    "timezone": "Europe/Amsterdam"
  },
  "geometry": {
    "type": "Point",
    "coordinates": [
      6.61389,
      52.13417
    ]
  }
}