{
  "type": "Feature",
  "properties": {
    "name": "Oosterbeek",
    "country": "NL",
    "subdivision": "03",
    "timezone": "Europe/Amsterdam"
  },
  "geometry": {
    "type": "Point",
    "coordinates": [
      5.84583,
      51.98583
    ]
  }
}