{
  "type": "Feature",
  "properties": {
    "name": "Opijnen",
    "country": "NL",
    "subdivision": "03",
    "timezone": "Europe/Amsterdam"
  },
  "geometry": {
    "type": "Point",
    "coordinates": [
      5.29861,
      51.82917
    ]
  }
}