{
  "type": "Feature",
  "properties": {
    "name": "Puiflijk",
    "country": "NL",
    "subdivision": "03",
    "timezone": "Europe/Amsterdam"
  },
  "geometry": {
    "type": "Point",
    "coordinates": [
      5.59028,
      51.87833
    ]
  }
}