{
  "type": "Feature",
  "properties": {
    "name": "Ruurlo",
    "country": "NL",
    "subdivision": "03",
    "timezone": "Europe/Amsterdam"
  },
  "geometry": {
    "type": "Point",
    "coordinates": [
      6.45,
      52.08833
    ]
  }
}