{
  "type": "Feature",
  "properties": {
    "name": "Scherpenzeel",
    "country": "NL",
    "subdivision": "03",
    "timezone": "Europe/Amsterdam"
  },
  "geometry": {
    "type": "Point",
    "coordinates": [
      5.48889,
      52.08
    ]
  }
}