{
  "type": "Feature",
  "properties": {
    "name": "Sluisoord",
    "country": "NL",
    "subdivision": "03",
    "timezone": "Europe/Amsterdam"
  },
  "geometry": {
    "type": "Point",
    "coordinates": [
      5.98145,
      52.22291
    ]
  }
}