{
  "type": "Feature",
  "properties": {
    "name": "Sprengenbos",
    "country": "NL",
    "subdivision": "03",
    "timezone": "Europe/Amsterdam"
  },
  "geometry": {
    "type": "Point",
    "coordinates": [
      5.94163,
      52.21902
    ]
  }
}