{
  "type": "Feature",
  "properties": {
    "name": "Tricht",
    "country": "NL",
    "subdivision": "03",
    "timezone": "Europe/Amsterdam"
  },
  "geometry": {
    "type": "Point",
    "coordinates": [
      5.26806,
      51.89083
    ]
  }
}