{
  "type": "Feature",
  "properties": {
    "name": "Warnsveld",
    "country": "NL",
    "subdivision": "03",
    "timezone": "Europe/Amsterdam"
  },
  "geometry": {
    "type": "Point",
    "coordinates": [
      6.23056,
      52.1375
    ]
  }
}