{
  "type": "Feature",
  "properties": {
    "name": "Westenenk",
    "country": "NL",
    "subdivision": "03",
    "timezone": "Europe/Amsterdam"
  },
  "geometry": {
    "type": "Point",
    "coordinates": [
      5.95656,
      52.19624
    ]
  }
}