{
  "type": "Feature",
  "properties": {
    "name": "Güroymak",
    "country": "TR",
    "subdivision": "13",
    "timezone": "Europe/Istanbul"
  },
  "geometry": {
    "type": "Point",
    "coordinates": [
      42.01558,
      38.5758
    ]
  }
}