{
  "type": "Feature",
  "properties": {
    "name": "Chinavita",
    "country": "CO",
    "subdivision": "36",
    "timezone": "America/Bogota"
  },
  "geometry": {
    "type": "Point",
    "coordinates": [
      -73.36823,
      5.16723
    ]
  }
}