{
  "type": "Feature",
  "properties": {
    "name": "Cucaita",
    "country": "CO",
    "subdivision": "36",
    "timezone": "America/Bogota"
  },
  "geometry": {
    "type": "Point",
    "coordinates": [
      -73.45433,
      5.54373
    ]
  }
}