{
  "type": "Feature",
  "properties": {
    "name": "El Espino",
    "country": "CO",
    "subdivision": "36",
    "timezone": "America/Bogota"
  },
  "geometry": {
    "type": "Point",
    "coordinates": [
      -72.49718,
      6.48277
    ]
  }
}