{
  "type": "Feature",
  "properties": {
    "name": "Güicán",
    "country": "CO",
    "subdivision": "36",
    "timezone": "America/Bogota"
  },
  "geometry": {
    "type": "Point",
    "coordinates": [
      -72.41539,
      6.46554
    ]
  }
}