{
  "type": "Feature",
  "properties": {
    "name": "Pesca",
    "country": "CO",
    "subdivision": "36",
    "timezone": "America/Bogota"
  },
  "geometry": {
    "type": "Point",
    "coordinates": [
      -73.05,
      5.55
    ]
  }
}