{
  "type": "Feature",
  "properties": {
    "name": "Socotá",
    "country": "CO",
    "subdivision": "36",
    "timezone": "America/Bogota"
  },
  "geometry": {
    "type": "Point",
    "coordinates": [
      -72.63509,
      6.04028
    ]
  }
}