{
  "type": "Feature",
  "properties": {
    "name": "Tunja",
    "country": "CO",
    "subdivision": "36",
    "timezone": "America/Bogota"
  },
  "geometry": {
    "type": "Point",
    "coordinates": [
      -73.36778,
      5.53528
    ]
  }
}