{
  "type": "Feature",
  "properties": {
    "name": "Turmequé",
    "country": "CO",
    "subdivision": "36",
    "timezone": "America/Bogota"
  },
  "geometry": {
    "type": "Point",
    "coordinates": [
      -73.49067,
      5.3236
    ]
  }
}