{
  "type": "Feature",
  "properties": {
    "name": "Afa",
    "country": "FR",
    "subdivision": "94",
    "timezone": "Europe/Paris"
  },
  "geometry": {
    "type": "Point",
    "coordinates": [
      8.79833,
      41.98396
    ]
  }
}