{
  "type": "Feature",
  "properties": {
    "name": "Albitreccia",
    "country": "FR",
    "subdivision": "94",
    "timezone": "Europe/Paris"
  },
  "geometry": {
    "type": "Point",
    "coordinates": [
      8.94262,
      41.86301
    ]
  }
}