{
  "type": "Feature",
  "properties": {
    "name": "Aléria",
    "country": "FR",
    "subdivision": "94",
    "timezone": "Europe/Paris"
  },
  "geometry": {
    "type": "Point",
    "coordinates": [
      9.51265,
      42.10431
    ]
  }
}