{
  "type": "Feature",
  "properties": {
    "name": "Bonifacio",
    "country": "FR",
    "subdivision": "94",
    "timezone": "Europe/Paris"
  },
  "geometry": {
    "type": "Point",
    "coordinates": [
      9.15667,
      41.38723
    ]
  }
}