{
  "type": "Feature",
  "properties": {
    "name": "Corte",
    "country": "FR",
    "subdivision": "94",
    "timezone": "Europe/Paris"
  },
  "geometry": {
    "type": "Point",
    "coordinates": [
      9.14917,
      42.30956
    ]
  }
}