{
  "type": "Feature",
  "properties": {
    "name": "Santa-Lucia-di-Moriani",
    "country": "FR",
    "subdivision": "94",
    "timezone": "Europe/Paris"
  },
  "geometry": {
    "type": "Point",
    "coordinates": [
      9.52242,
      42.38212
    ]
  }
}