{
  "type": "Feature",
  "properties": {
    "name": "El Castillo",
    "country": "CO",
    "subdivision": "19",
    "timezone": "America/Bogota"
  },
  "geometry": {
    "type": "Point",
    "coordinates": [
      -73.79488,
      3.56363
    ]
  }
}