{
  "type": "Feature",
  "properties": {
    "name": "El Dorado",
    "country": "CO",
    "subdivision": "19",
    "timezone": "America/Bogota"
  },
  "geometry": {
    "type": "Point",
    "coordinates": [
      -72.86834,
      2.77411
    ]
  }
}