{
  "type": "Feature",
  "properties": {
    "name": "Puerto Yuca",
    "country": "CO",
    "subdivision": "19",
    "timezone": "America/Bogota"
  },
  "geometry": {
    "type": "Point",
    "coordinates": [
      -73.20833,
      2.93833
    ]
  }
}