{
  "type": "Feature",
  "properties": {
    "name": "Restrepo",
    "country": "CO",
    "subdivision": "19",
    "timezone": "America/Bogota"
  },
  "geometry": {
    "type": "Point",
    "coordinates": [
      -73.56142,
      4.25833
    ]
  }
}