{
  "type": "Feature",
  "properties": {
    "name": "San Juan de Arama",
    "country": "CO",
    "subdivision": "19",
    "timezone": "America/Bogota"
  },
  "geometry": {
    "type": "Point",
    "coordinates": [
      -73.87267,
      3.36985
    ]
  }
}