{
  "type": "Feature",
  "properties": {
    "name": "Vistahermosa",
    "country": "CO",
    "subdivision": "19",
    "timezone": "America/Bogota"
  },
  "geometry": {
    "type": "Point",
    "coordinates": [
      -73.75156,
      3.12428
    ]
  }
}