{
  "type": "Feature",
  "properties": {
    "name": "Chachersk",
    "country": "BY",
    "subdivision": "02",
    "timezone": "Europe/Minsk"
  },
  "geometry": {
    "type": "Point",
    "coordinates": [
      30.9179,
      52.9164
    ]
  }
}