{
  "type": "Feature",
  "properties": {
    "name": "Pyetrykaw",
    "country": "BY",
    "subdivision": "02",
    "timezone": "Europe/Minsk"
  },
  "geometry": {
    "type": "Point",
    "coordinates": [
      28.4921,
      52.1289
    ]
  }
}