{
  "type": "Feature",
  "properties": {
    "name": "Kavieng",
    "country": "PG",
    "subdivision": "15",
    "timezone": "Pacific/Port_Moresby"
  },
  "geometry": {
    "type": "Point",
    "coordinates": [
      150.79516,
      -2.57337
    ]
  }
}