{
  "type": "Feature",
  "properties": {
    "name": "Adıyaman",
    "country": "TR",
    "subdivision": "02",
    "timezone": "Europe/Istanbul"
  },
  "geometry": {
    "type": "Point",
    "coordinates": [
      38.27629,
      37.76441
    ]
  }
}